Workbook

Sheet README
A1: BFCM 2026 Competitor Tracker (v1)
A2: Owner: Shayan Rana · Backup: Zarlish · Due Thu Oct 15, 2026 (ClickUp BFCM-2026 › Competitor BFCM tracker) · Built 2026-10-13 from the Command Center (primary) and Data Dive
A4: What it is for
A5: 1. Lift forecast (Erik Oct 8 / Oct 13): tune our BFCM lift per product on what competitors did, not only our own history - deal type, depth and BSR change last BFCM, and how hard they push at events.
A6: 2. Pricing and STR: where competitors set List Price today, how far over their price, and who already sits below our planned BFCM deal price (plan risk P2 'Competitors undercut on heroes' - report only, no regular-price cut without Joseph).
A7: 3. Event watch: one log for Nov 20 - Dec 1 competitor checks.
A9: Tabs
A10: Dashboard - one row per our product: our profile (SKUs, sizes, colours, price, margin), the competitor set, price position, List Price/STR read, our BFCM 2025 lift, Prime Day 2026 visibility lift (ours vs theirs) and Keepa completion.
A11: Competitors - every mapped competitor for every product (Command Center map), with current price / List Price / BSR / weekly units, listing details (variations, age, ads) from Data Dive, ASINsight traffic, Prime Day 2026 visibility, and the yellow BFCM 2025 + STR columns to fill from Keepa.
A12: Our BFCM 2025 - our own result per product: BFCM week vs the 30 days before and vs December, from the Command Center PPC/TACoS data, plus the deals and events the Command Center logged.
A13: Our Daily 2025 - day-by-day Oct 15 - Dec 15, 2025 per product (ad spend, ad sales, orders) to see the shape of the lift.
A14: Visibility History - Command Center daily placement scores summarised per window, per ASIN (organic and advertising). Competitor history starts Jan-Apr 2026, ours goes back to Oct 2025.
... A29: Our BFCM 2025 total sales are derived from the Command Center: ad spend / TACoS. Marked 'derived' wherever used.

Sheet Key Insights
A1: Family | B1: Our product | C1: Topic | D1: Insight (computed from the data on Oct 13, 2026)
A2: All | B2: Portfolio | C2: Our BFCM 2025 lift | D2: BFCM week 2025 daily total sales vs the 30 days before (derived from ad spend / TACoS): DC B4 4.25x, SL Cooling Comforter 3.39x, DC S6 3.08x, DC S4 2.64x, SSS4 2.59x, DC B6 2.49x, DC Satin Fitted 2.47x, DC Cooling 4pc 1.63x, DC Silk Pillowcase 1.35x, SL B6 1.20x, SL Cooling 4pc 1.14x. Ad spend per day rose DC B4 2.4x, SL Cooling Comforter 1.5x, DC S6 2.3x, DC S4 1.2x, SSS4 2.2x, DC B6 2.1x, DC Satin Fitted 1.7x, DC Cooling 4pc 2.2x, DC Silk Pillowcase 1.4x, SL B6 0.6x, SL Cooling 4pc 0.4x - lift came with heavier spend, so read lift and TACoS together.
A3: All | B3: Portfolio | C3: List Price / STR landscape | D3: 155 of 616 mapped competitor rows (25%) carry a List Price above their price. 30 sit within 12% (the band Joseph's study found Amazon shows), 64 are more than 25% over (usually ignored). Median List Price premium where set: 23%. Whether Amazon actually displays each one still needs the page / STR Panel check (Competitors tab, 'STR showing now?').
A4: All | B4: Portfolio | C4: Prime Day 2026 behaviour | D4: 259 competitor rows (86 brands) have Command Center visibility history over Prime Day 2026. Median organic visibility lift Jun 23-26 vs Jun 1-20: 1.07x. Competitor history does not reach BFCM 2025 (starts Jan-Apr 2026), so Prime Day is the closest in-house event read; BFCM 2025 needs Keepa.
A5: Bamboo | B5: Decolure Bamboo Sheets 4 Piece | C5: Who sells the most | D5: Top 5 of 55 mapped rivals by est weekly units: Love's cabin (Beatable) ~924/wk at $37.99, List Price $44.99 (+18%); Bedsure (Aspirational) ~809/wk at $62.99, List Price $69.99 (+11%); Pure Bamboo (Aspirational) ~809/wk at $109.99, no List Price; Hotel Sheets Direct (Aspirational) ~347/wk at $79.99, no List Price; KRIMANO (Beatable) ~185/wk at $84.99, no List Price. Tracked rivals ~5,455 units/wk; we sell ~453/wk (7.7% of the tracked set).
A6: Bamboo | B6: Decolure Bamboo Sheets 4 Piece | C6: List Price / STR | D6: 15 of 55 rivals carry a List Price above price; 3 inside 12%: Bedsure +11%, AiAngu +7%, Kickoff Home +10%. These are the ones most likely to show a strikethrough at BFCM - check them on the page first.
A7: Bamboo | B7: Decolure Bamboo Sheets 4 Piece | C7: Our BFCM 2025 | D7: BFCM week 2025 total sales 4.25x the prior-30-day daily rate; TACoS 6.3% in BFCM week vs 11.2% before; December ran 1.86x the pre-event rate.
A8: Bamboo | B8: Decolure Bamboo Sheets 4 Piece | C8: Prime Day 2026 visibility | D8: Our best child B08KQHRDDG: organic visibility 0.91x over Prime Day vs the 3 weeks before; mapped rivals' median 1.25x (n=14, rivals with a baseline score of 5+). Rivals gained more event visibility than we did.
A9: Bamboo | B9: Decolure Bamboo Sheets 4 Piece | C9: Price position | D9: 29 of 55 rivals are priced below our same-size (or Queen) price today. Our blended price $80.69, contribution $34.45/unit, break-even ACoS 43%.
A10: Bamboo | B10: Decolure Bamboo Sheets 6 Piece | C10: Who sells the most | D10: Top 5 of 46 mapped rivals by est weekly units: Love's cabin (Beatable) ~924/wk at $37.99, List Price $44.99 (+18%); Bedsure (Aspirational) ~809/wk at $62.99, List Price $69.99 (+11%); Pure Bamboo (Aspirational) ~809/wk at $109.99, no List Price; Hotel Sheets Direct (Aspirational) ~347/wk at $79.99, no List Price; KRIMANO (Beatable) ~185/wk at $84.99, no List Price. Tracked rivals ~4,821 units/wk; we sell ~476/wk (9.0% of the tracked set).
A11: Bamboo | B11: Decolure Bamboo Sheets 6 Piece | C11: List Price / STR | D11: 14 of 46 rivals carry a List Price above price; 3 inside 12%: Bedsure +11%, AiAngu +7%, Kickoff Home +10%. These are the ones most likely to show a strikethrough at BFCM - check them on the page first.
A12: Bamboo | B12: Decolure Bamboo Sheets 6 Piece | C12: Our BFCM 2025 | D12: BFCM week 2025 total sales 2.49x the prior-30-day daily rate; TACoS 6.4% in BFCM week vs 7.4% before; December ran 1.36x the pre-event rate.
... A91: Other | B91: Decolure Waterproof Chair Cover | C91: List Price / STR | D91: 5 of 23 rivals carry a List Price above price; 0 inside 12%. These are the ones most likely to show a strikethrough at BFCM - check them on the page first.
A93: Computed at build time from the Command Center (rosters, prices, List Price, est weekly units, our PPC/TACoS, visibility) and Data Dive. Estimates are estimates; Keepa fills the BFCM 2025 competitor history.

Sheet Dashboard
A1: PRODUCT | E1: OUR PRODUCT - Command Center | N1: COMPETITOR SET + OUR HISTORY (formulas) | AE1: COMPETITOR SET + OUR HISTORY (formulas)
A2: Family | B2: Our product | C2: Prod ID | D2: BFCM role (plan) | E2: Stage | F2: Our parent ASIN | G2: Our SKUs (variations) | H2: Sizes | I2: Colours | J2: Our blended price ($) | K2: Contribution / unit ($) | L2: Break-even ACoS | M2: Our units 28d | N2: Competitors mapped | O2: Aspirational | P2: Beatable | Q2: Poor | R2: Comp median price ($) | S2: Our price vs comp median | T2: Comps priced below us (same size) | U2: Comps with List Price set | V2: of which <=12% over (STR zone) | W2: Comp avg List Price % over | X2: Comp est weekly units (sum) | Y2: Our weekly units (28d/4) | Z2: Our share of tracked units | AA2: Comp median variations (DD) | AB2: Our BFCM 2025 lift (daily sales vs 30d pre) | AC2: Our BFCM 2025 TACoS | AD2: Our PD 2026 organic vis lift | AE2: Comp median PD 2026 organic vis lift | AF2: Keepa rows filled | AG2: Comp avg BFCM 2025 discount | AH2: Comp avg BFCM 2025 BSR lift
A3: Bamboo | B3: Decolure Bamboo Sheets 4 Piece | C3: 59 | D3: Hero: rank and profit | E3: Re-Launch | F3: B0BZQ1G5B8 | G3: 81 | H3: 5 | I3: 16 | J3: 80.694292 | K3: 34.445844 | L3: 0.42686841 | M3: 1813 | N3: =COUNTIF(Competitors!$C$3:$C$618,$C3) -> 55 | O3: =COUNTIFS(Competitors!$C$3:$C$618,$C3,Competitors!$J$3:$J$618,"Aspirational") -> 3 | P3: =COUNTIFS(Competitors!$C$3:$C$618,$C3,Competitors!$J$3:$J$618,"Beatable") -> 24 | Q3: =COUNTIFS(Competitors!$C$3:$C$618,$C3,Competitors!$J$3:$J$618,"Poor") -> 18 | R3: 79.99 | S3: =IF(AND(ISNUMBER(J3),ISNUMBER(R3),R3>0),J3/R3-1,"") -> 0.0088047455 | T3: =COUNTIFS(Competitors!$C$3:$C$618,$C3,Competitors!$Q$3:$Q$618,"<0") -> 29 | U3: =COUNTIFS(Competitors!$C$3:$C$618,$C3,Competitors!$M$3:$M$618,">0") -> 15 | V3: =COUNTIFS(Competitors!$C$3:$C$618,$C3,Competitors!$M$3:$M$618,">0",Competitors!$M$3:$M$618,"<=0.12") -> 3 | W3: =IFERROR(AVERAGEIFS(Competitors!$M$3:$M$618,Competitors!$C$3:$C$618,$C3,Competitors!$M$3:$M$618,">0"),"") -> 0.22158824 | X3: =SUMIF(Competitors!$C$3:$C$618,$C3,Competitors!$T$3:$T$618) -> 5455 | Y3: =IF(ISNUMBER(M3),M3/4,"") -> 453.25 | Z3: =IF(AND(ISNUMBER(Y3),X3>0),Y3/(Y3+X3),"") -> 0.076714763 | AA3: 56 | AB3: =IFERROR(IF(N(INDEX('Our BFCM 2025'!$S:$S,MATCH($C3,'Our BFCM 2025'!$C:$C,0)))=0,"",INDEX('Our BFCM 2025'!$S:$S,MATCH($C3,'Our BFCM 2025'!$C:$C,0))),"") -> 4.2549984 | AC3: =IFERROR(IF(N(INDEX('Our BFCM 2025'!$H:$H,MATCH($C3,'Our BFCM 2025'!$C:$C,0)))=0,"",INDEX('Our BFCM 2025'!$H:$H,MATCH($C3,'Our BFCM 2025'!$C:$C,0))),"") -> 0.062528589 | AD3: 0.90814196 | AE3: 1.2462863 | AF3: =COUNTIFS(Competitors!$C$3:$C$618,$C3,Competitors!$AY$3:$AY$618,"<>") -> 0 | AG3: =IFERROR(AVERAGEIFS(Competitors!$BD$3:$BD$618,Competitors!$C$3:$C$618,$C3),"") | AH3: =IFERROR(AVERAGEIFS(Competitors!$BH$3:$BH$618,Competitors!$C$3:$C$618,$C3),"")
A4: Bamboo | B4: Decolure Bamboo Sheets 6 Piece | C4: 30 | D4: Hero: rank and profit | E4: Re-Launch | F4: B0CQ31D5FM | G4: 86 | H4: 6 | I4: 17 | J4: 89.529424 | K4: 36.930305 | L4: 0.41249349 | M4: 1905 | N4: =COUNTIF(Competitors!$C$3:$C$618,$C4) -> 46 | O4: =COUNTIFS(Competitors!$C$3:$C$618,$C4,Competitors!$J$3:$J$618,"Aspirational") -> 4 | P4: =COUNTIFS(Competitors!$C$3:$C$618,$C4,Competitors!$J$3:$J$618,"Beatable") -> 24 | Q4: =COUNTIFS(Competitors!$C$3:$C$618,$C4,Competitors!$J$3:$J$618,"Poor") -> 18 | R4: 82.485 | S4: =IF(AND(ISNUMBER(J4),ISNUMBER(R4),R4>0),J4/R4-1,"") -> 0.08540248 | T4: =COUNTIFS(Competitors!$C$3:$C$618,$C4,Competitors!$Q$3:$Q$618,"<0") -> 29 | U4: =COUNTIFS(Competitors!$C$3:$C$618,$C4,Competitors!$M$3:$M$618,">0") -> 14 | V4: =COUNTIFS(Competitors!$C$3:$C$618,$C4,Competitors!$M$3:$M$618,">0",Competitors!$M$3:$M$618,"<=0.12") -> 3 | W4: =IFERROR(AVERAGEIFS(Competitors!$M$3:$M$618,Competitors!$C$3:$C$618,$C4,Competitors!$M$3:$M$618,">0"),"") -> 0.21955417 | X4: =SUMIF(Competitors!$C$3:$C$618,$C4,Competitors!$T$3:$T$618) -> 4821 | Y4: =IF(ISNUMBER(M4),M4/4,"") -> 476.25 | Z4: =IF(AND(ISNUMBER(Y4),X4>0),Y4/(Y4+X4),"") -> 0.089905139 | AA4: 52.5 | AB4: =IFERROR(IF(N(INDEX('Our BFCM 2025'!$S:$S,MATCH($C4,'Our BFCM 2025'!$C:$C,0)))=0,"",INDEX('Our BFCM 2025'!$S:$S,MATCH($C4,'Our BFCM 2025'!$C:$C,0))),"") -> 2.4883024 | AC4: =IFERROR(IF(N(INDEX('Our BFCM 2025'!$H:$H,MATCH($C4,'Our BFCM 2025'!$C:$C,0)))=0,"",INDEX('Our BFCM 2025'!$H:$H,MATCH($C4,'Our BFCM 2025'!$C:$C,0))),"") -> 0.064032365 | AD4: 1.4420922 | AE4: 1.2462863 | AF4: =COUNTIFS(Competitors!$C$3:$C$618,$C4,Competitors!$AY$3:$AY$618,"<>") -> 0 | AG4: =IFERROR(AVERAGEIFS(Competitors!$BD$3:$BD$618,Competitors!$C$3:$C$618,$C4),"") | AH4: =IFERROR(AVERAGEIFS(Competitors!$BH$3:$BH$618,Competitors!$C$3:$C$618,$C4),"")
A5: Bamboo | B5: Sleephoria Bamboo Sheets 6 Piece | C5: 32 | D5: Core | E5: Re-Launch | F5: B0DDTY8HFR | G5: 78 | H5: 5 | I5: 16 | J5: 67.067922 | K5: 15.992987 | L5: 0.23845956 | M5: 91 | N5: =COUNTIF(Competitors!$C$3:$C$618,$C5) -> 30 | O5: =COUNTIFS(Competitors!$C$3:$C$618,$C5,Competitors!$J$3:$J$618,"Aspirational") -> 4 | P5: =COUNTIFS(Competitors!$C$3:$C$618,$C5,Competitors!$J$3:$J$618,"Beatable") -> 8 | Q5: =COUNTIFS(Competitors!$C$3:$C$618,$C5,Competitors!$J$3:$J$618,"Poor") -> 18 | R5: 79.99 | S5: =IF(AND(ISNUMBER(J5),ISNUMBER(R5),R5>0),J5/R5-1,"") -> -0.16154617 | T5: =COUNTIFS(Competitors!$C$3:$C$618,$C5,Competitors!$Q$3:$Q$618,"<0") -> 9 | U5: =COUNTIFS(Competitors!$C$3:$C$618,$C5,Competitors!$M$3:$M$618,">0") -> 8 | V5: =COUNTIFS(Competitors!$C$3:$C$618,$C5,Competitors!$M$3:$M$618,">0",Competitors!$M$3:$M$618,"<=0.12") -> 2 | W5: =IFERROR(AVERAGEIFS(Competitors!$M$3:$M$618,Competitors!$C$3:$C$618,$C5,Competitors!$M$3:$M$618,">0"),"") -> 0.23466751 | X5: =SUMIF(Competitors!$C$3:$C$618,$C5,Competitors!$T$3:$T$618) -> 2409 | Y5: =IF(ISNUMBER(M5),M5/4,"") -> 22.75 | Z5: =IF(AND(ISNUMBER(Y5),X5>0),Y5/(Y5+X5),"") -> 0.0093554025 | AA5: 42.5 | AB5: =IFERROR(IF(N(INDEX('Our BFCM 2025'!$S:$S,MATCH($C5,'Our BFCM 2025'!$C:$C,0)))=0,"",INDEX('Our BFCM 2025'!$S:$S,MATCH($C5,'Our BFCM 2025'!$C:$C,0))),"") -> 1.20129 | AC5: =IFERROR(IF(N(INDEX('Our BFCM 2025'!$H:$H,MATCH($C5,'Our BFCM 2025'!$C:$C,0)))=0,"",INDEX('Our BFCM 2025'!$H:$H,MATCH($C5,'Our BFCM 2025'!$C:$C,0))),"") -> 0.18701621 | AD5: 0.19871795 | AE5: 1.3148085 | AF5: =COUNTIFS(Competitors!$C$3:$C$618,$C5,Competitors!$AY$3:$AY$618,"<>") -> 0 | AG5: =IFERROR(AVERAGEIFS(Competitors!$BD$3:$BD$618,Competitors!$C$3:$C$618,$C5),"") | AH5: =IFERROR(AVERAGEIFS(Competitors!$BH$3:$BH$618,Competitors!$C$3:$C$618,$C5),"")
A6: Bamboo | B6: Sleephoria Bamboo Sheets 4 Piece | C6: 36 | D6: Core | E6: Production | F6: B0DDTRVWNR | G6: 84 | H6: 5 | I6: 16 | J6: 54.99 | K6: 15.91 | L6: 0.28932533 | M6: 2 | N6: =COUNTIF(Competitors!$C$3:$C$618,$C6) -> 28 | O6: =COUNTIFS(Competitors!$C$3:$C$618,$C6,Competitors!$J$3:$J$618,"Aspirational") -> 2 | P6: =COUNTIFS(Competitors!$C$3:$C$618,$C6,Competitors!$J$3:$J$618,"Beatable") -> 8 | Q6: =COUNTIFS(Competitors!$C$3:$C$618,$C6,Competitors!$J$3:$J$618,"Poor") -> 18 | R6: 79.99 | S6: =IF(AND(ISNUMBER(J6),ISNUMBER(R6),R6>0),J6/R6-1,"") -> -0.31253907 | T6: =COUNTIFS(Competitors!$C$3:$C$618,$C6,Competitors!$Q$3:$Q$618,"<0") -> 4 | U6: =COUNTIFS(Competitors!$C$3:$C$618,$C6,Competitors!$M$3:$M$618,">0") -> 8 | V6: =COUNTIFS(Competitors!$C$3:$C$618,$C6,Competitors!$M$3:$M$618,">0",Competitors!$M$3:$M$618,"<=0.12") -> 2 | W6: =IFERROR(AVERAGEIFS(Competitors!$M$3:$M$618,Competitors!$C$3:$C$618,$C6,Competitors!$M$3:$M$618,">0"),"") -> 0.23466751 | X6: =SUMIF(Competitors!$C$3:$C$618,$C6,Competitors!$T$3:$T$618) -> 2399 | Y6: =IF(ISNUMBER(M6),M6/4,"") -> 0.5 | Z6: =IF(AND(ISNUMBER(Y6),X6>0),Y6/(Y6+X6),"") -> 0.00020837675 | AA6: 42.5 | AB6: =IFERROR(IF(N(INDEX('Our BFCM 2025'!$S:$S,MATCH($C6,'Our BFCM 2025'!$C:$C,0)))=0,"",INDEX('Our BFCM 2025'!$S:$S,MATCH($C6,'Our BFCM 2025'!$C:$C,0))),"") | AC6: =IFERROR(IF(N(INDEX('Our BFCM 2025'!$H:$H,MATCH($C6,'Our BFCM 2025'!$C:$C,0)))=0,"",INDEX('Our BFCM 2025'!$H:$H,MATCH($C6,'Our BFCM 2025'!$C:$C,0))),"") | AE6: 1.3148085 | AF6: =COUNTIFS(Competitors!$C$3:$C$618,$C6,Competitors!$AY$3:$AY$618,"<>") -> 0 | AG6: =IFERROR(AVERAGEIFS(Competitors!$BD$3:$BD$618,Competitors!$C$3:$C$618,$C6),"") | AH6: =IFERROR(AVERAGEIFS(Competitors!$BH$3:$BH$618,Competitors!$C$3:$C$618,$C6),"")
A7: Bamboo | B7: Decolure Bamboo Fitted Sheet | C7: 73 | D7: Excluded (ranking variations OOS to Dec 3) | E7: Launch | F7: B0FX2T8CG8 | G7: 22 | H7: 2 | I7: 11 | M7: 102 | N7: =COUNTIF(Competitors!$C$3:$C$618,$C7) -> 15 | O7: =COUNTIFS(Competitors!$C$3:$C$618,$C7,Competitors!$J$3:$J$618,"Aspirational") -> 3 | P7: =COUNTIFS(Competitors!$C$3:$C$618,$C7,Competitors!$J$3:$J$618,"Beatable") -> 9 | Q7: =COUNTIFS(Competitors!$C$3:$C$618,$C7,Competitors!$J$3:$J$618,"Poor") -> 1 | R7: 74.99 | S7: =IF(AND(ISNUMBER(J7),ISNUMBER(R7),R7>0),J7/R7-1,"") | T7: =COUNTIFS(Competitors!$C$3:$C$618,$C7,Competitors!$Q$3:$Q$618,"<0") -> 0 | U7: =COUNTIFS(Competitors!$C$3:$C$618,$C7,Competitors!$M$3:$M$618,">0") -> 5 | V7: =COUNTIFS(Competitors!$C$3:$C$618,$C7,Competitors!$M$3:$M$618,">0",Competitors!$M$3:$M$618,"<=0.12") -> 2 | W7: =IFERROR(AVERAGEIFS(Competitors!$M$3:$M$618,Competitors!$C$3:$C$618,$C7,Competitors!$M$3:$M$618,">0"),"") -> 0.2538565 | X7: =SUMIF(Competitors!$C$3:$C$618,$C7,Competitors!$T$3:$T$618) -> 2428 | Y7: =IF(ISNUMBER(M7),M7/4,"") -> 25.5 | Z7: =IF(AND(ISNUMBER(Y7),X7>0),Y7/(Y7+X7),"") -> 0.010393316 | AA7: 104 | AB7: =IFERROR(IF(N(INDEX('Our BFCM 2025'!$S:$S,MATCH($C7,'Our BFCM 2025'!$C:$C,0)))=0,"",INDEX('Our BFCM 2025'!$S:$S,MATCH($C7,'Our BFCM 2025'!$C:$C,0))),"") | AC7: =IFERROR(IF(N(INDEX('Our BFCM 2025'!$H:$H,MATCH($C7,'Our BFCM 2025'!$C:$C,0)))=0,"",INDEX('Our BFCM 2025'!$H:$H,MATCH($C7,'Our BFCM 2025'!$C:$C,0))),"") | AE7: 1.2415672 | AF7: =COUNTIFS(Competitors!$C$3:$C$618,$C7,Competitors!$AY$3:$AY$618,"<>") -> 0 | AG7: =IFERROR(AVERAGEIFS(Competitors!$BD$3:$BD$618,Competitors!$C$3:$C$618,$C7),"") | AH7: =IFERROR(AVERAGEIFS(Competitors!$BH$3:$BH$618,Competitors!$C$3:$C$618,$C7),"")
A8: Bamboo | B8: Sleephoria Bamboo Pillowcases | C8: 40 | D8: Other | E8: Production | F8: B0FX2RDXXR | G8: 54 | H8: 3 | I8: 18 | M8: 0 | N8: =COUNTIF(Competitors!$C$3:$C$618,$C8) -> 6 | O8: =COUNTIFS(Competitors!$C$3:$C$618,$C8,Competitors!$J$3:$J$618,"Aspirational") -> 0 | P8: =COUNTIFS(Competitors!$C$3:$C$618,$C8,Competitors!$J$3:$J$618,"Beatable") -> 0 | Q8: =COUNTIFS(Competitors!$C$3:$C$618,$C8,Competitors!$J$3:$J$618,"Poor") -> 0 | R8: 13.49 | S8: =IF(AND(ISNUMBER(J8),ISNUMBER(R8),R8>0),J8/R8-1,"") | T8: =COUNTIFS(Competitors!$C$3:$C$618,$C8,Competitors!$Q$3:$Q$618,"<0") -> 0 | U8: =COUNTIFS(Competitors!$C$3:$C$618,$C8,Competitors!$M$3:$M$618,">0") -> 2 | V8: =COUNTIFS(Competitors!$C$3:$C$618,$C8,Competitors!$M$3:$M$618,">0",Competitors!$M$3:$M$618,"<=0.12") -> 0 | W8: =IFERROR(AVERAGEIFS(Competitors!$M$3:$M$618,Competitors!$C$3:$C$618,$C8,Competitors!$M$3:$M$618,">0"),"") -> 0.44539162 | X8: =SUMIF(Competitors!$C$3:$C$618,$C8,Competitors!$T$3:$T$618) -> 3217 | Y8: =IF(ISNUMBER(M8),M8/4,"") -> 0 | Z8: =IF(AND(ISNUMBER(Y8),X8>0),Y8/(Y8+X8),"") -> 0 | AA8: 64 | AB8: =IFERROR(IF(N(INDEX('Our BFCM 2025'!$S:$S,MATCH($C8,'Our BFCM 2025'!$C:$C,0)))=0,"",INDEX('Our BFCM 2025'!$S:$S,MATCH($C8,'Our BFCM 2025'!$C:$C,0))),"") | AC8: =IFERROR(IF(N(INDEX('Our BFCM 2025'!$H:$H,MATCH($C8,'Our BFCM 2025'!$C:$C,0)))=0,"",INDEX('Our BFCM 2025'!$H:$H,MATCH($C8,'Our BFCM 2025'!$C:$C,0))),"") | AE8: 1.0414909 | AF8: =COUNTIFS(Competitors!$C$3:$C$618,$C8,Competitors!$AY$3:$AY$618,"<>") -> 0 | AG8: =IFERROR(AVERAGEIFS(Competitors!$BD$3:$BD$618,Competitors!$C$3:$C$618,$C8),"") | AH8: =IFERROR(AVERAGEIFS(Competitors!$BH$3:$BH$618,Competitors!$C$3:$C$618,$C8),"")
A9: Satin | B9: Decolure Satin Sheets 4 Piece | C9: 37 | D9: Clearance with margin | E9: Maintenance | F9: B0CQRY9WLD | G9: 125 | H9: 4 | I9: 29 | J9: 32.03725 | K9: 10.823128 | L9: 0.33782951 | M9: 2627 | N9: =COUNTIF(Competitors!$C$3:$C$618,$C9) -> 26 | O9: =COUNTIFS(Competitors!$C$3:$C$618,$C9,Competitors!$J$3:$J$618,"Aspirational") -> 3 | P9: =COUNTIFS(Competitors!$C$3:$C$618,$C9,Competitors!$J$3:$J$618,"Beatable") -> 13 | Q9: =COUNTIFS(Competitors!$C$3:$C$618,$C9,Competitors!$J$3:$J$618,"Poor") -> 8 | R9: 22.49 | S9: =IF(AND(ISNUMBER(J9),ISNUMBER(R9),R9>0),J9/R9-1,"") -> 0.42451089 | T9: =COUNTIFS(Competitors!$C$3:$C$618,$C9,Competitors!$Q$3:$Q$618,"<0") -> 26 | U9: =COUNTIFS(Competitors!$C$3:$C$618,$C9,Competitors!$M$3:$M$618,">0") -> 3 | V9: =COUNTIFS(Competitors!$C$3:$C$618,$C9,Competitors!$M$3:$M$618,">0",Competitors!$M$3:$M$618,"<=0.12") -> 0 | W9: =IFERROR(AVERAGEIFS(Competitors!$M$3:$M$618,Competitors!$C$3:$C$618,$C9,Competitors!$M$3:$M$618,">0"),"") -> 0.25953488 | X9: =SUMIF(Competitors!$C$3:$C$618,$C9,Competitors!$T$3:$T$618) -> 4991 | Y9: =IF(ISNUMBER(M9),M9/4,"") -> 656.75 | Z9: =IF(AND(ISNUMBER(Y9),X9>0),Y9/(Y9+X9),"") -> 0.11628525 | AA9: 105.5 | AB9: =IFERROR(IF(N(INDEX('Our BFCM 2025'!$S:$S,MATCH($C9,'Our BFCM 2025'!$C:$C,0)))=0,"",INDEX('Our BFCM 2025'!$S:$S,MATCH($C9,'Our BFCM 2025'!$C:$C,0))),"") -> 2.6361338 | AC9: =IFERROR(IF(N(INDEX('Our BFCM 2025'!$H:$H,MATCH($C9,'Our BFCM 2025'!$C:$C,0)))=0,"",INDEX('Our BFCM 2025'!$H:$H,MATCH($C9,'Our BFCM 2025'!$C:$C,0))),"") -> 0.048605254 | AD9: 1.242515 | AE9: 0.98611111 | AF9: =COUNTIFS(Competitors!$C$3:$C$618,$C9,Competitors!$AY$3:$AY$618,"<>") -> 0 | AG9: =IFERROR(AVERAGEIFS(Competitors!$BD$3:$BD$618,Competitors!$C$3:$C$618,$C9),"") | AH9: =IFERROR(AVERAGEIFS(Competitors!$BH$3:$BH$618,Competitors!$C$3:$C$618,$C9),"")
A10: Satin | B10: Decolure Satin Sheets 6 Piece | C10: 31 | D10: Clearance with margin | E10: Maintenance | F10: B0D9QQWYP4 | G10: 111 | H10: 4 | I10: 29 | J10: 32.904322 | K10: 9.0015031 | L10: 0.27356599 | M10: 479 | N10: =COUNTIF(Competitors!$C$3:$C$618,$C10) -> 26 | O10: =COUNTIFS(Competitors!$C$3:$C$618,$C10,Competitors!$J$3:$J$618,"Aspirational") -> 6 | P10: =COUNTIFS(Competitors!$C$3:$C$618,$C10,Competitors!$J$3:$J$618,"Beatable") -> 16 | Q10: =COUNTIFS(Competitors!$C$3:$C$618,$C10,Competitors!$J$3:$J$618,"Poor") -> 2 | R10: 22.49 | S10: =IF(AND(ISNUMBER(J10),ISNUMBER(R10),R10>0),J10/R10-1,"") -> 0.46306454 | T10: =COUNTIFS(Competitors!$C$3:$C$618,$C10,Competitors!$Q$3:$Q$618,"<0") -> 26 | U10: =COUNTIFS(Competitors!$C$3:$C$618,$C10,Competitors!$M$3:$M$618,">0") -> 3 | V10: =COUNTIFS(Competitors!$C$3:$C$618,$C10,Competitors!$M$3:$M$618,">0",Competitors!$M$3:$M$618,"<=0.12") -> 0 | W10: =IFERROR(AVERAGEIFS(Competitors!$M$3:$M$618,Competitors!$C$3:$C$618,$C10,Competitors!$M$3:$M$618,">0"),"") -> 0.25953488 | X10: =SUMIF(Competitors!$C$3:$C$618,$C10,Competitors!$T$3:$T$618) -> 4991 | Y10: =IF(ISNUMBER(M10),M10/4,"") -> 119.75 | Z10: =IF(AND(ISNUMBER(Y10),X10>0),Y10/(Y10+X10),"") -> 0.023431003 | AA10: 105.5 | AB10: =IFERROR(IF(N(INDEX('Our BFCM 2025'!$S:$S,MATCH($C10,'Our BFCM 2025'!$C:$C,0)))=0,"",INDEX('Our BFCM 2025'!$S:$S,MATCH($C10,'Our BFCM 2025'!$C:$C,0))),"") -> 3.084742 | AC10: =IFERROR(IF(N(INDEX('Our BFCM 2025'!$H:$H,MATCH($C10,'Our BFCM 2025'!$C:$C,0)))=0,"",INDEX('Our BFCM 2025'!$H:$H,MATCH($C10,'Our BFCM 2025'!$C:$C,0))),"") -> 0.14844922 | AD10: 1.215748 | AE10: 0.98611111 | AF10: =COUNTIFS(Competitors!$C$3:$C$618,$C10,Competitors!$AY$3:$AY$618,"<>") -> 0 | AG10: =IFERROR(AVERAGEIFS(Competitors!$BD$3:$BD$618,Competitors!$C$3:$C$618,$C10),"") | AH10: =IFERROR(AVERAGEIFS(Competitors!$BH$3:$BH$618,Competitors!$C$3:$C$618,$C10),"")
A11: Satin | B11: Sleephoria Satin Sheets 4 Piece | C11: 39 | D11: Clearance with margin | E11: Maintenance | F11: B0DDR4HJCS | G11: 116 | H11: 4 | I11: 29 | J11: 37.055714 | K11: 13.852086 | L11: 0.3738178 | M11: 700 | N11: =COUNTIF(Competitors!$C$3:$C$618,$C11) -> 29 | O11: =COUNTIFS(Competitors!$C$3:$C$618,$C11,Competitors!$J$3:$J$618,"Aspirational") -> 5 | P11: =COUNTIFS(Competitors!$C$3:$C$618,$C11,Competitors!$J$3:$J$618,"Beatable") -> 8 | Q11: =COUNTIFS(Competitors!$C$3:$C$618,$C11,Competitors!$J$3:$J$618,"Poor") -> 16 | R11: 21.99 | S11: =IF(AND(ISNUMBER(J11),ISNUMBER(R11),R11>0),J11/R11-1,"") -> 0.68511661 | T11: =COUNTIFS(Competitors!$C$3:$C$618,$C11,Competitors!$Q$3:$Q$618,"<0") -> 29 | U11: =COUNTIFS(Competitors!$C$3:$C$618,$C11,Competitors!$M$3:$M$618,">0") -> 4 | V11: =COUNTIFS(Competitors!$C$3:$C$618,$C11,Competitors!$M$3:$M$618,">0",Competitors!$M$3:$M$618,"<=0.12") -> 0 | W11: =IFERROR(AVERAGEIFS(Competitors!$M$3:$M$618,Competitors!$C$3:$C$618,$C11,Competitors!$M$3:$M$618,">0"),"") -> 0.25738583 | X11: =SUMIF(Competitors!$C$3:$C$618,$C11,Competitors!$T$3:$T$618) -> 5309 | Y11: =IF(ISNUMBER(M11),M11/4,"") -> 175 | Z11: =IF(AND(ISNUMBER(Y11),X11>0),Y11/(Y11+X11),"") -> 0.031911014 | AA11: 101.5 | AB11: =IFERROR(IF(N(INDEX('Our BFCM 2025'!$S:$S,MATCH($C11,'Our BFCM 2025'!$C:$C,0)))=0,"",INDEX('Our BFCM 2025'!$S:$S,MATCH($C11,'Our BFCM 2025'!$C:$C,0))),"") -> 2.5897224 | AC11: =IFERROR(IF(N(INDEX('Our BFCM 2025'!$H:$H,MATCH($C11,'Our BFCM 2025'!$C:$C,0)))=0,"",INDEX('Our BFCM 2025'!$H:$H,MATCH($C11,'Our BFCM 2025'!$C:$C,0))),"") -> 0.15765549 | AD11: 0.944 | AE11: 1.0089286 | AF11: =COUNTIFS(Competitors!$C$3:$C$618,$C11,Competitors!$AY$3:$AY$618,"<>") -> 0 | AG11: =IFERROR(AVERAGEIFS(Competitors!$BD$3:$BD$618,Competitors!$C$3:$C$618,$C11),"") | AH11: =IFERROR(AVERAGEIFS(Competitors!$BH$3:$BH$618,Competitors!$C$3:$C$618,$C11),"")
A12: Satin | B12: Sleephoria Satin Sheets 6pcs | C12: 74 | D12: Clearance with margin | E12: Production | F12: B0H41WN38B | G12: 116 | H12: 4 | I12: 29 | M12: 0 | N12: =COUNTIF(Competitors!$C$3:$C$618,$C12) -> 27 | O12: =COUNTIFS(Competitors!$C$3:$C$618,$C12,Competitors!$J$3:$J$618,"Aspirational") -> 0 | P12: =COUNTIFS(Competitors!$C$3:$C$618,$C12,Competitors!$J$3:$J$618,"Beatable") -> 0 | Q12: =COUNTIFS(Competitors!$C$3:$C$618,$C12,Competitors!$J$3:$J$618,"Poor") -> 0 | R12: 21.99 | S12: =IF(AND(ISNUMBER(J12),ISNUMBER(R12),R12>0),J12/R12-1,"") | T12: =COUNTIFS(Competitors!$C$3:$C$618,$C12,Competitors!$Q$3:$Q$618,"<0") -> 0 | U12: =COUNTIFS(Competitors!$C$3:$C$618,$C12,Competitors!$M$3:$M$618,">0") -> 4 | V12: =COUNTIFS(Competitors!$C$3:$C$618,$C12,Competitors!$M$3:$M$618,">0",Competitors!$M$3:$M$618,"<=0.12") -> 0 | W12: =IFERROR(AVERAGEIFS(Competitors!$M$3:$M$618,Competitors!$C$3:$C$618,$C12,Competitors!$M$3:$M$618,">0"),"") -> 0.25738583 | X12: =SUMIF(Competitors!$C$3:$C$618,$C12,Competitors!$T$3:$T$618) -> 5286 | Y12: =IF(ISNUMBER(M12),M12/4,"") -> 0 | Z12: =IF(AND(ISNUMBER(Y12),X12>0),Y12/(Y12+X12),"") -> 0 | AA12: 107 | AB12: =IFERROR(IF(N(INDEX('Our BFCM 2025'!$S:$S,MATCH($C12,'Our BFCM 2025'!$C:$C,0)))=0,"",INDEX('Our BFCM 2025'!$S:$S,MATCH($C12,'Our BFCM 2025'!$C:$C,0))),"") | AC12: =IFERROR(IF(N(INDEX('Our BFCM 2025'!$H:$H,MATCH($C12,'Our BFCM 2025'!$C:$C,0)))=0,"",INDEX('Our BFCM 2025'!$H:$H,MATCH($C12,'Our BFCM 2025'!$C:$C,0))),"") | AE12: 1.0178571 | AF12: =COUNTIFS(Competitors!$C$3:$C$618,$C12,Competitors!$AY$3:$AY$618,"<>") -> 0 | AG12: =IFERROR(AVERAGEIFS(Competitors!$BD$3:$BD$618,Competitors!$C$3:$C$618,$C12),"") | AH12: =IFERROR(AVERAGEIFS(Competitors!$BH$3:$BH$618,Competitors!$C$3:$C$618,$C12),"")
A13: Satin | B13: Decolure Satin Fitted Sheet | C13: 38 | D13: Opportunistic | E13: Maintenance | F13: B0DBVZV66D | G13: 68 | H13: 4 | I13: 17 | J13: 19.344242 | K13: 5.9104216 | L13: 0.30553906 | M13: 759 | N13: =COUNTIF(Competitors!$C$3:$C$618,$C13) -> 14 | O13: =COUNTIFS(Competitors!$C$3:$C$618,$C13,Competitors!$J$3:$J$618,"Aspirational") -> 0 | P13: =COUNTIFS(Competitors!$C$3:$C$618,$C13,Competitors!$J$3:$J$618,"Beatable") -> 5 | Q13: =COUNTIFS(Competitors!$C$3:$C$618,$C13,Competitors!$J$3:$J$618,"Poor") -> 5 | R13: 16.055 | S13: =IF(AND(ISNUMBER(J13),ISNUMBER(R13),R13>0),J13/R13-1,"") -> 0.2048734 | T13: =COUNTIFS(Competitors!$C$3:$C$618,$C13,Competitors!$Q$3:$Q$618,"<0") -> 12 | U13: =COUNTIFS(Competitors!$C$3:$C$618,$C13,Competitors!$M$3:$M$618,">0") -> 2 | V13: =COUNTIFS(Competitors!$C$3:$C$618,$C13,Competitors!$M$3:$M$618,">0",Competitors!$M$3:$M$618,"<=0.12") -> 0 | W13: =IFERROR(AVERAGEIFS(Competitors!$M$3:$M$618,Competitors!$C$3:$C$618,$C13,Competitors!$M$3:$M$618,">0"),"") -> 0.24512216 | X13: =SUMIF(Competitors!$C$3:$C$618,$C13,Competitors!$T$3:$T$618) -> 4248 | Y13: =IF(ISNUMBER(M13),M13/4,"") -> 189.75 | Z13: =IF(AND(ISNUMBER(Y13),X13>0),Y13/(Y13+X13),"") -> 0.042758154 | AA13: 128 | AB13: =IFERROR(IF(N(INDEX('Our BFCM 2025'!$S:$S,MATCH($C13,'Our BFCM 2025'!$C:$C,0)))=0,"",INDEX('Our BFCM 2025'!$S:$S,MATCH($C13,'Our BFCM 2025'!$C:$C,0))),"") -> 2.4693337 | AC13: =IFERROR(IF(N(INDEX('Our BFCM 2025'!$H:$H,MATCH($C13,'Our BFCM 2025'!$C:$C,0)))=0,"",INDEX('Our BFCM 2025'!$H:$H,MATCH($C13,'Our BFCM 2025'!$C:$C,0))),"") -> 0.077837782 | AD13: 1.0769231 | AE13: 1.1167535 | AF13: =COUNTIFS(Competitors!$C$3:$C$618,$C13,Competitors!$AY$3:$AY$618,"<>") -> 0 | AG13: =IFERROR(AVERAGEIFS(Competitors!$BD$3:$BD$618,Competitors!$C$3:$C$618,$C13),"") | AH13: =IFERROR(AVERAGEIFS(Competitors!$BH$3:$BH$618,Competitors!$C$3:$C$618,$C13),"")
A14: Silk | B14: Decolure Silk Pillowcase | C14: 55 | D14: Gifting | E14: Re-Launch | F14: B0DBR7PBVP | G14: 18 | H14: 3 | I14: 6 | J14: 50.203448 | K14: 18.460172 | L14: 0.36770726 | M14: 125 | N14: =COUNTIF(Competitors!$C$3:$C$618,$C14) -> 29 | O14: =COUNTIFS(Competitors!$C$3:$C$618,$C14,Competitors!$J$3:$J$618,"Aspirational") -> 5 | P14: =COUNTIFS(Competitors!$C$3:$C$618,$C14,Competitors!$J$3:$J$618,"Beatable") -> 6 | Q14: =COUNTIFS(Competitors!$C$3:$C$618,$C14,Competitors!$J$3:$J$618,"Poor") -> 1 | R14: 21.99 | S14: =IF(AND(ISNUMBER(J14),ISNUMBER(R14),R14>0),J14/R14-1,"") -> 1.2830127 | T14: =COUNTIFS(Competitors!$C$3:$C$618,$C14,Competitors!$Q$3:$Q$618,"<0") -> 25 | U14: =COUNTIFS(Competitors!$C$3:$C$618,$C14,Competitors!$M$3:$M$618,">0") -> 2 | V14: =COUNTIFS(Competitors!$C$3:$C$618,$C14,Competitors!$M$3:$M$618,">0",Competitors!$M$3:$M$618,"<=0.12") -> 2 | W14: =IFERROR(AVERAGEIFS(Competitors!$M$3:$M$618,Competitors!$C$3:$C$618,$C14,Competitors!$M$3:$M$618,">0"),"") -> 0.071286099 | X14: =SUMIF(Competitors!$C$3:$C$618,$C14,Competitors!$T$3:$T$618) -> 9718 | Y14: =IF(ISNUMBER(M14),M14/4,"") -> 31.25 | Z14: =IF(AND(ISNUMBER(Y14),X14>0),Y14/(Y14+X14),"") -> 0.0032053748 | AA14: 67 | AB14: =IFERROR(IF(N(INDEX('Our BFCM 2025'!$S:$S,MATCH($C14,'Our BFCM 2025'!$C:$C,0)))=0,"",INDEX('Our BFCM 2025'!$S:$S,MATCH($C14,'Our BFCM 2025'!$C:$C,0))),"") -> 1.3528479 | AC14: =IFERROR(IF(N(INDEX('Our BFCM 2025'!$H:$H,MATCH($C14,'Our BFCM 2025'!$C:$C,0)))=0,"",INDEX('Our BFCM 2025'!$H:$H,MATCH($C14,'Our BFCM 2025'!$C:$C,0))),"") -> 0.33571612 | AD14: 1.2977528 | AE14: 1.1650605 | AF14: =COUNTIFS(Competitors!$C$3:$C$618,$C14,Competitors!$AY$3:$AY$618,"<>") -> 0 | AG14: =IFERROR(AVERAGEIFS(Competitors!$BD$3:$BD$618,Competitors!$C$3:$C$618,$C14),"") | AH14: =IFERROR(AVERAGEIFS(Competitors!$BH$3:$BH$618,Competitors!$C$3:$C$618,$C14),"")
A15: Silk | B15: Sleephoria Silk Sleep Mask - Contoured | C15: 56 | D15: Gifting | E15: Liquidation | F15: B0F4XS1FWJ | G15: 4 | H15: 1 | I15: 4 | J15: 25.95 | K15: 8.34 | L15: 0.32138728 | M15: 4 | N15: =COUNTIF(Competitors!$C$3:$C$618,$C15) -> 27 | O15: =COUNTIFS(Competitors!$C$3:$C$618,$C15,Competitors!$J$3:$J$618,"Aspirational") -> 10 | P15: =COUNTIFS(Competitors!$C$3:$C$618,$C15,Competitors!$J$3:$J$618,"Beatable") -> 15 | Q15: =COUNTIFS(Competitors!$C$3:$C$618,$C15,Competitors!$J$3:$J$618,"Poor") -> 1 | R15: 22.49 | S15: =IF(AND(ISNUMBER(J15),ISNUMBER(R15),R15>0),J15/R15-1,"") -> 0.15384615 | T15: =COUNTIFS(Competitors!$C$3:$C$618,$C15,Competitors!$Q$3:$Q$618,"<0") -> 18 | U15: =COUNTIFS(Competitors!$C$3:$C$618,$C15,Competitors!$M$3:$M$618,">0") -> 7 | V15: =COUNTIFS(Competitors!$C$3:$C$618,$C15,Competitors!$M$3:$M$618,">0",Competitors!$M$3:$M$618,"<=0.12") -> 5 | W15: =IFERROR(AVERAGEIFS(Competitors!$M$3:$M$618,Competitors!$C$3:$C$618,$C15,Competitors!$M$3:$M$618,">0"),"") -> 0.22548917 | X15: =SUMIF(Competitors!$C$3:$C$618,$C15,Competitors!$T$3:$T$618) -> 28270 | Y15: =IF(ISNUMBER(M15),M15/4,"") -> 1 | Z15: =IF(AND(ISNUMBER(Y15),X15>0),Y15/(Y15+X15),"") -> 3.5371936e-05 | AA15: 5.5 | AB15: =IFERROR(IF(N(INDEX('Our BFCM 2025'!$S:$S,MATCH($C15,'Our BFCM 2025'!$C:$C,0)))=0,"",INDEX('Our BFCM 2025'!$S:$S,MATCH($C15,'Our BFCM 2025'!$C:$C,0))),"") | AC15: =IFERROR(IF(N(INDEX('Our BFCM 2025'!$H:$H,MATCH($C15,'Our BFCM 2025'!$C:$C,0)))=0,"",INDEX('Our BFCM 2025'!$H:$H,MATCH($C15,'Our BFCM 2025'!$C:$C,0))),"") | AE15: 1.0556398 | AF15: =COUNTIFS(Competitors!$C$3:$C$618,$C15,Competitors!$AY$3:$AY$618,"<>") -> 0 | AG15: =IFERROR(AVERAGEIFS(Competitors!$BD$3:$BD$618,Competitors!$C$3:$C$618,$C15),"") | AH15: =IFERROR(AVERAGEIFS(Competitors!$BH$3:$BH$618,Competitors!$C$3:$C$618,$C15),"")
A16: Silk | B16: Sleephoria Silk Sleep Mask - Velcro | C16: 57 | D16: Gifting | E16: Launch | F16: B0F4XQ7L8Q | G16: 4 | H16: 1 | I16: 4 | J16: 20.411538 | K16: 5.8323077 | L16: 0.28573582 | M16: 13 | N16: =COUNTIF(Competitors!$C$3:$C$618,$C16) -> 15 | O16: =COUNTIFS(Competitors!$C$3:$C$618,$C16,Competitors!$J$3:$J$618,"Aspirational") -> 6 | P16: =COUNTIFS(Competitors!$C$3:$C$618,$C16,Competitors!$J$3:$J$618,"Beatable") -> 5 | Q16: =COUNTIFS(Competitors!$C$3:$C$618,$C16,Competitors!$J$3:$J$618,"Poor") -> 0 | R16: 17.99 | S16: =IF(AND(ISNUMBER(J16),ISNUMBER(R16),R16>0),J16/R16-1,"") -> 0.13460469 | T16: =COUNTIFS(Competitors!$C$3:$C$618,$C16,Competitors!$Q$3:$Q$618,"<0") -> 10 | U16: =COUNTIFS(Competitors!$C$3:$C$618,$C16,Competitors!$M$3:$M$618,">0") -> 3 | V16: =COUNTIFS(Competitors!$C$3:$C$618,$C16,Competitors!$M$3:$M$618,">0",Competitors!$M$3:$M$618,"<=0.12") -> 2 | W16: =IFERROR(AVERAGEIFS(Competitors!$M$3:$M$618,Competitors!$C$3:$C$618,$C16,Competitors!$M$3:$M$618,">0"),"") -> 0.31967769 | X16: =SUMIF(Competitors!$C$3:$C$618,$C16,Competitors!$T$3:$T$618) -> 9878 | Y16: =IF(ISNUMBER(M16),M16/4,"") -> 3.25 | Z16: =IF(AND(ISNUMBER(Y16),X16>0),Y16/(Y16+X16),"") -> 0.00032890576 | AA16: 5.5 | AB16: =IFERROR(IF(N(INDEX('Our BFCM 2025'!$S:$S,MATCH($C16,'Our BFCM 2025'!$C:$C,0)))=0,"",INDEX('Our BFCM 2025'!$S:$S,MATCH($C16,'Our BFCM 2025'!$C:$C,0))),"") | AC16: =IFERROR(IF(N(INDEX('Our BFCM 2025'!$H:$H,MATCH($C16,'Our BFCM 2025'!$C:$C,0)))=0,"",INDEX('Our BFCM 2025'!$H:$H,MATCH($C16,'Our BFCM 2025'!$C:$C,0))),"") | AE16: 0.97139886 | AF16: =COUNTIFS(Competitors!$C$3:$C$618,$C16,Competitors!$AY$3:$AY$618,"<>") -> 0 | AG16: =IFERROR(AVERAGEIFS(Competitors!$BD$3:$BD$618,Competitors!$C$3:$C$618,$C16),"") | AH16: =IFERROR(AVERAGEIFS(Competitors!$BH$3:$BH$618,Competitors!$C$3:$C$618,$C16),"")
A17: Cooling | B17: Decolure Cooling Sheets 4 Piece | C17: 48 | D17: Off-season (aged variations only) | E17: Re-Launch | F17: B0CWJ2ZQJR | G17: 61 | H17: 6 | I17: 16 | J17: 40.326471 | K17: 11.542 | L17: 0.28621399 | M17: 89 | N17: =COUNTIF(Competitors!$C$3:$C$618,$C17) -> 28 | O17: =COUNTIFS(Competitors!$C$3:$C$618,$C17,Competitors!$J$3:$J$618,"Aspirational") -> 5 | P17: =COUNTIFS(Competitors!$C$3:$C$618,$C17,Competitors!$J$3:$J$618,"Beatable") -> 19 | Q17: =COUNTIFS(Competitors!$C$3:$C$618,$C17,Competitors!$J$3:$J$618,"Poor") -> 2 | R17: 84.99 | S17: =IF(AND(ISNUMBER(J17),ISNUMBER(R17),R17>0),J17/R17-1,"") -> -0.52551511 | T17: =COUNTIFS(Competitors!$C$3:$C$618,$C17,Competitors!$Q$3:$Q$618,"<0") -> 4 | U17: =COUNTIFS(Competitors!$C$3:$C$618,$C17,Competitors!$M$3:$M$618,">0") -> 10 | V17: =COUNTIFS(Competitors!$C$3:$C$618,$C17,Competitors!$M$3:$M$618,">0",Competitors!$M$3:$M$618,"<=0.12") -> 1 | W17: =IFERROR(AVERAGEIFS(Competitors!$M$3:$M$618,Competitors!$C$3:$C$618,$C17,Competitors!$M$3:$M$618,">0"),"") -> 0.27861813 | X17: =SUMIF(Competitors!$C$3:$C$618,$C17,Competitors!$T$3:$T$618) -> 2960 | Y17: =IF(ISNUMBER(M17),M17/4,"") -> 22.25 | Z17: =IF(AND(ISNUMBER(Y17),X17>0),Y17/(Y17+X17),"") -> 0.0074608098 | AA17: 70 | AB17: =IFERROR(IF(N(INDEX('Our BFCM 2025'!$S:$S,MATCH($C17,'Our BFCM 2025'!$C:$C,0)))=0,"",INDEX('Our BFCM 2025'!$S:$S,MATCH($C17,'Our BFCM 2025'!$C:$C,0))),"") -> 1.6283914 | AC17: =IFERROR(IF(N(INDEX('Our BFCM 2025'!$H:$H,MATCH($C17,'Our BFCM 2025'!$C:$C,0)))=0,"",INDEX('Our BFCM 2025'!$H:$H,MATCH($C17,'Our BFCM 2025'!$C:$C,0))),"") -> 0.068468955 | AE17: 1.3148085 | AF17: =COUNTIFS(Competitors!$C$3:$C$618,$C17,Competitors!$AY$3:$AY$618,"<>") -> 0 | AG17: =IFERROR(AVERAGEIFS(Competitors!$BD$3:$BD$618,Competitors!$C$3:$C$618,$C17),"") | AH17: =IFERROR(AVERAGEIFS(Competitors!$BH$3:$BH$618,Competitors!$C$3:$C$618,$C17),"")
A18: Cooling | B18: Sleephoria Cooling Sheets 4 Piece | C18: 45 | D18: Off-season (aged variations only) | E18: Re-Launch | F18: B0F7LXFGLX | G18: 61 | H18: 5 | I18: 13 | J18: 66.369518 | K18: 20.452831 | L18: 0.30816604 | M18: 332 | N18: =COUNTIF(Competitors!$C$3:$C$618,$C18) -> 36 | O18: =COUNTIFS(Competitors!$C$3:$C$618,$C18,Competitors!$J$3:$J$618,"Aspirational") -> 2 | P18: =COUNTIFS(Competitors!$C$3:$C$618,$C18,Competitors!$J$3:$J$618,"Beatable") -> 11 | Q18: =COUNTIFS(Competitors!$C$3:$C$618,$C18,Competitors!$J$3:$J$618,"Poor") -> 6 | R18: 79.495 | S18: =IF(AND(ISNUMBER(J18),ISNUMBER(R18),R18>0),J18/R18-1,"") -> -0.16511079 | T18: =COUNTIFS(Competitors!$C$3:$C$618,$C18,Competitors!$Q$3:$Q$618,"<0") -> 13 | U18: =COUNTIFS(Competitors!$C$3:$C$618,$C18,Competitors!$M$3:$M$618,">0") -> 15 | V18: =COUNTIFS(Competitors!$C$3:$C$618,$C18,Competitors!$M$3:$M$618,">0",Competitors!$M$3:$M$618,"<=0.12") -> 2 | W18: =IFERROR(AVERAGEIFS(Competitors!$M$3:$M$618,Competitors!$C$3:$C$618,$C18,Competitors!$M$3:$M$618,">0"),"") -> 0.22474776 | X18: =SUMIF(Competitors!$C$3:$C$618,$C18,Competitors!$T$3:$T$618) -> 4540 | Y18: =IF(ISNUMBER(M18),M18/4,"") -> 83 | Z18: =IF(AND(ISNUMBER(Y18),X18>0),Y18/(Y18+X18),"") -> 0.01795371 | AA18: 79 | AB18: =IFERROR(IF(N(INDEX('Our BFCM 2025'!$S:$S,MATCH($C18,'Our BFCM 2025'!$C:$C,0)))=0,"",INDEX('Our BFCM 2025'!$S:$S,MATCH($C18,'Our BFCM 2025'!$C:$C,0))),"") -> 1.1444276 | AC18: =IFERROR(IF(N(INDEX('Our BFCM 2025'!$H:$H,MATCH($C18,'Our BFCM 2025'!$C:$C,0)))=0,"",INDEX('Our BFCM 2025'!$H:$H,MATCH($C18,'Our BFCM 2025'!$C:$C,0))),"") -> 0.01606181 | AE18: 1.3124685 | AF18: =COUNTIFS(Competitors!$C$3:$C$618,$C18,Competitors!$AY$3:$AY$618,"<>") -> 0 | AG18: =IFERROR(AVERAGEIFS(Competitors!$BD$3:$BD$618,Competitors!$C$3:$C$618,$C18),"") | AH18: =IFERROR(AVERAGEIFS(Competitors!$BH$3:$BH$618,Competitors!$C$3:$C$618,$C18),"")
A19: Cooling | B19: Sleephoria Cooling Sheets 6 Piece | C19: 76 | D19: Off-season (aged variations only) | E19: Production | F19: B0H7JVGTZW | G19: 60 | H19: 5 | I19: 12 | M19: 0 | N19: =COUNTIF(Competitors!$C$3:$C$618,$C19) -> 7 | O19: =COUNTIFS(Competitors!$C$3:$C$618,$C19,Competitors!$J$3:$J$618,"Aspirational") -> 0 | P19: =COUNTIFS(Competitors!$C$3:$C$618,$C19,Competitors!$J$3:$J$618,"Beatable") -> 0 | Q19: =COUNTIFS(Competitors!$C$3:$C$618,$C19,Competitors!$J$3:$J$618,"Poor") -> 0 | R19: 139.99 | S19: =IF(AND(ISNUMBER(J19),ISNUMBER(R19),R19>0),J19/R19-1,"") | T19: =COUNTIFS(Competitors!$C$3:$C$618,$C19,Competitors!$Q$3:$Q$618,"<0") -> 0 | U19: =COUNTIFS(Competitors!$C$3:$C$618,$C19,Competitors!$M$3:$M$618,">0") -> 4 | V19: =COUNTIFS(Competitors!$C$3:$C$618,$C19,Competitors!$M$3:$M$618,">0",Competitors!$M$3:$M$618,"<=0.12") -> 1 | W19: =IFERROR(AVERAGEIFS(Competitors!$M$3:$M$618,Competitors!$C$3:$C$618,$C19,Competitors!$M$3:$M$618,">0"),"") -> 0.25997905 | X19: =SUMIF(Competitors!$C$3:$C$618,$C19,Competitors!$T$3:$T$618) -> 940 | Y19: =IF(ISNUMBER(M19),M19/4,"") -> 0 | Z19: =IF(AND(ISNUMBER(Y19),X19>0),Y19/(Y19+X19),"") -> 0 | AA19: 131 | AB19: =IFERROR(IF(N(INDEX('Our BFCM 2025'!$S:$S,MATCH($C19,'Our BFCM 2025'!$C:$C,0)))=0,"",INDEX('Our BFCM 2025'!$S:$S,MATCH($C19,'Our BFCM 2025'!$C:$C,0))),"") | AC19: =IFERROR(IF(N(INDEX('Our BFCM 2025'!$H:$H,MATCH($C19,'Our BFCM 2025'!$C:$C,0)))=0,"",INDEX('Our BFCM 2025'!$H:$H,MATCH($C19,'Our BFCM 2025'!$C:$C,0))),"") | AE19: 1.2549476 | AF19: =COUNTIFS(Competitors!$C$3:$C$618,$C19,Competitors!$AY$3:$AY$618,"<>") -> 0 | AG19: =IFERROR(AVERAGEIFS(Competitors!$BD$3:$BD$618,Competitors!$C$3:$C$618,$C19),"") | AH19: =IFERROR(AVERAGEIFS(Competitors!$BH$3:$BH$618,Competitors!$C$3:$C$618,$C19),"")
A20: Cooling | B20: CooLinens Cooling Sheets 4 Piece | C20: 69 | D20: Launch | E20: Production | F20: B0H6K5RPX6 | G20: 60 | H20: 5 | I20: 12 | M20: 42 | N20: =COUNTIF(Competitors!$C$3:$C$618,$C20) -> 14 | O20: =COUNTIFS(Competitors!$C$3:$C$618,$C20,Competitors!$J$3:$J$618,"Aspirational") -> 0 | P20: =COUNTIFS(Competitors!$C$3:$C$618,$C20,Competitors!$J$3:$J$618,"Beatable") -> 0 | Q20: =COUNTIFS(Competitors!$C$3:$C$618,$C20,Competitors!$J$3:$J$618,"Poor") -> 0 | R20: 137.995 | S20: =IF(AND(ISNUMBER(J20),ISNUMBER(R20),R20>0),J20/R20-1,"") | T20: =COUNTIFS(Competitors!$C$3:$C$618,$C20,Competitors!$Q$3:$Q$618,"<0") -> 0 | U20: =COUNTIFS(Competitors!$C$3:$C$618,$C20,Competitors!$M$3:$M$618,">0") -> 6 | V20: =COUNTIFS(Competitors!$C$3:$C$618,$C20,Competitors!$M$3:$M$618,">0",Competitors!$M$3:$M$618,"<=0.12") -> 0 | W20: =IFERROR(AVERAGEIFS(Competitors!$M$3:$M$618,Competitors!$C$3:$C$618,$C20,Competitors!$M$3:$M$618,">0"),"") -> 0.27311623 | X20: =SUMIF(Competitors!$C$3:$C$618,$C20,Competitors!$T$3:$T$618) -> 416 | Y20: =IF(ISNUMBER(M20),M20/4,"") -> 10.5 | Z20: =IF(AND(ISNUMBER(Y20),X20>0),Y20/(Y20+X20),"") -> 0.024618992 | AA20: 31 | AB20: =IFERROR(IF(N(INDEX('Our BFCM 2025'!$S:$S,MATCH($C20,'Our BFCM 2025'!$C:$C,0)))=0,"",INDEX('Our BFCM 2025'!$S:$S,MATCH($C20,'Our BFCM 2025'!$C:$C,0))),"") | AC20: =IFERROR(IF(N(INDEX('Our BFCM 2025'!$H:$H,MATCH($C20,'Our BFCM 2025'!$C:$C,0)))=0,"",INDEX('Our BFCM 2025'!$H:$H,MATCH($C20,'Our BFCM 2025'!$C:$C,0))),"") | AE20: 0.96406013 | AF20: =COUNTIFS(Competitors!$C$3:$C$618,$C20,Competitors!$AY$3:$AY$618,"<>") -> 0 | AG20: =IFERROR(AVERAGEIFS(Competitors!$BD$3:$BD$618,Competitors!$C$3:$C$618,$C20),"") | AH20: =IFERROR(AVERAGEIFS(Competitors!$BH$3:$BH$618,Competitors!$C$3:$C$618,$C20),"")
A21: Cooling | B21: CooLinens Cooling Pillowcases 2 Piece | C21: 70 | D21: Launch | E21: Launch | F21: B0H5X3L7M3 | G21: 12 | H21: 3 | I21: 4 | M21: 310 | N21: =COUNTIF(Competitors!$C$3:$C$618,$C21) -> 15 | O21: =COUNTIFS(Competitors!$C$3:$C$618,$C21,Competitors!$J$3:$J$618,"Aspirational") -> 3 | P21: =COUNTIFS(Competitors!$C$3:$C$618,$C21,Competitors!$J$3:$J$618,"Beatable") -> 11 | Q21: =COUNTIFS(Competitors!$C$3:$C$618,$C21,Competitors!$J$3:$J$618,"Poor") -> 1 | R21: 18.95 | S21: =IF(AND(ISNUMBER(J21),ISNUMBER(R21),R21>0),J21/R21-1,"") | T21: =COUNTIFS(Competitors!$C$3:$C$618,$C21,Competitors!$Q$3:$Q$618,"<0") -> 0 | U21: =COUNTIFS(Competitors!$C$3:$C$618,$C21,Competitors!$M$3:$M$618,">0") -> 3 | V21: =COUNTIFS(Competitors!$C$3:$C$618,$C21,Competitors!$M$3:$M$618,">0",Competitors!$M$3:$M$618,"<=0.12") -> 0 | W21: =IFERROR(AVERAGEIFS(Competitors!$M$3:$M$618,Competitors!$C$3:$C$618,$C21,Competitors!$M$3:$M$618,">0"),"") -> 0.29981515 | X21: =SUMIF(Competitors!$C$3:$C$618,$C21,Competitors!$T$3:$T$618) -> 737 | Y21: =IF(ISNUMBER(M21),M21/4,"") -> 77.5 | Z21: =IF(AND(ISNUMBER(Y21),X21>0),Y21/(Y21+X21),"") -> 0.095150399 | AA21: 14 | AB21: =IFERROR(IF(N(INDEX('Our BFCM 2025'!$S:$S,MATCH($C21,'Our BFCM 2025'!$C:$C,0)))=0,"",INDEX('Our BFCM 2025'!$S:$S,MATCH($C21,'Our BFCM 2025'!$C:$C,0))),"") | AC21: =IFERROR(IF(N(INDEX('Our BFCM 2025'!$H:$H,MATCH($C21,'Our BFCM 2025'!$C:$C,0)))=0,"",INDEX('Our BFCM 2025'!$H:$H,MATCH($C21,'Our BFCM 2025'!$C:$C,0))),"") | AE21: 1.1054243 | AF21: =COUNTIFS(Competitors!$C$3:$C$618,$C21,Competitors!$AY$3:$AY$618,"<>") -> 0 | AG21: =IFERROR(AVERAGEIFS(Competitors!$BD$3:$BD$618,Competitors!$C$3:$C$618,$C21),"") | AH21: =IFERROR(AVERAGEIFS(Competitors!$BH$3:$BH$618,Competitors!$C$3:$C$618,$C21),"")
A22: Cooling | B22: Sleephoria Cooling Pillowcases | C22: 43 | D22: Off-season | E22: Re-Launch | F22: B0F7LLMXSR | G22: 12 | H22: 3 | I22: 4 | J22: 20.878148 | K22: 6.8761111 | L22: 0.32934488 | M22: 54 | N22: =COUNTIF(Competitors!$C$3:$C$618,$C22) -> 21 | O22: =COUNTIFS(Competitors!$C$3:$C$618,$C22,Competitors!$J$3:$J$618,"Aspirational") -> 4 | P22: =COUNTIFS(Competitors!$C$3:$C$618,$C22,Competitors!$J$3:$J$618,"Beatable") -> 16 | Q22: =COUNTIFS(Competitors!$C$3:$C$618,$C22,Competitors!$J$3:$J$618,"Poor") -> 0 | R22: 18.95 | S22: =IF(AND(ISNUMBER(J22),ISNUMBER(R22),R22>0),J22/R22-1,"") -> 0.10174924 | T22: =COUNTIFS(Competitors!$C$3:$C$618,$C22,Competitors!$Q$3:$Q$618,"<0") -> 15 | U22: =COUNTIFS(Competitors!$C$3:$C$618,$C22,Competitors!$M$3:$M$618,">0") -> 5 | V22: =COUNTIFS(Competitors!$C$3:$C$618,$C22,Competitors!$M$3:$M$618,">0",Competitors!$M$3:$M$618,"<=0.12") -> 0 | W22: =IFERROR(AVERAGEIFS(Competitors!$M$3:$M$618,Competitors!$C$3:$C$618,$C22,Competitors!$M$3:$M$618,">0"),"") -> 0.26521448 | X22: =SUMIF(Competitors!$C$3:$C$618,$C22,Competitors!$T$3:$T$618) -> 2909 | Y22: =IF(ISNUMBER(M22),M22/4,"") -> 13.5 | Z22: =IF(AND(ISNUMBER(Y22),X22>0),Y22/(Y22+X22),"") -> 0.0046193328 | AA22: 12 | AB22: =IFERROR(IF(N(INDEX('Our BFCM 2025'!$S:$S,MATCH($C22,'Our BFCM 2025'!$C:$C,0)))=0,"",INDEX('Our BFCM 2025'!$S:$S,MATCH($C22,'Our BFCM 2025'!$C:$C,0))),"") | AC22: =IFERROR(IF(N(INDEX('Our BFCM 2025'!$H:$H,MATCH($C22,'Our BFCM 2025'!$C:$C,0)))=0,"",INDEX('Our BFCM 2025'!$H:$H,MATCH($C22,'Our BFCM 2025'!$C:$C,0))),"") | AE22: 1.0997375 | AF22: =COUNTIFS(Competitors!$C$3:$C$618,$C22,Competitors!$AY$3:$AY$618,"<>") -> 0 | AG22: =IFERROR(AVERAGEIFS(Competitors!$BD$3:$BD$618,Competitors!$C$3:$C$618,$C22),"") | AH22: =IFERROR(AVERAGEIFS(Competitors!$BH$3:$BH$618,Competitors!$C$3:$C$618,$C22),"")
A23: Cooling | B23: Sleephoria Cooling Comforter | C23: 42 | D23: Off-season (lost $2.4K at BFCM 2025) | E23: Re-Launch | F23: B0GHSH1BJK | G23: 20 | H23: 4 | I23: 5 | J23: 67.682308 | K23: 15.059846 | L23: 0.22250787 | M23: 78 | N23: =COUNTIF(Competitors!$C$3:$C$618,$C23) -> 18 | O23: =COUNTIFS(Competitors!$C$3:$C$618,$C23,Competitors!$J$3:$J$618,"Aspirational") -> 1 | P23: =COUNTIFS(Competitors!$C$3:$C$618,$C23,Competitors!$J$3:$J$618,"Beatable") -> 12 | Q23: =COUNTIFS(Competitors!$C$3:$C$618,$C23,Competitors!$J$3:$J$618,"Poor") -> 0 | R23: 46.945 | S23: =IF(AND(ISNUMBER(J23),ISNUMBER(R23),R23>0),J23/R23-1,"") -> 0.44173624 | T23: =COUNTIFS(Competitors!$C$3:$C$618,$C23,Competitors!$Q$3:$Q$618,"<0") -> 16 | U23: =COUNTIFS(Competitors!$C$3:$C$618,$C23,Competitors!$M$3:$M$618,">0") -> 5 | V23: =COUNTIFS(Competitors!$C$3:$C$618,$C23,Competitors!$M$3:$M$618,">0",Competitors!$M$3:$M$618,"<=0.12") -> 0 | W23: =IFERROR(AVERAGEIFS(Competitors!$M$3:$M$618,Competitors!$C$3:$C$618,$C23,Competitors!$M$3:$M$618,">0"),"") -> 0.27460384 | X23: =SUMIF(Competitors!$C$3:$C$618,$C23,Competitors!$T$3:$T$618) -> 1547 | Y23: =IF(ISNUMBER(M23),M23/4,"") -> 19.5 | Z23: =IF(AND(ISNUMBER(Y23),X23>0),Y23/(Y23+X23),"") -> 0.012448133 | AB23: =IFERROR(IF(N(INDEX('Our BFCM 2025'!$S:$S,MATCH($C23,'Our BFCM 2025'!$C:$C,0)))=0,"",INDEX('Our BFCM 2025'!$S:$S,MATCH($C23,'Our BFCM 2025'!$C:$C,0))),"") -> 3.3937629 | AC23: =IFERROR(IF(N(INDEX('Our BFCM 2025'!$H:$H,MATCH($C23,'Our BFCM 2025'!$C:$C,0)))=0,"",INDEX('Our BFCM 2025'!$H:$H,MATCH($C23,'Our BFCM 2025'!$C:$C,0))),"") -> 0.12283705 | AD23: 3.2537313 | AE23: 1.3749619 | AF23: =COUNTIFS(Competitors!$C$3:$C$618,$C23,Competitors!$AY$3:$AY$618,"<>") -> 0 | AG23: =IFERROR(AVERAGEIFS(Competitors!$BD$3:$BD$618,Competitors!$C$3:$C$618,$C23),"") | AH23: =IFERROR(AVERAGEIFS(Competitors!$BH$3:$BH$618,Competitors!$C$3:$C$618,$C23),"")
A24: Cooling | B24: Sleephoria Cooling Fitted Sheet | C24: 44 | D24: Off-season | E24: Re-Launch | F24: B0F7M4DPM6 | G24: 65 | H24: 5 | I24: 13 | J24: 33.225867 | K24: 8.3722222 | L24: 0.25197904 | M24: 513 | N24: =COUNTIF(Competitors!$C$3:$C$618,$C24) -> 11 | O24: =COUNTIFS(Competitors!$C$3:$C$618,$C24,Competitors!$J$3:$J$618,"Aspirational") -> 1 | P24: =COUNTIFS(Competitors!$C$3:$C$618,$C24,Competitors!$J$3:$J$618,"Beatable") -> 6 | Q24: =COUNTIFS(Competitors!$C$3:$C$618,$C24,Competitors!$J$3:$J$618,"Poor") -> 1 | R24: 62.99 | S24: =IF(AND(ISNUMBER(J24),ISNUMBER(R24),R24>0),J24/R24-1,"") -> -0.47252155 | T24: =COUNTIFS(Competitors!$C$3:$C$618,$C24,Competitors!$Q$3:$Q$618,"<0") -> 2 | U24: =COUNTIFS(Competitors!$C$3:$C$618,$C24,Competitors!$M$3:$M$618,">0") -> 5 | V24: =COUNTIFS(Competitors!$C$3:$C$618,$C24,Competitors!$M$3:$M$618,">0",Competitors!$M$3:$M$618,"<=0.12") -> 1 | W24: =IFERROR(AVERAGEIFS(Competitors!$M$3:$M$618,Competitors!$C$3:$C$618,$C24,Competitors!$M$3:$M$618,">0"),"") -> 0.28465465 | X24: =SUMIF(Competitors!$C$3:$C$618,$C24,Competitors!$T$3:$T$618) -> 2050 | Y24: =IF(ISNUMBER(M24),M24/4,"") -> 128.25 | Z24: =IF(AND(ISNUMBER(Y24),X24>0),Y24/(Y24+X24),"") -> 0.058877539 | AA24: 102.5 | AB24: =IFERROR(IF(N(INDEX('Our BFCM 2025'!$S:$S,MATCH($C24,'Our BFCM 2025'!$C:$C,0)))=0,"",INDEX('Our BFCM 2025'!$S:$S,MATCH($C24,'Our BFCM 2025'!$C:$C,0))),"") | AC24: =IFERROR(IF(N(INDEX('Our BFCM 2025'!$H:$H,MATCH($C24,'Our BFCM 2025'!$C:$C,0)))=0,"",INDEX('Our BFCM 2025'!$H:$H,MATCH($C24,'Our BFCM 2025'!$C:$C,0))),"") | AE24: 1.1787119 | AF24: =COUNTIFS(Competitors!$C$3:$C$618,$C24,Competitors!$AY$3:$AY$618,"<>") -> 0 | AG24: =IFERROR(AVERAGEIFS(Competitors!$BD$3:$BD$618,Competitors!$C$3:$C$618,$C24),"") | AH24: =IFERROR(AVERAGEIFS(Competitors!$BH$3:$BH$618,Competitors!$C$3:$C$618,$C24),"")
A25: Other | B25: Sleephoria Quilt Set | C25: 46 | D25: Liquidation | E25: Liquidation | F25: B0FGZF19SN | G25: 21 | H25: 3 | I25: 7 | J25: 29.02125 | K25: 1.4915625 | L25: 0.051395529 | M25: 32 | N25: =COUNTIF(Competitors!$C$3:$C$618,$C25) -> 19 | O25: =COUNTIFS(Competitors!$C$3:$C$618,$C25,Competitors!$J$3:$J$618,"Aspirational") -> 8 | P25: =COUNTIFS(Competitors!$C$3:$C$618,$C25,Competitors!$J$3:$J$618,"Beatable") -> 9 | Q25: =COUNTIFS(Competitors!$C$3:$C$618,$C25,Competitors!$J$3:$J$618,"Poor") -> 2 | R25: 33.99 | S25: =IF(AND(ISNUMBER(J25),ISNUMBER(R25),R25>0),J25/R25-1,"") -> -0.1461827 | T25: =COUNTIFS(Competitors!$C$3:$C$618,$C25,Competitors!$Q$3:$Q$618,"<0") -> 5 | U25: =COUNTIFS(Competitors!$C$3:$C$618,$C25,Competitors!$M$3:$M$618,">0") -> 3 | V25: =COUNTIFS(Competitors!$C$3:$C$618,$C25,Competitors!$M$3:$M$618,">0",Competitors!$M$3:$M$618,"<=0.12") -> 2 | W25: =IFERROR(AVERAGEIFS(Competitors!$M$3:$M$618,Competitors!$C$3:$C$618,$C25,Competitors!$M$3:$M$618,">0"),"") -> 0.13155026 | X25: =SUMIF(Competitors!$C$3:$C$618,$C25,Competitors!$T$3:$T$618) -> 2924 | Y25: =IF(ISNUMBER(M25),M25/4,"") -> 8 | Z25: =IF(AND(ISNUMBER(Y25),X25>0),Y25/(Y25+X25),"") -> 0.002728513 | AA25: 79 | AB25: =IFERROR(IF(N(INDEX('Our BFCM 2025'!$S:$S,MATCH($C25,'Our BFCM 2025'!$C:$C,0)))=0,"",INDEX('Our BFCM 2025'!$S:$S,MATCH($C25,'Our BFCM 2025'!$C:$C,0))),"") | AC25: =IFERROR(IF(N(INDEX('Our BFCM 2025'!$H:$H,MATCH($C25,'Our BFCM 2025'!$C:$C,0)))=0,"",INDEX('Our BFCM 2025'!$H:$H,MATCH($C25,'Our BFCM 2025'!$C:$C,0))),"") | AE25: 1.1020803 | AF25: =COUNTIFS(Competitors!$C$3:$C$618,$C25,Competitors!$AY$3:$AY$618,"<>") -> 0 | AG25: =IFERROR(AVERAGEIFS(Competitors!$BD$3:$BD$618,Competitors!$C$3:$C$618,$C25),"") | AH25: =IFERROR(AVERAGEIFS(Competitors!$BH$3:$BH$618,Competitors!$C$3:$C$618,$C25),"")
A26: Other | B26: Decolure Linen Curtains | C26: 53 | D26: Liquidation | E26: Liquidation | F26: B0F6371Q67 | G26: 42 | H26: 7 | I26: 6 | J26: 29.823333 | K26: -0.23 | L26: -0.77120823 | M26: 12 | N26: =COUNTIF(Competitors!$C$3:$C$618,$C26) -> 21 | O26: =COUNTIFS(Competitors!$C$3:$C$618,$C26,Competitors!$J$3:$J$618,"Aspirational") -> 7 | P26: =COUNTIFS(Competitors!$C$3:$C$618,$C26,Competitors!$J$3:$J$618,"Beatable") -> 8 | Q26: =COUNTIFS(Competitors!$C$3:$C$618,$C26,Competitors!$J$3:$J$618,"Poor") -> 6 | R26: 23.99 | S26: =IF(AND(ISNUMBER(J26),ISNUMBER(R26),R26>0),J26/R26-1,"") -> 0.24315687 | T26: =COUNTIFS(Competitors!$C$3:$C$618,$C26,Competitors!$Q$3:$Q$618,"<0") -> 16 | U26: =COUNTIFS(Competitors!$C$3:$C$618,$C26,Competitors!$M$3:$M$618,">0") -> 10 | V26: =COUNTIFS(Competitors!$C$3:$C$618,$C26,Competitors!$M$3:$M$618,">0",Competitors!$M$3:$M$618,"<=0.12") -> 1 | W26: =IFERROR(AVERAGEIFS(Competitors!$M$3:$M$618,Competitors!$C$3:$C$618,$C26,Competitors!$M$3:$M$618,">0"),"") -> 0.23840031 | X26: =SUMIF(Competitors!$C$3:$C$618,$C26,Competitors!$T$3:$T$618) -> 13914 | Y26: =IF(ISNUMBER(M26),M26/4,"") -> 3 | Z26: =IF(AND(ISNUMBER(Y26),X26>0),Y26/(Y26+X26),"") -> 0.0002155637 | AA26: 194 | AB26: =IFERROR(IF(N(INDEX('Our BFCM 2025'!$S:$S,MATCH($C26,'Our BFCM 2025'!$C:$C,0)))=0,"",INDEX('Our BFCM 2025'!$S:$S,MATCH($C26,'Our BFCM 2025'!$C:$C,0))),"") | AC26: =IFERROR(IF(N(INDEX('Our BFCM 2025'!$H:$H,MATCH($C26,'Our BFCM 2025'!$C:$C,0)))=0,"",INDEX('Our BFCM 2025'!$H:$H,MATCH($C26,'Our BFCM 2025'!$C:$C,0))),"") | AE26: 0.83017884 | AF26: =COUNTIFS(Competitors!$C$3:$C$618,$C26,Competitors!$AY$3:$AY$618,"<>") -> 0 | AG26: =IFERROR(AVERAGEIFS(Competitors!$BD$3:$BD$618,Competitors!$C$3:$C$618,$C26),"") | AH26: =IFERROR(AVERAGEIFS(Competitors!$BH$3:$BH$618,Competitors!$C$3:$C$618,$C26),"")
A27: Other | B27: Decolure Beach Towel | C27: 49 | D27: Other | E27: Liquidation | F27: B0DQ8NHCYM | G27: 14 | H27: 1 | I27: 7 | J27: 21.45 | K27: 5.475 | L27: 0.25524476 | M27: 2 | N27: =COUNTIF(Competitors!$C$3:$C$618,$C27) -> 13 | O27: =COUNTIFS(Competitors!$C$3:$C$618,$C27,Competitors!$J$3:$J$618,"Aspirational") -> 4 | P27: =COUNTIFS(Competitors!$C$3:$C$618,$C27,Competitors!$J$3:$J$618,"Beatable") -> 7 | Q27: =COUNTIFS(Competitors!$C$3:$C$618,$C27,Competitors!$J$3:$J$618,"Poor") -> 0 | R27: 14.99 | S27: =IF(AND(ISNUMBER(J27),ISNUMBER(R27),R27>0),J27/R27-1,"") -> 0.43095397 | T27: =COUNTIFS(Competitors!$C$3:$C$618,$C27,Competitors!$Q$3:$Q$618,"<0") -> 11 | U27: =COUNTIFS(Competitors!$C$3:$C$618,$C27,Competitors!$M$3:$M$618,">0") -> 1 | V27: =COUNTIFS(Competitors!$C$3:$C$618,$C27,Competitors!$M$3:$M$618,">0",Competitors!$M$3:$M$618,"<=0.12") -> 0 | W27: =IFERROR(AVERAGEIFS(Competitors!$M$3:$M$618,Competitors!$C$3:$C$618,$C27,Competitors!$M$3:$M$618,">0"),"") -> 0.28591851 | X27: =SUMIF(Competitors!$C$3:$C$618,$C27,Competitors!$T$3:$T$618) -> 154 | Y27: =IF(ISNUMBER(M27),M27/4,"") -> 0.5 | Z27: =IF(AND(ISNUMBER(Y27),X27>0),Y27/(Y27+X27),"") -> 0.003236246 | AA27: 7 | AB27: =IFERROR(IF(N(INDEX('Our BFCM 2025'!$S:$S,MATCH($C27,'Our BFCM 2025'!$C:$C,0)))=0,"",INDEX('Our BFCM 2025'!$S:$S,MATCH($C27,'Our BFCM 2025'!$C:$C,0))),"") | AC27: =IFERROR(IF(N(INDEX('Our BFCM 2025'!$H:$H,MATCH($C27,'Our BFCM 2025'!$C:$C,0)))=0,"",INDEX('Our BFCM 2025'!$H:$H,MATCH($C27,'Our BFCM 2025'!$C:$C,0))),"") | AF27: =COUNTIFS(Competitors!$C$3:$C$618,$C27,Competitors!$AY$3:$AY$618,"<>") -> 0 | AG27: =IFERROR(AVERAGEIFS(Competitors!$BD$3:$BD$618,Competitors!$C$3:$C$618,$C27),"") | AH27: =IFERROR(AVERAGEIFS(Competitors!$BH$3:$BH$618,Competitors!$C$3:$C$618,$C27),"")
A28: Other | B28: Decolure Front Door Welcome Sign | C28: 58 | D28: Other | E28: Liquidation | F28: B0DQ83G9MC | G28: 7 | H28: 1 | I28: 7 | J28: 37.95 | K28: 1.31 | L28: 0.034519104 | M28: 2 | N28: =COUNTIF(Competitors!$C$3:$C$618,$C28) -> 17 | O28: =COUNTIFS(Competitors!$C$3:$C$618,$C28,Competitors!$J$3:$J$618,"Aspirational") -> 3 | P28: =COUNTIFS(Competitors!$C$3:$C$618,$C28,Competitors!$J$3:$J$618,"Beatable") -> 13 | Q28: =COUNTIFS(Competitors!$C$3:$C$618,$C28,Competitors!$J$3:$J$618,"Poor") -> 0 | R28: 33.99 | S28: =IF(AND(ISNUMBER(J28),ISNUMBER(R28),R28>0),J28/R28-1,"") -> 0.11650485 | T28: =COUNTIFS(Competitors!$C$3:$C$618,$C28,Competitors!$Q$3:$Q$618,"<0") -> 12 | U28: =COUNTIFS(Competitors!$C$3:$C$618,$C28,Competitors!$M$3:$M$618,">0") -> 3 | V28: =COUNTIFS(Competitors!$C$3:$C$618,$C28,Competitors!$M$3:$M$618,">0",Competitors!$M$3:$M$618,"<=0.12") -> 1 | W28: =IFERROR(AVERAGEIFS(Competitors!$M$3:$M$618,Competitors!$C$3:$C$618,$C28,Competitors!$M$3:$M$618,">0"),"") -> 0.13975732 | X28: =SUMIF(Competitors!$C$3:$C$618,$C28,Competitors!$T$3:$T$618) -> 514 | Y28: =IF(ISNUMBER(M28),M28/4,"") -> 0.5 | Z28: =IF(AND(ISNUMBER(Y28),X28>0),Y28/(Y28+X28),"") -> 0.0009718173 | AA28: 3 | AB28: =IFERROR(IF(N(INDEX('Our BFCM 2025'!$S:$S,MATCH($C28,'Our BFCM 2025'!$C:$C,0)))=0,"",INDEX('Our BFCM 2025'!$S:$S,MATCH($C28,'Our BFCM 2025'!$C:$C,0))),"") | AC28: =IFERROR(IF(N(INDEX('Our BFCM 2025'!$H:$H,MATCH($C28,'Our BFCM 2025'!$C:$C,0)))=0,"",INDEX('Our BFCM 2025'!$H:$H,MATCH($C28,'Our BFCM 2025'!$C:$C,0))),"") | AF28: =COUNTIFS(Competitors!$C$3:$C$618,$C28,Competitors!$AY$3:$AY$618,"<>") -> 0 | AG28: =IFERROR(AVERAGEIFS(Competitors!$BD$3:$BD$618,Competitors!$C$3:$C$618,$C28),"") | AH28: =IFERROR(AVERAGEIFS(Competitors!$BH$3:$BH$618,Competitors!$C$3:$C$618,$C28),"")
A29: Other | B29: Decolure Waterproof Chair Cover | C29: 33 | D29: Other | E29: Liquidation | F29: B0CY6QPTVJ | G29: 12 | H29: 2 | I29: 6 | J29: 25.24 | K29: 3.2013333 | L29: 0.12683571 | M29: 30 | N29: =COUNTIF(Competitors!$C$3:$C$618,$C29) -> 23 | O29: =COUNTIFS(Competitors!$C$3:$C$618,$C29,Competitors!$J$3:$J$618,"Aspirational") -> 17 | P29: =COUNTIFS(Competitors!$C$3:$C$618,$C29,Competitors!$J$3:$J$618,"Beatable") -> 6 | Q29: =COUNTIFS(Competitors!$C$3:$C$618,$C29,Competitors!$J$3:$J$618,"Poor") -> 0 | R29: 22.94 | S29: =IF(AND(ISNUMBER(J29),ISNUMBER(R29),R29>0),J29/R29-1,"") -> 0.10026155 | T29: =COUNTIFS(Competitors!$C$3:$C$618,$C29,Competitors!$Q$3:$Q$618,"<0") -> 14 | U29: =COUNTIFS(Competitors!$C$3:$C$618,$C29,Competitors!$M$3:$M$618,">0") -> 5 | V29: =COUNTIFS(Competitors!$C$3:$C$618,$C29,Competitors!$M$3:$M$618,">0",Competitors!$M$3:$M$618,"<=0.12") -> 0 | W29: =IFERROR(AVERAGEIFS(Competitors!$M$3:$M$618,Competitors!$C$3:$C$618,$C29,Competitors!$M$3:$M$618,">0"),"") -> 0.19577708 | X29: =SUMIF(Competitors!$C$3:$C$618,$C29,Competitors!$T$3:$T$618) -> 1672 | Y29: =IF(ISNUMBER(M29),M29/4,"") -> 7.5 | Z29: =IF(AND(ISNUMBER(Y29),X29>0),Y29/(Y29+X29),"") -> 0.0044656148 | AA29: 68.5 | AB29: =IFERROR(IF(N(INDEX('Our BFCM 2025'!$S:$S,MATCH($C29,'Our BFCM 2025'!$C:$C,0)))=0,"",INDEX('Our BFCM 2025'!$S:$S,MATCH($C29,'Our BFCM 2025'!$C:$C,0))),"") | AC29: =IFERROR(IF(N(INDEX('Our BFCM 2025'!$H:$H,MATCH($C29,'Our BFCM 2025'!$C:$C,0)))=0,"",INDEX('Our BFCM 2025'!$H:$H,MATCH($C29,'Our BFCM 2025'!$C:$C,0))),"") | AF29: =COUNTIFS(Competitors!$C$3:$C$618,$C29,Competitors!$AY$3:$AY$618,"<>") -> 0 | AG29: =IFERROR(AVERAGEIFS(Competitors!$BD$3:$BD$618,Competitors!$C$3:$C$618,$C29),"") | AH29: =IFERROR(AVERAGEIFS(Competitors!$BH$3:$BH$618,Competitors!$C$3:$C$618,$C29),"")
A31: Medians are build-time values; every other grey cell is a live formula over the Competitors and Our BFCM 2025 tabs. Our PD 2026 organic visibility lift is for our best-selling child ASIN.

Sheet Competitors
A1: COMPETITOR (Command Center map) | K1: CURRENT MARKET - Command Center snapshot | S1: CURRENT MARKET - Command Center snapshot | V1: CURRENT MARKET - Command Center snapshot | Y1: LISTING DETAIL - Data Dive | AB1: LISTING DETAIL - Data Dive | AI1: CURRENT MARKET - Command Center snapshot | AK1: VISIBILITY HISTORY - Command Center (2026) | AO1: VISIBILITY HISTORY - Command Center (2026) | AR1: VISIBILITY HISTORY - Command Center (2026) | AU1: STR NOW - fill (Amazon page / Keepa) | AY1: BFCM 2025 + PRICE HISTORY - fill from Keepa | BE1: BFCM 2025 + PRICE HISTORY - fill from Keepa | BI1: BFCM 2025 + PRICE HISTORY - fill from Keepa | BO1: BFCM 2025 + PRICE HISTORY - fill from Keepa
A2: Family | B2: Our product | C2: Prod ID | D2: BFCM role (plan) | E2: Comp ID | F2: Brand | G2: Parent ASIN | H2: Tracked child ASIN | I2: Title | J2: Mapping tier | K2: Price now ($) | L2: List Price now ($) | M2: List Price % over price | N2: List Price band | O2: Size (from title) | P2: Our price, same size ($) | Q2: Their price vs ours (same size) | R2: Comparison basis | S2: BSR now | T2: Est weekly units | U2: Est monthly revenue ($) | V2: Rating | W2: Reviews | X2: Snapshot date | Y2: Variations (DD) | Z2: Listed (DD) | AA2: Listing age (yrs) | AB2: Family units 30d (DD est.) | AC2: Fulfilment | AD2: Active sellers | AE2: Seller country | AF2: Advertised KW % | AG2: TOS ad SV % | AH2: Page-1 KWs | AI2: ASINsight 7d traffic | AJ2: ASINsight keywords | AK2: Visibility history from | AL2: Organic score Jun 1-20 | AM2: Organic score PD Jun 23-26 | AN2: PD organic lift | AO2: Ad score Jun 1-20 | AP2: Ad score PD | AQ2: PD ad lift | AR2: Organic score Q2 (Apr 1-Jun 20) | AS2: Organic score Aug 18-Sep 16 | AT2: Organic trend (last30 vs Q2) | AU2: STR showing now? (Y/N) | AV2: STR label | AW2: Sold at List Price in last 90d? (Y/N) | AX2: Deal / coupon live now | AY2: BFCM 2025 deal type | AZ2: Deal start | BA2: Deal end | BB2: Pre-event typical price ($) | BC2: BFCM 2025 low price ($) | BD2: BFCM 2025 discount % | BE2: Coupon on top (%) | BF2: BSR pre-event avg | BG2: BSR BFCM week avg | BH2: BSR lift (x) | BI2: BSR Dec 2-31 avg | BJ2: OOS / lost Buy Box in BFCM? (Y/N) | BK2: PBDD 2025 deal price ($) | BL2: Lowest price last 90d ($) | BM2: Price below our price? | BN2: Below our 2026 deal price? | BO2: Notes
A3: Bamboo | B3: Decolure Bamboo Sheets 4 Piece | C3: 59 | D3: Hero: rank and profit | E3: 495 | F3: Bedsure | G3: B0BZ8T5BJ6 | H3: B07YK8VTJV | I3: Bedsure PureWoven 100% Rayon Derived from Bamboo, Queen Sheets, 4 Pieces | J3: Aspirational | K3: 62.99 | L3: 69.99 | M3: =IF(AND(ISNUMBER(L3),ISNUMBER(K3),K3>0),L3/K3-1,"") -> 0.11112875 | N3: =IF(M3="","No List Price",IF(M3<=0,"At/below price",IF(M3<=0.12,"<=12% (STR zone)",IF(M3<=0.25,"12-25%",">25% (likely ignored)")))) -> <=12% (STR zone) | O3: Queen | P3: 80.650959 | Q3: =IF(AND(ISNUMBER(K3),ISNUMBER(P3),N(P3)>0),K3/P3-1,"") -> -0.21898015 | R3: Same size (Queen) | S3: 256 | T3: 809 | U3: =IF(AND(ISNUMBER(K3),ISNUMBER(T3)),K3*T3*52/12,"") -> 220821.94 | V3: 4.4 | W3: 65061 | X3: 46307 | Y3: 131 | Z3: 43348 | AA3: =IF(ISNUMBER(Z3),(DATE(2026,10,13)-Z3)/365,"") -> 8.109589 | AB3: 45362 | AC3: FBA | AD3: 2 | AE3: US | AF3: 0.016494845 | AG3: 0.0010119049 | AH3: 343 | AI3: 2166046 | AJ3: 6935 | AK3: 2026-04-01 | AL3: 924.6 | AM3: 986.2 | AN3: =IF(AND(ISNUMBER(AM3),ISNUMBER(AL3),AL3>=5),AM3/AL3,"") -> 1.0666234 | AO3: 371.8 | AP3: 574.2 | AQ3: =IF(AND(ISNUMBER(AP3),ISNUMBER(AO3),AO3>=5),AP3/AO3,"") -> 1.5443787 | AR3: 832.8 | AS3: 785.1 | AT3: =IF(AND(ISNUMBER(AS3),ISNUMBER(AR3),AR3>0),AS3/AR3-1,"") -> -0.057276657 | BD3: =IF(AND(ISNUMBER(BB3),ISNUMBER(BC3),BB3>0),1-BC3/BB3,"") | BH3: =IF(AND(ISNUMBER(BF3),ISNUMBER(BG3),BG3>0),BF3/BG3,"") | BM3: =IF(ISNUMBER(Q3),IF(Q3<0,"YES","no"),"") -> YES | BN3: =IFERROR(IF(AND(ISNUMBER(K3),ISNUMBER(INDEX('Lift Inputs'!$H:$H,MATCH(C3,'Lift Inputs'!$C:$C,0)))),IF(K3<INDEX('Lift Inputs'!$H:$H,MATCH(C3,'Lift Inputs'!$C:$C,0)),"YES","no"),""),"")
A4: Bamboo | B4: Decolure Bamboo Sheets 4 Piece | C4: 59 | D4: Hero: rank and profit | E4: 4 | F4: Pure Bamboo | G4: B0CZQ52MTQ | H4: B07DZTQ4JC | I4: Pure Bamboo King Sheets, Genuine 100% Organic Viscose Derived from Bamboo Bed Sh | J4: Aspirational | K4: 109.99 | M4: =IF(AND(ISNUMBER(L4),ISNUMBER(K4),K4>0),L4/K4-1,"") | N4: =IF(M4="","No List Price",IF(M4<=0,"At/below price",IF(M4<=0.12,"<=12% (STR zone)",IF(M4<=0.25,"12-25%",">25% (likely ignored)")))) -> No List Price | O4: King | P4: 84.316772 | Q4: =IF(AND(ISNUMBER(K4),ISNUMBER(P4),N(P4)>0),K4/P4-1,"") -> 0.30448543 | R4: Same size (King) | S4: 304 | T4: 809 | U4: =IF(AND(ISNUMBER(K4),ISNUMBER(T4)),K4*T4*52/12,"") -> 385588.28 | V4: 4.5 | W4: 21927 | X4: 46307 | Y4: 181 | Z4: 43281 | AA4: =IF(ISNUMBER(Z4),(DATE(2026,10,13)-Z4)/365,"") -> 8.2931507 | AB4: 32356 | AC4: FBA | AD4: 2 | AE4: US | AF4: 0 | AG4: 0 | AH4: 268 | AI4: 2565055 | AJ4: 8283 | AK4: 2026-04-01 | AL4: 556.9 | AM4: 657.2 | AN4: =IF(AND(ISNUMBER(AM4),ISNUMBER(AL4),AL4>=5),AM4/AL4,"") -> 1.1801041 | AO4: 102 | AP4: 151.8 | AQ4: =IF(AND(ISNUMBER(AP4),ISNUMBER(AO4),AO4>=5),AP4/AO4,"") -> 1.4882353 | AR4: 259.8 | AS4: 667.9 | AT4: =IF(AND(ISNUMBER(AS4),ISNUMBER(AR4),AR4>0),AS4/AR4-1,"") -> 1.5708237 | BD4: =IF(AND(ISNUMBER(BB4),ISNUMBER(BC4),BB4>0),1-BC4/BB4,"") | BH4: =IF(AND(ISNUMBER(BF4),ISNUMBER(BG4),BG4>0),BF4/BG4,"") | BM4: =IF(ISNUMBER(Q4),IF(Q4<0,"YES","no"),"") -> no | BN4: =IFERROR(IF(AND(ISNUMBER(K4),ISNUMBER(INDEX('Lift Inputs'!$H:$H,MATCH(C4,'Lift Inputs'!$C:$C,0)))),IF(K4<INDEX('Lift Inputs'!$H:$H,MATCH(C4,'Lift Inputs'!$C:$C,0)),"YES","no"),""),"")
A5: Bamboo | B5: Decolure Bamboo Sheets 4 Piece | C5: 59 | D5: Hero: rank and profit | E5: 27 | F5: Hotel Sheets Direct | G5: B0G5N99X9R | H5: B01N9L2O9P | I5: Hotel Sheets Direct 4 Piece Bed Sheet Set Queen Size, 100% Viscose Derived from | J5: Aspirational | K5: 79.99 | M5: =IF(AND(ISNUMBER(L5),ISNUMBER(K5),K5>0),L5/K5-1,"") | N5: =IF(M5="","No List Price",IF(M5<=0,"At/below price",IF(M5<=0.12,"<=12% (STR zone)",IF(M5<=0.25,"12-25%",">25% (likely ignored)")))) -> No List Price | O5: Queen | P5: 80.650959 | Q5: =IF(AND(ISNUMBER(K5),ISNUMBER(P5),N(P5)>0),K5/P5-1,"") -> -0.0081953012 | R5: Same size (Queen) | S5: 2984 | T5: 347 | U5: =IF(AND(ISNUMBER(K5),ISNUMBER(T5)),K5*T5*52/12,"") -> 120278.3 | V5: 4.4 | W5: 37179 | X5: 46307 | Y5: 61 | Z5: 42729 | AA5: =IF(ISNUMBER(Z5),(DATE(2026,10,13)-Z5)/365,"") -> 9.8054795 | AB5: 8203 | AC5: FBA | AD5: 2 | AE5: US | AF5: 0.0021097046 | AG5: 0 | AH5: 382 | AI5: 451969 | AJ5: 4094 | AK5: 2026-01-01 | AL5: 263.5 | AM5: 474.2 | AN5: =IF(AND(ISNUMBER(AM5),ISNUMBER(AL5),AL5>=5),AM5/AL5,"") -> 1.7996205 | AO5: 24.4 | AP5: 31 | AQ5: =IF(AND(ISNUMBER(AP5),ISNUMBER(AO5),AO5>=5),AP5/AO5,"") -> 1.2704918 | AR5: 372.7 | AS5: 374.5 | AT5: =IF(AND(ISNUMBER(AS5),ISNUMBER(AR5),AR5>0),AS5/AR5-1,"") -> 0.0048296217 | BD5: =IF(AND(ISNUMBER(BB5),ISNUMBER(BC5),BB5>0),1-BC5/BB5,"") | BH5: =IF(AND(ISNUMBER(BF5),ISNUMBER(BG5),BG5>0),BF5/BG5,"") | BM5: =IF(ISNUMBER(Q5),IF(Q5<0,"YES","no"),"") -> YES | BN5: =IFERROR(IF(AND(ISNUMBER(K5),ISNUMBER(INDEX('Lift Inputs'!$H:$H,MATCH(C5,'Lift Inputs'!$C:$C,0)))),IF(K5<INDEX('Lift Inputs'!$H:$H,MATCH(C5,'Lift Inputs'!$C:$C,0)),"YES","no"),""),"")
A6: Bamboo | B6: Decolure Bamboo Sheets 4 Piece | C6: 59 | D6: Hero: rank and profit | E6: 696 | F6: Love's cabin | G6: B0DN1GGFL7 | H6: B0DN1DVKH5 | I6: Love's cabin 4 Piece Queen Sheet Set, 100% Rayon Derived from Bamboo, Cooling & | J6: Beatable | K6: 37.99 | L6: 44.99 | M6: =IF(AND(ISNUMBER(L6),ISNUMBER(K6),K6>0),L6/K6-1,"") -> 0.18425902 | N6: =IF(M6="","No List Price",IF(M6<=0,"At/below price",IF(M6<=0.12,"<=12% (STR zone)",IF(M6<=0.25,"12-25%",">25% (likely ignored)")))) -> 12-25% | O6: Queen | P6: 80.650959 | Q6: =IF(AND(ISNUMBER(K6),ISNUMBER(P6),N(P6)>0),K6/P6-1,"") -> -0.52895786 | R6: Same size (Queen) | S6: 501 | T6: 924 | U6: =IF(AND(ISNUMBER(K6),ISNUMBER(T6)),K6*T6*52/12,"") -> 152111.96 | V6: 4.4 | W6: 1900 | X6: 46307 | Y6: 176 | Z6: 45694 | AA6: =IF(ISNUMBER(Z6),(DATE(2026,10,13)-Z6)/365,"") -> 1.6821918 | AB6: 22978 | AC6: FBA | AD6: 5 | AE6: CN | AF6: 0 | AG6: 0 | AH6: 445 | AI6: 906346 | AJ6: 4326 | AK6: 2026-04-01 | AL6: 1478.5 | AM6: 1323.8 | AN6: =IF(AND(ISNUMBER(AM6),ISNUMBER(AL6),AL6>=5),AM6/AL6,"") -> 0.89536693 | AO6: 0 | AP6: 0 | AQ6: =IF(AND(ISNUMBER(AP6),ISNUMBER(AO6),AO6>=5),AP6/AO6,"") | AR6: 886.7 | AS6: 1364.5 | AT6: =IF(AND(ISNUMBER(AS6),ISNUMBER(AR6),AR6>0),AS6/AR6-1,"") -> 0.53885192 | BD6: =IF(AND(ISNUMBER(BB6),ISNUMBER(BC6),BB6>0),1-BC6/BB6,"") | BH6: =IF(AND(ISNUMBER(BF6),ISNUMBER(BG6),BG6>0),BF6/BG6,"") | BM6: =IF(ISNUMBER(Q6),IF(Q6<0,"YES","no"),"") -> YES | BN6: =IFERROR(IF(AND(ISNUMBER(K6),ISNUMBER(INDEX('Lift Inputs'!$H:$H,MATCH(C6,'Lift Inputs'!$C:$C,0)))),IF(K6<INDEX('Lift Inputs'!$H:$H,MATCH(C6,'Lift Inputs'!$C:$C,0)),"YES","no"),""),"")
A7: Bamboo | B7: Decolure Bamboo Sheets 4 Piece | C7: 59 | D7: Hero: rank and profit | E7: 33 | F7: KRIMANO | G7: B0FT7L9RSX | H7: B0FT7LZ2CD | I7: KRIMANO Bamboo Viscose Sheet Set King Size, Cooling Sheets Bed Set | J7: Beatable | K7: 84.99 | M7: =IF(AND(ISNUMBER(L7),ISNUMBER(K7),K7>0),L7/K7-1,"") | N7: =IF(M7="","No List Price",IF(M7<=0,"At/below price",IF(M7<=0.12,"<=12% (STR zone)",IF(M7<=0.25,"12-25%",">25% (likely ignored)")))) -> No List Price | O7: King | P7: 84.316772 | Q7: =IF(AND(ISNUMBER(K7),ISNUMBER(P7),N(P7)>0),K7/P7-1,"") -> 0.0079845128 | R7: Same size (King) | S7: 5664 | T7: 185 | U7: =IF(AND(ISNUMBER(K7),ISNUMBER(T7)),K7*T7*52/12,"") -> 68133.65 | V7: 4.5 | W7: 263 | X7: 46307 | Y7: 43 | Z7: 45944 | AA7: =IF(ISNUMBER(Z7),(DATE(2026,10,13)-Z7)/365,"") -> 0.99726027 | AB7: 5418 | AC7: FBA | AD7: 1 | AE7: HK | AF7: 0 | AG7: 0 | AH7: 295 | AI7: 334819 | AJ7: 2638 | AK7: 2026-01-01 | AL7: 198.1 | AM7: 260 | AN7: =IF(AND(ISNUMBER(AM7),ISNUMBER(AL7),AL7>=5),AM7/AL7,"") -> 1.3124685 | AO7: 89.9 | AP7: 320.5 | AQ7: =IF(AND(ISNUMBER(AP7),ISNUMBER(AO7),AO7>=5),AP7/AO7,"") -> 3.5650723 | AR7: 183.2 | AS7: 230.2 | AT7: =IF(AND(ISNUMBER(AS7),ISNUMBER(AR7),AR7>0),AS7/AR7-1,"") -> 0.25655022 | BD7: =IF(AND(ISNUMBER(BB7),ISNUMBER(BC7),BB7>0),1-BC7/BB7,"") | BH7: =IF(AND(ISNUMBER(BF7),ISNUMBER(BG7),BG7>0),BF7/BG7,"") | BM7: =IF(ISNUMBER(Q7),IF(Q7<0,"YES","no"),"") -> no | BN7: =IFERROR(IF(AND(ISNUMBER(K7),ISNUMBER(INDEX('Lift Inputs'!$H:$H,MATCH(C7,'Lift Inputs'!$C:$C,0)))),IF(K7<INDEX('Lift Inputs'!$H:$H,MATCH(C7,'Lift Inputs'!$C:$C,0)),"YES","no"),""),"")
A8: Bamboo | B8: Decolure Bamboo Sheets 4 Piece | C8: 59 | D8: Hero: rank and profit | E8: 1956 | F8: TRUE BAMBOO | G8: B0HHQ97HBL | H8: B0HD7R5L1D | I8: TRUE BAMBOO Sheets Set King Size - Silky Soft & Cooling - Dark Gray | J8: Beatable | K8: 114.99 | L8: 129.99 | M8: =IF(AND(ISNUMBER(L8),ISNUMBER(K8),K8>0),L8/K8-1,"") -> 0.13044613 | N8: =IF(M8="","No List Price",IF(M8<=0,"At/below price",IF(M8<=0.12,"<=12% (STR zone)",IF(M8<=0.25,"12-25%",">25% (likely ignored)")))) -> 12-25% | O8: King | P8: 84.316772 | Q8: =IF(AND(ISNUMBER(K8),ISNUMBER(P8),N(P8)>0),K8/P8-1,"") -> 0.36378561 | R8: Same size (King) | S8: 5934 | T8: 185 | U8: =IF(AND(ISNUMBER(K8),ISNUMBER(T8)),K8*T8*52/12,"") -> 92183.65 | V8: 4.6 | W8: 167 | X8: 46307 | AA8: =IF(ISNUMBER(Z8),(DATE(2026,10,13)-Z8)/365,"") | AI8: 557658 | AJ8: 2189 | AK8: 2026-04-01 | AL8: 0 | AM8: 0 | AN8: =IF(AND(ISNUMBER(AM8),ISNUMBER(AL8),AL8>=5),AM8/AL8,"") | AO8: 0 | AP8: 0 | AQ8: =IF(AND(ISNUMBER(AP8),ISNUMBER(AO8),AO8>=5),AP8/AO8,"") | AR8: 0 | AS8: 4.2 | AT8: =IF(AND(ISNUMBER(AS8),ISNUMBER(AR8),AR8>0),AS8/AR8-1,"") | BD8: =IF(AND(ISNUMBER(BB8),ISNUMBER(BC8),BB8>0),1-BC8/BB8,"") | BH8: =IF(AND(ISNUMBER(BF8),ISNUMBER(BG8),BG8>0),BF8/BG8,"") | BM8: =IF(ISNUMBER(Q8),IF(Q8<0,"YES","no"),"") -> no | BN8: =IFERROR(IF(AND(ISNUMBER(K8),ISNUMBER(INDEX('Lift Inputs'!$H:$H,MATCH(C8,'Lift Inputs'!$C:$C,0)))),IF(K8<INDEX('Lift Inputs'!$H:$H,MATCH(C8,'Lift Inputs'!$C:$C,0)),"YES","no"),""),"")
A9: Bamboo | B9: Decolure Bamboo Sheets 4 Piece | C9: 59 | D9: Hero: rank and profit | E9: 3 | F9: Bambaw | G9: B07K6SYX8L | H9: B0DR99Q37Y | I9: Bambaw 100% Viscose Derived from Bamboo Sheets Queen Size Set – 4pcs Cooling She | J9: Beatable | K9: 89.99 | M9: =IF(AND(ISNUMBER(L9),ISNUMBER(K9),K9>0),L9/K9-1,"") | N9: =IF(M9="","No List Price",IF(M9<=0,"At/below price",IF(M9<=0.12,"<=12% (STR zone)",IF(M9<=0.25,"12-25%",">25% (likely ignored)")))) -> No List Price | O9: Queen | P9: 80.650959 | Q9: =IF(AND(ISNUMBER(K9),ISNUMBER(P9),N(P9)>0),K9/P9-1,"") -> 0.11579578 | R9: Same size (Queen) | S9: 6971 | T9: 104 | U9: =IF(AND(ISNUMBER(K9),ISNUMBER(T9)),K9*T9*52/12,"") -> 40555.493 | V9: 4.3 | W9: 2766 | X9: 46307 | Y9: 104 | Z9: 45649 | AA9: =IF(ISNUMBER(Z9),(DATE(2026,10,13)-Z9)/365,"") -> 1.8054795 | AB9: 4777 | AC9: FBA | AD9: 1 | AE9: BE | AF9: 0 | AG9: 0 | AH9: 190 | AI9: 407949 | AJ9: 2137 | AK9: 2026-01-01 | AL9: 356.5 | AM9: 490 | AN9: =IF(AND(ISNUMBER(AM9),ISNUMBER(AL9),AL9>=5),AM9/AL9,"") -> 1.3744741 | AO9: 57.6 | AP9: 82.5 | AQ9: =IF(AND(ISNUMBER(AP9),ISNUMBER(AO9),AO9>=5),AP9/AO9,"") -> 1.4322917 | AR9: 239.9 | AS9: 571.4 | AT9: =IF(AND(ISNUMBER(AS9),ISNUMBER(AR9),AR9>0),AS9/AR9-1,"") -> 1.3818258 | BD9: =IF(AND(ISNUMBER(BB9),ISNUMBER(BC9),BB9>0),1-BC9/BB9,"") | BH9: =IF(AND(ISNUMBER(BF9),ISNUMBER(BG9),BG9>0),BF9/BG9,"") | BM9: =IF(ISNUMBER(Q9),IF(Q9<0,"YES","no"),"") -> no | BN9: =IFERROR(IF(AND(ISNUMBER(K9),ISNUMBER(INDEX('Lift Inputs'!$H:$H,MATCH(C9,'Lift Inputs'!$C:$C,0)))),IF(K9<INDEX('Lift Inputs'!$H:$H,MATCH(C9,'Lift Inputs'!$C:$C,0)),"YES","no"),""),"")
A10: Bamboo | B10: Decolure Bamboo Sheets 4 Piece | C10: 59 | D10: Hero: rank and profit | E10: 6 | F10: Bedsure | G10: B0FB8XS4D1 | H10: B0FB8XR43Q | I10: Bedsure PureWoven Organically Grown Bamboo Viscose Queen Sheet Set, 4PCS | J10: Beatable | K10: 89.99 | L10: 119.99 | M10: =IF(AND(ISNUMBER(L10),ISNUMBER(K10),K10>0),L10/K10-1,"") -> 0.33337037 | N10: =IF(M10="","No List Price",IF(M10<=0,"At/below price",IF(M10<=0.12,"<=12% (STR zone)",IF(M10<=0.25,"12-25%",">25% (likely ignored)")))) -> >25% (likely ignored) | O10: Queen | P10: 80.650959 | Q10: =IF(AND(ISNUMBER(K10),ISNUMBER(P10),N(P10)>0),K10/P10-1,"") -> 0.11579578 | R10: Same size (Queen) | S10: 8938 | T10: 104 | U10: =IF(AND(ISNUMBER(K10),ISNUMBER(T10)),K10*T10*52/12,"") -> 40555.493 | V10: 4.5 | W10: 588 | X10: 46307 | Y10: 39 | Z10: 45936 | AA10: =IF(ISNUMBER(Z10),(DATE(2026,10,13)-Z10)/365,"") -> 1.0191781 | AB10: 4014 | AC10: FBA | AD10: 4 | AE10: US | AF10: 0 | AG10: 0 | AH10: 313 | AI10: 840292 | AJ10: 3961 | AK10: 2026-01-01 | AL10: 279.8 | AM10: 493.8 | AN10: =IF(AND(ISNUMBER(AM10),ISNUMBER(AL10),AL10>=5),AM10/AL10,"") -> 1.764832 | AO10: 320.1 | AP10: 534.8 | AQ10: =IF(AND(ISNUMBER(AP10),ISNUMBER(AO10),AO10>=5),AP10/AO10,"") -> 1.6707279 | AR10: 248.7 | AS10: 226.2 | AT10: =IF(AND(ISNUMBER(AS10),ISNUMBER(AR10),AR10>0),AS10/AR10-1,"") -> -0.090470446 | BD10: =IF(AND(ISNUMBER(BB10),ISNUMBER(BC10),BB10>0),1-BC10/BB10,"") | BH10: =IF(AND(ISNUMBER(BF10),ISNUMBER(BG10),BG10>0),BF10/BG10,"") | BM10: =IF(ISNUMBER(Q10),IF(Q10<0,"YES","no"),"") -> no | BN10: =IFERROR(IF(AND(ISNUMBER(K10),ISNUMBER(INDEX('Lift Inputs'!$H:$H,MATCH(C10,'Lift Inputs'!$C:$C,0)))),IF(K10<INDEX('Lift Inputs'!$H:$H,MATCH(C10,'Lift Inputs'!$C:$C,0)),"YES","no"),""),"")
A11: Bamboo | B11: Decolure Bamboo Sheets 4 Piece | C11: 59 | D11: Hero: rank and profit | E11: 1507 | F11: SONORO KATE | G11: B0F4852T9V | H11: B0F4873G4H | I11: Bamboo Sheets | J11: Beatable | K11: 79.99 | M11: =IF(AND(ISNUMBER(L11),ISNUMBER(K11),K11>0),L11/K11-1,"") | N11: =IF(M11="","No List Price",IF(M11<=0,"At/below price",IF(M11<=0.12,"<=12% (STR zone)",IF(M11<=0.25,"12-25%",">25% (likely ignored)")))) -> No List Price | P11: 80.650959 | Q11: =IF(AND(ISNUMBER(K11),ISNUMBER(P11),N(P11)>0),K11/P11-1,"") -> -0.0081953012 | R11: Size unknown - vs our Queen | S11: 7961 | T11: 104 | U11: =IF(AND(ISNUMBER(K11),ISNUMBER(T11)),K11*T11*52/12,"") -> 36048.827 | V11: 4.5 | W11: 3776 | X11: 46307 | AA11: =IF(ISNUMBER(Z11),(DATE(2026,10,13)-Z11)/365,"") | AI11: 185157 | AJ11: 1447 | AK11: 2026-01-01 | AL11: 295.1 | AM11: 388 | AN11: =IF(AND(ISNUMBER(AM11),ISNUMBER(AL11),AL11>=5),AM11/AL11,"") -> 1.3148085 | AO11: 1.1 | AP11: 0.5 | AQ11: =IF(AND(ISNUMBER(AP11),ISNUMBER(AO11),AO11>=5),AP11/AO11,"") | AR11: 254.1 | AS11: 411.3 | AT11: =IF(AND(ISNUMBER(AS11),ISNUMBER(AR11),AR11>0),AS11/AR11-1,"") -> 0.61865407 | BD11: =IF(AND(ISNUMBER(BB11),ISNUMBER(BC11),BB11>0),1-BC11/BB11,"") | BH11: =IF(AND(ISNUMBER(BF11),ISNUMBER(BG11),BG11>0),BF11/BG11,"") | BM11: =IF(ISNUMBER(Q11),IF(Q11<0,"YES","no"),"") -> YES | BN11: =IFERROR(IF(AND(ISNUMBER(K11),ISNUMBER(INDEX('Lift Inputs'!$H:$H,MATCH(C11,'Lift Inputs'!$C:$C,0)))),IF(K11<INDEX('Lift Inputs'!$H:$H,MATCH(C11,'Lift Inputs'!$C:$C,0)),"YES","no"),""),"")
A12: Bamboo | B12: Decolure Bamboo Sheets 4 Piece | C12: 59 | D12: Hero: rank and profit | E12: 637 | F12: BC BELLA COTERIE | G12: B0H29V113N | H12: B08L86VLZB | I12: Bella Coterie Luxury Bamboo Viscose King Size Sheet Set | J12: Beatable | K12: 134.99 | M12: =IF(AND(ISNUMBER(L12),ISNUMBER(K12),K12>0),L12/K12-1,"") | N12: =IF(M12="","No List Price",IF(M12<=0,"At/below price",IF(M12<=0.12,"<=12% (STR zone)",IF(M12<=0.25,"12-25%",">25% (likely ignored)")))) -> No List Price | O12: King | P12: 84.316772 | Q12: =IF(AND(ISNUMBER(K12),ISNUMBER(P12),N(P12)>0),K12/P12-1,"") -> 0.60098634 | R12: Same size (King) | S12: 1358 | T12: 92 | U12: =IF(AND(ISNUMBER(K12),ISNUMBER(T12)),K12*T12*52/12,"") -> 53816.013 | V12: 4.4 | W12: 5871 | X12: 46307 | Y12: 258 | Z12: 44154 | AA12: =IF(ISNUMBER(Z12),(DATE(2026,10,13)-Z12)/365,"") -> 5.9013699 | AB12: 13039 | AC12: FBA | AD12: 1 | AE12: US | AF12: 0.80168776 | AG12: 0.36133922 | AH12: 316 | AI12: 591713 | AJ12: 5504 | AK12: 2026-04-01 | AL12: 107.7 | AM12: 191.5 | AN12: =IF(AND(ISNUMBER(AM12),ISNUMBER(AL12),AL12>=5),AM12/AL12,"") -> 1.7780873 | AO12: 49.4 | AP12: 99.8 | AQ12: =IF(AND(ISNUMBER(AP12),ISNUMBER(AO12),AO12>=5),AP12/AO12,"") -> 2.0202429 | AR12: 127.5 | AS12: 175.6 | AT12: =IF(AND(ISNUMBER(AS12),ISNUMBER(AR12),AR12>0),AS12/AR12-1,"") -> 0.3772549 | BD12: =IF(AND(ISNUMBER(BB12),ISNUMBER(BC12),BB12>0),1-BC12/BB12,"") | BH12: =IF(AND(ISNUMBER(BF12),ISNUMBER(BG12),BG12>0),BF12/BG12,"") | BM12: =IF(ISNUMBER(Q12),IF(Q12<0,"YES","no"),"") -> no | BN12: =IFERROR(IF(AND(ISNUMBER(K12),ISNUMBER(INDEX('Lift Inputs'!$H:$H,MATCH(C12,'Lift Inputs'!$C:$C,0)))),IF(K12<INDEX('Lift Inputs'!$H:$H,MATCH(C12,'Lift Inputs'!$C:$C,0)),"YES","no"),""),"")
A13: Bamboo | B13: Decolure Bamboo Sheets 4 Piece | C13: 59 | D13: Hero: rank and profit | E13: 1814 | F13: BAMPURE | G13: B0HC778XB4 | H13: B07XFP6BY2 | I13: BAMPURE 100% Rayon from Bamboo Sheets King Size - 4pc Cooling King Sheets | J13: Beatable | K13: 67.98 | L13: 99.99 | M13: =IF(AND(ISNUMBER(L13),ISNUMBER(K13),K13>0),L13/K13-1,"") -> 0.47087379 | N13: =IF(M13="","No List Price",IF(M13<=0,"At/below price",IF(M13<=0.12,"<=12% (STR zone)",IF(M13<=0.25,"12-25%",">25% (likely ignored)")))) -> >25% (likely ignored) | O13: King | P13: 84.316772 | Q13: =IF(AND(ISNUMBER(K13),ISNUMBER(P13),N(P13)>0),K13/P13-1,"") -> -0.19375471 | R13: Same size (King) | S13: 14479 | T13: 81 | U13: =IF(AND(ISNUMBER(K13),ISNUMBER(T13)),K13*T13*52/12,"") -> 23860.98 | V13: 4.4 | W13: 4095 | X13: 46307 | Y13: 40 | Z13: 43776 | AA13: =IF(ISNUMBER(Z13),(DATE(2026,10,13)-Z13)/365,"") -> 6.9369863 | AB13: 2824 | AC13: FBA | AD13: 1 | AE13: US | AF13: 0 | AG13: 0 | AH13: 158 | AI13: 67699 | AJ13: 1687 | AK13: 2026-04-01 | AL13: 83.8 | AM13: 85.2 | AN13: =IF(AND(ISNUMBER(AM13),ISNUMBER(AL13),AL13>=5),AM13/AL13,"") -> 1.0167064 | AO13: 10.4 | AP13: 24 | AQ13: =IF(AND(ISNUMBER(AP13),ISNUMBER(AO13),AO13>=5),AP13/AO13,"") -> 2.3076923 | AR13: 64.5 | AS13: 46 | AT13: =IF(AND(ISNUMBER(AS13),ISNUMBER(AR13),AR13>0),AS13/AR13-1,"") -> -0.28682171 | BD13: =IF(AND(ISNUMBER(BB13),ISNUMBER(BC13),BB13>0),1-BC13/BB13,"") | BH13: =IF(AND(ISNUMBER(BF13),ISNUMBER(BG13),BG13>0),BF13/BG13,"") | BM13: =IF(ISNUMBER(Q13),IF(Q13<0,"YES","no"),"") -> YES | BN13: =IFERROR(IF(AND(ISNUMBER(K13),ISNUMBER(INDEX('Lift Inputs'!$H:$H,MATCH(C13,'Lift Inputs'!$C:$C,0)))),IF(K13<INDEX('Lift Inputs'!$H:$H,MATCH(C13,'Lift Inputs'!$C:$C,0)),"YES","no"),""),"")
A14: Bamboo | B14: Decolure Bamboo Sheets 4 Piece | C14: 59 | D14: Hero: rank and profit | E14: 1945 | F14: BEDELITE | G14: B0GT98GVQN | H14: B0GT8Z4X5D | I14: BEDELITE Bamboo Viscose Sheet Set, Queen Size, 4 Pieces, White | J14: Beatable | K14: 84.98 | L14: 99.89 | M14: =IF(AND(ISNUMBER(L14),ISNUMBER(K14),K14>0),L14/K14-1,"") -> 0.17545305 | N14: =IF(M14="","No List Price",IF(M14<=0,"At/below price",IF(M14<=0.12,"<=12% (STR zone)",IF(M14<=0.25,"12-25%",">25% (likely ignored)")))) -> 12-25% | O14: Queen | P14: 80.650959 | Q14: =IF(AND(ISNUMBER(K14),ISNUMBER(P14),N(P14)>0),K14/P14-1,"") -> 0.053676251 | R14: Same size (Queen) | S14: 65907 | T14: 81 | U14: =IF(AND(ISNUMBER(K14),ISNUMBER(T14)),K14*T14*52/12,"") -> 29827.98 | V14: 4.5 | W14: 113 | X14: 46307 | AA14: =IF(ISNUMBER(Z14),(DATE(2026,10,13)-Z14)/365,"") | AI14: 212120 | AJ14: 1732 | AK14: 2026-04-01 | AL14: 141.2 | AM14: 114 | AN14: =IF(AND(ISNUMBER(AM14),ISNUMBER(AL14),AL14>=5),AM14/AL14,"") -> 0.80736544 | AO14: 193.2 | AP14: 145.5 | AQ14: =IF(AND(ISNUMBER(AP14),ISNUMBER(AO14),AO14>=5),AP14/AO14,"") -> 0.75310559 | AR14: 54.9 | AS14: 82.2 | AT14: =IF(AND(ISNUMBER(AS14),ISNUMBER(AR14),AR14>0),AS14/AR14-1,"") -> 0.49726776 | BD14: =IF(AND(ISNUMBER(BB14),ISNUMBER(BC14),BB14>0),1-BC14/BB14,"") | BH14: =IF(AND(ISNUMBER(BF14),ISNUMBER(BG14),BG14>0),BF14/BG14,"") | BM14: =IF(ISNUMBER(Q14),IF(Q14<0,"YES","no"),"") -> no | BN14: =IFERROR(IF(AND(ISNUMBER(K14),ISNUMBER(INDEX('Lift Inputs'!$H:$H,MATCH(C14,'Lift Inputs'!$C:$C,0)))),IF(K14<INDEX('Lift Inputs'!$H:$H,MATCH(C14,'Lift Inputs'!$C:$C,0)),"YES","no"),""),"")
A15: Bamboo | B15: Decolure Bamboo Sheets 4 Piece | C15: 59 | D15: Hero: rank and profit | E15: 22 | F15: SONORO KATE | G15: B0F29FQLFD | H15: B0F29F1JM5 | I15: SONORO KATE 100% Viscose Derived from Bamboo_Sheets Queen Size,4PC | J15: Beatable | K15: 59.99 | M15: =IF(AND(ISNUMBER(L15),ISNUMBER(K15),K15>0),L15/K15-1,"") | N15: =IF(M15="","No List Price",IF(M15<=0,"At/below price",IF(M15<=0.12,"<=12% (STR zone)",IF(M15<=0.25,"12-25%",">25% (likely ignored)")))) -> No List Price | O15: Queen | P15: 80.650959 | Q15: =IF(AND(ISNUMBER(K15),ISNUMBER(P15),N(P15)>0),K15/P15-1,"") -> -0.25617747 | R15: Same size (Queen) | S15: 23979 | T15: 81 | U15: =IF(AND(ISNUMBER(K15),ISNUMBER(T15)),K15*T15*52/12,"") -> 21056.49 | V15: 4.5 | W15: 3911 | X15: 46307 | Y15: 42 | Z15: 45740 | AA15: =IF(ISNUMBER(Z15),(DATE(2026,10,13)-Z15)/365,"") -> 1.5561644 | AB15: 1814 | AC15: FBA | AD15: 1 | AE15: CN | AF15: 0 | AG15: 0 | AH15: 278 | AI15: 114504 | AJ15: 947 | AK15: 2026-01-01 | AL15: 431.4 | AM15: 472.5 | AN15: =IF(AND(ISNUMBER(AM15),ISNUMBER(AL15),AL15>=5),AM15/AL15,"") -> 1.0952712 | AO15: 13.8 | AP15: 16.5 | AQ15: =IF(AND(ISNUMBER(AP15),ISNUMBER(AO15),AO15>=5),AP15/AO15,"") -> 1.1956522 | AR15: 365.3 | AS15: 327.3 | AT15: =IF(AND(ISNUMBER(AS15),ISNUMBER(AR15),AR15>0),AS15/AR15-1,"") -> -0.10402409 | BD15: =IF(AND(ISNUMBER(BB15),ISNUMBER(BC15),BB15>0),1-BC15/BB15,"") | BH15: =IF(AND(ISNUMBER(BF15),ISNUMBER(BG15),BG15>0),BF15/BG15,"") | BM15: =IF(ISNUMBER(Q15),IF(Q15<0,"YES","no"),"") -> YES | BN15: =IFERROR(IF(AND(ISNUMBER(K15),ISNUMBER(INDEX('Lift Inputs'!$H:$H,MATCH(C15,'Lift Inputs'!$C:$C,0)))),IF(K15<INDEX('Lift Inputs'!$H:$H,MATCH(C15,'Lift Inputs'!$C:$C,0)),"YES","no"),""),"")
A16: Bamboo | B16: Decolure Bamboo Sheets 4 Piece | C16: 59 | D16: Hero: rank and profit | E16: 1953 | F16: Davmabcjy | G16: B0HJZNMQ5G | H16: B0GXJYQR7H | I16: 100% Organically Grown Bamboo Viscose King Sheet Set with Pockets on Side | J16: Beatable | K16: 59.99 | M16: =IF(AND(ISNUMBER(L16),ISNUMBER(K16),K16>0),L16/K16-1,"") | N16: =IF(M16="","No List Price",IF(M16<=0,"At/below price",IF(M16<=0.12,"<=12% (STR zone)",IF(M16<=0.25,"12-25%",">25% (likely ignored)")))) -> No List Price | O16: King | P16: 84.316772 | Q16: =IF(AND(ISNUMBER(K16),ISNUMBER(P16),N(P16)>0),K16/P16-1,"") -> -0.2885164 | R16: Same size (King) | S16: 205508 | T16: 35 | U16: =IF(AND(ISNUMBER(K16),ISNUMBER(T16)),K16*T16*52/12,"") -> 9098.4833 | V16: 4.2 | W16: 81 | X16: 46307 | AA16: =IF(ISNUMBER(Z16),(DATE(2026,10,13)-Z16)/365,"") | AI16: 75425 | AJ16: 1329 | AK16: 2026-04-01 | AL16: 0 | AM16: 0 | AN16: =IF(AND(ISNUMBER(AM16),ISNUMBER(AL16),AL16>=5),AM16/AL16,"") | AO16: 0 | AP16: 0 | AQ16: =IF(AND(ISNUMBER(AP16),ISNUMBER(AO16),AO16>=5),AP16/AO16,"") | AR16: 0 | AS16: 69.1 | AT16: =IF(AND(ISNUMBER(AS16),ISNUMBER(AR16),AR16>0),AS16/AR16-1,"") | BD16: =IF(AND(ISNUMBER(BB16),ISNUMBER(BC16),BB16>0),1-BC16/BB16,"") | BH16: =IF(AND(ISNUMBER(BF16),ISNUMBER(BG16),BG16>0),BF16/BG16,"") | BM16: =IF(ISNUMBER(Q16),IF(Q16<0,"YES","no"),"") -> YES | BN16: =IFERROR(IF(AND(ISNUMBER(K16),ISNUMBER(INDEX('Lift Inputs'!$H:$H,MATCH(C16,'Lift Inputs'!$C:$C,0)))),IF(K16<INDEX('Lift Inputs'!$H:$H,MATCH(C16,'Lift Inputs'!$C:$C,0)),"YES","no"),""),"")
A17: Bamboo | B17: Decolure Bamboo Sheets 4 Piece | C17: 59 | D17: Hero: rank and profit | E17: 1510 | F17: DOZ by SIJO | G17: B0DCZGYVZ9 | H17: B0F24TRXCZ | I17: Bamboo Sheets | J17: Beatable | K17: 55 | M17: =IF(AND(ISNUMBER(L17),ISNUMBER(K17),K17>0),L17/K17-1,"") | N17: =IF(M17="","No List Price",IF(M17<=0,"At/below price",IF(M17<=0.12,"<=12% (STR zone)",IF(M17<=0.25,"12-25%",">25% (likely ignored)")))) -> No List Price | P17: 80.650959 | Q17: =IF(AND(ISNUMBER(K17),ISNUMBER(P17),N(P17)>0),K17/P17-1,"") -> -0.31804903 | R17: Size unknown - vs our Queen | S17: 4051 | T17: 35 | U17: =IF(AND(ISNUMBER(K17),ISNUMBER(T17)),K17*T17*52/12,"") -> 8341.6667 | V17: 4.4 | W17: 1909 | X17: 46307 | AA17: =IF(ISNUMBER(Z17),(DATE(2026,10,13)-Z17)/365,"") | AI17: 171534 | AJ17: 2682 | AN17: =IF(AND(ISNUMBER(AM17),ISNUMBER(AL17),AL17>=5),AM17/AL17,"") | AQ17: =IF(AND(ISNUMBER(AP17),ISNUMBER(AO17),AO17>=5),AP17/AO17,"") | AT17: =IF(AND(ISNUMBER(AS17),ISNUMBER(AR17),AR17>0),AS17/AR17-1,"") | BD17: =IF(AND(ISNUMBER(BB17),ISNUMBER(BC17),BB17>0),1-BC17/BB17,"") | BH17: =IF(AND(ISNUMBER(BF17),ISNUMBER(BG17),BG17>0),BF17/BG17,"") | BM17: =IF(ISNUMBER(Q17),IF(Q17<0,"YES","no"),"") -> YES | BN17: =IFERROR(IF(AND(ISNUMBER(K17),ISNUMBER(INDEX('Lift Inputs'!$H:$H,MATCH(C17,'Lift Inputs'!$C:$C,0)))),IF(K17<INDEX('Lift Inputs'!$H:$H,MATCH(C17,'Lift Inputs'!$C:$C,0)),"YES","no"),""),"")
A18: Bamboo | B18: Decolure Bamboo Sheets 4 Piece | C18: 59 | D18: Hero: rank and profit | E18: 1819 | F18: GOKOTTA | G18: B09WV7RN1V | H18: B0BR53P7DY | I18: GOKOTTA King Bamboo Rayon Sheets Set, Silky Soft Cooling Sheets Stay Put | J18: Beatable | K18: 109 | M18: =IF(AND(ISNUMBER(L18),ISNUMBER(K18),K18>0),L18/K18-1,"") | N18: =IF(M18="","No List Price",IF(M18<=0,"At/below price",IF(M18<=0.12,"<=12% (STR zone)",IF(M18<=0.25,"12-25%",">25% (likely ignored)")))) -> No List Price | O18: King | P18: 84.316772 | Q18: =IF(AND(ISNUMBER(K18),ISNUMBER(P18),N(P18)>0),K18/P18-1,"") -> 0.29274399 | R18: Same size (King) | S18: 16154 | T18: 35 | U18: =IF(AND(ISNUMBER(K18),ISNUMBER(T18)),K18*T18*52/12,"") -> 16531.667 | V18: 4.4 | W18: 3371 | X18: 46307 | Y18: 99 | Z18: 44922 | AA18: =IF(ISNUMBER(Z18),(DATE(2026,10,13)-Z18)/365,"") -> 3.7972603 | AB18: 2972 | AC18: FBA | AD18: 1 | AE18: TH | AF18: 0 | AG18: 0 | AH18: 68 | AI18: 76017 | AJ18: 1577 | AN18: =IF(AND(ISNUMBER(AM18),ISNUMBER(AL18),AL18>=5),AM18/AL18,"") | AQ18: =IF(AND(ISNUMBER(AP18),ISNUMBER(AO18),AO18>=5),AP18/AO18,"") | AT18: =IF(AND(ISNUMBER(AS18),ISNUMBER(AR18),AR18>0),AS18/AR18-1,"") | BD18: =IF(AND(ISNUMBER(BB18),ISNUMBER(BC18),BB18>0),1-BC18/BB18,"") | BH18: =IF(AND(ISNUMBER(BF18),ISNUMBER(BG18),BG18>0),BF18/BG18,"") | BM18: =IF(ISNUMBER(Q18),IF(Q18<0,"YES","no"),"") -> no | BN18: =IFERROR(IF(AND(ISNUMBER(K18),ISNUMBER(INDEX('Lift Inputs'!$H:$H,MATCH(C18,'Lift Inputs'!$C:$C,0)))),IF(K18<INDEX('Lift Inputs'!$H:$H,MATCH(C18,'Lift Inputs'!$C:$C,0)),"YES","no"),""),"")
A19: Bamboo | B19: Decolure Bamboo Sheets 4 Piece | C19: 59 | D19: Hero: rank and profit | E19: 1816 | F19: KARISSA MAE | G19: B0GT172Y8L | H19: B0G1CSCQTB | I19: Cooling Sheets | J19: Beatable | K19: 119.99 | M19: =IF(AND(ISNUMBER(L19),ISNUMBER(K19),K19>0),L19/K19-1,"") | N19: =IF(M19="","No List Price",IF(M19<=0,"At/below price",IF(M19<=0.12,"<=12% (STR zone)",IF(M19<=0.25,"12-25%",">25% (likely ignored)")))) -> No List Price | P19: 80.650959 | Q19: =IF(AND(ISNUMBER(K19),ISNUMBER(P19),N(P19)>0),K19/P19-1,"") -> 0.48776904 | R19: Size unknown - vs our Queen | S19: 15914 | T19: 35 | U19: =IF(AND(ISNUMBER(K19),ISNUMBER(T19)),K19*T19*52/12,"") -> 18198.483 | V19: 4.3 | W19: 474 | X19: 46307 | AA19: =IF(ISNUMBER(Z19),(DATE(2026,10,13)-Z19)/365,"") | AI19: 243610 | AJ19: 3715 | AK19: 2026-04-01 | AL19: 23.4 | AM19: 49.2 | AN19: =IF(AND(ISNUMBER(AM19),ISNUMBER(AL19),AL19>=5),AM19/AL19,"") -> 2.1025641 | AO19: 45.5 | AP19: 115.2 | AQ19: =IF(AND(ISNUMBER(AP19),ISNUMBER(AO19),AO19>=5),AP19/AO19,"") -> 2.5318681 | AR19: 23.6 | AS19: 2.9 | AT19: =IF(AND(ISNUMBER(AS19),ISNUMBER(AR19),AR19>0),AS19/AR19-1,"") -> -0.87711864 | BD19: =IF(AND(ISNUMBER(BB19),ISNUMBER(BC19),BB19>0),1-BC19/BB19,"") | BH19: =IF(AND(ISNUMBER(BF19),ISNUMBER(BG19),BG19>0),BF19/BG19,"") | BM19: =IF(ISNUMBER(Q19),IF(Q19<0,"YES","no"),"") -> no | BN19: =IFERROR(IF(AND(ISNUMBER(K19),ISNUMBER(INDEX('Lift Inputs'!$H:$H,MATCH(C19,'Lift Inputs'!$C:$C,0)))),IF(K19<INDEX('Lift Inputs'!$H:$H,MATCH(C19,'Lift Inputs'!$C:$C,0)),"YES","no"),""),"")
A20: Bamboo | B20: Decolure Bamboo Sheets 4 Piece | C20: 59 | D20: Hero: rank and profit | E20: 1943 | F20: Pillcase | G20: B0H1GGHHVN | H20: B0HFZQRXXQ | I20: 100% Real Bamboo Viscose & Lyocell Tencel Sheets Set Queen Size | Breathable & C | J20: Beatable | K20: 79 | L20: 109 | M20: =IF(AND(ISNUMBER(L20),ISNUMBER(K20),K20>0),L20/K20-1,"") -> 0.37974684 | N20: =IF(M20="","No List Price",IF(M20<=0,"At/below price",IF(M20<=0.12,"<=12% (STR zone)",IF(M20<=0.25,"12-25%",">25% (likely ignored)")))) -> >25% (likely ignored) | O20: Queen | P20: 80.650959 | Q20: =IF(AND(ISNUMBER(K20),ISNUMBER(P20),N(P20)>0),K20/P20-1,"") -> -0.020470419 | R20: Same size (Queen) | S20: 28003 | T20: 35 | U20: =IF(AND(ISNUMBER(K20),ISNUMBER(T20)),K20*T20*52/12,"") -> 11981.667 | V20: 4.8 | W20: 279 | X20: 46307 | AA20: =IF(ISNUMBER(Z20),(DATE(2026,10,13)-Z20)/365,"") | AI20: 216953 | AJ20: 1218 | AN20: =IF(AND(ISNUMBER(AM20),ISNUMBER(AL20),AL20>=5),AM20/AL20,"") | AQ20: =IF(AND(ISNUMBER(AP20),ISNUMBER(AO20),AO20>=5),AP20/AO20,"") | AT20: =IF(AND(ISNUMBER(AS20),ISNUMBER(AR20),AR20>0),AS20/AR20-1,"") | BD20: =IF(AND(ISNUMBER(BB20),ISNUMBER(BC20),BB20>0),1-BC20/BB20,"") | BH20: =IF(AND(ISNUMBER(BF20),ISNUMBER(BG20),BG20>0),BF20/BG20,"") | BM20: =IF(ISNUMBER(Q20),IF(Q20<0,"YES","no"),"") -> YES | BN20: =IFERROR(IF(AND(ISNUMBER(K20),ISNUMBER(INDEX('Lift Inputs'!$H:$H,MATCH(C20,'Lift Inputs'!$C:$C,0)))),IF(K20<INDEX('Lift Inputs'!$H:$H,MATCH(C20,'Lift Inputs'!$C:$C,0)),"YES","no"),""),"")
A21: Bamboo | B21: Decolure Bamboo Sheets 4 Piece | C21: 59 | D21: Hero: rank and profit | E21: 1955 | F21: Bamboo Bay | G21: B0DLD8982V | H21: B08M9QK14J | I21: Bamboo Bay 4 Piece Queen Size Sheet Set, 100% Viscose Made from Bamboo, Breathab | J21: Beatable | K21: 89.98 | M21: =IF(AND(ISNUMBER(L21),ISNUMBER(K21),K21>0),L21/K21-1,"") | N21: =IF(M21="","No List Price",IF(M21<=0,"At/below price",IF(M21<=0.12,"<=12% (STR zone)",IF(M21<=0.25,"12-25%",">25% (likely ignored)")))) -> No List Price | O21: Queen | P21: 80.650959 | Q21: =IF(AND(ISNUMBER(K21),ISNUMBER(P21),N(P21)>0),K21/P21-1,"") -> 0.11567179 | R21: Same size (Queen) | S21: 263209 | T21: 18 | U21: =IF(AND(ISNUMBER(K21),ISNUMBER(T21)),K21*T21*52/12,"") -> 7018.44 | V21: 4.4 | W21: 739 | X21: 46307 | AA21: =IF(ISNUMBER(Z21),(DATE(2026,10,13)-Z21)/365,"") | AI21: 67928 | AJ21: 1037 | AK21: 2026-04-01 | AL21: 70.2 | AM21: 51.5 | AN21: =IF(AND(ISNUMBER(AM21),ISNUMBER(AL21),AL21>=5),AM21/AL21,"") -> 0.73361823 | AO21: 0 | AP21: 0 | AQ21: =IF(AND(ISNUMBER(AP21),ISNUMBER(AO21),AO21>=5),AP21/AO21,"") | AR21: 34.4 | AS21: 24.5 | AT21: =IF(AND(ISNUMBER(AS21),ISNUMBER(AR21),AR21>0),AS21/AR21-1,"") -> -0.2877907 | BD21: =IF(AND(ISNUMBER(BB21),ISNUMBER(BC21),BB21>0),1-BC21/BB21,"") | BH21: =IF(AND(ISNUMBER(BF21),ISNUMBER(BG21),BG21>0),BF21/BG21,"") | BM21: =IF(ISNUMBER(Q21),IF(Q21<0,"YES","no"),"") -> no | BN21: =IFERROR(IF(AND(ISNUMBER(K21),ISNUMBER(INDEX('Lift Inputs'!$H:$H,MATCH(C21,'Lift Inputs'!$C:$C,0)))),IF(K21<INDEX('Lift Inputs'!$H:$H,MATCH(C21,'Lift Inputs'!$C:$C,0)),"YES","no"),""),"")
A22: Bamboo | B22: Decolure Bamboo Sheets 4 Piece | C22: 59 | D22: Hero: rank and profit | E22: 1950 | F22: California Design Den | G22: B0HFBJPD56 | H22: B0GWHPJ9SD | I22: California Design Den 100% Viscose from Bamboo Sheets Queen, Dark Olive | J22: Beatable | K22: 89.99 | M22: =IF(AND(ISNUMBER(L22),ISNUMBER(K22),K22>0),L22/K22-1,"") | N22: =IF(M22="","No List Price",IF(M22<=0,"At/below price",IF(M22<=0.12,"<=12% (STR zone)",IF(M22<=0.25,"12-25%",">25% (likely ignored)")))) -> No List Price | O22: Queen | P22: 80.650959 | Q22: =IF(AND(ISNUMBER(K22),ISNUMBER(P22),N(P22)>0),K22/P22-1,"") -> 0.11579578 | R22: Same size (Queen) | S22: 21237 | T22: 18 | U22: =IF(AND(ISNUMBER(K22),ISNUMBER(T22)),K22*T22*52/12,"") -> 7019.22 | V22: 4.6 | W22: 76 | X22: 46307 | AA22: =IF(ISNUMBER(Z22),(DATE(2026,10,13)-Z22)/365,"") | AI22: 103642 | AJ22: 2019 | AK22: 2026-04-01 | AL22: 0 | AM22: 0 | AN22: =IF(AND(ISNUMBER(AM22),ISNUMBER(AL22),AL22>=5),AM22/AL22,"") | AO22: 0 | AP22: 0 | AQ22: =IF(AND(ISNUMBER(AP22),ISNUMBER(AO22),AO22>=5),AP22/AO22,"") | AR22: 0 | AS22: 29.8 | AT22: =IF(AND(ISNUMBER(AS22),ISNUMBER(AR22),AR22>0),AS22/AR22-1,"") | BD22: =IF(AND(ISNUMBER(BB22),ISNUMBER(BC22),BB22>0),1-BC22/BB22,"") | BH22: =IF(AND(ISNUMBER(BF22),ISNUMBER(BG22),BG22>0),BF22/BG22,"") | BM22: =IF(ISNUMBER(Q22),IF(Q22<0,"YES","no"),"") -> no | BN22: =IFERROR(IF(AND(ISNUMBER(K22),ISNUMBER(INDEX('Lift Inputs'!$H:$H,MATCH(C22,'Lift Inputs'!$C:$C,0)))),IF(K22<INDEX('Lift Inputs'!$H:$H,MATCH(C22,'Lift Inputs'!$C:$C,0)),"YES","no"),""),"")
A23: Bamboo | B23: Decolure Bamboo Sheets 4 Piece | C23: 59 | D23: Hero: rank and profit | E23: 1948 | F23: Pillcase | G23: B0HK71WHZW | H23: B0H1BWY4MD | I23: 100% Real Bamboo Viscose & Lyocell Tencel Sheets Set Queen Size | Breathable & C | J23: Beatable | K23: 99 | M23: =IF(AND(ISNUMBER(L23),ISNUMBER(K23),K23>0),L23/K23-1,"") | N23: =IF(M23="","No List Price",IF(M23<=0,"At/below price",IF(M23<=0.12,"<=12% (STR zone)",IF(M23<=0.25,"12-25%",">25% (likely ignored)")))) -> No List Price | O23: Queen | P23: 80.650959 | Q23: =IF(AND(ISNUMBER(K23),ISNUMBER(P23),N(P23)>0),K23/P23-1,"") -> 0.22751175 | R23: Same size (Queen) | S23: 38116 | T23: 18 | U23: =IF(AND(ISNUMBER(K23),ISNUMBER(T23)),K23*T23*52/12,"") -> 7722 | V23: 4.9 | W23: 201 | X23: 46307 | AA23: =IF(ISNUMBER(Z23),(DATE(2026,10,13)-Z23)/365,"") | AI23: 116001 | AJ23: 1002 | AK23: 2026-04-01 | AL23: 0 | AM23: 0 | AN23: =IF(AND(ISNUMBER(AM23),ISNUMBER(AL23),AL23>=5),AM23/AL23,"") | AO23: 0 | AP23: 0 | AQ23: =IF(AND(ISNUMBER(AP23),ISNUMBER(AO23),AO23>=5),AP23/AO23,"") | AR23: 0 | AS23: 21.5 | AT23: =IF(AND(ISNUMBER(AS23),ISNUMBER(AR23),AR23>0),AS23/AR23-1,"") | BD23: =IF(AND(ISNUMBER(BB23),ISNUMBER(BC23),BB23>0),1-BC23/BB23,"") | BH23: =IF(AND(ISNUMBER(BF23),ISNUMBER(BG23),BG23>0),BF23/BG23,"") | BM23: =IF(ISNUMBER(Q23),IF(Q23<0,"YES","no"),"") -> no | BN23: =IFERROR(IF(AND(ISNUMBER(K23),ISNUMBER(INDEX('Lift Inputs'!$H:$H,MATCH(C23,'Lift Inputs'!$C:$C,0)))),IF(K23<INDEX('Lift Inputs'!$H:$H,MATCH(C23,'Lift Inputs'!$C:$C,0)),"YES","no"),""),"")
A24: Bamboo | B24: Decolure Bamboo Sheets 4 Piece | C24: 59 | D24: Hero: rank and profit | E24: 1944 | F24: TWK | G24: B0HHQG3RSW | H24: B0G1N8QS55 | I24: TWK Real 100% Viscose Derived from Bamboo Sheets Set Queen Size, Cooling & Silky | J24: Beatable | K24: 65 | L24: 79 | M24: =IF(AND(ISNUMBER(L24),ISNUMBER(K24),K24>0),L24/K24-1,"") -> 0.21538462 | N24: =IF(M24="","No List Price",IF(M24<=0,"At/below price",IF(M24<=0.12,"<=12% (STR zone)",IF(M24<=0.25,"12-25%",">25% (likely ignored)")))) -> 12-25% | O24: Queen | P24: 80.650959 | Q24: =IF(AND(ISNUMBER(K24),ISNUMBER(P24),N(P24)>0),K24/P24-1,"") -> -0.19405794 | R24: Same size (Queen) | S24: 196488 | T24: 18 | U24: =IF(AND(ISNUMBER(K24),ISNUMBER(T24)),K24*T24*52/12,"") -> 5070 | V24: 4.9 | W24: 121 | X24: 46307 | AA24: =IF(ISNUMBER(Z24),(DATE(2026,10,13)-Z24)/365,"") | AI24: 82471 | AJ24: 905 | AK24: 2026-04-01 | AL24: 2.2 | AM24: 2 | AN24: =IF(AND(ISNUMBER(AM24),ISNUMBER(AL24),AL24>=5),AM24/AL24,"") | AO24: 0 | AP24: 0 | AQ24: =IF(AND(ISNUMBER(AP24),ISNUMBER(AO24),AO24>=5),AP24/AO24,"") | AR24: 2 | AS24: 93.2 | AT24: =IF(AND(ISNUMBER(AS24),ISNUMBER(AR24),AR24>0),AS24/AR24-1,"") -> 45.6 | BD24: =IF(AND(ISNUMBER(BB24),ISNUMBER(BC24),BB24>0),1-BC24/BB24,"") | BH24: =IF(AND(ISNUMBER(BF24),ISNUMBER(BG24),BG24>0),BF24/BG24,"") | BM24: =IF(ISNUMBER(Q24),IF(Q24<0,"YES","no"),"") -> YES | BN24: =IFERROR(IF(AND(ISNUMBER(K24),ISNUMBER(INDEX('Lift Inputs'!$H:$H,MATCH(C24,'Lift Inputs'!$C:$C,0)))),IF(K24<INDEX('Lift Inputs'!$H:$H,MATCH(C24,'Lift Inputs'!$C:$C,0)),"YES","no"),""),"")
A25: Bamboo | B25: Decolure Bamboo Sheets 4 Piece | C25: 59 | D25: Hero: rank and profit | E25: 29 | F25: BAMPURE | G25: B0FH2WGKJV | H25: B07XC2KVM7 | I25: Bamboo Sheets | J25: Beatable | K25: 37.99 | M25: =IF(AND(ISNUMBER(L25),ISNUMBER(K25),K25>0),L25/K25-1,"") | N25: =IF(M25="","No List Price",IF(M25<=0,"At/below price",IF(M25<=0.12,"<=12% (STR zone)",IF(M25<=0.25,"12-25%",">25% (likely ignored)")))) -> No List Price | P25: 80.650959 | Q25: =IF(AND(ISNUMBER(K25),ISNUMBER(P25),N(P25)>0),K25/P25-1,"") -> -0.52895786 | R25: Size unknown - vs our Queen | S25: 2541068 | T25: 5 | U25: =IF(AND(ISNUMBER(K25),ISNUMBER(T25)),K25*T25*52/12,"") -> 823.11667 | V25: 4.4 | W25: 30 | X25: 46307 | AA25: =IF(ISNUMBER(Z25),(DATE(2026,10,13)-Z25)/365,"") | AN25: =IF(AND(ISNUMBER(AM25),ISNUMBER(AL25),AL25>=5),AM25/AL25,"") | AQ25: =IF(AND(ISNUMBER(AP25),ISNUMBER(AO25),AO25>=5),AP25/AO25,"") | AT25: =IF(AND(ISNUMBER(AS25),ISNUMBER(AR25),AR25>0),AS25/AR25-1,"") | BD25: =IF(AND(ISNUMBER(BB25),ISNUMBER(BC25),BB25>0),1-BC25/BB25,"") | BH25: =IF(AND(ISNUMBER(BF25),ISNUMBER(BG25),BG25>0),BF25/BG25,"") | BM25: =IF(ISNUMBER(Q25),IF(Q25<0,"YES","no"),"") -> YES | BN25: =IFERROR(IF(AND(ISNUMBER(K25),ISNUMBER(INDEX('Lift Inputs'!$H:$H,MATCH(C25,'Lift Inputs'!$C:$C,0)))),IF(K25<INDEX('Lift Inputs'!$H:$H,MATCH(C25,'Lift Inputs'!$C:$C,0)),"YES","no"),""),"")
A26: Bamboo | B26: Decolure Bamboo Sheets 4 Piece | C26: 59 | D26: Hero: rank and profit | E26: 7 | F26: BC BELLA COTERIE | G26: B0GKBNZ8TC | H26: B0G674ZDTV | I26: 4 Piece Bamboo Sheet Set | J26: Beatable | K26: 129.99 | M26: =IF(AND(ISNUMBER(L26),ISNUMBER(K26),K26>0),L26/K26-1,"") | N26: =IF(M26="","No List Price",IF(M26<=0,"At/below price",IF(M26<=0.12,"<=12% (STR zone)",IF(M26<=0.25,"12-25%",">25% (likely ignored)")))) -> No List Price | P26: 80.650959 | Q26: =IF(AND(ISNUMBER(K26),ISNUMBER(P26),N(P26)>0),K26/P26-1,"") -> 0.61176013 | R26: Size unknown - vs our Queen | S26: 1577 | T26: 5 | U26: =IF(AND(ISNUMBER(K26),ISNUMBER(T26)),K26*T26*52/12,"") -> 2816.45 | V26: 4.4 | W26: 5652 | X26: 46223 | AA26: =IF(ISNUMBER(Z26),(DATE(2026,10,13)-Z26)/365,"") | AN26: =IF(AND(ISNUMBER(AM26),ISNUMBER(AL26),AL26>=5),AM26/AL26,"") | AQ26: =IF(AND(ISNUMBER(AP26),ISNUMBER(AO26),AO26>=5),AP26/AO26,"") | AT26: =IF(AND(ISNUMBER(AS26),ISNUMBER(AR26),AR26>0),AS26/AR26-1,"") | BD26: =IF(AND(ISNUMBER(BB26),ISNUMBER(BC26),BB26>0),1-BC26/BB26,"") | BH26: =IF(AND(ISNUMBER(BF26),ISNUMBER(BG26),BG26>0),BF26/BG26,"") | BM26: =IF(ISNUMBER(Q26),IF(Q26<0,"YES","no"),"") -> no | BN26: =IFERROR(IF(AND(ISNUMBER(K26),ISNUMBER(INDEX('Lift Inputs'!$H:$H,MATCH(C26,'Lift Inputs'!$C:$C,0)))),IF(K26<INDEX('Lift Inputs'!$H:$H,MATCH(C26,'Lift Inputs'!$C:$C,0)),"YES","no"),""),"")
A27: Bamboo | B27: Decolure Bamboo Sheets 4 Piece | C27: 59 | D27: Hero: rank and profit | E27: 1939 | F27: Pillcase | G27: B0HJYG8V9Q | H27: B0HJYG8V9Q | I27: Cooling Hotel Bedding Sheet Set - 4pcs Bamboo Viscose & Tencel Blend, Moisture-W | J27: Beatable | K27: 79.99 | M27: =IF(AND(ISNUMBER(L27),ISNUMBER(K27),K27>0),L27/K27-1,"") | N27: =IF(M27="","No List Price",IF(M27<=0,"At/below price",IF(M27<=0.12,"<=12% (STR zone)",IF(M27<=0.25,"12-25%",">25% (likely ignored)")))) -> No List Price | P27: 80.650959 | Q27: =IF(AND(ISNUMBER(K27),ISNUMBER(P27),N(P27)>0),K27/P27-1,"") -> -0.0081953012 | R27: Size unknown - vs our Queen | S27: 762451 | T27: 5 | U27: =IF(AND(ISNUMBER(K27),ISNUMBER(T27)),K27*T27*52/12,"") -> 1733.1167 | V27: 4 | X27: 46307 | AA27: =IF(ISNUMBER(Z27),(DATE(2026,10,13)-Z27)/365,"") | AI27: 57075 | AJ27: 90 | AN27: =IF(AND(ISNUMBER(AM27),ISNUMBER(AL27),AL27>=5),AM27/AL27,"") | AQ27: =IF(AND(ISNUMBER(AP27),ISNUMBER(AO27),AO27>=5),AP27/AO27,"") | AT27: =IF(AND(ISNUMBER(AS27),ISNUMBER(AR27),AR27>0),AS27/AR27-1,"") | BD27: =IF(AND(ISNUMBER(BB27),ISNUMBER(BC27),BB27>0),1-BC27/BB27,"") | BH27: =IF(AND(ISNUMBER(BF27),ISNUMBER(BG27),BG27>0),BF27/BG27,"") | BM27: =IF(ISNUMBER(Q27),IF(Q27<0,"YES","no"),"") -> YES | BN27: =IFERROR(IF(AND(ISNUMBER(K27),ISNUMBER(INDEX('Lift Inputs'!$H:$H,MATCH(C27,'Lift Inputs'!$C:$C,0)))),IF(K27<INDEX('Lift Inputs'!$H:$H,MATCH(C27,'Lift Inputs'!$C:$C,0)),"YES","no"),""),"")
A28: Bamboo | B28: Decolure Bamboo Sheets 4 Piece | C28: 59 | D28: Hero: rank and profit | E28: 1954 | F28: Tafts | G28: B0D34K3FB9 | H28: B07YSVNCVT | I28: Bamboo Sheets Queen Size, 100% Pure Viscose derived from Bamboo Bed Sheet Set, L | J28: Beatable | K28: 104.99 | M28: =IF(AND(ISNUMBER(L28),ISNUMBER(K28),K28>0),L28/K28-1,"") | N28: =IF(M28="","No List Price",IF(M28<=0,"At/below price",IF(M28<=0.12,"<=12% (STR zone)",IF(M28<=0.25,"12-25%",">25% (likely ignored)")))) -> No List Price | O28: Queen | P28: 80.650959 | Q28: =IF(AND(ISNUMBER(K28),ISNUMBER(P28),N(P28)>0),K28/P28-1,"") -> 0.30178241 | R28: Same size (Queen) | S28: 184749 | T28: 5 | U28: =IF(AND(ISNUMBER(K28),ISNUMBER(T28)),K28*T28*52/12,"") -> 2274.7833 | V28: 4.5 | W28: 3184 | X28: 46307 | AA28: =IF(ISNUMBER(Z28),(DATE(2026,10,13)-Z28)/365,"") | AI28: 11787 | AJ28: 302 | AN28: =IF(AND(ISNUMBER(AM28),ISNUMBER(AL28),AL28>=5),AM28/AL28,"") | AQ28: =IF(AND(ISNUMBER(AP28),ISNUMBER(AO28),AO28>=5),AP28/AO28,"") | AT28: =IF(AND(ISNUMBER(AS28),ISNUMBER(AR28),AR28>0),AS28/AR28-1,"") | BD28: =IF(AND(ISNUMBER(BB28),ISNUMBER(BC28),BB28>0),1-BC28/BB28,"") | BH28: =IF(AND(ISNUMBER(BF28),ISNUMBER(BG28),BG28>0),BF28/BG28,"") | BM28: =IF(ISNUMBER(Q28),IF(Q28<0,"YES","no"),"") -> no | BN28: =IFERROR(IF(AND(ISNUMBER(K28),ISNUMBER(INDEX('Lift Inputs'!$H:$H,MATCH(C28,'Lift Inputs'!$C:$C,0)))),IF(K28<INDEX('Lift Inputs'!$H:$H,MATCH(C28,'Lift Inputs'!$C:$C,0)),"YES","no"),""),"")
A29: Bamboo | B29: Decolure Bamboo Sheets 4 Piece | C29: 59 | D29: Hero: rank and profit | E29: 1949 | F29: TWK | G29: B0HHRR4XGX | H29: B0HHRR4XGX | I29: TWK Real 100% Viscose Derived from Bamboo Sheets Set Queen Size, Cooling & Silky | J29: Beatable | K29: 105 | M29: =IF(AND(ISNUMBER(L29),ISNUMBER(K29),K29>0),L29/K29-1,"") | N29: =IF(M29="","No List Price",IF(M29<=0,"At/below price",IF(M29<=0.12,"<=12% (STR zone)",IF(M29<=0.25,"12-25%",">25% (likely ignored)")))) -> No List Price | O29: Queen | P29: 80.650959 | Q29: =IF(AND(ISNUMBER(K29),ISNUMBER(P29),N(P29)>0),K29/P29-1,"") -> 0.30190641 | R29: Same size (Queen) | T29: 5 | U29: =IF(AND(ISNUMBER(K29),ISNUMBER(T29)),K29*T29*52/12,"") -> 2275 | V29: 4.5 | X29: 46307 | AA29: =IF(ISNUMBER(Z29),(DATE(2026,10,13)-Z29)/365,"") | AI29: 30066 | AJ29: 74 | AN29: =IF(AND(ISNUMBER(AM29),ISNUMBER(AL29),AL29>=5),AM29/AL29,"") | AQ29: =IF(AND(ISNUMBER(AP29),ISNUMBER(AO29),AO29>=5),AP29/AO29,"") | AT29: =IF(AND(ISNUMBER(AS29),ISNUMBER(AR29),AR29>0),AS29/AR29-1,"") | BD29: =IF(AND(ISNUMBER(BB29),ISNUMBER(BC29),BB29>0),1-BC29/BB29,"") | BH29: =IF(AND(ISNUMBER(BF29),ISNUMBER(BG29),BG29>0),BF29/BG29,"") | BM29: =IF(ISNUMBER(Q29),IF(Q29<0,"YES","no"),"") -> no | BN29: =IFERROR(IF(AND(ISNUMBER(K29),ISNUMBER(INDEX('Lift Inputs'!$H:$H,MATCH(C29,'Lift Inputs'!$C:$C,0)))),IF(K29<INDEX('Lift Inputs'!$H:$H,MATCH(C29,'Lift Inputs'!$C:$C,0)),"YES","no"),""),"")
A30: Bamboo | B30: Decolure Bamboo Sheets 4 Piece | C30: 59 | D30: Hero: rank and profit | E30: 1516 | F30: AiAngu | G30: B0H3KP6R9B | H30: B0GX15Y7TT | I30: Bamboo Sheets | J30: Poor | K30: 74.99 | L30: 79.99 | M30: =IF(AND(ISNUMBER(L30),ISNUMBER(K30),K30>0),L30/K30-1,"") -> 0.066675557 | N30: =IF(M30="","No List Price",IF(M30<=0,"At/below price",IF(M30<=0.12,"<=12% (STR zone)",IF(M30<=0.25,"12-25%",">25% (likely ignored)")))) -> <=12% (STR zone) | P30: 80.650959 | Q30: =IF(AND(ISNUMBER(K30),ISNUMBER(P30),N(P30)>0),K30/P30-1,"") -> -0.070190844 | R30: Size unknown - vs our Queen | S30: 39296 | T30: 81 | U30: =IF(AND(ISNUMBER(K30),ISNUMBER(T30)),K30*T30*52/12,"") -> 26321.49 | V30: 4.6 | W30: 121 | X30: 46307 | AA30: =IF(ISNUMBER(Z30),(DATE(2026,10,13)-Z30)/365,"") | AN30: =IF(AND(ISNUMBER(AM30),ISNUMBER(AL30),AL30>=5),AM30/AL30,"") | AQ30: =IF(AND(ISNUMBER(AP30),ISNUMBER(AO30),AO30>=5),AP30/AO30,"") | AT30: =IF(AND(ISNUMBER(AS30),ISNUMBER(AR30),AR30>0),AS30/AR30-1,"") | BD30: =IF(AND(ISNUMBER(BB30),ISNUMBER(BC30),BB30>0),1-BC30/BB30,"") | BH30: =IF(AND(ISNUMBER(BF30),ISNUMBER(BG30),BG30>0),BF30/BG30,"") | BM30: =IF(ISNUMBER(Q30),IF(Q30<0,"YES","no"),"") -> YES | BN30: =IFERROR(IF(AND(ISNUMBER(K30),ISNUMBER(INDEX('Lift Inputs'!$H:$H,MATCH(C30,'Lift Inputs'!$C:$C,0)))),IF(K30<INDEX('Lift Inputs'!$H:$H,MATCH(C30,'Lift Inputs'!$C:$C,0)),"YES","no"),""),"")
A31: Bamboo | B31: Decolure Bamboo Sheets 4 Piece | C31: 59 | D31: Hero: rank and profit | E31: 1519 | F31: Cariloha | G31: B0F89K7BXJ | H31: B0DJV1K332 | I31: Cariloha Aloha Soft Bamboo Viscose Sheet Set - Natural - Queen | J31: Poor | K31: 107.1 | M31: =IF(AND(ISNUMBER(L31),ISNUMBER(K31),K31>0),L31/K31-1,"") | N31: =IF(M31="","No List Price",IF(M31<=0,"At/below price",IF(M31<=0.12,"<=12% (STR zone)",IF(M31<=0.25,"12-25%",">25% (likely ignored)")))) -> No List Price | O31: Queen | P31: 80.650959 | Q31: =IF(AND(ISNUMBER(K31),ISNUMBER(P31),N(P31)>0),K31/P31-1,"") -> 0.32794453 | R31: Same size (Queen) | S31: 15882 | T31: 81 | U31: =IF(AND(ISNUMBER(K31),ISNUMBER(T31)),K31*T31*52/12,"") -> 37592.1 | V31: 4.4 | W31: 426 | X31: 46307 | Y31: 35 | Z31: 45575 | AA31: =IF(ISNUMBER(Z31),(DATE(2026,10,13)-Z31)/365,"") -> 2.0082192 | AB31: 2442 | AC31: FBA | AD31: 1 | AE31: US | AF31: 0 | AG31: 0 | AH31: 231 | AN31: =IF(AND(ISNUMBER(AM31),ISNUMBER(AL31),AL31>=5),AM31/AL31,"") | AQ31: =IF(AND(ISNUMBER(AP31),ISNUMBER(AO31),AO31>=5),AP31/AO31,"") | AT31: =IF(AND(ISNUMBER(AS31),ISNUMBER(AR31),AR31>0),AS31/AR31-1,"") | BD31: =IF(AND(ISNUMBER(BB31),ISNUMBER(BC31),BB31>0),1-BC31/BB31,"") | BH31: =IF(AND(ISNUMBER(BF31),ISNUMBER(BG31),BG31>0),BF31/BG31,"") | BM31: =IF(ISNUMBER(Q31),IF(Q31<0,"YES","no"),"") -> no | BN31: =IFERROR(IF(AND(ISNUMBER(K31),ISNUMBER(INDEX('Lift Inputs'!$H:$H,MATCH(C31,'Lift Inputs'!$C:$C,0)))),IF(K31<INDEX('Lift Inputs'!$H:$H,MATCH(C31,'Lift Inputs'!$C:$C,0)),"YES","no"),""),"")
A32: Bamboo | B32: Decolure Bamboo Sheets 4 Piece | C32: 59 | D32: Hero: rank and profit | E32: 1508 | F32: ACCURATEX | G32: B0GMGSMLQ1 | H32: B09PYB9C45 | I32: ACCURATEX Cooling Sheets for Hot Sleepers, King Size, Grey | J32: Poor | K32: 69.99 | M32: =IF(AND(ISNUMBER(L32),ISNUMBER(K32),K32>0),L32/K32-1,"") | N32: =IF(M32="","No List Price",IF(M32<=0,"At/below price",IF(M32<=0.12,"<=12% (STR zone)",IF(M32<=0.25,"12-25%",">25% (likely ignored)")))) -> No List Price | O32: King | P32: 84.316772 | Q32: =IF(AND(ISNUMBER(K32),ISNUMBER(P32),N(P32)>0),K32/P32-1,"") -> -0.16991604 | R32: Same size (King) | S32: 33423 | T32: 35 | U32: =IF(AND(ISNUMBER(K32),ISNUMBER(T32)),K32*T32*52/12,"") -> 10615.15 | V32: 4.4 | W32: 1040 | X32: 46307 | Y32: 51 | Z32: 44681 | AA32: =IF(ISNUMBER(Z32),(DATE(2026,10,13)-Z32)/365,"") -> 4.4575342 | AB32: 1349 | AC32: FBA | AD32: 1 | AE32: CN | AF32: 0 | AG32: 0 | AH32: 152 | AN32: =IF(AND(ISNUMBER(AM32),ISNUMBER(AL32),AL32>=5),AM32/AL32,"") | AQ32: =IF(AND(ISNUMBER(AP32),ISNUMBER(AO32),AO32>=5),AP32/AO32,"") | AT32: =IF(AND(ISNUMBER(AS32),ISNUMBER(AR32),AR32>0),AS32/AR32-1,"") | BD32: =IF(AND(ISNUMBER(BB32),ISNUMBER(BC32),BB32>0),1-BC32/BB32,"") | BH32: =IF(AND(ISNUMBER(BF32),ISNUMBER(BG32),BG32>0),BF32/BG32,"") | BM32: =IF(ISNUMBER(Q32),IF(Q32<0,"YES","no"),"") -> YES | BN32: =IFERROR(IF(AND(ISNUMBER(K32),ISNUMBER(INDEX('Lift Inputs'!$H:$H,MATCH(C32,'Lift Inputs'!$C:$C,0)))),IF(K32<INDEX('Lift Inputs'!$H:$H,MATCH(C32,'Lift Inputs'!$C:$C,0)),"YES","no"),""),"")
A33: Bamboo | B33: Decolure Bamboo Sheets 4 Piece | C33: 59 | D33: Hero: rank and profit | E33: 31 | F33: Cozy Earth | G33: B0DSQ9V4ML | H33: B0F22JR4S8 | I33: Cozy Earth Luxury Bed Sheet Set, 100% Viscose from Bamboo Fabric | J33: Poor | K33: 328 | M33: =IF(AND(ISNUMBER(L33),ISNUMBER(K33),K33>0),L33/K33-1,"") | N33: =IF(M33="","No List Price",IF(M33<=0,"At/below price",IF(M33<=0.12,"<=12% (STR zone)",IF(M33<=0.25,"12-25%",">25% (likely ignored)")))) -> No List Price | P33: 80.650959 | Q33: =IF(AND(ISNUMBER(K33),ISNUMBER(P33),N(P33)>0),K33/P33-1,"") -> 3.0669076 | R33: Size unknown - vs our Queen | S33: 45709 | T33: 35 | U33: =IF(AND(ISNUMBER(K33),ISNUMBER(T33)),K33*T33*52/12,"") -> 49746.667 | V33: 3.9 | W33: 425 | X33: 46307 | Y33: 54 | Z33: 41624 | AA33: =IF(ISNUMBER(Z33),(DATE(2026,10,13)-Z33)/365,"") -> 12.832877 | AB33: 875 | AC33: FBA | AD33: 2 | AE33: US | AF33: 0 | AG33: 0 | AH33: 93 | AN33: =IF(AND(ISNUMBER(AM33),ISNUMBER(AL33),AL33>=5),AM33/AL33,"") | AQ33: =IF(AND(ISNUMBER(AP33),ISNUMBER(AO33),AO33>=5),AP33/AO33,"") | AT33: =IF(AND(ISNUMBER(AS33),ISNUMBER(AR33),AR33>0),AS33/AR33-1,"") | BD33: =IF(AND(ISNUMBER(BB33),ISNUMBER(BC33),BB33>0),1-BC33/BB33,"") | BH33: =IF(AND(ISNUMBER(BF33),ISNUMBER(BG33),BG33>0),BF33/BG33,"") | BM33: =IF(ISNUMBER(Q33),IF(Q33<0,"YES","no"),"") -> no | BN33: =IFERROR(IF(AND(ISNUMBER(K33),ISNUMBER(INDEX('Lift Inputs'!$H:$H,MATCH(C33,'Lift Inputs'!$C:$C,0)))),IF(K33<INDEX('Lift Inputs'!$H:$H,MATCH(C33,'Lift Inputs'!$C:$C,0)),"YES","no"),""),"")
A34: Bamboo | B34: Decolure Bamboo Sheets 4 Piece | C34: 59 | D34: Hero: rank and profit | E34: 1515 | F34: DREAMCARE | G34: B0DVZFLVMG | H34: B0CF2MND41 | I34: DREAMCARE 100% Rayon Bamboo Sheets King Size - 4pc Cooling Sheets King Size | J34: Poor | K34: 46.74 | L34: 59.99 | M34: =IF(AND(ISNUMBER(L34),ISNUMBER(K34),K34>0),L34/K34-1,"") -> 0.2834831 | N34: =IF(M34="","No List Price",IF(M34<=0,"At/below price",IF(M34<=0.12,"<=12% (STR zone)",IF(M34<=0.25,"12-25%",">25% (likely ignored)")))) -> >25% (likely ignored) | O34: King | P34: 84.316772 | Q34: =IF(AND(ISNUMBER(K34),ISNUMBER(P34),N(P34)>0),K34/P34-1,"") -> -0.44566189 | R34: Same size (King) | S34: 37217 | T34: 35 | U34: =IF(AND(ISNUMBER(K34),ISNUMBER(T34)),K34*T34*52/12,"") -> 7088.9 | V34: 4.5 | W34: 2261 | X34: 46307 | Y34: 30 | Z34: 45146 | AA34: =IF(ISNUMBER(Z34),(DATE(2026,10,13)-Z34)/365,"") -> 3.1835616 | AB34: 1260 | AC34: FBA | AD34: 2 | AE34: US | AF34: 0 | AG34: 0 | AH34: 222 | AN34: =IF(AND(ISNUMBER(AM34),ISNUMBER(AL34),AL34>=5),AM34/AL34,"") | AQ34: =IF(AND(ISNUMBER(AP34),ISNUMBER(AO34),AO34>=5),AP34/AO34,"") | AT34: =IF(AND(ISNUMBER(AS34),ISNUMBER(AR34),AR34>0),AS34/AR34-1,"") | BD34: =IF(AND(ISNUMBER(BB34),ISNUMBER(BC34),BB34>0),1-BC34/BB34,"") | BH34: =IF(AND(ISNUMBER(BF34),ISNUMBER(BG34),BG34>0),BF34/BG34,"") | BM34: =IF(ISNUMBER(Q34),IF(Q34<0,"YES","no"),"") -> YES | BN34: =IFERROR(IF(AND(ISNUMBER(K34),ISNUMBER(INDEX('Lift Inputs'!$H:$H,MATCH(C34,'Lift Inputs'!$C:$C,0)))),IF(K34<INDEX('Lift Inputs'!$H:$H,MATCH(C34,'Lift Inputs'!$C:$C,0)),"YES","no"),""),"")
A35: Bamboo | B35: Decolure Bamboo Sheets 4 Piece | C35: 59 | D35: Hero: rank and profit | E35: 32 | F35: HOT SLEEPER SHEETS | G35: B0DM3GDCTR | H35: B0D3XQM7DL | I35: Cooling Sheets Set Queen Size, Viscose Derived from Bamboo for Hot Sleepers | De | J35: Poor | K35: 51.29 | L35: 62.99 | M35: =IF(AND(ISNUMBER(L35),ISNUMBER(K35),K35>0),L35/K35-1,"") -> 0.22811464 | N35: =IF(M35="","No List Price",IF(M35<=0,"At/below price",IF(M35<=0.12,"<=12% (STR zone)",IF(M35<=0.25,"12-25%",">25% (likely ignored)")))) -> 12-25% | O35: Queen | P35: 80.650959 | Q35: =IF(AND(ISNUMBER(K35),ISNUMBER(P35),N(P35)>0),K35/P35-1,"") -> -0.36404972 | R35: Same size (Queen) | S35: 33959 | T35: 35 | U35: =IF(AND(ISNUMBER(K35),ISNUMBER(T35)),K35*T35*52/12,"") -> 7778.9833 | V35: 4.4 | W35: 674 | X35: 46307 | Y35: 74 | Z35: 45423 | AA35: =IF(ISNUMBER(Z35),(DATE(2026,10,13)-Z35)/365,"") -> 2.4246575 | AB35: 2428 | AC35: FBA | AD35: 1 | AE35: CN | AF35: 0 | AG35: 0 | AH35: 151 | AN35: =IF(AND(ISNUMBER(AM35),ISNUMBER(AL35),AL35>=5),AM35/AL35,"") | AQ35: =IF(AND(ISNUMBER(AP35),ISNUMBER(AO35),AO35>=5),AP35/AO35,"") | AT35: =IF(AND(ISNUMBER(AS35),ISNUMBER(AR35),AR35>0),AS35/AR35-1,"") | BD35: =IF(AND(ISNUMBER(BB35),ISNUMBER(BC35),BB35>0),1-BC35/BB35,"") | BH35: =IF(AND(ISNUMBER(BF35),ISNUMBER(BG35),BG35>0),BF35/BG35,"") | BM35: =IF(ISNUMBER(Q35),IF(Q35<0,"YES","no"),"") -> YES | BN35: =IFERROR(IF(AND(ISNUMBER(K35),ISNUMBER(INDEX('Lift Inputs'!$H:$H,MATCH(C35,'Lift Inputs'!$C:$C,0)))),IF(K35<INDEX('Lift Inputs'!$H:$H,MATCH(C35,'Lift Inputs'!$C:$C,0)),"YES","no"),""),"")
A36: Bamboo | B36: Decolure Bamboo Sheets 4 Piece | C36: 59 | D36: Hero: rank and profit | E36: 1522 | F36: Shilucheng | G36: B09PYKYCCF | H36: B09PYKYCCF | I36: Shilucheng 100% Viscose Derived from Bamboo_ Sheets Queen Size 4pcs | J36: Poor | K36: 46.66 | L36: 54.9 | M36: =IF(AND(ISNUMBER(L36),ISNUMBER(K36),K36>0),L36/K36-1,"") -> 0.17659666 | N36: =IF(M36="","No List Price",IF(M36<=0,"At/below price",IF(M36<=0.12,"<=12% (STR zone)",IF(M36<=0.25,"12-25%",">25% (likely ignored)")))) -> 12-25% | O36: Queen | P36: 80.650959 | Q36: =IF(AND(ISNUMBER(K36),ISNUMBER(P36),N(P36)>0),K36/P36-1,"") -> -0.42145759 | R36: Same size (Queen) | S36: 26043 | T36: 35 | U36: =IF(AND(ISNUMBER(K36),ISNUMBER(T36)),K36*T36*52/12,"") -> 7076.7667 | V36: 4.4 | W36: 6629 | X36: 46307 | Y36: 79 | Z36: 44652 | AA36: =IF(ISNUMBER(Z36),(DATE(2026,10,13)-Z36)/365,"") -> 4.5369863 | AB36: 1557 | AC36: FBA | AD36: 1 | AE36: CN | AF36: 0 | AG36: 0 | AH36: 167 | AK36: 2026-04-01 | AL36: 0 | AM36: 0 | AN36: =IF(AND(ISNUMBER(AM36),ISNUMBER(AL36),AL36>=5),AM36/AL36,"") | AO36: 0 | AP36: 0 | AQ36: =IF(AND(ISNUMBER(AP36),ISNUMBER(AO36),AO36>=5),AP36/AO36,"") | AR36: 13.3 | AS36: 0.3 | AT36: =IF(AND(ISNUMBER(AS36),ISNUMBER(AR36),AR36>0),AS36/AR36-1,"") -> -0.97744361 | BD36: =IF(AND(ISNUMBER(BB36),ISNUMBER(BC36),BB36>0),1-BC36/BB36,"") | BH36: =IF(AND(ISNUMBER(BF36),ISNUMBER(BG36),BG36>0),BF36/BG36,"") | BM36: =IF(ISNUMBER(Q36),IF(Q36<0,"YES","no"),"") -> YES | BN36: =IFERROR(IF(AND(ISNUMBER(K36),ISNUMBER(INDEX('Lift Inputs'!$H:$H,MATCH(C36,'Lift Inputs'!$C:$C,0)))),IF(K36<INDEX('Lift Inputs'!$H:$H,MATCH(C36,'Lift Inputs'!$C:$C,0)),"YES","no"),""),"")
A37: Bamboo | B37: Decolure Bamboo Sheets 4 Piece | C37: 59 | D37: Hero: rank and profit | E37: 30 | F37: Bamtek | G37: B0CZHCZQZ3 | H37: B09TQ6ZVKZ | I37: Viscose Bamboo Sheets Queen Size 4PC Set - Cooling Bedding for Hot Sleepers with | J37: Poor | K37: 94.99 | M37: =IF(AND(ISNUMBER(L37),ISNUMBER(K37),K37>0),L37/K37-1,"") | N37: =IF(M37="","No List Price",IF(M37<=0,"At/below price",IF(M37<=0.12,"<=12% (STR zone)",IF(M37<=0.25,"12-25%",">25% (likely ignored)")))) -> No List Price | O37: Queen | P37: 80.650959 | Q37: =IF(AND(ISNUMBER(K37),ISNUMBER(P37),N(P37)>0),K37/P37-1,"") -> 0.17779133 | R37: Same size (Queen) | S37: 79376 | T37: 18 | U37: =IF(AND(ISNUMBER(K37),ISNUMBER(T37)),K37*T37*52/12,"") -> 7409.22 | V37: 4.4 | W37: 641 | X37: 46307 | AA37: =IF(ISNUMBER(Z37),(DATE(2026,10,13)-Z37)/365,"") | AN37: =IF(AND(ISNUMBER(AM37),ISNUMBER(AL37),AL37>=5),AM37/AL37,"") | AQ37: =IF(AND(ISNUMBER(AP37),ISNUMBER(AO37),AO37>=5),AP37/AO37,"") | AT37: =IF(AND(ISNUMBER(AS37),ISNUMBER(AR37),AR37>0),AS37/AR37-1,"") | BD37: =IF(AND(ISNUMBER(BB37),ISNUMBER(BC37),BB37>0),1-BC37/BB37,"") | BH37: =IF(AND(ISNUMBER(BF37),ISNUMBER(BG37),BG37>0),BF37/BG37,"") | BM37: =IF(ISNUMBER(Q37),IF(Q37<0,"YES","no"),"") -> no | BN37: =IFERROR(IF(AND(ISNUMBER(K37),ISNUMBER(INDEX('Lift Inputs'!$H:$H,MATCH(C37,'Lift Inputs'!$C:$C,0)))),IF(K37<INDEX('Lift Inputs'!$H:$H,MATCH(C37,'Lift Inputs'!$C:$C,0)),"YES","no"),""),"")
A38: Bamboo | B38: Decolure Bamboo Sheets 4 Piece | C38: 59 | D38: Hero: rank and profit | E38: 28 | F38: JSD | G38: B0DTY15N29 | H38: B0DSZTLBV1 | I38: JSD Sage Green 100% Viscose Derived from Bamboo Cooling Sheet Set Queen | J38: Poor | K38: 56.99 | M38: =IF(AND(ISNUMBER(L38),ISNUMBER(K38),K38>0),L38/K38-1,"") | N38: =IF(M38="","No List Price",IF(M38<=0,"At/below price",IF(M38<=0.12,"<=12% (STR zone)",IF(M38<=0.25,"12-25%",">25% (likely ignored)")))) -> No List Price | O38: Queen | P38: 80.650959 | Q38: =IF(AND(ISNUMBER(K38),ISNUMBER(P38),N(P38)>0),K38/P38-1,"") -> -0.2933748 | R38: Same size (Queen) | S38: 76312 | T38: 18 | U38: =IF(AND(ISNUMBER(K38),ISNUMBER(T38)),K38*T38*52/12,"") -> 4445.22 | V38: 4.3 | W38: 281 | X38: 46307 | Y38: 32 | Z38: 45671 | AA38: =IF(ISNUMBER(Z38),(DATE(2026,10,13)-Z38)/365,"") -> 1.7452055 | AB38: 1508 | AC38: FBA | AD38: 1 | AE38: CN | AF38: 0 | AG38: 0 | AH38: 126 | AN38: =IF(AND(ISNUMBER(AM38),ISNUMBER(AL38),AL38>=5),AM38/AL38,"") | AQ38: =IF(AND(ISNUMBER(AP38),ISNUMBER(AO38),AO38>=5),AP38/AO38,"") | AT38: =IF(AND(ISNUMBER(AS38),ISNUMBER(AR38),AR38>0),AS38/AR38-1,"") | BD38: =IF(AND(ISNUMBER(BB38),ISNUMBER(BC38),BB38>0),1-BC38/BB38,"") | BH38: =IF(AND(ISNUMBER(BF38),ISNUMBER(BG38),BG38>0),BF38/BG38,"") | BM38: =IF(ISNUMBER(Q38),IF(Q38<0,"YES","no"),"") -> YES | BN38: =IFERROR(IF(AND(ISNUMBER(K38),ISNUMBER(INDEX('Lift Inputs'!$H:$H,MATCH(C38,'Lift Inputs'!$C:$C,0)))),IF(K38<INDEX('Lift Inputs'!$H:$H,MATCH(C38,'Lift Inputs'!$C:$C,0)),"YES","no"),""),"")
A39: Bamboo | B39: Decolure Bamboo Sheets 4 Piece | C39: 59 | D39: Hero: rank and profit | E39: 24 | F39: Kickoff Home | G39: B0D4KS4MVX | H39: B0CHN5ZPFH | I39: Bamboo Sheets | J39: Poor | K39: 76.99 | L39: 84.99 | M39: =IF(AND(ISNUMBER(L39),ISNUMBER(K39),K39>0),L39/K39-1,"") -> 0.1039096 | N39: =IF(M39="","No List Price",IF(M39<=0,"At/below price",IF(M39<=0.12,"<=12% (STR zone)",IF(M39<=0.25,"12-25%",">25% (likely ignored)")))) -> <=12% (STR zone) | P39: 80.650959 | Q39: =IF(AND(ISNUMBER(K39),ISNUMBER(P39),N(P39)>0),K39/P39-1,"") -> -0.045392627 | R39: Size unknown - vs our Queen | S39: 23579 | T39: 18 | U39: =IF(AND(ISNUMBER(K39),ISNUMBER(T39)),K39*T39*52/12,"") -> 6005.22 | V39: 4.6 | W39: 688 | X39: 46307 | AA39: =IF(ISNUMBER(Z39),(DATE(2026,10,13)-Z39)/365,"") | AI39: 58169 | AJ39: 1164 | AK39: 2026-04-01 | AL39: 1.3 | AM39: 2.2 | AN39: =IF(AND(ISNUMBER(AM39),ISNUMBER(AL39),AL39>=5),AM39/AL39,"") | AO39: 3.5 | AP39: 2.5 | AQ39: =IF(AND(ISNUMBER(AP39),ISNUMBER(AO39),AO39>=5),AP39/AO39,"") | AR39: 1.7 | AS39: 5.7 | AT39: =IF(AND(ISNUMBER(AS39),ISNUMBER(AR39),AR39>0),AS39/AR39-1,"") -> 2.3529412 | BD39: =IF(AND(ISNUMBER(BB39),ISNUMBER(BC39),BB39>0),1-BC39/BB39,"") | BH39: =IF(AND(ISNUMBER(BF39),ISNUMBER(BG39),BG39>0),BF39/BG39,"") | BM39: =IF(ISNUMBER(Q39),IF(Q39<0,"YES","no"),"") -> YES | BN39: =IFERROR(IF(AND(ISNUMBER(K39),ISNUMBER(INDEX('Lift Inputs'!$H:$H,MATCH(C39,'Lift Inputs'!$C:$C,0)))),IF(K39<INDEX('Lift Inputs'!$H:$H,MATCH(C39,'Lift Inputs'!$C:$C,0)),"YES","no"),""),"")
A40: Bamboo | B40: Decolure Bamboo Sheets 4 Piece | C40: 59 | D40: Hero: rank and profit | E40: 26 | F40: LB Luxury Bamboo Market | G40: B0D1HWHDL2 | H40: B0CH7N9WVC | I40: Bamboo Sheets | J40: Poor | K40: 129.94 | M40: =IF(AND(ISNUMBER(L40),ISNUMBER(K40),K40>0),L40/K40-1,"") | N40: =IF(M40="","No List Price",IF(M40<=0,"At/below price",IF(M40<=0.12,"<=12% (STR zone)",IF(M40<=0.25,"12-25%",">25% (likely ignored)")))) -> No List Price | P40: 80.650959 | Q40: =IF(AND(ISNUMBER(K40),ISNUMBER(P40),N(P40)>0),K40/P40-1,"") -> 0.61114017 | R40: Size unknown - vs our Queen | S40: 47800 | T40: 18 | U40: =IF(AND(ISNUMBER(K40),ISNUMBER(T40)),K40*T40*52/12,"") -> 10135.32 | V40: 4.5 | W40: 517 | X40: 46307 | AA40: =IF(ISNUMBER(Z40),(DATE(2026,10,13)-Z40)/365,"") | AN40: =IF(AND(ISNUMBER(AM40),ISNUMBER(AL40),AL40>=5),AM40/AL40,"") | AQ40: =IF(AND(ISNUMBER(AP40),ISNUMBER(AO40),AO40>=5),AP40/AO40,"") | AT40: =IF(AND(ISNUMBER(AS40),ISNUMBER(AR40),AR40>0),AS40/AR40-1,"") | BD40: =IF(AND(ISNUMBER(BB40),ISNUMBER(BC40),BB40>0),1-BC40/BB40,"") | BH40: =IF(AND(ISNUMBER(BF40),ISNUMBER(BG40),BG40>0),BF40/BG40,"") | BM40: =IF(ISNUMBER(Q40),IF(Q40<0,"YES","no"),"") -> no | BN40: =IFERROR(IF(AND(ISNUMBER(K40),ISNUMBER(INDEX('Lift Inputs'!$H:$H,MATCH(C40,'Lift Inputs'!$C:$C,0)))),IF(K40<INDEX('Lift Inputs'!$H:$H,MATCH(C40,'Lift Inputs'!$C:$C,0)),"YES","no"),""),"")
A41: Bamboo | B41: Decolure Bamboo Sheets 4 Piece | C41: 59 | D41: Hero: rank and profit | E41: 633 | F41: Shilucheng | G41: B0F2TBWTZR | H41: B0F2TBWTZR | I41: Shilucheng 100% Viscose Derived from Bamboo_Sheets, Extra Deep Pocket | J41: Poor | K41: 69.99 | L41: 84.99 | M41: =IF(AND(ISNUMBER(L41),ISNUMBER(K41),K41>0),L41/K41-1,"") -> 0.21431633 | N41: =IF(M41="","No List Price",IF(M41<=0,"At/below price",IF(M41<=0.12,"<=12% (STR zone)",IF(M41<=0.25,"12-25%",">25% (likely ignored)")))) -> 12-25% | P41: 80.650959 | Q41: =IF(AND(ISNUMBER(K41),ISNUMBER(P41),N(P41)>0),K41/P41-1,"") -> -0.13218639 | R41: Size unknown - vs our Queen | S41: 39194 | T41: 18 | U41: =IF(AND(ISNUMBER(K41),ISNUMBER(T41)),K41*T41*52/12,"") -> 5459.22 | V41: 4.5 | W41: 1639 | X41: 46307 | Y41: 32 | Z41: 45744 | AA41: =IF(ISNUMBER(Z41),(DATE(2026,10,13)-Z41)/365,"") -> 1.5452055 | AB41: 1201 | AC41: FBA | AD41: 1 | AE41: CN | AF41: 0 | AG41: 0 | AH41: 121 | AK41: 2026-04-01 | AL41: 0 | AM41: 0 | AN41: =IF(AND(ISNUMBER(AM41),ISNUMBER(AL41),AL41>=5),AM41/AL41,"") | AO41: 0 | AP41: 0 | AQ41: =IF(AND(ISNUMBER(AP41),ISNUMBER(AO41),AO41>=5),AP41/AO41,"") | AR41: 5.8 | AS41: 0.2 | AT41: =IF(AND(ISNUMBER(AS41),ISNUMBER(AR41),AR41>0),AS41/AR41-1,"") -> -0.96551724 | BD41: =IF(AND(ISNUMBER(BB41),ISNUMBER(BC41),BB41>0),1-BC41/BB41,"") | BH41: =IF(AND(ISNUMBER(BF41),ISNUMBER(BG41),BG41>0),BF41/BG41,"") | BM41: =IF(ISNUMBER(Q41),IF(Q41<0,"YES","no"),"") -> YES | BN41: =IFERROR(IF(AND(ISNUMBER(K41),ISNUMBER(INDEX('Lift Inputs'!$H:$H,MATCH(C41,'Lift Inputs'!$C:$C,0)))),IF(K41<INDEX('Lift Inputs'!$H:$H,MATCH(C41,'Lift Inputs'!$C:$C,0)),"YES","no"),""),"")
A42: Bamboo | B42: Decolure Bamboo Sheets 4 Piece | C42: 59 | D42: Hero: rank and profit | E42: 186 | F42: Bamboo Bay | G42: B0DLF1SWJ5 | H42: B07TBHLZJM | I42: Bamboo Sheets | J42: Poor | K42: 79.98 | M42: =IF(AND(ISNUMBER(L42),ISNUMBER(K42),K42>0),L42/K42-1,"") | N42: =IF(M42="","No List Price",IF(M42<=0,"At/below price",IF(M42<=0.12,"<=12% (STR zone)",IF(M42<=0.25,"12-25%",">25% (likely ignored)")))) -> No List Price | P42: 80.650959 | Q42: =IF(AND(ISNUMBER(K42),ISNUMBER(P42),N(P42)>0),K42/P42-1,"") -> -0.0083192923 | R42: Size unknown - vs our Queen | S42: 131083 | T42: 5 | U42: =IF(AND(ISNUMBER(K42),ISNUMBER(T42)),K42*T42*52/12,"") -> 1732.9 | V42: 4.5 | W42: 2691 | X42: 46307 | AA42: =IF(ISNUMBER(Z42),(DATE(2026,10,13)-Z42)/365,"") | AN42: =IF(AND(ISNUMBER(AM42),ISNUMBER(AL42),AL42>=5),AM42/AL42,"") | AQ42: =IF(AND(ISNUMBER(AP42),ISNUMBER(AO42),AO42>=5),AP42/AO42,"") | AT42: =IF(AND(ISNUMBER(AS42),ISNUMBER(AR42),AR42>0),AS42/AR42-1,"") | BD42: =IF(AND(ISNUMBER(BB42),ISNUMBER(BC42),BB42>0),1-BC42/BB42,"") | BH42: =IF(AND(ISNUMBER(BF42),ISNUMBER(BG42),BG42>0),BF42/BG42,"") | BM42: =IF(ISNUMBER(Q42),IF(Q42<0,"YES","no"),"") -> YES | BN42: =IFERROR(IF(AND(ISNUMBER(K42),ISNUMBER(INDEX('Lift Inputs'!$H:$H,MATCH(C42,'Lift Inputs'!$C:$C,0)))),IF(K42<INDEX('Lift Inputs'!$H:$H,MATCH(C42,'Lift Inputs'!$C:$C,0)),"YES","no"),""),"")
A43: Bamboo | B43: Decolure Bamboo Sheets 4 Piece | C43: 59 | D43: Hero: rank and profit | E43: 1512 | F43: LBRO2M | G43: B0F9FK3L6J | H43: B0F9FK7SMW | I43: LBRO2M Cooling Bed Sheet 100% Viscose Derived from Bamboo Sheet Set Queen Size 6 | J43: Poor | K43: 94.99 | M43: =IF(AND(ISNUMBER(L43),ISNUMBER(K43),K43>0),L43/K43-1,"") | N43: =IF(M43="","No List Price",IF(M43<=0,"At/below price",IF(M43<=0.12,"<=12% (STR zone)",IF(M43<=0.25,"12-25%",">25% (likely ignored)")))) -> No List Price | O43: Queen | P43: 80.650959 | Q43: =IF(AND(ISNUMBER(K43),ISNUMBER(P43),N(P43)>0),K43/P43-1,"") -> 0.17779133 | R43: Same size (Queen) | S43: 1003118 | T43: 5 | U43: =IF(AND(ISNUMBER(K43),ISNUMBER(T43)),K43*T43*52/12,"") -> 2058.1167 | V43: 4.4 | W43: 18 | X43: 46307 | AA43: =IF(ISNUMBER(Z43),(DATE(2026,10,13)-Z43)/365,"") | AN43: =IF(AND(ISNUMBER(AM43),ISNUMBER(AL43),AL43>=5),AM43/AL43,"") | AQ43: =IF(AND(ISNUMBER(AP43),ISNUMBER(AO43),AO43>=5),AP43/AO43,"") | AT43: =IF(AND(ISNUMBER(AS43),ISNUMBER(AR43),AR43>0),AS43/AR43-1,"") | BD43: =IF(AND(ISNUMBER(BB43),ISNUMBER(BC43),BB43>0),1-BC43/BB43,"") | BH43: =IF(AND(ISNUMBER(BF43),ISNUMBER(BG43),BG43>0),BF43/BG43,"") | BM43: =IF(ISNUMBER(Q43),IF(Q43<0,"YES","no"),"") -> no | BN43: =IFERROR(IF(AND(ISNUMBER(K43),ISNUMBER(INDEX('Lift Inputs'!$H:$H,MATCH(C43,'Lift Inputs'!$C:$C,0)))),IF(K43<INDEX('Lift Inputs'!$H:$H,MATCH(C43,'Lift Inputs'!$C:$C,0)),"YES","no"),""),"")
A44: Bamboo | B44: Decolure Bamboo Sheets 4 Piece | C44: 59 | D44: Hero: rank and profit | E44: 180 | F44: TWK | G44: B0GVP3B7LS | H44: B0GVP3B7LS | I44: TWK Luxury Sheet Set, Genuine 100% Viscose Derived from Bamboo, Cooling & Breath | J44: Poor | K44: 46.74 | M44: =IF(AND(ISNUMBER(L44),ISNUMBER(K44),K44>0),L44/K44-1,"") | N44: =IF(M44="","No List Price",IF(M44<=0,"At/below price",IF(M44<=0.12,"<=12% (STR zone)",IF(M44<=0.25,"12-25%",">25% (likely ignored)")))) -> No List Price | P44: 80.650959 | Q44: =IF(AND(ISNUMBER(K44),ISNUMBER(P44),N(P44)>0),K44/P44-1,"") -> -0.42046566 | R44: Size unknown - vs our Queen | S44: 2065761 | T44: 5 | U44: =IF(AND(ISNUMBER(K44),ISNUMBER(T44)),K44*T44*52/12,"") -> 1012.7 | V44: 4.5 | W44: 11 | X44: 46307 | Y44: 1 | Z44: 46078 | AA44: =IF(ISNUMBER(Z44),(DATE(2026,10,13)-Z44)/365,"") -> 0.63013699 | AB44: 5 | AC44: FBM | AD44: 0 | AE44: N/A | AF44: 0 | AG44: 0 | AH44: 0 | AN44: =IF(AND(ISNUMBER(AM44),ISNUMBER(AL44),AL44>=5),AM44/AL44,"") | AQ44: =IF(AND(ISNUMBER(AP44),ISNUMBER(AO44),AO44>=5),AP44/AO44,"") | AT44: =IF(AND(ISNUMBER(AS44),ISNUMBER(AR44),AR44>0),AS44/AR44-1,"") | BD44: =IF(AND(ISNUMBER(BB44),ISNUMBER(BC44),BB44>0),1-BC44/BB44,"") | BH44: =IF(AND(ISNUMBER(BF44),ISNUMBER(BG44),BG44>0),BF44/BG44,"") | BM44: =IF(ISNUMBER(Q44),IF(Q44<0,"YES","no"),"") -> YES | BN44: =IFERROR(IF(AND(ISNUMBER(K44),ISNUMBER(INDEX('Lift Inputs'!$H:$H,MATCH(C44,'Lift Inputs'!$C:$C,0)))),IF(K44<INDEX('Lift Inputs'!$H:$H,MATCH(C44,'Lift Inputs'!$C:$C,0)),"YES","no"),""),"")
A45: Bamboo | B45: Decolure Bamboo Sheets 4 Piece | C45: 59 | D45: Hero: rank and profit | E45: 1521 | F45: TWK | G45: B0DYT2QWLC | H45: B0DYT2QWLC | I45: TWK Luxury Sheet Set, Genuine 100% Organic Viscose Derived from Bamboo, Cooling | J45: Poor | K45: 109.99 | M45: =IF(AND(ISNUMBER(L45),ISNUMBER(K45),K45>0),L45/K45-1,"") | N45: =IF(M45="","No List Price",IF(M45<=0,"At/below price",IF(M45<=0.12,"<=12% (STR zone)",IF(M45<=0.25,"12-25%",">25% (likely ignored)")))) -> No List Price | P45: 80.650959 | Q45: =IF(AND(ISNUMBER(K45),ISNUMBER(P45),N(P45)>0),K45/P45-1,"") -> 0.36377796 | R45: Size unknown - vs our Queen | S45: 1506045 | T45: 5 | U45: =IF(AND(ISNUMBER(K45),ISNUMBER(T45)),K45*T45*52/12,"") -> 2383.1167 | V45: 4.5 | W45: 39 | X45: 46307 | Y45: 1 | Z45: 45716 | AA45: =IF(ISNUMBER(Z45),(DATE(2026,10,13)-Z45)/365,"") -> 1.6219178 | AB45: 12 | AC45: FBM | AD45: 0 | AE45: N/A | AF45: 0 | AG45: 0 | AH45: 0 | AN45: =IF(AND(ISNUMBER(AM45),ISNUMBER(AL45),AL45>=5),AM45/AL45,"") | AQ45: =IF(AND(ISNUMBER(AP45),ISNUMBER(AO45),AO45>=5),AP45/AO45,"") | AT45: =IF(AND(ISNUMBER(AS45),ISNUMBER(AR45),AR45>0),AS45/AR45-1,"") | BD45: =IF(AND(ISNUMBER(BB45),ISNUMBER(BC45),BB45>0),1-BC45/BB45,"") | BH45: =IF(AND(ISNUMBER(BF45),ISNUMBER(BG45),BG45>0),BF45/BG45,"") | BM45: =IF(ISNUMBER(Q45),IF(Q45<0,"YES","no"),"") -> no | BN45: =IFERROR(IF(AND(ISNUMBER(K45),ISNUMBER(INDEX('Lift Inputs'!$H:$H,MATCH(C45,'Lift Inputs'!$C:$C,0)))),IF(K45<INDEX('Lift Inputs'!$H:$H,MATCH(C45,'Lift Inputs'!$C:$C,0)),"YES","no"),""),"")
A46: Bamboo | B46: Decolure Bamboo Sheets 4 Piece | C46: 59 | D46: Hero: rank and profit | E46: 5 | F46: TWK | G46: B0GKFHP6L6 | H46: B0GW7H7RHY | I46: 4 Piece Bamboo Sheet Set | J46: Poor | K46: 109.99 | M46: =IF(AND(ISNUMBER(L46),ISNUMBER(K46),K46>0),L46/K46-1,"") | N46: =IF(M46="","No List Price",IF(M46<=0,"At/below price",IF(M46<=0.12,"<=12% (STR zone)",IF(M46<=0.25,"12-25%",">25% (likely ignored)")))) -> No List Price | P46: 80.650959 | Q46: =IF(AND(ISNUMBER(K46),ISNUMBER(P46),N(P46)>0),K46/P46-1,"") -> 0.36377796 | R46: Size unknown - vs our Queen | S46: 4355899 | T46: 5 | U46: =IF(AND(ISNUMBER(K46),ISNUMBER(T46)),K46*T46*52/12,"") -> 2383.1167 | V46: 4.5 | W46: 2 | X46: 46307 | AA46: =IF(ISNUMBER(Z46),(DATE(2026,10,13)-Z46)/365,"") | AN46: =IF(AND(ISNUMBER(AM46),ISNUMBER(AL46),AL46>=5),AM46/AL46,"") | AQ46: =IF(AND(ISNUMBER(AP46),ISNUMBER(AO46),AO46>=5),AP46/AO46,"") | AT46: =IF(AND(ISNUMBER(AS46),ISNUMBER(AR46),AR46>0),AS46/AR46-1,"") | BD46: =IF(AND(ISNUMBER(BB46),ISNUMBER(BC46),BB46>0),1-BC46/BB46,"") | BH46: =IF(AND(ISNUMBER(BF46),ISNUMBER(BG46),BG46>0),BF46/BG46,"") | BM46: =IF(ISNUMBER(Q46),IF(Q46<0,"YES","no"),"") -> no | BN46: =IFERROR(IF(AND(ISNUMBER(K46),ISNUMBER(INDEX('Lift Inputs'!$H:$H,MATCH(C46,'Lift Inputs'!$C:$C,0)))),IF(K46<INDEX('Lift Inputs'!$H:$H,MATCH(C46,'Lift Inputs'!$C:$C,0)),"YES","no"),""),"")
A47: Bamboo | B47: Decolure Bamboo Sheets 4 Piece | C47: 59 | D47: Hero: rank and profit | E47: 23 | F47: Vesta | G47: B0CZRJY68B | H47: B0DM214YG3 | I47: Vesta Sheet Set – Soft, Breathable & Cooling, 100% Viscose Derived from Bamboo, | J47: Poor | K47: 174.3 | M47: =IF(AND(ISNUMBER(L47),ISNUMBER(K47),K47>0),L47/K47-1,"") | N47: =IF(M47="","No List Price",IF(M47<=0,"At/below price",IF(M47<=0.12,"<=12% (STR zone)",IF(M47<=0.25,"12-25%",">25% (likely ignored)")))) -> No List Price | P47: 80.650959 | Q47: =IF(AND(ISNUMBER(K47),ISNUMBER(P47),N(P47)>0),K47/P47-1,"") -> 1.1611646 | R47: Size unknown - vs our Queen | S47: 591414 | T47: 5 | U47: =IF(AND(ISNUMBER(K47),ISNUMBER(T47)),K47*T47*52/12,"") -> 3776.5 | V47: 4.3 | W47: 35 | X47: 46307 | AA47: =IF(ISNUMBER(Z47),(DATE(2026,10,13)-Z47)/365,"") | AN47: =IF(AND(ISNUMBER(AM47),ISNUMBER(AL47),AL47>=5),AM47/AL47,"") | AQ47: =IF(AND(ISNUMBER(AP47),ISNUMBER(AO47),AO47>=5),AP47/AO47,"") | AT47: =IF(AND(ISNUMBER(AS47),ISNUMBER(AR47),AR47>0),AS47/AR47-1,"") | BD47: =IF(AND(ISNUMBER(BB47),ISNUMBER(BC47),BB47>0),1-BC47/BB47,"") | BH47: =IF(AND(ISNUMBER(BF47),ISNUMBER(BG47),BG47>0),BF47/BG47,"") | BM47: =IF(ISNUMBER(Q47),IF(Q47<0,"YES","no"),"") -> no | BN47: =IFERROR(IF(AND(ISNUMBER(K47),ISNUMBER(INDEX('Lift Inputs'!$H:$H,MATCH(C47,'Lift Inputs'!$C:$C,0)))),IF(K47<INDEX('Lift Inputs'!$H:$H,MATCH(C47,'Lift Inputs'!$C:$C,0)),"YES","no"),""),"")
A48: Bamboo | B48: Decolure Bamboo Sheets 4 Piece | C48: 59 | D48: Hero: rank and profit | E48: 1941 | F48: CozyLux | G48: B0GC2GQNMT | H48: B0GC5CJGWC | I48: CozyLux King Size Sheets Set, 100% Rayon Derived from Bamboo, Sateen Weave | K48: 35.99 | M48: =IF(AND(ISNUMBER(L48),ISNUMBER(K48),K48>0),L48/K48-1,"") | N48: =IF(M48="","No List Price",IF(M48<=0,"At/below price",IF(M48<=0.12,"<=12% (STR zone)",IF(M48<=0.25,"12-25%",">25% (likely ignored)")))) -> No List Price | O48: King | P48: 84.316772 | Q48: =IF(AND(ISNUMBER(K48),ISNUMBER(P48),N(P48)>0),K48/P48-1,"") -> -0.57315728 | R48: Same size (King) | S48: 33018 | T48: 185 | U48: =IF(AND(ISNUMBER(K48),ISNUMBER(T48)),K48*T48*52/12,"") -> 28851.983 | V48: 4.6 | W48: 93 | X48: 46307 | Y48: 18 | Z48: 46014 | AA48: =IF(ISNUMBER(Z48),(DATE(2026,10,13)-Z48)/365,"") -> 0.80547945 | AB48: 1963 | AC48: FBA | AD48: 1 | AE48: CN | AF48: 0 | AG48: 0 | AH48: 250 | AN48: =IF(AND(ISNUMBER(AM48),ISNUMBER(AL48),AL48>=5),AM48/AL48,"") | AQ48: =IF(AND(ISNUMBER(AP48),ISNUMBER(AO48),AO48>=5),AP48/AO48,"") | AT48: =IF(AND(ISNUMBER(AS48),ISNUMBER(AR48),AR48>0),AS48/AR48-1,"") | BD48: =IF(AND(ISNUMBER(BB48),ISNUMBER(BC48),BB48>0),1-BC48/BB48,"") | BH48: =IF(AND(ISNUMBER(BF48),ISNUMBER(BG48),BG48>0),BF48/BG48,"") | BM48: =IF(ISNUMBER(Q48),IF(Q48<0,"YES","no"),"") -> YES | BN48: =IFERROR(IF(AND(ISNUMBER(K48),ISNUMBER(INDEX('Lift Inputs'!$H:$H,MATCH(C48,'Lift Inputs'!$C:$C,0)))),IF(K48<INDEX('Lift Inputs'!$H:$H,MATCH(C48,'Lift Inputs'!$C:$C,0)),"YES","no"),""),"")
A49: Bamboo | B49: Decolure Bamboo Sheets 4 Piece | C49: 59 | D49: Hero: rank and profit | E49: 1946 | F49: Amazon Basics | G49: B0GFHP5V9H | H49: B0GFHGS4DP | I49: Amazon Basics Bamboo Viscose Sheet Set, 4-Piece, Queen, White | K49: 29.99 | M49: =IF(AND(ISNUMBER(L49),ISNUMBER(K49),K49>0),L49/K49-1,"") | N49: =IF(M49="","No List Price",IF(M49<=0,"At/below price",IF(M49<=0.12,"<=12% (STR zone)",IF(M49<=0.25,"12-25%",">25% (likely ignored)")))) -> No List Price | O49: Queen | P49: 80.650959 | Q49: =IF(AND(ISNUMBER(K49),ISNUMBER(P49),N(P49)>0),K49/P49-1,"") -> -0.62815073 | R49: Same size (Queen) | S49: 21965 | T49: 173 | U49: =IF(AND(ISNUMBER(K49),ISNUMBER(T49)),K49*T49*52/12,"") -> 22482.503 | V49: 4 | W49: 36 | X49: 46307 | AA49: =IF(ISNUMBER(Z49),(DATE(2026,10,13)-Z49)/365,"") | AN49: =IF(AND(ISNUMBER(AM49),ISNUMBER(AL49),AL49>=5),AM49/AL49,"") | AQ49: =IF(AND(ISNUMBER(AP49),ISNUMBER(AO49),AO49>=5),AP49/AO49,"") | AT49: =IF(AND(ISNUMBER(AS49),ISNUMBER(AR49),AR49>0),AS49/AR49-1,"") | BD49: =IF(AND(ISNUMBER(BB49),ISNUMBER(BC49),BB49>0),1-BC49/BB49,"") | BH49: =IF(AND(ISNUMBER(BF49),ISNUMBER(BG49),BG49>0),BF49/BG49,"") | BM49: =IF(ISNUMBER(Q49),IF(Q49<0,"YES","no"),"") -> YES | BN49: =IFERROR(IF(AND(ISNUMBER(K49),ISNUMBER(INDEX('Lift Inputs'!$H:$H,MATCH(C49,'Lift Inputs'!$C:$C,0)))),IF(K49<INDEX('Lift Inputs'!$H:$H,MATCH(C49,'Lift Inputs'!$C:$C,0)),"YES","no"),""),"")
A50: Bamboo | B50: Decolure Bamboo Sheets 4 Piece | C50: 59 | D50: Hero: rank and profit | E50: 1942 | F50: CGK Unlimited | G50: B0F2GR2DKR | H50: B0D429MCF7 | I50: 100% Rayon Derived from Bamboo - Bamboo Sheets Queen Size - Black | K50: 49.99 | M50: =IF(AND(ISNUMBER(L50),ISNUMBER(K50),K50>0),L50/K50-1,"") | N50: =IF(M50="","No List Price",IF(M50<=0,"At/below price",IF(M50<=0.12,"<=12% (STR zone)",IF(M50<=0.25,"12-25%",">25% (likely ignored)")))) -> No List Price | O50: Queen | P50: 80.650959 | Q50: =IF(AND(ISNUMBER(K50),ISNUMBER(P50),N(P50)>0),K50/P50-1,"") -> -0.38016856 | R50: Same size (Queen) | S50: 2554 | T50: 173 | U50: =IF(AND(ISNUMBER(K50),ISNUMBER(T50)),K50*T50*52/12,"") -> 37475.837 | V50: 4.4 | W50: 1169 | X50: 46307 | Y50: 58 | Z50: 45575 | AA50: =IF(ISNUMBER(Z50),(DATE(2026,10,13)-Z50)/365,"") -> 2.0082192 | AB50: 6444 | AC50: FBA | AD50: 1 | AE50: US | AF50: 0.024 | AG50: 0 | AH50: 403 | AN50: =IF(AND(ISNUMBER(AM50),ISNUMBER(AL50),AL50>=5),AM50/AL50,"") | AQ50: =IF(AND(ISNUMBER(AP50),ISNUMBER(AO50),AO50>=5),AP50/AO50,"") | AT50: =IF(AND(ISNUMBER(AS50),ISNUMBER(AR50),AR50>0),AS50/AR50-1,"") | BD50: =IF(AND(ISNUMBER(BB50),ISNUMBER(BC50),BB50>0),1-BC50/BB50,"") | BH50: =IF(AND(ISNUMBER(BF50),ISNUMBER(BG50),BG50>0),BF50/BG50,"") | BM50: =IF(ISNUMBER(Q50),IF(Q50<0,"YES","no"),"") -> YES | BN50: =IFERROR(IF(AND(ISNUMBER(K50),ISNUMBER(INDEX('Lift Inputs'!$H:$H,MATCH(C50,'Lift Inputs'!$C:$C,0)))),IF(K50<INDEX('Lift Inputs'!$H:$H,MATCH(C50,'Lift Inputs'!$C:$C,0)),"YES","no"),""),"")
A51: Bamboo | B51: Decolure Bamboo Sheets 4 Piece | C51: 59 | D51: Hero: rank and profit | E51: 1940 | F51: Shilucheng | G51: B0HJSVWNRS | H51: B0FWY1TGFK | I51: Shilucheng 4 Piece Queen Sheet Sets, Cooling Sheets, Dark Grey | K51: 34.99 | M51: =IF(AND(ISNUMBER(L51),ISNUMBER(K51),K51>0),L51/K51-1,"") | N51: =IF(M51="","No List Price",IF(M51<=0,"At/below price",IF(M51<=0.12,"<=12% (STR zone)",IF(M51<=0.25,"12-25%",">25% (likely ignored)")))) -> No List Price | O51: Queen | P51: 80.650959 | Q51: =IF(AND(ISNUMBER(K51),ISNUMBER(P51),N(P51)>0),K51/P51-1,"") -> -0.56615519 | R51: Same size (Queen) | S51: 5396 | T51: 173 | U51: =IF(AND(ISNUMBER(K51),ISNUMBER(T51)),K51*T51*52/12,"") -> 26230.837 | V51: 4.3 | W51: 24352 | X51: 46307 | AA51: =IF(ISNUMBER(Z51),(DATE(2026,10,13)-Z51)/365,"") | AI51: 135323 | AJ51: 1187 | AK51: 2026-04-01 | AL51: 0 | AM51: 0 | AN51: =IF(AND(ISNUMBER(AM51),ISNUMBER(AL51),AL51>=5),AM51/AL51,"") | AO51: 0 | AP51: 0 | AQ51: =IF(AND(ISNUMBER(AP51),ISNUMBER(AO51),AO51>=5),AP51/AO51,"") | AR51: 23.9 | AS51: 1.2 | AT51: =IF(AND(ISNUMBER(AS51),ISNUMBER(AR51),AR51>0),AS51/AR51-1,"") -> -0.94979079 | BD51: =IF(AND(ISNUMBER(BB51),ISNUMBER(BC51),BB51>0),1-BC51/BB51,"") | BH51: =IF(AND(ISNUMBER(BF51),ISNUMBER(BG51),BG51>0),BF51/BG51,"") | BM51: =IF(ISNUMBER(Q51),IF(Q51<0,"YES","no"),"") -> YES | BN51: =IFERROR(IF(AND(ISNUMBER(K51),ISNUMBER(INDEX('Lift Inputs'!$H:$H,MATCH(C51,'Lift Inputs'!$C:$C,0)))),IF(K51<INDEX('Lift Inputs'!$H:$H,MATCH(C51,'Lift Inputs'!$C:$C,0)),"YES","no"),""),"")
A52: Bamboo | B52: Decolure Bamboo Sheets 4 Piece | C52: 59 | D52: Hero: rank and profit | E52: 1951 | F52: Cosy House Collection | G52: B0CLBDW265 | H52: B0B4F4NTBL | I52: Cosy House Collection 100% Rayon Derived from Bamboo Bed Sheet Set | K52: 89.95 | M52: =IF(AND(ISNUMBER(L52),ISNUMBER(K52),K52>0),L52/K52-1,"") | N52: =IF(M52="","No List Price",IF(M52<=0,"At/below price",IF(M52<=0.12,"<=12% (STR zone)",IF(M52<=0.25,"12-25%",">25% (likely ignored)")))) -> No List Price | P52: 80.650959 | Q52: =IF(AND(ISNUMBER(K52),ISNUMBER(P52),N(P52)>0),K52/P52-1,"") -> 0.11529982 | R52: Size unknown - vs our Queen | S52: 20356 | T52: 35 | U52: =IF(AND(ISNUMBER(K52),ISNUMBER(T52)),K52*T52*52/12,"") -> 13642.417 | V52: 4.3 | W52: 7941 | X52: 46307 | Y52: 77 | Z52: 45344 | AA52: =IF(ISNUMBER(Z52),(DATE(2026,10,13)-Z52)/365,"") -> 2.6410959 | AB52: 3019 | AC52: FBA | AD52: 2 | AE52: US | AF52: 0 | AG52: 0 | AH52: 41 | AN52: =IF(AND(ISNUMBER(AM52),ISNUMBER(AL52),AL52>=5),AM52/AL52,"") | AQ52: =IF(AND(ISNUMBER(AP52),ISNUMBER(AO52),AO52>=5),AP52/AO52,"") | AT52: =IF(AND(ISNUMBER(AS52),ISNUMBER(AR52),AR52>0),AS52/AR52-1,"") | BD52: =IF(AND(ISNUMBER(BB52),ISNUMBER(BC52),BB52>0),1-BC52/BB52,"") | BH52: =IF(AND(ISNUMBER(BF52),ISNUMBER(BG52),BG52>0),BF52/BG52,"") | BM52: =IF(ISNUMBER(Q52),IF(Q52<0,"YES","no"),"") -> no | BN52: =IFERROR(IF(AND(ISNUMBER(K52),ISNUMBER(INDEX('Lift Inputs'!$H:$H,MATCH(C52,'Lift Inputs'!$C:$C,0)))),IF(K52<INDEX('Lift Inputs'!$H:$H,MATCH(C52,'Lift Inputs'!$C:$C,0)),"YES","no"),""),"")
A53: Bamboo | B53: Decolure Bamboo Sheets 4 Piece | C53: 59 | D53: Hero: rank and profit | E53: 763 | F53: MR&HM | G53: B0DQDMN3WK | H53: B0DL5NCTYF | I53: MR&HM Queen Sheets 4 Pieces, Rayon Derived from Bamboo Blend, Dark Grey | K53: 36.99 | M53: =IF(AND(ISNUMBER(L53),ISNUMBER(K53),K53>0),L53/K53-1,"") | N53: =IF(M53="","No List Price",IF(M53<=0,"At/below price",IF(M53<=0.12,"<=12% (STR zone)",IF(M53<=0.25,"12-25%",">25% (likely ignored)")))) -> No List Price | O53: Queen | P53: 80.650959 | Q53: =IF(AND(ISNUMBER(K53),ISNUMBER(P53),N(P53)>0),K53/P53-1,"") -> -0.54135697 | R53: Same size (Queen) | S53: 30653 | T53: 35 | U53: =IF(AND(ISNUMBER(K53),ISNUMBER(T53)),K53*T53*52/12,"") -> 5610.15 | V53: 4.4 | W53: 616 | X53: 46307 | Y53: 65 | Z53: 45593 | AA53: =IF(ISNUMBER(Z53),(DATE(2026,10,13)-Z53)/365,"") -> 1.9589041 | AB53: 1480 | AC53: FBA | AD53: 1 | AE53: HK | AF53: 0 | AG53: 0 | AH53: 212 | AN53: =IF(AND(ISNUMBER(AM53),ISNUMBER(AL53),AL53>=5),AM53/AL53,"") | AQ53: =IF(AND(ISNUMBER(AP53),ISNUMBER(AO53),AO53>=5),AP53/AO53,"") | AT53: =IF(AND(ISNUMBER(AS53),ISNUMBER(AR53),AR53>0),AS53/AR53-1,"") | BD53: =IF(AND(ISNUMBER(BB53),ISNUMBER(BC53),BB53>0),1-BC53/BB53,"") | BH53: =IF(AND(ISNUMBER(BF53),ISNUMBER(BG53),BG53>0),BF53/BG53,"") | BM53: =IF(ISNUMBER(Q53),IF(Q53<0,"YES","no"),"") -> YES | BN53: =IFERROR(IF(AND(ISNUMBER(K53),ISNUMBER(INDEX('Lift Inputs'!$H:$H,MATCH(C53,'Lift Inputs'!$C:$C,0)))),IF(K53<INDEX('Lift Inputs'!$H:$H,MATCH(C53,'Lift Inputs'!$C:$C,0)),"YES","no"),""),"")
A54: Bamboo | B54: Decolure Bamboo Sheets 4 Piece | C54: 59 | D54: Hero: rank and profit | E54: 1938 | F54: KAKIJUMN | G54: B0HFVC6529 | H54: B0H1MNZ16Z | I54: KAKIJUMN 6 Piece King Sheets Set, Rayon Derived from Bamboo Blend | K54: 38.39 | L54: 47.99 | M54: =IF(AND(ISNUMBER(L54),ISNUMBER(K54),K54>0),L54/K54-1,"") -> 0.25006512 | N54: =IF(M54="","No List Price",IF(M54<=0,"At/below price",IF(M54<=0.12,"<=12% (STR zone)",IF(M54<=0.25,"12-25%",">25% (likely ignored)")))) -> >25% (likely ignored) | O54: King | P54: 84.316772 | Q54: =IF(AND(ISNUMBER(K54),ISNUMBER(P54),N(P54)>0),K54/P54-1,"") -> -0.54469319 | R54: Same size (King) | S54: 64915 | T54: 18 | U54: =IF(AND(ISNUMBER(K54),ISNUMBER(T54)),K54*T54*52/12,"") -> 2994.42 | V54: 4 | W54: 71 | X54: 46307 | AA54: =IF(ISNUMBER(Z54),(DATE(2026,10,13)-Z54)/365,"") | AN54: =IF(AND(ISNUMBER(AM54),ISNUMBER(AL54),AL54>=5),AM54/AL54,"") | AQ54: =IF(AND(ISNUMBER(AP54),ISNUMBER(AO54),AO54>=5),AP54/AO54,"") | AT54: =IF(AND(ISNUMBER(AS54),ISNUMBER(AR54),AR54>0),AS54/AR54-1,"") | BD54: =IF(AND(ISNUMBER(BB54),ISNUMBER(BC54),BB54>0),1-BC54/BB54,"") | BH54: =IF(AND(ISNUMBER(BF54),ISNUMBER(BG54),BG54>0),BF54/BG54,"") | BM54: =IF(ISNUMBER(Q54),IF(Q54<0,"YES","no"),"") -> YES | BN54: =IFERROR(IF(AND(ISNUMBER(K54),ISNUMBER(INDEX('Lift Inputs'!$H:$H,MATCH(C54,'Lift Inputs'!$C:$C,0)))),IF(K54<INDEX('Lift Inputs'!$H:$H,MATCH(C54,'Lift Inputs'!$C:$C,0)),"YES","no"),""),"")
A55: Bamboo | B55: Decolure Bamboo Sheets 4 Piece | C55: 59 | D55: Hero: rank and profit | E55: 1820 | F55: Shilucheng | G55: B098JT1RF2 | H55: B098JT1RF2 | I55: Shilucheng 4 Piece King Sheet Sets, Cooling Sheets, Dark Grey | K55: 37.9 | M55: =IF(AND(ISNUMBER(L55),ISNUMBER(K55),K55>0),L55/K55-1,"") | N55: =IF(M55="","No List Price",IF(M55<=0,"At/below price",IF(M55<=0.12,"<=12% (STR zone)",IF(M55<=0.25,"12-25%",">25% (likely ignored)")))) -> No List Price | O55: King | P55: 84.316772 | Q55: =IF(AND(ISNUMBER(K55),ISNUMBER(P55),N(P55)>0),K55/P55-1,"") -> -0.55050461 | R55: Same size (King) | S55: 9187 | T55: 18 | U55: =IF(AND(ISNUMBER(K55),ISNUMBER(T55)),K55*T55*52/12,"") -> 2956.2 | V55: 4.3 | W55: 24333 | X55: 46286 | Y55: 100 | Z55: 44379 | AA55: =IF(ISNUMBER(Z55),(DATE(2026,10,13)-Z55)/365,"") -> 5.2849315 | AB55: 5599 | AC55: FBA | AD55: 1 | AE55: CN | AF55: 0 | AG55: 0 | AH55: 316 | AI55: 23320 | AJ55: 859 | AK55: 2026-04-01 | AL55: 0.1 | AM55: 2.5 | AN55: =IF(AND(ISNUMBER(AM55),ISNUMBER(AL55),AL55>=5),AM55/AL55,"") | AO55: 0 | AP55: 0 | AQ55: =IF(AND(ISNUMBER(AP55),ISNUMBER(AO55),AO55>=5),AP55/AO55,"") | AR55: 22.3 | AS55: 1 | AT55: =IF(AND(ISNUMBER(AS55),ISNUMBER(AR55),AR55>0),AS55/AR55-1,"") -> -0.95515695 | BD55: =IF(AND(ISNUMBER(BB55),ISNUMBER(BC55),BB55>0),1-BC55/BB55,"") | BH55: =IF(AND(ISNUMBER(BF55),ISNUMBER(BG55),BG55>0),BF55/BG55,"") | BM55: =IF(ISNUMBER(Q55),IF(Q55<0,"YES","no"),"") -> YES | BN55: =IFERROR(IF(AND(ISNUMBER(K55),ISNUMBER(INDEX('Lift Inputs'!$H:$H,MATCH(C55,'Lift Inputs'!$C:$C,0)))),IF(K55<INDEX('Lift Inputs'!$H:$H,MATCH(C55,'Lift Inputs'!$C:$C,0)),"YES","no"),""),"")
A56: Bamboo | B56: Decolure Bamboo Sheets 4 Piece | C56: 59 | D56: Hero: rank and profit | E56: 1952 | F56: Brooklyn Loom | G56: B0H29TVSQX | H56: B0FQ8JCH46 | I56: Brooklyn Loom 300 Thread Count Sateen 100% Rayon from Bamboo Deep Pocket 4 Piece | K56: 84.99 | M56: =IF(AND(ISNUMBER(L56),ISNUMBER(K56),K56>0),L56/K56-1,"") | N56: =IF(M56="","No List Price",IF(M56<=0,"At/below price",IF(M56<=0.12,"<=12% (STR zone)",IF(M56<=0.25,"12-25%",">25% (likely ignored)")))) -> No List Price | P56: 80.650959 | Q56: =IF(AND(ISNUMBER(K56),ISNUMBER(P56),N(P56)>0),K56/P56-1,"") -> 0.053800242 | R56: Size unknown - vs our Queen | S56: 1216102 | T56: 5 | U56: =IF(AND(ISNUMBER(K56),ISNUMBER(T56)),K56*T56*52/12,"") -> 1841.45 | V56: 4.5 | W56: 13 | X56: 46307 | AA56: =IF(ISNUMBER(Z56),(DATE(2026,10,13)-Z56)/365,"") | AN56: =IF(AND(ISNUMBER(AM56),ISNUMBER(AL56),AL56>=5),AM56/AL56,"") | AQ56: =IF(AND(ISNUMBER(AP56),ISNUMBER(AO56),AO56>=5),AP56/AO56,"") | AT56: =IF(AND(ISNUMBER(AS56),ISNUMBER(AR56),AR56>0),AS56/AR56-1,"") | BD56: =IF(AND(ISNUMBER(BB56),ISNUMBER(BC56),BB56>0),1-BC56/BB56,"") | BH56: =IF(AND(ISNUMBER(BF56),ISNUMBER(BG56),BG56>0),BF56/BG56,"") | BM56: =IF(ISNUMBER(Q56),IF(Q56<0,"YES","no"),"") -> no | BN56: =IFERROR(IF(AND(ISNUMBER(K56),ISNUMBER(INDEX('Lift Inputs'!$H:$H,MATCH(C56,'Lift Inputs'!$C:$C,0)))),IF(K56<INDEX('Lift Inputs'!$H:$H,MATCH(C56,'Lift Inputs'!$C:$C,0)),"YES","no"),""),"")
A57: Bamboo | B57: Decolure Bamboo Sheets 4 Piece | C57: 59 | D57: Hero: rank and profit | E57: 1947 | F57: MRIDU | G57: B0GSXPDW9C | H57: B0GSXRR9DN | I57: MRIDU Bamboo Viscose Sheet Set, 4-Piece, Pure White, King | K57: 89.99 | M57: =IF(AND(ISNUMBER(L57),ISNUMBER(K57),K57>0),L57/K57-1,"") | N57: =IF(M57="","No List Price",IF(M57<=0,"At/below price",IF(M57<=0.12,"<=12% (STR zone)",IF(M57<=0.25,"12-25%",">25% (likely ignored)")))) -> No List Price | O57: King | P57: 84.316772 | Q57: =IF(AND(ISNUMBER(K57),ISNUMBER(P57),N(P57)>0),K57/P57-1,"") -> 0.067284696 | R57: Same size (King) | S57: 1970806 | T57: 5 | U57: =IF(AND(ISNUMBER(K57),ISNUMBER(T57)),K57*T57*52/12,"") -> 1949.7833 | V57: 3.9 | W57: 24 | X57: 46307 | AA57: =IF(ISNUMBER(Z57),(DATE(2026,10,13)-Z57)/365,"") | AN57: =IF(AND(ISNUMBER(AM57),ISNUMBER(AL57),AL57>=5),AM57/AL57,"") | AQ57: =IF(AND(ISNUMBER(AP57),ISNUMBER(AO57),AO57>=5),AP57/AO57,"") | AT57: =IF(AND(ISNUMBER(AS57),ISNUMBER(AR57),AR57>0),AS57/AR57-1,"") | BD57: =IF(AND(ISNUMBER(BB57),ISNUMBER(BC57),BB57>0),1-BC57/BB57,"") | BH57: =IF(AND(ISNUMBER(BF57),ISNUMBER(BG57),BG57>0),BF57/BG57,"") | BM57: =IF(ISNUMBER(Q57),IF(Q57<0,"YES","no"),"") -> no | BN57: =IFERROR(IF(AND(ISNUMBER(K57),ISNUMBER(INDEX('Lift Inputs'!$H:$H,MATCH(C57,'Lift Inputs'!$C:$C,0)))),IF(K57<INDEX('Lift Inputs'!$H:$H,MATCH(C57,'Lift Inputs'!$C:$C,0)),"YES","no"),""),"")
A58: Bamboo | B58: Decolure Bamboo Sheets 6 Piece | C58: 30 | D58: Hero: rank and profit | E58: 495 | F58: Bedsure | G58: B0BZ8T5BJ6 | H58: B07YK8VTJV | I58: Bedsure PureWoven 100% Rayon Derived from Bamboo, Queen Sheets, 4 Pieces | J58: Aspirational | K58: 62.99 | L58: 69.99 | M58: =IF(AND(ISNUMBER(L58),ISNUMBER(K58),K58>0),L58/K58-1,"") -> 0.11112875 | N58: =IF(M58="","No List Price",IF(M58<=0,"At/below price",IF(M58<=0.12,"<=12% (STR zone)",IF(M58<=0.25,"12-25%",">25% (likely ignored)")))) -> <=12% (STR zone) | O58: Queen | P58: 90.683233 | Q58: =IF(AND(ISNUMBER(K58),ISNUMBER(P58),N(P58)>0),K58/P58-1,"") -> -0.30538427 | R58: Same size (Queen) | S58: 256 | T58: 809 | U58: =IF(AND(ISNUMBER(K58),ISNUMBER(T58)),K58*T58*52/12,"") -> 220821.94 | V58: 4.4 | W58: 65061 | X58: 46307 | Y58: 131 | Z58: 43348 | AA58: =IF(ISNUMBER(Z58),(DATE(2026,10,13)-Z58)/365,"") -> 8.109589 | AB58: 45362 | AC58: FBA | AD58: 2 | AE58: US | AF58: 0.016494845 | AG58: 0.0010119049 | AH58: 343 | AI58: 2166046 | AJ58: 6935 | AK58: 2026-04-01 | AL58: 924.6 | AM58: 986.2 | AN58: =IF(AND(ISNUMBER(AM58),ISNUMBER(AL58),AL58>=5),AM58/AL58,"") -> 1.0666234 | AO58: 371.8 | AP58: 574.2 | AQ58: =IF(AND(ISNUMBER(AP58),ISNUMBER(AO58),AO58>=5),AP58/AO58,"") -> 1.5443787 | AR58: 832.8 | AS58: 785.1 | AT58: =IF(AND(ISNUMBER(AS58),ISNUMBER(AR58),AR58>0),AS58/AR58-1,"") -> -0.057276657 | BD58: =IF(AND(ISNUMBER(BB58),ISNUMBER(BC58),BB58>0),1-BC58/BB58,"") | BH58: =IF(AND(ISNUMBER(BF58),ISNUMBER(BG58),BG58>0),BF58/BG58,"") | BM58: =IF(ISNUMBER(Q58),IF(Q58<0,"YES","no"),"") -> YES | BN58: =IFERROR(IF(AND(ISNUMBER(K58),ISNUMBER(INDEX('Lift Inputs'!$H:$H,MATCH(C58,'Lift Inputs'!$C:$C,0)))),IF(K58<INDEX('Lift Inputs'!$H:$H,MATCH(C58,'Lift Inputs'!$C:$C,0)),"YES","no"),""),"")
A59: Bamboo | B59: Decolure Bamboo Sheets 6 Piece | C59: 30 | D59: Hero: rank and profit | E59: 4 | F59: Pure Bamboo | G59: B0CZQ52MTQ | H59: B07DZTQ4JC | I59: Pure Bamboo King Sheets, Genuine 100% Organic Viscose Derived from Bamboo Bed Sh | J59: Aspirational | K59: 109.99 | M59: =IF(AND(ISNUMBER(L59),ISNUMBER(K59),K59>0),L59/K59-1,"") | N59: =IF(M59="","No List Price",IF(M59<=0,"At/below price",IF(M59<=0.12,"<=12% (STR zone)",IF(M59<=0.25,"12-25%",">25% (likely ignored)")))) -> No List Price | O59: King | P59: 90.861767 | Q59: =IF(AND(ISNUMBER(K59),ISNUMBER(P59),N(P59)>0),K59/P59-1,"") -> 0.21052015 | R59: Same size (King) | S59: 304 | T59: 809 | U59: =IF(AND(ISNUMBER(K59),ISNUMBER(T59)),K59*T59*52/12,"") -> 385588.28 | V59: 4.5 | W59: 21927 | X59: 46307 | Y59: 181 | Z59: 43281 | AA59: =IF(ISNUMBER(Z59),(DATE(2026,10,13)-Z59)/365,"") -> 8.2931507 | AB59: 32356 | AC59: FBA | AD59: 2 | AE59: US | AF59: 0 | AG59: 0 | AH59: 268 | AI59: 2565055 | AJ59: 8283 | AK59: 2026-04-01 | AL59: 556.9 | AM59: 657.2 | AN59: =IF(AND(ISNUMBER(AM59),ISNUMBER(AL59),AL59>=5),AM59/AL59,"") -> 1.1801041 | AO59: 102 | AP59: 151.8 | AQ59: =IF(AND(ISNUMBER(AP59),ISNUMBER(AO59),AO59>=5),AP59/AO59,"") -> 1.4882353 | AR59: 259.8 | AS59: 667.9 | AT59: =IF(AND(ISNUMBER(AS59),ISNUMBER(AR59),AR59>0),AS59/AR59-1,"") -> 1.5708237 | BD59: =IF(AND(ISNUMBER(BB59),ISNUMBER(BC59),BB59>0),1-BC59/BB59,"") | BH59: =IF(AND(ISNUMBER(BF59),ISNUMBER(BG59),BG59>0),BF59/BG59,"") | BM59: =IF(ISNUMBER(Q59),IF(Q59<0,"YES","no"),"") -> no | BN59: =IFERROR(IF(AND(ISNUMBER(K59),ISNUMBER(INDEX('Lift Inputs'!$H:$H,MATCH(C59,'Lift Inputs'!$C:$C,0)))),IF(K59<INDEX('Lift Inputs'!$H:$H,MATCH(C59,'Lift Inputs'!$C:$C,0)),"YES","no"),""),"")
A60: Bamboo | B60: Decolure Bamboo Sheets 6 Piece | C60: 30 | D60: Hero: rank and profit | E60: 27 | F60: Hotel Sheets Direct | G60: B0G5N99X9R | H60: B01N9L2O9P | I60: Hotel Sheets Direct 4 Piece Bed Sheet Set Queen Size, 100% Viscose Derived from | J60: Aspirational | K60: 79.99 | M60: =IF(AND(ISNUMBER(L60),ISNUMBER(K60),K60>0),L60/K60-1,"") | N60: =IF(M60="","No List Price",IF(M60<=0,"At/below price",IF(M60<=0.12,"<=12% (STR zone)",IF(M60<=0.25,"12-25%",">25% (likely ignored)")))) -> No List Price | O60: Queen | P60: 90.683233 | Q60: =IF(AND(ISNUMBER(K60),ISNUMBER(P60),N(P60)>0),K60/P60-1,"") -> -0.11791852 | R60: Same size (Queen) | S60: 2984 | T60: 347 | U60: =IF(AND(ISNUMBER(K60),ISNUMBER(T60)),K60*T60*52/12,"") -> 120278.3 | V60: 4.4 | W60: 37179 | X60: 46307 | Y60: 61 | Z60: 42729 | AA60: =IF(ISNUMBER(Z60),(DATE(2026,10,13)-Z60)/365,"") -> 9.8054795 | AB60: 8203 | AC60: FBA | AD60: 2 | AE60: US | AF60: 0.0021097046 | AG60: 0 | AH60: 382 | AI60: 451969 | AJ60: 4094 | AK60: 2026-01-01 | AL60: 263.5 | AM60: 474.2 | AN60: =IF(AND(ISNUMBER(AM60),ISNUMBER(AL60),AL60>=5),AM60/AL60,"") -> 1.7996205 | AO60: 24.4 | AP60: 31 | AQ60: =IF(AND(ISNUMBER(AP60),ISNUMBER(AO60),AO60>=5),AP60/AO60,"") -> 1.2704918 | AR60: 372.7 | AS60: 374.5 | AT60: =IF(AND(ISNUMBER(AS60),ISNUMBER(AR60),AR60>0),AS60/AR60-1,"") -> 0.0048296217 | BD60: =IF(AND(ISNUMBER(BB60),ISNUMBER(BC60),BB60>0),1-BC60/BB60,"") | BH60: =IF(AND(ISNUMBER(BF60),ISNUMBER(BG60),BG60>0),BF60/BG60,"") | BM60: =IF(ISNUMBER(Q60),IF(Q60<0,"YES","no"),"") -> YES | BN60: =IFERROR(IF(AND(ISNUMBER(K60),ISNUMBER(INDEX('Lift Inputs'!$H:$H,MATCH(C60,'Lift Inputs'!$C:$C,0)))),IF(K60<INDEX('Lift Inputs'!$H:$H,MATCH(C60,'Lift Inputs'!$C:$C,0)),"YES","no"),""),"")
A61: Bamboo | B61: Decolure Bamboo Sheets 6 Piece | C61: 30 | D61: Hero: rank and profit | E61: 29 | F61: BAMPURE | G61: B0FH2WGKJV | H61: B07XC2KVM7 | I61: Bamboo Sheets | J61: Aspirational | K61: 37.99 | M61: =IF(AND(ISNUMBER(L61),ISNUMBER(K61),K61>0),L61/K61-1,"") | N61: =IF(M61="","No List Price",IF(M61<=0,"At/below price",IF(M61<=0.12,"<=12% (STR zone)",IF(M61<=0.25,"12-25%",">25% (likely ignored)")))) -> No List Price | P61: 90.683233 | Q61: =IF(AND(ISNUMBER(K61),ISNUMBER(P61),N(P61)>0),K61/P61-1,"") -> -0.58106919 | R61: Size unknown - vs our Queen | S61: 2541068 | T61: 5 | U61: =IF(AND(ISNUMBER(K61),ISNUMBER(T61)),K61*T61*52/12,"") -> 823.11667 | V61: 4.4 | W61: 30 | X61: 46307 | AA61: =IF(ISNUMBER(Z61),(DATE(2026,10,13)-Z61)/365,"") | AN61: =IF(AND(ISNUMBER(AM61),ISNUMBER(AL61),AL61>=5),AM61/AL61,"") | AQ61: =IF(AND(ISNUMBER(AP61),ISNUMBER(AO61),AO61>=5),AP61/AO61,"") | AT61: =IF(AND(ISNUMBER(AS61),ISNUMBER(AR61),AR61>0),AS61/AR61-1,"") | BD61: =IF(AND(ISNUMBER(BB61),ISNUMBER(BC61),BB61>0),1-BC61/BB61,"") | BH61: =IF(AND(ISNUMBER(BF61),ISNUMBER(BG61),BG61>0),BF61/BG61,"") | BM61: =IF(ISNUMBER(Q61),IF(Q61<0,"YES","no"),"") -> YES | BN61: =IFERROR(IF(AND(ISNUMBER(K61),ISNUMBER(INDEX('Lift Inputs'!$H:$H,MATCH(C61,'Lift Inputs'!$C:$C,0)))),IF(K61<INDEX('Lift Inputs'!$H:$H,MATCH(C61,'Lift Inputs'!$C:$C,0)),"YES","no"),""),"")
A62: Bamboo | B62: Decolure Bamboo Sheets 6 Piece | C62: 30 | D62: Hero: rank and profit | E62: 696 | F62: Love's cabin | G62: B0DN1GGFL7 | H62: B0DN1DVKH5 | I62: Love's cabin 4 Piece Queen Sheet Set, 100% Rayon Derived from Bamboo, Cooling & | J62: Beatable | K62: 37.99 | L62: 44.99 | M62: =IF(AND(ISNUMBER(L62),ISNUMBER(K62),K62>0),L62/K62-1,"") -> 0.18425902 | N62: =IF(M62="","No List Price",IF(M62<=0,"At/below price",IF(M62<=0.12,"<=12% (STR zone)",IF(M62<=0.25,"12-25%",">25% (likely ignored)")))) -> 12-25% | O62: Queen | P62: 90.683233 | Q62: =IF(AND(ISNUMBER(K62),ISNUMBER(P62),N(P62)>0),K62/P62-1,"") -> -0.58106919 | R62: Same size (Queen) | S62: 501 | T62: 924 | U62: =IF(AND(ISNUMBER(K62),ISNUMBER(T62)),K62*T62*52/12,"") -> 152111.96 | V62: 4.4 | W62: 1900 | X62: 46307 | Y62: 176 | Z62: 45694 | AA62: =IF(ISNUMBER(Z62),(DATE(2026,10,13)-Z62)/365,"") -> 1.6821918 | AB62: 22978 | AC62: FBA | AD62: 5 | AE62: CN | AF62: 0 | AG62: 0 | AH62: 445 | AI62: 906346 | AJ62: 4326 | AK62: 2026-04-01 | AL62: 1478.5 | AM62: 1323.8 | AN62: =IF(AND(ISNUMBER(AM62),ISNUMBER(AL62),AL62>=5),AM62/AL62,"") -> 0.89536693 | AO62: 0 | AP62: 0 | AQ62: =IF(AND(ISNUMBER(AP62),ISNUMBER(AO62),AO62>=5),AP62/AO62,"") | AR62: 886.7 | AS62: 1364.5 | AT62: =IF(AND(ISNUMBER(AS62),ISNUMBER(AR62),AR62>0),AS62/AR62-1,"") -> 0.53885192 | BD62: =IF(AND(ISNUMBER(BB62),ISNUMBER(BC62),BB62>0),1-BC62/BB62,"") | BH62: =IF(AND(ISNUMBER(BF62),ISNUMBER(BG62),BG62>0),BF62/BG62,"") | BM62: =IF(ISNUMBER(Q62),IF(Q62<0,"YES","no"),"") -> YES | BN62: =IFERROR(IF(AND(ISNUMBER(K62),ISNUMBER(INDEX('Lift Inputs'!$H:$H,MATCH(C62,'Lift Inputs'!$C:$C,0)))),IF(K62<INDEX('Lift Inputs'!$H:$H,MATCH(C62,'Lift Inputs'!$C:$C,0)),"YES","no"),""),"")
A63: Bamboo | B63: Decolure Bamboo Sheets 6 Piece | C63: 30 | D63: Hero: rank and profit | E63: 33 | F63: KRIMANO | G63: B0FT7L9RSX | H63: B0FT7LZ2CD | I63: KRIMANO Bamboo Viscose Sheet Set King Size, Cooling Sheets Bed Set | J63: Beatable | K63: 84.99 | M63: =IF(AND(ISNUMBER(L63),ISNUMBER(K63),K63>0),L63/K63-1,"") | N63: =IF(M63="","No List Price",IF(M63<=0,"At/below price",IF(M63<=0.12,"<=12% (STR zone)",IF(M63<=0.25,"12-25%",">25% (likely ignored)")))) -> No List Price | O63: King | P63: 90.861767 | Q63: =IF(AND(ISNUMBER(K63),ISNUMBER(P63),N(P63)>0),K63/P63-1,"") -> -0.06462308 | R63: Same size (King) | S63: 5664 | T63: 185 | U63: =IF(AND(ISNUMBER(K63),ISNUMBER(T63)),K63*T63*52/12,"") -> 68133.65 | V63: 4.5 | W63: 263 | X63: 46307 | Y63: 43 | Z63: 45944 | AA63: =IF(ISNUMBER(Z63),(DATE(2026,10,13)-Z63)/365,"") -> 0.99726027 | AB63: 5418 | AC63: FBA | AD63: 1 | AE63: HK | AF63: 0 | AG63: 0 | AH63: 295 | AI63: 334819 | AJ63: 2638 | AK63: 2026-01-01 | AL63: 198.1 | AM63: 260 | AN63: =IF(AND(ISNUMBER(AM63),ISNUMBER(AL63),AL63>=5),AM63/AL63,"") -> 1.3124685 | AO63: 89.9 | AP63: 320.5 | AQ63: =IF(AND(ISNUMBER(AP63),ISNUMBER(AO63),AO63>=5),AP63/AO63,"") -> 3.5650723 | AR63: 183.2 | AS63: 230.2 | AT63: =IF(AND(ISNUMBER(AS63),ISNUMBER(AR63),AR63>0),AS63/AR63-1,"") -> 0.25655022 | BD63: =IF(AND(ISNUMBER(BB63),ISNUMBER(BC63),BB63>0),1-BC63/BB63,"") | BH63: =IF(AND(ISNUMBER(BF63),ISNUMBER(BG63),BG63>0),BF63/BG63,"") | BM63: =IF(ISNUMBER(Q63),IF(Q63<0,"YES","no"),"") -> YES | BN63: =IFERROR(IF(AND(ISNUMBER(K63),ISNUMBER(INDEX('Lift Inputs'!$H:$H,MATCH(C63,'Lift Inputs'!$C:$C,0)))),IF(K63<INDEX('Lift Inputs'!$H:$H,MATCH(C63,'Lift Inputs'!$C:$C,0)),"YES","no"),""),"")
A64: Bamboo | B64: Decolure Bamboo Sheets 6 Piece | C64: 30 | D64: Hero: rank and profit | E64: 1956 | F64: TRUE BAMBOO | G64: B0HHQ97HBL | H64: B0HD7R5L1D | I64: TRUE BAMBOO Sheets Set King Size - Silky Soft & Cooling - Dark Gray | J64: Beatable | K64: 114.99 | L64: 129.99 | M64: =IF(AND(ISNUMBER(L64),ISNUMBER(K64),K64>0),L64/K64-1,"") -> 0.13044613 | N64: =IF(M64="","No List Price",IF(M64<=0,"At/below price",IF(M64<=0.12,"<=12% (STR zone)",IF(M64<=0.25,"12-25%",">25% (likely ignored)")))) -> 12-25% | O64: King | P64: 90.861767 | Q64: =IF(AND(ISNUMBER(K64),ISNUMBER(P64),N(P64)>0),K64/P64-1,"") -> 0.26554879 | R64: Same size (King) | S64: 5934 | T64: 185 | U64: =IF(AND(ISNUMBER(K64),ISNUMBER(T64)),K64*T64*52/12,"") -> 92183.65 | V64: 4.6 | W64: 167 | X64: 46307 | AA64: =IF(ISNUMBER(Z64),(DATE(2026,10,13)-Z64)/365,"") | AI64: 557658 | AJ64: 2189 | AK64: 2026-04-01 | AL64: 0 | AM64: 0 | AN64: =IF(AND(ISNUMBER(AM64),ISNUMBER(AL64),AL64>=5),AM64/AL64,"") | AO64: 0 | AP64: 0 | AQ64: =IF(AND(ISNUMBER(AP64),ISNUMBER(AO64),AO64>=5),AP64/AO64,"") | AR64: 0 | AS64: 4.2 | AT64: =IF(AND(ISNUMBER(AS64),ISNUMBER(AR64),AR64>0),AS64/AR64-1,"") | BD64: =IF(AND(ISNUMBER(BB64),ISNUMBER(BC64),BB64>0),1-BC64/BB64,"") | BH64: =IF(AND(ISNUMBER(BF64),ISNUMBER(BG64),BG64>0),BF64/BG64,"") | BM64: =IF(ISNUMBER(Q64),IF(Q64<0,"YES","no"),"") -> no | BN64: =IFERROR(IF(AND(ISNUMBER(K64),ISNUMBER(INDEX('Lift Inputs'!$H:$H,MATCH(C64,'Lift Inputs'!$C:$C,0)))),IF(K64<INDEX('Lift Inputs'!$H:$H,MATCH(C64,'Lift Inputs'!$C:$C,0)),"YES","no"),""),"")
A65: Bamboo | B65: Decolure Bamboo Sheets 6 Piece | C65: 30 | D65: Hero: rank and profit | E65: 1940 | F65: Shilucheng | G65: B0HJSVWNRS | H65: B0FWY1TGFK | I65: Shilucheng 4 Piece Queen Sheet Sets, Cooling Sheets, Dark Grey | J65: Beatable | K65: 34.99 | M65: =IF(AND(ISNUMBER(L65),ISNUMBER(K65),K65>0),L65/K65-1,"") | N65: =IF(M65="","No List Price",IF(M65<=0,"At/below price",IF(M65<=0.12,"<=12% (STR zone)",IF(M65<=0.25,"12-25%",">25% (likely ignored)")))) -> No List Price | O65: Queen | P65: 90.683233 | Q65: =IF(AND(ISNUMBER(K65),ISNUMBER(P65),N(P65)>0),K65/P65-1,"") -> -0.61415138 | R65: Same size (Queen) | S65: 5396 | T65: 173 | U65: =IF(AND(ISNUMBER(K65),ISNUMBER(T65)),K65*T65*52/12,"") -> 26230.837 | V65: 4.3 | W65: 24352 | X65: 46307 | AA65: =IF(ISNUMBER(Z65),(DATE(2026,10,13)-Z65)/365,"") | AI65: 135323 | AJ65: 1187 | AK65: 2026-04-01 | AL65: 0 | AM65: 0 | AN65: =IF(AND(ISNUMBER(AM65),ISNUMBER(AL65),AL65>=5),AM65/AL65,"") | AO65: 0 | AP65: 0 | AQ65: =IF(AND(ISNUMBER(AP65),ISNUMBER(AO65),AO65>=5),AP65/AO65,"") | AR65: 23.9 | AS65: 1.2 | AT65: =IF(AND(ISNUMBER(AS65),ISNUMBER(AR65),AR65>0),AS65/AR65-1,"") -> -0.94979079 | BD65: =IF(AND(ISNUMBER(BB65),ISNUMBER(BC65),BB65>0),1-BC65/BB65,"") | BH65: =IF(AND(ISNUMBER(BF65),ISNUMBER(BG65),BG65>0),BF65/BG65,"") | BM65: =IF(ISNUMBER(Q65),IF(Q65<0,"YES","no"),"") -> YES | BN65: =IFERROR(IF(AND(ISNUMBER(K65),ISNUMBER(INDEX('Lift Inputs'!$H:$H,MATCH(C65,'Lift Inputs'!$C:$C,0)))),IF(K65<INDEX('Lift Inputs'!$H:$H,MATCH(C65,'Lift Inputs'!$C:$C,0)),"YES","no"),""),"")
A66: Bamboo | B66: Decolure Bamboo Sheets 6 Piece | C66: 30 | D66: Hero: rank and profit | E66: 3 | F66: Bambaw | G66: B07K6SYX8L | H66: B0DR99Q37Y | I66: Bambaw 100% Viscose Derived from Bamboo Sheets Queen Size Set – 4pcs Cooling She | J66: Beatable | K66: 89.99 | M66: =IF(AND(ISNUMBER(L66),ISNUMBER(K66),K66>0),L66/K66-1,"") | N66: =IF(M66="","No List Price",IF(M66<=0,"At/below price",IF(M66<=0.12,"<=12% (STR zone)",IF(M66<=0.25,"12-25%",">25% (likely ignored)")))) -> No List Price | O66: Queen | P66: 90.683233 | Q66: =IF(AND(ISNUMBER(K66),ISNUMBER(P66),N(P66)>0),K66/P66-1,"") -> -0.0076445563 | R66: Same size (Queen) | S66: 6971 | T66: 104 | U66: =IF(AND(ISNUMBER(K66),ISNUMBER(T66)),K66*T66*52/12,"") -> 40555.493 | V66: 4.3 | W66: 2766 | X66: 46307 | Y66: 104 | Z66: 45649 | AA66: =IF(ISNUMBER(Z66),(DATE(2026,10,13)-Z66)/365,"") -> 1.8054795 | AB66: 4777 | AC66: FBA | AD66: 1 | AE66: BE | AF66: 0 | AG66: 0 | AH66: 190 | AI66: 407949 | AJ66: 2137 | AK66: 2026-01-01 | AL66: 356.5 | AM66: 490 | AN66: =IF(AND(ISNUMBER(AM66),ISNUMBER(AL66),AL66>=5),AM66/AL66,"") -> 1.3744741 | AO66: 57.6 | AP66: 82.5 | AQ66: =IF(AND(ISNUMBER(AP66),ISNUMBER(AO66),AO66>=5),AP66/AO66,"") -> 1.4322917 | AR66: 239.9 | AS66: 571.4 | AT66: =IF(AND(ISNUMBER(AS66),ISNUMBER(AR66),AR66>0),AS66/AR66-1,"") -> 1.3818258 | BD66: =IF(AND(ISNUMBER(BB66),ISNUMBER(BC66),BB66>0),1-BC66/BB66,"") | BH66: =IF(AND(ISNUMBER(BF66),ISNUMBER(BG66),BG66>0),BF66/BG66,"") | BM66: =IF(ISNUMBER(Q66),IF(Q66<0,"YES","no"),"") -> YES | BN66: =IFERROR(IF(AND(ISNUMBER(K66),ISNUMBER(INDEX('Lift Inputs'!$H:$H,MATCH(C66,'Lift Inputs'!$C:$C,0)))),IF(K66<INDEX('Lift Inputs'!$H:$H,MATCH(C66,'Lift Inputs'!$C:$C,0)),"YES","no"),""),"")
A67: Bamboo | B67: Decolure Bamboo Sheets 6 Piece | C67: 30 | D67: Hero: rank and profit | E67: 6 | F67: Bedsure | G67: B0FB8XS4D1 | H67: B0FB8XR43Q | I67: Bedsure PureWoven Organically Grown Bamboo Viscose Queen Sheet Set, 4PCS | J67: Beatable | K67: 89.99 | L67: 119.99 | M67: =IF(AND(ISNUMBER(L67),ISNUMBER(K67),K67>0),L67/K67-1,"") -> 0.33337037 | N67: =IF(M67="","No List Price",IF(M67<=0,"At/below price",IF(M67<=0.12,"<=12% (STR zone)",IF(M67<=0.25,"12-25%",">25% (likely ignored)")))) -> >25% (likely ignored) | O67: Queen | P67: 90.683233 | Q67: =IF(AND(ISNUMBER(K67),ISNUMBER(P67),N(P67)>0),K67/P67-1,"") -> -0.0076445563 | R67: Same size (Queen) | S67: 8938 | T67: 104 | U67: =IF(AND(ISNUMBER(K67),ISNUMBER(T67)),K67*T67*52/12,"") -> 40555.493 | V67: 4.5 | W67: 588 | X67: 46307 | Y67: 39 | Z67: 45936 | AA67: =IF(ISNUMBER(Z67),(DATE(2026,10,13)-Z67)/365,"") -> 1.0191781 | AB67: 4014 | AC67: FBA | AD67: 4 | AE67: US | AF67: 0 | AG67: 0 | AH67: 313 | AI67: 840292 | AJ67: 3961 | AK67: 2026-01-01 | AL67: 279.8 | AM67: 493.8 | AN67: =IF(AND(ISNUMBER(AM67),ISNUMBER(AL67),AL67>=5),AM67/AL67,"") -> 1.764832 | AO67: 320.1 | AP67: 534.8 | AQ67: =IF(AND(ISNUMBER(AP67),ISNUMBER(AO67),AO67>=5),AP67/AO67,"") -> 1.6707279 | AR67: 248.7 | AS67: 226.2 | AT67: =IF(AND(ISNUMBER(AS67),ISNUMBER(AR67),AR67>0),AS67/AR67-1,"") -> -0.090470446 | BD67: =IF(AND(ISNUMBER(BB67),ISNUMBER(BC67),BB67>0),1-BC67/BB67,"") | BH67: =IF(AND(ISNUMBER(BF67),ISNUMBER(BG67),BG67>0),BF67/BG67,"") | BM67: =IF(ISNUMBER(Q67),IF(Q67<0,"YES","no"),"") -> YES | BN67: =IFERROR(IF(AND(ISNUMBER(K67),ISNUMBER(INDEX('Lift Inputs'!$H:$H,MATCH(C67,'Lift Inputs'!$C:$C,0)))),IF(K67<INDEX('Lift Inputs'!$H:$H,MATCH(C67,'Lift Inputs'!$C:$C,0)),"YES","no"),""),"")
A68: Bamboo | B68: Decolure Bamboo Sheets 6 Piece | C68: 30 | D68: Hero: rank and profit | E68: 1507 | F68: SONORO KATE | G68: B0F4852T9V | H68: B0F4873G4H | I68: Bamboo Sheets | J68: Beatable | K68: 79.99 | M68: =IF(AND(ISNUMBER(L68),ISNUMBER(K68),K68>0),L68/K68-1,"") | N68: =IF(M68="","No List Price",IF(M68<=0,"At/below price",IF(M68<=0.12,"<=12% (STR zone)",IF(M68<=0.25,"12-25%",">25% (likely ignored)")))) -> No List Price | P68: 90.683233 | Q68: =IF(AND(ISNUMBER(K68),ISNUMBER(P68),N(P68)>0),K68/P68-1,"") -> -0.11791852 | R68: Size unknown - vs our Queen | S68: 7961 | T68: 104 | U68: =IF(AND(ISNUMBER(K68),ISNUMBER(T68)),K68*T68*52/12,"") -> 36048.827 | V68: 4.5 | W68: 3776 | X68: 46307 | AA68: =IF(ISNUMBER(Z68),(DATE(2026,10,13)-Z68)/365,"") | AI68: 185157 | AJ68: 1447 | AK68: 2026-01-01 | AL68: 295.1 | AM68: 388 | AN68: =IF(AND(ISNUMBER(AM68),ISNUMBER(AL68),AL68>=5),AM68/AL68,"") -> 1.3148085 | AO68: 1.1 | AP68: 0.5 | AQ68: =IF(AND(ISNUMBER(AP68),ISNUMBER(AO68),AO68>=5),AP68/AO68,"") | AR68: 254.1 | AS68: 411.3 | AT68: =IF(AND(ISNUMBER(AS68),ISNUMBER(AR68),AR68>0),AS68/AR68-1,"") -> 0.61865407 | BD68: =IF(AND(ISNUMBER(BB68),ISNUMBER(BC68),BB68>0),1-BC68/BB68,"") | BH68: =IF(AND(ISNUMBER(BF68),ISNUMBER(BG68),BG68>0),BF68/BG68,"") | BM68: =IF(ISNUMBER(Q68),IF(Q68<0,"YES","no"),"") -> YES | BN68: =IFERROR(IF(AND(ISNUMBER(K68),ISNUMBER(INDEX('Lift Inputs'!$H:$H,MATCH(C68,'Lift Inputs'!$C:$C,0)))),IF(K68<INDEX('Lift Inputs'!$H:$H,MATCH(C68,'Lift Inputs'!$C:$C,0)),"YES","no"),""),"")
A69: Bamboo | B69: Decolure Bamboo Sheets 6 Piece | C69: 30 | D69: Hero: rank and profit | E69: 637 | F69: BC BELLA COTERIE | G69: B0H29V113N | H69: B08L86VLZB | I69: Bella Coterie Luxury Bamboo Viscose King Size Sheet Set | J69: Beatable | K69: 134.99 | M69: =IF(AND(ISNUMBER(L69),ISNUMBER(K69),K69>0),L69/K69-1,"") | N69: =IF(M69="","No List Price",IF(M69<=0,"At/below price",IF(M69<=0.12,"<=12% (STR zone)",IF(M69<=0.25,"12-25%",">25% (likely ignored)")))) -> No List Price | O69: King | P69: 90.861767 | Q69: =IF(AND(ISNUMBER(K69),ISNUMBER(P69),N(P69)>0),K69/P69-1,"") -> 0.48566338 | R69: Same size (King) | S69: 1358 | T69: 92 | U69: =IF(AND(ISNUMBER(K69),ISNUMBER(T69)),K69*T69*52/12,"") -> 53816.013 | V69: 4.4 | W69: 5871 | X69: 46307 | Y69: 258 | Z69: 44154 | AA69: =IF(ISNUMBER(Z69),(DATE(2026,10,13)-Z69)/365,"") -> 5.9013699 | AB69: 13039 | AC69: FBA | AD69: 1 | AE69: US | AF69: 0.80168776 | AG69: 0.36133922 | AH69: 316 | AI69: 591713 | AJ69: 5504 | AK69: 2026-04-01 | AL69: 107.7 | AM69: 191.5 | AN69: =IF(AND(ISNUMBER(AM69),ISNUMBER(AL69),AL69>=5),AM69/AL69,"") -> 1.7780873 | AO69: 49.4 | AP69: 99.8 | AQ69: =IF(AND(ISNUMBER(AP69),ISNUMBER(AO69),AO69>=5),AP69/AO69,"") -> 2.0202429 | AR69: 127.5 | AS69: 175.6 | AT69: =IF(AND(ISNUMBER(AS69),ISNUMBER(AR69),AR69>0),AS69/AR69-1,"") -> 0.3772549 | BD69: =IF(AND(ISNUMBER(BB69),ISNUMBER(BC69),BB69>0),1-BC69/BB69,"") | BH69: =IF(AND(ISNUMBER(BF69),ISNUMBER(BG69),BG69>0),BF69/BG69,"") | BM69: =IF(ISNUMBER(Q69),IF(Q69<0,"YES","no"),"") -> no | BN69: =IFERROR(IF(AND(ISNUMBER(K69),ISNUMBER(INDEX('Lift Inputs'!$H:$H,MATCH(C69,'Lift Inputs'!$C:$C,0)))),IF(K69<INDEX('Lift Inputs'!$H:$H,MATCH(C69,'Lift Inputs'!$C:$C,0)),"YES","no"),""),"")
A70: Bamboo | B70: Decolure Bamboo Sheets 6 Piece | C70: 30 | D70: Hero: rank and profit | E70: 1814 | F70: BAMPURE | G70: B0HC778XB4 | H70: B07XFP6BY2 | I70: BAMPURE 100% Rayon from Bamboo Sheets King Size - 4pc Cooling King Sheets | J70: Beatable | K70: 67.98 | L70: 99.99 | M70: =IF(AND(ISNUMBER(L70),ISNUMBER(K70),K70>0),L70/K70-1,"") -> 0.47087379 | N70: =IF(M70="","No List Price",IF(M70<=0,"At/below price",IF(M70<=0.12,"<=12% (STR zone)",IF(M70<=0.25,"12-25%",">25% (likely ignored)")))) -> >25% (likely ignored) | O70: King | P70: 90.861767 | Q70: =IF(AND(ISNUMBER(K70),ISNUMBER(P70),N(P70)>0),K70/P70-1,"") -> -0.25183053 | R70: Same size (King) | S70: 14479 | T70: 81 | U70: =IF(AND(ISNUMBER(K70),ISNUMBER(T70)),K70*T70*52/12,"") -> 23860.98 | V70: 4.4 | W70: 4095 | X70: 46307 | Y70: 40 | Z70: 43776 | AA70: =IF(ISNUMBER(Z70),(DATE(2026,10,13)-Z70)/365,"") -> 6.9369863 | AB70: 2824 | AC70: FBA | AD70: 1 | AE70: US | AF70: 0 | AG70: 0 | AH70: 158 | AI70: 67699 | AJ70: 1687 | AK70: 2026-04-01 | AL70: 83.8 | AM70: 85.2 | AN70: =IF(AND(ISNUMBER(AM70),ISNUMBER(AL70),AL70>=5),AM70/AL70,"") -> 1.0167064 | AO70: 10.4 | AP70: 24 | AQ70: =IF(AND(ISNUMBER(AP70),ISNUMBER(AO70),AO70>=5),AP70/AO70,"") -> 2.3076923 | AR70: 64.5 | AS70: 46 | AT70: =IF(AND(ISNUMBER(AS70),ISNUMBER(AR70),AR70>0),AS70/AR70-1,"") -> -0.28682171 | BD70: =IF(AND(ISNUMBER(BB70),ISNUMBER(BC70),BB70>0),1-BC70/BB70,"") | BH70: =IF(AND(ISNUMBER(BF70),ISNUMBER(BG70),BG70>0),BF70/BG70,"") | BM70: =IF(ISNUMBER(Q70),IF(Q70<0,"YES","no"),"") -> YES | BN70: =IFERROR(IF(AND(ISNUMBER(K70),ISNUMBER(INDEX('Lift Inputs'!$H:$H,MATCH(C70,'Lift Inputs'!$C:$C,0)))),IF(K70<INDEX('Lift Inputs'!$H:$H,MATCH(C70,'Lift Inputs'!$C:$C,0)),"YES","no"),""),"")
A71: Bamboo | B71: Decolure Bamboo Sheets 6 Piece | C71: 30 | D71: Hero: rank and profit | E71: 1945 | F71: BEDELITE | G71: B0GT98GVQN | H71: B0GT8Z4X5D | I71: BEDELITE Bamboo Viscose Sheet Set, Queen Size, 4 Pieces, White | J71: Beatable | K71: 84.98 | L71: 99.89 | M71: =IF(AND(ISNUMBER(L71),ISNUMBER(K71),K71>0),L71/K71-1,"") -> 0.17545305 | N71: =IF(M71="","No List Price",IF(M71<=0,"At/below price",IF(M71<=0.12,"<=12% (STR zone)",IF(M71<=0.25,"12-25%",">25% (likely ignored)")))) -> 12-25% | O71: Queen | P71: 90.683233 | Q71: =IF(AND(ISNUMBER(K71),ISNUMBER(P71),N(P71)>0),K71/P71-1,"") -> -0.062891815 | R71: Same size (Queen) | S71: 65907 | T71: 81 | U71: =IF(AND(ISNUMBER(K71),ISNUMBER(T71)),K71*T71*52/12,"") -> 29827.98 | V71: 4.5 | W71: 113 | X71: 46307 | AA71: =IF(ISNUMBER(Z71),(DATE(2026,10,13)-Z71)/365,"") | AI71: 212120 | AJ71: 1732 | AK71: 2026-04-01 | AL71: 141.2 | AM71: 114 | AN71: =IF(AND(ISNUMBER(AM71),ISNUMBER(AL71),AL71>=5),AM71/AL71,"") -> 0.80736544 | AO71: 193.2 | AP71: 145.5 | AQ71: =IF(AND(ISNUMBER(AP71),ISNUMBER(AO71),AO71>=5),AP71/AO71,"") -> 0.75310559 | AR71: 54.9 | AS71: 82.2 | AT71: =IF(AND(ISNUMBER(AS71),ISNUMBER(AR71),AR71>0),AS71/AR71-1,"") -> 0.49726776 | BD71: =IF(AND(ISNUMBER(BB71),ISNUMBER(BC71),BB71>0),1-BC71/BB71,"") | BH71: =IF(AND(ISNUMBER(BF71),ISNUMBER(BG71),BG71>0),BF71/BG71,"") | BM71: =IF(ISNUMBER(Q71),IF(Q71<0,"YES","no"),"") -> YES | BN71: =IFERROR(IF(AND(ISNUMBER(K71),ISNUMBER(INDEX('Lift Inputs'!$H:$H,MATCH(C71,'Lift Inputs'!$C:$C,0)))),IF(K71<INDEX('Lift Inputs'!$H:$H,MATCH(C71,'Lift Inputs'!$C:$C,0)),"YES","no"),""),"")
A72: Bamboo | B72: Decolure Bamboo Sheets 6 Piece | C72: 30 | D72: Hero: rank and profit | E72: 22 | F72: SONORO KATE | G72: B0F29FQLFD | H72: B0F29F1JM5 | I72: SONORO KATE 100% Viscose Derived from Bamboo_Sheets Queen Size,4PC | J72: Beatable | K72: 59.99 | M72: =IF(AND(ISNUMBER(L72),ISNUMBER(K72),K72>0),L72/K72-1,"") | N72: =IF(M72="","No List Price",IF(M72<=0,"At/below price",IF(M72<=0.12,"<=12% (STR zone)",IF(M72<=0.25,"12-25%",">25% (likely ignored)")))) -> No List Price | O72: Queen | P72: 90.683233 | Q72: =IF(AND(ISNUMBER(K72),ISNUMBER(P72),N(P72)>0),K72/P72-1,"") -> -0.33846646 | R72: Same size (Queen) | S72: 23979 | T72: 81 | U72: =IF(AND(ISNUMBER(K72),ISNUMBER(T72)),K72*T72*52/12,"") -> 21056.49 | V72: 4.5 | W72: 3911 | X72: 46307 | Y72: 42 | Z72: 45740 | AA72: =IF(ISNUMBER(Z72),(DATE(2026,10,13)-Z72)/365,"") -> 1.5561644 | AB72: 1814 | AC72: FBA | AD72: 1 | AE72: CN | AF72: 0 | AG72: 0 | AH72: 278 | AI72: 114504 | AJ72: 947 | AK72: 2026-01-01 | AL72: 431.4 | AM72: 472.5 | AN72: =IF(AND(ISNUMBER(AM72),ISNUMBER(AL72),AL72>=5),AM72/AL72,"") -> 1.0952712 | AO72: 13.8 | AP72: 16.5 | AQ72: =IF(AND(ISNUMBER(AP72),ISNUMBER(AO72),AO72>=5),AP72/AO72,"") -> 1.1956522 | AR72: 365.3 | AS72: 327.3 | AT72: =IF(AND(ISNUMBER(AS72),ISNUMBER(AR72),AR72>0),AS72/AR72-1,"") -> -0.10402409 | BD72: =IF(AND(ISNUMBER(BB72),ISNUMBER(BC72),BB72>0),1-BC72/BB72,"") | BH72: =IF(AND(ISNUMBER(BF72),ISNUMBER(BG72),BG72>0),BF72/BG72,"") | BM72: =IF(ISNUMBER(Q72),IF(Q72<0,"YES","no"),"") -> YES | BN72: =IFERROR(IF(AND(ISNUMBER(K72),ISNUMBER(INDEX('Lift Inputs'!$H:$H,MATCH(C72,'Lift Inputs'!$C:$C,0)))),IF(K72<INDEX('Lift Inputs'!$H:$H,MATCH(C72,'Lift Inputs'!$C:$C,0)),"YES","no"),""),"")
A73: Bamboo | B73: Decolure Bamboo Sheets 6 Piece | C73: 30 | D73: Hero: rank and profit | E73: 1953 | F73: Davmabcjy | G73: B0HJZNMQ5G | H73: B0GXJYQR7H | I73: 100% Organically Grown Bamboo Viscose King Sheet Set with Pockets on Side | J73: Beatable | K73: 59.99 | M73: =IF(AND(ISNUMBER(L73),ISNUMBER(K73),K73>0),L73/K73-1,"") | N73: =IF(M73="","No List Price",IF(M73<=0,"At/below price",IF(M73<=0.12,"<=12% (STR zone)",IF(M73<=0.25,"12-25%",">25% (likely ignored)")))) -> No List Price | O73: King | P73: 90.861767 | Q73: =IF(AND(ISNUMBER(K73),ISNUMBER(P73),N(P73)>0),K73/P73-1,"") -> -0.33976631 | R73: Same size (King) | S73: 205508 | T73: 35 | U73: =IF(AND(ISNUMBER(K73),ISNUMBER(T73)),K73*T73*52/12,"") -> 9098.4833 | V73: 4.2 | W73: 81 | X73: 46307 | AA73: =IF(ISNUMBER(Z73),(DATE(2026,10,13)-Z73)/365,"") | AI73: 75425 | AJ73: 1329 | AK73: 2026-04-01 | AL73: 0 | AM73: 0 | AN73: =IF(AND(ISNUMBER(AM73),ISNUMBER(AL73),AL73>=5),AM73/AL73,"") | AO73: 0 | AP73: 0 | AQ73: =IF(AND(ISNUMBER(AP73),ISNUMBER(AO73),AO73>=5),AP73/AO73,"") | AR73: 0 | AS73: 69.1 | AT73: =IF(AND(ISNUMBER(AS73),ISNUMBER(AR73),AR73>0),AS73/AR73-1,"") | BD73: =IF(AND(ISNUMBER(BB73),ISNUMBER(BC73),BB73>0),1-BC73/BB73,"") | BH73: =IF(AND(ISNUMBER(BF73),ISNUMBER(BG73),BG73>0),BF73/BG73,"") | BM73: =IF(ISNUMBER(Q73),IF(Q73<0,"YES","no"),"") -> YES | BN73: =IFERROR(IF(AND(ISNUMBER(K73),ISNUMBER(INDEX('Lift Inputs'!$H:$H,MATCH(C73,'Lift Inputs'!$C:$C,0)))),IF(K73<INDEX('Lift Inputs'!$H:$H,MATCH(C73,'Lift Inputs'!$C:$C,0)),"YES","no"),""),"")
A74: Bamboo | B74: Decolure Bamboo Sheets 6 Piece | C74: 30 | D74: Hero: rank and profit | E74: 1510 | F74: DOZ by SIJO | G74: B0DCZGYVZ9 | H74: B0F24TRXCZ | I74: Bamboo Sheets | J74: Beatable | K74: 55 | M74: =IF(AND(ISNUMBER(L74),ISNUMBER(K74),K74>0),L74/K74-1,"") | N74: =IF(M74="","No List Price",IF(M74<=0,"At/below price",IF(M74<=0.12,"<=12% (STR zone)",IF(M74<=0.25,"12-25%",">25% (likely ignored)")))) -> No List Price | P74: 90.683233 | Q74: =IF(AND(ISNUMBER(K74),ISNUMBER(P74),N(P74)>0),K74/P74-1,"") -> -0.39349317 | R74: Size unknown - vs our Queen | S74: 4051 | T74: 35 | U74: =IF(AND(ISNUMBER(K74),ISNUMBER(T74)),K74*T74*52/12,"") -> 8341.6667 | V74: 4.4 | W74: 1909 | X74: 46307 | AA74: =IF(ISNUMBER(Z74),(DATE(2026,10,13)-Z74)/365,"") | AI74: 171534 | AJ74: 2682 | AN74: =IF(AND(ISNUMBER(AM74),ISNUMBER(AL74),AL74>=5),AM74/AL74,"") | AQ74: =IF(AND(ISNUMBER(AP74),ISNUMBER(AO74),AO74>=5),AP74/AO74,"") | AT74: =IF(AND(ISNUMBER(AS74),ISNUMBER(AR74),AR74>0),AS74/AR74-1,"") | BD74: =IF(AND(ISNUMBER(BB74),ISNUMBER(BC74),BB74>0),1-BC74/BB74,"") | BH74: =IF(AND(ISNUMBER(BF74),ISNUMBER(BG74),BG74>0),BF74/BG74,"") | BM74: =IF(ISNUMBER(Q74),IF(Q74<0,"YES","no"),"") -> YES | BN74: =IFERROR(IF(AND(ISNUMBER(K74),ISNUMBER(INDEX('Lift Inputs'!$H:$H,MATCH(C74,'Lift Inputs'!$C:$C,0)))),IF(K74<INDEX('Lift Inputs'!$H:$H,MATCH(C74,'Lift Inputs'!$C:$C,0)),"YES","no"),""),"")
A75: Bamboo | B75: Decolure Bamboo Sheets 6 Piece | C75: 30 | D75: Hero: rank and profit | E75: 1819 | F75: GOKOTTA | G75: B09WV7RN1V | H75: B0BR53P7DY | I75: GOKOTTA King Bamboo Rayon Sheets Set, Silky Soft Cooling Sheets Stay Put | J75: Beatable | K75: 109 | M75: =IF(AND(ISNUMBER(L75),ISNUMBER(K75),K75>0),L75/K75-1,"") | N75: =IF(M75="","No List Price",IF(M75<=0,"At/below price",IF(M75<=0.12,"<=12% (STR zone)",IF(M75<=0.25,"12-25%",">25% (likely ignored)")))) -> No List Price | O75: King | P75: 90.861767 | Q75: =IF(AND(ISNUMBER(K75),ISNUMBER(P75),N(P75)>0),K75/P75-1,"") -> 0.19962448 | R75: Same size (King) | S75: 16154 | T75: 35 | U75: =IF(AND(ISNUMBER(K75),ISNUMBER(T75)),K75*T75*52/12,"") -> 16531.667 | V75: 4.4 | W75: 3371 | X75: 46307 | Y75: 99 | Z75: 44922 | AA75: =IF(ISNUMBER(Z75),(DATE(2026,10,13)-Z75)/365,"") -> 3.7972603 | AB75: 2972 | AC75: FBA | AD75: 1 | AE75: TH | AF75: 0 | AG75: 0 | AH75: 68 | AI75: 76017 | AJ75: 1577 | AN75: =IF(AND(ISNUMBER(AM75),ISNUMBER(AL75),AL75>=5),AM75/AL75,"") | AQ75: =IF(AND(ISNUMBER(AP75),ISNUMBER(AO75),AO75>=5),AP75/AO75,"") | AT75: =IF(AND(ISNUMBER(AS75),ISNUMBER(AR75),AR75>0),AS75/AR75-1,"") | BD75: =IF(AND(ISNUMBER(BB75),ISNUMBER(BC75),BB75>0),1-BC75/BB75,"") | BH75: =IF(AND(ISNUMBER(BF75),ISNUMBER(BG75),BG75>0),BF75/BG75,"") | BM75: =IF(ISNUMBER(Q75),IF(Q75<0,"YES","no"),"") -> no | BN75: =IFERROR(IF(AND(ISNUMBER(K75),ISNUMBER(INDEX('Lift Inputs'!$H:$H,MATCH(C75,'Lift Inputs'!$C:$C,0)))),IF(K75<INDEX('Lift Inputs'!$H:$H,MATCH(C75,'Lift Inputs'!$C:$C,0)),"YES","no"),""),"")
A76: Bamboo | B76: Decolure Bamboo Sheets 6 Piece | C76: 30 | D76: Hero: rank and profit | E76: 1816 | F76: KARISSA MAE | G76: B0GT172Y8L | H76: B0G1CSCQTB | I76: Cooling Sheets | J76: Beatable | K76: 119.99 | M76: =IF(AND(ISNUMBER(L76),ISNUMBER(K76),K76>0),L76/K76-1,"") | N76: =IF(M76="","No List Price",IF(M76<=0,"At/below price",IF(M76<=0.12,"<=12% (STR zone)",IF(M76<=0.25,"12-25%",">25% (likely ignored)")))) -> No List Price | P76: 90.683233 | Q76: =IF(AND(ISNUMBER(K76),ISNUMBER(P76),N(P76)>0),K76/P76-1,"") -> 0.32317735 | R76: Size unknown - vs our Queen | S76: 15914 | T76: 35 | U76: =IF(AND(ISNUMBER(K76),ISNUMBER(T76)),K76*T76*52/12,"") -> 18198.483 | V76: 4.3 | W76: 474 | X76: 46307 | AA76: =IF(ISNUMBER(Z76),(DATE(2026,10,13)-Z76)/365,"") | AI76: 243610 | AJ76: 3715 | AK76: 2026-04-01 | AL76: 23.4 | AM76: 49.2 | AN76: =IF(AND(ISNUMBER(AM76),ISNUMBER(AL76),AL76>=5),AM76/AL76,"") -> 2.1025641 | AO76: 45.5 | AP76: 115.2 | AQ76: =IF(AND(ISNUMBER(AP76),ISNUMBER(AO76),AO76>=5),AP76/AO76,"") -> 2.5318681 | AR76: 23.6 | AS76: 2.9 | AT76: =IF(AND(ISNUMBER(AS76),ISNUMBER(AR76),AR76>0),AS76/AR76-1,"") -> -0.87711864 | BD76: =IF(AND(ISNUMBER(BB76),ISNUMBER(BC76),BB76>0),1-BC76/BB76,"") | BH76: =IF(AND(ISNUMBER(BF76),ISNUMBER(BG76),BG76>0),BF76/BG76,"") | BM76: =IF(ISNUMBER(Q76),IF(Q76<0,"YES","no"),"") -> no | BN76: =IFERROR(IF(AND(ISNUMBER(K76),ISNUMBER(INDEX('Lift Inputs'!$H:$H,MATCH(C76,'Lift Inputs'!$C:$C,0)))),IF(K76<INDEX('Lift Inputs'!$H:$H,MATCH(C76,'Lift Inputs'!$C:$C,0)),"YES","no"),""),"")
A77: Bamboo | B77: Decolure Bamboo Sheets 6 Piece | C77: 30 | D77: Hero: rank and profit | E77: 1943 | F77: Pillcase | G77: B0H1GGHHVN | H77: B0HFZQRXXQ | I77: 100% Real Bamboo Viscose & Lyocell Tencel Sheets Set Queen Size | Breathable & C | J77: Beatable | K77: 79 | L77: 109 | M77: =IF(AND(ISNUMBER(L77),ISNUMBER(K77),K77>0),L77/K77-1,"") -> 0.37974684 | N77: =IF(M77="","No List Price",IF(M77<=0,"At/below price",IF(M77<=0.12,"<=12% (STR zone)",IF(M77<=0.25,"12-25%",">25% (likely ignored)")))) -> >25% (likely ignored) | O77: Queen | P77: 90.683233 | Q77: =IF(AND(ISNUMBER(K77),ISNUMBER(P77),N(P77)>0),K77/P77-1,"") -> -0.12883565 | R77: Same size (Queen) | S77: 28003 | T77: 35 | U77: =IF(AND(ISNUMBER(K77),ISNUMBER(T77)),K77*T77*52/12,"") -> 11981.667 | V77: 4.8 | W77: 279 | X77: 46307 | AA77: =IF(ISNUMBER(Z77),(DATE(2026,10,13)-Z77)/365,"") | AI77: 216953 | AJ77: 1218 | AN77: =IF(AND(ISNUMBER(AM77),ISNUMBER(AL77),AL77>=5),AM77/AL77,"") | AQ77: =IF(AND(ISNUMBER(AP77),ISNUMBER(AO77),AO77>=5),AP77/AO77,"") | AT77: =IF(AND(ISNUMBER(AS77),ISNUMBER(AR77),AR77>0),AS77/AR77-1,"") | BD77: =IF(AND(ISNUMBER(BB77),ISNUMBER(BC77),BB77>0),1-BC77/BB77,"") | BH77: =IF(AND(ISNUMBER(BF77),ISNUMBER(BG77),BG77>0),BF77/BG77,"") | BM77: =IF(ISNUMBER(Q77),IF(Q77<0,"YES","no"),"") -> YES | BN77: =IFERROR(IF(AND(ISNUMBER(K77),ISNUMBER(INDEX('Lift Inputs'!$H:$H,MATCH(C77,'Lift Inputs'!$C:$C,0)))),IF(K77<INDEX('Lift Inputs'!$H:$H,MATCH(C77,'Lift Inputs'!$C:$C,0)),"YES","no"),""),"")
A78: Bamboo | B78: Decolure Bamboo Sheets 6 Piece | C78: 30 | D78: Hero: rank and profit | E78: 1955 | F78: Bamboo Bay | G78: B0DLD8982V | H78: B08M9QK14J | I78: Bamboo Bay 4 Piece Queen Size Sheet Set, 100% Viscose Made from Bamboo, Breathab | J78: Beatable | K78: 89.98 | M78: =IF(AND(ISNUMBER(L78),ISNUMBER(K78),K78>0),L78/K78-1,"") | N78: =IF(M78="","No List Price",IF(M78<=0,"At/below price",IF(M78<=0.12,"<=12% (STR zone)",IF(M78<=0.25,"12-25%",">25% (likely ignored)")))) -> No List Price | O78: Queen | P78: 90.683233 | Q78: =IF(AND(ISNUMBER(K78),ISNUMBER(P78),N(P78)>0),K78/P78-1,"") -> -0.0077548303 | R78: Same size (Queen) | S78: 263209 | T78: 18 | U78: =IF(AND(ISNUMBER(K78),ISNUMBER(T78)),K78*T78*52/12,"") -> 7018.44 | V78: 4.4 | W78: 739 | X78: 46307 | AA78: =IF(ISNUMBER(Z78),(DATE(2026,10,13)-Z78)/365,"") | AI78: 67928 | AJ78: 1037 | AK78: 2026-04-01 | AL78: 70.2 | AM78: 51.5 | AN78: =IF(AND(ISNUMBER(AM78),ISNUMBER(AL78),AL78>=5),AM78/AL78,"") -> 0.73361823 | AO78: 0 | AP78: 0 | AQ78: =IF(AND(ISNUMBER(AP78),ISNUMBER(AO78),AO78>=5),AP78/AO78,"") | AR78: 34.4 | AS78: 24.5 | AT78: =IF(AND(ISNUMBER(AS78),ISNUMBER(AR78),AR78>0),AS78/AR78-1,"") -> -0.2877907 | BD78: =IF(AND(ISNUMBER(BB78),ISNUMBER(BC78),BB78>0),1-BC78/BB78,"") | BH78: =IF(AND(ISNUMBER(BF78),ISNUMBER(BG78),BG78>0),BF78/BG78,"") | BM78: =IF(ISNUMBER(Q78),IF(Q78<0,"YES","no"),"") -> YES | BN78: =IFERROR(IF(AND(ISNUMBER(K78),ISNUMBER(INDEX('Lift Inputs'!$H:$H,MATCH(C78,'Lift Inputs'!$C:$C,0)))),IF(K78<INDEX('Lift Inputs'!$H:$H,MATCH(C78,'Lift Inputs'!$C:$C,0)),"YES","no"),""),"")
A79: Bamboo | B79: Decolure Bamboo Sheets 6 Piece | C79: 30 | D79: Hero: rank and profit | E79: 1950 | F79: California Design Den | G79: B0HFBJPD56 | H79: B0GWHPJ9SD | I79: California Design Den 100% Viscose from Bamboo Sheets Queen, Dark Olive | J79: Beatable | K79: 89.99 | M79: =IF(AND(ISNUMBER(L79),ISNUMBER(K79),K79>0),L79/K79-1,"") | N79: =IF(M79="","No List Price",IF(M79<=0,"At/below price",IF(M79<=0.12,"<=12% (STR zone)",IF(M79<=0.25,"12-25%",">25% (likely ignored)")))) -> No List Price | O79: Queen | P79: 90.683233 | Q79: =IF(AND(ISNUMBER(K79),ISNUMBER(P79),N(P79)>0),K79/P79-1,"") -> -0.0076445563 | R79: Same size (Queen) | S79: 21237 | T79: 18 | U79: =IF(AND(ISNUMBER(K79),ISNUMBER(T79)),K79*T79*52/12,"") -> 7019.22 | V79: 4.6 | W79: 76 | X79: 46307 | AA79: =IF(ISNUMBER(Z79),(DATE(2026,10,13)-Z79)/365,"") | AI79: 103642 | AJ79: 2019 | AK79: 2026-04-01 | AL79: 0 | AM79: 0 | AN79: =IF(AND(ISNUMBER(AM79),ISNUMBER(AL79),AL79>=5),AM79/AL79,"") | AO79: 0 | AP79: 0 | AQ79: =IF(AND(ISNUMBER(AP79),ISNUMBER(AO79),AO79>=5),AP79/AO79,"") | AR79: 0 | AS79: 29.8 | AT79: =IF(AND(ISNUMBER(AS79),ISNUMBER(AR79),AR79>0),AS79/AR79-1,"") | BD79: =IF(AND(ISNUMBER(BB79),ISNUMBER(BC79),BB79>0),1-BC79/BB79,"") | BH79: =IF(AND(ISNUMBER(BF79),ISNUMBER(BG79),BG79>0),BF79/BG79,"") | BM79: =IF(ISNUMBER(Q79),IF(Q79<0,"YES","no"),"") -> YES | BN79: =IFERROR(IF(AND(ISNUMBER(K79),ISNUMBER(INDEX('Lift Inputs'!$H:$H,MATCH(C79,'Lift Inputs'!$C:$C,0)))),IF(K79<INDEX('Lift Inputs'!$H:$H,MATCH(C79,'Lift Inputs'!$C:$C,0)),"YES","no"),""),"")
A80: Bamboo | B80: Decolure Bamboo Sheets 6 Piece | C80: 30 | D80: Hero: rank and profit | E80: 1948 | F80: Pillcase | G80: B0HK71WHZW | H80: B0H1BWY4MD | I80: 100% Real Bamboo Viscose & Lyocell Tencel Sheets Set Queen Size | Breathable & C | J80: Beatable | K80: 99 | M80: =IF(AND(ISNUMBER(L80),ISNUMBER(K80),K80>0),L80/K80-1,"") | N80: =IF(M80="","No List Price",IF(M80<=0,"At/below price",IF(M80<=0.12,"<=12% (STR zone)",IF(M80<=0.25,"12-25%",">25% (likely ignored)")))) -> No List Price | O80: Queen | P80: 90.683233 | Q80: =IF(AND(ISNUMBER(K80),ISNUMBER(P80),N(P80)>0),K80/P80-1,"") -> 0.091712289 | R80: Same size (Queen) | S80: 38116 | T80: 18 | U80: =IF(AND(ISNUMBER(K80),ISNUMBER(T80)),K80*T80*52/12,"") -> 7722 | V80: 4.9 | W80: 201 | X80: 46307 | AA80: =IF(ISNUMBER(Z80),(DATE(2026,10,13)-Z80)/365,"") | AI80: 116001 | AJ80: 1002 | AK80: 2026-04-01 | AL80: 0 | AM80: 0 | AN80: =IF(AND(ISNUMBER(AM80),ISNUMBER(AL80),AL80>=5),AM80/AL80,"") | AO80: 0 | AP80: 0 | AQ80: =IF(AND(ISNUMBER(AP80),ISNUMBER(AO80),AO80>=5),AP80/AO80,"") | AR80: 0 | AS80: 21.5 | AT80: =IF(AND(ISNUMBER(AS80),ISNUMBER(AR80),AR80>0),AS80/AR80-1,"") | BD80: =IF(AND(ISNUMBER(BB80),ISNUMBER(BC80),BB80>0),1-BC80/BB80,"") | BH80: =IF(AND(ISNUMBER(BF80),ISNUMBER(BG80),BG80>0),BF80/BG80,"") | BM80: =IF(ISNUMBER(Q80),IF(Q80<0,"YES","no"),"") -> no | BN80: =IFERROR(IF(AND(ISNUMBER(K80),ISNUMBER(INDEX('Lift Inputs'!$H:$H,MATCH(C80,'Lift Inputs'!$C:$C,0)))),IF(K80<INDEX('Lift Inputs'!$H:$H,MATCH(C80,'Lift Inputs'!$C:$C,0)),"YES","no"),""),"")
A81: Bamboo | B81: Decolure Bamboo Sheets 6 Piece | C81: 30 | D81: Hero: rank and profit | E81: 1820 | F81: Shilucheng | G81: B098JT1RF2 | H81: B098JT1RF2 | I81: Shilucheng 4 Piece King Sheet Sets, Cooling Sheets, Dark Grey | J81: Beatable | K81: 37.9 | M81: =IF(AND(ISNUMBER(L81),ISNUMBER(K81),K81>0),L81/K81-1,"") | N81: =IF(M81="","No List Price",IF(M81<=0,"At/below price",IF(M81<=0.12,"<=12% (STR zone)",IF(M81<=0.25,"12-25%",">25% (likely ignored)")))) -> No List Price | O81: King | P81: 90.861767 | Q81: =IF(AND(ISNUMBER(K81),ISNUMBER(P81),N(P81)>0),K81/P81-1,"") -> -0.58288287 | R81: Same size (King) | S81: 9187 | T81: 18 | U81: =IF(AND(ISNUMBER(K81),ISNUMBER(T81)),K81*T81*52/12,"") -> 2956.2 | V81: 4.3 | W81: 24333 | X81: 46286 | Y81: 100 | Z81: 44379 | AA81: =IF(ISNUMBER(Z81),(DATE(2026,10,13)-Z81)/365,"") -> 5.2849315 | AB81: 5599 | AC81: FBA | AD81: 1 | AE81: CN | AF81: 0 | AG81: 0 | AH81: 316 | AI81: 23320 | AJ81: 859 | AK81: 2026-04-01 | AL81: 0.1 | AM81: 2.5 | AN81: =IF(AND(ISNUMBER(AM81),ISNUMBER(AL81),AL81>=5),AM81/AL81,"") | AO81: 0 | AP81: 0 | AQ81: =IF(AND(ISNUMBER(AP81),ISNUMBER(AO81),AO81>=5),AP81/AO81,"") | AR81: 22.3 | AS81: 1 | AT81: =IF(AND(ISNUMBER(AS81),ISNUMBER(AR81),AR81>0),AS81/AR81-1,"") -> -0.95515695 | BD81: =IF(AND(ISNUMBER(BB81),ISNUMBER(BC81),BB81>0),1-BC81/BB81,"") | BH81: =IF(AND(ISNUMBER(BF81),ISNUMBER(BG81),BG81>0),BF81/BG81,"") | BM81: =IF(ISNUMBER(Q81),IF(Q81<0,"YES","no"),"") -> YES | BN81: =IFERROR(IF(AND(ISNUMBER(K81),ISNUMBER(INDEX('Lift Inputs'!$H:$H,MATCH(C81,'Lift Inputs'!$C:$C,0)))),IF(K81<INDEX('Lift Inputs'!$H:$H,MATCH(C81,'Lift Inputs'!$C:$C,0)),"YES","no"),""),"")
A82: Bamboo | B82: Decolure Bamboo Sheets 6 Piece | C82: 30 | D82: Hero: rank and profit | E82: 1944 | F82: TWK | G82: B0HHQG3RSW | H82: B0G1N8QS55 | I82: TWK Real 100% Viscose Derived from Bamboo Sheets Set Queen Size, Cooling & Silky | J82: Beatable | K82: 65 | L82: 79 | M82: =IF(AND(ISNUMBER(L82),ISNUMBER(K82),K82>0),L82/K82-1,"") -> 0.21538462 | N82: =IF(M82="","No List Price",IF(M82<=0,"At/below price",IF(M82<=0.12,"<=12% (STR zone)",IF(M82<=0.25,"12-25%",">25% (likely ignored)")))) -> 12-25% | O82: Queen | P82: 90.683233 | Q82: =IF(AND(ISNUMBER(K82),ISNUMBER(P82),N(P82)>0),K82/P82-1,"") -> -0.2832192 | R82: Same size (Queen) | S82: 196488 | T82: 18 | U82: =IF(AND(ISNUMBER(K82),ISNUMBER(T82)),K82*T82*52/12,"") -> 5070 | V82: 4.9 | W82: 121 | X82: 46307 | AA82: =IF(ISNUMBER(Z82),(DATE(2026,10,13)-Z82)/365,"") | AI82: 82471 | AJ82: 905 | AK82: 2026-04-01 | AL82: 2.2 | AM82: 2 | AN82: =IF(AND(ISNUMBER(AM82),ISNUMBER(AL82),AL82>=5),AM82/AL82,"") | AO82: 0 | AP82: 0 | AQ82: =IF(AND(ISNUMBER(AP82),ISNUMBER(AO82),AO82>=5),AP82/AO82,"") | AR82: 2 | AS82: 93.2 | AT82: =IF(AND(ISNUMBER(AS82),ISNUMBER(AR82),AR82>0),AS82/AR82-1,"") -> 45.6 | BD82: =IF(AND(ISNUMBER(BB82),ISNUMBER(BC82),BB82>0),1-BC82/BB82,"") | BH82: =IF(AND(ISNUMBER(BF82),ISNUMBER(BG82),BG82>0),BF82/BG82,"") | BM82: =IF(ISNUMBER(Q82),IF(Q82<0,"YES","no"),"") -> YES | BN82: =IFERROR(IF(AND(ISNUMBER(K82),ISNUMBER(INDEX('Lift Inputs'!$H:$H,MATCH(C82,'Lift Inputs'!$C:$C,0)))),IF(K82<INDEX('Lift Inputs'!$H:$H,MATCH(C82,'Lift Inputs'!$C:$C,0)),"YES","no"),""),"")
A83: Bamboo | B83: Decolure Bamboo Sheets 6 Piece | C83: 30 | D83: Hero: rank and profit | E83: 7 | F83: BC BELLA COTERIE | G83: B0GKBNZ8TC | H83: B0G674ZDTV | I83: 4 Piece Bamboo Sheet Set | J83: Beatable | K83: 129.99 | M83: =IF(AND(ISNUMBER(L83),ISNUMBER(K83),K83>0),L83/K83-1,"") | N83: =IF(M83="","No List Price",IF(M83<=0,"At/below price",IF(M83<=0.12,"<=12% (STR zone)",IF(M83<=0.25,"12-25%",">25% (likely ignored)")))) -> No List Price | P83: 90.683233 | Q83: =IF(AND(ISNUMBER(K83),ISNUMBER(P83),N(P83)>0),K83/P83-1,"") -> 0.43345132 | R83: Size unknown - vs our Queen | S83: 1577 | T83: 5 | U83: =IF(AND(ISNUMBER(K83),ISNUMBER(T83)),K83*T83*52/12,"") -> 2816.45 | V83: 4.4 | W83: 5652 | X83: 46223 | AA83: =IF(ISNUMBER(Z83),(DATE(2026,10,13)-Z83)/365,"") | AN83: =IF(AND(ISNUMBER(AM83),ISNUMBER(AL83),AL83>=5),AM83/AL83,"") | AQ83: =IF(AND(ISNUMBER(AP83),ISNUMBER(AO83),AO83>=5),AP83/AO83,"") | AT83: =IF(AND(ISNUMBER(AS83),ISNUMBER(AR83),AR83>0),AS83/AR83-1,"") | BD83: =IF(AND(ISNUMBER(BB83),ISNUMBER(BC83),BB83>0),1-BC83/BB83,"") | BH83: =IF(AND(ISNUMBER(BF83),ISNUMBER(BG83),BG83>0),BF83/BG83,"") | BM83: =IF(ISNUMBER(Q83),IF(Q83<0,"YES","no"),"") -> no | BN83: =IFERROR(IF(AND(ISNUMBER(K83),ISNUMBER(INDEX('Lift Inputs'!$H:$H,MATCH(C83,'Lift Inputs'!$C:$C,0)))),IF(K83<INDEX('Lift Inputs'!$H:$H,MATCH(C83,'Lift Inputs'!$C:$C,0)),"YES","no"),""),"")
A84: Bamboo | B84: Decolure Bamboo Sheets 6 Piece | C84: 30 | D84: Hero: rank and profit | E84: 1954 | F84: Tafts | G84: B0D34K3FB9 | H84: B07YSVNCVT | I84: Bamboo Sheets Queen Size, 100% Pure Viscose derived from Bamboo Bed Sheet Set, L | J84: Beatable | K84: 104.99 | M84: =IF(AND(ISNUMBER(L84),ISNUMBER(K84),K84>0),L84/K84-1,"") | N84: =IF(M84="","No List Price",IF(M84<=0,"At/below price",IF(M84<=0.12,"<=12% (STR zone)",IF(M84<=0.25,"12-25%",">25% (likely ignored)")))) -> No List Price | O84: Queen | P84: 90.683233 | Q84: =IF(AND(ISNUMBER(K84),ISNUMBER(P84),N(P84)>0),K84/P84-1,"") -> 0.1577664 | R84: Same size (Queen) | S84: 184749 | T84: 5 | U84: =IF(AND(ISNUMBER(K84),ISNUMBER(T84)),K84*T84*52/12,"") -> 2274.7833 | V84: 4.5 | W84: 3184 | X84: 46307 | AA84: =IF(ISNUMBER(Z84),(DATE(2026,10,13)-Z84)/365,"") | AI84: 11787 | AJ84: 302 | AN84: =IF(AND(ISNUMBER(AM84),ISNUMBER(AL84),AL84>=5),AM84/AL84,"") | AQ84: =IF(AND(ISNUMBER(AP84),ISNUMBER(AO84),AO84>=5),AP84/AO84,"") | AT84: =IF(AND(ISNUMBER(AS84),ISNUMBER(AR84),AR84>0),AS84/AR84-1,"") | BD84: =IF(AND(ISNUMBER(BB84),ISNUMBER(BC84),BB84>0),1-BC84/BB84,"") | BH84: =IF(AND(ISNUMBER(BF84),ISNUMBER(BG84),BG84>0),BF84/BG84,"") | BM84: =IF(ISNUMBER(Q84),IF(Q84<0,"YES","no"),"") -> no | BN84: =IFERROR(IF(AND(ISNUMBER(K84),ISNUMBER(INDEX('Lift Inputs'!$H:$H,MATCH(C84,'Lift Inputs'!$C:$C,0)))),IF(K84<INDEX('Lift Inputs'!$H:$H,MATCH(C84,'Lift Inputs'!$C:$C,0)),"YES","no"),""),"")
A85: Bamboo | B85: Decolure Bamboo Sheets 6 Piece | C85: 30 | D85: Hero: rank and profit | E85: 1949 | F85: TWK | G85: B0HHRR4XGX | H85: B0HHRR4XGX | I85: TWK Real 100% Viscose Derived from Bamboo Sheets Set Queen Size, Cooling & Silky | J85: Beatable | K85: 105 | M85: =IF(AND(ISNUMBER(L85),ISNUMBER(K85),K85>0),L85/K85-1,"") | N85: =IF(M85="","No List Price",IF(M85<=0,"At/below price",IF(M85<=0.12,"<=12% (STR zone)",IF(M85<=0.25,"12-25%",">25% (likely ignored)")))) -> No List Price | O85: Queen | P85: 90.683233 | Q85: =IF(AND(ISNUMBER(K85),ISNUMBER(P85),N(P85)>0),K85/P85-1,"") -> 0.15787667 | R85: Same size (Queen) | T85: 5 | U85: =IF(AND(ISNUMBER(K85),ISNUMBER(T85)),K85*T85*52/12,"") -> 2275 | V85: 4.5 | X85: 46307 | AA85: =IF(ISNUMBER(Z85),(DATE(2026,10,13)-Z85)/365,"") | AI85: 30066 | AJ85: 74 | AN85: =IF(AND(ISNUMBER(AM85),ISNUMBER(AL85),AL85>=5),AM85/AL85,"") | AQ85: =IF(AND(ISNUMBER(AP85),ISNUMBER(AO85),AO85>=5),AP85/AO85,"") | AT85: =IF(AND(ISNUMBER(AS85),ISNUMBER(AR85),AR85>0),AS85/AR85-1,"") | BD85: =IF(AND(ISNUMBER(BB85),ISNUMBER(BC85),BB85>0),1-BC85/BB85,"") | BH85: =IF(AND(ISNUMBER(BF85),ISNUMBER(BG85),BG85>0),BF85/BG85,"") | BM85: =IF(ISNUMBER(Q85),IF(Q85<0,"YES","no"),"") -> no | BN85: =IFERROR(IF(AND(ISNUMBER(K85),ISNUMBER(INDEX('Lift Inputs'!$H:$H,MATCH(C85,'Lift Inputs'!$C:$C,0)))),IF(K85<INDEX('Lift Inputs'!$H:$H,MATCH(C85,'Lift Inputs'!$C:$C,0)),"YES","no"),""),"")
A86: Bamboo | B86: Decolure Bamboo Sheets 6 Piece | C86: 30 | D86: Hero: rank and profit | E86: 1516 | F86: AiAngu | G86: B0H3KP6R9B | H86: B0GX15Y7TT | I86: Bamboo Sheets | J86: Poor | K86: 74.99 | L86: 79.99 | M86: =IF(AND(ISNUMBER(L86),ISNUMBER(K86),K86>0),L86/K86-1,"") -> 0.066675557 | N86: =IF(M86="","No List Price",IF(M86<=0,"At/below price",IF(M86<=0.12,"<=12% (STR zone)",IF(M86<=0.25,"12-25%",">25% (likely ignored)")))) -> <=12% (STR zone) | P86: 90.683233 | Q86: =IF(AND(ISNUMBER(K86),ISNUMBER(P86),N(P86)>0),K86/P86-1,"") -> -0.17305551 | R86: Size unknown - vs our Queen | S86: 39296 | T86: 81 | U86: =IF(AND(ISNUMBER(K86),ISNUMBER(T86)),K86*T86*52/12,"") -> 26321.49 | V86: 4.6 | W86: 121 | X86: 46307 | AA86: =IF(ISNUMBER(Z86),(DATE(2026,10,13)-Z86)/365,"") | AN86: =IF(AND(ISNUMBER(AM86),ISNUMBER(AL86),AL86>=5),AM86/AL86,"") | AQ86: =IF(AND(ISNUMBER(AP86),ISNUMBER(AO86),AO86>=5),AP86/AO86,"") | AT86: =IF(AND(ISNUMBER(AS86),ISNUMBER(AR86),AR86>0),AS86/AR86-1,"") | BD86: =IF(AND(ISNUMBER(BB86),ISNUMBER(BC86),BB86>0),1-BC86/BB86,"") | BH86: =IF(AND(ISNUMBER(BF86),ISNUMBER(BG86),BG86>0),BF86/BG86,"") | BM86: =IF(ISNUMBER(Q86),IF(Q86<0,"YES","no"),"") -> YES | BN86: =IFERROR(IF(AND(ISNUMBER(K86),ISNUMBER(INDEX('Lift Inputs'!$H:$H,MATCH(C86,'Lift Inputs'!$C:$C,0)))),IF(K86<INDEX('Lift Inputs'!$H:$H,MATCH(C86,'Lift Inputs'!$C:$C,0)),"YES","no"),""),"")
A87: Bamboo | B87: Decolure Bamboo Sheets 6 Piece | C87: 30 | D87: Hero: rank and profit | E87: 1519 | F87: Cariloha | G87: B0F89K7BXJ | H87: B0DJV1K332 | I87: Cariloha Aloha Soft Bamboo Viscose Sheet Set - Natural - Queen | J87: Poor | K87: 107.1 | M87: =IF(AND(ISNUMBER(L87),ISNUMBER(K87),K87>0),L87/K87-1,"") | N87: =IF(M87="","No List Price",IF(M87<=0,"At/below price",IF(M87<=0.12,"<=12% (STR zone)",IF(M87<=0.25,"12-25%",">25% (likely ignored)")))) -> No List Price | O87: Queen | P87: 90.683233 | Q87: =IF(AND(ISNUMBER(K87),ISNUMBER(P87),N(P87)>0),K87/P87-1,"") -> 0.1810342 | R87: Same size (Queen) | S87: 15882 | T87: 81 | U87: =IF(AND(ISNUMBER(K87),ISNUMBER(T87)),K87*T87*52/12,"") -> 37592.1 | V87: 4.4 | W87: 426 | X87: 46307 | Y87: 35 | Z87: 45575 | AA87: =IF(ISNUMBER(Z87),(DATE(2026,10,13)-Z87)/365,"") -> 2.0082192 | AB87: 2442 | AC87: FBA | AD87: 1 | AE87: US | AF87: 0 | AG87: 0 | AH87: 231 | AN87: =IF(AND(ISNUMBER(AM87),ISNUMBER(AL87),AL87>=5),AM87/AL87,"") | AQ87: =IF(AND(ISNUMBER(AP87),ISNUMBER(AO87),AO87>=5),AP87/AO87,"") | AT87: =IF(AND(ISNUMBER(AS87),ISNUMBER(AR87),AR87>0),AS87/AR87-1,"") | BD87: =IF(AND(ISNUMBER(BB87),ISNUMBER(BC87),BB87>0),1-BC87/BB87,"") | BH87: =IF(AND(ISNUMBER(BF87),ISNUMBER(BG87),BG87>0),BF87/BG87,"") | BM87: =IF(ISNUMBER(Q87),IF(Q87<0,"YES","no"),"") -> no | BN87: =IFERROR(IF(AND(ISNUMBER(K87),ISNUMBER(INDEX('Lift Inputs'!$H:$H,MATCH(C87,'Lift Inputs'!$C:$C,0)))),IF(K87<INDEX('Lift Inputs'!$H:$H,MATCH(C87,'Lift Inputs'!$C:$C,0)),"YES","no"),""),"")
A88: Bamboo | B88: Decolure Bamboo Sheets 6 Piece | C88: 30 | D88: Hero: rank and profit | E88: 1508 | F88: ACCURATEX | G88: B0GMGSMLQ1 | H88: B09PYB9C45 | I88: ACCURATEX Cooling Sheets for Hot Sleepers, King Size, Grey | J88: Poor | K88: 69.99 | M88: =IF(AND(ISNUMBER(L88),ISNUMBER(K88),K88>0),L88/K88-1,"") | N88: =IF(M88="","No List Price",IF(M88<=0,"At/below price",IF(M88<=0.12,"<=12% (STR zone)",IF(M88<=0.25,"12-25%",">25% (likely ignored)")))) -> No List Price | O88: King | P88: 90.861767 | Q88: =IF(AND(ISNUMBER(K88),ISNUMBER(P88),N(P88)>0),K88/P88-1,"") -> -0.22970902 | R88: Same size (King) | S88: 33423 | T88: 35 | U88: =IF(AND(ISNUMBER(K88),ISNUMBER(T88)),K88*T88*52/12,"") -> 10615.15 | V88: 4.4 | W88: 1040 | X88: 46307 | Y88: 51 | Z88: 44681 | AA88: =IF(ISNUMBER(Z88),(DATE(2026,10,13)-Z88)/365,"") -> 4.4575342 | AB88: 1349 | AC88: FBA | AD88: 1 | AE88: CN | AF88: 0 | AG88: 0 | AH88: 152 | AN88: =IF(AND(ISNUMBER(AM88),ISNUMBER(AL88),AL88>=5),AM88/AL88,"") | AQ88: =IF(AND(ISNUMBER(AP88),ISNUMBER(AO88),AO88>=5),AP88/AO88,"") | AT88: =IF(AND(ISNUMBER(AS88),ISNUMBER(AR88),AR88>0),AS88/AR88-1,"") | BD88: =IF(AND(ISNUMBER(BB88),ISNUMBER(BC88),BB88>0),1-BC88/BB88,"") | BH88: =IF(AND(ISNUMBER(BF88),ISNUMBER(BG88),BG88>0),BF88/BG88,"") | BM88: =IF(ISNUMBER(Q88),IF(Q88<0,"YES","no"),"") -> YES | BN88: =IFERROR(IF(AND(ISNUMBER(K88),ISNUMBER(INDEX('Lift Inputs'!$H:$H,MATCH(C88,'Lift Inputs'!$C:$C,0)))),IF(K88<INDEX('Lift Inputs'!$H:$H,MATCH(C88,'Lift Inputs'!$C:$C,0)),"YES","no"),""),"")
A89: Bamboo | B89: Decolure Bamboo Sheets 6 Piece | C89: 30 | D89: Hero: rank and profit | E89: 31 | F89: Cozy Earth | G89: B0DSQ9V4ML | H89: B0F22JR4S8 | I89: Cozy Earth Luxury Bed Sheet Set, 100% Viscose from Bamboo Fabric | J89: Poor | K89: 328 | M89: =IF(AND(ISNUMBER(L89),ISNUMBER(K89),K89>0),L89/K89-1,"") | N89: =IF(M89="","No List Price",IF(M89<=0,"At/below price",IF(M89<=0.12,"<=12% (STR zone)",IF(M89<=0.25,"12-25%",">25% (likely ignored)")))) -> No List Price | P89: 90.683233 | Q89: =IF(AND(ISNUMBER(K89),ISNUMBER(P89),N(P89)>0),K89/P89-1,"") -> 2.6169862 | R89: Size unknown - vs our Queen | S89: 45709 | T89: 35 | U89: =IF(AND(ISNUMBER(K89),ISNUMBER(T89)),K89*T89*52/12,"") -> 49746.667 | V89: 3.9 | W89: 425 | X89: 46307 | Y89: 54 | Z89: 41624 | AA89: =IF(ISNUMBER(Z89),(DATE(2026,10,13)-Z89)/365,"") -> 12.832877 | AB89: 875 | AC89: FBA | AD89: 2 | AE89: US | AF89: 0 | AG89: 0 | AH89: 93 | AN89: =IF(AND(ISNUMBER(AM89),ISNUMBER(AL89),AL89>=5),AM89/AL89,"") | AQ89: =IF(AND(ISNUMBER(AP89),ISNUMBER(AO89),AO89>=5),AP89/AO89,"") | AT89: =IF(AND(ISNUMBER(AS89),ISNUMBER(AR89),AR89>0),AS89/AR89-1,"") | BD89: =IF(AND(ISNUMBER(BB89),ISNUMBER(BC89),BB89>0),1-BC89/BB89,"") | BH89: =IF(AND(ISNUMBER(BF89),ISNUMBER(BG89),BG89>0),BF89/BG89,"") | BM89: =IF(ISNUMBER(Q89),IF(Q89<0,"YES","no"),"") -> no | BN89: =IFERROR(IF(AND(ISNUMBER(K89),ISNUMBER(INDEX('Lift Inputs'!$H:$H,MATCH(C89,'Lift Inputs'!$C:$C,0)))),IF(K89<INDEX('Lift Inputs'!$H:$H,MATCH(C89,'Lift Inputs'!$C:$C,0)),"YES","no"),""),"")
A90: Bamboo | B90: Decolure Bamboo Sheets 6 Piece | C90: 30 | D90: Hero: rank and profit | E90: 1515 | F90: DREAMCARE | G90: B0DVZFLVMG | H90: B0CF2MND41 | I90: DREAMCARE 100% Rayon Bamboo Sheets King Size - 4pc Cooling Sheets King Size | J90: Poor | K90: 46.74 | L90: 59.99 | M90: =IF(AND(ISNUMBER(L90),ISNUMBER(K90),K90>0),L90/K90-1,"") -> 0.2834831 | N90: =IF(M90="","No List Price",IF(M90<=0,"At/below price",IF(M90<=0.12,"<=12% (STR zone)",IF(M90<=0.25,"12-25%",">25% (likely ignored)")))) -> >25% (likely ignored) | O90: King | P90: 90.861767 | Q90: =IF(AND(ISNUMBER(K90),ISNUMBER(P90),N(P90)>0),K90/P90-1,"") -> -0.48559222 | R90: Same size (King) | S90: 37217 | T90: 35 | U90: =IF(AND(ISNUMBER(K90),ISNUMBER(T90)),K90*T90*52/12,"") -> 7088.9 | V90: 4.5 | W90: 2261 | X90: 46307 | Y90: 30 | Z90: 45146 | AA90: =IF(ISNUMBER(Z90),(DATE(2026,10,13)-Z90)/365,"") -> 3.1835616 | AB90: 1260 | AC90: FBA | AD90: 2 | AE90: US | AF90: 0 | AG90: 0 | AH90: 222 | AN90: =IF(AND(ISNUMBER(AM90),ISNUMBER(AL90),AL90>=5),AM90/AL90,"") | AQ90: =IF(AND(ISNUMBER(AP90),ISNUMBER(AO90),AO90>=5),AP90/AO90,"") | AT90: =IF(AND(ISNUMBER(AS90),ISNUMBER(AR90),AR90>0),AS90/AR90-1,"") | BD90: =IF(AND(ISNUMBER(BB90),ISNUMBER(BC90),BB90>0),1-BC90/BB90,"") | BH90: =IF(AND(ISNUMBER(BF90),ISNUMBER(BG90),BG90>0),BF90/BG90,"") | BM90: =IF(ISNUMBER(Q90),IF(Q90<0,"YES","no"),"") -> YES | BN90: =IFERROR(IF(AND(ISNUMBER(K90),ISNUMBER(INDEX('Lift Inputs'!$H:$H,MATCH(C90,'Lift Inputs'!$C:$C,0)))),IF(K90<INDEX('Lift Inputs'!$H:$H,MATCH(C90,'Lift Inputs'!$C:$C,0)),"YES","no"),""),"")
A91: Bamboo | B91: Decolure Bamboo Sheets 6 Piece | C91: 30 | D91: Hero: rank and profit | E91: 32 | F91: HOT SLEEPER SHEETS | G91: B0DM3GDCTR | H91: B0D3XQM7DL | I91: Cooling Sheets Set Queen Size, Viscose Derived from Bamboo for Hot Sleepers | De | J91: Poor | K91: 51.29 | L91: 62.99 | M91: =IF(AND(ISNUMBER(L91),ISNUMBER(K91),K91>0),L91/K91-1,"") -> 0.22811464 | N91: =IF(M91="","No List Price",IF(M91<=0,"At/below price",IF(M91<=0.12,"<=12% (STR zone)",IF(M91<=0.25,"12-25%",">25% (likely ignored)")))) -> 12-25% | O91: Queen | P91: 90.683233 | Q91: =IF(AND(ISNUMBER(K91),ISNUMBER(P91),N(P91)>0),K91/P91-1,"") -> -0.43440481 | R91: Same size (Queen) | S91: 33959 | T91: 35 | U91: =IF(AND(ISNUMBER(K91),ISNUMBER(T91)),K91*T91*52/12,"") -> 7778.9833 | V91: 4.4 | W91: 674 | X91: 46307 | Y91: 74 | Z91: 45423 | AA91: =IF(ISNUMBER(Z91),(DATE(2026,10,13)-Z91)/365,"") -> 2.4246575 | AB91: 2428 | AC91: FBA | AD91: 1 | AE91: CN | AF91: 0 | AG91: 0 | AH91: 151 | AN91: =IF(AND(ISNUMBER(AM91),ISNUMBER(AL91),AL91>=5),AM91/AL91,"") | AQ91: =IF(AND(ISNUMBER(AP91),ISNUMBER(AO91),AO91>=5),AP91/AO91,"") | AT91: =IF(AND(ISNUMBER(AS91),ISNUMBER(AR91),AR91>0),AS91/AR91-1,"") | BD91: =IF(AND(ISNUMBER(BB91),ISNUMBER(BC91),BB91>0),1-BC91/BB91,"") | BH91: =IF(AND(ISNUMBER(BF91),ISNUMBER(BG91),BG91>0),BF91/BG91,"") | BM91: =IF(ISNUMBER(Q91),IF(Q91<0,"YES","no"),"") -> YES | BN91: =IFERROR(IF(AND(ISNUMBER(K91),ISNUMBER(INDEX('Lift Inputs'!$H:$H,MATCH(C91,'Lift Inputs'!$C:$C,0)))),IF(K91<INDEX('Lift Inputs'!$H:$H,MATCH(C91,'Lift Inputs'!$C:$C,0)),"YES","no"),""),"")
A92: Bamboo | B92: Decolure Bamboo Sheets 6 Piece | C92: 30 | D92: Hero: rank and profit | E92: 1522 | F92: Shilucheng | G92: B09PYKYCCF | H92: B09PYKYCCF | I92: Shilucheng 100% Viscose Derived from Bamboo_ Sheets Queen Size 4pcs | J92: Poor | K92: 46.66 | L92: 54.9 | M92: =IF(AND(ISNUMBER(L92),ISNUMBER(K92),K92>0),L92/K92-1,"") -> 0.17659666 | N92: =IF(M92="","No List Price",IF(M92<=0,"At/below price",IF(M92<=0.12,"<=12% (STR zone)",IF(M92<=0.25,"12-25%",">25% (likely ignored)")))) -> 12-25% | O92: Queen | P92: 90.683233 | Q92: =IF(AND(ISNUMBER(K92),ISNUMBER(P92),N(P92)>0),K92/P92-1,"") -> -0.48546166 | R92: Same size (Queen) | S92: 26043 | T92: 35 | U92: =IF(AND(ISNUMBER(K92),ISNUMBER(T92)),K92*T92*52/12,"") -> 7076.7667 | V92: 4.4 | W92: 6629 | X92: 46307 | Y92: 79 | Z92: 44652 | AA92: =IF(ISNUMBER(Z92),(DATE(2026,10,13)-Z92)/365,"") -> 4.5369863 | AB92: 1557 | AC92: FBA | AD92: 1 | AE92: CN | AF92: 0 | AG92: 0 | AH92: 167 | AK92: 2026-04-01 | AL92: 0 | AM92: 0 | AN92: =IF(AND(ISNUMBER(AM92),ISNUMBER(AL92),AL92>=5),AM92/AL92,"") | AO92: 0 | AP92: 0 | AQ92: =IF(AND(ISNUMBER(AP92),ISNUMBER(AO92),AO92>=5),AP92/AO92,"") | AR92: 13.3 | AS92: 0.3 | AT92: =IF(AND(ISNUMBER(AS92),ISNUMBER(AR92),AR92>0),AS92/AR92-1,"") -> -0.97744361 | BD92: =IF(AND(ISNUMBER(BB92),ISNUMBER(BC92),BB92>0),1-BC92/BB92,"") | BH92: =IF(AND(ISNUMBER(BF92),ISNUMBER(BG92),BG92>0),BF92/BG92,"") | BM92: =IF(ISNUMBER(Q92),IF(Q92<0,"YES","no"),"") -> YES | BN92: =IFERROR(IF(AND(ISNUMBER(K92),ISNUMBER(INDEX('Lift Inputs'!$H:$H,MATCH(C92,'Lift Inputs'!$C:$C,0)))),IF(K92<INDEX('Lift Inputs'!$H:$H,MATCH(C92,'Lift Inputs'!$C:$C,0)),"YES","no"),""),"")
A93: Bamboo | B93: Decolure Bamboo Sheets 6 Piece | C93: 30 | D93: Hero: rank and profit | E93: 30 | F93: Bamtek | G93: B0CZHCZQZ3 | H93: B09TQ6ZVKZ | I93: Viscose Bamboo Sheets Queen Size 4PC Set - Cooling Bedding for Hot Sleepers with | J93: Poor | K93: 94.99 | M93: =IF(AND(ISNUMBER(L93),ISNUMBER(K93),K93>0),L93/K93-1,"") | N93: =IF(M93="","No List Price",IF(M93<=0,"At/below price",IF(M93<=0.12,"<=12% (STR zone)",IF(M93<=0.25,"12-25%",">25% (likely ignored)")))) -> No List Price | O93: Queen | P93: 90.683233 | Q93: =IF(AND(ISNUMBER(K93),ISNUMBER(P93),N(P93)>0),K93/P93-1,"") -> 0.047492428 | R93: Same size (Queen) | S93: 79376 | T93: 18 | U93: =IF(AND(ISNUMBER(K93),ISNUMBER(T93)),K93*T93*52/12,"") -> 7409.22 | V93: 4.4 | W93: 641 | X93: 46307 | AA93: =IF(ISNUMBER(Z93),(DATE(2026,10,13)-Z93)/365,"") | AN93: =IF(AND(ISNUMBER(AM93),ISNUMBER(AL93),AL93>=5),AM93/AL93,"") | AQ93: =IF(AND(ISNUMBER(AP93),ISNUMBER(AO93),AO93>=5),AP93/AO93,"") | AT93: =IF(AND(ISNUMBER(AS93),ISNUMBER(AR93),AR93>0),AS93/AR93-1,"") | BD93: =IF(AND(ISNUMBER(BB93),ISNUMBER(BC93),BB93>0),1-BC93/BB93,"") | BH93: =IF(AND(ISNUMBER(BF93),ISNUMBER(BG93),BG93>0),BF93/BG93,"") | BM93: =IF(ISNUMBER(Q93),IF(Q93<0,"YES","no"),"") -> no | BN93: =IFERROR(IF(AND(ISNUMBER(K93),ISNUMBER(INDEX('Lift Inputs'!$H:$H,MATCH(C93,'Lift Inputs'!$C:$C,0)))),IF(K93<INDEX('Lift Inputs'!$H:$H,MATCH(C93,'Lift Inputs'!$C:$C,0)),"YES","no"),""),"")
A94: Bamboo | B94: Decolure Bamboo Sheets 6 Piece | C94: 30 | D94: Hero: rank and profit | E94: 28 | F94: JSD | G94: B0DTY15N29 | H94: B0DSZTLBV1 | I94: JSD Sage Green 100% Viscose Derived from Bamboo Cooling Sheet Set Queen | J94: Poor | K94: 56.99 | M94: =IF(AND(ISNUMBER(L94),ISNUMBER(K94),K94>0),L94/K94-1,"") | N94: =IF(M94="","No List Price",IF(M94<=0,"At/below price",IF(M94<=0.12,"<=12% (STR zone)",IF(M94<=0.25,"12-25%",">25% (likely ignored)")))) -> No List Price | O94: Queen | P94: 90.683233 | Q94: =IF(AND(ISNUMBER(K94),ISNUMBER(P94),N(P94)>0),K94/P94-1,"") -> -0.37154865 | R94: Same size (Queen) | S94: 76312 | T94: 18 | U94: =IF(AND(ISNUMBER(K94),ISNUMBER(T94)),K94*T94*52/12,"") -> 4445.22 | V94: 4.3 | W94: 281 | X94: 46307 | Y94: 32 | Z94: 45671 | AA94: =IF(ISNUMBER(Z94),(DATE(2026,10,13)-Z94)/365,"") -> 1.7452055 | AB94: 1508 | AC94: FBA | AD94: 1 | AE94: CN | AF94: 0 | AG94: 0 | AH94: 126 | AN94: =IF(AND(ISNUMBER(AM94),ISNUMBER(AL94),AL94>=5),AM94/AL94,"") | AQ94: =IF(AND(ISNUMBER(AP94),ISNUMBER(AO94),AO94>=5),AP94/AO94,"") | AT94: =IF(AND(ISNUMBER(AS94),ISNUMBER(AR94),AR94>0),AS94/AR94-1,"") | BD94: =IF(AND(ISNUMBER(BB94),ISNUMBER(BC94),BB94>0),1-BC94/BB94,"") | BH94: =IF(AND(ISNUMBER(BF94),ISNUMBER(BG94),BG94>0),BF94/BG94,"") | BM94: =IF(ISNUMBER(Q94),IF(Q94<0,"YES","no"),"") -> YES | BN94: =IFERROR(IF(AND(ISNUMBER(K94),ISNUMBER(INDEX('Lift Inputs'!$H:$H,MATCH(C94,'Lift Inputs'!$C:$C,0)))),IF(K94<INDEX('Lift Inputs'!$H:$H,MATCH(C94,'Lift Inputs'!$C:$C,0)),"YES","no"),""),"")
