Workbook
Name Products_US: Lists!$A$1:$A$28
Name Products_CA: Lists!$B$1:$B$7
Name Brands: Lists!$C$1:$C$246
Name Tiers: Lists!$D$1:$D$5
Name Families: Lists!$E$1:$E$6
Name Types: Lists!$F$1:$F$6

Sheet README
A1: BFCM 2026 Competitor Research
A2: Owner: Shayan Rana · Prepared for: Erik Fisher & Joseph Fisher · Backup: Zarlish · Final for Thu Oct 15, 2026 · Data as of Oct 13-15, 2026
A4: How to use it
A5: 1. US Dashboard and CA Dashboard - pick a product in the yellow cell (brand, tier and family narrow the competitors). Our product panel, stock tiles, competitor tiles and the competitor gallery update. 'Open the product tab' jumps to the full analysis.
A6: 2. Product Index - every product in both marketplaces with its image, variations and BFCM 2025 result; click a tab name to open it.
A7: 3. BFCM Stock - every variation: stock at Amazon, inbound, sales a day, units needed to Nov 30, run-out date with and without inbound, and status. Filter by product or status.
A8: 4. Product tabs - US tabs (blue) then CA tabs (orange), 33 in all. Each has: 1 Our product (plan, assumed deal prices, stock outlook, deal pricing notes) · 2 Our variations · 3 Our BFCM 2025 result · 4 Competitor landscape.
A9: 5. Data Check - the as-of date, coverage and verification result of every data set; Data Gaps - what is still missing.
A11: Key rules
A12: Our price = the latest catalog price read (US Oct 13, CA Oct 14); a variation without one shows no price.
A13: Assumed BFCM 2026 deal price, until final prices are set: 15% off today's price on Nov 19-26 and 20% off on Nov 27-30 (Black Friday to Cyber Monday). Amazon sets the reference price the day before the deal and can use a lower reference, which would lower the deal price.
A14: BFCM 2026 stock: demand at today's pace to Nov 18, then x the product's BFCM 2025 lift for Nov 19-30 (the account's lift where the product's own is missing or unreliable, labelled ASSUMED). Inbound has no arrival date, so each variation shows its run-out date with and without inbound.
... A17: Estimated weekly units and sales bands for competitors are estimates - use them to rank competitors, not as exact sales.

Sheet US Dashboard
B1: BFCM 2026 Tracker · Amazon.com (US) | AA1: All | AB1: All | AC1: All | AD1: All | AE1: All
B2: Pick a product in the yellow cell. Competitor type (Direct = same product and material as ours), brand, tier and family narrow the competitor list. Everything below updates instantly. | AA2: DC B4 | AB2: 100% Blackout Shield | AC2: Aspirational | AD2: Bamboo | AE2: Direct
B3: Owner: Shayan Rana · Prepared for: Erik Fisher & Joseph Fisher · Data as of Oct 13-15, 2026 | AA3: DC B6 | AB3: ACCURATEX | AC3: Beatable | AD3: Satin | AE3: Alternative material
B4: Product | C4: DC B4 | D4: ▼ pick from the list | E4: =IF($C$4="All","",IFERROR(_xlfn.IMAGE(IFERROR(INDEX(Lookup!$A$2:$Y$34,MATCH("US|"&$C$4,Lookup!$A$2:$A$34,0),5),"")),"IMAGE COMING SOON")) | F4: Our product | G4: =IF($C$4="All","All products",IFERROR(INDEX(Lookup!$A$2:$Y$34,MATCH("US|"&$C$4,Lookup!$A$2:$A$34,0),4),"")) | L4: STOCK AT AMAZON | N4: INBOUND | P4: UNITS NEEDED TO NOV 30 | R4: VARIATIONS SHORT / OUT OF STOCK | AA4: SL B6 | AB4: Adubor | AC4: Poor | AD4: Silk | AE4: Material not verified
B5: Brand | C5: All | D5: ▼ pick from the list | F5: Brand · parent ASIN | G5: =IF($C$4="All","",IFERROR(INDEX(Lookup!$A$2:$Y$34,MATCH("US|"&$C$4,Lookup!$A$2:$A$34,0),6),"")&" · "&IFERROR(INDEX(Lookup!$A$2:$Y$34,MATCH("US|"&$C$4,Lookup!$A$2:$A$34,0),7),"")) | L5: =IF($C$4="All","",IFERROR(INDEX(Lookup!$A$2:$Y$34,MATCH("US|"&$C$4,Lookup!$A$2:$A$34,0),16),"")) | N5: =IF($C$4="All","",IFERROR(INDEX(Lookup!$A$2:$Y$34,MATCH("US|"&$C$4,Lookup!$A$2:$A$34,0),17),"")) | P5: =IF($C$4="All","",IFERROR(INDEX(Lookup!$A$2:$Y$34,MATCH("US|"&$C$4,Lookup!$A$2:$A$34,0),18),"")) | R5: =IF($C$4="All","",IFERROR(INDEX(Lookup!$A$2:$Y$34,MATCH("US|"&$C$4,Lookup!$A$2:$A$34,0),22),"")&" / "&IFERROR(INDEX(Lookup!$A$2:$Y$34,MATCH("US|"&$C$4,Lookup!$A$2:$A$34,0),23),"")) | AA5: SL B4 | AB5: AiAngu | AC5: Untiered | AD5: Cooling | AE5: Different product type
B6: Tier | C6: All | D6: ▼ pick from the list | F6: Our price (best child) | G6: =IF($C$4="All","",IFERROR(INDEX(Lookup!$A$2:$Y$34,MATCH("US|"&$C$4,Lookup!$A$2:$A$34,0),10),"")) | AA6: DC Bamboo Fitted | AB6: akkialla | AD6: Other | AE6: Not classified
B7: Family | C7: All | D7: ▼ pick from the list | F7: Units, last 28 days | G7: =IF($C$4="All","",IFERROR(INDEX(Lookup!$A$2:$Y$34,MATCH("US|"&$C$4,Lookup!$A$2:$A$34,0),11),"")) | L7: COMPETITORS SHOWN | N7: MEDIAN COMPETITOR PRICE | P7: PRICED BELOW US | R7: AVG BFCM 2025 DISCOUNT | AA7: SL Bamboo Pillowcase | AB7: ALASKA BEAR
B8: Competitor type | C8: All | D8: ▼ pick from the list | F8: BFCM 2026 plan | G8: =IF($C$4="All","",IFERROR(INDEX(Lookup!$A$2:$Y$34,MATCH("US|"&$C$4,Lookup!$A$2:$A$34,0),13),"")) | L8: =COUNTIF(Data!$A$2:$A$745,TRUE) | N8: {=IFERROR(MEDIAN(IF((Data!$A$2:$A$745=TRUE)*ISNUMBER(Data!$N$2:$N$745),Data!$N$2:$N$745)),"")} | P8: =COUNTIFS(Data!$A$2:$A$745,TRUE,Data!$R$2:$R$745,"<0") | R8: =IFERROR(AVERAGEIFS(Data!$AD$2:$AD$745,Data!$A$2:$A$745,TRUE),"") | AA8: DC S4 | AB8: Amazon Basics
B9: → CA Dashboard | F9: Assumed deal price (15% / 20%) | G9: =IF(OR($C$4="All",IFERROR(INDEX(Lookup!$A$2:$Y$34,MATCH("US|"&$C$4,Lookup!$A$2:$A$34,0),14),"")=""),"No deal planned",TEXT(IFERROR(INDEX(Lookup!$A$2:$Y$34,MATCH("US|"&$C$4,Lookup!$A$2:$A$34,0),14),""),"$0.00")&" (Nov 19-26) · "&TEXT(IFERROR(INDEX(Lookup!$A$2:$Y$34,MATCH("US|"&$C$4,Lookup!$A$2:$A$34,0),15),""),"$0.00")&" (Nov 27-30)") | AA9: DC S6 | AB9: Andency
B10: → BFCM Stock | F10: BFCM 2025 sales lift | G10: =IF($C$4="All","",IFERROR(INDEX(Lookup!$A$2:$Y$34,MATCH("US|"&$C$4,Lookup!$A$2:$A$34,0),12),"")) | AA10: SSS4 | AB10: Anibedding
F11: Open the product tab: | G11: =IF($C$4="All","",HYPERLINK("#'"&IFERROR(INDEX(Lookup!$A$2:$Y$34,MATCH("US|"&$C$4,Lookup!$A$2:$A$34,0),3),"")&"'!A1",IFERROR(INDEX(Lookup!$A$2:$Y$34,MATCH("US|"&$C$4,Lookup!$A$2:$A$34,0),3),""))) | AA11: SL Satin 6pc | AB11: Artrello
AA12: DC Satin Fitted | AB12: ATreebay
B13: COMPETITORS (first 80 matches, in tier then weekly-units order) | AA13: DC Silk Pillowcase | AB13: Avolare
B14: # | C14: Image | D14: Brand · Tier | E14: Title | F14: Competitor type | G14: Size · colour | H14: Price | I14: List Price | J14: List % over | K14: vs our price | L14: BSR | M14: Wk units | N14: Rating | O14: Reviews | P14: Variations | Q14: BFCM 2025 discount | R14: ASIN | AA14: SL Mask Contoured | AB14: Back Bay Audio
B15: =IF(1<=COUNTIF(Data!$A$2:$A$745,TRUE),1,"") | C15: =IF(B15="","",IFERROR(_xlfn.IMAGE(IFERROR(IF(INDEX(Data!$J$2:$J$745,MATCH(1,Data!$B$2:$B$745,0))="","",INDEX(Data!$J$2:$J$745,MATCH(1,Data!$B$2:$B$745,0))),"")),"IMAGE COMING SOON")) | D15: =IF(B15="","",IFERROR(IF(INDEX(Data!$G$2:$G$745,MATCH(1,Data!$B$2:$B$745,0))="","",INDEX(Data!$G$2:$G$745,MATCH(1,Data!$B$2:$B$745,0))),"")&CHAR(10)&IFERROR(IF(INDEX(Data!$H$2:$H$745,MATCH(1,Data!$B$2:$B$745,0))="","",INDEX(Data!$H$2:$H$745,MATCH(1,Data!$B$2:$B$745,0))),"")) | E15: =IF(B15="","",IFERROR(IF(INDEX(Data!$I$2:$I$745,MATCH(1,Data!$B$2:$B$745,0))="","",INDEX(Data!$I$2:$I$745,MATCH(1,Data!$B$2:$B$745,0))),"")) | F15: =IF(B15="","",IFERROR(IF(INDEX(Data!$AJ$2:$AJ$745,MATCH(1,Data!$B$2:$B$745,0))="","",INDEX(Data!$AJ$2:$AJ$745,MATCH(1,Data!$B$2:$B$745,0))),"")) | G15: =IF(B15="","",TRIM(IFERROR(IF(INDEX(Data!$AF$2:$AF$745,MATCH(1,Data!$B$2:$B$745,0))="","",INDEX(Data!$AF$2:$AF$745,MATCH(1,Data!$B$2:$B$745,0))),"")&" "&IFERROR(IF(INDEX(Data!$AG$2:$AG$745,MATCH(1,Data!$B$2:$B$745,0))="","",INDEX(Data!$AG$2:$AG$745,MATCH(1,Data!$B$2:$B$745,0))),""))) | H15: =IF(B15="","",IFERROR(IF(INDEX(Data!$N$2:$N$745,MATCH(1,Data!$B$2:$B$745,0))="","",INDEX(Data!$N$2:$N$745,MATCH(1,Data!$B$2:$B$745,0))),"")) | I15: =IF(B15="","",IFERROR(IF(INDEX(Data!$O$2:$O$745,MATCH(1,Data!$B$2:$B$745,0))="","",INDEX(Data!$O$2:$O$745,MATCH(1,Data!$B$2:$B$745,0))),"")) | J15: =IF(B15="","",IFERROR(IF(INDEX(Data!$P$2:$P$745,MATCH(1,Data!$B$2:$B$745,0))="","",INDEX(Data!$P$2:$P$745,MATCH(1,Data!$B$2:$B$745,0))),"")) | K15: =IF(B15="","",IFERROR(IF(INDEX(Data!$R$2:$R$745,MATCH(1,Data!$B$2:$B$745,0))="","",INDEX(Data!$R$2:$R$745,MATCH(1,Data!$B$2:$B$745,0))),"")) | L15: =IF(B15="","",IFERROR(IF(INDEX(Data!$S$2:$S$745,MATCH(1,Data!$B$2:$B$745,0))="","",INDEX(Data!$S$2:$S$745,MATCH(1,Data!$B$2:$B$745,0))),"")) | M15: =IF(B15="","",IFERROR(IF(INDEX(Data!$T$2:$T$745,MATCH(1,Data!$B$2:$B$745,0))="","",INDEX(Data!$T$2:$T$745,MATCH(1,Data!$B$2:$B$745,0))),"")) | N15: =IF(B15="","",IFERROR(IF(INDEX(Data!$U$2:$U$745,MATCH(1,Data!$B$2:$B$745,0))="","",INDEX(Data!$U$2:$U$745,MATCH(1,Data!$B$2:$B$745,0))),"")) | O15: =IF(B15="","",IFERROR(IF(INDEX(Data!$V$2:$V$745,MATCH(1,Data!$B$2:$B$745,0))="","",INDEX(Data!$V$2:$V$745,MATCH(1,Data!$B$2:$B$745,0))),"")) | P15: =IF(B15="","",IFERROR(IF(INDEX(Data!$M$2:$M$745,MATCH(1,Data!$B$2:$B$745,0))="","",INDEX(Data!$M$2:$M$745,MATCH(1,Data!$B$2:$B$745,0))),"")) | Q15: =IF(B15="","",IFERROR(IF(INDEX(Data!$AD$2:$AD$745,MATCH(1,Data!$B$2:$B$745,0))="","",INDEX(Data!$AD$2:$AD$745,MATCH(1,Data!$B$2:$B$745,0))),"")) | R15: =IF(B15="","",IFERROR(IF(INDEX(Data!$L$2:$L$745,MATCH(1,Data!$B$2:$B$745,0))="","",INDEX(Data!$L$2:$L$745,MATCH(1,Data!$B$2:$B$745,0))),"")) | AA15: SL Mask Velcro | AB15: Bambaw
B16: =IF(2<=COUNTIF(Data!$A$2:$A$745,TRUE),2,"") | C16: =IF(B16="","",IFERROR(_xlfn.IMAGE(IFERROR(IF(INDEX(Data!$J$2:$J$745,MATCH(2,Data!$B$2:$B$745,0))="","",INDEX(Data!$J$2:$J$745,MATCH(2,Data!$B$2:$B$745,0))),"")),"IMAGE COMING SOON")) | D16: =IF(B16="","",IFERROR(IF(INDEX(Data!$G$2:$G$745,MATCH(2,Data!$B$2:$B$745,0))="","",INDEX(Data!$G$2:$G$745,MATCH(2,Data!$B$2:$B$745,0))),"")&CHAR(10)&IFERROR(IF(INDEX(Data!$H$2:$H$745,MATCH(2,Data!$B$2:$B$745,0))="","",INDEX(Data!$H$2:$H$745,MATCH(2,Data!$B$2:$B$745,0))),"")) | E16: =IF(B16="","",IFERROR(IF(INDEX(Data!$I$2:$I$745,MATCH(2,Data!$B$2:$B$745,0))="","",INDEX(Data!$I$2:$I$745,MATCH(2,Data!$B$2:$B$745,0))),"")) | F16: =IF(B16="","",IFERROR(IF(INDEX(Data!$AJ$2:$AJ$745,MATCH(2,Data!$B$2:$B$745,0))="","",INDEX(Data!$AJ$2:$AJ$745,MATCH(2,Data!$B$2:$B$745,0))),"")) | G16: =IF(B16="","",TRIM(IFERROR(IF(INDEX(Data!$AF$2:$AF$745,MATCH(2,Data!$B$2:$B$745,0))="","",INDEX(Data!$AF$2:$AF$745,MATCH(2,Data!$B$2:$B$745,0))),"")&" "&IFERROR(IF(INDEX(Data!$AG$2:$AG$745,MATCH(2,Data!$B$2:$B$745,0))="","",INDEX(Data!$AG$2:$AG$745,MATCH(2,Data!$B$2:$B$745,0))),""))) | H16: =IF(B16="","",IFERROR(IF(INDEX(Data!$N$2:$N$745,MATCH(2,Data!$B$2:$B$745,0))="","",INDEX(Data!$N$2:$N$745,MATCH(2,Data!$B$2:$B$745,0))),"")) | I16: =IF(B16="","",IFERROR(IF(INDEX(Data!$O$2:$O$745,MATCH(2,Data!$B$2:$B$745,0))="","",INDEX(Data!$O$2:$O$745,MATCH(2,Data!$B$2:$B$745,0))),"")) | J16: =IF(B16="","",IFERROR(IF(INDEX(Data!$P$2:$P$745,MATCH(2,Data!$B$2:$B$745,0))="","",INDEX(Data!$P$2:$P$745,MATCH(2,Data!$B$2:$B$745,0))),"")) | K16: =IF(B16="","",IFERROR(IF(INDEX(Data!$R$2:$R$745,MATCH(2,Data!$B$2:$B$745,0))="","",INDEX(Data!$R$2:$R$745,MATCH(2,Data!$B$2:$B$745,0))),"")) | L16: =IF(B16="","",IFERROR(IF(INDEX(Data!$S$2:$S$745,MATCH(2,Data!$B$2:$B$745,0))="","",INDEX(Data!$S$2:$S$745,MATCH(2,Data!$B$2:$B$745,0))),"")) | M16: =IF(B16="","",IFERROR(IF(INDEX(Data!$T$2:$T$745,MATCH(2,Data!$B$2:$B$745,0))="","",INDEX(Data!$T$2:$T$745,MATCH(2,Data!$B$2:$B$745,0))),"")) | N16: =IF(B16="","",IFERROR(IF(INDEX(Data!$U$2:$U$745,MATCH(2,Data!$B$2:$B$745,0))="","",INDEX(Data!$U$2:$U$745,MATCH(2,Data!$B$2:$B$745,0))),"")) | O16: =IF(B16="","",IFERROR(IF(INDEX(Data!$V$2:$V$745,MATCH(2,Data!$B$2:$B$745,0))="","",INDEX(Data!$V$2:$V$745,MATCH(2,Data!$B$2:$B$745,0))),"")) | P16: =IF(B16="","",IFERROR(IF(INDEX(Data!$M$2:$M$745,MATCH(2,Data!$B$2:$B$745,0))="","",INDEX(Data!$M$2:$M$745,MATCH(2,Data!$B$2:$B$745,0))),"")) | Q16: =IF(B16="","",IFERROR(IF(INDEX(Data!$AD$2:$AD$745,MATCH(2,Data!$B$2:$B$745,0))="","",INDEX(Data!$AD$2:$AD$745,MATCH(2,Data!$B$2:$B$745,0))),"")) | R16: =IF(B16="","",IFERROR(IF(INDEX(Data!$L$2:$L$745,MATCH(2,Data!$B$2:$B$745,0))="","",INDEX(Data!$L$2:$L$745,MATCH(2,Data!$B$2:$B$745,0))),"")) | AA16: DC Cooling 4pc | AB16: Bamboo Bay
B17: =IF(3<=COUNTIF(Data!$A$2:$A$745,TRUE),3,"") | C17: =IF(B17="","",IFERROR(_xlfn.IMAGE(IFERROR(IF(INDEX(Data!$J$2:$J$745,MATCH(3,Data!$B$2:$B$745,0))="","",INDEX(Data!$J$2:$J$745,MATCH(3,Data!$B$2:$B$745,0))),"")),"IMAGE COMING SOON")) | D17: =IF(B17="","",IFERROR(IF(INDEX(Data!$G$2:$G$745,MATCH(3,Data!$B$2:$B$745,0))="","",INDEX(Data!$G$2:$G$745,MATCH(3,Data!$B$2:$B$745,0))),"")&CHAR(10)&IFERROR(IF(INDEX(Data!$H$2:$H$745,MATCH(3,Data!$B$2:$B$745,0))="","",INDEX(Data!$H$2:$H$745,MATCH(3,Data!$B$2:$B$745,0))),"")) | E17: =IF(B17="","",IFERROR(IF(INDEX(Data!$I$2:$I$745,MATCH(3,Data!$B$2:$B$745,0))="","",INDEX(Data!$I$2:$I$745,MATCH(3,Data!$B$2:$B$745,0))),"")) | F17: =IF(B17="","",IFERROR(IF(INDEX(Data!$AJ$2:$AJ$745,MATCH(3,Data!$B$2:$B$745,0))="","",INDEX(Data!$AJ$2:$AJ$745,MATCH(3,Data!$B$2:$B$745,0))),"")) | G17: =IF(B17="","",TRIM(IFERROR(IF(INDEX(Data!$AF$2:$AF$745,MATCH(3,Data!$B$2:$B$745,0))="","",INDEX(Data!$AF$2:$AF$745,MATCH(3,Data!$B$2:$B$745,0))),"")&" "&IFERROR(IF(INDEX(Data!$AG$2:$AG$745,MATCH(3,Data!$B$2:$B$745,0))="","",INDEX(Data!$AG$2:$AG$745,MATCH(3,Data!$B$2:$B$745,0))),""))) | H17: =IF(B17="","",IFERROR(IF(INDEX(Data!$N$2:$N$745,MATCH(3,Data!$B$2:$B$745,0))="","",INDEX(Data!$N$2:$N$745,MATCH(3,Data!$B$2:$B$745,0))),"")) | I17: =IF(B17="","",IFERROR(IF(INDEX(Data!$O$2:$O$745,MATCH(3,Data!$B$2:$B$745,0))="","",INDEX(Data!$O$2:$O$745,MATCH(3,Data!$B$2:$B$745,0))),"")) | J17: =IF(B17="","",IFERROR(IF(INDEX(Data!$P$2:$P$745,MATCH(3,Data!$B$2:$B$745,0))="","",INDEX(Data!$P$2:$P$745,MATCH(3,Data!$B$2:$B$745,0))),"")) | K17: =IF(B17="","",IFERROR(IF(INDEX(Data!$R$2:$R$745,MATCH(3,Data!$B$2:$B$745,0))="","",INDEX(Data!$R$2:$R$745,MATCH(3,Data!$B$2:$B$745,0))),"")) | L17: =IF(B17="","",IFERROR(IF(INDEX(Data!$S$2:$S$745,MATCH(3,Data!$B$2:$B$745,0))="","",INDEX(Data!$S$2:$S$745,MATCH(3,Data!$B$2:$B$745,0))),"")) | M17: =IF(B17="","",IFERROR(IF(INDEX(Data!$T$2:$T$745,MATCH(3,Data!$B$2:$B$745,0))="","",INDEX(Data!$T$2:$T$745,MATCH(3,Data!$B$2:$B$745,0))),"")) | N17: =IF(B17="","",IFERROR(IF(INDEX(Data!$U$2:$U$745,MATCH(3,Data!$B$2:$B$745,0))="","",INDEX(Data!$U$2:$U$745,MATCH(3,Data!$B$2:$B$745,0))),"")) | O17: =IF(B17="","",IFERROR(IF(INDEX(Data!$V$2:$V$745,MATCH(3,Data!$B$2:$B$745,0))="","",INDEX(Data!$V$2:$V$745,MATCH(3,Data!$B$2:$B$745,0))),"")) | P17: =IF(B17="","",IFERROR(IF(INDEX(Data!$M$2:$M$745,MATCH(3,Data!$B$2:$B$745,0))="","",INDEX(Data!$M$2:$M$745,MATCH(3,Data!$B$2:$B$745,0))),"")) | Q17: =IF(B17="","",IFERROR(IF(INDEX(Data!$AD$2:$AD$745,MATCH(3,Data!$B$2:$B$745,0))="","",INDEX(Data!$AD$2:$AD$745,MATCH(3,Data!$B$2:$B$745,0))),"")) | R17: =IF(B17="","",IFERROR(IF(INDEX(Data!$L$2:$L$745,MATCH(3,Data!$B$2:$B$745,0))="","",INDEX(Data!$L$2:$L$745,MATCH(3,Data!$B$2:$B$745,0))),"")) | AA17: SL Cooling 4pc | AB17: BAMPURE
B18: =IF(4<=COUNTIF(Data!$A$2:$A$745,TRUE),4,"") | C18: =IF(B18="","",IFERROR(_xlfn.IMAGE(IFERROR(IF(INDEX(Data!$J$2:$J$745,MATCH(4,Data!$B$2:$B$745,0))="","",INDEX(Data!$J$2:$J$745,MATCH(4,Data!$B$2:$B$745,0))),"")),"IMAGE COMING SOON")) | D18: =IF(B18="","",IFERROR(IF(INDEX(Data!$G$2:$G$745,MATCH(4,Data!$B$2:$B$745,0))="","",INDEX(Data!$G$2:$G$745,MATCH(4,Data!$B$2:$B$745,0))),"")&CHAR(10)&IFERROR(IF(INDEX(Data!$H$2:$H$745,MATCH(4,Data!$B$2:$B$745,0))="","",INDEX(Data!$H$2:$H$745,MATCH(4,Data!$B$2:$B$745,0))),"")) | E18: =IF(B18="","",IFERROR(IF(INDEX(Data!$I$2:$I$745,MATCH(4,Data!$B$2:$B$745,0))="","",INDEX(Data!$I$2:$I$745,MATCH(4,Data!$B$2:$B$745,0))),"")) | F18: =IF(B18="","",IFERROR(IF(INDEX(Data!$AJ$2:$AJ$745,MATCH(4,Data!$B$2:$B$745,0))="","",INDEX(Data!$AJ$2:$AJ$745,MATCH(4,Data!$B$2:$B$745,0))),"")) | G18: =IF(B18="","",TRIM(IFERROR(IF(INDEX(Data!$AF$2:$AF$745,MATCH(4,Data!$B$2:$B$745,0))="","",INDEX(Data!$AF$2:$AF$745,MATCH(4,Data!$B$2:$B$745,0))),"")&" "&IFERROR(IF(INDEX(Data!$AG$2:$AG$745,MATCH(4,Data!$B$2:$B$745,0))="","",INDEX(Data!$AG$2:$AG$745,MATCH(4,Data!$B$2:$B$745,0))),""))) | H18: =IF(B18="","",IFERROR(IF(INDEX(Data!$N$2:$N$745,MATCH(4,Data!$B$2:$B$745,0))="","",INDEX(Data!$N$2:$N$745,MATCH(4,Data!$B$2:$B$745,0))),"")) | I18: =IF(B18="","",IFERROR(IF(INDEX(Data!$O$2:$O$745,MATCH(4,Data!$B$2:$B$745,0))="","",INDEX(Data!$O$2:$O$745,MATCH(4,Data!$B$2:$B$745,0))),"")) | J18: =IF(B18="","",IFERROR(IF(INDEX(Data!$P$2:$P$745,MATCH(4,Data!$B$2:$B$745,0))="","",INDEX(Data!$P$2:$P$745,MATCH(4,Data!$B$2:$B$745,0))),"")) | K18: =IF(B18="","",IFERROR(IF(INDEX(Data!$R$2:$R$745,MATCH(4,Data!$B$2:$B$745,0))="","",INDEX(Data!$R$2:$R$745,MATCH(4,Data!$B$2:$B$745,0))),"")) | L18: =IF(B18="","",IFERROR(IF(INDEX(Data!$S$2:$S$745,MATCH(4,Data!$B$2:$B$745,0))="","",INDEX(Data!$S$2:$S$745,MATCH(4,Data!$B$2:$B$745,0))),"")) | M18: =IF(B18="","",IFERROR(IF(INDEX(Data!$T$2:$T$745,MATCH(4,Data!$B$2:$B$745,0))="","",INDEX(Data!$T$2:$T$745,MATCH(4,Data!$B$2:$B$745,0))),"")) | N18: =IF(B18="","",IFERROR(IF(INDEX(Data!$U$2:$U$745,MATCH(4,Data!$B$2:$B$745,0))="","",INDEX(Data!$U$2:$U$745,MATCH(4,Data!$B$2:$B$745,0))),"")) | O18: =IF(B18="","",IFERROR(IF(INDEX(Data!$V$2:$V$745,MATCH(4,Data!$B$2:$B$745,0))="","",INDEX(Data!$V$2:$V$745,MATCH(4,Data!$B$2:$B$745,0))),"")) | P18: =IF(B18="","",IFERROR(IF(INDEX(Data!$M$2:$M$745,MATCH(4,Data!$B$2:$B$745,0))="","",INDEX(Data!$M$2:$M$745,MATCH(4,Data!$B$2:$B$745,0))),"")) | Q18: =IF(B18="","",IFERROR(IF(INDEX(Data!$AD$2:$AD$745,MATCH(4,Data!$B$2:$B$745,0))="","",INDEX(Data!$AD$2:$AD$745,MATCH(4,Data!$B$2:$B$745,0))),"")) | R18: =IF(B18="","",IFERROR(IF(INDEX(Data!$L$2:$L$745,MATCH(4,Data!$B$2:$B$745,0))="","",INDEX(Data!$L$2:$L$745,MATCH(4,Data!$B$2:$B$745,0))),"")) | AA18: SL Cooling 6pc | AB18: Bamtek
B19: =IF(5<=COUNTIF(Data!$A$2:$A$745,TRUE),5,"") | C19: =IF(B19="","",IFERROR(_xlfn.IMAGE(IFERROR(IF(INDEX(Data!$J$2:$J$745,MATCH(5,Data!$B$2:$B$745,0))="","",INDEX(Data!$J$2:$J$745,MATCH(5,Data!$B$2:$B$745,0))),"")),"IMAGE COMING SOON")) | D19: =IF(B19="","",IFERROR(IF(INDEX(Data!$G$2:$G$745,MATCH(5,Data!$B$2:$B$745,0))="","",INDEX(Data!$G$2:$G$745,MATCH(5,Data!$B$2:$B$745,0))),"")&CHAR(10)&IFERROR(IF(INDEX(Data!$H$2:$H$745,MATCH(5,Data!$B$2:$B$745,0))="","",INDEX(Data!$H$2:$H$745,MATCH(5,Data!$B$2:$B$745,0))),"")) | E19: =IF(B19="","",IFERROR(IF(INDEX(Data!$I$2:$I$745,MATCH(5,Data!$B$2:$B$745,0))="","",INDEX(Data!$I$2:$I$745,MATCH(5,Data!$B$2:$B$745,0))),"")) | F19: =IF(B19="","",IFERROR(IF(INDEX(Data!$AJ$2:$AJ$745,MATCH(5,Data!$B$2:$B$745,0))="","",INDEX(Data!$AJ$2:$AJ$745,MATCH(5,Data!$B$2:$B$745,0))),"")) | G19: =IF(B19="","",TRIM(IFERROR(IF(INDEX(Data!$AF$2:$AF$745,MATCH(5,Data!$B$2:$B$745,0))="","",INDEX(Data!$AF$2:$AF$745,MATCH(5,Data!$B$2:$B$745,0))),"")&" "&IFERROR(IF(INDEX(Data!$AG$2:$AG$745,MATCH(5,Data!$B$2:$B$745,0))="","",INDEX(Data!$AG$2:$AG$745,MATCH(5,Data!$B$2:$B$745,0))),""))) | H19: =IF(B19="","",IFERROR(IF(INDEX(Data!$N$2:$N$745,MATCH(5,Data!$B$2:$B$745,0))="","",INDEX(Data!$N$2:$N$745,MATCH(5,Data!$B$2:$B$745,0))),"")) | I19: =IF(B19="","",IFERROR(IF(INDEX(Data!$O$2:$O$745,MATCH(5,Data!$B$2:$B$745,0))="","",INDEX(Data!$O$2:$O$745,MATCH(5,Data!$B$2:$B$745,0))),"")) | J19: =IF(B19="","",IFERROR(IF(INDEX(Data!$P$2:$P$745,MATCH(5,Data!$B$2:$B$745,0))="","",INDEX(Data!$P$2:$P$745,MATCH(5,Data!$B$2:$B$745,0))),"")) | K19: =IF(B19="","",IFERROR(IF(INDEX(Data!$R$2:$R$745,MATCH(5,Data!$B$2:$B$745,0))="","",INDEX(Data!$R$2:$R$745,MATCH(5,Data!$B$2:$B$745,0))),"")) | L19: =IF(B19="","",IFERROR(IF(INDEX(Data!$S$2:$S$745,MATCH(5,Data!$B$2:$B$745,0))="","",INDEX(Data!$S$2:$S$745,MATCH(5,Data!$B$2:$B$745,0))),"")) | M19: =IF(B19="","",IFERROR(IF(INDEX(Data!$T$2:$T$745,MATCH(5,Data!$B$2:$B$745,0))="","",INDEX(Data!$T$2:$T$745,MATCH(5,Data!$B$2:$B$745,0))),"")) | N19: =IF(B19="","",IFERROR(IF(INDEX(Data!$U$2:$U$745,MATCH(5,Data!$B$2:$B$745,0))="","",INDEX(Data!$U$2:$U$745,MATCH(5,Data!$B$2:$B$745,0))),"")) | O19: =IF(B19="","",IFERROR(IF(INDEX(Data!$V$2:$V$745,MATCH(5,Data!$B$2:$B$745,0))="","",INDEX(Data!$V$2:$V$745,MATCH(5,Data!$B$2:$B$745,0))),"")) | P19: =IF(B19="","",IFERROR(IF(INDEX(Data!$M$2:$M$745,MATCH(5,Data!$B$2:$B$745,0))="","",INDEX(Data!$M$2:$M$745,MATCH(5,Data!$B$2:$B$745,0))),"")) | Q19: =IF(B19="","",IFERROR(IF(INDEX(Data!$AD$2:$AD$745,MATCH(5,Data!$B$2:$B$745,0))="","",INDEX(Data!$AD$2:$AD$745,MATCH(5,Data!$B$2:$B$745,0))),"")) | R19: =IF(B19="","",IFERROR(IF(INDEX(Data!$L$2:$L$745,MATCH(5,Data!$B$2:$B$745,0))="","",INDEX(Data!$L$2:$L$745,MATCH(5,Data!$B$2:$B$745,0))),"")) | AA19: CL Cooling Sheets | AB19: Bare Home
B20: =IF(6<=COUNTIF(Data!$A$2:$A$745,TRUE),6,"") | C20: =IF(B20="","",IFERROR(_xlfn.IMAGE(IFERROR(IF(INDEX(Data!$J$2:$J$745,MATCH(6,Data!$B$2:$B$745,0))="","",INDEX(Data!$J$2:$J$745,MATCH(6,Data!$B$2:$B$745,0))),"")),"IMAGE COMING SOON")) | D20: =IF(B20="","",IFERROR(IF(INDEX(Data!$G$2:$G$745,MATCH(6,Data!$B$2:$B$745,0))="","",INDEX(Data!$G$2:$G$745,MATCH(6,Data!$B$2:$B$745,0))),"")&CHAR(10)&IFERROR(IF(INDEX(Data!$H$2:$H$745,MATCH(6,Data!$B$2:$B$745,0))="","",INDEX(Data!$H$2:$H$745,MATCH(6,Data!$B$2:$B$745,0))),"")) | E20: =IF(B20="","",IFERROR(IF(INDEX(Data!$I$2:$I$745,MATCH(6,Data!$B$2:$B$745,0))="","",INDEX(Data!$I$2:$I$745,MATCH(6,Data!$B$2:$B$745,0))),"")) | F20: =IF(B20="","",IFERROR(IF(INDEX(Data!$AJ$2:$AJ$745,MATCH(6,Data!$B$2:$B$745,0))="","",INDEX(Data!$AJ$2:$AJ$745,MATCH(6,Data!$B$2:$B$745,0))),"")) | G20: =IF(B20="","",TRIM(IFERROR(IF(INDEX(Data!$AF$2:$AF$745,MATCH(6,Data!$B$2:$B$745,0))="","",INDEX(Data!$AF$2:$AF$745,MATCH(6,Data!$B$2:$B$745,0))),"")&" "&IFERROR(IF(INDEX(Data!$AG$2:$AG$745,MATCH(6,Data!$B$2:$B$745,0))="","",INDEX(Data!$AG$2:$AG$745,MATCH(6,Data!$B$2:$B$745,0))),""))) | H20: =IF(B20="","",IFERROR(IF(INDEX(Data!$N$2:$N$745,MATCH(6,Data!$B$2:$B$745,0))="","",INDEX(Data!$N$2:$N$745,MATCH(6,Data!$B$2:$B$745,0))),"")) | I20: =IF(B20="","",IFERROR(IF(INDEX(Data!$O$2:$O$745,MATCH(6,Data!$B$2:$B$745,0))="","",INDEX(Data!$O$2:$O$745,MATCH(6,Data!$B$2:$B$745,0))),"")) | J20: =IF(B20="","",IFERROR(IF(INDEX(Data!$P$2:$P$745,MATCH(6,Data!$B$2:$B$745,0))="","",INDEX(Data!$P$2:$P$745,MATCH(6,Data!$B$2:$B$745,0))),"")) | K20: =IF(B20="","",IFERROR(IF(INDEX(Data!$R$2:$R$745,MATCH(6,Data!$B$2:$B$745,0))="","",INDEX(Data!$R$2:$R$745,MATCH(6,Data!$B$2:$B$745,0))),"")) | L20: =IF(B20="","",IFERROR(IF(INDEX(Data!$S$2:$S$745,MATCH(6,Data!$B$2:$B$745,0))="","",INDEX(Data!$S$2:$S$745,MATCH(6,Data!$B$2:$B$745,0))),"")) | M20: =IF(B20="","",IFERROR(IF(INDEX(Data!$T$2:$T$745,MATCH(6,Data!$B$2:$B$745,0))="","",INDEX(Data!$T$2:$T$745,MATCH(6,Data!$B$2:$B$745,0))),"")) | N20: =IF(B20="","",IFERROR(IF(INDEX(Data!$U$2:$U$745,MATCH(6,Data!$B$2:$B$745,0))="","",INDEX(Data!$U$2:$U$745,MATCH(6,Data!$B$2:$B$745,0))),"")) | O20: =IF(B20="","",IFERROR(IF(INDEX(Data!$V$2:$V$745,MATCH(6,Data!$B$2:$B$745,0))="","",INDEX(Data!$V$2:$V$745,MATCH(6,Data!$B$2:$B$745,0))),"")) | P20: =IF(B20="","",IFERROR(IF(INDEX(Data!$M$2:$M$745,MATCH(6,Data!$B$2:$B$745,0))="","",INDEX(Data!$M$2:$M$745,MATCH(6,Data!$B$2:$B$745,0))),"")) | Q20: =IF(B20="","",IFERROR(IF(INDEX(Data!$AD$2:$AD$745,MATCH(6,Data!$B$2:$B$745,0))="","",INDEX(Data!$AD$2:$AD$745,MATCH(6,Data!$B$2:$B$745,0))),"")) | R20: =IF(B20="","",IFERROR(IF(INDEX(Data!$L$2:$L$745,MATCH(6,Data!$B$2:$B$745,0))="","",INDEX(Data!$L$2:$L$745,MATCH(6,Data!$B$2:$B$745,0))),"")) | AA20: CL Pillowcases | AB20: BC BELLA COTERIE
B21: =IF(7<=COUNTIF(Data!$A$2:$A$745,TRUE),7,"") | C21: =IF(B21="","",IFERROR(_xlfn.IMAGE(IFERROR(IF(INDEX(Data!$J$2:$J$745,MATCH(7,Data!$B$2:$B$745,0))="","",INDEX(Data!$J$2:$J$745,MATCH(7,Data!$B$2:$B$745,0))),"")),"IMAGE COMING SOON")) | D21: =IF(B21="","",IFERROR(IF(INDEX(Data!$G$2:$G$745,MATCH(7,Data!$B$2:$B$745,0))="","",INDEX(Data!$G$2:$G$745,MATCH(7,Data!$B$2:$B$745,0))),"")&CHAR(10)&IFERROR(IF(INDEX(Data!$H$2:$H$745,MATCH(7,Data!$B$2:$B$745,0))="","",INDEX(Data!$H$2:$H$745,MATCH(7,Data!$B$2:$B$745,0))),"")) | E21: =IF(B21="","",IFERROR(IF(INDEX(Data!$I$2:$I$745,MATCH(7,Data!$B$2:$B$745,0))="","",INDEX(Data!$I$2:$I$745,MATCH(7,Data!$B$2:$B$745,0))),"")) | F21: =IF(B21="","",IFERROR(IF(INDEX(Data!$AJ$2:$AJ$745,MATCH(7,Data!$B$2:$B$745,0))="","",INDEX(Data!$AJ$2:$AJ$745,MATCH(7,Data!$B$2:$B$745,0))),"")) | G21: =IF(B21="","",TRIM(IFERROR(IF(INDEX(Data!$AF$2:$AF$745,MATCH(7,Data!$B$2:$B$745,0))="","",INDEX(Data!$AF$2:$AF$745,MATCH(7,Data!$B$2:$B$745,0))),"")&" "&IFERROR(IF(INDEX(Data!$AG$2:$AG$745,MATCH(7,Data!$B$2:$B$745,0))="","",INDEX(Data!$AG$2:$AG$745,MATCH(7,Data!$B$2:$B$745,0))),""))) | H21: =IF(B21="","",IFERROR(IF(INDEX(Data!$N$2:$N$745,MATCH(7,Data!$B$2:$B$745,0))="","",INDEX(Data!$N$2:$N$745,MATCH(7,Data!$B$2:$B$745,0))),"")) | I21: =IF(B21="","",IFERROR(IF(INDEX(Data!$O$2:$O$745,MATCH(7,Data!$B$2:$B$745,0))="","",INDEX(Data!$O$2:$O$745,MATCH(7,Data!$B$2:$B$745,0))),"")) | J21: =IF(B21="","",IFERROR(IF(INDEX(Data!$P$2:$P$745,MATCH(7,Data!$B$2:$B$745,0))="","",INDEX(Data!$P$2:$P$745,MATCH(7,Data!$B$2:$B$745,0))),"")) | K21: =IF(B21="","",IFERROR(IF(INDEX(Data!$R$2:$R$745,MATCH(7,Data!$B$2:$B$745,0))="","",INDEX(Data!$R$2:$R$745,MATCH(7,Data!$B$2:$B$745,0))),"")) | L21: =IF(B21="","",IFERROR(IF(INDEX(Data!$S$2:$S$745,MATCH(7,Data!$B$2:$B$745,0))="","",INDEX(Data!$S$2:$S$745,MATCH(7,Data!$B$2:$B$745,0))),"")) | M21: =IF(B21="","",IFERROR(IF(INDEX(Data!$T$2:$T$745,MATCH(7,Data!$B$2:$B$745,0))="","",INDEX(Data!$T$2:$T$745,MATCH(7,Data!$B$2:$B$745,0))),"")) | N21: =IF(B21="","",IFERROR(IF(INDEX(Data!$U$2:$U$745,MATCH(7,Data!$B$2:$B$745,0))="","",INDEX(Data!$U$2:$U$745,MATCH(7,Data!$B$2:$B$745,0))),"")) | O21: =IF(B21="","",IFERROR(IF(INDEX(Data!$V$2:$V$745,MATCH(7,Data!$B$2:$B$745,0))="","",INDEX(Data!$V$2:$V$745,MATCH(7,Data!$B$2:$B$745,0))),"")) | P21: =IF(B21="","",IFERROR(IF(INDEX(Data!$M$2:$M$745,MATCH(7,Data!$B$2:$B$745,0))="","",INDEX(Data!$M$2:$M$745,MATCH(7,Data!$B$2:$B$745,0))),"")) | Q21: =IF(B21="","",IFERROR(IF(INDEX(Data!$AD$2:$AD$745,MATCH(7,Data!$B$2:$B$745,0))="","",INDEX(Data!$AD$2:$AD$745,MATCH(7,Data!$B$2:$B$745,0))),"")) | R21: =IF(B21="","",IFERROR(IF(INDEX(Data!$L$2:$L$745,MATCH(7,Data!$B$2:$B$745,0))="","",INDEX(Data!$L$2:$L$745,MATCH(7,Data!$B$2:$B$745,0))),"")) | AA21: SL Cooling Pillowcase | AB21: Beatrice Home Fashions
B22: =IF(8<=COUNTIF(Data!$A$2:$A$745,TRUE),8,"") | C22: =IF(B22="","",IFERROR(_xlfn.IMAGE(IFERROR(IF(INDEX(Data!$J$2:$J$745,MATCH(8,Data!$B$2:$B$745,0))="","",INDEX(Data!$J$2:$J$745,MATCH(8,Data!$B$2:$B$745,0))),"")),"IMAGE COMING SOON")) | D22: =IF(B22="","",IFERROR(IF(INDEX(Data!$G$2:$G$745,MATCH(8,Data!$B$2:$B$745,0))="","",INDEX(Data!$G$2:$G$745,MATCH(8,Data!$B$2:$B$745,0))),"")&CHAR(10)&IFERROR(IF(INDEX(Data!$H$2:$H$745,MATCH(8,Data!$B$2:$B$745,0))="","",INDEX(Data!$H$2:$H$745,MATCH(8,Data!$B$2:$B$745,0))),"")) | E22: =IF(B22="","",IFERROR(IF(INDEX(Data!$I$2:$I$745,MATCH(8,Data!$B$2:$B$745,0))="","",INDEX(Data!$I$2:$I$745,MATCH(8,Data!$B$2:$B$745,0))),"")) | F22: =IF(B22="","",IFERROR(IF(INDEX(Data!$AJ$2:$AJ$745,MATCH(8,Data!$B$2:$B$745,0))="","",INDEX(Data!$AJ$2:$AJ$745,MATCH(8,Data!$B$2:$B$745,0))),"")) | G22: =IF(B22="","",TRIM(IFERROR(IF(INDEX(Data!$AF$2:$AF$745,MATCH(8,Data!$B$2:$B$745,0))="","",INDEX(Data!$AF$2:$AF$745,MATCH(8,Data!$B$2:$B$745,0))),"")&" "&IFERROR(IF(INDEX(Data!$AG$2:$AG$745,MATCH(8,Data!$B$2:$B$745,0))="","",INDEX(Data!$AG$2:$AG$745,MATCH(8,Data!$B$2:$B$745,0))),""))) | H22: =IF(B22="","",IFERROR(IF(INDEX(Data!$N$2:$N$745,MATCH(8,Data!$B$2:$B$745,0))="","",INDEX(Data!$N$2:$N$745,MATCH(8,Data!$B$2:$B$745,0))),"")) | I22: =IF(B22="","",IFERROR(IF(INDEX(Data!$O$2:$O$745,MATCH(8,Data!$B$2:$B$745,0))="","",INDEX(Data!$O$2:$O$745,MATCH(8,Data!$B$2:$B$745,0))),"")) | J22: =IF(B22="","",IFERROR(IF(INDEX(Data!$P$2:$P$745,MATCH(8,Data!$B$2:$B$745,0))="","",INDEX(Data!$P$2:$P$745,MATCH(8,Data!$B$2:$B$745,0))),"")) | K22: =IF(B22="","",IFERROR(IF(INDEX(Data!$R$2:$R$745,MATCH(8,Data!$B$2:$B$745,0))="","",INDEX(Data!$R$2:$R$745,MATCH(8,Data!$B$2:$B$745,0))),"")) | L22: =IF(B22="","",IFERROR(IF(INDEX(Data!$S$2:$S$745,MATCH(8,Data!$B$2:$B$745,0))="","",INDEX(Data!$S$2:$S$745,MATCH(8,Data!$B$2:$B$745,0))),"")) | M22: =IF(B22="","",IFERROR(IF(INDEX(Data!$T$2:$T$745,MATCH(8,Data!$B$2:$B$745,0))="","",INDEX(Data!$T$2:$T$745,MATCH(8,Data!$B$2:$B$745,0))),"")) | N22: =IF(B22="","",IFERROR(IF(INDEX(Data!$U$2:$U$745,MATCH(8,Data!$B$2:$B$745,0))="","",INDEX(Data!$U$2:$U$745,MATCH(8,Data!$B$2:$B$745,0))),"")) | O22: =IF(B22="","",IFERROR(IF(INDEX(Data!$V$2:$V$745,MATCH(8,Data!$B$2:$B$745,0))="","",INDEX(Data!$V$2:$V$745,MATCH(8,Data!$B$2:$B$745,0))),"")) | P22: =IF(B22="","",IFERROR(IF(INDEX(Data!$M$2:$M$745,MATCH(8,Data!$B$2:$B$745,0))="","",INDEX(Data!$M$2:$M$745,MATCH(8,Data!$B$2:$B$745,0))),"")) | Q22: =IF(B22="","",IFERROR(IF(INDEX(Data!$AD$2:$AD$745,MATCH(8,Data!$B$2:$B$745,0))="","",INDEX(Data!$AD$2:$AD$745,MATCH(8,Data!$B$2:$B$745,0))),"")) | R22: =IF(B22="","",IFERROR(IF(INDEX(Data!$L$2:$L$745,MATCH(8,Data!$B$2:$B$745,0))="","",INDEX(Data!$L$2:$L$745,MATCH(8,Data!$B$2:$B$745,0))),"")) | AA22: SL Cooling Comforter | AB22: BEDELITE
B23: =IF(9<=COUNTIF(Data!$A$2:$A$745,TRUE),9,"") | C23: =IF(B23="","",IFERROR(_xlfn.IMAGE(IFERROR(IF(INDEX(Data!$J$2:$J$745,MATCH(9,Data!$B$2:$B$745,0))="","",INDEX(Data!$J$2:$J$745,MATCH(9,Data!$B$2:$B$745,0))),"")),"IMAGE COMING SOON")) | D23: =IF(B23="","",IFERROR(IF(INDEX(Data!$G$2:$G$745,MATCH(9,Data!$B$2:$B$745,0))="","",INDEX(Data!$G$2:$G$745,MATCH(9,Data!$B$2:$B$745,0))),"")&CHAR(10)&IFERROR(IF(INDEX(Data!$H$2:$H$745,MATCH(9,Data!$B$2:$B$745,0))="","",INDEX(Data!$H$2:$H$745,MATCH(9,Data!$B$2:$B$745,0))),"")) | E23: =IF(B23="","",IFERROR(IF(INDEX(Data!$I$2:$I$745,MATCH(9,Data!$B$2:$B$745,0))="","",INDEX(Data!$I$2:$I$745,MATCH(9,Data!$B$2:$B$745,0))),"")) | F23: =IF(B23="","",IFERROR(IF(INDEX(Data!$AJ$2:$AJ$745,MATCH(9,Data!$B$2:$B$745,0))="","",INDEX(Data!$AJ$2:$AJ$745,MATCH(9,Data!$B$2:$B$745,0))),"")) | G23: =IF(B23="","",TRIM(IFERROR(IF(INDEX(Data!$AF$2:$AF$745,MATCH(9,Data!$B$2:$B$745,0))="","",INDEX(Data!$AF$2:$AF$745,MATCH(9,Data!$B$2:$B$745,0))),"")&" "&IFERROR(IF(INDEX(Data!$AG$2:$AG$745,MATCH(9,Data!$B$2:$B$745,0))="","",INDEX(Data!$AG$2:$AG$745,MATCH(9,Data!$B$2:$B$745,0))),""))) | H23: =IF(B23="","",IFERROR(IF(INDEX(Data!$N$2:$N$745,MATCH(9,Data!$B$2:$B$745,0))="","",INDEX(Data!$N$2:$N$745,MATCH(9,Data!$B$2:$B$745,0))),"")) | I23: =IF(B23="","",IFERROR(IF(INDEX(Data!$O$2:$O$745,MATCH(9,Data!$B$2:$B$745,0))="","",INDEX(Data!$O$2:$O$745,MATCH(9,Data!$B$2:$B$745,0))),"")) | J23: =IF(B23="","",IFERROR(IF(INDEX(Data!$P$2:$P$745,MATCH(9,Data!$B$2:$B$745,0))="","",INDEX(Data!$P$2:$P$745,MATCH(9,Data!$B$2:$B$745,0))),"")) | K23: =IF(B23="","",IFERROR(IF(INDEX(Data!$R$2:$R$745,MATCH(9,Data!$B$2:$B$745,0))="","",INDEX(Data!$R$2:$R$745,MATCH(9,Data!$B$2:$B$745,0))),"")) | L23: =IF(B23="","",IFERROR(IF(INDEX(Data!$S$2:$S$745,MATCH(9,Data!$B$2:$B$745,0))="","",INDEX(Data!$S$2:$S$745,MATCH(9,Data!$B$2:$B$745,0))),"")) | M23: =IF(B23="","",IFERROR(IF(INDEX(Data!$T$2:$T$745,MATCH(9,Data!$B$2:$B$745,0))="","",INDEX(Data!$T$2:$T$745,MATCH(9,Data!$B$2:$B$745,0))),"")) | N23: =IF(B23="","",IFERROR(IF(INDEX(Data!$U$2:$U$745,MATCH(9,Data!$B$2:$B$745,0))="","",INDEX(Data!$U$2:$U$745,MATCH(9,Data!$B$2:$B$745,0))),"")) | O23: =IF(B23="","",IFERROR(IF(INDEX(Data!$V$2:$V$745,MATCH(9,Data!$B$2:$B$745,0))="","",INDEX(Data!$V$2:$V$745,MATCH(9,Data!$B$2:$B$745,0))),"")) | P23: =IF(B23="","",IFERROR(IF(INDEX(Data!$M$2:$M$745,MATCH(9,Data!$B$2:$B$745,0))="","",INDEX(Data!$M$2:$M$745,MATCH(9,Data!$B$2:$B$745,0))),"")) | Q23: =IF(B23="","",IFERROR(IF(INDEX(Data!$AD$2:$AD$745,MATCH(9,Data!$B$2:$B$745,0))="","",INDEX(Data!$AD$2:$AD$745,MATCH(9,Data!$B$2:$B$745,0))),"")) | R23: =IF(B23="","",IFERROR(IF(INDEX(Data!$L$2:$L$745,MATCH(9,Data!$B$2:$B$745,0))="","",INDEX(Data!$L$2:$L$745,MATCH(9,Data!$B$2:$B$745,0))),"")) | AA23: SL Cooling Fitted | AB23: Bedlifes
B24: =IF(10<=COUNTIF(Data!$A$2:$A$745,TRUE),10,"") | C24: =IF(B24="","",IFERROR(_xlfn.IMAGE(IFERROR(IF(INDEX(Data!$J$2:$J$745,MATCH(10,Data!$B$2:$B$745,0))="","",INDEX(Data!$J$2:$J$745,MATCH(10,Data!$B$2:$B$745,0))),"")),"IMAGE COMING SOON")) | D24: =IF(B24="","",IFERROR(IF(INDEX(Data!$G$2:$G$745,MATCH(10,Data!$B$2:$B$745,0))="","",INDEX(Data!$G$2:$G$745,MATCH(10,Data!$B$2:$B$745,0))),"")&CHAR(10)&IFERROR(IF(INDEX(Data!$H$2:$H$745,MATCH(10,Data!$B$2:$B$745,0))="","",INDEX(Data!$H$2:$H$745,MATCH(10,Data!$B$2:$B$745,0))),"")) | E24: =IF(B24="","",IFERROR(IF(INDEX(Data!$I$2:$I$745,MATCH(10,Data!$B$2:$B$745,0))="","",INDEX(Data!$I$2:$I$745,MATCH(10,Data!$B$2:$B$745,0))),"")) | F24: =IF(B24="","",IFERROR(IF(INDEX(Data!$AJ$2:$AJ$745,MATCH(10,Data!$B$2:$B$745,0))="","",INDEX(Data!$AJ$2:$AJ$745,MATCH(10,Data!$B$2:$B$745,0))),"")) | G24: =IF(B24="","",TRIM(IFERROR(IF(INDEX(Data!$AF$2:$AF$745,MATCH(10,Data!$B$2:$B$745,0))="","",INDEX(Data!$AF$2:$AF$745,MATCH(10,Data!$B$2:$B$745,0))),"")&" "&IFERROR(IF(INDEX(Data!$AG$2:$AG$745,MATCH(10,Data!$B$2:$B$745,0))="","",INDEX(Data!$AG$2:$AG$745,MATCH(10,Data!$B$2:$B$745,0))),""))) | H24: =IF(B24="","",IFERROR(IF(INDEX(Data!$N$2:$N$745,MATCH(10,Data!$B$2:$B$745,0))="","",INDEX(Data!$N$2:$N$745,MATCH(10,Data!$B$2:$B$745,0))),"")) | I24: =IF(B24="","",IFERROR(IF(INDEX(Data!$O$2:$O$745,MATCH(10,Data!$B$2:$B$745,0))="","",INDEX(Data!$O$2:$O$745,MATCH(10,Data!$B$2:$B$745,0))),"")) | J24: =IF(B24="","",IFERROR(IF(INDEX(Data!$P$2:$P$745,MATCH(10,Data!$B$2:$B$745,0))="","",INDEX(Data!$P$2:$P$745,MATCH(10,Data!$B$2:$B$745,0))),"")) | K24: =IF(B24="","",IFERROR(IF(INDEX(Data!$R$2:$R$745,MATCH(10,Data!$B$2:$B$745,0))="","",INDEX(Data!$R$2:$R$745,MATCH(10,Data!$B$2:$B$745,0))),"")) | L24: =IF(B24="","",IFERROR(IF(INDEX(Data!$S$2:$S$745,MATCH(10,Data!$B$2:$B$745,0))="","",INDEX(Data!$S$2:$S$745,MATCH(10,Data!$B$2:$B$745,0))),"")) | M24: =IF(B24="","",IFERROR(IF(INDEX(Data!$T$2:$T$745,MATCH(10,Data!$B$2:$B$745,0))="","",INDEX(Data!$T$2:$T$745,MATCH(10,Data!$B$2:$B$745,0))),"")) | N24: =IF(B24="","",IFERROR(IF(INDEX(Data!$U$2:$U$745,MATCH(10,Data!$B$2:$B$745,0))="","",INDEX(Data!$U$2:$U$745,MATCH(10,Data!$B$2:$B$745,0))),"")) | O24: =IF(B24="","",IFERROR(IF(INDEX(Data!$V$2:$V$745,MATCH(10,Data!$B$2:$B$745,0))="","",INDEX(Data!$V$2:$V$745,MATCH(10,Data!$B$2:$B$745,0))),"")) | P24: =IF(B24="","",IFERROR(IF(INDEX(Data!$M$2:$M$745,MATCH(10,Data!$B$2:$B$745,0))="","",INDEX(Data!$M$2:$M$745,MATCH(10,Data!$B$2:$B$745,0))),"")) | Q24: =IF(B24="","",IFERROR(IF(INDEX(Data!$AD$2:$AD$745,MATCH(10,Data!$B$2:$B$745,0))="","",INDEX(Data!$AD$2:$AD$745,MATCH(10,Data!$B$2:$B$745,0))),"")) | R24: =IF(B24="","",IFERROR(IF(INDEX(Data!$L$2:$L$745,MATCH(10,Data!$B$2:$B$745,0))="","",INDEX(Data!$L$2:$L$745,MATCH(10,Data!$B$2:$B$745,0))),"")) | AA24: SL Quilt Set | AB24: bedsmile
B25: =IF(11<=COUNTIF(Data!$A$2:$A$745,TRUE),11,"") | C25: =IF(B25="","",IFERROR(_xlfn.IMAGE(IFERROR(IF(INDEX(Data!$J$2:$J$745,MATCH(11,Data!$B$2:$B$745,0))="","",INDEX(Data!$J$2:$J$745,MATCH(11,Data!$B$2:$B$745,0))),"")),"IMAGE COMING SOON")) | D25: =IF(B25="","",IFERROR(IF(INDEX(Data!$G$2:$G$745,MATCH(11,Data!$B$2:$B$745,0))="","",INDEX(Data!$G$2:$G$745,MATCH(11,Data!$B$2:$B$745,0))),"")&CHAR(10)&IFERROR(IF(INDEX(Data!$H$2:$H$745,MATCH(11,Data!$B$2:$B$745,0))="","",INDEX(Data!$H$2:$H$745,MATCH(11,Data!$B$2:$B$745,0))),"")) | E25: =IF(B25="","",IFERROR(IF(INDEX(Data!$I$2:$I$745,MATCH(11,Data!$B$2:$B$745,0))="","",INDEX(Data!$I$2:$I$745,MATCH(11,Data!$B$2:$B$745,0))),"")) | F25: =IF(B25="","",IFERROR(IF(INDEX(Data!$AJ$2:$AJ$745,MATCH(11,Data!$B$2:$B$745,0))="","",INDEX(Data!$AJ$2:$AJ$745,MATCH(11,Data!$B$2:$B$745,0))),"")) | G25: =IF(B25="","",TRIM(IFERROR(IF(INDEX(Data!$AF$2:$AF$745,MATCH(11,Data!$B$2:$B$745,0))="","",INDEX(Data!$AF$2:$AF$745,MATCH(11,Data!$B$2:$B$745,0))),"")&" "&IFERROR(IF(INDEX(Data!$AG$2:$AG$745,MATCH(11,Data!$B$2:$B$745,0))="","",INDEX(Data!$AG$2:$AG$745,MATCH(11,Data!$B$2:$B$745,0))),""))) | H25: =IF(B25="","",IFERROR(IF(INDEX(Data!$N$2:$N$745,MATCH(11,Data!$B$2:$B$745,0))="","",INDEX(Data!$N$2:$N$745,MATCH(11,Data!$B$2:$B$745,0))),"")) | I25: =IF(B25="","",IFERROR(IF(INDEX(Data!$O$2:$O$745,MATCH(11,Data!$B$2:$B$745,0))="","",INDEX(Data!$O$2:$O$745,MATCH(11,Data!$B$2:$B$745,0))),"")) | J25: =IF(B25="","",IFERROR(IF(INDEX(Data!$P$2:$P$745,MATCH(11,Data!$B$2:$B$745,0))="","",INDEX(Data!$P$2:$P$745,MATCH(11,Data!$B$2:$B$745,0))),"")) | K25: =IF(B25="","",IFERROR(IF(INDEX(Data!$R$2:$R$745,MATCH(11,Data!$B$2:$B$745,0))="","",INDEX(Data!$R$2:$R$745,MATCH(11,Data!$B$2:$B$745,0))),"")) | L25: =IF(B25="","",IFERROR(IF(INDEX(Data!$S$2:$S$745,MATCH(11,Data!$B$2:$B$745,0))="","",INDEX(Data!$S$2:$S$745,MATCH(11,Data!$B$2:$B$745,0))),"")) | M25: =IF(B25="","",IFERROR(IF(INDEX(Data!$T$2:$T$745,MATCH(11,Data!$B$2:$B$745,0))="","",INDEX(Data!$T$2:$T$745,MATCH(11,Data!$B$2:$B$745,0))),"")) | N25: =IF(B25="","",IFERROR(IF(INDEX(Data!$U$2:$U$745,MATCH(11,Data!$B$2:$B$745,0))="","",INDEX(Data!$U$2:$U$745,MATCH(11,Data!$B$2:$B$745,0))),"")) | O25: =IF(B25="","",IFERROR(IF(INDEX(Data!$V$2:$V$745,MATCH(11,Data!$B$2:$B$745,0))="","",INDEX(Data!$V$2:$V$745,MATCH(11,Data!$B$2:$B$745,0))),"")) | P25: =IF(B25="","",IFERROR(IF(INDEX(Data!$M$2:$M$745,MATCH(11,Data!$B$2:$B$745,0))="","",INDEX(Data!$M$2:$M$745,MATCH(11,Data!$B$2:$B$745,0))),"")) | Q25: =IF(B25="","",IFERROR(IF(INDEX(Data!$AD$2:$AD$745,MATCH(11,Data!$B$2:$B$745,0))="","",INDEX(Data!$AD$2:$AD$745,MATCH(11,Data!$B$2:$B$745,0))),"")) | R25: =IF(B25="","",IFERROR(IF(INDEX(Data!$L$2:$L$745,MATCH(11,Data!$B$2:$B$745,0))="","",INDEX(Data!$L$2:$L$745,MATCH(11,Data!$B$2:$B$745,0))),"")) | AA25: DC Linen Curtains | AB25: Bedsure
B26: =IF(12<=COUNTIF(Data!$A$2:$A$745,TRUE),12,"") | C26: =IF(B26="","",IFERROR(_xlfn.IMAGE(IFERROR(IF(INDEX(Data!$J$2:$J$745,MATCH(12,Data!$B$2:$B$745,0))="","",INDEX(Data!$J$2:$J$745,MATCH(12,Data!$B$2:$B$745,0))),"")),"IMAGE COMING SOON")) | D26: =IF(B26="","",IFERROR(IF(INDEX(Data!$G$2:$G$745,MATCH(12,Data!$B$2:$B$745,0))="","",INDEX(Data!$G$2:$G$745,MATCH(12,Data!$B$2:$B$745,0))),"")&CHAR(10)&IFERROR(IF(INDEX(Data!$H$2:$H$745,MATCH(12,Data!$B$2:$B$745,0))="","",INDEX(Data!$H$2:$H$745,MATCH(12,Data!$B$2:$B$745,0))),"")) | E26: =IF(B26="","",IFERROR(IF(INDEX(Data!$I$2:$I$745,MATCH(12,Data!$B$2:$B$745,0))="","",INDEX(Data!$I$2:$I$745,MATCH(12,Data!$B$2:$B$745,0))),"")) | F26: =IF(B26="","",IFERROR(IF(INDEX(Data!$AJ$2:$AJ$745,MATCH(12,Data!$B$2:$B$745,0))="","",INDEX(Data!$AJ$2:$AJ$745,MATCH(12,Data!$B$2:$B$745,0))),"")) | G26: =IF(B26="","",TRIM(IFERROR(IF(INDEX(Data!$AF$2:$AF$745,MATCH(12,Data!$B$2:$B$745,0))="","",INDEX(Data!$AF$2:$AF$745,MATCH(12,Data!$B$2:$B$745,0))),"")&" "&IFERROR(IF(INDEX(Data!$AG$2:$AG$745,MATCH(12,Data!$B$2:$B$745,0))="","",INDEX(Data!$AG$2:$AG$745,MATCH(12,Data!$B$2:$B$745,0))),""))) | H26: =IF(B26="","",IFERROR(IF(INDEX(Data!$N$2:$N$745,MATCH(12,Data!$B$2:$B$745,0))="","",INDEX(Data!$N$2:$N$745,MATCH(12,Data!$B$2:$B$745,0))),"")) | I26: =IF(B26="","",IFERROR(IF(INDEX(Data!$O$2:$O$745,MATCH(12,Data!$B$2:$B$745,0))="","",INDEX(Data!$O$2:$O$745,MATCH(12,Data!$B$2:$B$745,0))),"")) | J26: =IF(B26="","",IFERROR(IF(INDEX(Data!$P$2:$P$745,MATCH(12,Data!$B$2:$B$745,0))="","",INDEX(Data!$P$2:$P$745,MATCH(12,Data!$B$2:$B$745,0))),"")) | K26: =IF(B26="","",IFERROR(IF(INDEX(Data!$R$2:$R$745,MATCH(12,Data!$B$2:$B$745,0))="","",INDEX(Data!$R$2:$R$745,MATCH(12,Data!$B$2:$B$745,0))),"")) | L26: =IF(B26="","",IFERROR(IF(INDEX(Data!$S$2:$S$745,MATCH(12,Data!$B$2:$B$745,0))="","",INDEX(Data!$S$2:$S$745,MATCH(12,Data!$B$2:$B$745,0))),"")) | M26: =IF(B26="","",IFERROR(IF(INDEX(Data!$T$2:$T$745,MATCH(12,Data!$B$2:$B$745,0))="","",INDEX(Data!$T$2:$T$745,MATCH(12,Data!$B$2:$B$745,0))),"")) | N26: =IF(B26="","",IFERROR(IF(INDEX(Data!$U$2:$U$745,MATCH(12,Data!$B$2:$B$745,0))="","",INDEX(Data!$U$2:$U$745,MATCH(12,Data!$B$2:$B$745,0))),"")) | O26: =IF(B26="","",IFERROR(IF(INDEX(Data!$V$2:$V$745,MATCH(12,Data!$B$2:$B$745,0))="","",INDEX(Data!$V$2:$V$745,MATCH(12,Data!$B$2:$B$745,0))),"")) | P26: =IF(B26="","",IFERROR(IF(INDEX(Data!$M$2:$M$745,MATCH(12,Data!$B$2:$B$745,0))="","",INDEX(Data!$M$2:$M$745,MATCH(12,Data!$B$2:$B$745,0))),"")) | Q26: =IF(B26="","",IFERROR(IF(INDEX(Data!$AD$2:$AD$745,MATCH(12,Data!$B$2:$B$745,0))="","",INDEX(Data!$AD$2:$AD$745,MATCH(12,Data!$B$2:$B$745,0))),"")) | R26: =IF(B26="","",IFERROR(IF(INDEX(Data!$L$2:$L$745,MATCH(12,Data!$B$2:$B$745,0))="","",INDEX(Data!$L$2:$L$745,MATCH(12,Data!$B$2:$B$745,0))),"")) | AA26: DC Beach Towel | AB26: Bedtter
B27: =IF(13<=COUNTIF(Data!$A$2:$A$745,TRUE),13,"") | C27: =IF(B27="","",IFERROR(_xlfn.IMAGE(IFERROR(IF(INDEX(Data!$J$2:$J$745,MATCH(13,Data!$B$2:$B$745,0))="","",INDEX(Data!$J$2:$J$745,MATCH(13,Data!$B$2:$B$745,0))),"")),"IMAGE COMING SOON")) | D27: =IF(B27="","",IFERROR(IF(INDEX(Data!$G$2:$G$745,MATCH(13,Data!$B$2:$B$745,0))="","",INDEX(Data!$G$2:$G$745,MATCH(13,Data!$B$2:$B$745,0))),"")&CHAR(10)&IFERROR(IF(INDEX(Data!$H$2:$H$745,MATCH(13,Data!$B$2:$B$745,0))="","",INDEX(Data!$H$2:$H$745,MATCH(13,Data!$B$2:$B$745,0))),"")) | E27: =IF(B27="","",IFERROR(IF(INDEX(Data!$I$2:$I$745,MATCH(13,Data!$B$2:$B$745,0))="","",INDEX(Data!$I$2:$I$745,MATCH(13,Data!$B$2:$B$745,0))),"")) | F27: =IF(B27="","",IFERROR(IF(INDEX(Data!$AJ$2:$AJ$745,MATCH(13,Data!$B$2:$B$745,0))="","",INDEX(Data!$AJ$2:$AJ$745,MATCH(13,Data!$B$2:$B$745,0))),"")) | G27: =IF(B27="","",TRIM(IFERROR(IF(INDEX(Data!$AF$2:$AF$745,MATCH(13,Data!$B$2:$B$745,0))="","",INDEX(Data!$AF$2:$AF$745,MATCH(13,Data!$B$2:$B$745,0))),"")&" "&IFERROR(IF(INDEX(Data!$AG$2:$AG$745,MATCH(13,Data!$B$2:$B$745,0))="","",INDEX(Data!$AG$2:$AG$745,MATCH(13,Data!$B$2:$B$745,0))),""))) | H27: =IF(B27="","",IFERROR(IF(INDEX(Data!$N$2:$N$745,MATCH(13,Data!$B$2:$B$745,0))="","",INDEX(Data!$N$2:$N$745,MATCH(13,Data!$B$2:$B$745,0))),"")) | I27: =IF(B27="","",IFERROR(IF(INDEX(Data!$O$2:$O$745,MATCH(13,Data!$B$2:$B$745,0))="","",INDEX(Data!$O$2:$O$745,MATCH(13,Data!$B$2:$B$745,0))),"")) | J27: =IF(B27="","",IFERROR(IF(INDEX(Data!$P$2:$P$745,MATCH(13,Data!$B$2:$B$745,0))="","",INDEX(Data!$P$2:$P$745,MATCH(13,Data!$B$2:$B$745,0))),"")) | K27: =IF(B27="","",IFERROR(IF(INDEX(Data!$R$2:$R$745,MATCH(13,Data!$B$2:$B$745,0))="","",INDEX(Data!$R$2:$R$745,MATCH(13,Data!$B$2:$B$745,0))),"")) | L27: =IF(B27="","",IFERROR(IF(INDEX(Data!$S$2:$S$745,MATCH(13,Data!$B$2:$B$745,0))="","",INDEX(Data!$S$2:$S$745,MATCH(13,Data!$B$2:$B$745,0))),"")) | M27: =IF(B27="","",IFERROR(IF(INDEX(Data!$T$2:$T$745,MATCH(13,Data!$B$2:$B$745,0))="","",INDEX(Data!$T$2:$T$745,MATCH(13,Data!$B$2:$B$745,0))),"")) | N27: =IF(B27="","",IFERROR(IF(INDEX(Data!$U$2:$U$745,MATCH(13,Data!$B$2:$B$745,0))="","",INDEX(Data!$U$2:$U$745,MATCH(13,Data!$B$2:$B$745,0))),"")) | O27: =IF(B27="","",IFERROR(IF(INDEX(Data!$V$2:$V$745,MATCH(13,Data!$B$2:$B$745,0))="","",INDEX(Data!$V$2:$V$745,MATCH(13,Data!$B$2:$B$745,0))),"")) | P27: =IF(B27="","",IFERROR(IF(INDEX(Data!$M$2:$M$745,MATCH(13,Data!$B$2:$B$745,0))="","",INDEX(Data!$M$2:$M$745,MATCH(13,Data!$B$2:$B$745,0))),"")) | Q27: =IF(B27="","",IFERROR(IF(INDEX(Data!$AD$2:$AD$745,MATCH(13,Data!$B$2:$B$745,0))="","",INDEX(Data!$AD$2:$AD$745,MATCH(13,Data!$B$2:$B$745,0))),"")) | R27: =IF(B27="","",IFERROR(IF(INDEX(Data!$L$2:$L$745,MATCH(13,Data!$B$2:$B$745,0))="","",INDEX(Data!$L$2:$L$745,MATCH(13,Data!$B$2:$B$745,0))),"")) | AA27: DC Welcome Sign | AB27: BGment
B28: =IF(14<=COUNTIF(Data!$A$2:$A$745,TRUE),14,"") | C28: =IF(B28="","",IFERROR(_xlfn.IMAGE(IFERROR(IF(INDEX(Data!$J$2:$J$745,MATCH(14,Data!$B$2:$B$745,0))="","",INDEX(Data!$J$2:$J$745,MATCH(14,Data!$B$2:$B$745,0))),"")),"IMAGE COMING SOON")) | D28: =IF(B28="","",IFERROR(IF(INDEX(Data!$G$2:$G$745,MATCH(14,Data!$B$2:$B$745,0))="","",INDEX(Data!$G$2:$G$745,MATCH(14,Data!$B$2:$B$745,0))),"")&CHAR(10)&IFERROR(IF(INDEX(Data!$H$2:$H$745,MATCH(14,Data!$B$2:$B$745,0))="","",INDEX(Data!$H$2:$H$745,MATCH(14,Data!$B$2:$B$745,0))),"")) | E28: =IF(B28="","",IFERROR(IF(INDEX(Data!$I$2:$I$745,MATCH(14,Data!$B$2:$B$745,0))="","",INDEX(Data!$I$2:$I$745,MATCH(14,Data!$B$2:$B$745,0))),"")) | F28: =IF(B28="","",IFERROR(IF(INDEX(Data!$AJ$2:$AJ$745,MATCH(14,Data!$B$2:$B$745,0))="","",INDEX(Data!$AJ$2:$AJ$745,MATCH(14,Data!$B$2:$B$745,0))),"")) | G28: =IF(B28="","",TRIM(IFERROR(IF(INDEX(Data!$AF$2:$AF$745,MATCH(14,Data!$B$2:$B$745,0))="","",INDEX(Data!$AF$2:$AF$745,MATCH(14,Data!$B$2:$B$745,0))),"")&" "&IFERROR(IF(INDEX(Data!$AG$2:$AG$745,MATCH(14,Data!$B$2:$B$745,0))="","",INDEX(Data!$AG$2:$AG$745,MATCH(14,Data!$B$2:$B$745,0))),""))) | H28: =IF(B28="","",IFERROR(IF(INDEX(Data!$N$2:$N$745,MATCH(14,Data!$B$2:$B$745,0))="","",INDEX(Data!$N$2:$N$745,MATCH(14,Data!$B$2:$B$745,0))),"")) | I28: =IF(B28="","",IFERROR(IF(INDEX(Data!$O$2:$O$745,MATCH(14,Data!$B$2:$B$745,0))="","",INDEX(Data!$O$2:$O$745,MATCH(14,Data!$B$2:$B$745,0))),"")) | J28: =IF(B28="","",IFERROR(IF(INDEX(Data!$P$2:$P$745,MATCH(14,Data!$B$2:$B$745,0))="","",INDEX(Data!$P$2:$P$745,MATCH(14,Data!$B$2:$B$745,0))),"")) | K28: =IF(B28="","",IFERROR(IF(INDEX(Data!$R$2:$R$745,MATCH(14,Data!$B$2:$B$745,0))="","",INDEX(Data!$R$2:$R$745,MATCH(14,Data!$B$2:$B$745,0))),"")) | L28: =IF(B28="","",IFERROR(IF(INDEX(Data!$S$2:$S$745,MATCH(14,Data!$B$2:$B$745,0))="","",INDEX(Data!$S$2:$S$745,MATCH(14,Data!$B$2:$B$745,0))),"")) | M28: =IF(B28="","",IFERROR(IF(INDEX(Data!$T$2:$T$745,MATCH(14,Data!$B$2:$B$745,0))="","",INDEX(Data!$T$2:$T$745,MATCH(14,Data!$B$2:$B$745,0))),"")) | N28: =IF(B28="","",IFERROR(IF(INDEX(Data!$U$2:$U$745,MATCH(14,Data!$B$2:$B$745,0))="","",INDEX(Data!$U$2:$U$745,MATCH(14,Data!$B$2:$B$745,0))),"")) | O28: =IF(B28="","",IFERROR(IF(INDEX(Data!$V$2:$V$745,MATCH(14,Data!$B$2:$B$745,0))="","",INDEX(Data!$V$2:$V$745,MATCH(14,Data!$B$2:$B$745,0))),"")) | P28: =IF(B28="","",IFERROR(IF(INDEX(Data!$M$2:$M$745,MATCH(14,Data!$B$2:$B$745,0))="","",INDEX(Data!$M$2:$M$745,MATCH(14,Data!$B$2:$B$745,0))),"")) | Q28: =IF(B28="","",IFERROR(IF(INDEX(Data!$AD$2:$AD$745,MATCH(14,Data!$B$2:$B$745,0))="","",INDEX(Data!$AD$2:$AD$745,MATCH(14,Data!$B$2:$B$745,0))),"")) | R28: =IF(B28="","",IFERROR(IF(INDEX(Data!$L$2:$L$745,MATCH(14,Data!$B$2:$B$745,0))="","",INDEX(Data!$L$2:$L$745,MATCH(14,Data!$B$2:$B$745,0))),"")) | AA28: DC Chair Cover | AB28: BIETYONE
B29: =IF(15<=COUNTIF(Data!$A$2:$A$745,TRUE),15,"") | C29: =IF(B29="","",IFERROR(_xlfn.IMAGE(IFERROR(IF(INDEX(Data!$J$2:$J$745,MATCH(15,Data!$B$2:$B$745,0))="","",INDEX(Data!$J$2:$J$745,MATCH(15,Data!$B$2:$B$745,0))),"")),"IMAGE COMING SOON")) | D29: =IF(B29="","",IFERROR(IF(INDEX(Data!$G$2:$G$745,MATCH(15,Data!$B$2:$B$745,0))="","",INDEX(Data!$G$2:$G$745,MATCH(15,Data!$B$2:$B$745,0))),"")&CHAR(10)&IFERROR(IF(INDEX(Data!$H$2:$H$745,MATCH(15,Data!$B$2:$B$745,0))="","",INDEX(Data!$H$2:$H$745,MATCH(15,Data!$B$2:$B$745,0))),"")) | E29: =IF(B29="","",IFERROR(IF(INDEX(Data!$I$2:$I$745,MATCH(15,Data!$B$2:$B$745,0))="","",INDEX(Data!$I$2:$I$745,MATCH(15,Data!$B$2:$B$745,0))),"")) | F29: =IF(B29="","",IFERROR(IF(INDEX(Data!$AJ$2:$AJ$745,MATCH(15,Data!$B$2:$B$745,0))="","",INDEX(Data!$AJ$2:$AJ$745,MATCH(15,Data!$B$2:$B$745,0))),"")) | G29: =IF(B29="","",TRIM(IFERROR(IF(INDEX(Data!$AF$2:$AF$745,MATCH(15,Data!$B$2:$B$745,0))="","",INDEX(Data!$AF$2:$AF$745,MATCH(15,Data!$B$2:$B$745,0))),"")&" "&IFERROR(IF(INDEX(Data!$AG$2:$AG$745,MATCH(15,Data!$B$2:$B$745,0))="","",INDEX(Data!$AG$2:$AG$745,MATCH(15,Data!$B$2:$B$745,0))),""))) | H29: =IF(B29="","",IFERROR(IF(INDEX(Data!$N$2:$N$745,MATCH(15,Data!$B$2:$B$745,0))="","",INDEX(Data!$N$2:$N$745,MATCH(15,Data!$B$2:$B$745,0))),"")) | I29: =IF(B29="","",IFERROR(IF(INDEX(Data!$O$2:$O$745,MATCH(15,Data!$B$2:$B$745,0))="","",INDEX(Data!$O$2:$O$745,MATCH(15,Data!$B$2:$B$745,0))),"")) | J29: =IF(B29="","",IFERROR(IF(INDEX(Data!$P$2:$P$745,MATCH(15,Data!$B$2:$B$745,0))="","",INDEX(Data!$P$2:$P$745,MATCH(15,Data!$B$2:$B$745,0))),"")) | K29: =IF(B29="","",IFERROR(IF(INDEX(Data!$R$2:$R$745,MATCH(15,Data!$B$2:$B$745,0))="","",INDEX(Data!$R$2:$R$745,MATCH(15,Data!$B$2:$B$745,0))),"")) | L29: =IF(B29="","",IFERROR(IF(INDEX(Data!$S$2:$S$745,MATCH(15,Data!$B$2:$B$745,0))="","",INDEX(Data!$S$2:$S$745,MATCH(15,Data!$B$2:$B$745,0))),"")) | M29: =IF(B29="","",IFERROR(IF(INDEX(Data!$T$2:$T$745,MATCH(15,Data!$B$2:$B$745,0))="","",INDEX(Data!$T$2:$T$745,MATCH(15,Data!$B$2:$B$745,0))),"")) | N29: =IF(B29="","",IFERROR(IF(INDEX(Data!$U$2:$U$745,MATCH(15,Data!$B$2:$B$745,0))="","",INDEX(Data!$U$2:$U$745,MATCH(15,Data!$B$2:$B$745,0))),"")) | O29: =IF(B29="","",IFERROR(IF(INDEX(Data!$V$2:$V$745,MATCH(15,Data!$B$2:$B$745,0))="","",INDEX(Data!$V$2:$V$745,MATCH(15,Data!$B$2:$B$745,0))),"")) | P29: =IF(B29="","",IFERROR(IF(INDEX(Data!$M$2:$M$745,MATCH(15,Data!$B$2:$B$745,0))="","",INDEX(Data!$M$2:$M$745,MATCH(15,Data!$B$2:$B$745,0))),"")) | Q29: =IF(B29="","",IFERROR(IF(INDEX(Data!$AD$2:$AD$745,MATCH(15,Data!$B$2:$B$745,0))="","",INDEX(Data!$AD$2:$AD$745,MATCH(15,Data!$B$2:$B$745,0))),"")) | R29: =IF(B29="","",IFERROR(IF(INDEX(Data!$L$2:$L$745,MATCH(15,Data!$B$2:$B$745,0))="","",INDEX(Data!$L$2:$L$745,MATCH(15,Data!$B$2:$B$745,0))),"")) | AB29: BLISSFORD
B30: =IF(16<=COUNTIF(Data!$A$2:$A$745,TRUE),16,"") | C30: =IF(B30="","",IFERROR(_xlfn.IMAGE(IFERROR(IF(INDEX(Data!$J$2:$J$745,MATCH(16,Data!$B$2:$B$745,0))="","",INDEX(Data!$J$2:$J$745,MATCH(16,Data!$B$2:$B$745,0))),"")),"IMAGE COMING SOON")) | D30: =IF(B30="","",IFERROR(IF(INDEX(Data!$G$2:$G$745,MATCH(16,Data!$B$2:$B$745,0))="","",INDEX(Data!$G$2:$G$745,MATCH(16,Data!$B$2:$B$745,0))),"")&CHAR(10)&IFERROR(IF(INDEX(Data!$H$2:$H$745,MATCH(16,Data!$B$2:$B$745,0))="","",INDEX(Data!$H$2:$H$745,MATCH(16,Data!$B$2:$B$745,0))),"")) | E30: =IF(B30="","",IFERROR(IF(INDEX(Data!$I$2:$I$745,MATCH(16,Data!$B$2:$B$745,0))="","",INDEX(Data!$I$2:$I$745,MATCH(16,Data!$B$2:$B$745,0))),"")) | F30: =IF(B30="","",IFERROR(IF(INDEX(Data!$AJ$2:$AJ$745,MATCH(16,Data!$B$2:$B$745,0))="","",INDEX(Data!$AJ$2:$AJ$745,MATCH(16,Data!$B$2:$B$745,0))),"")) | G30: =IF(B30="","",TRIM(IFERROR(IF(INDEX(Data!$AF$2:$AF$745,MATCH(16,Data!$B$2:$B$745,0))="","",INDEX(Data!$AF$2:$AF$745,MATCH(16,Data!$B$2:$B$745,0))),"")&" "&IFERROR(IF(INDEX(Data!$AG$2:$AG$745,MATCH(16,Data!$B$2:$B$745,0))="","",INDEX(Data!$AG$2:$AG$745,MATCH(16,Data!$B$2:$B$745,0))),""))) | H30: =IF(B30="","",IFERROR(IF(INDEX(Data!$N$2:$N$745,MATCH(16,Data!$B$2:$B$745,0))="","",INDEX(Data!$N$2:$N$745,MATCH(16,Data!$B$2:$B$745,0))),"")) | I30: =IF(B30="","",IFERROR(IF(INDEX(Data!$O$2:$O$745,MATCH(16,Data!$B$2:$B$745,0))="","",INDEX(Data!$O$2:$O$745,MATCH(16,Data!$B$2:$B$745,0))),"")) | J30: =IF(B30="","",IFERROR(IF(INDEX(Data!$P$2:$P$745,MATCH(16,Data!$B$2:$B$745,0))="","",INDEX(Data!$P$2:$P$745,MATCH(16,Data!$B$2:$B$745,0))),"")) | K30: =IF(B30="","",IFERROR(IF(INDEX(Data!$R$2:$R$745,MATCH(16,Data!$B$2:$B$745,0))="","",INDEX(Data!$R$2:$R$745,MATCH(16,Data!$B$2:$B$745,0))),"")) | L30: =IF(B30="","",IFERROR(IF(INDEX(Data!$S$2:$S$745,MATCH(16,Data!$B$2:$B$745,0))="","",INDEX(Data!$S$2:$S$745,MATCH(16,Data!$B$2:$B$745,0))),"")) | M30: =IF(B30="","",IFERROR(IF(INDEX(Data!$T$2:$T$745,MATCH(16,Data!$B$2:$B$745,0))="","",INDEX(Data!$T$2:$T$745,MATCH(16,Data!$B$2:$B$745,0))),"")) | N30: =IF(B30="","",IFERROR(IF(INDEX(Data!$U$2:$U$745,MATCH(16,Data!$B$2:$B$745,0))="","",INDEX(Data!$U$2:$U$745,MATCH(16,Data!$B$2:$B$745,0))),"")) | O30: =IF(B30="","",IFERROR(IF(INDEX(Data!$V$2:$V$745,MATCH(16,Data!$B$2:$B$745,0))="","",INDEX(Data!$V$2:$V$745,MATCH(16,Data!$B$2:$B$745,0))),"")) | P30: =IF(B30="","",IFERROR(IF(INDEX(Data!$M$2:$M$745,MATCH(16,Data!$B$2:$B$745,0))="","",INDEX(Data!$M$2:$M$745,MATCH(16,Data!$B$2:$B$745,0))),"")) | Q30: =IF(B30="","",IFERROR(IF(INDEX(Data!$AD$2:$AD$745,MATCH(16,Data!$B$2:$B$745,0))="","",INDEX(Data!$AD$2:$AD$745,MATCH(16,Data!$B$2:$B$745,0))),"")) | R30: =IF(B30="","",IFERROR(IF(INDEX(Data!$L$2:$L$745,MATCH(16,Data!$B$2:$B$745,0))="","",INDEX(Data!$L$2:$L$745,MATCH(16,Data!$B$2:$B$745,0))),"")) | AB30: BLISSY
B31: =IF(17<=COUNTIF(Data!$A$2:$A$745,TRUE),17,"") | C31: =IF(B31="","",IFERROR(_xlfn.IMAGE(IFERROR(IF(INDEX(Data!$J$2:$J$745,MATCH(17,Data!$B$2:$B$745,0))="","",INDEX(Data!$J$2:$J$745,MATCH(17,Data!$B$2:$B$745,0))),"")),"IMAGE COMING SOON")) | D31: =IF(B31="","",IFERROR(IF(INDEX(Data!$G$2:$G$745,MATCH(17,Data!$B$2:$B$745,0))="","",INDEX(Data!$G$2:$G$745,MATCH(17,Data!$B$2:$B$745,0))),"")&CHAR(10)&IFERROR(IF(INDEX(Data!$H$2:$H$745,MATCH(17,Data!$B$2:$B$745,0))="","",INDEX(Data!$H$2:$H$745,MATCH(17,Data!$B$2:$B$745,0))),"")) | E31: =IF(B31="","",IFERROR(IF(INDEX(Data!$I$2:$I$745,MATCH(17,Data!$B$2:$B$745,0))="","",INDEX(Data!$I$2:$I$745,MATCH(17,Data!$B$2:$B$745,0))),"")) | F31: =IF(B31="","",IFERROR(IF(INDEX(Data!$AJ$2:$AJ$745,MATCH(17,Data!$B$2:$B$745,0))="","",INDEX(Data!$AJ$2:$AJ$745,MATCH(17,Data!$B$2:$B$745,0))),"")) | G31: =IF(B31="","",TRIM(IFERROR(IF(INDEX(Data!$AF$2:$AF$745,MATCH(17,Data!$B$2:$B$745,0))="","",INDEX(Data!$AF$2:$AF$745,MATCH(17,Data!$B$2:$B$745,0))),"")&" "&IFERROR(IF(INDEX(Data!$AG$2:$AG$745,MATCH(17,Data!$B$2:$B$745,0))="","",INDEX(Data!$AG$2:$AG$745,MATCH(17,Data!$B$2:$B$745,0))),""))) | H31: =IF(B31="","",IFERROR(IF(INDEX(Data!$N$2:$N$745,MATCH(17,Data!$B$2:$B$745,0))="","",INDEX(Data!$N$2:$N$745,MATCH(17,Data!$B$2:$B$745,0))),"")) | I31: =IF(B31="","",IFERROR(IF(INDEX(Data!$O$2:$O$745,MATCH(17,Data!$B$2:$B$745,0))="","",INDEX(Data!$O$2:$O$745,MATCH(17,Data!$B$2:$B$745,0))),"")) | J31: =IF(B31="","",IFERROR(IF(INDEX(Data!$P$2:$P$745,MATCH(17,Data!$B$2:$B$745,0))="","",INDEX(Data!$P$2:$P$745,MATCH(17,Data!$B$2:$B$745,0))),"")) | K31: =IF(B31="","",IFERROR(IF(INDEX(Data!$R$2:$R$745,MATCH(17,Data!$B$2:$B$745,0))="","",INDEX(Data!$R$2:$R$745,MATCH(17,Data!$B$2:$B$745,0))),"")) | L31: =IF(B31="","",IFERROR(IF(INDEX(Data!$S$2:$S$745,MATCH(17,Data!$B$2:$B$745,0))="","",INDEX(Data!$S$2:$S$745,MATCH(17,Data!$B$2:$B$745,0))),"")) | M31: =IF(B31="","",IFERROR(IF(INDEX(Data!$T$2:$T$745,MATCH(17,Data!$B$2:$B$745,0))="","",INDEX(Data!$T$2:$T$745,MATCH(17,Data!$B$2:$B$745,0))),"")) | N31: =IF(B31="","",IFERROR(IF(INDEX(Data!$U$2:$U$745,MATCH(17,Data!$B$2:$B$745,0))="","",INDEX(Data!$U$2:$U$745,MATCH(17,Data!$B$2:$B$745,0))),"")) | O31: =IF(B31="","",IFERROR(IF(INDEX(Data!$V$2:$V$745,MATCH(17,Data!$B$2:$B$745,0))="","",INDEX(Data!$V$2:$V$745,MATCH(17,Data!$B$2:$B$745,0))),"")) | P31: =IF(B31="","",IFERROR(IF(INDEX(Data!$M$2:$M$745,MATCH(17,Data!$B$2:$B$745,0))="","",INDEX(Data!$M$2:$M$745,MATCH(17,Data!$B$2:$B$745,0))),"")) | Q31: =IF(B31="","",IFERROR(IF(INDEX(Data!$AD$2:$AD$745,MATCH(17,Data!$B$2:$B$745,0))="","",INDEX(Data!$AD$2:$AD$745,MATCH(17,Data!$B$2:$B$745,0))),"")) | R31: =IF(B31="","",IFERROR(IF(INDEX(Data!$L$2:$L$745,MATCH(17,Data!$B$2:$B$745,0))="","",INDEX(Data!$L$2:$L$745,MATCH(17,Data!$B$2:$B$745,0))),"")) | AB31: BLSSNZ
B32: =IF(18<=COUNTIF(Data!$A$2:$A$745,TRUE),18,"") | C32: =IF(B32="","",IFERROR(_xlfn.IMAGE(IFERROR(IF(INDEX(Data!$J$2:$J$745,MATCH(18,Data!$B$2:$B$745,0))="","",INDEX(Data!$J$2:$J$745,MATCH(18,Data!$B$2:$B$745,0))),"")),"IMAGE COMING SOON")) | D32: =IF(B32="","",IFERROR(IF(INDEX(Data!$G$2:$G$745,MATCH(18,Data!$B$2:$B$745,0))="","",INDEX(Data!$G$2:$G$745,MATCH(18,Data!$B$2:$B$745,0))),"")&CHAR(10)&IFERROR(IF(INDEX(Data!$H$2:$H$745,MATCH(18,Data!$B$2:$B$745,0))="","",INDEX(Data!$H$2:$H$745,MATCH(18,Data!$B$2:$B$745,0))),"")) | E32: =IF(B32="","",IFERROR(IF(INDEX(Data!$I$2:$I$745,MATCH(18,Data!$B$2:$B$745,0))="","",INDEX(Data!$I$2:$I$745,MATCH(18,Data!$B$2:$B$745,0))),"")) | F32: =IF(B32="","",IFERROR(IF(INDEX(Data!$AJ$2:$AJ$745,MATCH(18,Data!$B$2:$B$745,0))="","",INDEX(Data!$AJ$2:$AJ$745,MATCH(18,Data!$B$2:$B$745,0))),"")) | G32: =IF(B32="","",TRIM(IFERROR(IF(INDEX(Data!$AF$2:$AF$745,MATCH(18,Data!$B$2:$B$745,0))="","",INDEX(Data!$AF$2:$AF$745,MATCH(18,Data!$B$2:$B$745,0))),"")&" "&IFERROR(IF(INDEX(Data!$AG$2:$AG$745,MATCH(18,Data!$B$2:$B$745,0))="","",INDEX(Data!$AG$2:$AG$745,MATCH(18,Data!$B$2:$B$745,0))),""))) | H32: =IF(B32="","",IFERROR(IF(INDEX(Data!$N$2:$N$745,MATCH(18,Data!$B$2:$B$745,0))="","",INDEX(Data!$N$2:$N$745,MATCH(18,Data!$B$2:$B$745,0))),"")) | I32: =IF(B32="","",IFERROR(IF(INDEX(Data!$O$2:$O$745,MATCH(18,Data!$B$2:$B$745,0))="","",INDEX(Data!$O$2:$O$745,MATCH(18,Data!$B$2:$B$745,0))),"")) | J32: =IF(B32="","",IFERROR(IF(INDEX(Data!$P$2:$P$745,MATCH(18,Data!$B$2:$B$745,0))="","",INDEX(Data!$P$2:$P$745,MATCH(18,Data!$B$2:$B$745,0))),"")) | K32: =IF(B32="","",IFERROR(IF(INDEX(Data!$R$2:$R$745,MATCH(18,Data!$B$2:$B$745,0))="","",INDEX(Data!$R$2:$R$745,MATCH(18,Data!$B$2:$B$745,0))),"")) | L32: =IF(B32="","",IFERROR(IF(INDEX(Data!$S$2:$S$745,MATCH(18,Data!$B$2:$B$745,0))="","",INDEX(Data!$S$2:$S$745,MATCH(18,Data!$B$2:$B$745,0))),"")) | M32: =IF(B32="","",IFERROR(IF(INDEX(Data!$T$2:$T$745,MATCH(18,Data!$B$2:$B$745,0))="","",INDEX(Data!$T$2:$T$745,MATCH(18,Data!$B$2:$B$745,0))),"")) | N32: =IF(B32="","",IFERROR(IF(INDEX(Data!$U$2:$U$745,MATCH(18,Data!$B$2:$B$745,0))="","",INDEX(Data!$U$2:$U$745,MATCH(18,Data!$B$2:$B$745,0))),"")) | O32: =IF(B32="","",IFERROR(IF(INDEX(Data!$V$2:$V$745,MATCH(18,Data!$B$2:$B$745,0))="","",INDEX(Data!$V$2:$V$745,MATCH(18,Data!$B$2:$B$745,0))),"")) | P32: =IF(B32="","",IFERROR(IF(INDEX(Data!$M$2:$M$745,MATCH(18,Data!$B$2:$B$745,0))="","",INDEX(Data!$M$2:$M$745,MATCH(18,Data!$B$2:$B$745,0))),"")) | Q32: =IF(B32="","",IFERROR(IF(INDEX(Data!$AD$2:$AD$745,MATCH(18,Data!$B$2:$B$745,0))="","",INDEX(Data!$AD$2:$AD$745,MATCH(18,Data!$B$2:$B$745,0))),"")) | R32: =IF(B32="","",IFERROR(IF(INDEX(Data!$L$2:$L$745,MATCH(18,Data!$B$2:$B$745,0))="","",INDEX(Data!$L$2:$L$745,MATCH(18,Data!$B$2:$B$745,0))),"")) | AB32: Breescape
B33: =IF(19<=COUNTIF(Data!$A$2:$A$745,TRUE),19,"") | C33: =IF(B33="","",IFERROR(_xlfn.IMAGE(IFERROR(IF(INDEX(Data!$J$2:$J$745,MATCH(19,Data!$B$2:$B$745,0))="","",INDEX(Data!$J$2:$J$745,MATCH(19,Data!$B$2:$B$745,0))),"")),"IMAGE COMING SOON")) | D33: =IF(B33="","",IFERROR(IF(INDEX(Data!$G$2:$G$745,MATCH(19,Data!$B$2:$B$745,0))="","",INDEX(Data!$G$2:$G$745,MATCH(19,Data!$B$2:$B$745,0))),"")&CHAR(10)&IFERROR(IF(INDEX(Data!$H$2:$H$745,MATCH(19,Data!$B$2:$B$745,0))="","",INDEX(Data!$H$2:$H$745,MATCH(19,Data!$B$2:$B$745,0))),"")) | E33: =IF(B33="","",IFERROR(IF(INDEX(Data!$I$2:$I$745,MATCH(19,Data!$B$2:$B$745,0))="","",INDEX(Data!$I$2:$I$745,MATCH(19,Data!$B$2:$B$745,0))),"")) | F33: =IF(B33="","",IFERROR(IF(INDEX(Data!$AJ$2:$AJ$745,MATCH(19,Data!$B$2:$B$745,0))="","",INDEX(Data!$AJ$2:$AJ$745,MATCH(19,Data!$B$2:$B$745,0))),"")) | G33: =IF(B33="","",TRIM(IFERROR(IF(INDEX(Data!$AF$2:$AF$745,MATCH(19,Data!$B$2:$B$745,0))="","",INDEX(Data!$AF$2:$AF$745,MATCH(19,Data!$B$2:$B$745,0))),"")&" "&IFERROR(IF(INDEX(Data!$AG$2:$AG$745,MATCH(19,Data!$B$2:$B$745,0))="","",INDEX(Data!$AG$2:$AG$745,MATCH(19,Data!$B$2:$B$745,0))),""))) | H33: =IF(B33="","",IFERROR(IF(INDEX(Data!$N$2:$N$745,MATCH(19,Data!$B$2:$B$745,0))="","",INDEX(Data!$N$2:$N$745,MATCH(19,Data!$B$2:$B$745,0))),"")) | I33: =IF(B33="","",IFERROR(IF(INDEX(Data!$O$2:$O$745,MATCH(19,Data!$B$2:$B$745,0))="","",INDEX(Data!$O$2:$O$745,MATCH(19,Data!$B$2:$B$745,0))),"")) | J33: =IF(B33="","",IFERROR(IF(INDEX(Data!$P$2:$P$745,MATCH(19,Data!$B$2:$B$745,0))="","",INDEX(Data!$P$2:$P$745,MATCH(19,Data!$B$2:$B$745,0))),"")) | K33: =IF(B33="","",IFERROR(IF(INDEX(Data!$R$2:$R$745,MATCH(19,Data!$B$2:$B$745,0))="","",INDEX(Data!$R$2:$R$745,MATCH(19,Data!$B$2:$B$745,0))),"")) | L33: =IF(B33="","",IFERROR(IF(INDEX(Data!$S$2:$S$745,MATCH(19,Data!$B$2:$B$745,0))="","",INDEX(Data!$S$2:$S$745,MATCH(19,Data!$B$2:$B$745,0))),"")) | M33: =IF(B33="","",IFERROR(IF(INDEX(Data!$T$2:$T$745,MATCH(19,Data!$B$2:$B$745,0))="","",INDEX(Data!$T$2:$T$745,MATCH(19,Data!$B$2:$B$745,0))),"")) | N33: =IF(B33="","",IFERROR(IF(INDEX(Data!$U$2:$U$745,MATCH(19,Data!$B$2:$B$745,0))="","",INDEX(Data!$U$2:$U$745,MATCH(19,Data!$B$2:$B$745,0))),"")) | O33: =IF(B33="","",IFERROR(IF(INDEX(Data!$V$2:$V$745,MATCH(19,Data!$B$2:$B$745,0))="","",INDEX(Data!$V$2:$V$745,MATCH(19,Data!$B$2:$B$745,0))),"")) | P33: =IF(B33="","",IFERROR(IF(INDEX(Data!$M$2:$M$745,MATCH(19,Data!$B$2:$B$745,0))="","",INDEX(Data!$M$2:$M$745,MATCH(19,Data!$B$2:$B$745,0))),"")) | Q33: =IF(B33="","",IFERROR(IF(INDEX(Data!$AD$2:$AD$745,MATCH(19,Data!$B$2:$B$745,0))="","",INDEX(Data!$AD$2:$AD$745,MATCH(19,Data!$B$2:$B$745,0))),"")) | R33: =IF(B33="","",IFERROR(IF(INDEX(Data!$L$2:$L$745,MATCH(19,Data!$B$2:$B$745,0))="","",INDEX(Data!$L$2:$L$745,MATCH(19,Data!$B$2:$B$745,0))),"")) | AB33: Brooklinen
B34: =IF(20<=COUNTIF(Data!$A$2:$A$745,TRUE),20,"") | C34: =IF(B34="","",IFERROR(_xlfn.IMAGE(IFERROR(IF(INDEX(Data!$J$2:$J$745,MATCH(20,Data!$B$2:$B$745,0))="","",INDEX(Data!$J$2:$J$745,MATCH(20,Data!$B$2:$B$745,0))),"")),"IMAGE COMING SOON")) | D34: =IF(B34="","",IFERROR(IF(INDEX(Data!$G$2:$G$745,MATCH(20,Data!$B$2:$B$745,0))="","",INDEX(Data!$G$2:$G$745,MATCH(20,Data!$B$2:$B$745,0))),"")&CHAR(10)&IFERROR(IF(INDEX(Data!$H$2:$H$745,MATCH(20,Data!$B$2:$B$745,0))="","",INDEX(Data!$H$2:$H$745,MATCH(20,Data!$B$2:$B$745,0))),"")) | E34: =IF(B34="","",IFERROR(IF(INDEX(Data!$I$2:$I$745,MATCH(20,Data!$B$2:$B$745,0))="","",INDEX(Data!$I$2:$I$745,MATCH(20,Data!$B$2:$B$745,0))),"")) | F34: =IF(B34="","",IFERROR(IF(INDEX(Data!$AJ$2:$AJ$745,MATCH(20,Data!$B$2:$B$745,0))="","",INDEX(Data!$AJ$2:$AJ$745,MATCH(20,Data!$B$2:$B$745,0))),"")) | G34: =IF(B34="","",TRIM(IFERROR(IF(INDEX(Data!$AF$2:$AF$745,MATCH(20,Data!$B$2:$B$745,0))="","",INDEX(Data!$AF$2:$AF$745,MATCH(20,Data!$B$2:$B$745,0))),"")&" "&IFERROR(IF(INDEX(Data!$AG$2:$AG$745,MATCH(20,Data!$B$2:$B$745,0))="","",INDEX(Data!$AG$2:$AG$745,MATCH(20,Data!$B$2:$B$745,0))),""))) | H34: =IF(B34="","",IFERROR(IF(INDEX(Data!$N$2:$N$745,MATCH(20,Data!$B$2:$B$745,0))="","",INDEX(Data!$N$2:$N$745,MATCH(20,Data!$B$2:$B$745,0))),"")) | I34: =IF(B34="","",IFERROR(IF(INDEX(Data!$O$2:$O$745,MATCH(20,Data!$B$2:$B$745,0))="","",INDEX(Data!$O$2:$O$745,MATCH(20,Data!$B$2:$B$745,0))),"")) | J34: =IF(B34="","",IFERROR(IF(INDEX(Data!$P$2:$P$745,MATCH(20,Data!$B$2:$B$745,0))="","",INDEX(Data!$P$2:$P$745,MATCH(20,Data!$B$2:$B$745,0))),"")) | K34: =IF(B34="","",IFERROR(IF(INDEX(Data!$R$2:$R$745,MATCH(20,Data!$B$2:$B$745,0))="","",INDEX(Data!$R$2:$R$745,MATCH(20,Data!$B$2:$B$745,0))),"")) | L34: =IF(B34="","",IFERROR(IF(INDEX(Data!$S$2:$S$745,MATCH(20,Data!$B$2:$B$745,0))="","",INDEX(Data!$S$2:$S$745,MATCH(20,Data!$B$2:$B$745,0))),"")) | M34: =IF(B34="","",IFERROR(IF(INDEX(Data!$T$2:$T$745,MATCH(20,Data!$B$2:$B$745,0))="","",INDEX(Data!$T$2:$T$745,MATCH(20,Data!$B$2:$B$745,0))),"")) | N34: =IF(B34="","",IFERROR(IF(INDEX(Data!$U$2:$U$745,MATCH(20,Data!$B$2:$B$745,0))="","",INDEX(Data!$U$2:$U$745,MATCH(20,Data!$B$2:$B$745,0))),"")) | O34: =IF(B34="","",IFERROR(IF(INDEX(Data!$V$2:$V$745,MATCH(20,Data!$B$2:$B$745,0))="","",INDEX(Data!$V$2:$V$745,MATCH(20,Data!$B$2:$B$745,0))),"")) | P34: =IF(B34="","",IFERROR(IF(INDEX(Data!$M$2:$M$745,MATCH(20,Data!$B$2:$B$745,0))="","",INDEX(Data!$M$2:$M$745,MATCH(20,Data!$B$2:$B$745,0))),"")) | Q34: =IF(B34="","",IFERROR(IF(INDEX(Data!$AD$2:$AD$745,MATCH(20,Data!$B$2:$B$745,0))="","",INDEX(Data!$AD$2:$AD$745,MATCH(20,Data!$B$2:$B$745,0))),"")) | R34: =IF(B34="","",IFERROR(IF(INDEX(Data!$L$2:$L$745,MATCH(20,Data!$B$2:$B$745,0))="","",INDEX(Data!$L$2:$L$745,MATCH(20,Data!$B$2:$B$745,0))),"")) | AB34: Brooklyn Loom
B35: =IF(21<=COUNTIF(Data!$A$2:$A$745,TRUE),21,"") | C35: =IF(B35="","",IFERROR(_xlfn.IMAGE(IFERROR(IF(INDEX(Data!$J$2:$J$745,MATCH(21,Data!$B$2:$B$745,0))="","",INDEX(Data!$J$2:$J$745,MATCH(21,Data!$B$2:$B$745,0))),"")),"IMAGE COMING SOON")) | D35: =IF(B35="","",IFERROR(IF(INDEX(Data!$G$2:$G$745,MATCH(21,Data!$B$2:$B$745,0))="","",INDEX(Data!$G$2:$G$745,MATCH(21,Data!$B$2:$B$745,0))),"")&CHAR(10)&IFERROR(IF(INDEX(Data!$H$2:$H$745,MATCH(21,Data!$B$2:$B$745,0))="","",INDEX(Data!$H$2:$H$745,MATCH(21,Data!$B$2:$B$745,0))),"")) | E35: =IF(B35="","",IFERROR(IF(INDEX(Data!$I$2:$I$745,MATCH(21,Data!$B$2:$B$745,0))="","",INDEX(Data!$I$2:$I$745,MATCH(21,Data!$B$2:$B$745,0))),"")) | F35: =IF(B35="","",IFERROR(IF(INDEX(Data!$AJ$2:$AJ$745,MATCH(21,Data!$B$2:$B$745,0))="","",INDEX(Data!$AJ$2:$AJ$745,MATCH(21,Data!$B$2:$B$745,0))),"")) | G35: =IF(B35="","",TRIM(IFERROR(IF(INDEX(Data!$AF$2:$AF$745,MATCH(21,Data!$B$2:$B$745,0))="","",INDEX(Data!$AF$2:$AF$745,MATCH(21,Data!$B$2:$B$745,0))),"")&" "&IFERROR(IF(INDEX(Data!$AG$2:$AG$745,MATCH(21,Data!$B$2:$B$745,0))="","",INDEX(Data!$AG$2:$AG$745,MATCH(21,Data!$B$2:$B$745,0))),""))) | H35: =IF(B35="","",IFERROR(IF(INDEX(Data!$N$2:$N$745,MATCH(21,Data!$B$2:$B$745,0))="","",INDEX(Data!$N$2:$N$745,MATCH(21,Data!$B$2:$B$745,0))),"")) | I35: =IF(B35="","",IFERROR(IF(INDEX(Data!$O$2:$O$745,MATCH(21,Data!$B$2:$B$745,0))="","",INDEX(Data!$O$2:$O$745,MATCH(21,Data!$B$2:$B$745,0))),"")) | J35: =IF(B35="","",IFERROR(IF(INDEX(Data!$P$2:$P$745,MATCH(21,Data!$B$2:$B$745,0))="","",INDEX(Data!$P$2:$P$745,MATCH(21,Data!$B$2:$B$745,0))),"")) | K35: =IF(B35="","",IFERROR(IF(INDEX(Data!$R$2:$R$745,MATCH(21,Data!$B$2:$B$745,0))="","",INDEX(Data!$R$2:$R$745,MATCH(21,Data!$B$2:$B$745,0))),"")) | L35: =IF(B35="","",IFERROR(IF(INDEX(Data!$S$2:$S$745,MATCH(21,Data!$B$2:$B$745,0))="","",INDEX(Data!$S$2:$S$745,MATCH(21,Data!$B$2:$B$745,0))),"")) | M35: =IF(B35="","",IFERROR(IF(INDEX(Data!$T$2:$T$745,MATCH(21,Data!$B$2:$B$745,0))="","",INDEX(Data!$T$2:$T$745,MATCH(21,Data!$B$2:$B$745,0))),"")) | N35: =IF(B35="","",IFERROR(IF(INDEX(Data!$U$2:$U$745,MATCH(21,Data!$B$2:$B$745,0))="","",INDEX(Data!$U$2:$U$745,MATCH(21,Data!$B$2:$B$745,0))),"")) | O35: =IF(B35="","",IFERROR(IF(INDEX(Data!$V$2:$V$745,MATCH(21,Data!$B$2:$B$745,0))="","",INDEX(Data!$V$2:$V$745,MATCH(21,Data!$B$2:$B$745,0))),"")) | P35: =IF(B35="","",IFERROR(IF(INDEX(Data!$M$2:$M$745,MATCH(21,Data!$B$2:$B$745,0))="","",INDEX(Data!$M$2:$M$745,MATCH(21,Data!$B$2:$B$745,0))),"")) | Q35: =IF(B35="","",IFERROR(IF(INDEX(Data!$AD$2:$AD$745,MATCH(21,Data!$B$2:$B$745,0))="","",INDEX(Data!$AD$2:$AD$745,MATCH(21,Data!$B$2:$B$745,0))),"")) | R35: =IF(B35="","",IFERROR(IF(INDEX(Data!$L$2:$L$745,MATCH(21,Data!$B$2:$B$745,0))="","",INDEX(Data!$L$2:$L$745,MATCH(21,Data!$B$2:$B$745,0))),"")) | AB35: Brookstone
B36: =IF(22<=COUNTIF(Data!$A$2:$A$745,TRUE),22,"") | C36: =IF(B36="","",IFERROR(_xlfn.IMAGE(IFERROR(IF(INDEX(Data!$J$2:$J$745,MATCH(22,Data!$B$2:$B$745,0))="","",INDEX(Data!$J$2:$J$745,MATCH(22,Data!$B$2:$B$745,0))),"")),"IMAGE COMING SOON")) | D36: =IF(B36="","",IFERROR(IF(INDEX(Data!$G$2:$G$745,MATCH(22,Data!$B$2:$B$745,0))="","",INDEX(Data!$G$2:$G$745,MATCH(22,Data!$B$2:$B$745,0))),"")&CHAR(10)&IFERROR(IF(INDEX(Data!$H$2:$H$745,MATCH(22,Data!$B$2:$B$745,0))="","",INDEX(Data!$H$2:$H$745,MATCH(22,Data!$B$2:$B$745,0))),"")) | E36: =IF(B36="","",IFERROR(IF(INDEX(Data!$I$2:$I$745,MATCH(22,Data!$B$2:$B$745,0))="","",INDEX(Data!$I$2:$I$745,MATCH(22,Data!$B$2:$B$745,0))),"")) | F36: =IF(B36="","",IFERROR(IF(INDEX(Data!$AJ$2:$AJ$745,MATCH(22,Data!$B$2:$B$745,0))="","",INDEX(Data!$AJ$2:$AJ$745,MATCH(22,Data!$B$2:$B$745,0))),"")) | G36: =IF(B36="","",TRIM(IFERROR(IF(INDEX(Data!$AF$2:$AF$745,MATCH(22,Data!$B$2:$B$745,0))="","",INDEX(Data!$AF$2:$AF$745,MATCH(22,Data!$B$2:$B$745,0))),"")&" "&IFERROR(IF(INDEX(Data!$AG$2:$AG$745,MATCH(22,Data!$B$2:$B$745,0))="","",INDEX(Data!$AG$2:$AG$745,MATCH(22,Data!$B$2:$B$745,0))),""))) | H36: =IF(B36="","",IFERROR(IF(INDEX(Data!$N$2:$N$745,MATCH(22,Data!$B$2:$B$745,0))="","",INDEX(Data!$N$2:$N$745,MATCH(22,Data!$B$2:$B$745,0))),"")) | I36: =IF(B36="","",IFERROR(IF(INDEX(Data!$O$2:$O$745,MATCH(22,Data!$B$2:$B$745,0))="","",INDEX(Data!$O$2:$O$745,MATCH(22,Data!$B$2:$B$745,0))),"")) | J36: =IF(B36="","",IFERROR(IF(INDEX(Data!$P$2:$P$745,MATCH(22,Data!$B$2:$B$745,0))="","",INDEX(Data!$P$2:$P$745,MATCH(22,Data!$B$2:$B$745,0))),"")) | K36: =IF(B36="","",IFERROR(IF(INDEX(Data!$R$2:$R$745,MATCH(22,Data!$B$2:$B$745,0))="","",INDEX(Data!$R$2:$R$745,MATCH(22,Data!$B$2:$B$745,0))),"")) | L36: =IF(B36="","",IFERROR(IF(INDEX(Data!$S$2:$S$745,MATCH(22,Data!$B$2:$B$745,0))="","",INDEX(Data!$S$2:$S$745,MATCH(22,Data!$B$2:$B$745,0))),"")) | M36: =IF(B36="","",IFERROR(IF(INDEX(Data!$T$2:$T$745,MATCH(22,Data!$B$2:$B$745,0))="","",INDEX(Data!$T$2:$T$745,MATCH(22,Data!$B$2:$B$745,0))),"")) | N36: =IF(B36="","",IFERROR(IF(INDEX(Data!$U$2:$U$745,MATCH(22,Data!$B$2:$B$745,0))="","",INDEX(Data!$U$2:$U$745,MATCH(22,Data!$B$2:$B$745,0))),"")) | O36: =IF(B36="","",IFERROR(IF(INDEX(Data!$V$2:$V$745,MATCH(22,Data!$B$2:$B$745,0))="","",INDEX(Data!$V$2:$V$745,MATCH(22,Data!$B$2:$B$745,0))),"")) | P36: =IF(B36="","",IFERROR(IF(INDEX(Data!$M$2:$M$745,MATCH(22,Data!$B$2:$B$745,0))="","",INDEX(Data!$M$2:$M$745,MATCH(22,Data!$B$2:$B$745,0))),"")) | Q36: =IF(B36="","",IFERROR(IF(INDEX(Data!$AD$2:$AD$745,MATCH(22,Data!$B$2:$B$745,0))="","",INDEX(Data!$AD$2:$AD$745,MATCH(22,Data!$B$2:$B$745,0))),"")) | R36: =IF(B36="","",IFERROR(IF(INDEX(Data!$L$2:$L$745,MATCH(22,Data!$B$2:$B$745,0))="","",INDEX(Data!$L$2:$L$745,MATCH(22,Data!$B$2:$B$745,0))),"")) | AB36: California Design Den
B37: =IF(23<=COUNTIF(Data!$A$2:$A$745,TRUE),23,"") | C37: =IF(B37="","",IFERROR(_xlfn.IMAGE(IFERROR(IF(INDEX(Data!$J$2:$J$745,MATCH(23,Data!$B$2:$B$745,0))="","",INDEX(Data!$J$2:$J$745,MATCH(23,Data!$B$2:$B$745,0))),"")),"IMAGE COMING SOON")) | D37: =IF(B37="","",IFERROR(IF(INDEX(Data!$G$2:$G$745,MATCH(23,Data!$B$2:$B$745,0))="","",INDEX(Data!$G$2:$G$745,MATCH(23,Data!$B$2:$B$745,0))),"")&CHAR(10)&IFERROR(IF(INDEX(Data!$H$2:$H$745,MATCH(23,Data!$B$2:$B$745,0))="","",INDEX(Data!$H$2:$H$745,MATCH(23,Data!$B$2:$B$745,0))),"")) | E37: =IF(B37="","",IFERROR(IF(INDEX(Data!$I$2:$I$745,MATCH(23,Data!$B$2:$B$745,0))="","",INDEX(Data!$I$2:$I$745,MATCH(23,Data!$B$2:$B$745,0))),"")) | F37: =IF(B37="","",IFERROR(IF(INDEX(Data!$AJ$2:$AJ$745,MATCH(23,Data!$B$2:$B$745,0))="","",INDEX(Data!$AJ$2:$AJ$745,MATCH(23,Data!$B$2:$B$745,0))),"")) | G37: =IF(B37="","",TRIM(IFERROR(IF(INDEX(Data!$AF$2:$AF$745,MATCH(23,Data!$B$2:$B$745,0))="","",INDEX(Data!$AF$2:$AF$745,MATCH(23,Data!$B$2:$B$745,0))),"")&" "&IFERROR(IF(INDEX(Data!$AG$2:$AG$745,MATCH(23,Data!$B$2:$B$745,0))="","",INDEX(Data!$AG$2:$AG$745,MATCH(23,Data!$B$2:$B$745,0))),""))) | H37: =IF(B37="","",IFERROR(IF(INDEX(Data!$N$2:$N$745,MATCH(23,Data!$B$2:$B$745,0))="","",INDEX(Data!$N$2:$N$745,MATCH(23,Data!$B$2:$B$745,0))),"")) | I37: =IF(B37="","",IFERROR(IF(INDEX(Data!$O$2:$O$745,MATCH(23,Data!$B$2:$B$745,0))="","",INDEX(Data!$O$2:$O$745,MATCH(23,Data!$B$2:$B$745,0))),"")) | J37: =IF(B37="","",IFERROR(IF(INDEX(Data!$P$2:$P$745,MATCH(23,Data!$B$2:$B$745,0))="","",INDEX(Data!$P$2:$P$745,MATCH(23,Data!$B$2:$B$745,0))),"")) | K37: =IF(B37="","",IFERROR(IF(INDEX(Data!$R$2:$R$745,MATCH(23,Data!$B$2:$B$745,0))="","",INDEX(Data!$R$2:$R$745,MATCH(23,Data!$B$2:$B$745,0))),"")) | L37: =IF(B37="","",IFERROR(IF(INDEX(Data!$S$2:$S$745,MATCH(23,Data!$B$2:$B$745,0))="","",INDEX(Data!$S$2:$S$745,MATCH(23,Data!$B$2:$B$745,0))),"")) | M37: =IF(B37="","",IFERROR(IF(INDEX(Data!$T$2:$T$745,MATCH(23,Data!$B$2:$B$745,0))="","",INDEX(Data!$T$2:$T$745,MATCH(23,Data!$B$2:$B$745,0))),"")) | N37: =IF(B37="","",IFERROR(IF(INDEX(Data!$U$2:$U$745,MATCH(23,Data!$B$2:$B$745,0))="","",INDEX(Data!$U$2:$U$745,MATCH(23,Data!$B$2:$B$745,0))),"")) | O37: =IF(B37="","",IFERROR(IF(INDEX(Data!$V$2:$V$745,MATCH(23,Data!$B$2:$B$745,0))="","",INDEX(Data!$V$2:$V$745,MATCH(23,Data!$B$2:$B$745,0))),"")) | P37: =IF(B37="","",IFERROR(IF(INDEX(Data!$M$2:$M$745,MATCH(23,Data!$B$2:$B$745,0))="","",INDEX(Data!$M$2:$M$745,MATCH(23,Data!$B$2:$B$745,0))),"")) | Q37: =IF(B37="","",IFERROR(IF(INDEX(Data!$AD$2:$AD$745,MATCH(23,Data!$B$2:$B$745,0))="","",INDEX(Data!$AD$2:$AD$745,MATCH(23,Data!$B$2:$B$745,0))),"")) | R37: =IF(B37="","",IFERROR(IF(INDEX(Data!$L$2:$L$745,MATCH(23,Data!$B$2:$B$745,0))="","",INDEX(Data!$L$2:$L$745,MATCH(23,Data!$B$2:$B$745,0))),"")) | AB37: Candoury
B38: =IF(24<=COUNTIF(Data!$A$2:$A$745,TRUE),24,"") | C38: =IF(B38="","",IFERROR(_xlfn.IMAGE(IFERROR(IF(INDEX(Data!$J$2:$J$745,MATCH(24,Data!$B$2:$B$745,0))="","",INDEX(Data!$J$2:$J$745,MATCH(24,Data!$B$2:$B$745,0))),"")),"IMAGE COMING SOON")) | D38: =IF(B38="","",IFERROR(IF(INDEX(Data!$G$2:$G$745,MATCH(24,Data!$B$2:$B$745,0))="","",INDEX(Data!$G$2:$G$745,MATCH(24,Data!$B$2:$B$745,0))),"")&CHAR(10)&IFERROR(IF(INDEX(Data!$H$2:$H$745,MATCH(24,Data!$B$2:$B$745,0))="","",INDEX(Data!$H$2:$H$745,MATCH(24,Data!$B$2:$B$745,0))),"")) | E38: =IF(B38="","",IFERROR(IF(INDEX(Data!$I$2:$I$745,MATCH(24,Data!$B$2:$B$745,0))="","",INDEX(Data!$I$2:$I$745,MATCH(24,Data!$B$2:$B$745,0))),"")) | F38: =IF(B38="","",IFERROR(IF(INDEX(Data!$AJ$2:$AJ$745,MATCH(24,Data!$B$2:$B$745,0))="","",INDEX(Data!$AJ$2:$AJ$745,MATCH(24,Data!$B$2:$B$745,0))),"")) | G38: =IF(B38="","",TRIM(IFERROR(IF(INDEX(Data!$AF$2:$AF$745,MATCH(24,Data!$B$2:$B$745,0))="","",INDEX(Data!$AF$2:$AF$745,MATCH(24,Data!$B$2:$B$745,0))),"")&" "&IFERROR(IF(INDEX(Data!$AG$2:$AG$745,MATCH(24,Data!$B$2:$B$745,0))="","",INDEX(Data!$AG$2:$AG$745,MATCH(24,Data!$B$2:$B$745,0))),""))) | H38: =IF(B38="","",IFERROR(IF(INDEX(Data!$N$2:$N$745,MATCH(24,Data!$B$2:$B$745,0))="","",INDEX(Data!$N$2:$N$745,MATCH(24,Data!$B$2:$B$745,0))),"")) | I38: =IF(B38="","",IFERROR(IF(INDEX(Data!$O$2:$O$745,MATCH(24,Data!$B$2:$B$745,0))="","",INDEX(Data!$O$2:$O$745,MATCH(24,Data!$B$2:$B$745,0))),"")) | J38: =IF(B38="","",IFERROR(IF(INDEX(Data!$P$2:$P$745,MATCH(24,Data!$B$2:$B$745,0))="","",INDEX(Data!$P$2:$P$745,MATCH(24,Data!$B$2:$B$745,0))),"")) | K38: =IF(B38="","",IFERROR(IF(INDEX(Data!$R$2:$R$745,MATCH(24,Data!$B$2:$B$745,0))="","",INDEX(Data!$R$2:$R$745,MATCH(24,Data!$B$2:$B$745,0))),"")) | L38: =IF(B38="","",IFERROR(IF(INDEX(Data!$S$2:$S$745,MATCH(24,Data!$B$2:$B$745,0))="","",INDEX(Data!$S$2:$S$745,MATCH(24,Data!$B$2:$B$745,0))),"")) | M38: =IF(B38="","",IFERROR(IF(INDEX(Data!$T$2:$T$745,MATCH(24,Data!$B$2:$B$745,0))="","",INDEX(Data!$T$2:$T$745,MATCH(24,Data!$B$2:$B$745,0))),"")) | N38: =IF(B38="","",IFERROR(IF(INDEX(Data!$U$2:$U$745,MATCH(24,Data!$B$2:$B$745,0))="","",INDEX(Data!$U$2:$U$745,MATCH(24,Data!$B$2:$B$745,0))),"")) | O38: =IF(B38="","",IFERROR(IF(INDEX(Data!$V$2:$V$745,MATCH(24,Data!$B$2:$B$745,0))="","",INDEX(Data!$V$2:$V$745,MATCH(24,Data!$B$2:$B$745,0))),"")) | P38: =IF(B38="","",IFERROR(IF(INDEX(Data!$M$2:$M$745,MATCH(24,Data!$B$2:$B$745,0))="","",INDEX(Data!$M$2:$M$745,MATCH(24,Data!$B$2:$B$745,0))),"")) | Q38: =IF(B38="","",IFERROR(IF(INDEX(Data!$AD$2:$AD$745,MATCH(24,Data!$B$2:$B$745,0))="","",INDEX(Data!$AD$2:$AD$745,MATCH(24,Data!$B$2:$B$745,0))),"")) | R38: =IF(B38="","",IFERROR(IF(INDEX(Data!$L$2:$L$745,MATCH(24,Data!$B$2:$B$745,0))="","",INDEX(Data!$L$2:$L$745,MATCH(24,Data!$B$2:$B$745,0))),"")) | AB38: Cape Comforts
B39: =IF(25<=COUNTIF(Data!$A$2:$A$745,TRUE),25,"") | C39: =IF(B39="","",IFERROR(_xlfn.IMAGE(IFERROR(IF(INDEX(Data!$J$2:$J$745,MATCH(25,Data!$B$2:$B$745,0))="","",INDEX(Data!$J$2:$J$745,MATCH(25,Data!$B$2:$B$745,0))),"")),"IMAGE COMING SOON")) | D39: =IF(B39="","",IFERROR(IF(INDEX(Data!$G$2:$G$745,MATCH(25,Data!$B$2:$B$745,0))="","",INDEX(Data!$G$2:$G$745,MATCH(25,Data!$B$2:$B$745,0))),"")&CHAR(10)&IFERROR(IF(INDEX(Data!$H$2:$H$745,MATCH(25,Data!$B$2:$B$745,0))="","",INDEX(Data!$H$2:$H$745,MATCH(25,Data!$B$2:$B$745,0))),"")) | E39: =IF(B39="","",IFERROR(IF(INDEX(Data!$I$2:$I$745,MATCH(25,Data!$B$2:$B$745,0))="","",INDEX(Data!$I$2:$I$745,MATCH(25,Data!$B$2:$B$745,0))),"")) | F39: =IF(B39="","",IFERROR(IF(INDEX(Data!$AJ$2:$AJ$745,MATCH(25,Data!$B$2:$B$745,0))="","",INDEX(Data!$AJ$2:$AJ$745,MATCH(25,Data!$B$2:$B$745,0))),"")) | G39: =IF(B39="","",TRIM(IFERROR(IF(INDEX(Data!$AF$2:$AF$745,MATCH(25,Data!$B$2:$B$745,0))="","",INDEX(Data!$AF$2:$AF$745,MATCH(25,Data!$B$2:$B$745,0))),"")&" "&IFERROR(IF(INDEX(Data!$AG$2:$AG$745,MATCH(25,Data!$B$2:$B$745,0))="","",INDEX(Data!$AG$2:$AG$745,MATCH(25,Data!$B$2:$B$745,0))),""))) | H39: =IF(B39="","",IFERROR(IF(INDEX(Data!$N$2:$N$745,MATCH(25,Data!$B$2:$B$745,0))="","",INDEX(Data!$N$2:$N$745,MATCH(25,Data!$B$2:$B$745,0))),"")) | I39: =IF(B39="","",IFERROR(IF(INDEX(Data!$O$2:$O$745,MATCH(25,Data!$B$2:$B$745,0))="","",INDEX(Data!$O$2:$O$745,MATCH(25,Data!$B$2:$B$745,0))),"")) | J39: =IF(B39="","",IFERROR(IF(INDEX(Data!$P$2:$P$745,MATCH(25,Data!$B$2:$B$745,0))="","",INDEX(Data!$P$2:$P$745,MATCH(25,Data!$B$2:$B$745,0))),"")) | K39: =IF(B39="","",IFERROR(IF(INDEX(Data!$R$2:$R$745,MATCH(25,Data!$B$2:$B$745,0))="","",INDEX(Data!$R$2:$R$745,MATCH(25,Data!$B$2:$B$745,0))),"")) | L39: =IF(B39="","",IFERROR(IF(INDEX(Data!$S$2:$S$745,MATCH(25,Data!$B$2:$B$745,0))="","",INDEX(Data!$S$2:$S$745,MATCH(25,Data!$B$2:$B$745,0))),"")) | M39: =IF(B39="","",IFERROR(IF(INDEX(Data!$T$2:$T$745,MATCH(25,Data!$B$2:$B$745,0))="","",INDEX(Data!$T$2:$T$745,MATCH(25,Data!$B$2:$B$745,0))),"")) | N39: =IF(B39="","",IFERROR(IF(INDEX(Data!$U$2:$U$745,MATCH(25,Data!$B$2:$B$745,0))="","",INDEX(Data!$U$2:$U$745,MATCH(25,Data!$B$2:$B$745,0))),"")) | O39: =IF(B39="","",IFERROR(IF(INDEX(Data!$V$2:$V$745,MATCH(25,Data!$B$2:$B$745,0))="","",INDEX(Data!$V$2:$V$745,MATCH(25,Data!$B$2:$B$745,0))),"")) | P39: =IF(B39="","",IFERROR(IF(INDEX(Data!$M$2:$M$745,MATCH(25,Data!$B$2:$B$745,0))="","",INDEX(Data!$M$2:$M$745,MATCH(25,Data!$B$2:$B$745,0))),"")) | Q39: =IF(B39="","",IFERROR(IF(INDEX(Data!$AD$2:$AD$745,MATCH(25,Data!$B$2:$B$745,0))="","",INDEX(Data!$AD$2:$AD$745,MATCH(25,Data!$B$2:$B$745,0))),"")) | R39: =IF(B39="","",IFERROR(IF(INDEX(Data!$L$2:$L$745,MATCH(25,Data!$B$2:$B$745,0))="","",INDEX(Data!$L$2:$L$745,MATCH(25,Data!$B$2:$B$745,0))),"")) | AB39: Cariloha
B40: =IF(26<=COUNTIF(Data!$A$2:$A$745,TRUE),26,"") | C40: =IF(B40="","",IFERROR(_xlfn.IMAGE(IFERROR(IF(INDEX(Data!$J$2:$J$745,MATCH(26,Data!$B$2:$B$745,0))="","",INDEX(Data!$J$2:$J$745,MATCH(26,Data!$B$2:$B$745,0))),"")),"IMAGE COMING SOON")) | D40: =IF(B40="","",IFERROR(IF(INDEX(Data!$G$2:$G$745,MATCH(26,Data!$B$2:$B$745,0))="","",INDEX(Data!$G$2:$G$745,MATCH(26,Data!$B$2:$B$745,0))),"")&CHAR(10)&IFERROR(IF(INDEX(Data!$H$2:$H$745,MATCH(26,Data!$B$2:$B$745,0))="","",INDEX(Data!$H$2:$H$745,MATCH(26,Data!$B$2:$B$745,0))),"")) | E40: =IF(B40="","",IFERROR(IF(INDEX(Data!$I$2:$I$745,MATCH(26,Data!$B$2:$B$745,0))="","",INDEX(Data!$I$2:$I$745,MATCH(26,Data!$B$2:$B$745,0))),"")) | F40: =IF(B40="","",IFERROR(IF(INDEX(Data!$AJ$2:$AJ$745,MATCH(26,Data!$B$2:$B$745,0))="","",INDEX(Data!$AJ$2:$AJ$745,MATCH(26,Data!$B$2:$B$745,0))),"")) | G40: =IF(B40="","",TRIM(IFERROR(IF(INDEX(Data!$AF$2:$AF$745,MATCH(26,Data!$B$2:$B$745,0))="","",INDEX(Data!$AF$2:$AF$745,MATCH(26,Data!$B$2:$B$745,0))),"")&" "&IFERROR(IF(INDEX(Data!$AG$2:$AG$745,MATCH(26,Data!$B$2:$B$745,0))="","",INDEX(Data!$AG$2:$AG$745,MATCH(26,Data!$B$2:$B$745,0))),""))) | H40: =IF(B40="","",IFERROR(IF(INDEX(Data!$N$2:$N$745,MATCH(26,Data!$B$2:$B$745,0))="","",INDEX(Data!$N$2:$N$745,MATCH(26,Data!$B$2:$B$745,0))),"")) | I40: =IF(B40="","",IFERROR(IF(INDEX(Data!$O$2:$O$745,MATCH(26,Data!$B$2:$B$745,0))="","",INDEX(Data!$O$2:$O$745,MATCH(26,Data!$B$2:$B$745,0))),"")) | J40: =IF(B40="","",IFERROR(IF(INDEX(Data!$P$2:$P$745,MATCH(26,Data!$B$2:$B$745,0))="","",INDEX(Data!$P$2:$P$745,MATCH(26,Data!$B$2:$B$745,0))),"")) | K40: =IF(B40="","",IFERROR(IF(INDEX(Data!$R$2:$R$745,MATCH(26,Data!$B$2:$B$745,0))="","",INDEX(Data!$R$2:$R$745,MATCH(26,Data!$B$2:$B$745,0))),"")) | L40: =IF(B40="","",IFERROR(IF(INDEX(Data!$S$2:$S$745,MATCH(26,Data!$B$2:$B$745,0))="","",INDEX(Data!$S$2:$S$745,MATCH(26,Data!$B$2:$B$745,0))),"")) | M40: =IF(B40="","",IFERROR(IF(INDEX(Data!$T$2:$T$745,MATCH(26,Data!$B$2:$B$745,0))="","",INDEX(Data!$T$2:$T$745,MATCH(26,Data!$B$2:$B$745,0))),"")) | N40: =IF(B40="","",IFERROR(IF(INDEX(Data!$U$2:$U$745,MATCH(26,Data!$B$2:$B$745,0))="","",INDEX(Data!$U$2:$U$745,MATCH(26,Data!$B$2:$B$745,0))),"")) | O40: =IF(B40="","",IFERROR(IF(INDEX(Data!$V$2:$V$745,MATCH(26,Data!$B$2:$B$745,0))="","",INDEX(Data!$V$2:$V$745,MATCH(26,Data!$B$2:$B$745,0))),"")) | P40: =IF(B40="","",IFERROR(IF(INDEX(Data!$M$2:$M$745,MATCH(26,Data!$B$2:$B$745,0))="","",INDEX(Data!$M$2:$M$745,MATCH(26,Data!$B$2:$B$745,0))),"")) | Q40: =IF(B40="","",IFERROR(IF(INDEX(Data!$AD$2:$AD$745,MATCH(26,Data!$B$2:$B$745,0))="","",INDEX(Data!$AD$2:$AD$745,MATCH(26,Data!$B$2:$B$745,0))),"")) | R40: =IF(B40="","",IFERROR(IF(INDEX(Data!$L$2:$L$745,MATCH(26,Data!$B$2:$B$745,0))="","",INDEX(Data!$L$2:$L$745,MATCH(26,Data!$B$2:$B$745,0))),"")) | AB40: CAROMIO
B41: =IF(27<=COUNTIF(Data!$A$2:$A$745,TRUE),27,"") | C41: =IF(B41="","",IFERROR(_xlfn.IMAGE(IFERROR(IF(INDEX(Data!$J$2:$J$745,MATCH(27,Data!$B$2:$B$745,0))="","",INDEX(Data!$J$2:$J$745,MATCH(27,Data!$B$2:$B$745,0))),"")),"IMAGE COMING SOON")) | D41: =IF(B41="","",IFERROR(IF(INDEX(Data!$G$2:$G$745,MATCH(27,Data!$B$2:$B$745,0))="","",INDEX(Data!$G$2:$G$745,MATCH(27,Data!$B$2:$B$745,0))),"")&CHAR(10)&IFERROR(IF(INDEX(Data!$H$2:$H$745,MATCH(27,Data!$B$2:$B$745,0))="","",INDEX(Data!$H$2:$H$745,MATCH(27,Data!$B$2:$B$745,0))),"")) | E41: =IF(B41="","",IFERROR(IF(INDEX(Data!$I$2:$I$745,MATCH(27,Data!$B$2:$B$745,0))="","",INDEX(Data!$I$2:$I$745,MATCH(27,Data!$B$2:$B$745,0))),"")) | F41: =IF(B41="","",IFERROR(IF(INDEX(Data!$AJ$2:$AJ$745,MATCH(27,Data!$B$2:$B$745,0))="","",INDEX(Data!$AJ$2:$AJ$745,MATCH(27,Data!$B$2:$B$745,0))),"")) | G41: =IF(B41="","",TRIM(IFERROR(IF(INDEX(Data!$AF$2:$AF$745,MATCH(27,Data!$B$2:$B$745,0))="","",INDEX(Data!$AF$2:$AF$745,MATCH(27,Data!$B$2:$B$745,0))),"")&" "&IFERROR(IF(INDEX(Data!$AG$2:$AG$745,MATCH(27,Data!$B$2:$B$745,0))="","",INDEX(Data!$AG$2:$AG$745,MATCH(27,Data!$B$2:$B$745,0))),""))) | H41: =IF(B41="","",IFERROR(IF(INDEX(Data!$N$2:$N$745,MATCH(27,Data!$B$2:$B$745,0))="","",INDEX(Data!$N$2:$N$745,MATCH(27,Data!$B$2:$B$745,0))),"")) | I41: =IF(B41="","",IFERROR(IF(INDEX(Data!$O$2:$O$745,MATCH(27,Data!$B$2:$B$745,0))="","",INDEX(Data!$O$2:$O$745,MATCH(27,Data!$B$2:$B$745,0))),"")) | J41: =IF(B41="","",IFERROR(IF(INDEX(Data!$P$2:$P$745,MATCH(27,Data!$B$2:$B$745,0))="","",INDEX(Data!$P$2:$P$745,MATCH(27,Data!$B$2:$B$745,0))),"")) | K41: =IF(B41="","",IFERROR(IF(INDEX(Data!$R$2:$R$745,MATCH(27,Data!$B$2:$B$745,0))="","",INDEX(Data!$R$2:$R$745,MATCH(27,Data!$B$2:$B$745,0))),"")) | L41: =IF(B41="","",IFERROR(IF(INDEX(Data!$S$2:$S$745,MATCH(27,Data!$B$2:$B$745,0))="","",INDEX(Data!$S$2:$S$745,MATCH(27,Data!$B$2:$B$745,0))),"")) | M41: =IF(B41="","",IFERROR(IF(INDEX(Data!$T$2:$T$745,MATCH(27,Data!$B$2:$B$745,0))="","",INDEX(Data!$T$2:$T$745,MATCH(27,Data!$B$2:$B$745,0))),"")) | N41: =IF(B41="","",IFERROR(IF(INDEX(Data!$U$2:$U$745,MATCH(27,Data!$B$2:$B$745,0))="","",INDEX(Data!$U$2:$U$745,MATCH(27,Data!$B$2:$B$745,0))),"")) | O41: =IF(B41="","",IFERROR(IF(INDEX(Data!$V$2:$V$745,MATCH(27,Data!$B$2:$B$745,0))="","",INDEX(Data!$V$2:$V$745,MATCH(27,Data!$B$2:$B$745,0))),"")) | P41: =IF(B41="","",IFERROR(IF(INDEX(Data!$M$2:$M$745,MATCH(27,Data!$B$2:$B$745,0))="","",INDEX(Data!$M$2:$M$745,MATCH(27,Data!$B$2:$B$745,0))),"")) | Q41: =IF(B41="","",IFERROR(IF(INDEX(Data!$AD$2:$AD$745,MATCH(27,Data!$B$2:$B$745,0))="","",INDEX(Data!$AD$2:$AD$745,MATCH(27,Data!$B$2:$B$745,0))),"")) | R41: =IF(B41="","",IFERROR(IF(INDEX(Data!$L$2:$L$745,MATCH(27,Data!$B$2:$B$745,0))="","",INDEX(Data!$L$2:$L$745,MATCH(27,Data!$B$2:$B$745,0))),"")) | AB41: Casamollis
B42: =IF(28<=COUNTIF(Data!$A$2:$A$745,TRUE),28,"") | C42: =IF(B42="","",IFERROR(_xlfn.IMAGE(IFERROR(IF(INDEX(Data!$J$2:$J$745,MATCH(28,Data!$B$2:$B$745,0))="","",INDEX(Data!$J$2:$J$745,MATCH(28,Data!$B$2:$B$745,0))),"")),"IMAGE COMING SOON")) | D42: =IF(B42="","",IFERROR(IF(INDEX(Data!$G$2:$G$745,MATCH(28,Data!$B$2:$B$745,0))="","",INDEX(Data!$G$2:$G$745,MATCH(28,Data!$B$2:$B$745,0))),"")&CHAR(10)&IFERROR(IF(INDEX(Data!$H$2:$H$745,MATCH(28,Data!$B$2:$B$745,0))="","",INDEX(Data!$H$2:$H$745,MATCH(28,Data!$B$2:$B$745,0))),"")) | E42: =IF(B42="","",IFERROR(IF(INDEX(Data!$I$2:$I$745,MATCH(28,Data!$B$2:$B$745,0))="","",INDEX(Data!$I$2:$I$745,MATCH(28,Data!$B$2:$B$745,0))),"")) | F42: =IF(B42="","",IFERROR(IF(INDEX(Data!$AJ$2:$AJ$745,MATCH(28,Data!$B$2:$B$745,0))="","",INDEX(Data!$AJ$2:$AJ$745,MATCH(28,Data!$B$2:$B$745,0))),"")) | G42: =IF(B42="","",TRIM(IFERROR(IF(INDEX(Data!$AF$2:$AF$745,MATCH(28,Data!$B$2:$B$745,0))="","",INDEX(Data!$AF$2:$AF$745,MATCH(28,Data!$B$2:$B$745,0))),"")&" "&IFERROR(IF(INDEX(Data!$AG$2:$AG$745,MATCH(28,Data!$B$2:$B$745,0))="","",INDEX(Data!$AG$2:$AG$745,MATCH(28,Data!$B$2:$B$745,0))),""))) | H42: =IF(B42="","",IFERROR(IF(INDEX(Data!$N$2:$N$745,MATCH(28,Data!$B$2:$B$745,0))="","",INDEX(Data!$N$2:$N$745,MATCH(28,Data!$B$2:$B$745,0))),"")) | I42: =IF(B42="","",IFERROR(IF(INDEX(Data!$O$2:$O$745,MATCH(28,Data!$B$2:$B$745,0))="","",INDEX(Data!$O$2:$O$745,MATCH(28,Data!$B$2:$B$745,0))),"")) | J42: =IF(B42="","",IFERROR(IF(INDEX(Data!$P$2:$P$745,MATCH(28,Data!$B$2:$B$745,0))="","",INDEX(Data!$P$2:$P$745,MATCH(28,Data!$B$2:$B$745,0))),"")) | K42: =IF(B42="","",IFERROR(IF(INDEX(Data!$R$2:$R$745,MATCH(28,Data!$B$2:$B$745,0))="","",INDEX(Data!$R$2:$R$745,MATCH(28,Data!$B$2:$B$745,0))),"")) | L42: =IF(B42="","",IFERROR(IF(INDEX(Data!$S$2:$S$745,MATCH(28,Data!$B$2:$B$745,0))="","",INDEX(Data!$S$2:$S$745,MATCH(28,Data!$B$2:$B$745,0))),"")) | M42: =IF(B42="","",IFERROR(IF(INDEX(Data!$T$2:$T$745,MATCH(28,Data!$B$2:$B$745,0))="","",INDEX(Data!$T$2:$T$745,MATCH(28,Data!$B$2:$B$745,0))),"")) | N42: =IF(B42="","",IFERROR(IF(INDEX(Data!$U$2:$U$745,MATCH(28,Data!$B$2:$B$745,0))="","",INDEX(Data!$U$2:$U$745,MATCH(28,Data!$B$2:$B$745,0))),"")) | O42: =IF(B42="","",IFERROR(IF(INDEX(Data!$V$2:$V$745,MATCH(28,Data!$B$2:$B$745,0))="","",INDEX(Data!$V$2:$V$745,MATCH(28,Data!$B$2:$B$745,0))),"")) | P42: =IF(B42="","",IFERROR(IF(INDEX(Data!$M$2:$M$745,MATCH(28,Data!$B$2:$B$745,0))="","",INDEX(Data!$M$2:$M$745,MATCH(28,Data!$B$2:$B$745,0))),"")) | Q42: =IF(B42="","",IFERROR(IF(INDEX(Data!$AD$2:$AD$745,MATCH(28,Data!$B$2:$B$745,0))="","",INDEX(Data!$AD$2:$AD$745,MATCH(28,Data!$B$2:$B$745,0))),"")) | R42: =IF(B42="","",IFERROR(IF(INDEX(Data!$L$2:$L$745,MATCH(28,Data!$B$2:$B$745,0))="","",INDEX(Data!$L$2:$L$745,MATCH(28,Data!$B$2:$B$745,0))),"")) | AB42: Casbrove
B43: =IF(29<=COUNTIF(Data!$A$2:$A$745,TRUE),29,"") | C43: =IF(B43="","",IFERROR(_xlfn.IMAGE(IFERROR(IF(INDEX(Data!$J$2:$J$745,MATCH(29,Data!$B$2:$B$745,0))="","",INDEX(Data!$J$2:$J$745,MATCH(29,Data!$B$2:$B$745,0))),"")),"IMAGE COMING SOON")) | D43: =IF(B43="","",IFERROR(IF(INDEX(Data!$G$2:$G$745,MATCH(29,Data!$B$2:$B$745,0))="","",INDEX(Data!$G$2:$G$745,MATCH(29,Data!$B$2:$B$745,0))),"")&CHAR(10)&IFERROR(IF(INDEX(Data!$H$2:$H$745,MATCH(29,Data!$B$2:$B$745,0))="","",INDEX(Data!$H$2:$H$745,MATCH(29,Data!$B$2:$B$745,0))),"")) | E43: =IF(B43="","",IFERROR(IF(INDEX(Data!$I$2:$I$745,MATCH(29,Data!$B$2:$B$745,0))="","",INDEX(Data!$I$2:$I$745,MATCH(29,Data!$B$2:$B$745,0))),"")) | F43: =IF(B43="","",IFERROR(IF(INDEX(Data!$AJ$2:$AJ$745,MATCH(29,Data!$B$2:$B$745,0))="","",INDEX(Data!$AJ$2:$AJ$745,MATCH(29,Data!$B$2:$B$745,0))),"")) | G43: =IF(B43="","",TRIM(IFERROR(IF(INDEX(Data!$AF$2:$AF$745,MATCH(29,Data!$B$2:$B$745,0))="","",INDEX(Data!$AF$2:$AF$745,MATCH(29,Data!$B$2:$B$745,0))),"")&" "&IFERROR(IF(INDEX(Data!$AG$2:$AG$745,MATCH(29,Data!$B$2:$B$745,0))="","",INDEX(Data!$AG$2:$AG$745,MATCH(29,Data!$B$2:$B$745,0))),""))) | H43: =IF(B43="","",IFERROR(IF(INDEX(Data!$N$2:$N$745,MATCH(29,Data!$B$2:$B$745,0))="","",INDEX(Data!$N$2:$N$745,MATCH(29,Data!$B$2:$B$745,0))),"")) | I43: =IF(B43="","",IFERROR(IF(INDEX(Data!$O$2:$O$745,MATCH(29,Data!$B$2:$B$745,0))="","",INDEX(Data!$O$2:$O$745,MATCH(29,Data!$B$2:$B$745,0))),"")) | J43: =IF(B43="","",IFERROR(IF(INDEX(Data!$P$2:$P$745,MATCH(29,Data!$B$2:$B$745,0))="","",INDEX(Data!$P$2:$P$745,MATCH(29,Data!$B$2:$B$745,0))),"")) | K43: =IF(B43="","",IFERROR(IF(INDEX(Data!$R$2:$R$745,MATCH(29,Data!$B$2:$B$745,0))="","",INDEX(Data!$R$2:$R$745,MATCH(29,Data!$B$2:$B$745,0))),"")) | L43: =IF(B43="","",IFERROR(IF(INDEX(Data!$S$2:$S$745,MATCH(29,Data!$B$2:$B$745,0))="","",INDEX(Data!$S$2:$S$745,MATCH(29,Data!$B$2:$B$745,0))),"")) | M43: =IF(B43="","",IFERROR(IF(INDEX(Data!$T$2:$T$745,MATCH(29,Data!$B$2:$B$745,0))="","",INDEX(Data!$T$2:$T$745,MATCH(29,Data!$B$2:$B$745,0))),"")) | N43: =IF(B43="","",IFERROR(IF(INDEX(Data!$U$2:$U$745,MATCH(29,Data!$B$2:$B$745,0))="","",INDEX(Data!$U$2:$U$745,MATCH(29,Data!$B$2:$B$745,0))),"")) | O43: =IF(B43="","",IFERROR(IF(INDEX(Data!$V$2:$V$745,MATCH(29,Data!$B$2:$B$745,0))="","",INDEX(Data!$V$2:$V$745,MATCH(29,Data!$B$2:$B$745,0))),"")) | P43: =IF(B43="","",IFERROR(IF(INDEX(Data!$M$2:$M$745,MATCH(29,Data!$B$2:$B$745,0))="","",INDEX(Data!$M$2:$M$745,MATCH(29,Data!$B$2:$B$745,0))),"")) | Q43: =IF(B43="","",IFERROR(IF(INDEX(Data!$AD$2:$AD$745,MATCH(29,Data!$B$2:$B$745,0))="","",INDEX(Data!$AD$2:$AD$745,MATCH(29,Data!$B$2:$B$745,0))),"")) | R43: =IF(B43="","",IFERROR(IF(INDEX(Data!$L$2:$L$745,MATCH(29,Data!$B$2:$B$745,0))="","",INDEX(Data!$L$2:$L$745,MATCH(29,Data!$B$2:$B$745,0))),"")) | AB43: CGK Unlimited
B44: =IF(30<=COUNTIF(Data!$A$2:$A$745,TRUE),30,"") | C44: =IF(B44="","",IFERROR(_xlfn.IMAGE(IFERROR(IF(INDEX(Data!$J$2:$J$745,MATCH(30,Data!$B$2:$B$745,0))="","",INDEX(Data!$J$2:$J$745,MATCH(30,Data!$B$2:$B$745,0))),"")),"IMAGE COMING SOON")) | D44: =IF(B44="","",IFERROR(IF(INDEX(Data!$G$2:$G$745,MATCH(30,Data!$B$2:$B$745,0))="","",INDEX(Data!$G$2:$G$745,MATCH(30,Data!$B$2:$B$745,0))),"")&CHAR(10)&IFERROR(IF(INDEX(Data!$H$2:$H$745,MATCH(30,Data!$B$2:$B$745,0))="","",INDEX(Data!$H$2:$H$745,MATCH(30,Data!$B$2:$B$745,0))),"")) | E44: =IF(B44="","",IFERROR(IF(INDEX(Data!$I$2:$I$745,MATCH(30,Data!$B$2:$B$745,0))="","",INDEX(Data!$I$2:$I$745,MATCH(30,Data!$B$2:$B$745,0))),"")) | F44: =IF(B44="","",IFERROR(IF(INDEX(Data!$AJ$2:$AJ$745,MATCH(30,Data!$B$2:$B$745,0))="","",INDEX(Data!$AJ$2:$AJ$745,MATCH(30,Data!$B$2:$B$745,0))),"")) | G44: =IF(B44="","",TRIM(IFERROR(IF(INDEX(Data!$AF$2:$AF$745,MATCH(30,Data!$B$2:$B$745,0))="","",INDEX(Data!$AF$2:$AF$745,MATCH(30,Data!$B$2:$B$745,0))),"")&" "&IFERROR(IF(INDEX(Data!$AG$2:$AG$745,MATCH(30,Data!$B$2:$B$745,0))="","",INDEX(Data!$AG$2:$AG$745,MATCH(30,Data!$B$2:$B$745,0))),""))) | H44: =IF(B44="","",IFERROR(IF(INDEX(Data!$N$2:$N$745,MATCH(30,Data!$B$2:$B$745,0))="","",INDEX(Data!$N$2:$N$745,MATCH(30,Data!$B$2:$B$745,0))),"")) | I44: =IF(B44="","",IFERROR(IF(INDEX(Data!$O$2:$O$745,MATCH(30,Data!$B$2:$B$745,0))="","",INDEX(Data!$O$2:$O$745,MATCH(30,Data!$B$2:$B$745,0))),"")) | J44: =IF(B44="","",IFERROR(IF(INDEX(Data!$P$2:$P$745,MATCH(30,Data!$B$2:$B$745,0))="","",INDEX(Data!$P$2:$P$745,MATCH(30,Data!$B$2:$B$745,0))),"")) | K44: =IF(B44="","",IFERROR(IF(INDEX(Data!$R$2:$R$745,MATCH(30,Data!$B$2:$B$745,0))="","",INDEX(Data!$R$2:$R$745,MATCH(30,Data!$B$2:$B$745,0))),"")) | L44: =IF(B44="","",IFERROR(IF(INDEX(Data!$S$2:$S$745,MATCH(30,Data!$B$2:$B$745,0))="","",INDEX(Data!$S$2:$S$745,MATCH(30,Data!$B$2:$B$745,0))),"")) | M44: =IF(B44="","",IFERROR(IF(INDEX(Data!$T$2:$T$745,MATCH(30,Data!$B$2:$B$745,0))="","",INDEX(Data!$T$2:$T$745,MATCH(30,Data!$B$2:$B$745,0))),"")) | N44: =IF(B44="","",IFERROR(IF(INDEX(Data!$U$2:$U$745,MATCH(30,Data!$B$2:$B$745,0))="","",INDEX(Data!$U$2:$U$745,MATCH(30,Data!$B$2:$B$745,0))),"")) | O44: =IF(B44="","",IFERROR(IF(INDEX(Data!$V$2:$V$745,MATCH(30,Data!$B$2:$B$745,0))="","",INDEX(Data!$V$2:$V$745,MATCH(30,Data!$B$2:$B$745,0))),"")) | P44: =IF(B44="","",IFERROR(IF(INDEX(Data!$M$2:$M$745,MATCH(30,Data!$B$2:$B$745,0))="","",INDEX(Data!$M$2:$M$745,MATCH(30,Data!$B$2:$B$745,0))),"")) | Q44: =IF(B44="","",IFERROR(IF(INDEX(Data!$AD$2:$AD$745,MATCH(30,Data!$B$2:$B$745,0))="","",INDEX(Data!$AD$2:$AD$745,MATCH(30,Data!$B$2:$B$745,0))),"")) | R44: =IF(B44="","",IFERROR(IF(INDEX(Data!$L$2:$L$745,MATCH(30,Data!$B$2:$B$745,0))="","",INDEX(Data!$L$2:$L$745,MATCH(30,Data!$B$2:$B$745,0))),"")) | AB44: CHOSHOME
B45: =IF(31<=COUNTIF(Data!$A$2:$A$745,TRUE),31,"") | C45: =IF(B45="","",IFERROR(_xlfn.IMAGE(IFERROR(IF(INDEX(Data!$J$2:$J$745,MATCH(31,Data!$B$2:$B$745,0))="","",INDEX(Data!$J$2:$J$745,MATCH(31,Data!$B$2:$B$745,0))),"")),"IMAGE COMING SOON")) | D45: =IF(B45="","",IFERROR(IF(INDEX(Data!$G$2:$G$745,MATCH(31,Data!$B$2:$B$745,0))="","",INDEX(Data!$G$2:$G$745,MATCH(31,Data!$B$2:$B$745,0))),"")&CHAR(10)&IFERROR(IF(INDEX(Data!$H$2:$H$745,MATCH(31,Data!$B$2:$B$745,0))="","",INDEX(Data!$H$2:$H$745,MATCH(31,Data!$B$2:$B$745,0))),"")) | E45: =IF(B45="","",IFERROR(IF(INDEX(Data!$I$2:$I$745,MATCH(31,Data!$B$2:$B$745,0))="","",INDEX(Data!$I$2:$I$745,MATCH(31,Data!$B$2:$B$745,0))),"")) | F45: =IF(B45="","",IFERROR(IF(INDEX(Data!$AJ$2:$AJ$745,MATCH(31,Data!$B$2:$B$745,0))="","",INDEX(Data!$AJ$2:$AJ$745,MATCH(31,Data!$B$2:$B$745,0))),"")) | G45: =IF(B45="","",TRIM(IFERROR(IF(INDEX(Data!$AF$2:$AF$745,MATCH(31,Data!$B$2:$B$745,0))="","",INDEX(Data!$AF$2:$AF$745,MATCH(31,Data!$B$2:$B$745,0))),"")&" "&IFERROR(IF(INDEX(Data!$AG$2:$AG$745,MATCH(31,Data!$B$2:$B$745,0))="","",INDEX(Data!$AG$2:$AG$745,MATCH(31,Data!$B$2:$B$745,0))),""))) | H45: =IF(B45="","",IFERROR(IF(INDEX(Data!$N$2:$N$745,MATCH(31,Data!$B$2:$B$745,0))="","",INDEX(Data!$N$2:$N$745,MATCH(31,Data!$B$2:$B$745,0))),"")) | I45: =IF(B45="","",IFERROR(IF(INDEX(Data!$O$2:$O$745,MATCH(31,Data!$B$2:$B$745,0))="","",INDEX(Data!$O$2:$O$745,MATCH(31,Data!$B$2:$B$745,0))),"")) | J45: =IF(B45="","",IFERROR(IF(INDEX(Data!$P$2:$P$745,MATCH(31,Data!$B$2:$B$745,0))="","",INDEX(Data!$P$2:$P$745,MATCH(31,Data!$B$2:$B$745,0))),"")) | K45: =IF(B45="","",IFERROR(IF(INDEX(Data!$R$2:$R$745,MATCH(31,Data!$B$2:$B$745,0))="","",INDEX(Data!$R$2:$R$745,MATCH(31,Data!$B$2:$B$745,0))),"")) | L45: =IF(B45="","",IFERROR(IF(INDEX(Data!$S$2:$S$745,MATCH(31,Data!$B$2:$B$745,0))="","",INDEX(Data!$S$2:$S$745,MATCH(31,Data!$B$2:$B$745,0))),"")) | M45: =IF(B45="","",IFERROR(IF(INDEX(Data!$T$2:$T$745,MATCH(31,Data!$B$2:$B$745,0))="","",INDEX(Data!$T$2:$T$745,MATCH(31,Data!$B$2:$B$745,0))),"")) | N45: =IF(B45="","",IFERROR(IF(INDEX(Data!$U$2:$U$745,MATCH(31,Data!$B$2:$B$745,0))="","",INDEX(Data!$U$2:$U$745,MATCH(31,Data!$B$2:$B$745,0))),"")) | O45: =IF(B45="","",IFERROR(IF(INDEX(Data!$V$2:$V$745,MATCH(31,Data!$B$2:$B$745,0))="","",INDEX(Data!$V$2:$V$745,MATCH(31,Data!$B$2:$B$745,0))),"")) | P45: =IF(B45="","",IFERROR(IF(INDEX(Data!$M$2:$M$745,MATCH(31,Data!$B$2:$B$745,0))="","",INDEX(Data!$M$2:$M$745,MATCH(31,Data!$B$2:$B$745,0))),"")) | Q45: =IF(B45="","",IFERROR(IF(INDEX(Data!$AD$2:$AD$745,MATCH(31,Data!$B$2:$B$745,0))="","",INDEX(Data!$AD$2:$AD$745,MATCH(31,Data!$B$2:$B$745,0))),"")) | R45: =IF(B45="","",IFERROR(IF(INDEX(Data!$L$2:$L$745,MATCH(31,Data!$B$2:$B$745,0))="","",INDEX(Data!$L$2:$L$745,MATCH(31,Data!$B$2:$B$745,0))),"")) | AB45: Cobedzy
B46: =IF(32<=COUNTIF(Data!$A$2:$A$745,TRUE),32,"") | C46: =IF(B46="","",IFERROR(_xlfn.IMAGE(IFERROR(IF(INDEX(Data!$J$2:$J$745,MATCH(32,Data!$B$2:$B$745,0))="","",INDEX(Data!$J$2:$J$745,MATCH(32,Data!$B$2:$B$745,0))),"")),"IMAGE COMING SOON")) | D46: =IF(B46="","",IFERROR(IF(INDEX(Data!$G$2:$G$745,MATCH(32,Data!$B$2:$B$745,0))="","",INDEX(Data!$G$2:$G$745,MATCH(32,Data!$B$2:$B$745,0))),"")&CHAR(10)&IFERROR(IF(INDEX(Data!$H$2:$H$745,MATCH(32,Data!$B$2:$B$745,0))="","",INDEX(Data!$H$2:$H$745,MATCH(32,Data!$B$2:$B$745,0))),"")) | E46: =IF(B46="","",IFERROR(IF(INDEX(Data!$I$2:$I$745,MATCH(32,Data!$B$2:$B$745,0))="","",INDEX(Data!$I$2:$I$745,MATCH(32,Data!$B$2:$B$745,0))),"")) | F46: =IF(B46="","",IFERROR(IF(INDEX(Data!$AJ$2:$AJ$745,MATCH(32,Data!$B$2:$B$745,0))="","",INDEX(Data!$AJ$2:$AJ$745,MATCH(32,Data!$B$2:$B$745,0))),"")) | G46: =IF(B46="","",TRIM(IFERROR(IF(INDEX(Data!$AF$2:$AF$745,MATCH(32,Data!$B$2:$B$745,0))="","",INDEX(Data!$AF$2:$AF$745,MATCH(32,Data!$B$2:$B$745,0))),"")&" "&IFERROR(IF(INDEX(Data!$AG$2:$AG$745,MATCH(32,Data!$B$2:$B$745,0))="","",INDEX(Data!$AG$2:$AG$745,MATCH(32,Data!$B$2:$B$745,0))),""))) | H46: =IF(B46="","",IFERROR(IF(INDEX(Data!$N$2:$N$745,MATCH(32,Data!$B$2:$B$745,0))="","",INDEX(Data!$N$2:$N$745,MATCH(32,Data!$B$2:$B$745,0))),"")) | I46: =IF(B46="","",IFERROR(IF(INDEX(Data!$O$2:$O$745,MATCH(32,Data!$B$2:$B$745,0))="","",INDEX(Data!$O$2:$O$745,MATCH(32,Data!$B$2:$B$745,0))),"")) | J46: =IF(B46="","",IFERROR(IF(INDEX(Data!$P$2:$P$745,MATCH(32,Data!$B$2:$B$745,0))="","",INDEX(Data!$P$2:$P$745,MATCH(32,Data!$B$2:$B$745,0))),"")) | K46: =IF(B46="","",IFERROR(IF(INDEX(Data!$R$2:$R$745,MATCH(32,Data!$B$2:$B$745,0))="","",INDEX(Data!$R$2:$R$745,MATCH(32,Data!$B$2:$B$745,0))),"")) | L46: =IF(B46="","",IFERROR(IF(INDEX(Data!$S$2:$S$745,MATCH(32,Data!$B$2:$B$745,0))="","",INDEX(Data!$S$2:$S$745,MATCH(32,Data!$B$2:$B$745,0))),"")) | M46: =IF(B46="","",IFERROR(IF(INDEX(Data!$T$2:$T$745,MATCH(32,Data!$B$2:$B$745,0))="","",INDEX(Data!$T$2:$T$745,MATCH(32,Data!$B$2:$B$745,0))),"")) | N46: =IF(B46="","",IFERROR(IF(INDEX(Data!$U$2:$U$745,MATCH(32,Data!$B$2:$B$745,0))="","",INDEX(Data!$U$2:$U$745,MATCH(32,Data!$B$2:$B$745,0))),"")) | O46: =IF(B46="","",IFERROR(IF(INDEX(Data!$V$2:$V$745,MATCH(32,Data!$B$2:$B$745,0))="","",INDEX(Data!$V$2:$V$745,MATCH(32,Data!$B$2:$B$745,0))),"")) | P46: =IF(B46="","",IFERROR(IF(INDEX(Data!$M$2:$M$745,MATCH(32,Data!$B$2:$B$745,0))="","",INDEX(Data!$M$2:$M$745,MATCH(32,Data!$B$2:$B$745,0))),"")) | Q46: =IF(B46="","",IFERROR(IF(INDEX(Data!$AD$2:$AD$745,MATCH(32,Data!$B$2:$B$745,0))="","",INDEX(Data!$AD$2:$AD$745,MATCH(32,Data!$B$2:$B$745,0))),"")) | R46: =IF(B46="","",IFERROR(IF(INDEX(Data!$L$2:$L$745,MATCH(32,Data!$B$2:$B$745,0))="","",INDEX(Data!$L$2:$L$745,MATCH(32,Data!$B$2:$B$745,0))),"")) | AB46: Colorado Home Co
B47: =IF(33<=COUNTIF(Data!$A$2:$A$745,TRUE),33,"") | C47: =IF(B47="","",IFERROR(_xlfn.IMAGE(IFERROR(IF(INDEX(Data!$J$2:$J$745,MATCH(33,Data!$B$2:$B$745,0))="","",INDEX(Data!$J$2:$J$745,MATCH(33,Data!$B$2:$B$745,0))),"")),"IMAGE COMING SOON")) | D47: =IF(B47="","",IFERROR(IF(INDEX(Data!$G$2:$G$745,MATCH(33,Data!$B$2:$B$745,0))="","",INDEX(Data!$G$2:$G$745,MATCH(33,Data!$B$2:$B$745,0))),"")&CHAR(10)&IFERROR(IF(INDEX(Data!$H$2:$H$745,MATCH(33,Data!$B$2:$B$745,0))="","",INDEX(Data!$H$2:$H$745,MATCH(33,Data!$B$2:$B$745,0))),"")) | E47: =IF(B47="","",IFERROR(IF(INDEX(Data!$I$2:$I$745,MATCH(33,Data!$B$2:$B$745,0))="","",INDEX(Data!$I$2:$I$745,MATCH(33,Data!$B$2:$B$745,0))),"")) | F47: =IF(B47="","",IFERROR(IF(INDEX(Data!$AJ$2:$AJ$745,MATCH(33,Data!$B$2:$B$745,0))="","",INDEX(Data!$AJ$2:$AJ$745,MATCH(33,Data!$B$2:$B$745,0))),"")) | G47: =IF(B47="","",TRIM(IFERROR(IF(INDEX(Data!$AF$2:$AF$745,MATCH(33,Data!$B$2:$B$745,0))="","",INDEX(Data!$AF$2:$AF$745,MATCH(33,Data!$B$2:$B$745,0))),"")&" "&IFERROR(IF(INDEX(Data!$AG$2:$AG$745,MATCH(33,Data!$B$2:$B$745,0))="","",INDEX(Data!$AG$2:$AG$745,MATCH(33,Data!$B$2:$B$745,0))),""))) | H47: =IF(B47="","",IFERROR(IF(INDEX(Data!$N$2:$N$745,MATCH(33,Data!$B$2:$B$745,0))="","",INDEX(Data!$N$2:$N$745,MATCH(33,Data!$B$2:$B$745,0))),"")) | I47: =IF(B47="","",IFERROR(IF(INDEX(Data!$O$2:$O$745,MATCH(33,Data!$B$2:$B$745,0))="","",INDEX(Data!$O$2:$O$745,MATCH(33,Data!$B$2:$B$745,0))),"")) | J47: =IF(B47="","",IFERROR(IF(INDEX(Data!$P$2:$P$745,MATCH(33,Data!$B$2:$B$745,0))="","",INDEX(Data!$P$2:$P$745,MATCH(33,Data!$B$2:$B$745,0))),"")) | K47: =IF(B47="","",IFERROR(IF(INDEX(Data!$R$2:$R$745,MATCH(33,Data!$B$2:$B$745,0))="","",INDEX(Data!$R$2:$R$745,MATCH(33,Data!$B$2:$B$745,0))),"")) | L47: =IF(B47="","",IFERROR(IF(INDEX(Data!$S$2:$S$745,MATCH(33,Data!$B$2:$B$745,0))="","",INDEX(Data!$S$2:$S$745,MATCH(33,Data!$B$2:$B$745,0))),"")) | M47: =IF(B47="","",IFERROR(IF(INDEX(Data!$T$2:$T$745,MATCH(33,Data!$B$2:$B$745,0))="","",INDEX(Data!$T$2:$T$745,MATCH(33,Data!$B$2:$B$745,0))),"")) | N47: =IF(B47="","",IFERROR(IF(INDEX(Data!$U$2:$U$745,MATCH(33,Data!$B$2:$B$745,0))="","",INDEX(Data!$U$2:$U$745,MATCH(33,Data!$B$2:$B$745,0))),"")) | O47: =IF(B47="","",IFERROR(IF(INDEX(Data!$V$2:$V$745,MATCH(33,Data!$B$2:$B$745,0))="","",INDEX(Data!$V$2:$V$745,MATCH(33,Data!$B$2:$B$745,0))),"")) | P47: =IF(B47="","",IFERROR(IF(INDEX(Data!$M$2:$M$745,MATCH(33,Data!$B$2:$B$745,0))="","",INDEX(Data!$M$2:$M$745,MATCH(33,Data!$B$2:$B$745,0))),"")) | Q47: =IF(B47="","",IFERROR(IF(INDEX(Data!$AD$2:$AD$745,MATCH(33,Data!$B$2:$B$745,0))="","",INDEX(Data!$AD$2:$AD$745,MATCH(33,Data!$B$2:$B$745,0))),"")) | R47: =IF(B47="","",IFERROR(IF(INDEX(Data!$L$2:$L$745,MATCH(33,Data!$B$2:$B$745,0))="","",INDEX(Data!$L$2:$L$745,MATCH(33,Data!$B$2:$B$745,0))),"")) | AB47: Comfort Spaces
B48: =IF(34<=COUNTIF(Data!$A$2:$A$745,TRUE),34,"") | C48: =IF(B48="","",IFERROR(_xlfn.IMAGE(IFERROR(IF(INDEX(Data!$J$2:$J$745,MATCH(34,Data!$B$2:$B$745,0))="","",INDEX(Data!$J$2:$J$745,MATCH(34,Data!$B$2:$B$745,0))),"")),"IMAGE COMING SOON")) | D48: =IF(B48="","",IFERROR(IF(INDEX(Data!$G$2:$G$745,MATCH(34,Data!$B$2:$B$745,0))="","",INDEX(Data!$G$2:$G$745,MATCH(34,Data!$B$2:$B$745,0))),"")&CHAR(10)&IFERROR(IF(INDEX(Data!$H$2:$H$745,MATCH(34,Data!$B$2:$B$745,0))="","",INDEX(Data!$H$2:$H$745,MATCH(34,Data!$B$2:$B$745,0))),"")) | E48: =IF(B48="","",IFERROR(IF(INDEX(Data!$I$2:$I$745,MATCH(34,Data!$B$2:$B$745,0))="","",INDEX(Data!$I$2:$I$745,MATCH(34,Data!$B$2:$B$745,0))),"")) | F48: =IF(B48="","",IFERROR(IF(INDEX(Data!$AJ$2:$AJ$745,MATCH(34,Data!$B$2:$B$745,0))="","",INDEX(Data!$AJ$2:$AJ$745,MATCH(34,Data!$B$2:$B$745,0))),"")) | G48: =IF(B48="","",TRIM(IFERROR(IF(INDEX(Data!$AF$2:$AF$745,MATCH(34,Data!$B$2:$B$745,0))="","",INDEX(Data!$AF$2:$AF$745,MATCH(34,Data!$B$2:$B$745,0))),"")&" "&IFERROR(IF(INDEX(Data!$AG$2:$AG$745,MATCH(34,Data!$B$2:$B$745,0))="","",INDEX(Data!$AG$2:$AG$745,MATCH(34,Data!$B$2:$B$745,0))),""))) | H48: =IF(B48="","",IFERROR(IF(INDEX(Data!$N$2:$N$745,MATCH(34,Data!$B$2:$B$745,0))="","",INDEX(Data!$N$2:$N$745,MATCH(34,Data!$B$2:$B$745,0))),"")) | I48: =IF(B48="","",IFERROR(IF(INDEX(Data!$O$2:$O$745,MATCH(34,Data!$B$2:$B$745,0))="","",INDEX(Data!$O$2:$O$745,MATCH(34,Data!$B$2:$B$745,0))),"")) | J48: =IF(B48="","",IFERROR(IF(INDEX(Data!$P$2:$P$745,MATCH(34,Data!$B$2:$B$745,0))="","",INDEX(Data!$P$2:$P$745,MATCH(34,Data!$B$2:$B$745,0))),"")) | K48: =IF(B48="","",IFERROR(IF(INDEX(Data!$R$2:$R$745,MATCH(34,Data!$B$2:$B$745,0))="","",INDEX(Data!$R$2:$R$745,MATCH(34,Data!$B$2:$B$745,0))),"")) | L48: =IF(B48="","",IFERROR(IF(INDEX(Data!$S$2:$S$745,MATCH(34,Data!$B$2:$B$745,0))="","",INDEX(Data!$S$2:$S$745,MATCH(34,Data!$B$2:$B$745,0))),"")) | M48: =IF(B48="","",IFERROR(IF(INDEX(Data!$T$2:$T$745,MATCH(34,Data!$B$2:$B$745,0))="","",INDEX(Data!$T$2:$T$745,MATCH(34,Data!$B$2:$B$745,0))),"")) | N48: =IF(B48="","",IFERROR(IF(INDEX(Data!$U$2:$U$745,MATCH(34,Data!$B$2:$B$745,0))="","",INDEX(Data!$U$2:$U$745,MATCH(34,Data!$B$2:$B$745,0))),"")) | O48: =IF(B48="","",IFERROR(IF(INDEX(Data!$V$2:$V$745,MATCH(34,Data!$B$2:$B$745,0))="","",INDEX(Data!$V$2:$V$745,MATCH(34,Data!$B$2:$B$745,0))),"")) | P48: =IF(B48="","",IFERROR(IF(INDEX(Data!$M$2:$M$745,MATCH(34,Data!$B$2:$B$745,0))="","",INDEX(Data!$M$2:$M$745,MATCH(34,Data!$B$2:$B$745,0))),"")) | Q48: =IF(B48="","",IFERROR(IF(INDEX(Data!$AD$2:$AD$745,MATCH(34,Data!$B$2:$B$745,0))="","",INDEX(Data!$AD$2:$AD$745,MATCH(34,Data!$B$2:$B$745,0))),"")) | R48: =IF(B48="","",IFERROR(IF(INDEX(Data!$L$2:$L$745,MATCH(34,Data!$B$2:$B$745,0))="","",INDEX(Data!$L$2:$L$745,MATCH(34,Data!$B$2:$B$745,0))),"")) | AB48: comurdyo
B49: =IF(35<=COUNTIF(Data!$A$2:$A$745,TRUE),35,"") | C49: =IF(B49="","",IFERROR(_xlfn.IMAGE(IFERROR(IF(INDEX(Data!$J$2:$J$745,MATCH(35,Data!$B$2:$B$745,0))="","",INDEX(Data!$J$2:$J$745,MATCH(35,Data!$B$2:$B$745,0))),"")),"IMAGE COMING SOON")) | D49: =IF(B49="","",IFERROR(IF(INDEX(Data!$G$2:$G$745,MATCH(35,Data!$B$2:$B$745,0))="","",INDEX(Data!$G$2:$G$745,MATCH(35,Data!$B$2:$B$745,0))),"")&CHAR(10)&IFERROR(IF(INDEX(Data!$H$2:$H$745,MATCH(35,Data!$B$2:$B$745,0))="","",INDEX(Data!$H$2:$H$745,MATCH(35,Data!$B$2:$B$745,0))),"")) | E49: =IF(B49="","",IFERROR(IF(INDEX(Data!$I$2:$I$745,MATCH(35,Data!$B$2:$B$745,0))="","",INDEX(Data!$I$2:$I$745,MATCH(35,Data!$B$2:$B$745,0))),"")) | F49: =IF(B49="","",IFERROR(IF(INDEX(Data!$AJ$2:$AJ$745,MATCH(35,Data!$B$2:$B$745,0))="","",INDEX(Data!$AJ$2:$AJ$745,MATCH(35,Data!$B$2:$B$745,0))),"")) | G49: =IF(B49="","",TRIM(IFERROR(IF(INDEX(Data!$AF$2:$AF$745,MATCH(35,Data!$B$2:$B$745,0))="","",INDEX(Data!$AF$2:$AF$745,MATCH(35,Data!$B$2:$B$745,0))),"")&" "&IFERROR(IF(INDEX(Data!$AG$2:$AG$745,MATCH(35,Data!$B$2:$B$745,0))="","",INDEX(Data!$AG$2:$AG$745,MATCH(35,Data!$B$2:$B$745,0))),""))) | H49: =IF(B49="","",IFERROR(IF(INDEX(Data!$N$2:$N$745,MATCH(35,Data!$B$2:$B$745,0))="","",INDEX(Data!$N$2:$N$745,MATCH(35,Data!$B$2:$B$745,0))),"")) | I49: =IF(B49="","",IFERROR(IF(INDEX(Data!$O$2:$O$745,MATCH(35,Data!$B$2:$B$745,0))="","",INDEX(Data!$O$2:$O$745,MATCH(35,Data!$B$2:$B$745,0))),"")) | J49: =IF(B49="","",IFERROR(IF(INDEX(Data!$P$2:$P$745,MATCH(35,Data!$B$2:$B$745,0))="","",INDEX(Data!$P$2:$P$745,MATCH(35,Data!$B$2:$B$745,0))),"")) | K49: =IF(B49="","",IFERROR(IF(INDEX(Data!$R$2:$R$745,MATCH(35,Data!$B$2:$B$745,0))="","",INDEX(Data!$R$2:$R$745,MATCH(35,Data!$B$2:$B$745,0))),"")) | L49: =IF(B49="","",IFERROR(IF(INDEX(Data!$S$2:$S$745,MATCH(35,Data!$B$2:$B$745,0))="","",INDEX(Data!$S$2:$S$745,MATCH(35,Data!$B$2:$B$745,0))),"")) | M49: =IF(B49="","",IFERROR(IF(INDEX(Data!$T$2:$T$745,MATCH(35,Data!$B$2:$B$745,0))="","",INDEX(Data!$T$2:$T$745,MATCH(35,Data!$B$2:$B$745,0))),"")) | N49: =IF(B49="","",IFERROR(IF(INDEX(Data!$U$2:$U$745,MATCH(35,Data!$B$2:$B$745,0))="","",INDEX(Data!$U$2:$U$745,MATCH(35,Data!$B$2:$B$745,0))),"")) | O49: =IF(B49="","",IFERROR(IF(INDEX(Data!$V$2:$V$745,MATCH(35,Data!$B$2:$B$745,0))="","",INDEX(Data!$V$2:$V$745,MATCH(35,Data!$B$2:$B$745,0))),"")) | P49: =IF(B49="","",IFERROR(IF(INDEX(Data!$M$2:$M$745,MATCH(35,Data!$B$2:$B$745,0))="","",INDEX(Data!$M$2:$M$745,MATCH(35,Data!$B$2:$B$745,0))),"")) | Q49: =IF(B49="","",IFERROR(IF(INDEX(Data!$AD$2:$AD$745,MATCH(35,Data!$B$2:$B$745,0))="","",INDEX(Data!$AD$2:$AD$745,MATCH(35,Data!$B$2:$B$745,0))),"")) | R49: =IF(B49="","",IFERROR(IF(INDEX(Data!$L$2:$L$745,MATCH(35,Data!$B$2:$B$745,0))="","",INDEX(Data!$L$2:$L$745,MATCH(35,Data!$B$2:$B$745,0))),"")) | AB49: Consevisen
B50: =IF(36<=COUNTIF(Data!$A$2:$A$745,TRUE),36,"") | C50: =IF(B50="","",IFERROR(_xlfn.IMAGE(IFERROR(IF(INDEX(Data!$J$2:$J$745,MATCH(36,Data!$B$2:$B$745,0))="","",INDEX(Data!$J$2:$J$745,MATCH(36,Data!$B$2:$B$745,0))),"")),"IMAGE COMING SOON")) | D50: =IF(B50="","",IFERROR(IF(INDEX(Data!$G$2:$G$745,MATCH(36,Data!$B$2:$B$745,0))="","",INDEX(Data!$G$2:$G$745,MATCH(36,Data!$B$2:$B$745,0))),"")&CHAR(10)&IFERROR(IF(INDEX(Data!$H$2:$H$745,MATCH(36,Data!$B$2:$B$745,0))="","",INDEX(Data!$H$2:$H$745,MATCH(36,Data!$B$2:$B$745,0))),"")) | E50: =IF(B50="","",IFERROR(IF(INDEX(Data!$I$2:$I$745,MATCH(36,Data!$B$2:$B$745,0))="","",INDEX(Data!$I$2:$I$745,MATCH(36,Data!$B$2:$B$745,0))),"")) | F50: =IF(B50="","",IFERROR(IF(INDEX(Data!$AJ$2:$AJ$745,MATCH(36,Data!$B$2:$B$745,0))="","",INDEX(Data!$AJ$2:$AJ$745,MATCH(36,Data!$B$2:$B$745,0))),"")) | G50: =IF(B50="","",TRIM(IFERROR(IF(INDEX(Data!$AF$2:$AF$745,MATCH(36,Data!$B$2:$B$745,0))="","",INDEX(Data!$AF$2:$AF$745,MATCH(36,Data!$B$2:$B$745,0))),"")&" "&IFERROR(IF(INDEX(Data!$AG$2:$AG$745,MATCH(36,Data!$B$2:$B$745,0))="","",INDEX(Data!$AG$2:$AG$745,MATCH(36,Data!$B$2:$B$745,0))),""))) | H50: =IF(B50="","",IFERROR(IF(INDEX(Data!$N$2:$N$745,MATCH(36,Data!$B$2:$B$745,0))="","",INDEX(Data!$N$2:$N$745,MATCH(36,Data!$B$2:$B$745,0))),"")) | I50: =IF(B50="","",IFERROR(IF(INDEX(Data!$O$2:$O$745,MATCH(36,Data!$B$2:$B$745,0))="","",INDEX(Data!$O$2:$O$745,MATCH(36,Data!$B$2:$B$745,0))),"")) | J50: =IF(B50="","",IFERROR(IF(INDEX(Data!$P$2:$P$745,MATCH(36,Data!$B$2:$B$745,0))="","",INDEX(Data!$P$2:$P$745,MATCH(36,Data!$B$2:$B$745,0))),"")) | K50: =IF(B50="","",IFERROR(IF(INDEX(Data!$R$2:$R$745,MATCH(36,Data!$B$2:$B$745,0))="","",INDEX(Data!$R$2:$R$745,MATCH(36,Data!$B$2:$B$745,0))),"")) | L50: =IF(B50="","",IFERROR(IF(INDEX(Data!$S$2:$S$745,MATCH(36,Data!$B$2:$B$745,0))="","",INDEX(Data!$S$2:$S$745,MATCH(36,Data!$B$2:$B$745,0))),"")) | M50: =IF(B50="","",IFERROR(IF(INDEX(Data!$T$2:$T$745,MATCH(36,Data!$B$2:$B$745,0))="","",INDEX(Data!$T$2:$T$745,MATCH(36,Data!$B$2:$B$745,0))),"")) | N50: =IF(B50="","",IFERROR(IF(INDEX(Data!$U$2:$U$745,MATCH(36,Data!$B$2:$B$745,0))="","",INDEX(Data!$U$2:$U$745,MATCH(36,Data!$B$2:$B$745,0))),"")) | O50: =IF(B50="","",IFERROR(IF(INDEX(Data!$V$2:$V$745,MATCH(36,Data!$B$2:$B$745,0))="","",INDEX(Data!$V$2:$V$745,MATCH(36,Data!$B$2:$B$745,0))),"")) | P50: =IF(B50="","",IFERROR(IF(INDEX(Data!$M$2:$M$745,MATCH(36,Data!$B$2:$B$745,0))="","",INDEX(Data!$M$2:$M$745,MATCH(36,Data!$B$2:$B$745,0))),"")) | Q50: =IF(B50="","",IFERROR(IF(INDEX(Data!$AD$2:$AD$745,MATCH(36,Data!$B$2:$B$745,0))="","",INDEX(Data!$AD$2:$AD$745,MATCH(36,Data!$B$2:$B$745,0))),"")) | R50: =IF(B50="","",IFERROR(IF(INDEX(Data!$L$2:$L$745,MATCH(36,Data!$B$2:$B$745,0))="","",INDEX(Data!$L$2:$L$745,MATCH(36,Data!$B$2:$B$745,0))),"")) | AB50: Coop Home Goods
B51: =IF(37<=COUNTIF(Data!$A$2:$A$745,TRUE),37,"") | C51: =IF(B51="","",IFERROR(_xlfn.IMAGE(IFERROR(IF(INDEX(Data!$J$2:$J$745,MATCH(37,Data!$B$2:$B$745,0))="","",INDEX(Data!$J$2:$J$745,MATCH(37,Data!$B$2:$B$745,0))),"")),"IMAGE COMING SOON")) | D51: =IF(B51="","",IFERROR(IF(INDEX(Data!$G$2:$G$745,MATCH(37,Data!$B$2:$B$745,0))="","",INDEX(Data!$G$2:$G$745,MATCH(37,Data!$B$2:$B$745,0))),"")&CHAR(10)&IFERROR(IF(INDEX(Data!$H$2:$H$745,MATCH(37,Data!$B$2:$B$745,0))="","",INDEX(Data!$H$2:$H$745,MATCH(37,Data!$B$2:$B$745,0))),"")) | E51: =IF(B51="","",IFERROR(IF(INDEX(Data!$I$2:$I$745,MATCH(37,Data!$B$2:$B$745,0))="","",INDEX(Data!$I$2:$I$745,MATCH(37,Data!$B$2:$B$745,0))),"")) | F51: =IF(B51="","",IFERROR(IF(INDEX(Data!$AJ$2:$AJ$745,MATCH(37,Data!$B$2:$B$745,0))="","",INDEX(Data!$AJ$2:$AJ$745,MATCH(37,Data!$B$2:$B$745,0))),"")) | G51: =IF(B51="","",TRIM(IFERROR(IF(INDEX(Data!$AF$2:$AF$745,MATCH(37,Data!$B$2:$B$745,0))="","",INDEX(Data!$AF$2:$AF$745,MATCH(37,Data!$B$2:$B$745,0))),"")&" "&IFERROR(IF(INDEX(Data!$AG$2:$AG$745,MATCH(37,Data!$B$2:$B$745,0))="","",INDEX(Data!$AG$2:$AG$745,MATCH(37,Data!$B$2:$B$745,0))),""))) | H51: =IF(B51="","",IFERROR(IF(INDEX(Data!$N$2:$N$745,MATCH(37,Data!$B$2:$B$745,0))="","",INDEX(Data!$N$2:$N$745,MATCH(37,Data!$B$2:$B$745,0))),"")) | I51: =IF(B51="","",IFERROR(IF(INDEX(Data!$O$2:$O$745,MATCH(37,Data!$B$2:$B$745,0))="","",INDEX(Data!$O$2:$O$745,MATCH(37,Data!$B$2:$B$745,0))),"")) | J51: =IF(B51="","",IFERROR(IF(INDEX(Data!$P$2:$P$745,MATCH(37,Data!$B$2:$B$745,0))="","",INDEX(Data!$P$2:$P$745,MATCH(37,Data!$B$2:$B$745,0))),"")) | K51: =IF(B51="","",IFERROR(IF(INDEX(Data!$R$2:$R$745,MATCH(37,Data!$B$2:$B$745,0))="","",INDEX(Data!$R$2:$R$745,MATCH(37,Data!$B$2:$B$745,0))),"")) | L51: =IF(B51="","",IFERROR(IF(INDEX(Data!$S$2:$S$745,MATCH(37,Data!$B$2:$B$745,0))="","",INDEX(Data!$S$2:$S$745,MATCH(37,Data!$B$2:$B$745,0))),"")) | M51: =IF(B51="","",IFERROR(IF(INDEX(Data!$T$2:$T$745,MATCH(37,Data!$B$2:$B$745,0))="","",INDEX(Data!$T$2:$T$745,MATCH(37,Data!$B$2:$B$745,0))),"")) | N51: =IF(B51="","",IFERROR(IF(INDEX(Data!$U$2:$U$745,MATCH(37,Data!$B$2:$B$745,0))="","",INDEX(Data!$U$2:$U$745,MATCH(37,Data!$B$2:$B$745,0))),"")) | O51: =IF(B51="","",IFERROR(IF(INDEX(Data!$V$2:$V$745,MATCH(37,Data!$B$2:$B$745,0))="","",INDEX(Data!$V$2:$V$745,MATCH(37,Data!$B$2:$B$745,0))),"")) | P51: =IF(B51="","",IFERROR(IF(INDEX(Data!$M$2:$M$745,MATCH(37,Data!$B$2:$B$745,0))="","",INDEX(Data!$M$2:$M$745,MATCH(37,Data!$B$2:$B$745,0))),"")) | Q51: =IF(B51="","",IFERROR(IF(INDEX(Data!$AD$2:$AD$745,MATCH(37,Data!$B$2:$B$745,0))="","",INDEX(Data!$AD$2:$AD$745,MATCH(37,Data!$B$2:$B$745,0))),"")) | R51: =IF(B51="","",IFERROR(IF(INDEX(Data!$L$2:$L$745,MATCH(37,Data!$B$2:$B$745,0))="","",INDEX(Data!$L$2:$L$745,MATCH(37,Data!$B$2:$B$745,0))),"")) | AB51: Cosy House Collection
B52: =IF(38<=COUNTIF(Data!$A$2:$A$745,TRUE),38,"") | C52: =IF(B52="","",IFERROR(_xlfn.IMAGE(IFERROR(IF(INDEX(Data!$J$2:$J$745,MATCH(38,Data!$B$2:$B$745,0))="","",INDEX(Data!$J$2:$J$745,MATCH(38,Data!$B$2:$B$745,0))),"")),"IMAGE COMING SOON")) | D52: =IF(B52="","",IFERROR(IF(INDEX(Data!$G$2:$G$745,MATCH(38,Data!$B$2:$B$745,0))="","",INDEX(Data!$G$2:$G$745,MATCH(38,Data!$B$2:$B$745,0))),"")&CHAR(10)&IFERROR(IF(INDEX(Data!$H$2:$H$745,MATCH(38,Data!$B$2:$B$745,0))="","",INDEX(Data!$H$2:$H$745,MATCH(38,Data!$B$2:$B$745,0))),"")) | E52: =IF(B52="","",IFERROR(IF(INDEX(Data!$I$2:$I$745,MATCH(38,Data!$B$2:$B$745,0))="","",INDEX(Data!$I$2:$I$745,MATCH(38,Data!$B$2:$B$745,0))),"")) | F52: =IF(B52="","",IFERROR(IF(INDEX(Data!$AJ$2:$AJ$745,MATCH(38,Data!$B$2:$B$745,0))="","",INDEX(Data!$AJ$2:$AJ$745,MATCH(38,Data!$B$2:$B$745,0))),"")) | G52: =IF(B52="","",TRIM(IFERROR(IF(INDEX(Data!$AF$2:$AF$745,MATCH(38,Data!$B$2:$B$745,0))="","",INDEX(Data!$AF$2:$AF$745,MATCH(38,Data!$B$2:$B$745,0))),"")&" "&IFERROR(IF(INDEX(Data!$AG$2:$AG$745,MATCH(38,Data!$B$2:$B$745,0))="","",INDEX(Data!$AG$2:$AG$745,MATCH(38,Data!$B$2:$B$745,0))),""))) | H52: =IF(B52="","",IFERROR(IF(INDEX(Data!$N$2:$N$745,MATCH(38,Data!$B$2:$B$745,0))="","",INDEX(Data!$N$2:$N$745,MATCH(38,Data!$B$2:$B$745,0))),"")) | I52: =IF(B52="","",IFERROR(IF(INDEX(Data!$O$2:$O$745,MATCH(38,Data!$B$2:$B$745,0))="","",INDEX(Data!$O$2:$O$745,MATCH(38,Data!$B$2:$B$745,0))),"")) | J52: =IF(B52="","",IFERROR(IF(INDEX(Data!$P$2:$P$745,MATCH(38,Data!$B$2:$B$745,0))="","",INDEX(Data!$P$2:$P$745,MATCH(38,Data!$B$2:$B$745,0))),"")) | K52: =IF(B52="","",IFERROR(IF(INDEX(Data!$R$2:$R$745,MATCH(38,Data!$B$2:$B$745,0))="","",INDEX(Data!$R$2:$R$745,MATCH(38,Data!$B$2:$B$745,0))),"")) | L52: =IF(B52="","",IFERROR(IF(INDEX(Data!$S$2:$S$745,MATCH(38,Data!$B$2:$B$745,0))="","",INDEX(Data!$S$2:$S$745,MATCH(38,Data!$B$2:$B$745,0))),"")) | M52: =IF(B52="","",IFERROR(IF(INDEX(Data!$T$2:$T$745,MATCH(38,Data!$B$2:$B$745,0))="","",INDEX(Data!$T$2:$T$745,MATCH(38,Data!$B$2:$B$745,0))),"")) | N52: =IF(B52="","",IFERROR(IF(INDEX(Data!$U$2:$U$745,MATCH(38,Data!$B$2:$B$745,0))="","",INDEX(Data!$U$2:$U$745,MATCH(38,Data!$B$2:$B$745,0))),"")) | O52: =IF(B52="","",IFERROR(IF(INDEX(Data!$V$2:$V$745,MATCH(38,Data!$B$2:$B$745,0))="","",INDEX(Data!$V$2:$V$745,MATCH(38,Data!$B$2:$B$745,0))),"")) | P52: =IF(B52="","",IFERROR(IF(INDEX(Data!$M$2:$M$745,MATCH(38,Data!$B$2:$B$745,0))="","",INDEX(Data!$M$2:$M$745,MATCH(38,Data!$B$2:$B$745,0))),"")) | Q52: =IF(B52="","",IFERROR(IF(INDEX(Data!$AD$2:$AD$745,MATCH(38,Data!$B$2:$B$745,0))="","",INDEX(Data!$AD$2:$AD$745,MATCH(38,Data!$B$2:$B$745,0))),"")) | R52: =IF(B52="","",IFERROR(IF(INDEX(Data!$L$2:$L$745,MATCH(38,Data!$B$2:$B$745,0))="","",INDEX(Data!$L$2:$L$745,MATCH(38,Data!$B$2:$B$745,0))),"")) | AB52: Cozy Bliss
B53: =IF(39<=COUNTIF(Data!$A$2:$A$745,TRUE),39,"") | C53: =IF(B53="","",IFERROR(_xlfn.IMAGE(IFERROR(IF(INDEX(Data!$J$2:$J$745,MATCH(39,Data!$B$2:$B$745,0))="","",INDEX(Data!$J$2:$J$745,MATCH(39,Data!$B$2:$B$745,0))),"")),"IMAGE COMING SOON")) | D53: =IF(B53="","",IFERROR(IF(INDEX(Data!$G$2:$G$745,MATCH(39,Data!$B$2:$B$745,0))="","",INDEX(Data!$G$2:$G$745,MATCH(39,Data!$B$2:$B$745,0))),"")&CHAR(10)&IFERROR(IF(INDEX(Data!$H$2:$H$745,MATCH(39,Data!$B$2:$B$745,0))="","",INDEX(Data!$H$2:$H$745,MATCH(39,Data!$B$2:$B$745,0))),"")) | E53: =IF(B53="","",IFERROR(IF(INDEX(Data!$I$2:$I$745,MATCH(39,Data!$B$2:$B$745,0))="","",INDEX(Data!$I$2:$I$745,MATCH(39,Data!$B$2:$B$745,0))),"")) | F53: =IF(B53="","",IFERROR(IF(INDEX(Data!$AJ$2:$AJ$745,MATCH(39,Data!$B$2:$B$745,0))="","",INDEX(Data!$AJ$2:$AJ$745,MATCH(39,Data!$B$2:$B$745,0))),"")) | G53: =IF(B53="","",TRIM(IFERROR(IF(INDEX(Data!$AF$2:$AF$745,MATCH(39,Data!$B$2:$B$745,0))="","",INDEX(Data!$AF$2:$AF$745,MATCH(39,Data!$B$2:$B$745,0))),"")&" "&IFERROR(IF(INDEX(Data!$AG$2:$AG$745,MATCH(39,Data!$B$2:$B$745,0))="","",INDEX(Data!$AG$2:$AG$745,MATCH(39,Data!$B$2:$B$745,0))),""))) | H53: =IF(B53="","",IFERROR(IF(INDEX(Data!$N$2:$N$745,MATCH(39,Data!$B$2:$B$745,0))="","",INDEX(Data!$N$2:$N$745,MATCH(39,Data!$B$2:$B$745,0))),"")) | I53: =IF(B53="","",IFERROR(IF(INDEX(Data!$O$2:$O$745,MATCH(39,Data!$B$2:$B$745,0))="","",INDEX(Data!$O$2:$O$745,MATCH(39,Data!$B$2:$B$745,0))),"")) | J53: =IF(B53="","",IFERROR(IF(INDEX(Data!$P$2:$P$745,MATCH(39,Data!$B$2:$B$745,0))="","",INDEX(Data!$P$2:$P$745,MATCH(39,Data!$B$2:$B$745,0))),"")) | K53: =IF(B53="","",IFERROR(IF(INDEX(Data!$R$2:$R$745,MATCH(39,Data!$B$2:$B$745,0))="","",INDEX(Data!$R$2:$R$745,MATCH(39,Data!$B$2:$B$745,0))),"")) | L53: =IF(B53="","",IFERROR(IF(INDEX(Data!$S$2:$S$745,MATCH(39,Data!$B$2:$B$745,0))="","",INDEX(Data!$S$2:$S$745,MATCH(39,Data!$B$2:$B$745,0))),"")) | M53: =IF(B53="","",IFERROR(IF(INDEX(Data!$T$2:$T$745,MATCH(39,Data!$B$2:$B$745,0))="","",INDEX(Data!$T$2:$T$745,MATCH(39,Data!$B$2:$B$745,0))),"")) | N53: =IF(B53="","",IFERROR(IF(INDEX(Data!$U$2:$U$745,MATCH(39,Data!$B$2:$B$745,0))="","",INDEX(Data!$U$2:$U$745,MATCH(39,Data!$B$2:$B$745,0))),"")) | O53: =IF(B53="","",IFERROR(IF(INDEX(Data!$V$2:$V$745,MATCH(39,Data!$B$2:$B$745,0))="","",INDEX(Data!$V$2:$V$745,MATCH(39,Data!$B$2:$B$745,0))),"")) | P53: =IF(B53="","",IFERROR(IF(INDEX(Data!$M$2:$M$745,MATCH(39,Data!$B$2:$B$745,0))="","",INDEX(Data!$M$2:$M$745,MATCH(39,Data!$B$2:$B$745,0))),"")) | Q53: =IF(B53="","",IFERROR(IF(INDEX(Data!$AD$2:$AD$745,MATCH(39,Data!$B$2:$B$745,0))="","",INDEX(Data!$AD$2:$AD$745,MATCH(39,Data!$B$2:$B$745,0))),"")) | R53: =IF(B53="","",IFERROR(IF(INDEX(Data!$L$2:$L$745,MATCH(39,Data!$B$2:$B$745,0))="","",INDEX(Data!$L$2:$L$745,MATCH(39,Data!$B$2:$B$745,0))),"")) | AB53: Cozy Earth
B54: =IF(40<=COUNTIF(Data!$A$2:$A$745,TRUE),40,"") | C54: =IF(B54="","",IFERROR(_xlfn.IMAGE(IFERROR(IF(INDEX(Data!$J$2:$J$745,MATCH(40,Data!$B$2:$B$745,0))="","",INDEX(Data!$J$2:$J$745,MATCH(40,Data!$B$2:$B$745,0))),"")),"IMAGE COMING SOON")) | D54: =IF(B54="","",IFERROR(IF(INDEX(Data!$G$2:$G$745,MATCH(40,Data!$B$2:$B$745,0))="","",INDEX(Data!$G$2:$G$745,MATCH(40,Data!$B$2:$B$745,0))),"")&CHAR(10)&IFERROR(IF(INDEX(Data!$H$2:$H$745,MATCH(40,Data!$B$2:$B$745,0))="","",INDEX(Data!$H$2:$H$745,MATCH(40,Data!$B$2:$B$745,0))),"")) | E54: =IF(B54="","",IFERROR(IF(INDEX(Data!$I$2:$I$745,MATCH(40,Data!$B$2:$B$745,0))="","",INDEX(Data!$I$2:$I$745,MATCH(40,Data!$B$2:$B$745,0))),"")) | F54: =IF(B54="","",IFERROR(IF(INDEX(Data!$AJ$2:$AJ$745,MATCH(40,Data!$B$2:$B$745,0))="","",INDEX(Data!$AJ$2:$AJ$745,MATCH(40,Data!$B$2:$B$745,0))),"")) | G54: =IF(B54="","",TRIM(IFERROR(IF(INDEX(Data!$AF$2:$AF$745,MATCH(40,Data!$B$2:$B$745,0))="","",INDEX(Data!$AF$2:$AF$745,MATCH(40,Data!$B$2:$B$745,0))),"")&" "&IFERROR(IF(INDEX(Data!$AG$2:$AG$745,MATCH(40,Data!$B$2:$B$745,0))="","",INDEX(Data!$AG$2:$AG$745,MATCH(40,Data!$B$2:$B$745,0))),""))) | H54: =IF(B54="","",IFERROR(IF(INDEX(Data!$N$2:$N$745,MATCH(40,Data!$B$2:$B$745,0))="","",INDEX(Data!$N$2:$N$745,MATCH(40,Data!$B$2:$B$745,0))),"")) | I54: =IF(B54="","",IFERROR(IF(INDEX(Data!$O$2:$O$745,MATCH(40,Data!$B$2:$B$745,0))="","",INDEX(Data!$O$2:$O$745,MATCH(40,Data!$B$2:$B$745,0))),"")) | J54: =IF(B54="","",IFERROR(IF(INDEX(Data!$P$2:$P$745,MATCH(40,Data!$B$2:$B$745,0))="","",INDEX(Data!$P$2:$P$745,MATCH(40,Data!$B$2:$B$745,0))),"")) | K54: =IF(B54="","",IFERROR(IF(INDEX(Data!$R$2:$R$745,MATCH(40,Data!$B$2:$B$745,0))="","",INDEX(Data!$R$2:$R$745,MATCH(40,Data!$B$2:$B$745,0))),"")) | L54: =IF(B54="","",IFERROR(IF(INDEX(Data!$S$2:$S$745,MATCH(40,Data!$B$2:$B$745,0))="","",INDEX(Data!$S$2:$S$745,MATCH(40,Data!$B$2:$B$745,0))),"")) | M54: =IF(B54="","",IFERROR(IF(INDEX(Data!$T$2:$T$745,MATCH(40,Data!$B$2:$B$745,0))="","",INDEX(Data!$T$2:$T$745,MATCH(40,Data!$B$2:$B$745,0))),"")) | N54: =IF(B54="","",IFERROR(IF(INDEX(Data!$U$2:$U$745,MATCH(40,Data!$B$2:$B$745,0))="","",INDEX(Data!$U$2:$U$745,MATCH(40,Data!$B$2:$B$745,0))),"")) | O54: =IF(B54="","",IFERROR(IF(INDEX(Data!$V$2:$V$745,MATCH(40,Data!$B$2:$B$745,0))="","",INDEX(Data!$V$2:$V$745,MATCH(40,Data!$B$2:$B$745,0))),"")) | P54: =IF(B54="","",IFERROR(IF(INDEX(Data!$M$2:$M$745,MATCH(40,Data!$B$2:$B$745,0))="","",INDEX(Data!$M$2:$M$745,MATCH(40,Data!$B$2:$B$745,0))),"")) | Q54: =IF(B54="","",IFERROR(IF(INDEX(Data!$AD$2:$AD$745,MATCH(40,Data!$B$2:$B$745,0))="","",INDEX(Data!$AD$2:$AD$745,MATCH(40,Data!$B$2:$B$745,0))),"")) | R54: =IF(B54="","",IFERROR(IF(INDEX(Data!$L$2:$L$745,MATCH(40,Data!$B$2:$B$745,0))="","",INDEX(Data!$L$2:$L$745,MATCH(40,Data!$B$2:$B$745,0))),"")) | AB54: CozyLux
B55: =IF(41<=COUNTIF(Data!$A$2:$A$745,TRUE),41,"") | C55: =IF(B55="","",IFERROR(_xlfn.IMAGE(IFERROR(IF(INDEX(Data!$J$2:$J$745,MATCH(41,Data!$B$2:$B$745,0))="","",INDEX(Data!$J$2:$J$745,MATCH(41,Data!$B$2:$B$745,0))),"")),"IMAGE COMING SOON")) | D55: =IF(B55="","",IFERROR(IF(INDEX(Data!$G$2:$G$745,MATCH(41,Data!$B$2:$B$745,0))="","",INDEX(Data!$G$2:$G$745,MATCH(41,Data!$B$2:$B$745,0))),"")&CHAR(10)&IFERROR(IF(INDEX(Data!$H$2:$H$745,MATCH(41,Data!$B$2:$B$745,0))="","",INDEX(Data!$H$2:$H$745,MATCH(41,Data!$B$2:$B$745,0))),"")) | E55: =IF(B55="","",IFERROR(IF(INDEX(Data!$I$2:$I$745,MATCH(41,Data!$B$2:$B$745,0))="","",INDEX(Data!$I$2:$I$745,MATCH(41,Data!$B$2:$B$745,0))),"")) | F55: =IF(B55="","",IFERROR(IF(INDEX(Data!$AJ$2:$AJ$745,MATCH(41,Data!$B$2:$B$745,0))="","",INDEX(Data!$AJ$2:$AJ$745,MATCH(41,Data!$B$2:$B$745,0))),"")) | G55: =IF(B55="","",TRIM(IFERROR(IF(INDEX(Data!$AF$2:$AF$745,MATCH(41,Data!$B$2:$B$745,0))="","",INDEX(Data!$AF$2:$AF$745,MATCH(41,Data!$B$2:$B$745,0))),"")&" "&IFERROR(IF(INDEX(Data!$AG$2:$AG$745,MATCH(41,Data!$B$2:$B$745,0))="","",INDEX(Data!$AG$2:$AG$745,MATCH(41,Data!$B$2:$B$745,0))),""))) | H55: =IF(B55="","",IFERROR(IF(INDEX(Data!$N$2:$N$745,MATCH(41,Data!$B$2:$B$745,0))="","",INDEX(Data!$N$2:$N$745,MATCH(41,Data!$B$2:$B$745,0))),"")) | I55: =IF(B55="","",IFERROR(IF(INDEX(Data!$O$2:$O$745,MATCH(41,Data!$B$2:$B$745,0))="","",INDEX(Data!$O$2:$O$745,MATCH(41,Data!$B$2:$B$745,0))),"")) | J55: =IF(B55="","",IFERROR(IF(INDEX(Data!$P$2:$P$745,MATCH(41,Data!$B$2:$B$745,0))="","",INDEX(Data!$P$2:$P$745,MATCH(41,Data!$B$2:$B$745,0))),"")) | K55: =IF(B55="","",IFERROR(IF(INDEX(Data!$R$2:$R$745,MATCH(41,Data!$B$2:$B$745,0))="","",INDEX(Data!$R$2:$R$745,MATCH(41,Data!$B$2:$B$745,0))),"")) | L55: =IF(B55="","",IFERROR(IF(INDEX(Data!$S$2:$S$745,MATCH(41,Data!$B$2:$B$745,0))="","",INDEX(Data!$S$2:$S$745,MATCH(41,Data!$B$2:$B$745,0))),"")) | M55: =IF(B55="","",IFERROR(IF(INDEX(Data!$T$2:$T$745,MATCH(41,Data!$B$2:$B$745,0))="","",INDEX(Data!$T$2:$T$745,MATCH(41,Data!$B$2:$B$745,0))),"")) | N55: =IF(B55="","",IFERROR(IF(INDEX(Data!$U$2:$U$745,MATCH(41,Data!$B$2:$B$745,0))="","",INDEX(Data!$U$2:$U$745,MATCH(41,Data!$B$2:$B$745,0))),"")) | O55: =IF(B55="","",IFERROR(IF(INDEX(Data!$V$2:$V$745,MATCH(41,Data!$B$2:$B$745,0))="","",INDEX(Data!$V$2:$V$745,MATCH(41,Data!$B$2:$B$745,0))),"")) | P55: =IF(B55="","",IFERROR(IF(INDEX(Data!$M$2:$M$745,MATCH(41,Data!$B$2:$B$745,0))="","",INDEX(Data!$M$2:$M$745,MATCH(41,Data!$B$2:$B$745,0))),"")) | Q55: =IF(B55="","",IFERROR(IF(INDEX(Data!$AD$2:$AD$745,MATCH(41,Data!$B$2:$B$745,0))="","",INDEX(Data!$AD$2:$AD$745,MATCH(41,Data!$B$2:$B$745,0))),"")) | R55: =IF(B55="","",IFERROR(IF(INDEX(Data!$L$2:$L$745,MATCH(41,Data!$B$2:$B$745,0))="","",INDEX(Data!$L$2:$L$745,MATCH(41,Data!$B$2:$B$745,0))),"")) | AB55: CUCRAF
B56: =IF(42<=COUNTIF(Data!$A$2:$A$745,TRUE),42,"") | C56: =IF(B56="","",IFERROR(_xlfn.IMAGE(IFERROR(IF(INDEX(Data!$J$2:$J$745,MATCH(42,Data!$B$2:$B$745,0))="","",INDEX(Data!$J$2:$J$745,MATCH(42,Data!$B$2:$B$745,0))),"")),"IMAGE COMING SOON")) | D56: =IF(B56="","",IFERROR(IF(INDEX(Data!$G$2:$G$745,MATCH(42,Data!$B$2:$B$745,0))="","",INDEX(Data!$G$2:$G$745,MATCH(42,Data!$B$2:$B$745,0))),"")&CHAR(10)&IFERROR(IF(INDEX(Data!$H$2:$H$745,MATCH(42,Data!$B$2:$B$745,0))="","",INDEX(Data!$H$2:$H$745,MATCH(42,Data!$B$2:$B$745,0))),"")) | E56: =IF(B56="","",IFERROR(IF(INDEX(Data!$I$2:$I$745,MATCH(42,Data!$B$2:$B$745,0))="","",INDEX(Data!$I$2:$I$745,MATCH(42,Data!$B$2:$B$745,0))),"")) | F56: =IF(B56="","",IFERROR(IF(INDEX(Data!$AJ$2:$AJ$745,MATCH(42,Data!$B$2:$B$745,0))="","",INDEX(Data!$AJ$2:$AJ$745,MATCH(42,Data!$B$2:$B$745,0))),"")) | G56: =IF(B56="","",TRIM(IFERROR(IF(INDEX(Data!$AF$2:$AF$745,MATCH(42,Data!$B$2:$B$745,0))="","",INDEX(Data!$AF$2:$AF$745,MATCH(42,Data!$B$2:$B$745,0))),"")&" "&IFERROR(IF(INDEX(Data!$AG$2:$AG$745,MATCH(42,Data!$B$2:$B$745,0))="","",INDEX(Data!$AG$2:$AG$745,MATCH(42,Data!$B$2:$B$745,0))),""))) | H56: =IF(B56="","",IFERROR(IF(INDEX(Data!$N$2:$N$745,MATCH(42,Data!$B$2:$B$745,0))="","",INDEX(Data!$N$2:$N$745,MATCH(42,Data!$B$2:$B$745,0))),"")) | I56: =IF(B56="","",IFERROR(IF(INDEX(Data!$O$2:$O$745,MATCH(42,Data!$B$2:$B$745,0))="","",INDEX(Data!$O$2:$O$745,MATCH(42,Data!$B$2:$B$745,0))),"")) | J56: =IF(B56="","",IFERROR(IF(INDEX(Data!$P$2:$P$745,MATCH(42,Data!$B$2:$B$745,0))="","",INDEX(Data!$P$2:$P$745,MATCH(42,Data!$B$2:$B$745,0))),"")) | K56: =IF(B56="","",IFERROR(IF(INDEX(Data!$R$2:$R$745,MATCH(42,Data!$B$2:$B$745,0))="","",INDEX(Data!$R$2:$R$745,MATCH(42,Data!$B$2:$B$745,0))),"")) | L56: =IF(B56="","",IFERROR(IF(INDEX(Data!$S$2:$S$745,MATCH(42,Data!$B$2:$B$745,0))="","",INDEX(Data!$S$2:$S$745,MATCH(42,Data!$B$2:$B$745,0))),"")) | M56: =IF(B56="","",IFERROR(IF(INDEX(Data!$T$2:$T$745,MATCH(42,Data!$B$2:$B$745,0))="","",INDEX(Data!$T$2:$T$745,MATCH(42,Data!$B$2:$B$745,0))),"")) | N56: =IF(B56="","",IFERROR(IF(INDEX(Data!$U$2:$U$745,MATCH(42,Data!$B$2:$B$745,0))="","",INDEX(Data!$U$2:$U$745,MATCH(42,Data!$B$2:$B$745,0))),"")) | O56: =IF(B56="","",IFERROR(IF(INDEX(Data!$V$2:$V$745,MATCH(42,Data!$B$2:$B$745,0))="","",INDEX(Data!$V$2:$V$745,MATCH(42,Data!$B$2:$B$745,0))),"")) | P56: =IF(B56="","",IFERROR(IF(INDEX(Data!$M$2:$M$745,MATCH(42,Data!$B$2:$B$745,0))="","",INDEX(Data!$M$2:$M$745,MATCH(42,Data!$B$2:$B$745,0))),"")) | Q56: =IF(B56="","",IFERROR(IF(INDEX(Data!$AD$2:$AD$745,MATCH(42,Data!$B$2:$B$745,0))="","",INDEX(Data!$AD$2:$AD$745,MATCH(42,Data!$B$2:$B$745,0))),"")) | R56: =IF(B56="","",IFERROR(IF(INDEX(Data!$L$2:$L$745,MATCH(42,Data!$B$2:$B$745,0))="","",INDEX(Data!$L$2:$L$745,MATCH(42,Data!$B$2:$B$745,0))),"")) | AB56: David's Home
B57: =IF(43<=COUNTIF(Data!$A$2:$A$745,TRUE),43,"") | C57: =IF(B57="","",IFERROR(_xlfn.IMAGE(IFERROR(IF(INDEX(Data!$J$2:$J$745,MATCH(43,Data!$B$2:$B$745,0))="","",INDEX(Data!$J$2:$J$745,MATCH(43,Data!$B$2:$B$745,0))),"")),"IMAGE COMING SOON")) | D57: =IF(B57="","",IFERROR(IF(INDEX(Data!$G$2:$G$745,MATCH(43,Data!$B$2:$B$745,0))="","",INDEX(Data!$G$2:$G$745,MATCH(43,Data!$B$2:$B$745,0))),"")&CHAR(10)&IFERROR(IF(INDEX(Data!$H$2:$H$745,MATCH(43,Data!$B$2:$B$745,0))="","",INDEX(Data!$H$2:$H$745,MATCH(43,Data!$B$2:$B$745,0))),"")) | E57: =IF(B57="","",IFERROR(IF(INDEX(Data!$I$2:$I$745,MATCH(43,Data!$B$2:$B$745,0))="","",INDEX(Data!$I$2:$I$745,MATCH(43,Data!$B$2:$B$745,0))),"")) | F57: =IF(B57="","",IFERROR(IF(INDEX(Data!$AJ$2:$AJ$745,MATCH(43,Data!$B$2:$B$745,0))="","",INDEX(Data!$AJ$2:$AJ$745,MATCH(43,Data!$B$2:$B$745,0))),"")) | G57: =IF(B57="","",TRIM(IFERROR(IF(INDEX(Data!$AF$2:$AF$745,MATCH(43,Data!$B$2:$B$745,0))="","",INDEX(Data!$AF$2:$AF$745,MATCH(43,Data!$B$2:$B$745,0))),"")&" "&IFERROR(IF(INDEX(Data!$AG$2:$AG$745,MATCH(43,Data!$B$2:$B$745,0))="","",INDEX(Data!$AG$2:$AG$745,MATCH(43,Data!$B$2:$B$745,0))),""))) | H57: =IF(B57="","",IFERROR(IF(INDEX(Data!$N$2:$N$745,MATCH(43,Data!$B$2:$B$745,0))="","",INDEX(Data!$N$2:$N$745,MATCH(43,Data!$B$2:$B$745,0))),"")) | I57: =IF(B57="","",IFERROR(IF(INDEX(Data!$O$2:$O$745,MATCH(43,Data!$B$2:$B$745,0))="","",INDEX(Data!$O$2:$O$745,MATCH(43,Data!$B$2:$B$745,0))),"")) | J57: =IF(B57="","",IFERROR(IF(INDEX(Data!$P$2:$P$745,MATCH(43,Data!$B$2:$B$745,0))="","",INDEX(Data!$P$2:$P$745,MATCH(43,Data!$B$2:$B$745,0))),"")) | K57: =IF(B57="","",IFERROR(IF(INDEX(Data!$R$2:$R$745,MATCH(43,Data!$B$2:$B$745,0))="","",INDEX(Data!$R$2:$R$745,MATCH(43,Data!$B$2:$B$745,0))),"")) | L57: =IF(B57="","",IFERROR(IF(INDEX(Data!$S$2:$S$745,MATCH(43,Data!$B$2:$B$745,0))="","",INDEX(Data!$S$2:$S$745,MATCH(43,Data!$B$2:$B$745,0))),"")) | M57: =IF(B57="","",IFERROR(IF(INDEX(Data!$T$2:$T$745,MATCH(43,Data!$B$2:$B$745,0))="","",INDEX(Data!$T$2:$T$745,MATCH(43,Data!$B$2:$B$745,0))),"")) | N57: =IF(B57="","",IFERROR(IF(INDEX(Data!$U$2:$U$745,MATCH(43,Data!$B$2:$B$745,0))="","",INDEX(Data!$U$2:$U$745,MATCH(43,Data!$B$2:$B$745,0))),"")) | O57: =IF(B57="","",IFERROR(IF(INDEX(Data!$V$2:$V$745,MATCH(43,Data!$B$2:$B$745,0))="","",INDEX(Data!$V$2:$V$745,MATCH(43,Data!$B$2:$B$745,0))),"")) | P57: =IF(B57="","",IFERROR(IF(INDEX(Data!$M$2:$M$745,MATCH(43,Data!$B$2:$B$745,0))="","",INDEX(Data!$M$2:$M$745,MATCH(43,Data!$B$2:$B$745,0))),"")) | Q57: =IF(B57="","",IFERROR(IF(INDEX(Data!$AD$2:$AD$745,MATCH(43,Data!$B$2:$B$745,0))="","",INDEX(Data!$AD$2:$AD$745,MATCH(43,Data!$B$2:$B$745,0))),"")) | R57: =IF(B57="","",IFERROR(IF(INDEX(Data!$L$2:$L$745,MATCH(43,Data!$B$2:$B$745,0))="","",INDEX(Data!$L$2:$L$745,MATCH(43,Data!$B$2:$B$745,0))),"")) | AB57: Davmabcjy
B58: =IF(44<=COUNTIF(Data!$A$2:$A$745,TRUE),44,"") | C58: =IF(B58="","",IFERROR(_xlfn.IMAGE(IFERROR(IF(INDEX(Data!$J$2:$J$745,MATCH(44,Data!$B$2:$B$745,0))="","",INDEX(Data!$J$2:$J$745,MATCH(44,Data!$B$2:$B$745,0))),"")),"IMAGE COMING SOON")) | D58: =IF(B58="","",IFERROR(IF(INDEX(Data!$G$2:$G$745,MATCH(44,Data!$B$2:$B$745,0))="","",INDEX(Data!$G$2:$G$745,MATCH(44,Data!$B$2:$B$745,0))),"")&CHAR(10)&IFERROR(IF(INDEX(Data!$H$2:$H$745,MATCH(44,Data!$B$2:$B$745,0))="","",INDEX(Data!$H$2:$H$745,MATCH(44,Data!$B$2:$B$745,0))),"")) | E58: =IF(B58="","",IFERROR(IF(INDEX(Data!$I$2:$I$745,MATCH(44,Data!$B$2:$B$745,0))="","",INDEX(Data!$I$2:$I$745,MATCH(44,Data!$B$2:$B$745,0))),"")) | F58: =IF(B58="","",IFERROR(IF(INDEX(Data!$AJ$2:$AJ$745,MATCH(44,Data!$B$2:$B$745,0))="","",INDEX(Data!$AJ$2:$AJ$745,MATCH(44,Data!$B$2:$B$745,0))),"")) | G58: =IF(B58="","",TRIM(IFERROR(IF(INDEX(Data!$AF$2:$AF$745,MATCH(44,Data!$B$2:$B$745,0))="","",INDEX(Data!$AF$2:$AF$745,MATCH(44,Data!$B$2:$B$745,0))),"")&" "&IFERROR(IF(INDEX(Data!$AG$2:$AG$745,MATCH(44,Data!$B$2:$B$745,0))="","",INDEX(Data!$AG$2:$AG$745,MATCH(44,Data!$B$2:$B$745,0))),""))) | H58: =IF(B58="","",IFERROR(IF(INDEX(Data!$N$2:$N$745,MATCH(44,Data!$B$2:$B$745,0))="","",INDEX(Data!$N$2:$N$745,MATCH(44,Data!$B$2:$B$745,0))),"")) | I58: =IF(B58="","",IFERROR(IF(INDEX(Data!$O$2:$O$745,MATCH(44,Data!$B$2:$B$745,0))="","",INDEX(Data!$O$2:$O$745,MATCH(44,Data!$B$2:$B$745,0))),"")) | J58: =IF(B58="","",IFERROR(IF(INDEX(Data!$P$2:$P$745,MATCH(44,Data!$B$2:$B$745,0))="","",INDEX(Data!$P$2:$P$745,MATCH(44,Data!$B$2:$B$745,0))),"")) | K58: =IF(B58="","",IFERROR(IF(INDEX(Data!$R$2:$R$745,MATCH(44,Data!$B$2:$B$745,0))="","",INDEX(Data!$R$2:$R$745,MATCH(44,Data!$B$2:$B$745,0))),"")) | L58: =IF(B58="","",IFERROR(IF(INDEX(Data!$S$2:$S$745,MATCH(44,Data!$B$2:$B$745,0))="","",INDEX(Data!$S$2:$S$745,MATCH(44,Data!$B$2:$B$745,0))),"")) | M58: =IF(B58="","",IFERROR(IF(INDEX(Data!$T$2:$T$745,MATCH(44,Data!$B$2:$B$745,0))="","",INDEX(Data!$T$2:$T$745,MATCH(44,Data!$B$2:$B$745,0))),"")) | N58: =IF(B58="","",IFERROR(IF(INDEX(Data!$U$2:$U$745,MATCH(44,Data!$B$2:$B$745,0))="","",INDEX(Data!$U$2:$U$745,MATCH(44,Data!$B$2:$B$745,0))),"")) | O58: =IF(B58="","",IFERROR(IF(INDEX(Data!$V$2:$V$745,MATCH(44,Data!$B$2:$B$745,0))="","",INDEX(Data!$V$2:$V$745,MATCH(44,Data!$B$2:$B$745,0))),"")) | P58: =IF(B58="","",IFERROR(IF(INDEX(Data!$M$2:$M$745,MATCH(44,Data!$B$2:$B$745,0))="","",INDEX(Data!$M$2:$M$745,MATCH(44,Data!$B$2:$B$745,0))),"")) | Q58: =IF(B58="","",IFERROR(IF(INDEX(Data!$AD$2:$AD$745,MATCH(44,Data!$B$2:$B$745,0))="","",INDEX(Data!$AD$2:$AD$745,MATCH(44,Data!$B$2:$B$745,0))),"")) | R58: =IF(B58="","",IFERROR(IF(INDEX(Data!$L$2:$L$745,MATCH(44,Data!$B$2:$B$745,0))="","",INDEX(Data!$L$2:$L$745,MATCH(44,Data!$B$2:$B$745,0))),"")) | AB58: Degrees of Comfort
B59: =IF(45<=COUNTIF(Data!$A$2:$A$745,TRUE),45,"") | C59: =IF(B59="","",IFERROR(_xlfn.IMAGE(IFERROR(IF(INDEX(Data!$J$2:$J$745,MATCH(45,Data!$B$2:$B$745,0))="","",INDEX(Data!$J$2:$J$745,MATCH(45,Data!$B$2:$B$745,0))),"")),"IMAGE COMING SOON")) | D59: =IF(B59="","",IFERROR(IF(INDEX(Data!$G$2:$G$745,MATCH(45,Data!$B$2:$B$745,0))="","",INDEX(Data!$G$2:$G$745,MATCH(45,Data!$B$2:$B$745,0))),"")&CHAR(10)&IFERROR(IF(INDEX(Data!$H$2:$H$745,MATCH(45,Data!$B$2:$B$745,0))="","",INDEX(Data!$H$2:$H$745,MATCH(45,Data!$B$2:$B$745,0))),"")) | E59: =IF(B59="","",IFERROR(IF(INDEX(Data!$I$2:$I$745,MATCH(45,Data!$B$2:$B$745,0))="","",INDEX(Data!$I$2:$I$745,MATCH(45,Data!$B$2:$B$745,0))),"")) | F59: =IF(B59="","",IFERROR(IF(INDEX(Data!$AJ$2:$AJ$745,MATCH(45,Data!$B$2:$B$745,0))="","",INDEX(Data!$AJ$2:$AJ$745,MATCH(45,Data!$B$2:$B$745,0))),"")) | G59: =IF(B59="","",TRIM(IFERROR(IF(INDEX(Data!$AF$2:$AF$745,MATCH(45,Data!$B$2:$B$745,0))="","",INDEX(Data!$AF$2:$AF$745,MATCH(45,Data!$B$2:$B$745,0))),"")&" "&IFERROR(IF(INDEX(Data!$AG$2:$AG$745,MATCH(45,Data!$B$2:$B$745,0))="","",INDEX(Data!$AG$2:$AG$745,MATCH(45,Data!$B$2:$B$745,0))),""))) | H59: =IF(B59="","",IFERROR(IF(INDEX(Data!$N$2:$N$745,MATCH(45,Data!$B$2:$B$745,0))="","",INDEX(Data!$N$2:$N$745,MATCH(45,Data!$B$2:$B$745,0))),"")) | I59: =IF(B59="","",IFERROR(IF(INDEX(Data!$O$2:$O$745,MATCH(45,Data!$B$2:$B$745,0))="","",INDEX(Data!$O$2:$O$745,MATCH(45,Data!$B$2:$B$745,0))),"")) | J59: =IF(B59="","",IFERROR(IF(INDEX(Data!$P$2:$P$745,MATCH(45,Data!$B$2:$B$745,0))="","",INDEX(Data!$P$2:$P$745,MATCH(45,Data!$B$2:$B$745,0))),"")) | K59: =IF(B59="","",IFERROR(IF(INDEX(Data!$R$2:$R$745,MATCH(45,Data!$B$2:$B$745,0))="","",INDEX(Data!$R$2:$R$745,MATCH(45,Data!$B$2:$B$745,0))),"")) | L59: =IF(B59="","",IFERROR(IF(INDEX(Data!$S$2:$S$745,MATCH(45,Data!$B$2:$B$745,0))="","",INDEX(Data!$S$2:$S$745,MATCH(45,Data!$B$2:$B$745,0))),"")) | M59: =IF(B59="","",IFERROR(IF(INDEX(Data!$T$2:$T$745,MATCH(45,Data!$B$2:$B$745,0))="","",INDEX(Data!$T$2:$T$745,MATCH(45,Data!$B$2:$B$745,0))),"")) | N59: =IF(B59="","",IFERROR(IF(INDEX(Data!$U$2:$U$745,MATCH(45,Data!$B$2:$B$745,0))="","",INDEX(Data!$U$2:$U$745,MATCH(45,Data!$B$2:$B$745,0))),"")) | O59: =IF(B59="","",IFERROR(IF(INDEX(Data!$V$2:$V$745,MATCH(45,Data!$B$2:$B$745,0))="","",INDEX(Data!$V$2:$V$745,MATCH(45,Data!$B$2:$B$745,0))),"")) | P59: =IF(B59="","",IFERROR(IF(INDEX(Data!$M$2:$M$745,MATCH(45,Data!$B$2:$B$745,0))="","",INDEX(Data!$M$2:$M$745,MATCH(45,Data!$B$2:$B$745,0))),"")) | Q59: =IF(B59="","",IFERROR(IF(INDEX(Data!$AD$2:$AD$745,MATCH(45,Data!$B$2:$B$745,0))="","",INDEX(Data!$AD$2:$AD$745,MATCH(45,Data!$B$2:$B$745,0))),"")) | R59: =IF(B59="","",IFERROR(IF(INDEX(Data!$L$2:$L$745,MATCH(45,Data!$B$2:$B$745,0))="","",INDEX(Data!$L$2:$L$745,MATCH(45,Data!$B$2:$B$745,0))),"")) | AB59: DJY
B60: =IF(46<=COUNTIF(Data!$A$2:$A$745,TRUE),46,"") | C60: =IF(B60="","",IFERROR(_xlfn.IMAGE(IFERROR(IF(INDEX(Data!$J$2:$J$745,MATCH(46,Data!$B$2:$B$745,0))="","",INDEX(Data!$J$2:$J$745,MATCH(46,Data!$B$2:$B$745,0))),"")),"IMAGE COMING SOON")) | D60: =IF(B60="","",IFERROR(IF(INDEX(Data!$G$2:$G$745,MATCH(46,Data!$B$2:$B$745,0))="","",INDEX(Data!$G$2:$G$745,MATCH(46,Data!$B$2:$B$745,0))),"")&CHAR(10)&IFERROR(IF(INDEX(Data!$H$2:$H$745,MATCH(46,Data!$B$2:$B$745,0))="","",INDEX(Data!$H$2:$H$745,MATCH(46,Data!$B$2:$B$745,0))),"")) | E60: =IF(B60="","",IFERROR(IF(INDEX(Data!$I$2:$I$745,MATCH(46,Data!$B$2:$B$745,0))="","",INDEX(Data!$I$2:$I$745,MATCH(46,Data!$B$2:$B$745,0))),"")) | F60: =IF(B60="","",IFERROR(IF(INDEX(Data!$AJ$2:$AJ$745,MATCH(46,Data!$B$2:$B$745,0))="","",INDEX(Data!$AJ$2:$AJ$745,MATCH(46,Data!$B$2:$B$745,0))),"")) | G60: =IF(B60="","",TRIM(IFERROR(IF(INDEX(Data!$AF$2:$AF$745,MATCH(46,Data!$B$2:$B$745,0))="","",INDEX(Data!$AF$2:$AF$745,MATCH(46,Data!$B$2:$B$745,0))),"")&" "&IFERROR(IF(INDEX(Data!$AG$2:$AG$745,MATCH(46,Data!$B$2:$B$745,0))="","",INDEX(Data!$AG$2:$AG$745,MATCH(46,Data!$B$2:$B$745,0))),""))) | H60: =IF(B60="","",IFERROR(IF(INDEX(Data!$N$2:$N$745,MATCH(46,Data!$B$2:$B$745,0))="","",INDEX(Data!$N$2:$N$745,MATCH(46,Data!$B$2:$B$745,0))),"")) | I60: =IF(B60="","",IFERROR(IF(INDEX(Data!$O$2:$O$745,MATCH(46,Data!$B$2:$B$745,0))="","",INDEX(Data!$O$2:$O$745,MATCH(46,Data!$B$2:$B$745,0))),"")) | J60: =IF(B60="","",IFERROR(IF(INDEX(Data!$P$2:$P$745,MATCH(46,Data!$B$2:$B$745,0))="","",INDEX(Data!$P$2:$P$745,MATCH(46,Data!$B$2:$B$745,0))),"")) | K60: =IF(B60="","",IFERROR(IF(INDEX(Data!$R$2:$R$745,MATCH(46,Data!$B$2:$B$745,0))="","",INDEX(Data!$R$2:$R$745,MATCH(46,Data!$B$2:$B$745,0))),"")) | L60: =IF(B60="","",IFERROR(IF(INDEX(Data!$S$2:$S$745,MATCH(46,Data!$B$2:$B$745,0))="","",INDEX(Data!$S$2:$S$745,MATCH(46,Data!$B$2:$B$745,0))),"")) | M60: =IF(B60="","",IFERROR(IF(INDEX(Data!$T$2:$T$745,MATCH(46,Data!$B$2:$B$745,0))="","",INDEX(Data!$T$2:$T$745,MATCH(46,Data!$B$2:$B$745,0))),"")) | N60: =IF(B60="","",IFERROR(IF(INDEX(Data!$U$2:$U$745,MATCH(46,Data!$B$2:$B$745,0))="","",INDEX(Data!$U$2:$U$745,MATCH(46,Data!$B$2:$B$745,0))),"")) | O60: =IF(B60="","",IFERROR(IF(INDEX(Data!$V$2:$V$745,MATCH(46,Data!$B$2:$B$745,0))="","",INDEX(Data!$V$2:$V$745,MATCH(46,Data!$B$2:$B$745,0))),"")) | P60: =IF(B60="","",IFERROR(IF(INDEX(Data!$M$2:$M$745,MATCH(46,Data!$B$2:$B$745,0))="","",INDEX(Data!$M$2:$M$745,MATCH(46,Data!$B$2:$B$745,0))),"")) | Q60: =IF(B60="","",IFERROR(IF(INDEX(Data!$AD$2:$AD$745,MATCH(46,Data!$B$2:$B$745,0))="","",INDEX(Data!$AD$2:$AD$745,MATCH(46,Data!$B$2:$B$745,0))),"")) | R60: =IF(B60="","",IFERROR(IF(INDEX(Data!$L$2:$L$745,MATCH(46,Data!$B$2:$B$745,0))="","",INDEX(Data!$L$2:$L$745,MATCH(46,Data!$B$2:$B$745,0))),"")) | AB60: DKBslik
B61: =IF(47<=COUNTIF(Data!$A$2:$A$745,TRUE),47,"") | C61: =IF(B61="","",IFERROR(_xlfn.IMAGE(IFERROR(IF(INDEX(Data!$J$2:$J$745,MATCH(47,Data!$B$2:$B$745,0))="","",INDEX(Data!$J$2:$J$745,MATCH(47,Data!$B$2:$B$745,0))),"")),"IMAGE COMING SOON")) | D61: =IF(B61="","",IFERROR(IF(INDEX(Data!$G$2:$G$745,MATCH(47,Data!$B$2:$B$745,0))="","",INDEX(Data!$G$2:$G$745,MATCH(47,Data!$B$2:$B$745,0))),"")&CHAR(10)&IFERROR(IF(INDEX(Data!$H$2:$H$745,MATCH(47,Data!$B$2:$B$745,0))="","",INDEX(Data!$H$2:$H$745,MATCH(47,Data!$B$2:$B$745,0))),"")) | E61: =IF(B61="","",IFERROR(IF(INDEX(Data!$I$2:$I$745,MATCH(47,Data!$B$2:$B$745,0))="","",INDEX(Data!$I$2:$I$745,MATCH(47,Data!$B$2:$B$745,0))),"")) | F61: =IF(B61="","",IFERROR(IF(INDEX(Data!$AJ$2:$AJ$745,MATCH(47,Data!$B$2:$B$745,0))="","",INDEX(Data!$AJ$2:$AJ$745,MATCH(47,Data!$B$2:$B$745,0))),"")) | G61: =IF(B61="","",TRIM(IFERROR(IF(INDEX(Data!$AF$2:$AF$745,MATCH(47,Data!$B$2:$B$745,0))="","",INDEX(Data!$AF$2:$AF$745,MATCH(47,Data!$B$2:$B$745,0))),"")&" "&IFERROR(IF(INDEX(Data!$AG$2:$AG$745,MATCH(47,Data!$B$2:$B$745,0))="","",INDEX(Data!$AG$2:$AG$745,MATCH(47,Data!$B$2:$B$745,0))),""))) | H61: =IF(B61="","",IFERROR(IF(INDEX(Data!$N$2:$N$745,MATCH(47,Data!$B$2:$B$745,0))="","",INDEX(Data!$N$2:$N$745,MATCH(47,Data!$B$2:$B$745,0))),"")) | I61: =IF(B61="","",IFERROR(IF(INDEX(Data!$O$2:$O$745,MATCH(47,Data!$B$2:$B$745,0))="","",INDEX(Data!$O$2:$O$745,MATCH(47,Data!$B$2:$B$745,0))),"")) | J61: =IF(B61="","",IFERROR(IF(INDEX(Data!$P$2:$P$745,MATCH(47,Data!$B$2:$B$745,0))="","",INDEX(Data!$P$2:$P$745,MATCH(47,Data!$B$2:$B$745,0))),"")) | K61: =IF(B61="","",IFERROR(IF(INDEX(Data!$R$2:$R$745,MATCH(47,Data!$B$2:$B$745,0))="","",INDEX(Data!$R$2:$R$745,MATCH(47,Data!$B$2:$B$745,0))),"")) | L61: =IF(B61="","",IFERROR(IF(INDEX(Data!$S$2:$S$745,MATCH(47,Data!$B$2:$B$745,0))="","",INDEX(Data!$S$2:$S$745,MATCH(47,Data!$B$2:$B$745,0))),"")) | M61: =IF(B61="","",IFERROR(IF(INDEX(Data!$T$2:$T$745,MATCH(47,Data!$B$2:$B$745,0))="","",INDEX(Data!$T$2:$T$745,MATCH(47,Data!$B$2:$B$745,0))),"")) | N61: =IF(B61="","",IFERROR(IF(INDEX(Data!$U$2:$U$745,MATCH(47,Data!$B$2:$B$745,0))="","",INDEX(Data!$U$2:$U$745,MATCH(47,Data!$B$2:$B$745,0))),"")) | O61: =IF(B61="","",IFERROR(IF(INDEX(Data!$V$2:$V$745,MATCH(47,Data!$B$2:$B$745,0))="","",INDEX(Data!$V$2:$V$745,MATCH(47,Data!$B$2:$B$745,0))),"")) | P61: =IF(B61="","",IFERROR(IF(INDEX(Data!$M$2:$M$745,MATCH(47,Data!$B$2:$B$745,0))="","",INDEX(Data!$M$2:$M$745,MATCH(47,Data!$B$2:$B$745,0))),"")) | Q61: =IF(B61="","",IFERROR(IF(INDEX(Data!$AD$2:$AD$745,MATCH(47,Data!$B$2:$B$745,0))="","",INDEX(Data!$AD$2:$AD$745,MATCH(47,Data!$B$2:$B$745,0))),"")) | R61: =IF(B61="","",IFERROR(IF(INDEX(Data!$L$2:$L$745,MATCH(47,Data!$B$2:$B$745,0))="","",INDEX(Data!$L$2:$L$745,MATCH(47,Data!$B$2:$B$745,0))),"")) | AB61: Dlerom
B62: =IF(48<=COUNTIF(Data!$A$2:$A$745,TRUE),48,"") | C62: =IF(B62="","",IFERROR(_xlfn.IMAGE(IFERROR(IF(INDEX(Data!$J$2:$J$745,MATCH(48,Data!$B$2:$B$745,0))="","",INDEX(Data!$J$2:$J$745,MATCH(48,Data!$B$2:$B$745,0))),"")),"IMAGE COMING SOON")) | D62: =IF(B62="","",IFERROR(IF(INDEX(Data!$G$2:$G$745,MATCH(48,Data!$B$2:$B$745,0))="","",INDEX(Data!$G$2:$G$745,MATCH(48,Data!$B$2:$B$745,0))),"")&CHAR(10)&IFERROR(IF(INDEX(Data!$H$2:$H$745,MATCH(48,Data!$B$2:$B$745,0))="","",INDEX(Data!$H$2:$H$745,MATCH(48,Data!$B$2:$B$745,0))),"")) | E62: =IF(B62="","",IFERROR(IF(INDEX(Data!$I$2:$I$745,MATCH(48,Data!$B$2:$B$745,0))="","",INDEX(Data!$I$2:$I$745,MATCH(48,Data!$B$2:$B$745,0))),"")) | F62: =IF(B62="","",IFERROR(IF(INDEX(Data!$AJ$2:$AJ$745,MATCH(48,Data!$B$2:$B$745,0))="","",INDEX(Data!$AJ$2:$AJ$745,MATCH(48,Data!$B$2:$B$745,0))),"")) | G62: =IF(B62="","",TRIM(IFERROR(IF(INDEX(Data!$AF$2:$AF$745,MATCH(48,Data!$B$2:$B$745,0))="","",INDEX(Data!$AF$2:$AF$745,MATCH(48,Data!$B$2:$B$745,0))),"")&" "&IFERROR(IF(INDEX(Data!$AG$2:$AG$745,MATCH(48,Data!$B$2:$B$745,0))="","",INDEX(Data!$AG$2:$AG$745,MATCH(48,Data!$B$2:$B$745,0))),""))) | H62: =IF(B62="","",IFERROR(IF(INDEX(Data!$N$2:$N$745,MATCH(48,Data!$B$2:$B$745,0))="","",INDEX(Data!$N$2:$N$745,MATCH(48,Data!$B$2:$B$745,0))),"")) | I62: =IF(B62="","",IFERROR(IF(INDEX(Data!$O$2:$O$745,MATCH(48,Data!$B$2:$B$745,0))="","",INDEX(Data!$O$2:$O$745,MATCH(48,Data!$B$2:$B$745,0))),"")) | J62: =IF(B62="","",IFERROR(IF(INDEX(Data!$P$2:$P$745,MATCH(48,Data!$B$2:$B$745,0))="","",INDEX(Data!$P$2:$P$745,MATCH(48,Data!$B$2:$B$745,0))),"")) | K62: =IF(B62="","",IFERROR(IF(INDEX(Data!$R$2:$R$745,MATCH(48,Data!$B$2:$B$745,0))="","",INDEX(Data!$R$2:$R$745,MATCH(48,Data!$B$2:$B$745,0))),"")) | L62: =IF(B62="","",IFERROR(IF(INDEX(Data!$S$2:$S$745,MATCH(48,Data!$B$2:$B$745,0))="","",INDEX(Data!$S$2:$S$745,MATCH(48,Data!$B$2:$B$745,0))),"")) | M62: =IF(B62="","",IFERROR(IF(INDEX(Data!$T$2:$T$745,MATCH(48,Data!$B$2:$B$745,0))="","",INDEX(Data!$T$2:$T$745,MATCH(48,Data!$B$2:$B$745,0))),"")) | N62: =IF(B62="","",IFERROR(IF(INDEX(Data!$U$2:$U$745,MATCH(48,Data!$B$2:$B$745,0))="","",INDEX(Data!$U$2:$U$745,MATCH(48,Data!$B$2:$B$745,0))),"")) | O62: =IF(B62="","",IFERROR(IF(INDEX(Data!$V$2:$V$745,MATCH(48,Data!$B$2:$B$745,0))="","",INDEX(Data!$V$2:$V$745,MATCH(48,Data!$B$2:$B$745,0))),"")) | P62: =IF(B62="","",IFERROR(IF(INDEX(Data!$M$2:$M$745,MATCH(48,Data!$B$2:$B$745,0))="","",INDEX(Data!$M$2:$M$745,MATCH(48,Data!$B$2:$B$745,0))),"")) | Q62: =IF(B62="","",IFERROR(IF(INDEX(Data!$AD$2:$AD$745,MATCH(48,Data!$B$2:$B$745,0))="","",INDEX(Data!$AD$2:$AD$745,MATCH(48,Data!$B$2:$B$745,0))),"")) | R62: =IF(B62="","",IFERROR(IF(INDEX(Data!$L$2:$L$745,MATCH(48,Data!$B$2:$B$745,0))="","",INDEX(Data!$L$2:$L$745,MATCH(48,Data!$B$2:$B$745,0))),"")) | AB62: DOUSUI
B63: =IF(49<=COUNTIF(Data!$A$2:$A$745,TRUE),49,"") | C63: =IF(B63="","",IFERROR(_xlfn.IMAGE(IFERROR(IF(INDEX(Data!$J$2:$J$745,MATCH(49,Data!$B$2:$B$745,0))="","",INDEX(Data!$J$2:$J$745,MATCH(49,Data!$B$2:$B$745,0))),"")),"IMAGE COMING SOON")) | D63: =IF(B63="","",IFERROR(IF(INDEX(Data!$G$2:$G$745,MATCH(49,Data!$B$2:$B$745,0))="","",INDEX(Data!$G$2:$G$745,MATCH(49,Data!$B$2:$B$745,0))),"")&CHAR(10)&IFERROR(IF(INDEX(Data!$H$2:$H$745,MATCH(49,Data!$B$2:$B$745,0))="","",INDEX(Data!$H$2:$H$745,MATCH(49,Data!$B$2:$B$745,0))),"")) | E63: =IF(B63="","",IFERROR(IF(INDEX(Data!$I$2:$I$745,MATCH(49,Data!$B$2:$B$745,0))="","",INDEX(Data!$I$2:$I$745,MATCH(49,Data!$B$2:$B$745,0))),"")) | F63: =IF(B63="","",IFERROR(IF(INDEX(Data!$AJ$2:$AJ$745,MATCH(49,Data!$B$2:$B$745,0))="","",INDEX(Data!$AJ$2:$AJ$745,MATCH(49,Data!$B$2:$B$745,0))),"")) | G63: =IF(B63="","",TRIM(IFERROR(IF(INDEX(Data!$AF$2:$AF$745,MATCH(49,Data!$B$2:$B$745,0))="","",INDEX(Data!$AF$2:$AF$745,MATCH(49,Data!$B$2:$B$745,0))),"")&" "&IFERROR(IF(INDEX(Data!$AG$2:$AG$745,MATCH(49,Data!$B$2:$B$745,0))="","",INDEX(Data!$AG$2:$AG$745,MATCH(49,Data!$B$2:$B$745,0))),""))) | H63: =IF(B63="","",IFERROR(IF(INDEX(Data!$N$2:$N$745,MATCH(49,Data!$B$2:$B$745,0))="","",INDEX(Data!$N$2:$N$745,MATCH(49,Data!$B$2:$B$745,0))),"")) | I63: =IF(B63="","",IFERROR(IF(INDEX(Data!$O$2:$O$745,MATCH(49,Data!$B$2:$B$745,0))="","",INDEX(Data!$O$2:$O$745,MATCH(49,Data!$B$2:$B$745,0))),"")) | J63: =IF(B63="","",IFERROR(IF(INDEX(Data!$P$2:$P$745,MATCH(49,Data!$B$2:$B$745,0))="","",INDEX(Data!$P$2:$P$745,MATCH(49,Data!$B$2:$B$745,0))),"")) | K63: =IF(B63="","",IFERROR(IF(INDEX(Data!$R$2:$R$745,MATCH(49,Data!$B$2:$B$745,0))="","",INDEX(Data!$R$2:$R$745,MATCH(49,Data!$B$2:$B$745,0))),"")) | L63: =IF(B63="","",IFERROR(IF(INDEX(Data!$S$2:$S$745,MATCH(49,Data!$B$2:$B$745,0))="","",INDEX(Data!$S$2:$S$745,MATCH(49,Data!$B$2:$B$745,0))),"")) | M63: =IF(B63="","",IFERROR(IF(INDEX(Data!$T$2:$T$745,MATCH(49,Data!$B$2:$B$745,0))="","",INDEX(Data!$T$2:$T$745,MATCH(49,Data!$B$2:$B$745,0))),"")) | N63: =IF(B63="","",IFERROR(IF(INDEX(Data!$U$2:$U$745,MATCH(49,Data!$B$2:$B$745,0))="","",INDEX(Data!$U$2:$U$745,MATCH(49,Data!$B$2:$B$745,0))),"")) | O63: =IF(B63="","",IFERROR(IF(INDEX(Data!$V$2:$V$745,MATCH(49,Data!$B$2:$B$745,0))="","",INDEX(Data!$V$2:$V$745,MATCH(49,Data!$B$2:$B$745,0))),"")) | P63: =IF(B63="","",IFERROR(IF(INDEX(Data!$M$2:$M$745,MATCH(49,Data!$B$2:$B$745,0))="","",INDEX(Data!$M$2:$M$745,MATCH(49,Data!$B$2:$B$745,0))),"")) | Q63: =IF(B63="","",IFERROR(IF(INDEX(Data!$AD$2:$AD$745,MATCH(49,Data!$B$2:$B$745,0))="","",INDEX(Data!$AD$2:$AD$745,MATCH(49,Data!$B$2:$B$745,0))),"")) | R63: =IF(B63="","",IFERROR(IF(INDEX(Data!$L$2:$L$745,MATCH(49,Data!$B$2:$B$745,0))="","",INDEX(Data!$L$2:$L$745,MATCH(49,Data!$B$2:$B$745,0))),"")) | AB63: DOWNCOOL
B64: =IF(50<=COUNTIF(Data!$A$2:$A$745,TRUE),50,"") | C64: =IF(B64="","",IFERROR(_xlfn.IMAGE(IFERROR(IF(INDEX(Data!$J$2:$J$745,MATCH(50,Data!$B$2:$B$745,0))="","",INDEX(Data!$J$2:$J$745,MATCH(50,Data!$B$2:$B$745,0))),"")),"IMAGE COMING SOON")) | D64: =IF(B64="","",IFERROR(IF(INDEX(Data!$G$2:$G$745,MATCH(50,Data!$B$2:$B$745,0))="","",INDEX(Data!$G$2:$G$745,MATCH(50,Data!$B$2:$B$745,0))),"")&CHAR(10)&IFERROR(IF(INDEX(Data!$H$2:$H$745,MATCH(50,Data!$B$2:$B$745,0))="","",INDEX(Data!$H$2:$H$745,MATCH(50,Data!$B$2:$B$745,0))),"")) | E64: =IF(B64="","",IFERROR(IF(INDEX(Data!$I$2:$I$745,MATCH(50,Data!$B$2:$B$745,0))="","",INDEX(Data!$I$2:$I$745,MATCH(50,Data!$B$2:$B$745,0))),"")) | F64: =IF(B64="","",IFERROR(IF(INDEX(Data!$AJ$2:$AJ$745,MATCH(50,Data!$B$2:$B$745,0))="","",INDEX(Data!$AJ$2:$AJ$745,MATCH(50,Data!$B$2:$B$745,0))),"")) | G64: =IF(B64="","",TRIM(IFERROR(IF(INDEX(Data!$AF$2:$AF$745,MATCH(50,Data!$B$2:$B$745,0))="","",INDEX(Data!$AF$2:$AF$745,MATCH(50,Data!$B$2:$B$745,0))),"")&" "&IFERROR(IF(INDEX(Data!$AG$2:$AG$745,MATCH(50,Data!$B$2:$B$745,0))="","",INDEX(Data!$AG$2:$AG$745,MATCH(50,Data!$B$2:$B$745,0))),""))) | H64: =IF(B64="","",IFERROR(IF(INDEX(Data!$N$2:$N$745,MATCH(50,Data!$B$2:$B$745,0))="","",INDEX(Data!$N$2:$N$745,MATCH(50,Data!$B$2:$B$745,0))),"")) | I64: =IF(B64="","",IFERROR(IF(INDEX(Data!$O$2:$O$745,MATCH(50,Data!$B$2:$B$745,0))="","",INDEX(Data!$O$2:$O$745,MATCH(50,Data!$B$2:$B$745,0))),"")) | J64: =IF(B64="","",IFERROR(IF(INDEX(Data!$P$2:$P$745,MATCH(50,Data!$B$2:$B$745,0))="","",INDEX(Data!$P$2:$P$745,MATCH(50,Data!$B$2:$B$745,0))),"")) | K64: =IF(B64="","",IFERROR(IF(INDEX(Data!$R$2:$R$745,MATCH(50,Data!$B$2:$B$745,0))="","",INDEX(Data!$R$2:$R$745,MATCH(50,Data!$B$2:$B$745,0))),"")) | L64: =IF(B64="","",IFERROR(IF(INDEX(Data!$S$2:$S$745,MATCH(50,Data!$B$2:$B$745,0))="","",INDEX(Data!$S$2:$S$745,MATCH(50,Data!$B$2:$B$745,0))),"")) | M64: =IF(B64="","",IFERROR(IF(INDEX(Data!$T$2:$T$745,MATCH(50,Data!$B$2:$B$745,0))="","",INDEX(Data!$T$2:$T$745,MATCH(50,Data!$B$2:$B$745,0))),"")) | N64: =IF(B64="","",IFERROR(IF(INDEX(Data!$U$2:$U$745,MATCH(50,Data!$B$2:$B$745,0))="","",INDEX(Data!$U$2:$U$745,MATCH(50,Data!$B$2:$B$745,0))),"")) | O64: =IF(B64="","",IFERROR(IF(INDEX(Data!$V$2:$V$745,MATCH(50,Data!$B$2:$B$745,0))="","",INDEX(Data!$V$2:$V$745,MATCH(50,Data!$B$2:$B$745,0))),"")) | P64: =IF(B64="","",IFERROR(IF(INDEX(Data!$M$2:$M$745,MATCH(50,Data!$B$2:$B$745,0))="","",INDEX(Data!$M$2:$M$745,MATCH(50,Data!$B$2:$B$745,0))),"")) | Q64: =IF(B64="","",IFERROR(IF(INDEX(Data!$AD$2:$AD$745,MATCH(50,Data!$B$2:$B$745,0))="","",INDEX(Data!$AD$2:$AD$745,MATCH(50,Data!$B$2:$B$745,0))),"")) | R64: =IF(B64="","",IFERROR(IF(INDEX(Data!$L$2:$L$745,MATCH(50,Data!$B$2:$B$745,0))="","",INDEX(Data!$L$2:$L$745,MATCH(50,Data!$B$2:$B$745,0))),"")) | AB64: DOZ by SIJO
B65: =IF(51<=COUNTIF(Data!$A$2:$A$745,TRUE),51,"") | C65: =IF(B65="","",IFERROR(_xlfn.IMAGE(IFERROR(IF(INDEX(Data!$J$2:$J$745,MATCH(51,Data!$B$2:$B$745,0))="","",INDEX(Data!$J$2:$J$745,MATCH(51,Data!$B$2:$B$745,0))),"")),"IMAGE COMING SOON")) | D65: =IF(B65="","",IFERROR(IF(INDEX(Data!$G$2:$G$745,MATCH(51,Data!$B$2:$B$745,0))="","",INDEX(Data!$G$2:$G$745,MATCH(51,Data!$B$2:$B$745,0))),"")&CHAR(10)&IFERROR(IF(INDEX(Data!$H$2:$H$745,MATCH(51,Data!$B$2:$B$745,0))="","",INDEX(Data!$H$2:$H$745,MATCH(51,Data!$B$2:$B$745,0))),"")) | E65: =IF(B65="","",IFERROR(IF(INDEX(Data!$I$2:$I$745,MATCH(51,Data!$B$2:$B$745,0))="","",INDEX(Data!$I$2:$I$745,MATCH(51,Data!$B$2:$B$745,0))),"")) | F65: =IF(B65="","",IFERROR(IF(INDEX(Data!$AJ$2:$AJ$745,MATCH(51,Data!$B$2:$B$745,0))="","",INDEX(Data!$AJ$2:$AJ$745,MATCH(51,Data!$B$2:$B$745,0))),"")) | G65: =IF(B65="","",TRIM(IFERROR(IF(INDEX(Data!$AF$2:$AF$745,MATCH(51,Data!$B$2:$B$745,0))="","",INDEX(Data!$AF$2:$AF$745,MATCH(51,Data!$B$2:$B$745,0))),"")&" "&IFERROR(IF(INDEX(Data!$AG$2:$AG$745,MATCH(51,Data!$B$2:$B$745,0))="","",INDEX(Data!$AG$2:$AG$745,MATCH(51,Data!$B$2:$B$745,0))),""))) | H65: =IF(B65="","",IFERROR(IF(INDEX(Data!$N$2:$N$745,MATCH(51,Data!$B$2:$B$745,0))="","",INDEX(Data!$N$2:$N$745,MATCH(51,Data!$B$2:$B$745,0))),"")) | I65: =IF(B65="","",IFERROR(IF(INDEX(Data!$O$2:$O$745,MATCH(51,Data!$B$2:$B$745,0))="","",INDEX(Data!$O$2:$O$745,MATCH(51,Data!$B$2:$B$745,0))),"")) | J65: =IF(B65="","",IFERROR(IF(INDEX(Data!$P$2:$P$745,MATCH(51,Data!$B$2:$B$745,0))="","",INDEX(Data!$P$2:$P$745,MATCH(51,Data!$B$2:$B$745,0))),"")) | K65: =IF(B65="","",IFERROR(IF(INDEX(Data!$R$2:$R$745,MATCH(51,Data!$B$2:$B$745,0))="","",INDEX(Data!$R$2:$R$745,MATCH(51,Data!$B$2:$B$745,0))),"")) | L65: =IF(B65="","",IFERROR(IF(INDEX(Data!$S$2:$S$745,MATCH(51,Data!$B$2:$B$745,0))="","",INDEX(Data!$S$2:$S$745,MATCH(51,Data!$B$2:$B$745,0))),"")) | M65: =IF(B65="","",IFERROR(IF(INDEX(Data!$T$2:$T$745,MATCH(51,Data!$B$2:$B$745,0))="","",INDEX(Data!$T$2:$T$745,MATCH(51,Data!$B$2:$B$745,0))),"")) | N65: =IF(B65="","",IFERROR(IF(INDEX(Data!$U$2:$U$745,MATCH(51,Data!$B$2:$B$745,0))="","",INDEX(Data!$U$2:$U$745,MATCH(51,Data!$B$2:$B$745,0))),"")) | O65: =IF(B65="","",IFERROR(IF(INDEX(Data!$V$2:$V$745,MATCH(51,Data!$B$2:$B$745,0))="","",INDEX(Data!$V$2:$V$745,MATCH(51,Data!$B$2:$B$745,0))),"")) | P65: =IF(B65="","",IFERROR(IF(INDEX(Data!$M$2:$M$745,MATCH(51,Data!$B$2:$B$745,0))="","",INDEX(Data!$M$2:$M$745,MATCH(51,Data!$B$2:$B$745,0))),"")) | Q65: =IF(B65="","",IFERROR(IF(INDEX(Data!$AD$2:$AD$745,MATCH(51,Data!$B$2:$B$745,0))="","",INDEX(Data!$AD$2:$AD$745,MATCH(51,Data!$B$2:$B$745,0))),"")) | R65: =IF(B65="","",IFERROR(IF(INDEX(Data!$L$2:$L$745,MATCH(51,Data!$B$2:$B$745,0))="","",INDEX(Data!$L$2:$L$745,MATCH(51,Data!$B$2:$B$745,0))),"")) | AB65: DREAMCARE
B66: =IF(52<=COUNTIF(Data!$A$2:$A$745,TRUE),52,"") | C66: =IF(B66="","",IFERROR(_xlfn.IMAGE(IFERROR(IF(INDEX(Data!$J$2:$J$745,MATCH(52,Data!$B$2:$B$745,0))="","",INDEX(Data!$J$2:$J$745,MATCH(52,Data!$B$2:$B$745,0))),"")),"IMAGE COMING SOON")) | D66: =IF(B66="","",IFERROR(IF(INDEX(Data!$G$2:$G$745,MATCH(52,Data!$B$2:$B$745,0))="","",INDEX(Data!$G$2:$G$745,MATCH(52,Data!$B$2:$B$745,0))),"")&CHAR(10)&IFERROR(IF(INDEX(Data!$H$2:$H$745,MATCH(52,Data!$B$2:$B$745,0))="","",INDEX(Data!$H$2:$H$745,MATCH(52,Data!$B$2:$B$745,0))),"")) | E66: =IF(B66="","",IFERROR(IF(INDEX(Data!$I$2:$I$745,MATCH(52,Data!$B$2:$B$745,0))="","",INDEX(Data!$I$2:$I$745,MATCH(52,Data!$B$2:$B$745,0))),"")) | F66: =IF(B66="","",IFERROR(IF(INDEX(Data!$AJ$2:$AJ$745,MATCH(52,Data!$B$2:$B$745,0))="","",INDEX(Data!$AJ$2:$AJ$745,MATCH(52,Data!$B$2:$B$745,0))),"")) | G66: =IF(B66="","",TRIM(IFERROR(IF(INDEX(Data!$AF$2:$AF$745,MATCH(52,Data!$B$2:$B$745,0))="","",INDEX(Data!$AF$2:$AF$745,MATCH(52,Data!$B$2:$B$745,0))),"")&" "&IFERROR(IF(INDEX(Data!$AG$2:$AG$745,MATCH(52,Data!$B$2:$B$745,0))="","",INDEX(Data!$AG$2:$AG$745,MATCH(52,Data!$B$2:$B$745,0))),""))) | H66: =IF(B66="","",IFERROR(IF(INDEX(Data!$N$2:$N$745,MATCH(52,Data!$B$2:$B$745,0))="","",INDEX(Data!$N$2:$N$745,MATCH(52,Data!$B$2:$B$745,0))),"")) | I66: =IF(B66="","",IFERROR(IF(INDEX(Data!$O$2:$O$745,MATCH(52,Data!$B$2:$B$745,0))="","",INDEX(Data!$O$2:$O$745,MATCH(52,Data!$B$2:$B$745,0))),"")) | J66: =IF(B66="","",IFERROR(IF(INDEX(Data!$P$2:$P$745,MATCH(52,Data!$B$2:$B$745,0))="","",INDEX(Data!$P$2:$P$745,MATCH(52,Data!$B$2:$B$745,0))),"")) | K66: =IF(B66="","",IFERROR(IF(INDEX(Data!$R$2:$R$745,MATCH(52,Data!$B$2:$B$745,0))="","",INDEX(Data!$R$2:$R$745,MATCH(52,Data!$B$2:$B$745,0))),"")) | L66: =IF(B66="","",IFERROR(IF(INDEX(Data!$S$2:$S$745,MATCH(52,Data!$B$2:$B$745,0))="","",INDEX(Data!$S$2:$S$745,MATCH(52,Data!$B$2:$B$745,0))),"")) | M66: =IF(B66="","",IFERROR(IF(INDEX(Data!$T$2:$T$745,MATCH(52,Data!$B$2:$B$745,0))="","",INDEX(Data!$T$2:$T$745,MATCH(52,Data!$B$2:$B$745,0))),"")) | N66: =IF(B66="","",IFERROR(IF(INDEX(Data!$U$2:$U$745,MATCH(52,Data!$B$2:$B$745,0))="","",INDEX(Data!$U$2:$U$745,MATCH(52,Data!$B$2:$B$745,0))),"")) | O66: =IF(B66="","",IFERROR(IF(INDEX(Data!$V$2:$V$745,MATCH(52,Data!$B$2:$B$745,0))="","",INDEX(Data!$V$2:$V$745,MATCH(52,Data!$B$2:$B$745,0))),"")) | P66: =IF(B66="","",IFERROR(IF(INDEX(Data!$M$2:$M$745,MATCH(52,Data!$B$2:$B$745,0))="","",INDEX(Data!$M$2:$M$745,MATCH(52,Data!$B$2:$B$745,0))),"")) | Q66: =IF(B66="","",IFERROR(IF(INDEX(Data!$AD$2:$AD$745,MATCH(52,Data!$B$2:$B$745,0))="","",INDEX(Data!$AD$2:$AD$745,MATCH(52,Data!$B$2:$B$745,0))),"")) | R66: =IF(B66="","",IFERROR(IF(INDEX(Data!$L$2:$L$745,MATCH(52,Data!$B$2:$B$745,0))="","",INDEX(Data!$L$2:$L$745,MATCH(52,Data!$B$2:$B$745,0))),"")) | AB66: DROWSY
B67: =IF(53<=COUNTIF(Data!$A$2:$A$745,TRUE),53,"") | C67: =IF(B67="","",IFERROR(_xlfn.IMAGE(IFERROR(IF(INDEX(Data!$J$2:$J$745,MATCH(53,Data!$B$2:$B$745,0))="","",INDEX(Data!$J$2:$J$745,MATCH(53,Data!$B$2:$B$745,0))),"")),"IMAGE COMING SOON")) | D67: =IF(B67="","",IFERROR(IF(INDEX(Data!$G$2:$G$745,MATCH(53,Data!$B$2:$B$745,0))="","",INDEX(Data!$G$2:$G$745,MATCH(53,Data!$B$2:$B$745,0))),"")&CHAR(10)&IFERROR(IF(INDEX(Data!$H$2:$H$745,MATCH(53,Data!$B$2:$B$745,0))="","",INDEX(Data!$H$2:$H$745,MATCH(53,Data!$B$2:$B$745,0))),"")) | E67: =IF(B67="","",IFERROR(IF(INDEX(Data!$I$2:$I$745,MATCH(53,Data!$B$2:$B$745,0))="","",INDEX(Data!$I$2:$I$745,MATCH(53,Data!$B$2:$B$745,0))),"")) | F67: =IF(B67="","",IFERROR(IF(INDEX(Data!$AJ$2:$AJ$745,MATCH(53,Data!$B$2:$B$745,0))="","",INDEX(Data!$AJ$2:$AJ$745,MATCH(53,Data!$B$2:$B$745,0))),"")) | G67: =IF(B67="","",TRIM(IFERROR(IF(INDEX(Data!$AF$2:$AF$745,MATCH(53,Data!$B$2:$B$745,0))="","",INDEX(Data!$AF$2:$AF$745,MATCH(53,Data!$B$2:$B$745,0))),"")&" "&IFERROR(IF(INDEX(Data!$AG$2:$AG$745,MATCH(53,Data!$B$2:$B$745,0))="","",INDEX(Data!$AG$2:$AG$745,MATCH(53,Data!$B$2:$B$745,0))),""))) | H67: =IF(B67="","",IFERROR(IF(INDEX(Data!$N$2:$N$745,MATCH(53,Data!$B$2:$B$745,0))="","",INDEX(Data!$N$2:$N$745,MATCH(53,Data!$B$2:$B$745,0))),"")) | I67: =IF(B67="","",IFERROR(IF(INDEX(Data!$O$2:$O$745,MATCH(53,Data!$B$2:$B$745,0))="","",INDEX(Data!$O$2:$O$745,MATCH(53,Data!$B$2:$B$745,0))),"")) | J67: =IF(B67="","",IFERROR(IF(INDEX(Data!$P$2:$P$745,MATCH(53,Data!$B$2:$B$745,0))="","",INDEX(Data!$P$2:$P$745,MATCH(53,Data!$B$2:$B$745,0))),"")) | K67: =IF(B67="","",IFERROR(IF(INDEX(Data!$R$2:$R$745,MATCH(53,Data!$B$2:$B$745,0))="","",INDEX(Data!$R$2:$R$745,MATCH(53,Data!$B$2:$B$745,0))),"")) | L67: =IF(B67="","",IFERROR(IF(INDEX(Data!$S$2:$S$745,MATCH(53,Data!$B$2:$B$745,0))="","",INDEX(Data!$S$2:$S$745,MATCH(53,Data!$B$2:$B$745,0))),"")) | M67: =IF(B67="","",IFERROR(IF(INDEX(Data!$T$2:$T$745,MATCH(53,Data!$B$2:$B$745,0))="","",INDEX(Data!$T$2:$T$745,MATCH(53,Data!$B$2:$B$745,0))),"")) | N67: =IF(B67="","",IFERROR(IF(INDEX(Data!$U$2:$U$745,MATCH(53,Data!$B$2:$B$745,0))="","",INDEX(Data!$U$2:$U$745,MATCH(53,Data!$B$2:$B$745,0))),"")) | O67: =IF(B67="","",IFERROR(IF(INDEX(Data!$V$2:$V$745,MATCH(53,Data!$B$2:$B$745,0))="","",INDEX(Data!$V$2:$V$745,MATCH(53,Data!$B$2:$B$745,0))),"")) | P67: =IF(B67="","",IFERROR(IF(INDEX(Data!$M$2:$M$745,MATCH(53,Data!$B$2:$B$745,0))="","",INDEX(Data!$M$2:$M$745,MATCH(53,Data!$B$2:$B$745,0))),"")) | Q67: =IF(B67="","",IFERROR(IF(INDEX(Data!$AD$2:$AD$745,MATCH(53,Data!$B$2:$B$745,0))="","",INDEX(Data!$AD$2:$AD$745,MATCH(53,Data!$B$2:$B$745,0))),"")) | R67: =IF(B67="","",IFERROR(IF(INDEX(Data!$L$2:$L$745,MATCH(53,Data!$B$2:$B$745,0))="","",INDEX(Data!$L$2:$L$745,MATCH(53,Data!$B$2:$B$745,0))),"")) | AB67: EASELAND
B68: =IF(54<=COUNTIF(Data!$A$2:$A$745,TRUE),54,"") | C68: =IF(B68="","",IFERROR(_xlfn.IMAGE(IFERROR(IF(INDEX(Data!$J$2:$J$745,MATCH(54,Data!$B$2:$B$745,0))="","",INDEX(Data!$J$2:$J$745,MATCH(54,Data!$B$2:$B$745,0))),"")),"IMAGE COMING SOON")) | D68: =IF(B68="","",IFERROR(IF(INDEX(Data!$G$2:$G$745,MATCH(54,Data!$B$2:$B$745,0))="","",INDEX(Data!$G$2:$G$745,MATCH(54,Data!$B$2:$B$745,0))),"")&CHAR(10)&IFERROR(IF(INDEX(Data!$H$2:$H$745,MATCH(54,Data!$B$2:$B$745,0))="","",INDEX(Data!$H$2:$H$745,MATCH(54,Data!$B$2:$B$745,0))),"")) | E68: =IF(B68="","",IFERROR(IF(INDEX(Data!$I$2:$I$745,MATCH(54,Data!$B$2:$B$745,0))="","",INDEX(Data!$I$2:$I$745,MATCH(54,Data!$B$2:$B$745,0))),"")) | F68: =IF(B68="","",IFERROR(IF(INDEX(Data!$AJ$2:$AJ$745,MATCH(54,Data!$B$2:$B$745,0))="","",INDEX(Data!$AJ$2:$AJ$745,MATCH(54,Data!$B$2:$B$745,0))),"")) | G68: =IF(B68="","",TRIM(IFERROR(IF(INDEX(Data!$AF$2:$AF$745,MATCH(54,Data!$B$2:$B$745,0))="","",INDEX(Data!$AF$2:$AF$745,MATCH(54,Data!$B$2:$B$745,0))),"")&" "&IFERROR(IF(INDEX(Data!$AG$2:$AG$745,MATCH(54,Data!$B$2:$B$745,0))="","",INDEX(Data!$AG$2:$AG$745,MATCH(54,Data!$B$2:$B$745,0))),""))) | H68: =IF(B68="","",IFERROR(IF(INDEX(Data!$N$2:$N$745,MATCH(54,Data!$B$2:$B$745,0))="","",INDEX(Data!$N$2:$N$745,MATCH(54,Data!$B$2:$B$745,0))),"")) | I68: =IF(B68="","",IFERROR(IF(INDEX(Data!$O$2:$O$745,MATCH(54,Data!$B$2:$B$745,0))="","",INDEX(Data!$O$2:$O$745,MATCH(54,Data!$B$2:$B$745,0))),"")) | J68: =IF(B68="","",IFERROR(IF(INDEX(Data!$P$2:$P$745,MATCH(54,Data!$B$2:$B$745,0))="","",INDEX(Data!$P$2:$P$745,MATCH(54,Data!$B$2:$B$745,0))),"")) | K68: =IF(B68="","",IFERROR(IF(INDEX(Data!$R$2:$R$745,MATCH(54,Data!$B$2:$B$745,0))="","",INDEX(Data!$R$2:$R$745,MATCH(54,Data!$B$2:$B$745,0))),"")) | L68: =IF(B68="","",IFERROR(IF(INDEX(Data!$S$2:$S$745,MATCH(54,Data!$B$2:$B$745,0))="","",INDEX(Data!$S$2:$S$745,MATCH(54,Data!$B$2:$B$745,0))),"")) | M68: =IF(B68="","",IFERROR(IF(INDEX(Data!$T$2:$T$745,MATCH(54,Data!$B$2:$B$745,0))="","",INDEX(Data!$T$2:$T$745,MATCH(54,Data!$B$2:$B$745,0))),"")) | N68: =IF(B68="","",IFERROR(IF(INDEX(Data!$U$2:$U$745,MATCH(54,Data!$B$2:$B$745,0))="","",INDEX(Data!$U$2:$U$745,MATCH(54,Data!$B$2:$B$745,0))),"")) | O68: =IF(B68="","",IFERROR(IF(INDEX(Data!$V$2:$V$745,MATCH(54,Data!$B$2:$B$745,0))="","",INDEX(Data!$V$2:$V$745,MATCH(54,Data!$B$2:$B$745,0))),"")) | P68: =IF(B68="","",IFERROR(IF(INDEX(Data!$M$2:$M$745,MATCH(54,Data!$B$2:$B$745,0))="","",INDEX(Data!$M$2:$M$745,MATCH(54,Data!$B$2:$B$745,0))),"")) | Q68: =IF(B68="","",IFERROR(IF(INDEX(Data!$AD$2:$AD$745,MATCH(54,Data!$B$2:$B$745,0))="","",INDEX(Data!$AD$2:$AD$745,MATCH(54,Data!$B$2:$B$745,0))),"")) | R68: =IF(B68="","",IFERROR(IF(INDEX(Data!$L$2:$L$745,MATCH(54,Data!$B$2:$B$745,0))="","",INDEX(Data!$L$2:$L$745,MATCH(54,Data!$B$2:$B$745,0))),"")) | AB68: Easy-Going
B69: =IF(55<=COUNTIF(Data!$A$2:$A$745,TRUE),55,"") | C69: =IF(B69="","",IFERROR(_xlfn.IMAGE(IFERROR(IF(INDEX(Data!$J$2:$J$745,MATCH(55,Data!$B$2:$B$745,0))="","",INDEX(Data!$J$2:$J$745,MATCH(55,Data!$B$2:$B$745,0))),"")),"IMAGE COMING SOON")) | D69: =IF(B69="","",IFERROR(IF(INDEX(Data!$G$2:$G$745,MATCH(55,Data!$B$2:$B$745,0))="","",INDEX(Data!$G$2:$G$745,MATCH(55,Data!$B$2:$B$745,0))),"")&CHAR(10)&IFERROR(IF(INDEX(Data!$H$2:$H$745,MATCH(55,Data!$B$2:$B$745,0))="","",INDEX(Data!$H$2:$H$745,MATCH(55,Data!$B$2:$B$745,0))),"")) | E69: =IF(B69="","",IFERROR(IF(INDEX(Data!$I$2:$I$745,MATCH(55,Data!$B$2:$B$745,0))="","",INDEX(Data!$I$2:$I$745,MATCH(55,Data!$B$2:$B$745,0))),"")) | F69: =IF(B69="","",IFERROR(IF(INDEX(Data!$AJ$2:$AJ$745,MATCH(55,Data!$B$2:$B$745,0))="","",INDEX(Data!$AJ$2:$AJ$745,MATCH(55,Data!$B$2:$B$745,0))),"")) | G69: =IF(B69="","",TRIM(IFERROR(IF(INDEX(Data!$AF$2:$AF$745,MATCH(55,Data!$B$2:$B$745,0))="","",INDEX(Data!$AF$2:$AF$745,MATCH(55,Data!$B$2:$B$745,0))),"")&" "&IFERROR(IF(INDEX(Data!$AG$2:$AG$745,MATCH(55,Data!$B$2:$B$745,0))="","",INDEX(Data!$AG$2:$AG$745,MATCH(55,Data!$B$2:$B$745,0))),""))) | H69: =IF(B69="","",IFERROR(IF(INDEX(Data!$N$2:$N$745,MATCH(55,Data!$B$2:$B$745,0))="","",INDEX(Data!$N$2:$N$745,MATCH(55,Data!$B$2:$B$745,0))),"")) | I69: =IF(B69="","",IFERROR(IF(INDEX(Data!$O$2:$O$745,MATCH(55,Data!$B$2:$B$745,0))="","",INDEX(Data!$O$2:$O$745,MATCH(55,Data!$B$2:$B$745,0))),"")) | J69: =IF(B69="","",IFERROR(IF(INDEX(Data!$P$2:$P$745,MATCH(55,Data!$B$2:$B$745,0))="","",INDEX(Data!$P$2:$P$745,MATCH(55,Data!$B$2:$B$745,0))),"")) | K69: =IF(B69="","",IFERROR(IF(INDEX(Data!$R$2:$R$745,MATCH(55,Data!$B$2:$B$745,0))="","",INDEX(Data!$R$2:$R$745,MATCH(55,Data!$B$2:$B$745,0))),"")) | L69: =IF(B69="","",IFERROR(IF(INDEX(Data!$S$2:$S$745,MATCH(55,Data!$B$2:$B$745,0))="","",INDEX(Data!$S$2:$S$745,MATCH(55,Data!$B$2:$B$745,0))),"")) | M69: =IF(B69="","",IFERROR(IF(INDEX(Data!$T$2:$T$745,MATCH(55,Data!$B$2:$B$745,0))="","",INDEX(Data!$T$2:$T$745,MATCH(55,Data!$B$2:$B$745,0))),"")) | N69: =IF(B69="","",IFERROR(IF(INDEX(Data!$U$2:$U$745,MATCH(55,Data!$B$2:$B$745,0))="","",INDEX(Data!$U$2:$U$745,MATCH(55,Data!$B$2:$B$745,0))),"")) | O69: =IF(B69="","",IFERROR(IF(INDEX(Data!$V$2:$V$745,MATCH(55,Data!$B$2:$B$745,0))="","",INDEX(Data!$V$2:$V$745,MATCH(55,Data!$B$2:$B$745,0))),"")) | P69: =IF(B69="","",IFERROR(IF(INDEX(Data!$M$2:$M$745,MATCH(55,Data!$B$2:$B$745,0))="","",INDEX(Data!$M$2:$M$745,MATCH(55,Data!$B$2:$B$745,0))),"")) | Q69: =IF(B69="","",IFERROR(IF(INDEX(Data!$AD$2:$AD$745,MATCH(55,Data!$B$2:$B$745,0))="","",INDEX(Data!$AD$2:$AD$745,MATCH(55,Data!$B$2:$B$745,0))),"")) | R69: =IF(B69="","",IFERROR(IF(INDEX(Data!$L$2:$L$745,MATCH(55,Data!$B$2:$B$745,0))="","",INDEX(Data!$L$2:$L$745,MATCH(55,Data!$B$2:$B$745,0))),"")) | AB69: Elegear
B70: =IF(56<=COUNTIF(Data!$A$2:$A$745,TRUE),56,"") | C70: =IF(B70="","",IFERROR(_xlfn.IMAGE(IFERROR(IF(INDEX(Data!$J$2:$J$745,MATCH(56,Data!$B$2:$B$745,0))="","",INDEX(Data!$J$2:$J$745,MATCH(56,Data!$B$2:$B$745,0))),"")),"IMAGE COMING SOON")) | D70: =IF(B70="","",IFERROR(IF(INDEX(Data!$G$2:$G$745,MATCH(56,Data!$B$2:$B$745,0))="","",INDEX(Data!$G$2:$G$745,MATCH(56,Data!$B$2:$B$745,0))),"")&CHAR(10)&IFERROR(IF(INDEX(Data!$H$2:$H$745,MATCH(56,Data!$B$2:$B$745,0))="","",INDEX(Data!$H$2:$H$745,MATCH(56,Data!$B$2:$B$745,0))),"")) | E70: =IF(B70="","",IFERROR(IF(INDEX(Data!$I$2:$I$745,MATCH(56,Data!$B$2:$B$745,0))="","",INDEX(Data!$I$2:$I$745,MATCH(56,Data!$B$2:$B$745,0))),"")) | F70: =IF(B70="","",IFERROR(IF(INDEX(Data!$AJ$2:$AJ$745,MATCH(56,Data!$B$2:$B$745,0))="","",INDEX(Data!$AJ$2:$AJ$745,MATCH(56,Data!$B$2:$B$745,0))),"")) | G70: =IF(B70="","",TRIM(IFERROR(IF(INDEX(Data!$AF$2:$AF$745,MATCH(56,Data!$B$2:$B$745,0))="","",INDEX(Data!$AF$2:$AF$745,MATCH(56,Data!$B$2:$B$745,0))),"")&" "&IFERROR(IF(INDEX(Data!$AG$2:$AG$745,MATCH(56,Data!$B$2:$B$745,0))="","",INDEX(Data!$AG$2:$AG$745,MATCH(56,Data!$B$2:$B$745,0))),""))) | H70: =IF(B70="","",IFERROR(IF(INDEX(Data!$N$2:$N$745,MATCH(56,Data!$B$2:$B$745,0))="","",INDEX(Data!$N$2:$N$745,MATCH(56,Data!$B$2:$B$745,0))),"")) | I70: =IF(B70="","",IFERROR(IF(INDEX(Data!$O$2:$O$745,MATCH(56,Data!$B$2:$B$745,0))="","",INDEX(Data!$O$2:$O$745,MATCH(56,Data!$B$2:$B$745,0))),"")) | J70: =IF(B70="","",IFERROR(IF(INDEX(Data!$P$2:$P$745,MATCH(56,Data!$B$2:$B$745,0))="","",INDEX(Data!$P$2:$P$745,MATCH(56,Data!$B$2:$B$745,0))),"")) | K70: =IF(B70="","",IFERROR(IF(INDEX(Data!$R$2:$R$745,MATCH(56,Data!$B$2:$B$745,0))="","",INDEX(Data!$R$2:$R$745,MATCH(56,Data!$B$2:$B$745,0))),"")) | L70: =IF(B70="","",IFERROR(IF(INDEX(Data!$S$2:$S$745,MATCH(56,Data!$B$2:$B$745,0))="","",INDEX(Data!$S$2:$S$745,MATCH(56,Data!$B$2:$B$745,0))),"")) | M70: =IF(B70="","",IFERROR(IF(INDEX(Data!$T$2:$T$745,MATCH(56,Data!$B$2:$B$745,0))="","",INDEX(Data!$T$2:$T$745,MATCH(56,Data!$B$2:$B$745,0))),"")) | N70: =IF(B70="","",IFERROR(IF(INDEX(Data!$U$2:$U$745,MATCH(56,Data!$B$2:$B$745,0))="","",INDEX(Data!$U$2:$U$745,MATCH(56,Data!$B$2:$B$745,0))),"")) | O70: =IF(B70="","",IFERROR(IF(INDEX(Data!$V$2:$V$745,MATCH(56,Data!$B$2:$B$745,0))="","",INDEX(Data!$V$2:$V$745,MATCH(56,Data!$B$2:$B$745,0))),"")) | P70: =IF(B70="","",IFERROR(IF(INDEX(Data!$M$2:$M$745,MATCH(56,Data!$B$2:$B$745,0))="","",INDEX(Data!$M$2:$M$745,MATCH(56,Data!$B$2:$B$745,0))),"")) | Q70: =IF(B70="","",IFERROR(IF(INDEX(Data!$AD$2:$AD$745,MATCH(56,Data!$B$2:$B$745,0))="","",INDEX(Data!$AD$2:$AD$745,MATCH(56,Data!$B$2:$B$745,0))),"")) | R70: =IF(B70="","",IFERROR(IF(INDEX(Data!$L$2:$L$745,MATCH(56,Data!$B$2:$B$745,0))="","",INDEX(Data!$L$2:$L$745,MATCH(56,Data!$B$2:$B$745,0))),"")) | AB70: ELIBABA
B71: =IF(57<=COUNTIF(Data!$A$2:$A$745,TRUE),57,"") | C71: =IF(B71="","",IFERROR(_xlfn.IMAGE(IFERROR(IF(INDEX(Data!$J$2:$J$745,MATCH(57,Data!$B$2:$B$745,0))="","",INDEX(Data!$J$2:$J$745,MATCH(57,Data!$B$2:$B$745,0))),"")),"IMAGE COMING SOON")) | D71: =IF(B71="","",IFERROR(IF(INDEX(Data!$G$2:$G$745,MATCH(57,Data!$B$2:$B$745,0))="","",INDEX(Data!$G$2:$G$745,MATCH(57,Data!$B$2:$B$745,0))),"")&CHAR(10)&IFERROR(IF(INDEX(Data!$H$2:$H$745,MATCH(57,Data!$B$2:$B$745,0))="","",INDEX(Data!$H$2:$H$745,MATCH(57,Data!$B$2:$B$745,0))),"")) | E71: =IF(B71="","",IFERROR(IF(INDEX(Data!$I$2:$I$745,MATCH(57,Data!$B$2:$B$745,0))="","",INDEX(Data!$I$2:$I$745,MATCH(57,Data!$B$2:$B$745,0))),"")) | F71: =IF(B71="","",IFERROR(IF(INDEX(Data!$AJ$2:$AJ$745,MATCH(57,Data!$B$2:$B$745,0))="","",INDEX(Data!$AJ$2:$AJ$745,MATCH(57,Data!$B$2:$B$745,0))),"")) | G71: =IF(B71="","",TRIM(IFERROR(IF(INDEX(Data!$AF$2:$AF$745,MATCH(57,Data!$B$2:$B$745,0))="","",INDEX(Data!$AF$2:$AF$745,MATCH(57,Data!$B$2:$B$745,0))),"")&" "&IFERROR(IF(INDEX(Data!$AG$2:$AG$745,MATCH(57,Data!$B$2:$B$745,0))="","",INDEX(Data!$AG$2:$AG$745,MATCH(57,Data!$B$2:$B$745,0))),""))) | H71: =IF(B71="","",IFERROR(IF(INDEX(Data!$N$2:$N$745,MATCH(57,Data!$B$2:$B$745,0))="","",INDEX(Data!$N$2:$N$745,MATCH(57,Data!$B$2:$B$745,0))),"")) | I71: =IF(B71="","",IFERROR(IF(INDEX(Data!$O$2:$O$745,MATCH(57,Data!$B$2:$B$745,0))="","",INDEX(Data!$O$2:$O$745,MATCH(57,Data!$B$2:$B$745,0))),"")) | J71: =IF(B71="","",IFERROR(IF(INDEX(Data!$P$2:$P$745,MATCH(57,Data!$B$2:$B$745,0))="","",INDEX(Data!$P$2:$P$745,MATCH(57,Data!$B$2:$B$745,0))),"")) | K71: =IF(B71="","",IFERROR(IF(INDEX(Data!$R$2:$R$745,MATCH(57,Data!$B$2:$B$745,0))="","",INDEX(Data!$R$2:$R$745,MATCH(57,Data!$B$2:$B$745,0))),"")) | L71: =IF(B71="","",IFERROR(IF(INDEX(Data!$S$2:$S$745,MATCH(57,Data!$B$2:$B$745,0))="","",INDEX(Data!$S$2:$S$745,MATCH(57,Data!$B$2:$B$745,0))),"")) | M71: =IF(B71="","",IFERROR(IF(INDEX(Data!$T$2:$T$745,MATCH(57,Data!$B$2:$B$745,0))="","",INDEX(Data!$T$2:$T$745,MATCH(57,Data!$B$2:$B$745,0))),"")) | N71: =IF(B71="","",IFERROR(IF(INDEX(Data!$U$2:$U$745,MATCH(57,Data!$B$2:$B$745,0))="","",INDEX(Data!$U$2:$U$745,MATCH(57,Data!$B$2:$B$745,0))),"")) | O71: =IF(B71="","",IFERROR(IF(INDEX(Data!$V$2:$V$745,MATCH(57,Data!$B$2:$B$745,0))="","",INDEX(Data!$V$2:$V$745,MATCH(57,Data!$B$2:$B$745,0))),"")) | P71: =IF(B71="","",IFERROR(IF(INDEX(Data!$M$2:$M$745,MATCH(57,Data!$B$2:$B$745,0))="","",INDEX(Data!$M$2:$M$745,MATCH(57,Data!$B$2:$B$745,0))),"")) | Q71: =IF(B71="","",IFERROR(IF(INDEX(Data!$AD$2:$AD$745,MATCH(57,Data!$B$2:$B$745,0))="","",INDEX(Data!$AD$2:$AD$745,MATCH(57,Data!$B$2:$B$745,0))),"")) | R71: =IF(B71="","",IFERROR(IF(INDEX(Data!$L$2:$L$745,MATCH(57,Data!$B$2:$B$745,0))="","",INDEX(Data!$L$2:$L$745,MATCH(57,Data!$B$2:$B$745,0))),"")) | AB71: EverGrace
B72: =IF(58<=COUNTIF(Data!$A$2:$A$745,TRUE),58,"") | C72: =IF(B72="","",IFERROR(_xlfn.IMAGE(IFERROR(IF(INDEX(Data!$J$2:$J$745,MATCH(58,Data!$B$2:$B$745,0))="","",INDEX(Data!$J$2:$J$745,MATCH(58,Data!$B$2:$B$745,0))),"")),"IMAGE COMING SOON")) | D72: =IF(B72="","",IFERROR(IF(INDEX(Data!$G$2:$G$745,MATCH(58,Data!$B$2:$B$745,0))="","",INDEX(Data!$G$2:$G$745,MATCH(58,Data!$B$2:$B$745,0))),"")&CHAR(10)&IFERROR(IF(INDEX(Data!$H$2:$H$745,MATCH(58,Data!$B$2:$B$745,0))="","",INDEX(Data!$H$2:$H$745,MATCH(58,Data!$B$2:$B$745,0))),"")) | E72: =IF(B72="","",IFERROR(IF(INDEX(Data!$I$2:$I$745,MATCH(58,Data!$B$2:$B$745,0))="","",INDEX(Data!$I$2:$I$745,MATCH(58,Data!$B$2:$B$745,0))),"")) | F72: =IF(B72="","",IFERROR(IF(INDEX(Data!$AJ$2:$AJ$745,MATCH(58,Data!$B$2:$B$745,0))="","",INDEX(Data!$AJ$2:$AJ$745,MATCH(58,Data!$B$2:$B$745,0))),"")) | G72: =IF(B72="","",TRIM(IFERROR(IF(INDEX(Data!$AF$2:$AF$745,MATCH(58,Data!$B$2:$B$745,0))="","",INDEX(Data!$AF$2:$AF$745,MATCH(58,Data!$B$2:$B$745,0))),"")&" "&IFERROR(IF(INDEX(Data!$AG$2:$AG$745,MATCH(58,Data!$B$2:$B$745,0))="","",INDEX(Data!$AG$2:$AG$745,MATCH(58,Data!$B$2:$B$745,0))),""))) | H72: =IF(B72="","",IFERROR(IF(INDEX(Data!$N$2:$N$745,MATCH(58,Data!$B$2:$B$745,0))="","",INDEX(Data!$N$2:$N$745,MATCH(58,Data!$B$2:$B$745,0))),"")) | I72: =IF(B72="","",IFERROR(IF(INDEX(Data!$O$2:$O$745,MATCH(58,Data!$B$2:$B$745,0))="","",INDEX(Data!$O$2:$O$745,MATCH(58,Data!$B$2:$B$745,0))),"")) | J72: =IF(B72="","",IFERROR(IF(INDEX(Data!$P$2:$P$745,MATCH(58,Data!$B$2:$B$745,0))="","",INDEX(Data!$P$2:$P$745,MATCH(58,Data!$B$2:$B$745,0))),"")) | K72: =IF(B72="","",IFERROR(IF(INDEX(Data!$R$2:$R$745,MATCH(58,Data!$B$2:$B$745,0))="","",INDEX(Data!$R$2:$R$745,MATCH(58,Data!$B$2:$B$745,0))),"")) | L72: =IF(B72="","",IFERROR(IF(INDEX(Data!$S$2:$S$745,MATCH(58,Data!$B$2:$B$745,0))="","",INDEX(Data!$S$2:$S$745,MATCH(58,Data!$B$2:$B$745,0))),"")) | M72: =IF(B72="","",IFERROR(IF(INDEX(Data!$T$2:$T$745,MATCH(58,Data!$B$2:$B$745,0))="","",INDEX(Data!$T$2:$T$745,MATCH(58,Data!$B$2:$B$745,0))),"")) | N72: =IF(B72="","",IFERROR(IF(INDEX(Data!$U$2:$U$745,MATCH(58,Data!$B$2:$B$745,0))="","",INDEX(Data!$U$2:$U$745,MATCH(58,Data!$B$2:$B$745,0))),"")) | O72: =IF(B72="","",IFERROR(IF(INDEX(Data!$V$2:$V$745,MATCH(58,Data!$B$2:$B$745,0))="","",INDEX(Data!$V$2:$V$745,MATCH(58,Data!$B$2:$B$745,0))),"")) | P72: =IF(B72="","",IFERROR(IF(INDEX(Data!$M$2:$M$745,MATCH(58,Data!$B$2:$B$745,0))="","",INDEX(Data!$M$2:$M$745,MATCH(58,Data!$B$2:$B$745,0))),"")) | Q72: =IF(B72="","",IFERROR(IF(INDEX(Data!$AD$2:$AD$745,MATCH(58,Data!$B$2:$B$745,0))="","",INDEX(Data!$AD$2:$AD$745,MATCH(58,Data!$B$2:$B$745,0))),"")) | R72: =IF(B72="","",IFERROR(IF(INDEX(Data!$L$2:$L$745,MATCH(58,Data!$B$2:$B$745,0))="","",INDEX(Data!$L$2:$L$745,MATCH(58,Data!$B$2:$B$745,0))),"")) | AB72: Exclusivo Mezcla
B73: =IF(59<=COUNTIF(Data!$A$2:$A$745,TRUE),59,"") | C73: =IF(B73="","",IFERROR(_xlfn.IMAGE(IFERROR(IF(INDEX(Data!$J$2:$J$745,MATCH(59,Data!$B$2:$B$745,0))="","",INDEX(Data!$J$2:$J$745,MATCH(59,Data!$B$2:$B$745,0))),"")),"IMAGE COMING SOON")) | D73: =IF(B73="","",IFERROR(IF(INDEX(Data!$G$2:$G$745,MATCH(59,Data!$B$2:$B$745,0))="","",INDEX(Data!$G$2:$G$745,MATCH(59,Data!$B$2:$B$745,0))),"")&CHAR(10)&IFERROR(IF(INDEX(Data!$H$2:$H$745,MATCH(59,Data!$B$2:$B$745,0))="","",INDEX(Data!$H$2:$H$745,MATCH(59,Data!$B$2:$B$745,0))),"")) | E73: =IF(B73="","",IFERROR(IF(INDEX(Data!$I$2:$I$745,MATCH(59,Data!$B$2:$B$745,0))="","",INDEX(Data!$I$2:$I$745,MATCH(59,Data!$B$2:$B$745,0))),"")) | F73: =IF(B73="","",IFERROR(IF(INDEX(Data!$AJ$2:$AJ$745,MATCH(59,Data!$B$2:$B$745,0))="","",INDEX(Data!$AJ$2:$AJ$745,MATCH(59,Data!$B$2:$B$745,0))),"")) | G73: =IF(B73="","",TRIM(IFERROR(IF(INDEX(Data!$AF$2:$AF$745,MATCH(59,Data!$B$2:$B$745,0))="","",INDEX(Data!$AF$2:$AF$745,MATCH(59,Data!$B$2:$B$745,0))),"")&" "&IFERROR(IF(INDEX(Data!$AG$2:$AG$745,MATCH(59,Data!$B$2:$B$745,0))="","",INDEX(Data!$AG$2:$AG$745,MATCH(59,Data!$B$2:$B$745,0))),""))) | H73: =IF(B73="","",IFERROR(IF(INDEX(Data!$N$2:$N$745,MATCH(59,Data!$B$2:$B$745,0))="","",INDEX(Data!$N$2:$N$745,MATCH(59,Data!$B$2:$B$745,0))),"")) | I73: =IF(B73="","",IFERROR(IF(INDEX(Data!$O$2:$O$745,MATCH(59,Data!$B$2:$B$745,0))="","",INDEX(Data!$O$2:$O$745,MATCH(59,Data!$B$2:$B$745,0))),"")) | J73: =IF(B73="","",IFERROR(IF(INDEX(Data!$P$2:$P$745,MATCH(59,Data!$B$2:$B$745,0))="","",INDEX(Data!$P$2:$P$745,MATCH(59,Data!$B$2:$B$745,0))),"")) | K73: =IF(B73="","",IFERROR(IF(INDEX(Data!$R$2:$R$745,MATCH(59,Data!$B$2:$B$745,0))="","",INDEX(Data!$R$2:$R$745,MATCH(59,Data!$B$2:$B$745,0))),"")) | L73: =IF(B73="","",IFERROR(IF(INDEX(Data!$S$2:$S$745,MATCH(59,Data!$B$2:$B$745,0))="","",INDEX(Data!$S$2:$S$745,MATCH(59,Data!$B$2:$B$745,0))),"")) | M73: =IF(B73="","",IFERROR(IF(INDEX(Data!$T$2:$T$745,MATCH(59,Data!$B$2:$B$745,0))="","",INDEX(Data!$T$2:$T$745,MATCH(59,Data!$B$2:$B$745,0))),"")) | N73: =IF(B73="","",IFERROR(IF(INDEX(Data!$U$2:$U$745,MATCH(59,Data!$B$2:$B$745,0))="","",INDEX(Data!$U$2:$U$745,MATCH(59,Data!$B$2:$B$745,0))),"")) | O73: =IF(B73="","",IFERROR(IF(INDEX(Data!$V$2:$V$745,MATCH(59,Data!$B$2:$B$745,0))="","",INDEX(Data!$V$2:$V$745,MATCH(59,Data!$B$2:$B$745,0))),"")) | P73: =IF(B73="","",IFERROR(IF(INDEX(Data!$M$2:$M$745,MATCH(59,Data!$B$2:$B$745,0))="","",INDEX(Data!$M$2:$M$745,MATCH(59,Data!$B$2:$B$745,0))),"")) | Q73: =IF(B73="","",IFERROR(IF(INDEX(Data!$AD$2:$AD$745,MATCH(59,Data!$B$2:$B$745,0))="","",INDEX(Data!$AD$2:$AD$745,MATCH(59,Data!$B$2:$B$745,0))),"")) | R73: =IF(B73="","",IFERROR(IF(INDEX(Data!$L$2:$L$745,MATCH(59,Data!$B$2:$B$745,0))="","",INDEX(Data!$L$2:$L$745,MATCH(59,Data!$B$2:$B$745,0))),"")) | AB73: Fafua
B74: =IF(60<=COUNTIF(Data!$A$2:$A$745,TRUE),60,"") | C74: =IF(B74="","",IFERROR(_xlfn.IMAGE(IFERROR(IF(INDEX(Data!$J$2:$J$745,MATCH(60,Data!$B$2:$B$745,0))="","",INDEX(Data!$J$2:$J$745,MATCH(60,Data!$B$2:$B$745,0))),"")),"IMAGE COMING SOON")) | D74: =IF(B74="","",IFERROR(IF(INDEX(Data!$G$2:$G$745,MATCH(60,Data!$B$2:$B$745,0))="","",INDEX(Data!$G$2:$G$745,MATCH(60,Data!$B$2:$B$745,0))),"")&CHAR(10)&IFERROR(IF(INDEX(Data!$H$2:$H$745,MATCH(60,Data!$B$2:$B$745,0))="","",INDEX(Data!$H$2:$H$745,MATCH(60,Data!$B$2:$B$745,0))),"")) | E74: =IF(B74="","",IFERROR(IF(INDEX(Data!$I$2:$I$745,MATCH(60,Data!$B$2:$B$745,0))="","",INDEX(Data!$I$2:$I$745,MATCH(60,Data!$B$2:$B$745,0))),"")) | F74: =IF(B74="","",IFERROR(IF(INDEX(Data!$AJ$2:$AJ$745,MATCH(60,Data!$B$2:$B$745,0))="","",INDEX(Data!$AJ$2:$AJ$745,MATCH(60,Data!$B$2:$B$745,0))),"")) | G74: =IF(B74="","",TRIM(IFERROR(IF(INDEX(Data!$AF$2:$AF$745,MATCH(60,Data!$B$2:$B$745,0))="","",INDEX(Data!$AF$2:$AF$745,MATCH(60,Data!$B$2:$B$745,0))),"")&" "&IFERROR(IF(INDEX(Data!$AG$2:$AG$745,MATCH(60,Data!$B$2:$B$745,0))="","",INDEX(Data!$AG$2:$AG$745,MATCH(60,Data!$B$2:$B$745,0))),""))) | H74: =IF(B74="","",IFERROR(IF(INDEX(Data!$N$2:$N$745,MATCH(60,Data!$B$2:$B$745,0))="","",INDEX(Data!$N$2:$N$745,MATCH(60,Data!$B$2:$B$745,0))),"")) | I74: =IF(B74="","",IFERROR(IF(INDEX(Data!$O$2:$O$745,MATCH(60,Data!$B$2:$B$745,0))="","",INDEX(Data!$O$2:$O$745,MATCH(60,Data!$B$2:$B$745,0))),"")) | J74: =IF(B74="","",IFERROR(IF(INDEX(Data!$P$2:$P$745,MATCH(60,Data!$B$2:$B$745,0))="","",INDEX(Data!$P$2:$P$745,MATCH(60,Data!$B$2:$B$745,0))),"")) | K74: =IF(B74="","",IFERROR(IF(INDEX(Data!$R$2:$R$745,MATCH(60,Data!$B$2:$B$745,0))="","",INDEX(Data!$R$2:$R$745,MATCH(60,Data!$B$2:$B$745,0))),"")) | L74: =IF(B74="","",IFERROR(IF(INDEX(Data!$S$2:$S$745,MATCH(60,Data!$B$2:$B$745,0))="","",INDEX(Data!$S$2:$S$745,MATCH(60,Data!$B$2:$B$745,0))),"")) | M74: =IF(B74="","",IFERROR(IF(INDEX(Data!$T$2:$T$745,MATCH(60,Data!$B$2:$B$745,0))="","",INDEX(Data!$T$2:$T$745,MATCH(60,Data!$B$2:$B$745,0))),"")) | N74: =IF(B74="","",IFERROR(IF(INDEX(Data!$U$2:$U$745,MATCH(60,Data!$B$2:$B$745,0))="","",INDEX(Data!$U$2:$U$745,MATCH(60,Data!$B$2:$B$745,0))),"")) | O74: =IF(B74="","",IFERROR(IF(INDEX(Data!$V$2:$V$745,MATCH(60,Data!$B$2:$B$745,0))="","",INDEX(Data!$V$2:$V$745,MATCH(60,Data!$B$2:$B$745,0))),"")) | P74: =IF(B74="","",IFERROR(IF(INDEX(Data!$M$2:$M$745,MATCH(60,Data!$B$2:$B$745,0))="","",INDEX(Data!$M$2:$M$745,MATCH(60,Data!$B$2:$B$745,0))),"")) | Q74: =IF(B74="","",IFERROR(IF(INDEX(Data!$AD$2:$AD$745,MATCH(60,Data!$B$2:$B$745,0))="","",INDEX(Data!$AD$2:$AD$745,MATCH(60,Data!$B$2:$B$745,0))),"")) | R74: =IF(B74="","",IFERROR(IF(INDEX(Data!$L$2:$L$745,MATCH(60,Data!$B$2:$B$745,0))="","",INDEX(Data!$L$2:$L$745,MATCH(60,Data!$B$2:$B$745,0))),"")) | AB74: FengXinZi Store
B75: =IF(61<=COUNTIF(Data!$A$2:$A$745,TRUE),61,"") | C75: =IF(B75="","",IFERROR(_xlfn.IMAGE(IFERROR(IF(INDEX(Data!$J$2:$J$745,MATCH(61,Data!$B$2:$B$745,0))="","",INDEX(Data!$J$2:$J$745,MATCH(61,Data!$B$2:$B$745,0))),"")),"IMAGE COMING SOON")) | D75: =IF(B75="","",IFERROR(IF(INDEX(Data!$G$2:$G$745,MATCH(61,Data!$B$2:$B$745,0))="","",INDEX(Data!$G$2:$G$745,MATCH(61,Data!$B$2:$B$745,0))),"")&CHAR(10)&IFERROR(IF(INDEX(Data!$H$2:$H$745,MATCH(61,Data!$B$2:$B$745,0))="","",INDEX(Data!$H$2:$H$745,MATCH(61,Data!$B$2:$B$745,0))),"")) | E75: =IF(B75="","",IFERROR(IF(INDEX(Data!$I$2:$I$745,MATCH(61,Data!$B$2:$B$745,0))="","",INDEX(Data!$I$2:$I$745,MATCH(61,Data!$B$2:$B$745,0))),"")) | F75: =IF(B75="","",IFERROR(IF(INDEX(Data!$AJ$2:$AJ$745,MATCH(61,Data!$B$2:$B$745,0))="","",INDEX(Data!$AJ$2:$AJ$745,MATCH(61,Data!$B$2:$B$745,0))),"")) | G75: =IF(B75="","",TRIM(IFERROR(IF(INDEX(Data!$AF$2:$AF$745,MATCH(61,Data!$B$2:$B$745,0))="","",INDEX(Data!$AF$2:$AF$745,MATCH(61,Data!$B$2:$B$745,0))),"")&" "&IFERROR(IF(INDEX(Data!$AG$2:$AG$745,MATCH(61,Data!$B$2:$B$745,0))="","",INDEX(Data!$AG$2:$AG$745,MATCH(61,Data!$B$2:$B$745,0))),""))) | H75: =IF(B75="","",IFERROR(IF(INDEX(Data!$N$2:$N$745,MATCH(61,Data!$B$2:$B$745,0))="","",INDEX(Data!$N$2:$N$745,MATCH(61,Data!$B$2:$B$745,0))),"")) | I75: =IF(B75="","",IFERROR(IF(INDEX(Data!$O$2:$O$745,MATCH(61,Data!$B$2:$B$745,0))="","",INDEX(Data!$O$2:$O$745,MATCH(61,Data!$B$2:$B$745,0))),"")) | J75: =IF(B75="","",IFERROR(IF(INDEX(Data!$P$2:$P$745,MATCH(61,Data!$B$2:$B$745,0))="","",INDEX(Data!$P$2:$P$745,MATCH(61,Data!$B$2:$B$745,0))),"")) | K75: =IF(B75="","",IFERROR(IF(INDEX(Data!$R$2:$R$745,MATCH(61,Data!$B$2:$B$745,0))="","",INDEX(Data!$R$2:$R$745,MATCH(61,Data!$B$2:$B$745,0))),"")) | L75: =IF(B75="","",IFERROR(IF(INDEX(Data!$S$2:$S$745,MATCH(61,Data!$B$2:$B$745,0))="","",INDEX(Data!$S$2:$S$745,MATCH(61,Data!$B$2:$B$745,0))),"")) | M75: =IF(B75="","",IFERROR(IF(INDEX(Data!$T$2:$T$745,MATCH(61,Data!$B$2:$B$745,0))="","",INDEX(Data!$T$2:$T$745,MATCH(61,Data!$B$2:$B$745,0))),"")) | N75: =IF(B75="","",IFERROR(IF(INDEX(Data!$U$2:$U$745,MATCH(61,Data!$B$2:$B$745,0))="","",INDEX(Data!$U$2:$U$745,MATCH(61,Data!$B$2:$B$745,0))),"")) | O75: =IF(B75="","",IFERROR(IF(INDEX(Data!$V$2:$V$745,MATCH(61,Data!$B$2:$B$745,0))="","",INDEX(Data!$V$2:$V$745,MATCH(61,Data!$B$2:$B$745,0))),"")) | P75: =IF(B75="","",IFERROR(IF(INDEX(Data!$M$2:$M$745,MATCH(61,Data!$B$2:$B$745,0))="","",INDEX(Data!$M$2:$M$745,MATCH(61,Data!$B$2:$B$745,0))),"")) | Q75: =IF(B75="","",IFERROR(IF(INDEX(Data!$AD$2:$AD$745,MATCH(61,Data!$B$2:$B$745,0))="","",INDEX(Data!$AD$2:$AD$745,MATCH(61,Data!$B$2:$B$745,0))),"")) | R75: =IF(B75="","",IFERROR(IF(INDEX(Data!$L$2:$L$745,MATCH(61,Data!$B$2:$B$745,0))="","",INDEX(Data!$L$2:$L$745,MATCH(61,Data!$B$2:$B$745,0))),"")) | AB75: FESHKA
B76: =IF(62<=COUNTIF(Data!$A$2:$A$745,TRUE),62,"") | C76: =IF(B76="","",IFERROR(_xlfn.IMAGE(IFERROR(IF(INDEX(Data!$J$2:$J$745,MATCH(62,Data!$B$2:$B$745,0))="","",INDEX(Data!$J$2:$J$745,MATCH(62,Data!$B$2:$B$745,0))),"")),"IMAGE COMING SOON")) | D76: =IF(B76="","",IFERROR(IF(INDEX(Data!$G$2:$G$745,MATCH(62,Data!$B$2:$B$745,0))="","",INDEX(Data!$G$2:$G$745,MATCH(62,Data!$B$2:$B$745,0))),"")&CHAR(10)&IFERROR(IF(INDEX(Data!$H$2:$H$745,MATCH(62,Data!$B$2:$B$745,0))="","",INDEX(Data!$H$2:$H$745,MATCH(62,Data!$B$2:$B$745,0))),"")) | E76: =IF(B76="","",IFERROR(IF(INDEX(Data!$I$2:$I$745,MATCH(62,Data!$B$2:$B$745,0))="","",INDEX(Data!$I$2:$I$745,MATCH(62,Data!$B$2:$B$745,0))),"")) | F76: =IF(B76="","",IFERROR(IF(INDEX(Data!$AJ$2:$AJ$745,MATCH(62,Data!$B$2:$B$745,0))="","",INDEX(Data!$AJ$2:$AJ$745,MATCH(62,Data!$B$2:$B$745,0))),"")) | G76: =IF(B76="","",TRIM(IFERROR(IF(INDEX(Data!$AF$2:$AF$745,MATCH(62,Data!$B$2:$B$745,0))="","",INDEX(Data!$AF$2:$AF$745,MATCH(62,Data!$B$2:$B$745,0))),"")&" "&IFERROR(IF(INDEX(Data!$AG$2:$AG$745,MATCH(62,Data!$B$2:$B$745,0))="","",INDEX(Data!$AG$2:$AG$745,MATCH(62,Data!$B$2:$B$745,0))),""))) | H76: =IF(B76="","",IFERROR(IF(INDEX(Data!$N$2:$N$745,MATCH(62,Data!$B$2:$B$745,0))="","",INDEX(Data!$N$2:$N$745,MATCH(62,Data!$B$2:$B$745,0))),"")) | I76: =IF(B76="","",IFERROR(IF(INDEX(Data!$O$2:$O$745,MATCH(62,Data!$B$2:$B$745,0))="","",INDEX(Data!$O$2:$O$745,MATCH(62,Data!$B$2:$B$745,0))),"")) | J76: =IF(B76="","",IFERROR(IF(INDEX(Data!$P$2:$P$745,MATCH(62,Data!$B$2:$B$745,0))="","",INDEX(Data!$P$2:$P$745,MATCH(62,Data!$B$2:$B$745,0))),"")) | K76: =IF(B76="","",IFERROR(IF(INDEX(Data!$R$2:$R$745,MATCH(62,Data!$B$2:$B$745,0))="","",INDEX(Data!$R$2:$R$745,MATCH(62,Data!$B$2:$B$745,0))),"")) | L76: =IF(B76="","",IFERROR(IF(INDEX(Data!$S$2:$S$745,MATCH(62,Data!$B$2:$B$745,0))="","",INDEX(Data!$S$2:$S$745,MATCH(62,Data!$B$2:$B$745,0))),"")) | M76: =IF(B76="","",IFERROR(IF(INDEX(Data!$T$2:$T$745,MATCH(62,Data!$B$2:$B$745,0))="","",INDEX(Data!$T$2:$T$745,MATCH(62,Data!$B$2:$B$745,0))),"")) | N76: =IF(B76="","",IFERROR(IF(INDEX(Data!$U$2:$U$745,MATCH(62,Data!$B$2:$B$745,0))="","",INDEX(Data!$U$2:$U$745,MATCH(62,Data!$B$2:$B$745,0))),"")) | O76: =IF(B76="","",IFERROR(IF(INDEX(Data!$V$2:$V$745,MATCH(62,Data!$B$2:$B$745,0))="","",INDEX(Data!$V$2:$V$745,MATCH(62,Data!$B$2:$B$745,0))),"")) | P76: =IF(B76="","",IFERROR(IF(INDEX(Data!$M$2:$M$745,MATCH(62,Data!$B$2:$B$745,0))="","",INDEX(Data!$M$2:$M$745,MATCH(62,Data!$B$2:$B$745,0))),"")) | Q76: =IF(B76="","",IFERROR(IF(INDEX(Data!$AD$2:$AD$745,MATCH(62,Data!$B$2:$B$745,0))="","",INDEX(Data!$AD$2:$AD$745,MATCH(62,Data!$B$2:$B$745,0))),"")) | R76: =IF(B76="","",IFERROR(IF(INDEX(Data!$L$2:$L$745,MATCH(62,Data!$B$2:$B$745,0))="","",INDEX(Data!$L$2:$L$745,MATCH(62,Data!$B$2:$B$745,0))),"")) | AB76: Fishers Finery
B77: =IF(63<=COUNTIF(Data!$A$2:$A$745,TRUE),63,"") | C77: =IF(B77="","",IFERROR(_xlfn.IMAGE(IFERROR(IF(INDEX(Data!$J$2:$J$745,MATCH(63,Data!$B$2:$B$745,0))="","",INDEX(Data!$J$2:$J$745,MATCH(63,Data!$B$2:$B$745,0))),"")),"IMAGE COMING SOON")) | D77: =IF(B77="","",IFERROR(IF(INDEX(Data!$G$2:$G$745,MATCH(63,Data!$B$2:$B$745,0))="","",INDEX(Data!$G$2:$G$745,MATCH(63,Data!$B$2:$B$745,0))),"")&CHAR(10)&IFERROR(IF(INDEX(Data!$H$2:$H$745,MATCH(63,Data!$B$2:$B$745,0))="","",INDEX(Data!$H$2:$H$745,MATCH(63,Data!$B$2:$B$745,0))),"")) | E77: =IF(B77="","",IFERROR(IF(INDEX(Data!$I$2:$I$745,MATCH(63,Data!$B$2:$B$745,0))="","",INDEX(Data!$I$2:$I$745,MATCH(63,Data!$B$2:$B$745,0))),"")) | F77: =IF(B77="","",IFERROR(IF(INDEX(Data!$AJ$2:$AJ$745,MATCH(63,Data!$B$2:$B$745,0))="","",INDEX(Data!$AJ$2:$AJ$745,MATCH(63,Data!$B$2:$B$745,0))),"")) | G77: =IF(B77="","",TRIM(IFERROR(IF(INDEX(Data!$AF$2:$AF$745,MATCH(63,Data!$B$2:$B$745,0))="","",INDEX(Data!$AF$2:$AF$745,MATCH(63,Data!$B$2:$B$745,0))),"")&" "&IFERROR(IF(INDEX(Data!$AG$2:$AG$745,MATCH(63,Data!$B$2:$B$745,0))="","",INDEX(Data!$AG$2:$AG$745,MATCH(63,Data!$B$2:$B$745,0))),""))) | H77: =IF(B77="","",IFERROR(IF(INDEX(Data!$N$2:$N$745,MATCH(63,Data!$B$2:$B$745,0))="","",INDEX(Data!$N$2:$N$745,MATCH(63,Data!$B$2:$B$745,0))),"")) | I77: =IF(B77="","",IFERROR(IF(INDEX(Data!$O$2:$O$745,MATCH(63,Data!$B$2:$B$745,0))="","",INDEX(Data!$O$2:$O$745,MATCH(63,Data!$B$2:$B$745,0))),"")) | J77: =IF(B77="","",IFERROR(IF(INDEX(Data!$P$2:$P$745,MATCH(63,Data!$B$2:$B$745,0))="","",INDEX(Data!$P$2:$P$745,MATCH(63,Data!$B$2:$B$745,0))),"")) | K77: =IF(B77="","",IFERROR(IF(INDEX(Data!$R$2:$R$745,MATCH(63,Data!$B$2:$B$745,0))="","",INDEX(Data!$R$2:$R$745,MATCH(63,Data!$B$2:$B$745,0))),"")) | L77: =IF(B77="","",IFERROR(IF(INDEX(Data!$S$2:$S$745,MATCH(63,Data!$B$2:$B$745,0))="","",INDEX(Data!$S$2:$S$745,MATCH(63,Data!$B$2:$B$745,0))),"")) | M77: =IF(B77="","",IFERROR(IF(INDEX(Data!$T$2:$T$745,MATCH(63,Data!$B$2:$B$745,0))="","",INDEX(Data!$T$2:$T$745,MATCH(63,Data!$B$2:$B$745,0))),"")) | N77: =IF(B77="","",IFERROR(IF(INDEX(Data!$U$2:$U$745,MATCH(63,Data!$B$2:$B$745,0))="","",INDEX(Data!$U$2:$U$745,MATCH(63,Data!$B$2:$B$745,0))),"")) | O77: =IF(B77="","",IFERROR(IF(INDEX(Data!$V$2:$V$745,MATCH(63,Data!$B$2:$B$745,0))="","",INDEX(Data!$V$2:$V$745,MATCH(63,Data!$B$2:$B$745,0))),"")) | P77: =IF(B77="","",IFERROR(IF(INDEX(Data!$M$2:$M$745,MATCH(63,Data!$B$2:$B$745,0))="","",INDEX(Data!$M$2:$M$745,MATCH(63,Data!$B$2:$B$745,0))),"")) | Q77: =IF(B77="","",IFERROR(IF(INDEX(Data!$AD$2:$AD$745,MATCH(63,Data!$B$2:$B$745,0))="","",INDEX(Data!$AD$2:$AD$745,MATCH(63,Data!$B$2:$B$745,0))),"")) | R77: =IF(B77="","",IFERROR(IF(INDEX(Data!$L$2:$L$745,MATCH(63,Data!$B$2:$B$745,0))="","",INDEX(Data!$L$2:$L$745,MATCH(63,Data!$B$2:$B$745,0))),"")) | AB77: Fittia
B78: =IF(64<=COUNTIF(Data!$A$2:$A$745,TRUE),64,"") | C78: =IF(B78="","",IFERROR(_xlfn.IMAGE(IFERROR(IF(INDEX(Data!$J$2:$J$745,MATCH(64,Data!$B$2:$B$745,0))="","",INDEX(Data!$J$2:$J$745,MATCH(64,Data!$B$2:$B$745,0))),"")),"IMAGE COMING SOON")) | D78: =IF(B78="","",IFERROR(IF(INDEX(Data!$G$2:$G$745,MATCH(64,Data!$B$2:$B$745,0))="","",INDEX(Data!$G$2:$G$745,MATCH(64,Data!$B$2:$B$745,0))),"")&CHAR(10)&IFERROR(IF(INDEX(Data!$H$2:$H$745,MATCH(64,Data!$B$2:$B$745,0))="","",INDEX(Data!$H$2:$H$745,MATCH(64,Data!$B$2:$B$745,0))),"")) | E78: =IF(B78="","",IFERROR(IF(INDEX(Data!$I$2:$I$745,MATCH(64,Data!$B$2:$B$745,0))="","",INDEX(Data!$I$2:$I$745,MATCH(64,Data!$B$2:$B$745,0))),"")) | F78: =IF(B78="","",IFERROR(IF(INDEX(Data!$AJ$2:$AJ$745,MATCH(64,Data!$B$2:$B$745,0))="","",INDEX(Data!$AJ$2:$AJ$745,MATCH(64,Data!$B$2:$B$745,0))),"")) | G78: =IF(B78="","",TRIM(IFERROR(IF(INDEX(Data!$AF$2:$AF$745,MATCH(64,Data!$B$2:$B$745,0))="","",INDEX(Data!$AF$2:$AF$745,MATCH(64,Data!$B$2:$B$745,0))),"")&" "&IFERROR(IF(INDEX(Data!$AG$2:$AG$745,MATCH(64,Data!$B$2:$B$745,0))="","",INDEX(Data!$AG$2:$AG$745,MATCH(64,Data!$B$2:$B$745,0))),""))) | H78: =IF(B78="","",IFERROR(IF(INDEX(Data!$N$2:$N$745,MATCH(64,Data!$B$2:$B$745,0))="","",INDEX(Data!$N$2:$N$745,MATCH(64,Data!$B$2:$B$745,0))),"")) | I78: =IF(B78="","",IFERROR(IF(INDEX(Data!$O$2:$O$745,MATCH(64,Data!$B$2:$B$745,0))="","",INDEX(Data!$O$2:$O$745,MATCH(64,Data!$B$2:$B$745,0))),"")) | J78: =IF(B78="","",IFERROR(IF(INDEX(Data!$P$2:$P$745,MATCH(64,Data!$B$2:$B$745,0))="","",INDEX(Data!$P$2:$P$745,MATCH(64,Data!$B$2:$B$745,0))),"")) | K78: =IF(B78="","",IFERROR(IF(INDEX(Data!$R$2:$R$745,MATCH(64,Data!$B$2:$B$745,0))="","",INDEX(Data!$R$2:$R$745,MATCH(64,Data!$B$2:$B$745,0))),"")) | L78: =IF(B78="","",IFERROR(IF(INDEX(Data!$S$2:$S$745,MATCH(64,Data!$B$2:$B$745,0))="","",INDEX(Data!$S$2:$S$745,MATCH(64,Data!$B$2:$B$745,0))),"")) | M78: =IF(B78="","",IFERROR(IF(INDEX(Data!$T$2:$T$745,MATCH(64,Data!$B$2:$B$745,0))="","",INDEX(Data!$T$2:$T$745,MATCH(64,Data!$B$2:$B$745,0))),"")) | N78: =IF(B78="","",IFERROR(IF(INDEX(Data!$U$2:$U$745,MATCH(64,Data!$B$2:$B$745,0))="","",INDEX(Data!$U$2:$U$745,MATCH(64,Data!$B$2:$B$745,0))),"")) | O78: =IF(B78="","",IFERROR(IF(INDEX(Data!$V$2:$V$745,MATCH(64,Data!$B$2:$B$745,0))="","",INDEX(Data!$V$2:$V$745,MATCH(64,Data!$B$2:$B$745,0))),"")) | P78: =IF(B78="","",IFERROR(IF(INDEX(Data!$M$2:$M$745,MATCH(64,Data!$B$2:$B$745,0))="","",INDEX(Data!$M$2:$M$745,MATCH(64,Data!$B$2:$B$745,0))),"")) | Q78: =IF(B78="","",IFERROR(IF(INDEX(Data!$AD$2:$AD$745,MATCH(64,Data!$B$2:$B$745,0))="","",INDEX(Data!$AD$2:$AD$745,MATCH(64,Data!$B$2:$B$745,0))),"")) | R78: =IF(B78="","",IFERROR(IF(INDEX(Data!$L$2:$L$745,MATCH(64,Data!$B$2:$B$745,0))="","",INDEX(Data!$L$2:$L$745,MATCH(64,Data!$B$2:$B$745,0))),"")) | AB78: FLCA
B79: =IF(65<=COUNTIF(Data!$A$2:$A$745,TRUE),65,"") | C79: =IF(B79="","",IFERROR(_xlfn.IMAGE(IFERROR(IF(INDEX(Data!$J$2:$J$745,MATCH(65,Data!$B$2:$B$745,0))="","",INDEX(Data!$J$2:$J$745,MATCH(65,Data!$B$2:$B$745,0))),"")),"IMAGE COMING SOON")) | D79: =IF(B79="","",IFERROR(IF(INDEX(Data!$G$2:$G$745,MATCH(65,Data!$B$2:$B$745,0))="","",INDEX(Data!$G$2:$G$745,MATCH(65,Data!$B$2:$B$745,0))),"")&CHAR(10)&IFERROR(IF(INDEX(Data!$H$2:$H$745,MATCH(65,Data!$B$2:$B$745,0))="","",INDEX(Data!$H$2:$H$745,MATCH(65,Data!$B$2:$B$745,0))),"")) | E79: =IF(B79="","",IFERROR(IF(INDEX(Data!$I$2:$I$745,MATCH(65,Data!$B$2:$B$745,0))="","",INDEX(Data!$I$2:$I$745,MATCH(65,Data!$B$2:$B$745,0))),"")) | F79: =IF(B79="","",IFERROR(IF(INDEX(Data!$AJ$2:$AJ$745,MATCH(65,Data!$B$2:$B$745,0))="","",INDEX(Data!$AJ$2:$AJ$745,MATCH(65,Data!$B$2:$B$745,0))),"")) | G79: =IF(B79="","",TRIM(IFERROR(IF(INDEX(Data!$AF$2:$AF$745,MATCH(65,Data!$B$2:$B$745,0))="","",INDEX(Data!$AF$2:$AF$745,MATCH(65,Data!$B$2:$B$745,0))),"")&" "&IFERROR(IF(INDEX(Data!$AG$2:$AG$745,MATCH(65,Data!$B$2:$B$745,0))="","",INDEX(Data!$AG$2:$AG$745,MATCH(65,Data!$B$2:$B$745,0))),""))) | H79: =IF(B79="","",IFERROR(IF(INDEX(Data!$N$2:$N$745,MATCH(65,Data!$B$2:$B$745,0))="","",INDEX(Data!$N$2:$N$745,MATCH(65,Data!$B$2:$B$745,0))),"")) | I79: =IF(B79="","",IFERROR(IF(INDEX(Data!$O$2:$O$745,MATCH(65,Data!$B$2:$B$745,0))="","",INDEX(Data!$O$2:$O$745,MATCH(65,Data!$B$2:$B$745,0))),"")) | J79: =IF(B79="","",IFERROR(IF(INDEX(Data!$P$2:$P$745,MATCH(65,Data!$B$2:$B$745,0))="","",INDEX(Data!$P$2:$P$745,MATCH(65,Data!$B$2:$B$745,0))),"")) | K79: =IF(B79="","",IFERROR(IF(INDEX(Data!$R$2:$R$745,MATCH(65,Data!$B$2:$B$745,0))="","",INDEX(Data!$R$2:$R$745,MATCH(65,Data!$B$2:$B$745,0))),"")) | L79: =IF(B79="","",IFERROR(IF(INDEX(Data!$S$2:$S$745,MATCH(65,Data!$B$2:$B$745,0))="","",INDEX(Data!$S$2:$S$745,MATCH(65,Data!$B$2:$B$745,0))),"")) | M79: =IF(B79="","",IFERROR(IF(INDEX(Data!$T$2:$T$745,MATCH(65,Data!$B$2:$B$745,0))="","",INDEX(Data!$T$2:$T$745,MATCH(65,Data!$B$2:$B$745,0))),"")) | N79: =IF(B79="","",IFERROR(IF(INDEX(Data!$U$2:$U$745,MATCH(65,Data!$B$2:$B$745,0))="","",INDEX(Data!$U$2:$U$745,MATCH(65,Data!$B$2:$B$745,0))),"")) | O79: =IF(B79="","",IFERROR(IF(INDEX(Data!$V$2:$V$745,MATCH(65,Data!$B$2:$B$745,0))="","",INDEX(Data!$V$2:$V$745,MATCH(65,Data!$B$2:$B$745,0))),"")) | P79: =IF(B79="","",IFERROR(IF(INDEX(Data!$M$2:$M$745,MATCH(65,Data!$B$2:$B$745,0))="","",INDEX(Data!$M$2:$M$745,MATCH(65,Data!$B$2:$B$745,0))),"")) | Q79: =IF(B79="","",IFERROR(IF(INDEX(Data!$AD$2:$AD$745,MATCH(65,Data!$B$2:$B$745,0))="","",INDEX(Data!$AD$2:$AD$745,MATCH(65,Data!$B$2:$B$745,0))),"")) | R79: =IF(B79="","",IFERROR(IF(INDEX(Data!$L$2:$L$745,MATCH(65,Data!$B$2:$B$745,0))="","",INDEX(Data!$L$2:$L$745,MATCH(65,Data!$B$2:$B$745,0))),"")) | AB79: flowtorely
B80: =IF(66<=COUNTIF(Data!$A$2:$A$745,TRUE),66,"") | C80: =IF(B80="","",IFERROR(_xlfn.IMAGE(IFERROR(IF(INDEX(Data!$J$2:$J$745,MATCH(66,Data!$B$2:$B$745,0))="","",INDEX(Data!$J$2:$J$745,MATCH(66,Data!$B$2:$B$745,0))),"")),"IMAGE COMING SOON")) | D80: =IF(B80="","",IFERROR(IF(INDEX(Data!$G$2:$G$745,MATCH(66,Data!$B$2:$B$745,0))="","",INDEX(Data!$G$2:$G$745,MATCH(66,Data!$B$2:$B$745,0))),"")&CHAR(10)&IFERROR(IF(INDEX(Data!$H$2:$H$745,MATCH(66,Data!$B$2:$B$745,0))="","",INDEX(Data!$H$2:$H$745,MATCH(66,Data!$B$2:$B$745,0))),"")) | E80: =IF(B80="","",IFERROR(IF(INDEX(Data!$I$2:$I$745,MATCH(66,Data!$B$2:$B$745,0))="","",INDEX(Data!$I$2:$I$745,MATCH(66,Data!$B$2:$B$745,0))),"")) | F80: =IF(B80="","",IFERROR(IF(INDEX(Data!$AJ$2:$AJ$745,MATCH(66,Data!$B$2:$B$745,0))="","",INDEX(Data!$AJ$2:$AJ$745,MATCH(66,Data!$B$2:$B$745,0))),"")) | G80: =IF(B80="","",TRIM(IFERROR(IF(INDEX(Data!$AF$2:$AF$745,MATCH(66,Data!$B$2:$B$745,0))="","",INDEX(Data!$AF$2:$AF$745,MATCH(66,Data!$B$2:$B$745,0))),"")&" "&IFERROR(IF(INDEX(Data!$AG$2:$AG$745,MATCH(66,Data!$B$2:$B$745,0))="","",INDEX(Data!$AG$2:$AG$745,MATCH(66,Data!$B$2:$B$745,0))),""))) | H80: =IF(B80="","",IFERROR(IF(INDEX(Data!$N$2:$N$745,MATCH(66,Data!$B$2:$B$745,0))="","",INDEX(Data!$N$2:$N$745,MATCH(66,Data!$B$2:$B$745,0))),"")) | I80: =IF(B80="","",IFERROR(IF(INDEX(Data!$O$2:$O$745,MATCH(66,Data!$B$2:$B$745,0))="","",INDEX(Data!$O$2:$O$745,MATCH(66,Data!$B$2:$B$745,0))),"")) | J80: =IF(B80="","",IFERROR(IF(INDEX(Data!$P$2:$P$745,MATCH(66,Data!$B$2:$B$745,0))="","",INDEX(Data!$P$2:$P$745,MATCH(66,Data!$B$2:$B$745,0))),"")) | K80: =IF(B80="","",IFERROR(IF(INDEX(Data!$R$2:$R$745,MATCH(66,Data!$B$2:$B$745,0))="","",INDEX(Data!$R$2:$R$745,MATCH(66,Data!$B$2:$B$745,0))),"")) | L80: =IF(B80="","",IFERROR(IF(INDEX(Data!$S$2:$S$745,MATCH(66,Data!$B$2:$B$745,0))="","",INDEX(Data!$S$2:$S$745,MATCH(66,Data!$B$2:$B$745,0))),"")) | M80: =IF(B80="","",IFERROR(IF(INDEX(Data!$T$2:$T$745,MATCH(66,Data!$B$2:$B$745,0))="","",INDEX(Data!$T$2:$T$745,MATCH(66,Data!$B$2:$B$745,0))),"")) | N80: =IF(B80="","",IFERROR(IF(INDEX(Data!$U$2:$U$745,MATCH(66,Data!$B$2:$B$745,0))="","",INDEX(Data!$U$2:$U$745,MATCH(66,Data!$B$2:$B$745,0))),"")) | O80: =IF(B80="","",IFERROR(IF(INDEX(Data!$V$2:$V$745,MATCH(66,Data!$B$2:$B$745,0))="","",INDEX(Data!$V$2:$V$745,MATCH(66,Data!$B$2:$B$745,0))),"")) | P80: =IF(B80="","",IFERROR(IF(INDEX(Data!$M$2:$M$745,MATCH(66,Data!$B$2:$B$745,0))="","",INDEX(Data!$M$2:$M$745,MATCH(66,Data!$B$2:$B$745,0))),"")) | Q80: =IF(B80="","",IFERROR(IF(INDEX(Data!$AD$2:$AD$745,MATCH(66,Data!$B$2:$B$745,0))="","",INDEX(Data!$AD$2:$AD$745,MATCH(66,Data!$B$2:$B$745,0))),"")) | R80: =IF(B80="","",IFERROR(IF(INDEX(Data!$L$2:$L$745,MATCH(66,Data!$B$2:$B$745,0))="","",INDEX(Data!$L$2:$L$745,MATCH(66,Data!$B$2:$B$745,0))),"")) | AB80: FLYMME
B81: =IF(67<=COUNTIF(Data!$A$2:$A$745,TRUE),67,"") | C81: =IF(B81="","",IFERROR(_xlfn.IMAGE(IFERROR(IF(INDEX(Data!$J$2:$J$745,MATCH(67,Data!$B$2:$B$745,0))="","",INDEX(Data!$J$2:$J$745,MATCH(67,Data!$B$2:$B$745,0))),"")),"IMAGE COMING SOON")) | D81: =IF(B81="","",IFERROR(IF(INDEX(Data!$G$2:$G$745,MATCH(67,Data!$B$2:$B$745,0))="","",INDEX(Data!$G$2:$G$745,MATCH(67,Data!$B$2:$B$745,0))),"")&CHAR(10)&IFERROR(IF(INDEX(Data!$H$2:$H$745,MATCH(67,Data!$B$2:$B$745,0))="","",INDEX(Data!$H$2:$H$745,MATCH(67,Data!$B$2:$B$745,0))),"")) | E81: =IF(B81="","",IFERROR(IF(INDEX(Data!$I$2:$I$745,MATCH(67,Data!$B$2:$B$745,0))="","",INDEX(Data!$I$2:$I$745,MATCH(67,Data!$B$2:$B$745,0))),"")) | F81: =IF(B81="","",IFERROR(IF(INDEX(Data!$AJ$2:$AJ$745,MATCH(67,Data!$B$2:$B$745,0))="","",INDEX(Data!$AJ$2:$AJ$745,MATCH(67,Data!$B$2:$B$745,0))),"")) | G81: =IF(B81="","",TRIM(IFERROR(IF(INDEX(Data!$AF$2:$AF$745,MATCH(67,Data!$B$2:$B$745,0))="","",INDEX(Data!$AF$2:$AF$745,MATCH(67,Data!$B$2:$B$745,0))),"")&" "&IFERROR(IF(INDEX(Data!$AG$2:$AG$745,MATCH(67,Data!$B$2:$B$745,0))="","",INDEX(Data!$AG$2:$AG$745,MATCH(67,Data!$B$2:$B$745,0))),""))) | H81: =IF(B81="","",IFERROR(IF(INDEX(Data!$N$2:$N$745,MATCH(67,Data!$B$2:$B$745,0))="","",INDEX(Data!$N$2:$N$745,MATCH(67,Data!$B$2:$B$745,0))),"")) | I81: =IF(B81="","",IFERROR(IF(INDEX(Data!$O$2:$O$745,MATCH(67,Data!$B$2:$B$745,0))="","",INDEX(Data!$O$2:$O$745,MATCH(67,Data!$B$2:$B$745,0))),"")) | J81: =IF(B81="","",IFERROR(IF(INDEX(Data!$P$2:$P$745,MATCH(67,Data!$B$2:$B$745,0))="","",INDEX(Data!$P$2:$P$745,MATCH(67,Data!$B$2:$B$745,0))),"")) | K81: =IF(B81="","",IFERROR(IF(INDEX(Data!$R$2:$R$745,MATCH(67,Data!$B$2:$B$745,0))="","",INDEX(Data!$R$2:$R$745,MATCH(67,Data!$B$2:$B$745,0))),"")) | L81: =IF(B81="","",IFERROR(IF(INDEX(Data!$S$2:$S$745,MATCH(67,Data!$B$2:$B$745,0))="","",INDEX(Data!$S$2:$S$745,MATCH(67,Data!$B$2:$B$745,0))),"")) | M81: =IF(B81="","",IFERROR(IF(INDEX(Data!$T$2:$T$745,MATCH(67,Data!$B$2:$B$745,0))="","",INDEX(Data!$T$2:$T$745,MATCH(67,Data!$B$2:$B$745,0))),"")) | N81: =IF(B81="","",IFERROR(IF(INDEX(Data!$U$2:$U$745,MATCH(67,Data!$B$2:$B$745,0))="","",INDEX(Data!$U$2:$U$745,MATCH(67,Data!$B$2:$B$745,0))),"")) | O81: =IF(B81="","",IFERROR(IF(INDEX(Data!$V$2:$V$745,MATCH(67,Data!$B$2:$B$745,0))="","",INDEX(Data!$V$2:$V$745,MATCH(67,Data!$B$2:$B$745,0))),"")) | P81: =IF(B81="","",IFERROR(IF(INDEX(Data!$M$2:$M$745,MATCH(67,Data!$B$2:$B$745,0))="","",INDEX(Data!$M$2:$M$745,MATCH(67,Data!$B$2:$B$745,0))),"")) | Q81: =IF(B81="","",IFERROR(IF(INDEX(Data!$AD$2:$AD$745,MATCH(67,Data!$B$2:$B$745,0))="","",INDEX(Data!$AD$2:$AD$745,MATCH(67,Data!$B$2:$B$745,0))),"")) | R81: =IF(B81="","",IFERROR(IF(INDEX(Data!$L$2:$L$745,MATCH(67,Data!$B$2:$B$745,0))="","",INDEX(Data!$L$2:$L$745,MATCH(67,Data!$B$2:$B$745,0))),"")) | AB81: FORCHEER
B82: =IF(68<=COUNTIF(Data!$A$2:$A$745,TRUE),68,"") | C82: =IF(B82="","",IFERROR(_xlfn.IMAGE(IFERROR(IF(INDEX(Data!$J$2:$J$745,MATCH(68,Data!$B$2:$B$745,0))="","",INDEX(Data!$J$2:$J$745,MATCH(68,Data!$B$2:$B$745,0))),"")),"IMAGE COMING SOON")) | D82: =IF(B82="","",IFERROR(IF(INDEX(Data!$G$2:$G$745,MATCH(68,Data!$B$2:$B$745,0))="","",INDEX(Data!$G$2:$G$745,MATCH(68,Data!$B$2:$B$745,0))),"")&CHAR(10)&IFERROR(IF(INDEX(Data!$H$2:$H$745,MATCH(68,Data!$B$2:$B$745,0))="","",INDEX(Data!$H$2:$H$745,MATCH(68,Data!$B$2:$B$745,0))),"")) | E82: =IF(B82="","",IFERROR(IF(INDEX(Data!$I$2:$I$745,MATCH(68,Data!$B$2:$B$745,0))="","",INDEX(Data!$I$2:$I$745,MATCH(68,Data!$B$2:$B$745,0))),"")) | F82: =IF(B82="","",IFERROR(IF(INDEX(Data!$AJ$2:$AJ$745,MATCH(68,Data!$B$2:$B$745,0))="","",INDEX(Data!$AJ$2:$AJ$745,MATCH(68,Data!$B$2:$B$745,0))),"")) | G82: =IF(B82="","",TRIM(IFERROR(IF(INDEX(Data!$AF$2:$AF$745,MATCH(68,Data!$B$2:$B$745,0))="","",INDEX(Data!$AF$2:$AF$745,MATCH(68,Data!$B$2:$B$745,0))),"")&" "&IFERROR(IF(INDEX(Data!$AG$2:$AG$745,MATCH(68,Data!$B$2:$B$745,0))="","",INDEX(Data!$AG$2:$AG$745,MATCH(68,Data!$B$2:$B$745,0))),""))) | H82: =IF(B82="","",IFERROR(IF(INDEX(Data!$N$2:$N$745,MATCH(68,Data!$B$2:$B$745,0))="","",INDEX(Data!$N$2:$N$745,MATCH(68,Data!$B$2:$B$745,0))),"")) | I82: =IF(B82="","",IFERROR(IF(INDEX(Data!$O$2:$O$745,MATCH(68,Data!$B$2:$B$745,0))="","",INDEX(Data!$O$2:$O$745,MATCH(68,Data!$B$2:$B$745,0))),"")) | J82: =IF(B82="","",IFERROR(IF(INDEX(Data!$P$2:$P$745,MATCH(68,Data!$B$2:$B$745,0))="","",INDEX(Data!$P$2:$P$745,MATCH(68,Data!$B$2:$B$745,0))),"")) | K82: =IF(B82="","",IFERROR(IF(INDEX(Data!$R$2:$R$745,MATCH(68,Data!$B$2:$B$745,0))="","",INDEX(Data!$R$2:$R$745,MATCH(68,Data!$B$2:$B$745,0))),"")) | L82: =IF(B82="","",IFERROR(IF(INDEX(Data!$S$2:$S$745,MATCH(68,Data!$B$2:$B$745,0))="","",INDEX(Data!$S$2:$S$745,MATCH(68,Data!$B$2:$B$745,0))),"")) | M82: =IF(B82="","",IFERROR(IF(INDEX(Data!$T$2:$T$745,MATCH(68,Data!$B$2:$B$745,0))="","",INDEX(Data!$T$2:$T$745,MATCH(68,Data!$B$2:$B$745,0))),"")) | N82: =IF(B82="","",IFERROR(IF(INDEX(Data!$U$2:$U$745,MATCH(68,Data!$B$2:$B$745,0))="","",INDEX(Data!$U$2:$U$745,MATCH(68,Data!$B$2:$B$745,0))),"")) | O82: =IF(B82="","",IFERROR(IF(INDEX(Data!$V$2:$V$745,MATCH(68,Data!$B$2:$B$745,0))="","",INDEX(Data!$V$2:$V$745,MATCH(68,Data!$B$2:$B$745,0))),"")) | P82: =IF(B82="","",IFERROR(IF(INDEX(Data!$M$2:$M$745,MATCH(68,Data!$B$2:$B$745,0))="","",INDEX(Data!$M$2:$M$745,MATCH(68,Data!$B$2:$B$745,0))),"")) | Q82: =IF(B82="","",IFERROR(IF(INDEX(Data!$AD$2:$AD$745,MATCH(68,Data!$B$2:$B$745,0))="","",INDEX(Data!$AD$2:$AD$745,MATCH(68,Data!$B$2:$B$745,0))),"")) | R82: =IF(B82="","",IFERROR(IF(INDEX(Data!$L$2:$L$745,MATCH(68,Data!$B$2:$B$745,0))="","",INDEX(Data!$L$2:$L$745,MATCH(68,Data!$B$2:$B$745,0))),"")) | AB82: FreshCulture
B83: =IF(69<=COUNTIF(Data!$A$2:$A$745,TRUE),69,"") | C83: =IF(B83="","",IFERROR(_xlfn.IMAGE(IFERROR(IF(INDEX(Data!$J$2:$J$745,MATCH(69,Data!$B$2:$B$745,0))="","",INDEX(Data!$J$2:$J$745,MATCH(69,Data!$B$2:$B$745,0))),"")),"IMAGE COMING SOON")) | D83: =IF(B83="","",IFERROR(IF(INDEX(Data!$G$2:$G$745,MATCH(69,Data!$B$2:$B$745,0))="","",INDEX(Data!$G$2:$G$745,MATCH(69,Data!$B$2:$B$745,0))),"")&CHAR(10)&IFERROR(IF(INDEX(Data!$H$2:$H$745,MATCH(69,Data!$B$2:$B$745,0))="","",INDEX(Data!$H$2:$H$745,MATCH(69,Data!$B$2:$B$745,0))),"")) | E83: =IF(B83="","",IFERROR(IF(INDEX(Data!$I$2:$I$745,MATCH(69,Data!$B$2:$B$745,0))="","",INDEX(Data!$I$2:$I$745,MATCH(69,Data!$B$2:$B$745,0))),"")) | F83: =IF(B83="","",IFERROR(IF(INDEX(Data!$AJ$2:$AJ$745,MATCH(69,Data!$B$2:$B$745,0))="","",INDEX(Data!$AJ$2:$AJ$745,MATCH(69,Data!$B$2:$B$745,0))),"")) | G83: =IF(B83="","",TRIM(IFERROR(IF(INDEX(Data!$AF$2:$AF$745,MATCH(69,Data!$B$2:$B$745,0))="","",INDEX(Data!$AF$2:$AF$745,MATCH(69,Data!$B$2:$B$745,0))),"")&" "&IFERROR(IF(INDEX(Data!$AG$2:$AG$745,MATCH(69,Data!$B$2:$B$745,0))="","",INDEX(Data!$AG$2:$AG$745,MATCH(69,Data!$B$2:$B$745,0))),""))) | H83: =IF(B83="","",IFERROR(IF(INDEX(Data!$N$2:$N$745,MATCH(69,Data!$B$2:$B$745,0))="","",INDEX(Data!$N$2:$N$745,MATCH(69,Data!$B$2:$B$745,0))),"")) | I83: =IF(B83="","",IFERROR(IF(INDEX(Data!$O$2:$O$745,MATCH(69,Data!$B$2:$B$745,0))="","",INDEX(Data!$O$2:$O$745,MATCH(69,Data!$B$2:$B$745,0))),"")) | J83: =IF(B83="","",IFERROR(IF(INDEX(Data!$P$2:$P$745,MATCH(69,Data!$B$2:$B$745,0))="","",INDEX(Data!$P$2:$P$745,MATCH(69,Data!$B$2:$B$745,0))),"")) | K83: =IF(B83="","",IFERROR(IF(INDEX(Data!$R$2:$R$745,MATCH(69,Data!$B$2:$B$745,0))="","",INDEX(Data!$R$2:$R$745,MATCH(69,Data!$B$2:$B$745,0))),"")) | L83: =IF(B83="","",IFERROR(IF(INDEX(Data!$S$2:$S$745,MATCH(69,Data!$B$2:$B$745,0))="","",INDEX(Data!$S$2:$S$745,MATCH(69,Data!$B$2:$B$745,0))),"")) | M83: =IF(B83="","",IFERROR(IF(INDEX(Data!$T$2:$T$745,MATCH(69,Data!$B$2:$B$745,0))="","",INDEX(Data!$T$2:$T$745,MATCH(69,Data!$B$2:$B$745,0))),"")) | N83: =IF(B83="","",IFERROR(IF(INDEX(Data!$U$2:$U$745,MATCH(69,Data!$B$2:$B$745,0))="","",INDEX(Data!$U$2:$U$745,MATCH(69,Data!$B$2:$B$745,0))),"")) | O83: =IF(B83="","",IFERROR(IF(INDEX(Data!$V$2:$V$745,MATCH(69,Data!$B$2:$B$745,0))="","",INDEX(Data!$V$2:$V$745,MATCH(69,Data!$B$2:$B$745,0))),"")) | P83: =IF(B83="","",IFERROR(IF(INDEX(Data!$M$2:$M$745,MATCH(69,Data!$B$2:$B$745,0))="","",INDEX(Data!$M$2:$M$745,MATCH(69,Data!$B$2:$B$745,0))),"")) | Q83: =IF(B83="","",IFERROR(IF(INDEX(Data!$AD$2:$AD$745,MATCH(69,Data!$B$2:$B$745,0))="","",INDEX(Data!$AD$2:$AD$745,MATCH(69,Data!$B$2:$B$745,0))),"")) | R83: =IF(B83="","",IFERROR(IF(INDEX(Data!$L$2:$L$745,MATCH(69,Data!$B$2:$B$745,0))="","",INDEX(Data!$L$2:$L$745,MATCH(69,Data!$B$2:$B$745,0))),"")) | AB83: Gabire
