Workbook

Sheet Overview
A1: Sleephoria Boho Throw Blanket: PPC clean-up, hard cap and rebuild plan
A2: For Shayan Rana, with Joseph Fisher | Data as of 22 Oct 2026 | Parent ASIN B0HGLF8X5Q, Amazon US
A4: Verdict
A5: Conversion is too low to buy traffic, so the account holds: only campaigns generating orders stay live ('bohemian throw blanket' and 'bohemian blanket', bids unchanged, top-of-search boosts capped at +300%) plus brand defence, inside a $25 a day ceiling. Every other campaign is paused, but not deleted: core terms with real demand are kept for a retest, mixed campaigns are rebuilt cleanly, and wrong-intent terms become negatives. The new campaign structure is built from scratch only after the listing and the other fixes pass their gates (Rebuild Plan tab).
A7: Key numbers
A8: Metric | B8: Since launch | C8: Last 30 days | D8: Last 15 days | E8: Note
A9: Ad spend | B9: =Campaigns!O46 -> 1648.02 | C9: =Campaigns!X46 -> 487.49 | D9: =Campaigns!AD46 -> 236.54
A10: Clicks | B10: =Campaigns!N46 -> 3093 | C10: =Campaigns!W46 -> 486 | D10: =Campaigns!AC46 -> 215
A11: Orders | B11: =Campaigns!P46 -> 34 | C11: =Campaigns!Y46 -> 4 | D11: =Campaigns!AE46 -> 2 | E11: Recent windows still filling in (7-day attribution)
A12: Ad sales | B12: =Campaigns!Q46 -> 1072.65 | C12: =Campaigns!Z46 -> 131.96 | D12: =Campaigns!AF46 -> 69.98
A13: Cost per click | B13: =IF(B10=0,"",B9/B10) -> 0.5328225 | C13: =IF(C10=0,"",C9/C10) -> 1.0030658 | D13: =IF(D10=0,"",D9/D10) -> 1.100186 | E13: Plan base bid $0.45 to $0.50
A14: Conversion (orders / clicks) | B14: =IF(B10=0,"",B11/B10) -> 0.010992564 | C14: =IF(C10=0,"",C11/C10) -> 0.0082304527 | D14: =IF(D10=0,"",D11/D10) -> 0.0093023256 | E14: Market CVR on boho searches about 1.3% to 2.4% (SQP)
A15: ACoS | B15: =IF(B12=0,"",B9/B12) -> 1.5364005 | C15: =IF(C12=0,"",C9/C12) -> 3.6942255 | D15: =IF(D12=0,"",D9/D12) -> 3.3801086 | E15: Break-even about 12.6% (Rules tab)
A16: Spend per order | B16: =IF(B11=0,"",B9/B11) -> 48.471176 | C16: =IF(C11=0,"",C9/C11) -> 121.8725 | D16: =IF(D11=0,"",D9/D11) -> 118.27 | E16: Contribution per unit $3.44 to $4.37
A18: Wasted ad spend
A19: Measure | B19: Amount | C19: Note
A20: Spend on search terms that never produced an order (since launch) | B20: ='Search Terms'!B141 -> 733.15 | C20: Search Terms tab
A21: Share of all search-term spend | B21: ='Search Terms'!B142 -> 0.44612866
A22: Spend on campaigns with 0 orders since launch | B22: =SUMIFS(Campaigns!$O$6:$O$45,Campaigns!$P$6:$P$45,0) -> 539.09 | C22: Decisions tab, 'Wasted spend' column
A23: Ad loss since launch (spend minus contribution earned on ad orders) | B23: =B9-B11*Rules!$B$34 -> 1515.25 | C23: Contribution is an estimate until D8
A24: Last 30 days: spend on campaigns now paused or kept paused | B24: ='Live Set'!B20 -> 390.61 | C24: This is the spend the pause list removes
A25: Expected spend per month after the change | B25: ='Live Set'!B17 -> 97.593793 | C25: 3 live campaigns, limited by search volume
A26: Maximum possible spend per month (budgets fully used) | B26: ='Live Set'!B18 -> 750 | C26: $25 a day ceiling (Phase 0 / D4)
A27: Expected cut vs the last 30 days | B27: ='Live Set'!B21 -> 0.7998035
A29: Decision summary (all 40 campaigns; SP exact and product targeting are the only ad types running)
A30: Decision category | B30: Campaigns | C30: Live after the change | D30: Spend since launch | E30: Orders since launch | F30: Spend, last 30 days
A31: =Decisions!A18 -> 1 RETAIN (generating orders) | B31: =Decisions!B18 -> 2 | C31: =Decisions!C18 -> 2 | D31: =Decisions!D18 -> 173.26 | E31: =Decisions!E18 -> 6 | F31: =Decisions!F18 -> 96.88
A32: =Decisions!A19 -> 2 ADJUST (bid / placement) | B32: =Decisions!B19 -> 1 | C32: =Decisions!C19 -> 1 | D32: =Decisions!D19 -> 1.38 | E32: =Decisions!E19 -> 0 | F32: =Decisions!F19 -> 0
A33: =Decisions!A20 -> 3 RETEST AFTER REBUILD | B33: =Decisions!B20 -> 6 | C33: =Decisions!C20 -> 0 | D33: =Decisions!D20 -> 480.77 | E33: =Decisions!E20 -> 13 | F33: =Decisions!F20 -> 51.91
A34: =Decisions!A21 -> 4 RESTRUCTURE IN REBUILD | B34: =Decisions!B21 -> 6 | C34: =Decisions!C21 -> 0 | D34: =Decisions!D21 -> 461.08 | E34: =Decisions!E21 -> 12 | F34: =Decisions!F21 -> 150.3
A35: =Decisions!A22 -> 5 PAUSE (wasted spend) | B35: =Decisions!B22 -> 25 | C35: =Decisions!C22 -> 0 | D35: =Decisions!D22 -> 531.53 | E35: =Decisions!E22 -> 3 | F35: =Decisions!F22 -> 188.4
A37: How each campaign was judged
A38: 1 RETAIN: orders on Amazon in the last 30 days and a cart-add rate in line with the market. Stays live with bids cut to what a click is worth.
A39: 2 ADJUST: kept live for protection (brand defence); settings brought inside the plan's limits.
A40: 3 RETEST AFTER REBUILD: real demand and the right intent, but the current page does not convert it (or no recent orders). Paused, not negated; first in line for the new structure with a pass mark.
A41: 4 RESTRUCTURE IN REBUILD: useful keywords stuck in a badly built campaign (mixed intents, wrong SKU, wrong size). Paused now; rebuilt correctly later.
A42: 5 PAUSE (wasted spend): no orders on Amazon after enough clicks, or the wrong product, size or colour. Paused; the search terms become negatives in the rebuild.
A43: Core terms were not paused on click count alone: each was checked for what a click is worth, bids and modifiers, placement results, relevance and the market's conversion on that search (Core Term Test tab).
A45: What changed from the last version
A46: 3 campaigns live with bids held (no tests). Budgets $10 / $10 / $5 = $25 a day, the Phase 0 / D4 ceiling, so no campaign runs out after one or two top-of-search clicks; expected spend stays about $3 to $5 a day because these terms are small. Top-of-search boosts on 'bohemian blanket' (+450%) and brand defence (+380%) come down to +300%.
A47: Off-Amazon investigated (Placements tab): a 2-week burst on idle budgets, not an account switch-off.
A49: What to do now (Shayan, after Joseph approves on the Approvals tab)
A50: 1. Set the portfolio budget on 'SLEEPHORIA - Boho Blanket' to $25 a day (the Phase 0 / D4 ceiling).
... A63: Sales take up to 7 days to be credited. SQP is a sample. Off-Amazon orders are implied. Nothing in the ad account was changed by this review.

Sheet Decisions
A1: Campaign-by-campaign decision: retain, adjust, retest, restructure or pause
A2: Every boho campaign, all ad types and match types. Numbers are looked up from the Campaigns and Search Terms tabs. Yellow column is for you.
A4: Ad type and match type coverage
A5: Ad type / match type | B5: Campaigns | C5: Enabled now | D5: Spend since launch | E5: Note
A6: Sponsored Products: Exact keyword | B6: =COUNTIF(Campaigns!$D$6:$D$45,"SP Exact keyword") -> 30 | C6: =COUNTIFS(Campaigns!$D$6:$D$45,"SP Exact keyword",Campaigns!$H$6:$H$45,"ENABLED") -> 15 | D6: =SUMIFS(Campaigns!$O$6:$O$45,Campaigns!$D$6:$D$45,"SP Exact keyword") -> 1444.15 | E6: All keyword campaigns are exact
A7: Sponsored Products: Product targeting (ASIN) | B7: =COUNTIF(Campaigns!$D$6:$D$45,"SP Product targeting") -> 10 | C7: =COUNTIFS(Campaigns!$D$6:$D$45,"SP Product targeting",Campaigns!$H$6:$H$45,"ENABLED") -> 7 | D7: =SUMIFS(Campaigns!$O$6:$O$45,Campaigns!$D$6:$D$45,"SP Product targeting") -> 203.87 | E7: All advertise Bouquet 60x80
A8: Sponsored Products: Phrase | B8: 0 | C8: 0 | D8: 0 | E8: None exist
A9: Sponsored Products: Broad | B9: 0 | C9: 0 | D9: 0 | E9: None exist
A10: Sponsored Products: Auto | B10: 0 | C10: 0 | D10: 0 | E10: None exist
A11: Sponsored Brands (headline) | B11: 0 | C11: 0 | D11: 0 | E11: None exist (no brand assets yet)
A12: Sponsored Brands Video | B12: 0 | C12: 0 | D12: 0 | E12: None exist (no product video yet)
A13: Sponsored Display | B13: 0 | C13: 0 | D13: 0 | E13: None exist
A14: Source: Command Center lists 40 campaigns for this product, all Sponsored Products (30 exact, 10 product targeting); DataDive's campaign list matches; the decision pack records 0% Sponsored Brands and Display. Nothing else to pause.
A16: Summary by decision
A17: Decision category | B17: Campaigns | C17: Live after the change | D17: Spend since launch | E17: Orders since launch | F17: Spend, last 30 days | G17: Orders, last 30 days | H17: Spend on zero-order campaigns since launch
A18: 1 RETAIN (generating orders) | B18: =COUNTIF(Campaigns!$AT$6:$AT$45,$A18) -> 2 | C18: =COUNTIFS(Campaigns!$AT$6:$AT$45,$A18,Campaigns!$AU$6:$AU$45,"ENABLED") -> 2 | D18: =SUMIFS(Campaigns!$O$6:$O$45,Campaigns!$AT$6:$AT$45,$A18) -> 173.26 | E18: =SUMIFS(Campaigns!$P$6:$P$45,Campaigns!$AT$6:$AT$45,$A18) -> 6 | F18: =SUMIFS(Campaigns!$X$6:$X$45,Campaigns!$AT$6:$AT$45,$A18) -> 96.88 | G18: =SUMIFS(Campaigns!$Y$6:$Y$45,Campaigns!$AT$6:$AT$45,$A18) -> 3 | H18: =SUMIFS(Campaigns!$O$6:$O$45,Campaigns!$AT$6:$AT$45,$A18,Campaigns!$P$6:$P$45,0) -> 0
A19: 2 ADJUST (bid / placement) | B19: =COUNTIF(Campaigns!$AT$6:$AT$45,$A19) -> 1 | C19: =COUNTIFS(Campaigns!$AT$6:$AT$45,$A19,Campaigns!$AU$6:$AU$45,"ENABLED") -> 1 | D19: =SUMIFS(Campaigns!$O$6:$O$45,Campaigns!$AT$6:$AT$45,$A19) -> 1.38 | E19: =SUMIFS(Campaigns!$P$6:$P$45,Campaigns!$AT$6:$AT$45,$A19) -> 0 | F19: =SUMIFS(Campaigns!$X$6:$X$45,Campaigns!$AT$6:$AT$45,$A19) -> 0 | G19: =SUMIFS(Campaigns!$Y$6:$Y$45,Campaigns!$AT$6:$AT$45,$A19) -> 0 | H19: =SUMIFS(Campaigns!$O$6:$O$45,Campaigns!$AT$6:$AT$45,$A19,Campaigns!$P$6:$P$45,0) -> 1.38
A20: 3 RETEST AFTER REBUILD | B20: =COUNTIF(Campaigns!$AT$6:$AT$45,$A20) -> 6 | C20: =COUNTIFS(Campaigns!$AT$6:$AT$45,$A20,Campaigns!$AU$6:$AU$45,"ENABLED") -> 0 | D20: =SUMIFS(Campaigns!$O$6:$O$45,Campaigns!$AT$6:$AT$45,$A20) -> 480.77 | E20: =SUMIFS(Campaigns!$P$6:$P$45,Campaigns!$AT$6:$AT$45,$A20) -> 13 | F20: =SUMIFS(Campaigns!$X$6:$X$45,Campaigns!$AT$6:$AT$45,$A20) -> 51.91 | G20: =SUMIFS(Campaigns!$Y$6:$Y$45,Campaigns!$AT$6:$AT$45,$A20) -> 0 | H20: =SUMIFS(Campaigns!$O$6:$O$45,Campaigns!$AT$6:$AT$45,$A20,Campaigns!$P$6:$P$45,0) -> 42.81
A21: 4 RESTRUCTURE IN REBUILD | B21: =COUNTIF(Campaigns!$AT$6:$AT$45,$A21) -> 6 | C21: =COUNTIFS(Campaigns!$AT$6:$AT$45,$A21,Campaigns!$AU$6:$AU$45,"ENABLED") -> 0 | D21: =SUMIFS(Campaigns!$O$6:$O$45,Campaigns!$AT$6:$AT$45,$A21) -> 461.08 | E21: =SUMIFS(Campaigns!$P$6:$P$45,Campaigns!$AT$6:$AT$45,$A21) -> 12 | F21: =SUMIFS(Campaigns!$X$6:$X$45,Campaigns!$AT$6:$AT$45,$A21) -> 150.3 | G21: =SUMIFS(Campaigns!$Y$6:$Y$45,Campaigns!$AT$6:$AT$45,$A21) -> 1 | H21: =SUMIFS(Campaigns!$O$6:$O$45,Campaigns!$AT$6:$AT$45,$A21,Campaigns!$P$6:$P$45,0) -> 22.9
A22: 5 PAUSE (wasted spend) | B22: =COUNTIF(Campaigns!$AT$6:$AT$45,$A22) -> 25 | C22: =COUNTIFS(Campaigns!$AT$6:$AT$45,$A22,Campaigns!$AU$6:$AU$45,"ENABLED") -> 0 | D22: =SUMIFS(Campaigns!$O$6:$O$45,Campaigns!$AT$6:$AT$45,$A22) -> 531.53 | E22: =SUMIFS(Campaigns!$P$6:$P$45,Campaigns!$AT$6:$AT$45,$A22) -> 3 | F22: =SUMIFS(Campaigns!$X$6:$X$45,Campaigns!$AT$6:$AT$45,$A22) -> 188.4 | G22: =SUMIFS(Campaigns!$Y$6:$Y$45,Campaigns!$AT$6:$AT$45,$A22) -> 0 | H22: =SUMIFS(Campaigns!$O$6:$O$45,Campaigns!$AT$6:$AT$45,$A22,Campaigns!$P$6:$P$45,0) -> 472
A23: TOTAL | B23: =SUM(B18:B22) -> 40 | C23: =SUM(C18:C22) -> 3 | D23: =SUM(D18:D22) -> 1648.02 | E23: =SUM(E18:E22) -> 34 | F23: =SUM(F18:F22) -> 487.49 | G23: =SUM(G18:G22) -> 4 | H23: =SUM(H18:H22) -> 539.09
A25: Campaign list (sorted by decision, then spend)
A26: Decision category | B26: Campaign | C26: Campaign ID | D26: Ad type / match | E26: Main keyword or ASIN | F26: State now | G26: New state | H26: Clicks since launch | I26: Orders since launch | J26: Spend since launch | K26: ACoS since launch | L26: CPC since launch | M26: On-Amazon clicks | N26: On-Amazon orders | O26: Clicks, last 30 days | P26: Orders, last 30 days | Q26: Spend, last 30 days | R26: Wasted spend (campaign had 0 orders) | S26: TOS modifier | T26: Search volume | U26: Relevancy | V26: Organic rank | W26: Action | X26: Why (data) | Y26: In the rebuild | Z26: Approver | AA26: Done? (Y/N)
A27: 1 RETAIN (generating orders) | B27: bohemian throw blanket | C27: 271118311398471 | D27: =INDEX(Campaigns!$D$6:$D$45,MATCH($C27,Campaigns!$A$6:$A$45,0)) -> SP Exact keyword | E27: bohemian throw blanket | F27: =INDEX(Campaigns!$H$6:$H$45,MATCH($C27,Campaigns!$A$6:$A$45,0)) -> ENABLED | G27: =INDEX(Campaigns!$AU$6:$AU$45,MATCH($C27,Campaigns!$A$6:$A$45,0)) -> ENABLED | H27: =INDEX(Campaigns!$N$6:$N$45,MATCH($C27,Campaigns!$A$6:$A$45,0)) -> 184 | I27: =INDEX(Campaigns!$P$6:$P$45,MATCH($C27,Campaigns!$A$6:$A$45,0)) -> 4 | J27: =INDEX(Campaigns!$O$6:$O$45,MATCH($C27,Campaigns!$A$6:$A$45,0)) -> 128.41 | K27: =INDEX(Campaigns!$U$6:$U$45,MATCH($C27,Campaigns!$A$6:$A$45,0)) -> 0.85067903 | L27: =INDEX(Campaigns!$T$6:$T$45,MATCH($C27,Campaigns!$A$6:$A$45,0)) -> 0.69788043 | M27: =INDEX(Campaigns!$AH$6:$AH$45,MATCH($C27,Campaigns!$A$6:$A$45,0))+INDEX(Campaigns!$AJ$6:$AJ$45,MATCH($C27,Campaigns!$A$6:$A$45,0))+INDEX(Campaigns!$AL$6:$AL$45,MATCH($C27,Campaigns!$A$6:$A$45,0)) -> 184 | N27: 4 | O27: =INDEX(Campaigns!$W$6:$W$45,MATCH($C27,Campaigns!$A$6:$A$45,0)) -> 92 | P27: =INDEX(Campaigns!$Y$6:$Y$45,MATCH($C27,Campaigns!$A$6:$A$45,0)) -> 1 | Q27: =INDEX(Campaigns!$X$6:$X$45,MATCH($C27,Campaigns!$A$6:$A$45,0)) -> 69.17 | R27: =IF(I27=0,J27,0) -> 0 | S27: =IF(INDEX(Campaigns!$J$6:$J$45,MATCH($C27,Campaigns!$A$6:$A$45,0))="","",INDEX(Campaigns!$J$6:$J$45,MATCH($C27,Campaigns!$A$6:$A$45,0))) -> 2.8 | T27: =IFERROR(INDEX('Search Terms'!$C$5:$C$137,MATCH($E27,'Search Terms'!$A$5:$A$137,0)),"") -> 725 | U27: =IFERROR(INDEX('Search Terms'!$B$5:$B$137,MATCH($E27,'Search Terms'!$A$5:$A$137,0)),"") -> Relevant | V27: =IFERROR(INDEX('Search Terms'!$D$5:$D$137,MATCH($E27,'Search Terms'!$A$5:$A$137,0)),"") -> 79 | W27: Keep live. Bid unchanged ($0.52); TOS +280% unchanged; budget $9.41 to $10 a day | X27: Only live core term still converting: 4 on-Amazon orders since launch, 1 in the last 30 days. SQP cart adds in line with the market (3 on 24 clicks vs 3.2 expected). ACoS 85%. Held as is (no bid test); the budget covers about 6 top-of-search clicks a day at its real CPC ($1.72). | Y27: Core exact, single keyword, Butterfly 50x60 | Z27: Joseph approves; Shayan applies
A28: 1 RETAIN (generating orders) | B28: bohemian blanket | C28: 274384612784893 | D28: =INDEX(Campaigns!$D$6:$D$45,MATCH($C28,Campaigns!$A$6:$A$45,0)) -> SP Exact keyword | E28: bohemian blanket | F28: =INDEX(Campaigns!$H$6:$H$45,MATCH($C28,Campaigns!$A$6:$A$45,0)) -> PAUSED | G28: =INDEX(Campaigns!$AU$6:$AU$45,MATCH($C28,Campaigns!$A$6:$A$45,0)) -> ENABLED | H28: =INDEX(Campaigns!$N$6:$N$45,MATCH($C28,Campaigns!$A$6:$A$45,0)) -> 50 | I28: =INDEX(Campaigns!$P$6:$P$45,MATCH($C28,Campaigns!$A$6:$A$45,0)) -> 2 | J28: =INDEX(Campaigns!$O$6:$O$45,MATCH($C28,Campaigns!$A$6:$A$45,0)) -> 44.85 | K28: =INDEX(Campaigns!$U$6:$U$45,MATCH($C28,Campaigns!$A$6:$A$45,0)) -> 0.72362052 | L28: =INDEX(Campaigns!$T$6:$T$45,MATCH($C28,Campaigns!$A$6:$A$45,0)) -> 0.897 | M28: =INDEX(Campaigns!$AH$6:$AH$45,MATCH($C28,Campaigns!$A$6:$A$45,0))+INDEX(Campaigns!$AJ$6:$AJ$45,MATCH($C28,Campaigns!$A$6:$A$45,0))+INDEX(Campaigns!$AL$6:$AL$45,MATCH($C28,Campaigns!$A$6:$A$45,0)) -> 50 | N28: 2 | O28: =INDEX(Campaigns!$W$6:$W$45,MATCH($C28,Campaigns!$A$6:$A$45,0)) -> 28 | P28: =INDEX(Campaigns!$Y$6:$Y$45,MATCH($C28,Campaigns!$A$6:$A$45,0)) -> 2 | Q28: =INDEX(Campaigns!$X$6:$X$45,MATCH($C28,Campaigns!$A$6:$A$45,0)) -> 27.71 | R28: =IF(I28=0,J28,0) -> 0 | S28: =IF(INDEX(Campaigns!$J$6:$J$45,MATCH($C28,Campaigns!$A$6:$A$45,0))="","",INDEX(Campaigns!$J$6:$J$45,MATCH($C28,Campaigns!$A$6:$A$45,0))) | T28: =IFERROR(INDEX('Search Terms'!$C$5:$C$137,MATCH($E28,'Search Terms'!$A$5:$A$137,0)),"") -> 591 | U28: =IFERROR(INDEX('Search Terms'!$B$5:$B$137,MATCH($E28,'Search Terms'!$A$5:$A$137,0)),"") -> Highly Relevant | V28: =IFERROR(INDEX('Search Terms'!$D$5:$D$137,MATCH($E28,'Search Terms'!$A$5:$A$137,0)),"") -> 85 | W28: Re-enable. Bid unchanged ($0.69); TOS +450% to +300%; budget $10 a day | X28: Best converter on the product: 2 orders on 50 clicks (4.0%), both in the last 30 days, ACoS 72%. It was paused on early-September data. TOS +450% let it pay up to $3.80 a click; +300% caps that at $2.76. | Y28: Core exact, single keyword | Z28: Joseph approves; Shayan applies
A29: 2 ADJUST (bid / placement) | B29: sleephoria boho throw blanket | C29: 94080520861158 | D29: =INDEX(Campaigns!$D$6:$D$45,MATCH($C29,Campaigns!$A$6:$A$45,0)) -> SP Exact keyword | E29: sleephoria boho throw blanket | F29: =INDEX(Campaigns!$H$6:$H$45,MATCH($C29,Campaigns!$A$6:$A$45,0)) -> ENABLED | G29: =INDEX(Campaigns!$AU$6:$AU$45,MATCH($C29,Campaigns!$A$6:$A$45,0)) -> ENABLED | H29: =INDEX(Campaigns!$N$6:$N$45,MATCH($C29,Campaigns!$A$6:$A$45,0)) -> 4 | I29: =INDEX(Campaigns!$P$6:$P$45,MATCH($C29,Campaigns!$A$6:$A$45,0)) -> 0 | J29: =INDEX(Campaigns!$O$6:$O$45,MATCH($C29,Campaigns!$A$6:$A$45,0)) -> 1.38 | K29: =INDEX(Campaigns!$U$6:$U$45,MATCH($C29,Campaigns!$A$6:$A$45,0)) | L29: =INDEX(Campaigns!$T$6:$T$45,MATCH($C29,Campaigns!$A$6:$A$45,0)) -> 0.345 | M29: =INDEX(Campaigns!$AH$6:$AH$45,MATCH($C29,Campaigns!$A$6:$A$45,0))+INDEX(Campaigns!$AJ$6:$AJ$45,MATCH($C29,Campaigns!$A$6:$A$45,0))+INDEX(Campaigns!$AL$6:$AL$45,MATCH($C29,Campaigns!$A$6:$A$45,0)) -> 4 | N29: 0 | O29: =INDEX(Campaigns!$W$6:$W$45,MATCH($C29,Campaigns!$A$6:$A$45,0)) -> 0 | P29: =INDEX(Campaigns!$Y$6:$Y$45,MATCH($C29,Campaigns!$A$6:$A$45,0)) -> 0 | Q29: =INDEX(Campaigns!$X$6:$X$45,MATCH($C29,Campaigns!$A$6:$A$45,0)) -> 0 | R29: =IF(I29=0,J29,0) -> 1.38 | S29: =IF(INDEX(Campaigns!$J$6:$J$45,MATCH($C29,Campaigns!$A$6:$A$45,0))="","",INDEX(Campaigns!$J$6:$J$45,MATCH($C29,Campaigns!$A$6:$A$45,0))) -> 3.8 | T29: =IFERROR(INDEX('Search Terms'!$C$5:$C$137,MATCH($E29,'Search Terms'!$A$5:$A$137,0)),"") -> 9 | U29: =IFERROR(INDEX('Search Terms'!$B$5:$B$137,MATCH($E29,'Search Terms'!$A$5:$A$137,0)),"") -> Branded | V29: =IFERROR(INDEX('Search Terms'!$D$5:$D$137,MATCH($E29,'Search Terms'!$A$5:$A$137,0)),"") -> 1 | W29: Keep live. Bid unchanged ($0.68); TOS +380% to +300%; budget $11.32 to $5 a day | X29: Own-brand searches: 4 clicks, $1.38 since launch. Cheap protection for the listing, but the modifier is above the plan's +300% cap. | Y29: Brand defence SP exact; add a Sponsored Brands headline once brand assets exist | Z29: Joseph approves; Shayan applies
A30: 3 RETEST AFTER REBUILD | B30: boho throw blankets for couch | C30: 240955455575163 | D30: =INDEX(Campaigns!$D$6:$D$45,MATCH($C30,Campaigns!$A$6:$A$45,0)) -> SP Exact keyword | E30: boho throw blankets for couch | F30: =INDEX(Campaigns!$H$6:$H$45,MATCH($C30,Campaigns!$A$6:$A$45,0)) -> ENABLED | G30: =INDEX(Campaigns!$AU$6:$AU$45,MATCH($C30,Campaigns!$A$6:$A$45,0)) -> PAUSED | H30: =INDEX(Campaigns!$N$6:$N$45,MATCH($C30,Campaigns!$A$6:$A$45,0)) -> 476 | I30: =INDEX(Campaigns!$P$6:$P$45,MATCH($C30,Campaigns!$A$6:$A$45,0)) -> 5 | J30: =INDEX(Campaigns!$O$6:$O$45,MATCH($C30,Campaigns!$A$6:$A$45,0)) -> 158.98 | K30: =INDEX(Campaigns!$U$6:$U$45,MATCH($C30,Campaigns!$A$6:$A$45,0)) -> 1.0531964 | L30: =INDEX(Campaigns!$T$6:$T$45,MATCH($C30,Campaigns!$A$6:$A$45,0)) -> 0.3339916 | M30: =INDEX(Campaigns!$AH$6:$AH$45,MATCH($C30,Campaigns!$A$6:$A$45,0))+INDEX(Campaigns!$AJ$6:$AJ$45,MATCH($C30,Campaigns!$A$6:$A$45,0))+INDEX(Campaigns!$AL$6:$AL$45,MATCH($C30,Campaigns!$A$6:$A$45,0)) -> 54 | N30: 1 | O30: =INDEX(Campaigns!$W$6:$W$45,MATCH($C30,Campaigns!$A$6:$A$45,0)) -> 31 | P30: =INDEX(Campaigns!$Y$6:$Y$45,MATCH($C30,Campaigns!$A$6:$A$45,0)) -> 0 | Q30: =INDEX(Campaigns!$X$6:$X$45,MATCH($C30,Campaigns!$A$6:$A$45,0)) -> 44.99 | R30: =IF(I30=0,J30,0) -> 0 | S30: =IF(INDEX(Campaigns!$J$6:$J$45,MATCH($C30,Campaigns!$A$6:$A$45,0))="","",INDEX(Campaigns!$J$6:$J$45,MATCH($C30,Campaigns!$A$6:$A$45,0))) -> 3 | T30: =IFERROR(INDEX('Search Terms'!$C$5:$C$137,MATCH($E30,'Search Terms'!$A$5:$A$137,0)),"") -> 497 | U30: =IFERROR(INDEX('Search Terms'!$B$5:$B$137,MATCH($E30,'Search Terms'!$A$5:$A$137,0)),"") -> Relevant | V30: =IFERROR(INDEX('Search Terms'!$D$5:$D$137,MATCH($E30,'Search Terms'!$A$5:$A$137,0)),"") -> 85 | W30: Pause now; retest after the rebuild | X30: 5 orders since launch, but 4 came from Off-Amazon traffic (422 of 476 clicks), which has stopped. On Amazon: 1 order on 54 clicks, and 0 orders on 31 clicks ($45) in the last 30 days. SQP cart adds are fine (3 on 23 clicks), so the term fits; the page does not close. | Y30: Couch-intent exact, Butterfly 50x60 | Z30: Joseph approves; Shayan applies
A31: 3 RETEST AFTER REBUILD | B31: boho blanket | C31: 131359054806082 | D31: =INDEX(Campaigns!$D$6:$D$45,MATCH($C31,Campaigns!$A$6:$A$45,0)) -> SP Exact keyword | E31: boho blanket | F31: =INDEX(Campaigns!$H$6:$H$45,MATCH($C31,Campaigns!$A$6:$A$45,0)) -> PAUSED | G31: =INDEX(Campaigns!$AU$6:$AU$45,MATCH($C31,Campaigns!$A$6:$A$45,0)) -> PAUSED | H31: =INDEX(Campaigns!$N$6:$N$45,MATCH($C31,Campaigns!$A$6:$A$45,0)) -> 187 | I31: =INDEX(Campaigns!$P$6:$P$45,MATCH($C31,Campaigns!$A$6:$A$45,0)) -> 3 | J31: =INDEX(Campaigns!$O$6:$O$45,MATCH($C31,Campaigns!$A$6:$A$45,0)) -> 138.56 | K31: =INDEX(Campaigns!$U$6:$U$45,MATCH($C31,Campaigns!$A$6:$A$45,0)) -> 1.5573789 | L31: =INDEX(Campaigns!$T$6:$T$45,MATCH($C31,Campaigns!$A$6:$A$45,0)) -> 0.74096257 | M31: =INDEX(Campaigns!$AH$6:$AH$45,MATCH($C31,Campaigns!$A$6:$A$45,0))+INDEX(Campaigns!$AJ$6:$AJ$45,MATCH($C31,Campaigns!$A$6:$A$45,0))+INDEX(Campaigns!$AL$6:$AL$45,MATCH($C31,Campaigns!$A$6:$A$45,0)) -> 185 | N31: 3 | O31: =INDEX(Campaigns!$W$6:$W$45,MATCH($C31,Campaigns!$A$6:$A$45,0)) -> 0 | P31: =INDEX(Campaigns!$Y$6:$Y$45,MATCH($C31,Campaigns!$A$6:$A$45,0)) -> 0 | Q31: =INDEX(Campaigns!$X$6:$X$45,MATCH($C31,Campaigns!$A$6:$A$45,0)) -> 0 | R31: =IF(I31=0,J31,0) -> 0 | S31: =IF(INDEX(Campaigns!$J$6:$J$45,MATCH($C31,Campaigns!$A$6:$A$45,0))="","",INDEX(Campaigns!$J$6:$J$45,MATCH($C31,Campaigns!$A$6:$A$45,0))) | T31: =IFERROR(INDEX('Search Terms'!$C$5:$C$137,MATCH($E31,'Search Terms'!$A$5:$A$137,0)),"") -> 4932 | U31: =IFERROR(INDEX('Search Terms'!$B$5:$B$137,MATCH($E31,'Search Terms'!$A$5:$A$137,0)),"") -> Relevant | V31: =IFERROR(INDEX('Search Terms'!$D$5:$D$137,MATCH($E31,'Search Terms'!$A$5:$A$137,0)),"") -> 133 | W31: Keep paused; retest after the rebuild | X31: 3 orders on 185 on-Amazon clicks (1.6%), all from product pages; ACoS 156% on a $40 a day budget. SQP cart adds are normal for the market (3 on 29 vs 3.4 expected), so the term fits; the old page does not close. Large demand (4,932 a month): worth retesting on the new page, not worth paying for on the old one. | Y31: Core exact, single keyword | Z31: Joseph approves; Shayan applies
A32: 3 RETEST AFTER REBUILD | B32: boho throw | C32: 143967856454663 | D32: =INDEX(Campaigns!$D$6:$D$45,MATCH($C32,Campaigns!$A$6:$A$45,0)) -> SP Exact keyword | E32: boho throw | F32: =INDEX(Campaigns!$H$6:$H$45,MATCH($C32,Campaigns!$A$6:$A$45,0)) -> PAUSED | G32: =INDEX(Campaigns!$AU$6:$AU$45,MATCH($C32,Campaigns!$A$6:$A$45,0)) -> PAUSED | H32: =INDEX(Campaigns!$N$6:$N$45,MATCH($C32,Campaigns!$A$6:$A$45,0)) -> 125 | I32: =INDEX(Campaigns!$P$6:$P$45,MATCH($C32,Campaigns!$A$6:$A$45,0)) -> 3 | J32: =INDEX(Campaigns!$O$6:$O$45,MATCH($C32,Campaigns!$A$6:$A$45,0)) -> 92.74 | K32: =INDEX(Campaigns!$U$6:$U$45,MATCH($C32,Campaigns!$A$6:$A$45,0)) -> 1.1453625 | L32: =INDEX(Campaigns!$T$6:$T$45,MATCH($C32,Campaigns!$A$6:$A$45,0)) -> 0.74192 | M32: =INDEX(Campaigns!$AH$6:$AH$45,MATCH($C32,Campaigns!$A$6:$A$45,0))+INDEX(Campaigns!$AJ$6:$AJ$45,MATCH($C32,Campaigns!$A$6:$A$45,0))+INDEX(Campaigns!$AL$6:$AL$45,MATCH($C32,Campaigns!$A$6:$A$45,0)) -> 125 | N32: 3 | O32: =INDEX(Campaigns!$W$6:$W$45,MATCH($C32,Campaigns!$A$6:$A$45,0)) -> 0 | P32: =INDEX(Campaigns!$Y$6:$Y$45,MATCH($C32,Campaigns!$A$6:$A$45,0)) -> 0 | Q32: =INDEX(Campaigns!$X$6:$X$45,MATCH($C32,Campaigns!$A$6:$A$45,0)) -> 0 | R32: =IF(I32=0,J32,0) -> 0 | S32: =IF(INDEX(Campaigns!$J$6:$J$45,MATCH($C32,Campaigns!$A$6:$A$45,0))="","",INDEX(Campaigns!$J$6:$J$45,MATCH($C32,Campaigns!$A$6:$A$45,0))) | T32: =IFERROR(INDEX('Search Terms'!$C$5:$C$137,MATCH($E32,'Search Terms'!$A$5:$A$137,0)),"") -> 1229 | U32: =IFERROR(INDEX('Search Terms'!$B$5:$B$137,MATCH($E32,'Search Terms'!$A$5:$A$137,0)),"") -> Relevant | V32: =IFERROR(INDEX('Search Terms'!$D$5:$D$137,MATCH($E32,'Search Terms'!$A$5:$A$137,0)),"") -> 94 | W32: Keep paused; retest first after the rebuild | X32: 3 orders on 125 clicks (2.4%), all at Top of Search; ACoS 115%. The closest of the core terms to break-even, but no orders since September and SQP shows 1 cart add on 34 clicks vs about 3.9 expected. | Y32: Core exact, single keyword | Z32: Joseph approves; Shayan applies
A33: 3 RETEST AFTER REBUILD | B33: boho throw blanket | C33: 136479271696362 | D33: =INDEX(Campaigns!$D$6:$D$45,MATCH($C33,Campaigns!$A$6:$A$45,0)) -> SP Exact keyword | E33: boho throw blanket | F33: =INDEX(Campaigns!$H$6:$H$45,MATCH($C33,Campaigns!$A$6:$A$45,0)) -> PAUSED | G33: =INDEX(Campaigns!$AU$6:$AU$45,MATCH($C33,Campaigns!$A$6:$A$45,0)) -> PAUSED | H33: =INDEX(Campaigns!$N$6:$N$45,MATCH($C33,Campaigns!$A$6:$A$45,0)) -> 44 | I33: =INDEX(Campaigns!$P$6:$P$45,MATCH($C33,Campaigns!$A$6:$A$45,0)) -> 0 | J33: =INDEX(Campaigns!$O$6:$O$45,MATCH($C33,Campaigns!$A$6:$A$45,0)) -> 42.81 | K33: =INDEX(Campaigns!$U$6:$U$45,MATCH($C33,Campaigns!$A$6:$A$45,0)) | L33: =INDEX(Campaigns!$T$6:$T$45,MATCH($C33,Campaigns!$A$6:$A$45,0)) -> 0.97295455 | M33: =INDEX(Campaigns!$AH$6:$AH$45,MATCH($C33,Campaigns!$A$6:$A$45,0))+INDEX(Campaigns!$AJ$6:$AJ$45,MATCH($C33,Campaigns!$A$6:$A$45,0))+INDEX(Campaigns!$AL$6:$AL$45,MATCH($C33,Campaigns!$A$6:$A$45,0)) -> 43 | N33: 0 | O33: =INDEX(Campaigns!$W$6:$W$45,MATCH($C33,Campaigns!$A$6:$A$45,0)) -> 0 | P33: =INDEX(Campaigns!$Y$6:$Y$45,MATCH($C33,Campaigns!$A$6:$A$45,0)) -> 0 | Q33: =INDEX(Campaigns!$X$6:$X$45,MATCH($C33,Campaigns!$A$6:$A$45,0)) -> 0 | R33: =IF(I33=0,J33,0) -> 42.81 | S33: =IF(INDEX(Campaigns!$J$6:$J$45,MATCH($C33,Campaigns!$A$6:$A$45,0))="","",INDEX(Campaigns!$J$6:$J$45,MATCH($C33,Campaigns!$A$6:$A$45,0))) | T33: =IFERROR(INDEX('Search Terms'!$C$5:$C$137,MATCH($E33,'Search Terms'!$A$5:$A$137,0)),"") -> 9420 | U33: =IFERROR(INDEX('Search Terms'!$B$5:$B$137,MATCH($E33,'Search Terms'!$A$5:$A$137,0)),"") -> Relevant | V33: =IFERROR(INDEX('Search Terms'!$D$5:$D$137,MATCH($E33,'Search Terms'!$A$5:$A$137,0)),"") -> 99 | W33: Keep paused. Do not negate. First exact test after the rebuild at the worth-based bid | X33: Hero term (9,420 searches a month; organic rank about 99). 42 clicks, 0 orders, $39. SQP: 0 add-to-carts on 38 clicks where the market rate (13%) predicts about 5, a chance of about 0.5%. The listing is not converting this search, and a lower bid cannot fix that. It paid $0.94 a click (Top of Search $1.33 at +300%) against about $0.17 a click is worth at the market's 1.6% CVR. Full workings: Core Term Test tab. | Y33: Core exact, single keyword, Butterfly 50x60. Pass mark: 2+ cart adds per 20 clicks, 1+ order per 50 clicks | Z33: Joseph approves; Shayan applies
A34: 3 RETEST AFTER REBUILD | B34: boho cotton blanket | C34: 153632991648836 | D34: =INDEX(Campaigns!$D$6:$D$45,MATCH($C34,Campaigns!$A$6:$A$45,0)) -> SP Exact keyword | E34: boho cotton blanket | F34: =INDEX(Campaigns!$H$6:$H$45,MATCH($C34,Campaigns!$A$6:$A$45,0)) -> PAUSED | G34: =INDEX(Campaigns!$AU$6:$AU$45,MATCH($C34,Campaigns!$A$6:$A$45,0)) -> PAUSED | H34: =INDEX(Campaigns!$N$6:$N$45,MATCH($C34,Campaigns!$A$6:$A$45,0)) -> 35 | I34: =INDEX(Campaigns!$P$6:$P$45,MATCH($C34,Campaigns!$A$6:$A$45,0)) -> 1 | J34: =INDEX(Campaigns!$O$6:$O$45,MATCH($C34,Campaigns!$A$6:$A$45,0)) -> 36.98 | K34: =INDEX(Campaigns!$U$6:$U$45,MATCH($C34,Campaigns!$A$6:$A$45,0)) -> 1.0568734 | L34: =INDEX(Campaigns!$T$6:$T$45,MATCH($C34,Campaigns!$A$6:$A$45,0)) -> 1.0565714 | M34: =INDEX(Campaigns!$AH$6:$AH$45,MATCH($C34,Campaigns!$A$6:$A$45,0))+INDEX(Campaigns!$AJ$6:$AJ$45,MATCH($C34,Campaigns!$A$6:$A$45,0))+INDEX(Campaigns!$AL$6:$AL$45,MATCH($C34,Campaigns!$A$6:$A$45,0)) -> 35 | N34: 1 | O34: =INDEX(Campaigns!$W$6:$W$45,MATCH($C34,Campaigns!$A$6:$A$45,0)) -> 0 | P34: =INDEX(Campaigns!$Y$6:$Y$45,MATCH($C34,Campaigns!$A$6:$A$45,0)) -> 0 | Q34: =INDEX(Campaigns!$X$6:$X$45,MATCH($C34,Campaigns!$A$6:$A$45,0)) -> 0 | R34: =IF(I34=0,J34,0) -> 0 | S34: =IF(INDEX(Campaigns!$J$6:$J$45,MATCH($C34,Campaigns!$A$6:$A$45,0))="","",INDEX(Campaigns!$J$6:$J$45,MATCH($C34,Campaigns!$A$6:$A$45,0))) | T34: =IFERROR(INDEX('Search Terms'!$C$5:$C$137,MATCH($E34,'Search Terms'!$A$5:$A$137,0)),"") -> 365 | U34: =IFERROR(INDEX('Search Terms'!$B$5:$B$137,MATCH($E34,'Search Terms'!$A$5:$A$137,0)),"") -> Highly Relevant | V34: =IFERROR(INDEX('Search Terms'!$D$5:$D$137,MATCH($E34,'Search Terms'!$A$5:$A$137,0)),"") -> 55 | W34: Keep paused; retest after the rebuild | X34: 1 order on 35 clicks (Top of Search); rated Highly Relevant; organic rank about 55. Too little data to justify spend before the page is fixed. | Y34: Material lane exact | Z34: Joseph approves; Shayan applies
A35: 3 RETEST AFTER REBUILD | B35: rustic floral boho blanket | C35: 122105077616953 | D35: =INDEX(Campaigns!$D$6:$D$45,MATCH($C35,Campaigns!$A$6:$A$45,0)) -> SP Exact keyword | E35: rustic floral boho blanket | F35: =INDEX(Campaigns!$H$6:$H$45,MATCH($C35,Campaigns!$A$6:$A$45,0)) -> ENABLED | G35: =INDEX(Campaigns!$AU$6:$AU$45,MATCH($C35,Campaigns!$A$6:$A$45,0)) -> PAUSED | H35: =INDEX(Campaigns!$N$6:$N$45,MATCH($C35,Campaigns!$A$6:$A$45,0)) -> 7 | I35: =INDEX(Campaigns!$P$6:$P$45,MATCH($C35,Campaigns!$A$6:$A$45,0)) -> 1 | J35: =INDEX(Campaigns!$O$6:$O$45,MATCH($C35,Campaigns!$A$6:$A$45,0)) -> 10.7 | K35: =INDEX(Campaigns!$U$6:$U$45,MATCH($C35,Campaigns!$A$6:$A$45,0)) -> 0.30580166 | L35: =INDEX(Campaigns!$T$6:$T$45,MATCH($C35,Campaigns!$A$6:$A$45,0)) -> 1.5285714 | M35: =INDEX(Campaigns!$AH$6:$AH$45,MATCH($C35,Campaigns!$A$6:$A$45,0))+INDEX(Campaigns!$AJ$6:$AJ$45,MATCH($C35,Campaigns!$A$6:$A$45,0))+INDEX(Campaigns!$AL$6:$AL$45,MATCH($C35,Campaigns!$A$6:$A$45,0)) -> 7 | N35: 1 | O35: =INDEX(Campaigns!$W$6:$W$45,MATCH($C35,Campaigns!$A$6:$A$45,0)) -> 4 | P35: =INDEX(Campaigns!$Y$6:$Y$45,MATCH($C35,Campaigns!$A$6:$A$45,0)) -> 0 | Q35: =INDEX(Campaigns!$X$6:$X$45,MATCH($C35,Campaigns!$A$6:$A$45,0)) -> 6.92 | R35: =IF(I35=0,J35,0) -> 0 | S35: =IF(INDEX(Campaigns!$J$6:$J$45,MATCH($C35,Campaigns!$A$6:$A$45,0))="","",INDEX(Campaigns!$J$6:$J$45,MATCH($C35,Campaigns!$A$6:$A$45,0))) -> 3 | T35: =IFERROR(INDEX('Search Terms'!$C$5:$C$137,MATCH($E35,'Search Terms'!$A$5:$A$137,0)),"") -> 33 | U35: =IFERROR(INDEX('Search Terms'!$B$5:$B$137,MATCH($E35,'Search Terms'!$A$5:$A$137,0)),"") -> Lower Relevant | V35: =IFERROR(INDEX('Search Terms'!$D$5:$D$137,MATCH($E35,'Search Terms'!$A$5:$A$137,0)),"") -> 39 | W35: Pause now; retest after the rebuild | X35: 1 order on 7 clicks since launch; 0 orders on 4 clicks at $1.73 a click in the last 30 days. Too few clicks to judge, and it advertises Bouquet 50x60, the weakest pattern. | Y35: Design lane (vintage floral), Bloom or Bouquet | Z35: Joseph approves; Shayan applies
A36: 4 RESTRUCTURE IN REBUILD | B36: boho king size blanket | C36: 43669682187702 | D36: =INDEX(Campaigns!$D$6:$D$45,MATCH($C36,Campaigns!$A$6:$A$45,0)) -> SP Exact keyword | E36: boho king size blanket | F36: =INDEX(Campaigns!$H$6:$H$45,MATCH($C36,Campaigns!$A$6:$A$45,0)) -> ENABLED | G36: =INDEX(Campaigns!$AU$6:$AU$45,MATCH($C36,Campaigns!$A$6:$A$45,0)) -> PAUSED | H36: =INDEX(Campaigns!$N$6:$N$45,MATCH($C36,Campaigns!$A$6:$A$45,0)) -> 1063 | I36: =INDEX(Campaigns!$P$6:$P$45,MATCH($C36,Campaigns!$A$6:$A$45,0)) -> 9 | J36: =INDEX(Campaigns!$O$6:$O$45,MATCH($C36,Campaigns!$A$6:$A$45,0)) -> 239.23 | K36: =INDEX(Campaigns!$U$6:$U$45,MATCH($C36,Campaigns!$A$6:$A$45,0)) -> 0.84560461 | L36: =INDEX(Campaigns!$T$6:$T$45,MATCH($C36,Campaigns!$A$6:$A$45,0)) -> 0.22505174 | M36: =INDEX(Campaigns!$AH$6:$AH$45,MATCH($C36,Campaigns!$A$6:$A$45,0))+INDEX(Campaigns!$AJ$6:$AJ$45,MATCH($C36,Campaigns!$A$6:$A$45,0))+INDEX(Campaigns!$AL$6:$AL$45,MATCH($C36,Campaigns!$A$6:$A$45,0)) -> 36 | N36: 0 | O36: =INDEX(Campaigns!$W$6:$W$45,MATCH($C36,Campaigns!$A$6:$A$45,0)) -> 28 | P36: =INDEX(Campaigns!$Y$6:$Y$45,MATCH($C36,Campaigns!$A$6:$A$45,0)) -> 0 | Q36: =INDEX(Campaigns!$X$6:$X$45,MATCH($C36,Campaigns!$A$6:$A$45,0)) -> 34.14 | R36: =IF(I36=0,J36,0) -> 0 | S36: =IF(INDEX(Campaigns!$J$6:$J$45,MATCH($C36,Campaigns!$A$6:$A$45,0))="","",INDEX(Campaigns!$J$6:$J$45,MATCH($C36,Campaigns!$A$6:$A$45,0))) -> 4.13 | T36: =IFERROR(INDEX('Search Terms'!$C$5:$C$137,MATCH($E36,'Search Terms'!$A$5:$A$137,0)),"") -> 94 | U36: =IFERROR(INDEX('Search Terms'!$B$5:$B$137,MATCH($E36,'Search Terms'!$A$5:$A$137,0)),"") -> Lower Relevant | V36: =IFERROR(INDEX('Search Terms'!$D$5:$D$137,MATCH($E36,'Search Terms'!$A$5:$A$137,0)),"") -> 113 | W36: Pause now. In the rebuild: negate king terms; move the 60x80 size terms to a size lane on the 60x80 SKU | X36: All 9 orders came from Off-Amazon (1,027 of 1,063 clicks), which stopped in late September. On Amazon: 0 orders on 36 clicks; bid $0.97 x +413% = up to $4.98 a click; the largest budget ($30). It mixes king-size terms (wrong size for a 60x80 throw) with 'boho blanket 60x 80' (the right size; organic rank 32). | Y36: Size lane exact (60x80, 50x60), SKU-matched | Z36: Joseph approves; Shayan applies
A37: 4 RESTRUCTURE IN REBUILD | B37: B0BLRBXBX5 | C37: 103168292442380 | D37: =INDEX(Campaigns!$D$6:$D$45,MATCH($C37,Campaigns!$A$6:$A$45,0)) -> SP Product targeting | E37: b0blrbxbx5 | F37: =INDEX(Campaigns!$H$6:$H$45,MATCH($C37,Campaigns!$A$6:$A$45,0)) -> ENABLED | G37: =INDEX(Campaigns!$AU$6:$AU$45,MATCH($C37,Campaigns!$A$6:$A$45,0)) -> PAUSED | H37: =INDEX(Campaigns!$N$6:$N$45,MATCH($C37,Campaigns!$A$6:$A$45,0)) -> 67 | I37: =INDEX(Campaigns!$P$6:$P$45,MATCH($C37,Campaigns!$A$6:$A$45,0)) -> 1 | J37: =INDEX(Campaigns!$O$6:$O$45,MATCH($C37,Campaigns!$A$6:$A$45,0)) -> 103.08 | K37: =INDEX(Campaigns!$U$6:$U$45,MATCH($C37,Campaigns!$A$6:$A$45,0)) -> 2.9459846 | L37: =INDEX(Campaigns!$T$6:$T$45,MATCH($C37,Campaigns!$A$6:$A$45,0)) -> 1.5385075 | M37: =INDEX(Campaigns!$AH$6:$AH$45,MATCH($C37,Campaigns!$A$6:$A$45,0))+INDEX(Campaigns!$AJ$6:$AJ$45,MATCH($C37,Campaigns!$A$6:$A$45,0))+INDEX(Campaigns!$AL$6:$AL$45,MATCH($C37,Campaigns!$A$6:$A$45,0)) -> 67 | N37: 1 | O37: =INDEX(Campaigns!$W$6:$W$45,MATCH($C37,Campaigns!$A$6:$A$45,0)) -> 66 | P37: =INDEX(Campaigns!$Y$6:$Y$45,MATCH($C37,Campaigns!$A$6:$A$45,0)) -> 1 | Q37: =INDEX(Campaigns!$X$6:$X$45,MATCH($C37,Campaigns!$A$6:$A$45,0)) -> 102.49 | R37: =IF(I37=0,J37,0) -> 0 | S37: =IF(INDEX(Campaigns!$J$6:$J$45,MATCH($C37,Campaigns!$A$6:$A$45,0))="","",INDEX(Campaigns!$J$6:$J$45,MATCH($C37,Campaigns!$A$6:$A$45,0))) -> 2.8 | T37: =IFERROR(INDEX('Search Terms'!$C$5:$C$137,MATCH($E37,'Search Terms'!$A$5:$A$137,0)),"") -> 0 | U37: =IFERROR(INDEX('Search Terms'!$B$5:$B$137,MATCH($E37,'Search Terms'!$A$5:$A$137,0)),"") -> Not Relevant | V37: =IFERROR(INDEX('Search Terms'!$D$5:$D$137,MATCH($E37,'Search Terms'!$A$5:$A$137,0)),"") -> 0 | W37: Pause now; rebuild as a size- and price-matched product-targeting lane | X37: The only competitor target with an order: 1 on 67 clicks, $103 per order, $1.54 a click, 90% of spend at Top of Search (+280%). All 10 product-targeting campaigns advertise Bouquet 60x80 whatever the competitor's size or price (MSGKV 60x80 sells at $29.99 vs our $34.99). | Y37: PAT by size and price match, Butterfly first, keyword-parity bids | Z37: Joseph approves; Shayan applies
A38: 4 RESTRUCTURE IN REBUILD | B38: boho scandinavian cotton blanket | C38: 143960123876477 | D38: =INDEX(Campaigns!$D$6:$D$45,MATCH($C38,Campaigns!$A$6:$A$45,0)) -> SP Exact keyword | E38: boho scandinavian cotton blanket | F38: =INDEX(Campaigns!$H$6:$H$45,MATCH($C38,Campaigns!$A$6:$A$45,0)) -> PAUSED | G38: =INDEX(Campaigns!$AU$6:$AU$45,MATCH($C38,Campaigns!$A$6:$A$45,0)) -> PAUSED | H38: =INDEX(Campaigns!$N$6:$N$45,MATCH($C38,Campaigns!$A$6:$A$45,0)) -> 77 | I38: =INDEX(Campaigns!$P$6:$P$45,MATCH($C38,Campaigns!$A$6:$A$45,0)) -> 1 | J38: =INDEX(Campaigns!$O$6:$O$45,MATCH($C38,Campaigns!$A$6:$A$45,0)) -> 62.97 | K38: =INDEX(Campaigns!$U$6:$U$45,MATCH($C38,Campaigns!$A$6:$A$45,0)) -> 2.3330863 | L38: =INDEX(Campaigns!$T$6:$T$45,MATCH($C38,Campaigns!$A$6:$A$45,0)) -> 0.81779221 | M38: =INDEX(Campaigns!$AH$6:$AH$45,MATCH($C38,Campaigns!$A$6:$A$45,0))+INDEX(Campaigns!$AJ$6:$AJ$45,MATCH($C38,Campaigns!$A$6:$A$45,0))+INDEX(Campaigns!$AL$6:$AL$45,MATCH($C38,Campaigns!$A$6:$A$45,0)) -> 62 | N38: 1 | O38: =INDEX(Campaigns!$W$6:$W$45,MATCH($C38,Campaigns!$A$6:$A$45,0)) -> 0 | P38: =INDEX(Campaigns!$Y$6:$Y$45,MATCH($C38,Campaigns!$A$6:$A$45,0)) -> 0 | Q38: =INDEX(Campaigns!$X$6:$X$45,MATCH($C38,Campaigns!$A$6:$A$45,0)) -> 0 | R38: =IF(I38=0,J38,0) -> 0 | S38: =IF(INDEX(Campaigns!$J$6:$J$45,MATCH($C38,Campaigns!$A$6:$A$45,0))="","",INDEX(Campaigns!$J$6:$J$45,MATCH($C38,Campaigns!$A$6:$A$45,0))) | T38: =IFERROR(INDEX('Search Terms'!$C$5:$C$137,MATCH($E38,'Search Terms'!$A$5:$A$137,0)),"") -> 122 | U38: =IFERROR(INDEX('Search Terms'!$B$5:$B$137,MATCH($E38,'Search Terms'!$A$5:$A$137,0)),"") -> Relevant | V38: =IFERROR(INDEX('Search Terms'!$D$5:$D$137,MATCH($E38,'Search Terms'!$A$5:$A$137,0)),"") -> 11 | W38: Keep paused; split in the rebuild | X38: 5 keywords in one campaign; 1 order on 62 on-Amazon clicks; TOS +450%. 'Scandinavian' does not describe this product. | Y38: 'boho cotton throw blanket' to the material lane; drop 'scandinavian' | Z38: Joseph approves; Shayan applies
... A66: 5 PAUSE (wasted spend) | B66: boho cotton throw blanket no fringe | C66: 194745831752971 | D66: =INDEX(Campaigns!$D$6:$D$45,MATCH($C66,Campaigns!$A$6:$A$45,0)) -> SP Exact keyword | E66: boho cotton throw blanket no fringe | F66: =INDEX(Campaigns!$H$6:$H$45,MATCH($C66,Campaigns!$A$6:$A$45,0)) -> ENABLED | G66: =INDEX(Campaigns!$AU$6:$AU$45,MATCH($C66,Campaigns!$A$6:$A$45,0)) -> PAUSED | H66: =INDEX(Campaigns!$N$6:$N$45,MATCH($C66,Campaigns!$A$6:$A$45,0)) -> 1 | I66: =INDEX(Campaigns!$P$6:$P$45,MATCH($C66,Campaigns!$A$6:$A$45,0)) -> 0 | J66: =INDEX(Campaigns!$O$6:$O$45,MATCH($C66,Campaigns!$A$6:$A$45,0)) -> 0.5 | K66: =INDEX(Campaigns!$U$6:$U$45,MATCH($C66,Campaigns!$A$6:$A$45,0)) | L66: =INDEX(Campaigns!$T$6:$T$45,MATCH($C66,Campaigns!$A$6:$A$45,0)) -> 0.5 | M66: =INDEX(Campaigns!$AH$6:$AH$45,MATCH($C66,Campaigns!$A$6:$A$45,0))+INDEX(Campaigns!$AJ$6:$AJ$45,MATCH($C66,Campaigns!$A$6:$A$45,0))+INDEX(Campaigns!$AL$6:$AL$45,MATCH($C66,Campaigns!$A$6:$A$45,0)) -> 1 | N66: 0 | O66: =INDEX(Campaigns!$W$6:$W$45,MATCH($C66,Campaigns!$A$6:$A$45,0)) -> 0 | P66: =INDEX(Campaigns!$Y$6:$Y$45,MATCH($C66,Campaigns!$A$6:$A$45,0)) -> 0 | Q66: =INDEX(Campaigns!$X$6:$X$45,MATCH($C66,Campaigns!$A$6:$A$45,0)) -> 0 | R66: =IF(I66=0,J66,0) -> 0.5 | S66: =IF(INDEX(Campaigns!$J$6:$J$45,MATCH($C66,Campaigns!$A$6:$A$45,0))="","",INDEX(Campaigns!$J$6:$J$45,MATCH($C66,Campaigns!$A$6:$A$45,0))) -> 3.8 | T66: =IFERROR(INDEX('Search Terms'!$C$5:$C$137,MATCH($E66,'Search Terms'!$A$5:$A$137,0)),"") -> 2 | U66: =IFERROR(INDEX('Search Terms'!$B$5:$B$137,MATCH($E66,'Search Terms'!$A$5:$A$137,0)),"") -> Relevant | V66: =IFERROR(INDEX('Search Terms'!$D$5:$D$137,MATCH($E66,'Search Terms'!$A$5:$A$137,0)),"") -> 58 | W66: Pause now | X66: 'No fringe' contradicts the product (it has tassels). 1 click. | Y66: Negative phrase 'no fringe' | Z66: Joseph approves; Shayan applies

Sheet Live Set
A1: What stays live: hold settings, budgets and the $25 a day ceiling
A2: Only the campaigns generating orders, plus brand defence. Bids are held (no tests). Top-of-search boosts are capped at the plan's +300%. Budgets are sized to cover several clicks a day at the real CPC, so a campaign does not run out after one click.
A4: Campaign | B4: Campaign ID | C4: State now | D4: New state | E4: Orders, last 30 days | F4: On-Amazon orders since launch | G4: Base bid (held) | H4: TOS boost now | I4: TOS boost new | J4: Max TOS bid now | K4: Max TOS bid new | L4: Real CPC, Top of Search | M4: Real CPC, product page | N4: Clicks per day (last 30 days) | O4: Spend per day (last 30 days) | P4: Daily budget now | Q4: Daily budget new | R4: TOS clicks the budget covers (real CPC) | S4: TOS clicks at the max bid | T4: Product-page clicks the budget covers | U4: Expected spend per day | V4: A click is worth (38% target ACoS)
A5: bohemian throw blanket | B5: 271118311398471 | C5: =INDEX(Campaigns!$H$6:$H$45,MATCH($B5,Campaigns!$A$6:$A$45,0)) -> ENABLED | D5: =INDEX(Campaigns!$AU$6:$AU$45,MATCH($B5,Campaigns!$A$6:$A$45,0)) -> ENABLED | E5: =INDEX(Campaigns!$Y$6:$Y$45,MATCH($B5,Campaigns!$A$6:$A$45,0)) -> 1 | F5: 4 | G5: 0.52 | H5: 2.8 | I5: 2.8 | J5: =G5*(1+H5) -> 1.976 | K5: =G5*(1+I5) -> 1.976 | L5: =IF(INDEX(Campaigns!$AH$6:$AH$45,MATCH($B5,Campaigns!$A$6:$A$45,0))=0,0,INDEX(Campaigns!$AI$6:$AI$45,MATCH($B5,Campaigns!$A$6:$A$45,0))/INDEX(Campaigns!$AH$6:$AH$45,MATCH($B5,Campaigns!$A$6:$A$45,0))) -> 1.58 | M5: =IF(INDEX(Campaigns!$AJ$6:$AJ$45,MATCH($B5,Campaigns!$A$6:$A$45,0))=0,0,INDEX(Campaigns!$AK$6:$AK$45,MATCH($B5,Campaigns!$A$6:$A$45,0))/INDEX(Campaigns!$AJ$6:$AJ$45,MATCH($B5,Campaigns!$A$6:$A$45,0))) -> 0.53283871 | N5: =INDEX(Campaigns!$W$6:$W$45,MATCH($B5,Campaigns!$A$6:$A$45,0))/30 -> 3.0666667 | O5: =INDEX(Campaigns!$X$6:$X$45,MATCH($B5,Campaigns!$A$6:$A$45,0))/30 -> 2.3056667 | P5: 9.41 | Q5: 10 | R5: =IF(L5=0,"",Q5/L5) -> 6.3291139 | S5: =IF(K5=0,"",Q5/K5) -> 5.0607287 | T5: =IF(M5=0,"",Q5/M5) -> 18.767405 | U5: =MIN(Q5,MAX(O5,INDEX(Campaigns!$O$6:$O$45,MATCH($B5,Campaigns!$A$6:$A$45,0))/Rules!$B$25)) -> 2.3056667 | V5: =Rules!$B$19*IF(INDEX(Campaigns!$P$6:$P$45,MATCH($B5,Campaigns!$A$6:$A$45,0))=0,Rules!$B$35,INDEX(Campaigns!$Q$6:$Q$45,MATCH($B5,Campaigns!$A$6:$A$45,0))/INDEX(Campaigns!$P$6:$P$45,MATCH($B5,Campaigns!$A$6:$A$45,0)))*(F5+Rules!$B$36*Rules!$B$20)/(INDEX(Campaigns!$AH$6:$AH$45,MATCH($B5,Campaigns!$A$6:$A$45,0))+INDEX(Campaigns!$AJ$6:$AJ$45,MATCH($B5,Campaigns!$A$6:$A$45,0))+INDEX(Campaigns!$AL$6:$AL$45,MATCH($B5,Campaigns!$A$6:$A$45,0))+Rules!$B$20) -> 0.28441653
A6: bohemian blanket | B6: 274384612784893 | C6: =INDEX(Campaigns!$H$6:$H$45,MATCH($B6,Campaigns!$A$6:$A$45,0)) -> PAUSED | D6: =INDEX(Campaigns!$AU$6:$AU$45,MATCH($B6,Campaigns!$A$6:$A$45,0)) -> ENABLED | E6: =INDEX(Campaigns!$Y$6:$Y$45,MATCH($B6,Campaigns!$A$6:$A$45,0)) -> 2 | F6: 2 | G6: 0.69 | H6: 4.5 | I6: 3 | J6: =G6*(1+H6) -> 3.795 | K6: =G6*(1+I6) -> 2.76 | L6: =IF(INDEX(Campaigns!$AH$6:$AH$45,MATCH($B6,Campaigns!$A$6:$A$45,0))=0,0,INDEX(Campaigns!$AI$6:$AI$45,MATCH($B6,Campaigns!$A$6:$A$45,0))/INDEX(Campaigns!$AH$6:$AH$45,MATCH($B6,Campaigns!$A$6:$A$45,0))) -> 1.2410526 | M6: =IF(INDEX(Campaigns!$AJ$6:$AJ$45,MATCH($B6,Campaigns!$A$6:$A$45,0))=0,0,INDEX(Campaigns!$AK$6:$AK$45,MATCH($B6,Campaigns!$A$6:$A$45,0))/INDEX(Campaigns!$AJ$6:$AJ$45,MATCH($B6,Campaigns!$A$6:$A$45,0))) -> 0.69 | N6: =INDEX(Campaigns!$W$6:$W$45,MATCH($B6,Campaigns!$A$6:$A$45,0))/30 -> 0.93333333 | O6: =INDEX(Campaigns!$X$6:$X$45,MATCH($B6,Campaigns!$A$6:$A$45,0))/30 -> 0.92366667 | P6: 6.38 | Q6: 10 | R6: =IF(L6=0,"",Q6/L6) -> 8.057676 | S6: =IF(K6=0,"",Q6/K6) -> 3.6231884 | T6: =IF(M6=0,"",Q6/M6) -> 14.492754 | U6: =MIN(Q6,MAX(O6,INDEX(Campaigns!$O$6:$O$45,MATCH($B6,Campaigns!$A$6:$A$45,0))/Rules!$B$25)) -> 0.92366667 | V6: =Rules!$B$19*IF(INDEX(Campaigns!$P$6:$P$45,MATCH($B6,Campaigns!$A$6:$A$45,0))=0,Rules!$B$35,INDEX(Campaigns!$Q$6:$Q$45,MATCH($B6,Campaigns!$A$6:$A$45,0))/INDEX(Campaigns!$P$6:$P$45,MATCH($B6,Campaigns!$A$6:$A$45,0)))*(F6+Rules!$B$36*Rules!$B$20)/(INDEX(Campaigns!$AH$6:$AH$45,MATCH($B6,Campaigns!$A$6:$A$45,0))+INDEX(Campaigns!$AJ$6:$AJ$45,MATCH($B6,Campaigns!$A$6:$A$45,0))+INDEX(Campaigns!$AL$6:$AL$45,MATCH($B6,Campaigns!$A$6:$A$45,0))+Rules!$B$20) -> 0.31101246
A7: sleephoria boho throw blanket | B7: 94080520861158 | C7: =INDEX(Campaigns!$H$6:$H$45,MATCH($B7,Campaigns!$A$6:$A$45,0)) -> ENABLED | D7: =INDEX(Campaigns!$AU$6:$AU$45,MATCH($B7,Campaigns!$A$6:$A$45,0)) -> ENABLED | E7: =INDEX(Campaigns!$Y$6:$Y$45,MATCH($B7,Campaigns!$A$6:$A$45,0)) -> 0 | F7: 0 | G7: 0.68 | H7: 3.8 | I7: 3 | J7: =G7*(1+H7) -> 3.264 | K7: =G7*(1+I7) -> 2.72 | L7: =IF(INDEX(Campaigns!$AH$6:$AH$45,MATCH($B7,Campaigns!$A$6:$A$45,0))=0,0,INDEX(Campaigns!$AI$6:$AI$45,MATCH($B7,Campaigns!$A$6:$A$45,0))/INDEX(Campaigns!$AH$6:$AH$45,MATCH($B7,Campaigns!$A$6:$A$45,0))) -> 0.345 | M7: =IF(INDEX(Campaigns!$AJ$6:$AJ$45,MATCH($B7,Campaigns!$A$6:$A$45,0))=0,0,INDEX(Campaigns!$AK$6:$AK$45,MATCH($B7,Campaigns!$A$6:$A$45,0))/INDEX(Campaigns!$AJ$6:$AJ$45,MATCH($B7,Campaigns!$A$6:$A$45,0))) -> 0 | N7: =INDEX(Campaigns!$W$6:$W$45,MATCH($B7,Campaigns!$A$6:$A$45,0))/30 -> 0 | O7: =INDEX(Campaigns!$X$6:$X$45,MATCH($B7,Campaigns!$A$6:$A$45,0))/30 -> 0 | P7: 11.32 | Q7: 5 | R7: =IF(L7=0,"",Q7/L7) -> 14.492754 | S7: =IF(K7=0,"",Q7/K7) -> 1.8382353 | T7: =IF(M7=0,"",Q7/M7) | U7: =MIN(Q7,MAX(O7,INDEX(Campaigns!$O$6:$O$45,MATCH($B7,Campaigns!$A$6:$A$45,0))/Rules!$B$25)) -> 0.023793103 | V7: =Rules!$B$19*IF(INDEX(Campaigns!$P$6:$P$45,MATCH($B7,Campaigns!$A$6:$A$45,0))=0,Rules!$B$35,INDEX(Campaigns!$Q$6:$Q$45,MATCH($B7,Campaigns!$A$6:$A$45,0))/INDEX(Campaigns!$P$6:$P$45,MATCH($B7,Campaigns!$A$6:$A$45,0)))*(F7+Rules!$B$36*Rules!$B$20)/(INDEX(Campaigns!$AH$6:$AH$45,MATCH($B7,Campaigns!$A$6:$A$45,0))+INDEX(Campaigns!$AJ$6:$AJ$45,MATCH($B7,Campaigns!$A$6:$A$45,0))+INDEX(Campaigns!$AL$6:$AL$45,MATCH($B7,Campaigns!$A$6:$A$45,0))+Rules!$B$20) -> 0.13979345
A8: TOTAL live set | E8: =SUM(E5:E7) -> 3 | F8: =SUM(F5:F7) -> 6 | N8: =SUM(N5:N7) -> 4 | O8: =SUM(O5:O7) -> 3.2293333 | P8: =SUM(P5:P7) -> 27.11 | Q8: =SUM(Q5:Q7) -> 25 | U8: =SUM(U5:U7) -> 3.2531264
A10: Ceiling, expected spend and savings
A11: Hard portfolio ceiling per day (Phase 0 / D4, Rules tab) | B11: =Rules!$B$5 -> 25
A12: Ceiling per week | B12: =B11*7 -> 175
A13: Sum of live campaign budgets per day | B13: =Q8 -> 25
A14: Status | B14: =IF(B13<=B11,"Budgets fit inside the ceiling","Budgets exceed the ceiling: the portfolio cap stops spend at "&TEXT(B11,"$0")&" a day") -> Budgets fit inside the ceiling
A15: Expected spend per day (limited by search volume) | B15: =U8 -> 3.2531264
A16: Expected spend per week | B16: =B15*7 -> 22.771885
A17: Expected spend per month | B17: =B15*30 -> 97.593793
A18: Maximum possible spend per month (budgets fully used) | B18: =MIN(B13,B11)*30 -> 750
A19: Last 30 days: total spend | B19: =Campaigns!X46 -> 487.49
A20: Last 30 days: spend on campaigns now paused or kept paused | B20: =SUMIFS(Campaigns!$X$6:$X$45,Campaigns!$AU$6:$AU$45,"PAUSED") -> 390.61
A21: Expected cut vs the last 30 days | B21: =IF(B19=0,0,1-B17/B19) -> 0.7998035
A22: D4 weekly ceiling | B22: =Rules!$B$7 -> 175
A23: Weekly headroom at full budgets | B23: =B22-MIN(B13,B11)*7 -> 0
A25: Notes
A26: Budgets are ceilings, not spend targets. These are exact-match terms with about 20 to 25 searches a day each, so actual spend should stay near the last 30 days' rate; the budgets only stop a campaign going out of budget after one or two top-of-search clicks.
A27: Bids are held as they are (no bid tests). Only the two top-of-search boosts above the plan's +300% are brought down, so a single click can cost at most about $2.76.
A28: The +450% to +300% and +380% to +300% steps are larger than the 20-point rule in config/thresholds.yml, so they need Joseph's sign-off (in the bulk file as two 'Bidding Adjustment' rows).
A29: 'A click is worth' is for reference only: on the current listing no live campaign earns its clicks back. That is accepted while the account holds until the rebuild.
A30: Set the $25 ceiling as the 'SLEEPHORIA - Boho Blanket' portfolio budget in the console (the bulk file cannot set it). Then leave everything for 14 days.

Sheet Core Term Test
A1: Core terms: is it the bid, the placement, or the listing? (evidence before any pause or bid cut)
A2: Market columns: Amazon Search Query Performance (Brand Analytics) for the whole search, 23 Aug to 17 Oct (weekly). Ours: our 6 live ASINs. PPC columns: our search-term report since launch. SQP is a sample; read it as rates.
A4: Search query | B4: Weeks | C4: Market searches | D4: Market impressions | E4: Market clicks | F4: Market cart adds | G4: Market purchases | H4: Market cart-add rate | I4: Market CVR | J4: Our impressions | K4: Our impression share | L4: Our clicks | M4: Our click share | N4: Our cart adds | O4: Cart adds expected at market rate | P4: Chance of this few cart adds | Q4: Our purchases (SQP) | R4: PPC clicks since launch | S4: PPC orders | T4: PPC spend | U4: CPC paid | V4: Organic rank | W4: A click is worth (target ACoS, market CVR) | X4: Break-even CPC (market CVR) | Y4: Paid vs worth | Z4: Read
A5: boho throw blanket | B5: 8 | C5: 53763 | D5: 1764878 | E5: 21938 | F5: 2842 | G5: 360 | H5: =IF(E5=0,0,F5/E5) -> 0.1295469 | I5: =IF(E5=0,0,G5/E5) -> 0.016409882 | J5: 6756 | K5: =IF(D5=0,0,J5/D5) -> 0.0038280266 | L5: 38 | M5: =IF(E5=0,0,L5/E5) -> 0.0017321543 | N5: 0 | O5: =L5*H5 -> 4.9227824 | P5: =BINOMDIST(N5,L5,H5,TRUE()) -> 0.0051324438 | Q5: 0 | R5: =IFERROR(INDEX('Search Terms'!$F$5:$F$137,MATCH($A5,'Search Terms'!$A$5:$A$137,0)),0) -> 42 | S5: =IFERROR(INDEX('Search Terms'!$G$5:$G$137,MATCH($A5,'Search Terms'!$A$5:$A$137,0)),0) -> 0 | T5: =IFERROR(INDEX('Search Terms'!$H$5:$H$137,MATCH($A5,'Search Terms'!$A$5:$A$137,0)),0) -> 39.35 | U5: =IF(R5=0,0,T5/R5) -> 0.93690476 | V5: =IFERROR(INDEX('Search Terms'!$D$5:$D$137,MATCH($A5,'Search Terms'!$A$5:$A$137,0)),"") -> 99 | W5: =Rules!$B$19*Rules!$B$35*I5 -> 0.19324606 | X5: =Rules!$B$34*I5 -> 0.064080591 | Y5: =IF(W5=0,"",U5/W5) -> 4.8482478 | Z5: Listing problem on this search: 0 cart adds where about 5 were expected. Bid cuts cannot fix it. Keep paused; first retest after the rebuild.
A6: boho blanket | B6: 8 | C6: 31570 | D6: 1162248 | E6: 10184 | F6: 1193 | G6: 171 | H6: =IF(E6=0,0,F6/E6) -> 0.11714454 | I6: =IF(E6=0,0,G6/E6) -> 0.016791045 | J6: 3089 | K6: =IF(D6=0,0,J6/D6) -> 0.0026577804 | L6: 29 | M6: =IF(E6=0,0,L6/E6) -> 0.0028476041 | N6: 3 | O6: =L6*H6 -> 3.3971917 | P6: =BINOMDIST(N6,L6,H6,TRUE()) -> 0.55365087 | Q6: 0 | R6: =IFERROR(INDEX('Search Terms'!$F$5:$F$137,MATCH($A6,'Search Terms'!$A$5:$A$137,0)),0) -> 179 | S6: =IFERROR(INDEX('Search Terms'!$G$5:$G$137,MATCH($A6,'Search Terms'!$A$5:$A$137,0)),0) -> 2 | T6: =IFERROR(INDEX('Search Terms'!$H$5:$H$137,MATCH($A6,'Search Terms'!$A$5:$A$137,0)),0) -> 132.1 | U6: =IF(R6=0,0,T6/R6) -> 0.73798883 | V6: =IFERROR(INDEX('Search Terms'!$D$5:$D$137,MATCH($A6,'Search Terms'!$A$5:$A$137,0)),"") -> 133 | W6: =Rules!$B$19*Rules!$B$35*I6 -> 0.1977347 | X6: =Rules!$B$34*I6 -> 0.06556903 | Y6: =IF(W6=0,"",U6/W6) -> 3.7322171 | Z6: Cart adds normal for the market; orders came only from product pages. Retest after the rebuild.
A7: boho throw | B7: 7 | C7: 5417 | D7: 154631 | E7: 2731 | F7: 311 | G7: 58 | H7: =IF(E7=0,0,F7/E7) -> 0.1138777 | I7: =IF(E7=0,0,G7/E7) -> 0.021237642 | J7: 1542 | K7: =IF(D7=0,0,J7/D7) -> 0.0099721272 | L7: 34 | M7: =IF(E7=0,0,L7/E7) -> 0.012449652 | N7: 1 | O7: =L7*H7 -> 3.8718418 | P7: =BINOMDIST(N7,L7,H7,TRUE()) -> 0.088046508 | Q7: 1 | R7: =IFERROR(INDEX('Search Terms'!$F$5:$F$137,MATCH($A7,'Search Terms'!$A$5:$A$137,0)),0) -> 113 | S7: =IFERROR(INDEX('Search Terms'!$G$5:$G$137,MATCH($A7,'Search Terms'!$A$5:$A$137,0)),0) -> 1 | T7: =IFERROR(INDEX('Search Terms'!$H$5:$H$137,MATCH($A7,'Search Terms'!$A$5:$A$137,0)),0) -> 81.58 | U7: =IF(R7=0,0,T7/R7) -> 0.7219469 | V7: =IFERROR(INDEX('Search Terms'!$D$5:$D$137,MATCH($A7,'Search Terms'!$A$5:$A$137,0)),"") -> 94 | W7: =Rules!$B$19*Rules!$B$35*I7 -> 0.25009872 | X7: =Rules!$B$34*I7 -> 0.082932992 | Y7: =IF(W7=0,"",U7/W7) -> 2.8866477 | Z7: Fewer cart adds than the market (1 vs about 4). Retest first after the rebuild: best PPC CVR of the core terms.
A8: throw blanket boho | B8: 7 | C8: 4113 | D8: 125312 | E8: 1921 | F8: 242 | G8: 29 | H8: =IF(E8=0,0,F8/E8) -> 0.12597605 | I8: =IF(E8=0,0,G8/E8) -> 0.015096304 | J8: 893 | K8: =IF(D8=0,0,J8/D8) -> 0.007126213 | L8: 14 | M8: =IF(E8=0,0,L8/E8) -> 0.0072878709 | N8: 1 | O8: =L8*H8 -> 1.7636648 | P8: =BINOMDIST(N8,L8,H8,TRUE()) -> 0.45817021 | Q8: 0 | R8: =IFERROR(INDEX('Search Terms'!$F$5:$F$137,MATCH($A8,'Search Terms'!$A$5:$A$137,0)),0) -> 69 | S8: =IFERROR(INDEX('Search Terms'!$G$5:$G$137,MATCH($A8,'Search Terms'!$A$5:$A$137,0)),0) -> 0 | T8: =IFERROR(INDEX('Search Terms'!$H$5:$H$137,MATCH($A8,'Search Terms'!$A$5:$A$137,0)),0) -> 59.04 | U8: =IF(R8=0,0,T8/R8) -> 0.85565217 | V8: =IFERROR(INDEX('Search Terms'!$D$5:$D$137,MATCH($A8,'Search Terms'!$A$5:$A$137,0)),"") -> 125 | W8: =Rules!$B$19*Rules!$B$35*I8 -> 0.1777771 | X8: =Rules!$B$34*I8 -> 0.058951067 | Y8: =IF(W8=0,"",U8/W8) -> 4.813062 | Z8: Few clicks, 1 cart add. Covered by the 'boho throw blanket' retest.
A9: boho blanket throw | B9: 6 | C9: 2927 | D9: 79741 | E9: 1468 | F9: 199 | G9: 35 | H9: =IF(E9=0,0,F9/E9) -> 0.13555858 | I9: =IF(E9=0,0,G9/E9) -> 0.023841962 | J9: 852 | K9: =IF(D9=0,0,J9/D9) -> 0.010684591 | L9: 22 | M9: =IF(E9=0,0,L9/E9) -> 0.014986376 | N9: 1 | O9: =L9*H9 -> 2.9822888 | P9: =BINOMDIST(N9,L9,H9,TRUE()) -> 0.18052553 | Q9: 0 | R9: =IFERROR(INDEX('Search Terms'!$F$5:$F$137,MATCH($A9,'Search Terms'!$A$5:$A$137,0)),0) -> 98 | S9: =IFERROR(INDEX('Search Terms'!$G$5:$G$137,MATCH($A9,'Search Terms'!$A$5:$A$137,0)),0) -> 0 | T9: =IFERROR(INDEX('Search Terms'!$H$5:$H$137,MATCH($A9,'Search Terms'!$A$5:$A$137,0)),0) -> 81.77 | U9: =IF(R9=0,0,T9/R9) -> 0.83438776 | V9: =IFERROR(INDEX('Search Terms'!$D$5:$D$137,MATCH($A9,'Search Terms'!$A$5:$A$137,0)),"") -> 120 | W9: =Rules!$B$19*Rules!$B$35*I9 -> 0.28076771 | X9: =Rules!$B$34*I9 -> 0.093102861 | Y9: =IF(W9=0,"",U9/W9) -> 2.9718081 | Z9: 1 cart add on 22 clicks; 0 PPC orders on 98 clicks. No separate campaign in the rebuild.
A10: bohemian throw blanket | B10: 8 | C10: 2828 | D10: 83010 | E10: 1390 | F10: 184 | G10: 18 | H10: =IF(E10=0,0,F10/E10) -> 0.1323741 | I10: =IF(E10=0,0,G10/E10) -> 0.01294964 | J10: 1427 | K10: =IF(D10=0,0,J10/D10) -> 0.0171907 | L10: 24 | M10: =IF(E10=0,0,L10/E10) -> 0.017266187 | N10: 3 | O10: =L10*H10 -> 3.1769784 | P10: =BINOMDIST(N10,L10,H10,TRUE()) -> 0.60510068 | Q10: 0 | R10: =IFERROR(INDEX('Search Terms'!$F$5:$F$137,MATCH($A10,'Search Terms'!$A$5:$A$137,0)),0) -> 182 | S10: =IFERROR(INDEX('Search Terms'!$G$5:$G$137,MATCH($A10,'Search Terms'!$A$5:$A$137,0)),0) -> 4 | T10: =IFERROR(INDEX('Search Terms'!$H$5:$H$137,MATCH($A10,'Search Terms'!$A$5:$A$137,0)),0) -> 124.87 | U10: =IF(R10=0,0,T10/R10) -> 0.6860989 | V10: =IFERROR(INDEX('Search Terms'!$D$5:$D$137,MATCH($A10,'Search Terms'!$A$5:$A$137,0)),"") -> 79 | W10: =Rules!$B$19*Rules!$B$35*I10 -> 0.15249755 | X10: =Rules!$B$34*I10 -> 0.050568345 | Y10: =IF(W10=0,"",U10/W10) -> 4.4990814 | Z10: Cart adds in line with the market. Converting in PPC: keep live at a lower bid.
A11: bohemian blanket | B11: 7 | C11: 1719 | D11: 51710 | E11: 671 | F11: 75 | G11: 10 | H11: =IF(E11=0,0,F11/E11) -> 0.11177347 | I11: =IF(E11=0,0,G11/E11) -> 0.01490313 | J11: 690 | K11: =IF(D11=0,0,J11/D11) -> 0.013343647 | L11: 14 | M11: =IF(E11=0,0,L11/E11) -> 0.020864382 | N11: 1 | O11: =L11*H11 -> 1.5648286 | P11: =BINOMDIST(N11,L11,H11,TRUE()) -> 0.52543128 | Q11: 0 | R11: =IFERROR(INDEX('Search Terms'!$F$5:$F$137,MATCH($A11,'Search Terms'!$A$5:$A$137,0)),0) -> 41 | S11: =IFERROR(INDEX('Search Terms'!$G$5:$G$137,MATCH($A11,'Search Terms'!$A$5:$A$137,0)),0) -> 1 | T11: =IFERROR(INDEX('Search Terms'!$H$5:$H$137,MATCH($A11,'Search Terms'!$A$5:$A$137,0)),0) -> 35.93 | U11: =IF(R11=0,0,T11/R11) -> 0.87634146 | V11: =IFERROR(INDEX('Search Terms'!$D$5:$D$137,MATCH($A11,'Search Terms'!$A$5:$A$137,0)),"") -> 85 | W11: =Rules!$B$19*Rules!$B$35*I11 -> 0.17550224 | X11: =Rules!$B$34*I11 -> 0.058196721 | Y11: =IF(W11=0,"",U11/W11) -> 4.993335 | Z11: Small sample; best PPC CVR (4%). Keep live at the worth-based bid.
A12: boho throws | B12: 7 | C12: 1768 | D12: 53387 | E12: 985 | F12: 73 | G12: 13 | H12: =IF(E12=0,0,F12/E12) -> 0.074111675 | I12: =IF(E12=0,0,G12/E12) -> 0.01319797 | J12: 540 | K12: =IF(D12=0,0,J12/D12) -> 0.010114822 | L12: 12 | M12: =IF(E12=0,0,L12/E12) -> 0.012182741 | N12: 1 | O12: =L12*H12 -> 0.8893401 | P12: =BINOMDIST(N12,L12,H12,TRUE()) -> 0.77817266 | Q12: 1 | R12: =IFERROR(INDEX('Search Terms'!$F$5:$F$137,MATCH($A12,'Search Terms'!$A$5:$A$137,0)),0) -> 11 | S12: =IFERROR(INDEX('Search Terms'!$G$5:$G$137,MATCH($A12,'Search Terms'!$A$5:$A$137,0)),0) -> 2 | T12: =IFERROR(INDEX('Search Terms'!$H$5:$H$137,MATCH($A12,'Search Terms'!$A$5:$A$137,0)),0) -> 10.44 | U12: =IF(R12=0,0,T12/R12) -> 0.94909091 | V12: =IFERROR(INDEX('Search Terms'!$D$5:$D$137,MATCH($A12,'Search Terms'!$A$5:$A$137,0)),"") -> 80 | W12: =Rules!$B$19*Rules!$B$35*I12 -> 0.15542193 | X12: =Rules!$B$34*I12 -> 0.051538071 | Y12: =IF(W12=0,"",U12/W12) -> 6.1065444 | Z12: 1 SQP purchase; 2 PPC orders on 11 clicks. Include in the rebuild's core exact set.
A13: boho cotton blanket | B13: 7 | C13: 1365 | D13: 38806 | E13: 878 | F13: 45 | G13: 8 | H13: =IF(E13=0,0,F13/E13) -> 0.051252847 | I13: =IF(E13=0,0,G13/E13) -> 0.0091116173 | J13: 640 | K13: =IF(D13=0,0,J13/D13) -> 0.016492295 | L13: 29 | M13: =IF(E13=0,0,L13/E13) -> 0.033029613 | N13: 1 | O13: =L13*H13 -> 1.4863326 | P13: =BINOMDIST(N13,L13,H13,TRUE()) -> 0.55811896 | Q13: 0 | R13: =IFERROR(INDEX('Search Terms'!$F$5:$F$137,MATCH($A13,'Search Terms'!$A$5:$A$137,0)),0) -> 35 | S13: =IFERROR(INDEX('Search Terms'!$G$5:$G$137,MATCH($A13,'Search Terms'!$A$5:$A$137,0)),0) -> 1 | T13: =IFERROR(INDEX('Search Terms'!$H$5:$H$137,MATCH($A13,'Search Terms'!$A$5:$A$137,0)),0) -> 37.34 | U13: =IF(R13=0,0,T13/R13) -> 1.0668571 | V13: =IFERROR(INDEX('Search Terms'!$D$5:$D$137,MATCH($A13,'Search Terms'!$A$5:$A$137,0)),"") -> 55 | W13: =Rules!$B$19*Rules!$B$35*I13 -> 0.10730023 | X13: =Rules!$B$34*I13 -> 0.035580866 | Y13: =IF(W13=0,"",U13/W13) -> 9.9427295 | Z13: Cart-add rate is low for the whole market (5%). Material lane, low priority.
A14: boho throw blankets for couch | B14: 7 | C14: 1537 | D14: 41780 | E14: 879 | F14: 83 | G14: 15 | H14: =IF(E14=0,0,F14/E14) -> 0.094425484 | I14: =IF(E14=0,0,G14/E14) -> 0.017064846 | J14: 940 | K14: =IF(D14=0,0,J14/D14) -> 0.022498803 | L14: 23 | M14: =IF(E14=0,0,L14/E14) -> 0.026166098 | N14: 3 | O14: =L14*H14 -> 2.1717861 | P14: =BINOMDIST(N14,L14,H14,TRUE()) -> 0.8332473 | Q14: 1 | R14: =IFERROR(INDEX('Search Terms'!$F$5:$F$137,MATCH($A14,'Search Terms'!$A$5:$A$137,0)),0) -> 108 | S14: =IFERROR(INDEX('Search Terms'!$G$5:$G$137,MATCH($A14,'Search Terms'!$A$5:$A$137,0)),0) -> 1 | T14: =IFERROR(INDEX('Search Terms'!$H$5:$H$137,MATCH($A14,'Search Terms'!$A$5:$A$137,0)),0) -> 85.08 | U14: =IF(R14=0,0,T14/R14) -> 0.78777778 | V14: =IFERROR(INDEX('Search Terms'!$D$5:$D$137,MATCH($A14,'Search Terms'!$A$5:$A$137,0)),"") -> 85 | W14: =Rules!$B$19*Rules!$B$35*I14 -> 0.20095904 | X14: =Rules!$B$34*I14 -> 0.066638225 | Y14: =IF(W14=0,"",U14/W14) -> 3.9200912 | Z14: Cart adds normal (3 on 23). Couch lane in the rebuild.
A16: Deep dive: 'boho throw blanket' (core term, 42 clicks, 0 orders)
A17: Check | B17: What the data says | G17: Conclusion
A18: Portable CPC (what a click is worth) | B18: Market CVR 1.64% x average price $30.99 x 38% target ACoS = about $0.19 a click (cell W5). At break-even it is about $0.06. We paid $0.94 on average. | G18: No bid level makes this term pay on the current page.
A19: Bid and bid adjustments | B19: Campaign paused; Fixed bids; TOS modifier +300%; budget $30 a day. Top of Search clicks cost about $1.33, product-page clicks about $0.61 (Command Center, campaign-level split). | G19: The +300% modifier bought expensive TOS clicks that did not convert.
A20: Placement performance | B20: About 18 TOS clicks and 18 product-page clicks, 5 rest-of-search, 0 Off-Amazon; 0 orders in every placement. | G20: Not a placement mix problem: nothing converted anywhere.
A21: Search-term relevance | B21: Rated Relevant; 9,420 searches a month (H10), about 6,000 to 7,000 a week in SQP; 25 of 35 page-one results are natural or woven throws, median $29.69 (pack file 06). | G21: The term fits the product. Do not negate it.
A22: Conversion potential | B22: Market: 13% of clicks add to cart, 1.64% buy. Ours: 0 cart adds on 38 clicks; about 5 expected; chance of 0 by luck about 0.5% (cell P5). Organic rank about 99. | G22: Shoppers on this search reject our listing before the cart. Fix the page (main image, title, price-to-value, A+), then retest.
A23: Decision | B23: Keep paused (already paused). No negative, no archive. First exact campaign in the rebuild at the worth-based bid, Butterfly 50x60. | G23: Pass mark after the rebuild: 2+ cart adds per 20 clicks and 1+ order per 50 clicks; otherwise stop.

Sheet Search Terms
A1: Every search term since launch: what it cost, what it returned, and what happens to it in the rebuild
A2: 133 terms, 24 Aug to 22 Oct (Command Center). Organic rank is the median over the window (blank when unranked on half or more of the days). 'Status' is a formula; 'Rebuild treatment' is the recommendation.
A4: Search term | B4: Relevancy (MKL) | C4: Search volume / month | D4: Organic rank (median) | E4: Impr. | F4: Clicks | G4: Orders | H4: Spend | I4: Sales | J4: CPC | K4: CVR | L4: ACoS | M4: Off-Amazon share of clicks | N4: Status | O4: Rebuild treatment
A5: boho king size blanket | B5: Lower Relevant | C5: 94 | D5: 113 | E5: 16412 | F5: 1041 | G5: 9 | H5: 212.99 | I5: 282.91 | J5: =IF(F5=0,0,H5/F5) -> 0.20460134 | K5: =IF(F5=0,0,G5/F5) -> 0.0086455331 | L5: =IF(I5=0,"",H5/I5) -> 0.75285426 | M5: 0.96613358 | N5: =IF(G5>0,"Converting",IF(F5>=Rules!$B$10,"Waste: 20+ clicks, 0 orders",IF(H5>0,"Waste so far (under 20 clicks)",""))) -> Converting | O5: Orders came via Off-Amazon traffic (stopped): do not harvest on Amazon
A6: boho blanket | B6: Relevant | C6: 4932 | D6: 133 | E6: 22178 | F6: 179 | G6: 2 | H6: 132.1 | I6: 61.98 | J6: =IF(F6=0,0,H6/F6) -> 0.73798883 | K6: =IF(F6=0,0,G6/F6) -> 0.011173184 | L6: =IF(I6=0,"",H6/I6) -> 2.1313327 | M6: 0 | N6: =IF(G6>0,"Converting",IF(F6>=Rules!$B$10,"Waste: 20+ clicks, 0 orders",IF(H6>0,"Waste so far (under 20 clicks)",""))) -> Converting | O6: Converting: own exact campaign in the rebuild
A7: bohemian throw blanket | B7: Relevant | C7: 725 | D7: 79 | E7: 17704 | F7: 182 | G7: 4 | H7: 124.87 | I7: 150.95 | J7: =IF(F7=0,0,H7/F7) -> 0.6860989 | K7: =IF(F7=0,0,G7/F7) -> 0.021978022 | L7: =IF(I7=0,"",H7/I7) -> 0.82722756 | M7: 0 | N7: =IF(G7>0,"Converting",IF(F7>=Rules!$B$10,"Waste: 20+ clicks, 0 orders",IF(H7>0,"Waste so far (under 20 clicks)",""))) -> Converting | O7: Converting: own exact campaign in the rebuild
A8: boho throw blankets for couch | B8: Relevant | C8: 497 | D8: 85 | E8: 4893 | F8: 108 | G8: 1 | H8: 85.08 | I8: 26.99 | J8: =IF(F8=0,0,H8/F8) -> 0.78777778 | K8: =IF(F8=0,0,G8/F8) -> 0.0092592593 | L8: =IF(I8=0,"",H8/I8) -> 3.1522786 | M8: 0.88655462 | N8: =IF(G8>0,"Converting",IF(F8>=Rules!$B$10,"Waste: 20+ clicks, 0 orders",IF(H8>0,"Waste so far (under 20 clicks)",""))) -> Converting | O8: Orders came via Off-Amazon traffic (stopped): do not harvest on Amazon
A9: boho blanket throw | B9: Relevant | C9: 869 | D9: 120 | E9: 11748 | F9: 98 | G9: 0 | H9: 81.77 | I9: 0 | J9: =IF(F9=0,0,H9/F9) -> 0.83438776 | K9: =IF(F9=0,0,G9/F9) -> 0 | L9: =IF(I9=0,"",H9/I9) | M9: 0 | N9: =IF(G9>0,"Converting",IF(F9>=Rules!$B$10,"Waste: 20+ clicks, 0 orders",IF(H9>0,"Waste so far (under 20 clicks)",""))) -> Waste: 20+ clicks, 0 orders | O9: Core intent: retest after the rebuild (do not negate)
A10: boho throw | B10: Relevant | C10: 1229 | D10: 94 | E10: 9372 | F10: 113 | G10: 1 | H10: 81.58 | I10: 26.99 | J10: =IF(F10=0,0,H10/F10) -> 0.7219469 | K10: =IF(F10=0,0,G10/F10) -> 0.0088495575 | L10: =IF(I10=0,"",H10/I10) -> 3.022601 | M10: 0 | N10: =IF(G10>0,"Converting",IF(F10>=Rules!$B$10,"Waste: 20+ clicks, 0 orders",IF(H10>0,"Waste so far (under 20 clicks)",""))) -> Converting | O10: Converting: own exact campaign in the rebuild
A11: boho throw blanket for couch | B11: Relevant | C11: 167 | E11: 5248 | F11: 368 | G11: 4 | H11: 73.9 | I11: 123.96 | J11: =IF(F11=0,0,H11/F11) -> 0.20081522 | K11: =IF(F11=0,0,G11/F11) -> 0.010869565 | L11: =IF(I11=0,"",H11/I11) -> 0.59616005 | M11: 0.88655462 | N11: =IF(G11>0,"Converting",IF(F11>=Rules!$B$10,"Waste: 20+ clicks, 0 orders",IF(H11>0,"Waste so far (under 20 clicks)",""))) -> Converting | O11: Orders came via Off-Amazon traffic (stopped): do not harvest on Amazon
A12: boho blanket king | B12: Highly Relevant | C12: 301 | E12: 2989 | F12: 128 | G12: 3 | H12: 62.99 | I12: 88.97 | J12: =IF(F12=0,0,H12/F12) -> 0.49210938 | K12: =IF(F12=0,0,G12/F12) -> 0.0234375 | L12: =IF(I12=0,"",H12/I12) -> 0.70799146 | M12: 0.74169922 | N12: =IF(G12>0,"Converting",IF(F12>=Rules!$B$10,"Waste: 20+ clicks, 0 orders",IF(H12>0,"Waste so far (under 20 clicks)",""))) -> Converting | O12: Converting: own exact campaign in the rebuild
A13: throw blanket boho | B13: Relevant | C13: 1145 | D13: 125 | E13: 6088 | F13: 69 | G13: 0 | H13: 59.04 | I13: 0 | J13: =IF(F13=0,0,H13/F13) -> 0.85565217 | K13: =IF(F13=0,0,G13/F13) -> 0 | L13: =IF(I13=0,"",H13/I13) | M13: 0 | N13: =IF(G13>0,"Converting",IF(F13>=Rules!$B$10,"Waste: 20+ clicks, 0 orders",IF(H13>0,"Waste so far (under 20 clicks)",""))) -> Waste: 20+ clicks, 0 orders | O13: Core intent: retest after the rebuild (do not negate)
A14: boho throw blanket | B14: Relevant | C14: 9420 | D14: 99 | E14: 3407 | F14: 42 | G14: 0 | H14: 39.35 | I14: 0 | J14: =IF(F14=0,0,H14/F14) -> 0.93690476 | K14: =IF(F14=0,0,G14/F14) -> 0 | L14: =IF(I14=0,"",H14/I14) | M14: 0.0046382189 | N14: =IF(G14>0,"Converting",IF(F14>=Rules!$B$10,"Waste: 20+ clicks, 0 orders",IF(H14>0,"Waste so far (under 20 clicks)",""))) -> Waste: 20+ clicks, 0 orders | O14: Core intent: retest after the rebuild (do not negate)
A15: boho cotton blanket | B15: Highly Relevant | C15: 365 | D15: 55 | E15: 2042 | F15: 35 | G15: 1 | H15: 37.34 | I15: 34.99 | J15: =IF(F15=0,0,H15/F15) -> 1.0668571 | K15: =IF(F15=0,0,G15/F15) -> 0.028571429 | L15: =IF(I15=0,"",H15/I15) -> 1.067162 | M15: 0 | N15: =IF(G15>0,"Converting",IF(F15>=Rules!$B$10,"Waste: 20+ clicks, 0 orders",IF(H15>0,"Waste so far (under 20 clicks)",""))) -> Converting | O15: Converting: own exact campaign in the rebuild
A16: bohemian blanket | B16: Highly Relevant | C16: 591 | D16: 85 | E16: 3706 | F16: 41 | G16: 1 | H16: 35.93 | I16: 26.99 | J16: =IF(F16=0,0,H16/F16) -> 0.87634146 | K16: =IF(F16=0,0,G16/F16) -> 0.024390244 | L16: =IF(I16=0,"",H16/I16) -> 1.3312338 | M16: 0 | N16: =IF(G16>0,"Converting",IF(F16>=Rules!$B$10,"Waste: 20+ clicks, 0 orders",IF(H16>0,"Waste so far (under 20 clicks)",""))) -> Converting | O16: Converting: own exact campaign in the rebuild
A17: boho picnic blanket | B17: Lower Relevant | C17: 1047 | E17: 482 | F17: 18 | G17: 0 | H17: 28.44 | I17: 0 | J17: =IF(F17=0,0,H17/F17) -> 1.58 | K17: =IF(F17=0,0,G17/F17) -> 0 | L17: =IF(I17=0,"",H17/I17) | M17: 0 | N17: =IF(G17>0,"Converting",IF(F17>=Rules!$B$10,"Waste: 20+ clicks, 0 orders",IF(H17>0,"Waste so far (under 20 clicks)",""))) -> Waste so far (under 20 clicks) | O17: Negative in the rebuild (wrong size, product or colour)
A18: cotton boho blanket | B18: Lower Relevant | C18: 77 | D18: 47 | E18: 6741 | F18: 34 | G18: 0 | H18: 27.7 | I18: 0 | J18: =IF(F18=0,0,H18/F18) -> 0.81470588 | K18: =IF(F18=0,0,G18/F18) -> 0 | L18: =IF(I18=0,"",H18/I18) | M18: 0.19480519 | N18: =IF(G18>0,"Converting",IF(F18>=Rules!$B$10,"Waste: 20+ clicks, 0 orders",IF(H18>0,"Waste so far (under 20 clicks)",""))) -> Waste: 20+ clicks, 0 orders | O18: Test lane in the rebuild (design / material / size)
A19: boho throw blanket for bed | B19: Highly Relevant | C19: 608 | D19: 104 | E19: 3357 | F19: 27 | G19: 0 | H19: 26.58 | I19: 0 | J19: =IF(F19=0,0,H19/F19) -> 0.98444444 | K19: =IF(F19=0,0,G19/F19) -> 0 | L19: =IF(I19=0,"",H19/I19) | M19: 0 | N19: =IF(G19>0,"Converting",IF(F19>=Rules!$B$10,"Waste: 20+ clicks, 0 orders",IF(H19>0,"Waste so far (under 20 clicks)",""))) -> Waste: 20+ clicks, 0 orders | O19: Core intent: retest after the rebuild (do not negate)
A20: boho king blanket | B20: Relevant | C20: 392 | E20: 644 | F20: 19 | G20: 0 | H20: 26.04 | I20: 0 | J20: =IF(F20=0,0,H20/F20) -> 1.3705263 | K20: =IF(F20=0,0,G20/F20) -> 0 | L20: =IF(I20=0,"",H20/I20) | M20: 0.35594395 | N20: =IF(G20>0,"Converting",IF(F20>=Rules!$B$10,"Waste: 20+ clicks, 0 orders",IF(H20>0,"Waste so far (under 20 clicks)",""))) -> Waste so far (under 20 clicks) | O20: Negative in the rebuild (wrong size, product or colour)
A21: king size boho blanket | B21: Lower Relevant | C21: 310 | D21: 136 | E21: 410 | F21: 18 | G21: 0 | H21: 21.49 | I21: 0 | J21: =IF(F21=0,0,H21/F21) -> 1.1938889 | K21: =IF(F21=0,0,G21/F21) -> 0 | L21: =IF(I21=0,"",H21/I21) | M21: 0 | N21: =IF(G21>0,"Converting",IF(F21>=Rules!$B$10,"Waste: 20+ clicks, 0 orders",IF(H21>0,"Waste so far (under 20 clicks)",""))) -> Waste so far (under 20 clicks) | O21: Negative in the rebuild (wrong size, product or colour)
A22: blue boho throw blanket | B22: Lower Relevant | C22: 48 | E22: 1095 | F22: 75 | G22: 0 | H22: 19.89 | I22: 0 | J22: =IF(F22=0,0,H22/F22) -> 0.2652 | K22: =IF(F22=0,0,G22/F22) -> 0 | L22: =IF(I22=0,"",H22/I22) | M22: 0.91139241 | N22: =IF(G22>0,"Converting",IF(F22>=Rules!$B$10,"Waste: 20+ clicks, 0 orders",IF(H22>0,"Waste so far (under 20 clicks)",""))) -> Waste: 20+ clicks, 0 orders | O22: Negative in the rebuild (wrong size, product or colour)
A23: boho heated blanket | B23: Lower Relevant | C23: 380 | E23: 607 | F23: 43 | G23: 0 | H23: 19.66 | I23: 0 | J23: =IF(F23=0,0,H23/F23) -> 0.4572093 | K23: =IF(F23=0,0,G23/F23) -> 0 | L23: =IF(I23=0,"",H23/I23) | M23: 0.93023256 | N23: =IF(G23>0,"Converting",IF(F23>=Rules!$B$10,"Waste: 20+ clicks, 0 orders",IF(H23>0,"Waste so far (under 20 clicks)",""))) -> Waste: 20+ clicks, 0 orders | O23: Negative in the rebuild (wrong size, product or colour)
A24: b0f542wld5 | B24: Not Relevant | E24: 4782 | F24: 33 | G24: 0 | H24: 19.32 | I24: 0 | J24: =IF(F24=0,0,H24/F24) -> 0.58545455 | K24: =IF(F24=0,0,G24/F24) -> 0 | L24: =IF(I24=0,"",H24/I24) | M24: 0 | N24: =IF(G24>0,"Converting",IF(F24>=Rules!$B$10,"Waste: 20+ clicks, 0 orders",IF(H24>0,"Waste so far (under 20 clicks)",""))) -> Waste: 20+ clicks, 0 orders | O24: Product target: retest only size- and price-matched; negate if 0 orders again
A25: boho blanket king size | B25: Relevant | C25: 348 | E25: 472 | F25: 17 | G25: 0 | H25: 18.19 | I25: 0 | J25: =IF(F25=0,0,H25/F25) -> 1.07 | K25: =IF(F25=0,0,G25/F25) -> 0 | L25: =IF(I25=0,"",H25/I25) | M25: 0.13511029 | N25: =IF(G25>0,"Converting",IF(F25>=Rules!$B$10,"Waste: 20+ clicks, 0 orders",IF(H25>0,"Waste so far (under 20 clicks)",""))) -> Waste so far (under 20 clicks) | O25: Negative in the rebuild (wrong size, product or colour)
A26: boho cotton throw blanket | B26: Lower Relevant | C26: 26 | D26: 38 | E26: 349 | F26: 24 | G26: 1 | H26: 16.95 | I26: 26.99 | J26: =IF(F26=0,0,H26/F26) -> 0.70625 | K26: =IF(F26=0,0,G26/F26) -> 0.041666667 | L26: =IF(I26=0,"",H26/I26) -> 0.62801037 | M26: 0.19480519 | N26: =IF(G26>0,"Converting",IF(F26>=Rules!$B$10,"Waste: 20+ clicks, 0 orders",IF(H26>0,"Waste so far (under 20 clicks)",""))) -> Converting | O26: Converting: own exact campaign in the rebuild
A27: boho couch blanket | B27: Relevant | C27: 49 | D27: 140 | E27: 135 | F27: 10 | G27: 0 | H27: 16.17 | I27: 0 | J27: =IF(F27=0,0,H27/F27) -> 1.617 | K27: =IF(F27=0,0,G27/F27) -> 0 | L27: =IF(I27=0,"",H27/I27) | M27: 0 | N27: =IF(G27>0,"Converting",IF(F27>=Rules!$B$10,"Waste: 20+ clicks, 0 orders",IF(H27>0,"Waste so far (under 20 clicks)",""))) -> Waste so far (under 20 clicks) | O27: Core intent: retest after the rebuild (do not negate)
A28: b0frf3jgk9 | B28: Not Relevant | E28: 2443 | F28: 19 | G28: 0 | H28: 15.58 | I28: 0 | J28: =IF(F28=0,0,H28/F28) -> 0.82 | K28: =IF(F28=0,0,G28/F28) -> 0 | L28: =IF(I28=0,"",H28/I28) | M28: 0 | N28: =IF(G28>0,"Converting",IF(F28>=Rules!$B$10,"Waste: 20+ clicks, 0 orders",IF(H28>0,"Waste so far (under 20 clicks)",""))) -> Waste so far (under 20 clicks) | O28: Product target: retest only size- and price-matched; negate if 0 orders again
A29: b0f9wsbg6b | B29: Not Relevant | E29: 2789 | F29: 24 | G29: 0 | H29: 15.31 | I29: 0 | J29: =IF(F29=0,0,H29/F29) -> 0.63791667 | K29: =IF(F29=0,0,G29/F29) -> 0 | L29: =IF(I29=0,"",H29/I29) | M29: 0 | N29: =IF(G29>0,"Converting",IF(F29>=Rules!$B$10,"Waste: 20+ clicks, 0 orders",IF(H29>0,"Waste so far (under 20 clicks)",""))) -> Waste: 20+ clicks, 0 orders | O29: Product target: retest only size- and price-matched; negate if 0 orders again
A30: boho blanket queen | B30: Relevant | C30: 526 | D30: 101 | E30: 581 | F30: 12 | G30: 0 | H30: 12.57 | I30: 0 | J30: =IF(F30=0,0,H30/F30) -> 1.0475 | K30: =IF(F30=0,0,G30/F30) -> 0 | L30: =IF(I30=0,"",H30/I30) | M30: 0 | N30: =IF(G30>0,"Converting",IF(F30>=Rules!$B$10,"Waste: 20+ clicks, 0 orders",IF(H30>0,"Waste so far (under 20 clicks)",""))) -> Waste so far (under 20 clicks) | O30: Negative in the rebuild (wrong size, product or colour)
A31: b0dhktztmn | B31: Not Relevant | E31: 3095 | F31: 21 | G31: 0 | H31: 12.39 | I31: 0 | J31: =IF(F31=0,0,H31/F31) -> 0.59 | K31: =IF(F31=0,0,G31/F31) -> 0 | L31: =IF(I31=0,"",H31/I31) | M31: 0 | N31: =IF(G31>0,"Converting",IF(F31>=Rules!$B$10,"Waste: 20+ clicks, 0 orders",IF(H31>0,"Waste so far (under 20 clicks)",""))) -> Waste: 20+ clicks, 0 orders | O31: Product target: retest only size- and price-matched; negate if 0 orders again
A32: b0blrbxbx5 | B32: Not Relevant | E32: 3904 | F32: 18 | G32: 0 | H32: 10.62 | I32: 0 | J32: =IF(F32=0,0,H32/F32) -> 0.59 | K32: =IF(F32=0,0,G32/F32) -> 0 | L32: =IF(I32=0,"",H32/I32) | M32: 0 | N32: =IF(G32>0,"Converting",IF(F32>=Rules!$B$10,"Waste: 20+ clicks, 0 orders",IF(H32>0,"Waste so far (under 20 clicks)",""))) -> Waste so far (under 20 clicks) | O32: Product target: retest only size- and price-matched; negate if 0 orders again
A33: boho throws | B33: Relevant | C33: 555 | D33: 80 | E33: 212 | F33: 11 | G33: 2 | H33: 10.44 | I33: 53.98 | J33: =IF(F33=0,0,H33/F33) -> 0.94909091 | K33: =IF(F33=0,0,G33/F33) -> 0.18181818 | L33: =IF(I33=0,"",H33/I33) -> 0.19340496 | M33: 0 | N33: =IF(G33>0,"Converting",IF(F33>=Rules!$B$10,"Waste: 20+ clicks, 0 orders",IF(H33>0,"Waste so far (under 20 clicks)",""))) -> Converting | O33: Converting: own exact campaign in the rebuild
A34: throw blanket for couch boho | B34: Relevant | C34: 249 | D34: 76 | E34: 457 | F34: 18 | G34: 1 | H34: 10.25 | I34: 34.99 | J34: =IF(F34=0,0,H34/F34) -> 0.56944444 | K34: =IF(F34=0,0,G34/F34) -> 0.055555556 | L34: =IF(I34=0,"",H34/I34) -> 0.29294084 | M34: 0.31578947 | N34: =IF(G34>0,"Converting",IF(F34>=Rules!$B$10,"Waste: 20+ clicks, 0 orders",IF(H34>0,"Waste so far (under 20 clicks)",""))) -> Converting | O34: Converting: own exact campaign in the rebuild
A35: boho cotton blankets queen size | B35: Lower Relevant | C35: 48 | D35: 43 | E35: 299 | F35: 7 | G35: 0 | H35: 9.28 | I35: 0 | J35: =IF(F35=0,0,H35/F35) -> 1.3257143 | K35: =IF(F35=0,0,G35/F35) -> 0 | L35: =IF(I35=0,"",H35/I35) | M35: 0 | N35: =IF(G35>0,"Converting",IF(F35>=Rules!$B$10,"Waste: 20+ clicks, 0 orders",IF(H35>0,"Waste so far (under 20 clicks)",""))) -> Waste so far (under 20 clicks) | O35: Negative in the rebuild (wrong size, product or colour)
A36: bohemian blankets | B36: Relevant | C36: 81 | E36: 106 | F36: 9 | G36: 1 | H36: 8.92 | I36: 34.99 | J36: =IF(F36=0,0,H36/F36) -> 0.99111111 | K36: =IF(F36=0,0,G36/F36) -> 0.11111111 | L36: =IF(I36=0,"",H36/I36) -> 0.25492998 | M36: 0 | N36: =IF(G36>0,"Converting",IF(F36>=Rules!$B$10,"Waste: 20+ clicks, 0 orders",IF(H36>0,"Waste so far (under 20 clicks)",""))) -> Converting | O36: Converting: own exact campaign in the rebuild
A37: boho blanket 60x 80 | B37: Relevant | C37: 10 | D37: 32 | E37: 503 | F37: 12 | G37: 0 | H37: 8.48 | I37: 0 | J37: =IF(F37=0,0,H37/F37) -> 0.70666667 | K37: =IF(F37=0,0,G37/F37) -> 0 | L37: =IF(I37=0,"",H37/I37) | M37: 0.96613358 | N37: =IF(G37>0,"Converting",IF(F37>=Rules!$B$10,"Waste: 20+ clicks, 0 orders",IF(H37>0,"Waste so far (under 20 clicks)",""))) -> Waste so far (under 20 clicks) | O37: Test lane in the rebuild (design / material / size)
A38: boho scandinavian cotton blankets | B38: Relevant | C38: 22 | E38: 1058 | F38: 11 | G38: 0 | H38: 8.47 | I38: 0 | J38: =IF(F38=0,0,H38/F38) -> 0.77 | K38: =IF(F38=0,0,G38/F38) -> 0 | L38: =IF(I38=0,"",H38/I38) | M38: 0.19480519 | N38: =IF(G38>0,"Converting",IF(F38>=Rules!$B$10,"Waste: 20+ clicks, 0 orders",IF(H38>0,"Waste so far (under 20 clicks)",""))) -> Waste so far (under 20 clicks) | O38: Negative in the rebuild (wrong size, product or colour)
A39: b0drfz787f | B39: Not Relevant | E39: 777 | F39: 13 | G39: 0 | H39: 8.41 | I39: 0 | J39: =IF(F39=0,0,H39/F39) -> 0.64692308 | K39: =IF(F39=0,0,G39/F39) -> 0 | L39: =IF(I39=0,"",H39/I39) | M39: 0 | N39: =IF(G39>0,"Converting",IF(F39>=Rules!$B$10,"Waste: 20+ clicks, 0 orders",IF(H39>0,"Waste so far (under 20 clicks)",""))) -> Waste so far (under 20 clicks) | O39: Product target: retest only size- and price-matched; negate if 0 orders again
A40: king boho blanket | B40: Lower Relevant | C40: 64 | E40: 21 | F40: 5 | G40: 0 | H40: 8.25 | I40: 0 | J40: =IF(F40=0,0,H40/F40) -> 1.65 | K40: =IF(F40=0,0,G40/F40) -> 0 | L40: =IF(I40=0,"",H40/I40) | M40: 0 | N40: =IF(G40>0,"Converting",IF(F40>=Rules!$B$10,"Waste: 20+ clicks, 0 orders",IF(H40>0,"Waste so far (under 20 clicks)",""))) -> Waste so far (under 20 clicks) | O40: Negative in the rebuild (wrong size, product or colour)
A41: rustic floral boho blanket | B41: Lower Relevant | C41: 33 | D41: 39 | E41: 22 | F41: 5 | G41: 1 | H41: 8.13 | I41: 34.99 | J41: =IF(F41=0,0,H41/F41) -> 1.626 | K41: =IF(F41=0,0,G41/F41) -> 0.2 | L41: =IF(I41=0,"",H41/I41) -> 0.2323521 | M41: 0 | N41: =IF(G41>0,"Converting",IF(F41>=Rules!$B$10,"Waste: 20+ clicks, 0 orders",IF(H41>0,"Waste so far (under 20 clicks)",""))) -> Converting | O41: Converting: own exact campaign in the rebuild
A42: boho blankets queen | B42: Lower Relevant | C42: 28 | E42: 106 | F42: 6 | G42: 0 | H42: 7.6 | I42: 0 | J42: =IF(F42=0,0,H42/F42) -> 1.2666667 | K42: =IF(F42=0,0,G42/F42) -> 0 | L42: =IF(I42=0,"",H42/I42) | M42: 0 | N42: =IF(G42>0,"Converting",IF(F42>=Rules!$B$10,"Waste: 20+ clicks, 0 orders",IF(H42>0,"Waste so far (under 20 clicks)",""))) -> Waste so far (under 20 clicks) | O42: Negative in the rebuild (wrong size, product or colour)
A43: boho bed throws | B43: Relevant | C43: 27 | E43: 218 | F43: 7 | G43: 0 | H43: 7.34 | I43: 0 | J43: =IF(F43=0,0,H43/F43) -> 1.0485714 | K43: =IF(F43=0,0,G43/F43) -> 0 | L43: =IF(I43=0,"",H43/I43) | M43: 0.31578947 | N43: =IF(G43>0,"Converting",IF(F43>=Rules!$B$10,"Waste: 20+ clicks, 0 orders",IF(H43>0,"Waste so far (under 20 clicks)",""))) -> Waste so far (under 20 clicks) | O43: Core intent: retest after the rebuild (do not negate)
A44: boho blankets king size | B44: Lower Relevant | C44: 99 | E44: 209 | F44: 8 | G44: 0 | H44: 7.26 | I44: 0 | J44: =IF(F44=0,0,H44/F44) -> 0.9075 | K44: =IF(F44=0,0,G44/F44) -> 0 | L44: =IF(I44=0,"",H44/I44) | M44: 0.095703125 | N44: =IF(G44>0,"Converting",IF(F44>=Rules!$B$10,"Waste: 20+ clicks, 0 orders",IF(H44>0,"Waste so far (under 20 clicks)",""))) -> Waste so far (under 20 clicks) | O44: Negative in the rebuild (wrong size, product or colour)
A45: b0d4hq4b6y | B45: Not Relevant | E45: 1012 | F45: 12 | G45: 0 | H45: 7.08 | I45: 0 | J45: =IF(F45=0,0,H45/F45) -> 0.59 | K45: =IF(F45=0,0,G45/F45) -> 0 | L45: =IF(I45=0,"",H45/I45) | M45: 0 | N45: =IF(G45>0,"Converting",IF(F45>=Rules!$B$10,"Waste: 20+ clicks, 0 orders",IF(H45>0,"Waste so far (under 20 clicks)",""))) -> Waste so far (under 20 clicks) | O45: Product target: retest only size- and price-matched; negate if 0 orders again
A46: boho scandinavian cotton blanket | B46: Relevant | C46: 122 | D46: 11 | E46: 66 | F46: 5 | G46: 0 | H46: 6.86 | I46: 0 | J46: =IF(F46=0,0,H46/F46) -> 1.372 | K46: =IF(F46=0,0,G46/F46) -> 0 | L46: =IF(I46=0,"",H46/I46) | M46: 0.19480519 | N46: =IF(G46>0,"Converting",IF(F46>=Rules!$B$10,"Waste: 20+ clicks, 0 orders",IF(H46>0,"Waste so far (under 20 clicks)",""))) -> Waste so far (under 20 clicks) | O46: Negative in the rebuild (wrong size, product or colour)
A47: throw blanket | B47: Lower Relevant | C47: 192912 | E47: 21 | F47: 3 | G47: 0 | H47: 6.84 | I47: 0 | J47: =IF(F47=0,0,H47/F47) -> 2.28 | K47: =IF(F47=0,0,G47/F47) -> 0 | L47: =IF(I47=0,"",H47/I47) | M47: 0 | N47: =IF(G47>0,"Converting",IF(F47>=Rules!$B$10,"Waste: 20+ clicks, 0 orders",IF(H47>0,"Waste so far (under 20 clicks)",""))) -> Waste so far (under 20 clicks) | O47: Negative exact (too broad for this listing)
A48: boho blankets | B48: Highly Relevant | C48: 965 | D48: 105 | E48: 929 | F48: 8 | G48: 1 | H48: 6.46 | I48: 26.99 | J48: =IF(F48=0,0,H48/F48) -> 0.8075 | K48: =IF(F48=0,0,G48/F48) -> 0.125 | L48: =IF(I48=0,"",H48/I48) -> 0.23934791 | M48: 0 | N48: =IF(G48>0,"Converting",IF(F48>=Rules!$B$10,"Waste: 20+ clicks, 0 orders",IF(H48>0,"Waste so far (under 20 clicks)",""))) -> Converting | O48: Converting: own exact campaign in the rebuild
A49: boho blankets and throws | B49: Relevant | C49: 342 | D49: 109 | E49: 33 | F49: 5 | G49: 0 | H49: 6.34 | I49: 0 | J49: =IF(F49=0,0,H49/F49) -> 1.268 | K49: =IF(F49=0,0,G49/F49) -> 0 | L49: =IF(I49=0,"",H49/I49) | M49: 0 | N49: =IF(G49>0,"Converting",IF(F49>=Rules!$B$10,"Waste: 20+ clicks, 0 orders",IF(H49>0,"Waste so far (under 20 clicks)",""))) -> Waste so far (under 20 clicks) | O49: Core intent: retest after the rebuild (do not negate)
A50: floral quilt | B50: Relevant | C50: 4188 | E50: 17 | F50: 3 | G50: 0 | H50: 5.73 | I50: 0 | J50: =IF(F50=0,0,H50/F50) -> 1.91 | K50: =IF(F50=0,0,G50/F50) -> 0 | L50: =IF(I50=0,"",H50/I50) | M50: 0 | N50: =IF(G50>0,"Converting",IF(F50>=Rules!$B$10,"Waste: 20+ clicks, 0 orders",IF(H50>0,"Waste so far (under 20 clicks)",""))) -> Waste so far (under 20 clicks) | O50: Negative in the rebuild (wrong size, product or colour)
A51: throw blankets for bed boho | B51: Lower Relevant | C51: 386 | D51: 106 | E51: 27 | F51: 4 | G51: 0 | H51: 5.42 | I51: 0 | J51: =IF(F51=0,0,H51/F51) -> 1.355 | K51: =IF(F51=0,0,G51/F51) -> 0 | L51: =IF(I51=0,"",H51/I51) | M51: 0 | N51: =IF(G51>0,"Converting",IF(F51>=Rules!$B$10,"Waste: 20+ clicks, 0 orders",IF(H51>0,"Waste so far (under 20 clicks)",""))) -> Waste so far (under 20 clicks) | O51: Core intent: retest after the rebuild (do not negate)
A52: b0ds28q1lt | B52: Not Relevant | E52: 416 | F52: 9 | G52: 0 | H52: 5.04 | I52: 0 | J52: =IF(F52=0,0,H52/F52) -> 0.56 | K52: =IF(F52=0,0,G52/F52) -> 0 | L52: =IF(I52=0,"",H52/I52) | M52: 0 | N52: =IF(G52>0,"Converting",IF(F52>=Rules!$B$10,"Waste: 20+ clicks, 0 orders",IF(H52>0,"Waste so far (under 20 clicks)",""))) -> Waste so far (under 20 clicks) | O52: Product target: retest only size- and price-matched; negate if 0 orders again
A53: blanket boho | B53: Relevant | C53: 240 | D53: 117 | E53: 18 | F53: 3 | G53: 0 | H53: 5.01 | I53: 0 | J53: =IF(F53=0,0,H53/F53) -> 1.67 | K53: =IF(F53=0,0,G53/F53) -> 0 | L53: =IF(I53=0,"",H53/I53) | M53: 0.21052632 | N53: =IF(G53>0,"Converting",IF(F53>=Rules!$B$10,"Waste: 20+ clicks, 0 orders",IF(H53>0,"Waste so far (under 20 clicks)",""))) -> Waste so far (under 20 clicks) | O53: Core intent: retest after the rebuild (do not negate)
A54: boho blanket for bed | B54: Lower Relevant | C54: 42 | E54: 22 | F54: 5 | G54: 0 | H54: 4.96 | I54: 0 | J54: =IF(F54=0,0,H54/F54) -> 0.992 | K54: =IF(F54=0,0,G54/F54) -> 0 | L54: =IF(I54=0,"",H54/I54) | M54: 0.31578947 | N54: =IF(G54>0,"Converting",IF(F54>=Rules!$B$10,"Waste: 20+ clicks, 0 orders",IF(H54>0,"Waste so far (under 20 clicks)",""))) -> Waste so far (under 20 clicks) | O54: Core intent: retest after the rebuild (do not negate)
A55: boho throw blankets | B55: Highly Relevant | C55: 636 | D55: 111 | E55: 25 | F55: 3 | G55: 0 | H55: 4.75 | I55: 0 | J55: =IF(F55=0,0,H55/F55) -> 1.5833333 | K55: =IF(F55=0,0,G55/F55) -> 0 | L55: =IF(I55=0,"",H55/I55) | M55: 0 | N55: =IF(G55>0,"Converting",IF(F55>=Rules!$B$10,"Waste: 20+ clicks, 0 orders",IF(H55>0,"Waste so far (under 20 clicks)",""))) -> Waste so far (under 20 clicks) | O55: Core intent: retest after the rebuild (do not negate)
A56: quilt blanket | B56: Lower Relevant | C56: 3293 | E56: 65 | F56: 2 | G56: 0 | H56: 4.72 | I56: 0 | J56: =IF(F56=0,0,H56/F56) -> 2.36 | K56: =IF(F56=0,0,G56/F56) -> 0 | L56: =IF(I56=0,"",H56/I56) | M56: 0 | N56: =IF(G56>0,"Converting",IF(F56>=Rules!$B$10,"Waste: 20+ clicks, 0 orders",IF(H56>0,"Waste so far (under 20 clicks)",""))) -> Waste so far (under 20 clicks) | O56: Negative in the rebuild (wrong size, product or colour)
A57: quilted throw | B57: Lower Relevant | C57: 1748 | E57: 26 | F57: 2 | G57: 0 | H57: 4.72 | I57: 0 | J57: =IF(F57=0,0,H57/F57) -> 2.36 | K57: =IF(F57=0,0,G57/F57) -> 0 | L57: =IF(I57=0,"",H57/I57) | M57: 0 | N57: =IF(G57>0,"Converting",IF(F57>=Rules!$B$10,"Waste: 20+ clicks, 0 orders",IF(H57>0,"Waste so far (under 20 clicks)",""))) -> Waste so far (under 20 clicks) | O57: Negative in the rebuild (wrong size, product or colour)
A58: boho beach blanket | B58: Lower Relevant | C58: 644 | E58: 3 | F58: 1 | G58: 0 | H58: 4.68 | I58: 0 | J58: =IF(F58=0,0,H58/F58) -> 4.68 | K58: =IF(F58=0,0,G58/F58) -> 0 | L58: =IF(I58=0,"",H58/I58) | M58: 0 | N58: =IF(G58>0,"Converting",IF(F58>=Rules!$B$10,"Waste: 20+ clicks, 0 orders",IF(H58>0,"Waste so far (under 20 clicks)",""))) -> Waste so far (under 20 clicks) | O58: Negative in the rebuild (wrong size, product or colour)
A59: beach blanket boho | B59: Relevant | C59: 31 | E59: 2 | F59: 1 | G59: 0 | H59: 4.47 | I59: 0 | J59: =IF(F59=0,0,H59/F59) -> 4.47 | K59: =IF(F59=0,0,G59/F59) -> 0 | L59: =IF(I59=0,"",H59/I59) | M59: 0 | N59: =IF(G59>0,"Converting",IF(F59>=Rules!$B$10,"Waste: 20+ clicks, 0 orders",IF(H59>0,"Waste so far (under 20 clicks)",""))) -> Waste so far (under 20 clicks) | O59: Negative in the rebuild (wrong size, product or colour)
A60: throw blankets boho | B60: Lower Relevant | C60: 367 | E60: 42 | F60: 2 | G60: 0 | H60: 4.34 | I60: 0 | J60: =IF(F60=0,0,H60/F60) -> 2.17 | K60: =IF(F60=0,0,G60/F60) -> 0 | L60: =IF(I60=0,"",H60/I60) | M60: 0 | N60: =IF(G60>0,"Converting",IF(F60>=Rules!$B$10,"Waste: 20+ clicks, 0 orders",IF(H60>0,"Waste so far (under 20 clicks)",""))) -> Waste so far (under 20 clicks) | O60: Core intent: retest after the rebuild (do not negate)
A61: blue boho blanket | B61: Lower Relevant | C61: 21 | E61: 19 | F61: 4 | G61: 0 | H61: 4.18 | I61: 0 | J61: =IF(F61=0,0,H61/F61) -> 1.045 | K61: =IF(F61=0,0,G61/F61) -> 0 | L61: =IF(I61=0,"",H61/I61) | M61: 0.91139241 | N61: =IF(G61>0,"Converting",IF(F61>=Rules!$B$10,"Waste: 20+ clicks, 0 orders",IF(H61>0,"Waste so far (under 20 clicks)",""))) -> Waste so far (under 20 clicks) | O61: Negative in the rebuild (wrong size, product or colour)
A62: green throw blanket | B62: Lower Relevant | C62: 15764 | E62: 49 | F62: 2 | G62: 0 | H62: 4.05 | I62: 0 | J62: =IF(F62=0,0,H62/F62) -> 2.025 | K62: =IF(F62=0,0,G62/F62) -> 0 | L62: =IF(I62=0,"",H62/I62) | M62: 0 | N62: =IF(G62>0,"Converting",IF(F62>=Rules!$B$10,"Waste: 20+ clicks, 0 orders",IF(H62>0,"Waste so far (under 20 clicks)",""))) -> Waste so far (under 20 clicks) | O62: Negative in the rebuild (wrong size, product or colour)
A63: bohemian throw blankets | B63: Lower Relevant | C63: 12 | E63: 4 | F63: 2 | G63: 0 | H63: 3.54 | I63: 0 | J63: =IF(F63=0,0,H63/F63) -> 1.77 | K63: =IF(F63=0,0,G63/F63) -> 0 | L63: =IF(I63=0,"",H63/I63) | M63: 0 | N63: =IF(G63>0,"Converting",IF(F63>=Rules!$B$10,"Waste: 20+ clicks, 0 orders",IF(H63>0,"Waste so far (under 20 clicks)",""))) -> Waste so far (under 20 clicks) | O63: Core intent: retest after the rebuild (do not negate)
A64: boho cotton blanket queen | B64: Lower Relevant | C64: 18 | E64: 7 | F64: 2 | G64: 0 | H64: 3.37 | I64: 0 | J64: =IF(F64=0,0,H64/F64) -> 1.685 | K64: =IF(F64=0,0,G64/F64) -> 0 | L64: =IF(I64=0,"",H64/I64) | M64: 0 | N64: =IF(G64>0,"Converting",IF(F64>=Rules!$B$10,"Waste: 20+ clicks, 0 orders",IF(H64>0,"Waste so far (under 20 clicks)",""))) -> Waste so far (under 20 clicks) | O64: Negative in the rebuild (wrong size, product or colour)
A65: boho blankets for bed | B65: Relevant | C65: 63 | D65: 89 | E65: 6 | F65: 2 | G65: 0 | H65: 2.41 | I65: 0 | J65: =IF(F65=0,0,H65/F65) -> 1.205 | K65: =IF(F65=0,0,G65/F65) -> 0 | L65: =IF(I65=0,"",H65/I65) | M65: 0.31578947 | N65: =IF(G65>0,"Converting",IF(F65>=Rules!$B$10,"Waste: 20+ clicks, 0 orders",IF(H65>0,"Waste so far (under 20 clicks)",""))) -> Waste so far (under 20 clicks) | O65: Core intent: retest after the rebuild (do not negate)
A66: 100 cotton blanket | B66: Relevant | C66: 1486 | E66: 12 | F66: 1 | G66: 0 | H66: 2.36 | I66: 0 | J66: =IF(F66=0,0,H66/F66) -> 2.36 | K66: =IF(F66=0,0,G66/F66) -> 0 | L66: =IF(I66=0,"",H66/I66) | M66: 0 | N66: =IF(G66>0,"Converting",IF(F66>=Rules!$B$10,"Waste: 20+ clicks, 0 orders",IF(H66>0,"Waste so far (under 20 clicks)",""))) -> Waste so far (under 20 clicks) | O66: Test lane in the rebuild (design / material / size)
A67: b0b5xx22j6 | B67: Not Relevant | E67: 169 | F67: 4 | G67: 0 | H67: 2.36 | I67: 0 | J67: =IF(F67=0,0,H67/F67) -> 0.59 | K67: =IF(F67=0,0,G67/F67) -> 0 | L67: =IF(I67=0,"",H67/I67) | M67: 0 | N67: =IF(G67>0,"Converting",IF(F67>=Rules!$B$10,"Waste: 20+ clicks, 0 orders",IF(H67>0,"Waste so far (under 20 clicks)",""))) -> Waste so far (under 20 clicks) | O67: Product target: retest only size- and price-matched; negate if 0 orders again
A68: bohemian quilt | B68: Relevant | C68: 644 | E68: 5 | F68: 1 | G68: 0 | H68: 2.36 | I68: 0 | J68: =IF(F68=0,0,H68/F68) -> 2.36 | K68: =IF(F68=0,0,G68/F68) -> 0 | L68: =IF(I68=0,"",H68/I68) | M68: 0 | N68: =IF(G68>0,"Converting",IF(F68>=Rules!$B$10,"Waste: 20+ clicks, 0 orders",IF(H68>0,"Waste so far (under 20 clicks)",""))) -> Waste so far (under 20 clicks) | O68: Negative in the rebuild (wrong size, product or colour)
A69: butterfly throw blanket | B69: Relevant | C69: 776 | E69: 3 | F69: 1 | G69: 0 | H69: 2.36 | I69: 0 | J69: =IF(F69=0,0,H69/F69) -> 2.36 | K69: =IF(F69=0,0,G69/F69) -> 0 | L69: =IF(I69=0,"",H69/I69) | M69: 0 | N69: =IF(G69>0,"Converting",IF(F69>=Rules!$B$10,"Waste: 20+ clicks, 0 orders",IF(H69>0,"Waste so far (under 20 clicks)",""))) -> Waste so far (under 20 clicks) | O69: Test lane in the rebuild (design / material / size)
A70: couch throw | B70: Lower Relevant | C70: 2386 | E70: 11 | F70: 1 | G70: 0 | H70: 2.36 | I70: 0 | J70: =IF(F70=0,0,H70/F70) -> 2.36 | K70: =IF(F70=0,0,G70/F70) -> 0 | L70: =IF(I70=0,"",H70/I70) | M70: 0 | N70: =IF(G70>0,"Converting",IF(F70>=Rules!$B$10,"Waste: 20+ clicks, 0 orders",IF(H70>0,"Waste so far (under 20 clicks)",""))) -> Waste so far (under 20 clicks) | O70: Negative exact (too broad for this listing)
A71: eddie bauer throw | B71: Lower Relevant | E71: 5 | F71: 1 | G71: 0 | H71: 2.36 | I71: 0 | J71: =IF(F71=0,0,H71/F71) -> 2.36 | K71: =IF(F71=0,0,G71/F71) -> 0 | L71: =IF(I71=0,"",H71/I71) | M71: 0 | N71: =IF(G71>0,"Converting",IF(F71>=Rules!$B$10,"Waste: 20+ clicks, 0 orders",IF(H71>0,"Waste so far (under 20 clicks)",""))) -> Waste so far (under 20 clicks) | O71: Negative in the rebuild (wrong size, product or colour)
A72: minky blanket | B72: Lower Relevant | C72: 4740 | E72: 6 | F72: 1 | G72: 0 | H72: 2.36 | I72: 0 | J72: =IF(F72=0,0,H72/F72) -> 2.36 | K72: =IF(F72=0,0,G72/F72) -> 0 | L72: =IF(I72=0,"",H72/I72) | M72: 0 | N72: =IF(G72>0,"Converting",IF(F72>=Rules!$B$10,"Waste: 20+ clicks, 0 orders",IF(H72>0,"Waste so far (under 20 clicks)",""))) -> Waste so far (under 20 clicks) | O72: Negative in the rebuild (wrong size, product or colour)
A73: orange quilt | B73: Lower Relevant | C73: 593 | E73: 16 | F73: 1 | G73: 0 | H73: 2.36 | I73: 0 | J73: =IF(F73=0,0,H73/F73) -> 2.36 | K73: =IF(F73=0,0,G73/F73) -> 0 | L73: =IF(I73=0,"",H73/I73) | M73: 0 | N73: =IF(G73>0,"Converting",IF(F73>=Rules!$B$10,"Waste: 20+ clicks, 0 orders",IF(H73>0,"Waste so far (under 20 clicks)",""))) -> Waste so far (under 20 clicks) | O73: Negative in the rebuild (wrong size, product or colour)
A74: throw blanket cotton | B74: Relevant | C74: 1848 | D74: 140 | E74: 4 | F74: 1 | G74: 0 | H74: 2.36 | I74: 0 | J74: =IF(F74=0,0,H74/F74) -> 2.36 | K74: =IF(F74=0,0,G74/F74) -> 0 | L74: =IF(I74=0,"",H74/I74) | M74: 0 | N74: =IF(G74>0,"Converting",IF(F74>=Rules!$B$10,"Waste: 20+ clicks, 0 orders",IF(H74>0,"Waste so far (under 20 clicks)",""))) -> Waste so far (under 20 clicks) | O74: Test lane in the rebuild (design / material / size)
A75: totoro blanket | B75: Lower Relevant | C75: 235 | E75: 5 | F75: 1 | G75: 0 | H75: 2.36 | I75: 0 | J75: =IF(F75=0,0,H75/F75) -> 2.36 | K75: =IF(F75=0,0,G75/F75) -> 0 | L75: =IF(I75=0,"",H75/I75) | M75: 0 | N75: =IF(G75>0,"Converting",IF(F75>=Rules!$B$10,"Waste: 20+ clicks, 0 orders",IF(H75>0,"Waste so far (under 20 clicks)",""))) -> Waste so far (under 20 clicks) | O75: Negative in the rebuild (wrong size, product or colour)
A76: western blanket for bed | B76: Relevant | E76: 3 | F76: 1 | G76: 0 | H76: 2.36 | I76: 0 | J76: =IF(F76=0,0,H76/F76) -> 2.36 | K76: =IF(F76=0,0,G76/F76) -> 0 | L76: =IF(I76=0,"",H76/I76) | M76: 0 | N76: =IF(G76>0,"Converting",IF(F76>=Rules!$B$10,"Waste: 20+ clicks, 0 orders",IF(H76>0,"Waste so far (under 20 clicks)",""))) -> Waste so far (under 20 clicks) | O76: Negative in the rebuild (wrong size, product or colour)
A77: luxury throw | B77: Lower Relevant | E77: 1 | F77: 1 | G77: 1 | H77: 2.28 | I77: 34.99 | J77: =IF(F77=0,0,H77/F77) -> 2.28 | K77: =IF(F77=0,0,G77/F77) -> 1 | L77: =IF(I77=0,"",H77/I77) -> 0.065161475 | M77: 0 | N77: =IF(G77>0,"Converting",IF(F77>=Rules!$B$10,"Waste: 20+ clicks, 0 orders",IF(H77>0,"Waste so far (under 20 clicks)",""))) -> Converting | O77: Converting: own exact campaign in the rebuild
A78: throws for chairs | B78: Relevant | C78: 615 | E78: 11 | F78: 1 | G78: 0 | H78: 2.27 | I78: 0 | J78: =IF(F78=0,0,H78/F78) -> 2.27 | K78: =IF(F78=0,0,G78/F78) -> 0 | L78: =IF(I78=0,"",H78/I78) | M78: 0 | N78: =IF(G78>0,"Converting",IF(F78>=Rules!$B$10,"Waste: 20+ clicks, 0 orders",IF(H78>0,"Waste so far (under 20 clicks)",""))) -> Waste so far (under 20 clicks) | O78: Negative exact (too broad for this listing)
A79: tommy hilfiger throw blanket | B79: Relevant | C79: 58 | E79: 1 | F79: 1 | G79: 0 | H79: 2.25 | I79: 0 | J79: =IF(F79=0,0,H79/F79) -> 2.25 | K79: =IF(F79=0,0,G79/F79) -> 0 | L79: =IF(I79=0,"",H79/I79) | M79: 0 | N79: =IF(G79>0,"Converting",IF(F79>=Rules!$B$10,"Waste: 20+ clicks, 0 orders",IF(H79>0,"Waste so far (under 20 clicks)",""))) -> Waste so far (under 20 clicks) | O79: Negative in the rebuild (wrong size, product or colour)
A80: nordic blanket | B80: Lower Relevant | C80: 250 | E80: 1 | F80: 1 | G80: 0 | H80: 2.23 | I80: 0 | J80: =IF(F80=0,0,H80/F80) -> 2.23 | K80: =IF(F80=0,0,G80/F80) -> 0 | L80: =IF(I80=0,"",H80/I80) | M80: 0 | N80: =IF(G80>0,"Converting",IF(F80>=Rules!$B$10,"Waste: 20+ clicks, 0 orders",IF(H80>0,"Waste so far (under 20 clicks)",""))) -> Waste so far (under 20 clicks) | O80: Negative in the rebuild (wrong size, product or colour)
A81: 60x80 cotton throw | B81: Lower Relevant | C81: 11 | E81: 4 | F81: 1 | G81: 0 | H81: 2.22 | I81: 0 | J81: =IF(F81=0,0,H81/F81) -> 2.22 | K81: =IF(F81=0,0,G81/F81) -> 0 | L81: =IF(I81=0,"",H81/I81) | M81: 0 | N81: =IF(G81>0,"Converting",IF(F81>=Rules!$B$10,"Waste: 20+ clicks, 0 orders",IF(H81>0,"Waste so far (under 20 clicks)",""))) -> Waste so far (under 20 clicks) | O81: Test lane in the rebuild (design / material / size)
A82: boho bed throw | B82: Lower Relevant | C82: 244 | D82: 123 | E82: 8 | F82: 2 | G82: 0 | H82: 2.11 | I82: 0 | J82: =IF(F82=0,0,H82/F82) -> 1.055 | K82: =IF(F82=0,0,G82/F82) -> 0 | L82: =IF(I82=0,"",H82/I82) | M82: 0.31578947 | N82: =IF(G82>0,"Converting",IF(F82>=Rules!$B$10,"Waste: 20+ clicks, 0 orders",IF(H82>0,"Waste so far (under 20 clicks)",""))) -> Waste so far (under 20 clicks) | O82: Core intent: retest after the rebuild (do not negate)
A83: decorative throw blanket | B83: Lower Relevant | C83: 1740 | E83: 11 | F83: 1 | G83: 0 | H83: 2.1 | I83: 0 | J83: =IF(F83=0,0,H83/F83) -> 2.1 | K83: =IF(F83=0,0,G83/F83) -> 0 | L83: =IF(I83=0,"",H83/I83) | M83: 0 | N83: =IF(G83>0,"Converting",IF(F83>=Rules!$B$10,"Waste: 20+ clicks, 0 orders",IF(H83>0,"Waste so far (under 20 clicks)",""))) -> Waste so far (under 20 clicks) | O83: Negative exact (too broad for this listing)
A84: blanket throws for couch | B84: Lower Relevant | C84: 776 | E84: 11 | F84: 1 | G84: 0 | H84: 2.08 | I84: 0 | J84: =IF(F84=0,0,H84/F84) -> 2.08 | K84: =IF(F84=0,0,G84/F84) -> 0 | L84: =IF(I84=0,"",H84/I84) | M84: 0 | N84: =IF(G84>0,"Converting",IF(F84>=Rules!$B$10,"Waste: 20+ clicks, 0 orders",IF(H84>0,"Waste so far (under 20 clicks)",""))) -> Waste so far (under 20 clicks) | O84: Negative exact (too broad for this listing)
A85: 100% cotton boho blanket king | B85: Relevant | E85: 1 | F85: 1 | G85: 0 | H85: 2.02 | I85: 0 | J85: =IF(F85=0,0,H85/F85) -> 2.02 | K85: =IF(F85=0,0,G85/F85) -> 0 | L85: =IF(I85=0,"",H85/I85) | M85: 0 | N85: =IF(G85>0,"Converting",IF(F85>=Rules!$B$10,"Waste: 20+ clicks, 0 orders",IF(H85>0,"Waste so far (under 20 clicks)",""))) -> Waste so far (under 20 clicks) | O85: Negative in the rebuild (wrong size, product or colour)
A86: cotton quilt throw | B86: Relevant | C86: 605 | E86: 2 | F86: 1 | G86: 0 | H86: 2.01 | I86: 0 | J86: =IF(F86=0,0,H86/F86) -> 2.01 | K86: =IF(F86=0,0,G86/F86) -> 0 | L86: =IF(I86=0,"",H86/I86) | M86: 0 | N86: =IF(G86>0,"Converting",IF(F86>=Rules!$B$10,"Waste: 20+ clicks, 0 orders",IF(H86>0,"Waste so far (under 20 clicks)",""))) -> Waste so far (under 20 clicks) | O86: Negative in the rebuild (wrong size, product or colour)
A87: tropical throw blanket | B87: Relevant | C87: 610 | E87: 6 | F87: 1 | G87: 0 | H87: 1.94 | I87: 0 | J87: =IF(F87=0,0,H87/F87) -> 1.94 | K87: =IF(F87=0,0,G87/F87) -> 0 | L87: =IF(I87=0,"",H87/I87) | M87: 0 | N87: =IF(G87>0,"Converting",IF(F87>=Rules!$B$10,"Waste: 20+ clicks, 0 orders",IF(H87>0,"Waste so far (under 20 clicks)",""))) -> Waste so far (under 20 clicks) | O87: Negative in the rebuild (wrong size, product or colour)
A88: throw blanket bed boho | B88: Lower Relevant | C88: 14 | E88: 8 | F88: 1 | G88: 0 | H88: 1.83 | I88: 0 | J88: =IF(F88=0,0,H88/F88) -> 1.83 | K88: =IF(F88=0,0,G88/F88) -> 0 | L88: =IF(I88=0,"",H88/I88) | M88: 0 | N88: =IF(G88>0,"Converting",IF(F88>=Rules!$B$10,"Waste: 20+ clicks, 0 orders",IF(H88>0,"Waste so far (under 20 clicks)",""))) -> Waste so far (under 20 clicks) | O88: Core intent: retest after the rebuild (do not negate)
A89: big boho blanket | B89: Relevant | C89: 12 | D89: 78 | E89: 1 | F89: 1 | G89: 0 | H89: 1.82 | I89: 0 | J89: =IF(F89=0,0,H89/F89) -> 1.82 | K89: =IF(F89=0,0,G89/F89) -> 0 | L89: =IF(I89=0,"",H89/I89) | M89: 0.96613358 | N89: =IF(G89>0,"Converting",IF(F89>=Rules!$B$10,"Waste: 20+ clicks, 0 orders",IF(H89>0,"Waste so far (under 20 clicks)",""))) -> Waste so far (under 20 clicks) | O89: Core intent: retest after the rebuild (do not negate)
A90: boho floral cotton blanket | B90: Lower Relevant | C90: 11 | E90: 5 | F90: 1 | G90: 0 | H90: 1.82 | I90: 0 | J90: =IF(F90=0,0,H90/F90) -> 1.82 | K90: =IF(F90=0,0,G90/F90) -> 0 | L90: =IF(I90=0,"",H90/I90) | M90: 0 | N90: =IF(G90>0,"Converting",IF(F90>=Rules!$B$10,"Waste: 20+ clicks, 0 orders",IF(H90>0,"Waste so far (under 20 clicks)",""))) -> Waste so far (under 20 clicks) | O90: Test lane in the rebuild (design / material / size)
A91: queen blanket | B91: Relevant | C91: 8540 | E91: 7 | F91: 1 | G91: 0 | H91: 1.81 | I91: 0 | J91: =IF(F91=0,0,H91/F91) -> 1.81 | K91: =IF(F91=0,0,G91/F91) -> 0 | L91: =IF(I91=0,"",H91/I91) | M91: 0 | N91: =IF(G91>0,"Converting",IF(F91>=Rules!$B$10,"Waste: 20+ clicks, 0 orders",IF(H91>0,"Waste so far (under 20 clicks)",""))) -> Waste so far (under 20 clicks) | O91: Negative in the rebuild (wrong size, product or colour)
A92: boho king size blankets | E92: 9 | F92: 1 | G92: 0 | H92: 1.73 | I92: 0 | J92: =IF(F92=0,0,H92/F92) -> 1.73 | K92: =IF(F92=0,0,G92/F92) -> 0 | L92: =IF(I92=0,"",H92/I92) | M92: 0.96613358 | N92: =IF(G92>0,"Converting",IF(F92>=Rules!$B$10,"Waste: 20+ clicks, 0 orders",IF(H92>0,"Waste so far (under 20 clicks)",""))) -> Waste so far (under 20 clicks) | O92: Negative in the rebuild (wrong size, product or colour)
A93: cotton boho blankets | B93: Lower Relevant | C93: 5 | E93: 8 | F93: 2 | G93: 0 | H93: 1.7 | I93: 0 | J93: =IF(F93=0,0,H93/F93) -> 0.85 | K93: =IF(F93=0,0,G93/F93) -> 0 | L93: =IF(I93=0,"",H93/I93) | M93: 0.19480519 | N93: =IF(G93>0,"Converting",IF(F93>=Rules!$B$10,"Waste: 20+ clicks, 0 orders",IF(H93>0,"Waste so far (under 20 clicks)",""))) -> Waste so far (under 20 clicks) | O93: Test lane in the rebuild (design / material / size)
A94: couch quilt | B94: Relevant | C94: 617 | E94: 6 | F94: 1 | G94: 0 | H94: 1.7 | I94: 0 | J94: =IF(F94=0,0,H94/F94) -> 1.7 | K94: =IF(F94=0,0,G94/F94) -> 0 | L94: =IF(I94=0,"",H94/I94) | M94: 0 | N94: =IF(G94>0,"Converting",IF(F94>=Rules!$B$10,"Waste: 20+ clicks, 0 orders",IF(H94>0,"Waste so far (under 20 clicks)",""))) -> Waste so far (under 20 clicks) | O94: Negative in the rebuild (wrong size, product or colour)
A95: soft boho throw blanket | B95: Lower Relevant | C95: 89 | D95: 115 | E95: 3 | F95: 1 | G95: 0 | H95: 1.66 | I95: 0 | J95: =IF(F95=0,0,H95/F95) -> 1.66 | K95: =IF(F95=0,0,G95/F95) -> 0 | L95: =IF(I95=0,"",H95/I95) | M95: 0.31578947 | N95: =IF(G95>0,"Converting",IF(F95>=Rules!$B$10,"Waste: 20+ clicks, 0 orders",IF(H95>0,"Waste so far (under 20 clicks)",""))) -> Waste so far (under 20 clicks) | O95: Core intent: retest after the rebuild (do not negate)
A96: boho blanket throws | B96: Lower Relevant | C96: 10 | E96: 1 | F96: 1 | G96: 0 | H96: 1.62 | I96: 0 | J96: =IF(F96=0,0,H96/F96) -> 1.62 | K96: =IF(F96=0,0,G96/F96) -> 0 | L96: =IF(I96=0,"",H96/I96) | M96: 0 | N96: =IF(G96>0,"Converting",IF(F96>=Rules!$B$10,"Waste: 20+ clicks, 0 orders",IF(H96>0,"Waste so far (under 20 clicks)",""))) -> Waste so far (under 20 clicks) | O96: Core intent: retest after the rebuild (do not negate)
A97: throw blanket floral | B97: Lower Relevant | C97: 598 | E97: 2 | F97: 1 | G97: 0 | H97: 1.52 | I97: 0 | J97: =IF(F97=0,0,H97/F97) -> 1.52 | K97: =IF(F97=0,0,G97/F97) -> 0 | L97: =IF(I97=0,"",H97/I97) | M97: 0 | N97: =IF(G97>0,"Converting",IF(F97>=Rules!$B$10,"Waste: 20+ clicks, 0 orders",IF(H97>0,"Waste so far (under 20 clicks)",""))) -> Waste so far (under 20 clicks) | O97: Test lane in the rebuild (design / material / size)
A98: boho soft blanket | E98: 1 | F98: 1 | G98: 0 | H98: 1.44 | I98: 0 | J98: =IF(F98=0,0,H98/F98) -> 1.44 | K98: =IF(F98=0,0,G98/F98) -> 0 | L98: =IF(I98=0,"",H98/I98) | M98: 0 | N98: =IF(G98>0,"Converting",IF(F98>=Rules!$B$10,"Waste: 20+ clicks, 0 orders",IF(H98>0,"Waste so far (under 20 clicks)",""))) -> Waste so far (under 20 clicks) | O98: Core intent: retest after the rebuild (do not negate)
A99: sleephoria boho throw blanket | B99: Branded | C99: 9 | D99: 1 | E99: 5 | F99: 4 | G99: 0 | H99: 1.38 | I99: 0 | J99: =IF(F99=0,0,H99/F99) -> 0.345 | K99: =IF(F99=0,0,G99/F99) -> 0 | L99: =IF(I99=0,"",H99/I99) | M99: 0 | N99: =IF(G99>0,"Converting",IF(F99>=Rules!$B$10,"Waste: 20+ clicks, 0 orders",IF(H99>0,"Waste so far (under 20 clicks)",""))) -> Waste so far (under 20 clicks) | O99: Brand defence: keep
A100: bohemian gifts | B100: Lower Relevant | C100: 99 | E100: 3 | F100: 1 | G100: 0 | H100: 1.37 | I100: 0 | J100: =IF(F100=0,0,H100/F100) -> 1.37 | K100: =IF(F100=0,0,G100/F100) -> 0 | L100: =IF(I100=0,"",H100/I100) | M100: 0 | N100: =IF(G100>0,"Converting",IF(F100>=Rules!$B$10,"Waste: 20+ clicks, 0 orders",IF(H100>0,"Waste so far (under 20 clicks)",""))) -> Waste so far (under 20 clicks) | O100: Core intent: retest after the rebuild (do not negate)
A101: boho beach blankets | B101: Lower Relevant | E101: 6 | F101: 1 | G101: 0 | H101: 1.35 | I101: 0 | J101: =IF(F101=0,0,H101/F101) -> 1.35 | K101: =IF(F101=0,0,G101/F101) -> 0 | L101: =IF(I101=0,"",H101/I101) | M101: 0 | N101: =IF(G101>0,"Converting",IF(F101>=Rules!$B$10,"Waste: 20+ clicks, 0 orders",IF(H101>0,"Waste so far (under 20 clicks)",""))) -> Waste so far (under 20 clicks) | O101: Negative in the rebuild (wrong size, product or colour)
...

Sheet Rebuild Plan
A1: Rebuild the campaign structure from scratch, only after the listing and other fixes are verified
A2: Until every gate below passes, the account stays in maintenance mode (Live Set tab, hard cap). Yellow cells are for status and dates.
A4: A. Gates: all must pass before any new campaign is built
A5: # | B5: Gate | C5: Pass mark | D5: Owner | E5: Source | F5: Status | G5: Date verified
A6: 1 | B6: Listing rebuild live | C6: Title leads with 'boho throw blanket' (first 80 characters); 'Uzbek' moved to bullet 2; main image test B; scale, texture, reversible and lifestyle images; 5-module A+; 20-second video; descriptive variation names | D6: Joseph, Nat, AB | E6: Pack D5, file 10; target 6 Nov
A7: 2 | B7: Image errors fixed | C7: No wrong size anywhere (box art shows 50" x 40"); misspelt 'Elcephoria' removed from box art; size truth on every child | D7: AB, Nat | E7: Slack 20 Oct (AB screenshot)
A8: 3 | B8: Conversion verified on the new page | C8: Unit session % of at least the Rules-tab gate (4%) on 300+ sessions over 14 days; cart-add rate on 'boho throw blanket' at or above the market's (13%) in SQP | D8: Joseph | E8: Pack files 09, 10, 14; Core Term Test tab
A9: 4 | B9: Catalogue hygiene | C9: Unmerged test children Inactive; variation family correct; review count stable for 14 days | D9: AB | E9: Pack P1-6
A10: 5 | B10: Quality and negative feedback | C10: Moosa's Decision Cards closed for colour accuracy, shrinkage guidance and loose threads; return reasons per child pulled | D10: Moosa | E10: Pack P2-1
A11: 6 | B11: Unit economics | C11: Landed cost reconciled (D8); FBA fee and cube per child confirmed; break-even ACoS per SKU loaded in SellerBoard and the Command Center | D11: Joseph, Zarlish | E11: Pack D8, T2
A12: 7 | B12: Price set after BFCM | C12: D1 and D2 closed; post-BFCM price per size decided (50x60 test at $29.99 per pack rule 3) | D12: Erik, Joseph | E12: Pack file 08
A13: 8 | B13: Inventory and exit plan | C13: D6 decided: units to sell through by 14 Mar 2027 and units kept; the ad envelope sized to that plan | D13: Joseph, Haroon, Zarlish | E13: Pack file 09, D6
A14: 9 | B14: Keyword data refreshed | C14: October Cerebro and SQP pulled (T3); syntax library built for this product in the Command Center (today it has none); size terms 60x80 / 50x60 moved off the exclude list | D14: Joseph | E14: Pack T3; Command Center
A15: 10 | B15: Tracking and ownership | C15: Rank tracking on core and lane terms (DataDive or DataRova); Off-Amazon question answered; day-to-day owner named (D9); weekly Friday report agreed | D15: Erik, Joseph | E15: Pack D9, file 12
B16: Gates passed | C16: =COUNTIF(F6:F15,"Pass")&" of 10 -> "&IF(COUNTIF(F6:F15,"Pass")=10,"BUILD","STAY IN MAINTENANCE") -> 0 of 10 -> STAY IN MAINTENANCE
B17: Type 'Pass' in the Status column when a gate is verified.
A19: B. Target structure (built new, not edited from the old campaigns)
A20: # | B20: Campaign group | C20: Objective | D20: Ad type and match | E20: Start set of targets | F20: SKU routing | G20: Start bid | H20: Budget share | I20: Pass mark (after 100 clicks) | J20: Stop rule
A21: 1 | B21: Brand defence | C21: Defensive | D21: SP Exact; Sponsored Brands headline once brand assets exist | E21: sleephoria, sleephoria blanket, sleephoria boho throw blanket | F21: All children | G21: Low; keep top of search | H21: 5% | I21: Impression share on brand terms 80%+ | J21: None (always on, capped)
A22: 2 | B22: Core exact: proven | C22: Profitable conversion | D22: SP Exact, one keyword per campaign | E22: bohemian throw blanket, bohemian blanket, boho throws, boho throw | F22: Butterfly 50x60 primary; 60x80 for bed terms | G22: Worth-based: target ACoS x AOV x CVR (Live Set method) | H22: 30% | I22: CVR 4%+; ACoS at or under break-even after the rebuild | J22: CVR under 2% after 100 clicks: pause
A23: 3 | B23: Core exact: retest | C23: Ranking (capped loss) | D23: SP Exact, one keyword per campaign | E23: boho throw blanket, boho blanket, boho throw blankets for couch | F23: Butterfly 50x60 | G23: Worth-based; TOS modifier from placement CVRs, max +300% | H23: 25% | I23: 2+ cart adds per 20 clicks; 1+ order per 50 clicks; organic rank moving toward top 20 | J23: No order in 50 clicks: pause
A24: 4 | B24: Design lane | C24: Discovery to conversion | D24: SP Phrase; exacts of other lanes negated | E24: vintage floral throw blanket, floral throw blanket, woven throw blanket, throw blanket with tassels, reversible throw blanket | F24: Bloom / Bouquet for floral; Butterfly for woven and tassel | G24: 60% of core bid | H24: 10% | I24: CVR 3%+ | J24: CVR under 2% after 100 clicks: pause
A25: 5 | B25: Butterfly lane | C25: Profitable conversion | D25: SP Exact | E25: butterfly throw blanket, butterfly blanket, butterfly throw | F25: Butterfly only | G25: Worth-based | H25: 5% | I25: CVR 3%+ | J25: CVR under 2%: pause
A26: 6 | B26: Material lane | C26: Discovery | D26: SP Phrase | E26: cotton throw blanket, 100% cotton throw blanket, boho cotton blanket, cotton throw blanket for couch | F26: Butterfly | G26: 60% of core bid | H26: 10% | I26: CVR 3%+ | J26: CVR under 2%: pause
A27: 7 | B27: Size lane | C27: Profitable conversion | D27: SP Exact | E27: throw blanket 60x80, 60x80 throw blankets, 50x60 throw blanket, boho blanket 60x80 | F27: Matching size child only | G27: Worth-based | H27: 5% | I27: CVR 3%+ | J27: CVR under 2%: pause
A28: 8 | B28: Fall hybrid (seasonal, only if timing allows) | C28: Seasonal test | D28: SP Exact and phrase | E28: fall boho throw blanket, autumn boho blanket, fall floral throw blanket | F28: Butterfly / Bloom | G28: Worth-based | H28: 5% for 14 days | I28: CVR at least the core CVR and 3%+ | J28: Under 2%: pause; ends after Thanksgiving
A29: 9 | B29: Auto discovery | C29: Harvest | D29: SP Auto, close match only | E29: Auto | F29: Butterfly 50x60 | G29: $0.20 to $0.30 | H29: 5% | I29: Terms with 2+ orders harvested to exact | J29: Negate terms with 15+ clicks and 0 orders
A30: 10 | B30: Competitor product targeting | C30: Conquest (after core passes) | D30: SP Product targeting | E30: Bailix B0DHKTZTMN, MSGKV B0BLRBXBX5, LUTBM B0BN9XZJY4, VANJOROY B0DYTLQC93 (size and price matched) | F30: Same size as the competitor page; Butterfly first | G30: Keyword-parity | H30: 0% until core passes, then up to 10% | I30: CVR 2%+ | J30: 0 orders in 30 clicks: pause
A31: 11 | B31: Sponsored Brands Video | C31: Consideration | D31: SBV on core and design terms | E31: Core and design keywords | F31: Butterfly hero | G31: Category-typical | H31: 0% until the video is live | I31: CTR above SP; CVR 2%+ | J31: ACoS above 3x break-even after 100 clicks
A32: 12 | B32: Sponsored Display | C32: Retargeting | D32: SD views remarketing | E32: Viewed our listing, 30 days | F32: All | G32: Low | H32: 0% until CVR passes | I32: ROAS above 1 | J32: No order in 30 days
A34: C. Rules the new structure is built on
A35: 1. | B35: Every campaign has one objective, one match type and one SKU. No campaign mixes intents (the old setup mixed king terms with 60x80 terms, and couch with bed and beach).
A36: 2. | B36: Starting bids come from what a click is worth (target ACoS x order value x expected CVR), not from suggested bids. Top of Search modifier from measured placement CVRs, never above +300%.
A37: 3. | B37: Break-even ACoS comes from the reconciled landed cost per SKU (gate 6), not the current estimate.
A38: 4. | B38: Negatives from day one: king, queen, twin, quilt, comforter, picnic, beach, heated, fleece, muslin, no fringe, non-matching colours, competitor brand names, and every 'Negative' term on the Search Terms tab.
A39: 5. | B39: Phrase campaigns carry their lane's exact terms as negative exact, so each search has one owner.
A40: 6. | B40: Budget envelope sized to the inventory plan (gate 8) and released lane by lane: a lane gets more budget only after it passes its mark at 100 clicks.
A41: 7. | B41: Weekly read every Friday (pack file 12 report). Change one lever per campaign per cycle, then hold 14 days (repo README principles 3 and 4).
A42: 8. | B42: Naming: SL-BB-SP-[MATCH]-[keyword or ASIN]-[lane]-[SKU], so every report groups by lane and SKU.
A44: D. Timeline
A45: # | B45: When | C45: What | D45: Who
A46: 1 | B46: Now to 6 Nov | C46: Maintenance mode: only the Live Set runs, under the hard cap. Everything else paused, nothing deleted.
A47: 2 | B47: 6 Nov | C47: Rebuilt listing live (gate 1).
A48: 3 | B48: 6 to 20 Nov | C48: 14 days of conversion data on the new page, with the Live Set only (gate 3). Close gates 4 to 10 in parallel.
A49: 4 | B49: About 20 Nov | C49: Gate review. All pass: build the new structure as a bulk file and upload. Any fail: stay in maintenance and fix that gate.
A50: 5 | B50: Launch + 14 days | C50: First read per lane against its pass mark; release or cut budget lane by lane.
A51: 6 | B51: 15 Jan 2027 | C51: Sell-through review against the D6 plan.
A52: 7 | B52: 14 Mar 2027 | C52: Last removal or liquidation date before the $5.45 aged-fee band (check receipt dates).

Sheet Approvals
A1: Decisions for Joseph
A2: Pauses, re-enables, bid cuts above 15% and modifier changes need the manager (config/thresholds.yml authority). Record each decision in the yellow cells.
A4: # | B4: Decision | C4: Recommendation | D4: Evidence | E4: Decision | F4: Date
A5: 1 | B5: Spend ceiling (D4) | C5: Set the 'SLEEPHORIA - Boho Blanket' portfolio budget to $25 a day ($175 a week), the Phase 0 / D4 figure | D5: Open decision from Erik's 20 Oct post. Live budgets add up to $25; expected spend about $3 to $5 a day (Live Set tab).
A6: 2 | B6: Upload the bulk file | C6: 3 enabled, 37 paused, 2 top-of-search boost rows | D6: Decisions tab; the bulk file passed all upload checks
A7: 3 | B7: 'bohemian throw blanket' | C7: Keep live; bid $0.52 and TOS +280% unchanged; budget $9.41 to $10 | D7: 4 on-Amazon orders, 1 in the last 30 days
A8: 4 | B8: Re-enable 'bohemian blanket' | C8: Bid $0.69 unchanged; TOS +450% to +300%; budget $10 | D8: 2 orders in the last 30 days; +450% allowed up to $3.80 a click
A9: 5 | B9: Brand defence | C9: Bid $0.68 unchanged; TOS +380% to +300%; budget $11.32 to $5 | D9: Plan cap +300%; brand clicks cost about $0.34
A10: 6 | B10: TOS steps above the 20-point rule | C10: Approve +450% to +300% and +380% to +300% in one step | D10: config/thresholds.yml W6 limits placement moves to 20 points per 14 days
A11: 7 | B11: 'boho throw blanket' (hero term) | C11: Keep paused; do not negate; first test after the rebuild | D11: Core Term Test tab: 0 cart adds on 38 clicks
A12: 8 | B12: Off-Amazon | C12: Check the 11 to 12 Sep change history on 'boho king size blanket' and the Off-Amazon setting on the 3 live campaigns | D12: Placements tab: 2-week burst on idle budgets, stopped as campaigns were cut or paused
A13: 9 | B13: Rebuild | C13: Approve the gates and the target structure; build only when all gates pass | D13: Rebuild Plan tab

Sheet Campaigns
A1: All 40 boho campaigns: settings, metrics, checks and decision
A2: Sorted by spend since launch. Metrics: Ecotero Command Center (Sponsored Products, US). State, budget, TOS modifier: DataDive, 22 Oct 2026. Sales take up to 7 days to be credited, so recent windows read slightly low.
A4: Campaign | H4: Settings, 22 Oct | M4: Since launch: 24 Aug to 22 Oct | W4: Last 30 days: 23 Sep to 22 Oct | AC4: Last 15 days: 8 to 22 Oct | AH4: Placement since launch (spend split from Amazon's placement share) | AQ4: Checks (formulas) | AT4: Decision
A5: Campaign ID | B5: Campaign name | C5: Target(s) | D5: Type | E5: Keyword family | F5: Advertised SKU | G5: Plan status (Phase 0) | H5: State | I5: Daily budget | J5: TOS modifier | K5: Base bid (known) | L5: Max TOS bid | M5: Impr. | N5: Clicks | O5: Spend | P5: Orders | Q5: Sales | R5: CTR | S5: CVR | T5: CPC | U5: ACoS | V5: ROAS | W5: Clicks | X5: Spend | Y5: Orders | Z5: Sales | AA5: CVR | AB5: ACoS | AC5: Clicks | AD5: Spend | AE5: Orders | AF5: Sales | AG5: CVR | AH5: TOS clicks | AI5: TOS spend | AJ5: Product page clicks | AK5: Product page spend | AL5: Rest of search clicks | AM5: Rest of search spend | AN5: Off-Amazon clicks | AO5: Off-Amazon spend | AP5: Off-Amazon share of spend | AQ5: CVR rule (since launch) | AR5: ACoS check | AS5: TOS modifier check | AT5: Decision category | AU5: New state | AV5: Action | AW5: Why | AX5: Approver | AY5: Done? (Y/N)
A6: 43669682187702 | B6: SL-BB-SP-boho king size blanket-Boho|Blanket|Size-VLSV-Exact-Rank-Fixed-SL-BOHO-BLANKET-BUTTERFLY-60x80-1-PC | C6: big boho blanket · boho blanket 60x 80 · boho king size blanket +1 more keywords | D6: SP Exact keyword | E6: Boho size (king / queen / 60x80) | F6: SL-BOHO-BLANKET-BUTTERFLY-60x80-1-PC | G6: Phase 0: run (as 'converting long tail') | H6: ENABLED | I6: 30.09 | J6: 4.13 | K6: 0.97 | L6: =IF(OR(K6="",J6=""),"",K6*(1+J6)) -> 4.9761 | M6: 19211 | N6: 1063 | O6: 239.23 | P6: 9 | Q6: 282.91 | R6: =IF(M6=0,0,N6/M6) -> 0.055332882 | S6: =IF(N6=0,0,P6/N6) -> 0.008466604 | T6: =IF(N6=0,0,O6/N6) -> 0.22505174 | U6: =IF(Q6=0,"",O6/Q6) -> 0.84560461 | V6: =IF(O6=0,0,Q6/O6) -> 1.1825858 | W6: 28 | X6: 34.14 | Y6: 0 | Z6: 0 | AA6: =IF(W6=0,0,Y6/W6) -> 0 | AB6: =IF(Z6=0,"",X6/Z6) | AC6: 18 | AD6: 21.48 | AE6: 0 | AF6: 0 | AG6: =IF(AC6=0,0,AE6/AC6) -> 0 | AH6: 11 | AI6: 23.41 | AJ6: 21 | AK6: 17.03 | AL6: 4 | AM6: 3.66 | AN6: 1027 | AO6: 195.13 | AP6: =IF(O6=0,0,AO6/O6) -> 0.81565857 | AQ6: =IF(N6<Rules!$B$10,"Under 20 clicks: too early",IF(P6=0,"20+ clicks, 0 orders: negate / pause",IF(N6<Rules!$B$11,"Under 100 clicks: watch",IF(S6>=Rules!$B$12,"4%+: keep",IF(S6>=Rules!$B$13,"2% to 4%: hold at lower bid","Under 2%: pause"))))) -> Under 2%: pause | AR6: =IF(O6=0,"",IF(Q6=0,"Spend, no sales",IF(U6>Rules!$B$33,"Above 3x break-even","Within 3x break-even"))) -> Above 3x break-even | AS6: =IF(OR(J6="",H6<>"ENABLED"),"",IF(J6>Rules!$B$9,"Above +300% cap","OK")) -> Above +300% cap | AT6: 4 RESTRUCTURE IN REBUILD | AU6: PAUSED | AV6: Pause now. In the rebuild: negate king terms; move the 60x80 size terms to a size lane on the 60x80 SKU | AW6: All 9 orders came from Off-Amazon (1,027 of 1,063 clicks), which stopped in late September. On Amazon: 0 orders on 36 clicks; bid $0.97 x +413% = up to $4.98 a click; the largest budget ($30). It mixes king-size terms (wrong size for a 60x80 throw) with 'boho blanket 60x 80' (the right size; organic rank 32). | AX6: Joseph approves; Shayan applies
A7: 240955455575163 | B7: SL-BB-SP-boho throw blankets for couch-Boho|Blanket|Core-VLSV-Exact-Rank-Fixed-SL-BOHO-BLANKET-BUTTERFLY-50x60-1-PC | C7: boho throw blankets for couch | D7: SP Exact keyword | E7: Boho couch / bed | F7: SL-BOHO-BLANKET-BUTTERFLY-50x60-1-PC | G7: Not in Phase 0 | H7: ENABLED | I7: 13.04 | J7: 3 | L7: =IF(OR(K7="",J7=""),"",K7*(1+J7)) | M7: 12334 | N7: 476 | O7: 158.98 | P7: 5 | Q7: 150.95 | R7: =IF(M7=0,0,N7/M7) -> 0.038592509 | S7: =IF(N7=0,0,P7/N7) -> 0.010504202 | T7: =IF(N7=0,0,O7/N7) -> 0.3339916 | U7: =IF(Q7=0,"",O7/Q7) -> 1.0531964 | V7: =IF(O7=0,0,Q7/O7) -> 0.9494905 | W7: 31 | X7: 44.99 | Y7: 0 | Z7: 0 | AA7: =IF(W7=0,0,Y7/W7) -> 0 | AB7: =IF(Z7=0,"",X7/Z7) | AC7: 7 | AD7: 12.48 | AE7: 0 | AF7: 0 | AG7: =IF(AC7=0,0,AE7/AC7) -> 0 | AH7: 26 | AI7: 47.63 | AJ7: 27 | AK7: 31.46 | AL7: 1 | AM7: 0.64 | AN7: 422 | AO7: 79.25 | AP7: =IF(O7=0,0,AO7/O7) -> 0.49849038 | AQ7: =IF(N7<Rules!$B$10,"Under 20 clicks: too early",IF(P7=0,"20+ clicks, 0 orders: negate / pause",IF(N7<Rules!$B$11,"Under 100 clicks: watch",IF(S7>=Rules!$B$12,"4%+: keep",IF(S7>=Rules!$B$13,"2% to 4%: hold at lower bid","Under 2%: pause"))))) -> Under 2%: pause | AR7: =IF(O7=0,"",IF(Q7=0,"Spend, no sales",IF(U7>Rules!$B$33,"Above 3x break-even","Within 3x break-even"))) -> Above 3x break-even | AS7: =IF(OR(J7="",H7<>"ENABLED"),"",IF(J7>Rules!$B$9,"Above +300% cap","OK")) -> OK | AT7: 3 RETEST AFTER REBUILD | AU7: PAUSED | AV7: Pause now; retest after the rebuild | AW7: 5 orders since launch, but 4 came from Off-Amazon traffic (422 of 476 clicks), which has stopped. On Amazon: 1 order on 54 clicks, and 0 orders on 31 clicks ($45) in the last 30 days. SQP cart adds are fine (3 on 23 clicks), so the term fits; the page does not close. | AX7: Joseph approves; Shayan applies
A8: 131359054806082 | B8: SL-BB-SP-boho blanket-Boho|Blanket|Core-MSV-Exact-Rank-Fixed-SL-BOHO-BLANKET-BUTTERFLY-50x60-1-PC | C8: boho blanket | D8: SP Exact keyword | E8: Boho core | F8: SL-BOHO-BLANKET-BUTTERFLY-50x60-1-PC | G8: Phase 0: run | H8: PAUSED | I8: 40 | L8: =IF(OR(K8="",J8=""),"",K8*(1+J8)) | M8: 24103 | N8: 187 | O8: 138.56 | P8: 3 | Q8: 88.97 | R8: =IF(M8=0,0,N8/M8) -> 0.0077583703 | S8: =IF(N8=0,0,P8/N8) -> 0.016042781 | T8: =IF(N8=0,0,O8/N8) -> 0.74096257 | U8: =IF(Q8=0,"",O8/Q8) -> 1.5573789 | V8: =IF(O8=0,0,Q8/O8) -> 0.6421045 | W8: 0 | X8: 0 | Y8: 0 | Z8: 0 | AA8: =IF(W8=0,0,Y8/W8) -> 0 | AB8: =IF(Z8=0,"",X8/Z8) | AC8: 0 | AD8: 0 | AE8: 0 | AF8: 0 | AG8: =IF(AC8=0,0,AE8/AC8) -> 0 | AH8: 15 | AI8: 19.03 | AJ8: 168 | AK8: 118.06 | AL8: 2 | AM8: 1.48 | AN8: 0 | AO8: 0 | AP8: =IF(O8=0,0,AO8/O8) -> 0 | AQ8: =IF(N8<Rules!$B$10,"Under 20 clicks: too early",IF(P8=0,"20+ clicks, 0 orders: negate / pause",IF(N8<Rules!$B$11,"Under 100 clicks: watch",IF(S8>=Rules!$B$12,"4%+: keep",IF(S8>=Rules!$B$13,"2% to 4%: hold at lower bid","Under 2%: pause"))))) -> Under 2%: pause | AR8: =IF(O8=0,"",IF(Q8=0,"Spend, no sales",IF(U8>Rules!$B$33,"Above 3x break-even","Within 3x break-even"))) -> Above 3x break-even | AS8: =IF(OR(J8="",H8<>"ENABLED"),"",IF(J8>Rules!$B$9,"Above +300% cap","OK")) | AT8: 3 RETEST AFTER REBUILD | AU8: PAUSED | AV8: Keep paused; retest after the rebuild | AW8: 3 orders on 185 on-Amazon clicks (1.6%), all from product pages; ACoS 156% on a $40 a day budget. SQP cart adds are normal for the market (3 on 29 vs 3.4 expected), so the term fits; the old page does not close. Large demand (4,932 a month): worth retesting on the new page, not worth paying for on the old one. | AX8: Joseph approves; Shayan applies
A9: 271118311398471 | B9: SL-BB-SP-bohemian throw blanket-Boho|Blanket|Core-LSV-Exact-Rank-Fixed-SL-BOHO-BLANKET-BUTTERFLY-50x60-1-PC | C9: bohemian throw blanket | D9: SP Exact keyword | E9: Boho core | F9: SL-BOHO-BLANKET-BUTTERFLY-50x60-1-PC | G9: Phase 0: run | H9: ENABLED | I9: 9.41 | J9: 2.8 | K9: 0.52 | L9: =IF(OR(K9="",J9=""),"",K9*(1+J9)) -> 1.976 | M9: 18482 | N9: 184 | O9: 128.41 | P9: 4 | Q9: 150.95 | R9: =IF(M9=0,0,N9/M9) -> 0.0099556325 | S9: =IF(N9=0,0,P9/N9) -> 0.02173913 | T9: =IF(N9=0,0,O9/N9) -> 0.69788043 | U9: =IF(Q9=0,"",O9/Q9) -> 0.85067903 | V9: =IF(O9=0,0,Q9/O9) -> 1.1755315 | W9: 92 | X9: 69.17 | Y9: 1 | Z9: 34.99 | AA9: =IF(W9=0,0,Y9/W9) -> 0.010869565 | AB9: =IF(Z9=0,"",X9/Z9) -> 1.9768505 | AC9: 40 | AD9: 29.79 | AE9: 1 | AF9: 34.99 | AG9: =IF(AC9=0,0,AE9/AC9) -> 0.025 | AH9: 29 | AI9: 45.82 | AJ9: 155 | AK9: 82.59 | AL9: 0 | AM9: 0 | AN9: 0 | AO9: 0 | AP9: =IF(O9=0,0,AO9/O9) -> 0 | AQ9: =IF(N9<Rules!$B$10,"Under 20 clicks: too early",IF(P9=0,"20+ clicks, 0 orders: negate / pause",IF(N9<Rules!$B$11,"Under 100 clicks: watch",IF(S9>=Rules!$B$12,"4%+: keep",IF(S9>=Rules!$B$13,"2% to 4%: hold at lower bid","Under 2%: pause"))))) -> 2% to 4%: hold at lower bid | AR9: =IF(O9=0,"",IF(Q9=0,"Spend, no sales",IF(U9>Rules!$B$33,"Above 3x break-even","Within 3x break-even"))) -> Above 3x break-even | AS9: =IF(OR(J9="",H9<>"ENABLED"),"",IF(J9>Rules!$B$9,"Above +300% cap","OK")) -> OK | AT9: 1 RETAIN (generating orders) | AU9: ENABLED | AV9: Keep live. Bid unchanged ($0.52); TOS +280% unchanged; budget $9.41 to $10 a day | AW9: Only live core term still converting: 4 on-Amazon orders since launch, 1 in the last 30 days. SQP cart adds in line with the market (3 on 24 clicks vs 3.2 expected). ACoS 85%. Held as is (no bid test); the budget covers about 6 top-of-search clicks a day at its real CPC ($1.72). | AX9: Joseph approves; Shayan applies
A10: 103168292442380 | B10: SL-BB-SP-B0BLRBXBX5-Exact-Conq-Fixed-SL-BOHO-BLANKET-BOUQUET-60x80-1-PC | C10: B0BLRBXBX5 | D10: SP Product targeting | E10: Competitor PAT | F10: SL-BOHO-BLANKET-BOUQUET-60x80-1-PC | G10: Not in Phase 0 (Phase 1 lane L9) | H10: ENABLED | I10: 4.5 | J10: 2.8 | L10: =IF(OR(K10="",J10=""),"",K10*(1+J10)) | M10: 7633 | N10: 67 | O10: 103.08 | P10: 1 | Q10: 34.99 | R10: =IF(M10=0,0,N10/M10) -> 0.0087776759 | S10: =IF(N10=0,0,P10/N10) -> 0.014925373 | T10: =IF(N10=0,0,O10/N10) -> 1.5385075 | U10: =IF(Q10=0,"",O10/Q10) -> 2.9459846 | V10: =IF(O10=0,0,Q10/O10) -> 0.33944509 | W10: 66 | X10: 102.49 | Y10: 1 | Z10: 34.99 | AA10: =IF(W10=0,0,Y10/W10) -> 0.015151515 | AB10: =IF(Z10=0,"",X10/Z10) -> 2.9291226 | AC10: 48 | AD10: 84.43 | AE10: 1 | AF10: 34.99 | AG10: =IF(AC10=0,0,AE10/AC10) -> 0.020833333 | AH10: 48 | AI10: 91.87 | AJ10: 18 | AK10: 10.62 | AL10: 1 | AM10: 0.59 | AN10: 0 | AO10: 0 | AP10: =IF(O10=0,0,AO10/O10) -> 0 | AQ10: =IF(N10<Rules!$B$10,"Under 20 clicks: too early",IF(P10=0,"20+ clicks, 0 orders: negate / pause",IF(N10<Rules!$B$11,"Under 100 clicks: watch",IF(S10>=Rules!$B$12,"4%+: keep",IF(S10>=Rules!$B$13,"2% to 4%: hold at lower bid","Under 2%: pause"))))) -> Under 100 clicks: watch | AR10: =IF(O10=0,"",IF(Q10=0,"Spend, no sales",IF(U10>Rules!$B$33,"Above 3x break-even","Within 3x break-even"))) -> Above 3x break-even | AS10: =IF(OR(J10="",H10<>"ENABLED"),"",IF(J10>Rules!$B$9,"Above +300% cap","OK")) -> OK | AT10: 4 RESTRUCTURE IN REBUILD | AU10: PAUSED | AV10: Pause now; rebuild as a size- and price-matched product-targeting lane | AW10: The only competitor target with an order: 1 on 67 clicks, $103 per order, $1.54 a click, 90% of spend at Top of Search (+280%). All 10 product-targeting campaigns advertise Bouquet 60x80 whatever the competitor's size or price (MSGKV 60x80 sells at $29.99 vs our $34.99). | AX10: Joseph approves; Shayan applies
A11: 143967856454663 | B11: SL-BB-SP-boho throw-Boho|Blanket|Core-MSV-Exact-Rank-Fixed-SL-BOHO-BLANKET-BUTTERFLY-50x60-1-PC | C11: boho throw | D11: SP Exact keyword | E11: Boho core | F11: SL-BOHO-BLANKET-BUTTERFLY-50x60-1-PC | G11: Phase 0: run | H11: PAUSED | I11: 5.72 | L11: =IF(OR(K11="",J11=""),"",K11*(1+J11)) | M11: 10439 | N11: 125 | O11: 92.74 | P11: 3 | Q11: 80.97 | R11: =IF(M11=0,0,N11/M11) -> 0.011974327 | S11: =IF(N11=0,0,P11/N11) -> 0.024 | T11: =IF(N11=0,0,O11/N11) -> 0.74192 | U11: =IF(Q11=0,"",O11/Q11) -> 1.1453625 | V11: =IF(O11=0,0,Q11/O11) -> 0.87308605 | W11: 0 | X11: 0 | Y11: 0 | Z11: 0 | AA11: =IF(W11=0,0,Y11/W11) -> 0 | AB11: =IF(Z11=0,"",X11/Z11) | AC11: 0 | AD11: 0 | AE11: 0 | AF11: 0 | AG11: =IF(AC11=0,0,AE11/AC11) -> 0 | AH11: 39 | AI11: 47.01 | AJ11: 83 | AK11: 43.78 | AL11: 3 | AM11: 1.95 | AN11: 0 | AO11: 0 | AP11: =IF(O11=0,0,AO11/O11) -> 0 | AQ11: =IF(N11<Rules!$B$10,"Under 20 clicks: too early",IF(P11=0,"20+ clicks, 0 orders: negate / pause",IF(N11<Rules!$B$11,"Under 100 clicks: watch",IF(S11>=Rules!$B$12,"4%+: keep",IF(S11>=Rules!$B$13,"2% to 4%: hold at lower bid","Under 2%: pause"))))) -> 2% to 4%: hold at lower bid | AR11: =IF(O11=0,"",IF(Q11=0,"Spend, no sales",IF(U11>Rules!$B$33,"Above 3x break-even","Within 3x break-even"))) -> Above 3x break-even | AS11: =IF(OR(J11="",H11<>"ENABLED"),"",IF(J11>Rules!$B$9,"Above +300% cap","OK")) | AT11: 3 RETEST AFTER REBUILD | AU11: PAUSED | AV11: Keep paused; retest first after the rebuild | AW11: 3 orders on 125 clicks (2.4%), all at Top of Search; ACoS 115%. The closest of the core terms to break-even, but no orders since September and SQP shows 1 cart add on 34 clicks vs about 3.9 expected. | AX11: Joseph approves; Shayan applies
A12: 52789396358241 | B12: SL-BB-SP-throw blanket boho-Boho|Blanket|Core-MSV-Exact-Rank-Fixed-SL-BOHO-BLANKET-BUTTERFLY-50x60-1-PC | C12: throw blanket boho | D12: SP Exact keyword | E12: Boho core | F12: SL-BOHO-BLANKET-BUTTERFLY-50x60-1-PC | G12: Phase 0: run AND stop list | H12: PAUSED | I12: 6.59 | L12: =IF(OR(K12="",J12=""),"",K12*(1+J12)) | M12: 6970 | N12: 71 | O12: 63.38 | P12: 0 | Q12: 0 | R12: =IF(M12=0,0,N12/M12) -> 0.010186514 | S12: =IF(N12=0,0,P12/N12) -> 0 | T12: =IF(N12=0,0,O12/N12) -> 0.89267606 | U12: =IF(Q12=0,"",O12/Q12) | V12: =IF(O12=0,0,Q12/O12) -> 0 | W12: 0 | X12: 0 | Y12: 0 | Z12: 0 | AA12: =IF(W12=0,0,Y12/W12) -> 0 | AB12: =IF(Z12=0,"",X12/Z12) | AC12: 0 | AD12: 0 | AE12: 0 | AF12: 0 | AG12: =IF(AC12=0,0,AE12/AC12) -> 0 | AH12: 14 | AI12: 25.12 | AJ12: 57 | AK12: 38.26 | AL12: 0 | AM12: 0 | AN12: 0 | AO12: 0 | AP12: =IF(O12=0,0,AO12/O12) -> 0 | AQ12: =IF(N12<Rules!$B$10,"Under 20 clicks: too early",IF(P12=0,"20+ clicks, 0 orders: negate / pause",IF(N12<Rules!$B$11,"Under 100 clicks: watch",IF(S12>=Rules!$B$12,"4%+: keep",IF(S12>=Rules!$B$13,"2% to 4%: hold at lower bid","Under 2%: pause"))))) -> 20+ clicks, 0 orders: negate / pause | AR12: =IF(O12=0,"",IF(Q12=0,"Spend, no sales",IF(U12>Rules!$B$33,"Above 3x break-even","Within 3x break-even"))) -> Spend, no sales | AS12: =IF(OR(J12="",H12<>"ENABLED"),"",IF(J12>Rules!$B$9,"Above +300% cap","OK")) | AT12: 5 PAUSE (wasted spend) | AU12: PAUSED | AV12: Keep paused; drop from the core list | AW12: 0 orders on 71 clicks ($63); SQP 1 cart add on 14 clicks. Same intent as 'boho throw blanket', whose retest covers it; no separate campaign needed. | AX12: Joseph approves; Shayan applies
A13: 143960123876477 | B13: SL-BB-SP-boho scandinavian cotton blanket-Boho|Blanket|Material-VLSV-Exact-Rank-Fixed-SL-BOHO-BLANKET-BUTTERFLY-50x60-1-PC | C13: boho blanket throw cotton · boho cotton throw blanket · boho scandinavian cotton blanket +2 more keywords | D13: SP Exact keyword | E13: Boho material (cotton) | F13: SL-BOHO-BLANKET-BUTTERFLY-50x60-1-PC | G13: Not in Phase 0 | H13: PAUSED | I13: 47.56 | L13: =IF(OR(K13="",J13=""),"",K13*(1+J13)) | M13: 11819 | N13: 77 | O13: 62.97 | P13: 1 | Q13: 26.99 | R13: =IF(M13=0,0,N13/M13) -> 0.0065149336 | S13: =IF(N13=0,0,P13/N13) -> 0.012987013 | T13: =IF(N13=0,0,O13/N13) -> 0.81779221 | U13: =IF(Q13=0,"",O13/Q13) -> 2.3330863 | V13: =IF(O13=0,0,Q13/O13) -> 0.4286168 | W13: 0 | X13: 0 | Y13: 0 | Z13: 0 | AA13: =IF(W13=0,0,Y13/W13) -> 0 | AB13: =IF(Z13=0,"",X13/Z13) | AC13: 0 | AD13: 0 | AE13: 0 | AF13: 0 | AG13: =IF(AC13=0,0,AE13/AC13) -> 0 | AH13: 23 | AI13: 31.46 | AJ13: 35 | AK13: 25.1 | AL13: 4 | AM13: 3.44 | AN13: 15 | AO13: 2.97 | AP13: =IF(O13=0,0,AO13/O13) -> 0.047165317 | AQ13: =IF(N13<Rules!$B$10,"Under 20 clicks: too early",IF(P13=0,"20+ clicks, 0 orders: negate / pause",IF(N13<Rules!$B$11,"Under 100 clicks: watch",IF(S13>=Rules!$B$12,"4%+: keep",IF(S13>=Rules!$B$13,"2% to 4%: hold at lower bid","Under 2%: pause"))))) -> Under 100 clicks: watch | AR13: =IF(O13=0,"",IF(Q13=0,"Spend, no sales",IF(U13>Rules!$B$33,"Above 3x break-even","Within 3x break-even"))) -> Above 3x break-even | AS13: =IF(OR(J13="",H13<>"ENABLED"),"",IF(J13>Rules!$B$9,"Above +300% cap","OK")) | AT13: 4 RESTRUCTURE IN REBUILD | AU13: PAUSED | AV13: Keep paused; split in the rebuild | AW13: 5 keywords in one campaign; 1 order on 62 on-Amazon clicks; TOS +450%. 'Scandinavian' does not describe this product. | AX13: Joseph approves; Shayan applies
A14: 73752905509119 | B14: SL-BB-SP-boho blankets and throws-Boho|Blanket|Core-VLSV-Exact-Rank-Fixed-SL-BOHO-BLANKET-BUTTERFLY-50x60-1-PC | C14: boho blankets and throws | D14: SP Exact keyword | E14: Boho core | F14: SL-BOHO-BLANKET-BUTTERFLY-50x60-1-PC | G14: Phase 0: stop list | H14: PAUSED | I14: 7.56 | L14: =IF(OR(K14="",J14=""),"",K14*(1+J14)) | M14: 10098 | N14: 72 | O14: 62.18 | P14: 0 | Q14: 0 | R14: =IF(M14=0,0,N14/M14) -> 0.0071301248 | S14: =IF(N14=0,0,P14/N14) -> 0 | T14: =IF(N14=0,0,O14/N14) -> 0.86361111 | U14: =IF(Q14=0,"",O14/Q14) | V14: =IF(O14=0,0,Q14/O14) -> 0 | W14: 2 | X14: 1.36 | Y14: 0 | Z14: 0 | AA14: =IF(W14=0,0,Y14/W14) -> 0 | AB14: =IF(Z14=0,"",X14/Z14) | AC14: 0 | AD14: 0 | AE14: 0 | AF14: 0 | AG14: =IF(AC14=0,0,AE14/AC14) -> 0 | AH14: 16 | AI14: 26.02 | AJ14: 54 | AK14: 34.98 | AL14: 2 | AM14: 1.18 | AN14: 0 | AO14: 0 | AP14: =IF(O14=0,0,AO14/O14) -> 0 | AQ14: =IF(N14<Rules!$B$10,"Under 20 clicks: too early",IF(P14=0,"20+ clicks, 0 orders: negate / pause",IF(N14<Rules!$B$11,"Under 100 clicks: watch",IF(S14>=Rules!$B$12,"4%+: keep",IF(S14>=Rules!$B$13,"2% to 4%: hold at lower bid","Under 2%: pause"))))) -> 20+ clicks, 0 orders: negate / pause | AR14: =IF(O14=0,"",IF(Q14=0,"Spend, no sales",IF(U14>Rules!$B$33,"Above 3x break-even","Within 3x break-even"))) -> Spend, no sales | AS14: =IF(OR(J14="",H14<>"ENABLED"),"",IF(J14>Rules!$B$9,"Above +300% cap","OK")) | AT14: 5 PAUSE (wasted spend) | AU14: PAUSED | AV14: Keep paused | AW14: Stop list. 0 orders on 72 clicks ($62). | AX14: Joseph approves; Shayan applies
A15: 140892082966699 | B15: SL-BB-SP-boho blanket king-Boho|Blanket|Size-VLSV-Exact-Rank-Fixed-SL-BOHO-BLANKET-BUTTERFLY-60x80-1-PC | C15: boho blanket king | D15: SP Exact keyword | E15: Boho size (king / queen / 60x80) | F15: SL-BOHO-BLANKET-BUTTERFLY-60x80-1-PC | G15: Exclude list (king / queen) | H15: ENABLED | I15: 5.66 | J15: 3.56 | L15: =IF(OR(K15="",J15=""),"",K15*(1+J15)) | M15: 3733 | N15: 128 | O15: 59.53 | P15: 3 | Q15: 88.97 | R15: =IF(M15=0,0,N15/M15) -> 0.034288776 | S15: =IF(N15=0,0,P15/N15) -> 0.0234375 | T15: =IF(N15=0,0,O15/N15) -> 0.46507813 | U15: =IF(Q15=0,"",O15/Q15) -> 0.66910194 | V15: =IF(O15=0,0,Q15/O15) -> 1.4945406 | W15: 22 | X15: 19.03 | Y15: 0 | Z15: 0 | AA15: =IF(W15=0,0,Y15/W15) -> 0 | AB15: =IF(Z15=0,"",X15/Z15) | AC15: 19 | AD15: 17.08 | AE15: 0 | AF15: 0 | AG15: =IF(AC15=0,0,AE15/AC15) -> 0 | AH15: 8 | AI15: 12.92 | AJ15: 21 | AK15: 13.52 | AL15: 1 | AM15: 0.65 | AN15: 98 | AO15: 32.44 | AP15: =IF(O15=0,0,AO15/O15) -> 0.54493533 | AQ15: =IF(N15<Rules!$B$10,"Under 20 clicks: too early",IF(P15=0,"20+ clicks, 0 orders: negate / pause",IF(N15<Rules!$B$11,"Under 100 clicks: watch",IF(S15>=Rules!$B$12,"4%+: keep",IF(S15>=Rules!$B$13,"2% to 4%: hold at lower bid","Under 2%: pause"))))) -> 2% to 4%: hold at lower bid | AR15: =IF(O15=0,"",IF(Q15=0,"Spend, no sales",IF(U15>Rules!$B$33,"Above 3x break-even","Within 3x break-even"))) -> Above 3x break-even | AS15: =IF(OR(J15="",H15<>"ENABLED"),"",IF(J15>Rules!$B$9,"Above +300% cap","OK")) -> Above +300% cap | AT15: 5 PAUSE (wasted spend) | AU15: PAUSED | AV15: Pause now | AW15: 3 orders, all from Off-Amazon traffic (98 of 128 clicks), which has stopped. On Amazon: 0 orders on 30 clicks. King intent; TOS +356%. | AX15: Joseph approves; Shayan applies
A16: 274384612784893 | B16: SL-BB-SP-bohemian blanket-Boho|Blanket|Core-LSV-Exact-Rank-Fixed-SL-BOHO-BLANKET-BUTTERFLY-50x60-1-PC | C16: bohemian blanket | D16: SP Exact keyword | E16: Boho core | F16: SL-BOHO-BLANKET-BUTTERFLY-50x60-1-PC | G16: Phase 0: stop list | H16: PAUSED | I16: 6.38 | L16: =IF(OR(K16="",J16=""),"",K16*(1+J16)) | M16: 5397 | N16: 50 | O16: 44.85 | P16: 2 | Q16: 61.98 | R16: =IF(M16=0,0,N16/M16) -> 0.0092644062 | S16: =IF(N16=0,0,P16/N16) -> 0.04 | T16: =IF(N16=0,0,O16/N16) -> 0.897 | U16: =IF(Q16=0,"",O16/Q16) -> 0.72362052 | V16: =IF(O16=0,0,Q16/O16) -> 1.3819398 | W16: 28 | X16: 27.71 | Y16: 2 | Z16: 61.98 | AA16: =IF(W16=0,0,Y16/W16) -> 0.071428571 | AB16: =IF(Z16=0,"",X16/Z16) -> 0.4470797 | AC16: 0 | AD16: 0 | AE16: 0 | AF16: 0 | AG16: =IF(AC16=0,0,AE16/AC16) -> 0 | AH16: 19 | AI16: 23.58 | AJ16: 30 | AK16: 20.7 | AL16: 1 | AM16: 0.57 | AN16: 0 | AO16: 0 | AP16: =IF(O16=0,0,AO16/O16) -> 0 | AQ16: =IF(N16<Rules!$B$10,"Under 20 clicks: too early",IF(P16=0,"20+ clicks, 0 orders: negate / pause",IF(N16<Rules!$B$11,"Under 100 clicks: watch",IF(S16>=Rules!$B$12,"4%+: keep",IF(S16>=Rules!$B$13,"2% to 4%: hold at lower bid","Under 2%: pause"))))) -> Under 100 clicks: watch | AR16: =IF(O16=0,"",IF(Q16=0,"Spend, no sales",IF(U16>Rules!$B$33,"Above 3x break-even","Within 3x break-even"))) -> Above 3x break-even | AS16: =IF(OR(J16="",H16<>"ENABLED"),"",IF(J16>Rules!$B$9,"Above +300% cap","OK")) | AT16: 1 RETAIN (generating orders) | AU16: ENABLED | AV16: Re-enable. Bid unchanged ($0.69); TOS +450% to +300%; budget $10 a day | AW16: Best converter on the product: 2 orders on 50 clicks (4.0%), both in the last 30 days, ACoS 72%. It was paused on early-September data. TOS +450% let it pay up to $3.80 a click; +300% caps that at $2.76. | AX16: Joseph approves; Shayan applies
A17: 136479271696362 | B17: SL-BB-SP-boho throw blanket-Boho|Blanket|Core-MSV-Exact-Rank-Fixed-SL-BOHO-BLANKET-BUTTERFLY-50x60-1-PC | C17: boho throw blanket | D17: SP Exact keyword | E17: Boho core | F17: SL-BOHO-BLANKET-BUTTERFLY-50x60-1-PC | G17: Phase 0: run | H17: PAUSED | I17: 30 | L17: =IF(OR(K17="",J17=""),"",K17*(1+J17)) | M17: 3481 | N17: 44 | O17: 42.81 | P17: 0 | Q17: 0 | R17: =IF(M17=0,0,N17/M17) -> 0.012640046 | S17: =IF(N17=0,0,P17/N17) -> 0 | T17: =IF(N17=0,0,O17/N17) -> 0.97295455 | U17: =IF(Q17=0,"",O17/Q17) | V17: =IF(O17=0,0,Q17/O17) -> 0 | W17: 0 | X17: 0 | Y17: 0 | Z17: 0 | AA17: =IF(W17=0,0,Y17/W17) -> 0 | AB17: =IF(Z17=0,"",X17/Z17) | AC17: 0 | AD17: 0 | AE17: 0 | AF17: 0 | AG17: =IF(AC17=0,0,AE17/AC17) -> 0 | AH17: 19 | AI17: 27.01 | AJ17: 19 | AK17: 12.51 | AL17: 5 | AM17: 3.29 | AN17: 0 | AO17: 0 | AP17: =IF(O17=0,0,AO17/O17) -> 0 | AQ17: =IF(N17<Rules!$B$10,"Under 20 clicks: too early",IF(P17=0,"20+ clicks, 0 orders: negate / pause",IF(N17<Rules!$B$11,"Under 100 clicks: watch",IF(S17>=Rules!$B$12,"4%+: keep",IF(S17>=Rules!$B$13,"2% to 4%: hold at lower bid","Under 2%: pause"))))) -> 20+ clicks, 0 orders: negate / pause | AR17: =IF(O17=0,"",IF(Q17=0,"Spend, no sales",IF(U17>Rules!$B$33,"Above 3x break-even","Within 3x break-even"))) -> Spend, no sales | AS17: =IF(OR(J17="",H17<>"ENABLED"),"",IF(J17>Rules!$B$9,"Above +300% cap","OK")) | AT17: 3 RETEST AFTER REBUILD | AU17: PAUSED | AV17: Keep paused. Do not negate. First exact test after the rebuild at the worth-based bid | AW17: Hero term (9,420 searches a month; organic rank about 99). 42 clicks, 0 orders, $39. SQP: 0 add-to-carts on 38 clicks where the market rate (13%) predicts about 5, a chance of about 0.5%. The listing is not converting this search, and a lower bid cannot fix that. It paid $0.94 a click (Top of Search $1.33 at +300%) against about $0.17 a click is worth at the market's 1.6% CVR. Full workings: Core Term Test tab. | AX17: Joseph approves; Shayan applies
A18: 153632991648836 | B18: SL-BB-SP-boho cotton blanket-Boho|Blanket|Material-VLSV-Exact-Rank-Fixed-SL-BOHO-BLANKET-BUTTERFLY-50x60-1-PC | C18: boho cotton blanket | D18: SP Exact keyword | E18: Boho material (cotton) | F18: SL-BOHO-BLANKET-BUTTERFLY-50x60-1-PC | G18: Not in Phase 0 | H18: PAUSED | I18: 7.11 | L18: =IF(OR(K18="",J18=""),"",K18*(1+J18)) | M18: 2574 | N18: 35 | O18: 36.98 | P18: 1 | Q18: 34.99 | R18: =IF(M18=0,0,N18/M18) -> 0.013597514 | S18: =IF(N18=0,0,P18/N18) -> 0.028571429 | T18: =IF(N18=0,0,O18/N18) -> 1.0565714 | U18: =IF(Q18=0,"",O18/Q18) -> 1.0568734 | V18: =IF(O18=0,0,Q18/O18) -> 0.94618713 | W18: 0 | X18: 0 | Y18: 0 | Z18: 0 | AA18: =IF(W18=0,0,Y18/W18) -> 0 | AB18: =IF(Z18=0,"",X18/Z18) | AC18: 0 | AD18: 0 | AE18: 0 | AF18: 0 | AG18: =IF(AC18=0,0,AE18/AC18) -> 0 | AH18: 26 | AI18: 31.61 | AJ18: 9 | AK18: 5.37 | AL18: 0 | AM18: 0 | AN18: 0 | AO18: 0 | AP18: =IF(O18=0,0,AO18/O18) -> 0 | AQ18: =IF(N18<Rules!$B$10,"Under 20 clicks: too early",IF(P18=0,"20+ clicks, 0 orders: negate / pause",IF(N18<Rules!$B$11,"Under 100 clicks: watch",IF(S18>=Rules!$B$12,"4%+: keep",IF(S18>=Rules!$B$13,"2% to 4%: hold at lower bid","Under 2%: pause"))))) -> Under 100 clicks: watch | AR18: =IF(O18=0,"",IF(Q18=0,"Spend, no sales",IF(U18>Rules!$B$33,"Above 3x break-even","Within 3x break-even"))) -> Above 3x break-even | AS18: =IF(OR(J18="",H18<>"ENABLED"),"",IF(J18>Rules!$B$9,"Above +300% cap","OK")) | AT18: 3 RETEST AFTER REBUILD | AU18: PAUSED | AV18: Keep paused; retest after the rebuild | AW18: 1 order on 35 clicks (Top of Search); rated Highly Relevant; organic rank about 55. Too little data to justify spend before the page is fixed. | AX18: Joseph approves; Shayan applies
A19: 269303623430005 | B19: SL-BB-SP-throw blanket for couch boho-Boho|Blanket|Core-VLSV-Exact-Rank-Fixed-SL-BOHO-BLANKET-BUTTERFLY-50x60-1-PC | C19: blanket boho · boho bed throw · boho blankets for bed +2 more keywords | D19: SP Exact keyword | E19: Boho couch / bed | F19: SL-BOHO-BLANKET-BUTTERFLY-50x60-1-PC | G19: Not in Phase 0 | H19: PAUSED | I19: 49.63 | L19: =IF(OR(K19="",J19=""),"",K19*(1+J19)) | M19: 2383 | N19: 38 | O19: 32.9 | P19: 1 | Q19: 34.99 | R19: =IF(M19=0,0,N19/M19) -> 0.015946286 | S19: =IF(N19=0,0,P19/N19) -> 0.026315789 | T19: =IF(N19=0,0,O19/N19) -> 0.86578947 | U19: =IF(Q19=0,"",O19/Q19) -> 0.94026865 | V19: =IF(O19=0,0,Q19/O19) -> 1.0635258 | W19: 1 | X19: 1.16 | Y19: 0 | Z19: 0 | AA19: =IF(W19=0,0,Y19/W19) -> 0 | AB19: =IF(Z19=0,"",X19/Z19) | AC19: 0 | AD19: 0 | AE19: 0 | AF19: 0 | AG19: =IF(AC19=0,0,AE19/AC19) -> 0 | AH19: 16 | AI19: 20.58 | AJ19: 5 | AK19: 5.5 | AL19: 5 | AM19: 4.41 | AN19: 12 | AO19: 2.41 | AP19: =IF(O19=0,0,AO19/O19) -> 0.07325228 | AQ19: =IF(N19<Rules!$B$10,"Under 20 clicks: too early",IF(P19=0,"20+ clicks, 0 orders: negate / pause",IF(N19<Rules!$B$11,"Under 100 clicks: watch",IF(S19>=Rules!$B$12,"4%+: keep",IF(S19>=Rules!$B$13,"2% to 4%: hold at lower bid","Under 2%: pause"))))) -> Under 100 clicks: watch | AR19: =IF(O19=0,"",IF(Q19=0,"Spend, no sales",IF(U19>Rules!$B$33,"Above 3x break-even","Within 3x break-even"))) -> Above 3x break-even | AS19: =IF(OR(J19="",H19<>"ENABLED"),"",IF(J19>Rules!$B$9,"Above +300% cap","OK")) | AT19: 4 RESTRUCTURE IN REBUILD | AU19: PAUSED | AV19: Keep paused; split in the rebuild | AW19: 5 keywords mixing couch and bed intent ('blanket boho', 'boho bed throw', 'boho blankets for bed'); 1 order on 26 on-Amazon clicks. | AX19: Joseph approves; Shayan applies
A20: 248203141513937 | B20: SL-BB-SP-king size boho blanket-Boho|Blanket|Size-VLSV-Exact-Rank-Fixed-SL-BOHO-BLANKET-BUTTERFLY-60x80-1-PC | C20: king size boho blanket | D20: SP Exact keyword | E20: Boho size (king / queen / 60x80) | F20: SL-BOHO-BLANKET-BUTTERFLY-60x80-1-PC | G20: Exclude list (king / queen) | H20: ENABLED | I20: 5.66 | J20: 3 | L20: =IF(OR(K20="",J20=""),"",K20*(1+J20)) | M20: 1075 | N20: 23 | O20: 29.74 | P20: 0 | Q20: 0 | R20: =IF(M20=0,0,N20/M20) -> 0.021395349 | S20: =IF(N20=0,0,P20/N20) -> 0 | T20: =IF(N20=0,0,O20/N20) -> 1.2930435 | U20: =IF(Q20=0,"",O20/Q20) | V20: =IF(O20=0,0,Q20/O20) -> 0 | W20: 14 | X20: 19 | Y20: 0 | Z20: 0 | AA20: =IF(W20=0,0,Y20/W20) -> 0 | AB20: =IF(Z20=0,"",X20/Z20) | AC20: 7 | AD20: 7.4 | AE20: 0 | AF20: 0 | AG20: =IF(AC20=0,0,AE20/AC20) -> 0 | AH20: 18 | AI20: 26.5 | AJ20: 4 | AK20: 2.59 | AL20: 1 | AM20: 0.65 | AN20: 0 | AO20: 0 | AP20: =IF(O20=0,0,AO20/O20) -> 0 | AQ20: =IF(N20<Rules!$B$10,"Under 20 clicks: too early",IF(P20=0,"20+ clicks, 0 orders: negate / pause",IF(N20<Rules!$B$11,"Under 100 clicks: watch",IF(S20>=Rules!$B$12,"4%+: keep",IF(S20>=Rules!$B$13,"2% to 4%: hold at lower bid","Under 2%: pause"))))) -> 20+ clicks, 0 orders: negate / pause | AR20: =IF(O20=0,"",IF(Q20=0,"Spend, no sales",IF(U20>Rules!$B$33,"Above 3x break-even","Within 3x break-even"))) -> Spend, no sales | AS20: =IF(OR(J20="",H20<>"ENABLED"),"",IF(J20>Rules!$B$9,"Above +300% cap","OK")) -> OK | AT20: 5 PAUSE (wasted spend) | AU20: PAUSED | AV20: Pause now | AW20: 0 orders on 23 clicks ($29.74). King-size intent: wrong size for this product; on the pack's exclude list. | AX20: Joseph approves; Shayan applies
A21: 88375236561649 | B21: SL-BB-SP-boho picnic blanket-Boho|Blanket|Core-MSV-Exact-Rank-Fixed-SL-BOHO-BLANKET-BUTTERFLY-50x60-1-PC | C21: boho picnic blanket | D21: SP Exact keyword | E21: Boho off-intent (picnic / beach / heated) | F21: SL-BOHO-BLANKET-BUTTERFLY-50x60-1-PC | G21: Phase 0: stop list | H21: ENABLED | I21: 12.14 | J21: 3.3 | L21: =IF(OR(K21="",J21=""),"",K21*(1+J21)) | M21: 1723 | N21: 18 | O21: 28.44 | P21: 0 | Q21: 0 | R21: =IF(M21=0,0,N21/M21) -> 0.010446895 | S21: =IF(N21=0,0,P21/N21) -> 0 | T21: =IF(N21=0,0,O21/N21) -> 1.58 | U21: =IF(Q21=0,"",O21/Q21) | V21: =IF(O21=0,0,Q21/O21) -> 0 | W21: 7 | X21: 10.12 | Y21: 0 | Z21: 0 | AA21: =IF(W21=0,0,Y21/W21) -> 0 | AB21: =IF(Z21=0,"",X21/Z21) | AC21: 5 | AD21: 6.12 | AE21: 0 | AF21: 0 | AG21: =IF(AC21=0,0,AE21/AC21) -> 0 | AH21: 9 | AI21: 19.87 | AJ21: 7 | AK21: 6.71 | AL21: 2 | AM21: 1.86 | AN21: 0 | AO21: 0 | AP21: =IF(O21=0,0,AO21/O21) -> 0 | AQ21: =IF(N21<Rules!$B$10,"Under 20 clicks: too early",IF(P21=0,"20+ clicks, 0 orders: negate / pause",IF(N21<Rules!$B$11,"Under 100 clicks: watch",IF(S21>=Rules!$B$12,"4%+: keep",IF(S21>=Rules!$B$13,"2% to 4%: hold at lower bid","Under 2%: pause"))))) -> Under 20 clicks: too early | AR21: =IF(O21=0,"",IF(Q21=0,"Spend, no sales",IF(U21>Rules!$B$33,"Above 3x break-even","Within 3x break-even"))) -> Spend, no sales | AS21: =IF(OR(J21="",H21<>"ENABLED"),"",IF(J21>Rules!$B$9,"Above +300% cap","OK")) -> Above +300% cap | AT21: 5 PAUSE (wasted spend) | AU21: PAUSED | AV21: Pause now | AW21: Stop list, still running. Wrong product (picnic). 0 orders on 18 clicks ($28); TOS +330%. | AX21: Joseph approves; Shayan applies
A22: 201568460000366 | B22: SL-BB-SP-boho blanket king size-Boho|Blanket|Size-VLSV-Exact-Rank-Fixed-SL-BOHO-BLANKET-BUTTERFLY-60x80-1-PC | C22: boho blanket king size | D22: SP Exact keyword | E22: Boho size (king / queen / 60x80) | F22: SL-BOHO-BLANKET-BUTTERFLY-60x80-1-PC | G22: Exclude list (king / queen) | H22: PAUSED | I22: 5.66 | L22: =IF(OR(K22="",J22=""),"",K22*(1+J22)) | M22: 1674 | N22: 24 | O22: 28.09 | P22: 0 | Q22: 0 | R22: =IF(M22=0,0,N22/M22) -> 0.014336918 | S22: =IF(N22=0,0,P22/N22) -> 0 | T22: =IF(N22=0,0,O22/N22) -> 1.1704167 | U22: =IF(Q22=0,"",O22/Q22) | V22: =IF(O22=0,0,Q22/O22) -> 0 | W22: 11 | X22: 9.93 | Y22: 0 | Z22: 0 | AA22: =IF(W22=0,0,Y22/W22) -> 0 | AB22: =IF(Z22=0,"",X22/Z22) | AC22: 0 | AD22: 0 | AE22: 0 | AF22: 0 | AG22: =IF(AC22=0,0,AE22/AC22) -> 0 | AH22: 9 | AI22: 17.65 | AJ22: 15 | AK22: 10.44 | AL22: 0 | AM22: 0 | AN22: 0 | AO22: 0 | AP22: =IF(O22=0,0,AO22/O22) -> 0 | AQ22: =IF(N22<Rules!$B$10,"Under 20 clicks: too early",IF(P22=0,"20+ clicks, 0 orders: negate / pause",IF(N22<Rules!$B$11,"Under 100 clicks: watch",IF(S22>=Rules!$B$12,"4%+: keep",IF(S22>=Rules!$B$13,"2% to 4%: hold at lower bid","Under 2%: pause"))))) -> 20+ clicks, 0 orders: negate / pause | AR22: =IF(O22=0,"",IF(Q22=0,"Spend, no sales",IF(U22>Rules!$B$33,"Above 3x break-even","Within 3x break-even"))) -> Spend, no sales | AS22: =IF(OR(J22="",H22<>"ENABLED"),"",IF(J22>Rules!$B$9,"Above +300% cap","OK")) | AT22: 5 PAUSE (wasted spend) | AU22: PAUSED | AV22: Keep paused | AW22: 0 orders on 24 clicks ($28). King intent. | AX22: Joseph approves; Shayan applies
A23: 199196980921698 | B23: SL-BB-SP-boho blanket throw-Boho|Blanket|Core-LSV-Exact-Rank-Fixed-SL-BOHO-BLANKET-BUTTERFLY-50x60-1-PC | C23: boho blanket throw | D23: SP Exact keyword | E23: Boho core | F23: SL-BOHO-BLANKET-BUTTERFLY-50x60-1-PC | G23: Phase 0: stop list | H23: PAUSED | I23: 7.64 | L23: =IF(OR(K23="",J23=""),"",K23*(1+J23)) | M23: 2560 | N23: 32 | O23: 27.55 | P23: 0 | Q23: 0 | R23: =IF(M23=0,0,N23/M23) -> 0.0125 | S23: =IF(N23=0,0,P23/N23) -> 0 | T23: =IF(N23=0,0,O23/N23) -> 0.8609375 | U23: =IF(Q23=0,"",O23/Q23) | V23: =IF(O23=0,0,Q23/O23) -> 0 | W23: 0 | X23: 0 | Y23: 0 | Z23: 0 | AA23: =IF(W23=0,0,Y23/W23) -> 0 | AB23: =IF(Z23=0,"",X23/Z23) | AC23: 0 | AD23: 0 | AE23: 0 | AF23: 0 | AG23: =IF(AC23=0,0,AE23/AC23) -> 0 | AH23: 8 | AI23: 11.27 | AJ23: 21 | AK23: 14.2 | AL23: 3 | AM23: 2.08 | AN23: 0 | AO23: 0 | AP23: =IF(O23=0,0,AO23/O23) -> 0 | AQ23: =IF(N23<Rules!$B$10,"Under 20 clicks: too early",IF(P23=0,"20+ clicks, 0 orders: negate / pause",IF(N23<Rules!$B$11,"Under 100 clicks: watch",IF(S23>=Rules!$B$12,"4%+: keep",IF(S23>=Rules!$B$13,"2% to 4%: hold at lower bid","Under 2%: pause"))))) -> 20+ clicks, 0 orders: negate / pause | AR23: =IF(O23=0,"",IF(Q23=0,"Spend, no sales",IF(U23>Rules!$B$33,"Above 3x break-even","Within 3x break-even"))) -> Spend, no sales | AS23: =IF(OR(J23="",H23<>"ENABLED"),"",IF(J23>Rules!$B$9,"Above +300% cap","OK")) | AT23: 5 PAUSE (wasted spend) | AU23: PAUSED | AV23: Keep paused | AW23: Stop list. 0 orders on 32 clicks in its campaign; as a search term 0 orders on 98 clicks ($82) across campaigns; SQP 1 cart add on 22 clicks. | AX23: Joseph approves; Shayan applies
A24: 158494562127971 | B24: SL-BB-SP-boho throw blanket for bed-Boho|Blanket|Core-LSV-Exact-Rank-Fixed-SL-BOHO-BLANKET-BUTTERFLY-50x60-1-PC | C24: boho throw blanket for bed | D24: SP Exact keyword | E24: Boho couch / bed | F24: SL-BOHO-BLANKET-BUTTERFLY-50x60-1-PC | G24: Phase 0: stop list | H24: PAUSED | I24: 9.34 | L24: =IF(OR(K24="",J24=""),"",K24*(1+J24)) | M24: 5076 | N24: 28 | O24: 27.35 | P24: 0 | Q24: 0 | R24: =IF(M24=0,0,N24/M24) -> 0.0055161545 | S24: =IF(N24=0,0,P24/N24) -> 0 | T24: =IF(N24=0,0,O24/N24) -> 0.97678571 | U24: =IF(Q24=0,"",O24/Q24) | V24: =IF(O24=0,0,Q24/O24) -> 0 | W24: 10 | X24: 9 | Y24: 0 | Z24: 0 | AA24: =IF(W24=0,0,Y24/W24) -> 0 | AB24: =IF(Z24=0,"",X24/Z24) | AC24: 0 | AD24: 0 | AE24: 0 | AF24: 0 | AG24: =IF(AC24=0,0,AE24/AC24) -> 0 | AH24: 13 | AI24: 13.13 | AJ24: 14 | AK24: 13.21 | AL24: 1 | AM24: 1.01 | AN24: 0 | AO24: 0 | AP24: =IF(O24=0,0,AO24/O24) -> 0 | AQ24: =IF(N24<Rules!$B$10,"Under 20 clicks: too early",IF(P24=0,"20+ clicks, 0 orders: negate / pause",IF(N24<Rules!$B$11,"Under 100 clicks: watch",IF(S24>=Rules!$B$12,"4%+: keep",IF(S24>=Rules!$B$13,"2% to 4%: hold at lower bid","Under 2%: pause"))))) -> 20+ clicks, 0 orders: negate / pause | AR24: =IF(O24=0,"",IF(Q24=0,"Spend, no sales",IF(U24>Rules!$B$33,"Above 3x break-even","Within 3x break-even"))) -> Spend, no sales | AS24: =IF(OR(J24="",H24<>"ENABLED"),"",IF(J24>Rules!$B$9,"Above +300% cap","OK")) | AT24: 5 PAUSE (wasted spend) | AU24: PAUSED | AV24: Keep paused | AW24: Stop list. 0 orders on 28 clicks. | AX24: Joseph approves; Shayan applies
A25: 264225421869119 | B25: SL-BB-SP-B0FRF3JGK9-Exact-Conq-Fixed-SL-BOHO-BLANKET-BOUQUET-60x80-1-PC | C25: B0FRF3JGK9 | D25: SP Product targeting | E25: Competitor PAT | F25: SL-BOHO-BLANKET-BOUQUET-60x80-1-PC | G25: Not in Phase 0 (Phase 1 lane L9) | H25: ENABLED | I25: 4.5 | J25: 0 | L25: =IF(OR(K25="",J25=""),"",K25*(1+J25)) | M25: 6341 | N25: 31 | O25: 25.24 | P25: 0 | Q25: 0 | R25: =IF(M25=0,0,N25/M25) -> 0.0048888188 | S25: =IF(N25=0,0,P25/N25) -> 0 | T25: =IF(N25=0,0,O25/N25) -> 0.81419355 | U25: =IF(Q25=0,"",O25/Q25) | V25: =IF(O25=0,0,Q25/O25) -> 0 | W25: 26 | X25: 21.14 | Y25: 0 | Z25: 0 | AA25: =IF(W25=0,0,Y25/W25) -> 0 | AB25: =IF(Z25=0,"",X25/Z25) | AC25: 19 | AD25: 15.58 | AE25: 0 | AF25: 0 | AG25: =IF(AC25=0,0,AE25/AC25) -> 0 | AH25: 4 | AI25: 3.2 | AJ25: 19 | AK25: 15.58 | AL25: 8 | AM25: 6.46 | AN25: 0 | AO25: 0 | AP25: =IF(O25=0,0,AO25/O25) -> 0 | AQ25: =IF(N25<Rules!$B$10,"Under 20 clicks: too early",IF(P25=0,"20+ clicks, 0 orders: negate / pause",IF(N25<Rules!$B$11,"Under 100 clicks: watch",IF(S25>=Rules!$B$12,"4%+: keep",IF(S25>=Rules!$B$13,"2% to 4%: hold at lower bid","Under 2%: pause"))))) -> 20+ clicks, 0 orders: negate / pause | AR25: =IF(O25=0,"",IF(Q25=0,"Spend, no sales",IF(U25>Rules!$B$33,"Above 3x break-even","Within 3x break-even"))) -> Spend, no sales | AS25: =IF(OR(J25="",H25<>"ENABLED"),"",IF(J25>Rules!$B$9,"Above +300% cap","OK")) -> OK | AT25: 5 PAUSE (wasted spend) | AU25: PAUSED | AV25: Pause now | AW25: 0 orders on 31 clicks ($25.24). Advertises Bouquet 60x80 regardless of the competitor's size or price. | AX25: Joseph approves; Shayan applies
A26: 179711585918274 | B26: SL-BB-SP-boho blanket throw colorful-Boho|Blanket|Color-VLSV-Exact-Rank-Fixed-SL-BOHO-BLANKET-BUTTERFLY-50x60-1-PC | C26: beige boho throw blanket · blue boho blanket · blue boho throw blanket +1 more keywords | D26: SP Exact keyword | E26: Boho pattern / colour | F26: SL-BOHO-BLANKET-BUTTERFLY-50x60-1-PC | G26: Not in Phase 0 | H26: PAUSED | I26: 40.83 | L26: =IF(OR(K26="",J26=""),"",K26*(1+J26)) | M26: 1818 | N26: 79 | O26: 24.07 | P26: 0 | Q26: 0 | R26: =IF(M26=0,0,N26/M26) -> 0.043454345 | S26: =IF(N26=0,0,P26/N26) -> 0 | T26: =IF(N26=0,0,O26/N26) -> 0.30468354 | U26: =IF(Q26=0,"",O26/Q26) | V26: =IF(O26=0,0,Q26/O26) -> 0 | W26: 0 | X26: 0 | Y26: 0 | Z26: 0 | AA26: =IF(W26=0,0,Y26/W26) -> 0 | AB26: =IF(Z26=0,"",X26/Z26) | AC26: 0 | AD26: 0 | AE26: 0 | AF26: 0 | AG26: =IF(AC26=0,0,AE26/AC26) -> 0 | AH26: 4 | AI26: 4.8 | AJ26: 2 | AK26: 1.93 | AL26: 1 | AM26: 0.78 | AN26: 72 | AO26: 16.56 | AP26: =IF(O26=0,0,AO26/O26) -> 0.68799335 | AQ26: =IF(N26<Rules!$B$10,"Under 20 clicks: too early",IF(P26=0,"20+ clicks, 0 orders: negate / pause",IF(N26<Rules!$B$11,"Under 100 clicks: watch",IF(S26>=Rules!$B$12,"4%+: keep",IF(S26>=Rules!$B$13,"2% to 4%: hold at lower bid","Under 2%: pause"))))) -> 20+ clicks, 0 orders: negate / pause | AR26: =IF(O26=0,"",IF(Q26=0,"Spend, no sales",IF(U26>Rules!$B$33,"Above 3x break-even","Within 3x break-even"))) -> Spend, no sales | AS26: =IF(OR(J26="",H26<>"ENABLED"),"",IF(J26>Rules!$B$9,"Above +300% cap","OK")) | AT26: 5 PAUSE (wasted spend) | AU26: PAUSED | AV26: Keep paused | AW26: Colour terms (beige, blue) that do not match the patterns. 0 orders on 79 clicks. | AX26: Joseph approves; Shayan applies
A27: 20309127916243 | B27: SL-BB-SP-boho blanket queen-Boho|Blanket|Size-LSV-Exact-Rank-Fixed-SL-BOHO-BLANKET-BUTTERFLY-50x60-1-PC | C27: boho blanket queen | D27: SP Exact keyword | E27: Boho size (king / queen / 60x80) | F27: SL-BOHO-BLANKET-BUTTERFLY-50x60-1-PC | G27: Phase 0: stop list | H27: PAUSED | I27: 8.7 | L27: =IF(OR(K27="",J27=""),"",K27*(1+J27)) | M27: 2235 | N27: 18 | O27: 20.86 | P27: 0 | Q27: 0 | R27: =IF(M27=0,0,N27/M27) -> 0.0080536913 | S27: =IF(N27=0,0,P27/N27) -> 0 | T27: =IF(N27=0,0,O27/N27) -> 1.1588889 | U27: =IF(Q27=0,"",O27/Q27) | V27: =IF(O27=0,0,Q27/O27) -> 0 | W27: 8 | X27: 8.91 | Y27: 0 | Z27: 0 | AA27: =IF(W27=0,0,Y27/W27) -> 0 | AB27: =IF(Z27=0,"",X27/Z27) | AC27: 0 | AD27: 0 | AE27: 0 | AF27: 0 | AG27: =IF(AC27=0,0,AE27/AC27) -> 0 | AH27: 10 | AI27: 14.44 | AJ27: 7 | AK27: 5.56 | AL27: 1 | AM27: 0.86 | AN27: 0 | AO27: 0 | AP27: =IF(O27=0,0,AO27/O27) -> 0 | AQ27: =IF(N27<Rules!$B$10,"Under 20 clicks: too early",IF(P27=0,"20+ clicks, 0 orders: negate / pause",IF(N27<Rules!$B$11,"Under 100 clicks: watch",IF(S27>=Rules!$B$12,"4%+: keep",IF(S27>=Rules!$B$13,"2% to 4%: hold at lower bid","Under 2%: pause"))))) -> Under 20 clicks: too early | AR27: =IF(O27=0,"",IF(Q27=0,"Spend, no sales",IF(U27>Rules!$B$33,"Above 3x break-even","Within 3x break-even"))) -> Spend, no sales | AS27: =IF(OR(J27="",H27<>"ENABLED"),"",IF(J27>Rules!$B$9,"Above +300% cap","OK")) | AT27: 5 PAUSE (wasted spend) | AU27: PAUSED | AV27: Keep paused | AW27: Stop list. 0 orders on 18 clicks. | AX27: Joseph approves; Shayan applies
A28: 31470852710316 | B28: SL-BB-SP-boho couch blanket-Boho|Blanket|Core-VLSV-Exact-Rank-Fixed-SL-BOHO-BLANKET-BUTTERFLY-50x60-1-PC | C28: beach blanket boho · boho couch blanket | D28: SP Exact keyword | E28: Boho couch / bed | F28: SL-BOHO-BLANKET-BUTTERFLY-50x60-1-PC | G28: Not in Phase 0 (holds stop-list term) | H28: ENABLED | I28: 19.95 | J28: 3.6 | L28: =IF(OR(K28="",J28=""),"",K28*(1+J28)) | M28: 503 | N28: 11 | O28: 20.64 | P28: 0 | Q28: 0 | R28: =IF(M28=0,0,N28/M28) -> 0.021868787 | S28: =IF(N28=0,0,P28/N28) -> 0 | T28: =IF(N28=0,0,O28/N28) -> 1.8763636 | U28: =IF(Q28=0,"",O28/Q28) | V28: =IF(O28=0,0,Q28/O28) -> 0 | W28: 4 | X28: 11.4 | Y28: 0 | Z28: 0 | AA28: =IF(W28=0,0,Y28/W28) -> 0 | AB28: =IF(Z28=0,"",X28/Z28) | AC28: 2 | AD28: 7.11 | AE28: 0 | AF28: 0 | AG28: =IF(AC28=0,0,AE28/AC28) -> 0 | AH28: 9 | AI28: 18.98 | AJ28: 1 | AK28: 1.02 | AL28: 1 | AM28: 0.64 | AN28: 0 | AO28: 0 | AP28: =IF(O28=0,0,AO28/O28) -> 0 | AQ28: =IF(N28<Rules!$B$10,"Under 20 clicks: too early",IF(P28=0,"20+ clicks, 0 orders: negate / pause",IF(N28<Rules!$B$11,"Under 100 clicks: watch",IF(S28>=Rules!$B$12,"4%+: keep",IF(S28>=Rules!$B$13,"2% to 4%: hold at lower bid","Under 2%: pause"))))) -> Under 20 clicks: too early | AR28: =IF(O28=0,"",IF(Q28=0,"Spend, no sales",IF(U28>Rules!$B$33,"Above 3x break-even","Within 3x break-even"))) -> Spend, no sales | AS28: =IF(OR(J28="",H28<>"ENABLED"),"",IF(J28>Rules!$B$9,"Above +300% cap","OK")) -> Above +300% cap | AT28: 4 RESTRUCTURE IN REBUILD | AU28: PAUSED | AV28: Pause now; restructure in the rebuild | AW28: Holds 'beach blanket boho' (stop list, wrong product) next to 'boho couch blanket'. 0 orders on 11 clicks; $3.55 a click in the last 15 days; TOS +360%. | AX28: Joseph approves; Shayan applies
A29: 27058612184707 | B29: SL-BB-SP-boho heated blanket-Boho|Blanket|Core-VLSV-Exact-Rank-Fixed-SL-BOHO-BLANKET-BUTTERFLY-50x60-1-PC | C29: boho heated blanket | D29: SP Exact keyword | E29: Boho off-intent (picnic / beach / heated) | F29: SL-BOHO-BLANKET-BUTTERFLY-50x60-1-PC | G29: Phase 0: stop list | H29: PAUSED | I29: 11.21 | L29: =IF(OR(K29="",J29=""),"",K29*(1+J29)) | M29: 657 | N29: 43 | O29: 19.66 | P29: 0 | Q29: 0 | R29: =IF(M29=0,0,N29/M29) -> 0.065449011 | S29: =IF(N29=0,0,P29/N29) -> 0 | T29: =IF(N29=0,0,O29/N29) -> 0.4572093 | U29: =IF(Q29=0,"",O29/Q29) | V29: =IF(O29=0,0,Q29/O29) -> 0 | W29: 0 | X29: 0 | Y29: 0 | Z29: 0 | AA29: =IF(W29=0,0,Y29/W29) -> 0 | AB29: =IF(Z29=0,"",X29/Z29) | AC29: 0 | AD29: 0 | AE29: 0 | AF29: 0 | AG29: =IF(AC29=0,0,AE29/AC29) -> 0 | AH29: 3 | AI29: 12.08 | AJ29: 0 | AK29: 0 | AL29: 0 | AM29: 0 | AN29: 40 | AO29: 7.58 | AP29: =IF(O29=0,0,AO29/O29) -> 0.38555443 | AQ29: =IF(N29<Rules!$B$10,"Under 20 clicks: too early",IF(P29=0,"20+ clicks, 0 orders: negate / pause",IF(N29<Rules!$B$11,"Under 100 clicks: watch",IF(S29>=Rules!$B$12,"4%+: keep",IF(S29>=Rules!$B$13,"2% to 4%: hold at lower bid","Under 2%: pause"))))) -> 20+ clicks, 0 orders: negate / pause | AR29: =IF(O29=0,"",IF(Q29=0,"Spend, no sales",IF(U29>Rules!$B$33,"Above 3x break-even","Within 3x break-even"))) -> Spend, no sales | AS29: =IF(OR(J29="",H29<>"ENABLED"),"",IF(J29>Rules!$B$9,"Above +300% cap","OK")) | AT29: 5 PAUSE (wasted spend) | AU29: PAUSED | AV29: Keep paused | AW29: Wrong product (heated). 0 orders on 43 clicks. | AX29: Joseph approves; Shayan applies
A30: 136043663989806 | B30: SL-BB-SP-B0F542WLD5-Exact-Conq-Fixed-SL-BOHO-BLANKET-BOUQUET-60x80-1-PC | C30: B0F542WLD5 | D30: SP Product targeting | E30: Competitor PAT | F30: SL-BOHO-BLANKET-BOUQUET-60x80-1-PC | G30: Not in Phase 0 (Phase 1 lane L9) | H30: PAUSED | I30: 4.5 | L30: =IF(OR(K30="",J30=""),"",K30*(1+J30)) | M30: 5262 | N30: 33 | O30: 19.32 | P30: 0 | Q30: 0 | R30: =IF(M30=0,0,N30/M30) -> 0.0062713797 | S30: =IF(N30=0,0,P30/N30) -> 0 | T30: =IF(N30=0,0,O30/N30) -> 0.58545455 | U30: =IF(Q30=0,"",O30/Q30) | V30: =IF(O30=0,0,Q30/O30) -> 0 | W30: 29 | X30: 16.96 | Y30: 0 | Z30: 0 | AA30: =IF(W30=0,0,Y30/W30) -> 0 | AB30: =IF(Z30=0,"",X30/Z30) | AC30: 0 | AD30: 0 | AE30: 0 | AF30: 0 | AG30: =IF(AC30=0,0,AE30/AC30) -> 0 | AH30: 0 | AI30: 0 | AJ30: 33 | AK30: 19.32 | AL30: 0 | AM30: 0 | AN30: 0 | AO30: 0 | AP30: =IF(O30=0,0,AO30/O30) -> 0 | AQ30: =IF(N30<Rules!$B$10,"Under 20 clicks: too early",IF(P30=0,"20+ clicks, 0 orders: negate / pause",IF(N30<Rules!$B$11,"Under 100 clicks: watch",IF(S30>=Rules!$B$12,"4%+: keep",IF(S30>=Rules!$B$13,"2% to 4%: hold at lower bid","Under 2%: pause"))))) -> 20+ clicks, 0 orders: negate / pause | AR30: =IF(O30=0,"",IF(Q30=0,"Spend, no sales",IF(U30>Rules!$B$33,"Above 3x break-even","Within 3x break-even"))) -> Spend, no sales | AS30: =IF(OR(J30="",H30<>"ENABLED"),"",IF(J30>Rules!$B$9,"Above +300% cap","OK")) | AT30: 5 PAUSE (wasted spend) | AU30: PAUSED | AV30: Keep paused | AW30: 0 orders on 33 clicks ($19.32). Advertises Bouquet 60x80 regardless of the competitor's size or price. | AX30: Joseph approves; Shayan applies
A31: 227544042687099 | B31: SL-BB-SP-B0F9WSBG6B-Exact-Conq-Fixed-SL-BOHO-BLANKET-BOUQUET-60x80-1-PC | C31: B0F9WSBG6B | D31: SP Product targeting | E31: Competitor PAT | F31: SL-BOHO-BLANKET-BOUQUET-60x80-1-PC | G31: Not in Phase 0 (Phase 1 lane L9) | H31: ENABLED | I31: 4.5 | J31: 0 | L31: =IF(OR(K31="",J31=""),"",K31*(1+J31)) | M31: 4406 | N31: 24 | O31: 15.31 | P31: 0 | Q31: 0 | R31: =IF(M31=0,0,N31/M31) -> 0.0054471176 | S31: =IF(N31=0,0,P31/N31) -> 0 | T31: =IF(N31=0,0,O31/N31) -> 0.63791667 | U31: =IF(Q31=0,"",O31/Q31) | V31: =IF(O31=0,0,Q31/O31) -> 0 | W31: 23 | X31: 14.66 | Y31: 0 | Z31: 0 | AA31: =IF(W31=0,0,Y31/W31) -> 0 | AB31: =IF(Z31=0,"",X31/Z31) | AC31: 12 | AD31: 7.51 | AE31: 0 | AF31: 0 | AG31: =IF(AC31=0,0,AE31/AC31) -> 0 | AH31: 0 | AI31: 0 | AJ31: 24 | AK31: 15.31 | AL31: 0 | AM31: 0 | AN31: 0 | AO31: 0 | AP31: =IF(O31=0,0,AO31/O31) -> 0 | AQ31: =IF(N31<Rules!$B$10,"Under 20 clicks: too early",IF(P31=0,"20+ clicks, 0 orders: negate / pause",IF(N31<Rules!$B$11,"Under 100 clicks: watch",IF(S31>=Rules!$B$12,"4%+: keep",IF(S31>=Rules!$B$13,"2% to 4%: hold at lower bid","Under 2%: pause"))))) -> 20+ clicks, 0 orders: negate / pause | AR31: =IF(O31=0,"",IF(Q31=0,"Spend, no sales",IF(U31>Rules!$B$33,"Above 3x break-even","Within 3x break-even"))) -> Spend, no sales | AS31: =IF(OR(J31="",H31<>"ENABLED"),"",IF(J31>Rules!$B$9,"Above +300% cap","OK")) -> OK | AT31: 5 PAUSE (wasted spend) | AU31: PAUSED | AV31: Pause now | AW31: 0 orders on 24 clicks ($15.31). Advertises Bouquet 60x80 regardless of the competitor's size or price. | AX31: Joseph approves; Shayan applies
A32: 198006936823591 | B32: SL-BB-SP-B0DHKTZTMN-Exact-Conq-Fixed-SL-BOHO-BLANKET-BOUQUET-60x80-1-PC | C32: B0DHKTZTMN | D32: SP Product targeting | E32: Competitor PAT | F32: SL-BOHO-BLANKET-BOUQUET-60x80-1-PC | G32: Not in Phase 0 (Phase 1 lane L9) | H32: PAUSED | I32: 4.5 | L32: =IF(OR(K32="",J32=""),"",K32*(1+J32)) | M32: 3649 | N32: 22 | O32: 12.98 | P32: 0 | Q32: 0 | R32: =IF(M32=0,0,N32/M32) -> 0.0060290491 | S32: =IF(N32=0,0,P32/N32) -> 0 | T32: =IF(N32=0,0,O32/N32) -> 0.59 | U32: =IF(Q32=0,"",O32/Q32) | V32: =IF(O32=0,0,Q32/O32) -> 0 | W32: 19 | X32: 11.21 | Y32: 0 | Z32: 0 | AA32: =IF(W32=0,0,Y32/W32) -> 0 | AB32: =IF(Z32=0,"",X32/Z32) | AC32: 0 | AD32: 0 | AE32: 0 | AF32: 0 | AG32: =IF(AC32=0,0,AE32/AC32) -> 0 | AH32: 1 | AI32: 0.59 | AJ32: 21 | AK32: 12.39 | AL32: 0 | AM32: 0 | AN32: 0 | AO32: 0 | AP32: =IF(O32=0,0,AO32/O32) -> 0 | AQ32: =IF(N32<Rules!$B$10,"Under 20 clicks: too early",IF(P32=0,"20+ clicks, 0 orders: negate / pause",IF(N32<Rules!$B$11,"Under 100 clicks: watch",IF(S32>=Rules!$B$12,"4%+: keep",IF(S32>=Rules!$B$13,"2% to 4%: hold at lower bid","Under 2%: pause"))))) -> 20+ clicks, 0 orders: negate / pause | AR32: =IF(O32=0,"",IF(Q32=0,"Spend, no sales",IF(U32>Rules!$B$33,"Above 3x break-even","Within 3x break-even"))) -> Spend, no sales | AS32: =IF(OR(J32="",H32<>"ENABLED"),"",IF(J32>Rules!$B$9,"Above +300% cap","OK")) | AT32: 5 PAUSE (wasted spend) | AU32: PAUSED | AV32: Keep paused | AW32: 0 orders on 22 clicks ($12.98). Advertises Bouquet 60x80 regardless of the competitor's size or price. Bailix is the supplier's own brand. | AX32: Joseph approves; Shayan applies
A33: 4619427091358 | B33: SL-BB-SP-boho cotton blankets queen size-Boho|Blanket|Size-VLSV-Exact-Rank-Fixed-SL-BOHO-BLANKET-BUTTERFLY-50x60-1-PC | C33: boho cotton blankets queen size | D33: SP Exact keyword | E33: Boho size (king / queen / 60x80) | F33: SL-BOHO-BLANKET-BUTTERFLY-50x60-1-PC | G33: Exclude list (king / queen) | H33: ENABLED | I33: 8.6 | J33: 3.8 | L33: =IF(OR(K33="",J33=""),"",K33*(1+J33)) | M33: 818 | N33: 9 | O33: 12.65 | P33: 0 | Q33: 0 | R33: =IF(M33=0,0,N33/M33) -> 0.011002445 | S33: =IF(N33=0,0,P33/N33) -> 0 | T33: =IF(N33=0,0,O33/N33) -> 1.4055556 | U33: =IF(Q33=0,"",O33/Q33) | V33: =IF(O33=0,0,Q33/O33) -> 0 | W33: 7 | X33: 9.25 | Y33: 0 | Z33: 0 | AA33: =IF(W33=0,0,Y33/W33) -> 0 | AB33: =IF(Z33=0,"",X33/Z33) | AC33: 2 | AD33: 1.98 | AE33: 0 | AF33: 0 | AG33: =IF(AC33=0,0,AE33/AC33) -> 0 | AH33: 6 | AI33: 9.68 | AJ33: 3 | AK33: 2.97 | AL33: 0 | AM33: 0 | AN33: 0 | AO33: 0 | AP33: =IF(O33=0,0,AO33/O33) -> 0 | AQ33: =IF(N33<Rules!$B$10,"Under 20 clicks: too early",IF(P33=0,"20+ clicks, 0 orders: negate / pause",IF(N33<Rules!$B$11,"Under 100 clicks: watch",IF(S33>=Rules!$B$12,"4%+: keep",IF(S33>=Rules!$B$13,"2% to 4%: hold at lower bid","Under 2%: pause"))))) -> Under 20 clicks: too early | AR33: =IF(O33=0,"",IF(Q33=0,"Spend, no sales",IF(U33>Rules!$B$33,"Above 3x break-even","Within 3x break-even"))) -> Spend, no sales | AS33: =IF(OR(J33="",H33<>"ENABLED"),"",IF(J33>Rules!$B$9,"Above +300% cap","OK")) -> Above +300% cap | AT33: 5 PAUSE (wasted spend) | AU33: PAUSED | AV33: Pause now | AW33: 0 orders on 9 clicks. Queen bed-size intent; TOS +380%. | AX33: Joseph approves; Shayan applies
A34: 145716739151597 | B34: SL-BB-SP-boho king blanket-Boho|Blanket|Size-VLSV-Exact-Rank-Fixed-SL-BOHO-BLANKET-BUTTERFLY-60x80-1-PC | C34: boho king blanket | D34: SP Exact keyword | E34: Boho size (king / queen / 60x80) | F34: SL-BOHO-BLANKET-BUTTERFLY-60x80-1-PC | G34: Exclude list (king / queen) | H34: ENABLED | I34: 5.66 | J34: 3 | L34: =IF(OR(K34="",J34=""),"",K34*(1+J34)) | M34: 1282 | N34: 12 | O34: 12.58 | P34: 0 | Q34: 0 | R34: =IF(M34=0,0,N34/M34) -> 0.0093603744 | S34: =IF(N34=0,0,P34/N34) -> 0 | T34: =IF(N34=0,0,O34/N34) -> 1.0483333 | U34: =IF(Q34=0,"",O34/Q34) | V34: =IF(O34=0,0,Q34/O34) -> 0 | W34: 11 | X34: 11.04 | Y34: 0 | Z34: 0 | AA34: =IF(W34=0,0,Y34/W34) -> 0 | AB34: =IF(Z34=0,"",X34/Z34) | AC34: 5 | AD34: 3.4 | AE34: 0 | AF34: 0 | AG34: =IF(AC34=0,0,AE34/AC34) -> 0 | AH34: 5 | AI34: 7.82 | AJ34: 7 | AK34: 4.76 | AL34: 0 | AM34: 0 | AN34: 0 | AO34: 0 | AP34: =IF(O34=0,0,AO34/O34) -> 0 | AQ34: =IF(N34<Rules!$B$10,"Under 20 clicks: too early",IF(P34=0,"20+ clicks, 0 orders: negate / pause",IF(N34<Rules!$B$11,"Under 100 clicks: watch",IF(S34>=Rules!$B$12,"4%+: keep",IF(S34>=Rules!$B$13,"2% to 4%: hold at lower bid","Under 2%: pause"))))) -> Under 20 clicks: too early | AR34: =IF(O34=0,"",IF(Q34=0,"Spend, no sales",IF(U34>Rules!$B$33,"Above 3x break-even","Within 3x break-even"))) -> Spend, no sales | AS34: =IF(OR(J34="",H34<>"ENABLED"),"",IF(J34>Rules!$B$9,"Above +300% cap","OK")) -> OK | AT34: 5 PAUSE (wasted spend) | AU34: PAUSED | AV34: Pause now | AW34: 0 orders on 12 clicks. King intent. | AX34: Joseph approves; Shayan applies
A35: 122105077616953 | B35: SL-BB-SP-rustic floral boho blanket-Boho|Blanket|Pattern-VLSV-Exact-Rank-Fixed-SL-BOHO-BLANKET-BOUQUET-50x60-1-PC | C35: boho floral cotton blankets · rustic floral boho blanket | D35: SP Exact keyword | E35: Boho pattern / colour | F35: SL-BOHO-BLANKET-BOUQUET-50x60-1-PC | G35: Not in Phase 0 | H35: ENABLED | I35: 13.97 | J35: 3 | L35: =IF(OR(K35="",J35=""),"",K35*(1+J35)) | M35: 321 | N35: 7 | O35: 10.7 | P35: 1 | Q35: 34.99 | R35: =IF(M35=0,0,N35/M35) -> 0.021806854 | S35: =IF(N35=0,0,P35/N35) -> 0.14285714 | T35: =IF(N35=0,0,O35/N35) -> 1.5285714 | U35: =IF(Q35=0,"",O35/Q35) -> 0.30580166 | V35: =IF(O35=0,0,Q35/O35) -> 3.2700935 | W35: 4 | X35: 6.92 | Y35: 0 | Z35: 0 | AA35: =IF(W35=0,0,Y35/W35) -> 0 | AB35: =IF(Z35=0,"",X35/Z35) | AC35: 2 | AD35: 2.57 | AE35: 0 | AF35: 0 | AG35: =IF(AC35=0,0,AE35/AC35) -> 0 | AH35: 5 | AI35: 9.26 | AJ35: 1 | AK35: 0.75 | AL35: 1 | AM35: 0.69 | AN35: 0 | AO35: 0 | AP35: =IF(O35=0,0,AO35/O35) -> 0 | AQ35: =IF(N35<Rules!$B$10,"Under 20 clicks: too early",IF(P35=0,"20+ clicks, 0 orders: negate / pause",IF(N35<Rules!$B$11,"Under 100 clicks: watch",IF(S35>=Rules!$B$12,"4%+: keep",IF(S35>=Rules!$B$13,"2% to 4%: hold at lower bid","Under 2%: pause"))))) -> Under 20 clicks: too early | AR35: =IF(O35=0,"",IF(Q35=0,"Spend, no sales",IF(U35>Rules!$B$33,"Above 3x break-even","Within 3x break-even"))) -> Within 3x break-even | AS35: =IF(OR(J35="",H35<>"ENABLED"),"",IF(J35>Rules!$B$9,"Above +300% cap","OK")) -> OK | AT35: 3 RETEST AFTER REBUILD | AU35: PAUSED | AV35: Pause now; retest after the rebuild | AW35: 1 order on 7 clicks since launch; 0 orders on 4 clicks at $1.73 a click in the last 30 days. Too few clicks to judge, and it advertises Bouquet 50x60, the weakest pattern. | AX35: Joseph approves; Shayan applies
A36: 40188236585691 | B36: SL-BB-SP-B0D4HQ4B6Y-Exact-Conq-Fixed-SL-BOHO-BLANKET-BOUQUET-60x80-1-PC | C36: B0D4HQ4B6Y | D36: SP Product targeting | E36: Competitor PAT | F36: SL-BOHO-BLANKET-BOUQUET-60x80-1-PC | G36: Not in Phase 0 (Phase 1 lane L9) | H36: PAUSED | I36: 4.5 | L36: =IF(OR(K36="",J36=""),"",K36*(1+J36)) | M36: 1475 | N36: 16 | O36: 9.3 | P36: 0 | Q36: 0 | R36: =IF(M36=0,0,N36/M36) -> 0.010847458 | S36: =IF(N36=0,0,P36/N36) -> 0 | T36: =IF(N36=0,0,O36/N36) -> 0.58125 | U36: =IF(Q36=0,"",O36/Q36) | V36: =IF(O36=0,0,Q36/O36) -> 0 | W36: 10 | X36: 5.9 | Y36: 0 | Z36: 0 | AA36: =IF(W36=0,0,Y36/W36) -> 0 | AB36: =IF(Z36=0,"",X36/Z36) | AC36: 0 | AD36: 0 | AE36: 0 | AF36: 0 | AG36: =IF(AC36=0,0,AE36/AC36) -> 0 | AH36: 1 | AI36: 0.45 | AJ36: 12 | AK36: 7.08 | AL36: 3 | AM36: 1.77 | AN36: 0 | AO36: 0 | AP36: =IF(O36=0,0,AO36/O36) -> 0 | AQ36: =IF(N36<Rules!$B$10,"Under 20 clicks: too early",IF(P36=0,"20+ clicks, 0 orders: negate / pause",IF(N36<Rules!$B$11,"Under 100 clicks: watch",IF(S36>=Rules!$B$12,"4%+: keep",IF(S36>=Rules!$B$13,"2% to 4%: hold at lower bid","Under 2%: pause"))))) -> Under 20 clicks: too early | AR36: =IF(O36=0,"",IF(Q36=0,"Spend, no sales",IF(U36>Rules!$B$33,"Above 3x break-even","Within 3x break-even"))) -> Spend, no sales | AS36: =IF(OR(J36="",H36<>"ENABLED"),"",IF(J36>Rules!$B$9,"Above +300% cap","OK")) | AT36: 5 PAUSE (wasted spend) | AU36: PAUSED | AV36: Keep paused | AW36: 0 orders on 16 clicks ($9.30). Advertises Bouquet 60x80 regardless of the competitor's size or price. | AX36: Joseph approves; Shayan applies
A37: 10400641750207 | B37: SL-BB-SP-B0DRFZ787F-Exact-Conq-Fixed-SL-BOHO-BLANKET-BOUQUET-60x80-1-PC | C37: B0DRFZ787F | D37: SP Product targeting | E37: Competitor PAT | F37: SL-BOHO-BLANKET-BOUQUET-60x80-1-PC | G37: Not in Phase 0 (Phase 1 lane L9) | H37: ENABLED | I37: 4.5 | J37: 0 | L37: =IF(OR(K37="",J37=""),"",K37*(1+J37)) | M37: 1773 | N37: 13 | O37: 8.41 | P37: 0 | Q37: 0 | R37: =IF(M37=0,0,N37/M37) -> 0.0073322053 | S37: =IF(N37=0,0,P37/N37) -> 0 | T37: =IF(N37=0,0,O37/N37) -> 0.64692308 | U37: =IF(Q37=0,"",O37/Q37) | V37: =IF(O37=0,0,Q37/O37) -> 0 | W37: 11 | X37: 7.11 | Y37: 0 | Z37: 0 | AA37: =IF(W37=0,0,Y37/W37) -> 0 | AB37: =IF(Z37=0,"",X37/Z37) | AC37: 10 | AD37: 6.46 | AE37: 0 | AF37: 0 | AG37: =IF(AC37=0,0,AE37/AC37) -> 0 | AH37: 0 | AI37: 0 | AJ37: 13 | AK37: 8.41 | AL37: 0 | AM37: 0 | AN37: 0 | AO37: 0 | AP37: =IF(O37=0,0,AO37/O37) -> 0 | AQ37: =IF(N37<Rules!$B$10,"Under 20 clicks: too early",IF(P37=0,"20+ clicks, 0 orders: negate / pause",IF(N37<Rules!$B$11,"Under 100 clicks: watch",IF(S37>=Rules!$B$12,"4%+: keep",IF(S37>=Rules!$B$13,"2% to 4%: hold at lower bid","Under 2%: pause"))))) -> Under 20 clicks: too early | AR37: =IF(O37=0,"",IF(Q37=0,"Spend, no sales",IF(U37>Rules!$B$33,"Above 3x break-even","Within 3x break-even"))) -> Spend, no sales | AS37: =IF(OR(J37="",H37<>"ENABLED"),"",IF(J37>Rules!$B$9,"Above +300% cap","OK")) -> OK | AT37: 5 PAUSE (wasted spend) | AU37: PAUSED | AV37: Pause now | AW37: 0 orders on 13 clicks ($8.41). Advertises Bouquet 60x80 regardless of the competitor's size or price. | AX37: Joseph approves; Shayan applies
A38: 216012309710462 | B38: SL-BB-SP-throw blankets for bed boho-Boho|Blanket|Core-VLSV-Exact-Rank-Fixed-SL-BOHO-BLANKET-BUTTERFLY-50x60-1-PC | C38: throw blankets for bed boho | D38: SP Exact keyword | E38: Boho couch / bed | F38: SL-BOHO-BLANKET-BUTTERFLY-50x60-1-PC | G38: Not in Phase 0 | H38: ENABLED | I38: 8.7 | J38: 3.8 | L38: =IF(OR(K38="",J38=""),"",K38*(1+J38)) | M38: 335 | N38: 6 | O38: 8.13 | P38: 0 | Q38: 0 | R38: =IF(M38=0,0,N38/M38) -> 0.017910448 | S38: =IF(N38=0,0,P38/N38) -> 0 | T38: =IF(N38=0,0,O38/N38) -> 1.355 | U38: =IF(Q38=0,"",O38/Q38) | V38: =IF(O38=0,0,Q38/O38) -> 0 | W38: 3 | X38: 3.55 | Y38: 0 | Z38: 0 | AA38: =IF(W38=0,0,Y38/W38) -> 0 | AB38: =IF(Z38=0,"",X38/Z38) | AC38: 3 | AD38: 3.55 | AE38: 0 | AF38: 0 | AG38: =IF(AC38=0,0,AE38/AC38) -> 0 | AH38: 4 | AI38: 6.41 | AJ38: 2 | AK38: 1.72 | AL38: 0 | AM38: 0 | AN38: 0 | AO38: 0 | AP38: =IF(O38=0,0,AO38/O38) -> 0 | AQ38: =IF(N38<Rules!$B$10,"Under 20 clicks: too early",IF(P38=0,"20+ clicks, 0 orders: negate / pause",IF(N38<Rules!$B$11,"Under 100 clicks: watch",IF(S38>=Rules!$B$12,"4%+: keep",IF(S38>=Rules!$B$13,"2% to 4%: hold at lower bid","Under 2%: pause"))))) -> Under 20 clicks: too early | AR38: =IF(O38=0,"",IF(Q38=0,"Spend, no sales",IF(U38>Rules!$B$33,"Above 3x break-even","Within 3x break-even"))) -> Spend, no sales | AS38: =IF(OR(J38="",H38<>"ENABLED"),"",IF(J38>Rules!$B$9,"Above +300% cap","OK")) -> Above +300% cap | AT38: 5 PAUSE (wasted spend) | AU38: PAUSED | AV38: Pause now | AW38: 0 orders on 6 clicks; low volume (386 a month); TOS +380%. | AX38: Joseph approves; Shayan applies
A39: 85219022747841 | B39: SL-BB-SP-B0DS28Q1LT-Exact-Conq-Fixed-SL-BOHO-BLANKET-BOUQUET-60x80-1-PC | C39: B0DS28Q1LT | D39: SP Product targeting | E39: Competitor PAT | F39: SL-BOHO-BLANKET-BOUQUET-60x80-1-PC | G39: Not in Phase 0 (Phase 1 lane L9) | H39: ENABLED | I39: 4.5 | J39: 0 | L39: =IF(OR(K39="",J39=""),"",K39*(1+J39)) | M39: 1531 | N39: 13 | O39: 7.28 | P39: 0 | Q39: 0 | R39: =IF(M39=0,0,N39/M39) -> 0.0084911822 | S39: =IF(N39=0,0,P39/N39) -> 0 | T39: =IF(N39=0,0,O39/N39) -> 0.56 | U39: =IF(Q39=0,"",O39/Q39) | V39: =IF(O39=0,0,Q39/O39) -> 0 | W39: 13 | X39: 7.28 | Y39: 0 | Z39: 0 | AA39: =IF(W39=0,0,Y39/W39) -> 0 | AB39: =IF(Z39=0,"",X39/Z39) | AC39: 12 | AD39: 6.72 | AE39: 0 | AF39: 0 | AG39: =IF(AC39=0,0,AE39/AC39) -> 0 | AH39: 3 | AI39: 1.68 | AJ39: 9 | AK39: 5.04 | AL39: 1 | AM39: 0.56 | AN39: 0 | AO39: 0 | AP39: =IF(O39=0,0,AO39/O39) -> 0 | AQ39: =IF(N39<Rules!$B$10,"Under 20 clicks: too early",IF(P39=0,"20+ clicks, 0 orders: negate / pause",IF(N39<Rules!$B$11,"Under 100 clicks: watch",IF(S39>=Rules!$B$12,"4%+: keep",IF(S39>=Rules!$B$13,"2% to 4%: hold at lower bid","Under 2%: pause"))))) -> Under 20 clicks: too early | AR39: =IF(O39=0,"",IF(Q39=0,"Spend, no sales",IF(U39>Rules!$B$33,"Above 3x break-even","Within 3x break-even"))) -> Spend, no sales | AS39: =IF(OR(J39="",H39<>"ENABLED"),"",IF(J39>Rules!$B$9,"Above +300% cap","OK")) -> OK | AT39: 5 PAUSE (wasted spend) | AU39: PAUSED | AV39: Pause now | AW39: 0 orders on 13 clicks ($7.28). Advertises Bouquet 60x80 regardless of the competitor's size or price. | AX39: Joseph approves; Shayan applies
A40: 64445529912580 | B40: SL-BB-SP-boho beach blanket-Boho|Blanket|Core-LSV-Exact-Rank-Fixed-SL-BOHO-BLANKET-BUTTERFLY-50x60-1-PC | C40: boho beach blanket | D40: SP Exact keyword | E40: Boho off-intent (picnic / beach / heated) | F40: SL-BOHO-BLANKET-BUTTERFLY-50x60-1-PC | G40: Phase 0: stop list | H40: ENABLED | I40: 8.83 | J40: 4.4 | L40: =IF(OR(K40="",J40=""),"",K40*(1+J40)) | M40: 234 | N40: 2 | O40: 6.03 | P40: 0 | Q40: 0 | R40: =IF(M40=0,0,N40/M40) -> 0.0085470085 | S40: =IF(N40=0,0,P40/N40) -> 0 | T40: =IF(N40=0,0,O40/N40) -> 3.015 | U40: =IF(Q40=0,"",O40/Q40) | V40: =IF(O40=0,0,Q40/O40) -> 0 | W40: 0 | X40: 0 | Y40: 0 | Z40: 0 | AA40: =IF(W40=0,0,Y40/W40) -> 0 | AB40: =IF(Z40=0,"",X40/Z40) | AC40: 0 | AD40: 0 | AE40: 0 | AF40: 0 | AG40: =IF(AC40=0,0,AE40/AC40) -> 0 | AH40: 2 | AI40: 6.03 | AJ40: 0 | AK40: 0 | AL40: 0 | AM40: 0 | AN40: 0 | AO40: 0 | AP40: =IF(O40=0,0,AO40/O40) -> 0 | AQ40: =IF(N40<Rules!$B$10,"Under 20 clicks: too early",IF(P40=0,"20+ clicks, 0 orders: negate / pause",IF(N40<Rules!$B$11,"Under 100 clicks: watch",IF(S40>=Rules!$B$12,"4%+: keep",IF(S40>=Rules!$B$13,"2% to 4%: hold at lower bid","Under 2%: pause"))))) -> Under 20 clicks: too early | AR40: =IF(O40=0,"",IF(Q40=0,"Spend, no sales",IF(U40>Rules!$B$33,"Above 3x break-even","Within 3x break-even"))) -> Spend, no sales | AS40: =IF(OR(J40="",H40<>"ENABLED"),"",IF(J40>Rules!$B$9,"Above +300% cap","OK")) -> Above +300% cap | AT40: 5 PAUSE (wasted spend) | AU40: PAUSED | AV40: Pause now | AW40: Stop list, still running. Wrong product (beach). TOS +440%, the highest on the product. | AX40: Joseph approves; Shayan applies
A41: 132877072716330 | B41: SL-BB-SP-B0B5XX22J6-Exact-Conq-Fixed-SL-BOHO-BLANKET-BOUQUET-60x80-1-PC | C41: B0B5XX22J6 | D41: SP Product targeting | E41: Competitor PAT | F41: SL-BOHO-BLANKET-BOUQUET-60x80-1-PC | G41: Not in Phase 0 (Phase 1 lane L9) | H41: ENABLED | I41: 4.5 | J41: 0 | L41: =IF(OR(K41="",J41=""),"",K41*(1+J41)) | M41: 966 | N41: 4 | O41: 2.36 | P41: 0 | Q41: 0 | R41: =IF(M41=0,0,N41/M41) -> 0.0041407867 | S41: =IF(N41=0,0,P41/N41) -> 0 | T41: =IF(N41=0,0,O41/N41) -> 0.59 | U41: =IF(Q41=0,"",O41/Q41) | V41: =IF(O41=0,0,Q41/O41) -> 0 | W41: 4 | X41: 2.36 | Y41: 0 | Z41: 0 | AA41: =IF(W41=0,0,Y41/W41) -> 0 | AB41: =IF(Z41=0,"",X41/Z41) | AC41: 3 | AD41: 1.77 | AE41: 0 | AF41: 0 | AG41: =IF(AC41=0,0,AE41/AC41) -> 0 | AH41: 0 | AI41: 0 | AJ41: 4 | AK41: 2.36 | AL41: 0 | AM41: 0 | AN41: 0 | AO41: 0 | AP41: =IF(O41=0,0,AO41/O41) -> 0 | AQ41: =IF(N41<Rules!$B$10,"Under 20 clicks: too early",IF(P41=0,"20+ clicks, 0 orders: negate / pause",IF(N41<Rules!$B$11,"Under 100 clicks: watch",IF(S41>=Rules!$B$12,"4%+: keep",IF(S41>=Rules!$B$13,"2% to 4%: hold at lower bid","Under 2%: pause"))))) -> Under 20 clicks: too early | AR41: =IF(O41=0,"",IF(Q41=0,"Spend, no sales",IF(U41>Rules!$B$33,"Above 3x break-even","Within 3x break-even"))) -> Spend, no sales | AS41: =IF(OR(J41="",H41<>"ENABLED"),"",IF(J41>Rules!$B$9,"Above +300% cap","OK")) -> OK | AT41: 5 PAUSE (wasted spend) | AU41: PAUSED | AV41: Pause now | AW41: 0 orders on 4 clicks ($2.36). Advertises Bouquet 60x80 regardless of the competitor's size or price. | AX41: Joseph approves; Shayan applies
A42: 37588435988821 | B42: SL-BB-SP-boho blanket throw patterned-Boho|Blanket|Pattern-VLSV-Exact-Rank-Fixed-SL-BOHO-BLANKET-BUTTERFLY-50x60-1-PC | C42: boho blanket throw patterned · boho reversible throw blanket · reversible boho blanket with patterns | D42: SP Exact keyword | E42: Boho pattern / colour | F42: SL-BOHO-BLANKET-BUTTERFLY-50x60-1-PC | G42: Not in Phase 0 | H42: ENABLED | I42: 19.76 | J42: 3.8 | L42: =IF(OR(K42="",J42=""),"",K42*(1+J42)) | M42: 46 | N42: 2 | O42: 2.26 | P42: 0 | Q42: 0 | R42: =IF(M42=0,0,N42/M42) -> 0.043478261 | S42: =IF(N42=0,0,P42/N42) -> 0 | T42: =IF(N42=0,0,O42/N42) -> 1.13 | U42: =IF(Q42=0,"",O42/Q42) | V42: =IF(O42=0,0,Q42/O42) -> 0 | W42: 1 | X42: 1.11 | Y42: 0 | Z42: 0 | AA42: =IF(W42=0,0,Y42/W42) -> 0 | AB42: =IF(Z42=0,"",X42/Z42) | AC42: 1 | AD42: 1.11 | AE42: 0 | AF42: 0 | AG42: =IF(AC42=0,0,AE42/AC42) -> 0 | AH42: 2 | AI42: 2.26 | AJ42: 0 | AK42: 0 | AL42: 0 | AM42: 0 | AN42: 0 | AO42: 0 | AP42: =IF(O42=0,0,AO42/O42) -> 0 | AQ42: =IF(N42<Rules!$B$10,"Under 20 clicks: too early",IF(P42=0,"20+ clicks, 0 orders: negate / pause",IF(N42<Rules!$B$11,"Under 100 clicks: watch",IF(S42>=Rules!$B$12,"4%+: keep",IF(S42>=Rules!$B$13,"2% to 4%: hold at lower bid","Under 2%: pause"))))) -> Under 20 clicks: too early | AR42: =IF(O42=0,"",IF(Q42=0,"Spend, no sales",IF(U42>Rules!$B$33,"Above 3x break-even","Within 3x break-even"))) -> Spend, no sales | AS42: =IF(OR(J42="",H42<>"ENABLED"),"",IF(J42>Rules!$B$9,"Above +300% cap","OK")) -> Above +300% cap | AT42: 4 RESTRUCTURE IN REBUILD | AU42: PAUSED | AV42: Pause now; restructure in the rebuild | AW42: 3 keywords including 'boho reversible throw blanket', a real feature of the product. 0 orders on 2 clicks; TOS +380%. | AX42: Joseph approves; Shayan applies
A43: 94080520861158 | B43: SL-BB-SP-sleephoria boho throw blanket-Branded Keyword-VLSV-Exact-Branded-Fixed-SL-BOHO-BLANKET-BUTTERFLY-50x60-1-PC | C43: boho throw blanket sleephoria · sleephoria boho throw blanket | D43: SP Exact keyword | E43: Brand defence | F43: SL-BOHO-BLANKET-BUTTERFLY-50x60-1-PC | G43: Phase 0: run | H43: ENABLED | I43: 11.32 | J43: 3.8 | L43: =IF(OR(K43="",J43=""),"",K43*(1+J43)) | M43: 16 | N43: 4 | O43: 1.38 | P43: 0 | Q43: 0 | R43: =IF(M43=0,0,N43/M43) -> 0.25 | S43: =IF(N43=0,0,P43/N43) -> 0 | T43: =IF(N43=0,0,O43/N43) -> 0.345 | U43: =IF(Q43=0,"",O43/Q43) | V43: =IF(O43=0,0,Q43/O43) -> 0 | W43: 0 | X43: 0 | Y43: 0 | Z43: 0 | AA43: =IF(W43=0,0,Y43/W43) -> 0 | AB43: =IF(Z43=0,"",X43/Z43) | AC43: 0 | AD43: 0 | AE43: 0 | AF43: 0 | AG43: =IF(AC43=0,0,AE43/AC43) -> 0 | AH43: 4 | AI43: 1.38 | AJ43: 0 | AK43: 0 | AL43: 0 | AM43: 0 | AN43: 0 | AO43: 0 | AP43: =IF(O43=0,0,AO43/O43) -> 0 | AQ43: =IF(N43<Rules!$B$10,"Under 20 clicks: too early",IF(P43=0,"20+ clicks, 0 orders: negate / pause",IF(N43<Rules!$B$11,"Under 100 clicks: watch",IF(S43>=Rules!$B$12,"4%+: keep",IF(S43>=Rules!$B$13,"2% to 4%: hold at lower bid","Under 2%: pause"))))) -> Under 20 clicks: too early | AR43: =IF(O43=0,"",IF(Q43=0,"Spend, no sales",IF(U43>Rules!$B$33,"Above 3x break-even","Within 3x break-even"))) -> Spend, no sales | AS43: =IF(OR(J43="",H43<>"ENABLED"),"",IF(J43>Rules!$B$9,"Above +300% cap","OK")) -> Above +300% cap | AT43: 2 ADJUST (bid / placement) | AU43: ENABLED | AV43: Keep live. Bid unchanged ($0.68); TOS +380% to +300%; budget $11.32 to $5 a day | AW43: Own-brand searches: 4 clicks, $1.38 since launch. Cheap protection for the listing, but the modifier is above the plan's +300% cap. | AX43: Joseph approves; Shayan applies
A44: 61013504041994 | B44: SL-BB-SP-B0G2RBNQ2X-Exact-Conq-Fixed-SL-BOHO-BLANKET-BOUQUET-60x80-1-PC | C44: B0G2RBNQ2X | D44: SP Product targeting | E44: Competitor PAT | F44: SL-BOHO-BLANKET-BOUQUET-60x80-1-PC | G44: Not in Phase 0 (Phase 1 lane L9) | H44: ENABLED | I44: 4.5 | J44: 0 | L44: =IF(OR(K44="",J44=""),"",K44*(1+J44)) | M44: 367 | N44: 1 | O44: 0.59 | P44: 0 | Q44: 0 | R44: =IF(M44=0,0,N44/M44) -> 0.0027247956 | S44: =IF(N44=0,0,P44/N44) -> 0 | T44: =IF(N44=0,0,O44/N44) -> 0.59 | U44: =IF(Q44=0,"",O44/Q44) | V44: =IF(O44=0,0,Q44/O44) -> 0 | W44: 1 | X44: 0.59 | Y44: 0 | Z44: 0 | AA44: =IF(W44=0,0,Y44/W44) -> 0 | AB44: =IF(Z44=0,"",X44/Z44) | AC44: 0 | AD44: 0 | AE44: 0 | AF44: 0 | AG44: =IF(AC44=0,0,AE44/AC44) -> 0 | AH44: 0 | AI44: 0 | AJ44: 1 | AK44: 0.59 | AL44: 0 | AM44: 0 | AN44: 0 | AO44: 0 | AP44: =IF(O44=0,0,AO44/O44) -> 0 | AQ44: =IF(N44<Rules!$B$10,"Under 20 clicks: too early",IF(P44=0,"20+ clicks, 0 orders: negate / pause",IF(N44<Rules!$B$11,"Under 100 clicks: watch",IF(S44>=Rules!$B$12,"4%+: keep",IF(S44>=Rules!$B$13,"2% to 4%: hold at lower bid","Under 2%: pause"))))) -> Under 20 clicks: too early | AR44: =IF(O44=0,"",IF(Q44=0,"Spend, no sales",IF(U44>Rules!$B$33,"Above 3x break-even","Within 3x break-even"))) -> Spend, no sales | AS44: =IF(OR(J44="",H44<>"ENABLED"),"",IF(J44>Rules!$B$9,"Above +300% cap","OK")) -> OK | AT44: 5 PAUSE (wasted spend) | AU44: PAUSED | AV44: Pause now | AW44: 0 orders on 1 clicks ($0.59). Advertises Bouquet 60x80 regardless of the competitor's size or price. | AX44: Joseph approves; Shayan applies
A45: 194745831752971 | B45: SL-BB-SP-boho cotton throw blanket no fringe-Boho|Blanket|Material-VLSV-Exact-Rank-Fixed-SL-BOHO-BLANKET-BUTTERFLY-50x60-1-PC | C45: boho cotton throw blanket no fringe | D45: SP Exact keyword | E45: Boho material (cotton) | F45: SL-BOHO-BLANKET-BUTTERFLY-50x60-1-PC | G45: Not in Phase 0 | H45: ENABLED | I45: 6.59 | J45: 3.8 | L45: =IF(OR(K45="",J45=""),"",K45*(1+J45)) | M45: 7 | N45: 1 | O45: 0.5 | P45: 0 | Q45: 0 | R45: =IF(M45=0,0,N45/M45) -> 0.14285714 | S45: =IF(N45=0,0,P45/N45) -> 0 | T45: =IF(N45=0,0,O45/N45) -> 0.5 | U45: =IF(Q45=0,"",O45/Q45) | V45: =IF(O45=0,0,Q45/O45) -> 0 | W45: 0 | X45: 0 | Y45: 0 | Z45: 0 | AA45: =IF(W45=0,0,Y45/W45) -> 0 | AB45: =IF(Z45=0,"",X45/Z45) | AC45: 0 | AD45: 0 | AE45: 0 | AF45: 0 | AG45: =IF(AC45=0,0,AE45/AC45) -> 0 | AH45: 0 | AI45: 0 | AJ45: 0 | AK45: 0 | AL45: 1 | AM45: 0.5 | AN45: 0 | AO45: 0 | AP45: =IF(O45=0,0,AO45/O45) -> 0 | AQ45: =IF(N45<Rules!$B$10,"Under 20 clicks: too early",IF(P45=0,"20+ clicks, 0 orders: negate / pause",IF(N45<Rules!$B$11,"Under 100 clicks: watch",IF(S45>=Rules!$B$12,"4%+: keep",IF(S45>=Rules!$B$13,"2% to 4%: hold at lower bid","Under 2%: pause"))))) -> Under 20 clicks: too early | AR45: =IF(O45=0,"",IF(Q45=0,"Spend, no sales",IF(U45>Rules!$B$33,"Above 3x break-even","Within 3x break-even"))) -> Spend, no sales | AS45: =IF(OR(J45="",H45<>"ENABLED"),"",IF(J45>Rules!$B$9,"Above +300% cap","OK")) -> Above +300% cap | AT45: 5 PAUSE (wasted spend) | AU45: PAUSED | AV45: Pause now | AW45: 'No fringe' contradicts the product (it has tassels). 1 click. | AX45: Joseph approves; Shayan applies
A46: TOTAL (all 40 campaigns) | I46: =SUMIFS(I6:I45,H6:H45,"ENABLED") -> 210.88 | M46: =SUM(M6:M45) -> 184807 | N46: =SUM(N6:N45) -> 3093 | O46: =SUM(O6:O45) -> 1648.02 | P46: =SUM(P6:P45) -> 34 | Q46: =SUM(Q6:Q45) -> 1072.65 | R46: =IF(M46=0,0,N46/M46) -> 0.016736379 | S46: =IF(N46=0,0,P46/N46) -> 0.010992564 | T46: =IF(N46=0,0,O46/N46) -> 0.5328225 | U46: =IF(Q46=0,"",O46/Q46) -> 1.5364005 | V46: =IF(O46=0,0,Q46/O46) -> 0.65087196 | W46: =SUM(W6:W45) -> 486 | X46: =SUM(X6:X45) -> 487.49 | Y46: =SUM(Y6:Y45) -> 4 | Z46: =SUM(Z6:Z45) -> 131.96 | AA46: =IF(W46=0,0,Y46/W46) -> 0.0082304527 | AB46: =IF(Z46=0,"",X46/Z46) -> 3.6942255 | AC46: =SUM(AC6:AC45) -> 215 | AD46: =SUM(AD6:AD45) -> 236.54 | AE46: =SUM(AE6:AE45) -> 2 | AF46: =SUM(AF6:AF45) -> 69.98 | AG46: =IF(AC46=0,0,AE46/AC46) -> 0.0093023256 | AH46: =SUM(AH6:AH45) -> 429 | AI46: =SUM(AI6:AI45) -> 660.55 | AJ46: =SUM(AJ6:AJ45) -> 922 | AK46: =SUM(AK6:AK45) -> 611.42 | AL46: =SUM(AL6:AL45) -> 53 | AM46: =SUM(AM6:AM45) -> 39.72 | AN46: =SUM(AN6:AN45) -> 1686 | AO46: =SUM(AO6:AO45) -> 336.34 | AP46: =IF(O46=0,0,AO46/O46) -> 0.20408733

Sheet Spend Mix
A1: Where the money went: by keyword family and by decision
A2: SUMIFS over the Campaigns tab.
A4: Keyword family | B4: Campaigns | C4: Enabled now | D4: Live after the change | E4: Spend since launch | F4: Clicks since launch | G4: Orders since launch | H4: CVR since launch | I4: ACoS since launch | J4: Spend, last 30 days | K4: Orders, last 30 days | L4: Share of last 30 days spend
A5: Brand defence | B5: =COUNTIF(Campaigns!$E$6:$E$45,$A5) -> 1 | C5: =COUNTIFS(Campaigns!$E$6:$E$45,$A5,Campaigns!$H$6:$H$45,"ENABLED") -> 1 | D5: =COUNTIFS(Campaigns!$E$6:$E$45,$A5,Campaigns!$AU$6:$AU$45,"ENABLED") -> 1 | E5: =SUMIFS(Campaigns!$O$6:$O$45,Campaigns!$E$6:$E$45,$A5) -> 1.38 | F5: =SUMIFS(Campaigns!$N$6:$N$45,Campaigns!$E$6:$E$45,$A5) -> 4 | G5: =SUMIFS(Campaigns!$P$6:$P$45,Campaigns!$E$6:$E$45,$A5) -> 0 | H5: =IF(F5=0,0,G5/F5) -> 0 | I5: =IF(SUMIFS(Campaigns!$Q$6:$Q$45,Campaigns!$E$6:$E$45,$A5)=0,"",E5/SUMIFS(Campaigns!$Q$6:$Q$45,Campaigns!$E$6:$E$45,$A5)) | J5: =SUMIFS(Campaigns!$X$6:$X$45,Campaigns!$E$6:$E$45,$A5) -> 0 | K5: =SUMIFS(Campaigns!$Y$6:$Y$45,Campaigns!$E$6:$E$45,$A5) -> 0 | L5: =IF($J$13=0,0,J5/$J$13) -> 0
A6: Boho core | B6: =COUNTIF(Campaigns!$E$6:$E$45,$A6) -> 8 | C6: =COUNTIFS(Campaigns!$E$6:$E$45,$A6,Campaigns!$H$6:$H$45,"ENABLED") -> 1 | D6: =COUNTIFS(Campaigns!$E$6:$E$45,$A6,Campaigns!$AU$6:$AU$45,"ENABLED") -> 2 | E6: =SUMIFS(Campaigns!$O$6:$O$45,Campaigns!$E$6:$E$45,$A6) -> 600.48 | F6: =SUMIFS(Campaigns!$N$6:$N$45,Campaigns!$E$6:$E$45,$A6) -> 765 | G6: =SUMIFS(Campaigns!$P$6:$P$45,Campaigns!$E$6:$E$45,$A6) -> 12 | H6: =IF(F6=0,0,G6/F6) -> 0.015686275 | I6: =IF(SUMIFS(Campaigns!$Q$6:$Q$45,Campaigns!$E$6:$E$45,$A6)=0,"",E6/SUMIFS(Campaigns!$Q$6:$Q$45,Campaigns!$E$6:$E$45,$A6)) -> 1.5683652 | J6: =SUMIFS(Campaigns!$X$6:$X$45,Campaigns!$E$6:$E$45,$A6) -> 98.24 | K6: =SUMIFS(Campaigns!$Y$6:$Y$45,Campaigns!$E$6:$E$45,$A6) -> 3 | L6: =IF($J$13=0,0,J6/$J$13) -> 0.20152208
A7: Boho couch / bed | B7: =COUNTIF(Campaigns!$E$6:$E$45,$A7) -> 5 | C7: =COUNTIFS(Campaigns!$E$6:$E$45,$A7,Campaigns!$H$6:$H$45,"ENABLED") -> 3 | D7: =COUNTIFS(Campaigns!$E$6:$E$45,$A7,Campaigns!$AU$6:$AU$45,"ENABLED") -> 0 | E7: =SUMIFS(Campaigns!$O$6:$O$45,Campaigns!$E$6:$E$45,$A7) -> 248 | F7: =SUMIFS(Campaigns!$N$6:$N$45,Campaigns!$E$6:$E$45,$A7) -> 559 | G7: =SUMIFS(Campaigns!$P$6:$P$45,Campaigns!$E$6:$E$45,$A7) -> 6 | H7: =IF(F7=0,0,G7/F7) -> 0.010733453 | I7: =IF(SUMIFS(Campaigns!$Q$6:$Q$45,Campaigns!$E$6:$E$45,$A7)=0,"",E7/SUMIFS(Campaigns!$Q$6:$Q$45,Campaigns!$E$6:$E$45,$A7)) -> 1.3337636 | J7: =SUMIFS(Campaigns!$X$6:$X$45,Campaigns!$E$6:$E$45,$A7) -> 70.1 | K7: =SUMIFS(Campaigns!$Y$6:$Y$45,Campaigns!$E$6:$E$45,$A7) -> 0 | L7: =IF($J$13=0,0,J7/$J$13) -> 0.14379782
A8: Boho size (king / queen / 60x80) | B8: =COUNTIF(Campaigns!$E$6:$E$45,$A8) -> 7 | C8: =COUNTIFS(Campaigns!$E$6:$E$45,$A8,Campaigns!$H$6:$H$45,"ENABLED") -> 5 | D8: =COUNTIFS(Campaigns!$E$6:$E$45,$A8,Campaigns!$AU$6:$AU$45,"ENABLED") -> 0 | E8: =SUMIFS(Campaigns!$O$6:$O$45,Campaigns!$E$6:$E$45,$A8) -> 402.68 | F8: =SUMIFS(Campaigns!$N$6:$N$45,Campaigns!$E$6:$E$45,$A8) -> 1277 | G8: =SUMIFS(Campaigns!$P$6:$P$45,Campaigns!$E$6:$E$45,$A8) -> 12 | H8: =IF(F8=0,0,G8/F8) -> 0.0093970243 | I8: =IF(SUMIFS(Campaigns!$Q$6:$Q$45,Campaigns!$E$6:$E$45,$A8)=0,"",E8/SUMIFS(Campaigns!$Q$6:$Q$45,Campaigns!$E$6:$E$45,$A8)) -> 1.0828224 | J8: =SUMIFS(Campaigns!$X$6:$X$45,Campaigns!$E$6:$E$45,$A8) -> 111.3 | K8: =SUMIFS(Campaigns!$Y$6:$Y$45,Campaigns!$E$6:$E$45,$A8) -> 0 | L8: =IF($J$13=0,0,J8/$J$13) -> 0.22831238
A9: Boho off-intent (picnic / beach / heated) | B9: =COUNTIF(Campaigns!$E$6:$E$45,$A9) -> 3 | C9: =COUNTIFS(Campaigns!$E$6:$E$45,$A9,Campaigns!$H$6:$H$45,"ENABLED") -> 2 | D9: =COUNTIFS(Campaigns!$E$6:$E$45,$A9,Campaigns!$AU$6:$AU$45,"ENABLED") -> 0 | E9: =SUMIFS(Campaigns!$O$6:$O$45,Campaigns!$E$6:$E$45,$A9) -> 54.13 | F9: =SUMIFS(Campaigns!$N$6:$N$45,Campaigns!$E$6:$E$45,$A9) -> 63 | G9: =SUMIFS(Campaigns!$P$6:$P$45,Campaigns!$E$6:$E$45,$A9) -> 0 | H9: =IF(F9=0,0,G9/F9) -> 0 | I9: =IF(SUMIFS(Campaigns!$Q$6:$Q$45,Campaigns!$E$6:$E$45,$A9)=0,"",E9/SUMIFS(Campaigns!$Q$6:$Q$45,Campaigns!$E$6:$E$45,$A9)) | J9: =SUMIFS(Campaigns!$X$6:$X$45,Campaigns!$E$6:$E$45,$A9) -> 10.12 | K9: =SUMIFS(Campaigns!$Y$6:$Y$45,Campaigns!$E$6:$E$45,$A9) -> 0 | L9: =IF($J$13=0,0,J9/$J$13) -> 0.0207594
A10: Boho material (cotton) | B10: =COUNTIF(Campaigns!$E$6:$E$45,$A10) -> 3 | C10: =COUNTIFS(Campaigns!$E$6:$E$45,$A10,Campaigns!$H$6:$H$45,"ENABLED") -> 1 | D10: =COUNTIFS(Campaigns!$E$6:$E$45,$A10,Campaigns!$AU$6:$AU$45,"ENABLED") -> 0 | E10: =SUMIFS(Campaigns!$O$6:$O$45,Campaigns!$E$6:$E$45,$A10) -> 100.45 | F10: =SUMIFS(Campaigns!$N$6:$N$45,Campaigns!$E$6:$E$45,$A10) -> 113 | G10: =SUMIFS(Campaigns!$P$6:$P$45,Campaigns!$E$6:$E$45,$A10) -> 2 | H10: =IF(F10=0,0,G10/F10) -> 0.017699115 | I10: =IF(SUMIFS(Campaigns!$Q$6:$Q$45,Campaigns!$E$6:$E$45,$A10)=0,"",E10/SUMIFS(Campaigns!$Q$6:$Q$45,Campaigns!$E$6:$E$45,$A10)) -> 1.6206841 | J10: =SUMIFS(Campaigns!$X$6:$X$45,Campaigns!$E$6:$E$45,$A10) -> 0 | K10: =SUMIFS(Campaigns!$Y$6:$Y$45,Campaigns!$E$6:$E$45,$A10) -> 0 | L10: =IF($J$13=0,0,J10/$J$13) -> 0
A11: Boho pattern / colour | B11: =COUNTIF(Campaigns!$E$6:$E$45,$A11) -> 3 | C11: =COUNTIFS(Campaigns!$E$6:$E$45,$A11,Campaigns!$H$6:$H$45,"ENABLED") -> 2 | D11: =COUNTIFS(Campaigns!$E$6:$E$45,$A11,Campaigns!$AU$6:$AU$45,"ENABLED") -> 0 | E11: =SUMIFS(Campaigns!$O$6:$O$45,Campaigns!$E$6:$E$45,$A11) -> 37.03 | F11: =SUMIFS(Campaigns!$N$6:$N$45,Campaigns!$E$6:$E$45,$A11) -> 88 | G11: =SUMIFS(Campaigns!$P$6:$P$45,Campaigns!$E$6:$E$45,$A11) -> 1 | H11: =IF(F11=0,0,G11/F11) -> 0.011363636 | I11: =IF(SUMIFS(Campaigns!$Q$6:$Q$45,Campaigns!$E$6:$E$45,$A11)=0,"",E11/SUMIFS(Campaigns!$Q$6:$Q$45,Campaigns!$E$6:$E$45,$A11)) -> 1.0583024 | J11: =SUMIFS(Campaigns!$X$6:$X$45,Campaigns!$E$6:$E$45,$A11) -> 8.03 | K11: =SUMIFS(Campaigns!$Y$6:$Y$45,Campaigns!$E$6:$E$45,$A11) -> 0 | L11: =IF($J$13=0,0,J11/$J$13) -> 0.016472133
A12: Competitor PAT | B12: =COUNTIF(Campaigns!$E$6:$E$45,$A12) -> 10 | C12: =COUNTIFS(Campaigns!$E$6:$E$45,$A12,Campaigns!$H$6:$H$45,"ENABLED") -> 7 | D12: =COUNTIFS(Campaigns!$E$6:$E$45,$A12,Campaigns!$AU$6:$AU$45,"ENABLED") -> 0 | E12: =SUMIFS(Campaigns!$O$6:$O$45,Campaigns!$E$6:$E$45,$A12) -> 203.87 | F12: =SUMIFS(Campaigns!$N$6:$N$45,Campaigns!$E$6:$E$45,$A12) -> 224 | G12: =SUMIFS(Campaigns!$P$6:$P$45,Campaigns!$E$6:$E$45,$A12) -> 1 | H12: =IF(F12=0,0,G12/F12) -> 0.0044642857 | I12: =IF(SUMIFS(Campaigns!$Q$6:$Q$45,Campaigns!$E$6:$E$45,$A12)=0,"",E12/SUMIFS(Campaigns!$Q$6:$Q$45,Campaigns!$E$6:$E$45,$A12)) -> 5.8265219 | J12: =SUMIFS(Campaigns!$X$6:$X$45,Campaigns!$E$6:$E$45,$A12) -> 189.7 | K12: =SUMIFS(Campaigns!$Y$6:$Y$45,Campaigns!$E$6:$E$45,$A12) -> 1 | L12: =IF($J$13=0,0,J12/$J$13) -> 0.38913619
A13: TOTAL | B13: =SUM(B5:B12) -> 40 | C13: =SUM(C5:C12) -> 22 | D13: =SUM(D5:D12) -> 3 | E13: =SUM(E5:E12) -> 1648.02 | F13: =SUM(F5:F12) -> 3093 | G13: =SUM(G5:G12) -> 34 | H13: =IF(F13=0,0,G13/F13) -> 0.010992564 | I13: =IF(SUM(Campaigns!$Q$6:$Q$45)=0,"",E13/SUM(Campaigns!$Q$6:$Q$45)) -> 1.5364005 | J13: =SUM(J5:J12) -> 487.49 | K13: =SUM(K5:K12) -> 4 | L13: =SUM(L5:L12) -> 1

Sheet Placements
A1: Placement split: where clicks, spend and orders came from
A2: Clicks and spend: SUMs over the Campaigns tab. On-Amazon orders: Amazon's placement report at campaign grain. Off-Amazon orders are not reported, so they are total orders minus on-Amazon orders (implied).
A4: Placement (since launch) | B4: Clicks | C4: Spend | D4: Orders | E4: CVR | F4: CPC | G4: Share of spend | H4: Read
A5: Top of Search | B5: =SUM(Campaigns!$AH$6:$AH$45) -> 429 | C5: =SUM(Campaigns!$AI$6:$AI$45) -> 660.55 | D5: 11 | E5: =IF(B5=0,0,D5/B5) -> 0.025641026 | F5: =IF(B5=0,0,C5/B5) -> 1.5397436 | G5: =IF($C$9=0,0,C5/$C$9) -> 0.40081188 | H5: Best CVR on Amazon. TOS clicks are worth about 2x an average click.
A6: Product pages | B6: =SUM(Campaigns!$AJ$6:$AJ$45) -> 922 | C6: =SUM(Campaigns!$AK$6:$AK$45) -> 611.42 | D6: 6 | E6: =IF(B6=0,0,D6/B6) -> 0.0065075922 | F6: =IF(B6=0,0,C6/B6) -> 0.66314534 | G6: =IF($C$9=0,0,C6/$C$9) -> 0.37100053 | H6: Most on-Amazon clicks, lowest CVR. Base bids set low.
A7: Rest of Search | B7: =SUM(Campaigns!$AL$6:$AL$45) -> 53 | C7: =SUM(Campaigns!$AM$6:$AM$45) -> 39.72 | D7: 1 | E7: =IF(B7=0,0,D7/B7) -> 0.018867925 | F7: =IF(B7=0,0,C7/B7) -> 0.74943396 | G7: =IF($C$9=0,0,C7/$C$9) -> 0.024101503 | H7: Small.
A8: Off-Amazon | B8: =SUM(Campaigns!$AN$6:$AN$45) -> 1686 | C8: =SUM(Campaigns!$AO$6:$AO$45) -> 336.34 | D8: =SUM(Campaigns!$P$6:$P$45)-SUM(D5:D7) -> 16 | E8: =IF(B8=0,0,D8/B8) -> 0.009489917 | F8: =IF(B8=0,0,C8/B8) -> 0.19948992 | G8: =IF($C$9=0,0,C8/$C$9) -> 0.20408609 | H8: About half of all orders at about $0.20 a click. 0 clicks in the last 30 days.
A9: TOTAL | B9: =SUM(B5:B8) -> 3090 | C9: =SUM(C5:C8) -> 1648.03 | D9: =SUM(D5:D8) -> 34 | E9: =IF(B9=0,0,D9/B9) -> 0.011003236 | F9: =IF(B9=0,0,C9/B9) -> 0.53334304 | G9: =SUM(G5:G8) -> 1
A11: Off-Amazon investigation: why it stopped
A12: Finding: it was not switched off. It was a burst of about 2 weeks (about 6 to 18 Sep, about 1,690 clicks at $0.20) that spent idle budget on a few boho campaigns, then stopped campaign by campaign as those campaigns were cut back or paused.
A13: Why those campaigns: Ali's Day 10 read (about 4 Sep) flagged four campaigns holding $30 to $50 a day at under 3% budget use. Three of them took Off-Amazon traffic days later. Off-Amazon ads use the campaign's own budget and max bid and are on by default ('Increase reach'); creator placements were added from 10 Aug 2026 (trade press).
A14: Not account-wide: other products kept getting Off-Amazon clicks after 19 Sep (table below), so nothing was switched off at account level.
A15: Not confirmed: who changed what on 11 and 12 Sep (Campaign Manager history on 'boho king size blanket'), and whether 'Limit off-Amazon spend' is set (visible in a fresh bulk export, 'Off-Amazon ad serving' column).
A17: Campaign that took Off-Amazon traffic | B17: Off-Amazon days | C17: Peak clicks a day | D17: CPC | E17: What happened
A18: boho king size blanket | B18: 7 to 11 Sep | C18: 317 | D18: $0.19 | E18: 317 clicks and $60.23 on each of 9, 10 and 11 Sep (budget-limited); 0 impressions on 12 Sep; Amazon-only afterwards (now $0.97 bid, +413%)
A19: boho throw blankets for couch | B19: 10 to 15 Sep | C19: 118 | D19: $0.15 to $0.22 | E19: Stopped after 15 Sep; still enabled, Amazon-only
A20: boho blanket throw colorful | B20: 13 Sep | C20: 72 | D20: $0.23 | E20: One day only; campaign now paused
A21: boho blanket king | B21: 16 to 18 Sep | C21: 44 | D21: $0.26 to $0.54 | E21: Stopped after 18 Sep; Amazon-only afterwards
A22: boho heated, scandinavian, throw blanket for couch boho | B22: Sep | C22: 40 | D22: about $0.20 | E22: Small amounts; all now paused
A24: Date | B24: Boho: Off-Amazon clicks | C24: Boho: all clicks | D24: Bamboo 4-PC: Off-Amazon | E24: Quilt Set: Off-Amazon
A25: 2026-09-01 | B25: 0 | C25: 45 | D25: 0 | E25: 2
A26: 2026-09-02 | B26: 0 | C26: 51 | D26: 0 | E26: 1
A27: 2026-09-03 | B27: 0 | C27: 82 | D27: 0 | E27: 1
A28: 2026-09-04 | B28: 1 | C28: 23 | D28: 0 | E28: 1
A29: 2026-09-05 | B29: 0 | C29: 28 | D29: 1 | E29: 3
A30: 2026-09-06 | B30: 6 | C30: 38 | D30: 0 | E30: 4
A31: 2026-09-07 | B31: 10 | C31: 46 | D31: 1 | E31: 2
A32: 2026-09-08 | B32: 73 | C32: 103 | D32: 1 | E32: 4
A33: 2026-09-09 | B33: 328 | C33: 345 | D33: 5 | E33: 0
A34: 2026-09-10 | B34: 326 | C34: 348 | D34: 0 | E34: 2
A35: 2026-09-11 | B35: 356 | C35: 368 | D35: 1 | E35: 4
A36: 2026-09-12 | B36: 103 | C36: 116 | D36: 2 | E36: 5
... A75: 2026-10-21 | B75: 0 | C75: 14 | D75: 2 | E75: 12

Sheet Stop List
A1: Stop list check: the 9 terms in the pack, status on 22 Oct
A2: Looked up from the Campaigns tab by campaign ID.
A4: Stop-list term | B4: Pack evidence (to 9 Sep) | C4: Campaign ID | D4: State now | E4: Clicks since launch | F4: Orders since launch | G4: Spend since launch | H4: CVR since launch | I4: Status | J4: Decision now
A5: throw blanket boho | B5: $41.63, 0 orders | C5: 52789396358241 | D5: =INDEX(Campaigns!$H$6:$H$45,MATCH($C5,Campaigns!$A$6:$A$45,0)) -> PAUSED | E5: =INDEX(Campaigns!$N$6:$N$45,MATCH($C5,Campaigns!$A$6:$A$45,0)) -> 71 | F5: =INDEX(Campaigns!$P$6:$P$45,MATCH($C5,Campaigns!$A$6:$A$45,0)) -> 0 | G5: =INDEX(Campaigns!$O$6:$O$45,MATCH($C5,Campaigns!$A$6:$A$45,0)) -> 63.38 | H5: =IF(E5=0,0,F5/E5) -> 0 | I5: =IF(D5="PAUSED","Done","Still running: pause") -> Done | J5: =INDEX(Campaigns!$AT$6:$AT$45,MATCH($C5,Campaigns!$A$6:$A$45,0))&": "&INDEX(Campaigns!$AV$6:$AV$45,MATCH($C5,Campaigns!$A$6:$A$45,0)) -> 5 PAUSE (wasted spend): Keep paused; drop from the core list
A6: boho blankets and throws | B6: $20.83, 0 orders | C6: 73752905509119 | D6: =INDEX(Campaigns!$H$6:$H$45,MATCH($C6,Campaigns!$A$6:$A$45,0)) -> PAUSED | E6: =INDEX(Campaigns!$N$6:$N$45,MATCH($C6,Campaigns!$A$6:$A$45,0)) -> 72 | F6: =INDEX(Campaigns!$P$6:$P$45,MATCH($C6,Campaigns!$A$6:$A$45,0)) -> 0 | G6: =INDEX(Campaigns!$O$6:$O$45,MATCH($C6,Campaigns!$A$6:$A$45,0)) -> 62.18 | H6: =IF(E6=0,0,F6/E6) -> 0 | I6: =IF(D6="PAUSED","Done","Still running: pause") -> Done | J6: =INDEX(Campaigns!$AT$6:$AT$45,MATCH($C6,Campaigns!$A$6:$A$45,0))&": "&INDEX(Campaigns!$AV$6:$AV$45,MATCH($C6,Campaigns!$A$6:$A$45,0)) -> 5 PAUSE (wasted spend): Keep paused
A7: boho blanket throw | B7: $14.47, 0 orders | C7: 199196980921698 | D7: =INDEX(Campaigns!$H$6:$H$45,MATCH($C7,Campaigns!$A$6:$A$45,0)) -> PAUSED | E7: =INDEX(Campaigns!$N$6:$N$45,MATCH($C7,Campaigns!$A$6:$A$45,0)) -> 32 | F7: =INDEX(Campaigns!$P$6:$P$45,MATCH($C7,Campaigns!$A$6:$A$45,0)) -> 0 | G7: =INDEX(Campaigns!$O$6:$O$45,MATCH($C7,Campaigns!$A$6:$A$45,0)) -> 27.55 | H7: =IF(E7=0,0,F7/E7) -> 0 | I7: =IF(D7="PAUSED","Done","Still running: pause") -> Done | J7: =INDEX(Campaigns!$AT$6:$AT$45,MATCH($C7,Campaigns!$A$6:$A$45,0))&": "&INDEX(Campaigns!$AV$6:$AV$45,MATCH($C7,Campaigns!$A$6:$A$45,0)) -> 5 PAUSE (wasted spend): Keep paused
A8: boho blanket queen | B8: $8.31, 0 orders | C8: 20309127916243 | D8: =INDEX(Campaigns!$H$6:$H$45,MATCH($C8,Campaigns!$A$6:$A$45,0)) -> PAUSED | E8: =INDEX(Campaigns!$N$6:$N$45,MATCH($C8,Campaigns!$A$6:$A$45,0)) -> 18 | F8: =INDEX(Campaigns!$P$6:$P$45,MATCH($C8,Campaigns!$A$6:$A$45,0)) -> 0 | G8: =INDEX(Campaigns!$O$6:$O$45,MATCH($C8,Campaigns!$A$6:$A$45,0)) -> 20.86 | H8: =IF(E8=0,0,F8/E8) -> 0 | I8: =IF(D8="PAUSED","Done","Still running: pause") -> Done | J8: =INDEX(Campaigns!$AT$6:$AT$45,MATCH($C8,Campaigns!$A$6:$A$45,0))&": "&INDEX(Campaigns!$AV$6:$AV$45,MATCH($C8,Campaigns!$A$6:$A$45,0)) -> 5 PAUSE (wasted spend): Keep paused
