Workbook

Sheet START HERE
A1: Topic | B1: Read me
A2: Status | B2: Evidence-limited research package. Public evidence collected; domestic rank panels, measured keyword demand/CPC/CVR, competitor sales, quotes and review histories are NOT verified.
A3: Date | B3: 26 October 2026; geography split US/CA/UK. Monetary currency explicit in every financial table.
A4: Legend | B4: FACT=observed official/page evidence; CLAIM=seller assertion; ESTIMATE=publisher model; CALC=derived; ASSUMPTION=analyst scenario; GAP=unavailable.
A5: Edit | B5: Economics numeric inputs F:AG and BH (runway months) are blue. Derived formulas black. All commercial scenario inputs require replacement with approved quotes/pilot results.
A6: Samples | B6: 1627 query-ASIN observations, 1568 distinct marketplace-ASIN pairs, 33 query pages. Not a probability sample.
A7: Prices | B7: Title-screened but mixed sizes/sets; US/UK retained Colombia delivery destination. Currency corrected through UI. No normalized domestic price distribution claimed.
A8: Ratings | B8: Displayed total ratings, not written review count; K/M rounded; pooled variants/countries possible. No review-growth trend from one snapshot.
A9: Review corpus | B9: 122 visible review cards: 40 Canadian, 33 UK, 25 US, 24 other by reviewer location. US reviews obtained from imported reviews on CA/UK pages. Top/helpful sample, not complaint prevalence.
A10: Formula basis | B10: Per shipped order; discounts and refunds reduce revenue; landed cost charged once with zero returned-inventory recovery; referral refund and admin approximated. FBA charged on every shipment.
A11: UK accounting | B11: Retail price assumed VAT-inclusive at20%; referral charged on VAT-inclusive order amount. Fee VAT assumed recoverable. Customs base is factory+packaging proxy, NOT a legal valuation.
A12: Break-even | B12: BE ACoS=pre-ad contribution / initial gross discounted order revenue. BE CPC=pre-ad contribution*CVR. Blended CM assumes stated paid-order share; attribution halo ignored.
... A15: Use | B15: Choose feasibility work, not production purchase orders. No outreach, ads, purchases or launch commitments made.

Sheet Market
A1: Country | B1: Broad bedding2024 USDm | C1: GVR CAGR2025-33 % | D1: Offline2024 % | E1: Home textiles2025 USDm | F1: Bed linen share2025 % | G1: Home textiles2026 USDm | H1: Mordor CAGR2026-31 % | I1: Sources | J1: Derived bed linen2025 USDm | K1: Derived broad online2024 USDm
A2: US | B2: 32748.9 | C2: 8.8 | D2: 75.19 | E2: 26480 | F2: 42.15 | G2: 27500 | H2: 3.86 | I2: M01; M07 | J2: =E2*F2/100 -> 11161.32 | K2: =B2*(1-D2/100) -> 8125.0021
A3: CA | B3: 6061.7 | C3: 10.9 | D3: 78.07 | E3: 3120 | F3: 43.77 | G3: 3290 | H3: 4.58 | I3: M02; M09 | J3: =E3*F3/100 -> 1365.624 | K3: =B3*(1-D3/100) -> 1329.3308
A4: UK | B4: 8016.7 | C4: 7.2 | D4: 67.46 | E4: 7620 | F4: 45.92 | G4: 7750 | H4: 1.76 | I4: M03; M08 | J4: =E4*F4/100 -> 3499.104 | K4: =B4*(1-D4/100) -> 2608.6342

Sheet Product segments
A1: Segment | B1: Query bucket | C1: Demand/use cases (judgement) | D1: Materials | E1: Proposed specs to test | F1: Competition | G1: Differentiation hypothesis | H1: Manufacturing | I1: Recommendation
A2: Sheets / sheet sets | B2: sheets | C2: Replacement, first-home, guest-room and gifting use cases; exact demand unmeasured | D2: Cotton percale/sateen; microfiber; regenerated cellulose | E2: Proposed: 200-300 single-ply percale or 300-500 sateen; declare fibre percentages; fit after washing, not just cut dimensions | F2: High price transparency, entrenched ratings; generic cooling/organic is already common | G2: Differentiated cotton with measured fit and wash durability; narrow colours/sizes | H2: Medium: weaving/finishing, shrink allowance, consistent dye lots | I2: Investigate differentiated; avoid undifferentiated head-term launch
A3: Fitted sheets | B3: fitted | C3: Replacement-only purchases and difficult mattress depths; niche size volumes unmeasured | D3: Cotton, cotton/polyester, microfiber, jersey | E3: Proposed: explicit mattress-depth range, elastic recovery, orientation label; separate shallow/deep patterns | F3: Deep-pocket and orientation features already offered; feature presence alone is not a moat | G3: Verified post-wash fit for specific depth/size; replacement availability | H3: Medium: corner seam, elastic tension and shrink fit | I3: Investigate; willingness-to-pay unvalidated
A4: Pillowcases | B4: pillowcase | C4: Replacement, extra pillows, hair/skin-positioning and gifts | D4: Cotton, polyester satin, silk, lyocell | E4: State pair vs single; internal usable length; envelope/zip closure; silk momme only for actual silk | F4: Low AOV makes shipping and acquisition disproportionately expensive | G4: Add-on, replacement pair, coordinated colours; bundle to improve basket economics | H4: Low-medium: seam/closure finish and sizing | I4: Investigate as niche/bundle; weak standalone broad-PPC economics
A5: Duvet covers | B5: duvet | C5: Decor refresh and washable protection; country-specific naming and size | D5: Cotton percale/sateen, cotton blend, linen, lyocell | E5: Actual insert dimensions; corner/side ties, seam and zipper cycling; clarify no insert; colourfastness | F5: Washed-cotton linen-look and ties already widespread | G5: Easy assembly plus tested fit/colourfastness; UK-native dimensions | H5: Medium: large-panel alignment, shrinkage and closure | I5: Investigate US/UK differentiated and hospitality
A6: Comforters / duvet inserts | B6: comforter | C6: Seasonal warmth, room bundles and all-in-one convenience | D6: Polyester/down alternative, down/feather, cotton shell | E6: Fill weight/composition; UK tog where tested; baffle/box construction; washing/drying instructions | F6: Value bed-in-a-bag bundles set a low reference price; bulk inflates logistics | G6: Specific warmth/weight need backed by testing, not generic all-season claim | H6: High: fill uniformity, migration, compression, drying and product-rule checks | I6: Postpone broad launch; niche feasibility only
A7: Quilts / coverlets | B7: quilt | C7: Decorative layering and lightweight seasonal use | D7: Cotton shell/fill, blends, microfiber | E7: Distinguish cotton shell from fill; finished dimensions, quilting density, wash behaviour | F7: Pattern/style inventory fragments demand; UK quilt query can mean duvet insert | G7: Wash-durable lightweight layer for specific climate/use | H7: Medium-high: quilting capacity, stitch durability, colour and fill | I7: Investigate design-led narrow assortment; no inferred UK demand from query
A8: Mattress protectors | B8: protector | C8: Spills, hygiene and mattress preservation | D8: Cotton or viscose blend top, polyurethane membrane, polyester skirt | E8: Waterproof after repeated washes, noise, thermal comfort, fit depth; verify actual layers | F8: SafeRest/Utopia/PlushDeluxe/Silentnight have substantial visible trust signals | G8: Quiet leak-tested protector with honest composition and clear care | H8: High: membrane lamination, seal integrity and product classification | I8: Postpone commodity; differentiated only after lab validation
A9: Mattress toppers / pads | B9: topper | C9: Comfort retrofit and dorm/guest use | D9: Foam, latex, hollowfibre, down/feather; cellulose cover claims | E9: Separate foam thickness/density from quilted pad loft; recovery and durability tests | F9: Search mixes thin pads and thick foam; high volume/return risk; health claims require support | G9: Narrow comfort use case with measured retention and realistic imagery | H9: High: bulky freight, compression recovery, flammability scope and returns | I9: Postpone for capital-light entrant
A10: Blankets, throws, flannel and other | B10: other | C10: Seasonal warmth, decoration; nursery and heated products are distinct risk classes | D10: Cotton, wool, fleece, flannel; electric components if heated | E10: GSM and dimensions; lint/pilling, wash shrinkage; special child/electrical requirements | F10: Gift/style-driven promotion and seasonal leftovers | G10: Non-electrical adult-use layers; hospitality replenishment | H10: Medium; higher for weighted/heated/child products | I10: Investigate selectively; exclude regulated extensions from initial launch

Sheet Materials
A1: Material | B1: Definition | C1: Consumer proposition | D1: Proposed checks | E1: Risk | F1: Evidence
A2: Cotton percale | B2: Fibre cotton; plain weave, not a fibre called percale | C2: Crisp, matte, breathable positioning; wrinkles may be accepted or disliked | D2: Proposed 200-300 single-ply TC, documented yarn/weight; post-wash shrink and tear tests | E2: Avoid assuming high TC or Egyptian wording proves quality | F2: D01; LIVE_US_sheets; LIVE_CA_sheets
A3: Cotton sateen | B3: Cotton in a sateen weave | C3: Smooth, lustrous hand; warmth and snag sensitivity depend on construction | D3: Proposed 300-500 single-ply TC; abrasion, pilling, dimensional stability | E3: Not interchangeable with polyester satin | F3: D01; LIVE_US_sheets
A4: Microfiber / polyester satin | B4: Synthetic fibre; satin is a weave | C4: Affordable, soft and easy-care positioning; thermal comfort is subjective | D4: Specify GSM, yarn and finish; pilling/static/colourfastness testing | E4: Low differentiation and low selling prices challenge paid acquisition | F4: LIVE_US_fitted; LIVE_UK_sheets
A5: Cotton blends | B5: Percentages determine actual material | C5: Easy-care and laundry durability may suit hospitality | D5: Declare fibre percentages; measure dry time and repeated-wash serviceability | E5: Do not market as 100% cotton or infer equal breathability | F5: D07; M07; M09
A6: Bamboo-derived viscose/rayon | B6: Regenerated cellulose, not raw bamboo fibre | C6: Soft/drapey positioning; wet strength, shrinkage and authenticity concerns | D6: Correct generic name, fabric weight and construction; independent composition and wash tests | E6: FTC requires rayon/viscose made from bamboo wording; no unsupported natural-antibacterial or eco claim | F6: R02; PDP_CA_bamboo; PDP_CA_protector
A7: Lyocell | B7: Regenerated cellulose; TENCEL is a trademark not generic composition proof | C7: Smooth hand and moisture-management positioning | D7: Verify licensed branding if used; composition, process evidence, pilling/shrink tests | E7: Low observed search coverage is not proof of an open market | F7: D06; LIVE_US_lyocell; LIVE_CA_lyocell; LIVE_UK_lyocell
A8: Linen / flax | B8: Flax fibre; linen-look cotton is not linen | C8: Textured premium positioning, wrinkles and initial roughness tradeoffs | D8: Proposed 150-180 GSM for testing, not universal optimal weight; seam slippage/shrink tests | E8: Higher material/capital exposure; source certified chain if claimed | F8: D01; LIVE_US_linen
A9: Silk / wool / down / latex / foam | B9: Distinct fibres/fills and regulatory pathways | C9: Specialized feel, insulation or support; not one comparable category | D9: Verify silk momme, wool content, down fill and foam density as applicable | E9: Separate filled-product, flammability, allergen and health-claim diligence | F9: R01; R11; LIVE_US_topper

Sheet Competitor observations
A1: country | B1: currency | C1: segment | D1: query | E1: position | F1: asin | G1: brand | H1: title | I1: size | J1: material_claim | K1: display_price | L1: rating | M1: ratings_approx | N1: sponsored_visible | O1: promotion_text | P1: query_match_screen | Q1: bought_badge | R1: source | S1: url | T1: research_date | U1: limitation
A2: CA | B2: CAD | C2: bamboo | D2: bamboo viscose sheet set | E2: 1 | F2: B0H9QD7RD5 | G2: Sasttie | H2: Sasttie White Silky-Soft Bamboo Sheets Queen Size 4-Piece, 100% Rayon Made from Bamboo 300TC, Cooling Sheet for Hot Sleepers, 16" Deep Pocket, Secure Corner Straps, Head Tag, Washable & Breathable | I2: Queen | J2: Regenerated cellulose or blend claim | K2: 49.99 | L2: 4.4 | M2: 44 | N2: =FALSE() -> FALSE | P2: =TRUE() -> TRUE | R2: LIVE_CA_bamboo | S2: https://www.amazon.ca/dp/B0H9QD7RD5 | T2: 2026-10-26 | U2: No fixed postal code; mixed variants; rating counts may be pooled/global and K/M rounded. No sales inference from badges.
A3: CA | B3: CAD | C3: bamboo | D3: bamboo viscose sheet set | E3: 2 | F3: B0CQ2ZWGNQ | G3: DECOLURE | H3: DECOLURE 100% Organic Viscose Derived from Bamboo Sheets Queen Size 6pcs - Ultra Soft & Luxuriously Cooling, 17" Deep Pocket, Double Stitching, Perfect for Hot Sleepers - Queen Bed Sheets (White) | I3: Queen | J3: Regenerated cellulose or blend claim | K3: 99.99 | L3: 4.4 | M3: 3300 | N3: =FALSE() -> FALSE | P3: =TRUE() -> TRUE | R3: LIVE_CA_bamboo | S3: https://www.amazon.ca/dp/B0CQ2ZWGNQ | T3: 2026-10-26 | U3: No fixed postal code; mixed variants; rating counts may be pooled/global and K/M rounded. No sales inference from badges.
A4: CA | B4: CAD | C4: bamboo | D4: bamboo viscose sheet set | E4: 3 | F4: B07YKCQBBL | G4: Bedsure | H4: Bedsure Sheet King Size - 4 Piece 100% Bamboo Rayon Sheet Set Dark Grey | I4: King | J4: Regenerated cellulose or blend claim | K4: 74.98 | L4: 4.3 | M4: 60900 | N4: =FALSE() -> FALSE | O4: Limited-time deal | List: $129.99 | List: | P4: =TRUE() -> TRUE | Q4: 100+ bought in past month | R4: LIVE_CA_bamboo | S4: https://www.amazon.ca/dp/B07YKCQBBL | T4: 2026-10-26 | U4: No fixed postal code; mixed variants; rating counts may be pooled/global and K/M rounded. No sales inference from badges.
A5: CA | B5: CAD | C5: bamboo | D5: bamboo viscose sheet set | E5: 4 | F5: B0H4LQTR5T | G5: Unresolved (title insufficient) | H5: Queen Size Sheet Set, Viscose Bamboo Sheets 4-Piece, 100% Viscose Derived from Bamboo, Hotel Luxury Silky & Cooling for Hot Sleepers, Deep Pocket Up to 17", Navy Blue | I5: Queen | J5: Regenerated cellulose or blend claim | K5: 79.99 | L5: 4.5 | M5: 26 | N5: =FALSE() -> FALSE | O5: Save 8% | Was: $87.39 | Was: | Save 5% on any 2 | P5: =TRUE() -> TRUE | R5: LIVE_CA_bamboo | S5: https://www.amazon.ca/dp/B0H4LQTR5T | T5: 2026-10-26 | U5: No fixed postal code; mixed variants; rating counts may be pooled/global and K/M rounded. No sales inference from badges.
A6: CA | B6: CAD | C6: bamboo | D6: bamboo viscose sheet set | E6: 5 | F6: B0C3R5NGGQ | G6: Unresolved (title insufficient) | H6: Cooling 100% Viscose Derived from Bamboo Sheet Set, Full, 4 Pc, White | I6: Full | J6: Regenerated cellulose or blend claim | K6: 59.99 | L6: 4.3 | M6: 108 | N6: =FALSE() -> FALSE | O6: Save 14% | List: $69.99 | List: | P6: =TRUE() -> TRUE | R6: LIVE_CA_bamboo | S6: https://www.amazon.ca/dp/B0C3R5NGGQ | T6: 2026-10-26 | U6: No fixed postal code; mixed variants; rating counts may be pooled/global and K/M rounded. No sales inference from badges.
A7: CA | B7: CAD | C7: bamboo | D7: bamboo viscose sheet set | E7: 6 | F7: B0FT7LV7PP | G7: Unresolved (title insufficient) | H7: Bamboo Viscose Sheet Set Queen Size, Cooling Sheets Bed Set 4pcs | I7: Queen | J7: Regenerated cellulose or blend claim | K7: 84.99 | L7: 4.4 | M7: 827 | N7: =FALSE() -> FALSE | O7: Save 5% on any 2 | P7: =TRUE() -> TRUE | R7: LIVE_CA_bamboo | S7: https://www.amazon.ca/dp/B0FT7LV7PP | T7: 2026-10-26 | U7: No fixed postal code; mixed variants; rating counts may be pooled/global and K/M rounded. No sales inference from badges.
A8: CA | B8: CAD | C8: bamboo | D8: bamboo viscose sheet set | E8: 7 | F8: B0CQ2XQF9N | G8: DECOLURE | H8: DECOLURE 100% Organic Viscose Derived from Bamboo Sheets King Size 6pcs - Ultra Soft & Luxuriously Cooling, 17" Deep Pocket, Double Stitching, Perfect for Hot Sleepers - King Bed Sheets (White) | I8: King | J8: Regenerated cellulose or blend claim | K8: 99.99 | L8: 4.4 | M8: 3300 | N8: =FALSE() -> FALSE | P8: =TRUE() -> TRUE | Q8: 50+ bought in past month | R8: LIVE_CA_bamboo | S8: https://www.amazon.ca/dp/B0CQ2XQF9N | T8: 2026-10-26 | U8: No fixed postal code; mixed variants; rating counts may be pooled/global and K/M rounded. No sales inference from badges.
A9: CA | B9: CAD | C9: bamboo | D9: bamboo viscose sheet set | E9: 8 | F9: B0H4LW9WBT | G9: Unresolved (title insufficient) | H9: Full Size Sheet Set, Viscose Bamboo Sheets 4-Piece, 100% Viscose Derived from Bamboo, Hotel Luxury Silky & Cooling for Hot Sleepers, Deep Pocket Up to 17", Grey | I9: Full | J9: Regenerated cellulose or blend claim | K9: 79.99 | L9: 4.5 | M9: 26 | N9: =FALSE() -> FALSE | O9: Save 11% | Was: $89.99 | Was: | Save 5% on any 2 | P9: =TRUE() -> TRUE | R9: LIVE_CA_bamboo | S9: https://www.amazon.ca/dp/B0H4LW9WBT | T9: 2026-10-26 | U9: No fixed postal code; mixed variants; rating counts may be pooled/global and K/M rounded. No sales inference from badges.
A10: CA | B10: CAD | C10: bamboo | D10: bamboo viscose sheet set | E10: 9 | F10: B0CQ33C286 | G10: DECOLURE | H10: DECOLURE 100% Organic Viscose Derived from Bamboo Sheets Queen Size 6pcs - Ultra Soft & Luxuriously Cooling, 17" Deep Pocket, Double Stitching, Perfect for Hot Sleepers - Queen Bed Sheets (Charcoal) | I10: Queen | J10: Regenerated cellulose or blend claim | K10: 99.99 | L10: 4.4 | M10: 3300 | N10: =FALSE() -> FALSE | P10: =TRUE() -> TRUE | R10: LIVE_CA_bamboo | S10: https://www.amazon.ca/dp/B0CQ33C286 | T10: 2026-10-26 | U10: No fixed postal code; mixed variants; rating counts may be pooled/global and K/M rounded. No sales inference from badges.
A11: CA | B11: CAD | C11: bamboo | D11: bamboo viscose sheet set | E11: 10 | F11: B0F1KK74XH | G11: Unresolved (title insufficient) | H11: Viviland Cooling Queen Sheets, 100% Viscose Derived Bamboo, Sky Blue | I11: Queen | J11: Regenerated cellulose or blend claim | K11: 66.49 | L11: 4.4 | M11: 155 | N11: =FALSE() -> FALSE | O11: Was: $69.99 | Was: | P11: =TRUE() -> TRUE | R11: LIVE_CA_bamboo | S11: https://www.amazon.ca/dp/B0F1KK74XH | T11: 2026-10-26 | U11: No fixed postal code; mixed variants; rating counts may be pooled/global and K/M rounded. No sales inference from badges.
A12: CA | B12: CAD | C12: bamboo | D12: bamboo viscose sheet set | E12: 11 | F12: B0CGZR147P | G12: Unresolved (title insufficient) | H12: Andency Bamboo Cooling Beige Sheet Set, 4pcs King Sheets for Hot Sleepers | I12: King | J12: Regenerated cellulose or blend claim | K12: 69.99 | L12: 4.4 | M12: 742 | N12: =FALSE() -> FALSE | O12: Was: $74.99 | Was: | P12: =TRUE() -> TRUE | R12: LIVE_CA_bamboo | S12: https://www.amazon.ca/dp/B0CGZR147P | T12: 2026-10-26 | U12: No fixed postal code; mixed variants; rating counts may be pooled/global and K/M rounded. No sales inference from badges.
A13: CA | B13: CAD | C13: bamboo | D13: bamboo viscose sheet set | E13: 12 | F13: B0GCZS2W4S | G13: Unresolved (title insufficient) | H13: Viviland Cooling Full Sheets, 100% Viscose Derived Bamboo, Coral | I13: Full | J13: Regenerated cellulose or blend claim | K13: 56.83 | L13: 4.4 | M13: 155 | N13: =FALSE() -> FALSE | O13: Was: $61.99 | Was: | P13: =TRUE() -> TRUE | R13: LIVE_CA_bamboo | S13: https://www.amazon.ca/dp/B0GCZS2W4S | T13: 2026-10-26 | U13: No fixed postal code; mixed variants; rating counts may be pooled/global and K/M rounded. No sales inference from badges.
A14: CA | B14: CAD | C14: bamboo | D14: bamboo viscose sheet set | E14: 13 | F14: B07XF1NLLW | G14: Unresolved (title insufficient) | H14: BAMPURE 100% Organic Bamboo Sheets King 4PC - Cooling Sheets Set | I14: King | J14: Regenerated cellulose or blend claim | K14: 104.99 | L14: 4.3 | M14: 7300 | N14: =FALSE() -> FALSE | O14: Save 50% on 1 when you buy 2 | P14: =TRUE() -> TRUE | R14: LIVE_CA_bamboo | S14: https://www.amazon.ca/dp/B07XF1NLLW | T14: 2026-10-26 | U14: No fixed postal code; mixed variants; rating counts may be pooled/global and K/M rounded. No sales inference from badges.
A15: CA | B15: CAD | C15: bamboo | D15: bamboo viscose sheet set | E15: 14 | F15: B0BZPZPGDC | G15: DECOLURE | H15: DECOLURE 100% Organic Bamboo Viscose Sheets Full Size 4 pcs - Ultra Soft & Luxuriously Cooling, 16" Deep Pocket, Double Stitching,Perfect for Hot Sleepers - Luxury Full Bed Sheets Set (Light Olive) | I15: Full | J15: Regenerated cellulose or blend claim | K15: 79.99 | L15: 4.4 | M15: 5800 | N15: =FALSE() -> FALSE | P15: =TRUE() -> TRUE | R15: LIVE_CA_bamboo | S15: https://www.amazon.ca/dp/B0BZPZPGDC | T15: 2026-10-26 | U15: No fixed postal code; mixed variants; rating counts may be pooled/global and K/M rounded. No sales inference from badges.
A16: CA | B16: CAD | C16: bamboo | D16: bamboo viscose sheet set | E16: 15 | F16: B0DR99Q37Y | G16: Bambaw | H16: Bambaw 100% Viscose Derived from Bamboo Sheets Queen Size Set – 4pcs Cooling Sheet Set, Super Soft Sheets Queen Size, Luxury Bed Sheets, Deep Pocket Fits Up to 16'' Mattresses (Charcoal) | I16: Queen | J16: Regenerated cellulose or blend claim | K16: 125.94 | L16: 4.3 | M16: 3000 | N16: =FALSE() -> FALSE | O16: Limited-time deal | Was: $139.95 | Was: | P16: =TRUE() -> TRUE | R16: LIVE_CA_bamboo | S16: https://www.amazon.ca/dp/B0DR99Q37Y | T16: 2026-10-26 | U16: No fixed postal code; mixed variants; rating counts may be pooled/global and K/M rounded. No sales inference from badges.
A17: CA | B17: CAD | C17: bamboo | D17: bamboo viscose sheet set | E17: 16 | F17: B09PYB9C45 | G17: Unresolved (title insufficient) | H17: ACCURATEX Bamboo Cooling Sheets for Hot Sleepers, King Size,Grey | I17: King | J17: Regenerated cellulose or blend claim | K17: 104.99 | L17: 4.3 | M17: 1000 | N17: =FALSE() -> FALSE | P17: =TRUE() -> TRUE | Q17: 50+ bought in past month | R17: LIVE_CA_bamboo | S17: https://www.amazon.ca/dp/B09PYB9C45 | T17: 2026-10-26 | U17: No fixed postal code; mixed variants; rating counts may be pooled/global and K/M rounded. No sales inference from badges.
A18: CA | B18: CAD | C18: bamboo | D18: bamboo viscose sheet set | E18: 17 | F18: B08MJW1N18 | G18: Unresolved (title insufficient) | H18: Bamboo Bay Luxury Bamboo Sheets Twin Size - 4 Piece Ultra Soft Twin Cooling Sheets for Hot Sleepers - 100% Organic Bamboo Twin Sheet Set Fits Up to 16" Deep Pocket - Eco Friendly - Twin - Light Blue | I18: Twin | J18: Regenerated cellulose or blend claim | K18: 46.99 | L18: 4.4 | M18: 2800 | N18: =FALSE() -> FALSE | P18: =TRUE() -> TRUE | R18: LIVE_CA_bamboo | S18: https://www.amazon.ca/dp/B08MJW1N18 | T18: 2026-10-26 | U18: No fixed postal code; mixed variants; rating counts may be pooled/global and K/M rounded. No sales inference from badges.
A19: CA | B19: CAD | C19: bamboo | D19: bamboo viscose sheet set | E19: 18 | F19: B0DL5NCTYF | G19: Unresolved (title insufficient) | H19: MR&HM Queen Sheets 4 Pieces, Rayon Derived from Bamboo Blend, Dark Grey | I19: Queen | J19: Regenerated cellulose or blend claim | K19: 58.99 | L19: 4.2 | M19: 617 | N19: =FALSE() -> FALSE | P19: =TRUE() -> TRUE | R19: LIVE_CA_bamboo | S19: https://www.amazon.ca/dp/B0DL5NCTYF | T19: 2026-10-26 | U19: No fixed postal code; mixed variants; rating counts may be pooled/global and K/M rounded. No sales inference from badges.
A20: CA | B20: CAD | C20: bamboo | D20: bamboo viscose sheet set | E20: 19 | F20: B0F2HW8MY2 | G20: Bambaw | H20: Bambaw 3pcs Set - 100% Viscose Derived from Bamboo Duvet Cover Queen Size Set, Duvet Cover Cooling for Hot Sleepers, Super Soft & Breathable, OEKO-TEX® STANDARD 100 Certified, No Comforter (Sand) | I20: Queen | J20: Regenerated cellulose or blend claim | K20: 125.95 | L20: 4.5 | M20: 256 | N20: =FALSE() -> FALSE | P20: =TRUE() -> TRUE | R20: LIVE_CA_bamboo | S20: https://www.amazon.ca/dp/B0F2HW8MY2 | T20: 2026-10-26 | U20: No fixed postal code; mixed variants; rating counts may be pooled/global and K/M rounded. No sales inference from badges.
A21: CA | B21: CAD | C21: bamboo | D21: bamboo viscose sheet set | E21: 20 | F21: B0GVDDCJVT | G21: Unresolved (title insufficient) | H21: 100% Bamboo Viscose Twin XL Size Sheets Set, 400 Thread Count, 3 Pieces | I21: Twin XL | J21: Regenerated cellulose or blend claim | L21: 4.4 | M21: 82 | N21: =FALSE() -> FALSE | P21: =TRUE() -> TRUE | R21: LIVE_CA_bamboo | S21: https://www.amazon.ca/dp/B0GVDDCJVT | T21: 2026-10-26 | U21: No fixed postal code; mixed variants; rating counts may be pooled/global and K/M rounded. No sales inference from badges.
A22: CA | B22: CAD | C22: bamboo | D22: bamboo viscose sheet set | E22: 21 | F22: B0G34XJ831 | G22: Unresolved (title insufficient) | H22: 100% Bamboo Viscose Cooling Fitted Sheet Queen Olive Green and Pillowcases | I22: Queen | J22: Regenerated cellulose or blend claim | K22: 59.99 | L22: 4.1 | M22: 36 | N22: =FALSE() -> FALSE | P22: =TRUE() -> TRUE | R22: LIVE_CA_bamboo | S22: https://www.amazon.ca/dp/B0G34XJ831 | T22: 2026-10-26 | U22: No fixed postal code; mixed variants; rating counts may be pooled/global and K/M rounded. No sales inference from badges.
A23: CA | B23: CAD | C23: bamboo | D23: bamboo viscose sheet set | E23: 22 | F23: B0DJTGXZQF | G23: Unresolved (title insufficient) | H23: Luxury Viscose from Bamboo Bath Towel Set, Set of 6, Graphite | I23: Unspecified | J23: Regenerated cellulose or blend claim | K23: 89.99 | L23: 4.3 | M23: 186 | N23: =FALSE() -> FALSE | P23: =TRUE() -> TRUE | R23: LIVE_CA_bamboo | S23: https://www.amazon.ca/dp/B0DJTGXZQF | T23: 2026-10-26 | U23: No fixed postal code; mixed variants; rating counts may be pooled/global and K/M rounded. No sales inference from badges.
A24: CA | B24: CAD | C24: bamboo | D24: bamboo viscose sheet set | E24: 23 | F24: B01M16WBW1 | G24: Unresolved (title insufficient) | H24: Queen Size 4 Piece Sheet Set - Comfy Breathable & Cooling Sheets - White | I24: Queen | J24: Not resolved from title | K24: 25.49 | L24: 4.4 | M24: 444800 | N24: =FALSE() -> FALSE | O24: List: $39.99 | List: | P24: =TRUE() -> TRUE | Q24: 4K+ bought in past month | R24: LIVE_CA_bamboo | S24: https://www.amazon.ca/dp/B01M16WBW1 | T24: 2026-10-26 | U24: No fixed postal code; mixed variants; rating counts may be pooled/global and K/M rounded. No sales inference from badges.
A25: CA | B25: CAD | C25: bamboo | D25: bamboo viscose sheet set | E25: 24 | F25: B0GTYZS5B9 | G25: Unresolved (title insufficient) | H25: QUTOOL 100% Viscose Made from Bamboo Queen Sheet Sets, 4PC Cooling Bed Sheets with Extra Deep Pocket up to 18'', Hotel Luxury Silky Bedding for Hot Sleepers, Breathable, Light Gray | I25: Queen | J25: Regenerated cellulose or blend claim | K25: 101.59 | L25: 4.5 | M25: 49 | N25: =FALSE() -> FALSE | P25: =TRUE() -> TRUE | R25: LIVE_CA_bamboo | S25: https://www.amazon.ca/dp/B0GTYZS5B9 | T25: 2026-10-26 | U25: No fixed postal code; mixed variants; rating counts may be pooled/global and K/M rounded. No sales inference from badges.
A26: CA | B26: CAD | C26: bamboo | D26: bamboo viscose sheet set | E26: 25 | F26: B0FDB3L3Y3 | G26: Unresolved (title insufficient) | H26: ROYALE LINENS Bamboo Viscose Queen Sheet Set - Cooling Bed Sheet Set - 1 Fitted, 1 Flat & 2 Pillowcase - Fits Up to 16" - Organic Viscose Derived from Bamboo - Bedding Sheet Set (Queen, Nimbus Cloud) | I26: Queen | J26: Regenerated cellulose or blend claim | K26: 42.99 | L26: 4.2 | M26: 254 | N26: =FALSE() -> FALSE | P26: =TRUE() -> TRUE | R26: LIVE_CA_bamboo | S26: https://www.amazon.ca/dp/B0FDB3L3Y3 | T26: 2026-10-26 | U26: No fixed postal code; mixed variants; rating counts may be pooled/global and K/M rounded. No sales inference from badges.
A27: CA | B27: CAD | C27: bamboo | D27: bamboo viscose sheet set | E27: 26 | F27: B0DS21FNX6 | G27: Unresolved (title insufficient) | H27: 100% Viscose Derived from Bamboo Fitted Sheet Set 3 Piece - 2 Pillowcase 1 Fitted Sheet with 16" Deep Pocket, Hotel Luxury Silky Bedding, Ultra Soft, Cooling for Hot Sleepers(Blue Queen) | I27: Queen | J27: Regenerated cellulose or blend claim | K27: 33.8 | L27: 4.2 | M27: 51 | N27: =FALSE() -> FALSE | P27: =TRUE() -> TRUE | R27: LIVE_CA_bamboo | S27: https://www.amazon.ca/dp/B0DS21FNX6 | T27: 2026-10-26 | U27: No fixed postal code; mixed variants; rating counts may be pooled/global and K/M rounded. No sales inference from badges.
A28: CA | B28: CAD | C28: bamboo | D28: bamboo viscose sheet set | E28: 27 | F28: B0FXWFJ9C1 | G28: Unresolved (title insufficient) | H28: 100% Bamboo Rayon Cooling Sheets Twin Set Dark Gray Silky Soft Bedding | I28: Twin | J28: Regenerated cellulose or blend claim | K28: 74.99 | L28: 4.7 | M28: 12 | N28: =FALSE() -> FALSE | P28: =TRUE() -> TRUE | R28: LIVE_CA_bamboo | S28: https://www.amazon.ca/dp/B0FXWFJ9C1 | T28: 2026-10-26 | U28: No fixed postal code; mixed variants; rating counts may be pooled/global and K/M rounded. No sales inference from badges.
A29: CA | B29: CAD | C29: bamboo | D29: bamboo viscose sheet set | E29: 28 | F29: B0BYPL2QXC | G29: Unresolved (title insufficient) | H29: Bare Home 100% Rayon Made from Bamboo Sheet Set (Full, Grey) | I29: Full | J29: Regenerated cellulose or blend claim | K29: 98.99 | L29: 4.4 | M29: 870 | N29: =FALSE() -> FALSE | O29: Was: $105.99 | Was: | P29: =TRUE() -> TRUE | R29: LIVE_CA_bamboo | S29: https://www.amazon.ca/dp/B0BYPL2QXC | T29: 2026-10-26 | U29: No fixed postal code; mixed variants; rating counts may be pooled/global and K/M rounded. No sales inference from badges.
A30: CA | B30: CAD | C30: bamboo | D30: bamboo viscose sheet set | E30: 29 | F30: B0CGX4G67T | G30: Unresolved (title insufficient) | H30: HENGWEITEXT Bamboo Sheets King Bed Sheet Set,Textured 60% Viscose from Bamboo 40% Cotton Sheets Set King Size,Wrinkle Free 4 Piece Shrinkage and Fade Resistant | I30: King | J30: Regenerated cellulose or blend claim | K30: 23.99 | L30: 3 | M30: 5 | N30: =FALSE() -> FALSE | P30: =TRUE() -> TRUE | R30: LIVE_CA_bamboo | S30: https://www.amazon.ca/dp/B0CGX4G67T | T30: 2026-10-26 | U30: No fixed postal code; mixed variants; rating counts may be pooled/global and K/M rounded. No sales inference from badges.
A31: CA | B31: CAD | C31: bamboo | D31: bamboo viscose sheet set | E31: 30 | F31: B0H3BVJ68C | G31: Bambaw | H31: Bambaw 100% Viscose Derived from Bamboo Fitted Sheet Twin XL – Twin XL Single Fitted Sheet, Cooling, Soft & Breathable, Crisp & Smooth Feel, Deep Pocket Fits Up to 15" Mattresses (White) | I31: Twin XL | J31: Regenerated cellulose or blend claim | K31: 65.95 | L31: 4.4 | M31: 871 | N31: =FALSE() -> FALSE | P31: =TRUE() -> TRUE | R31: LIVE_CA_bamboo | S31: https://www.amazon.ca/dp/B0H3BVJ68C | T31: 2026-10-26 | U31: No fixed postal code; mixed variants; rating counts may be pooled/global and K/M rounded. No sales inference from badges.
A32: CA | B32: CAD | C32: bamboo | D32: bamboo viscose sheet set | E32: 31 | F32: B096BM64KC | G32: Pure Bamboo | H32: PURE BAMBOO Sheets 100% Genuine Bamboo Viscose, King, Pesto | I32: King | J32: Regenerated cellulose or blend claim | K32: 164.99 | L32: 4.3 | M32: 20600 | N32: =FALSE() -> FALSE | P32: =TRUE() -> TRUE | R32: LIVE_CA_bamboo | S32: https://www.amazon.ca/dp/B096BM64KC | T32: 2026-10-26 | U32: No fixed postal code; mixed variants; rating counts may be pooled/global and K/M rounded. No sales inference from badges.
A33: CA | B33: CAD | C33: bamboo | D33: bamboo viscose sheet set | E33: 32 | F33: B0FCZRHF11 | G33: Unresolved (title insufficient) | H33: 100% Organically Grown Bamboo Viscose Full Sheet Set, 4Pcs, Light Blue | I33: Full | J33: Regenerated cellulose or blend claim | K33: 93.57 | N33: =FALSE() -> FALSE | P33: =TRUE() -> TRUE | R33: LIVE_CA_bamboo | S33: https://www.amazon.ca/dp/B0FCZRHF11 | T33: 2026-10-26 | U33: No fixed postal code; mixed variants; rating counts may be pooled/global and K/M rounded. No sales inference from badges.
A34: CA | B34: CAD | C34: bamboo | D34: bamboo viscose sheet set | E34: 33 | F34: B0DZHJHSNX | G34: Unresolved (title insufficient) | H34: 18-24 Inch Extra Deep Pocket Queen Size Sheets Set, 100% Viscose Derived from Bamboo Sheets Queen Size Bed Sheets, 4Pcs Soft Forest Green Cooling Sheets for Hot Sleepers | I34: Queen | J34: Regenerated cellulose or blend claim | K34: 108.51 | L34: 4.4 | M34: 125 | N34: =FALSE() -> FALSE | P34: =TRUE() -> TRUE | R34: LIVE_CA_bamboo | S34: https://www.amazon.ca/dp/B0DZHJHSNX | T34: 2026-10-26 | U34: No fixed postal code; mixed variants; rating counts may be pooled/global and K/M rounded. No sales inference from badges.
A35: CA | B35: CAD | C35: bamboo | D35: bamboo viscose sheet set | E35: 34 | F35: B07V49Z6H6 | G35: Hotel Sheets Direct | H35: Hotel Sheets Direct Bamboo Bed Sheet Set - 100% Viscose from Bamboo Sheet Set, Cooling, Thermoregulating, Hypoallergenic (Queen, Light Pink) | I35: Queen | J35: Regenerated cellulose or blend claim | K35: 110.99 | L35: 4.3 | M35: 14100 | N35: =FALSE() -> FALSE | P35: =TRUE() -> TRUE | R35: LIVE_CA_bamboo | S35: https://www.amazon.ca/dp/B07V49Z6H6 | T35: 2026-10-26 | U35: No fixed postal code; mixed variants; rating counts may be pooled/global and K/M rounded. No sales inference from badges.
A36: CA | B36: CAD | C36: bamboo | D36: bamboo viscose sheet set | E36: 35 | F36: B0DSZMTCL2 | G36: JSD | H36: JSD Dusty Pink 100% Viscose Derived from Bamboo Queen Sheet Set, Cooling Sheets for Hot Sleepers, 300TC Sateen Weave Breathable Silky, Deep Pocket with Corner Straps, Oeko-Tex Certified | I36: Queen | J36: Regenerated cellulose or blend claim | K36: 80.52 | L36: 4.4 | M36: 285 | N36: =FALSE() -> FALSE | O36: Was: $99.76 | Was: | P36: =TRUE() -> TRUE | R36: LIVE_CA_bamboo | S36: https://www.amazon.ca/dp/B0DSZMTCL2 | T36: 2026-10-26 | U36: No fixed postal code; mixed variants; rating counts may be pooled/global and K/M rounded. No sales inference from badges.
A37: CA | B37: CAD | C37: bamboo | D37: bamboo viscose sheet set | E37: 36 | F37: B08F3DFWJM | G37: Unresolved (title insufficient) | H37: Gökotta Queen Bed Sheets 4 Piece, 100% FSC® Certified Bamboo, Cooling | I37: Queen | J37: Regenerated cellulose or blend claim | K37: 139.99 | L37: 4.4 | M37: 2700 | N37: =FALSE() -> FALSE | O37: You pay $129.99 with coupon | P37: =TRUE() -> TRUE | R37: LIVE_CA_bamboo | S37: https://www.amazon.ca/dp/B08F3DFWJM | T37: 2026-10-26 | U37: No fixed postal code; mixed variants; rating counts may be pooled/global and K/M rounded. No sales inference from badges.
A38: CA | B38: CAD | C38: bamboo | D38: bamboo viscose sheet set | E38: 37 | F38: B0F6J9CMW4 | G38: Unresolved (title insufficient) | H38: 100% Organic Bamboo 4 Pcs Bed Sheet Set – Cooling Sheets for Hot Sleepers | Ultra Soft, Breathable | 17" Deep Pocket (Silver Mist, Queen Size 4 pcs Set) | I38: Queen | J38: Regenerated cellulose or blend claim | K38: 73.97 | L38: 4.3 | M38: 48 | N38: =FALSE() -> FALSE | P38: =TRUE() -> TRUE | R38: LIVE_CA_bamboo | S38: https://www.amazon.ca/dp/B0F6J9CMW4 | T38: 2026-10-26 | U38: No fixed postal code; mixed variants; rating counts may be pooled/global and K/M rounded. No sales inference from badges.
A39: CA | B39: CAD | C39: bamboo | D39: bamboo viscose sheet set | E39: 38 | F39: B09RJSYCKR | G39: Unresolved (title insufficient) | H39: Bella Coterie Luxury Bamboo Viscose Split King Sheet Set, Organically Grown | I39: King | J39: Regenerated cellulose or blend claim | L39: 4.4 | M39: 6200 | N39: =FALSE() -> FALSE | P39: =TRUE() -> TRUE | R39: LIVE_CA_bamboo | S39: https://www.amazon.ca/dp/B09RJSYCKR | T39: 2026-10-26 | U39: No fixed postal code; mixed variants; rating counts may be pooled/global and K/M rounded. No sales inference from badges.
A40: CA | B40: CAD | C40: bamboo | D40: bamboo viscose sheet set | E40: 39 | F40: B0DPLJ4BN4 | G40: Unresolved (title insufficient) | H40: BAMPURE 100% Organic Bamboo Sheets Queen 4PC - Cooling Sheets Set | I40: Queen | J40: Regenerated cellulose or blend claim | K40: 72.99 | L40: 3.3 | M40: 18 | N40: =FALSE() -> FALSE | O40: List: $89.99 | List: | P40: =TRUE() -> TRUE | R40: LIVE_CA_bamboo | S40: https://www.amazon.ca/dp/B0DPLJ4BN4 | T40: 2026-10-26 | U40: No fixed postal code; mixed variants; rating counts may be pooled/global and K/M rounded. No sales inference from badges.
A41: CA | B41: CAD | C41: bamboo | D41: bamboo viscose sheet set | E41: 40 | F41: B0C9LS5H2T | G41: DECOLURE | H41: DECOLURE Cooling Sheets Queen Set 4pcs - Luxurious & Ultra-Soft Bamboo Viscose Microfiber Queen Size Bed Sheets - Cooling (Navy) | I41: Queen | J41: Synthetic or blend; verify composition | L41: 4.1 | M41: 1000 | N41: =FALSE() -> FALSE | P41: =TRUE() -> TRUE | R41: LIVE_CA_bamboo | S41: https://www.amazon.ca/dp/B0C9LS5H2T | T41: 2026-10-26 | U41: No fixed postal code; mixed variants; rating counts may be pooled/global and K/M rounded. No sales inference from badges.
A42: CA | B42: CAD | C42: bamboo | D42: bamboo viscose sheet set | E42: 41 | F42: B0B8JLLT45 | G42: Unresolved (title insufficient) | H42: DOZ Sheet Set, 100% Viscose derived from Bamboo, Organically Grown, Buttery Soft, Cooling Sheets, High GSM, Deep Pockets - 3 Piece - 2 Pillowcases 1 Fitted Sheet (Forest, Queen) | I42: Queen | J42: Regenerated cellulose or blend claim | K42: 90.42 | L42: 4.4 | M42: 213 | N42: =FALSE() -> FALSE | P42: =TRUE() -> TRUE | R42: LIVE_CA_bamboo | S42: https://www.amazon.ca/dp/B0B8JLLT45 | T42: 2026-10-26 | U42: No fixed postal code; mixed variants; rating counts may be pooled/global and K/M rounded. No sales inference from badges.
A43: CA | B43: CAD | C43: bamboo | D43: bamboo viscose sheet set | E43: 42 | F43: B0H264JWBK | G43: Unresolved (title insufficient) | H43: DREAMCARE 100% Rayon Bamboo Sheets California King - 4pc Cooling Sheets | I43: California King | J43: Regenerated cellulose or blend claim | K43: 92.82 | L43: 4.7 | M43: 1300 | N43: =FALSE() -> FALSE | P43: =TRUE() -> TRUE | R43: LIVE_CA_bamboo | S43: https://www.amazon.ca/dp/B0H264JWBK | T43: 2026-10-26 | U43: No fixed postal code; mixed variants; rating counts may be pooled/global and K/M rounded. No sales inference from badges.
A44: CA | B44: CAD | C44: bamboo | D44: bamboo viscose sheet set | E44: 43 | F44: B09KXYHH13 | G44: Unresolved (title insufficient) | H44: CAROMIO King Size Sheets Rayon Derived from Bamboo, Cooling Bed Sheets | I44: King | J44: Regenerated cellulose or blend claim | L44: 4.2 | M44: 1000 | N44: =FALSE() -> FALSE | P44: =TRUE() -> TRUE | R44: LIVE_CA_bamboo | S44: https://www.amazon.ca/dp/B09KXYHH13 | T44: 2026-10-26 | U44: No fixed postal code; mixed variants; rating counts may be pooled/global and K/M rounded. No sales inference from badges.
A45: CA | B45: CAD | C45: bamboo | D45: bamboo viscose sheet set | E45: 44 | F45: B0B8JHBPJ4 | G45: DOZ by SIJO | H45: DOZ by SIJO 100% Organic Bamboo Sheet Set, Buttery Soft, Cooling for Hot Sleepers, Silky Breathable, Oeko-TEX, High GSM, 16" Deep Pockets - 3pc - 2 Pillowcases 1 Fitted Sheet (Dove, Queen) | I45: Queen | J45: Regenerated cellulose or blend claim | K45: 119.7 | L45: 4.4 | M45: 435 | N45: =FALSE() -> FALSE | P45: =TRUE() -> TRUE | R45: LIVE_CA_bamboo | S45: https://www.amazon.ca/dp/B0B8JHBPJ4 | T45: 2026-10-26 | U45: No fixed postal code; mixed variants; rating counts may be pooled/global and K/M rounded. No sales inference from badges.
A46: CA | B46: CAD | C46: bamboo | D46: bamboo viscose sheet set | E46: 45 | F46: B07Y8TTK9B | G46: Hotel Sheets Direct | H46: Hotel Sheets Direct 4 Piece Bed Sheet Set Queen Size, 100% Viscose Derived from Bamboo Sheets Set with 2 Pillowcases, Cooling & Breathable Luxury Bedding, Moisture-Wicking & Silky Soft, Burgundy | I46: Queen | J46: Regenerated cellulose or blend claim | K46: 110.99 | L46: 4.3 | M46: 617 | N46: =FALSE() -> FALSE | P46: =TRUE() -> TRUE | R46: LIVE_CA_bamboo | S46: https://www.amazon.ca/dp/B07Y8TTK9B | T46: 2026-10-26 | U46: No fixed postal code; mixed variants; rating counts may be pooled/global and K/M rounded. No sales inference from badges.
A47: CA | B47: CAD | C47: bamboo | D47: bamboo viscose sheet set | E47: 46 | F47: B0HFQY2FF3 | G47: Unresolved (title insufficient) | H47: Bamboo Viscose Grounding Sheets, Silver Infused Cooling Breathable for Hot Sleeper | I47: Unspecified | J47: Regenerated cellulose or blend claim | K47: 79.98 | L47: 4.2 | M47: 124 | N47: =FALSE() -> FALSE | P47: =TRUE() -> TRUE | R47: LIVE_CA_bamboo | S47: https://www.amazon.ca/dp/B0HFQY2FF3 | T47: 2026-10-26 | U47: No fixed postal code; mixed variants; rating counts may be pooled/global and K/M rounded. No sales inference from badges.
A48: CA | B48: CAD | C48: bamboo | D48: bamboo viscose sheet set | E48: 47 | F48: B01DX29P8O | G48: Unresolved (title insufficient) | H48: Abripedic 100% Bamboo 600 Thread Count King Size Solid Ivory Sheet set, Super Soft & Cool Bamboo Viscose Sheets | I48: King | J48: Regenerated cellulose or blend claim | K48: 147.99 | L48: 4.7 | M48: 12 | N48: =FALSE() -> FALSE | P48: =TRUE() -> TRUE | R48: LIVE_CA_bamboo | S48: https://www.amazon.ca/dp/B01DX29P8O | T48: 2026-10-26 | U48: No fixed postal code; mixed variants; rating counts may be pooled/global and K/M rounded. No sales inference from badges.
A49: CA | B49: CAD | C49: bamboo | D49: bamboo viscose sheet set | E49: 48 | F49: B0D4ZPFKB3 | G49: Unresolved (title insufficient) | H49: Aibaser Viscose from Bamboo and Cotton Bath Towels Set of 2-35x70 Inch Ultra Soft, Highly Absorbent Large Shower Towels for Bathroom, Spa & Gym (Green) | I49: Unspecified | J49: Regenerated cellulose or blend claim | K49: 41.11 | L49: 4.2 | M49: 3400 | N49: =FALSE() -> FALSE | P49: =TRUE() -> TRUE | R49: LIVE_CA_bamboo | S49: https://www.amazon.ca/dp/B0D4ZPFKB3 | T49: 2026-10-26 | U49: No fixed postal code; mixed variants; rating counts may be pooled/global and K/M rounded. No sales inference from badges.
A50: CA | B50: CAD | C50: comforter | D50: comforter set | E50: 1 | F50: B0DCCZRNFZ | G50: Unresolved (title insufficient) | H50: Comforter Double Size, 7 Piece Bed in a Bag Set with Sheets - Beige | I50: Double | J50: Not resolved from title | K50: 31.99 | L50: 4.3 | M50: 4600 | N50: =FALSE() -> FALSE | O50: Save 43% | Was: $56.51 | Was: | P50: =TRUE() -> TRUE | Q50: 50+ bought in past month | R50: LIVE_CA_comforter | S50: https://www.amazon.ca/dp/B0DCCZRNFZ | T50: 2026-10-26 | U50: No fixed postal code; mixed variants; rating counts may be pooled/global and K/M rounded. No sales inference from badges.
A51: CA | B51: CAD | C51: comforter | D51: comforter set | E51: 2 | F51: B0C1ZZHWC7 | G51: Unresolved (title insufficient) | H51: All Season Queen Size Comforter Set 3 PCs, Premium 350GSM Soft Quilted Down Alternative Comforter+2 Pillow Shams with Corner Tabs-Machine Washable Dark Grey, Queen（88 * 88） | I51: Queen | J51: Not resolved from title | K51: 35.9 | L51: 4.6 | M51: 2200 | N51: =FALSE() -> FALSE | O51: Limited-time deal | List: $39.89 | List: | P51: =TRUE() -> TRUE | Q51: 900+ bought in past month | R51: LIVE_CA_comforter | S51: https://www.amazon.ca/dp/B0C1ZZHWC7 | T51: 2026-10-26 | U51: No fixed postal code; mixed variants; rating counts may be pooled/global and K/M rounded. No sales inference from badges.
A52: CA | B52: CAD | C52: comforter | D52: comforter set | E52: 3 | F52: B0DCDMFTRX | G52: Unresolved (title insufficient) | H52: Comforter Queen Size, 7 Piece Bed in a Bag Set with Sheets, Pintuck - Beige | I52: Queen | J52: Not resolved from title | K52: 43.99 | L52: 4.3 | M52: 4600 | N52: =FALSE() -> FALSE | O52: Was: $67.99 | Was: | P52: =TRUE() -> TRUE | Q52: 100+ bought in past month | R52: LIVE_CA_comforter | S52: https://www.amazon.ca/dp/B0DCDMFTRX | T52: 2026-10-26 | U52: No fixed postal code; mixed variants; rating counts may be pooled/global and K/M rounded. No sales inference from badges.
A53: CA | B53: CAD | C53: comforter | D53: comforter set | E53: 4 | F53: B0C27QM69F | G53: Unresolved (title insufficient) | H53: HYMOKEGE Queen Comforter Set Seersucker 7 Pieces, All Season Luxury Bed in a Bag for Bedroom, Bedding Set with Comforters, Sheets, Pillowcases & Shams, Dark Grey | I53: Queen | J53: Not resolved from title | K53: 52.19 | L53: 4.2 | M53: 1800 | N53: =FALSE() -> FALSE | O53: Limited-time deal | Was: $57.99 | Was: | P53: =TRUE() -> TRUE | Q53: 400+ bought in past month | R53: LIVE_CA_comforter | S53: https://www.amazon.ca/dp/B0C27QM69F | T53: 2026-10-26 | U53: No fixed postal code; mixed variants; rating counts may be pooled/global and K/M rounded. No sales inference from badges.
A54: CA | B54: CAD | C54: comforter | D54: comforter set | E54: 5 | F54: B0CGLP3QSF | G54: Bedsure | H54: Bedsure Prewashed Queen Comforter Set - Ultra-Soft Bedding 3 Pieces Beige | I54: Queen | J54: Not resolved from title | K54: 43.99 | L54: 4.3 | M54: 11600 | N54: =FALSE() -> FALSE | O54: List: $47.99 | List: | P54: =TRUE() -> TRUE | Q54: 600+ bought in past month | R54: LIVE_CA_comforter | S54: https://www.amazon.ca/dp/B0CGLP3QSF | T54: 2026-10-26 | U54: No fixed postal code; mixed variants; rating counts may be pooled/global and K/M rounded. No sales inference from badges.
A55: CA | B55: CAD | C55: comforter | D55: comforter set | E55: 6 | F55: B0GSQJLKL5 | G55: Unresolved (title insufficient) | H55: JOLLYVOGUE Queen Comforter Set 7 Pieces Dark Green, Cationic Dyeing Bed in a Bag Queen, Double-Tone Bedding Set with Down Alternative Comforter, Sheets, Pillowcases & Shams | I55: Queen | J55: Not resolved from title | K55: 48.59 | L55: 4.4 | M55: 214 | N55: =FALSE() -> FALSE | O55: Was: $53.99 | Was: | P55: =TRUE() -> TRUE | Q55: 100+ bought in past month | R55: LIVE_CA_comforter | S55: https://www.amazon.ca/dp/B0GSQJLKL5 | T55: 2026-10-26 | U55: No fixed postal code; mixed variants; rating counts may be pooled/global and K/M rounded. No sales inference from badges.
A56: CA | B56: CAD | C56: comforter | D56: comforter set | E56: 7 | F56: B0C7K5BTZV | G56: Unresolved (title insufficient) | H56: Maple&Stone Double Bed Comforter Set, 7 Pieces Bed in a Bag Full Black | I56: Full | J56: Not resolved from title | K56: 59.99 | L56: 4.5 | M56: 3400 | N56: =FALSE() -> FALSE | P56: =TRUE() -> TRUE | Q56: 100+ bought in past month | R56: LIVE_CA_comforter | S56: https://www.amazon.ca/dp/B0C7K5BTZV | T56: 2026-10-26 | U56: No fixed postal code; mixed variants; rating counts may be pooled/global and K/M rounded. No sales inference from badges.
A57: CA | B57: CAD | C57: comforter | D57: comforter set | E57: 8 | F57: B0GJCF2LY3 | G57: Unresolved (title insufficient) | H57: BEDELITE Fluffy Queen Comforter Set, Grey Fleece Bed Set 3 Pieces | I57: Queen | J57: Not resolved from title | K57: 49.99 | L57: 4.4 | M57: 456 | N57: =FALSE() -> FALSE | O57: Limited-time deal | Was: $55.99 | Was: | P57: =TRUE() -> TRUE | Q57: 200+ bought in past month | R57: LIVE_CA_comforter | S57: https://www.amazon.ca/dp/B0GJCF2LY3 | T57: 2026-10-26 | U57: No fixed postal code; mixed variants; rating counts may be pooled/global and K/M rounded. No sales inference from badges.
A58: CA | B58: CAD | C58: comforter | D58: comforter set | E58: 9 | F58: B0BLVH5YX3 | G58: Unresolved (title insufficient) | H58: HEVUMYI 7-Piece Queen Comforter Set, Dark Gray | I58: Queen | J58: Not resolved from title | K58: 59.99 | L58: 4.3 | M58: 11900 | N58: =FALSE() -> FALSE | P58: =TRUE() -> TRUE | Q58: 500+ bought in past month | R58: LIVE_CA_comforter | S58: https://www.amazon.ca/dp/B0BLVH5YX3 | T58: 2026-10-26 | U58: No fixed postal code; mixed variants; rating counts may be pooled/global and K/M rounded. No sales inference from badges.
A59: CA | B59: CAD | C59: comforter | D59: comforter set | E59: 10 | F59: B0DFPMJWXZ | G59: Unresolved (title insufficient) | H59: MUXHOMO 7 Pieces Queen Comforter Set, Reversible Bed in a Bag Queen Size, All Season Queen Bedding Set with Comforter, Flat Sheet, Fitted Sheet, Pillowcases & Shams, Red & Black | I59: Queen | J59: Not resolved from title | K59: 59.99 | L59: 4.6 | M59: 797 | N59: =FALSE() -> FALSE | P59: =TRUE() -> TRUE | Q59: 400+ bought in past month | R59: LIVE_CA_comforter | S59: https://www.amazon.ca/dp/B0DFPMJWXZ | T59: 2026-10-26 | U59: No fixed postal code; mixed variants; rating counts may be pooled/global and K/M rounded. No sales inference from badges.
A60: CA | B60: CAD | C60: comforter | D60: comforter set | E60: 11 | F60: B0DKCTQ978 | G60: Wake In Cloud | H60: Wake In Cloud - Floral Comforter Set, Coquette Cottagecore Aesthetic Flower Shabby Chic Pattern for Women Teen Girls, Soft Lightweight Bedding, 3 Pieces, White Blue, Full Size | I60: Full | J60: Not resolved from title | K60: 44.99 | L60: 4.3 | M60: 773 | N60: =FALSE() -> FALSE | P60: =TRUE() -> TRUE | Q60: 50+ bought in past month | R60: LIVE_CA_comforter | S60: https://www.amazon.ca/dp/B0DKCTQ978 | T60: 2026-10-26 | U60: No fixed postal code; mixed variants; rating counts may be pooled/global and K/M rounded. No sales inference from badges.
A61: CA | B61: CAD | C61: comforter | D61: comforter set | E61: 12 | F61: B0CGLPC42G | G61: Bedsure | H61: Bedsure Prewashed King Comforter Set - Ultra-Soft Bedding 3 Pieces Beige | I61: King | J61: Not resolved from title | K61: 52.99 | L61: 4.3 | M61: 11600 | N61: =FALSE() -> FALSE | O61: List: $59.99 | List: | P61: =TRUE() -> TRUE | Q61: 300+ bought in past month | R61: LIVE_CA_comforter | S61: https://www.amazon.ca/dp/B0CGLPC42G | T61: 2026-10-26 | U61: No fixed postal code; mixed variants; rating counts may be pooled/global and K/M rounded. No sales inference from badges.
A62: CA | B62: CAD | C62: comforter | D62: comforter set | E62: 13 | F62: B0CJJT1PT6 | G62: Unresolved (title insufficient) | H62: Queen Comforter Set-7 Pieces Soft Prewashed Bed in a Bag Queen Bedding Sets | I62: Queen | J62: Not resolved from title | K62: 71.99 | L62: 4.5 | M62: 1900 | N62: =FALSE() -> FALSE | O62: Limited-time deal | List: $79.99 | List: | Save 5% on any 2 | P62: =TRUE() -> TRUE | Q62: 100+ bought in past month | R62: LIVE_CA_comforter | S62: https://www.amazon.ca/dp/B0CJJT1PT6 | T62: 2026-10-26 | U62: No fixed postal code; mixed variants; rating counts may be pooled/global and K/M rounded. No sales inference from badges.
A63: CA | B63: CAD | C63: comforter | D63: comforter set | E63: 14 | F63: B0CQS8N71F | G63: Unresolved (title insufficient) | H63: JOLLYVOGUE Queen Comforter Set 7 Pieces - Black Bed in a Bag Ultra-Soft - Goose Down Alternative - Premium 1800 Series with Comforter, Sheets, Shams & Pillowcases | I63: Queen | J63: Not resolved from title | K63: 59.99 | L63: 4.3 | M63: 1100 | N63: =FALSE() -> FALSE | P63: =TRUE() -> TRUE | Q63: 600+ bought in past month | R63: LIVE_CA_comforter | S63: https://www.amazon.ca/dp/B0CQS8N71F | T63: 2026-10-26 | U63: No fixed postal code; mixed variants; rating counts may be pooled/global and K/M rounded. No sales inference from badges.
A64: CA | B64: CAD | C64: comforter | D64: comforter set | E64: 15 | F64: B0DD436JG2 | G64: Unresolved (title insufficient) | H64: YIKUSH Pink Queen Comforter Set 3 Piece, Ruffled Queen Bedding Set | I64: Queen | J64: Not resolved from title | K64: 54.99 | L64: 4.4 | M64: 164 | N64: =FALSE() -> FALSE | P64: =TRUE() -> TRUE | Q64: 100+ bought in past month | R64: LIVE_CA_comforter | S64: https://www.amazon.ca/dp/B0DD436JG2 | T64: 2026-10-26 | U64: No fixed postal code; mixed variants; rating counts may be pooled/global and K/M rounded. No sales inference from badges.
A65: CA | B65: CAD | C65: comforter | D65: comforter set | E65: 16 | F65: B0F1KLH9LZ | G65: Unresolved (title insufficient) | H65: MUXHOMO Queen Comforter Set 7 Pieces, Sage Green Bed in a Bag Queen Reversible Botanical Flowers Design, Ultra Soft & Breathable Bedding Sets with Comforter, Sheets, Pillowcases & Shams | I65: Queen | J65: Not resolved from title | K65: 59.99 | L65: 4.4 | M65: 388 | N65: =FALSE() -> FALSE | P65: =TRUE() -> TRUE | Q65: 200+ bought in past month | R65: LIVE_CA_comforter | S65: https://www.amazon.ca/dp/B0F1KLH9LZ | T65: 2026-10-26 | U65: No fixed postal code; mixed variants; rating counts may be pooled/global and K/M rounded. No sales inference from badges.
A66: CA | B66: CAD | C66: comforter | D66: comforter set | E66: 17 | F66: B0C5XQ26SM | G66: Unresolved (title insufficient) | H66: Andency Comforter Queen Beige, Boho Bedding Comforter Sets 3 Pieces | I66: Queen | J66: Not resolved from title | K66: 47.49 | L66: 4.4 | M66: 3500 | N66: =FALSE() -> FALSE | O66: Was: $49.99 | Was: | P66: =TRUE() -> TRUE | Q66: 100+ bought in past month | R66: LIVE_CA_comforter | S66: https://www.amazon.ca/dp/B0C5XQ26SM | T66: 2026-10-26 | U66: No fixed postal code; mixed variants; rating counts may be pooled/global and K/M rounded. No sales inference from badges.
A67: CA | B67: CAD | C67: comforter | D67: comforter set | E67: 18 | F67: B0DK6G1PY1 | G67: PHF | H67: PHF Soft Waffle Comforter Set Queen Size- Comfy Breathable Waffle Weave Comforter with 2 Pillow Shams, 3 Pieces No Snagging Lightweight Bedding Set for All Season, Cream | I67: Queen | J67: Not resolved from title | K67: 58.39 | L67: 4.3 | M67: 313 | N67: =FALSE() -> FALSE | O67: Was: $69.29 | Was: | P67: =TRUE() -> TRUE | Q67: 50+ bought in past month | R67: LIVE_CA_comforter | S67: https://www.amazon.ca/dp/B0DK6G1PY1 | T67: 2026-10-26 | U67: No fixed postal code; mixed variants; rating counts may be pooled/global and K/M rounded. No sales inference from badges.
A68: CA | B68: CAD | C68: comforter | D68: comforter set | E68: 19 | F68: B0FP4Y68NM | G68: Unresolved (title insufficient) | H68: BEDELITE Fleece Queen Comforter Set, Soft Fluffy Bedding Set, Black | I68: Queen | J68: Not resolved from title | K68: 62.99 | L68: 4.6 | M68: 563 | N68: =FALSE() -> FALSE | O68: Limited-time deal | Was: $69.99 | Was: | P68: =TRUE() -> TRUE | Q68: 100+ bought in past month | R68: LIVE_CA_comforter | S68: https://www.amazon.ca/dp/B0FP4Y68NM | T68: 2026-10-26 | U68: No fixed postal code; mixed variants; rating counts may be pooled/global and K/M rounded. No sales inference from badges.
A69: CA | B69: CAD | C69: comforter | D69: comforter set | E69: 20 | F69: B0DXK4H9GK | G69: Unresolved (title insufficient) | H69: Cozylux Queen Comforter Set Beige - 7 Pieces Vertical Quilted Bed in a Bag | I69: Queen | J69: Not resolved from title | K69: 55.99 | L69: 4.5 | M69: 1500 | N69: =FALSE() -> FALSE | O69: Was: $59.99 | Was: | Save 5% on any 2 | P69: =TRUE() -> TRUE | Q69: 200+ bought in past month | R69: LIVE_CA_comforter | S69: https://www.amazon.ca/dp/B0DXK4H9GK | T69: 2026-10-26 | U69: No fixed postal code; mixed variants; rating counts may be pooled/global and K/M rounded. No sales inference from badges.
A70: CA | B70: CAD | C70: comforter | D70: comforter set | E70: 21 | F70: B0CD76QM24 | G70: Bedsure | H70: Bedsure Tufted Boho King Comforter Set - Bedroom Decor Beige 3 Pieces | I70: King | J70: Not resolved from title | K70: 76.99 | L70: 4.4 | M70: 3800 | N70: =FALSE() -> FALSE | O70: List: $84.99 | List: | P70: =TRUE() -> TRUE | R70: LIVE_CA_comforter | S70: https://www.amazon.ca/dp/B0CD76QM24 | T70: 2026-10-26 | U70: No fixed postal code; mixed variants; rating counts may be pooled/global and K/M rounded. No sales inference from badges.
A71: CA | B71: CAD | C71: comforter | D71: comforter set | E71: 22 | F71: B0CMZV1P69 | G71: Unresolved (title insufficient) | H71: Andency Comforter Queen 7 Pieces, Dark Emerald Green Boho Bed in a Bag | I71: Queen | J71: Not resolved from title | K71: 63.99 | L71: 4.5 | M71: 3700 | N71: =FALSE() -> FALSE | P71: =TRUE() -> TRUE | Q71: 50+ bought in past month | R71: LIVE_CA_comforter | S71: https://www.amazon.ca/dp/B0CMZV1P69 | T71: 2026-10-26 | U71: No fixed postal code; mixed variants; rating counts may be pooled/global and K/M rounded. No sales inference from badges.
A72: CA | B72: CAD | C72: comforter | D72: comforter set | E72: 23 | F72: B0BPH4FVRS | G72: Unresolved (title insufficient) | H72: 7 Pieces Bed in a Bag Floral Comforter Set Queen Flowers Bedding Set Soft Microfiber Comforter Sets with 1 Comforter 1 Flat Sheet 1 Fitted Sheet 2 Pillowshams and 2 Pillowcases | I72: Queen | J72: Synthetic or blend; verify composition | K72: 69.01 | L72: 4.4 | M72: 1700 | N72: =FALSE() -> FALSE | O72: You pay $63.01 with coupon | P72: =TRUE() -> TRUE | R72: LIVE_CA_comforter | S72: https://www.amazon.ca/dp/B0BPH4FVRS | T72: 2026-10-26 | U72: No fixed postal code; mixed variants; rating counts may be pooled/global and K/M rounded. No sales inference from badges.
A73: CA | B73: CAD | C73: comforter | D73: comforter set | E73: 24 | F73: B0DFBVHBJT | G73: Unresolved (title insufficient) | H73: YIKUSH Fluffy Queen Comforter Set 3 Piece, Cream White Fleece Bedding Set | I73: Queen | J73: Not resolved from title | K73: 52.99 | L73: 4.4 | M73: 224 | N73: =FALSE() -> FALSE | P73: =TRUE() -> TRUE | Q73: 100+ bought in past month | R73: LIVE_CA_comforter | S73: https://www.amazon.ca/dp/B0DFBVHBJT | T73: 2026-10-26 | U73: No fixed postal code; mixed variants; rating counts may be pooled/global and K/M rounded. No sales inference from badges.
A74: CA | B74: CAD | C74: comforter | D74: comforter set | E74: 25 | F74: B0F9XTP4DM | G74: Unresolved (title insufficient) | H74: MUXHOMO 7 Pieces Queen Comforter Set, Soft Bed in a Bag Queen Size, All Season Bedding Set with Comforter, Flat Sheet, Fitted Sheet, Pillowcases & Shams, Beige | I74: Queen | J74: Not resolved from title | K74: 49.99 | L74: 4.2 | M74: 200 | N74: =FALSE() -> FALSE | P74: =TRUE() -> TRUE | Q74: 200+ bought in past month | R74: LIVE_CA_comforter | S74: https://www.amazon.ca/dp/B0F9XTP4DM | T74: 2026-10-26 | U74: No fixed postal code; mixed variants; rating counts may be pooled/global and K/M rounded. No sales inference from badges.
A75: CA | B75: CAD | C75: comforter | D75: comforter set | E75: 26 | F75: B0GRFNTZT2 | G75: Unresolved (title insufficient) | H75: Exclusivo Mezcla Reversible Comforter Set Queen Size, Floral White | I75: Queen | J75: Not resolved from title | K75: 39.99 | L75: 4.2 | M75: 5000 | N75: =FALSE() -> FALSE | O75: Limited-time deal | Was: $46.99 | Was: | P75: =TRUE() -> TRUE | R75: LIVE_CA_comforter | S75: https://www.amazon.ca/dp/B0GRFNTZT2 | T75: 2026-10-26 | U75: No fixed postal code; mixed variants; rating counts may be pooled/global and K/M rounded. No sales inference from badges.
A76: CA | B76: CAD | C76: comforter | D76: comforter set | E76: 27 | F76: B0GZZJVZ5P | G76: Bedsure | H76: Bedsure Cloud Bubble Queen Comforter Set - Soft Fluffy Bedding Beige 3 Pcs | I76: Queen | J76: Not resolved from title | K76: 89.99 | L76: 4.4 | M76: 44 | N76: =FALSE() -> FALSE | O76: Was: $109.99 | Was: | P76: =TRUE() -> TRUE | Q76: 50+ bought in past month | R76: LIVE_CA_comforter | S76: https://www.amazon.ca/dp/B0GZZJVZ5P | T76: 2026-10-26 | U76: No fixed postal code; mixed variants; rating counts may be pooled/global and K/M rounded. No sales inference from badges.
A77: CA | B77: CAD | C77: comforter | D77: comforter set | E77: 28 | F77: B0CMPW8Q9S | G77: Unresolved (title insufficient) | H77: Wajade Faux Fur Comforter Set Queen Size, 3 Pcs Ultra Soft Marbled Sage Green Fluffy Comforter Set Marble Print Furry Bedding Set for All Seasons, 1 Plush Comforter Set+2 Pillow Covers | I77: Queen | J77: Not resolved from title | K77: 23.8 | L77: 4.1 | M77: 116 | N77: =FALSE() -> FALSE | O77: Limited-time deal | Was: $32.99 | Was: | Save 5% on any 2 | P77: =TRUE() -> TRUE | R77: LIVE_CA_comforter | S77: https://www.amazon.ca/dp/B0CMPW8Q9S | T77: 2026-10-26 | U77: No fixed postal code; mixed variants; rating counts may be pooled/global and K/M rounded. No sales inference from badges.
A78: CA | B78: CAD | C78: comforter | D78: comforter set | E78: 29 | F78: B0FQ59RQGF | G78: Sasttie | H78: Sasttie Fluffy Queen Comforter Set, 3 PC Soft Fleece Bedding, Cream White | I78: Queen | J78: Not resolved from title | K78: 55.99 | L78: 4.6 | M78: 595 | N78: =FALSE() -> FALSE | P78: =TRUE() -> TRUE | Q78: 100+ bought in past month | R78: LIVE_CA_comforter | S78: https://www.amazon.ca/dp/B0FQ59RQGF | T78: 2026-10-26 | U78: No fixed postal code; mixed variants; rating counts may be pooled/global and K/M rounded. No sales inference from badges.
A79: CA | B79: CAD | C79: comforter | D79: comforter set | E79: 30 | F79: B0CNXBJG8K | G79: Unresolved (title insufficient) | H79: Andency Fluffy Comforter Queen, 3 Pieces Queen Comforter Bedding Set White | I79: Queen | J79: Not resolved from title | K79: 76.99 | L79: 4.6 | M79: 872 | N79: =FALSE() -> FALSE | P79: =TRUE() -> TRUE | R79: LIVE_CA_comforter | S79: https://www.amazon.ca/dp/B0CNXBJG8K | T79: 2026-10-26 | U79: No fixed postal code; mixed variants; rating counts may be pooled/global and K/M rounded. No sales inference from badges.
A80: CA | B80: CAD | C80: comforter | D80: comforter set | E80: 31 | F80: B08JYV9D75 | G80: Unresolved (title insufficient) | H80: Decroom Lightweight 3 Pieces Comforter Set Full Quilted Duvet Insert | I80: Full | J80: Not resolved from title | K80: 47.59 | L80: 4.4 | M80: 13200 | N80: =FALSE() -> FALSE | O80: Limited-time deal | List: $55.99 | List: | P80: =TRUE() -> TRUE | Q80: 50+ bought in past month | R80: LIVE_CA_comforter | S80: https://www.amazon.ca/dp/B08JYV9D75 | T80: 2026-10-26 | U80: No fixed postal code; mixed variants; rating counts may be pooled/global and K/M rounded. No sales inference from badges.
A81: CA | B81: CAD | C81: comforter | D81: comforter set | E81: 32 | F81: B077N1535Z | G81: Wake In Cloud | H81: Wake In Cloud - Floral Comforter Set, Botanical Flowers Pattern Printed, 100% Cotton Fabric with Soft Microfiber Inner Fill Beddings, 3 Pieces, Queen Size | I81: Queen | J81: Synthetic or blend; verify composition | K81: 53.99 | L81: 4.4 | M81: 3500 | N81: =FALSE() -> FALSE | O81: Save 14% | Was: $62.99 | Was: | P81: =TRUE() -> TRUE | Q81: 50+ bought in past month | R81: LIVE_CA_comforter | S81: https://www.amazon.ca/dp/B077N1535Z | T81: 2026-10-26 | U81: No fixed postal code; mixed variants; rating counts may be pooled/global and K/M rounded. No sales inference from badges.
A82: CA | B82: CAD | C82: comforter | D82: comforter set | E82: 33 | F82: B0C2YVBNRV | G82: Unresolved (title insufficient) | H82: Luxudecor Floral Comforter Set Queen Size 7 Piece, Purple Flower Bed in a Bag, Elegant Floral Comforter with Sheet Set, Soft Microfiber Bedding Set for All Season (Purple, 90/inx90/in) AB090155Q7U | I82: Queen | J82: Synthetic or blend; verify composition | K82: 79.99 | L82: 4.4 | M82: 3100 | N82: =FALSE() -> FALSE | O82: You pay $74.99 with coupon | P82: =TRUE() -> TRUE | Q82: 50+ bought in past month | R82: LIVE_CA_comforter | S82: https://www.amazon.ca/dp/B0C2YVBNRV | T82: 2026-10-26 | U82: No fixed postal code; mixed variants; rating counts may be pooled/global and K/M rounded. No sales inference from badges.
A83: CA | B83: CAD | C83: comforter | D83: comforter set | E83: 34 | F83: B0D19CR79M | G83: Unresolved (title insufficient) | H83: Comforter Double Size, 7 Piece Bed in a Bag Set with Sheets - White | I83: Double | J83: Not resolved from title | K83: 59.99 | L83: 4.2 | M83: 88 | N83: =FALSE() -> FALSE | O83: Was: $69.99 | Was: | P83: =TRUE() -> TRUE | R83: LIVE_CA_comforter | S83: https://www.amazon.ca/dp/B0D19CR79M | T83: 2026-10-26 | U83: No fixed postal code; mixed variants; rating counts may be pooled/global and K/M rounded. No sales inference from badges.
A84: CA | B84: CAD | C84: comforter | D84: comforter set | E84: 35 | F84: B09QLXYZKR | G84: Unresolved (title insufficient) | H84: All Season Queen Comforter Set 3 PCs Soft Quilted Down Alternative Comforter+2 Pillow Shams with Corner Tabs,Winter Summer Warm Fluffy,Machine Washable (Queen, Grey) | I84: Queen | J84: Not resolved from title | K84: 53.9 | L84: 4.6 | M84: 2100 | N84: =FALSE() -> FALSE | P84: =TRUE() -> TRUE | Q84: 200+ bought in past month | R84: LIVE_CA_comforter | S84: https://www.amazon.ca/dp/B09QLXYZKR | T84: 2026-10-26 | U84: No fixed postal code; mixed variants; rating counts may be pooled/global and K/M rounded. No sales inference from badges.
A85: CA | B85: CAD | C85: comforter | D85: comforter set | E85: 36 | F85: B0DX75YHHS | G85: Sasttie | H85: Sasttie Queen Comforter Set, 7-Piece Bed in a Bag, Pintuck Bedding Sets for All Season, Includes Comforter, Flat Sheet, Fitted Sheet, Pillowcases and Pillowshams, Beige | I85: Queen | J85: Not resolved from title | K85: 64.99 | L85: 4.4 | M85: 2700 | N85: =FALSE() -> FALSE | P85: =TRUE() -> TRUE | Q85: 50+ bought in past month | R85: LIVE_CA_comforter | S85: https://www.amazon.ca/dp/B0DX75YHHS | T85: 2026-10-26 | U85: No fixed postal code; mixed variants; rating counts may be pooled/global and K/M rounded. No sales inference from badges.
A86: CA | B86: CAD | C86: comforter | D86: comforter set | E86: 37 | F86: B0H32VRS3K | G86: Unresolved (title insufficient) | H86: BEDELITE Faux Fur Queen Comforter Set Light Grey,Fluffy Bedding,2 Pillowcases | I86: Queen | J86: Not resolved from title | K86: 56.99 | L86: 4.5 | M86: 15 | N86: =FALSE() -> FALSE | O86: Was: $59.99 | Was: | P86: =TRUE() -> TRUE | Q86: 50+ bought in past month | R86: LIVE_CA_comforter | S86: https://www.amazon.ca/dp/B0H32VRS3K | T86: 2026-10-26 | U86: No fixed postal code; mixed variants; rating counts may be pooled/global and K/M rounded. No sales inference from badges.
A87: CA | B87: CAD | C87: comforter | D87: comforter set | E87: 38 | F87: B07YD83845 | G87: Wake In Cloud | H87: Wake In Cloud Floral Comforter Set, Beige, Queen | I87: Queen | J87: Not resolved from title | K87: 49.99 | L87: 4.4 | M87: 579 | N87: =FALSE() -> FALSE | P87: =TRUE() -> TRUE | Q87: 50+ bought in past month | R87: LIVE_CA_comforter | S87: https://www.amazon.ca/dp/B07YD83845 | T87: 2026-10-26 | U87: No fixed postal code; mixed variants; rating counts may be pooled/global and K/M rounded. No sales inference from badges.
A88: CA | B88: CAD | C88: comforter | D88: comforter set | E88: 39 | F88: B08L66HRVC | G88: Unresolved (title insufficient) | H88: Exclusivo Mezcla Reversible Soft Queen Comforter Set, 3 Pieces | I88: Queen | J88: Not resolved from title | K88: 39.99 | L88: 4.4 | M88: 9000 | N88: =FALSE() -> FALSE | O88: List: $49.99 | List: | P88: =TRUE() -> TRUE | Q88: 100+ bought in past month | R88: LIVE_CA_comforter | S88: https://www.amazon.ca/dp/B08L66HRVC | T88: 2026-10-26 | U88: No fixed postal code; mixed variants; rating counts may be pooled/global and K/M rounded. No sales inference from badges.
A89: CA | B89: CAD | C89: comforter | D89: comforter set | E89: 40 | F89: B0C8T7NRJC | G89: Bedsure | H89: Bedsure Fluffy Comforter Set King - Super Soft Fleece Striped Cream White | I89: King | J89: Not resolved from title | K89: 69.99 | L89: 4.6 | M89: 2900 | N89: =FALSE() -> FALSE | P89: =TRUE() -> TRUE | Q89: 100+ bought in past month | R89: LIVE_CA_comforter | S89: https://www.amazon.ca/dp/B0C8T7NRJC | T89: 2026-10-26 | U89: No fixed postal code; mixed variants; rating counts may be pooled/global and K/M rounded. No sales inference from badges.
A90: CA | B90: CAD | C90: comforter | D90: comforter set | E90: 41 | F90: B0C27RPK94 | G90: Unresolved (title insufficient) | H90: HYMOKEGE King Size Comforter Set Seersucker 7 Pieces, All Season Luxury Bed in a Bag for Bedroom, Bedding Set with Comforters, Sheets, Pillowcases & Shams, Dark Grey | I90: King | J90: Not resolved from title | K90: 66.99 | L90: 4.2 | M90: 1800 | N90: =FALSE() -> FALSE | P90: =TRUE() -> TRUE | Q90: 100+ bought in past month | R90: LIVE_CA_comforter | S90: https://www.amazon.ca/dp/B0C27RPK94 | T90: 2026-10-26 | U90: No fixed postal code; mixed variants; rating counts may be pooled/global and K/M rounded. No sales inference from badges.
A91: CA | B91: CAD | C91: comforter | D91: comforter set | E91: 42 | F91: B09ZTTYFFR | G91: Unresolved (title insufficient) | H91: Litanika White Queen Comforter Set, 3 Pieces Lightweight Solid Bed Set | I91: Queen | J91: Not resolved from title | K91: 41 | L91: 4.5 | M91: 11000 | N91: =FALSE() -> FALSE | P91: =TRUE() -> TRUE | R91: LIVE_CA_comforter | S91: https://www.amazon.ca/dp/B09ZTTYFFR | T91: 2026-10-26 | U91: No fixed postal code; mixed variants; rating counts may be pooled/global and K/M rounded. No sales inference from badges.
A92: CA | B92: CAD | C92: comforter | D92: comforter set | E92: 43 | F92: B0D94YVKN3 | G92: Unresolved (title insufficient) | H92: Chezmoi Collection Upland 7-Piece Quilted Patchwork Comforter Set, Black/Gray/Light Gray, Queen | I92: Queen | J92: Not resolved from title | K92: 149.05 | L92: 3.9 | M92: 154 | N92: =FALSE() -> FALSE | P92: =TRUE() -> TRUE | R92: LIVE_CA_comforter | S92: https://www.amazon.ca/dp/B0D94YVKN3 | T92: 2026-10-26 | U92: No fixed postal code; mixed variants; rating counts may be pooled/global and K/M rounded. No sales inference from badges.
A93: CA | B93: CAD | C93: comforter | D93: comforter set | E93: 44 | F93: B0CXPVQ5DK | G93: Unresolved (title insufficient) | H93: Monbix Queen Comforter Set 7 Pieces Cationic Green Bed in a Bag | I93: Queen | J93: Not resolved from title | K93: 86.39 | L93: 4.2 | M93: 3700 | N93: =FALSE() -> FALSE | O93: Limited-time deal | Was: $95.99 | Was: | P93: =TRUE() -> TRUE | Q93: 50+ bought in past month | R93: LIVE_CA_comforter | S93: https://www.amazon.ca/dp/B0CXPVQ5DK | T93: 2026-10-26 | U93: No fixed postal code; mixed variants; rating counts may be pooled/global and K/M rounded. No sales inference from badges.
A94: CA | B94: CAD | C94: comforter | D94: comforter set | E94: 45 | F94: B08FRHT8L3 | G94: Amazon Basics | H94: Amazon Basics 7-Piece Lightweight Microfiber Bed-in-a-Bag Comforter Bedding Set - Full/Queen, Gray Calvin Stripe | I94: Queen | J94: Synthetic or blend; verify composition | K94: 59.99 | L94: 4.6 | M94: 11200 | N94: =FALSE() -> FALSE | P94: =TRUE() -> TRUE | Q94: 200+ bought in past month | R94: LIVE_CA_comforter | S94: https://www.amazon.ca/dp/B08FRHT8L3 | T94: 2026-10-26 | U94: No fixed postal code; mixed variants; rating counts may be pooled/global and K/M rounded. No sales inference from badges.
A95: CA | B95: CAD | C95: comforter | D95: comforter set | E95: 46 | F95: B08BZ192N9 | G95: Unresolved (title insufficient) | H95: Andency Queen Pinch Pleat White Comforter Set 3 Piece Bedding | I95: Queen | J95: Not resolved from title | K95: 47.49 | L95: 4.5 | M95: 9300 | N95: =FALSE() -> FALSE | O95: Was: $49.99 | Was: | P95: =TRUE() -> TRUE | R95: LIVE_CA_comforter | S95: https://www.amazon.ca/dp/B08BZ192N9 | T95: 2026-10-26 | U95: No fixed postal code; mixed variants; rating counts may be pooled/global and K/M rounded. No sales inference from badges.
A96: CA | B96: CAD | C96: comforter | D96: comforter set | E96: 47 | F96: B0CZHC7C1S | G96: Unresolved (title insufficient) | H96: Dobuyly Grey Queen Comforter Set 7 Piece Bed in a Bag, Gray Floral Printed on White Comforter Set with Sheets, Soft Microfiber Botanical Farmhouse Bedding Set for All Season | I96: Queen | J96: Synthetic or blend; verify composition | K96: 74.08 | L96: 4.4 | M96: 2500 | N96: =FALSE() -> FALSE | O96: Save 6% on any 2 | P96: =TRUE() -> TRUE | R96: LIVE_CA_comforter | S96: https://www.amazon.ca/dp/B0CZHC7C1S | T96: 2026-10-26 | U96: No fixed postal code; mixed variants; rating counts may be pooled/global and K/M rounded. No sales inference from badges.
A97: CA | B97: CAD | C97: comforter | D97: comforter set | E97: 48 | F97: B0CBPRLJ8Y | G97: Unresolved (title insufficient) | H97: Queen Comforter Set-7 Pieces Beige Soft Bed in a Bag Queen Bedding Sets | I97: Queen | J97: Not resolved from title | K97: 59.49 | L97: 4.3 | M97: 1500 | N97: =FALSE() -> FALSE | O97: Limited-time deal | Was: $69.99 | Was: | P97: =TRUE() -> TRUE | R97: LIVE_CA_comforter | S97: https://www.amazon.ca/dp/B0CBPRLJ8Y | T97: 2026-10-26 | U97: No fixed postal code; mixed variants; rating counts may be pooled/global and K/M rounded. No sales inference from badges.
A98: CA | B98: CAD | C98: duvet | D98: cotton duvet cover set | E98: 1 | F98: B0C699R8B6 | G98: LIFETOWN | H98: LIFETOWN 100% Washed Cotton Duvet Cover Set Linen Feel Natural Wrinkle Lightweight Comfy (Queen, White) | I98: Queen | J98: Linen-look; not proven flax | K98: 79.99 | L98: 4.5 | M98: 2000 | N98: =FALSE() -> FALSE | P98: =TRUE() -> TRUE | Q98: 100+ bought in past month | R98: LIVE_CA_duvet | S98: https://www.amazon.ca/dp/B0C699R8B6 | T98: 2026-10-26 | U98: No fixed postal code; mixed variants; rating counts may be pooled/global and K/M rounded. No sales inference from badges.
A99: CA | B99: CAD | C99: duvet | D99: cotton duvet cover set | E99: 2 | F99: B07FN7LNSW | G99: Wake In Cloud | H99: Wake In Cloud - Dusty Pink Cotton Duvet Cover Set, Queen Size, 100% Washed Cotton Plain Solid Color, Linen Like Textured, Breathable Durable Farmhouse Neutral Bedding Set, 3 Pieces | I99: Queen | J99: Linen-look; not proven flax | K99: 44.99 | L99: 4 | M99: 2700 | N99: =FALSE() -> FALSE | P99: =TRUE() -> TRUE | R99: LIVE_CA_duvet | S99: https://www.amazon.ca/dp/B07FN7LNSW | T99: 2026-10-26 | U99: No fixed postal code; mixed variants; rating counts may be pooled/global and K/M rounded. No sales inference from badges.
A100: CA | B100: CAD | C100: duvet | D100: cotton duvet cover set | E100: 3 | F100: B0B259ZHPQ | G100: FANSTIVE | H100: FANSTIVE Olive Green Cotton Duvet Cover Set Linen Feel, Queen | I100: Queen | J100: Linen-look; not proven flax | K100: 66.99 | L100: 4.3 | M100: 1000 | N100: =FALSE() -> FALSE | O100: You pay $56.94 with coupon | P100: =TRUE() -> TRUE | Q100: 100+ bought in past month | R100: LIVE_CA_duvet | S100: https://www.amazon.ca/dp/B0B259ZHPQ | T100: 2026-10-26 | U100: No fixed postal code; mixed variants; rating counts may be pooled/global and K/M rounded. No sales inference from badges.
...

Sheet Price review barriers
A1: country | B1: segment | C1: cards | D1: matched_prices | E1: min | F1: p25 | G1: median | H1: p75 | I1: max | J1: ratings_n | K1: median_ratings | L1: sponsored_cards | M1: brand_resolved | N1: top3_known_card_share | O1: top3 | P1: source
A2: CA | B2: bamboo | C2: 48 | D2: 44 | E2: 23.99 | F2: 61.48 | G2: 80.255 | H2: 104.14 | I2: 164.99 | J2: 47 | K2: 617 | L2: 0 | M2: 15 | N2: 0.66666667 | O2: DECOLURE / Bambaw / Hotel Sheets Direct | P2: LIVE_CA_bamboo
A3: CA | B3: comforter | C3: 48 | D3: 48 | E3: 23.8 | F3: 47.84 | G3: 56.49 | H3: 64.74 | I3: 149.05 | J3: 48 | K3: 1850 | L3: 0 | M3: 12 | N3: 0.83333333 | O3: Bedsure / Wake In Cloud / Sasttie | P3: LIVE_CA_comforter
A4: CA | B4: duvet | C4: 48 | D4: 43 | E4: 38.99 | F4: 50.99 | G4: 69.99 | H4: 79.99 | I4: 179.99 | J4: 43 | K4: 1000 | L4: 0 | M4: 25 | N4: 0.68 | O4: Wake In Cloud / Bedsure / LIFETOWN | P4: LIVE_CA_duvet
A5: CA | B5: fitted | C5: 48 | D5: 48 | E5: 10.96 | F5: 19.8775 | G5: 26.74 | H5: 36.365 | I5: 64.99 | J5: 48 | K5: 1550 | L5: 0 | M5: 15 | N5: 0.66666667 | O5: Utopia Bedding / Linen Home / CGK | P5: LIVE_CA_fitted
A6: CA | B6: linen | C6: 48 | D6: 12 | E6: 154.84 | F6: 160.49 | G6: 189.99 | H6: 243.5875 | I6: 319.47 | J6: 12 | K6: 272 | L6: 0 | M6: 20 | N6: 0.6 | O6: Simple&Opulence / Bedsure / MooMee | P6: LIVE_CA_linen
A7: CA | B7: lyocell | C7: 48 | D7: 47 | E7: 33.99 | F7: 76.49 | G7: 99.99 | H7: 122.51 | I7: 376.53 | J7: 46 | K7: 210.5 | L7: 0 | M7: 13 | N7: 0.53846154 | O7: Linenwalas / Bedsure / California Design Den | P7: LIVE_CA_lyocell
A8: CA | B8: pillowcase | C8: 48 | D8: 48 | E8: 10.99 | F8: 15.99 | G8: 18.49 | H8: 29.235 | I8: 56.96 | J8: 48 | K8: 1200 | L8: 0 | M8: 16 | N8: 0.5625 | O8: Amazon Basics / California Design Den / Deep Dream | P8: LIVE_CA_pillowcase
A9: CA | B9: protector | C9: 48 | D9: 48 | E9: 13 | F9: 23.105 | G9: 30.945 | H9: 36.9675 | I9: 79.99 | J9: 48 | K9: 3650 | L9: 0 | M9: 17 | N9: 0.82352941 | O9: Utopia Bedding / BEDLORE / Sasttie | P9: LIVE_CA_protector
A10: CA | B10: quilt | C10: 48 | D10: 44 | E10: 34.19 | F10: 56.615 | G10: 98.44 | H10: 119.99 | I10: 176.76 | J10: 48 | K10: 453 | L10: 0 | M10: 8 | N10: 0.875 | O10: Joyreap / Utopia Bedding / PHF | P10: LIVE_CA_quilt
A11: CA | B11: sheets | C11: 58 | D11: 47 | E11: 32.77 | F11: 44.99 | G11: 56.99 | H11: 75.99 | I11: 119.99 | J11: 48 | K11: 1950 | L11: 10 | M11: 25 | N11: 0.56 | O11: California Design Den / Amazon Basics / THREAD SPREAD | P11: LIVE_CA_sheets
A12: CA | B12: topper | C12: 48 | D12: 48 | E12: 25.99 | F12: 56.24 | G12: 74.945 | H12: 111.5925 | I12: 554 | J12: 48 | K12: 1049 | L12: 0 | M12: 7 | N12: 0.57142857 | O12: Utopia Bedding / Niagara Sleep Solution / BEDLORE | P12: LIVE_CA_topper
A13: UK | B13: bamboo | C13: 48 | D13: 47 | E13: 19.5 | F13: 48.29 | G13: 69.38 | H13: 99.77 | I13: 353.34 | J13: 47 | K13: 186 | L13: 0 | M13: 10 | N13: 0.8 | O13: Love's cabin / DECOLURE / PHF | P13: LIVE_UK_bamboo
A14: UK | B14: comforter | C14: 48 | D14: 0 | J14: 0 | L14: 0 | M14: 20 | N14: 0.85 | O14: GC GAVENO CAVAILIA / PRIME LINENS / Utopia Bedding | P14: LIVE_UK_comforter
A15: UK | B15: duvet | C15: 48 | D15: 29 | E15: 10.55 | F15: 13.99 | G15: 21.04 | H15: 26.845 | I15: 38 | J15: 34 | K15: 895 | L15: 0 | M15: 19 | N15: 0.68421053 | O15: GC GAVENO CAVAILIA / Yard / Dreams & Drapes | P15: LIVE_UK_duvet
A16: UK | B16: fitted | C16: 48 | D16: 25 | E16: 7.16 | F16: 8.99 | G16: 11.37 | H16: 22.665 | I16: 31.18 | J16: 48 | K16: 1350 | L16: 0 | M16: 18 | N16: 0.66666667 | O16: Utopia Bedding / Amazon Basics / Sapphire Collection | P16: LIVE_UK_fitted
A17: UK | B17: linen | C17: 48 | D17: 8 | E17: 24.04 | F17: 26.18 | G17: 82.89 | H17: 147.955 | I17: 166.23 | J17: 8 | K17: 2000 | L17: 0 | M17: 13 | N17: 0.46153846 | O17: Utopia Bedding / TEXAS LINEN CO. / Yard | P17: LIVE_UK_linen
A18: UK | B18: lyocell | C18: 48 | D18: 47 | E18: 29.24 | F18: 66.34 | G18: 78.07 | H18: 103.36 | I18: 189.31 | J18: 42 | K18: 47 | L18: 0 | M18: 0 | P18: LIVE_UK_lyocell
A19: UK | B19: pillowcase | C19: 48 | D19: 19 | E19: 3.99 | F19: 6.08 | G19: 9.89 | H19: 12 | I19: 22.92 | J19: 48 | K19: 540.5 | L19: 0 | M19: 14 | N19: 0.85714286 | O19: Sapphire Collection / Amazon Basics / Yard | P19: LIVE_UK_pillowcase
A20: UK | B20: protector | C20: 48 | D20: 24 | E20: 6.99 | F20: 8.9925 | G20: 11.385 | H20: 16.7425 | I20: 26 | J20: 48 | K20: 540.5 | L20: 0 | M20: 13 | N20: 0.84615385 | O20: Silentnight / Amazon Basics / Utopia Bedding | P20: LIVE_UK_protector
A21: UK | B21: quilt | C21: 48 | D21: 0 | J21: 0 | L21: 0 | M21: 24 | N21: 0.625 | O21: Silentnight / Littens / GC GAVENO CAVAILIA | P21: LIVE_UK_quilt
A22: UK | B22: sheets | C22: 48 | D22: 17 | E22: 12.05 | F22: 31.075 | G22: 47.22 | H22: 58.145 | I22: 77.1 | J22: 30 | K22: 430 | L22: 0 | M22: 14 | N22: 0.5 | O22: Utopia Bedding / GC GAVENO CAVAILIA / Elegant Comfort | P22: LIVE_UK_sheets
A23: UK | B23: topper | C23: 60 | D23: 29 | E23: 9.94 | F23: 19.99 | G23: 31.99 | H23: 47.27 | I23: 130.24 | J23: 60 | K23: 307.5 | L23: 12 | M23: 18 | N23: 0.88888889 | O23: Silentnight / GC GAVENO CAVAILIA / GMTEXTILES | P23: LIVE_UK_topper
A24: US | B24: bamboo | C24: 48 | D24: 48 | E24: 24.99 | F24: 43.4825 | G24: 59.99 | H24: 79.74 | I24: 134.99 | J24: 48 | K24: 463 | L24: 0 | M24: 23 | N24: 0.60869565 | O24: Pure Bamboo / Bedsure / Love's cabin | P24: LIVE_US_bamboo
A25: US | B25: comforter | C25: 48 | D25: 48 | E25: 21.98 | F25: 30.4875 | G25: 36.99 | H25: 49.9675 | I25: 309 | J25: 48 | K25: 4400 | L25: 0 | M25: 9 | N25: 1 | O25: Bedsure / Love's cabin / Sasttie | P25: LIVE_US_comforter
A26: US | B26: duvet | C26: 48 | D26: 41 | E26: 14.99 | F26: 48.17 | G26: 55.99 | H26: 68.99 | I26: 89.99 | J26: 42 | K26: 1300 | L26: 0 | M26: 28 | N26: 0.67857143 | O26: Bedsure / OAITE / BESTOUCH | P26: LIVE_US_duvet
A27: US | B27: fitted | C27: 48 | D27: 46 | E27: 8.99 | F27: 17.8775 | G27: 19.99 | H27: 29.99 | I27: 79.99 | J27: 48 | K27: 20500 | L27: 0 | M27: 19 | N27: 0.84210526 | O27: CGK / California Design Den / Hearth & Harbor | P27: LIVE_US_fitted
A28: US | B28: linen | C28: 48 | D28: 31 | E28: 90.24 | F28: 103.99 | G28: 119.99 | H28: 129.99 | I28: 145.99 | J28: 31 | K28: 1600 | L28: 0 | M28: 17 | N28: 0.58823529 | O28: Bedsure / LANE LINEN / Simple&Opulence | P28: LIVE_US_linen
A29: US | B29: lyocell | C29: 48 | D29: 47 | E29: 26.79 | F29: 55.99 | G29: 70.84 | H29: 89.99 | I29: 159.99 | J29: 47 | K29: 158 | L29: 0 | M29: 4 | N29: 0.75 | O29: Bedsure / Love's cabin / SIJO | P29: LIVE_US_lyocell
A30: US | B30: pillowcase | C30: 59 | D30: 58 | E30: 8.99 | F30: 14.99 | G30: 19.99 | H30: 23.92 | I30: 65.99 | J30: 58 | K30: 1800 | L30: 12 | M30: 23 | N30: 0.82608696 | O30: California Design Den / THREAD SPREAD / LANE LINEN | P30: LIVE_US_pillowcase
A31: US | B31: protector | C31: 48 | D31: 46 | E31: 11.99 | F31: 20.49 | G31: 32.49 | H31: 42.88 | I31: 119 | J31: 48 | K31: 9700 | L31: 0 | M31: 23 | N31: 0.69565217 | O31: SafeRest / PlushDeluxe / Utopia Bedding | P31: LIVE_US_protector
A32: US | B32: quilt | C32: 58 | D32: 57 | E32: 15.29 | F32: 52.09 | G32: 69.99 | H32: 87.74 | I32: 169.99 | J32: 58 | K32: 696 | L32: 12 | M32: 8 | N32: 1 | O32: Love's cabin / Bedsure | P32: LIVE_US_quilt
A33: US | B33: sheets | C33: 48 | D33: 38 | E33: 15 | F33: 33.065 | G33: 41.99 | H33: 53.49 | I33: 149.99 | J33: 38 | K33: 3100 | L33: 0 | M33: 24 | N33: 0.54166667 | O33: LANE LINEN / TEXAS LINEN CO. / Casa Platino | P33: LIVE_US_sheets
A34: US | B34: topper | C34: 48 | D34: 44 | E34: 13.99 | F34: 49.9825 | G34: 69.99 | H34: 105.99 | I34: 349 | J34: 48 | K34: 1850 | L34: 0 | M34: 12 | N34: 0.83333333 | O34: LINENSPA / EASELAND / Lucid | P34: LIVE_US_topper

Sheet Listing detail
A1: Country | B1: Segment | C1: ASIN | D1: Byline | E1: Aplus DOM nodes | F1: Image thumbs | G1: Video/quality limitation | H1: Visible review cards | I1: URL | J1: Source | K1: Notes | L1: Observed seller | M1: Observed shipper
A2: CA | B2: duvet | C2: B0C699R8B6 | D2: Visit the LIFETOWN Store | E2: 3 | F2: 7 | G2: Video count not verified; DOM presence is not quality score | H2: 13 | I2: https://www.amazon.ca/dp/B0C699R8B6 | J2: PDP_CA_duvet | K2: Page text/specifications in evidence archive. Brand != seller != manufacturer. No inferred seller revenue. | L2: LIFETOWN | M2: Amazon
A3: UK | B3: topper | C3: B072M5ZT78 | D3: Visit the GMTEXTILES Store | E3: 3 | F3: 7 | G3: Video count not verified; DOM presence is not quality score | H3: 13 | I3: https://www.amazon.co.uk/dp/B072M5ZT78 | J3: PDP_UK_topper | K3: Page text/specifications in evidence archive. Brand != seller != manufacturer. No inferred seller revenue. | L3: Unverified | M3: Unverified
A4: UK | B4: protector | C4: B08FRKXJ9R | D4: Visit the Silentnight Store | E4: 3 | F4: 7 | G4: Video count not verified; DOM presence is not quality score | H4: 13 | I4: https://www.amazon.co.uk/dp/B08FRKXJ9R | J4: PDP_UK_protector | K4: Page text/specifications in evidence archive. Brand != seller != manufacturer. No inferred seller revenue. | L4: Unverified | M4: Unverified
A5: UK | B5: bamboo | C5: B0DN1DDRHR | D5: Brand: Love's cabin | E5: 1 | F5: 7 | G5: 2 video references; DOM presence is not quality score | H5: 5 | I5: https://www.amazon.co.uk/dp/B0DN1DDRHR | J5: PDP_UK_bamboo | K5: Page text/specifications in evidence archive. Brand != seller != manufacturer. No inferred seller revenue. | L5: Unverified | M5: Unverified
A6: UK | B6: sheets | C6: B0CGJGRFW9 | D6: Visit the Utopia Bedding Store | E6: 1 | F6: 7 | G6: Video count not verified; DOM presence is not quality score | H6: 13 | I6: https://www.amazon.co.uk/dp/B0CGJGRFW9 | J6: PDP_UK_sheets | K6: Page text/specifications in evidence archive. Brand != seller != manufacturer. No inferred seller revenue. | L6: Unverified | M6: Unverified
A7: UK | B7: duvet | C7: B00J4RM850 | D7: Visit the Sapphire Collection Store | E7: 2 | F7: 5 | G7: Video count not verified; DOM presence is not quality score | H7: 13 | I7: https://www.amazon.co.uk/dp/B00J4RM850 | J7: PDP_UK_duvet | K7: Page text/specifications in evidence archive. Brand != seller != manufacturer. No inferred seller revenue. | L7: Unverified | M7: Unverified
A8: US | B8: protector | C8: B07HC2WHS1 | D8: Visit the PlushDeluxe Store | E8: 3 | F8: 7 | G8: 8 video references; DOM presence is not quality score | H8: 0 | I8: https://www.amazon.com/dp/B07HC2WHS1 | J8: PDP_US_protector | K8: Page text/specifications in evidence archive. Brand != seller != manufacturer. No inferred seller revenue. | L8: PlushDeluxe | M8: Amazon
A9: US | B9: sheets | C9: B07RY59C3W | D9: Visit the LANE LINEN Store | E9: 3 | F9: 7 | G9: 8 video references; DOM presence is not quality score | H9: 0 | I9: https://www.amazon.com/dp/B07RY59C3W | J9: PDP_US_sheets | K9: Page text/specifications in evidence archive. Brand != seller != manufacturer. No inferred seller revenue. | L9: Homespun Global | M9: Amazon
A10: CA | B10: sheets | C10: B0DST3PF14 | D10: Visit the THREAD SPREAD Store | E10: 2 | F10: 7 | G10: Video count not verified; DOM presence is not quality score | H10: 13 | I10: https://www.amazon.ca/dp/B0DST3PF14 | J10: PDP_CA_sheets | K10: Page text/specifications in evidence archive. Brand != seller != manufacturer. No inferred seller revenue. | L10: Thread Spread | M10: Amazon
A11: US | B11: duvet | C11: B0BP6DZ862 | D11: Visit the Bedsure Store | E11: 3 | F11: 7 | G11: 11 video references; DOM presence is not quality score | H11: 0 | I11: https://www.amazon.com/dp/B0BP6DZ862 | J11: PDP_US_duvet | K11: Page text/specifications in evidence archive. Brand != seller != manufacturer. No inferred seller revenue. | L11: Bedsure Collections | M11: Amazon
A12: US | B12: bamboo | C12: B0F29F1JM5 | D12: Visit the SONORO KATE Store | E12: 2 | F12: 7 | G12: Video count not verified; DOM presence is not quality score | H12: 0 | I12: https://www.amazon.com/dp/B0F29F1JM5 | J12: PDP_US_bamboo | K12: Page text/specifications in evidence archive. Brand != seller != manufacturer. No inferred seller revenue. | L12: SONORO KATE | M12: Amazon
A13: CA | B13: topper | C13: B07D5DN269 | D13: Visit the Niagara Sleep Solution Store | E13: 2 | F13: 7 | G13: 4 video references; DOM presence is not quality score | H13: 13 | I13: https://www.amazon.ca/dp/B07D5DN269 | J13: PDP_CA_topper | K13: Page text/specifications in evidence archive. Brand != seller != manufacturer. No inferred seller revenue. | L13: Niagara Sleep Solutions | M13: Amazon
... A16: CA | B16: bamboo | C16: B0H9QD7RD5 | D16: Visit the Sasttie Store | E16: 2 | F16: 7 | G16: 3 video references; DOM presence is not quality score | H16: 13 | I16: https://www.amazon.ca/dp/B0H9QD7RD5 | J16: PDP_CA_bamboo | K16: Page text/specifications in evidence archive. Brand != seller != manufacturer. No inferred seller revenue. | L16: MMT_SASTTIE | M16: Amazon

Sheet Review evidence
A1: source | B1: asin | C1: market | D1: review_id | E1: geo_date | F1: text | G1: reviewer_country | H1: vine | I1: verified | J1: themes | K1: method
A2: PDP_CA_bamboo | B2: B0H9QD7RD5 | C2: CA | D2: RL9SNNH75OSSL | E2: Canada on October 22, 2026 | F2: MM2 5 out of 5 stars Softest Sheets EVER + Amazing Price Reviewed in Canada on October 22, 2026 Colour Name: WhiteSize: King Verified Purchase I just got into bed in these sheets and they are SO incredibly soft and airy. I’ll definitely be ordering at least another set. The price is is super reasonable as well, and they are much nicer than any other sheets I have that cost more than twice the price. 2 people found this helpful Helpful Report | G2: CA | H2: =FALSE() -> FALSE | I2: =TRUE() -> TRUE | J2: comfort_softness; value | K2: Case-insensitive keyword mentions; multi-label; no positive/negative classification; displayed helpfulness sample, not random.
A3: PDP_CA_bamboo | B3: B0H9QD7RD5 | C3: CA | D3: R1H0ZZKCIPN647 | E3: Canada on October 3, 2026 | F3: Linda B 4 out of 5 stars Lovely soft and blue. Please don’t pill Reviewed in Canada on October 3, 2026 Colour Name: Light BlueSize: Queen Vine customer review of free product I desperately needed new sheets. I had managed to accidentally rip a hole in my current fitted sheet while aggressively scrubbing at a stain, which seemed like a reasonably good indication that its two-year career had come to an end. Enter these lovely blue sheets. First impressions are very good. They’re extremely soft and have the silky, smooth feel you expect from bamboo-derived rayon. I also really like the colour. The light blue is pretty without being overly bright, and it gives the bed a fresh look. There are a couple of design details here that I particularly appreciate. The fitted sheet has a tag clearly marked for the head of the bed. This may sound ridiculous, but if you have ever stood there turning and flipping a fitted sheet several times trying to figure out which way it goes, you hear me. Anything that eliminates unnecessary fitted-sheet gymnastics is welcome. They’ve also added extra elastic straps at the corners to help keep the fitted sheet anchored to the mattress. It’s designed for mattresses up to 16 inches deep and has elastic around the entire edge as well. I’m hoping these features will keep it from working loose during the night, because a fitted sheet that slowly migrates off the mattress or folds under your butt is one of my particular pet peeves. The bamboo-derived rayon is lightweight and breathable, and this type of fabric is known for helping move moisture away from the skin. That’s part of the appeal for people who tend to sleep warm. The 300-thread-count weave also gives the sheets a nice balance between being lightweight and feeling substantial rather than paper-thin. There is one thing I’m reserving judgment on, though: durability. I’ve had inexpensive silky sheets before that felt wonderful when they were new and then developed pilling after only a handful of washes. Rayon made from bamboo is soft and comfortable, but that doesn’t automatically make it exceptionally durable. The fibres can be more vulnerable to friction and rough washing than some sturdier cotton fabrics, and pilling can occur when they break or work their way to the surface. These sheets specifically recommend washing separately on a gentle cycle and tumble drying on low, which I intend to follow. Hopefully, that will help preserve the fabric. I’m just not willing to declare them long-term winners until they’ve survived a reasonable number of trips through the laundry. After all, sheets need to be washed regularly. At $70 for the queen-size four-piece set, I think the price is reasonable. Comparable bamboo-derived rayon sheet sets in Canada generally fall in the $50–$80 range, while more established bamboo-sheet brands can easily cost over $100. So these aren’t dirt cheap, but they’re also not unusually expensive for this type of fabric. For that price, you’re getting some nice features beyond simply a pretty set of sheets: the bamboo-derived fabric, 300-thread-count construction, deep 16-inch pocket, full elastic edge, extra corner straps, envelope-style pillowcases and the extremely useful head-of-bed tag. Please don’t pill. I’m begging you. If they stay this soft and smooth after a few months of regular use, I’ll be very impressed. Read more One person found this helpful Helpful Report | G3: CA | H3: =TRUE() -> TRUE | I3: =FALSE() -> FALSE | J3: comfort_softness; thermal_breathability; fit_sizing; durability_pilling; colour_fading; care_wrinkles; value; authenticity_material | K3: Case-insensitive keyword mentions; multi-label; no positive/negative classification; displayed helpfulness sample, not random.
A4: PDP_CA_bamboo | B4: B0H9QD7RD5 | C4: CA | D4: R6URC0AT3TOOK | E4: Canada on October 24, 2026 | F4: Sylvie V. 5 out of 5 stars Très doux Reviewed in Canada on October 24, 2026 Colour Name: Dark GreySize: Queen Verified Purchase Très bonne qualité pour le prix. Helpful Report Translate review to English | G4: CA | H4: =FALSE() -> FALSE | I4: =TRUE() -> TRUE | J4: value | K4: Case-insensitive keyword mentions; multi-label; no positive/negative classification; displayed helpfulness sample, not random.
A5: PDP_CA_bamboo | B5: B0H9QD7RD5 | C5: CA | D5: R2VTZ23634KZWD | E5: Canada on October 11, 2026 | F5: Maya 4 out of 5 stars Fitted sheets that deliver what they promise. Reviewed in Canada on October 11, 2026 Colour Name: Light GreySize: Queen Vine customer review of free product This add says these sheets are silky smooth, and they absolutely are. They feel so fresh and soft, have a beautiful silk feel to them, without being as silky as silk (if that makes sense). If you try them, you will absolutely understand what I am trying to say. Regardless, they are quite lovely to sleep in, and do keep one quite cool. They also cool down so fast, so if you like to constantly looking for a new colder spot with your feet, this will be great for you. When I first opened the pack, there were a lot of lose strings all over the sheets. Nothing that made any seems come undone, but I was worried for a minute. The stitching overall also felt a bit less-than, but in the end they have held up very well so far. I love the extra stretch bands on the corners, and am so happy it has a side-marker, letting me know what way is up and down. Of course I am a rebel though, and always but the head end towards the bottom. I have washed it twice already now, and it does really well on a cold-gentle cycle and then on a low tumble dry. The material dries pretty quickly too, so even hanging them (if you have the room) is absolutely an option. The sizing for my queen bed is quite giving, and even my very thick pillows fit into them without any problems, and the fitted sheet still has plenty of room on the corners, even though I have quite a high pillow-top on my mattress. This means however that the corners of the sheet are a bit lower than the corners of my mattress. They get covered up with the other sheet and blankets anyways, but I understand how this might not please everyone. Overall, I still quite like these ones, and love the many colour options they have available. 100% Rayon, they truly help me stay cool at night, the colour is very close to the pictures in the add, they wash well, and at a current price-point of just under $70, they seem quite average for this material and size. Read more Helpful Report | G5: CA | H5: =TRUE() -> TRUE | I5: =FALSE() -> FALSE | J5: comfort_softness; thermal_breathability; fit_sizing; colour_fading; care_wrinkles; value; authenticity_material | K5: Case-insensitive keyword mentions; multi-label; no positive/negative classification; displayed helpfulness sample, not random.
A6: PDP_CA_bamboo | B6: B0H9QD7RD5 | C6: CA | D6: R24MPMD6GE3V1D | E6: Canada on October 16, 2026 | F6: Amazon Customer 5 out of 5 stars Incredibly soft Reviewed in Canada on October 16, 2026 Colour Name: WhiteSize: Queen Vine customer review of free product These are easily the softest sheets and pillowcases I've used. They're comfortable, breathable, fit our queen bedding properly, and have a clean, simple appearance. Coles Notes: - The sheets arrive in a nicely presented package made from the same material as the bedding. Rather than being crammed into a disposable plastic bag, the set feels properly packaged, which makes a good first impression. - The colour and appearance match the listing photos accurately, so there were no surprises when I unpacked them. It is worth noting that they are fairly opaque so you may see darker pillows through them. - The overall manufacturing quality seems good. I didn't notice any problematic seams, loose threads, or other obvious defects. - The standout feature is the softness. These are genuinely the softest sheets and pillowcases I've used, and you can tell as soon as you touch the material. They're very comfortable to sleep on and under, and I wish I'd switched to this type of bedding sooner. - The fabric also feels breathable and comfortable during use. While I haven't done any specific temperature testing, I appreciate how pleasant they feel when sleeping. - Went through washer/dryer without any issues. - The set fits our queen-sized mattress and queen-sized pillows without any issues. The fitted sheet has enough stretch to get over the mattress fairly easily and stayed in place during use. - The pillowcases have a simple flap at the opening that tucks the end of the pillow inside. It's a small detail, but it gives the bed a neater appearance and keeps the pillow from sticking out. - At the time of ordering, the four-piece set was $64.99. Considering the quality, fit, and especially the softness, I think that's a fair price for a set of sheets I'm genuinely happy to use. Read more Helpful Report | G6: CA | H6: =TRUE() -> TRUE | I6: =FALSE() -> FALSE | J6: comfort_softness; thermal_breathability; fit_sizing; colour_fading; care_wrinkles; value; packaging | K6: Case-insensitive keyword mentions; multi-label; no positive/negative classification; displayed helpfulness sample, not random.
A7: PDP_CA_bamboo | B7: B0H9QD7RD5 | C7: CA | D7: R2K6HB1NFLH630 | E7: Canada on October 14, 2026 | F7: Amazon Customer 3 out of 5 stars No cooling provided Reviewed in Canada on October 14, 2026 Colour Name: BeigeSize: King Vine customer review of free product I was impressed with how smooth and silky these sheets were right out of the package. I usually prefer cotton sheets but was drawn to these rayon ones as they claimed to be cooling sheets for hot sleepers. I have been sleeping on them for over 2 weeks now and do not find them to be cooling at all. The fabric feels a bit scratchy now that they have been washed a few times. What I do like about them is the deep secure pockets and especially the corner straps. Those are an amazing addition and they work really well to keep the sheet in place on the bed. Rayon does wrinkle so you need to get them out of the washer and dryer quickly. Overall I would say they are “okay”, however, I am disappointed in the fact that they do not provide any coolness while sleeping, as advertised. One person found this helpful Helpful Report | G7: CA | H7: =TRUE() -> TRUE | I7: =FALSE() -> FALSE | J7: thermal_breathability; fit_sizing; care_wrinkles; authenticity_material; packaging | K7: Case-insensitive keyword mentions; multi-label; no positive/negative classification; displayed helpfulness sample, not random.
A8: PDP_CA_bamboo | B8: B0H9QD7RD5 | C8: CA | D8: ROQ4MCVN2V02Q | E8: Canada on October 11, 2026 | F8: nicolletiti1553 5 out of 5 stars The sheets are a generous size Reviewed in Canada on October 11, 2026 Colour Name: Olive GreenSize: Queen Vine customer review of free product Love, love, love the colour! Okay so my bedroom is many shades of green and this sheet set fits in perfectly. The set feels so soft and has a bit of a sheen to them and almost give silk vibes. The size of the sheets is very generous, I have a deep mattress and often struggle to find sheets that will fit my mattress but these are perfect. The top and bottom of the fitted sheet are marked so it is easy to put on the mattress and the corners have a wide elastic band that help to pull the fitted sheet snuggly around the corners leaving it smooth. The pillow cases fit bigger pillows and have a deep flap that keeps the case on the pillows and looking good. The stitching and seams on this set are all even & straight without any frayed edges or wavy or odd lines. I am very pleased with this set. Helpful Report | G8: CA | H8: =TRUE() -> TRUE | I8: =FALSE() -> FALSE | J8: comfort_softness; fit_sizing; colour_fading | K8: Case-insensitive keyword mentions; multi-label; no positive/negative classification; displayed helpfulness sample, not random.
A9: PDP_CA_bamboo | B9: B0H9QD7RD5 | C9: CA | D9: R1NNKO7ASXBWNK | E9: Canada on October 9, 2026 | F9: Uncle Ed 4 out of 5 stars Comfortable Bamboo Rayon Sheets with Lightweight Fabric Reviewed in Canada on October 9, 2026 Colour Name: SandSize: Queen Vine customer review of free product For $69.99 at the time of this review, I think this is a good-quality sheet set overall. I got the Sand colour, and the material has a soft, smooth feel. The set is made from 100% rayon derived from bamboo and is listed as 300 thread count. It includes four pieces: a fitted sheet, flat sheet, and two 20 x 30 inch pillowcases. The fitted sheet is designed for mattresses up to 16 inches deep and has elastic around the entire edge plus four corner straps to help keep it in place. There are also a couple of useful details that I like. The fitted sheet has a head tag that makes it easier to orient correctly on the mattress, and the pillowcases use an envelope closure so the pillows stay tucked inside. The overall quality is good, but the fabric is relatively thin. It has a lightweight feel rather than the heavier feel some people may expect from bedding at this price. The other noticeable issue is wrinkling. This material wrinkles very easily, so after washing and drying it does not come out looking particularly smooth. If a neat appearance is important, some additional effort may be needed. The listing states that the set is OEKO-TEX Standard 100 certified and gives certification number 24.HCN.57362 through Hohenstein. Care instructions are machine wash, low-heat drying, and no bleach. Overall, I like the softness, the fit features, and the general quality. The main things to keep in mind are that the material is fairly thin and very prone to wrinkling. Read more One person found this helpful Helpful Report | G9: CA | H9: =TRUE() -> TRUE | I9: =FALSE() -> FALSE | J9: comfort_softness; thermal_breathability; fit_sizing; colour_fading; care_wrinkles; value; authenticity_material | K9: Case-insensitive keyword mentions; multi-label; no positive/negative classification; displayed helpfulness sample, not random.
A10: PDP_CA_bamboo | B10: B0H9QD7RD5 | C10: CA | D10: R186ETONLZ2BFP | E10: the United States on October 18, 2026 | F10: Roscoe Fauni 5 out of 5 stars Really nice sheets for the price! Reviewed in the United States on October 18, 2026 Colour Name: Light BlueSize: Queen Verified Purchase Nice sheets, feels the same as another sheets I tried at a store that is more expensive. Queen size 16” fits snuggly into my 16” mattress. Washed cold, gentle cycle, low heat for fifteen minutes then finished with air fluff and all wrinkles are gone and sheets still cool. Hopefully it can stay cool after hours of use at night. If so, will buy again! Report | G10: US | H10: =FALSE() -> FALSE | I10: =TRUE() -> TRUE | J10: thermal_breathability; fit_sizing; care_wrinkles | K10: Case-insensitive keyword mentions; multi-label; no positive/negative classification; displayed helpfulness sample, not random.
A11: PDP_CA_bamboo | B11: B0H9QD7RD5 | C11: CA | D11: R1B6TUF2TJRJJ0 | E11: the United States on October 13, 2026 | F11: noflyingzone 5 out of 5 stars Incredibly Soft, Breathable, and Excellent Quality Bamboo Sheets! Reviewed in the United States on October 13, 2026 Colour Name: Light GreySize: Queen Vine customer review of free product I absolutely love these bamboo sheets! The first thing I noticed was how incredibly soft and silky they feel against my skin. The fabric has a nice, substantial thickness and feels very well made, yet it's surprisingly lightweight and breathable. It's the perfect combination of comfort and quality without feeling heavy or overly warm. What really impresses me is how comfortable they are to sleep in. The material feels smooth and cool against the skin, making it especially nice for warmer nights. Unlike some other sheets I've owned, these don't seem to attract lint or fuzz, which is a huge plus. They maintain a clean, smooth appearance without much effort. They also wash really well! The fabric stays soft and smooth after laundering, and I haven't noticed any issues with lint buildup. I also appreciate the thoughtful design, including the deep pockets and corner straps that help keep the fitted sheet in place. Overall, these sheets exceeded my expectations. They feel luxurious, breathable, and comfortable, with a nice thickness that makes them feel like high-quality bedding. I would definitely recommend them to anyone looking for soft, cooling sheets that are also easy to care for. I love them! Read more Report | G11: US | H11: =TRUE() -> TRUE | I11: =FALSE() -> FALSE | J11: comfort_softness; thermal_breathability; fit_sizing; care_wrinkles; authenticity_material | K11: Case-insensitive keyword mentions; multi-label; no positive/negative classification; displayed helpfulness sample, not random.
A12: PDP_CA_bamboo | B12: B0H9QD7RD5 | C12: CA | D12: R1WP5UQ843TDVZ | E12: the United States on October 19, 2026 | F12: Folk 2 out of 5 stars Terrible seam quality. Ripped immediately Reviewed in the United States on October 19, 2026 Colour Name: Olive GreenSize: King Verified Purchase Didn't even get a chance to try them; a huge hole ripped in the pillow case during laundering (I followed the tag instructions) The seams separate from the fabric with very little tension. Poor quality. Which is a shame, because the fabric itself feels cool and silky. Report | G12: US | H12: =FALSE() -> FALSE | I12: =TRUE() -> TRUE | J12: thermal_breathability; durability_pilling | K12: Case-insensitive keyword mentions; multi-label; no positive/negative classification; displayed helpfulness sample, not random.
A13: PDP_CA_bamboo | B13: B0H9QD7RD5 | C13: CA | D13: R3ORI7B2TAETYU | E13: the United States on October 19, 2026 | F13: Katrina Kiefer 5 out of 5 stars They're like going to bed on a puff of air. Doing miss this bargain! Reviewed in the United States on October 19, 2026 Colour Name: IvorySize: King Vine customer review of free product These may be the silkiest,softest sheets I've ever slept on, and that's saying a lot. There are few things I'm willing to pay a whole lot of money for, and the highest count Egyptian cotton sheets has always been one of them. If you've ever priced out the high end kind I'm talking about you understand the kind of sticker shock I'm talking about. Now here comes these bamboo fiber-based sheets in an entire king set for less than half the cost of a single high end cotton one and they're devine. It's like sleeping on air. I will say I haven't noticed myself sleeping any cooler as they advertise, but I bought them to see if they might feel as good as my others. They do. Softer if that's possible. I only wish they came in a greater variety of colors than those offered when I ordered them. Completely worth they lettuce point A bargain at that Report | G13: US | H13: =TRUE() -> TRUE | I13: =FALSE() -> FALSE | J13: comfort_softness; thermal_breathability; colour_fading; value; authenticity_material | K13: Case-insensitive keyword mentions; multi-label; no positive/negative classification; displayed helpfulness sample, not random.
A14: PDP_CA_bamboo | B14: B0H9QD7RD5 | C14: CA | D14: R2ZH18VWCVM86I | E14: the United States on October 12, 2026 | F14: Customer Review 5 out of 5 stars Stay cool! Reviewed in the United States on October 12, 2026 Colour Name: IvorySize: King Vine customer review of free product I got these because I tend to sleep hot and wanted something breathable. Not my first rodeo, I've tried and loved bamboo sheets before, and this excellent set is no exception: the material is very soft right out of the box and feels naturally cool to the touch. The best feature is the way they fit the bed. Again, not unique in my experience with bamboo sheets--for some reason, they're just easier to make the bed with. My mattress is modern/on the thicker side, and usually, the corners slip off after a night or two. These have extra elastic corner straps that anchor the sheets down, so they haven't pulled off at all. Mercifully, they also have a head/foot tag sewn in, which saves time when you're making a king-size bed--that's always a welcome benefit, but especially annoying when its lacking on a non-patterned sheet so you cannot otherwis determine which is top-to-bottom vs. side-to-side for a king sized bed. They washed without shrinking or losing that smooth texture. If you deal with night sweats or hate wrestling with loose fitted sheets, these do exactly what they are supposed to do. Time will tell if they hold their white color.... Report | G14: US | H14: =TRUE() -> TRUE | I14: =FALSE() -> FALSE | J14: comfort_softness; thermal_breathability; fit_sizing; shrinkage; colour_fading; care_wrinkles; authenticity_material; packaging | K14: Case-insensitive keyword mentions; multi-label; no positive/negative classification; displayed helpfulness sample, not random.
A15: PDP_CA_duvet | B15: B0C699R8B6 | C15: CA | D15: R31JY7WM9TG1Q4 | E15: Canada on August 18, 2026 | F15: Samuel Noack 5 out of 5 stars Cozy, cotton, & light Reviewed in Canada on August 18, 2026 Size: Queen (90" x 90")Colour Name: Linen Verified Purchase This duvet cover is gorgeous and comfy. Love that it’s 100% cotton, has a linen look which feels lived in, and has a functional zipper. It’s also nice and light, so it doesn’t add much weight to your duvet/comforter. I got the linen colour and it’s a nice warm shade. I was going for soft neutrals and a bit more warmth since there’s a lot of grey around (for now). It looks fine against the grey, even better in person and in better lighting than my picture shows. Matches my linen cover from Ikea pretty well. 9 people found this helpful Helpful Report | G15: CA | H15: =FALSE() -> FALSE | I15: =TRUE() -> TRUE | J15: comfort_softness; thermal_breathability; colour_fading; authenticity_material | K15: Case-insensitive keyword mentions; multi-label; no positive/negative classification; displayed helpfulness sample, not random.
A16: PDP_CA_duvet | B16: B0C699R8B6 | C16: CA | D16: R1NLB9QBOGVUVW | E16: Canada on August 26, 2024 | F16: Tracey 5 out of 5 stars IM SO PLEASED!!! Reviewed in Canada on August 26, 2024 Size: California King (104" x 98")Colour Name: Bright White Verified Purchase I researched for weeks, read so many reviews, and spent so much time looking for the right duvet cover because I’m so picky. I don’t like duvet covers because they are a pain to put on, the duvet gets all twisted inside, and you lose the light, delicate feeling of the down feathers. May as well just use a regular synthetic comforter if you are going to put a wrong cover on but I was tired of constantly dry cleaning and buying new duvets. IM SO HAPPY WITH THIS DUVET COVER!!!! Bright white is actually bright white. There’s no chemical odour as others have stated in other reviews. The size is accurate. Measure your duvet as they widely vary in size. Not one curse word putting it on my duvet. The 4 corner ties are placed correctly. Right out of the package the cover had only minimal wrinkles. The quality is fantastic for the price.. better than I expected! The cotton material is just perfect.. not too thick but not cheap n thin either. I love the feel of the material. I’m thinking of buying another just for backup purposes. Highly recommend!! 69 people found this helpful Helpful Report | G16: CA | H16: =FALSE() -> FALSE | I16: =TRUE() -> TRUE | J16: comfort_softness; fit_sizing; care_wrinkles; value; authenticity_material; packaging | K16: Case-insensitive keyword mentions; multi-label; no positive/negative classification; displayed helpfulness sample, not random.
A17: PDP_CA_duvet | B17: B0C699R8B6 | C17: CA | D17: R1FJ55NZAUQAIX | E17: Canada on October 8, 2026 | F17: Loveridge1 5 out of 5 stars Best bang for your buck! Reviewed in Canada on October 8, 2026 Size: King (104" x 90")Colour Name: Mauve Brown Verified Purchase Really great quality and breathable. Doesn't feel stuffy or hot at all. I will definitely buy a second one/diff colour in the future. Helpful Report | G17: CA | H17: =FALSE() -> FALSE | I17: =TRUE() -> TRUE | J17: thermal_breathability; colour_fading | K17: Case-insensitive keyword mentions; multi-label; no positive/negative classification; displayed helpfulness sample, not random.
A18: PDP_CA_duvet | B18: B0C699R8B6 | C18: CA | D18: RM37CLRYBV9WY | E18: Canada on July 27, 2026 | F18: LM 4 out of 5 stars Feels like linen. Softer when washed. 4 inside loops Reviewed in Canada on July 27, 2026 Size: Full (80" x 90")Colour Name: Olive Green Verified Purchase So far good quality. The ties inside are loops. I guess i could cut in half to make a tie. They are on each corner on the inside of the duvet cover. Helpful Report | G18: CA | H18: =FALSE() -> FALSE | I18: =TRUE() -> TRUE | J18: fit_sizing | K18: Case-insensitive keyword mentions; multi-label; no positive/negative classification; displayed helpfulness sample, not random.
A19: PDP_CA_duvet | B19: B0C699R8B6 | C19: CA | D19: R1Y8QF0MMUP4S6 | E19: Canada on October 13, 2026 | F19: NadiaB 5 out of 5 stars Makes the bed look so chic Reviewed in Canada on October 13, 2026 Size: Queen (90" x 90")Colour Name: Mauve Brown Verified Purchase Felt it was a little pricey, but I love this duvet cover. It has a linen look to it and the colour is exactly what I was looking for (like taupe but they call it mauve brown). Has strong inside to tie the duvet insert and the zipper glides really well. One person found this helpful Helpful Report | G19: CA | H19: =FALSE() -> FALSE | I19: =TRUE() -> TRUE | J19: colour_fading; value | K19: Case-insensitive keyword mentions; multi-label; no positive/negative classification; displayed helpfulness sample, not random.
A20: PDP_CA_duvet | B20: B0C699R8B6 | C20: CA | D20: R1VUOZI8ZY4FV5 | E20: Canada on August 24, 2026 | F20: Chelsea 5 out of 5 stars MUST HAVE!!! Reviewed in Canada on August 24, 2026 Size: Queen (90" x 90")Colour Name: Mauve Brown Verified Purchase Absolutely love this duvet cover it’s soft. It feels like linen, which has a luxurious feeling when I climb into bed also love love love the colour obsessed. 2 people found this helpful Helpful Report | G20: CA | H20: =FALSE() -> FALSE | I20: =TRUE() -> TRUE | J20: comfort_softness; colour_fading | K20: Case-insensitive keyword mentions; multi-label; no positive/negative classification; displayed helpfulness sample, not random.
A21: PDP_CA_duvet | B21: B0C699R8B6 | C21: CA | D21: R24LZ8D3KWVI3R | E21: Canada on December 22, 2025 | F21: Caiti Rose 3 out of 5 stars Great Look and Feel, but didn't last a year. Reviewed in Canada on December 22, 2025 Size: King (104" x 90")Colour Name: Forest Green Verified Purchase I was initially really happy with this duvet cover. It was the perfect colour and "linen look" that I wanted without a crazy price tag. This set has a lovely, soft, live-in feel right out of the package and the natural wrinkles gave the bed a cozy vibe. I've had this for just under a year now and while it's been a dream to sleep under, the quality just hasn't held up as well as I hoped it would. I recently noticed a significant rip after running it through the wash and while I sure I can get a few more weeks out of it, it definitely needs to be replaced soon. If you're looking for a guest room set that won't be used every night, this is a perfect, stylish choice, but for a primary bed, be aware that the lightweight nature of the cotton means it might not survive a full year of regular use. Definitely a "get what you pay for" type of situation. 19 people found this helpful Helpful Report | G21: CA | H21: =FALSE() -> FALSE | I21: =TRUE() -> TRUE | J21: comfort_softness; durability_pilling; colour_fading; care_wrinkles; value; authenticity_material; packaging | K21: Case-insensitive keyword mentions; multi-label; no positive/negative classification; displayed helpfulness sample, not random.
A22: PDP_CA_duvet | B22: B0C699R8B6 | C22: CA | D22: R38MOJFLYLF881 | E22: Canada on September 26, 2026 | F22: Nancy 5 out of 5 stars My favorite cover Reviewed in Canada on September 26, 2026 Size: King (104" x 90")Colour Name: Cream Grey Verified Purchase This is my favorite cover. Looks amazing in our country life vibe room. The texture, the comfort, I don't find it too warm. My security blanket. The corner ties are great as well for it to never move out of place, and the zipper enclosures us people who can't stand the button look Helpful Report | G22: CA | H22: =FALSE() -> FALSE | I22: =TRUE() -> TRUE | J22: comfort_softness; thermal_breathability; fit_sizing | K22: Case-insensitive keyword mentions; multi-label; no positive/negative classification; displayed helpfulness sample, not random.
A23: PDP_CA_duvet | B23: B0C699R8B6 | C23: CA | D23: R7GR58RCW10FH | E23: the United States on May 17, 2024 | F23: Sue (TheCozyIntrovert) 5 out of 5 stars It’s crispy- in a good way Reviewed in the United States on May 17, 2024 Size: Queen (90" x 90")Colour Name: Sage Green Verified Purchase I have used the jersey knit duvet by this same brand for years and absolutely loved it. I decided to search for another duvet and could not find one anywhere that I liked. I decided to just get a different color of the jersey knit one and realized that they had another version. I got the sage green one and it’s super cool and crisp. I love a soft bed in the winter, but in the summer I want a crispy bed and that’s exactly what this is. Seriously, it’s so hard to find good bedding now days, it’s hard to believe these inexpensive Amazon duvet covers are good, but they are! Report | G23: US | H23: =FALSE() -> FALSE | I23: =TRUE() -> TRUE | J23: comfort_softness; thermal_breathability; colour_fading | K23: Case-insensitive keyword mentions; multi-label; no positive/negative classification; displayed helpfulness sample, not random.
A24: PDP_CA_duvet | B24: B0C699R8B6 | C24: CA | D24: RO44U76YCJCJ5 | E24: the United States on August 30, 2021 | F24: Kennedy 5 out of 5 stars Great duvet cover! Reviewed in the United States on August 30, 2021 Size: Full (80" x 90")Colour Name: Cornflower Blue Verified Purchase I got one in grey when I went to college for my dorm and it was so comfy and super soft! I then had to go back home for online school and bought another for my room at home! It has stayed super nice and soft even through time and after multiple washes. I have sensory issues also and had no issue with the cover being itchy or weird feeling. Report | G24: US | H24: =FALSE() -> FALSE | I24: =TRUE() -> TRUE | J24: comfort_softness; care_wrinkles | K24: Case-insensitive keyword mentions; multi-label; no positive/negative classification; displayed helpfulness sample, not random.
A25: PDP_CA_duvet | B25: B0C699R8B6 | C25: CA | D25: RP78HG3URGTQG | E25: the United States on February 27, 2024 | F25: marybeth00 5 out of 5 stars Lovely Color, true to picture. Reviewed in the United States on February 27, 2024 Size: Twin (68" x 90")Colour Name: Cornflower Blue Verified Purchase Perfect color and fits my twin duvet nicely. Report | G25: US | H25: =FALSE() -> FALSE | I25: =TRUE() -> TRUE | J25: fit_sizing; colour_fading | K25: Case-insensitive keyword mentions; multi-label; no positive/negative classification; displayed helpfulness sample, not random.
A26: PDP_CA_duvet | B26: B0C699R8B6 | C26: CA | D26: R11ABQYN2FKOVD | E26: the United States on December 28, 2024 | F26: Megan Nystrand 4 out of 5 stars Really beautiful color! Reviewed in the United States on December 28, 2024 Size: Queen (90" x 90")Colour Name: Forest Green Verified Purchase The fabric could be softer, but the overall color and fit is just beautiful. Report | G26: US | H26: =FALSE() -> FALSE | I26: =TRUE() -> TRUE | J26: comfort_softness; fit_sizing; colour_fading | K26: Case-insensitive keyword mentions; multi-label; no positive/negative classification; displayed helpfulness sample, not random.
... A36: PDP_CA_protector | B36: B01E02DU0U | C36: CA | D36: R2QT6IFFH21FDJ | E36: the United States on September 12, 2026 | F36: Rex Marvin Beach 5 out of 5 stars Bamboo mattress protector Reviewed in the United States on September 12, 2026 Item Parcel Quantity: 1Size: Queen Verified Purchase The queen bamboo mattress cover was soft to the touch and the sides stretched to fit snugly. My cat accidentally urinated on the cover. The protector cover underneath worked. I washed it in vold water and low heat and it looked like new. It's the best mattress cover I ever had, and it's price is quite affordable. Report | G36: US | H36: =FALSE() -> FALSE | I36: =TRUE() -> TRUE | J36: comfort_softness; thermal_breathability; fit_sizing; care_wrinkles; value; authenticity_material | K36: Case-insensitive keyword mentions; multi-label; no positive/negative classification; displayed helpfulness sample, not random.
A37: PDP_CA_protector | B37: B01E02DU0U | C37: CA | D37: R6CWQ2XY6EVOO | E37: Mexico on October 25, 2025 | F37: Tx town & country 5 out of 5 stars nice Reviewed in Mexico on October 25, 2025 Item Parcel Quantity: 1Size: Twin Verified Purchase Nice quality Report | G37: Other | H37: =FALSE() -> FALSE | I37: =TRUE() -> TRUE | K37: Case-insensitive keyword mentions; multi-label; no positive/negative classification; displayed helpfulness sample, not random.
A38: PDP_CA_protector | B38: B01E02DU0U | C38: CA | D38: R2756D6ITO34QJ | E38: the United States on October 12, 2026 | F38: b 5 out of 5 stars Perfect protector! Reviewed in the United States on October 12, 2026 Item Parcel Quantity: 1Size: Queen Verified Purchase This is a great mattress protector! Thankfully I’ve had no spills yet, but I did have an incident with Mother Nature coming very unexpectedly, and nothing got through this protector to my mattress. The stain even came right out in the wash. I toss and turn a lot in my sleep, and this stays perfectly in place. I haven’t had any issues with it shifting or popping off. It’s held up great in the wash, and I haven’t noticed any issues with it not being breathable. For under $20, this is more than worth it and I’m glad to know my mattress will stay nice and clean with this on. Report | G38: US | H38: =FALSE() -> FALSE | I38: =TRUE() -> TRUE | J38: thermal_breathability; colour_fading; care_wrinkles; value; waterproof_noise | K38: Case-insensitive keyword mentions; multi-label; no positive/negative classification; displayed helpfulness sample, not random.
A39: PDP_CA_protector | B39: B01E02DU0U | C39: CA | D39: R2I0GAA50Q26A8 | E39: Mexico on December 22, 2022 | F39: Martha Patricia 5 out of 5 stars Muy bueno Reviewed in Mexico on December 22, 2022 Item Parcel Quantity: 1Size: Queen Verified Purchase Excelente Report | G39: Other | H39: =FALSE() -> FALSE | I39: =TRUE() -> TRUE | K39: Case-insensitive keyword mentions; multi-label; no positive/negative classification; displayed helpfulness sample, not random.
A40: PDP_CA_protector | B40: B01E02DU0U | C40: CA | D40: R1XAIUILN62NNI | E40: the United States on September 19, 2026 | F40: Danny Ross 5 out of 5 stars Look no further for comfort Reviewed in the United States on September 19, 2026 Item Parcel Quantity: 1Size: Twin Verified Purchase Purchases as a replacement for my other one that I had from another brand and this is 10 times better. I have a twin size mattress that is 15 in in height and this stays in place. It is super soft while also retaining its shape and has definitely helped during some nights of intense sweat. Protected my mattress and get out of a better product. Super simple to clean as well. If you're looking for something to protect your mattress, this is the one. Report | G40: US | H40: =FALSE() -> FALSE | I40: =TRUE() -> TRUE | J40: comfort_softness; fit_sizing | K40: Case-insensitive keyword mentions; multi-label; no positive/negative classification; displayed helpfulness sample, not random.
A41: PDP_CA_sheets | B41: B0DST3PF14 | C41: CA | D41: R278J83VWZMMW7 | E41: Canada on October 3, 2026 | F41: K Allinson 5 out of 5 stars Great quality sheets Reviewed in Canada on October 3, 2026 Size: QueenColour Name: Light Blue Verified Purchase Excellent quality sheets. Love them Helpful Report | G41: CA | H41: =FALSE() -> FALSE | I41: =TRUE() -> TRUE | K41: Case-insensitive keyword mentions; multi-label; no positive/negative classification; displayed helpfulness sample, not random.
A42: PDP_CA_sheets | B42: B0DST3PF14 | C42: CA | D42: R3LLWIX6TJBH0D | E42: Canada on August 14, 2026 | F42: Gene D. 4 out of 5 stars Would not work Reviewed in Canada on August 14, 2026 Verified Purchase Pockets were not deep enough. Ask for 18” pocket got 15” Helpful Report | G42: CA | H42: =FALSE() -> FALSE | I42: =TRUE() -> TRUE | J42: fit_sizing | K42: Case-insensitive keyword mentions; multi-label; no positive/negative classification; displayed helpfulness sample, not random.
A43: PDP_CA_sheets | B43: B0DST3PF14 | C43: CA | D43: R1TD1QTIKG3QZZ | E43: Canada on September 1, 2026 | F43: Westcove 5 out of 5 stars Quality Reviewed in Canada on September 1, 2026 Verified Purchase My second set, they are nice and deep and cover the mattress and base. Nice cotton Helpful Report | G43: CA | H43: =FALSE() -> FALSE | I43: =TRUE() -> TRUE | J43: fit_sizing; authenticity_material | K43: Case-insensitive keyword mentions; multi-label; no positive/negative classification; displayed helpfulness sample, not random.
A44: PDP_CA_sheets | B44: B0DST3PF14 | C44: CA | D44: RBUSYCV7W0DZJ | E44: Canada on January 21, 2026 | F44: Katelyn Dickson 1 out of 5 stars Thin but fitted sheet fits Reviewed in Canada on January 21, 2026 Size: QueenColour Name: Ivory Verified Purchase Tried it on my bed before washing to make sure the fitted sheet would fit. After washing, it no longer fit. The material is sooo thin and scratchy. The quality is half that of the cheap off brand Ive had for years. Super disappointed. Will be returning. Helpful Report | G44: CA | H44: =FALSE() -> FALSE | I44: =TRUE() -> TRUE | J44: fit_sizing; care_wrinkles; value | K44: Case-insensitive keyword mentions; multi-label; no positive/negative classification; displayed helpfulness sample, not random.
A45: PDP_CA_sheets | B45: B0DST3PF14 | C45: CA | D45: R2BJGW9R2ASXBW | E45: Canada on July 27, 2025 | F45: SK 3 out of 5 stars Rougher than expected Reviewed in Canada on July 27, 2025 Verified Purchase A little rougher than expected for 100% cotton. Also smelt very bad until it was washed. Wouldnt recommend unless you like rougher sheets. Helpful Report | G45: CA | H45: =FALSE() -> FALSE | I45: =TRUE() -> TRUE | J45: care_wrinkles; authenticity_material | K45: Case-insensitive keyword mentions; multi-label; no positive/negative classification; displayed helpfulness sample, not random.
A46: PDP_CA_sheets | B46: B0DST3PF14 | C46: CA | D46: R1K6UGVZAZDMYR | E46: Canada on August 4, 2025 | F46: Amazon_Junkie 5 out of 5 stars Hands down best sheets! Reviewed in Canada on August 4, 2025 Size: QueenColour Name: Light Blue Verified Purchase I like these so much that I've bought 2 sets, and will purchase another set in a different colour. They are soft and get softer with each wash, but more than that, they BREATHE. As a woman who suffers from hot flashes, these have saved me. Sadly, microfiber though lovely and smooth, just left me a sweaty mess. These are cool in the summer and warm in the winter. I layered with 100% cotton blankets, and I'm a happy camper. 9 people found this helpful Helpful Report | G46: CA | H46: =FALSE() -> FALSE | I46: =TRUE() -> TRUE | J46: comfort_softness; thermal_breathability; colour_fading; care_wrinkles; authenticity_material | K46: Case-insensitive keyword mentions; multi-label; no positive/negative classification; displayed helpfulness sample, not random.
A47: PDP_CA_sheets | B47: B0DST3PF14 | C47: CA | D47: R40UNLI0ZV17P | E47: Canada on June 4, 2026 | F47: mirrandy 4 out of 5 stars Seems good. As described Reviewed in Canada on June 4, 2026 Verified Purchase As described but be careful about shrinking. There's some shrinking but it still fits well. Not too tight or loose. So far I'm happy. Will have to see about durability. Helpful Report | G47: CA | H47: =FALSE() -> FALSE | I47: =TRUE() -> TRUE | J47: fit_sizing; durability_pilling; shrinkage | K47: Case-insensitive keyword mentions; multi-label; no positive/negative classification; displayed helpfulness sample, not random.
A48: PDP_CA_sheets | B48: B0DST3PF14 | C48: CA | D48: RKHD751UM6RPM | E48: Canada on October 18, 2025 | F48: Shelly 5 out of 5 stars Good quality and prices Reviewed in Canada on October 18, 2025 Verified Purchase Good quality for good price Helpful Report | G48: CA | H48: =FALSE() -> FALSE | I48: =TRUE() -> TRUE | J48: value | K48: Case-insensitive keyword mentions; multi-label; no positive/negative classification; displayed helpfulness sample, not random.
A49: PDP_CA_sheets | B49: B0DST3PF14 | C49: CA | D49: R2RMH02RZ4Q1P5 | E49: Mexico on April 3, 2026 | F49: Jose Gerardo Avila Gomez 5 out of 5 stars Cumple ampliamente mis expectativas Reviewed in Mexico on April 3, 2026 Verified Purchase Excelente calidad Report Translate review to English | G49: Other | H49: =FALSE() -> FALSE | I49: =TRUE() -> TRUE | K49: Case-insensitive keyword mentions; multi-label; no positive/negative classification; displayed helpfulness sample, not random.
A50: PDP_CA_sheets | B50: B0DST3PF14 | C50: CA | D50: R3OC9EOS2MPZ6L | E50: the United States on August 3, 2020 | F50: Satisfied customer 5 out of 5 stars Awesome sheets Reviewed in the United States on August 3, 2020 Verified Purchase Best sheets ever - I plan to purchase another set/color. I purchased the blue set - and the color is just as vibrant in person as it is online. Report | G50: US | H50: =FALSE() -> FALSE | I50: =TRUE() -> TRUE | J50: colour_fading | K50: Case-insensitive keyword mentions; multi-label; no positive/negative classification; displayed helpfulness sample, not random.
A51: PDP_CA_sheets | B51: B0DST3PF14 | C51: CA | D51: R2EB4LWKRQZUFX | E51: the United States on June 4, 2020 | F51: Ann Nominus 5 out of 5 stars Gorgeous color on silky soft cotton Reviewed in the United States on June 4, 2020 Verified Purchase Bought several sets of pillowcases for just my bed. These are beautiful and match my new sheets. I've washed them and they are even more soft than before. Treat yourself in your favorite color!! Report | G51: US | H51: =FALSE() -> FALSE | I51: =TRUE() -> TRUE | J51: comfort_softness; colour_fading; care_wrinkles | K51: Case-insensitive keyword mentions; multi-label; no positive/negative classification; displayed helpfulness sample, not random.
A52: PDP_CA_sheets | B52: B0DST3PF14 | C52: CA | D52: R2BUAFESY5T4HO | E52: the United States on March 7, 2020 | F52: Gotcha 5 out of 5 stars Great price and value. Excellent product Reviewed in the United States on March 7, 2020 Verified Purchase What a great shopping experience super fast delivery like next day practically. Excellent value never had to leave the comfort of my home. You can't beat that Report | G52: US | H52: =FALSE() -> FALSE | I52: =TRUE() -> TRUE | J52: comfort_softness; value; packaging | K52: Case-insensitive keyword mentions; multi-label; no positive/negative classification; displayed helpfulness sample, not random.
A53: PDP_CA_sheets | B53: B0DST3PF14 | C53: CA | D53: R1KW5IPM70BSV6 | E53: the United States on June 6, 2020 | F53: TasFitz 5 out of 5 stars Sleep's Best Friend Reviewed in the United States on June 6, 2020 Verified Purchase These are a vibrant royal blue. They are so soft and thick. Great price for the quality! Report | G53: US | H53: =FALSE() -> FALSE | I53: =TRUE() -> TRUE | J53: comfort_softness; value | K53: Case-insensitive keyword mentions; multi-label; no positive/negative classification; displayed helpfulness sample, not random.
A54: PDP_CA_topper | B54: B07D5DN269 | C54: CA | D54: R3S5GSNX99YX4L | E54: Canada on October 16, 2026 | F54: Amazon Customer 5 out of 5 stars Poofy soft Reviewed in Canada on October 16, 2026 Colour Name: GreenSize: QueenItem thickness string: Standard Inches Verified Purchase Arrived as expected. Fluffed up in dryer on low for 20 mins. Fit perfectly. Turned my slightly too firm mattress into poofy and soft. Way more comfortable sleep. Also noticed it's not making me hot like my old memory foam topper did. Haven't had for long but so far so good. One person found this helpful Helpful Report | G54: CA | H54: =FALSE() -> FALSE | I54: =TRUE() -> TRUE | J54: comfort_softness; thermal_breathability; fit_sizing; care_wrinkles; packaging | K54: Case-insensitive keyword mentions; multi-label; no positive/negative classification; displayed helpfulness sample, not random.
A55: PDP_CA_topper | B55: B07D5DN269 | C55: CA | D55: RAHXTGU694SSD | E55: Canada on October 19, 2026 | F55: Amazon Customer 5 out of 5 stars Great for neck and back pain Reviewed in Canada on October 19, 2026 Colour Name: GreenSize: QueenItem thickness string: Standard Inches Verified Purchase I was having extreme neck and back pain before I purchased this. I just noticed that it has almost gone away. I feel so much better. It feels soft and comfy and I’m having a great night. Sleep on it. I highly recommend it. I very seldom do a review, but this one deserves one. 3 people found this helpful Helpful Report | G55: CA | H55: =FALSE() -> FALSE | I55: =TRUE() -> TRUE | J55: comfort_softness | K55: Case-insensitive keyword mentions; multi-label; no positive/negative classification; displayed helpfulness sample, not random.
A56: PDP_CA_topper | B56: B07D5DN269 | C56: CA | D56: R3H1H2RBCNONGE | E56: Canada on September 27, 2026 | F56: Caroline lacombe 4 out of 5 stars Bien contente Reviewed in Canada on September 27, 2026 Colour Name: GreenSize: QueenItem thickness string: Standard Inches Verified Purchase Bien moelleux et apaise tres bien les points de pression au courant de la nuit On se lève avec le corps reposé Pour le prix, ca vaut la peine Mon chat et moi ont l'adore 😻 L'étoile manquante: jaurais aimé quil soit un peu plus epais 5 people found this helpful Helpful Report Translate review to English | G56: CA | H56: =FALSE() -> FALSE | I56: =TRUE() -> TRUE | J56: comfort_softness; value | K56: Case-insensitive keyword mentions; multi-label; no positive/negative classification; displayed helpfulness sample, not random.
A57: PDP_CA_topper | B57: B07D5DN269 | C57: CA | D57: RNFGJ0SJEAUWQ | E57: Canada on October 8, 2026 | F57: D Thomson 5 out of 5 stars Love this mattress topper Reviewed in Canada on October 8, 2026 Colour Name: GreenSize: KingItem thickness string: Standard Inches Verified Purchase I love this mattress topper. It is gonna hold us over very well until we can afford a new mattress as the fabric on the top of the mattress is starting to split around the buttons so this gives us a nice barrier between the filling and our sheet. It’s just enough cushioning to be comfortable and not bulky. 3 people found this helpful Helpful Report | G57: CA | H57: =FALSE() -> FALSE | I57: =TRUE() -> TRUE | J57: comfort_softness | K57: Case-insensitive keyword mentions; multi-label; no positive/negative classification; displayed helpfulness sample, not random.
A58: PDP_CA_topper | B58: B07D5DN269 | C58: CA | D58: R3U5LO8ZG3SIAQ | E58: Canada on September 26, 2026 | F58: Kellie Burgess 5 out of 5 stars Comfy- soft and helped Reviewed in Canada on September 26, 2026 Colour Name: GreenSize: QueenItem thickness string: Standard Inches Verified Purchase Have been having some back and side pain after knee surgery and was hoping this would help with sleeping; it’s amazing. So comfy and has minimized the pain with the extra cushioning. Highly recommended- Can’t wait to crawl into bed at night. 7 people found this helpful Helpful Report | G58: CA | H58: =FALSE() -> FALSE | I58: =TRUE() -> TRUE | J58: comfort_softness | K58: Case-insensitive keyword mentions; multi-label; no positive/negative classification; displayed helpfulness sample, not random.
A59: PDP_CA_topper | B59: B07D5DN269 | C59: CA | D59: RBLL0R7RGY6CD | E59: Canada on October 9, 2026 | F59: SL 3 out of 5 stars Comfortable but not very durable Reviewed in Canada on October 9, 2026 Colour Name: GreenSize: KingItem thickness string: Standard Inches Verified Purchase Really happy with this topper in terms of comfort and cooling factor. The night it was in the wash we could immediately tell because it's that effective. For a king-sized mattress this is a pretty good price point ($80) and was enough of an improvement to get us through until we replace our mattress. Unfortunately it came out of its first wash cycle with an enormous hole, which is kind of a bummer. Will still use it, but not sure if it'll make it through a second wash 🫠 One note is that the green text on the cover is visible through your bedding if you have white sheets - I don't really care, but that may bother some people. 2 people found this helpful Helpful Report | G59: CA | H59: =FALSE() -> FALSE | I59: =TRUE() -> TRUE | J59: comfort_softness; thermal_breathability; fit_sizing; durability_pilling; care_wrinkles; value | K59: Case-insensitive keyword mentions; multi-label; no positive/negative classification; displayed helpfulness sample, not random.
A60: PDP_CA_topper | B60: B07D5DN269 | C60: CA | D60: R2XW5GKLZDPNTW | E60: Canada on September 14, 2026 | F60: Marie-Claude Guay 5 out of 5 stars Tout a fait soyeux et ultra confortable Reviewed in Canada on September 14, 2026 Colour Name: GreenSize: Twin XLItem thickness string: Standard Inches Verified Purchase Fantastique. Il ajoute un confort très surprenant. C'est c9mme dormir sur un nuage. Il est soyeux, juste assez epais pour donner le confort "hotel" . Il est exactement comme l'avait décrit les autres personnes qui l'avaient acheté. Dans mon cas, c'était pour rajouter par dessus un matelas de tente roulotte et c'est maintenant un parfait . Je recommande ce produit et je vais sûrement en acheter un autre pour la maison. 2 people found this helpful Helpful Report Translate review to English | G60: CA | H60: =FALSE() -> FALSE | I60: =TRUE() -> TRUE | K60: Case-insensitive keyword mentions; multi-label; no positive/negative classification; displayed helpfulness sample, not random.
A61: PDP_CA_topper | B61: B07D5DN269 | C61: CA | D61: R15W3E54B5RGPB | E61: Canada on September 18, 2026 | F61: Saint 4 out of 5 stars Comfortable - but could be better! Reviewed in Canada on September 18, 2026 Colour Name: New GreySize: TwinItem thickness string: Standard Inches Verified Purchase Satisfied with this mattress cover. Exactly as described. Perfect size, seems to be holding up nice. Definitely thought it could be a little more comfortable by the description- but overall I’m happy with purchase. 3 people found this helpful Helpful Report | G61: CA | H61: =FALSE() -> FALSE | I61: =TRUE() -> TRUE | J61: comfort_softness; fit_sizing | K61: Case-insensitive keyword mentions; multi-label; no positive/negative classification; displayed helpfulness sample, not random.
A62: PDP_CA_topper | B62: B07D5DN269 | C62: CA | D62: R1649QR6WCIC1H | E62: Japan on September 20, 2026 | F62: Erica Whitsell 1 out of 5 stars Not as advertised Reviewed in Japan on September 20, 2026 Colour Name: New GreySize: TwinItem thickness string: Standard Inches Verified Purchase It is not like it is advertised. I was expecting a thick, squishy, memory foam-like mattress pad but it’s not. It’s very soft so there is no support at all. I already have a foam mattress topper on my bed but my bed is still too hard so I bought this. It made almost no difference. It’s also not nearly as thick as shown in the photos even after “inflating” overnight. I was concerned when it came shrink wrapped in a tiny package. If you’re looking for true support I wouldn’t recommend this. Report | G62: Other | H62: =FALSE() -> FALSE | I62: =TRUE() -> TRUE | J62: comfort_softness; shrinkage; packaging | K62: Case-insensitive keyword mentions; multi-label; no positive/negative classification; displayed helpfulness sample, not random.
A63: PDP_CA_topper | B63: B07D5DN269 | C63: CA | D63: R1DQ2B6QSG103A | E63: Mexico on August 23, 2026 | F63: Myrna chavez 5 out of 5 stars Super Reviewed in Mexico on August 23, 2026 Colour Name: GreenSize: QueenItem thickness string: Standard Inches Verified Purchase Excelente compra!! Report Translate review to English | G63: Other | H63: =FALSE() -> FALSE | I63: =TRUE() -> TRUE | K63: Case-insensitive keyword mentions; multi-label; no positive/negative classification; displayed helpfulness sample, not random.
A64: PDP_CA_topper | B64: B07D5DN269 | C64: CA | D64: R1Q4V6X58PLS9R | E64: the United Kingdom on February 15, 2024 | F64: Amazon Customer 5 out of 5 stars Can’t believe it! Reviewed in the United Kingdom on February 15, 2024 Colour Name: GreenSize: FullItem thickness string: Standard Inches Verified Purchase I rarely write reviews but just had to convey how good this topper is. My fiancée suffers with fibromyalgia amongst multiple other mobility issues. We couldn’t justify buying a new mattress but she was waking up each day in pain. We then purchased a Silent Night mattress topper, which added a bit of support but not much. After reading some reviews we decided to give this a shot rather than opting for a more expensive branded one which we couldn’t really afford. Long story short, we are SO glad we purchased this! We got the Bamboo topper option, and immediately after removing from the packaging we saw just how cushioned it was. I shook it and let it sit for around half a hour before making the bed. Putting it over the mattress and original topper we had was simpler than other topper options - usually they rely on elastic or just balance on top and move around in the night. This topper has a full elasticated fabric skirt which easily fits our double mattress. The topper has completely reinvented our uncomfortable mattress! The cushioning is just the right balance of bouncy yet firm, and honestly feels like sleeping on a fancy hotel bed. Granted we are using it in combination with the Silent Night offering, but the shift in comfort after adding this topper is unreal. I realise I’ve written a lot but I really hope this can help someone in a situation similar to ours who cannot afford an expensive orthopaedic mattress and needs a solution that, whilst not as cheap as some others, is a great deal more reasonable than some brands. I will update this if anything changes but seeing my partner wake up in significantly less pain is proof enough for me that this is a great purchase. My only fault if I had to pick one as it doesn’t have cooling properties like it claims. This may be somewhat to do with layering it on top of another topper. However, this is a tiny issue in the scheme of just how incredible it is to sleep on for the price we paid. I’m always hesitant to fork out close to £50 for something I haven’t even tried in person, but I’m so glad we took this gamble. My partner and I both have different wants in a mattress, especially given her medical needs, but this works perfectly for us both! Essay over - these reviews helped me make my decision so I hope this one assists someone else! Read more Report | G64: UK | H64: =FALSE() -> FALSE | I64: =TRUE() -> TRUE | J64: comfort_softness; thermal_breathability; fit_sizing; value; authenticity_material; packaging | K64: Case-insensitive keyword mentions; multi-label; no positive/negative classification; displayed helpfulness sample, not random.
A65: PDP_CA_topper | B65: B07D5DN269 | C65: CA | D65: R2EP3K7SHP1KDX | E65: the United States on September 17, 2026 | F65: Anahlee 5 out of 5 stars Totally recommend Reviewed in the United States on September 17, 2026 Colour Name: WhiteSize: Twin XLItem thickness string: Standard Inches Verified Purchase Great cushioning and extremely easy to put onto any bed!! accurate fit Report | G65: US | H65: =FALSE() -> FALSE | I65: =TRUE() -> TRUE | J65: fit_sizing | K65: Case-insensitive keyword mentions; multi-label; no positive/negative classification; displayed helpfulness sample, not random.
A66: PDP_CA_topper | B66: B07D5DN269 | C66: CA | D66: R2IRMAUV5I47KB | E66: the United Arab Emirates on September 21, 2025 | F66: obaid saeed almehairi 2 out of 5 stars Not worthy Reviewed in the United Arab Emirates on September 21, 2025 Colour Name: GreenSize: Twin XLItem thickness string: Standard Inches Verified Purchase Not worth waste of time Report | G66: Other | H66: =FALSE() -> FALSE | I66: =TRUE() -> TRUE | J66: value | K66: Case-insensitive keyword mentions; multi-label; no positive/negative classification; displayed helpfulness sample, not random.
A67: PDP_UK_bamboo | B67: B0DN1DDRHR | C67: UK | D67: R1927XQUDJL779 | E67: the United States on 11 September 2026 | F67: Tina Galyon 5 out of 5 stars Best sheets I’ve ever bought! Reviewed in the United States on 11 September 2026 Size Name: QueenColour Name: 01-white Verified Purchase These are literally the best sheets I’ve ever bought! So buttery soft! They fit my queen bed just like they should. The pockets are just deep enough to fit each corner. They don’t come off at all. There has also been no pilling or uncomfortable balls. They are cooling, my hot sleeping husband says they are very breathable. The thickness is also another perfect point!!!! Will be buying these every time I need new sheets!!! Report | G67: US | H67: =FALSE() -> FALSE | I67: =TRUE() -> TRUE | J67: comfort_softness; thermal_breathability; fit_sizing; durability_pilling | K67: Case-insensitive keyword mentions; multi-label; no positive/negative classification; displayed helpfulness sample, not random.
A68: PDP_UK_bamboo | B68: B0DN1DDRHR | C68: UK | D68: R1SBR0LEZOWAOK | E68: Mexico on 20 August 2026 | F68: Evelina Aguilar 4 out of 5 stars Frescura Reviewed in Mexico on 20 August 2026 Size Name: KingColour Name: 05-sea Glass Verified Purchase Son frescas. de recomienda para los días de calor Report Translate review to English | G68: Other | H68: =FALSE() -> FALSE | I68: =TRUE() -> TRUE | J68: thermal_breathability | K68: Case-insensitive keyword mentions; multi-label; no positive/negative classification; displayed helpfulness sample, not random.
A69: PDP_UK_bamboo | B69: B0DN1DDRHR | C69: UK | D69: R2GSNVS323TX4G | E69: the United States on 23 September 2026 | F69: Melissa Howard 5 out of 5 stars Satiny soft, smooth, and cooling! Reviewed in the United States on 23 September 2026 Size Name: FullColour Name: 15-olive Green Verified Purchase These sheets are incredible! So soft, smooth, and cooling! They feel like absolutely luxury for a very affordable price. The color is vibrant. I can be under a top sheet and duvet and still the sheets don't get hot. Perfect for those hot sleepers or if you want to treat yourself or your guests to a fancy, luxurious bed! I haven't noticed any excessive wrinkling beyond the expected "rumpling" of being slept on. Smoothing it out with your hand works well if you're going for that "magazine" styling when you make your bed. I will be buying more sets of this for our guest room and more colors for my bed! Report | G69: US | H69: =FALSE() -> FALSE | I69: =TRUE() -> TRUE | J69: comfort_softness; thermal_breathability; colour_fading; care_wrinkles; value | K69: Case-insensitive keyword mentions; multi-label; no positive/negative classification; displayed helpfulness sample, not random.
A70: PDP_UK_bamboo | B70: B0DN1DDRHR | C70: UK | D70: RBATVZ9L3E0J1 | E70: the United States on 27 September 2026 | F70: Kelsey Badour 5 out of 5 stars Worth the money Reviewed in the United States on 27 September 2026 Size Name: KingColour Name: 07-bluish Grey Verified Purchase Amazing and feels really soft and like the actually stay on the bed and the sheets have like a cold feel to especially with the fan on Report | G70: US | H70: =FALSE() -> FALSE | I70: =TRUE() -> TRUE | J70: comfort_softness | K70: Case-insensitive keyword mentions; multi-label; no positive/negative classification; displayed helpfulness sample, not random.
A71: PDP_UK_bamboo | B71: B0DN1DDRHR | C71: UK | D71: R16ISUR8XPT406 | E71: the United States on 14 October 2026 | F71: TS 4 out of 5 stars My favorite summer sheets Reviewed in the United States on 14 October 2026 Size Name: KingColour Name: 07-bluish Grey Verified Purchase LOVE the soft, cool feel of these sheets. They are my new favorite sheets, especially for the summertime when you want to feel a little bit cooler. They are soft and have nice straps that keep the sheet corners on thick mattresses. The color selection is nice and offers a great variety. The only reason for four stars instead of five is because you only get two pillowcases. For a king set there should be four pillowcases. These sheets are a great price for what you get, however. Report | G71: US | H71: =FALSE() -> FALSE | I71: =TRUE() -> TRUE | J71: comfort_softness; thermal_breathability; fit_sizing; colour_fading; value | K71: Case-insensitive keyword mentions; multi-label; no positive/negative classification; displayed helpfulness sample, not random.
A72: PDP_UK_duvet | B72: B00J4RM850 | C72: UK | D72: R4MVZ7L8MW2SG | E72: the United Kingdom on 17 April 2026 | F72: Meredith 5 out of 5 stars Feels so much nicer than mixed fibre and pure white looks so fresh Reviewed in the United Kingdom on 17 April 2026 Size Name: DoubleColour Name: White Verified Purchase Just spent by first night under this Duvet cover. As delivered, it could benefit from ironing as being cotton, and folded up for packaging, there are quite a few creases, but it is very comfortable and feels much nicer than the duvet cover it replaces which was a mixed fibre. This feels so much nicer, and though I usually get patterned covers, simple white has made my room look airier and fresher. Super! I am delighted with the purchase and consider it very good value for a 100% Egyptian Cotton cover. The pillow cases are alo nice and fit snugly ovr my pillows. I typically prefer Oxford style, but as I have four pillows on my bed I am using such styled cases on the top two of my bed which works perfectly. I don't thinmk with Oxford style pillowcases one would wish the lower cases to be so styled, so the two normal cases included are perfect for purpose. 2 people found this helpful Helpful Report | G72: UK | H72: =FALSE() -> FALSE | I72: =TRUE() -> TRUE | J72: comfort_softness; fit_sizing; care_wrinkles; value; authenticity_material; packaging | K72: Case-insensitive keyword mentions; multi-label; no positive/negative classification; displayed helpfulness sample, not random.
A73: PDP_UK_duvet | B73: B00J4RM850 | C73: UK | D73: R2ZHH5I7FMQAMG | E73: the United Kingdom on 5 August 2026 | F73: K Hirst 5 out of 5 stars If you want a single bedding set that looks smart, this is a good buy Reviewed in the United Kingdom on 5 August 2026 Size Name: SingleColour Name: Black Verified Purchase If you are wondering whether this bedding set will make a single bed look more finished without spending silly money, yes. It is one of those simple purchases that makes the whole room look tidier straight away. The black colour looks clean and smart, the cotton feels pleasant, and having the matching pillowcase included makes it easy to put the bed together properly. It is not trying to be fancy for the sake of it, it just does the everyday job well and looks better than mismatched bedding. My tip would be to give it a wash first and fit it carefully at the corners so it sits neatly. Comfortable, good looking and very easy to recommend. Five stars. One person found this helpful Helpful Report | G73: UK | H73: =FALSE() -> FALSE | I73: =TRUE() -> TRUE | J73: comfort_softness; fit_sizing; colour_fading; care_wrinkles; authenticity_material | K73: Case-insensitive keyword mentions; multi-label; no positive/negative classification; displayed helpfulness sample, not random.
A74: PDP_UK_duvet | B74: B00J4RM850 | C74: UK | D74: RH9I86P79MR3Q | E74: the United Kingdom on 18 December 2025 | F74: Withdrawnmist 4 out of 5 stars ⭐️⭐️⭐️⭐️ Lovely quality, but wash separately at first Reviewed in the United Kingdom on 18 December 2025 Size Name: SingleColour Name: Red Verified Purchase The Sapphire Collection 100% Egyptian Cotton 200 Thread Count duvet cover with pillowcases is very good quality overall and feels comfortable and breathable to sleep under. The cotton is soft, smooth, and pleasant against the skin, and the fabric feels well made rather than thin or flimsy. It has that crisp, fresh feel you’d expect from Egyptian cotton and sits nicely on the bed. The stitching and finish are also good, with no loose threads or quality issues, and it washes well in terms of keeping its shape and texture. However, it’s very important to wash this bedding separately the first time. Unfortunately, it did release dye and stained some of my other clothes in the wash. This was disappointing and something buyers should be aware of, especially if washing with lighter items. Once washed on its own, it’s been absolutely fine, and the colour now seems stable. Because of this initial issue, I’ve knocked one star off what would otherwise be a five-star product. Pros: Soft, comfortable Egyptian cotton Good weight and breathable fabric Well made with a quality finish Cons: Must be washed separately initially due to colour bleed Overall, it’s a good duvet set with a nice feel and finish, but take care with the first wash. Shopping research Spend a few minutes for better results Read more 11 people found this helpful Helpful Report | G74: UK | H74: =FALSE() -> FALSE | I74: =TRUE() -> TRUE | J74: comfort_softness; thermal_breathability; colour_fading; care_wrinkles; authenticity_material | K74: Case-insensitive keyword mentions; multi-label; no positive/negative classification; displayed helpfulness sample, not random.
A75: PDP_UK_duvet | B75: B00J4RM850 | C75: UK | D75: RRX7PHVRA34Y5 | E75: the United Kingdom on 15 October 2026 | F75: Anjanie Emmanuel 5 out of 5 stars Great item Reviewed in the United Kingdom on 15 October 2026 Size Name: KingColour Name: White Verified Purchase Feels beautiful to sleep under Helpful Report | G75: UK | H75: =FALSE() -> FALSE | I75: =TRUE() -> TRUE | K75: Case-insensitive keyword mentions; multi-label; no positive/negative classification; displayed helpfulness sample, not random.
A76: PDP_UK_duvet | B76: B00J4RM850 | C76: UK | D76: R3E4QMVO5NAY72 | E76: the United Kingdom on 26 September 2026 | F76: Janet MacDonald 5 out of 5 stars Feels great Reviewed in the United Kingdom on 26 September 2026 Size Name: DoubleColour Name: Teal Verified Purchase Lovely material, feels great, washes well One person found this helpful Helpful Report | G76: UK | H76: =FALSE() -> FALSE | I76: =TRUE() -> TRUE | J76: care_wrinkles | K76: Case-insensitive keyword mentions; multi-label; no positive/negative classification; displayed helpfulness sample, not random.
A77: PDP_UK_duvet | B77: B00J4RM850 | C77: UK | D77: R1AYM08FK35575 | E77: the United Kingdom on 5 October 2026 | F77: Adele Mauback 5 out of 5 stars Niiiice!! Reviewed in the United Kingdom on 5 October 2026 Size Name: DoubleColour Name: White Verified Purchase Comfort at its finest One person found this helpful Helpful Report | G77: UK | H77: =FALSE() -> FALSE | I77: =TRUE() -> TRUE | J77: comfort_softness | K77: Case-insensitive keyword mentions; multi-label; no positive/negative classification; displayed helpfulness sample, not random.
A78: PDP_UK_duvet | B78: B00J4RM850 | C78: UK | D78: R3CKIPB3C38Z8W | E78: the United Kingdom on 28 January 2026 | F78: Emily Dawe 3 out of 5 stars Bad smell Reviewed in the United Kingdom on 28 January 2026 Size Name: KingColour Name: White Verified Purchase Product arrived quickly. A little disappointed with the quality of the product. It feels scratchy and not how ‘Egyptian cotton’ should feel. It also had an awful fishy smell. I have since washed and it has come out smelling fresh. But I can tell the product won’t last long due to quality. 3 people found this helpful Helpful Report | G78: UK | H78: =FALSE() -> FALSE | I78: =TRUE() -> TRUE | J78: care_wrinkles; authenticity_material; packaging | K78: Case-insensitive keyword mentions; multi-label; no positive/negative classification; displayed helpfulness sample, not random.
A79: PDP_UK_duvet | B79: B00J4RM850 | C79: UK | D79: RAYBVQX5GAWER | E79: the United Kingdom on 10 September 2026 | F79: Linky 4 out of 5 stars Good but wrong colour Reviewed in the United Kingdom on 10 September 2026 Size Name: KingColour Name: Grey Verified Purchase The covers are really comfortable and feel nice to the touch. My only concern is I ordered a grey duvet cover but it’s actually brown. One person found this helpful Helpful Report | G79: UK | H79: =FALSE() -> FALSE | I79: =TRUE() -> TRUE | J79: comfort_softness | K79: Case-insensitive keyword mentions; multi-label; no positive/negative classification; displayed helpfulness sample, not random.
A80: PDP_UK_duvet | B80: B00J4RM850 | C80: UK | D80: R25YJNAOV4OT5T | E80: Italy on 19 October 2016 | F80: HowImetYourCat 5 out of 5 stars Ottima qualità di tessuto Reviewed in Italy on 19 October 2016 Size Name: KingColour Name: Black Verified Purchase Ho acquistato il set e, nonostante il mio letto sia un 150x200 ho scelto la king size in quanto al momento era l'unica disponibile adatta a non lasciarmi a schiena all'aria. La qualità del cotone è ottima, regge bene ai lavaggi e con i giusti prodotti e temperature non scolorisce nemmeno, e le misure di 220 x 230 sono perfette per coprire a sufficienza ma senza esagerare. Report Translate review to English | G80: Other | H80: =FALSE() -> FALSE | I80: =TRUE() -> TRUE | J80: fit_sizing; care_wrinkles | K80: Case-insensitive keyword mentions; multi-label; no positive/negative classification; displayed helpfulness sample, not random.
A81: PDP_UK_duvet | B81: B00J4RM850 | C81: UK | D81: R2SA4T32BWLYO1 | E81: Spain on 30 April 2026 | F81: Amazon Customer 5 out of 5 stars Very happy with the quality & good price Reviewed in Spain on 30 April 2026 Size Name: KingColour Name: White Verified Purchase Very good quality Report | G81: Other | H81: =FALSE() -> FALSE | I81: =TRUE() -> TRUE | K81: Case-insensitive keyword mentions; multi-label; no positive/negative classification; displayed helpfulness sample, not random.
A82: PDP_UK_duvet | B82: B00J4RM850 | C82: UK | D82: R3CXWSBXC30RKQ | E82: France on 2 February 2026 | F82: Fannette 5 out of 5 stars Très bon produit Reviewed in France on 2 February 2026 Size Name: SingleColour Name: White Verified Purchase Description qui manque de précision sur le choix des dimensions je trouve par contre Report Translate review to English | G82: Other | H82: =FALSE() -> FALSE | I82: =TRUE() -> TRUE | K82: Case-insensitive keyword mentions; multi-label; no positive/negative classification; displayed helpfulness sample, not random.
A83: PDP_UK_duvet | B83: B00J4RM850 | C83: UK | D83: RIJPIJ29K9546 | E83: Germany on 19 December 2017 | F83: Tower 5 out of 5 stars Endlich ein Bezug, worin die Decke hält Reviewed in Germany on 19 December 2017 Size Name: DoubleColour Name: Black Verified Purchase Wir haben uns irgendwann mal eine große Bettdecke gegönnt (200x200) und alle bisher bestellten Bezüge waren nicht das Wahre, da die Decke darin immer verrutschte. Super nervig. In diesem Bezug passiert es nicht, juhuu :D Ich habe keine Ahnung, wovon das abhängig ist, aber wir lieben diesen Bezug und es wird direkt ein weiterer bestellt. Wie in den anderen Rezensionen zu lesen, haben die Kopfkissenbezüge keine herkömmliche, deutsche Größe. Scheinbar sind die Kissenbezüge für die USA ausgelegt, denn da sind diese Größen ganz typisch. Wie richtig in den Produktfotos abgebildet, sind es längliche Bezüge. Dass eine Seite offen ist, ist für diese "Verschlussart" (oder wie man es nennen möchte) völlig normal - genauso kenne ich diese Bezüge aus der USA. Na ja, da unsere Daunenkissen eh nicht pralle voll sind, können wir die untere Kante einfach umfalten und dann passen sie perfekt in die Bezüge. Report Translate review to English | G83: Other | H83: =FALSE() -> FALSE | I83: =TRUE() -> TRUE | K83: Case-insensitive keyword mentions; multi-label; no positive/negative classification; displayed helpfulness sample, not random.
A84: PDP_UK_duvet | B84: B00J4RM850 | C84: UK | D84: RNZ8SKEBPYL8T | E84: Germany on 17 April 2017 | F84: Sandra 4 out of 5 stars Super Farbe, passt perfekt, einfach zu verschließen Reviewed in Germany on 17 April 2017 Size Name: KingColour Name: Aubergine Verified Purchase Die Farbe ist wirklich sehr schön, der Stoff ist ziemlich dünn aber mit einer dicken Decke im inneren auch super für kalte Tage. Durch Druckknöpfe kann man die decke super einfach verschließen, der einzige Mangel ist, das die Decke beim waschen extrem Färbt (das Wasser wird komplett rot), also am besten separat waschen... Aber trotz allem leuchtet die Farbe nach der 5. wäsche noch Report Translate review to English | G84: Other | H84: =FALSE() -> FALSE | I84: =TRUE() -> TRUE | K84: Case-insensitive keyword mentions; multi-label; no positive/negative classification; displayed helpfulness sample, not random.
A85: PDP_UK_protector | B85: B08FRKXJ9R | C85: UK | D85: R14W9THIS5RY2B | E85: the United Kingdom on 22 August 2026 | F85: SanityGaming 5 out of 5 stars ⭐⭐⭐⭐⭐ 5/5 – Fantastic Quality, Exactly What I'd Expect from Silentnight Reviewed in the United Kingdom on 22 August 2026 Size Name: SingleSet name: 1 Pack Verified Purchase Really pleased with this Silentnight waterproof mattress protector. It's well made, feels good quality and does exactly what I wanted from a mattress protector. The overall construction feels reassuringly good rather than cheap or flimsy, and it fits nicely on the mattress. It's a simple product, but with something designed to protect your mattress, good materials and construction are exactly what matter. For me, it's the typical quality I've come to expect from Silentnight. There isn't any unnecessary complication – fit it to the bed and it gets on with doing its job. Overall, fantastic quality, nicely made and a good way of adding an extra layer of protection to your mattress. Very happy with it and would happily buy Silentnight again. ⭐⭐⭐⭐⭐ 3 people found this helpful Helpful Report | G85: UK | H85: =FALSE() -> FALSE | I85: =TRUE() -> TRUE | J85: fit_sizing; value; waterproof_noise | K85: Case-insensitive keyword mentions; multi-label; no positive/negative classification; displayed helpfulness sample, not random.
A86: PDP_UK_protector | B86: B08FRKXJ9R | C86: UK | D86: RW4A7MUEE103E | E86: the United Kingdom on 4 September 2026 | F86: Martin 5 out of 5 stars A good quality mattress protector Reviewed in the United Kingdom on 4 September 2026 Size Name: SingleSet name: 1 Pack Verified Purchase I really love this waterproof mattress protector. It is good quality for money and it fits the mattress well. It feels really soft and has worked well so far. 2 people found this helpful Helpful Report | G86: UK | H86: =FALSE() -> FALSE | I86: =TRUE() -> TRUE | J86: comfort_softness; fit_sizing; waterproof_noise | K86: Case-insensitive keyword mentions; multi-label; no positive/negative classification; displayed helpfulness sample, not random.
A87: PDP_UK_protector | B87: B08FRKXJ9R | C87: UK | D87: R4N68MRHRKCDK | E87: the United Kingdom on 24 June 2026 | F87: Cyprus2021 4 out of 5 stars Seems ok and just fits the double mattress Reviewed in the United Kingdom on 24 June 2026 Size Name: DoubleSet name: 1 Pack Verified Purchase Quite thin and waterproof one side like a sheet material on the top part that goes on the mattress but the same fabric not two separate ones, well it feels like it anyway, it was cheap but better than Terry towelling in this heat 4 people found this helpful Helpful Report | G87: UK | H87: =FALSE() -> FALSE | I87: =TRUE() -> TRUE | J87: thermal_breathability; value; waterproof_noise | K87: Case-insensitive keyword mentions; multi-label; no positive/negative classification; displayed helpfulness sample, not random.
A88: PDP_UK_protector | B88: B08FRKXJ9R | C88: UK | D88: R1ZGYQCY9VC3KB | E88: the United Kingdom on 8 January 2024 | F88: Muhammad Iqbal 5 out of 5 stars Silentnight Waterproof Mattress Protector - Effective Protection with a Minor Noise Consideration Reviewed in the United Kingdom on 8 January 2024 Size Name: SingleSet name: 4 Pack Verified Purchase The Silentnight Waterproof Mattress Protector has proven to be a valuable addition, offering effective mattress protection. While its waterproof feature is commendable, it's worth noting that it can be a bit noisy when sleeping directly on it. However, this minor concern can be easily mitigated by placing a thicker sheet over it. Pros: Effective Waterproofing: The mattress protector successfully safeguards the mattress against spills and stains, providing reliable protection and extending the mattress's lifespan. Easy to Clean: The waterproof feature makes cleaning a breeze, preventing liquids from seeping into the mattress and simplifying the maintenance process. Secure Fit: The protector fits well on the mattress, staying securely in place without slipping or bunching during use. Cons: Minor Noise Issue: When sleeping directly on the protector, there is a noticeable noise when feet rub against it. This may affect individuals sensitive to sounds during sleep. Recommendation: To address the noise concern, I recommend placing another thicker sheet over the Silentnight Waterproof Mattress Protector. This simple solution not only mitigates the noise issue but also enhances overall comfort. The protector remains a valuable investment for preserving the mattress while requiring a small adjustment for noise reduction. Conclusion: The Silentnight Waterproof Mattress Protector fulfills its primary purpose of protecting the mattress effectively. While there is a minor noise consideration, this can be easily resolved by layering an additional sheet. Overall, it's a practical choice for maintaining a clean and protected sleeping surface, and I recommend it for those looking for reliable mattress protection. Read more 65 people found this helpful Helpful Report | G88: UK | H88: =FALSE() -> FALSE | I88: =TRUE() -> TRUE | J88: comfort_softness; fit_sizing; colour_fading; value; waterproof_noise | K88: Case-insensitive keyword mentions; multi-label; no positive/negative classification; displayed helpfulness sample, not random.
A89: PDP_UK_protector | B89: B08FRKXJ9R | C89: UK | D89: RFB6SMZ7SPC6S | E89: the United Kingdom on 9 November 2024 | F89: Maggs 5 out of 5 stars Silentnight waterproof single sheet Reviewed in the United Kingdom on 9 November 2024 Size Name: SingleSet name: 1 Pack Verified Purchase This is a great product bought at a good average price. I had compared lots for price instore and online, eventually choosing this as silent night is a reliable brand and this had decent feedback. I'm using it on my young child's single bed, it is a good fit with elasticated corners. The mattress is thinner than most as is a bunk bed mattress, this means that the sheet has excess depth but easy enough to tuck under and doesn't cause any issues. The protector was well packaged on arrival, no weird smell to the sheet on unfolding, some packaged items like these tend to adopt odd scents. This is virtually noise less, I can hear the tiniest of rusting when there is movement but it is nothing that causes a disturbance. So far no wet nights so cannot comment on its effectiveness but I have faith in the brand. I've sat on the bed, there is no discomfort from this being under the bedsheets, infact I'd go as far as saying you can't tell it's there to begin with. Great buy. Would buy again and I recommend it. Read more 8 people found this helpful Helpful Report | G89: UK | H89: =FALSE() -> FALSE | I89: =TRUE() -> TRUE | J89: fit_sizing; value; waterproof_noise; packaging | K89: Case-insensitive keyword mentions; multi-label; no positive/negative classification; displayed helpfulness sample, not random.
A90: PDP_UK_protector | B90: B08FRKXJ9R | C90: UK | D90: R17I9N9SE44ADH | E90: the United Kingdom on 15 July 2026 | F90: katybgood 5 out of 5 stars Comfy and waterproof Reviewed in the United Kingdom on 15 July 2026 Size Name: DoubleSet name: 4 Pack Verified Purchase This is the second time I’ve bought these mattress protectors. They do what they say, they’re waterproof and they’re comfy. They don’t rustle and sound waterproof like others I’ve tried. Helpful Report | G90: UK | H90: =FALSE() -> FALSE | I90: =TRUE() -> TRUE | J90: comfort_softness; waterproof_noise | K90: Case-insensitive keyword mentions; multi-label; no positive/negative classification; displayed helpfulness sample, not random.
A91: PDP_UK_protector | B91: B08FRKXJ9R | C91: UK | D91: R2CDCPOR4D8O4I | E91: the United Kingdom on 20 October 2026 | F91: Joanne beech 5 out of 5 stars Totally worth the money, great waterproof protector Reviewed in the United Kingdom on 20 October 2026 Size Name: DoubleSet name: 1 Pack Verified Purchase Happy with purchase, can confirm it's waterproof and didn't go through at all, Helpful Report | G91: UK | H91: =FALSE() -> FALSE | I91: =TRUE() -> TRUE | J91: waterproof_noise | K91: Case-insensitive keyword mentions; multi-label; no positive/negative classification; displayed helpfulness sample, not random.
A92: PDP_UK_protector | B92: B08FRKXJ9R | C92: UK | D92: RZKTZ4VTMNDKS | E92: the United Kingdom on 24 May 2026 | F92: Faith OJ 3 out of 5 stars But too plasticky Reviewed in the United Kingdom on 24 May 2026 Size Name: DoubleSet name: 1 Pack Verified Purchase Does what it says on the tin. But a bit too plasticky for my liking. Leading some rustling noise, it’s a bit sweaty and manages to slide off the bed it one corner after a couple nights :( One person found this helpful Helpful Report | G92: UK | H92: =FALSE() -> FALSE | I92: =TRUE() -> TRUE | J92: fit_sizing; waterproof_noise | K92: Case-insensitive keyword mentions; multi-label; no positive/negative classification; displayed helpfulness sample, not random.
A93: PDP_UK_protector | B93: B08FRKXJ9R | C93: UK | D93: R1FTSUG7993O4Z | E93: Spain on 25 July 2025 | F93: joanna 5 out of 5 stars Completely waterproof Reviewed in Spain on 25 July 2025 Size Name: DoubleSet name: 1 Pack Verified Purchase Completely waterproof unlike others that claim to be. Not made with noisy material either. Report | G93: Other | H93: =FALSE() -> FALSE | I93: =TRUE() -> TRUE | J93: waterproof_noise | K93: Case-insensitive keyword mentions; multi-label; no positive/negative classification; displayed helpfulness sample, not random.
A94: PDP_UK_protector | B94: B08FRKXJ9R | C94: UK | D94: R1KCG4QW1ZKQGU | E94: Ireland on 3 March 2026 | F94: Amazon Customer 5 out of 5 stars Arrived in clear plastic Reviewed in Ireland on 3 March 2026 Size Name: DoubleSet name: 1 Pack Verified Purchase Very thin. Arrived in clear packing. Report | G94: Other | H94: =FALSE() -> FALSE | I94: =TRUE() -> TRUE | J94: packaging | K94: Case-insensitive keyword mentions; multi-label; no positive/negative classification; displayed helpfulness sample, not random.
A95: PDP_UK_protector | B95: B08FRKXJ9R | C95: UK | D95: R1LIRQFH5YQ38H | E95: Ireland on 11 May 2026 | F95: Eamon Mahoney 1 out of 5 stars Absolutely not waterproof Reviewed in Ireland on 11 May 2026 Size Name: SingleSet name: 1 Pack Verified Purchase Absolutely not waterproof. Urine stains soaked straight through onto the mattress. Have no idea where these other 5 star reviews are coming from Report | G95: Other | H95: =FALSE() -> FALSE | I95: =TRUE() -> TRUE | J95: colour_fading; waterproof_noise | K95: Case-insensitive keyword mentions; multi-label; no positive/negative classification; displayed helpfulness sample, not random.
A96: PDP_UK_protector | B96: B08FRKXJ9R | C96: UK | D96: R9V4LU030QHVB | E96: Spain on 27 April 2025 | F96: Ismaelmg 5 out of 5 stars Muy buena elección Reviewed in Spain on 27 April 2025 Size Name: SingleSet name: 1 Pack Verified Purchase Muy buena calidad. Una vez puesto no se nota.Ajusta muy bien. Report Translate review to English | G96: Other | H96: =FALSE() -> FALSE | I96: =TRUE() -> TRUE | K96: Case-insensitive keyword mentions; multi-label; no positive/negative classification; displayed helpfulness sample, not random.
A97: PDP_UK_protector | B97: B08FRKXJ9R | C97: UK | D97: R2F6ISPC51AYDF | E97: Spain on 11 July 2024 | F97: sara stokes 5 out of 5 stars Perfecto Reviewed in Spain on 11 July 2024 Size Name: KingSet name: 1 Pack Verified Purchase Funciona muy bien y no se causa el cuerpo sudar, no podemos darnos cuenta de que está en la cama! Report Translate review to English | G97: Other | H97: =FALSE() -> FALSE | I97: =TRUE() -> TRUE | K97: Case-insensitive keyword mentions; multi-label; no positive/negative classification; displayed helpfulness sample, not random.
A98: PDP_UK_sheets | B98: B0CGJGRFW9 | C98: UK | D98: R37LNLDJDAQE0Q | E98: the United Kingdom on 4 May 2026 | F98: maggiemoo 5 out of 5 stars Ample size Reviewed in the United Kingdom on 4 May 2026 Size Name: QueenColour Name: 02 - White Verified Purchase A fantastic set lots of sheet which covers my king size bed Good value Helpful Report | G98: UK | H98: =FALSE() -> FALSE | I98: =TRUE() -> TRUE | J98: fit_sizing; value | K98: Case-insensitive keyword mentions; multi-label; no positive/negative classification; displayed helpfulness sample, not random.
A99: PDP_UK_sheets | B99: B0CGJGRFW9 | C99: UK | D99: R2RCKUVOT3N195 | E99: the United Kingdom on 24 April 2026 | F99: Susan Simpson 5 out of 5 stars Very soft Reviewed in the United Kingdom on 24 April 2026 Size Name: QueenColour Name: 12 - Sage Verified Purchase Fabulous. Very good fabric. Helpful Report | G99: UK | H99: =FALSE() -> FALSE | I99: =TRUE() -> TRUE | K99: Case-insensitive keyword mentions; multi-label; no positive/negative classification; displayed helpfulness sample, not random.
A100: PDP_UK_sheets | B100: B0CGJGRFW9 | C100: UK | D100: R3FALCSLBKJA8P | E100: the United Kingdom on 31 October 2025 | F100: Dalecia Baptiste 5 out of 5 stars The quality and size is very important. Reviewed in the United Kingdom on 31 October 2025 Size Name: QueenColour Name: 02 - White Verified Purchase Sticks to the perfect size. quality is soft and comfortable. Helpful Report | G100: UK | H100: =FALSE() -> FALSE | I100: =TRUE() -> TRUE | J100: comfort_softness; fit_sizing | K100: Case-insensitive keyword mentions; multi-label; no positive/negative classification; displayed helpfulness sample, not random.
A101: PDP_UK_sheets | B101: B0CGJGRFW9 | C101: UK | D101: R3GIDA7WEWI8YJ | E101: the United Kingdom on 3 April 2025 | F101: Zebroo 4 out of 5 stars Incorrect sizing Reviewed in the United Kingdom on 3 April 2025 Size Name: QueenColour Name: 02 - White Verified Purchase Really good quality and great price, but incorrect sizing - requested queen but sent double. Helpful Report | G101: UK | H101: =FALSE() -> FALSE | I101: =TRUE() -> TRUE | J101: fit_sizing; value | K101: Case-insensitive keyword mentions; multi-label; no positive/negative classification; displayed helpfulness sample, not random.
A102: PDP_UK_sheets | B102: B0CGJGRFW9 | C102: UK | D102: R2K9S9TXJLZZ49 | E102: the United Kingdom on 4 April 2026 | F102: sandra wyse 5 out of 5 stars Good value Reviewed in the United Kingdom on 4 April 2026 Size Name: QueenColour Name: 02 - White Verified Purchase Very comfty Helpful Report | G102: UK | H102: =FALSE() -> FALSE | I102: =TRUE() -> TRUE | K102: Case-insensitive keyword mentions; multi-label; no positive/negative classification; displayed helpfulness sample, not random.
A103: PDP_UK_sheets | B103: B0CGJGRFW9 | C103: UK | D103: R361PS3D317IZS | E103: the United Kingdom on 20 December 2025 | F103: phooey 5 out of 5 stars Bed topper Reviewed in the United Kingdom on 20 December 2025 Size Name: KingColour Name: Black Verified Purchase Very good fits well Very soft Helpful Report | G103: UK | H103: =FALSE() -> FALSE | I103: =TRUE() -> TRUE | J103: comfort_softness; fit_sizing | K103: Case-insensitive keyword mentions; multi-label; no positive/negative classification; displayed helpfulness sample, not random.
A104: PDP_UK_sheets | B104: B0CGJGRFW9 | C104: UK | D104: R1NLW8GYT8JECW | E104: the United Kingdom on 29 November 2025 | F104: Xabier Bustinduy 5 out of 5 stars Great value Reviewed in the United Kingdom on 29 November 2025 Size Name: QueenColour Name: 02 - White Verified Purchase Very soft Helpful Report | G104: UK | H104: =FALSE() -> FALSE | I104: =TRUE() -> TRUE | J104: comfort_softness | K104: Case-insensitive keyword mentions; multi-label; no positive/negative classification; displayed helpfulness sample, not random.
A105: PDP_UK_sheets | B105: B0CGJGRFW9 | C105: UK | D105: R35V7O4WE8RIDG | E105: the United Kingdom on 26 November 2025 | F105: Brian, Glasgow 5 out of 5 stars Utopia bedding Reviewed in the United Kingdom on 26 November 2025 Size Name: QueenColour Name: 02 - White Verified Purchase Excellent value for the money luxury without doubt Helpful Report | G105: UK | H105: =FALSE() -> FALSE | I105: =TRUE() -> TRUE | J105: value | K105: Case-insensitive keyword mentions; multi-label; no positive/negative classification; displayed helpfulness sample, not random.
A106: PDP_UK_sheets | B106: B0CGJGRFW9 | C106: UK | D106: R10IMHBP1XK27F | E106: Singapore on 3 April 2026 | F106: Andrew N. 5 out of 5 stars Comfortable Reviewed in Singapore on 3 April 2026 Size Name: TwinColour Name: 02 - White Verified Purchase Soft and comfy. Recommend. Report | G106: Other | H106: =FALSE() -> FALSE | I106: =TRUE() -> TRUE | J106: comfort_softness | K106: Case-insensitive keyword mentions; multi-label; no positive/negative classification; displayed helpfulness sample, not random.
A107: PDP_UK_sheets | B107: B0CGJGRFW9 | C107: UK | D107: R12D98XKKB2KUT | E107: Germany on 14 April 2025 | F107: NT 5 out of 5 stars Soft and Comfortable Reviewed in Germany on 14 April 2025 Size Name: KingColour Name: 01 - White Verified Purchase I love this sheet set. It's soft and comfortable and simply elegant. Report | G107: Other | H107: =FALSE() -> FALSE | I107: =TRUE() -> TRUE | J107: comfort_softness | K107: Case-insensitive keyword mentions; multi-label; no positive/negative classification; displayed helpfulness sample, not random.
A108: PDP_UK_sheets | B108: B0CGJGRFW9 | C108: UK | D108: R15QXXRHFBMAHN | E108: the United States on 3 August 2023 | F108: Shereka Braithwaite 5 out of 5 stars 100% quality Reviewed in the United States on 3 August 2023 Verified Purchase Utopia never fails. Always delivering quality sheets and it's the color is case resistant and qhzet is so soft and comfy Report | G108: US | H108: =FALSE() -> FALSE | I108: =TRUE() -> TRUE | J108: comfort_softness; colour_fading; packaging | K108: Case-insensitive keyword mentions; multi-label; no positive/negative classification; displayed helpfulness sample, not random.
A109: PDP_UK_sheets | B109: B0CGJGRFW9 | C109: UK | D109: R1AWIBJQVML0SJ | E109: the United States on 21 June 2026 | F109: Rukhsar 3 out of 5 stars Good Reviewed in the United States on 21 June 2026 Verified Purchase Bedsheet quality is good and soft. Color was nice and price was normal Report | G109: US | H109: =FALSE() -> FALSE | I109: =TRUE() -> TRUE | J109: comfort_softness; colour_fading; value | K109: Case-insensitive keyword mentions; multi-label; no positive/negative classification; displayed helpfulness sample, not random.
...

Sheet Review themes
A1: reviewer_country | B1: theme | C1: mentions | D1: sample_n | E1: share | F1: interpretation
A2: US | B2: comfort_softness | C2: 17 | D2: 25 | E2: 0.68 | F2: Mention frequency only, not complaint prevalence or population estimate
A3: US | B3: thermal_breathability | C3: 11 | D3: 25 | E3: 0.44 | F3: Mention frequency only, not complaint prevalence or population estimate
A4: US | B4: fit_sizing | C4: 10 | D4: 25 | E4: 0.4 | F4: Mention frequency only, not complaint prevalence or population estimate
A5: US | B5: durability_pilling | C5: 2 | D5: 25 | E5: 0.08 | F5: Mention frequency only, not complaint prevalence or population estimate
A6: US | B6: shrinkage | C6: 1 | D6: 25 | E6: 0.04 | F6: Mention frequency only, not complaint prevalence or population estimate
A7: US | B7: colour_fading | C7: 13 | D7: 25 | E7: 0.52 | F7: Mention frequency only, not complaint prevalence or population estimate
A8: US | B8: care_wrinkles | C8: 9 | D8: 25 | E8: 0.36 | F8: Mention frequency only, not complaint prevalence or population estimate
A9: US | B9: value | C9: 9 | D9: 25 | E9: 0.36 | F9: Mention frequency only, not complaint prevalence or population estimate
A10: US | B10: authenticity_material | C10: 4 | D10: 25 | E10: 0.16 | F10: Mention frequency only, not complaint prevalence or population estimate
A11: US | B11: waterproof_noise | C11: 1 | D11: 25 | E11: 0.04 | F11: Mention frequency only, not complaint prevalence or population estimate
A12: US | B12: packaging | C12: 4 | D12: 25 | E12: 0.16 | F12: Mention frequency only, not complaint prevalence or population estimate
A13: CA | B13: comfort_softness | C13: 25 | D13: 40 | E13: 0.625 | F13: Mention frequency only, not complaint prevalence or population estimate
... A45: Other | B45: packaging | C45: 3 | D45: 24 | E45: 0.125 | F45: Mention frequency only, not complaint prevalence or population estimate

Sheet Keywords and ads
A1: Market | B1: Query | C1: Bucket | D1: Observed cards | E1: Sponsored-labelled cards | F1: Search volume | G1: Organic rank domestic | H1: CPC | I1: CTR | J1: Order CVR | K1: ACoS | L1: ROAS | M1: TACoS | N1: Source | O1: Limit
A2: CA | B2: bamboo viscose sheet set | C2: bamboo | D2: 48 | E2: 0 | F2: GAP | G2: GAP | H2: GAP | I2: GAP | J2: GAP | K2: GAP | L2: GAP | M2: GAP | N2: LIVE_CA_bamboo | O2: Observed sponsored cards only; absence is not zero ad competition. No search volume, search-share or CPC inferred. UK quilt/comforter must be localized.
A3: CA | B3: comforter set | C3: comforter | D3: 48 | E3: 0 | F3: GAP | G3: GAP | H3: GAP | I3: GAP | J3: GAP | K3: GAP | L3: GAP | M3: GAP | N3: LIVE_CA_comforter | O3: Observed sponsored cards only; absence is not zero ad competition. No search volume, search-share or CPC inferred. UK quilt/comforter must be localized.
A4: CA | B4: cotton duvet cover set | C4: duvet | D4: 48 | E4: 0 | F4: GAP | G4: GAP | H4: GAP | I4: GAP | J4: GAP | K4: GAP | L4: GAP | M4: GAP | N4: LIVE_CA_duvet | O4: Observed sponsored cards only; absence is not zero ad competition. No search volume, search-share or CPC inferred. UK quilt/comforter must be localized.
A5: CA | B5: deep pocket fitted sheet | C5: fitted | D5: 48 | E5: 0 | F5: GAP | G5: GAP | H5: GAP | I5: GAP | J5: GAP | K5: GAP | L5: GAP | M5: GAP | N5: LIVE_CA_fitted | O5: Observed sponsored cards only; absence is not zero ad competition. No search volume, search-share or CPC inferred. UK quilt/comforter must be localized.
A6: CA | B6: linen sheet set | C6: linen | D6: 48 | E6: 0 | F6: GAP | G6: GAP | H6: GAP | I6: GAP | J6: GAP | K6: GAP | L6: GAP | M6: GAP | N6: LIVE_CA_linen | O6: Observed sponsored cards only; absence is not zero ad competition. No search volume, search-share or CPC inferred. UK quilt/comforter must be localized.
A7: CA | B7: lyocell sheet set | C7: lyocell | D7: 48 | E7: 0 | F7: GAP | G7: GAP | H7: GAP | I7: GAP | J7: GAP | K7: GAP | L7: GAP | M7: GAP | N7: LIVE_CA_lyocell | O7: Observed sponsored cards only; absence is not zero ad competition. No search volume, search-share or CPC inferred. UK quilt/comforter must be localized.
A8: CA | B8: cotton pillowcases | C8: pillowcase | D8: 48 | E8: 0 | F8: GAP | G8: GAP | H8: GAP | I8: GAP | J8: GAP | K8: GAP | L8: GAP | M8: GAP | N8: LIVE_CA_pillowcase | O8: Observed sponsored cards only; absence is not zero ad competition. No search volume, search-share or CPC inferred. UK quilt/comforter must be localized.
A9: CA | B9: waterproof mattress protector | C9: protector | D9: 48 | E9: 0 | F9: GAP | G9: GAP | H9: GAP | I9: GAP | J9: GAP | K9: GAP | L9: GAP | M9: GAP | N9: LIVE_CA_protector | O9: Observed sponsored cards only; absence is not zero ad competition. No search volume, search-share or CPC inferred. UK quilt/comforter must be localized.
A10: CA | B10: cotton quilt | C10: quilt | D10: 48 | E10: 0 | F10: GAP | G10: GAP | H10: GAP | I10: GAP | J10: GAP | K10: GAP | L10: GAP | M10: GAP | N10: LIVE_CA_quilt | O10: Observed sponsored cards only; absence is not zero ad competition. No search volume, search-share or CPC inferred. UK quilt/comforter must be localized.
A11: CA | B11: cotton sheet set | C11: sheets | D11: 58 | E11: 10 | F11: GAP | G11: GAP | H11: GAP | I11: GAP | J11: GAP | K11: GAP | L11: GAP | M11: GAP | N11: LIVE_CA_sheets | O11: Observed sponsored cards only; absence is not zero ad competition. No search volume, search-share or CPC inferred. UK quilt/comforter must be localized.
A12: CA | B12: mattress topper | C12: topper | D12: 48 | E12: 0 | F12: GAP | G12: GAP | H12: GAP | I12: GAP | J12: GAP | K12: GAP | L12: GAP | M12: GAP | N12: LIVE_CA_topper | O12: Observed sponsored cards only; absence is not zero ad competition. No search volume, search-share or CPC inferred. UK quilt/comforter must be localized.
A13: UK | B13: bamboo viscose sheet set | C13: bamboo | D13: 48 | E13: 0 | F13: GAP | G13: GAP | H13: GAP | I13: GAP | J13: GAP | K13: GAP | L13: GAP | M13: GAP | N13: LIVE_UK_bamboo | O13: Observed sponsored cards only; absence is not zero ad competition. No search volume, search-share or CPC inferred. UK quilt/comforter must be localized.
... A34: US | B34: mattress topper | C34: topper | D34: 48 | E34: 0 | F34: GAP | G34: GAP | H34: GAP | I34: GAP | J34: GAP | K34: GAP | L34: GAP | M34: GAP | N34: LIVE_US_topper | O34: Observed sponsored cards only; absence is not zero ad competition. No search volume, search-share or CPC inferred. UK quilt/comforter must be localized.

Sheet Channels
A1: Market | B1: Channel | C1: Demand proposition | D1: Acquisition | E1: Economics/operations | F1: Suitability | G1: Evidence
A2: US | B2: Amazon | C2: Large discoverable assortment; fast-fulfilment expectation | D2: Auction-driven acquisition; CPC/CVR not independently measured | E2: Referral, fulfilment, storage, returns and ads; strong ratings barriers | F2: Best to test a measurable point of difference with limited SKUs | G2: LIVE_US_*; F01
A3: CA | B3: Amazon | C3: Smaller addressable country; local fulfilment matters | D3: Do not assume cheaper CPC than US; unmeasured | E3: CAD exposure, duty, bilingual labels, dispersed last-mile costs | F3: Narrow locally-stocked assortment only after duty/landed-cost quote | G3: LIVE_CA_*; R07; R19; R26
A4: UK | B4: Amazon | C4: Price-sensitive sample; native sizes and vocabulary essential | D4: Head-term acquisition unmeasured; use native fitted/duvet terms | E4: VAT-inclusive retail and category/price-specific fee thresholds | F4: Test fitted/replacement and duvet propositions; confirm fee classification | G4: LIVE_UK_*; F03; R09
A5: All, separately | B5: DTC website | C5: Control education, bundles and email retention | D5: Paid social/search CAC unknown; organic/creator traffic not free | E5: No marketplace referral, but payment fees, 3PL, parcel shipping, returns and content CAC | F5: Useful for differentiated storytelling; standalone pillowcases need basket-building | G5: D01; channel assessment is analyst judgement
A6: US/CA/UK | B6: Other marketplaces | C6: Walmart/Wayfair/Etsy/eBay are candidate channels, not verified sales pools | D6: Own platform rules and advertising, not transferable Amazon CVR | E6: Service levels, commissions, return terms and handmade/resale eligibility vary | F6: Assess channel fit after product; do not assume all platforms accept a generic imported brand | G6: Analyst channel shortlist; fee/reach diligence pending
A7: US/CA/UK | B7: Retail / wholesale | C7: Shelf discovery and retailer trust | D7: Sell-in process replaces some consumer CAC; buyer acquisition still costs | E7: Wholesale price, trade allowances, chargebacks, terms and assortment commitments | F7: Only with buyer interest and quote-backed wholesale contribution | G7: M07-M09; C08
A8: UK first; US/CA secondary | B8: Hospitality / institutional | C8: Repeat replacement and wash performance matter | D8: Longer B2B selling/sampling cycle; no Amazon review moat | E8: Contract pricing, laundering validation, credit terms, local inventory and service | F8: Promising feasibility track for standard white cotton-rich linen; no demand contract secured | G8: M07-M09; C11-C14
A9: All, separately | B9: Private-label / contract manufacture | C9: Buyer supplies brand/channel; manufacturer supplies specification compliance | D9: Lower brand marketing burden, concentrated customer risk | E9: Tight quotes/MOQs, audits, payment risk, quality claims and working capital | F9: Potential Pakistan sourcing fit; no factory capability or capacity assumed | G9: C11; C12; C14; R12

Sheet Risks
A1: Risk | B1: Severity judgement | C1: Evidence/issue | D1: Mitigation | E1: Verification metric | F1: Sources
A2: Demand extrapolation | B2: High | C2: Industry totals include mattresses or non-bedding textiles; search pages are not TAM | D2: Use separate denominators; acquire country/category demand exports | E2: Independent demand data; 24-36 month series | F2: M01-M09
A3: Price/rank sampling | B3: High | C3: US/UK overseas destination; mixed configurations and variants; one time point | D3: Repeat domestic postcode, device and query panels; retain exact child identity | E3: At least repeated weekly snapshots and normalized size/set comparisons | F3: LIVE_*
A4: Advertising and cash burn | B4: High | C4: No credible bedding-specific country CPC/CVR benchmark recovered | D4: Pilot with loss cap and contribution-based CPC ceiling; no inferred competitor spend | E4: CPC, CTR, order CVR, refund-adjusted contribution, TACoS | F4: Scenario model
A5: Tariff and tax | B5: High | C5: No single Pakistan duty rate applies to all bedding or all countries | D5: Broker confirms fibre/construction HS code, origin and current additional duties | E5: Written landed quote and tax treatment | F5: R07; R22-R28
A6: Quality and material claims | B6: High | C6: Fit, bleed, membrane failure, shrinkage and fibre-authenticity risk | D6: Independent testing plus lot inspection and traceability | E6: Post-wash fit, colourfastness, pilling, leakage, complaint/return reasons | F6: R01-R04; R19; reviews
A7: Inventory fragmentation | B7: High | C7: Sizes x colours x sets multiply slow stock and replenishment gaps | D7: Limit assortment; size-level MOQ and reorder model | E7: DOS, sell-through, forecast error, aged inventory | F7: Analyst judgement
A8: Working capital / FX | B8: High | C8: PKR manufacturing cost may still be USD-invoiced; CAD/GBP sales and deposits | D8: Model settlement timing and FX stress; do not double-count inventory as expense | E8: Cash conversion cycle, deposit exposure, FX +/-10% | F8: Scenario model
A9: Review interpretation | B9: Medium-high | C9: Helpful/top reviews, Vine, imported reviews and variation pooling bias evidence | D9: Separate reviewer geography, incentives, dates and variant; balanced coding next | E9: Theme counts and denominators, recent low-star sample | F9: reviews_coded.json
A10: Regulatory scope | B10: High | C10: Filled pads/toppers, children, heated bedding differ from adult sheets | D10: Product-specific safety/label/chemical assessment before purchase order | E10: Test reports, labels, importer records, recall procedure | F10: R01; R04; R11; R19
A11: Supplier and transit | B11: High | C11: No factory quotation, audit, MOQ, capacity or shipping service verified | D11: RFQs and sample wash tests; quote Incoterms and local returns provider | E11: OTIF, defect rate, actual transit/cost, supplier concentration | F11: C11-C14; R12

Sheet Opportunity scorecard
A1: ID | B1: Country | C1: Opportunity | D1: Disposition | E1: Demand | F1: Growth | G1: Competition ease | H1: Differentiation | I1: Acquisition ease | J1: Contribution potential | K1: Manufacturing feasibility | L1: Capital efficiency | M1: Risk resilience | N1: Sources | O1: Logic | P1: Confidence | Q1: Weighted score
A2: O1 | B2: UK | C2: Hospitality/private-label cotton-rich white linen | D2: Investigate first | E2: 4 | F2: 3 | G2: 3 | H2: 4 | I2: 4 | J2: 3 | K2: 4 | L2: 3 | M2: 3 | N2: M08; R22-R25; C11-C14 | O2: Potential origin preference and repeat laundering need; confirm buyer demand and origin before assuming advantage | P2: Medium-low | Q2: =(E2*15+F2*5+G2*15+H2*15+I2*10+J2*15+K2*10+L2*10+M2*5)/5 -> 70
A3: O2 | B3: US | C3: Wash-tested cotton percale with verified mattress fit | D3: Investigate first | E3: 5 | F3: 3 | G3: 2 | H3: 4 | I3: 2 | J3: 3 | K3: 4 | L3: 3 | M3: 3 | N3: M07; D01; LIVE_US_sheets; reviews | O3: Largest country scale in cited series; fit/quality proof needs to beat established cotton offers | P3: Medium-low | Q3: =(E3*15+F3*5+G3*15+H3*15+I3*10+J3*15+K3*10+L3*10+M3*5)/5 -> 66
A4: O3 | B4: UK | C4: Native-size easy-fit cotton duvet cover system | D4: Investigate first | E4: 4 | F4: 2 | G4: 2 | H4: 4 | I4: 3 | J4: 3 | K4: 4 | L4: 4 | M4: 3 | N4: M08; D06; LIVE_UK_duvet; PDP_UK_duvet | O4: Demonstrate wash-stable sizing and closure convenience; defend price against retail anchors | P4: Medium-low | Q4: =(E4*15+F4*5+G4*15+H4*15+I4*10+J4*15+K4*10+L4*10+M4*5)/5 -> 66
A5: O4 | B5: CA | C5: Fit-validated cotton sheets with local replenishment | D5: Investigate further | E5: 3 | F5: 3 | G5: 3 | H5: 4 | I5: 3 | J5: 3 | K5: 4 | L5: 3 | M5: 3 | N5: M09; LIVE_CA_sheets; R19; R26; reviews | O5: Fit complaints support testing, but smaller market and duty/fulfilment can offset pricing | P5: Low-medium | Q5: =(E5*15+F5*5+G5*15+H5*15+I5*10+J5*15+K5*10+L5*10+M5*5)/5 -> 65
A6: O5 | B6: US | C6: Replacement pillowcase / fitted-sheet bundles | D6: Investigate further | E6: 3 | F6: 3 | G6: 3 | H6: 4 | I6: 3 | J6: 3 | K6: 4 | L6: 4 | M6: 3 | N6: LIVE_US_fitted; LIVE_US_pillowcase; reviews | O6: Lower unit/bulk exposure; sell as problem-specific bundle rather than commodity single | P6: Low | Q6: =(E6*15+F6*5+G6*15+H6*15+I6*10+J6*15+K6*10+L6*10+M6*5)/5 -> 67
A7: O6 | B7: UK | C7: Premium linen/lyocell DTC collection | D7: Postpone | E7: 3 | F7: 3 | G7: 3 | H7: 3 | I7: 2 | J7: 3 | K7: 2 | L7: 2 | M7: 2 | N7: D06; LIVE_UK_linen; LIVE_UK_lyocell | O7: Premium story not enough; material cost, local demand and CAC unverified | P7: Low | Q7: =(E7*15+F7*5+G7*15+H7*15+I7*10+J7*15+K7*10+L7*10+M7*5)/5 -> 53
A8: O7 | B8: US | C8: Commodity microfiber sheet set | D8: Avoid head-on entry | E8: 5 | F8: 2 | G8: 1 | H8: 1 | I8: 1 | J8: 2 | K8: 5 | L8: 3 | M8: 2 | N8: LIVE_US_sheets; LIVE_US_fitted | O8: Large demand does not remove mature low-price trust and ad barriers | P8: Medium | Q8: =(E8*15+F8*5+G8*15+H8*15+I8*10+J8*15+K8*10+L8*10+M8*5)/5 -> 49
A9: O8 | B9: CA | C9: Commodity waterproof mattress protector | D9: Postpone | E9: 3 | F9: 3 | G9: 1 | H9: 2 | I9: 2 | J9: 2 | K9: 2 | L9: 3 | M9: 2 | N9: LIVE_CA_protector; PDP_CA_protector | O9: Utopia and others show substantial ratings at low prices; technical validation burden | P9: Medium-low | Q9: =(E9*15+F9*5+G9*15+H9*15+I9*10+J9*15+K9*10+L9*10+M9*5)/5 -> 43
A10: O9 | B10: US | C10: Bulky foam mattress topper | D10: Postpone | E10: 4 | F10: 3 | G10: 2 | H10: 2 | I10: 2 | J10: 2 | K10: 1 | L10: 1 | M10: 1 | N10: LIVE_US_topper; R11 | O10: Bulky freight, returns and product safety scope dominate capital risk | P10: Medium-low | Q10: =(E10*15+F10*5+G10*15+H10*15+I10*10+J10*15+K10*10+L10*10+M10*5)/5 -> 42
A11: O10 | B11: UK | C11: Commodity comforter / duvet insert | D11: Postpone | E11: 3 | F11: 2 | G11: 2 | H11: 2 | I11: 2 | J11: 2 | K11: 2 | L11: 2 | M11: 2 | N11: LIVE_UK_comforter; LIVE_UK_quilt | O11: Vocabulary and size mismatch plus established warmth/value propositions | P11: Low | Q11: =(E11*15+F11*5+G11*15+H11*15+I11*10+J11*15+K11*10+L11*10+M11*5)/5 -> 43

Sheet Score methodology
A1: Dimension | B1: Weight % | C1: Scale
A2: Demand | B2: 15 | C2: 1=unattractive/high burden; 3=mixed or unknown; 5=attractive/low burden. Analyst judgement, not measured category score.
A3: Growth | B3: 5 | C3: 1=unattractive/high burden; 3=mixed or unknown; 5=attractive/low burden. Analyst judgement, not measured category score.
A4: Competition ease | B4: 15 | C4: 1=unattractive/high burden; 3=mixed or unknown; 5=attractive/low burden. Analyst judgement, not measured category score.
A5: Differentiation | B5: 15 | C5: 1=unattractive/high burden; 3=mixed or unknown; 5=attractive/low burden. Analyst judgement, not measured category score.
A6: Acquisition ease | B6: 10 | C6: 1=unattractive/high burden; 3=mixed or unknown; 5=attractive/low burden. Analyst judgement, not measured category score.
A7: Contribution potential | B7: 15 | C7: 1=unattractive/high burden; 3=mixed or unknown; 5=attractive/low burden. Analyst judgement, not measured category score.
A8: Manufacturing feasibility | B8: 10 | C8: 1=unattractive/high burden; 3=mixed or unknown; 5=attractive/low burden. Analyst judgement, not measured category score.
A9: Capital efficiency | B9: 10 | C9: 1=unattractive/high burden; 3=mixed or unknown; 5=attractive/low burden. Analyst judgement, not measured category score.
A10: Risk resilience | B10: 5 | C10: 1=unattractive/high burden; 3=mixed or unknown; 5=attractive/low burden. Analyst judgement, not measured category score.
A11: Confidence | B11: Low to medium-low | C11: Unknown CAC/quotes scored conservatively; do not interpret 1-5 point total differences as robust. A +/-1 change in a 15%-weight dimension changes total by3 points.

Sheet Economics
A1: id | B1: country | C1: currency | D1: tier | E1: concept | F1: price | G1: discount | H1: vat | I1: returns | J1: factory_placeholder | K1: packaging | L1: freight | M1: insurance | N1: duty_rate | O1: brokerage | P1: inbound | Q1: referral | R1: fulfilment | S1: storage | T1: return_handling | U1: refund_admin | V1: other_variable | W1: cpc | X1: cvr | Y1: paid_order_share | Z1: fixed_monthly | AA1: moq | AB1: launch_setup | AC1: launch_media | AD1: reorder_deposit_fraction | AE1: tax_float | AF1: reserve_rate | AG1: return_recovery | AH1: gross_discounted | AI1: net_order | AJ1: retained_revenue | AK1: customs_value_proxy | AL1: duty | AM1: landed | AN1: referral_cost | AO1: pre_ad | AP1: cpa | AQ1: ad_order_cm | AR1: blended_cm | AS1: cm_pct | AT1: be_acos | AU1: be_cpc | AV1: acos | AW1: roas | AX1: tacos | AY1: be_units | AZ1: be_sales | BA1: inventory_cash | BB1: reorder_cash | BC1: operating_runway | BD1: base_cash | BE1: reserve | BF1: launch_cash | BG1: evidence | BH1: runway_months
A2: US-Low | B2: US | C2: USD | D2: Low | E2: Replacement pair/bundle | F2: 29.99 | G2: 0.05 | H2: 0 | I2: 0.05 | J2: 7 | K2: 0.4 | L2: 1 | M2: 0.08 | N2: 0.2 | O2: 0.25 | P2: 0.4 | Q2: 0.15 | R2: 4 | S2: 0.1 | T2: 1.5 | U2: 0.4 | V2: 0.3 | W2: 0.75 | X2: 0.08 | Y2: 0.6 | Z2: 500 | AA2: 200 | AB2: 1500 | AC2: 2000 | AD2: 0.3 | AE2: 0 | AF2: 0.15 | AG2: 0 | AH2: =F2*(1-G2) -> 28.4905 | AI2: =AH2/(1+H2) -> 28.4905 | AJ2: =AI2*(1-I2) -> 27.065975 | AK2: =J2+K2 -> 7.4 | AL2: =AK2*N2 -> 1.48 | AM2: =AK2+L2+M2+AL2+O2+P2 -> 10.61 | AN2: =AH2*Q2*(1-I2)+I2*U2 -> 4.0798963 | AO2: =AJ2-AM2-AN2-R2-S2-I2*T2-V2+I2*AG2 -> 7.9010787 | AP2: =IF(X2>0,W2/X2,1000000000) -> 9.375 | AQ2: =AO2-AP2 -> -1.4739213 | AR2: =AO2-AP2*Y2 -> 2.2760787 | AS2: =AR2/AJ2 -> 0.084093728 | AT2: =AO2/AH2 -> 0.27732327 | AU2: =AO2*X2 -> 0.6320863 | AV2: =AP2/AH2 -> 0.32905705 | AW2: =IF(AV2>0,1/AV2,0) -> 3.0389867 | AX2: =AV2*Y2 -> 0.19743423 | AY2: =IF(AR2>0,ROUNDUP(Z2/AR2,0),"No break-even at these inputs") -> 220 | AZ2: =IF(ISNUMBER(AY2),AY2*AH2,"N/A") -> 6267.91 | BA2: =AA2*AM2 -> 2122 | BB2: =BA2*AD2 -> 636.6 | BC2: =Z2*BH2 -> 1500 | BD2: =BA2+BB2+AB2+AC2+BC2+AE2 -> 7758.6 | BE2: =BD2*AF2 -> 1163.79 | BF2: =BD2+BE2 -> 8922.39 | BG2: All inputs ASSUMPTION except UK VAT 20% (R09), CA Home/Kitchen referral 15% (F02), and UK Home Products 8% at <=GBP20 otherwise 15% conditional category (F03). US referral15% is planning assumption. CA17% is published cotton bed-linen MFN example R26, application unverified; US20% duty is stress placeholder not legal rate; UK0% conditional DCTS, not clearance quote. Factory numbers are budget test values, NOT estimated actual manufacturing cost. FBA/storage/freight/ads require quotes or trials. | BH2: 3
