Workbook

Sheet Overall analysis
A1: Satin Sheets 4 Piece (US): exact decisions on the 29 Sep audit, run 20260929-6050bf68
A2: Every figure carries its date range; figures are compared only on identical days. Sources: Data sources tab.
A4: Key findings
A5: Satin is a maintenance product with a thin margin: profit after ads is 4.1% (Sellerboard 30 Aug–29 Sep) and Queen loses money after ads (−$540). Queen Black spends $267–310 a day on ads against about $102–127 that would break even.
A6: The run does nothing for rank and cuts or re-colours the campaigns that own the terms we can win. Push a small set where we convert and click at or above market: the King and Full head terms (scores 71–83).
A7: The Queen head terms score Low: our like-for-like conversion is about half the market (satin sheets queen size 3.36% vs 6.83%, search-query data 30 Aug–26 Sep) and rivals at #1–2 sell at $17.99–19.99 against our $29.95. Fix the offer before buying rank.
A8: Deal days are nearly margin-free: break-even ACoS at the Lightning Deal price is 7.5% on Queen Black and 4.8% on King Grey. The last deal lifted rank through the badge, not the ads. Hold prices on deal days.
A9: Break-even is 23.3% on the audit window (Sellerboard), not the engine's 28.5%; at full price about 25%. The audit window includes 6 deal days.
A10: 103 campaigns held as "not serving" spent $4,634 (CC 31 Aug–29 Sep), mostly Queen Black at 39–87% ACoS. Releasing and pricing them to break-even is the largest saving.
A11: Full Black runs out about 4 Dec with no purchase order; Queen Red about 10 Oct and Queen Dark Green about 2 Oct.
A13: Where the product stands
A14: Metric | B14: Window | C14: Value | D14: Engine | E14: Source
A15: Break-even ACoS (all-in) | B15: 30 Aug–29 Sep | C15: 0.2326 | D15: 0.2847 | E15: Sellerboard; engine margin block
A16: Profit per unit before ads | B16: 30 Aug–29 Sep | C16: 7.02 | D16: 8.56 | E16: Sellerboard
A17: Profit after ads, all sizes | B17: 30 Aug–29 Sep | C17: 4700 | E17: Sellerboard
A18: Profit after ads, Queen | B18: 30 Aug–29 Sep | C18: -540 | E18: Sellerboard
A19: Ad spend per day | B19: 15–28 Sep | C19: 586.93 | D19: 630.38 | E19: Command Center campaign view
A20: TACoS | B20: 15–27 Sep | C20: 0.1664 | D20: 0.1749 | E20: Command Center product view
A21: Queen Black units per day | B21: 30 Aug–29 Sep | C21: 20.3 | E21: Sellerboard
A22: Queen Black available | B22: 29 Sep | C22: 1807 | E22: Sellerboard
A23: Full Black available | B23: 29 Sep | C23: 722 | E23: Sellerboard
A24: King (all colours) available | B24: 29 Sep | C24: 4186 | D24: 47 | E24: Sellerboard; engine size map
A26: Decisions by type (every campaign)
A27: Decision type | B27: Campaigns | C27: 30d spend $ (CC 31 Aug–29 Sep) | D27: Share of spend
A28: Retag only | B28: =COUNTIF('Every campaign'!$AH$2:$AH$565,A28) -> 121 | C28: =SUMIF('Every campaign'!$AH$2:$AH$565,A28,'Every campaign'!$AA$2:$AA$565) -> 571.79 | D28: =IF($C$50=0,0,C28/$C$50) -> 0.029728039
A29: Pause | B29: =COUNTIF('Every campaign'!$AH$2:$AH$565,A29) -> 78 | C29: =SUMIF('Every campaign'!$AH$2:$AH$565,A29,'Every campaign'!$AA$2:$AA$565) -> 763.51 | D29: =IF($C$50=0,0,C29/$C$50) -> 0.039695789
A30: Rename only | B30: =COUNTIF('Every campaign'!$AH$2:$AH$565,A30) -> 53 | C30: =SUMIF('Every campaign'!$AH$2:$AH$565,A30,'Every campaign'!$AA$2:$AA$565) -> 696.63 | D30: =IF($C$50=0,0,C30/$C$50) -> 0.036218619
A31: Release hold + price to break-even | B31: =COUNTIF('Every campaign'!$AH$2:$AH$565,A31) -> 52 | C31: =SUMIF('Every campaign'!$AH$2:$AH$565,A31,'Every campaign'!$AA$2:$AA$565) -> 3389.56 | D31: =IF($C$50=0,0,C31/$C$50) -> 0.17622724
A32: No change | B32: =COUNTIF('Every campaign'!$AH$2:$AH$565,A32) -> 48 | C32: =SUMIF('Every campaign'!$AH$2:$AH$565,A32,'Every campaign'!$AA$2:$AA$565) -> 1139.36 | D32: =IF($C$50=0,0,C32/$C$50) -> 0.059236676
A33: No change (engine move rejected/held) | B33: =COUNTIF('Every campaign'!$AH$2:$AH$565,A33) -> 45 | C33: =SUMIF('Every campaign'!$AH$2:$AH$565,A33,'Every campaign'!$AA$2:$AA$565) -> 111.36 | D33: =IF($C$50=0,0,C33/$C$50) -> 0.0057897383
A34: Release hold, keep price | B34: =COUNTIF('Every campaign'!$AH$2:$AH$565,A34) -> 37 | C34: =SUMIF('Every campaign'!$AH$2:$AH$565,A34,'Every campaign'!$AA$2:$AA$565) -> 103.55 | D34: =IF($C$50=0,0,C34/$C$50) -> 0.0053836871
A35: Price cut | B35: =COUNTIF('Every campaign'!$AH$2:$AH$565,A35) -> 34 | C35: =SUMIF('Every campaign'!$AH$2:$AH$565,A35,'Every campaign'!$AA$2:$AA$565) -> 4327.76 | D35: =IF($C$50=0,0,C35/$C$50) -> 0.22500537
A36: Keep paused | B36: =COUNTIF('Every campaign'!$AH$2:$AH$565,A36) -> 27 | C36: =SUMIF('Every campaign'!$AH$2:$AH$565,A36,'Every campaign'!$AA$2:$AA$565) -> 52.97 | D36: =IF($C$50=0,0,C36/$C$50) -> 0.002753973
A37: Child swap | B37: =COUNTIF('Every campaign'!$AH$2:$AH$565,A37) -> 18 | C37: =SUMIF('Every campaign'!$AH$2:$AH$565,A37,'Every campaign'!$AA$2:$AA$565) -> 427.75 | D37: =IF($C$50=0,0,C37/$C$50) -> 0.022239229
A38: Reject pause | B38: =COUNTIF('Every campaign'!$AH$2:$AH$565,A38) -> 10 | C38: =SUMIF('Every campaign'!$AH$2:$AH$565,A38,'Every campaign'!$AA$2:$AA$565) -> 65.74 | D38: =IF($C$50=0,0,C38/$C$50) -> 0.0034179005
A39: Ranking push | B39: =COUNTIF('Every campaign'!$AH$2:$AH$565,A39) -> 9 | C39: =SUMIF('Every campaign'!$AH$2:$AH$565,A39,'Every campaign'!$AA$2:$AA$565) -> 2506.83 | D39: =IF($C$50=0,0,C39/$C$50) -> 0.13033306
... A49: Ranking push (your decision) | B49: =COUNTIF('Every campaign'!$AH$2:$AH$565,A49) -> 1 | C49: =SUMIF('Every campaign'!$AH$2:$AH$565,A49,'Every campaign'!$AA$2:$AA$565) -> 1514.72 | D49: =IF($C$50=0,0,C49/$C$50) -> 0.078752087
A50: Total | B50: =SUM(B28:B49) -> 564 | C50: =SUM(C28:C49) -> 19234.03
A52: Ranking push (Ranking push tab)
A53: Set | B53: Terms | C53: TOS clicks/day now | D53: TOS clicks/day planned | E53: Budget/day $ | F53: Loss/day, full price $ | G53: Loss/day, deal days $
A54: Recommended now (King, Full, small Queen terms) | B54: =COUNTIF('Ranking push'!$AI$2:$AI$27,"Yes") -> 8 | C54: =SUMIF('Ranking push'!$AI$2:$AI$27,"Yes",'Ranking push'!$O$2:$O$27) -> 19.498 | D54: =SUMIF('Ranking push'!$AI$2:$AI$27,"Yes",'Ranking push'!$P$2:$P$27) -> 24.8879 | E54: =SUMIF('Ranking push'!$AI$2:$AI$27,"Yes",'Ranking push'!$Z$2:$Z$27) -> 81.6777 | F54: =SUMIF('Ranking push'!$AI$2:$AI$27,"Yes",'Ranking push'!$AG$2:$AG$27) -> 36.56915 | G54: =SUMIF('Ranking push'!$AI$2:$AI$27,"Yes",'Ranking push'!$AH$2:$AH$27) -> 61.866544
A55: Full plan (PUSH + PUSH-SMALL) | B55: =COUNTIF('Ranking push'!$J$2:$J$27,"PUSH*") -> 9 | C55: =SUMIF('Ranking push'!$J$2:$J$27,"PUSH*",'Ranking push'!$O$2:$O$27) -> 47.3333 | D55: =SUMIF('Ranking push'!$J$2:$J$27,"PUSH*",'Ranking push'!$P$2:$P$27) -> 103.8994 | E55: =SUMIF('Ranking push'!$J$2:$J$27,"PUSH*",'Ranking push'!$Z$2:$Z$27) -> 268.7962 | F55: =SUMIF('Ranking push'!$J$2:$J$27,"PUSH*",'Ranking push'!$AG$2:$AG$27) -> 126.1015 | G55: =SUMIF('Ranking push'!$J$2:$J$27,"PUSH*",'Ranking push'!$AH$2:$AH$27) -> 219.04693
A57: Needs your decision
A58: 1. Which lane governs Satin: maintenance (operator ruling 21 Sep) with the small push we recommend, or Erik's ranking push.
A59: 2. The full plan: add "satin sheets" and "silk sheets queen" (+$137 a day, about $126 a day of loss at full price and $219 on deal days), or hold them at today's price through 28 Oct (recommended).
A60: 3. Sign-off for the funded loss on the recommended set: about $37 a day at full price and $62 on deal days.
A61: 4. King advertised colour on the King terms outside the push: King Grey or King Black.
A62: 5. Confirm the 1 Oct Lightning Deal, and the prices and children in each deal.
A63: 6. Arrival dates for Queen Black, Full Black and Twin Black; a Full Black order by about 20 Oct.

Sheet Every campaign
A1: Campaign ID | B1: Campaign name | C1: Keywords / targets | D1: Keyword acted on | E1: Status now | F1: Objective now | G1: Correct objective | H1: Syntax | I1: Match / targeting | J1: Advertised child now | K1: Advertised child after | L1: Base bid now | M1: Base bid after | N1: TOS % now | O1: TOS % after | P1: TOS price now | Q1: TOS price after | R1: PP % now | S1: PP % after | T1: ROS % now | U1: ROS % after | V1: Budget now | W1: Budget after | X1: State after | Y1: Negatives | Z1: Rename | AA1: 30d spend $ | AB1: 30d clicks | AC1: 30d orders | AD1: 30d ACoS % | AE1: 30d TOS click share % | AF1: 30d PP click share % | AG1: 90d orders | AH1: Decision type | AI1: Decision | AJ1: Why | AK1: Source | AL1: Ranking push
A2: 504037860004352 | B2: D-S4-SP-satin sheets queen-(Satin)-HSV-Exact-Rank-DO-SATIN-WHITE-QUEEN-V2 | C2: satin sheets queen size [exact, $2.12, 443 clicks]; satin sheets queen [exact, $2.15, 101 clicks]; satin sheet queen [exact, paused, $3.00] | D2: satin sheets queen / satin sheets queen size | E2: ENABLED | F2: Ranking | G2: Ranking | H2: Satin|Queen | I2: Exact | J2: SATIN-QUEEN-BLACK | K2: SATIN-QUEEN-BLACK | L2: $2.12 / $2.15 | M2: $1.59 / $1.61 | N2: 80 | O2: 104 | P2: 3.82 | Q2: 3.24 | R2: 0 | S2: 0 | T2: 0 | U2: 0 | V2: 120 | W2: 120 | X2: ENABLED | Y2: none | Z2: defer — engine name wrong (SKU token SATIN-QUEEN-BLACK); load a corrected name after 28 Oct | AA2: 1522.55 | AB2: 544 | AC2: 104 | AD2: 46.7 | AE2: 40.07 | AF2: 56.62 | AG2: 202 | AH2: Price cut | AI2: MAINTAIN: cut base 25% ($2.12 → $1.59, $2.15 → $1.61); TOS +80% → +104% (TOS $3.82 → $3.24); re-score on the 1 Oct and 6 Oct deal days before any Queen push | AJ2: 46.7% ACoS on 104 orders / 544 clicks (CC 31 Aug–29 Sep). The class step undoes the mix fix: Today TOS $2.12×1.80 = $3.82. Written $1.83×1.77 = $3.24. TOS:PP ratio goes 1.80 → 1.77 on a campaign at 57% PP / 40% TOS (audit read, 308 of 544 clicks). | AK2: seq 1 tos: correct to 104%; seq 4 bid: correct to 1.59; seq 5 bid: correct to 1.61; seq 1798 child: reject — keep SATIN-QUEEN-BLACK; seq 2867 rename CHANGE; seq 0 budget hold $120 → pass | AL2: MAINTAIN · score 49 and 42 · CVR half the market like-for-like; re-score on the 1 Oct and 6 Oct deal days; push 16–28 Oct only if deal-day TOS CVR reaches market
A3: 527361393975073 | B3: D-S4-SP-satin sheets-(Satin)-HSV-Exact-Rank-DO-SATIN-QUEEN-GREY | C3: satin sheets [exact, $1.15, 739 clicks] | D3: satin sheets | E3: ENABLED | F3: Ranking | G3: Ranking | H3: Satin | I3: Exact | J3: SATIN-QUEEN-BLACK | K3: SATIN-QUEEN-BLACK | L3: $1.15 | M3: $1.15 | N3: 100 | O3: 100 | P3: 2.3 | Q3: 2.3 | R3: 0 | S3: 0 | T3: 0 | U3: 0 | V3: 70 | W3: 70 | X3: ENABLED | Y3: none | Z3: load (clean): DSS4-SP-Satin Sheets-[Satin]-(HSV)-Exact-(Ranking)-DO-SATIN-QUEEN-BLACK | AA3: 1514.72 | AB3: 739 | AC3: 127 | AD3: 39 | AE3: 88.36 | AF3: 7.85 | AG3: 366 | AH3: Ranking push (your decision) | AI3: HOLD satin sheets (#5) at today's price: base $1.15, TOS $2.30 (+100%), budget $70 through 28 Oct; no class cut. Full-plan option: TOS $2.32 and budget $145, then +20% steps to $2.48 if under 70% of 60 TOS clicks/day arrive | AJ3: 39.0% ACoS on 127 orders / 739 clicks (CC 31 Aug–29 Sep). Head term "satin sheets" at #5 (our crawl 29 Sep), SV 30,210, three deals ahead (1, 6 and 16–28 Oct). | AK3: seq 2868 rename LOAD; seq 8 hold → hold through 28 Oct; re-issue −15% on 29 Oct; seq 11 hold → hold through 28 Oct; re-issue −15% on 29 Oct | AL3: PUSH-SMALL in the full plan only · score 51 · 60 TOS clicks/day (now 21) · TOS $2.32–2.48 · $142/day · loss $7.30/order full price, $12.15 deal
A4: 512077609025515 | B4: DECOLURE - SATIN 4 - LTSF Campaign | C4: Auto: close-match; loose-match; substitutes | D4: whole campaign | E4: ENABLED | F4: Liquidation | G4: Liquidation | I4: Auto | J4: SATIN-FULL-PURPLE | K4: SATIN-FULL-PURPLE | L4: n/a (no target bid in audit) | M4: n/a | N4: 0 | O4: 0 | V4: 50 | W4: 50 | X4: ENABLED | Y4: add 13 negatives (seq 2266) · add negative exact: satin sheets full; silk sheets twin; king satin sheets; silk bed sheets queen; silk bed sheets; satin sheets queen; queen satin sheet set; king size satin sheets | Z4: none | AA4: 787.5 | AB4: 1438 | AC4: 86 | AD4: 29.2 | AE4: 3.27 | AF4: 27.68 | AG4: 220 | AH4: Negatives only | AI4: Add negatives | AJ4: Negative rows agreed with review 40 (add 13 negatives (seq 2266)); 29.2% ACoS on 86 orders / 1438 clicks (CC 31 Aug–29 Sep). | AK4: seq 2266 negatives: agree with review 40
A5: 414850094869263 | B5: D-S4-SP-Auto-Agr-Auto-Disc-DO-SATIN-QUEEN-BLACK | C5: complements [auto, $0.70]; substitutes [auto, $0.79] | D5: all enabled targets: complements; substitutes | E5: ENABLED | F5: Discovery | G5: Discovery | I5: Auto | J5: SATIN-QUEEN-BLACK | K5: SATIN-QUEEN-BLACK | L5: $0.70 / $0.79 | M5: $0.52 / $0.59 | N5: 0 | O5: 0 | P5: 0.7 | Q5: 0.52 | V5: 40 | W5: 40 | X5: ENABLED | Y5: hold seq 1788 (terms not named); add 9 negatives (seq 2269) · add negative exact: satin sheets full; silk bed sheets; silk bed sheets full · negative product target B0839MKJMV | Z5: load (clean): DSS4-SP-Auto-(AUTO)-Auto-(Discovery)-DO-SATIN-QUEEN-BLACK | AA5: 687.93 | AB5: 801 | AC5: 53 | AD5: 43.3 | AE5: 4.74 | AF5: 15.48 | AG5: 214 | AH5: Release hold + price to break-even | AI5: Release hold; cut base $0.70 / $0.79 → $0.52 / $0.59 | AJ5: 43.3% ACoS, 53 orders on 801 clicks (CC 31 Aug–29 Sep) vs Queen Black break-even 17.8%; BE base = $5.03 contribution (Queen Black) × 6.6% CVR = $0.33; cap 25% cut. | AK5: seq 1788 negatives: flag: unverifiable; seq 2269 negatives: agree with review 40; seq 2871 rename LOAD; seq 1719,1720 NOT SERVING hold(s) → release; price to break-even (our addition, reviewer D)
A6: 379276084224195 | B6: Decolure_SP_Exact_PAT_Defensive | C6: Product targets: B0839KG4VY; B0839L4HWH; B0839L5PDJ +530 more targets | D6: — | E6: ENABLED | F6: Defensive | G6: Defensive | I6: ASIN | J6: SATIN-QUEEN-BLACK | K6: SATIN-QUEEN-BLACK | L6: n/a (no target bid in audit) | M6: n/a | N6: 0 | O6: 0 | V6: 48.46 | W6: 48.46 | X6: ENABLED | Y6: none | Z6: none | AA6: 674.61 | AB6: 843 | AC6: 99 | AD6: 20.6 | AE6: 2.49 | AF6: 84.46 | AG6: 403 | AH6: No change | AI6: No change | AJ6: No run decision and no issue found; 20.6% ACoS on 99 orders / 843 clicks (CC 31 Aug–29 Sep). | AK6: no run decision
A7: 265771609218691 | B7: D-S4-king silk sheet set - [Silk|King] - Exact - Ran - DO - SATIN-4PC-KING-GREY | C7: king silk sheet set [exact, $2.75, 170 clicks] | D7: king silk sheet set (buys the search term: king size silk sheets set) | E7: ENABLED | F7: Ranking | G7: Ranking | H7: OUT | I7: Exact | J7: SATIN-4PC-KING-GREY | K7: SATIN-4PC-KING-GREY | L7: $2.75 | M7: $2.07 | N7: 100 | O7: 100 | P7: 5.5 | Q7: 4.14 | R7: 0 | S7: 0 | T7: 30 | U7: 0 | V7: 30 | W7: 30 | X7: ENABLED | Y7: none | Z7: load (clean): DSS4-SP-King Silk Sheet Set-[Silk|King]-(LSV)-Exact-(Ranking)-DO-SATIN-4PC-KING-GREY | AA7: 614.8 | AB7: 170 | AC7: 32 | AD7: 58.4 | AE7: 89.41 | AF7: 0 | AG7: 71 | AH7: Ranking push | AI7: PUSH-SMALL king size silk sheets set (10 → 3): cut base 25% ($2.75 → $2.07), TOS $5.50 → $4.14 (the market bound is $4.06); ROS 30% → 0%; budget $30 | AJ7: 58.4% ACoS (CC 31 Aug–29 Sep, 32 orders / 170 clicks) on King Grey, break-even ≈15%. | AK7: seq 15 ros: agree with review 40; seq 2869 rename LOAD; seq 16 bid hold → load (correct: load it) | AL7: PUSH-SMALL · score 64 · 3.7 TOS clicks/day · TOS ≈$4.06–4.14 · $15/day · loss $14.10/order full price, $19.12 deal
A8: 96870561028328 | B8: D-S4-king size silk sheets - [Silk|King] - Exact - Ran - DO - SATIN-4PC-KING-GREY | C8: king size silk sheets [exact, $2.30, 161 clicks] | D8: king size silk sheets | E8: ENABLED | F8: Ranking | G8: Ranking | H8: OUT | I8: Exact | J8: SATIN-4PC-KING-GREY | K8: SATIN-4PC-KING-GREY | L8: $2.30 | M8: $1.73 | N8: 100 | O8: 100 | P8: 4.6 | Q8: 3.46 | R8: 0 | S8: 0 | T8: 0 | U8: 0 | V8: 23.28 | W8: 14.67 | X8: ENABLED | Y8: none | Z8: load (clean): DSS4-SP-King Size Silk Sheets-[Silk|King]-(LSV)-Exact-(Ranking)-DO-SATIN-4PC-KING-GREY | AA8: 545.81 | AB8: 161 | AC8: 23 | AD8: 71.2 | AE8: 76.4 | AF8: 13.66 | AG8: 46 | AH8: Price cut | AI8: Cut base 25% ($2.30 → $1.73); Budget $23.28 → $14.67 | AJ8: 71.2% ACoS (CC 30d). The cut fails only because of an engine defect. | AK8: seq 17 budget: agree with review 40; seq 18 tos: correct: drop the no-move row 18, load 21; seq 21 bid: pass: load alone; seq 2872 rename LOAD
A9: 103662305423437 | B9: D-S4-SP-satin sheets queen-(Satin)-HSV-Broad-Disc-DO-SATIN-QUEEN-GREY | C9: satin sheets queen [broad, $1.30]; satin sheets queen [broad, $1.36] | D9: satin sheets queen | E9: ENABLED | F9: Discovery | G9: Discovery | I9: Broad | J9: SATIN-QUEEN-BLACK | K9: SATIN-QUEEN-BLACK | L9: $1.30 | M9: $0.98 | N9: 25 | O9: 25 | P9: 1.62 | Q9: 1.23 | V9: 20 | W9: 20 | X9: ENABLED | Y9: add 5 negatives (seq 2259) · add negative exact: black satin sheets; silk bed sheets; king size satin sheets; queen satin sheet set; silk queen bed sheets set; satin bed sheets full; silk sheets full size | Z9: none | AA9: 505.75 | AB9: 331 | AC9: 48 | AD9: 33.8 | AE9: 47.43 | AF9: 16.62 | AG9: 214 | AH9: Release hold + price to break-even | AI9: Release hold; cut base $1.30 → $0.98; Keep enabled (fold held) | AJ9: 33.8% ACoS on 48 orders / 331 clicks (CC 31 Aug–29 Sep). The survivors are smaller (e.g. 2849: 215 orders folded into a 14-order survivor, 90d). 2857 repeats review 28's 2868. | AK9: seq 2259 negatives: agree with review 40; seq 2849 structure: hold (agree); seq 1717,1971 NOT SERVING hold(s) → release; price to break-even (our addition, reviewer D)
A10: 82540637405662 | B10: D-S4-satin sheets full size - [Satin|Full] - Exact - Ran - DO - SATIN-FULL-BLACK | C10: satin sheets full size [exact, $1.13, 138 clicks] | D10: satin sheets full size (buys the search term: satin sheets full) | E10: ENABLED | F10: Ranking | G10: Ranking | H10: OUT | I10: Exact | J10: SATIN-FULL-BLACK | K10: SATIN-FULL-BLACK | L10: $1.13 | M10: $1.13 | N10: 230 | O10: 230 | P10: 3.73 | Q10: 3.73 | R10: 0 | S10: 0 | T10: 0 | U10: 0 | V10: 30 | W10: 30 | X10: ENABLED | Y10: none | Z10: defer — engine name wrong (SKU token SATIN-FULL-BLACK); load a corrected name after 28 Oct | AA10: 445.56 | AB10: 138 | AC10: 45 | AD10: 33.2 | AE10: 99.28 | AF10: 0.72 | AG10: 65 | AH10: Ranking push | AI10: PUSH satin sheets full (4 → 3): hold base $1.13 and TOS $3.73 (+230%, at the market bound); budget $30; target 8.0 TOS clicks/day (now 3.9) | AJ10: Engine swap SATIN-FULL-BLACK → SATIN-4PCS-FULL-ROSEWOOD rejected: the pick comes from the broken size map, and SATIN-FULL-BLACK is the size's best seller with cover (SB 30 Aug–29 Sep); the engine rename writes a wrong token and is deferred; 33.2% ACoS on 45 orders / 138 clicks (CC 31 Aug–29 Sep). | AK10: seq 1800 child: reject — keep SATIN-FULL-BLACK; seq 2873 rename CHANGE | AL10: PUSH · score 82 · 8.0 TOS clicks/day (now 3.9) · TOS $3.73 (market bound $3.69) · $30/day · 1.9 orders/day · loss $7.19/order full price, $11.66 deal
A11: 274586208953923 | B11: D-S4-king satin sheets - [Satin|King] - Exact - Ran - DO - SATIN-4PC-KING-GREY | C11: king satin sheets [exact] | D11: king satin sheets | E11: ENABLED | F11: Ranking | G11: Ranking | H11: Satin|King | I11: Exact | J11: SATIN-4PC-KING-GREY | K11: SATIN-4PC-KING-GREY | L11: $2.00 | M11: $1.50 | N11: 44 | O11: 73 | P11: 2.88 | Q11: 2.59 | U11: 0 | V11: 20.42 | W11: 20.42 | X11: ENABLED | Y11: none | Z11: load (clean): DSS4-SP-King Satin Sheets-[Satin|King]-(LSV)-Exact-(Ranking)-DO-SATIN-4PC-KING-GREY | AA11: 395.83 | AB11: 169 | AC11: 25 | AD11: 48.7 | AE11: 55.62 | AF11: 37.28 | AG11: 58 | AH11: Mix fix + price cut | AI11: Mix fix in one write: base $2.00 → $1.50, boost → 73% (top of search $2.88 → $2.59); 48.7% ACoS vs King Grey 18.9% break-even at full price; product pages 37% of clicks | AJ11: Clean rename (SKU token and objective match what the campaign advertises); 48.7% ACoS on 25 orders / 169 clicks (CC 31 Aug–29 Sep). Note: above break-even with no pricing row in the run; price at the next cycle unless it is chosen for the ranking push. | AK11: seq 2071 retag LOAD; seq 2876 rename LOAD
A12: 33389871513217 | B12: D-S4-satin sheets king - [Satin|King] - Exact - Ran - DO - SATIN-4PC-KING-GREY | C12: satin sheets king [exact, $1.27, 153 clicks] | D12: satin sheets king | E12: ENABLED | F12: Ranking | G12: Ranking | H12: Satin|King | I12: Exact | J12: SATIN-4PC-KING-GREY | K12: SATIN-4PC-KING-GREY | L12: $1.27 | M12: $1.27 | N12: 120 | O12: 120 | P12: 2.79 | Q12: 2.79 | R12: 0 | S12: 0 | T12: 0 | U12: 0 | V12: 15 | W12: 20 | X12: ENABLED | Y12: add negative exact: satin sheets king size | Z12: load (clean): DSS4-SP-Satin Sheets King-[Satin|King]-(MSV)-Exact-(Ranking)-DO-SATIN-4PC-KING-GREY | AA12: 359.53 | AB12: 153 | AC12: 36 | AD12: 28.3 | AE12: 84.21 | AF12: 15.13 | AG12: 51 | AH12: Ranking push | AI12: PUSH satin sheets king (4 → 3): reject the 10% base cut; hold base $1.27 and TOS $2.79 (+120%); budget $15 → $20; tune daily to 5.3 TOS clicks/day | AJ12: 28.3% ACoS on 36 orders / 153 clicks (CC 31 Aug–29 Sep) vs King Grey break-even 15.3%; audit row loads as written (review 40 agrees). | AK12: seq 31 bid: pass (flag); seq 2879 rename LOAD | AL12: PUSH · score 83 · 5.3 TOS clicks/day (now 5.3) · TOS $2.79 · $16/day · 1.2 orders/day · loss $6.29/order full price, $11.31 deal
A13: 137973631643313 | B13: D-S4-SP-EXACT-silk sheets full size-Silk|Full-SATIN-FULL-BLACK | C13: silk sheets full size [exact] | D13: silk sheets full size (buys the search term: silk sheets full) | E13: ENABLED | F13: Ranking | G13: Ranking | I13: Exact | J13: SATIN-FULL-BLACK | K13: SATIN-FULL-BLACK | L13: n/a (no target bid in audit) | M13: n/a | N13: 50 | O13: 52 | Q13: 2.6 | V13: 12 | W13: 15 | X13: ENABLED | Y13: hold seq 2775 (held) | Z13: none | AA13: 348.4 | AB13: 146 | AC13: 37 | AD13: 31.8 | AE13: 80.82 | AF13: 8.9 | AG13: 42 | AH13: Ranking push | AI13: PUSH silk sheets full (5 → 3): TOS +50% → +52% (TOS $2.56 → $2.60); budget $12 → $15 (budget-capped now) | AJ13: 31.8% ACoS on 37 orders / 146 clicks (CC 31 Aug–29 Sep). This pause and #2771 each name the other as the survivor, so "silk sheets full size" goes dark. Keep this campaign: 42 orders in 90d, $12.38/day. | AK13: seq 1440 state: hold; seq 2775 negatives: agree with review 40 | AL13: PUSH · score 80 · 3.3 TOS clicks/day (now 2.9) · TOS $2.60 · $10/day on the term · 0.8 orders/day · loss $2.17/order full price, $6.64 deal
A14: 34079573232348 | B14: D-S4-SP-BROAD-silk bedsheets-Silk-SATIN-QUEEN-GREY | C14: silk bedsheets [broad, $1.20]; silk bedsheets [broad, $1.20] | D14: whole campaign | E14: ENABLED | F14: Discovery | G14: Discovery | I14: Broad | J14: SATIN-QUEEN-GREY | K14: SATIN-QUEEN-GREY | L14: $1.20 | M14: $1.20 | N14: 0 | O14: 0 | P14: 1.2 | Q14: 1.2 | V14: 15 | W14: 15 | X14: PAUSED | Y14: hold seq 1789 (terms not named); add 3 negatives (seq 2257) | Z14: none | AA14: 310.92 | AB14: 239 | AC14: 25 | AD14: 39.1 | AE14: 2.94 | AF14: 30.67 | AG14: 28 | AH14: Pause | AI14: Pause (seq 2856) | AJ14: 39.1% ACoS on 25 orders / 239 clicks (CC 31 Aug–29 Sep). The survivor's budget is $5/day and it spent $46.20 in 14 days. It cannot absorb the loser's $205.07 in 14 days (audit spend_14d), so this is a pause of a 38.4%-ACoS broad (CC 7/2–9/29), not a merge. | AK14: seq 1789 negatives: flag: unverifiable; seq 2257 negatives: agree with review 40; seq 2856 structure: pass as a pause (flag); seq 1721 NOT SERVING hold(s) moot — campaign paused
A15: 108995710931187 | B15: D-S4-silk sheets twin - [Silk|Twin] - Exact - Ran - DO - SATIN-TWIN-BLACK-NEW | C15: silk sheets twin [exact, $1.10, 97 clicks] | D15: silk sheets twin | E15: ENABLED | F15: Ranking | G15: Ranking | H15: OUT | I15: Exact | J15: SATIN-TWIN-BLACK-NEW | K15: SATIN-TWIN-BLACK-NEW | L15: $1.10 | M15: $1.10 | N15: 220 | O15: 220 | P15: 3.52 | Q15: 3.52 | R15: 0 | S15: 0 | T15: 30 | U15: 0 | V15: 16 | W15: 16 | X15: ENABLED | Y15: none | Z15: defer — engine name wrong (SKU token SATIN-TWIN-BLACK-NEW); load a corrected name after 28 Oct | AA15: 292.64 | AB15: 97 | AC15: 13 | AD15: 81.2 | AE15: 98.97 | AF15: 1.03 | AG15: 20 | AH15: Hold (price) | AI15: HOLD: don't load the run's cuts (budget $16 → $8, TOS $3.52 → $2.65) while "silk sheets twin" is unranked and Twin Black may be losing its featured offer; close tuner record 2851 as superseded | AJ15: 81.2% ACoS on 13 orders / 97 clicks (CC 31 Aug–29 Sep) vs Twin Black break-even 31.4%; audit row loads as written (review 40 agrees). Note: plan move to SATIN-TWIN-GREY before 16 Oct (Twin Black 66 units, ~34 days). | AK15: seq 32 budget: pass (flag); seq 33 tos: pass (flag); seq 35 ros: pass the cuts; drop the rank claim; close the 27 Sep tuner r…; seq 36 bid: pass (flag); seq 1803 child: reject — keep SATIN-TWIN-BLACK-NEW; seq 2880 rename CHANGE | AL15: MAINTAIN · score 46 · Twin Black cover 33 days; unranked 29 Sep
A16: 428094781835473 | B16: DCS-SP-Auto/LTSF-Def-Multi LTSF SKUs | C16: Auto: close-match; complements; loose-match +1 more targets | D16: — | E16: ENABLED | F16: Liquidation | G16: Liquidation | I16: Auto | J16: SATIN-STRIPE-FULL-GOLD | K16: SATIN-STRIPE-FULL-GOLD | L16: n/a (no target bid in audit) | M16: n/a | N16: 0 | O16: 0 | V16: 20 | W16: 20 | X16: ENABLED | Y16: add negative exact in the satin-sheet ad group only: chair covers; chair covers for dining chairs | Z16: none | AA16: 270.33 | AB16: 612 | AC16: 31 | AD16: 24.5 | AE16: 1.8 | AF16: 68.46 | AG16: 141 | AH16: No change | AI16: No change | AJ16: No run decision and no issue found; 24.5% ACoS on 31 orders / 612 clicks (CC 31 Aug–29 Sep). | AK16: no run decision
A17: 40865602759529 | B17: D-S4-silk sheets queen size - [Silk|Queen] - Exact - Ran - DO - SATIN-QUEEN-BLACK | C17: silk sheets queen size [exact] | D17: silk sheets queen size (buys the search term: silk sheets queen) | E17: ENABLED | F17: Ranking | G17: Ranking | H17: Silk|Queen | I17: Exact | J17: SATIN-QUEEN-BLACK | K17: SATIN-QUEEN-BLACK | L17: $1.41 | M17: $1.41 | N17: 30 | O17: 66 | P17: 1.83 | Q17: 2.34 | V17: 25 | W17: 40 | X17: ENABLED | Y17: none | Z17: defer — engine name wrong (SKU token SATIN-QUEEN-BLACK); load a corrected name after 28 Oct | AA17: 261.91 | AB17: 151 | AC17: 32 | AD17: 27.1 | AE17: 82.78 | AF17: 0 | AG17: 91 | AH17: Ranking push | AI17: OWNER of silk sheets queen (#10; was #6 before its clicks fell on 8 Sep): release the hold; keep base $1.41, boost 30% → 66% (TOS $1.83 → $2.34, what the duplicate already pays); budget $25 → $40 (takes the duplicate's $15); restore about 10 TOS clicks a day. Full-plan option: 20 a day | AJ17: 27.1% ACoS, 32 orders on 151 clicks (CC 31 Aug–29 Sep) vs Queen Black break-even 17.8%; BE base = $5.03 contribution (Queen Black) × 21.2% CVR = $1.07; cap 25% cut. | AK17: seq 1813 child: reject — keep SATIN-QUEEN-BLACK; seq 2076 retag LOAD; seq 2898 rename CHANGE; seq 1975 NOT SERVING hold(s) → release; price to break-even (our addition, reviewer D) | AL17: RESTORE · score 55 · ~10 TOS clicks/day (7.2 now; ~10 before 8 Sep) · TOS $2.34 · full plan: 20/day at $2.33, $47/day
A18: 234075729975572 | B18: D-S4-black silk sheets - [Silk] - Exact - Ran - DO - SATIN-QUEEN-BLACK | C18: black silk sheets [exact] | D18: black silk sheets | E18: ENABLED | F18: Ranking | G18: Conversions | H18: Silk | I18: Exact | J18: SATIN-QUEEN-BLACK | K18: SATIN-QUEEN-BLACK | L18: $1.42 | M18: $1.06 | N18: 35 | O18: 35 | P18: 1.92 | Q18: 1.43 | V18: 10 | W18: 10 | X18: ENABLED | Y18: none | Z18: defer — engine name wrong ((Conversion)); load a corrected name after 28 Oct | AA18: 261.61 | AB18: 155 | AC18: 19 | AD18: 40.4 | AE18: 57.79 | AF18: 33.77 | AG18: 45 | AH18: Release hold + price to break-even | AI18: Release hold; cut base $1.42 → $1.06; retag → Conversions | AJ18: 40.4% ACoS, 19 orders on 155 clicks (CC 31 Aug–29 Sep) vs Queen Black break-even 17.8%; BE base = $5.03 contribution (Queen Black) × 12.3% CVR = $0.62; cap 25% cut. | AK18: seq 2072 retag correct to Conversions; seq 2882 rename CHANGE; seq 1973 NOT SERVING hold(s) → release; price to break-even (our addition, reviewer D) | AL18: MAINTAIN · score 29
A19: 509115242799026 | B19: D-S4-SP-king satin sheet set-(Satin)-VLSV-Exact-Rank-DO-SATIN-KING-BLACK-V2 | C19: king size satin sheet set [exact, $2.60, 81 clicks]; king satin sheets set [exact, $2.35, 4 clicks]; king satin sheet set [exact, $1.43]; king size satin sheets set [exact, $1.65] | D19: whole campaign | E19: PAUSED | F19: Ranking | G19: Ranking | H19: Satin|King | I19: Exact | J19: SATIN-4PC-KING-GREY | K19: SATIN-KING-BLACK | L19: $2.60 / $2.35 / $1.43 / $1.65 | M19: $1.70 / $1.70 / $1.43 / $1.65 | N19: 50 | O19: 50 | P19: 3.9 | Q19: 2.55 | R19: 0 | S19: 0 | T19: 0 | U19: 0 | V19: 12 | W19: 12 | X19: ENABLED | Y19: none | Z19: load (clean): DSS4-SP-King Size Satin Sheet Set-[Satin|King]-(LSV)-Exact-(Ranking)-DO-SATIN-4PC-KING-GREY | AA19: 247.68 | AB19: 85 | AC19: 9 | AD19: 85.9 | AE19: 80 | AF19: 8.24 | AG19: 51 | AH19: Revive at break-even | AI19: Revive at break-even base ($1.70 max); Swap child to SATIN-KING-BLACK | AJ19: 85.9% ACoS on 9 orders / 85 clicks (CC 31 Aug–29 Sep). The review's "King on 10 shelf days" is wrong: King Grey has 1,057 units (210 days, SB 9/29). The real reason is margin. | AK19: seq 2827 structure: hold, reason corrected; seq 2891 rename LOAD
A20: 287639399820558 | B20: D-S4-SP-red satin sheet-(Satin)-LSV-Exact-Rank-DO-SATIN-RED-QUEEN | C20: red satin sheet [exact, $1.40, 157 clicks] | D20: whole campaign | E20: ENABLED | F20: Ranking | G20: Conversions | H20: Satin | I20: Exact | J20: SATIN-4PC-RED-QUEEN | K20: SATIN-4PCS-KING-RED | L20: $1.40 | M20: $1.32 | N20: 65 | O20: 65 | P20: 2.31 | Q20: 2.18 | R20: 0 | S20: 0 | T20: 0 | U20: 0 | V20: 13 | W20: 9.1 | X20: ENABLED | Y20: none | Z20: defer — engine name wrong (SKU token SATIN-4PC-RED-QUEEN; (Conversion)); load a corrected name after 28 Oct | AA20: 245.96 | AB20: 157 | AC20: 28 | AD20: 29.7 | AE20: 33.12 | AF20: 64.97 | AG20: 32 | AH20: Child swap | AI20: Swap child to SATIN-4PCS-KING-RED; Cut base 6% ($1.40 → $1.32); Budget $13 → $9.1; retag → Conversions | AJ20: 29.7% ACoS on 28 orders / 157 clicks (CC 31 Aug–29 Sep). Swap by hand now (seq 1804); Queen Red 34 units, out ~10 Oct (SB 29 Sep). | AK20: seq 45 budget: pass (flag); seq 49 bid: agree with review 40; seq 1804 child: pass — apply NOW (outside the held group); seq 2881 rename CHANGE; our addition: standard → Conversions (colour term "red satin sheet")
A21: 520117564893402 | B21: SATIN-QUEEN-GREY SP - Silk Sheets - Exact 091323 | C21: silk sheets [exact, $0.98, 118 clicks] | D21: silk sheets | E21: ENABLED | F21: Ranking | G21: Ranking | H21: OUT | I21: Exact | J21: SATIN-QUEEN-GREY | K21: SATIN-QUEEN-BLACK | L21: $0.98 | M21: $0.98 | N21: 130 | O21: 72 | P21: 2.25 | Q21: 1.69 | R21: 0 | S21: 0 | T21: 0 | U21: 0 | V21: 20 | W21: 20 | X21: ENABLED | Y21: none | Z21: load (clean): DSS4-SP-Silk Sheets-[Silk]-(VHSV)-Exact-(Ranking)-DO-SATIN-QUEEN-GREY | AA21: 245.75 | AB21: 118 | AC21: 21 | AD21: 33.8 | AE21: 91.53 | AF21: 5.93 | AG21: 28 | AH21: Price cut | AI21: MAINTAIN silk sheets (#28): swap the ad from Queen Grey to Queen Black (the Queen velocity leader); TOS +130% → +72% (TOS $2.25 → $1.69); 33.8% ACoS against Queen Grey 11.2% break-even | AJ21: Clean rename (SKU token and objective match what the campaign advertises); 33.8% ACoS on 21 orders / 118 clicks (CC 31 Aug–29 Sep). Note: above break-even with no pricing row in the run; price at the next cycle unless it is chosen for the ranking push. | AK21: seq 2877 rename LOAD | AL21: MAINTAIN · score 29 · wrong child (Queen Grey)
A22: 152213290901148 | B22: D-S4-TESTING-NEW-FEATURE | C22: keyword-group="Keywords related to your product category" [$0.69] | D22: keyword-group="Keywords related to your product category" | E22: ENABLED | F22: Conversions | G22: Discovery | I22: Theme | J22: SATIN-4PCS-FULL-ROSEWOOD | K22: SATIN-4PCS-FULL-ROSEWOOD | L22: $0.69 | M22: $0.52 | N22: 0 | O22: 0 | P22: 0.69 | Q22: 0.52 | V22: 10 | W22: 10 | X22: ENABLED | Y22: none | Z22: defer — engine name wrong ((Discovery)); load a corrected name after 28 Oct | AA22: 243.74 | AB22: 304 | AC22: 18 | AD22: 46.4 | AE22: 1.32 | AF22: 28.95 | AG22: 37 | AH22: Release hold + price to break-even | AI22: Release hold; cut base $0.69 → $0.52; retag → Discovery | AJ22: 46.4% ACoS, 18 orders on 304 clicks (CC 31 Aug–29 Sep) vs Full Rosewood break-even 15.0%; BE base = $4.50 contribution (Full Rosewood) × 5.9% CVR = $0.27; cap 25% cut. | AK22: seq 2073 retag correct to Discovery; seq 2883 rename CHANGE; seq 1725 NOT SERVING hold(s) → release; price to break-even (our addition, reviewer D)
A23: 323452708337783 | B23: D-S4-SP-Auto-Agr-Auto-Disc-DO-SATIN-WHITE-QUEEN | C23: close-match [auto, $0.84]; loose-match [auto, $0.70] | D23: all enabled targets: close-match; loose-match | E23: ENABLED | F23: Discovery | G23: Discovery | I23: Auto | J23: SATIN-QUEEN-BLACK | K23: SATIN-QUEEN-BLACK | L23: $0.84 / $0.70 | M23: $0.63 / $0.52 | N23: 0 | O23: 0 | P23: 0.84 | Q23: 0.63 | V23: 40 | W23: 40 | X23: ENABLED | Y23: hold seq 1791 (terms not named); add 9 negatives (seq 2264) · add negative exact: silk sheets queen; silk bed sheets · negative product target B0839MKJMV | Z23: defer — engine name wrong (SKU token SATIN-QUEEN-BLACK + suffix elsewhere); load a corrected name after 28 Oct | AA23: 242.28 | AB23: 296 | AC23: 19 | AD23: 43.8 | AE23: 14.19 | AF23: 5.07 | AG23: 106 | AH23: Release hold + price to break-even | AI23: Release hold; cut base $0.84 / $0.70 → $0.63 / $0.52 | AJ23: 43.8% ACoS, 19 orders on 296 clicks (CC 31 Aug–29 Sep) vs Queen Black break-even 17.8%; BE base = $5.03 contribution (Queen Black) × 6.4% CVR = $0.32; cap 25% cut. | AK23: seq 1791 negatives: flag: unverifiable; seq 2264 negatives: agree with review 40; seq 2896 rename CHANGE; seq 1730,1731 NOT SERVING hold(s) → release; price to break-even (our addition, reviewer D)
A24: 100830568607053 | B24: D-S4-SP-silk sheets queen-(Silk)-HSV-Exact-Rank-DO-SATIN-QUEEN-BLACK | C24: silk sheets queen [exact, $1.17, 104 clicks] | D24: silk sheets queen | E24: ENABLED | F24: Ranking | G24: Ranking | H24: OUT | I24: Exact | J24: SATIN-QUEEN-BLACK | K24: SATIN-QUEEN-BLACK | L24: $1.17 | M24: $1.17 | N24: 100 | O24: 100 | P24: 2.34 | Q24: 2.34 | R24: 0 | S24: 0 | T24: 0 | U24: 0 | V24: 15 | W24: 15 | X24: PAUSED | Y24: none | Z24: defer — engine name wrong (SKU token SATIN-QUEEN-BLACK); load a corrected name after 28 Oct | AA24: 234.7 | AB24: 104 | AC24: 32 | AD24: 24 | AE24: 95.19 | AF24: 4.81 | AG24: 73 | AH24: Pause (duplicate) | AI24: PAUSE: duplicate exact on silk sheets queen (same keyword, same Queen Black ad as 40865602759529, which keeps the term with 142 of its 245 clicks); its $15 budget moves to the owner | AJ24: No run decision and no issue found; 24.0% ACoS on 32 orders / 104 clicks (CC 31 Aug–29 Sep). Note: above break-even with no pricing row in the run; price at the next cycle unless it is chosen for the ranking push. | AK24: seq 1802 child: reject — keep SATIN-QUEEN-BLACK; seq 2878 rename CHANGE | AL24: Duplicate owner of silk sheets queen · paused into 40865602759529
A25: 34608790713465 | B25: D-S4-SP-EXACT-silk bedsheets-Silk-SATIN-QUEEN-BLACK | C25: silk bedsheets [exact] | D25: silk bedsheets (buys the search term: silk bed sheets) | E25: ENABLED | F25: Ranking | G25: Conversions | I25: Exact | J25: SATIN-QUEEN-BLACK | K25: SATIN-QUEEN-BLACK | L25: $1.78 | M25: $1.33 | N25: 0 | O25: 0 | P25: 1.78 | Q25: 1.33 | V25: 10 | W25: 10 | X25: ENABLED | Y25: none | Z25: defer — engine name wrong ((Conversion)); load a corrected name after 28 Oct | AA25: 234.04 | AB25: 130 | AC25: 9 | AD25: 86.6 | AE25: 56.15 | AF25: 23.85 | AG25: 16 | AH25: Price cut | AI25: Cut base $1.78 → $1.33 (break-even, 25% cap); retag → Conversions | AJ25: 86.6% ACoS, 9 orders on 130 clicks (CC 31 Aug–29 Sep) vs Queen Black break-even 17.8%; BE base = $5.03 contribution (Queen Black) × 6.9% CVR = $0.35; cap 25% cut. | AK25: seq 2074 retag correct to Conversions; seq 2884 rename CHANGE; seq 1453 state hold → correct: cut the bid | AL25: MAINTAIN · score 37
A26: 238180925389130 | B26: D-S4-SP-queen size silk sheets-(Silk)-MSV-Exact-Rank-DO-SATIN-QUEEN-BLACK | C26: queen satin sheets [exact, $1.99, 107 clicks]; queen bed sheet set silk satin [exact, $0.50]; queen comforter sets with sheets and pillows [exact, paused, $1.25]; queen fitted sheet deep pocket satin [exact, $0.50]; queen fitted sheet pillow case satin taupe [exact, $0.50]; queen size silk sheets [exact, $0.50] | D26: queen satin sheets | E26: ENABLED | F26: Ranking | G26: Ranking | H26: Satin|Queen | I26: Exact | J26: SATIN-QUEEN-BLACK | K26: SATIN-QUEEN-BLACK | L26: $1.99 | M26: $1.49 | N26: 30 | O26: 56 | P26: 2.59 | Q26: 2.33 | R26: 0 | S26: 0 | T26: 0 | U26: 0 | V26: 10 | W26: 10 | X26: ENABLED | Y26: none | Z26: defer — engine name wrong (SKU token SATIN-QUEEN-BLACK); load a corrected name after 28 Oct | AA26: 228.69 | AB26: 107 | AC26: 27 | AD26: 27 | AE26: 37.38 | AF26: 57.94 | AG26: 48 | AH26: Mix fix + price cut | AI26: Mix fix in one write: base $1.99 → $1.49, boost → 56% (top of search $2.59 → $2.33); target "queen satin sheets"; 27.0% ACoS vs Queen Black 22.5%; product pages 58% | AJ26: No run decision and no issue found; 27.0% ACoS on 27 orders / 107 clicks (CC 31 Aug–29 Sep). Note: above break-even with no pricing row in the run; price at the next cycle unless it is chosen for the ranking push. | AK26: seq 1808 child: reject — keep SATIN-QUEEN-BLACK; seq 2888 rename CHANGE
A27: 244008066214488 | B27: D-S4-satin bed sheets full - [Satin|Full] - Exact - Ran - DO - SATIN-FULL-BLACK | C27: satin bed sheets full [exact, $1.14, 63 clicks] | D27: satin bed sheets full | E27: ENABLED | F27: Ranking | G27: Ranking | H27: OUT | I27: Exact | J27: SATIN-FULL-BLACK | K27: SATIN-FULL-BLACK | L27: $1.14 | M27: $0.93 | N27: 300 | O27: 300 | P27: 4.56 | Q27: 3.72 | R27: 0 | S27: 0 | T27: 0 | U27: 0 | V27: 9.53 | W27: 9.53 | X27: ENABLED | Y27: none | Z27: defer — engine name wrong (SKU token SATIN-FULL-BLACK); load a corrected name after 28 Oct | AA27: 198.58 | AB27: 63 | AC27: 11 | AD27: 60.6 | AE27: 95.24 | AF27: 1.59 | AG27: 16 | AH27: Price cut | AI27: Cut base 18% ($1.14 → $0.93) | AJ27: 60.6% ACoS on 11 orders / 63 clicks (CC 31 Aug–29 Sep). PROTECT −10% leaves TOS at $4.12, still above the engine's market bound of $3.74. The row is at 2.17× BE with 11 orders. $0.93 × 4.00 = $3.72, a −18% cut, inside the cap. | AK27: seq 74 bid: correct to 0.93; seq 1806 child: reject — keep SATIN-FULL-BLACK; seq 2886 rename CHANGE; seq 71 TOS hold → correct: cut (delivered by the base cut, TOS % kept)
A28: 224280280721130 | B28: D-S4-silk twin bed sheets - [Silk|Twin] - Exact - Ran - DO - SATIN-TWIN-BLACK-NEW | C28: silk twin bed sheets [exact, $1.29, 58 clicks] | D28: silk twin bed sheets | E28: PAUSED | F28: Ranking | G28: Ranking | H28: OUT | I28: Exact | J28: SATIN-TWIN-BLACK-NEW | K28: SATIN-TWIN-BLACK-NEW | L28: $1.29 | M28: $1.29 | N28: 300 | O28: 300 | P28: 5.16 | Q28: 5.16 | R28: 0 | S28: 0 | T28: 0 | U28: 0 | V28: 15 | W28: 15 | X28: ENABLED | Y28: none | Z28: load (clean): DSS4-SP-Silk Twin Bed Sheets-[Silk|Twin]-(LSV)-Exact-(Ranking)-DO-SATIN-TWIN-BLACK-NEW | AA28: 196.59 | AB28: 58 | AC28: 9 | AD28: 78.5 | AE28: 100 | AF28: 0 | AG28: 25 | AH28: Restart | AI28: RESTART after the Twin Black listing check: the silk twin bed sheets exact was paused outside the tuner (last served 22 Sep; rank 8 → 100 on 24 Sep). Keep base $1.29 and boost +300% | AJ28: 78.5% ACoS on 9 orders / 58 clicks (CC 31 Aug–29 Sep). Revive rejected: 30d ACoS 78.5%. The child is a 3-pc set with 66 units and 33 days of cover (SB, out ~1 Nov). | AK28: seq 2816 structure: hold; seq 2890 rename LOAD
A29: 152138103637187 | B29: D-S4-SP-satin sheets king-(Satin)-HSV-Phrase-Disc-DO-SATIN-4PC-KING-GREY | C29: satin sheets king [phrase, $1.90]; satin sheets king [phrase, $1.90] | D29: satin sheets king | E29: ENABLED | F29: Discovery | G29: Discovery | I29: Phrase | J29: SATIN-4PC-KING-GREY | K29: SATIN-4PC-KING-GREY | L29: $1.90 | M29: $1.42 | N29: 50 | O29: 50 | P29: 2.85 | Q29: 2.13 | V29: 15 | W29: 15 | X29: ENABLED | Y29: add negative exact: satin sheets king | Z29: load (clean): DSS4-SP-Satin Sheets King-[Satin|King]-(MSV)-Phrase-(Discovery)-DO-SATIN-4PC-KING-GREY | AA29: 189.86 | AB29: 79 | AC29: 12 | AD29: 44.5 | AE29: 74.68 | AF29: 10.13 | AG29: 21 | AH29: Release hold + price to break-even | AI29: Release hold; cut base $1.90 → $1.42 | AJ29: 44.5% ACoS, 12 orders on 79 clicks (CC 31 Aug–29 Sep) vs King Grey break-even 15.3%; BE base = $4.93 contribution (King Grey) × 15.2% CVR = $0.75; cap 25% cut. | AK29: seq 2875 rename LOAD; seq 1723,1972 NOT SERVING hold(s) → release; price to break-even (our addition, reviewer D)
A30: 246449445739132 | B30: D-S4-full satin sheets set - [Satin|Full] - Exact - Ran - DO - SATIN-FULL-BLACK | C30: full satin sheets set [exact, $1.10, 55 clicks] | D30: full satin sheets set | E30: ENABLED | F30: Ranking | G30: Ranking | H30: OUT | I30: Exact | J30: SATIN-FULL-BLACK | K30: SATIN-FULL-BLACK | L30: $1.10 | M30: $0.99 | N30: 300 | O30: 300 | P30: 4.4 | Q30: 3.96 | R30: 0 | S30: 0 | T30: 0 | U30: 0 | V30: 9.7 | W30: 9.7 | X30: ENABLED | Y30: none | Z30: defer — engine name wrong (SKU token SATIN-FULL-BLACK); load a corrected name after 28 Oct | AA30: 187.29 | AB30: 55 | AC30: 15 | AD30: 43 | AE30: 98.18 | AF30: 0 | AG30: 20 | AH30: Price cut | AI30: Cut base 10% ($1.10 → $0.99) | AJ30: 43.0% ACoS on 15 orders / 55 clicks (CC 31 Aug–29 Sep) vs Full Black break-even 27.5%; audit row loads as written (review 40 agrees). | AK30: seq 84 bid: agree with review 40; seq 1807 child: reject — keep SATIN-FULL-BLACK; seq 2887 rename CHANGE; seq 81 TOS hold → correct: cut (delivered by the base cut, TOS % kept)
A31: 189967409565927 | B31: D-S4-satin sheets king size - [Satin|King] - Exact - Ran - DO - SATIN-4PC-KING-GREY | C31: satin sheets king size [exact] | D31: satin sheets king size | E31: ENABLED | F31: Ranking | G31: Ranking | H31: Satin|King | I31: Exact | J31: SATIN-4PC-KING-GREY | K31: SATIN-4PC-KING-GREY | L31: n/a (no target bid in audit) | M31: n/a | N31: 60 | O31: 60 | V31: 20 | W31: 20 | X31: ENABLED | Y31: add negative exact: satin sheets king | Z31: load (clean): DSS4-SP-Satin Sheets King Size-[Satin|King]-(LSV)-Exact-(Ranking)-DO-SATIN-4PC-KING-GREY | AA31: 167.72 | AB31: 81 | AC31: 12 | AD31: 45.4 | AE31: 67.9 | AF31: 7.41 | AG31: 44 | AH31: Ranking push | AI31: HOLD AT TARGET satin sheets king size (#2): hold TOS $2.51 (+60%) through 28 Oct; after 11 Nov probe TOS −3–5% | AJ31: Clean rename (SKU token and objective match what the campaign advertises); 45.4% ACoS on 12 orders / 81 clicks (CC 31 Aug–29 Sep). Note: above break-even with no pricing row in the run; price at the next cycle unless it is chosen for the ranking push. | AK31: seq 2077 retag LOAD; seq 2899 rename LOAD | AL31: HOLD-AT-TARGET · score 80 · 0.8 TOS clicks/day · TOS $2.51 · $2/day · loss $7.86/order full price
A32: 173283715685585 | B32: D-S4-full silk bed sheets - [Silk|Full] - Exact - Ran - DO - SATIN-FULL-BLACK | C32: full silk bed sheets [exact, $1.45, 57 clicks] | D32: full silk bed sheets | E32: ENABLED | F32: Ranking | G32: Ranking | H32: OUT | I32: Exact | J32: SATIN-FULL-BLACK | K32: SATIN-FULL-BLACK | L32: $1.45 | M32: $1.09 | N32: 120 | O32: 120 | P32: 3.19 | Q32: 2.4 | R32: 0 | S32: 0 | T32: 0 | U32: 0 | V32: 11.29 | W32: 5.65 | X32: ENABLED | Y32: none | Z32: defer — engine name wrong (SKU token SATIN-FULL-BLACK); load a corrected name after 28 Oct | AA32: 162.64 | AB32: 57 | AC32: 14 | AD32: 39.8 | AE32: 98.25 | AF32: 0 | AG32: 26 | AH32: Price cut | AI32: Cut base 25% ($1.45 → $1.09); Budget $11.29 → $5.65 | AJ32: 39.8% ACoS on 14 orders / 57 clicks (CC 31 Aug–29 Sep). The written −29.7% breaks the team's 25% base-cut cap for a target with real sales (14 orders on 57 clicks, audit read). No orders at risk are named. | AK32: seq 85 budget: agree with review 40; seq 86 tos: drop (hold 120); seq 89 bid: correct to 1.09; seq 1810 child: reject — keep SATIN-FULL-BLACK; seq 2893 rename CHANGE
A33: 48825734993999 | B33: D-S4-SP-EXACT-queen silk sheet-Silk|Queen-SATIN-QUEEN-BLACK | C33: queen silk sheet [exact] | D33: queen silk sheet | E33: ENABLED | F33: Ranking | G33: Ranking | I33: Exact | J33: SATIN-QUEEN-BLACK | K33: SATIN-QUEEN-BLACK | L33: $1.86 | M33: $1.40 | N33: 0 | O33: 19 | P33: 1.86 | Q33: 1.67 | U33: 0 | V33: 10 | W33: 10 | X33: ENABLED | Y33: none | Z33: defer — engine name wrong (SKU token SATIN-QUEEN-BLACK); load a corrected name after 28 Oct | AA33: 151.01 | AB33: 81 | AC33: 9 | AD33: 56.4 | AE33: 30.86 | AF33: 56.79 | AG33: 17 | AH33: Mix fix + price cut | AI33: Mix fix in one write: base $1.86 → $1.40, boost → 19% (top of search $1.86 → $1.67); rest of search 20% → 0%; 56.4% ACoS vs Queen Black 22.5%; product pages 57% | AJ33: No run decision and no issue found; 56.4% ACoS on 9 orders / 81 clicks (CC 31 Aug–29 Sep). Note: above break-even with no pricing row in the run; price at the next cycle unless it is chosen for the ranking push. | AK33: seq 1820 child: reject — keep SATIN-QUEEN-BLACK; seq 2086 retag LOAD; seq 2913 rename CHANGE
A34: 208595143922254 | B34: D-S4-SP-AUTO-CATCH ALL | C34: complements [auto, $0.78] | D34: complements | E34: ENABLED | F34: Discovery | G34: Discovery | I34: Auto | J34: SATIN-QUEEN-GREY | K34: SATIN-QUEEN-GREY | L34: $0.78 | M34: $0.58 | N34: 0 | O34: 0 | P34: 0.78 | Q34: 0.58 | V34: 100 | W34: 100 | X34: ENABLED | Y34: hold seq 1792 (terms not named); add 9 negatives (seq 2273) · negative product target B0839MKJMV | Z34: load (clean): DSS4-SP-Auto-(AUTO)-Auto-(Discovery)-DO-SATIN-QUEEN-GREY | AA34: 146.82 | AB34: 231 | AC34: 13 | AD34: 40.3 | AE34: 1.73 | AF34: 61.47 | AG34: 141 | AH34: Release hold + price to break-even | AI34: Release hold; cut base $0.78 → $0.58 | AJ34: 40.3% ACoS, 13 orders on 231 clicks (CC 31 Aug–29 Sep) vs Queen Grey break-even 11.2%; BE base = $3.28 contribution (Queen Grey) × 5.6% CVR = $0.18; cap 25% cut. | AK34: seq 1792 negatives: flag: unverifiable; seq 2080 retag LOAD; seq 2273 negatives: agree with review 40; seq 2903 rename LOAD; seq 1732 NOT SERVING hold(s) → release; price to break-even (our addition, reviewer D)
A35: 167888639670385 | B35: D-S4-SP-EXACT-silk sheets king size-Silk|King-SATIN-4PC-KING-GREY | C35: silk sheets king size [exact] | D35: silk sheets king size (buys the search term: silk sheets king) | E35: ENABLED | F35: Ranking | G35: Ranking | I35: Exact | J35: SATIN-4PC-KING-GREY | K35: SATIN-4PC-KING-GREY | L35: $1.50 | M35: $1.12 | N35: 0 | O35: 34 | P35: 1.5 | Q35: 1.5 | U35: 0 | V35: 10 | W35: 10 | X35: ENABLED | Y35: none | Z35: load (clean): DSS4-SP-Silk Sheets King Size-[Silk|King]-(LSV)-Exact-(Ranking)-DO-SATIN-4PC-KING-GREY | AA35: 144.79 | AB35: 84 | AC35: 15 | AD35: 28.7 | AE35: 15.48 | AF35: 1.19 | AG35: 20 | AH35: Ranking push | AI35: Mix fix in one write: base $1.50 → $1.12, boost → 34% (top of search $1.50 → $1.50); rest of search 20% → 0% (83% of clicks); FIX FIRST silk sheets king (#40): get 70% of clicks to the top before any push | AJ35: Clean rename (SKU token and objective match what the campaign advertises); 28.7% ACoS on 15 orders / 84 clicks (CC 31 Aug–29 Sep). Note: above break-even with no pricing row in the run; price at the next cycle unless it is chosen for the ranking push. | AK35: seq 2083 retag LOAD; seq 2909 rename LOAD | AL35: FIX-FIRST · score 50 · TOS 15% of clicks · ceiling $0.74
A36: 162964778769639 | B36: SSS4-PHRASE-(silk sheet set)-Browse Kws Migr. | C36: silk sheet set [phrase, $1.01]; silk sheet set [phrase, $2.00] | D36: silk sheet set | E36: ENABLED | F36: Discovery | G36: Discovery | I36: Phrase | J36: SATIN-QUEEN-BLACK | K36: SATIN-QUEEN-BLACK | L36: $1.01 | M36: $0.76 | N36: 0 | O36: 0 | P36: 1.01 | Q36: 0.76 | V36: 30 | W36: 30 | X36: ENABLED | Y36: hold seq 1794 (terms not named); add 1 negatives (seq 2275) · add negative exact: queen silk sheets set; king size silk sheets set | Z36: load (clean): DSS4-SP-Silk Sheet Set-[Silk]-(LSV)-Phrase-(Discovery)-DO-SATIN-QUEEN-BLACK | AA36: 143.73 | AB36: 106 | AC36: 9 | AD36: 53.9 | AE36: 34.29 | AF36: 13.33 | AG36: 61 | AH36: Release hold + price to break-even | AI36: Release hold; cut base $1.01 → $0.76 | AJ36: 53.9% ACoS, 9 orders on 106 clicks (CC 31 Aug–29 Sep) vs Queen Black break-even 17.8%; BE base = $5.03 contribution (Queen Black) × 8.5% CVR = $0.43; cap 25% cut. | AK36: seq 1794 negatives: flag: unverifiable; seq 2101 retag LOAD; seq 2275 negatives: agree with review 40; seq 2942 rename LOAD; seq 1743 NOT SERVING hold(s) → release; price to break-even (our addition, reviewer D)
A37: 47024149807888 | B37: D-S4-SP-PHRASE-silk bedsheets-Silk-SATIN-QUEEN-GREY | C37: silk bedsheets [phrase, $1.50]; silk bedsheets [phrase, $1.50] | D37: whole campaign | E37: ENABLED | F37: Discovery | G37: Discovery | I37: Phrase | J37: SATIN-QUEEN-GREY | K37: SATIN-QUEEN-GREY | L37: $1.50 | M37: $1.50 | N37: 0 | O37: 0 | P37: 1.5 | Q37: 1.5 | V37: 5 | W37: 5 | X37: PAUSED | Y37: none | Z37: none | AA37: 143.6 | AB37: 87 | AC37: 9 | AD37: 55.8 | AE37: 10.34 | AF37: 27.59 | AG37: 11 | AH37: Pause | AI37: Pause (seq 2859) | AJ37: 55.8% ACoS on 9 orders / 87 clicks (CC 31 Aug–29 Sep). Second discovery campaign in its family (fold = pause; only negatives move). | AK37: seq 2859 structure: agree with review 40; seq 1728 NOT SERVING hold(s) moot — campaign paused
A38: 24229225667028 | B38: D-S4-SP-queen sheet silk-(Silk)-LSV-Exact-Rank-DO-SATIN-WHITE-QUEEN | C38: silk fitted sheet [exact, $1.68, 25 clicks]; queen sheet silk [exact, $1.83, 18 clicks]; queen bed sheet silk [exact, $1.35, 8 clicks]; satin silk sheet set queen [exact, $1.90]; silk bed sheet [exact, paused, $1.41]; silk bedsheet [exact, paused, $2.66]; silk sheet [exact, paused, $3.17] | D38: 117005423745524; 13334085515870; 46784893351913; 77370120349440 | E38: ENABLED | F38: Ranking | G38: Ranking | H38: OUT | I38: Exact | J38: SATIN-QUEEN-BLACK | K38: SATIN-QUEEN-BLACK | L38: $1.68 / $1.83 / $1.35 / $1.90 / $1.68 / $1.83 / $1.35 / $1.90 | M38: $1.68 / $1.83 / $1.35 / $1.90 / $1.26 / $1.37 / $1.01 / $1.43 | N38: 100 | O38: 100 | P38: 3.36 | Q38: 3.36 | R38: 0 | S38: 0 | T38: 0 | U38: 0 | V38: 10 | W38: 5 | X38: ENABLED | Y38: none | Z38: defer — engine name wrong (SKU token SATIN-QUEEN-BLACK); load a corrected name after 28 Oct | AA38: 142.72 | AB38: 51 | AC38: 9 | AD38: 52.6 | AE38: 86.27 | AF38: 11.76 | AG38: 31 | AH38: Price cut | AI38: Cut base 25% ($1.68 / $1.83 / $1.35 / $1.90 / $1.68 / $1.83 / $1.35 / $1.90 → $1.68 / $1.83 / $1.35 / $1.90 / $1.26 / $1.37 / $1.01 / $1.43); Budget $10 → $5 | AJ38: 52.6% ACoS on 9 orders / 51 clicks (CC 31 Aug–29 Sep). Cuts of −29.6% to −30.1% on targets with 1, 5 and 3 orders break the 25% cap. With the modifier at 100% the TOS price still falls 25%. Mix is right: 86% TOS, 12% PP (CC 30d). | AK38: seq 90 budget: agree with review 40; seq 91 tos: drop (hold 100); seq 94 bid: correct to 1.26/1.37/1.01/1.43; seq 95 bid: correct to 1.26/1.37/1.01/1.43; seq 96 bid: correct to 1.26/1.37/1.01/1.43; seq 97 bid: correct to 1.26/1.37/1.01/1.43; seq 1805 child: reject — keep SATIN-QUEEN-BLACK; seq 2885 rename CHANGE
A39: 173446552008266 | B39: D-S4-satin queen sheets set - [Satin|Queen] - Exact - Ran - DO - SATIN-QUEEN-BLACK | C39: satin queen sheets set [exact] | D39: satin queen sheets set | E39: ENABLED | F39: Ranking | G39: Ranking | H39: Satin|Queen | I39: Exact | J39: SATIN-QUEEN-BLACK | K39: SATIN-QUEEN-BLACK | L39: $1.65 | M39: $1.24 | N39: 30 | O39: 73 | P39: 2.15 | Q39: 2.15 | U39: 0 | V39: 14.13 | W39: 14.13 | X39: ENABLED | Y39: none | Z39: defer — engine name wrong (SKU token SATIN-QUEEN-BLACK); load a corrected name after 28 Oct | AA39: 139.09 | AB39: 77 | AC39: 6 | AD39: 75.7 | AE39: 49.35 | AF39: 41.56 | AG39: 44 | AH39: Ranking push | AI39: Mix fix in one write: base $1.65 → $1.24, boost → 73% (top of search $2.15 → $2.15); PUSH-SMALL satin queen sheets set (8 → 3): hold the top-of-search price; product pages 42% | AJ39: No run decision and no issue found; 75.7% ACoS on 6 orders / 77 clicks (CC 31 Aug–29 Sep). Note: above break-even with no pricing row in the run; price at the next cycle unless it is chosen for the ranking push. | AK39: seq 1815 child: reject — keep SATIN-QUEEN-BLACK; seq 2079 retag LOAD; seq 2902 rename CHANGE | AL39: PUSH-SMALL · score 50 · 1.7 TOS clicks/day (now 1.2) · TOS $2.03 · $5/day · loss $4.01/order full price, $8.86 deal
A40: 50488152164936 | B40: D-S4-SP-satin sheets for queen-(Satin)-HSV-Exact-Rank-DO-SATIN-QUEEN-BLACK | C40: satin sheets for queen [exact, $1.42, 53 clicks] | D40: satin sheets for queen (buys the search term: satin sheets queen) | E40: ENABLED | F40: Ranking | G40: Ranking | H40: OUT | I40: Exact | J40: SATIN-QUEEN-BLACK | K40: SATIN-QUEEN-BLACK | L40: $1.42 | M40: $1.07 | N40: 120 | O40: 163 | P40: 3.12 | Q40: 2.81 | R40: 0 | S40: 0 | T40: 5 | U40: 0 | V40: 9 | W40: 5 | X40: ENABLED | Y40: add negative exact: satin sheets queen; satin sheets queen size | Z40: defer — engine name wrong (SKU token SATIN-QUEEN-BLACK); load a corrected name after 28 Oct | AA40: 132.41 | AB40: 53 | AC40: 10 | AD40: 42.7 | AE40: 69.81 | AF40: 28.3 | AG40: 29 | AH40: Mix fix + price cut | AI40: Mix fix in one write: base $1.42 → $1.07, boost → 163% (top of search $3.12 → $2.81); rest of search 5% → 0%; 42.7% ACoS vs Queen Black 22.5%; product pages 28% | AJ40: 42.7% ACoS on 10 orders / 53 clicks (CC 31 Aug–29 Sep). −25% base with the modifier at 120% gives TOS $2.35 and PP $1.07. The TOS:PP ratio stays 2.2 instead of dropping to 1.83. | AK40: seq 101 budget: pass (flag); seq 102 tos: drop (hold 120); seq 104 ros: flag: take the cuts only after closing tuner record 2848 as…; seq 105 bid: correct to 1.07; seq 1812 child: reject — keep SATIN-QUEEN-BLACK; seq 2897 rename CHANGE | AL40: MAINTAIN · score 49
A41: 152302990884047 | B41: D-S4-silk queen bed sheets set - [Silk|Queen] - Exact - Ran - DO - SATIN-QUEEN-BLACK | C41: silk queen bed sheets set [exact] | D41: silk queen bed sheets set | E41: ENABLED | F41: Ranking | G41: Ranking | H41: Silk|Queen | I41: Exact | J41: SATIN-QUEEN-BLACK | K41: SATIN-QUEEN-BLACK | L41: $1.50 | M41: $1.12 | N41: 30 | O41: 57 | P41: 1.95 | Q41: 1.76 | U41: 0 | V41: 10.92 | W41: 10.92 | X41: ENABLED | Y41: none | Z41: defer — engine name wrong (SKU token SATIN-QUEEN-BLACK); load a corrected name after 28 Oct | AA41: 132.08 | AB41: 75 | AC41: 10 | AD41: 43.5 | AE41: 62.67 | AF41: 36 | AG41: 43 | AH41: Mix fix + price cut | AI41: Mix fix in one write: base $1.50 → $1.12, boost → 57% (top of search $1.95 → $1.76); release the hold; 43.5% ACoS vs Queen Black 22.5%; product pages 36% | AJ41: 43.5% ACoS, 10 orders on 75 clicks (CC 31 Aug–29 Sep) vs Queen Black break-even 17.8%; BE base = $5.03 contribution (Queen Black) × 13.3% CVR = $0.67; cap 25% cut. | AK41: seq 1814 child: reject — keep SATIN-QUEEN-BLACK; seq 2078 retag LOAD; seq 2901 rename CHANGE; seq 1977 NOT SERVING hold(s) → release; price to break-even (our addition, reviewer D) | AL41: MAINTAIN · score 32
A42: 217109942552945 | B42: D-S4-SP-queen sheets silk-(Silk)-MSV-Broad-Disc-DO-SATIN-QUEEN-GREY | C42: queen sheets silk [broad, $1.27]; queen sheets silk [broad, $1.27] | D42: queen sheets silk | E42: ENABLED | F42: Discovery | G42: Discovery | I42: Broad | J42: SATIN-QUEEN-BLACK | K42: SATIN-QUEEN-BLACK | L42: $1.27 | M42: $0.95 | N42: 10 | O42: 10 | P42: 1.4 | Q42: 1.04 | V42: 5 | W42: 5 | X42: ENABLED | Y42: hold seq 1790 (terms not named); add 4 negatives (seq 2261) · add negative exact: king silk sheets; satin bed sheets queen | Z42: none | AA42: 118.62 | AB42: 89 | AC42: 11 | AD42: 34.7 | AE42: 49.44 | AF42: 13.48 | AG42: 92 | AH42: Release hold + price to break-even | AI42: Release hold; cut base $1.27 → $0.95; Keep enabled (fold held) | AJ42: 34.7% ACoS on 11 orders / 89 clicks (CC 31 Aug–29 Sep). The survivors are smaller (e.g. 2849: 215 orders folded into a 14-order survivor, 90d). 2857 repeats review 28's 2868. | AK42: seq 1790 negatives: flag: unverifiable; seq 2261 negatives: agree with review 40; seq 2857 structure: hold (agree); seq 1726,1974 NOT SERVING hold(s) → release; price to break-even (our addition, reviewer D)
A43: 4187663354432 | B43: D-S4-SP-silk sheets-(Silk)-HSV-Broad-Disc-DO-SATIN-FULL-GREY | C43: silk sheets [broad] | D43: whole campaign | E43: ENABLED | F43: Discovery | G43: Discovery | I43: Broad | J43: SATIN-QUEEN-BLACK | K43: SATIN-QUEEN-BLACK | L43: n/a (no target bid in audit) | M43: n/a | N43: 45 | O43: 45 | V43: 5 | W43: 5 | X43: ENABLED | Y43: none | Z43: load (clean): DSS4-SP-Silk Sheets-[Silk]-(VHSV)-Broad-(Discovery)-DO-SATIN-QUEEN-BLACK | AA43: 117.76 | AB43: 121 | AC43: 21 | AD43: 19.2 | AE43: 52.07 | AF43: 1.65 | AG43: 45 | AH43: Rename only | AI43: Load rename only | AJ43: Clean rename (SKU token and objective match what the campaign advertises); 19.2% ACoS on 21 orders / 121 clicks (CC 31 Aug–29 Sep). | AK43: seq 2900 rename LOAD
A44: 90694496079420 | B44: SATIN-TWIN-GREY SP Exact 032923 STR 15 JP | C44: twin satin sheet sets [exact, $1.76, 28 clicks] | D44: twin satin sheet sets | E44: ENABLED | F44: Ranking | G44: Ranking | H44: OUT | I44: Exact | J44: SATIN-TWIN-BLACK-NEW | K44: SATIN-TWIN-BLACK-NEW | L44: $1.76 | M44: $1.41 | N44: 300 | O44: 215 | P44: 7.04 | Q44: 4.44 | R44: 0 | S44: 0 | T44: 0 | U44: 0 | V44: 5 | W44: 5 | X44: ENABLED | Y44: none | Z44: defer — engine name wrong (SKU token SATIN-TWIN-BLACK-NEW); load a corrected name after 28 Oct | AA44: 110.35 | AB44: 29 | AC44: 4 | AD44: 101.2 | AE44: 96.55 | AF44: 3.45 | AG44: 12 | AH44: Price cut | AI44: Cut base 20% ($1.76 → $1.41); TOS 300% → 215% | AJ44: 101.2% ACoS on 4 orders / 29 clicks (CC 31 Aug–29 Sep). A no-op again, so replace it with a real move: #110 base $1.41 with modifier 215% writes TOS $4.44, at or under the engine's own market bound of $4.46. Today $7.04 = 1.76×4.00. Note: plan move to SATIN-TWIN-GREY before 16 Oct (Twin Black 66 units, ~34 days). | AK44: seq 107 tos: correct to 215%; seq 110 bid: pass (with 107→215); seq 1811 child: reject — keep SATIN-TWIN-BLACK-NEW; seq 2894 rename CHANGE
A45: 134608688897105 | B45: D-S4-silk black sheets - [Silk] - Exact - Ran - DO - SATIN-QUEEN-BLACK | C45: silk black sheets [exact, $1.34, 46 clicks] | D45: silk black sheets | E45: ENABLED | F45: Ranking | G45: Conversions | H45: OUT | I45: Exact | J45: SATIN-QUEEN-BLACK | K45: SATIN-QUEEN-BLACK | L45: $1.34 | M45: $1.01 | N45: 90 | O45: 115 | P45: 2.55 | Q45: 2.17 | R45: 0 | S45: 0 | T45: 0 | U45: 0 | V45: 10 | W45: 10 | X45: ENABLED | Y45: none | Z45: defer — engine name wrong ((Conversion)); load a corrected name after 28 Oct | AA45: 107 | AB45: 46 | AC45: 5 | AD45: 69.6 | AE45: 93.48 | AF45: 6.52 | AG45: 16 | AH45: Price cut | AI45: Cut base 25% ($1.34 → $1.01); TOS 90% → 115%; retag → Conversions | AJ45: 69.6% ACoS on 5 orders / 46 clicks (CC 31 Aug–29 Sep). See #115. The GENTLE class takes 15% from a row at 2.49× BE; the step is set by rank proximity, not economics. | AK45: seq 112 tos: correct to 115%; seq 115 bid: correct to 1.01; seq 2895 rename CHANGE; our addition: standard → Conversions (colour term "silk black sheets")
A46: 152256281509429 | B46: D-S4-satin sheets full - [Satin|Full] - Broad - Disc - DO - SATIN-4PCS-FULL-ROSEWOOD | C46: satin sheets full [broad] | D46: whole campaign | E46: ENABLED | F46: Discovery | G46: Discovery | H46: Satin|Full | I46: Broad | J46: SATIN-FULL-GREY | K46: SATIN-FULL-GREY | L46: n/a (no target bid in audit) | M46: n/a | N46: 20 | O46: 20 | V46: 15 | W46: 15 | X46: ENABLED | Y46: add 2 negatives (seq 2260) · add negative exact: silk sheets; satin sheets full; satin sheets; silk sheets queen; silk sheets full; king satin sheets | Z46: defer — engine name wrong (SKU token SATIN-FULL-GREY); load a corrected name after 28 Oct | AA46: 106.47 | AB46: 114 | AC46: 11 | AD46: 32.4 | AE46: 29.82 | AF46: 32.46 | AG46: 33 | AH46: Negatives only | AI46: Add negatives | AJ46: Negative rows agreed with review 40 (add 2 negatives (seq 2260)); 32.4% ACoS on 11 orders / 114 clicks (CC 31 Aug–29 Sep). | AK46: seq 1832 child: reject — keep SATIN-FULL-GREY; seq 2260 negatives: agree with review 40; seq 2932 rename CHANGE
A47: 27425066208772 | B47: D-S4-SP-EXACT-dark blue satin sheets-Satin-SATIN-4PC-QUEEN-NAVY BLUE | C47: dark blue satin sheets [exact] | D47: whole campaign | E47: ENABLED | F47: Conversions | G47: Conversions | I47: Exact | J47: SATIN-4PC-QUEEN-NAVY BLUE | K47: SATIN-4PC-QUEEN-NAVY BLUE | L47: n/a (no target bid in audit) | M47: n/a | N47: 0 | O47: 0 | V47: 9.92 | W47: 9.92 | X47: ENABLED | Y47: none | Z47: load (clean): DSS4-SP-Dark Blue Satin Sheets-(VLSV)-Exact-(Conversion)-DO-SATIN-4PC-QUEEN-NAVY BLUE | AA47: 101.24 | AB47: 50 | AC47: 12 | AD47: 24.4 | AE47: 12 | AF47: 86 | AG47: 13 | AH47: Rename only | AI47: Load rename only | AJ47: Clean rename (SKU token and objective match what the campaign advertises); 24.4% ACoS on 12 orders / 50 clicks (CC 31 Aug–29 Sep). | AK47: seq 2084 retag LOAD; seq 2910 rename LOAD
A48: 146264161268494 | B48: D-S4-SP-PHRASE-silk sheets full size-Silk|Full-SATIN-FULL-GREY | C48: silk sheets full size [phrase, $1.50]; silk sheets full size [phrase, $1.50] | D48: silk sheets full size | E48: ENABLED | F48: Discovery | G48: Discovery | I48: Phrase | J48: SATIN-FULL-GREY | K48: SATIN-FULL-GREY | L48: $1.50 | M48: $1.12 | N48: 0 | O48: 0 | P48: 1.5 | Q48: 1.12 | V48: 5 | W48: 5 | X48: ENABLED | Y48: hold seq 1793 (terms not named) · add negative exact: silk sheets full; silk sheets full size | Z48: defer — engine name wrong (SKU token SATIN-FULL-GREY); load a corrected name after 28 Oct | AA48: 101.17 | AB48: 63 | AC48: 9 | AD48: 38.6 | AE48: 16.13 | AF48: 35.48 | AG48: 11 | AH48: Release hold + price to break-even | AI48: Release hold; cut base $1.50 → $1.12 | AJ48: 38.6% ACoS, 9 orders on 63 clicks (CC 31 Aug–29 Sep) vs Full Grey break-even 26.2%; BE base = $7.62 contribution (Full Grey) × 14.3% CVR = $1.09; cap 25% cut. | AK48: seq 1793 negatives: flag: unverifiable; seq 1817 child: reject — keep SATIN-FULL-GREY; seq 2081 retag LOAD; seq 2906 rename CHANGE; seq 1733 NOT SERVING hold(s) → release; price to break-even (our addition, reviewer D)
A49: 59818700734597 | B49: D-S4-satin king sheets set - [Satin|King] - Exact - Ran - DO - SATIN-4PC-KING-GREY | C49: satin king sheets set [exact] | D49: satin king sheets set | E49: ENABLED | F49: Ranking | G49: Ranking | H49: Satin|King | I49: Exact | J49: SATIN-4PC-KING-GREY | K49: SATIN-4PC-KING-GREY | L49: $1.73 | M49: $1.30 | N49: 30 | O49: 55 | P49: 2.25 | Q49: 2.02 | U49: 0 | V49: 16.74 | W49: 16.74 | X49: ENABLED | Y49: none | Z49: load (clean): DSS4-SP-Satin King Sheets Set-[Satin|King]-(LSV)-Exact-(Ranking)-DO-SATIN-4PC-KING-GREY | AA49: 97.81 | AB49: 52 | AC49: 7 | AD49: 42.2 | AE49: 47.06 | AF49: 29.41 | AG49: 17 | AH49: Mix fix + price cut | AI49: Mix fix in one write: base $1.73 → $1.30, boost → 55% (top of search $2.25 → $2.02); rest of search → 0% (24% of clicks); 42.2% ACoS vs King Grey 18.9%; product pages 29% | AJ49: Clean rename (SKU token and objective match what the campaign advertises); 42.2% ACoS on 7 orders / 52 clicks (CC 31 Aug–29 Sep). Note: above break-even with no pricing row in the run; price at the next cycle unless it is chosen for the ranking push. | AK49: seq 2099 retag LOAD; seq 2937 rename LOAD
A50: 117094112974140 | B50: D-S4-black silk sheets queen - [Silk|Queen] - Exact - Ran - DO - SATIN-QUEEN-BLACK | C50: black silk sheets queen [exact] | D50: black silk sheets queen | E50: ENABLED | F50: Ranking | G50: Conversions | H50: Silk|Queen | I50: Exact | J50: SATIN-QUEEN-BLACK | K50: SATIN-QUEEN-BLACK | L50: $1.55 | M50: $1.16 | N50: 30 | O50: 30 | P50: 2.02 | Q50: 1.51 | V50: 13.51 | W50: 13.51 | X50: ENABLED | Y50: none | Z50: defer — engine name wrong ((Conversion)); load a corrected name after 28 Oct | AA50: 94.68 | AB50: 50 | AC50: 11 | AD50: 32.7 | AE50: 46 | AF50: 24 | AG50: 37 | AH50: Release hold + price to break-even | AI50: Release hold; cut base $1.55 → $1.16; retag → Conversions | AJ50: 32.7% ACoS, 11 orders on 50 clicks (CC 31 Aug–29 Sep) vs Queen Black break-even 17.8%; BE base = $5.03 contribution (Queen Black) × 22.0% CVR = $1.11; cap 25% cut. | AK50: seq 2085 retag correct to Conversions; seq 2912 rename CHANGE; seq 1978 NOT SERVING hold(s) → release; price to break-even (our addition, reviewer D)
A51: 119529723647443 | B51: SSS4-PHRASE-(silk bedsheets)-Browse Kws Migr. | C51: silk bedsheets [phrase, $1.41]; silk bedsheets [phrase, $2.00] | D51: whole campaign | E51: ENABLED | F51: Discovery | G51: Discovery | I51: Phrase | J51: SATIN-QUEEN-BLACK | K51: SATIN-QUEEN-BLACK | L51: $1.41 | M51: $1.41 | N51: 0 | O51: 0 | P51: 1.41 | Q51: 1.41 | V51: 20 | W51: 20 | X51: PAUSED | Y51: none | Z51: none | AA51: 94.04 | AB51: 67 | AC51: 3 | AD51: 109.8 | AE51: 76.12 | AF51: 0 | AG51: 47 | AH51: Pause | AI51: Pause (seq 2860) | AJ51: 109.8% ACoS on 3 orders / 67 clicks (CC 31 Aug–29 Sep). Only the fences travel, never the keywords. Phrase "silk sheet set" does not cover "silk bedsheets" or "silk bed sheets", so the coverage is dropped, not merged. | AK51: seq 2860 structure: pass as pauses (flag); seq 1751 NOT SERVING hold(s) moot — campaign paused
A52: 204281123271494 | B52: D-S4-satin full size bed sheets - [Satin|Full] - Exact - Ran - DO - SATIN-FULL-BLACK | C52: satin full size bed sheets [exact, $1.01, 30 clicks] | D52: satin full size bed sheets | E52: ENABLED | F52: Ranking | G52: Ranking | H52: OUT | I52: Exact | J52: SATIN-FULL-BLACK | K52: SATIN-FULL-BLACK | L52: $1.01 | M52: $0.86 | N52: 260 | O52: 260 | P52: 3.64 | Q52: 3.1 | R52: 0 | S52: 0 | T52: 0 | U52: 0 | V52: 23.83 | W52: 23.83 | X52: ENABLED | Y52: none | Z52: defer — engine name wrong (SKU token SATIN-FULL-BLACK); load a corrected name after 28 Oct | AA52: 93.69 | AB52: 30 | AC52: 10 | AD52: 31.1 | AE52: 93.33 | AF52: 6.67 | AG52: 49 | AH52: Price cut | AI52: Cut base 15% ($1.01 → $0.86) | AJ52: 31.1% ACoS on 10 orders / 30 clicks (CC 31 Aug–29 Sep) vs Full Black break-even 27.5%; audit row loads as written (review 40 agrees). | AK52: seq 120 bid: pass (flag); seq 1819 child: reject — keep SATIN-FULL-BLACK; seq 2911 rename CHANGE
A53: 49674570581247 | B53: D-S4-SP-queen size sheets silk-(Silk)-LSV-Exact-Rank-DO-SATIN-QUEEN-GREY | C53: queen size sheets silk [exact, $1.79, 29 clicks] | D53: — | E53: ENABLED | F53: Ranking | G53: Ranking | H53: OUT | I53: Exact | J53: SATIN-QUEEN-BLACK | K53: SATIN-QUEEN-BLACK | L53: $1.79 | M53: $1.79 | N53: 100 | O53: 100 | P53: 3.58 | Q53: 3.58 | R53: 0 | S53: 0 | T53: 0 | U53: 0 | V53: 5 | W53: 5 | X53: ENABLED | Y53: none | Z53: defer — engine name wrong (SKU token SATIN-QUEEN-BLACK); load a corrected name after 28 Oct | AA53: 89.72 | AB53: 29 | AC53: 8 | AD53: 36.7 | AE53: 93.1 | AF53: 0 | AG53: 24 | AH53: No change (flag: above break-even) | AI53: No change in this run — flag: 36.7% ACoS vs Queen Black break-even 17.8% (no run row prices it) | AJ53: No run decision and no issue found; 36.7% ACoS on 8 orders / 29 clicks (CC 31 Aug–29 Sep). Note: above break-even with no pricing row in the run; price at the next cycle unless it is chosen for the ranking push. | AK53: seq 1816 child: reject — keep SATIN-QUEEN-BLACK; seq 2904 rename CHANGE
A54: 19421880211317 | B54: D-S4-queen silk sheets set - [Silk|Queen] - Exact - Ran - DO - SATIN-QUEEN-BLACK | C54: queen silk sheets set [exact, $0.78, 48 clicks] | D54: queen silk sheets set | E54: ENABLED | F54: Ranking | G54: Ranking | H54: OUT | I54: Exact | J54: SATIN-QUEEN-BLACK | K54: SATIN-QUEEN-BLACK | L54: $0.78 | M54: $0.78 | N54: 140 | O54: 80 | P54: 1.87 | Q54: 1.4 | R54: 0 | S54: 0 | T54: 0 | U54: 0 | V54: 20 | W54: 20 | X54: ENABLED | Y54: none | Z54: defer — engine name wrong (SKU token SATIN-QUEEN-BLACK); load a corrected name after 28 Oct | AA54: 86.65 | AB54: 48 | AC54: 11 | AD54: 26.3 | AE54: 97.92 | AF54: 0 | AG54: 46 | AH54: Price cut | AI54: MAINTAIN queen silk sheets set: TOS +140% → +80% (TOS $1.87 → $1.40); 26.3% ACoS against Queen Black 17.8% break-even | AJ54: No run decision and no issue found; 26.3% ACoS on 11 orders / 48 clicks (CC 31 Aug–29 Sep). Note: above break-even with no pricing row in the run; price at the next cycle unless it is chosen for the ranking push. | AK54: seq 1828 child: reject — keep SATIN-QUEEN-BLACK; seq 2926 rename CHANGE | AL54: MAINTAIN · score 38
A55: 119446025046609 | B55: D-S4-red satin sheets - [Satin] - Exact - Ran - DO - SATIN-4PC-RED-QUEEN | C55: red satin sheets [exact] | D55: whole campaign | E55: ENABLED | F55: Ranking | G55: Conversions | H55: Satin | I55: Exact | J55: SATIN-4PC-RED-QUEEN | K55: SATIN-4PCS-KING-RED | L55: n/a (no target bid in audit) | M55: n/a | N55: 50 | O55: 50 | V55: 6.52 | W55: 6.52 | X55: ENABLED | Y55: none | Z55: defer — engine name wrong (SKU token SATIN-4PC-RED-QUEEN; (Conversion)); load a corrected name after 28 Oct | AA55: 85.82 | AB55: 76 | AC55: 8 | AD55: 32.8 | AE55: 51.32 | AF55: 44.74 | AG55: 36 | AH55: Child swap | AI55: Swap child to SATIN-4PCS-KING-RED; retag → Conversions | AJ55: 32.8% ACoS on 8 orders / 76 clicks (CC 31 Aug–29 Sep). Swap by hand now (seq 1825); Queen Red 34 units, out ~10 Oct (SB 29 Sep). | AK55: seq 1825 child: pass — apply NOW (outside the held group); seq 2089 retag correct to Conversions; seq 2918 rename CHANGE
A56: 276983621807441 | B56: D-S4-twin silk sheets - [Silk|Twin] - Exact - Ran - DO - SATIN-TWIN-BLACK-NEW | C56: twin silk sheets [exact, $1.44, 33 clicks] | D56: twin silk sheets | E56: ENABLED | F56: Ranking | G56: Ranking | H56: OUT | I56: Exact | J56: SATIN-TWIN-BLACK-NEW | K56: SATIN-TWIN-BLACK-NEW | L56: $1.44 | M56: $1.08 | N56: 100 | O56: 100 | P56: 2.88 | Q56: 2.16 | R56: 0 | S56: 0 | T56: 0 | U56: 0 | V56: 11.64 | W56: 5.82 | X56: ENABLED | Y56: none | Z56: defer — engine name wrong (SKU token SATIN-TWIN-BLACK-NEW); load a corrected name after 28 Oct | AA56: 83.59 | AB56: 33 | AC56: 5 | AD56: 55.4 | AE56: 96.97 | AF56: 3.03 | AG56: 21 | AH56: Price cut | AI56: Cut base 25% ($1.44 → $1.08); Budget $11.64 → $5.82 | AJ56: 55.4% ACoS on 5 orders / 33 clicks (CC 31 Aug–29 Sep). −29.9% breaks the cap (5 orders). $1.08 × 2.00 = $2.16. Note: plan move to SATIN-TWIN-GREY before 16 Oct (Twin Black 66 units, ~34 days). | AK56: seq 131 budget: agree with review 40; seq 132 tos: drop (hold 100); seq 135 bid: correct to 1.08; seq 1833 child: reject — keep SATIN-TWIN-BLACK-NEW; seq 2933 rename CHANGE
A57: 156074162580081 | B57: D-S4-sateen sheets king size - [Satin|King] - Exact - Ran - DO - SATIN-4PC-KING-GREY | C57: sateen sheets king size [exact] | D57: — | E57: ENABLED | F57: Ranking | G57: Ranking | H57: Satin|King | I57: Exact | J57: SATIN-4PC-KING-GREY | K57: SATIN-4PC-KING-GREY | L57: n/a (no target bid in audit) | M57: n/a | N57: 50 | O57: 50 | V57: 25.16 | W57: 25.16 | X57: ENABLED | Y57: none | Z57: load (clean): DSS4-SP-Sateen Sheets King Size-[Satin|King]-(LSV)-Exact-(Ranking)-DO-SATIN-4PC-KING-GREY | AA57: 82.1 | AB57: 29 | AC57: 3 | AD57: 87.9 | AE57: 34.48 | AF57: 0 | AG57: 6 | AH57: No change (flag: above break-even) | AI57: No change in this run — flag: 87.9% ACoS vs King Grey break-even 15.3% (no run row prices it) | AJ57: Clean rename (SKU token and objective match what the campaign advertises); 87.9% ACoS on 3 orders / 29 clicks (CC 31 Aug–29 Sep). Note: above break-even with no pricing row in the run; price at the next cycle unless it is chosen for the ranking push. | AK57: seq 2082 retag LOAD; seq 2908 rename LOAD
A58: 159484070732130 | B58: D-S4-black satin sheets full - [Satin|Full] - Exact - Ran - DO - SATIN-FULL-BLACK | C58: black satin sheets full [exact, $1.27, 34 clicks] | D58: black satin sheets full | E58: ENABLED | F58: Ranking | G58: Conversions | H58: OUT | I58: Exact | J58: SATIN-FULL-BLACK | K58: SATIN-FULL-BLACK | L58: $1.27 | M58: $1.27 | N58: 100 | O58: 100 | P58: 2.54 | Q58: 2.54 | R58: 0 | S58: 0 | T58: 30 | U58: 0 | V58: 19.4 | W58: 19.4 | X58: ENABLED | Y58: none | Z58: defer — engine name wrong ((Conversion)); load a corrected name after 28 Oct | AA58: 81.98 | AB58: 34 | AC58: 16 | AD58: 17.3 | AE58: 94.12 | AF58: 2.94 | AG58: 34 | AH58: Price cut | AI58: ROS 30% → 0%; retag → Conversions | AJ58: Objective Ranking → Conversions by the standard (colour term "black satin sheets full"); 17.3% ACoS on 16 orders / 34 clicks (CC 31 Aug–29 Sep). | AK58: seq 139 ros: agree with review 40; seq 2905 rename CHANGE; our addition: standard → Conversions (colour term "black satin sheets full")
A59: 36991466146796 | B59: D-S4-full size bed sheets silk - [Silk|Full] - Exact - Ran - DO - SATIN-FULL-BLACK | C59: full size bed sheets silk [exact, $1.14, 32 clicks] | D59: full size bed sheets silk | E59: ENABLED | F59: Ranking | G59: Ranking | H59: OUT | I59: Exact | J59: SATIN-FULL-BLACK | K59: SATIN-FULL-BLACK | L59: $1.14 | M59: $0.86 | N59: 120 | O59: 120 | P59: 2.51 | Q59: 1.89 | R59: 0 | S59: 0 | T59: 0 | U59: 0 | V59: 15 | W59: 7.5 | X59: ENABLED | Y59: none | Z59: defer — engine name wrong (SKU token SATIN-FULL-BLACK); load a corrected name after 28 Oct | AA59: 76.97 | AB59: 32 | AC59: 9 | AD59: 29.4 | AE59: 100 | AF59: 0 | AG59: 16 | AH59: Price cut | AI59: Cut base 25% ($1.14 → $0.86); Budget $15 → $7.5 | AJ59: 29.4% ACoS on 9 orders / 32 clicks (CC 31 Aug–29 Sep) vs Full Black break-even 27.5%; audit row loads as written (review 40 agrees). | AK59: seq 141 budget: agree with review 40; seq 145 bid: pass (flag); seq 1822 child: reject — keep SATIN-FULL-BLACK; seq 2915 rename CHANGE
A60: 279063293275463 | B60: D-S4-white silk sheets queen - [Silk|Queen] - Exact - Ran - DO - SATIN-WHITE-QUEEN | C60: white silk sheets queen [exact] | D60: white silk sheets queen | E60: ENABLED | F60: Ranking | G60: Conversions | H60: Silk|Queen | I60: Exact | J60: SATIN-WHITE-QUEEN | K60: SATIN-WHITE-QUEEN | L60: $1.53 | M60: $1.32 | N60: 50 | O60: 50 | P60: 2.29 | Q60: 1.98 | V60: 11.36 | W60: 11.36 | X60: ENABLED | Y60: none | Z60: defer — engine name wrong ((Conversion)); load a corrected name after 28 Oct | AA60: 76.83 | AB60: 41 | AC60: 6 | AD60: 41.5 | AE60: 70.73 | AF60: 24.39 | AG60: 22 | AH60: Release hold + price to break-even | AI60: Release hold; cut base $1.53 → $1.32; retag → Conversions | AJ60: 41.5% ACoS, 6 orders on 41 clicks (CC 31 Aug–29 Sep) vs Queen White break-even 29.1%; BE base = $9.02 contribution (Queen White) × 14.6% CVR = $1.32; cap 25% cut. | AK60: seq 2092 retag correct to Conversions; seq 2924 rename CHANGE; seq 1981 NOT SERVING hold(s) → release; price to break-even (our addition, reviewer D)
A61: 166165612969671 | B61: D-S4-full silk sheets - [Silk|Full] - Exact - Ran - DO - SATIN-FULL-BLACK | C61: full silk sheets [exact] | D61: full silk sheets | E61: ENABLED | F61: Ranking | G61: Ranking | H61: Silk|Full | I61: Exact | J61: SATIN-FULL-BLACK | K61: SATIN-FULL-BLACK | L61: $1.50 | M61: $1.50 | N61: 50 | O61: 50 | P61: 2.25 | Q61: 2.25 | V61: 11.68 | W61: 11.68 | X61: ENABLED | Y61: none | Z61: defer — engine name wrong (SKU token SATIN-FULL-BLACK); load a corrected name after 28 Oct | AA61: 76.7 | AB61: 36 | AC61: 7 | AD61: 37.5 | AE61: 94.44 | AF61: 2.78 | AG61: 14 | AH61: Release hold, keep price | AI61: Release hold; keep base $1.50 (at/under break-even) | AJ61: 37.5% ACoS, 7 orders on 36 clicks (CC 31 Aug–29 Sep) vs Full Black break-even 27.5%; BE base = $8.04 contribution (Full Black) × 19.4% CVR = $1.56; cap 25% cut. | AK61: seq 1823 child: reject — keep SATIN-FULL-BLACK; seq 2088 retag LOAD; seq 2916 rename CHANGE; seq 1979 NOT SERVING hold(s) → release; price to break-even (our addition, reviewer D)
A62: 80956023116321 | B62: D-S4-SP-EXACT-satin full sheets-Satin|Full-SATIN-FULL-BLACK | C62: satin full sheets [exact, $2.21]; satin full sheets [exact, $2.21] | D62: satin full sheets | E62: ENABLED | F62: Conversions | G62: Ranking | I62: Exact | J62: SATIN-FULL-BLACK | K62: SATIN-FULL-BLACK | L62: $2.21 | M62: $1.66 | N62: 0 | O62: 20 | P62: 2.21 | Q62: 1.99 | U62: 0 | V62: 9.58 | W62: 9.58 | X62: ENABLED | Y62: none | Z62: defer — engine name wrong (SKU token SATIN-FULL-BLACK; (Ranking)); load a corrected name after 28 Oct | AA62: 69.97 | AB62: 33 | AC62: 4 | AD62: 59.4 | AE62: 15.15 | AF62: 81.82 | AG62: 4 | AH62: Mix fix + price cut | AI62: Mix fix in one write: base $2.21 → $1.66, boost → 20% (top of search $2.21 → $1.99); release the hold; 59.4% ACoS vs Full Black 28.5%; product pages 82% | AJ62: 59.4% ACoS, 4 orders on 33 clicks (CC 31 Aug–29 Sep) vs Full Black break-even 27.5%; BE base = $8.04 contribution (Full Black) × 12.1% CVR = $0.97; cap 25% cut. | AK62: seq 1821 child: reject — keep SATIN-FULL-BLACK; seq 2087 retag correct to Ranking; seq 2914 rename CHANGE; seq 1735 NOT SERVING hold(s) → release; price to break-even (our addition, reviewer D)
A63: 68788829997180 | B63: SSS4-PHRASE-(silk bed sheets)-Browse Kws Migr. | C63: silk bed sheets [phrase, $1.04]; silk bed sheets [phrase, $2.25] | D63: whole campaign | E63: ENABLED | F63: Discovery | G63: Discovery | I63: Phrase | J63: SATIN-QUEEN-BLACK | K63: SATIN-QUEEN-BLACK | L63: $1.04 | M63: $1.04 | N63: 0 | O63: 0 | P63: 1.04 | Q63: 1.04 | V63: 10 | W63: 10 | X63: PAUSED | Y63: none | Z63: none | AA63: 69.56 | AB63: 48 | AC63: 4 | AD63: 56.6 | AE63: 25.53 | AF63: 6.38 | AG63: 37 | AH63: Pause | AI63: Pause (seq 2861) | AJ63: 56.6% ACoS on 4 orders / 48 clicks (CC 31 Aug–29 Sep). Only the fences travel, never the keywords. Phrase "silk sheet set" does not cover "silk bedsheets" or "silk bed sheets", so the coverage is dropped, not merged. | AK63: seq 2861 structure: pass as pauses (flag); seq 1755 NOT SERVING hold(s) moot — campaign paused
A64: 72069146058874 | B64: D-S4-bed sheets full size silk - [Silk|Full] - Exact - Ran - DO - SATIN-FULL-BLACK | C64: bed sheets full size silk [exact, $1.46, 18 clicks] | D64: whole campaign | E64: PAUSED | F64: Ranking | G64: Ranking | H64: OUT | I64: Exact | J64: SATIN-FULL-BLACK | K64: SATIN-FULL-BLACK | L64: $1.46 | M64: $1.46 | N64: 300 | O64: 300 | P64: 5.84 | Q64: 5.84 | R64: 0 | S64: 0 | T64: 0 | U64: 0 | V64: 11.37 | W64: 11.37 | X64: PAUSED | Y64: none | Z64: load (clean): DSS4-SP-Bed Sheets Full Size Silk-[Silk|Full]-(LSV)-Exact-(Ranking)-DO-SATIN-FULL-BLACK | AA64: 69.43 | AB64: 18 | AC64: 2 | AD64: 119.9 | AE64: 100 | AF64: 0 | AG64: 8 | AH64: Rename only | AI64: Load rename only | AJ64: Clean rename (SKU token and objective match what the campaign advertises); 119.9% ACoS on 2 orders / 18 clicks (CC 31 Aug–29 Sep). | AK64: seq 2948 rename LOAD
A65: 126220886415242 | B65: D-S4-silky sheets queen - [Silk|Queen] - Exact - Ran - DO - SATIN-QUEEN-BLACK | C65: silky sheets queen [exact, $0.59, 29 clicks] | D65: silky sheets queen | E65: ENABLED | F65: Ranking | G65: Ranking | H65: OUT | I65: Exact | J65: SATIN-QUEEN-BLACK | K65: SATIN-QUEEN-BLACK | L65: $0.59 | M65: $0.50 | N65: 300 | O65: 300 | P65: 2.36 | Q65: 2 | R65: 0 | S65: 0 | T65: 0 | U65: 0 | V65: 13.74 | W65: 13.74 | X65: ENABLED | Y65: none | Z65: defer — engine name wrong (SKU token SATIN-QUEEN-BLACK); load a corrected name after 28 Oct | AA65: 66.92 | AB65: 29 | AC65: 8 | AD65: 28.1 | AE65: 100 | AF65: 0 | AG65: 20 | AH65: Price cut | AI65: Cut base 15% ($0.59 → $0.50) | AJ65: 28.1% ACoS on 8 orders / 29 clicks (CC 31 Aug–29 Sep) vs Queen Black break-even 17.8%; audit row loads as written (review 40 agrees). | AK65: seq 155 bid: pass (flag); seq 1830 child: reject — keep SATIN-QUEEN-BLACK; seq 2928 rename CHANGE
A66: 10111709816414 | B66: D-S4-queen bed sheets silk - [Silk|Queen] - Exact - Ran - DO - SATIN-QUEEN-BLACK | C66: queen bed sheets silk [exact] | D66: queen bed sheets silk | E66: ENABLED | F66: Ranking | G66: Ranking | H66: Silk|Queen | I66: Exact | J66: SATIN-QUEEN-BLACK | K66: SATIN-QUEEN-BLACK | L66: $1.46 | M66: $1.09 | N66: 50 | O66: 50 | P66: 2.19 | Q66: 1.64 | V66: 10.84 | W66: 10.84 | X66: ENABLED | Y66: none | Z66: defer — engine name wrong (SKU token SATIN-QUEEN-BLACK); load a corrected name after 28 Oct | AA66: 64.73 | AB66: 31 | AC66: 6 | AD66: 38.2 | AE66: 93.55 | AF66: 0 | AG66: 18 | AH66: Release hold + price to break-even | AI66: Release hold; cut base $1.46 → $1.09 | AJ66: 38.2% ACoS, 6 orders on 31 clicks (CC 31 Aug–29 Sep) vs Queen Black break-even 17.8%; BE base = $5.03 contribution (Queen Black) × 19.4% CVR = $0.97; cap 25% cut. | AK66: seq 1834 child: reject — keep SATIN-QUEEN-BLACK; seq 2097 retag LOAD; seq 2934 rename CHANGE; seq 1983 NOT SERVING hold(s) → release; price to break-even (our addition, reviewer D)
A67: 195376730173968 | B67: D-S4-twin satin sheets - [Satin|Twin] - Exact - Ran - DO - SATIN-TWIN-BLACK-NEW | C67: twin satin sheets [exact, $1.55, 25 clicks] | D67: twin satin sheets | E67: ENABLED | F67: Ranking | G67: Ranking | H67: OUT | I67: Exact | J67: SATIN-TWIN-BLACK-NEW | K67: SATIN-TWIN-BLACK-NEW | L67: $1.55 | M67: $1.16 | N67: 100 | O67: 100 | P67: 3.1 | Q67: 2.32 | R67: 0 | S67: 0 | T67: 0 | U67: 0 | V67: 12.53 | W67: 6.27 | X67: ENABLED | Y67: none | Z67: defer — engine name wrong (SKU token SATIN-TWIN-BLACK-NEW); load a corrected name after 28 Oct | AA67: 63.21 | AB67: 25 | AC67: 7 | AD67: 33.3 | AE67: 80 | AF67: 20 | AG67: 20 | AH67: Price cut | AI67: Cut base 25% ($1.55 → $1.16); Budget $12.53 → $6.27 | AJ67: 33.3% ACoS on 7 orders / 25 clicks (CC 31 Aug–29 Sep). −29.7% breaks the cap (7 orders). $1.16 × 2.00 = $2.32. Note: plan move to SATIN-TWIN-GREY before 16 Oct (Twin Black 66 units, ~34 days). | AK67: seq 156 budget: agree with review 40; seq 157 tos: drop (hold 100); seq 160 bid: correct to 1.16; seq 1818 child: reject — keep SATIN-TWIN-BLACK-NEW; seq 2907 rename CHANGE
A68: 45314620215925 | B68: D-S4-SP-EXACT-black silk sheets full-Silk|Full-SATIN-FULL-BLACK | C68: black silk sheets full [exact] | D68: whole campaign | E68: ENABLED | F68: Ranking | G68: Conversions | I68: Exact | J68: SATIN-FULL-BLACK | K68: SATIN-FULL-BLACK | L68: n/a (no target bid in audit) | M68: n/a | N68: 0 | O68: 0 | V68: 9.58 | W68: 9.58 | X68: ENABLED | Y68: none | Z68: defer — engine name wrong ((Conversion)); load a corrected name after 28 Oct | AA68: 62.61 | AB68: 37 | AC68: 4 | AD68: 53.1 | AE68: 47.22 | AF68: 38.89 | AG68: 4 | AH68: Retag only | AI68: retag → Conversions | AJ68: Objective Ranking → Conversions by the standard (our retag verdict); 53.1% ACoS on 4 orders / 37 clicks (CC 31 Aug–29 Sep). | AK68: seq 2091 retag correct to Conversions; seq 2922 rename CHANGE
A69: 96686463090060 | B69: D-S4-grey silk sheets - [Silk] - Exact - Ran - DO - SATIN-QUEEN-GREY | C69: grey silk sheets [exact, $1.37, 37 clicks] | D69: whole campaign | E69: PAUSED | F69: Ranking | G69: Conversions | H69: OUT | I69: Exact | J69: SATIN-QUEEN-GREY | K69: SATIN-QUEEN-GREY | L69: $1.37 | M69: $0.47 | N69: 100 | O69: 100 | P69: 2.74 | Q69: 0.94 | R69: 0 | S69: 0 | T69: 0 | U69: 0 | V69: 8.31 | W69: 8.31 | X69: ENABLED | Y69: none | Z69: defer — engine name wrong ((Conversion)); load a corrected name after 28 Oct | AA69: 62.48 | AB69: 37 | AC69: 5 | AD69: 42.5 | AE69: 33.33 | AF69: 63.89 | AG69: 18 | AH69: Revive at break-even | AI69: Revive at break-even base ($0.47 max); retag → Conversions | AJ69: 42.5% ACoS on 5 orders / 37 clicks (CC 31 Aug–29 Sep). Queen Grey break-even is 10.8% (SB 8/30–9/28). | AK69: seq 2836 structure: correct to ruling-D price; seq 2959 rename CHANGE; our addition: standard → Conversions (colour term "grey silk sheets")
A70: 96788673180864 | B70: D-S4-purple silk sheets - [Silk] - Exact - Ran - DO - SATIN-QUEEN-PURPLE | C70: purple silk sheets [exact] | D70: whole campaign | E70: ENABLED | F70: Ranking | G70: Conversions | H70: Silk | I70: Exact | J70: SATIN-QUEEN-PURPLE | K70: SATIN-QUEEN-PURPLE | L70: n/a (no target bid in audit) | M70: n/a | N70: 0 | O70: 0 | V70: 12 | W70: 12 | X70: ENABLED | Y70: none | Z70: defer — engine name wrong ((Conversion)); load a corrected name after 28 Oct | AA70: 62.24 | AB70: 76 | AC70: 5 | AD70: 41.1 | AE70: 5.26 | AF70: 88.16 | AG70: 36 | AH70: Retag only | AI70: retag → Conversions | AJ70: Objective Ranking → Conversions by the standard (our retag verdict); 41.1% ACoS on 5 orders / 76 clicks (CC 31 Aug–29 Sep). | AK70: seq 2102 retag correct to Conversions; seq 2943 rename CHANGE
A71: 9973300181593 | B71: D-S4-SP-EXACT-black queen sheets-Generic-SATIN-QUEEN-BLACK | C71: black queen sheets [exact, $1.55]; black queen sheets [exact, $1.55] | D71: black queen sheets | E71: ENABLED | F71: Conversions | G71: Conversions | I71: Exact | J71: SATIN-QUEEN-BLACK | K71: SATIN-QUEEN-BLACK | L71: $1.55 | M71: $1.16 | N71: 0 | O71: 0 | P71: 1.55 | Q71: 1.16 | V71: 8.06 | W71: 8.06 | X71: ENABLED | Y71: none | Z71: load (clean): DSS4-SP-Black Queen Sheets-(MSV)-Exact-(Conversion)-DO-SATIN-QUEEN-BLACK | AA71: 60.59 | AB71: 36 | AC71: 4 | AD71: 58.3 | AE71: 0 | AF71: 48.57 | AG71: 5 | AH71: Release hold + price to break-even | AI71: Release hold; cut base $1.55 → $1.16 | AJ71: 58.3% ACoS, 4 orders on 36 clicks (CC 31 Aug–29 Sep) vs Queen Black break-even 17.8%; BE base = $5.03 contribution (Queen Black) × 11.1% CVR = $0.56; cap 25% cut. | AK71: seq 2096 retag LOAD; seq 2931 rename LOAD; seq 1741 NOT SERVING hold(s) → release; price to break-even (our addition, reviewer D)
A72: 47941523261030 | B72: D-S4-SP-EXACT-satin bedsheets queen size-Satin|Queen-SATIN-QUEEN-BLACK | C72: satin bedsheets queen size [exact] | D72: satin bedsheets queen size (buys the search term: satin bed sheets queen) | E72: ENABLED | F72: Ranking | G72: Conversions | I72: Exact | J72: SATIN-QUEEN-BLACK | K72: SATIN-QUEEN-BLACK | L72: n/a (no target bid in audit) | M72: n/a | N72: 0 | O72: 0 | V72: 8.06 | W72: 8.06 | X72: ENABLED | Y72: add negative exact: satin bed sheets queen (only after the owner holds its top-of-search price) | Z72: defer — engine name wrong (SKU token SATIN-QUEEN-BLACK; (Conversion)); load a corrected name after 28 Oct | AA72: 59.44 | AB72: 31 | AC72: 7 | AD72: 27.7 | AE72: 58.06 | AF72: 3.23 | AG72: 7 | AH72: Retag only | AI72: retag → Conversions | AJ72: Objective Ranking → Conversions by the standard (our retag verdict); 27.7% ACoS on 7 orders / 31 clicks (CC 31 Aug–29 Sep). | AK72: seq 1827 child: reject — keep SATIN-QUEEN-BLACK; seq 2093 retag correct to Conversions; seq 2925 rename CHANGE | AL72: PUSH-SMALL · score 60 · 0.7 TOS clicks/day · TOS $1.77 · $1/day (with 79231677791815) · loss $2.75/order full price, $7.60 deal
A73: 221215321421557 | B73: D-S4-SP-EXACT-silk bedsheets queen-Silk|Queen-SATIN-QUEEN-BLACK | C73: silk bedsheets queen [exact, $1.86]; silk bedsheets queen [exact, $1.86] | D73: silk bedsheets queen (buys the search term: silk bed sheets queen) | E73: PAUSED | F73: Conversions | G73: Conversions | I73: Exact | J73: SATIN-QUEEN-BLACK | K73: SATIN-QUEEN-BLACK | L73: n/a (no target bid in audit) | M73: n/a | N73: 0 | O73: 0 | V73: 8.06 | W73: 8.06 | X73: PAUSED | Y73: none | Z73: load (clean): DSS4-SP-Silk Bedsheets Queen-(VLSV)-Exact-(Conversion)-DO-SATIN-QUEEN-BLACK | AA73: 58.3 | AB73: 30 | AC73: 3 | AD73: 69.5 | AE73: 66.67 | AF73: 0 | AG73: 3 | AH73: Rename only | AI73: Load rename only | AJ73: Clean rename (SKU token and objective match what the campaign advertises); 69.5% ACoS on 3 orders / 30 clicks (CC 31 Aug–29 Sep). | AK73: seq 2112 retag LOAD; seq 2960 rename LOAD | AL73: MAINTAIN · score 36
A74: 243989248483473 | B74: D-S4-SP-queen size satin sheets set-(Satin)-MSV-Exact-Rank-DO-SS-SATIN-RED-QUEEN-4PCS | C74: queen size satin sheets set [exact, $1.54, 32 clicks] | D74: queen size satin sheets set (buys the search term: queen satin sheet set) | E74: ENABLED | F74: Ranking | G74: Ranking | H74: Satin|Queen | I74: Exact | J74: SATIN-QUEEN-BLACK | K74: SATIN-QUEEN-BLACK | L74: $1.54 | M74: $1.54 | N74: 25 | O74: 25 | P74: 1.93 | Q74: 1.93 | R74: 1 | S74: 0 | T74: 0 | U74: 0 | V74: 3.91 | W74: 3.91 | X74: PAUSED | Y74: none | Z74: defer — engine name wrong (SKU token SATIN-QUEEN-BLACK); load a corrected name after 28 Oct | AA74: 57.13 | AB74: 32 | AC74: 4 | AD74: 51.6 | AE74: 71.88 | AF74: 6.25 | AG74: 15 | AH74: Pause | AI74: Pause target "queen size satin sheets set" (its only target — campaign goes dark) | AJ74: 51.6% ACoS on 4 orders / 32 clicks (CC 31 Aug–29 Sep). Engine target pause agreed with review 40: "queen size satin sheets set" is bought EXACT by 2 enabled campaigns — one exact owner per term (the ownership axiom); | AK74: seq 168 pp: agree with review 40; seq 1835 child: reject — keep SATIN-QUEEN-BLACK; seq 2769 state: agree with review 40; seq 2938 rename CHANGE | AL74: MAINTAIN · score 36 · target "queen satin sheet set" TOS $1.93 → $1.44
A75: 171902714860303 | B75: D-S4-king sheets silk - [Silk|King] - Exact - Ran - DO - SATIN-4PC-KING-GREY | C75: king sheets silk [exact] | D75: king sheets silk | E75: ENABLED | F75: Ranking | G75: Ranking | H75: Silk|King | I75: Exact | J75: SATIN-4PC-KING-GREY | K75: SATIN-4PC-KING-GREY | L75: $1.64 | M75: $1.34 | N75: 70 | O75: 70 | P75: 2.79 | Q75: 2.28 | V75: 15.97 | W75: 15.97 | X75: ENABLED | Y75: none | Z75: load (clean): DSS4-SP-King Sheets Silk-[Silk|King]-(LSV)-Exact-(Ranking)-DO-SATIN-4PC-KING-GREY | AA75: 55.68 | AB75: 22 | AC75: 6 | AD75: 28 | AE75: 86.36 | AF75: 0 | AG75: 13 | AH75: Release hold + price to break-even | AI75: Release hold; cut base $1.64 → $1.34 | AJ75: 28.0% ACoS, 6 orders on 22 clicks (CC 31 Aug–29 Sep) vs King Grey break-even 15.3%; BE base = $4.93 contribution (King Grey) × 27.3% CVR = $1.34; cap 25% cut. | AK75: seq 2100 retag LOAD; seq 2941 rename LOAD; seq 1985 NOT SERVING hold(s) → release; price to break-even (our addition, reviewer D)
A76: 276865047785028 | B76: D-S4-silk bed sheets full size - [Silk|Full] - Exact - Ran - DO - SATIN-FULL-BLACK | C76: silk bed sheets full size [exact] | D76: silk bed sheets full size (buys the search term: silk bed sheets full) | E76: PAUSED | F76: Ranking | G76: Ranking | H76: Silk|Full | I76: Exact | J76: SATIN-FULL-BLACK | K76: SATIN-FULL-BLACK | L76: n/a (no target bid in audit) | M76: n/a | N76: 50 | O76: 50 | V76: 13.47 | W76: 13.47 | X76: PAUSED | Y76: none | Z76: none | AA76: 55.55 | AB76: 30 | AC76: 4 | AD76: 48 | AE76: 96.67 | AF76: 0 | AG76: 36 | AH76: No change | AI76: Keep paused | AJ76: No run decision and no issue found; 48.0% ACoS on 4 orders / 30 clicks (CC 31 Aug–29 Sep). | AK76: no run decision | AL76: Paused owner; the push runs on 50992822442833
A77: 170402329751715 | B77: D-S4-satin bed sheets queen - [Satin|Queen] - Broad - Disc - DO - SATIN-QUEEN-GREY | C77: satin bed sheets queen [broad] | D77: — | E77: ENABLED | F77: Discovery | G77: Discovery | H77: Satin|Queen | I77: Broad | J77: SATIN-QUEEN-GREY | K77: SATIN-QUEEN-GREY | L77: n/a (no target bid in audit) | M77: n/a | N77: 0 | O77: 0 | V77: 10 | W77: 10 | X77: ENABLED | Y77: add 3 negatives (seq 2263) · add negative exact: satin bed sheets queen; satin sheets; silk sheets; silk bed sheets; satin sheets queen size; queen silk sheets set; queen satin sheet set; king size satin sheets; silk sheets queen | Z77: none | AA77: 51.27 | AB77: 65 | AC77: 15 | AD77: 11.6 | AE77: 1.54 | AF77: 26.15 | AG77: 19 | AH77: No change | AI77: Keep enabled (fold held) | AJ77: 11.6% ACoS on 15 orders / 65 clicks (CC 31 Aug–29 Sep). The survivors are smaller (e.g. 2849: 215 orders folded into a 14-order survivor, 90d). 2857 repeats review 28's 2868. | AK77: seq 2263 negatives: agree with review 40; seq 2850 structure: hold (agree)
A78: 253348963885567 | B78: D-S4-twin sheets silk - [Silk|Twin] - Exact - Ran - DO - SATIN-TWIN-BLACK-NEW | C78: twin sheets silk [exact, $1.66, 17 clicks] | D78: twin sheets silk | E78: ENABLED | F78: Ranking | G78: Ranking | H78: OUT | I78: Exact | J78: SATIN-TWIN-BLACK-NEW | K78: SATIN-TWIN-BLACK-NEW | L78: $1.66 | M78: $1.25 | N78: 150 | O78: 166 | P78: 4.15 | Q78: 3.33 | R78: 0 | S78: 0 | T78: 0 | U78: 0 | V78: 13.42 | W78: 9.39 | X78: ENABLED | Y78: none | Z78: defer — engine name wrong (SKU token SATIN-TWIN-BLACK-NEW); load a corrected name after 28 Oct | AA78: 51.23 | AB78: 17 | AC78: 2 | AD78: 88.5 | AE78: 58.82 | AF78: 35.29 | AG78: 8 | AH78: Mix fix + price cut | AI78: Mix fix in one write: base $1.66 → $1.25, boost → 166% (top of search $4.15 → $3.33); 88.5% ACoS vs Twin Black 31.1%; product pages 35%; keeps the engine's −20% at the top | AJ78: 88.5% ACoS on 2 orders / 17 clicks (CC 31 Aug–29 Sep) vs Twin Black break-even 31.4%; audit row loads as written (review 40 agrees). Note: plan move to SATIN-TWIN-GREY before 16 Oct (Twin Black 66 units, ~34 days). | AK78: seq 171 budget: agree with review 40; seq 172 tos: pass (flag); seq 175 bid: pass (flag); seq 1826 child: reject — keep SATIN-TWIN-BLACK-NEW; seq 2920 rename CHANGE
A79: 4681005199760 | B79: D-S4-SP-EXACT-twin size satin sheets-Satin|Twin-SATIN-TWIN-BLACK-NEW | C79: twin size satin sheets [exact] | D79: twin size satin sheets | E79: ENABLED | F79: Ranking | G79: Ranking | I79: Exact | J79: SATIN-TWIN-BLACK-NEW | K79: SATIN-TWIN-BLACK-NEW | L79: $2.50 | M79: $1.88 | N79: 0 | O79: 20 | P79: 2.5 | Q79: 2.25 | U79: 0 | V79: 10.83 | W79: 10.83 | X79: ENABLED | Y79: none | Z79: defer — engine name wrong (SKU token SATIN-TWIN-BLACK-NEW); load a corrected name after 28 Oct | AA79: 50.96 | AB79: 21 | AC79: 2 | AD79: 102.1 | AE79: 14.29 | AF79: 47.62 | AG79: 3 | AH79: Mix fix + price cut | AI79: Mix fix in one write: base $2.50 → $1.88, boost → 20% (top of search $2.50 → $2.25); rest of search → 0% (33% of clicks); 102.1% ACoS vs Twin Black 31.1%; product pages 48% | AJ79: No run decision and no issue found; 102.1% ACoS on 2 orders / 21 clicks (CC 31 Aug–29 Sep). Note: above break-even with no pricing row in the run; price at the next cycle unless it is chosen for the ranking push; plan move to SATIN-TWIN-GREY before 16 Oct (Twin Black 66 units, ~34 days). | AK79: seq 1844 child: reject — keep SATIN-TWIN-BLACK-NEW; seq 2113 retag LOAD; seq 2961 rename CHANGE
A80: 237149166614031 | B80: SSS4-PHRASE-(satin sheets)-Browse Kws Migr. | C80: satin sheets [phrase, $1.07] | D80: satin sheets | E80: ENABLED | F80: Discovery | G80: Discovery | I80: Phrase | J80: SATIN-QUEEN-BLACK | K80: SATIN-QUEEN-BLACK | L80: $1.07 | M80: $0.80 | N80: 0 | O80: 0 | P80: 1.07 | Q80: 0.8 | V80: 5 | W80: 5 | X80: ENABLED | Y80: add 5 negatives (seq 2271) · add negative exact: satin sheets queen size; satin sheets | Z80: load (clean): DSS4-SP-Satin Sheets-[Satin]-(HSV)-Phrase-(Discovery)-DO-SATIN-QUEEN-BLACK | AA80: 48.42 | AB80: 54 | AC80: 3 | AD80: 53.9 | AE80: 18.52 | AF80: 5.56 | AG80: 30 | AH80: Release hold + price to break-even | AI80: Release hold; cut base $1.07 → $0.80 | AJ80: 53.9% ACoS, 3 orders on 54 clicks (CC 31 Aug–29 Sep) vs Queen Black break-even 17.8%; BE base = $5.03 contribution (Queen Black) × 5.6% CVR = $0.28; cap 25% cut. | AK80: seq 2193 retag LOAD; seq 2271 negatives: agree with review 40; seq 3179 rename LOAD; seq 1777 NOT SERVING hold(s) → release; price to break-even (our addition, reviewer D)
A81: 484073051253364 | B81: D-S4-SP-decolure satin sheets-Brand-Agr-Broad-Def-DO-SATIN-QUEEN-BLACK | C81: decolure satin; decolure satin sheets [broad] | D81: whole campaign | E81: ENABLED | F81: Defensive | G81: Defensive | I81: Broad | J81: SATIN-QUEEN-BLACK | K81: SATIN-QUEEN-BLACK | L81: n/a (no target bid in audit) | M81: n/a | N81: 100 | O81: 100 | V81: 10 | W81: 10 | X81: ENABLED | Y81: add negative exact: satin sheets full | Z81: load (clean): DSS4-SP-Decolure Satin-(VLSV)-Broad-(Defensive)-DO-SATIN-QUEEN-BLACK | AA81: 47.58 | AB81: 61 | AC81: 14 | AD81: 11.2 | AE81: 86.89 | AF81: 11.48 | AG81: 126 | AH81: Rename only | AI81: Load rename only | AJ81: Clean rename (SKU token and objective match what the campaign advertises); 11.2% ACoS on 14 orders / 61 clicks (CC 31 Aug–29 Sep). | AK81: seq 2921 rename LOAD
A82: 125893435398877 | B82: D-S4-SP-PHRASE-silk satin sheets-Silk-SATIN-QUEEN-GREY | C82: silk satin sheets [phrase, $0.91]; silk satin sheets [phrase, $0.91] | D82: whole campaign | E82: ENABLED | F82: Discovery | G82: Discovery | I82: Phrase | J82: SATIN-QUEEN-GREY | K82: SATIN-QUEEN-GREY | L82: $0.91 | M82: $0.91 | N82: 0 | O82: 0 | P82: 0.91 | Q82: 0.91 | V82: 5 | W82: 5 | X82: PAUSED | Y82: none | Z82: none | AA82: 47.5 | AB82: 60 | AC82: 4 | AD82: 37.9 | AE82: 3.33 | AF82: 8.33 | AG82: 5 | AH82: Pause | AI82: Pause (seq 2852) | AJ82: 37.9% ACoS on 4 orders / 60 clicks (CC 31 Aug–29 Sep). Second discovery campaign in its family (fold = pause; only negatives move). | AK82: seq 2852 structure: agree with review 40; seq 1739 NOT SERVING hold(s) moot — campaign paused
A83: 218060067204712 | B83: D-S4-SP-EXACT-olive green silk sheets-Silk-SATIN-4PC-QUEEN-DARK GREEN | C83: olive green silk sheets [exact, $2.30]; olive green silk sheets [exact, $2.30] | D83: olive green silk sheets | E83: ENABLED | F83: Conversions | G83: Conversions | I83: Exact | J83: SATIN-4PC-QUEEN-DARK GREEN | K83: SATIN-4PC-KING-DARK GREEN | L83: $2.30 | M83: $1.72 | N83: 0 | O83: 0 | P83: 2.3 | Q83: 1.72 | V83: 9.27 | W83: 9.27 | X83: ENABLED | Y83: none | Z83: load (clean): DSS4-SP-Olive Green Silk Sheets-(VLSV)-Exact-(Conversion)-DO-SATIN-4PC-QUEEN-DARK GREEN | AA83: 47.19 | AB83: 22 | AC83: 3 | AD83: 54 | AE83: 13.64 | AF83: 81.82 | AG83: 4 | AH83: Release hold + price to break-even | AI83: Release hold; cut base $2.30 → $1.72; Swap child to SATIN-4PC-KING-DARK GREEN | AJ83: 54.0% ACoS, 3 orders on 22 clicks (CC 31 Aug–29 Sep) vs blended (other colour) break-even 23.3%; BE base = $7.02 contribution (blended (other colour)) × 13.6% CVR = $0.96; cap 25% cut. | AK83: seq 2090 retag LOAD; seq 2919 rename LOAD; seq 1737 NOT SERVING hold(s) → release; price to break-even (our addition, reviewer D); our addition (corrections §5 / reviewer C A4)
A84: 181043135198607 | B84: D-S4-SP-EXACT-silk satin sheets-Silk-SATIN-QUEEN-BLACK | C84: silk satin sheets [exact] | D84: whole campaign | E84: ENABLED | F84: Ranking | G84: Ranking | I84: Exact | J84: SATIN-QUEEN-BLACK | K84: SATIN-QUEEN-BLACK | L84: n/a (no target bid in audit) | M84: n/a | N84: 50 | O84: 50 | V84: 8.04 | W84: 8.04 | X84: ENABLED | Y84: none | Z84: load (clean): DSS4-SP-Silk Satin Sheets-[Satin]-(LSV)-Exact-(Ranking)-DO-SATIN-QUEEN-BLACK | AA84: 46.59 | AB84: 31 | AC84: 8 | AD84: 19.4 | AE84: 83.87 | AF84: 6.45 | AG84: 11 | AH84: Rename only | AI84: Load rename only | AJ84: Clean rename (SKU token and objective match what the campaign advertises); 19.4% ACoS on 8 orders / 31 clicks (CC 31 Aug–29 Sep). | AK84: seq 2105 retag LOAD; seq 2950 rename LOAD
A85: 179785157492956 | B85: D-S4-SP-king size bed sheets silk-(Silk)-LSV-Exact-Rank-DO-FH-CXP0-5741 | C85: king size bed sheets silk [exact, $1.38, 18 clicks] | D85: king size bed sheets silk | E85: ENABLED | F85: Ranking | G85: Ranking | H85: OUT | I85: Exact | J85: SATIN-4PC-KING-GREY | K85: SATIN-4PC-KING-GREY | L85: $1.38 | M85: $1.03 | N85: 100 | O85: 100 | P85: 2.76 | Q85: 2.06 | R85: 0 | S85: 0 | T85: 10 | U85: 0 | V85: 191.91 | W85: 95.96 | X85: ENABLED | Y85: none | Z85: load (clean): DSS4-SP-King Size Bed Sheets Silk-[Silk|King]-(VLSV)-Exact-(Ranking)-DO-SATIN-4PC-KING-GREY | AA85: 46.09 | AB85: 18 | AC85: 3 | AD85: 49.4 | AE85: 100 | AF85: 0 | AG85: 9 | AH85: Price cut | AI85: Cut base 25% ($1.38 → $1.03); ROS 10% → 0%; Budget $191.91 → $95.96 | AJ85: 49.4% ACoS on 3 orders / 18 clicks (CC 31 Aug–29 Sep) vs King Grey break-even 15.3%; audit row loads as written (review 40 agrees). | AK85: seq 176 budget: agree with review 40; seq 179 ros: agree with review 40; seq 180 bid: agree with review 40; seq 2936 rename LOAD
A86: 239111461875974 | B86: D-S4-SP-EXACT-decolure satin bed sheets-Brand-SATIN-QUEEN-BLACK | C86: decolure satin bed sheets [exact] | D86: whole campaign | E86: ENABLED | F86: Defensive | G86: Defensive | I86: Exact | J86: SATIN-QUEEN-BLACK | K86: SATIN-QUEEN-BLACK | L86: n/a (no target bid in audit) | M86: n/a | N86: 50 | O86: 50 | V86: 8.06 | W86: 8.06 | X86: ENABLED | Y86: none | Z86: load (clean): DSS4-SP-Decolure Satin Bed Sheets-(VLSV)-Exact-(Defensive)-DO-SATIN-QUEEN-BLACK | AA86: 46.06 | AB86: 33 | AC86: 9 | AD86: 15.4 | AE86: 21.21 | AF86: 72.73 | AG86: 12 | AH86: Rename only | AI86: Load rename only | AJ86: Clean rename (SKU token and objective match what the campaign advertises); 15.4% ACoS on 9 orders / 33 clicks (CC 31 Aug–29 Sep). | AK86: seq 2117 retag LOAD; seq 2967 rename LOAD
A87: 14719207426710 | B87: D-S4-SP-silk sheet set full-(Silk)-LSV-Exact-Rank-DO-SATIN-FULL-BLACK | C87: silk sheets full size [exact, $1.40, 15 clicks]; silk sheet set full [exact, $1.55, 7 clicks]; silk sheets full bed [exact, paused, $2.35]; silk sheets full size bed set [exact, paused, $2.16]; silk sheets and pillow cases full [exact, paused, $2.21] | D87: silk sheets full size; silk sheet set full | E87: ENABLED | F87: Ranking | G87: Ranking | H87: OUT | I87: Exact | J87: SATIN-FULL-BLACK | K87: SATIN-FULL-BLACK | L87: $1.40 / $1.55 | M87: $1.40 / $1.55 | N87: 50 | O87: 50 | P87: 2.1 | Q87: 2.1 | R87: 0 | S87: 0 | T87: 10 | U87: 0 | V87: 5 | W87: 5 | X87: ENABLED | Y87: add negative exact: silk sheets full size; silk sheets full | Z87: defer — engine name wrong (SKU token SATIN-FULL-BLACK); load a corrected name after 28 Oct | AA87: 45.4 | AB87: 22 | AC87: 4 | AD87: 38.5 | AE87: 95.45 | AF87: 4.55 | AG87: 18 | AH87: Pause target | AI87: Pause target "silk sheets full size" (campaign stays on with 1 other target(s)); Keep target "silk sheet set full" enabled (reject pause seq 2770); ROS 10% → 0% | AJ87: 38.5% ACoS on 4 orders / 22 clicks (CC 31 Aug–29 Sep). Circular with #1443, whose campaign #2770 names as the survivor. Keep this target; pass #1443. | AK87: seq 184 ros: agree with review 40; seq 1824 child: reject — keep SATIN-FULL-BLACK; seq 2770 state: hold; seq 2771 state: agree with review 40; seq 2917 rename CHANGE
A88: 101321352254672 | B88: D-S4-silk queen sheets - [Silk|Queen] - Exact - Ran - DO - SATIN-QUEEN-BLACK | C88: silk queen sheets [exact] | D88: silk queen sheets | E88: ENABLED | F88: Ranking | G88: Ranking | H88: Silk|Queen | I88: Exact | J88: SATIN-QUEEN-BLACK | K88: SATIN-QUEEN-BLACK | L88: $1.39 | M88: $1.35 | N88: 30 | O88: 30 | P88: 1.81 | Q88: 1.76 | V88: 10.32 | W88: 10.32 | X88: ENABLED | Y88: none | Z88: defer — engine name wrong (SKU token SATIN-QUEEN-BLACK); load a corrected name after 28 Oct | AA88: 44.77 | AB88: 26 | AC88: 7 | AD88: 24.6 | AE88: 88.46 | AF88: 0 | AG88: 23 | AH88: Release hold + price to break-even | AI88: Release hold; cut base $1.39 → $1.35 | AJ88: 24.6% ACoS, 7 orders on 26 clicks (CC 31 Aug–29 Sep) vs Queen Black break-even 17.8%; BE base = $5.03 contribution (Queen Black) × 26.9% CVR = $1.35; cap 25% cut. | AK88: seq 1856 child: reject — keep SATIN-QUEEN-BLACK; seq 2126 retag LOAD; seq 2988 rename CHANGE; seq 1995 NOT SERVING hold(s) → release; price to break-even (our addition, reviewer D)
A89: 244395883069947 | B89: D-S4-SP-PHRASE-silk sheets king size-Silk|King-SATIN-4PC-KING-GREY | C89: silk sheets king size [phrase] | D89: whole campaign | E89: ENABLED | F89: Discovery | G89: Discovery | I89: Phrase | J89: SATIN-4PC-KING-GREY | K89: SATIN-4PC-KING-GREY | L89: n/a (no target bid in audit) | M89: n/a | N89: 0 | O89: 0 | V89: 5 | W89: 5 | X89: ENABLED | Y89: none | Z89: load (clean): DSS4-SP-Silk Sheets King Size-[Silk|King]-(LSV)-Phrase-(Discovery)-DO-SATIN-4PC-KING-GREY | AA89: 43.12 | AB89: 30 | AC89: 7 | AD89: 18.8 | AE89: 26.67 | AF89: 0 | AG89: 8 | AH89: Rename only | AI89: Load rename only | AJ89: Clean rename (SKU token and objective match what the campaign advertises); 18.8% ACoS on 7 orders / 30 clicks (CC 31 Aug–29 Sep). | AK89: seq 2110 retag LOAD; seq 2956 rename LOAD
A90: 129065458297522 | B90: D-S4-white satin sheets - [Satin] - Exact - Ran - DO - SATIN-WHITE-QUEEN | C90: white satin sheets [exact, $0.98, 24 clicks] | D90: whole campaign | E90: ENABLED | F90: Ranking | G90: Conversions | H90: Satin | I90: Exact | J90: SATIN-WHITE-QUEEN | K90: SATIN-WHITE-QUEEN | L90: $0.98 | M90: $0.98 | N90: 110 | O90: 110 | P90: 2.06 | Q90: 2.06 | R90: 0 | S90: 0 | T90: 0 | U90: 0 | V90: 6.39 | W90: 6.39 | X90: ENABLED | Y90: none | Z90: defer — engine name wrong ((Conversion)); load a corrected name after 28 Oct | AA90: 38.78 | AB90: 24 | AC90: 9 | AD90: 13.9 | AE90: 65.22 | AF90: 34.78 | AG90: 16 | AH90: Retag only | AI90: retag → Conversions | AJ90: Objective Ranking → Conversions by the standard (colour term "white satin sheets"); 13.9% ACoS on 9 orders / 24 clicks (CC 31 Aug–29 Sep). | AK90: seq 2953 rename CHANGE; our addition: standard → Conversions (colour term "white satin sheets")
A91: 389488083794809 | B91: D-S4-SP-pink satin sheet-(Satin)-VLSV-Exact-Rank-DO-SATIN-QUEEN-PINK | C91: pink satin sheet [exact, $0.65, 57 clicks] | D91: pink satin sheet | E91: ENABLED | F91: Ranking | G91: Conversions | H91: Satin | I91: Exact | J91: SATIN-QUEEN-PINK | K91: SATIN-QUEEN-PINK | L91: $0.65 | M91: $0.50 | N91: 60 | O91: 108 | P91: 1.04 | Q91: 1.04 | R91: 0 | S91: 0 | T91: 0 | U91: 0 | V91: 10 | W91: 5 | X91: ENABLED | Y91: none | Z91: defer — engine name wrong ((Conversion)); load a corrected name after 28 Oct | AA91: 38.66 | AB91: 57 | AC91: 2 | AD91: 58.7 | AE91: 10.71 | AF91: 76.79 | AG91: 7 | AH91: Price cut | AI91: Cut base 23% ($0.65 → $0.50); TOS 60% → 108%; Budget $10 → $5; retag → Conversions | AJ91: 58.7% ACoS on 2 orders / 57 clicks (CC 31 Aug–29 Sep). A HARD cut on a TOS price already under its ceiling: TOS $1.04 vs $1.87 ceiling (0.42× after the cut to $0.78). The loss is on product pages: 43 PP vs 6 TOS clicks (audit read); 76.8% PP (CC 30d). | AK91: seq 195 budget: agree with review 40; seq 196 tos: correct to 108%; seq 199 bid: correct to 0.50; seq 2844 structure: agree with review 40; seq 2976 rename CHANGE; our addition: standard → Conversions (colour term "pink satin sheet")
A92: 165862484156935 | B92: D-S4-silk sheets queen size bed set - [Silk|Queen] - Exact - Ran - DO - SATIN-QUEEN-BLACK | C92: silk sheets queen size bed set [exact, $0.87, 13 clicks] | D92: silk sheets queen size bed set | E92: ENABLED | F92: Ranking | G92: Ranking | H92: OUT | I92: Exact | J92: SATIN-QUEEN-BLACK | K92: SATIN-QUEEN-BLACK | L92: $0.87 | M92: $0.61 | N92: 300 | O92: 300 | P92: 3.48 | Q92: 2.44 | R92: 0 | S92: 0 | T92: 0 | U92: 0 | V92: 20.2 | W92: 10.1 | X92: ENABLED | Y92: none | Z92: defer — engine name wrong (SKU token SATIN-QUEEN-BLACK); load a corrected name after 28 Oct | AA92: 37.75 | AB92: 13 | AC92: 0 | AE92: 100 | AF92: 0 | AG92: 4 | AH92: Price cut | AI92: Cut base 30% ($0.87 → $0.61); Budget $20.2 → $10.1 | AJ92: no sales ACoS on 0 orders / 13 clicks (CC 31 Aug–29 Sep) vs Queen Black break-even 17.8%; audit row loads as written (review 40 agrees). | AK92: seq 200 budget: agree with review 40; seq 204 bid: agree with review 40; seq 1829 child: reject — keep SATIN-QUEEN-BLACK; seq 2927 rename CHANGE
A93: 258041816107512 | B93: D-S4-SP-satin sheets queen size deep pocket-(Satin)-LSV-Exact-Rank-DO-SATIN-QUEEN-BLACK | C93: satin sheets queen size deep pocket [exact, $1.20, 18 clicks]; satin sheets deep pockets queen [exact, paused, $2.06]; satin sheets queen hotel luxury silky bed sheets [exact, paused, $1.65]; satin silk sheets queen set [exact, $1.46] | D93: satin sheets queen size deep pocket; satin silk sheets queen set | E93: ENABLED | F93: Ranking | G93: Ranking | H93: Satin|Queen | I93: Exact | J93: SATIN-QUEEN-BLACK | K93: SATIN-QUEEN-BLACK | L93: $1.20 / $1.46 | M93: $0.90 / $1.10 | N93: 85 | O93: 85 | P93: 2.22 | Q93: 1.67 | R93: 0 | S93: 0 | T93: 5 | U93: 5 | V93: 10 | W93: 5 | X93: ENABLED | Y93: none | Z93: defer — engine name wrong (SKU token SATIN-QUEEN-BLACK); load a corrected name after 28 Oct | AA93: 37.45 | AB93: 18 | AC93: 2 | AD93: 62.5 | AE93: 100 | AF93: 0 | AG93: 19 | AH93: Price cut | AI93: Cut base 25% ($1.20 / $1.46 → $0.90 / $1.10); Budget $10 → $5 | AJ93: 62.5% ACoS on 2 orders / 18 clicks (CC 31 Aug–29 Sep) vs Queen Black break-even 17.8%; audit row loads as written (review 40 agrees). | AK93: seq 205 budget: agree with review 40; seq 209 bid: agree with review 40; seq 212 bid: agree with review 40; seq 1836 child: reject — keep SATIN-QUEEN-BLACK; seq 2939 rename CHANGE
A94: 253974915161779 | B94: D-S4-white satin sheets queen - [Satin|Queen] - Exact - Ran - DO - SATIN-WHITE-QUEEN | C94: white satin sheets queen [exact] | D94: whole campaign | E94: ENABLED | F94: Ranking | G94: Conversions | H94: Satin|Queen | I94: Exact | J94: SATIN-WHITE-QUEEN | K94: SATIN-WHITE-QUEEN | L94: n/a (no target bid in audit) | M94: n/a | N94: 20 | O94: 20 | V94: 13.33 | W94: 13.33 | X94: ENABLED | Y94: none | Z94: defer — engine name wrong ((Conversion)); load a corrected name after 28 Oct | AA94: 36.81 | AB94: 23 | AC94: 6 | AD94: 21.8 | AE94: 21.74 | AF94: 56.52 | AG94: 32 | AH94: Retag only | AI94: retag → Conversions | AJ94: Objective Ranking → Conversions by the standard (our retag verdict); 21.8% ACoS on 6 orders / 23 clicks (CC 31 Aug–29 Sep). | AK94: seq 2098 retag correct to Conversions; seq 2935 rename CHANGE
A95: 272586279246311 | B95: D-S4-SP-EXACT-gray satin sheets-Satin-SATIN-QUEEN-GREY | C95: gray satin sheets [exact] | D95: — | E95: ENABLED | F95: Conversions | G95: Conversions | I95: Exact | J95: SATIN-QUEEN-GREY | K95: SATIN-QUEEN-GREY | L95: n/a (no target bid in audit) | M95: n/a | N95: 0 | O95: 0 | V95: 8.45 | W95: 8.45 | X95: ENABLED | Y95: none | Z95: load (clean): DSS4-SP-Gray Satin Sheets-(VLSV)-Exact-(Conversion)-DO-SATIN-QUEEN-GREY | AA95: 36.64 | AB95: 19 | AC95: 4 | AD95: 31.1 | AE95: 5.26 | AF95: 89.47 | AG95: 7 | AH95: No change (flag: above break-even) | AI95: No change in this run — flag: 31.1% ACoS vs Queen Grey break-even 11.2% (no run row prices it) | AJ95: Clean rename (SKU token and objective match what the campaign advertises); 31.1% ACoS on 4 orders / 19 clicks (CC 31 Aug–29 Sep). Note: above break-even with no pricing row in the run; price at the next cycle unless it is chosen for the ranking push. | AK95: seq 2103 retag LOAD; seq 2947 rename LOAD
A96: 228452491938143 | B96: D-S4-SP-EXACT-decolure sheet-Brand-SATIN-QUEEN-BLACK | C96: decolure sheet [exact] | D96: whole campaign | E96: ENABLED | F96: Defensive | G96: Defensive | I96: Exact | J96: SATIN-QUEEN-BLACK | K96: SATIN-QUEEN-BLACK | L96: n/a (no target bid in audit) | M96: n/a | N96: 0 | O96: 0 | V96: 8.06 | W96: 8.06 | X96: ENABLED | Y96: none | Z96: load (clean): DSS4-SP-Decolure Sheet-(VLSV)-Exact-(Defensive)-DO-SATIN-QUEEN-BLACK | AA96: 34.6 | AB96: 23 | AC96: 10 | AD96: 8.4 | AE96: 30.43 | AF96: 69.57 | AG96: 10 | AH96: Rename only | AI96: Load rename only | AJ96: Clean rename (SKU token and objective match what the campaign advertises); 8.4% ACoS on 10 orders / 23 clicks (CC 31 Aug–29 Sep). | AK96: seq 2125 retag LOAD; seq 2987 rename LOAD
A97: 267925169057994 | B97: D-S4-queen sheet set silk - [Silk|Queen] - Exact - Ran - DO - SATIN-QUEEN-BLACK | C97: queen sheet set silk [exact, $0.75, 15 clicks] | D97: whole campaign | E97: PAUSED | F97: Ranking | G97: Ranking | H97: OUT | I97: Exact | J97: SATIN-QUEEN-BLACK | K97: SATIN-QUEEN-BLACK | L97: $0.75 | M97: $0.52 | N97: 225 | O97: 0 | P97: 2.44 | Q97: 0.52 | R97: 0 | S97: 0 | T97: 0 | U97: 0 | V97: 23.39 | W97: 5 | X97: ENABLED | Y97: none | Z97: load (clean): DSS4-SP-Queen Sheet Set Silk-[Silk|Queen]-(LSV)-Exact-(Ranking)-DO-SATIN-QUEEN-BLACK | AA97: 33.89 | AB97: 15 | AC97: 1 | AD97: 117.8 | AE97: 100 | AF97: 0 | AG97: 29 | AH97: Revive (harvest) | AI97: Revive at harvest price; Cut base 31% ($0.75 → $0.52); TOS 225% → 0%; Budget $23.39 → $5 | AJ97: 117.8% ACoS on 1 orders / 15 clicks (CC 31 Aug–29 Sep). Harvest revive (seq 2323) agreed with review 40; priced for profit with a $5 budget and TOS boost removed. Note: revive seq 2838 dropped as a duplicate; the harvest revive and its price win. | AK97: seq 2311 retag correct to Ranking; seq 2318 bid: agree with review 40; seq 2319 tos: agree with review 40; seq 2320 pp: agree with review 40; seq 2321 ros: agree with review 40; seq 2322 budget: agree with review 40; seq 2323 state: agree with review 40; seq 2838 structure: hold (duplicate of harvest 2323); seq 2990 rename LOAD
A98: 211241691618706 | B98: D-S4-gold satin sheets - [Satin] - Exact - Ran - DO - SATIN-GOLD-KING | C98: gold satin sheets [exact] | D98: whole campaign | E98: ENABLED | F98: Ranking | G98: Conversions | H98: Satin | I98: Exact | J98: SATIN-GOLD-QUEEN | K98: SATIN-GOLD-QUEEN | L98: n/a (no target bid in audit) | M98: n/a | N98: 50 | O98: 50 | V98: 4.17 | W98: 4.17 | X98: ENABLED | Y98: none | Z98: defer — engine name wrong ((Conversion)); load a corrected name after 28 Oct | AA98: 33.68 | AB98: 53 | AC98: 2 | AD98: 52.7 | AE98: 15.09 | AF98: 75.47 | AG98: 9 | AH98: Retag only | AI98: retag → Conversions | AJ98: Objective Ranking → Conversions by the standard (our retag verdict); 52.7% ACoS on 2 orders / 53 clicks (CC 31 Aug–29 Sep). | AK98: seq 2107 retag correct to Conversions; seq 2952 rename CHANGE
A99: 54895613793659 | B99: D-S4-green satin sheets - [Satin] - Exact - Ran - DO - SATIN-4PC-QUEEN-DARK GREEN | C99: green satin sheets [exact, $1.15, 22 clicks] | D99: whole campaign | E99: ENABLED | F99: Ranking | G99: Conversions | H99: Satin | I99: Exact | J99: SATIN-4PC-QUEEN-DARK GREEN | K99: SATIN-4PC-KING-DARK GREEN | L99: $1.15 | M99: $1.04 | N99: 90 | O99: 58 | P99: 2.18 | Q99: 1.64 | R99: 0 | S99: 0 | T99: 0 | U99: 0 | V99: 7.5 | W99: 5 | X99: ENABLED | Y99: none | Z99: defer — engine name wrong (SKU token SATIN-4PC-QUEEN-DARK GREEN; (Conversion)); load a corrected name after 28 Oct | AA99: 33.37 | AB99: 22 | AC99: 2 | AD99: 55.7 | AE99: 50 | AF99: 45.45 | AG99: 7 | AH99: Child swap | AI99: Swap child to SATIN-4PC-KING-DARK GREEN; Cut base 10% ($1.15 → $1.04); TOS 90% → 58%; Budget $7.5 → $5; retag → Conversions | AJ99: 55.7% ACoS on 2 orders / 22 clicks (CC 31 Aug–29 Sep). Correct to SATIN-4PC-KING-DARK GREEN (and/or SATIN-4PC-FULL-DARK GREEN) — NOW (seq 1837). | AK99: seq 218 budget: agree with review 40; seq 219 tos: agree with review 40; seq 222 bid: agree with review 40; seq 1837 child: correct to SATIN-4PC-KING-DARK GREEN (and/or SATIN-4PC-FULL-…; seq 2940 rename CHANGE; our addition: standard → Conversions (colour term "green satin sheets")
A100: 245425710999426 | B100: D-S4-queen satin sheet set - [Satin|Queen] - Broad - Disc - DO - SATIN-QUEEN-GREY | C100: queen satin sheet set [broad] | D100: — | E100: ENABLED | F100: Discovery | G100: Discovery | H100: Satin|Queen | I100: Broad | J100: SATIN-QUEEN-GREY | K100: SATIN-QUEEN-GREY | L100: n/a (no target bid in audit) | M100: n/a | N100: 0 | O100: 0 | V100: 10 | W100: 10 | X100: ENABLED | Y100: add 2 negatives minus the "white satin sheet set queen" wall (seq 2265) · add negative exact: silk sheets queen; satin sheets; silk sheets; satin sheets queen size; queen satin sheet set; silk queen bed sheets set | Z100: none | AA100: 33.24 | AB100: 44 | AC100: 9 | AD100: 13.7 | AE100: 0 | AF100: 6.82 | AG100: 12 | AH100: No change | AI100: Keep enabled (fold held) | AJ100: 13.7% ACoS on 9 orders / 44 clicks (CC 31 Aug–29 Sep). The survivors are smaller (e.g. 2849: 215 orders folded into a 14-order survivor, 90d). 2857 repeats review 28's 2868. | AK100: seq 2265 negatives: correct: drop the "white satin sheet set queen" wall; seq 2851 structure: hold (agree)
...

Sheet Ranking push
A1: Term | B1: Score components: CVR (25) | C1: CTR (20) | D1: Rank (15) | E1: Competitors (15) | F1: Inventory (15) | G1: Economics (10) | H1: Score | I1: Tier | J1: Action | K1: Rank 29 Sep | L1: Target | M1: Advertised child | N1: Monthly search volume | O1: TOS clicks/day now | P1: TOS clicks/day planned | Q1: TOS CVR 30d % | R1: Our CVR (SQP) % | S1: Market CVR (SQP) % | T1: Our CTR (SQP) % | U1: Market CTR (SQP) % | V1: TOS share of term clicks % | W1: Product-page share % | X1: TOS price now $ | Y1: This write $ | Z1: Budget/day $ | AA1: Orders/day planned | AB1: Cost per order at this write $ | AC1: Profit per unit, full price $ | AD1: Profit per unit, deal price $ | AE1: Loss per order, full price $ | AF1: Loss per order, deal price $ | AG1: Loss/day, full price $ | AH1: Loss/day, deal days $ | AI1: Recommended now | AJ1: Missing condition | AK1: Owning campaign(s)
A2: satin sheets king | B2: 15.54 | C2: 20 | D2: 14 | E2: 15 | F2: 15 | G2: 3.46 | H2: =ROUND(SUM(B2:G2),0) -> 83 | I2: =IF(H2>=70,"High",IF(H2>=50,"Medium","Low")) -> High | J2: PUSH | K2: 4 | L2: 3 | M2: King Grey | N2: 4280 | O2: 5.2643 | P2: 5.2643 | Q2: 22.0247 | R2: 4.77 | S2: 4.95 | T2: 3.02 | U2: 1.93 | V2: 76.6649 | W2: 13.6375 | X2: 2.794 | Y2: 2.794 | Z2: 15.8978 | AA2: =P2*Q2/100 -> 1.1594463 | AB2: 12.6858 | AC2: 6.4 | AD2: 1.38 | AE2: =AB2-AC2 -> 6.2858 | AF2: =AB2-AD2 -> 11.3058 | AG2: =AA2*AE2 -> 7.2880474 | AH2: =AA2*AF2 -> 13.108468 | AI2: Yes | AJ2: CVR not above market like-for-like (SQP); economics: CPO 2.3x contribution | AK2: 33389871513217 D-S4-satin sheets king - [Satin|King] - Exact - Ran - DO - SATIN-4PC-KING-GREY
A3: satin sheets full | B3: 16.06 | C3: 20 | D3: 14 | E3: 13 | F3: 12 | G3: 6.49 | H3: =ROUND(SUM(B3:G3),0) -> 82 | I3: =IF(H3>=70,"High",IF(H3>=50,"Medium","Low")) -> High | J3: PUSH | K3: 4 | L3: 3 | M3: Full Black | N3: 4438 | O3: 3.9108 | P3: 8 | Q3: 23.425 | R3: 10.01 | S3: 6.96 | T3: 2.82 | U3: 2.06 | V3: 71.5395 | W3: 10.0886 | X3: 3.729 | Y3: 3.6861 | Z3: 30.1118 | AA3: =P3*Q3/100 -> 1.874 | AB3: 15.7356 | AC3: 8.55 | AD3: 4.08 | AE3: =AB3-AC3 -> 7.1856 | AF3: =AB3-AD3 -> 11.6556 | AG3: =AA3*AE3 -> 13.465814 | AH3: =AA3*AF3 -> 21.842594 | AI3: Yes | AJ3: — | AK3: 82540637405662 D-S4-satin sheets full size - [Satin|Full] - Exact - Ran - DO - SATIN-FULL-BLACK
A4: satin sheets king size | B4: 13.78 | C4: 20 | D4: 15 | E4: 15 | F4: 15 | G4: 1.38 | H4: =ROUND(SUM(B4:G4),0) -> 80 | I4: =IF(H4>=70,"High",IF(H4>=50,"Medium","Low")) -> High | J4: HOLD-AT-TARGET | K4: 2 | L4: 2 | M4: King Grey | N4: 695 | O4: 0.8122 | P4: 0.8122 | Q4: 17.6116 | R4: 6.88 | S4: 5.35 | T4: 2.87 | U4: 2 | V4: 73.8319 | W4: 10.2162 | X4: 2.512 | Y4: 2.512 | Z4: 2.2166 | AA4: =P4*Q4/100 -> 0.14304142 | AB4: 14.2634 | AC4: 6.4 | AD4: 1.38 | AE4: =AB4-AC4 -> 7.8634 | AF4: =AB4-AD4 -> 12.8834 | AG4: =AA4*AE4 -> 1.1247919 | AH4: =AA4*AF4 -> 1.8428598 | AI4: Yes | AJ4: economics: CPO 2.7x contribution | AK4: 189967409565927 D-S4-satin sheets king size - [Satin|King] - Exact - Ran - DO - SATIN-4PC-KING-GREY
A5: silk sheets full | B5: 20.04 | C5: 8.31 | D5: 13 | E5: 15 | F5: 15 | G5: 8.33 | H5: =ROUND(SUM(B5:G5),0) -> 80 | I5: =IF(H5>=70,"High",IF(H5>=50,"Medium","Low")) -> High | J5: PUSH | K5: 5 | L5: 3 | M5: Full Black | N5: 6739 | O5: 2.872 | P5: 3.2879 | Q5: 24.2078 | R5: 10.11 | S5: 6.04 | T5: 1.41 | U5: 1.97 | V5: 67.3113 | W5: 14.4755 | X5: 2.565 | Y5: 2.5951 | Z5: 9.5885 | AA5: =P5*Q5/100 -> 0.79592826 | AB5: 10.72 | AC5: 8.55 | AD5: 4.08 | AE5: =AB5-AC5 -> 2.17 | AF5: =AB5-AD5 -> 6.64 | AG5: =AA5*AE5 -> 1.7271643 | AH5: =AA5*AF5 -> 5.2849636 | AI5: Yes | AJ5: CTR not above market (SQP) | AK5: 137973631643313 D-S4-SP-EXACT-silk sheets full size-Silk|Full-SATIN-FULL-BLACK
A6: silk bed sheets full | B6: 6.37 | C6: 14 | D6: 14 | E6: 15 | F6: 15 | G6: 6.89 | H6: =ROUND(SUM(B6:G6),0) -> 71 | I6: =IF(H6>=70,"High",IF(H6>=50,"Medium","Low")) -> High | J6: PUSH | K6: 4 | L6: 3 | M6: Full Black | N6: 2200 | O6: 1.0301 | P6: 1.4286 | Q6: 15.0119 | R6: 5.87 | S6: 5.91 | T6: 1.87 | U6: 1.87 | V6: 73.5772 | W6: 7.0102 | X6: 1.9573 | Y6: 1.9573 | Z6: 2.8922 | AA6: =P6*Q6/100 -> 0.21446 | AB6: 13.0382 | AC6: 8.55 | AD6: 4.08 | AE6: =AB6-AC6 -> 4.4882 | AF6: =AB6-AD6 -> 8.9582 | AG6: =AA6*AE6 -> 0.96253939 | AH6: =AA6*AF6 -> 1.9211756 | AI6: Yes | AJ6: CVR not above market like-for-like (SQP) | AK6: 276865047785028 D-S4-silk bed sheets full size - [Silk|Full] - Exact - Ran - DO - SATIN-FULL-BLACK (PAUSED); 50992822442833 D-S4-SP-silk bed sheets full size-(Silk)-MSV-Exact-Rank-DO-SATIN-FULL-GREY
A7: king size silk sheets set | B7: 11.71 | C7: 20 | D7: 2 | E7: 15 | F7: 15 | G7: 0 | H7: =ROUND(SUM(B7:G7),0) -> 64 | I7: =IF(H7>=70,"High",IF(H7>=50,"Medium","Low")) -> Medium | J7: PUSH-SMALL | K7: 10 | L7: 3 | M7: King Grey | N7: 1961 | O7: 3.7092 | P7: 3.7092 | Q7: 19.8145 | R7: 8.06 | S7: 6.56 | T7: 3.6 | U7: 1.96 | V7: 87.619 | W7: 0.4121 | X7: 5.5 | Y7: 4.0619 | Z7: 15.1145 | AA7: =P7*Q7/100 -> 0.73495943 | AB7: 20.4997 | AC7: 6.4 | AD7: 1.38 | AE7: =AB7-AC7 -> 14.0997 | AF7: =AB7-AD7 -> 19.1197 | AG7: =AA7*AE7 -> 10.362708 | AH7: =AA7*AF7 -> 14.052204 | AI7: Yes | AJ7: economics: CPO 3.6x contribution | AK7: 265771609218691 D-S4-king silk sheet set - [Silk|King] - Exact - Ran - DO - SATIN-4PC-KING-GREY
A8: satin bed sheets queen | B8: 15.39 | C8: 9.53 | D8: 6 | E8: 9 | F8: 15 | G8: 5.57 | H8: =ROUND(SUM(B8:G8),0) -> 60 | I8: =IF(H8>=70,"High",IF(H8>=50,"Medium","Low")) -> Medium | J8: PUSH-SMALL | K8: 6 | L8: 3 | M8: Queen Black | N8: 2200 | O8: 0.6811 | P8: 0.6811 | Q8: 18.6169 | R8: 12.33 | S8: 6.05 | T8: 1.53 | U8: 1.97 | V8: 45.4075 | W8: 10.8385 | X8: 1.7666 | Y8: 1.7666 | Z8: 1.3468 | AA8: =P8*Q8/100 -> 0.12679971 | AB8: 9.4891 | AC8: 6.74 | AD8: 1.89 | AE8: =AB8-AC8 -> 2.7491 | AF8: =AB8-AD8 -> 7.5991 | AG8: =AA8*AE8 -> 0.34858507 | AH8: =AA8*AF8 -> 0.96356365 | AI8: Yes | AJ8: CTR not above market (SQP) | AK8: 47941523261030 D-S4-SP-EXACT-satin bedsheets queen size-Satin|Queen-SATIN-QUEEN-BLACK; 79231677791815 D-S4-satin bed sheets queen - [Satin|Queen] - Exact - Ran - DO - SATIN-QUEEN-BLACK
A9: silk sheets queen | B9: 10.45 | C9: 12.67 | D9: 4 | E9: 9 | F9: 15 | G9: 3.94 | H9: =ROUND(SUM(B9:G9),0) -> 55 | I9: =IF(H9>=70,"High",IF(H9>=50,"Medium","Low")) -> Medium | J9: PUSH-SMALL | K9: 10 | L9: 3 | M9: Queen Black | N9: 15189 | O9: 7.2246 | P9: 20.0408 | Q9: 20.9483 | R9: 6.01 | S9: 6.16 | T9: 1.82 | U9: 1.95 | V9: 75.518 | W9: 5.0047 | X9: 2.0276 | Y9: 2.3318 | Z9: 47.2166 | AA9: =P9*Q9/100 -> 4.1982069 | AB9: 11.1312 | AC9: 6.74 | AD9: 1.89 | AE9: =AB9-AC9 -> 4.3912 | AF9: =AB9-AD9 -> 9.2412 | AG9: =AA9*AE9 -> 18.435166 | AH9: =AA9*AF9 -> 38.79647 | AI9: Restore to about 10 TOS clicks/day on one exact; the push to 20 is your decision | AJ9: CTR not above market (SQP); CVR not above market like-for-like (SQP); economics: CPO 2.2x contribution | AK9: 40865602759529 D-S4-silk sheets queen size - [Silk|Queen] - Exact - Ran - DO - SATIN-QUEEN-BLACK; 100830568607053 D-S4-SP-silk sheets queen-(Silk)-HSV-Exact-Rank-DO-SATIN-QUEEN-BLACK
A10: satin sheets | B10: 14.28 | C10: 10.08 | D10: 10 | E10: 4 | F10: 12 | G10: 1.05 | H10: =ROUND(SUM(B10:G10),0) -> 51 | I10: =IF(H10>=70,"High",IF(H10>=50,"Medium","Low")) -> Medium | J10: PUSH-SMALL | K10: 5 | L10: 3 | M10: Queen Black | N10: 30210 | O10: 21.4229 | P10: 59.7829 | Q10: 16.5564 | R10: 4.08 | S10: 4.05 | T10: 1.95 | U10: 1.95 | V10: 79.3442 | W10: 10.2569 | X10: 2.3 | Y10: 2.324 | Z10: 142.1185 | AA10: =P10*Q10/100 -> 9.8978961 | AB10: 14.0367 | AC10: 6.74 | AD10: 1.89 | AE10: =AB10-AC10 -> 7.2967 | AF10: =AB10-AD10 -> 12.1467 | AG10: =AA10*AE10 -> 72.221978 | AH10: =AA10*AF10 -> 120.22677 | AI10: Your decision (full plan) | AJ10: economics: CPO 2.8x contribution; target rank held by strong rivals | AK10: 527361393975073 D-S4-SP-satin sheets-(Satin)-HSV-Exact-Rank-DO-SATIN-QUEEN-GREY
A11: silk sheets king | B11: 14.98 | C11: 2 | D11: 0 | E11: 15 | F11: 15 | G11: 3.51 | H11: =ROUND(SUM(B11:G11),0) -> 50 | I11: =IF(H11>=70,"High",IF(H11>=50,"Medium","Low")) -> Medium | J11: FIX-FIRST | K11: 40 | L11: 3 | M11: King Grey | N11: 6731 | O11: 0.421 | P11: 0.421 | Q11: 15.018 | R11: 5.73 | S11: 4.35 | T11: 1.12 | U11: 1.98 | V11: 15.401 | W11: 3.3186 | X11: 1.4796 | Y11: 1.1097 | Z11: 0.5342 | AA11: =P11*Q11/100 -> 0.06322578 | AB11: 7.3889 | AC11: 6.4 | AD11: 1.38 | AE11: =AB11-AC11 -> 0.9889 | AF11: =AB11-AD11 -> 6.0089 | AG11: =AA11*AE11 -> 0.062523974 | AH11: =AA11*AF11 -> 0.37991739 | AI11: Fix the mix first | AJ11: CTR not above market (SQP); economics: CPO 2.3x contribution | AK11: 167888639670385 D-S4-SP-EXACT-silk sheets king size-Silk|King-SATIN-4PC-KING-GREY
A12: satin queen sheets set | B12: 4.47 | C12: 12.93 | D12: 2 | E12: 11 | F12: 15 | G12: 4.32 | H12: =ROUND(SUM(B12:G12),0) -> 50 | I12: =IF(H12>=70,"High",IF(H12>=50,"Medium","Low")) -> Medium | J12: PUSH-SMALL | K12: 8 | L12: 3 | M12: Queen Black | N12: 1971 | O12: 1.2183 | P12: 1.7046 | Q12: 18.8842 | R12: 5.43 | S12: 6.99 | T12: 2.2 | U12: 1.98 | V12: 48.0906 | W12: 40.8684 | X12: 2.0293 | Y12: 2.0293 | Z12: 4.5095 | AA12: =P12*Q12/100 -> 0.32190007 | AB12: 10.7459 | AC12: 6.74 | AD12: 1.89 | AE12: =AB12-AC12 -> 4.0059 | AF12: =AB12-AD12 -> 8.8559 | AG12: =AA12*AE12 -> 1.2894995 | AH12: =AA12*AF12 -> 2.8507149 | AI12: Yes | AJ12: CVR not above market like-for-like (SQP); economics: CPO 2.1x contribution | AK12: 173446552008266 D-S4-satin queen sheets set - [Satin|Queen] - Exact - Ran - DO - SATIN-QUEEN-BLACK
A13: satin sheets queen | B13: 4.96 | C13: 16.89 | D13: 6 | E13: 6 | F13: 15 | G13: 0 | H13: =ROUND(SUM(B13:G13),0) -> 49 | I13: =IF(H13>=70,"High",IF(H13>=50,"Medium","Low")) -> Low | J13: MAINTAIN | K13: 6 | L13: 3 | M13: Queen Black | N13: 1842 | O13: 1.6873 | P13: 1.6873 | Q13: 16.8455 | R13: 3.27 | S13: 5.63 | T13: 2.49 | U13: 1.87 | V13: 49.6253 | W13: 46.8953 | X13: 3.87 | Y13: 2.9025 | Z13: 6.8255 | AA13: =P13*Q13/100 -> 0.28423412 | AB13: 17.2301 | AC13: 6.74 | AD13: 1.89 | AE13: =AB13-AC13 -> 10.4901 | AF13: =AB13-AD13 -> 15.3401 | AG13: =AA13*AE13 -> 2.9816444 | AH13: =AA13*AF13 -> 4.3601798 | AI13: Maintain | AJ13: CVR not above market like-for-like (SQP); economics: CPO 3.5x contribution | AK13: 504037860004352 D-S4-SP-satin sheets queen-...-SATIN-WHITE-QUEEN-V2 (target "satin sheets queen"); 50488152164936 D-S4-SP-satin sheets for queen-(Satin)-HSV-Exact-Rank-DO-SATIN-QUEEN-BLACK
A14: satin sheet set | B14: 13.48 | C14: 8.71 | D14: 2 | E14: 2 | F14: 15 | G14: 6.23 | H14: =ROUND(SUM(B14:G14),0) -> 47 | I14: =IF(H14>=70,"High",IF(H14>=50,"Medium","Low")) -> Low | J14: MAINTAIN | K14: 9 | L14: 3 | M14: Queen Black | N14: 1025 | O14: 0.041 | P14: 0.041 | Q14: 16.1887 | S14: 2.02 | T14: 1.75 | U14: 1.69 | V14: 10.2482 | W14: 27.2901 | X14: 1.2416 | Y14: 0.9312 | Z14: 0.1059 | AA14: =P14*Q14/100 -> 0.006637367 | AB14: 5.7523 | AC14: 6.74 | AD14: 1.89 | AE14: =AB14-AC14 -> -0.9877 | AF14: =AB14-AD14 -> 3.8623 | AG14: =AA14*AE14 -> -0.0065557274 | AH14: =AA14*AF14 -> 0.025635503 | AI14: Maintain | AJ14: target rank held by strong rivals
A15: silk sheets twin | B15: 8.09 | C15: 20 | D15: 0 | E15: 10 | F15: 8 | G15: 0 | H15: =ROUND(SUM(B15:G15),0) -> 46 | I15: =IF(H15>=70,"High",IF(H15>=50,"Medium","Low")) -> Low | J15: MAINTAIN | K15: unranked | L15: 3 | M15: Twin Black (3-pc) | N15: 3222 | O15: 3.0131 | P15: 3.0131 | Q15: 13.2164 | R15: 5.62 | S15: 5.08 | T15: 2.78 | U15: 1.84 | V15: 84.4801 | W15: 5.5226 | X15: 3.52 | Y15: 2.64 | Z15: 8.1713 | AA15: =P15*Q15/100 -> 0.39822335 | AB15: 19.9752 | AC15: 8.69 | AD15: 4.49 | AE15: =AB15-AC15 -> 11.2852 | AF15: =AB15-AD15 -> 15.4852 | AG15: =AA15*AE15 -> 4.4940301 | AH15: =AA15*AF15 -> 6.1665682 | AI15: Maintain | AJ15: stock to sustain; economics: CPO 3.1x contribution | AK15: 108995710931187 D-S4-silk sheets twin - [Silk|Twin] - Exact - Ran - DO - SATIN-TWIN-BLACK-NEW
A16: black satin sheets | B16: 10 | C16: 2 | D16: 11 | E16: 3 | F16: 15 | G16: 3.94 | H16: =ROUND(SUM(B16:G16),0) -> 45 | I16: =IF(H16>=70,"High",IF(H16>=50,"Medium","Low")) -> Low | J16: MAINTAIN | K16: 4 | L16: 3 | M16: Queen Black | N16: 3271 | O16: 0.2098 | P16: 0.2098 | Q16: 16.1887 | R16: 14.41 | S16: 8.24 | T16: 0.98 | U16: 1.93 | V16: 29.9704 | W16: 20.667 | X16: 1.5658 | Y16: 1.1744 | Z16: 0.3596 | AA16: =P16*Q16/100 -> 0.033963893 | AB16: 7.2543 | AC16: 6.74 | AD16: 1.89 | AE16: =AB16-AC16 -> 0.5143 | AF16: =AB16-AD16 -> 5.3643 | AG16: =AA16*AE16 -> 0.01746763 | AH16: =AA16*AF16 -> 0.18219251 | AI16: Maintain | AJ16: CTR not above market (SQP); economics: CPO 2.2x contribution; target rank held by strong rivals | AK16: 132033654836368 D-S4-black satin sheets - [Satin] - Exact - Ran - DO - SATIN-QUEEN-BLACK
A17: satin sheets queen size | B17: 9.05 | C17: 9.25 | D17: 6 | E17: 6 | F17: 12 | G17: 0 | H17: =ROUND(SUM(B17:G17),0) -> 42 | I17: =IF(H17>=70,"High",IF(H17>=50,"Medium","Low")) -> Low | J17: MAINTAIN | K17: 7 | L17: 3 | M17: Queen Black | N17: 7792 | O17: 6.8124 | P17: 6.8124 | Q17: 26.0235 | R17: 3.36 | S17: 6.83 | T17: 2 | U17: 2.1 | V17: 39.6072 | W17: 54.4663 | X17: 3.816 | Y17: 2.862 | Z17: 30.6688 | AA17: =P17*Q17/100 -> 1.7728249 | AB17: 10.9977 | AC17: 6.74 | AD17: 1.89 | AE17: =AB17-AC17 -> 4.2577 | AF17: =AB17-AD17 -> 9.1077 | AG17: =AA17*AE17 -> 7.5481566 | AH17: =AA17*AF17 -> 16.146357 | AI17: Maintain | AJ17: CTR not above market (SQP); CVR not above market like-for-like (SQP); economics: CPO 3.1x contribution | AK17: 504037860004352 D-S4-SP-satin sheets queen-(Satin)-HSV-Exact-Rank-DO-SATIN-WHITE-QUEEN-V2 (target "satin sheets queen size")
A18: silk sheet set | B18: 7.5 | C18: 14 | D18: 0 | E18: 6 | F18: 15 | G18: 0 | H18: =ROUND(SUM(B18:G18),0) -> 43 | I18: =IF(H18>=70,"High",IF(H18>=50,"Medium","Low")) -> Low | J18: MAINTAIN | K18: 25 | L18: 3 | M18: Queen Black | N18: 1674 | O18: 0.1321 | P18: 0.1321 | Q18: 8.7112 | S18: 2.32 | T18: 2.52 | U18: 1.67 | V18: 30.4747 | W18: 16.2534 | X18: 1.287 | Y18: 0.9652 | Z18: 0.1728 | AA18: =P18*Q18/100 -> 0.011507495 | AB18: 11.0802 | AC18: 6.74 | AD18: 1.89 | AE18: =AB18-AC18 -> 4.3402 | AF18: =AB18-AD18 -> 9.1902 | AG18: =AA18*AE18 -> 0.049944831 | AH18: =AA18*AF18 -> 0.10575618 | AI18: Maintain | AJ18: CVR not above market like-for-like (SQP); economics: CPO 3.4x contribution
A19: satin bed sheets | B19: 7.5 | C19: 2 | D19: 2 | E19: 2 | F19: 15 | G19: 9.09 | H19: =ROUND(SUM(B19:G19),0) -> 38 | I19: =IF(H19>=70,"High",IF(H19>=50,"Medium","Low")) -> Low | J19: MAINTAIN | K19: 12 | L19: 3 | M19: Queen Black | N19: 4438 | O19: 0.039 | P19: 0.039 | Q19: 16.1887 | S19: 3.34 | T19: 0.89 | U19: 1.92 | V19: 6.1505 | W19: 37.758 | X19: 0.8367 | Y19: 0.8143 | Z19: 0.1318 | AA19: =P19*Q19/100 -> 0.006313593 | AB19: 5.03 | AC19: 6.74 | AD19: 1.89 | AE19: =AB19-AC19 -> -1.71 | AF19: =AB19-AD19 -> 3.14 | AG19: =AA19*AE19 -> -0.010796244 | AH19: =AA19*AF19 -> 0.019824682 | AI19: Maintain | AJ19: CTR not above market (SQP); CVR not above market like-for-like (SQP); target rank held by strong rivals
A20: queen silk sheets set | B20: 2.09 | C20: 8.3 | D20: 4 | E20: 4 | F20: 15 | G20: 4.3 | H20: =ROUND(SUM(B20:G20),0) -> 38 | I20: =IF(H20>=70,"High",IF(H20>=50,"Medium","Low")) -> Low | J20: MAINTAIN | K20: 9 | L20: 3 | M20: Queen Black | N20: 3324 | O20: 1.3658 | P20: 1.3658 | Q20: 19.1367 | R20: 7.88 | S20: 9.32 | T20: 1.43 | U20: 2 | V20: 80.3434 | W20: 5.6894 | X20: 1.872 | Y20: 1.404 | Z20: 1.9931 | AA20: =P20*Q20/100 -> 0.26136905 | AB20: 7.3367 | AC20: 6.74 | AD20: 1.89 | AE20: =AB20-AC20 -> 0.5967 | AF20: =AB20-AD20 -> 5.4467 | AG20: =AA20*AE20 -> 0.15595891 | AH20: =AA20*AF20 -> 1.4235988 | AI20: Maintain | AJ20: CTR not above market (SQP); CVR not above market like-for-like (SQP); economics: CPO 2.1x contribution; target rank held by strong rivals | AK20: 19421880211317 D-S4-queen silk sheets set - [Silk|Queen] - Exact - Ran - DO - SATIN-QUEEN-BLACK
A21: silk bed sheets | B21: 6.99 | C21: 8 | D21: 0 | E21: 7 | F21: 15 | G21: 0 | H21: =ROUND(SUM(B21:G21),0) -> 37 | I21: =IF(H21>=70,"High",IF(H21>=50,"Medium","Low")) -> Low | J21: MAINTAIN | K21: 19 | L21: 3 | M21: Queen Black | N21: 12374 | O21: 1.0654 | P21: 1.0654 | Q21: 9.891 | R21: 1.26 | S21: 2.91 | T21: 0.77 | U21: 1.79 | V21: 37.6032 | W21: 22.1323 | X21: 1.6541 | Y21: 1.2405 | Z21: 1.8403 | AA21: =P21*Q21/100 -> 0.10537871 | AB21: 12.5422 | AC21: 6.74 | AD21: 1.89 | AE21: =AB21-AC21 -> 5.8022 | AF21: =AB21-AD21 -> 10.6522 | AG21: =AA21*AE21 -> 0.61142837 | AH21: =AA21*AF21 -> 1.1225151 | AI21: Maintain | AJ21: CTR not above market (SQP); CVR not above market like-for-like (SQP); economics: CPO 3.8x contribution | AK21: 34608790713465 D-S4-SP-EXACT-silk bedsheets-Silk-SATIN-QUEEN-BLACK
A22: queen satin sheet set | B22: 0 | C22: 2.48 | D22: 6 | E22: 9 | F22: 15 | G22: 3.13 | H22: =ROUND(SUM(B22:G22),0) -> 36 | I22: =IF(H22>=70,"High",IF(H22>=50,"Medium","Low")) -> Low | J22: MAINTAIN | K22: 6 | L22: 3 | M22: Queen Black | N22: 2274 | O22: 0.5635 | P22: 0.5635 | Q22: 18.2162 | R22: 5.6 | S22: 9.77 | T22: 1.47 | U22: 2.03 | V22: 52.8305 | W22: 14.9091 | X22: 1.925 | Y22: 1.4438 | Z22: 1.0585 | AA22: =P22*Q22/100 -> 0.10264829 | AB22: 7.9256 | AC22: 6.74 | AD22: 1.89 | AE22: =AB22-AC22 -> 1.1856 | AF22: =AB22-AD22 -> 6.0356 | AG22: =AA22*AE22 -> 0.12169981 | AH22: =AA22*AF22 -> 0.619544 | AI22: Maintain | AJ22: CTR not above market (SQP); CVR not above market like-for-like (SQP); economics: CPO 2.4x contribution | AK22: 243989248483473 D-S4-SP-queen size satin sheets set-(Satin)-MSV-Exact-Rank-DO-SS-SATIN-RED-QUEEN-4PCS
A23: silk bed sheets queen | B23: 3.31 | C23: 8 | D23: 0 | E23: 7 | F23: 15 | G23: 2.21 | H23: =ROUND(SUM(B23:G23),0) -> 36 | I23: =IF(H23>=70,"High",IF(H23>=50,"Medium","Low")) -> Low | J23: MAINTAIN | K23: 14 | L23: 3 | M23: Queen Black | N23: 4954 | O23: 0.7004 | P23: 0.7004 | Q23: 15.0112 | R23: 2.28 | S23: 5.64 | T23: 1.13 | U23: 1.79 | V23: 48.8631 | W23: 9.2835 | X23: 1.86 | Y23: 1.395 | Z23: 1.2245 | AA23: =P23*Q23/100 -> 0.10513844 | AB23: 9.2931 | AC23: 6.74 | AD23: 1.89 | AE23: =AB23-AC23 -> 2.5531 | AF23: =AB23-AD23 -> 7.4031 | AG23: =AA23*AE23 -> 0.26842896 | AH23: =AA23*AF23 -> 0.77835042 | AI23: Maintain | AJ23: CTR not above market (SQP); CVR not above market like-for-like (SQP); economics: CPO 2.6x contribution | AK23: 221215321421557 D-S4-SP-EXACT-silk bedsheets queen-Silk|Queen-SATIN-QUEEN-BLACK (PAUSED); 99038470646931 D-S4-silk bed sheets queen - [Silk|Queen] - Exact - Ran - DO - SATIN-QUEEN-BLACK
A24: satin sheets twin | B24: 10 | C24: 2 | D24: 0 | E24: 10 | F24: 8 | G24: 4.88 | H24: =ROUND(SUM(B24:G24),0) -> 35 | I24: =IF(H24>=70,"High",IF(H24>=50,"Medium","Low")) -> Low | J24: MAINTAIN | K24: 106 | L24: 3 | M24: Twin Black (3-pc) | N24: 2274 | O24: 0.0264 | P24: 0.0264 | Q24: 6.0224 | S24: 4.6 | T24: 0.74 | U24: 1.88 | V24: 7.9227 | W24: 30.0133 | X24: 0.901 | Y24: 0.6757 | Z24: 0.0629 | AA24: =P24*Q24/100 -> 0.0015899136 | AB24: 11.2205 | AC24: 8.69 | AD24: 4.49 | AE24: =AB24-AC24 -> 2.5305 | AF24: =AB24-AD24 -> 6.7305 | AG24: =AA24*AE24 -> 0.0040232764 | AH24: =AA24*AF24 -> 0.010700913 | AI24: Maintain | AJ24: CTR not above market (SQP); stock to sustain; economics: CPO 2.0x contribution
A25: silk queen bed sheets set | B25: 3.11 | C25: 5.43 | D25: 2 | E25: 4 | F25: 15 | G25: 2.59 | H25: =ROUND(SUM(B25:G25),0) -> 32 | I25: =IF(H25>=70,"High",IF(H25>=50,"Medium","Low")) -> Low | J25: MAINTAIN | K25: 12 | L25: 3 | M25: Queen Black | N25: 3492 | O25: 1.5997 | P25: 1.5997 | Q25: 17.7565 | R25: 3.44 | S25: 6.77 | T25: 1.37 | U25: 1.92 | V25: 59.989 | W25: 34.9959 | X25: 1.9281 | Y25: 1.4461 | Z25: 3.213 | AA25: =P25*Q25/100 -> 0.28405073 | AB25: 8.1441 | AC25: 6.74 | AD25: 1.89 | AE25: =AB25-AC25 -> 1.4041 | AF25: =AB25-AD25 -> 6.2541 | AG25: =AA25*AE25 -> 0.39883563 | AH25: =AA25*AF25 -> 1.7764817 | AI25: Maintain | AJ25: CTR not above market (SQP); CVR not above market like-for-like (SQP); economics: CPO 2.5x contribution; target rank held by strong rivals | AK25: 152302990884047 D-S4-silk queen bed sheets set - [Silk|Queen] - Exact - Ran - DO - SATIN-QUEEN-BLACK
A26: silk sheets | B26: 14.2 | C26: 4.67 | D26: 0 | E26: 7 | F26: 3 | G26: 0 | H26: =ROUND(SUM(B26:G26),0) -> 29 | I26: =IF(H26>=70,"High",IF(H26>=50,"Medium","Low")) -> Low | J26: MAINTAIN | K26: 28 | L26: 3 | M26: Queen Grey | N26: 51852 | O26: 3.749 | P26: 3.749 | Q26: 14.4216 | R26: 1.07 | S26: 2.98 | T26: 1.04 | U26: 1.66 | V26: 52.5559 | W26: 17.7053 | X26: 2.254 | Y26: 1.6905 | Z26: 7.5754 | AA26: =P26*Q26/100 -> 0.54066578 | AB26: 11.722 | AC26: 3.28 | AE26: =AB26-AC26 -> 8.442 | AG26: =AA26*AE26 -> 4.5643005 | AI26: Maintain | AJ26: CTR not above market (SQP); CVR not above market like-for-like (SQP); stock to sustain; economics: CPO 5.1x contribution | AK26: 520117564893402 SATIN-QUEEN-GREY SP - Silk Sheets - Exact 091323
A27: black silk sheets | B27: 0.48 | C27: 6.66 | D27: 2 | E27: 5 | F27: 15 | G27: 0 | H27: =ROUND(SUM(B27:G27),0) -> 29 | I27: =IF(H27>=70,"High",IF(H27>=50,"Medium","Low")) -> Low | J27: MAINTAIN | K27: 10 | L27: 3 | M27: Queen Black | N27: 6231 | O27: 2.9281 | P27: 2.9281 | Q27: 6.4708 | R27: 5.61 | S27: 7.6 | T27: 1.45 | U27: 2.16 | V27: 57.7922 | W27: 33.7662 | X27: 1.8772 | Y27: 1.4079 | Z27: 5.7283 | AA27: =P27*Q27/100 -> 0.18947149 | AB27: 21.7576 | AC27: 6.74 | AD27: 1.89 | AE27: =AB27-AC27 -> 15.0176 | AF27: =AB27-AD27 -> 19.8676 | AG27: =AA27*AE27 -> 2.8454071 | AH27: =AA27*AF27 -> 3.7643439 | AI27: Maintain | AJ27: CTR not above market (SQP); CVR not above market like-for-like (SQP); economics: CPO 6.3x contribution; target rank held by strong rivals | AK27: 234075729975572 D-S4-black silk sheets - [Silk] - Exact - Ran - DO - SATIN-QUEEN-BLACK

Sheet Competitors
A1: Head term | B1: Our org / SP (ASINsight 9/28) | C1: Our org (DD radar 9/29) | D1: Our 7-d traffic (ad %) | E1: #1–2 tracked (ASINsight 9/28) | F1: DD niche 9/11 top holders | G1: Next rival to pass | H1: Only Aspirational above #3? | I1: Rank 3–5 benchmark | J1: Est. clicks/day (A–B) | K1: Est. ad $/day (A–B)
A2: satin sheets | B2: 3 / 11 | C2: 5 | D2: 13,935 (44%) | E2: BEDELITE-144 (Beat) #1, MR&HM (Beat) #2 | F2: #1 BEDELITE(Beat), #2 MR&HM(Beat), #4 Love's cabin(Asp), #5 DECOLURE(us) | G2: MR&HM (Beat) at #2, gap 1 | H2: no | I2: Love's cabin #3 | J2: 45–108 | K2: $18–44
A3: silk sheets | B3: 46 / 20 | C3: 29 | D3: 12,081 (44%) | E3: BEDELITE-144 (Beat) #1, MR&HM (Beat) #2 | F3: #1 BEDELITE(Beat), #2 MR&HM(Beat), #6 Love's cabin(Asp), #9 Lanest Housing(Beat) | G3: FreshCulture (Poor) at #42, gap 4 | H3: no | I3: MR&HM #2 | J3: 44–156 | K3: $21–73
A4: satin sheets queen size | B4: 5 / 10 | C4: 5 | D4: 9,572 (53%) | E4: BEDELITE-144 (Beat) #1, MR&HM (Beat) #2 | F4: #1 BEDELITE(Beat), #2 MR&HM(Beat), #4 Love's cabin(Asp), #5 Lanest Housing(Beat) | G4: Love's cabin (Asp) at #3, gap 2 | H4: no | I4: Love's cabin #3 | J4: 15–27 | K4: $6–10
A5: satin sheets queen | B5: 6 / 13 | C5: 6 | D5: 1,055 (66%) | E5: BEDELITE-144 (Beat) #1, Love's cabin (Asp) #2 | F5: #1 BEDELITE(Beat), #2 MR&HM(Beat), #3 Love's cabin(Asp), #5 Lanest Housing(Beat) | G5: CozyLux (Beat) at #4, gap 2 | H5: no | I5: MR&HM #3 | J5: 1–4 | K5: $1–3
A6: silk sheets queen | B6: 6 / 17 | C6: 8 | D6: 7,698 (44%) | E6: BEDELITE-144 (Beat) #1, MR&HM (Beat) #2 | F6: #1 BEDELITE(Beat), #2 MR&HM(Beat), #6 Love's cabin(Asp), #8 Lanest Housing(Beat) | G6: MR&HM (Beat) at #2, gap 4 | H6: no | I6: MR&HM #2 | J6: 14–45 | K6: $4–13
A7: satin sheets king | B7: 4 / 1 | C7: 3 | D7: 1,710 (21%) | E7: FreshCulture (Poor) #2 | F7: #1 BEDELITE(Beat), #3 MR&HM(Beat), #6 SLEEP SANCTUARY(sister), #7 DECOLURE(us) | G7: FreshCulture (Poor) at #2, gap 2 | H7: no | I7: P Pothuiny #5 | J7: 3–11 | K7: $0–2
A8: satin sheets king size | B8: 2 / 3 | C8: 4 | D8: 444 (65%) | E8: none tracked | F8: #1 BEDELITE(Beat), #5 P Pothuiny(Poor), #6 DECOLURE(us), #8 MR&HM(Beat) | G8: none — we lead tracked rivals | H8: ASINsight: none tracked at #1–2; DD 9/11: no (BEDELITE-144 #1) | I8: FreshCulture #3 | J8: 0–2 | K8: $0–0
A9: silk sheets king | B9: 33 / 8 | C9: 32 | D9: 2,563 (44%) | E9: none tracked | F9: #1 BEDELITE(Beat), #3 MR&HM(Beat), #7 SLEEP SANCTUARY(sister), #18 P Pothuiny(Poor) | G9: Lanest Housing (Beat) at #22, gap 11 | H9: ASINsight: none tracked at #1–2; DD 9/11: no (BEDELITE-144 #1) | I9: CozyLux #6 | J9: 3–19 | K9: $1–6
A10: queen satin sheet set | B10: 6 / 2 | C10: 6 | D10: 1,415 (66%) | E10: BEDELITE-144 (Beat) #1, MR&HM (Beat) #2 | F10: #1 BEDELITE(Beat), #2 MR&HM(Beat), #4 Love's cabin(Asp), #5 Lanest Housing(Beat) | G10: Love's cabin (Asp) at #5, gap 1 | H10: no | I10: CozyLux #3 | J10: 1–8 | K10: $0–0
A11: satin bed sheets queen | B11: 4 / 15 | C11: 5 | D11: 1,328 (58%) | E11: BEDELITE-144 (Beat) #1, MR&HM (Beat) #2 | F11: #1 BEDELITE(Beat), #2 MR&HM(Beat), #4 Love's cabin(Asp), #5 Lanest Housing(Beat) | G11: CozyLux (Beat) at #3, gap 1 | H11: no | I11: CozyLux #3 | J11: 1–5 | K11: $0–0
A12: silk sheet set | B12: 26 / 5 | C12: 24 | D12: 168 (0%) | E12: BEDELITE-144 (Beat) #1 | F12: #1 BEDELITE(Beat), #3 Love's cabin(Asp), #5 MR&HM(Beat), #14 DECOLURE(us) | G12: Pure Bedding (Poor) at #12, gap 14 | H12: no | I12: Love's cabin #3 | J12: 2–4 | K12: $0–1
... A19: silk bed sheets | B19: 12 / 11 | C19: 18 | D19: 3,765 (22%) | E19: BEDELITE-144 (Beat) #1 | F19: #1 BEDELITE(Beat), #2 MR&HM(Beat), #4 Love's cabin(Asp), #11 Lanest Housing(Beat) | G19: Love's cabin (Asp) at #7, gap 5 | H19: no | I19: MR&HM #3 | J19: 21–38 | K19: $14–25
A21: Rank-speed benchmark
A22: Sleep Sanctuary (sister brand, B0F2G983W3): "satin sheets queen size" #26 → #6 in 9 days (17–26 Aug), holding sponsored rank 1–3 every day; lost ground within about 2 weeks once ads went intermittent (Data Dive rank radar, daily).
A23: Sleep Sanctuary: "silk sheets twin" #18 → #4 in 17 days, same pattern.
A24: BEDELITE-144 (B0CSFTRP2X, $17.99): #1 on 17 of 18 head terms (Data Dive niche 11 Sep) after cutting price $23.99 → $17.99 since 15 Aug; 18% ad share.
A25: MR&HM ($19.99): "silk sheets" #12 → #2 (15 Aug → 11 Sep), then cut price $27.99 → $19.99; 20% ad share.
A26: Rival median price $22.99; only Vonty ($30.99) sits in our $29.95–33.95 band (competitor context, 28 Sep).
A27: Rival clicks and ad spend are estimates: ASinsight 7-day traffic × a CTR calibrated on our own SQP (1.08%), or SQP market clicks × top-3 click share ÷ 3.

Sheet New campaigns
A1: Seq | B1: New campaign | C1: Ad type | D1: Match | E1: Engine child | F1: Targets (engine) | G1: Budget $/day | H1: Bid | I1: Objective (engine) | J1: Our call (workbook) | K1: Our verdict | L1: Child after | M1: Deciding fact / what to change | N1: Other reviewer view | O1: Source
A2: 2235 | B2: DSS4-SD-OwnPage-QUEEN-(PAT)-Targeting-(Defensive)-Reach-FIX-SATIN-WHITE-QUEEN-TEST | C2: SD | D2: TARGETING_EXPRESSION | E2: SATIN-WHITE-QUEEN | F2: B0CV4D54FV, B0CQRXDZYF, B08KRW2BX3, B0CQRXKRPN, B0BG1YXQGT, B0BG21THPM, B0BZPV84V7, B09G6JSW33, B0CQRZ6JQ3, B09G6L5ZW6, B09G6K9C65 | G2: 5 | I2: Defensive | J2: HOLD, RE-POINT / RE-DATE | K2: Hold; re-point; re-date | L2: SATIN-QUEEN-BLACK | M2: Re-point the ad to Queen Black and add B0839MKJMV (the Queen Black page, ~46% of product traffic) to the own-page targets; move the read from 20 Oct (inside the Best Deal) to after 11 Nov. | O2: audit seq 2235; workbook verdict "hold / re-date"
A3: 2246 | B3: DSS4-SD-OwnPage-QUEEN-(PAT)-Targeting-(Defensive)-Clicks-FIX-SATIN-WHITE-QUEEN-TEST | C3: SD | D3: TARGETING_EXPRESSION | E3: SATIN-WHITE-QUEEN | F3: B0DD4JMGXN, B0CQRWGHJN, B0839LQG4C, B0CNS8T4ZK, B0CQRXLH6M, B0839L4HWH, B0BG228RDJ, B0DBR4XYLB, B09G6LBXRX, B09G6KCTXW, B09G6K328B | G3: 5 | I3: Defensive | J3: HOLD, RE-POINT / RE-DATE | K3: Hold; re-point; re-date | L3: SATIN-QUEEN-BLACK | M3: Same as 2235 (the clicks arm of the same split test). | O3: audit seq 2246; workbook verdict "hold / re-date"
A4: 2324 | B4: DSS4-SP-Harvest-(PAT)-Targeting-(Conversion)-FIX-SATIN-QUEEN-BLACK-TEST | C4: Sponsored Products | D4: TARGETING_EXPRESSION | E4: SATIN-QUEEN-BLACK | F4: asin="B082B4Z5QB"; asin="B0BNMC3V1T"; asin="B0CSFTZ5B9"; asin="B09G17SQXF"; asin="B09SH16ZMN"; asin="B0GT19ZY4F"; asin="B0CSFX48M3"; asin="B0CM5NFXX1"; asin="B07X1LN13P"; asin="B08FRFF5R7" | G4: 5 | I4: Conversions | J4: CHANGE | K4: Re-point targets; re-date | L4: SATIN-QUEEN-BLACK | M4: Drop B082B4Z5QB (already a $1.06 target in Defensive campaign 12066855874066) and B0CSFTZ5B9 (also in conquest 2341); move the 20 Oct read to after 11 Nov. | O4: audit seq 2324; workbook verdict "correct"
A5: 2332 | B5: DSS4-SD-Harvest-(PAT)-Targeting-(Conversion)-FIX-SATIN-QUEEN-BLACK-TEST | C5: SD | D5: TARGETING_EXPRESSION | E5: SATIN-QUEEN-BLACK | F5: B082B4Z5QB, B0BNMC3V1T, B0CSFTZ5B9, B09G17SQXF, B09SH16ZMN, B0GT19ZY4F, B0CSFX48M3, B0CM5NFXX1, B07X1LN13P, B08FRFF5R7 | G5: 5 | I5: Conversions | J5: CHANGE | K5: Re-point targets; re-date | L5: SATIN-QUEEN-BLACK | M5: Same target corrections as its SP twin 2324; move the 20 Oct read to after 11 Nov. | O5: audit seq 2332; workbook verdict "correct"
A6: 2341 | B6: DSS4-SP-Conquest-(PAT)-Targeting-(Conquesting)-FIX-SATIN-QUEEN-BLACK-TEST | C6: Sponsored Products | D6: TARGETING_EXPRESSION | E6: SATIN-QUEEN-BLACK | F6: asin="B08HM6WT6X"; asin="B08HM65Z68"; asin="B0D2CQ6VNT"; asin="B082B5CY3D"; asin="B07VTSWJPH"; asin="B0CSFTRP2X"; asin="B0CSFTZ5B9"; asin="B0CSFW9QKP"; asin="B08P16XLP2" | G6: 21.21 | I6: Conquesting | J6: HOLD | K6: Hold (until 29 Oct, then re-price) | L6: SATIN-QUEEN-BLACK | M6: Duplicates live conquest targets B08HM6WT6X / B08P16XLP2 and harvest target B0CSFTZ5B9; $8.40 CPA ceiling comes from the engine's $8.56/unit margin vs Queen Black's $5.03 (SB 30 Aug–29 Sep); 135-click read falls on the 6 Oct deal day. | N6: hold until 29 Oct, then re-price | O6: audit seq 2341; workbook verdict "hold"
A7: 2373 | B7: DSS4-SP-satin sheet set queen-[Satin|Queen]-(LSV)-Exact-(Conversion)-DO-SATIN-4PCS-QUEEN-STONE-GREY-TEST | C7: Sponsored Products | D7: EXACT | E7: SATIN-4PCS-QUEEN-STONE-GREY | F7: satin sheet set queen | G7: 5.76 | H7: 1.92 | I7: Conversions | J7: CHANGE | K7: Hold; re-point; re-date | L7: SATIN-QUEEN-BLACK (or SATIN-WHITE-QUEEN) | M7: Advertises Queen Stone Grey ($2.94/unit, ~10% break-even, SB 30 Aug–29 Sep) at a 22.34% ACoS target, so each order loses ~$3.50; re-point to Queen Black (≤17.8% ACoS) or White Queen, and read after 11 Nov, not 20 Oct. | N7: hold; re-point to SATIN-WHITE-QUEEN | O7: audit seq 2373; workbook verdict "correct the child"
A8: 2385 | B8: DSS4-SP-chair covers-[unassigned]-(NOSV)-Exact-(Conversion)-DO-SATIN-4PCS-QUEEN-STONE-GREY-TEST | C8: Sponsored Products | D8: EXACT | E8: SATIN-4PCS-QUEEN-STONE-GREY | F8: chair covers | G8: 5 | H8: 0.72 | I8: Conversions | J8: HOLD | K8: Hold; drop from this product | L8: — | M8: "chair covers" is product 33's halo term; held last run as 2383 and returned unchanged. | O8: audit seq 2385; workbook verdict "hold (agree)"
A9: 2397 | B9: DSS4-SP-silk fitted sheet queen-[unassigned]-(VLSV)-Exact-(Conversion)-DO-SATIN-4PCS-QUEEN-STONE-GREY-TEST | C9: Sponsored Products | D9: EXACT | E9: SATIN-4PCS-QUEEN-STONE-GREY | F9: silk fitted sheet queen | G9: 5 | H9: 1.26 | I9: Conversions | J9: CHANGE | K9: Hold; re-point; re-date | L9: SATIN-QUEEN-BLACK (or SATIN-WHITE-QUEEN) | M9: Advertises Queen Stone Grey ($2.94/unit, ~10% break-even, SB 30 Aug–29 Sep) at a 22.34% ACoS target, so each order loses ~$3.50; re-point to Queen Black (≤17.8% ACoS) or White Queen, and read after 11 Nov, not 20 Oct. | N9: hold; re-point to SATIN-WHITE-QUEEN | O9: audit seq 2397; workbook verdict "correct the child"
A10: 2409 | B10: DSS4-SP-satin sheets queen size bed set-[Satin|Queen]-(LSV)-Exact-(Conversion)-DO-SATIN-4PCS-QUEEN-STONE-GREY-TEST | C10: Sponsored Products | D10: EXACT | E10: SATIN-4PCS-QUEEN-STONE-GREY | F10: satin sheets queen size bed set | G10: 5.76 | H10: 1.92 | I10: Conversions | J10: CHANGE | K10: Hold; re-point; re-date | L10: SATIN-QUEEN-BLACK (or SATIN-WHITE-QUEEN) | M10: Advertises Queen Stone Grey ($2.94/unit, ~10% break-even, SB 30 Aug–29 Sep) at a 22.34% ACoS target, so each order loses ~$3.50; re-point to Queen Black (≤17.8% ACoS) or White Queen, and read after 11 Nov, not 20 Oct. | N10: hold; re-point to SATIN-WHITE-QUEEN | O10: audit seq 2409; workbook verdict "correct the child"
A11: 2421 | B11: DSS4-SP-sateen sheets-[Satin]-(MSV)-Exact-(Conversion)-DO-SATIN-4PCS-QUEEN-STONE-GREY-TEST | C11: Sponsored Products | D11: EXACT | E11: SATIN-4PCS-QUEEN-STONE-GREY | F11: sateen sheets | G11: 5 | H11: 1.28 | I11: Conversions | J11: CHANGE | K11: Hold; re-point; re-date | L11: SATIN-QUEEN-BLACK (or SATIN-WHITE-QUEEN) | M11: Advertises Queen Stone Grey ($2.94/unit, ~10% break-even, SB 30 Aug–29 Sep) at a 22.34% ACoS target, so each order loses ~$3.50; re-point to Queen Black (≤17.8% ACoS) or White Queen, and read after 11 Nov, not 20 Oct. | N11: hold; re-point to SATIN-WHITE-QUEEN | O11: audit seq 2421; workbook verdict "correct the child"
A12: 2433 | B12: DSS4-SP-satin silk sheets full-[unassigned]-(LSV)-Exact-(Conversion)-DO-SATIN-4PCS-FULL-ROSEWOOD-TEST | C12: Sponsored Products | D12: EXACT | E12: SATIN-4PCS-FULL-ROSEWOOD | F12: satin silk sheets full | G12: 5.55 | H12: 1.85 | I12: Conversions | J12: HOLD | K12: Hold (evidence is attribution noise) | L12: n/a while held | M12: Source tails show as many or more orders than clicks (e.g. 2445: 20 orders on 12 clicks) and mix sizes onto one child; several terms are irrelevant (silver glitter, Spanish, skull). Rebuild only on a clean term read. | N12: hold; re-point to SATIN-FULL-BLACK | O12: audit seq 2433; workbook verdict "hold"
A13: 2445 | B13: DSS4-SP-100 silk sheets full-[unassigned]-(LSV)-Exact-(Conversion)-DO-SATIN-4PCS-FULL-ROSEWOOD-TEST | C13: Sponsored Products | D13: EXACT | E13: SATIN-4PCS-FULL-ROSEWOOD | F13: 100 silk sheets full | G13: 5.55 | H13: 1.85 | I13: Conversions | J13: HOLD | K13: Hold (evidence is attribution noise) | L13: n/a while held | M13: Source tails show as many or more orders than clicks (e.g. 2445: 20 orders on 12 clicks) and mix sizes onto one child; several terms are irrelevant (silver glitter, Spanish, skull). Rebuild only on a clean term read. | N13: hold; re-point to SATIN-FULL-BLACK | O13: audit seq 2445; workbook verdict "hold"
A14: 2457 | B14: DSS4-SP-real satin bed sheets-[unassigned]-(LSV)-Exact-(Conversion)-DO-SATIN-4PCS-QUEEN-STONE-GREY-TEST | C14: Sponsored Products | D14: EXACT | E14: SATIN-4PCS-QUEEN-STONE-GREY | F14: real satin bed sheets | G14: 5.55 | H14: 1.85 | I14: Conversions | J14: HOLD | K14: Hold (evidence is attribution noise) | L14: n/a while held | M14: Source tails show as many or more orders than clicks (e.g. 2445: 20 orders on 12 clicks) and mix sizes onto one child; several terms are irrelevant (silver glitter, Spanish, skull). Rebuild only on a clean term read. | N14: hold; re-point to SATIN-WHITE-QUEEN | O14: audit seq 2457; workbook verdict "hold"
A15: 2469 | B15: DSS4-SP-red dining chair covers set of 6-[unassigned]-(LSV)-Exact-(Conversion)-DO-SATIN-4PCS-KING-RED-TEST | C15: Sponsored Products | D15: EXACT | E15: SATIN-4PCS-KING-RED | F15: red dining chair covers set of 6 | G15: 5 | H15: 1.31 | I15: Conversions | J15: HOLD | K15: Hold; drop from this product | L15: — | M15: Chair-cover terms belong to product 33; the engine's "10 shelf days" reason is wrong (King Red 262 + 402 inbound, SB 29 Sep). | N15: hold (agree on the chair-cover terms; the stock reason is wrong) | O15: audit seq 2469; workbook verdict "hold, reason corrected"
A16: 2481 | B16: DSS4-SP-silver glitter sheets full size bed deep pocket-[unassigned]-(LSV)-Exact-(Conversion)-DO-SATIN-4PCS-FULL-ROSEWOOD-TEST | C16: Sponsored Products | D16: EXACT | E16: SATIN-4PCS-FULL-ROSEWOOD | F16: silver glitter sheets full size bed deep pocket | G16: 5.55 | H16: 1.85 | I16: Conversions | J16: HOLD | K16: Hold (evidence is attribution noise) | L16: n/a while held | M16: Source tails show as many or more orders than clicks (e.g. 2445: 20 orders on 12 clicks) and mix sizes onto one child; several terms are irrelevant (silver glitter, Spanish, skull). Rebuild only on a clean term read. | N16: hold; re-point to SATIN-FULL-BLACK | O16: audit seq 2481; workbook verdict "hold"
A17: 2493 | B17: DSS4-SP-sheets full size silk-[Silk|Full]-(LSV)-Exact-(Conversion)-DO-SATIN-4PCS-FULL-ROSEWOOD-TEST | C17: Sponsored Products | D17: EXACT | E17: SATIN-4PCS-FULL-ROSEWOOD | F17: sheets full size silk | G17: 5.88 | H17: 1.96 | I17: Conversions | J17: LOAD | K17: Re-point to Full Black; re-date | L17: SATIN-FULL-BLACK | M17: Advertises Full Rosewood ($4.50/unit, 15.0% break-even, 1.2 units/day) against Full Black ($8.04, 27.5%, 11.2/day; SB 30 Aug–29 Sep); move the 20 Oct read to after 11 Nov. | N17: hold; re-point to SATIN-FULL-BLACK | O17: audit seq 2493; workbook verdict "pass"
A18: 2505 | B18: DSS4-SP-juego de sábanas queen satin-[unassigned]-(NOSV)-Exact-(Conversion)-DO-SATIN-4PCS-QUEEN-STONE-GREY-TEST | C18: Sponsored Products | D18: EXACT | E18: SATIN-4PCS-QUEEN-STONE-GREY | F18: juego de sábanas queen satin | G18: 5 | H18: 1.53 | I18: Conversions | J18: HOLD | K18: Hold (evidence is attribution noise) | L18: n/a while held | M18: Source tails show as many or more orders than clicks (e.g. 2445: 20 orders on 12 clicks) and mix sizes onto one child; several terms are irrelevant (silver glitter, Spanish, skull). Rebuild only on a clean term read. | N18: hold; re-point to SATIN-WHITE-QUEEN | O18: audit seq 2505; workbook verdict "hold"
A19: 2517 | B19: DSS4-SP-silk sheet and pillowcase set-[Silk]-(NOSV)-Exact-(Conversion)-DO-SATIN-4PCS-QUEEN-STONE-GREY-TEST | C19: Sponsored Products | D19: EXACT | E19: SATIN-4PCS-QUEEN-STONE-GREY | F19: silk sheet and pillowcase set | G19: 5.31 | H19: 1.77 | I19: Conversions | J19: HOLD | K19: Hold (evidence is attribution noise) | L19: n/a while held | M19: Source tails show as many or more orders than clicks (e.g. 2445: 20 orders on 12 clicks) and mix sizes onto one child; several terms are irrelevant (silver glitter, Spanish, skull). Rebuild only on a clean term read. | N19: hold; re-point to SATIN-WHITE-QUEEN | O19: audit seq 2517; workbook verdict "hold"
A20: 2601 | B20: DSS4-SP-queen satin sheets set-[Satin|Queen]-(VLSV)-Exact-(Conversion)-DO-SATIN-4PCS-QUEEN-STONE-GREY-TEST | C20: Sponsored Products | D20: EXACT | E20: SATIN-4PCS-QUEEN-STONE-GREY | F20: queen satin sheets set | G20: 5 | H20: 1.63 | I20: Conversions | J20: CHANGE | K20: Hold; re-point; re-date | L20: SATIN-QUEEN-BLACK (or SATIN-WHITE-QUEEN) | M20: Advertises Queen Stone Grey ($2.94/unit, ~10% break-even, SB 30 Aug–29 Sep) at a 22.34% ACoS target, so each order loses ~$3.50; re-point to Queen Black (≤17.8% ACoS) or White Queen, and read after 11 Nov, not 20 Oct. | N20: hold; re-point to SATIN-WHITE-QUEEN | O20: audit seq 2601; workbook verdict "correct the child"
... A22: 2757 | B22: DSS4-SP-silk bedsheets full size bed-[Silk|Full]-(NOSV)-Exact-(Conversion)-DO-SATIN-4PCS-FULL-ROSEWOOD-TEST | C22: Sponsored Products | D22: EXACT | E22: SATIN-4PCS-FULL-ROSEWOOD | F22: silk bedsheets full size bed | G22: 5 | H22: 1.1 | I22: Conversions | J22: LOAD | K22: Re-point to Full Black; re-date | L22: SATIN-FULL-BLACK | M22: Advertises Full Rosewood ($4.50/unit, 15.0% break-even, 1.2 units/day) against Full Black ($8.04, 27.5%, 11.2/day; SB 30 Aug–29 Sep); move the 20 Oct read to after 11 Nov. | N22: hold; re-point to SATIN-FULL-BLACK | O22: audit seq 2757; workbook verdict "pass"

Sheet Not in the run
A1: Area | B1: What is needed | C1: Campaign(s) | D1: Decision | E1: Deciding fact (window) | F1: Source
A2: Negation | B2: Negate our own ASIN "b0839mkjmv" as a search term | C2: Auto / broad / phrase campaigns where it serves (not itemised in the run) | D2: negative exact "b0839mkjmv" in each serving campaign | E2: $820 spent on our own ASIN as a search term (CC 2 Jul–29 Sep) | F2: corrections §10
A3: Negation | B3: Negate chair-cover search terms (product 33's halo) | C3: Satin auto / broad campaigns serving chair-cover terms | D3: negative phrase "chair cover(s)" | E3: Chair-cover terms belong to product 33; builds 2385 and 2469 already held for this reason | F3: corrections §10; reviewer B/D
A4: Child swap | B4: olive green silk sheets → King Dark Green | C4: 218060067204712 | D4: swap SATIN-4PC-QUEEN-DARK GREEN → SATIN-4PC-KING-DARK GREEN (or FULL-DARK GREEN), by hand, now; retag Conversions | E4: Queen Dark Green 6 units, ~3 days, out ~1 Oct; King Dark Green 116, Full Dark Green 96 (SB 29 Sep); $26.62 spend in 14d (audit) | F4: corrections §5; reviewer C A4
A5: Child swap / ownership | B5: Bamboo defensive campaign on King Rosewood | C5: 302124675724544 | D5: swap SATIN-4PCS-KING-ROSEWOOD → SATIN-KING-BLACK now; move campaign to the bamboo product's ownership | E5: King Rosewood 4 units (~2 days, SB 29 Sep); $8.49 spend 14d (audit) | F5: corrections §5; reviewer C A4
A6: Ownership | B6: Two more Bamboo 6-pc Defensive PAT campaigns filed under satin | C6: 345754272659953; 545053729101534 | D6: decide ownership (bamboo portfolio); objective Defensive is correct | E6: Target Decolure bamboo ASINs B0CQ2XQF9N / B0CQ2ZWGNQ / B0CQ33H4QW with satin ads | F6: corrections §10; reviewer C finding 9
A7: Child swap | B7: Six King black-colour exacts advertise King Grey | C7: 115346154431177; 205502557228684; 541158880050314; 139699829640851; 162830140596082; 17776649090891 | D7: swap SATIN-4PC-KING-GREY → SATIN-KING-BLACK (low stakes) | E7: King Black 1,385 units (SB 29 Sep); $0 spend 14d | F7: corrections §5; reviewer C A4
A8: Child swap | B8: plum → Queen Purple; silver → Queen Grey | C8: 85523138318625; 113668823711741 | D8: swap SATIN-QUEEN-BLACK → SATIN-QUEEN-PURPLE (plum) and → SATIN-QUEEN-GREY (silver) | E8: Queen Purple 143, Queen Grey 1,145 units (SB 29 Sep); $1.35 / $0 spend 14d | F8: corrections §5; reviewer C A4
A9: Child swap | B9: red silky sheet set queen (enabled; not paused by the run) | C9: 270072732682449 | D9: swap SATIN-4PC-RED-QUEEN → SATIN-4PCS-KING-RED, or pause with the other red-queen rows | E9: Queen Red 34 units, ~11 days, out ~10 Oct (SB 29 Sep) | F9: reviewer C A4
A10: Stock plan | B10: Twin Black → Twin Grey before the Best Deal | C10: 108995710931187; 90694496079420; 276983621807441; 195376730173968; 253348963885567; 4681005199760; 176668458976065; 183041310179172; 177239915449451; 442077551467168; 259161668032687; 2107301851159; 274098888993841; 16985401580492; 175024333400120 | D10: plan the move of every enabled Twin Black campaign to SATIN-TWIN-GREY before 16 Oct | E10: Twin Black 66 units, 2.0/day, ~34 days, out ~1 Nov; Twin Grey 94 units (SB 29 Sep) | F10: corrections §5; reviewer C A4
A11: Objective | B11: Declared-Ranking colour / competitor / Spanish / misspelled campaigns the retag pass never reads | C11: 102 campaigns (see "Every campaign", Source = "our addition: standard") | D11: retag → Conversions | E11: Retag pass only reads UNSET rows; C counted 78 colour campaigns (71 enabled, $368.62 in 14d) | F11: corrections §11; reviewer C finding 9
A12: Objective | B12: Competitor "bedsure" campaigns under Ranking | C12: 331342999808577; 466655261824746 | D12: retag → Conversions (or negate) | E12: Targets "bedsure dark gray king bed sheets", "bedsure satin sheet set full" | F12: reviewer C A4
... A19: Rank | B19: Twin rank collapse 23–26 Sep | C19: Twin campaigns | D19: find the cause (listing, stock, competitor) before reading any Twin cut | E19: satin twin sheets 24 → 141, silk twin bed sheets 8 → 100, satin sheets twin 17 → 106 (engine timelines, 29 Sep) | F19: corrections §13

Sheet Read me
A1: Item | B1: Definition
A2: Workbook | B2: R3 — per-campaign decisions for the Satin Sheets 4 Piece (US) audit run 20260929-6050bf68, built 29 Sep 2026.
A3: Scope | B3: 564 campaigns in the run ("Every campaign"), 21 new campaigns ("New campaigns"), and the decisions the run needs but does not contain ("Not in the run"). Sorted by 30d spend, highest first.
A4: Rule of precedence | B4: Our verdict in the corrections workbook ("Every decision") wins: "correct to X" → X; LOAD → the audit value; HOLD / DROP / REJECT → current value. Holds that should move (corrections §7) are applied. Where the run is silent, the row is "No change" unless an issue is found (then it is our addition, flagged in Source).
A5: NOT SERVING holds | B5: 119 holds on 103 campaigns are released. Break-even base = child contribution (Sellerboard 30 Aug–29 Sep) × campaign CVR (CC 31 Aug–29 Sep); the new base is max(break-even, current × 0.75) if the campaign had orders in 30d, max(break-even, current × 0.50) if not, and never above the current bid. No clicks in 30d → keep the base (a cut only lowers delivery). TOS % is left unchanged, so the TOS price falls with the base. 10 of the 103 are paused by folds and are not priced.
A6: Child contribution ($/unit before ads, SB 30 Aug–29 Sep) | B6: Queen Black 5.03 · Queen Grey 3.28 · White Queen 9.02 · Queen Stone Grey 2.94 · Queen Red 8.15 · King Grey 4.93 · King Black 9.10 · King Red 6.75 · Full Black 8.04 · Full Grey 7.62 · Full Rosewood 4.50 · Twin Black 8.50 · Twin Grey 6.93 · blended 7.02 for every other colour.
A7: Revives at break-even | B7: Revives our verdict re-prices (2817, 2818, 2831, 2836; 2827 re-pointed to King Black) use break-even base = contribution × CC 90d CVR (2 Jul–29 Sep), with no cap because the campaign is paused.
A8: Objective standard | B8: brand → Defensive; generic exact → Ranking; colour / competitor / Spanish / misspelled / irrelevant exact → Conversions; auto / broad / phrase / theme → Discovery; competitor ASIN → Conquesting; own ASIN → Defensive; Liquidation, Sponsored Brands and Sponsored Display kept as declared. Retag rows use our verdict; other campaigns are classified from the campaign name keyword and CC targets.
A9: Columns | B9: Campaign ID / name / status / objective / syntax / child: audit JSON `campaigns`. Match / targeting: from the name and CC. Base bid now: enabled target bids in the audit JSON; for 25 NOT-SERVING campaigns without one, the CC bid snapshot of 29 Sep. "n/a" = no bid in either source. TOS price = base × (1 + TOS %) on the campaign's main target. PP / ROS = product-page / rest-of-search boosts. State after = ENABLED / PAUSED after all decisions. Negatives: rows to add (held rows named). Rename: load (clean name) / defer (engine name wrong; load a corrected name after 28 Oct) / none.
A10: Performance windows | B10: 30d spend, clicks, orders, ACoS, TOS and PP click share: Command Center campaign view 31 Aug–29 Sep 2026 (raw/campaigns_30d_placements.csv; the trailing 7 days carry 7-day attribution and read low). 90d orders: CC 2 Jul–29 Sep (raw/campaigns_90d.csv), falling back to the audit's 90-day read. Break-even ACoS per child: Sellerboard 30 Aug–29 Sep. Stock: Sellerboard 29 Sep.
A11: Decision / Why / Source | B11: Decision: the action in plain words. Decision type: a grouping for counts. Why: the deciding figure with its window. Source: audit seq(s) with our verdict, or "our addition".
A12: Ranking push | B12: Left blank for the push-tier fill (Erik's direction: pick the keywords to push, with clicks, sales and volume needed).
... A22: Required TOS clicks/day | B22: Units/day needed at the target rank ÷ top-of-search CVR; the larger of the engine plan and the rival-at-target estimate when they agree within 2×, the rival estimate when they do not; never below current delivery.

Sheet Data sources
A1: Written to | B1: Source | C1: Object | D1: Obtained via | E1: Query or request | F1: Parameters | G1: Run at | H1: Row count | I1: Changes after retrieval | J1: Notes
A2: 'Every campaign'!A1:AJ565 | B2: PPC audit run 20260929-6050bf68 | C2: ppc-audit-20260929-6050bf68.json (campaigns, decisions, considered, builds) | D2: Uploaded by user | E2: Audit JSON for Satin Sheets 4 Piece US | F2: product 37 | G2: 2026-09-29 | H2: 564 | I2: One row per campaign; our verdict applied per decision
A3: 'Every campaign'!Y1:AE565 | B3: Command Center (ecotero-command-center) | C3: ppc_campaigns | D3: Run by Claude | E3: Campaign performance with placements | F3: product 37; 2026-08-31..2026-09-29 (30d); 2026-07-02..2026-09-29 (90d) | G3: 2026-09-29 | H3: 564 | I3: Joined on campaign ID
A4: 'Ranking push'!A1:AE27 | B4: Command Center; Data Dive rank radar B0839MKJMV (SQP); DataRova crawl; Sellerboard | C4: ppc_keywords, ppc_keyword_campaigns, ppc_campaign_targets, ppc_ranks, ppc_syntax_groups; get_rank_radar_sqp_data | D4: Run by Claude | E4: Per-term TOS clicks, CVR, CTR, TOS impression share, rank, SQP market and ASIN rates | F4: CC 2026-08-31..09-29 and 07-02..09-29; SQP weeks 30 Aug–26 Sep and 5 Jul–26 Sep; ranks 29 Sep and 30 Aug | G4: 2026-09-29 | H4: 26 | I4: Scored and sized by the bids and placements rules | J4: SQP basis (child or parent) not confirmed
A5: 'Ranking push' contribution | B5: Sellerboard | C5: dashboard_table (Ecotero, amazon.com) | D5: Run by Claude | E5: Profit before ads per unit by SKU | F5: 2026-08-30..2026-09-29 | G5: 2026-09-29 | H5: 13 | I5: Profit ÷ units per SKU | J5: All-in: COGS, fees, storage, refunds
A6: 'Competitors'!A1:K19 | B6: Command Center traffic tools (ASinsight); Data Dive niche and rank radar | C6: traffic_market_keywords, traffic_competitor, traffic_position_trends; get_niche_keywords, get_niche_competitors, get_rank_radar_data | D6: Run by Claude (read-only) | E6: Who holds ranks 1–10 on 18 head terms, rival traffic and estimated clicks | F6: ASinsight exports 28–29 Sep; Data Dive snapshots 26 Feb, 19 May, 15 Aug, 11 Sep; radar 1 Jul–29 Sep | G6: 2026-09-29 | H6: 18 | I6: Clicks and spend estimated | J6: No rival click, hourly or sponsored-rank data
A7: 'New campaigns', 'Not in the run' | B7: Audit JSON builds; corrections review | C7: builds (21); review files A–F | D7: Run by Claude | E7: Verdict per new campaign; campaigns the run is missing | G7: 2026-09-29 | H7: 39
