Workbook

Sheet Summary
A1: CooLinens Cooling Sheets 4PC — Data-Backed PPC Launch Strategy (DRAFT v2)
A2: Go-live 15 Oct 2026 · US · Parent B0H6K5RPX6 · Prepared 8 Oct 2026 for the 10 Oct review · v2 = v1 + full historical analysis (see CooLinens_Cooling_Sheets_4PC_Historical_Analysis_v1.xlsx) · MKL integration pending (see MKL_Intake)
A4: 1. Bottom line
A5: • Benchmark = Sleephoria Cooling Sheets 4PC (same COGS to within $0.30/size, same 12 colours, same sizes, same list price today: Queen $79.99 / King $84.99). Decolure is a $38 microfiber tier — use it for "what not to do", not for economics.
A6: • CooLinens is therefore a near-twin of Sleephoria, not a premium tier above it. Because the two are the same product at the same price, the main launch risk is the two listings bidding against each other on the same keywords. (v1 cited Decolure's session collapse after Sleephoria's launch; the historical analysis shows Decolure's decline started in Jul 2025, before Sleephoria's ads — that rationale is withdrawn.) SOP-33 requires a declared owner per shared keyword root before ranking-size spend.
A7: • Proposal: CooLinens leads the QUEEN cluster (biggest size: 41% of CooLinens stock, ~35–42% of category units) where Sleephoria is weak (organic 45–69) — and Sleephoria keeps the roots it already wins (head term #11–18, King #8–18, Twin #5, Cal King #3–9, "hot sleepers" #5–7). Two of our listings on page 1 > two listings bidding against each other.
A8: • Day 0 = 12 single-keyword SP Exact campaigns on the Queen Graphite child (B0H6K1MKQW, 373 FBA units; Graphite converted 13% vs 3.7% for other colours at Sleephoria). Fixed bids, all placement modifiers 0, no broad/phrase/auto/SB/SD/PAT on day 1 (SOP-22 P3.4).
A9: • Queen terms open as a SOP-33 P5 probe (50 → 100 clicks), are declared ~22 Oct, then scale to ranking size before the BFCM pre-event window (13 Nov). Day-0 budget ≈ $130/day (~$910/wk); post-declaration ≈ $175/day (~$1,220/wk) inside a declared $1,750/wk envelope, leaving ~$530/wk for Batch 2 / Phase 2. Projected blended ACoS ≈ 41% at 9% CVR. Queen ranking rows ≈ $113/day vs a Sleephoria-equivalent $135/day (cross-check). Every number is a live formula on editable inputs.
A10: 2. What the history says (numbers in the benchmark tabs)
A11: • Sleephoria launch curve (ad months 1→2→3): TACoS 24% → 15% → 10%, margin 3% → 11% → 17%; first ~20% margin in ad month 5. Spend $17.6k → $11.5k → $6.4k. CPC $4.87 → $4.24 → $2.49.
A12: • Top-10 on the head terms took ~12 days at ~$790/day, CPC ~$5, ACoS ~50% (with Prime Big Deal Days tailwind and some prior organic history). Rank decayed within 2–4 weeks whenever spend fell below ~$70/day or CVR collapsed (Dec–Jan and Jun–Jul).
A13: • Plan to NON-BRAND benchmarks: Sleephoria non-brand ACoS 31.5%, CVR 10.6%, CPC $2.24 (its blended figures lean on branded search at 14% ACoS, which CooLinens will not have).
... A28: Sources: Sellerboard (Ecotero account), Ecotero command center (ppc_* / traffic_* tools, products 45, 48, 69), DataDive niches & Rank Radar (read-only), team SOPs 06/12–19/22/23/28–30/32/33 + config/thresholds.yml in this repo. No live campaign was changed.

Sheet Economics
A1: CooLinens unit economics & bid ceilings (PROVISIONAL spine — SOP-22 P2.3 / rule M1)
A2: Blue = inputs. Price from Ali Muhammad's 6 Oct launch note; FBA fee & COGS from Sellerboard (Ecotero) 8 Oct 2026; referral 15%. Tag PROVISIONAL until per-variation margin lands (no fee data in command center yet).
A4: Input | B4: Value | C4: Source / rationale
A5: Launch CVR (base) | B5: 0.09 | C5: Sleephoria non-brand CVR 10.6% (Dec-25→Oct-26); Sep-26 at $77.58 ASP = 9.4%. New listing with 24 Vine reviews → 9% base.
A6: Launch CVR (downside) | B6: 0.06 | C6: Sleephoria Oct-26 with stockouts = 6.2%; market SQP CVR on cooling terms ≈ 3–4%.
A7: Refund + storage allowance ($/unit) | B7: 3.5 | C7: Sleephoria refund rate 5.4% lifetime; storage ~ $1/unit. Not in the per-unit fee estimate.
A8: Target ACoS factor (× BE) | B8: 0.5 | C8: SOP-22 rule M1: TargetACOS = 50% × BE_ACOS
A9: Max acceptable ACoS factor (× BE) | B9: 0.75 | C9: SOP-22 rule M1: MaxAccACOS = 75% × BE_ACOS
A10: Account reference Expected CPC | B10: 2.8 | C10: SOP-12/22: use $2.80 PROVISIONAL when no per-term Expected CPC exists
A11: Launch CPC premium (× Sleephoria hist CPC) | B11: 1.25 | C11: Sleephoria launch CPC was $4.87 vs $2.24 steady non-brand; new brand + TOS competition. Assumption.
A12: CPC floor | B12: 1.5 | C12: Assumption: below this, head-term exacts did not serve at Sleephoria/Decolure.
A13: Target purchase share at target rank | B13: 0.08 | C13: DSTR input. Market is fragmented (top-3 conversion share 4.2%); Sleephoria held 0.4–1.7% share at rank 11–45. 8% = launch headroom to out-sell the rank-10 incumbents (ad + organic). Assumption — calibrate after week 2.
A14: Default market purchase rate (purchases ÷ searches) | B14: 0.017 | C14: SQP Jul–Sep 2026 median across cooling terms (term-specific rates used where available).
A15: Capped-test / probe clicks (tranche 1) | B15: 50 | C15: SOP-33 P5 tranche 1 = 50 clicks (tranche 2 up to 100)
A16: Capped-test window (days) | B16: 14 | C16: SOP-22 WE-1 capped test over 14 days
... A18: Weekly envelope (declared) | B18: 1750 | C18: Declared envelope for the batch-1 plan; G7: budgets must sum ≤ 110% of envelope.
A20: Per-size economics
A21: Size | B21: Price | C21: Referral % | D21: Referral $ | E21: FBA fee | F21: COGS (landed) | G21: Allowance | H21: Margin / order | I21: BE ACoS | J21: Target ACoS | K21: Max acc. ACoS | L21: Max profitable CPC (base CVR) | M21: Max profitable CPC (downside CVR) | N21: Target CPC (base CVR) | O21: Margin class | P21: FBA stock 8 Oct | Q21: Stock share | R21: Sleephoria units share L90D | S21: Sleephoria NP/unit L90D
A22: Twin | B22: 62.99 | C22: 0.15 | D22: =B22*C22 -> 9.4485 | E22: 7.9 | F22: 19.94 | G22: =Economics!$B$7 -> 3.5 | H22: =B22-D22-E22-F22-G22 -> 22.2015 | I22: =IF(B22>0,H22/B22,0) -> 0.35246071 | J22: =I22*Economics!$B$8 -> 0.17623035 | K22: =I22*Economics!$B$9 -> 0.26434553 | L22: =H22*Economics!$B$5 -> 1.998135 | M22: =H22*Economics!$B$6 -> 1.33209 | N22: =B22*J22*Economics!$B$5 -> 0.9990675 | O22: =IF(H22<6,"THIN",IF(H22<=15,"STANDARD","RICH")) -> RICH | P22: 387 | Q22: =P22/SUM($P$22:$P$26) -> 0.10386473 | R22: 0.115 | S22: 15.69
A23: Full | B23: 67.99 | C23: 0.15 | D23: =B23*C23 -> 10.1985 | E23: 8.31 | F23: 24.61 | G23: =Economics!$B$7 -> 3.5 | H23: =B23-D23-E23-F23-G23 -> 21.3715 | I23: =IF(B23>0,H23/B23,0) -> 0.31433299 | J23: =I23*Economics!$B$8 -> 0.1571665 | K23: =I23*Economics!$B$9 -> 0.23574974 | L23: =H23*Economics!$B$5 -> 1.923435 | M23: =H23*Economics!$B$6 -> 1.28229 | N23: =B23*J23*Economics!$B$5 -> 0.9617175 | O23: =IF(H23<6,"THIN",IF(H23<=15,"STANDARD","RICH")) -> RICH | P23: 530 | Q23: =P23/SUM($P$22:$P$26) -> 0.14224369 | R23: 0.139 | S23: 10.38
A24: Queen | B24: 79.99 | C24: 0.15 | D24: =B24*C24 -> 11.9985 | E24: 8.5 | F24: 25.88 | G24: =Economics!$B$7 -> 3.5 | H24: =B24-D24-E24-F24-G24 -> 30.1115 | I24: =IF(B24>0,H24/B24,0) -> 0.37644081 | J24: =I24*Economics!$B$8 -> 0.1882204 | K24: =I24*Economics!$B$9 -> 0.2823306 | L24: =H24*Economics!$B$5 -> 2.710035 | M24: =H24*Economics!$B$6 -> 1.80669 | N24: =B24*J24*Economics!$B$5 -> 1.3550175 | O24: =IF(H24<6,"THIN",IF(H24<=15,"STANDARD","RICH")) -> RICH | P24: 1541 | Q24: =P24/SUM($P$22:$P$26) -> 0.41358025 | R24: 0.343 | S24: 11.68
A25: King | B25: 84.99 | C25: 0.15 | D25: =B25*C25 -> 12.7485 | E25: 8.9 | F25: 30.02 | G25: =Economics!$B$7 -> 3.5 | H25: =B25-D25-E25-F25-G25 -> 29.8215 | I25: =IF(B25>0,H25/B25,0) -> 0.35088246 | J25: =I25*Economics!$B$8 -> 0.17544123 | K25: =I25*Economics!$B$9 -> 0.26316184 | L25: =H25*Economics!$B$5 -> 2.683935 | M25: =H25*Economics!$B$6 -> 1.78929 | N25: =B25*J25*Economics!$B$5 -> 1.3419675 | O25: =IF(H25<6,"THIN",IF(H25<=15,"STANDARD","RICH")) -> RICH | P25: 873 | Q25: =P25/SUM($P$22:$P$26) -> 0.23429952 | R25: 0.29 | S25: 15.03
A26: Cal King | B26: 86.99 | C26: 0.15 | D26: =B26*C26 -> 13.0485 | E26: 8.73 | F26: 31.62 | G26: =Economics!$B$7 -> 3.5 | H26: =B26-D26-E26-F26-G26 -> 30.0915 | I26: =IF(B26>0,H26/B26,0) -> 0.34591907 | J26: =I26*Economics!$B$8 -> 0.17295954 | K26: =I26*Economics!$B$9 -> 0.2594393 | L26: =H26*Economics!$B$5 -> 2.708235 | M26: =H26*Economics!$B$6 -> 1.80549 | N26: =B26*J26*Economics!$B$5 -> 1.3541175 | O26: =IF(H26<6,"THIN",IF(H26<=15,"STANDARD","RICH")) -> RICH | P26: 395 | Q26: =P26/SUM($P$22:$P$26) -> 0.10601181 | R26: 0.114 | S26: 19.59
A28: Notes
A29: BE ACoS here (≈31–38%) is higher than Sleephoria's command-center figure (~31%) only because it uses today's list prices; Sleephoria at the same $79.99/$84.99 has the same math.
A30: Margin class RICH (> $15/order) on every size → THIN-margin CPC cap (margin ÷ 3) does not apply.
A31: Ceiling read (SOP-23): Expected CPC ÷ max profitable CPC ≤0.8 SAFE · 0.8–1.0 AT-CEILING · 1.0–1.5 PUSH-ONLY · >1.5 UNJUSTIFIABLE outside a sized push.
A32: Full has the thinnest margin and the lowest Sleephoria NP/unit → do not lead with Full; King is the best Sleephoria profit engine but its keywords are the most expensive (CPC $3.3–4.9).

Sheet Batch1_Plan
A1: Batch 1 — Day-0 single-keyword SP Exact plan (go-live 15 Oct 2026)
A2: SOP-22 P3: one campaign / one keyword / one ad group · fixed bids · TOS/ROS/PP modifiers 0 · advertised SKU = D2 preferred variation. Blue = inputs; black = formulas (edit Economics inputs to re-size).
A4: # | B4: Keyword | C4: Type | D4: Sibling status (SOP-33) | E4: Objective | F4: Campaign name (SOP-12 App. A) | G4: Advertised SKU (D2) | H4: ASIN | I4: Size | J4: Wk SV (6 Oct) | K4: DD monthly SV | L4: SV tier | M4: Rivals organic top-10 | N4: Ad share of traffic | O4: Sleephoria org rank | P4: Decolure org rank | Q4: Sleephoria hist clicks | R4: Sleephoria hist CPC | S4: Sleephoria hist CVR | T4: Sleephoria hist ACoS | U4: Expected CPC = start bid | V4: Market purchase rate | W4: DSTR (orders/day) | X4: CVR used | Y4: Clicks/day — Day 0 (probe/cap) | Z4: Daily budget — Day 0 | AA4: Clicks/day — post-declaration | AB4: Daily budget — post-declaration | AC4: Price | AD4: Projected ACoS | AE4: BE ACoS | AF4: Weekly loss ceiling (post-decl.) | AG4: Max profitable CPC | AH4: Ceiling read | AI4: Target organic rank | AJ4: Rationale / evidence
A5: 1 | B5: cooling sheets queen | C5: Ranking | D5: Shared root — Sleephoria live, organic 35–45 (not owner-grade) | E5: Ranking | F5: CLCS4-SP-cooling sheets queen-VHSV-Exact-Rank-Fix-Q-GRAPHITE | G5: CL-COOLING-SHEET-QUEEN-GRAPHITE | H5: B0H6K1MKQW | I5: Queen | J5: 7904 | K5: 41329 | L5: VHSV | M5: 4 | N5: 0.451 | O5: 45 | P5: 110 | Q5: 2552 | R5: 2.24 | S5: 0.1187 | T5: 0.289 | U5: =IF(R5="",Economics!$B$10,MAX(Economics!$B$12,R5*Economics!$B$11)) -> 2.8 | V5: 0.0175 | W5: =IF(C5="Ranking",J5/7*V5*Economics!$B$13,0) -> 1.5808 | X5: =Economics!$B$5 -> 0.09 | Y5: =Economics!$B$15/Economics!$B$16 -> 3.5714286 | Z5: =MAX(Economics!$B$17,Y5*U5) -> 10 | AA5: =IF(C5="Ranking",MAX(W5/X5,Economics!$B$15/Economics!$B$16),Economics!$B$15/Economics!$B$16) -> 17.564444 | AB5: =MAX(Economics!$B$17,AA5*U5) -> 49.180444 | AC5: =INDEX(Economics!$B$22:$B$26,MATCH(I5,Economics!$A$22:$A$26,0)) -> 79.99 | AD5: =U5/(AC5*X5) -> 0.38893751 | AE5: =INDEX(Economics!$I$22:$I$26,MATCH(I5,Economics!$A$22:$A$26,0)) -> 0.37644081 | AF5: =MAX(0,(AD5-AE5)*AA5*7*X5*AC5) -> 11.061297 | AG5: =INDEX(Economics!$L$22:$L$26,MATCH(I5,Economics!$A$22:$A$26,0)) -> 2.710035 | AH5: =IF(U5/AG5<=0.8,"SAFE",IF(U5/AG5<=1,"AT-CEILING",IF(U5/AG5<=1.5,"PUSH-ONLY","UNJUSTIFIABLE"))) -> PUSH-ONLY | AI5: 10 | AJ5: Largest size term (DD 41.3k/mo). Sleephoria 28.9% ACoS / 11.9% CVR here — proven converter. Sleephoria fell from #5 to 35–45 → open gap.
A6: 2 | B6: queen sheets cooling | C6: Ranking | D6: Shared root — Sleephoria organic 69 | E6: Ranking | F6: CLCS4-SP-queen sheets cooling-HSV-Exact-Rank-Fix-Q-GRAPHITE | G6: CL-COOLING-SHEET-QUEEN-GRAPHITE | H6: B0H6K1MKQW | I6: Queen | J6: 1212 | K6: 7935 | L6: HSV | M6: 2 | N6: 0.365 | O6: 69 | P6: 127 | Q6: 55 | R6: 2.42 | S6: 0.0909 | T6: 0.37 | U6: =IF(R6="",Economics!$B$10,MAX(Economics!$B$12,R6*Economics!$B$11)) -> 3.025 | V6: 0.0307 | W6: =IF(C6="Ranking",J6/7*V6*Economics!$B$13,0) -> 0.42523886 | X6: =Economics!$B$5 -> 0.09 | Y6: =Economics!$B$15/Economics!$B$16 -> 3.5714286 | Z6: =MAX(Economics!$B$17,Y6*U6) -> 10.803571 | AA6: =IF(C6="Ranking",MAX(W6/X6,Economics!$B$15/Economics!$B$16),Economics!$B$15/Economics!$B$16) -> 4.7248762 | AB6: =MAX(Economics!$B$17,AA6*U6) -> 14.29275 | AC6: =INDEX(Economics!$B$22:$B$26,MATCH(I6,Economics!$A$22:$A$26,0)) -> 79.99 | AD6: =U6/(AC6*X6) -> 0.42019141 | AE6: =INDEX(Economics!$I$22:$I$26,MATCH(I6,Economics!$A$22:$A$26,0)) -> 0.37644081 | AF6: =MAX(0,(AD6-AE6)*AA6*7*X6*AC6) -> 10.417194 | AG6: =INDEX(Economics!$L$22:$L$26,MATCH(I6,Economics!$A$22:$A$26,0)) -> 2.710035 | AH6: =IF(U6/AG6<=0.8,"SAFE",IF(U6/AG6<=1,"AT-CEILING",IF(U6/AG6<=1.5,"PUSH-ONLY","UNJUSTIFIABLE"))) -> PUSH-ONLY | AI6: 10 | AJ6: DD ~7.9k/mo; SQP purchase rate 3.1% (highest of queen terms). No sibling in top 30.
A7: 3 | B7: queen cooling sheets | C7: Ranking | D7: Shared root — Sleephoria organic 45, Decolure 130 | E7: Ranking | F7: CLCS4-SP-queen cooling sheets-HSV-Exact-Rank-Fix-Q-GRAPHITE | G7: CL-COOLING-SHEET-QUEEN-GRAPHITE | H7: B0H6K1MKQW | I7: Queen | J7: 1127 | K7: 6994 | L7: HSV | M7: 2 | N7: 0.367 | O7: 45 | P7: 130 | Q7: 78 | R7: 2.38 | S7: 0.1282 | T7: 0.23 | U7: =IF(R7="",Economics!$B$10,MAX(Economics!$B$12,R7*Economics!$B$11)) -> 2.975 | V7: 0.0288 | W7: =IF(C7="Ranking",J7/7*V7*Economics!$B$13,0) -> 0.370944 | X7: =Economics!$B$5 -> 0.09 | Y7: =Economics!$B$15/Economics!$B$16 -> 3.5714286 | Z7: =MAX(Economics!$B$17,Y7*U7) -> 10.625 | AA7: =IF(C7="Ranking",MAX(W7/X7,Economics!$B$15/Economics!$B$16),Economics!$B$15/Economics!$B$16) -> 4.1216 | AB7: =MAX(Economics!$B$17,AA7*U7) -> 12.26176 | AC7: =INDEX(Economics!$B$22:$B$26,MATCH(I7,Economics!$A$22:$A$26,0)) -> 79.99 | AD7: =U7/(AC7*X7) -> 0.4132461 | AE7: =INDEX(Economics!$I$22:$I$26,MATCH(I7,Economics!$A$22:$A$26,0)) -> 0.37644081 | AF7: =MAX(0,(AD7-AE7)*AA7*7*X7*AC7) -> 7.6445582 | AG7: =INDEX(Economics!$L$22:$L$26,MATCH(I7,Economics!$A$22:$A$26,0)) -> 2.710035 | AH7: =IF(U7/AG7<=0.8,"SAFE",IF(U7/AG7<=1,"AT-CEILING",IF(U7/AG7<=1.5,"PUSH-ONLY","UNJUSTIFIABLE"))) -> PUSH-ONLY | AI7: 10 | AJ7: DD 7.0k/mo; Sleephoria 23% ACoS / 12.8% CVR when served.
A8: 4 | B8: cooling bed sheets queen | C8: Ranking | D8: Shared root — Sleephoria organic 18 (borderline) | E8: Ranking | F8: CLCS4-SP-cooling bed sheets queen-HSV-Exact-Rank-Fix-Q-GRAPHITE | G8: CL-COOLING-SHEET-QUEEN-GRAPHITE | H8: B0H6K1MKQW | I8: Queen | J8: 598 | K8: 4766 | L8: HSV | M8: 4 | N8: 0.305 | O8: 18 | P8: 140 | Q8: 86 | R8: 1.96 | S8: 0.0465 | T8: 0.569 | U8: =IF(R8="",Economics!$B$10,MAX(Economics!$B$12,R8*Economics!$B$11)) -> 2.45 | V8: 0.0156 | W8: =IF(C8="Ranking",J8/7*V8*Economics!$B$13,0) -> 0.10661486 | X8: =Economics!$B$5 -> 0.09 | Y8: =Economics!$B$15/Economics!$B$16 -> 3.5714286 | Z8: =MAX(Economics!$B$17,Y8*U8) -> 10 | AA8: =IF(C8="Ranking",MAX(W8/X8,Economics!$B$15/Economics!$B$16),Economics!$B$15/Economics!$B$16) -> 3.5714286 | AB8: =MAX(Economics!$B$17,AA8*U8) -> 10 | AC8: =INDEX(Economics!$B$22:$B$26,MATCH(I8,Economics!$A$22:$A$26,0)) -> 79.99 | AD8: =U8/(AC8*X8) -> 0.34032032 | AE8: =INDEX(Economics!$I$22:$I$26,MATCH(I8,Economics!$A$22:$A$26,0)) -> 0.37644081 | AF8: =MAX(0,(AD8-AE8)*AA8*7*X8*AC8) -> 0 | AG8: =INDEX(Economics!$L$22:$L$26,MATCH(I8,Economics!$A$22:$A$26,0)) -> 2.710035 | AH8: =IF(U8/AG8<=0.8,"SAFE",IF(U8/AG8<=1,"AT-CEILING",IF(U8/AG8<=1.5,"PUSH-ONLY","UNJUSTIFIABLE"))) -> AT-CEILING | AI8: 15 | AJ8: DD 4.8k/mo; Decolure ranked top-10 here in 2025 on a $38 product. Watch CVR (Sleephoria 4.7% on 86 clicks).
A9: 5 | B9: queen size cooling sheets | C9: Ranking | D9: Shared root — Sleephoria organic 48 | E9: Ranking | F9: CLCS4-SP-queen size cooling sheets-HSV-Exact-Rank-Fix-Q-GRAPHITE | G9: CL-COOLING-SHEET-QUEEN-GRAPHITE | H9: B0H6K1MKQW | I9: Queen | J9: 572 | K9: 3107 | L9: HSV | M9: 2 | N9: 0.349 | O9: 48 | P9: 142 | Q9: 37 | R9: 3.05 | S9: 0.027 | T9: 1.413 | U9: =IF(R9="",Economics!$B$10,MAX(Economics!$B$12,R9*Economics!$B$11)) -> 3.8125 | V9: 0.0275 | W9: =IF(C9="Ranking",J9/7*V9*Economics!$B$13,0) -> 0.17977143 | X9: =Economics!$B$5 -> 0.09 | Y9: =Economics!$B$15/Economics!$B$16 -> 3.5714286 | Z9: =MAX(Economics!$B$17,Y9*U9) -> 13.616071 | AA9: =IF(C9="Ranking",MAX(W9/X9,Economics!$B$15/Economics!$B$16),Economics!$B$15/Economics!$B$16) -> 3.5714286 | AB9: =MAX(Economics!$B$17,AA9*U9) -> 13.616071 | AC9: =INDEX(Economics!$B$22:$B$26,MATCH(I9,Economics!$A$22:$A$26,0)) -> 79.99 | AD9: =U9/(AC9*X9) -> 0.52958009 | AE9: =INDEX(Economics!$I$22:$I$26,MATCH(I9,Economics!$A$22:$A$26,0)) -> 0.37644081 | AF9: =MAX(0,(AD9-AE9)*AA9*7*X9*AC9) -> 27.561625 | AG9: =INDEX(Economics!$L$22:$L$26,MATCH(I9,Economics!$A$22:$A$26,0)) -> 2.710035 | AH9: =IF(U9/AG9<=0.8,"SAFE",IF(U9/AG9<=1,"AT-CEILING",IF(U9/AG9<=1.5,"PUSH-ONLY","UNJUSTIFIABLE"))) -> PUSH-ONLY | AI9: 15 | AJ9: Gap term; Sleephoria wasted $113 here (1 order / 37 clicks) — start at Expected CPC, no TOS modifier.
A10: 6 | B10: cooling queen sheets | C10: Ranking | D10: Shared root — Sleephoria organic 24 | E10: Ranking | F10: CLCS4-SP-cooling queen sheets-HSV-Exact-Rank-Fix-Q-GRAPHITE | G10: CL-COOLING-SHEET-QUEEN-GRAPHITE | H10: B0H6K1MKQW | I10: Queen | J10: 592 | K10: 3027 | L10: HSV | M10: 2 | N10: 0.311 | O10: 24 | P10: 124 | Q10: 234 | R10: 2.95 | S10: 0.1111 | T10: 0.38 | U10: =IF(R10="",Economics!$B$10,MAX(Economics!$B$12,R10*Economics!$B$11)) -> 3.6875 | V10: 0.0186 | W10: =IF(C10="Ranking",J10/7*V10*Economics!$B$13,0) -> 0.12584229 | X10: =Economics!$B$5 -> 0.09 | Y10: =Economics!$B$15/Economics!$B$16 -> 3.5714286 | Z10: =MAX(Economics!$B$17,Y10*U10) -> 13.169643 | AA10: =IF(C10="Ranking",MAX(W10/X10,Economics!$B$15/Economics!$B$16),Economics!$B$15/Economics!$B$16) -> 3.5714286 | AB10: =MAX(Economics!$B$17,AA10*U10) -> 13.169643 | AC10: =INDEX(Economics!$B$22:$B$26,MATCH(I10,Economics!$A$22:$A$26,0)) -> 79.99 | AD10: =U10/(AC10*X10) -> 0.5122168 | AE10: =INDEX(Economics!$I$22:$I$26,MATCH(I10,Economics!$A$22:$A$26,0)) -> 0.37644081 | AF10: =MAX(0,(AD10-AE10)*AA10*7*X10*AC10) -> 24.436625 | AG10: =INDEX(Economics!$L$22:$L$26,MATCH(I10,Economics!$A$22:$A$26,0)) -> 2.710035 | AH10: =IF(U10/AG10<=0.8,"SAFE",IF(U10/AG10<=1,"AT-CEILING",IF(U10/AG10<=1.5,"PUSH-ONLY","UNJUSTIFIABLE"))) -> PUSH-ONLY | AI10: 15 | AJ10: Sleephoria 38% ACoS / 11.1% CVR (234 clicks) — growth-acceptable.
A11: 7 | B11: cooling sheet set | C11: Discovery (capped) | D11: Weakly held — Sleephoria organic 38 | E11: Discovery | F11: CLCS4-SP-cooling sheet set-HSV-Exact-Disc-Fix-Q-GRAPHITE | G11: CL-COOLING-SHEET-QUEEN-GRAPHITE | H11: B0H6K1MKQW | I11: Queen | J11: 337 | K11: 3289 | L11: HSV | M11: 3 | N11: 0.415 | O11: 38 | P11: 135 | Q11: 61 | R11: 2.35 | S11: 0.0984 | T11: 0.302 | U11: =IF(R11="",Economics!$B$10,MAX(Economics!$B$12,R11*Economics!$B$11)) -> 2.9375 | V11: 0.0066 | W11: =IF(C11="Ranking",J11/7*V11*Economics!$B$13,0) -> 0 | X11: =Economics!$B$5 -> 0.09 | Y11: =Economics!$B$15/Economics!$B$16 -> 3.5714286 | Z11: =MAX(Economics!$B$17,Y11*U11) -> 10.491071 | AA11: =IF(C11="Ranking",MAX(W11/X11,Economics!$B$15/Economics!$B$16),Economics!$B$15/Economics!$B$16) -> 3.5714286 | AB11: =MAX(Economics!$B$17,AA11*U11) -> 10.491071 | AC11: =INDEX(Economics!$B$22:$B$26,MATCH(I11,Economics!$A$22:$A$26,0)) -> 79.99 | AD11: =U11/(AC11*X11) -> 0.40803712 | AE11: =INDEX(Economics!$I$22:$I$26,MATCH(I11,Economics!$A$22:$A$26,0)) -> 0.37644081 | AF11: =MAX(0,(AD11-AE11)*AA11*7*X11*AC11) -> 5.686625 | AG11: =INDEX(Economics!$L$22:$L$26,MATCH(I11,Economics!$A$22:$A$26,0)) -> 2.710035 | AH11: =IF(U11/AG11<=0.8,"SAFE",IF(U11/AG11<=1,"AT-CEILING",IF(U11/AG11<=1.5,"PUSH-ONLY","UNJUSTIFIABLE"))) -> PUSH-ONLY | AI11: 20 | AJ11: Set-intent term matches 4-piece; Sleephoria 30.2% ACoS. Premium rival Breescape #10.
A12: 8 | B12: best cooling sheets | C12: Discovery (capped) | D12: Weakly held — Sleephoria organic 34 | E12: Discovery | F12: CLCS4-SP-best cooling sheets-HSV-Exact-Disc-Fix-Q-GRAPHITE | G12: CL-COOLING-SHEET-QUEEN-GRAPHITE | H12: B0H6K1MKQW | I12: Queen | J12: 259 | K12: 2716 | L12: HSV | M12: 4 | N12: 0.253 | O12: 34 | P12: 140 | Q12: 211 | R12: 1.32 | S12: 0.0521 | T12: 0.373 | U12: =IF(R12="",Economics!$B$10,MAX(Economics!$B$12,R12*Economics!$B$11)) -> 1.65 | V12: 0.0056 | W12: =IF(C12="Ranking",J12/7*V12*Economics!$B$13,0) -> 0 | X12: =Economics!$B$5 -> 0.09 | Y12: =Economics!$B$15/Economics!$B$16 -> 3.5714286 | Z12: =MAX(Economics!$B$17,Y12*U12) -> 10 | AA12: =IF(C12="Ranking",MAX(W12/X12,Economics!$B$15/Economics!$B$16),Economics!$B$15/Economics!$B$16) -> 3.5714286 | AB12: =MAX(Economics!$B$17,AA12*U12) -> 10 | AC12: =INDEX(Economics!$B$22:$B$26,MATCH(I12,Economics!$A$22:$A$26,0)) -> 79.99 | AD12: =U12/(AC12*X12) -> 0.22919532 | AE12: =INDEX(Economics!$I$22:$I$26,MATCH(I12,Economics!$A$22:$A$26,0)) -> 0.37644081 | AF12: =MAX(0,(AD12-AE12)*AA12*7*X12*AC12) -> 0 | AG12: =INDEX(Economics!$L$22:$L$26,MATCH(I12,Economics!$A$22:$A$26,0)) -> 2.710035 | AH12: =IF(U12/AG12<=0.8,"SAFE",IF(U12/AG12<=1,"AT-CEILING",IF(U12/AG12<=1.5,"PUSH-ONLY","UNJUSTIFIABLE"))) -> SAFE | AI12: 20 | AJ12: Comparison shoppers; REST #17. Sleephoria 37% ACoS / 5.2% CVR → keep capped.
A13: 9 | B13: cooling bedding | C13: Discovery (capped) | D13: Unowned — neither sibling ranks | E13: Discovery | F13: CLCS4-SP-cooling bedding-HSV-Exact-Disc-Fix-Q-GRAPHITE | G13: CL-COOLING-SHEET-QUEEN-GRAPHITE | H13: B0H6K1MKQW | I13: Queen | J13: 494 | K13: 4862 | L13: HSV | M13: 0 | N13: 0.406 | O13: NR | P13: NR | Q13: 2 | U13: =IF(R13="",Economics!$B$10,MAX(Economics!$B$12,R13*Economics!$B$11)) -> 2.8 | V13: =Economics!$B$14 -> 0.017 | W13: =IF(C13="Ranking",J13/7*V13*Economics!$B$13,0) -> 0 | X13: =Economics!$B$5 -> 0.09 | Y13: =Economics!$B$15/Economics!$B$16 -> 3.5714286 | Z13: =MAX(Economics!$B$17,Y13*U13) -> 10 | AA13: =IF(C13="Ranking",MAX(W13/X13,Economics!$B$15/Economics!$B$16),Economics!$B$15/Economics!$B$16) -> 3.5714286 | AB13: =MAX(Economics!$B$17,AA13*U13) -> 10 | AC13: =INDEX(Economics!$B$22:$B$26,MATCH(I13,Economics!$A$22:$A$26,0)) -> 79.99 | AD13: =U13/(AC13*X13) -> 0.38893751 | AE13: =INDEX(Economics!$I$22:$I$26,MATCH(I13,Economics!$A$22:$A$26,0)) -> 0.37644081 | AF13: =MAX(0,(AD13-AE13)*AA13*7*X13*AC13) -> 2.249125 | AG13: =INDEX(Economics!$L$22:$L$26,MATCH(I13,Economics!$A$22:$A$26,0)) -> 2.710035 | AH13: =IF(U13/AG13<=0.8,"SAFE",IF(U13/AG13<=1,"AT-CEILING",IF(U13/AG13<=1.5,"PUSH-ONLY","UNJUSTIFIABLE"))) -> PUSH-ONLY | AI13: 20 | AJ13: DD 4.9k/mo; 0 rivals in organic top 10. Uncontested.
A14: 10 | B14: hot sleepers must haves | C14: Discovery (capped) | D14: Unowned — Sleephoria organic 130 | E14: Discovery | F14: CLCS4-SP-hot sleepers must haves-HSV-Exact-Disc-Fix-Q-GRAPHITE | G14: CL-COOLING-SHEET-QUEEN-GRAPHITE | H14: B0H6K1MKQW | I14: Queen | J14: 463 | K14: 3837 | L14: HSV | M14: 0 | N14: 0.718 | O14: 130 | P14: NR | Q14: 2 | U14: =IF(R14="",Economics!$B$10,MAX(Economics!$B$12,R14*Economics!$B$11)) -> 2.8 | V14: 0.0056 | W14: =IF(C14="Ranking",J14/7*V14*Economics!$B$13,0) -> 0 | X14: =Economics!$B$5 -> 0.09 | Y14: =Economics!$B$15/Economics!$B$16 -> 3.5714286 | Z14: =MAX(Economics!$B$17,Y14*U14) -> 10 | AA14: =IF(C14="Ranking",MAX(W14/X14,Economics!$B$15/Economics!$B$16),Economics!$B$15/Economics!$B$16) -> 3.5714286 | AB14: =MAX(Economics!$B$17,AA14*U14) -> 10 | AC14: =INDEX(Economics!$B$22:$B$26,MATCH(I14,Economics!$A$22:$A$26,0)) -> 79.99 | AD14: =U14/(AC14*X14) -> 0.38893751 | AE14: =INDEX(Economics!$I$22:$I$26,MATCH(I14,Economics!$A$22:$A$26,0)) -> 0.37644081 | AF14: =MAX(0,(AD14-AE14)*AA14*7*X14*AC14) -> 2.249125 | AG14: =INDEX(Economics!$L$22:$L$26,MATCH(I14,Economics!$A$22:$A$26,0)) -> 2.710035 | AH14: =IF(U14/AG14<=0.8,"SAFE",IF(U14/AG14<=1,"AT-CEILING",IF(U14/AG14<=1.5,"PUSH-ONLY","UNJUSTIFIABLE"))) -> PUSH-ONLY | AI14: 20 | AJ14: DD 3.8k/mo; 0 rivals organic top 10, 72% ad traffic. Gift/listicle intent — test only.
A15: 11 | B15: cooling sheets | C15: Probe (sibling-owned) | D15: Sleephoria-owned — organic 11–18 | E15: Discovery | F15: CLCS4-SP-cooling sheets-VHSV-Exact-Disc-Fix-Q-GRAPHITE | G15: CL-COOLING-SHEET-QUEEN-GRAPHITE | H15: B0H6K1MKQW | I15: Queen | J15: 16968 | K15: 129480 | L15: VHSV | M15: 3 | N15: 0.509 | O15: 13 | P15: 132 | Q15: 485 | R15: 2.01 | S15: 0.0948 | T15: 0.295 | U15: =IF(R15="",Economics!$B$10,MAX(Economics!$B$12,R15*Economics!$B$11)) -> 2.5125 | V15: 0.0073 | W15: =IF(C15="Ranking",J15/7*V15*Economics!$B$13,0) -> 0 | X15: =Economics!$B$5 -> 0.09 | Y15: =Economics!$B$15/Economics!$B$16 -> 3.5714286 | Z15: =MAX(Economics!$B$17,Y15*U15) -> 10 | AA15: =IF(C15="Ranking",MAX(W15/X15,Economics!$B$15/Economics!$B$16),Economics!$B$15/Economics!$B$16) -> 3.5714286 | AB15: =MAX(Economics!$B$17,AA15*U15) -> 10 | AC15: =INDEX(Economics!$B$22:$B$26,MATCH(I15,Economics!$A$22:$A$26,0)) -> 79.99 | AD15: =U15/(AC15*X15) -> 0.34900196 | AE15: =INDEX(Economics!$I$22:$I$26,MATCH(I15,Economics!$A$22:$A$26,0)) -> 0.37644081 | AF15: =MAX(0,(AD15-AE15)*AA15*7*X15*AC15) -> 0 | AG15: =INDEX(Economics!$L$22:$L$26,MATCH(I15,Economics!$A$22:$A$26,0)) -> 2.710035 | AH15: =IF(U15/AG15<=0.8,"SAFE",IF(U15/AG15<=1,"AT-CEILING",IF(U15/AG15<=1.5,"PUSH-ONLY","UNJUSTIFIABLE"))) -> AT-CEILING | AJ15: Head term (DD 129k/mo). Capped probe only: collect CooLinens CVR for SOP-33 ceiling test; no ranking spend.
A16: 12 | B16: cooling bed sheets | C16: Probe (sibling-owned) | D16: Sleephoria-owned — organic 15–18 | E16: Discovery | F16: CLCS4-SP-cooling bed sheets-VHSV-Exact-Disc-Fix-Q-GRAPHITE | G16: CL-COOLING-SHEET-QUEEN-GRAPHITE | H16: B0H6K1MKQW | I16: Queen | J16: 3632 | K16: 21134 | L16: VHSV | M16: 4 | N16: 0.425 | O16: 18 | P16: 92 | Q16: 259 | R16: 2.45 | S16: 0.0772 | T16: 0.421 | U16: =IF(R16="",Economics!$B$10,MAX(Economics!$B$12,R16*Economics!$B$11)) -> 3.0625 | V16: 0.0074 | W16: =IF(C16="Ranking",J16/7*V16*Economics!$B$13,0) -> 0 | X16: =Economics!$B$5 -> 0.09 | Y16: =Economics!$B$15/Economics!$B$16 -> 3.5714286 | Z16: =MAX(Economics!$B$17,Y16*U16) -> 10.9375 | AA16: =IF(C16="Ranking",MAX(W16/X16,Economics!$B$15/Economics!$B$16),Economics!$B$15/Economics!$B$16) -> 3.5714286 | AB16: =MAX(Economics!$B$17,AA16*U16) -> 10.9375 | AC16: =INDEX(Economics!$B$22:$B$26,MATCH(I16,Economics!$A$22:$A$26,0)) -> 79.99 | AD16: =U16/(AC16*X16) -> 0.4254004 | AE16: =INDEX(Economics!$I$22:$I$26,MATCH(I16,Economics!$A$22:$A$26,0)) -> 0.37644081 | AF16: =MAX(0,(AD16-AE16)*AA16*7*X16*AC16) -> 8.811625 | AG16: =INDEX(Economics!$L$22:$L$26,MATCH(I16,Economics!$A$22:$A$26,0)) -> 2.710035 | AH16: =IF(U16/AG16<=0.8,"SAFE",IF(U16/AG16<=1,"AT-CEILING",IF(U16/AG16<=1.5,"PUSH-ONLY","UNJUSTIFIABLE"))) -> PUSH-ONLY | AJ16: DD 21k/mo. Capped probe only.
B17: TOTAL | Y17: =SUM(Y5:Y16) -> 42.857143 | Z17: =SUM(Z5:Z16) -> 129.64286 | AA17: =SUM(AA5:AA16) -> 58.553778 | AB17: =SUM(AB5:AB16) -> 173.94924 | AF17: =SUM(AF5:AF16) -> 100.1178
B19: Weekly budget — Day 0 | C19: =Z17*7 -> 907.5
B20: Weekly budget — post-declaration | C20: =AB17*7 -> 1217.6447
B21: Declared weekly envelope | C21: =Economics!$B$18 -> 1750
B22: G7 check: post-declaration budgets ≤ 110% of envelope | C22: =IF(C20<=1.1*C21,"PASS","FAIL — raise envelope or drop terms") -> PASS
B23: Projected weekly ad sales — post-declaration (clicks × CVR × price) | C23: =SUMPRODUCT(AA5:AA16,X5:X16,AC5:AC16)*7 -> 2950.7415
B24: Projected blended ACoS — post-declaration | C24: =IF(C23>0,C20/C23,0) -> 0.41265718
B25: Cross-check: Sleephoria launch-month spend/day (Oct-25) | C25: =608 -> 608
B26: Cross-check: Queen share of Sleephoria cooling spend (Cooling+Queen $8,873 ÷ Cooling $40,089) | C26: =8873/40089 -> 0.22133254
B27: Cross-check: Sleephoria-equivalent Queen spend/day | C27: =C25*C26 -> 134.57018
B28: Queen ranking rows — post-declaration $/day (this plan) | C28: =SUMIF(C5:C16,"Ranking",AB5:AB16) -> 112.52067
B31: Day 0: Ranking rows run at probe level (tranche 1 = 50 clicks over 14 days, bid = Expected CPC) until the SOP-33 owner declaration (target ~22 Oct). Post-declaration = DSTR ÷ CVR clicks/day (SOP-23 M2), floored at the probe rate.
B32: DSTR = weekly SV ÷ 7 × market purchase rate (SQP Jul–Sep 2026 where available) × target purchase share. Sleephoria empirical cross-check: top-10 in ~12 days at ~$790/day across ~100 campaigns, CPC ~$5, ACoS ~50% (with PBDD tailwind). If ranks have not moved by week 3, the SOP-23 sizing is too light — escalate, do not silently add spend.
B33: Placements: TOS / ROS / PP modifiers start at 0 (SOP-22 P3.9). First TOS raise only after ≥15 clicks/7d with TOS CVR > ROS CVR and CPA ≤ ceiling, ≤ +20 pts per move, one move per 14 days (thresholds.yml W6). Off-Amazon: exclude (Sleephoria $661, 0 orders).
B34: Budgets: Sleephoria's branded and King ranking campaigns ran out of budget before noon — check D6 (ranking campaigns must not cap before 20:00) daily during week 1; budget relief ≤ +25% once/week is pre-authorised.
B35: Halo: none on day 0. Sleephoria colour test: Graphite 13% CVR vs 3.7% for all other colours → hero-only. Re-point to Queen Cool Grey (B0H6JWNCK3, 280 FBA) only if Queen Graphite DOH < 21.
B36: Not on day 0 (SOP-22 P3.4/F1): broad, phrase, auto, SB/SBV/SD, PAT/conquest, own-brand defence (no branded search yet).

Sheet Preferred_Backup
A1: Preferred (D2) and backup advertised variation per size
A2: Evidence: Sleephoria & Decolure colour demand by unit share (hero-only ads distort per-SKU CVR/NP), CooLinens FBA 8 Oct 2026. Switch to backup when preferred cover < 21 days (trailing-7d velocity) or below the unit floor with nothing receivable in 10 days; switch back at ≥ 45 days cover.
A4: size | B4: preferred_sku | C4: preferred_asin | D4: preferred_fba_2026-10-08 | E4: preferred_inbound | F4: proj_vel_u_day (SL analogue, hero) | G4: preferred_DOH_base | H4: preferred_DOH_hero_x1.5 | I4: backup_sku | J4: backup_asin | K4: backup_fba_2026-10-08 | L4: backup_inbound | M4: backup_DOH_if_it_inherits_hero_velocity | N4: SL_share_in_size_pref_pct | O4: SL_share_in_size_backup_pct | P4: BM_share_in_size_pref_pct | Q4: BM_share_in_size_backup_pct | R4: switch_to_backup_when | S4: switch_back_when | T4: rationale
A5: Queen | B5: CL-COOLING-SHEET-QUEEN-GRAPHITE | C5: B0H6K1MKQW | D5: 373 | E5: 0 | F5: 3.62 | G5: 103 | H5: 69 | I5: CL-COOLING-SHEET-QUEEN-COOL-GREY | J5: B0H6JWNCK3 | K5: 280 | L5: 0 | M5: 77 | N5: 20 | O5: 14 | P5: 25.6 | Q5: 14.8 | R5: preferred available FBA DOH < 21 at trailing-7d velocity OR preferred FBA < 76 units, with no inbound receivable within 10 days | S5: preferred available FBA >= 45 DOH (received, not just shipped) | T5: Graphite = #1 Queen colour in SL (20% of Queen units, 1,021 u) and BM (BM-QUEEN-GRAPHITE-GREY #1 SKU, 25.6% of BM Queen); deepest CL stock. Cool Grey = #2 in both brands (SL 14%, BM 14.8%) and 2nd-deepest CL stock. Both colours carry ad-landing traffic so their unit-session % (2.4-2.8%) understates true preference.
A6: King | B6: CL-COOLING-SHEET-KING-GRAPHITE | C6: B0H6JXBD3K | D6: 174 | E6: 0 | F6: 2.31 | G6: 75 | H6: 50 | I6: CL-COOLING-SHEET-KING-COOL-GREY | J6: B0H6K77BRL | K6: 146 | L6: 0 | M6: 63 | N6: 19.9 | O6: 12.1 | P6: 17.5 | Q6: 19.5 | R6: preferred available FBA DOH < 21 at trailing-7d velocity OR preferred FBA < 49 units, with no inbound receivable within 10 days | S6: preferred available FBA >= 45 DOH (received, not just shipped) | T6: Graphite #1 King colour SL (19.9%, 26.5% in Jul-Oct 2026) and in BM (17.5%); Cool Grey #2 in SL (12.1%) and #1 in BM (19.5%). CL King Light Grey (#3 SL, best King CVR 6.6%) has only 42 units, too thin for a backup.
A7: CalKing | B7: CL-COOLING-SHEET-CAL-KING-GRAPHITE | C7: B0H6JV73R5 | D7: 66 | E7: 0 | F7: 0.53 | G7: 124 | H7: 82 | I7: CL-COOLING-SHEET-CAL-KING-MIDNIGHT-BLACK | J7: B0H6JZG4W5 | K7: 42 | L7: 0 | M7: 79 | N7: 20.8 | O7: 9.2 | P7: 14.6 | Q7: 11.9 | R7: preferred available FBA DOH < 21 at trailing-7d velocity OR preferred FBA < 15 units, with no inbound receivable within 10 days | S7: preferred available FBA >= 45 DOH (received, not just shipped) | T7: Graphite #1 Cal King in SL (20.8%) and BM (14.6%). Cool Grey is #2 by demand (SL 13.3%, BM 16.2%) but CL holds only 24 units; Midnight Black (SL 9.2%, BM 11.9%, CVR 5.1%) has 42 units, so it is the stock-feasible backup; Cool Grey is tertiary.
A8: Full | B8: CL-COOLING-SHEET-FULL-COOL-GREY | C8: B0H6K4KPGJ | D8: 90 | E8: 0 | F8: 0.77 | G8: 117 | H8: 78 | I8: CL-COOLING-SHEET-FULL-GRAPHITE | J8: B0H6K1C7N1 | K8: 54 | L8: 0 | M8: 70 | N8: 16.5 | O8: 10.9 | P8: 12.5 | Q8: 14.2 | R8: preferred available FBA DOH < 21 at trailing-7d velocity OR preferred FBA < 16 units, with no inbound receivable within 10 days | S8: preferred available FBA >= 45 DOH (received, not just shipped) | T8: SL Full Cool Grey #1 (16.5%) but it was the advertised Full child; Graphite #2 SL (10.9%) and #1 BM Full (14.2%). In Jul-Oct 2026 Full colours are near-even (Midnight Black 13.2%, Cool Grey 10.1%, Graphite 9.6%). Preferred = Cool Grey on CL stock depth (90 vs 54); Graphite backup keeps the dark-grey hero family; Midnight Black (66 u) tertiary.
A9: Twin | B9: CL-COOLING-SHEET-TWIN-GRAPHITE | C9: B0H6K1TJWV | D9: 41 | E9: 0 | F9: 0.73 | G9: 56 | H9: 37 | I9: CL-COOLING-SHEET-TWIN-NAVY-BLUE | J9: B0H6K777C2 | K9: 35 | L9: 1 | M9: 48 | N9: 21.9 | O9: 16.3 | P9: 14.3 | Q9: 9.2 | R9: preferred available FBA DOH < 21 at trailing-7d velocity OR preferred FBA < 15 units, with no inbound receivable within 10 days | S9: preferred available FBA >= 45 DOH (received, not just shipped) | T9: Graphite #1 Twin in SL (21.9%) and BM (14.3%). Navy Blue #2 SL (16.3%, 19.6% in Jul-Oct 2026, best Twin CVR 7.4%). White (48 u) is a stock-deeper tertiary. Both Twin preferred and backup are thin (41/35 u).

Sheet Roadmap
A1: Phase roadmap & dated checkpoints
A2: Dates follow SOP-22 phases, SOP-33 arbitration and the SOP-32 BFCM window (Black Friday 27 Nov 2026, Cyber Monday 30 Nov 2026).
A4: Date | B4: Phase / gate | C4: Actions | D4: Owner | E4: Artifact (SOP)
A5: 8–10 Oct | B5: Pre-launch (P1, day −5) | C5: Strategy review (this file); MKL intake → G12 hygiene; G5 indexing check of all 12 terms on B0H6K1MKQW; G6 inventory; G11 sibling scan; event-window row; envelope G7. | D5: PPC Lead, launch operator | E5: Countersigned P1 checklist; blocker list
A6: 10 Oct | B6: Pre-launch | C6: PPC Lead rulings on Open_Items 1–4. SOP-33 finding opened on shared Queen/head roots; ceiling test (CooLinens margin × best family CVR × depth). | D6: PPC Lead, Brand owner | E6: S-series finding + composite card
A7: 13 Oct | B7: Pre-launch (P2) | C7: Clone Command Workbook; T0 cells AOV/Margin/BE/Target/MaxAcc/ExpectedCPC/Envelope = PROVISIONAL. Build day-0 bulk (12 campaigns). Pre-load walls: "coolinens" negative phrase in Sleephoria/Decolure discovery; sibling ASINs as negative ASIN in all CooLinens auto later. | D7: PPC Specialist | E7: Bulk file + T3 registry + T6 predictions (one per term)
A8: 15 Oct (Day 0) | B8: Phase 1 — Batch 1 | C8: 12 single-keyword exacts live on Queen Graphite; fixed bids = Expected CPC; modifiers 0; Queen ranking terms at probe tranche 1; daily D1–D7 checks start. | D8: PPC Specialist | E8: P3 standup record
A9: 20–22 Oct | B9: Phase 1 — Probe read | C9: Tranche 1 (50 clicks) read; extend to 100 clicks if CVR verdict needed. Six-step structural inspection (SOP-33 P7). Declaration: Queen roots → CooLinens (proposed); Sleephoria Queen terms → DEFEND AT FLOOR; walls confirmed same day. | D9: PPC Lead + Brand owner | E9: Declaration record (6 fields, 3 numeric re-arbitration triggers)
A10: 23 Oct | B10: Phase 1 — Ranking push | C10: Scale Queen exacts to post-declaration size (Batch1_Plan col AB). Sizing worksheet per push (SOP-23), 3-week horizon, stop-loss S-R5. | D10: PPC Specialist | E10: SOP-23 sizing worksheet
A11: 28 Oct | B11: BFCM T-30 | C11: BFCM event plan due (SOP-32): must NAME the CooLinens push, any Phase 2 standup, caps (baseline × lift), deal (recommend coupon / Prime-exclusive discount). | D11: PPC Lead | E11: Event plan v1
A12: 29 Oct | B12: Phase 1 — Batch 2 | C12: 14-day pass: Queen tail Class-2 consolidated exact (see Batch2_Candidates) funded from released budget + unspent envelope (envelope-neutral). MKL-driven additions. | D12: PPC Specialist | E12: P5 progression log
A13: 5 Nov | B13: Honeymoon exit (illustrative 21 days) | C13: No efficiency tightening before this date (SOP-22 P4.3). After: weekly steering per README cadence. | D13: PPC Lead | E13: T5 row
A14: 5–12 Nov | B14: Phase 2 entry (if P7 passes AND named in event plan) | C14: Auto close-match (low bid) + family broad (Queen root, down-only) + harvest register. If not named in the event plan → defer to ≥15 Dec. | D14: PPC Specialist | E14: P7 phase-advance record
A15: 9 Nov | B15: Sibling conflict | C15: Sleephoria Queen "wave 1" push was scheduled — must be cancelled or redirected per the declaration (cannot open on an undeclared/non-owned root, SOP-33 P3). | D15: PPC Lead | E15: Sleephoria plan amendment
... A22: Jan 2027+ | B22: Phase 3–4 (post handoff) | C22: PAT/conquest (PAT_Shortlist), SB brand defence (once branded search exists), SBV if SP CPC ≥ 1.5× ceiling. P10 11-field handoff packet → KDR weekly system. | D22: PPC Lead | E22: P10 packet, P12 co-sign

Sheet Launch_Targets
A1: Launch targets & stop rules
A2: Calibrated on Sleephoria's Oct-25 → Feb-26 curve, discounted for an off-season, new-brand start. SOP-22 §3 launch TACoS band 15–25% (F2).
A4: When | B4: Metric | C4: Target / rule | D4: Basis
A5: Wk 1–2 (15–28 Oct) | B5: Delivery | C5: Every batch-1 exact ≥ 15 clicks / 7 days; no ranking campaign out of budget before 20:00 (D6) | D5: SOP-22 G2; thresholds D6
A6: Wk 1–2 | B6: Conversion | C6: Queen Graphite CVR ≥ 8% on ≥ 50 probe clicks (verdict at 100) | D6: Sleephoria non-brand 10.6%; Sep-26 at $77.58 = 9.4%
A7: Wk 1–2 | B7: Efficiency | C7: Ranking terms ACoS ≤ 80% (ranking envelope 50–80%); blended ≤ 60% | D7: SOP-23 F1; Sleephoria launch 48.8%
A8: Wk 1–2 | B8: Rank | C8: "cooling sheets queen" organic ≤ 50 | D8: Sleephoria went 34–101 → 4 in ~10 days with ~$790/day
A9: Wk 3–4 (to 11 Nov) | B9: Rank | C9: Queen ranking cluster organic top 20 on ≥ 3 of 6 terms | D9: Batch1_Plan target ranks
A10: Wk 3–4 | B10: Volume / TACoS | C10: ≥ 10 units/day total; TACoS ≤ 30% | D10: Sleephoria month-1 TACoS 24.5%; off-season discount
A11: Wk 6 (26 Nov, pre-BFCM) | B11: Rank | C11: "cooling sheets queen" top 15; cluster top 20 on ≥ 5 of 6 | D11: —
A12: Wk 6 | B12: TACoS | C12: ≤ 25% (top of launch band) | D12: SOP-22 F2
A13: Wk 8–10 (Dec) | B13: Rank → taper | C13: Top 10 on target terms 2 consecutive weeks → TAPER ~10%/week | D13: SOP-23 S-R6 / M3
A14: Wk 8–10 | B14: Efficiency | C14: ACoS ≤ 40%; TACoS ≤ 15%; NP/unit ≥ $7 | D14: Sleephoria ad month 2–3: TACoS 15% → 10%, NP/unit $7.25 → $10.51
A15: Wk 12–16 (Jan–Feb) | B15: Seasonal context | C15: Jan is the demand trough (SQP index 0.55; purchases 0.48). Judge Jan on rank held + TACoS, not on unit growth. | D15: Historical_Analysis: Seasonality
... A20: Continuous | B20: Inventory | C20: Re-point the advertised child to the BACKUP when preferred cover < 21 days or below the unit floor (Preferred_Backup); G6 RED at ≤ 14 days | D20: Median cover 14 days before observed stockouts = 17.5 days; Sleephoria never re-pointed and lost peak season

Sheet Open_Items
A1: Open items & rulings required before go-live
A2: Owner decides; this file proposes.
A4: # | B4: Item | C4: Proposal | D4: Decision owner | E4: Impact
A5: 1 | B5: Sibling ownership of Queen roots (SOP-33) | C5: CooLinens = owner of Queen roots; Sleephoria keeps head/King/Twin/Cal King/hot-sleeper roots; Sleephoria Queen terms → DEFEND AT FLOOR | D5: PPC Lead + Brand owner | E5: Blocks ranking-size spend on Queen terms
A6: 2 | B6: Sleephoria Queen "wave 1" push scheduled 9 Nov | C6: Cancel or redirect to King cluster (Sleephoria King CVR 12–16%) | D6: PPC Lead | E6: Two pushes on one root = self-bidding
A7: 3 | B7: O3 FAR-BEHIND review gate (24 Vine reviews vs top-5 median far higher) | C7: Waive for launch: Sleephoria ranked top-10 with ~39 Vine reviews in Oct-25 | D7: PPC Lead | E7: SOP-23 bars ranking pushes otherwise
A8: 4 | B8: Mechanical CODE RED (launch TACoS) vs BFCM Recovery Mode precedence (AM-16) | C8: Record CODE RED; Event Mode governs the launch exacts named in the BFCM plan | D8: PPC Lead | E8: Needed before 28 Oct event plan
A9: 5 | B9: SOP-33 P3.5 "no new exact instance" on undeclared roots vs P5 probe / SOP-22 I-11 capped test | C9: Treat day-0 Queen exacts as the P5 probe (capped) | D9: PPC Lead | E9: Otherwise Queen terms cannot go live on 15 Oct
A10: 6 | B10: thresholds.yml vs v4.0 conflicts (G2 clicks 15 vs 10; harvest 3 vs 2 orders; TOS share floor 30% vs 20%; objective mix) | C10: Use SOP/v4.0 values for launch; thresholds.yml after handoff | D10: PPC Lead | E10: —
A11: 7 | B11: G5 indexing of all 12 batch-1 terms on B0H6K1MKQW | C11: Check this week (listing was made live 7 Oct for creator outreach) | D11: Launch operator | E11: Unindexed terms cannot enter batch 1
A12: 8 | B12: Fabric & claims (bamboo / Tencel / Coolmax / Q-Max?) | C12: Confirm; drives material keywords and negatives | D12: Brand owner | E12: Decolure "bamboo" terms failed (60–118% ACoS)
A13: 9 | B13: BFCM deal | C13: Coupon or Prime-exclusive discount on Queen/King Graphite | D13: Brand owner | E13: PBDD 2026: TACoS 7.7% with deal vs 17% without
A14: 10 | B14: CooLinens fee data missing in command center | C14: Load fees so BE ACoS can be computed natively (spine is PROVISIONAL) | D14: Data owner | E14: —
A15: 11 | B15: Creatives final by 15 Oct (Nat) | C15: Launch exacts only once main/secondary/A+ are final — price/image changes reset CVR reads (G9) | D15: Creative | E15: Sleephoria Aug–Sep price + image changes preceded CVR slide
A16: 12 | B16: Re-order for the Mar–Jul peak (no CooLinens inbound) | C16: Place PO sized to land by early March; prioritise Queen/King Graphite + Cool Grey and thin Twin/Cal King SKUs | D16: Brand owner / Ops | E16: Stockout at peak was the costliest event in Sleephoria history
A17: 13 | B17: MKL | C17: Merge on arrival (MKL_Intake); re-score relevancy against live listing; finalise Batch 2 + negatives | D17: PPC team | E17: G12 requires MKL refreshed within 30 days

Sheet Batch2_Candidates
A1: Batch 2 / Phase 2 candidates (from history + market data; finalise after MKL)
A2: Funded only from released budget + unspent envelope (SOP-22 P5). Graduation bar into exact = 3 orders (S-H1).
A4: Term / surface | B4: Bucket | C4: Historical evidence | D4: Proposed owner
A5: queen sheet set cooling | B5: Queen tail (Class-2 consolidated exact) | C5: Sleephoria 8.5% ACoS on 8 clicks / 3 orders; Decolure 52% | D5: CooLinens (if Queen declared)
A6: cooling queen sheet set | B6: Queen tail | C6: Low data at Sleephoria | D6: CooLinens
A7: queen cooling sheet set | B7: Queen tail | C7: Low data | D7: CooLinens
A8: cooling sheets queen size | B8: Queen tail | C8: Sleephoria 38.6% ACoS, 5.8% CVR (504 clicks) — bid conservatively | D8: CooLinens
A9: sheets queen cooling | B9: Queen tail | C9: Sleephoria org 35–41 | D9: CooLinens
A10: queen size sheets cooling | B10: Queen tail | C10: Sleephoria 36% ACoS | D10: CooLinens
A11: cool sheets queen | B11: Queen tail | C11: Sleephoria 22.8% ACoS, 15% CVR; Decolure 17.8% | D11: CooLinens
A12: queen bed sheets cooling | B12: Queen tail | C12: Sleephoria org 14, 35.5% ACoS → shared; probe only | D12: Sleephoria-held — probe
A13: cooling sheets queen deep pockets | B13: Queen tail | C13: Low data; Decolure 0 orders / 32 clicks | D13: CooLinens — capped
A14: cooling bedding set | B14: Discovery | C14: DD 1.3k/mo; 1 rival top 10 | D14: Unowned
A15: deep pocket cooling sheets | B15: Discovery | C15: Sleephoria 53.6% ACoS (23 clicks) | D15: Unowned — capped
... A22: <MKL additions> | B22: Pending MKL | C22: Insert MKL-scored terms here (relevancy + syntax tag required, G12) | D22: —

Sheet Negatives_Day1
A1: Negative & wall architecture (SOP-29) — pre-load at each structure event
A2: Exact campaigns get NO keyword pre-load. These apply to every broad / phrase / auto surface when Phase 2 opens, plus the sibling walls which go in on day 0.
A4: Term / ASIN set | B4: Match | C4: Scope | D4: Evidence / reason
A5: sleephoria | B5: Negative phrase | C5: All CooLinens discovery surfaces | D5: Sibling brand wall (SOP-29 P7)
A6: decolure | B6: Negative phrase | C6: All CooLinens discovery surfaces | D6: Sibling brand wall
A7: coolinens | B7: Negative phrase | C7: All Sleephoria + Decolure non-branded discovery (day 0) | D7: Reverse wall — stop siblings buying CooLinens brand traffic
A8: Sleephoria & Decolure child ASINs | B8: Negative ASIN | C8: CooLinens auto / PAT (when opened) | D8: Self-cannibalisation wall
A9: CooLinens child ASINs | B9: Negative ASIN | C9: Sleephoria + Decolure auto / PAT | D9: Reverse wall
A10: Declared CooLinens Queen roots (e.g. "cooling sheets queen") | B10: Negative exact (then phrase on root) | C10: Sleephoria discovery, same day as declaration | D10: SOP-33 wall; Sleephoria keeps model-specific variants at DEFEND AT FLOOR
A11: Graduated exacts | B11: Negative exact | C11: Every broad/phrase/auto that could serve them | D11: Isolation (SOP-12 P1.9)
A12: fan | B12: Negative phrase | C12: Discovery | D12: Sleephoria: "under the sheets cooling fan", "bed cooling fan under sheets" — 0 orders
A13: bed jet / bed cooling system | B13: Negative phrase | C13: Discovery | D13: Sleephoria 0–1 orders; device intent
A14: comforter | B14: Negative phrase | C14: Discovery | D14: Sleephoria + Decolure 0-order spend; separate Sleephoria product
A15: blanket | B15: Negative phrase | C15: Discovery | D15: Decolure $22, 0 orders
... A28: Watch, not negate: king cooling sheets, cold sheets, cold bed sheets, black cooling sheets, cooling bed set | B28: Bid down / TOS-only | C28: — | D28: Relevant but uneconomic at Sleephoria (60–78% ACoS); not CooLinens roots at launch
A30: Reactive negation (after launch): ≥ 2× target CPA spend, 0 orders, ≥ 10 clicks, 60-day window (thresholds.yml W4a; SOP-29 AM-1 — v4.0 value not specified). Never negate an in-window converter.

Sheet PAT_Shortlist
A1: PAT / conquest shortlist — Phase 3–4 only (NOT at launch, SOP-22 §5)
A2: SOP-16 S-C1: we must win ≥ 2 of price / rating / review count (or rival OOS). Enter CooLinens rating once Vine reviews settle (yellow cell).
A4: CooLinens Queen price | B4: 79.99
A5: CooLinens rating (enter) | B5: 4.4
A6: CooLinens review count (enter) | B6: 24
A8: Rival | B8: ASINs | C8: Rival price | D8: Rival rating | E8: Rival reviews | F8: We win price? | G8: We win rating? | H8: We win reviews? | I8: Wins (of 3) | J8: S-C1 gate | K8: Recommendation
A9: Breescape | B9: B0DSPZJKTB / B0DSPZ9151 / B0DSPZSVFL | C9: 149.99 | D9: 4.2 | E9: 593 | F9: =IF(C9="","",IF($B$4<C9,1,0)) -> 1 | G9: =IF(D9="","",IF($B$5>D9,1,0)) -> 1 | H9: =IF(E9="","",IF($B$6>E9,1,0)) -> 0 | I9: =SUM(F9:H9) -> 2 | J9: =IF(I9>=2,"PASS","FAIL") -> PASS | K9: Target
A10: Breescape (old parents) | B10: B0DSPYXPSP / B0DSQ26RH3 | C10: 139.99 | D10: 3.8 | E10: 72 | F10: =IF(C10="","",IF($B$4<C10,1,0)) -> 1 | G10: =IF(D10="","",IF($B$5>D10,1,0)) -> 1 | H10: =IF(E10="","",IF($B$6>E10,1,0)) -> 0 | I10: =SUM(F10:H10) -> 2 | J10: =IF(I10>=2,"PASS","FAIL") -> PASS | K10: Target
A11: REST Evercool+ | B11: B0BLYSGFRW / B0C56ZNQVQ / B0D9JJSNC5 / B0D25LDRPS | C11: 164.25 | D11: 4.3 | E11: 1133 | F11: =IF(C11="","",IF($B$4<C11,1,0)) -> 1 | G11: =IF(D11="","",IF($B$5>D11,1,0)) -> 1 | H11: =IF(E11="","",IF($B$6>E11,1,0)) -> 0 | I11: =SUM(F11:H11) -> 2 | J11: =IF(I11>=2,"PASS","FAIL") -> PASS | K11: Target
A12: SHEEX | B12: B00EWJS3PO | C12: 149 | D12: 4.5 | E12: 3254 | F12: =IF(C12="","",IF($B$4<C12,1,0)) -> 1 | G12: =IF(D12="","",IF($B$5>D12,1,0)) -> 0 | H12: =IF(E12="","",IF($B$6>E12,1,0)) -> 0 | I12: =SUM(F12:H12) -> 1 | J12: =IF(I12>=2,"PASS","FAIL") -> FAIL | K12: Target (price only — needs rating win)
A13: Cozy Bliss Premium (3pc, no flat) | B13: B0DMNQDZNB / B0DMNP5BC8 | C13: 89.99 | D13: 4.5 | E13: 436 | F13: =IF(C13="","",IF($B$4<C13,1,0)) -> 1 | G13: =IF(D13="","",IF($B$5>D13,1,0)) -> 0 | H13: =IF(E13="","",IF($B$6>E13,1,0)) -> 0 | I13: =SUM(F13:H13) -> 1 | J13: =IF(I13>=2,"PASS","FAIL") -> FAIL | K13: Target (3pc vs our 4pc)
A14: Dream Valley (3pc King) | B14: B0D3WMGX6P | C14: 99 | F14: =IF(C14="","",IF($B$4<C14,1,0)) -> 1 | G14: =IF(D14="","",IF($B$5>D14,1,0)) | H14: =IF(E14="","",IF($B$6>E14,1,0)) | I14: =SUM(F14:H14) -> 1 | J14: =IF(I14>=2,"PASS","FAIL") -> FAIL | K14: Target
A15: Degrees of Comfort PolarEdge Pro | B15: B0DYS4HVM3 | C15: 148.99 | D15: 4.3 | E15: 59 | F15: =IF(C15="","",IF($B$4<C15,1,0)) -> 1 | G15: =IF(D15="","",IF($B$5>D15,1,0)) -> 1 | H15: =IF(E15="","",IF($B$6>E15,1,0)) -> 0 | I15: =SUM(F15:H15) -> 2 | J15: =IF(I15>=2,"PASS","FAIL") -> PASS | K15: Target
A16: DOWNCOOL | B16: B0F93XMMQY | C16: 79.99 | D16: 4.1 | E16: 24 | F16: =IF(C16="","",IF($B$4<C16,1,0)) -> 0 | G16: =IF(D16="","",IF($B$5>D16,1,0)) -> 1 | H16: =IF(E16="","",IF($B$6>E16,1,0)) -> 0 | I16: =SUM(F16:H16) -> 1 | J16: =IF(I16>=2,"PASS","FAIL") -> FAIL | K16: Target
A17: Elegear | B17: B0GCHG6VG6 / B0GCHRGYZZ | C17: 89.99 | D17: 4.4 | E17: 129 | F17: =IF(C17="","",IF($B$4<C17,1,0)) -> 1 | G17: =IF(D17="","",IF($B$5>D17,1,0)) -> 0 | H17: =IF(E17="","",IF($B$6>E17,1,0)) -> 0 | I17: =SUM(F17:H17) -> 1 | J17: =IF(I17>=2,"PASS","FAIL") -> FAIL | K17: Target
A18: KARISSA MAE | B18: B0G1CSCQTB | C18: 119.99 | D18: 4.3 | E18: 472 | F18: =IF(C18="","",IF($B$4<C18,1,0)) -> 1 | G18: =IF(D18="","",IF($B$5>D18,1,0)) -> 1 | H18: =IF(E18="","",IF($B$6>E18,1,0)) -> 0 | I18: =SUM(F18:H18) -> 2 | J18: =IF(I18>=2,"PASS","FAIL") -> PASS | K18: Target
A19: Pillcase legacy listings | B19: B0FLDYD61P / B0GZ243WW5 | C19: 79 | D19: 2.5 | E19: 250 | F19: =IF(C19="","",IF($B$4<C19,1,0)) -> 0 | G19: =IF(D19="","",IF($B$5>D19,1,0)) -> 1 | H19: =IF(E19="","",IF($B$6>E19,1,0)) -> 0 | I19: =SUM(F19:H19) -> 1 | J19: =IF(I19>=2,"PASS","FAIL") -> FAIL | K19: Target
A20: TWK | B20: B0DYT2QWLC | C20: 62.1 | D20: 3.6 | E20: 131 | F20: =IF(C20="","",IF($B$4<C20,1,0)) -> 0 | G20: =IF(D20="","",IF($B$5>D20,1,0)) -> 1 | H20: =IF(E20="","",IF($B$6>E20,1,0)) -> 0 | I20: =SUM(F20:H20) -> 1 | J20: =IF(I20>=2,"PASS","FAIL") -> FAIL | K20: Test
A21: Brookstone fitted only | B21: B0CTKL3YJ2 | C21: 69.99 | D21: 4.1 | E21: 183 | F21: =IF(C21="","",IF($B$4<C21,1,0)) -> 0 | G21: =IF(D21="","",IF($B$5>D21,1,0)) -> 1 | H21: =IF(E21="","",IF($B$6>E21,1,0)) -> 0 | I21: =SUM(F21:H21) -> 1 | J21: =IF(I21>=2,"PASS","FAIL") -> FAIL | K21: Test (fitted-only shopper)
A22: Degrees of Comfort Coolmax | B22: B08YS6WZRR | C22: 28.49 | D22: 4.1 | E22: 7324 | F22: =IF(C22="","",IF($B$4<C22,1,0)) -> 0 | G22: =IF(D22="","",IF($B$5>D22,1,0)) -> 1 | H22: =IF(E22="","",IF($B$6>E22,1,0)) -> 0 | I22: =SUM(F22:H22) -> 1 | J22: =IF(I22>=2,"PASS","FAIL") -> FAIL | K22: AVOID
A23: Comfort Spaces | B23: B08R6MTY36 | C23: 28.49 | D23: 4.1 | E23: 23009 | F23: =IF(C23="","",IF($B$4<C23,1,0)) -> 0 | G23: =IF(D23="","",IF($B$5>D23,1,0)) -> 1 | H23: =IF(E23="","",IF($B$6>E23,1,0)) -> 0 | I23: =SUM(F23:H23) -> 1 | J23: =IF(I23>=2,"PASS","FAIL") -> FAIL | K23: AVOID
A24: Love's cabin | B24: B0DN1DVKH5 | C24: 37.99 | D24: 4.4 | E24: 1856 | F24: =IF(C24="","",IF($B$4<C24,1,0)) -> 0 | G24: =IF(D24="","",IF($B$5>D24,1,0)) -> 0 | H24: =IF(E24="","",IF($B$6>E24,1,0)) -> 0 | I24: =SUM(F24:H24) -> 0 | J24: =IF(I24>=2,"PASS","FAIL") -> FAIL | K24: AVOID
A25: Bedsure PureWoven | B25: B07YKCZHGK | C25: 64.59 | D25: 4.4 | E25: 64995 | F25: =IF(C25="","",IF($B$4<C25,1,0)) -> 0 | G25: =IF(D25="","",IF($B$5>D25,1,0)) -> 0 | H25: =IF(E25="","",IF($B$6>E25,1,0)) -> 0 | I25: =SUM(F25:H25) -> 0 | J25: =IF(I25>=2,"PASS","FAIL") -> FAIL | K25: AVOID
A26: CGK microfiber | B26: B01M16WBW1 | C26: 24.99 | D26: 4.5 | E26: 461815 | F26: =IF(C26="","",IF($B$4<C26,1,0)) -> 0 | G26: =IF(D26="","",IF($B$5>D26,1,0)) -> 0 | H26: =IF(E26="","",IF($B$6>E26,1,0)) -> 0 | I26: =SUM(F26:H26) -> 0 | J26: =IF(I26>=2,"PASS","FAIL") -> FAIL | K26: AVOID
A27: Pure Bamboo | B27: B07DZTQ4JC | C27: 109.99 | D27: 4.5 | E27: 21857 | F27: =IF(C27="","",IF($B$4<C27,1,0)) -> 1 | G27: =IF(D27="","",IF($B$5>D27,1,0)) -> 0 | H27: =IF(E27="","",IF($B$6>E27,1,0)) -> 0 | I27: =SUM(F27:H27) -> 1 | J27: =IF(I27>=2,"PASS","FAIL") -> FAIL | K27: Test only

Sheet Brand_Compare
A1: Sleephoria vs Decolure — what is repeatable
A2: Sellerboard (Ecotero account) + Ecotero command center. Sleephoria PPC data from 3 Oct 2025; Decolure PPC detail from Sep 2025 (launch Oct 2023 not in PPC data).
A4: Dimension | B4: Sleephoria 4PC | C4: Decolure 4PC | D4: Carry-over to CooLinens
A5: Price tier (Queen) | B5: $64.99 → $79.99 now | C5: ~$38 | D5: Sleephoria
A6: COGS / unit | B6: $26.31 | C6: $15.81 | D6: CooLinens = Sleephoria
A7: Amazon fees / unit | B7: $19.19 | C7: $19.13 | D7: Fees same $ → price drives profit
A8: NP / unit (L12M) | B8: $11.24 | C8: −$4.68 | D8: —
A9: TACoS (L12M) | B9: 9.6% | C9: 16.2% | D9: —
A10: Ad months 1–3 TACoS | B10: 24% → 15% → 10% | C10: 30% → 21% → 22% | D10: Sleephoria curve = template
A11: Ad months 1–3 margin | B11: 3% → 11% → 17% | C11: −12% → −4% → −21% | D11: —
A12: Non-brand ACoS / CVR / CPC | B12: 31.5% / 10.6% / $2.24 | C12: 51.6% / 6.6% / $1.36 | D12: Plan to Sleephoria non-brand
A13: Branded share of keyword ad sales | B13: ~40% at 14% ACoS | C13: small | D13: Not available to CooLinens at launch
A14: Best structure | B14: Single-kw exact per size on hero child + low-bid auto/broad harvest + branded defence | C14: Own-ASIN defence + LTSF autos (multi-product, blurs reads) | D14: Single-kw exact on hero child
A15: Worst structure | B15: Single-kw exact on "king cooling sheets" (57.9% ACoS, $4.86 CPC) | C15: Exact ranking pushes off-season (59.5% ACoS); broad 209% | D15: Gate King; no off-season rank buying
... A22: Size mix (units) | B22: Queen 42%, King 26%, Full 15%, Twin 9%, Cal King 8% | C22: Queen 48%, King 27%, Full 12%, Cal King 8%, Twin 6% | D22: Queen lead; CooLinens stock 41/23/14/11/10 matches

Sheet Sleephoria_Monthly
A1: Sleephoria Monthly
A2: Sellerboard (total business) + command-center PPC (7-day attribution, includes sibling-variation halo). PPC data starts 3 Oct 2025.
A4: Month | B4: Sales $ | C4: Units | D4: Orders | E4: Refund % | F4: Ad spend $ | G4: TACoS % | H4: COGS $ | I4: Amazon fees $ | J4: Net profit $ | K4: Margin % | L4: NP / unit | M4: ASP | N4: Sessions | O4: Unit session % | P4: LTSF $
A5: 2025-07 | B5: 1919.68 | C5: 32 | D5: 32 | E5: 0 | F5: 0 | G5: 0 | H5: -766.4 | I5: -276.46 | J5: -982.87 | K5: -51.2 | L5: -30.71 | M5: 59.99 | N5: 99 | O5: 32.32 | P5: 0
A6: 2025-08 | B6: 2849.53 | C6: 47 | D6: 44 | E6: 0 | F6: 0 | G6: 0 | H6: -1163.85 | I6: -876.2 | J6: 329.56 | K6: 11.57 | L6: 7.01 | M6: 60.63 | N6: 3834 | O6: 1.23 | P6: 0
A7: 2025-09 | B7: 4529.18 | C7: 82 | D7: 76 | E7: 4.9 | F7: 0 | G7: 0 | H7: -1887.11 | I7: -1576.26 | J7: 908.06 | K7: 20.05 | L7: 11.07 | M7: 55.23 | N7: 2887 | O7: 2.84 | P7: 0
A8: 2025-10 | B8: 72449.24 | C8: 1187 | D8: 1162 | E8: 2.8 | F8: 17635.66 | G8: 24.3 | H8: -29594.06 | I8: -21172.85 | J8: 2031.89 | K8: 2.8 | L8: 1.71 | M8: 61.04 | N8: 19407 | O8: 6.12 | P8: 0
A9: 2025-11 | B9: 76508.15 | C9: 1186 | D9: 1167 | E9: 5 | F9: 11480.77 | G9: 15 | H9: -29318.28 | I9: -24562.41 | J9: 8601.15 | K9: 11.24 | L9: 7.25 | M9: 64.51 | N9: 20061 | O9: 5.91 | P9: 0
A10: 2025-12 | B10: 63859.59 | C10: 1003 | D10: 988 | E10: 4.9 | F10: 6361.05 | G10: 10 | H10: -24581.8 | I10: -19960.92 | J10: 10539.7 | K10: 16.5 | L10: 10.51 | M10: 63.67 | N10: 15284 | O10: 6.56 | P10: 0
A11: 2026-01 | B11: 24375.16 | C11: 372 | D11: 358 | E11: 12.4 | F11: 1634.34 | G11: 6.7 | H11: -9915.07 | I11: -6942.95 | J11: 4013 | K11: 16.46 | L11: 10.79 | M11: 65.52 | N11: 9518 | O11: 3.91 | P11: -0.73
A12: 2026-02 | B12: 57344.39 | C12: 866 | D12: 855 | E12: 4.5 | F12: 3290.88 | G12: 5.7 | H12: -23646.14 | I12: -15919.36 | J12: 12784.12 | K12: 22.29 | L12: 14.76 | M12: 66.22 | N12: 16412 | O12: 5.28 | P12: -38.23
A13: 2026-03 | B13: 122501.4 | C13: 1873 | D13: 1845 | E13: 3.3 | F13: 5376.24 | G13: 4.4 | H13: -51381.79 | I13: -33656.62 | J13: 29172.14 | K13: 23.81 | L13: 15.58 | M13: 65.4 | N13: 59708 | O13: 3.14 | P13: -22.36
A14: 2026-04 | B14: 103299.26 | C14: 1586 | D14: 1568 | E14: 7.4 | F14: 4159.69 | G14: 4 | H14: -42411.57 | I14: -29396.96 | J14: 21419.36 | K14: 20.74 | L14: 13.51 | M14: 65.13 | N14: 63352 | O14: 2.5 | P14: -1.93
A15: 2026-05 | B15: 57946.17 | C15: 888 | D15: 871 | E15: 7.3 | F15: 4408.76 | G15: 7.6 | H15: -23704.74 | I15: -16611.15 | J15: 9986.32 | K15: 17.23 | L15: 11.25 | M15: 65.25 | N15: 22122 | O15: 4.01 | P15: 0
A16: 2026-06 | B16: 34284.34 | C16: 560 | D16: 548 | E16: 7.7 | F16: 4912.76 | G16: 14.3 | H16: -14280.92 | I16: -9543.07 | J16: 3494.75 | K16: 10.19 | L16: 6.24 | M16: 61.22 | N16: 21322 | O16: 2.63 | P16: 0
... A20: 2026-10-MTD | B20: 10268.7 | C20: 131 | D20: 131 | E20: 5.3 | F20: 1482.05 | G20: 14.4 | H20: -3738.64 | I20: -2653.33 | J20: 2012.62 | K20: 19.6 | L20: 15.36 | M20: 78.39 | N20: 2750 | O20: 4.76 | P20: 0
A22: PPC trajectory (Ecotero command center)
A23: Month | B23: PPC spend | C23: Ad sales | D23: ACoS % | E23: TACoS % | F23: Impressions | G23: Clicks | H23: CTR % | I23: CPC | J23: CVR % | K23: Orders | L23: Spend/day
A24: 2025-10 | B24: 17636 | C24: 36174 | D24: 48.8 | E24: 24.5 | F24: 255511 | G24: 3621 | H24: 1.42 | I24: 4.87 | J24: 16.2 | K24: 587 | L24: 608
A25: 2025-11 | B25: 11481 | C25: 25610 | D25: 44.8 | E25: 15 | F25: 197132 | G25: 2709 | H25: 1.37 | I25: 4.24 | J25: 14.9 | K25: 403 | L25: 383
A26: 2025-12 | B26: 6361 | C26: 23684 | D26: 26.9 | E26: 10 | F26: 256525 | G26: 2554 | H26: 1 | I26: 2.49 | J26: 15.1 | K26: 386 | L26: 205
A27: 2026-01 | B27: 1634 | C27: 5355 | D27: 30.5 | E27: 6.7 | F27: 88155 | G27: 820 | H27: 0.93 | I27: 1.99 | J27: 11.1 | K27: 91 | L27: 53
A28: 2026-02 | B28: 3291 | C28: 13909 | D28: 23.7 | E28: 5.7 | F28: 119532 | G28: 1435 | H28: 1.2 | I28: 2.29 | J28: 15.4 | K28: 221 | L28: 118
A29: 2026-03 | B29: 5382 | C29: 24656 | D29: 21.8 | E29: 4.4 | F29: 158510 | G29: 2353 | H29: 1.48 | I29: 2.29 | J29: 16.5 | K29: 389 | L29: 174
A30: 2026-04 | B30: 4165 | C30: 15644 | D30: 26.6 | E30: 4 | F30: 158678 | G30: 2094 | H30: 1.32 | I30: 1.99 | J30: 12.2 | K30: 256 | L30: 139
A31: 2026-05 | B31: 4411 | C31: 16069 | D31: 27.5 | E31: 7.6 | F31: 306571 | G31: 2137 | H31: 0.7 | I31: 2.06 | J31: 12.1 | K31: 259 | L31: 142
A32: 2026-06 | B32: 4916 | C32: 13512 | D32: 36.4 | E32: 14.2 | F32: 230687 | G32: 2383 | H32: 1.03 | I32: 2.06 | J32: 9.9 | K32: 235 | L32: 164
A33: 2026-07 | B33: 2025 | C33: 8791 | D33: 23 | E33: 6.8 | F33: 131201 | G33: 1350 | H33: 1.03 | I33: 1.5 | J33: 11.2 | K33: 151 | L33: 65
A34: 2026-08 | B34: 6578 | C34: 28302 | D34: 23.2 | E34: 8.8 | F34: 477465 | G34: 3407 | H34: 0.71 | I34: 1.93 | J34: 11.7 | K34: 397 | L34: 212
A35: 2026-09 | B35: 7423 | C35: 26676 | D35: 27.8 | E35: 11.7 | F35: 509129 | G35: 3656 | H35: 0.72 | I35: 2.03 | J35: 9.4 | K35: 344 | L35: 247
A36: 2026-10 | B36: 1482 | C36: 3744 | D36: 39.6 | E36: 15.8 | F36: 170207 | G36: 793 | H36: 0.47 | I36: 1.87 | J36: 6.2 | K36: 49 | L36: 212

Sheet Decolure_Monthly
A1: Decolure Monthly
A2: Sellerboard (total business), Oct 2023 → Oct 2026 MTD. PPC detail per month in Decolure PPC section below.
A4: Month | B4: Sales $ | C4: Units | D4: Orders | E4: Refund % | F4: Ad spend $ | G4: TACoS % | H4: COGS $ | I4: Amazon fees $ | J4: Net profit $ | K4: Margin % | L4: NP / unit | M4: ASP | N4: Sessions | O4: Unit session % | P4: LTSF $
A5: 2023-10 | B5: 1481.4 | C5: 255 | D5: 253 | E5: 0.4 | F5: 0 | G5: 0 | H5: -2969.85 | I5: 299.19 | J5: -1206.92 | K5: -81.47 | L5: -4.73 | M5: 5.81 | N5: 2781 | O5: 9.17 | P5: 0
A6: 2023-11 | B6: 31955.95 | C6: 1001 | D6: 990 | E6: 2 | F6: 9507.3 | G6: 29.8 | H6: -11564.56 | I6: -14096.53 | J6: -3782.07 | K6: -11.84 | L6: -3.78 | M6: 31.92 | N6: 19164 | O6: 5.22 | P6: 0
A7: 2023-12 | B7: 24483.45 | C7: 731 | D7: 721 | E7: 5.6 | F7: 5039.02 | G7: 20.6 | H7: -8482.92 | I7: -10667.05 | J7: -933.36 | K7: -3.81 | L7: -1.28 | M7: 33.49 | N7: 14109 | O7: 5.18 | P7: 0
A8: 2024-01 | B8: 4791.05 | C8: 141 | D8: 140 | E8: 20.6 | F8: 1053.05 | G8: 22 | H8: -1738.5 | I8: -2356.72 | J8: -1011.09 | K8: -21.1 | L8: -7.17 | M8: 33.98 | N8: 3973 | O8: 3.55 | P8: 0
A9: 2024-02 | B9: 2991.75 | C9: 85 | D9: 85 | E9: 9.4 | F9: 149.75 | G9: 5 | H9: -1015.03 | I9: -1196.78 | J9: 473.89 | K9: 15.84 | L9: 5.58 | M9: 35.2 | N9: 2390 | O9: 3.56 | P9: 0
A10: 2024-03 | B10: 12372.1 | C10: 359 | D10: 352 | E10: 2.8 | F10: 4202.06 | G10: 34 | H10: -4240.7 | I10: -4414.17 | J10: -1085.25 | K10: -8.77 | L10: -3.02 | M10: 34.46 | N10: 8538 | O10: 4.2 | P10: 0
A11: 2024-04 | B11: 60307.95 | C11: 1765 | D11: 1734 | E11: 2.3 | F11: 15658.42 | G11: 26 | H11: -20339.32 | I11: -21491.73 | J11: -1656.46 | K11: -2.75 | L11: -0.94 | M11: 34.17 | N11: 37844 | O11: 4.66 | P11: -45.11
A12: 2024-05 | B12: 64392.05 | C12: 1730 | D12: 1705 | E12: 4.5 | F12: 14035.14 | G12: 21.8 | H12: -19914.84 | I12: -22302.9 | J12: 5536.23 | K12: 8.6 | L12: 3.2 | M12: 37.22 | N12: 40645 | O12: 4.26 | P12: -34.36
A13: 2024-06 | B13: 43550.2 | C13: 1359 | D13: 1342 | E13: 3.4 | F13: 7573.11 | G13: 17.4 | H13: -16001.81 | I13: -16281.12 | J13: 2367.06 | K13: 5.44 | L13: 1.74 | M13: 32.05 | N13: 27625 | O13: 4.92 | P13: -22.02
A14: 2024-07 | B14: 64573.48 | C14: 1945 | D14: 1912 | E14: 3.4 | F14: 9173.96 | G14: 14.2 | H14: -22972.08 | I14: -24207.21 | J14: 5618.16 | K14: 8.7 | L14: 2.89 | M14: 33.2 | N14: 41965 | O14: 4.63 | P14: -33.37
A15: 2024-08 | B15: 84561.93 | C15: 2353 | D15: 2325 | E15: 4.3 | F15: 16505.35 | G15: 19.5 | H15: -28618.51 | I15: -29485.63 | J15: 5828.1 | K15: 6.89 | L15: 2.48 | M15: 35.94 | N15: 50502 | O15: 4.66 | P15: 0
A16: 2024-09 | B16: 41068.5 | C16: 1072 | D16: 1052 | E16: 6.2 | F16: 7328.33 | G16: 17.8 | H16: -13004.86 | I16: -14159.45 | J16: 3625.33 | K16: 8.83 | L16: 3.38 | M16: 38.31 | N16: 25091 | O16: 4.27 | P16: -21.06
... A41: 2026-10-MTD | B41: 1504.1 | C41: 38 | D41: 38 | E41: 0 | F41: 615.28 | G41: 40.9 | H41: -608.8 | I41: -506.47 | J41: -226.45 | K41: -15.06 | L41: -5.96 | M41: 39.58 | N41: 792 | O41: 4.8 | P41: 0
A43: PPC trajectory (Ecotero command center)
A44: From | B44: To | C44: PPC spend | D44: Ad sales | E44: ACoS % | F44: TACoS % | G44: Impressions | H44: Clicks | I44: CTR % | J44: CPC | K44: CVR % | L44: Orders
A45: 2025-04-27 | B45: 2025-05-31 | C45: 1328.05 | D45: 2514.05 | E45: 52.8 | F45: 1.88 | G45: 87901 | H45: 723 | I45: 0.82 | J45: 1.84 | K45: 9.82 | L45: 71
A46: 2025-06-01 | B46: 2025-06-30 | C46: 3938.35 | D46: 6935.35 | E46: 56.8 | F46: 6.19 | G46: 244282 | H46: 2194 | I46: 0.9 | J46: 1.8 | K46: 7.98 | L46: 175
A47: 2025-07-01 | B47: 2025-07-31 | C47: 4381.52 | D47: 8129.44 | E47: 53.9 | F47: 6.81 | G47: 280720 | H47: 2445 | I47: 0.87 | J47: 1.79 | K47: 8.63 | L47: 211
A48: 2025-08-01 | B48: 2025-08-31 | C48: 1891.01 | D48: 3602.17 | E48: 52.5 | F48: 6.34 | G48: 145104 | H48: 1060 | I48: 0.73 | J48: 1.78 | K48: 8.4 | L48: 89
A49: 2025-09-01 | B49: 2025-09-30 | C49: 1124.28 | D49: 2832.87 | E49: 39.7 | F49: 9.71 | G49: 87331 | H49: 550 | I49: 0.63 | J49: 2.04 | K49: 10.18 | L49: 56
A50: 2025-10-01 | B50: 2025-10-31 | C50: 731.4 | D50: 1389.09 | E50: 52.7 | F50: 10.33 | G50: 54514 | H50: 325 | I50: 0.6 | J50: 2.25 | K50: 8.62 | L50: 28
A51: 2025-11-01 | B51: 2025-11-30 | C51: 355.79 | D51: 1071.76 | E51: 33.2 | F51: 5.98 | G51: 37557 | H51: 186 | I51: 0.5 | J51: 1.91 | K51: 12.37 | L51: 23
A52: 2025-12-01 | B52: 2025-12-31 | C52: 555.92 | D52: 1841.88 | E52: 30.2 | F52: 6 | G52: 52697 | H52: 308 | I52: 0.58 | J52: 1.8 | K52: 12.01 | L52: 37
A53: 2026-01-01 | B53: 2026-01-31 | C53: 496.42 | D53: 1006.81 | E53: 49.3 | F53: 6.78 | G53: 50872 | H53: 280 | I53: 0.55 | J53: 1.77 | K53: 7.14 | L53: 20
A54: 2026-02-01 | B54: 2026-02-28 | C54: 297.32 | D54: 1070.69 | E54: 27.8 | F54: 3.98 | G54: 25256 | H54: 182 | I54: 0.72 | J54: 1.63 | K54: 12.09 | L54: 22
A55: 2026-03-01 | B55: 2026-03-31 | C55: 130.64 | D55: 645.76 | E55: 20.2 | F55: 1.26 | G55: 47891 | H55: 196 | I55: 0.41 | J55: 0.67 | K55: 8.16 | L55: 16
A56: 2026-04-01 | B56: 2026-04-30 | C56: 679.7 | D56: 2548.76 | E56: 26.7 | F56: 7.36 | G56: 73023 | H56: 1036 | I56: 1.42 | J56: 0.66 | K56: 5.79 | L56: 60
... A63: TOTAL_2024-01-01 | B63: 2026-10-08 | C63: 30808.17 | D63: 64963.64 | E63: 47.4 | F63: 4.51 | G63: 2394988 | H63: 26601 | I63: 1.11 | J63: 1.16 | K63: 6.11 | L63: 1624

Sheet KW_Sleephoria
A1: Sleephoria search terms — non-brand, relevant (29 Dec 2025 → 7 Oct 2026)
A2: Class: PROFITABLE ≤31% ACoS · GROWTH 31–45% · MARGINAL 45–60% · WASTE >60% w/ $20+ spend, or ≥15 clicks & 0 orders · LOW-DATA otherwise. Launch push (Oct–Dec 2025) has no search-term detail.
A4: Keyword | B4: Relevancy | C4: Syntax | D4: Search volume | E4: Impressions | F4: Clicks | G4: CTR % | H4: CPC | I4: CVR % | J4: Orders | K4: Spend $ | L4: Sales $ | M4: ACoS % | N4: Median organic rank | O4: Class
A5: cooling sheets full size | B5: Highly Relevant | C5: Cooling|Full | D5: 6228 | E5: 340921 | F5: 2305 | G5: 0.68 | H5: 2.49 | I5: 12.02 | J5: 277 | K5: 5739.76 | L5: 16455.32 | M5: 34.9 | N5: 11 | O5: GROWTH-ACCEPTABLE
A6: cooling sheets queen | B6: Highly Relevant | C6: Cooling|Queen | D6: 30225 | E6: 169257 | F6: 2552 | G6: 1.51 | H6: 2.24 | I6: 11.87 | J6: 303 | K6: 5718.99 | L6: 19776.51 | M6: 28.9 | N6: 23 | O6: PROFITABLE
A7: king size cooling sheets | B7: Highly Relevant | C7: Cooling|King | D7: 4967 | E7: 117767 | F7: 1029 | G7: 0.87 | H7: 3.91 | I7: 15.84 | J7: 163 | K7: 4023.11 | L7: 12083.33 | M7: 33.3 | N7: 13 | O7: GROWTH-ACCEPTABLE
A8: cooling sheets king size | B8: Highly Relevant | C8: Cooling|King | D8: 19413 | E8: 81032 | F8: 651 | G8: 0.8 | H8: 3.28 | I8: 11.06 | J8: 72 | K8: 2134.37 | L8: 5728.74 | M8: 37.3 | N8: 13 | O8: GROWTH-ACCEPTABLE
A9: king cooling sheets | B9: Highly Relevant | C9: Cooling|King | D9: 3271 | E9: 22887 | F9: 300 | G9: 1.31 | H9: 4.17 | I9: 9 | J9: 27 | K9: 1251.08 | L9: 2073.73 | M9: 60.3 | N9: 34 | O9: WASTE
A10: california king cooling sheets | B10: Highly Relevant | C10: Cooling|California King | D10: 924 | E10: 8615 | F10: 324 | G10: 3.76 | H10: 3.69 | I10: 16.67 | J10: 54 | K10: 1196.48 | L10: 3934.45 | M10: 30.4 | N10: 6 | O10: PROFITABLE
A11: twin cooling sheets | B11: Highly Relevant | C11: Cooling|Twin | D11: 1305 | E11: 58405 | F11: 614 | G11: 1.05 | H11: 1.7 | I11: 10.75 | J11: 66 | K11: 1041.08 | L11: 3554.99 | M11: 29.3 | N11: 5 | O11: PROFITABLE
A12: cooling sheets | B12: Highly Relevant | C12: Cooling | D12: 77377 | E12: 43272 | F12: 485 | G12: 1.12 | H12: 2.01 | I12: 9.48 | J12: 46 | K12: 972.58 | L12: 3298.46 | M12: 29.5 | N12: 11 | O12: PROFITABLE
A13: cal king cooling sheets | B13: Highly Relevant | C13: Cooling|California King | D13: 672 | E13: 14214 | F13: 227 | G13: 1.6 | H13: 3.71 | I13: 17.18 | J13: 39 | K13: 842.19 | L13: 2831.6 | M13: 29.7 | N13: 10 | O13: PROFITABLE
A14: cooling sheets queen size | B14: Highly Relevant | C14: Cooling|Queen | D14: 924 | E14: 44222 | F14: 504 | G14: 1.14 | H14: 1.4 | I14: 5.75 | J14: 29 | K14: 705.93 | L14: 1828.63 | M14: 38.6 | N14: 20 | O14: GROWTH-ACCEPTABLE
A15: cooling queen sheets | B15: Highly Relevant | C15: Cooling|Queen | D15: 2635 | E15: 26834 | F15: 234 | G15: 0.87 | H15: 2.95 | I15: 11.11 | J15: 26 | K15: 690.27 | L15: 1814.7 | M15: 38 | N15: 20 | O15: GROWTH-ACCEPTABLE
A16: cooling bed sheets | B16: Highly Relevant | C16: Cooling | D16: 12715 | E16: 15682 | F16: 259 | G16: 1.65 | H16: 2.45 | I16: 7.72 | J16: 20 | K16: 635.41 | L16: 1508.3 | M16: 42.1 | N16: 13 | O16: GROWTH-ACCEPTABLE
... A18: cooling sheets king | B18: Highly Relevant | C18: Cooling|King | D18: 2630 | E18: 4646 | F18: 115 | G18: 2.48 | H18: 3.27 | I18: 9.57 | J18: 11 | K18: 376.43 | L18: 876.89 | M18: 42.9 | N18: 28 | O18: GROWTH-ACCEPTABLE
A19: cali king cooling sheets | B19: Highly Relevant | C19: Cooling|King | D19: 402 | E19: 2480 | F19: 92 | G19: 3.71 | H19: 3.46 | I19: 17.39 | J19: 16 | K19: 318.01 | L19: 1169.34 | M19: 27.2 | O19: PROFITABLE
A20: cooling sheets twin | B20: Highly Relevant | C20: Cooling|Twin | D20: 2976 | E20: 40277 | F20: 172 | G20: 0.43 | H20: 1.71 | I20: 13.37 | J20: 23 | K20: 293.71 | L20: 1392.64 | M20: 21.1 | N20: 4 | O20: PROFITABLE
A21: cool sheets queen | B21: Highly Relevant | C21: Cooling|Queen | D21: 766 | E21: 2338 | F21: 120 | G21: 5.13 | H21: 2.39 | I21: 15 | J21: 18 | K21: 286.63 | L21: 1254.81 | M21: 22.8 | N21: 19 | O21: PROFITABLE
A22: best cooling sheets | B22: Highly Relevant | C22: Cooling | D22: 1023 | E22: 9282 | F22: 211 | G22: 2.27 | H22: 1.32 | I22: 5.21 | J22: 11 | K22: 279.27 | L22: 747.89 | M22: 37.3 | N22: 23 | O22: GROWTH-ACCEPTABLE
A23: stay cool sheets | B23: Highly Relevant | D23: 70 | E23: 2411 | F23: 113 | G23: 4.69 | H23: 2.43 | I23: 9.73 | J23: 11 | K23: 274.47 | L23: 732.89 | M23: 37.5 | O23: GROWTH-ACCEPTABLE
A24: cooling full size sheets | B24: Highly Relevant | C24: Cooling|Full | D24: 822 | E24: 13839 | F24: 155 | G24: 1.12 | H24: 1.59 | I24: 10.97 | J24: 17 | K24: 246.9 | L24: 948.79 | M24: 26 | N24: 13 | O24: PROFITABLE
A25: cold sheets for hot sleepers | B25: Highly Relevant | C25: Cooling | D25: 822 | E25: 7781 | F25: 103 | G25: 1.32 | H25: 2.34 | I25: 7.77 | J25: 8 | K25: 241.49 | L25: 644.92 | M25: 37.4 | N25: 15 | O25: GROWTH-ACCEPTABLE
A26: cooling king sheets | B26: Highly Relevant | C26: Cooling|King | D26: 2637 | E26: 2197 | F26: 66 | G26: 3 | H26: 3.62 | I26: 9.09 | J26: 6 | K26: 239.17 | L26: 464.94 | M26: 51.4 | N26: 26 | O26: MARGINAL(45-60)
A27: cooling bed sheets king | B27: Highly Relevant | C27: Cooling|King | D27: 1961 | E27: 8637 | F27: 69 | G27: 0.8 | H27: 3.39 | I27: 14.49 | J27: 10 | K27: 233.93 | L27: 829.9 | M27: 28.2 | N27: 47 | O27: PROFITABLE
A28: cool sheets for hot sleepers | B28: Highly Relevant | C28: Cooling | D28: 1961 | E28: 1974 | F28: 71 | G28: 3.6 | H28: 2.81 | I28: 9.86 | J28: 7 | K28: 199.69 | L28: 564.93 | M28: 35.3 | N28: 14 | O28: GROWTH-ACCEPTABLE
A29: queen cooling sheets | B29: Highly Relevant | C29: Cooling|Queen | D29: 4728 | E29: 9876 | F29: 78 | G29: 0.79 | H29: 2.38 | I29: 12.82 | J29: 10 | K29: 185.26 | L29: 804.9 | M29: 23 | N29: 29 | O29: PROFITABLE
A30: cooling bed sheets queen | B30: Highly Relevant | C30: Cooling|Queen | D30: 2976 | E30: 14580 | F30: 86 | G30: 0.59 | H30: 1.96 | I30: 4.65 | J30: 4 | K30: 168.66 | L30: 296.21 | M30: 56.9 | N30: 9 | O30: MARGINAL(45-60)
A31: full size sheets cooling | B31: Highly Relevant | C31: Cooling|Full | D31: 1959 | E31: 29471 | F31: 112 | G31: 0.38 | H31: 1.45 | I31: 8.93 | J31: 10 | K31: 161.99 | L31: 596.55 | M31: 27.2 | N31: 20 | O31: PROFITABLE
A32: cooling sheets for hot sleepers | B32: Highly Relevant | C32: Cooling | D32: 901 | E32: 6746 | F32: 80 | G32: 1.19 | H32: 1.96 | I32: 1.25 | J32: 1 | K32: 156.48 | L32: 54.99 | M32: 284.6 | N32: 19 | O32: WASTE
A33: king size bed sheets cooling | B33: Highly Relevant | C33: Cooling|King | D33: 819 | E33: 6358 | F33: 50 | G33: 0.79 | H33: 2.91 | I33: 12 | J33: 6 | K33: 145.4 | L33: 494.94 | M33: 29.4 | N33: 34 | O33: PROFITABLE
A34: cooling sheet set | B34: Highly Relevant | C34: Cooling | D34: 1669 | E34: 5586 | F34: 61 | G34: 1.09 | H34: 2.35 | I34: 9.84 | J34: 6 | K34: 143.3 | L34: 474.94 | M34: 30.2 | N34: 32 | O34: PROFITABLE
A35: cooling bed sheets full | B35: Highly Relevant | C35: Cooling|Full | D35: 924 | E35: 1355 | F35: 65 | G35: 4.8 | H35: 2.13 | I35: 6.15 | J35: 4 | K35: 138.34 | L35: 249.96 | M35: 55.3 | N35: 10 | O35: MARGINAL(45-60)
... A39: king sheets cooling | B39: Highly Relevant | C39: Cooling|King | D39: 4954 | E39: 725 | F39: 27 | G39: 3.72 | H39: 4.68 | I39: 18.52 | J39: 5 | K39: 126.39 | L39: 419.95 | M39: 30.1 | N39: 51 | O39: PROFITABLE
A40: cool queen sheets | B40: Highly Relevant | C40: Cooling|Queen | D40: 489 | E40: 1154 | F40: 46 | G40: 3.99 | H40: 2.58 | I40: 13.04 | J40: 6 | K40: 118.74 | L40: 415.94 | M40: 28.5 | O40: PROFITABLE
A41: queen size cooling sheets | B41: Highly Relevant | C41: Cooling|Queen | D41: 2632 | E41: 7547 | F41: 37 | G41: 0.49 | H41: 3.05 | I41: 2.7 | J41: 1 | K41: 112.99 | L41: 79.99 | M41: 141.3 | N41: 15 | O41: WASTE
A42: queen bed sheets cooling | B42: Highly Relevant | C42: Cooling|Queen | D42: 2630 | E42: 13827 | F42: 35 | G42: 0.25 | H42: 3.14 | I42: 11.43 | J42: 4 | K42: 109.97 | L42: 309.96 | M42: 35.5 | N42: 26 | O42: GROWTH-ACCEPTABLE
A43: best cooling sheets for hot sleepers | B43: Highly Relevant | C43: Cooling | D43: 575 | E43: 2242 | F43: 44 | G43: 1.96 | H43: 2.5 | I43: 11.36 | J43: 5 | K43: 109.96 | L43: 363.95 | M43: 30.2 | N43: 33 | O43: PROFITABLE
A44: cooling sheets for night sweats | B44: Highly Relevant | C44: Cooling | D44: 439 | E44: 1243 | F44: 46 | G44: 3.7 | H44: 2.33 | I44: 8.7 | J44: 4 | K44: 107.34 | L44: 284.96 | M44: 37.7 | N44: 16 | O44: GROWTH-ACCEPTABLE
A45: cold bed sheets | B45: Highly Relevant | C45: Cooling | D45: 924 | E45: 1360 | F45: 37 | G45: 2.72 | H45: 2.72 | I45: 5.41 | J45: 2 | K45: 100.57 | L45: 154.98 | M45: 64.9 | N45: 7 | O45: WASTE
A46: full size cooling sheets | B46: Highly Relevant | C46: Cooling|Full | D46: 1735 | E46: 1170 | F46: 45 | G46: 3.85 | H46: 2.23 | I46: 6.67 | J46: 3 | K46: 100.24 | L46: 184.97 | M46: 54.2 | N46: 15 | O46: MARGINAL(45-60)
A47: king size cool sheets | B47: Lower Relevant | D47: 47 | E47: 62 | F47: 19 | G47: 30.65 | H47: 4.8 | I47: 10.53 | J47: 2 | K47: 91.22 | L47: 145.98 | M47: 62.5 | O47: WASTE
A48: cooling queen size sheets | B48: Highly Relevant | C48: Cooling|Queen | D48: 512 | E48: 302 | F48: 28 | G48: 9.27 | H48: 3.15 | I48: 21.43 | J48: 6 | K48: 88.22 | L48: 419.94 | M48: 21 | O48: PROFITABLE
A49: cool sheets full | B49: Highly Relevant | D49: 207 | E49: 183 | F49: 29 | G49: 15.85 | H49: 2.98 | I49: 6.9 | J49: 2 | K49: 86.43 | L49: 119.98 | M49: 72 | O49: WASTE
A50: king size sheets set cooling | B50: Highly Relevant | C50: Cooling|King | D50: 3492 | E50: 1048 | F50: 30 | G50: 2.86 | H50: 2.59 | I50: 13.33 | J50: 4 | K50: 77.76 | L50: 339.96 | M50: 22.9 | N50: 60 | O50: PROFITABLE
A51: king size cooling sheet | B51: Lower Relevant | D51: 70 | E51: 69 | F51: 16 | G51: 23.19 | H51: 4.14 | I51: 6.25 | J51: 1 | K51: 66.27 | L51: 84.99 | M51: 78 | O51: WASTE
A52: cooling bed sheets full size | B52: Highly Relevant | C52: Cooling|Full | D52: 598 | E52: 413 | F52: 28 | G52: 6.78 | H52: 2.35 | I52: 28.57 | J52: 8 | K52: 65.93 | L52: 491.92 | M52: 13.4 | N52: 20 | O52: PROFITABLE
A53: cooling deep pocket queen sheets | B53: Highly Relevant | C53: Cooling|Queen | D53: 766 | E53: 8065 | F53: 34 | G53: 0.42 | H53: 1.83 | I53: 5.88 | J53: 2 | K53: 62.26 | L53: 159.98 | M53: 38.9 | N53: 62 | O53: GROWTH-ACCEPTABLE
A54: king size sheets cooling | B54: Highly Relevant | C54: Cooling|King | D54: 659 | E54: 235 | F54: 18 | G54: 7.66 | H54: 3.4 | I54: 0 | J54: 0 | K54: 61.24 | L54: 0 | N54: 21 | O54: WASTE
A55: cooling king size sheets | B55: Highly Relevant | C55: Cooling|King | D55: 1023 | E55: 231 | F55: 18 | G55: 7.79 | H55: 3.23 | I55: 5.56 | J55: 1 | K55: 58.14 | L55: 84.99 | M55: 68.4 | N55: 17 | O55: WASTE
A56: california king cool sheets | B56: Highly Relevant | D56: 38 | E56: 82 | F56: 14 | G56: 17.07 | H56: 4.13 | I56: 14.29 | J56: 2 | K56: 57.8 | L56: 161.98 | M56: 35.7 | O56: GROWTH-ACCEPTABLE
A57: cooling bed sheets for hot sleepers | B57: Highly Relevant | C57: Cooling | D57: 364 | E57: 1695 | F57: 29 | G57: 1.71 | H57: 1.9 | I57: 6.9 | J57: 2 | K57: 55.17 | L57: 129.98 | M57: 42.4 | N57: 6 | O57: GROWTH-ACCEPTABLE
A58: cooling sheets california king | B58: Highly Relevant | C58: Cooling|California King | D58: 1025 | E58: 159 | F58: 19 | G58: 11.95 | H58: 2.9 | I58: 0 | J58: 0 | K58: 55.13 | L58: 0 | N58: 6 | O58: WASTE
A59: cold bed sheets queen | B59: Highly Relevant | D59: 118 | E59: 303 | F59: 18 | G59: 5.94 | H59: 2.97 | I59: 0 | J59: 0 | K59: 53.51 | L59: 0 | O59: WASTE
A60: king cooling sheet | B60: Lower Relevant | D60: 59 | E60: 483 | F60: 13 | G60: 2.69 | H60: 4.1 | I60: 23.08 | J60: 3 | K60: 53.32 | L60: 226.97 | M60: 23.5 | O60: PROFITABLE
A61: cold sheets | B61: Highly Relevant | C61: Cooling | D61: 924 | E61: 653 | F61: 28 | G61: 4.29 | H61: 1.9 | I61: 0 | J61: 0 | K61: 53.19 | L61: 0 | N61: 11 | O61: WASTE
A62: cool bed sheets king size | B62: Highly Relevant | D62: 15 | E62: 57 | F62: 15 | G62: 26.32 | H62: 3.52 | I62: 13.33 | J62: 2 | K62: 52.81 | L62: 254.97 | M62: 20.7 | O62: PROFITABLE
A63: california king cooling sheet | B63: Highly Relevant | D63: 34 | E63: 44 | F63: 13 | G63: 29.55 | H63: 3.72 | I63: 0 | J63: 0 | K63: 48.31 | L63: 0 | O63: WASTE
A64: king bed sheets cooling | B64: Highly Relevant | C64: Cooling|King | D64: 1109 | E64: 126 | F64: 14 | G64: 11.11 | H64: 3.42 | I64: 28.57 | J64: 4 | K64: 47.92 | L64: 334.96 | M64: 14.3 | N64: 62 | O64: PROFITABLE
A65: deep pocket cooling sheets | B65: Highly Relevant | C65: Cooling | D65: 901 | E65: 1673 | F65: 23 | G65: 1.37 | H65: 1.98 | I65: 4.35 | J65: 1 | K65: 45.52 | L65: 84.99 | M65: 53.6 | N65: 40 | O65: MARGINAL(45-60)
A66: twin cooling sheet | B66: Lower Relevant | D66: 82 | E66: 127 | F66: 18 | G66: 14.17 | H66: 2.35 | I66: 27.78 | J66: 5 | K66: 42.22 | L66: 221.95 | M66: 19 | O66: PROFITABLE
A67: king size cooling sheets set | B67: Highly Relevant | C67: Cooling|King | D67: 1023 | E67: 139 | F67: 13 | G67: 9.35 | H67: 3.12 | I67: 30.77 | J67: 4 | K67: 40.52 | L67: 314.96 | M67: 12.9 | N67: 33 | O67: PROFITABLE
A68: cold sheets queen | B68: Highly Relevant | C68: Cooling|Queen | D68: 501 | E68: 627 | F68: 21 | G68: 3.35 | H68: 1.84 | I68: 19.05 | J68: 4 | K68: 38.69 | L68: 314.96 | M68: 12.3 | O68: PROFITABLE
A69: cooling full sheets | B69: Highly Relevant | D69: 72 | E69: 72 | F69: 16 | G69: 22.22 | H69: 2.41 | I69: 6.25 | J69: 1 | K69: 38.56 | L69: 64.99 | M69: 59.3 | O69: MARGINAL(45-60)
A70: breathable cooling sheets | B70: Highly Relevant | C70: Cooling | D70: 285 | E70: 1404 | F70: 14 | G70: 1 | H70: 2.74 | I70: 14.29 | J70: 2 | K70: 38.34 | L70: 134.98 | M70: 28.4 | O70: PROFITABLE
A71: california king sheet sets cooling | B71: Highly Relevant | C71: Cooling|California King | D71: 682 | E71: 66 | F71: 12 | G71: 18.18 | H71: 3.15 | I71: 8.33 | J71: 1 | K71: 37.85 | L71: 169.98 | M71: 22.3 | N71: 46 | O71: PROFITABLE
A72: cool sheets king size | B72: Highly Relevant | C72: Cooling|King | D72: 646 | E72: 91 | F72: 13 | G72: 14.29 | H72: 2.81 | I72: 23.08 | J72: 3 | K72: 36.51 | L72: 204.97 | M72: 17.8 | N72: 22 | O72: PROFITABLE
A73: cooling queen sheet | B73: Lower Relevant | D73: 67 | E73: 307 | F73: 17 | G73: 5.54 | H73: 2.13 | I73: 5.88 | J73: 1 | K73: 36.23 | L73: 79.99 | M73: 45.3 | O73: MARGINAL(45-60)
A74: deep pocket queen sheets cooling | B74: Highly Relevant | C74: Cooling|Queen | D74: 766 | E74: 4070 | F74: 22 | G74: 0.54 | H74: 1.63 | I74: 4.55 | J74: 1 | K74: 35.8 | L74: 74.99 | M74: 47.7 | N74: 54 | O74: MARGINAL(45-60)
A75: purple cooling sheets | B75: Highly Relevant | C75: Cooling | D75: 344 | E75: 3212 | F75: 44 | G75: 1.37 | H75: 0.8 | I75: 4.55 | J75: 2 | K75: 35.11 | L75: 159.98 | M75: 21.9 | O75: PROFITABLE
A76: deep pocket king sheet set cooling | B76: Highly Relevant | C76: Cooling|King | D76: 636 | E76: 62 | F76: 11 | G76: 17.74 | H76: 3.13 | I76: 0 | J76: 0 | K76: 34.44 | L76: 0 | O76: WASTE
A77: queen bed cooling sheets | B77: Highly Relevant | C77: Cooling|Queen | D77: 588 | E77: 456 | F77: 13 | G77: 2.85 | H77: 2.45 | I77: 0 | J77: 0 | K77: 31.9 | L77: 0 | N77: 9 | O77: WASTE
A78: king sheet set cooling | B78: Highly Relevant | C78: Cooling|King | D78: 1023 | E78: 185 | F78: 10 | G78: 5.41 | H78: 3.19 | I78: 0 | J78: 0 | K78: 31.89 | L78: 0 | N78: 77 | O78: WASTE
A79: deep pocket cooling queen sheets | B79: Highly Relevant | C79: Cooling|Queen | D79: 677 | E79: 232 | F79: 14 | G79: 6.03 | H79: 2.25 | I79: 0 | J79: 0 | K79: 31.54 | L79: 0 | N79: 47 | O79: WASTE
A80: cooling bed set | B80: Lower Relevant | C80: Cooling | D80: 1109 | E80: 615 | F80: 12 | G80: 1.95 | H80: 2.62 | I80: 0 | J80: 0 | K80: 31.42 | L80: 0 | N80: 87 | O80: WASTE
A81: queen cooling sheets deep pockets | B81: Highly Relevant | C81: Cooling|Queen | D81: 535 | E81: 1417 | F81: 15 | G81: 1.06 | H81: 1.96 | I81: 6.67 | J81: 1 | K81: 29.45 | L81: 79.99 | M81: 36.8 | N81: 74 | O81: GROWTH-ACCEPTABLE
A82: cooling sheets cal king | B82: Highly Relevant | C82: Cooling|California King | D82: 537 | E82: 1002 | F82: 14 | G82: 1.4 | H82: 2.08 | I82: 14.29 | J82: 2 | K82: 29.09 | L82: 164.98 | M82: 17.6 | O82: PROFITABLE
A83: queen size sheets cooling | B83: Highly Relevant | C83: Cooling|Queen | D83: 1023 | E83: 1201 | F83: 12 | G83: 1 | H83: 2.41 | I83: 8.33 | J83: 1 | K83: 28.91 | L83: 79.99 | M83: 36.1 | N83: 30 | O83: GROWTH-ACCEPTABLE
A84: cooling sheets king size for hot sleepers | B84: Highly Relevant | C84: Cooling|King | D84: 479 | E84: 485 | F84: 13 | G84: 2.68 | H84: 2.19 | I84: 15.38 | J84: 2 | K84: 28.52 | L84: 144.98 | M84: 19.7 | O84: PROFITABLE
A85: soft cooling sheets | B85: Highly Relevant | C85: Cooling | D85: 939 | E85: 262 | F85: 10 | G85: 3.82 | H85: 2.8 | I85: 0 | J85: 0 | K85: 27.99 | L85: 0 | N85: 35 | O85: LOW-DATA
A86: cool sheets king | B86: Highly Relevant | D86: 248 | E86: 68 | F86: 10 | G86: 14.71 | H86: 2.8 | I86: 20 | J86: 2 | K86: 27.96 | L86: 149.98 | M86: 18.6 | O86: PROFITABLE
A87: cooling sheets hot sleepers | B87: Highly Relevant | C87: Cooling | D87: 659 | E87: 86 | F87: 10 | G87: 11.63 | H87: 2.79 | I87: 20 | J87: 2 | K87: 27.85 | L87: 144.98 | M87: 19.2 | O87: PROFITABLE
A88: cooling bed sheet | B88: Highly Relevant | C88: Cooling | D88: 672 | E88: 41 | F88: 10 | G88: 24.39 | H88: 2.75 | I88: 10 | J88: 1 | K88: 27.54 | L88: 84.99 | M88: 32.4 | N88: 18 | O88: GROWTH-ACCEPTABLE
A89: cooling california king sheets | B89: Highly Relevant | C89: Cooling|California King | D89: 639 | E89: 3260 | F89: 13 | G89: 0.4 | H89: 2.05 | I89: 0 | J89: 0 | K89: 26.61 | L89: 0 | N89: 10 | O89: LOW-DATA
A90: deep pocket cooling king sheet set | B90: Highly Relevant | C90: Cooling|King | D90: 593 | E90: 62 | F90: 8 | G90: 12.9 | H90: 3.17 | I90: 12.5 | J90: 1 | K90: 25.36 | L90: 84.99 | M90: 29.8 | O90: PROFITABLE
A91: king size cooling sheets deep pocket set | B91: Highly Relevant | C91: Cooling|King | D91: 601 | E91: 133 | F91: 9 | G91: 6.77 | H91: 2.81 | I91: 0 | J91: 0 | K91: 25.3 | L91: 0 | N91: 61 | O91: LOW-DATA
A92: cal king cool sheets | B92: Highly Relevant | D92: 12 | E92: 21 | F92: 6 | G92: 28.57 | H92: 4.22 | I92: 16.67 | J92: 1 | K92: 25.29 | L92: 69.99 | M92: 36.1 | O92: GROWTH-ACCEPTABLE
A93: king cooling sheets deep pocket | B93: Highly Relevant | C93: Cooling|King | D93: 651 | E93: 1456 | F93: 13 | G93: 0.89 | H93: 1.88 | I93: 7.69 | J93: 1 | K93: 24.41 | L93: 84.99 | M93: 28.7 | N93: 137 | O93: PROFITABLE
A94: cooling bed sheets king size | B94: Highly Relevant | C94: Cooling|King | D94: 424 | E94: 43 | F94: 7 | G94: 16.28 | H94: 3.47 | I94: 0 | J94: 0 | K94: 24.26 | L94: 0 | O94: LOW-DATA
A95: cooling bed set king | B95: Lower Relevant | C95: Cooling|King | D95: 319 | E95: 84 | F95: 9 | G95: 10.71 | H95: 2.64 | I95: 22.22 | J95: 2 | K95: 23.72 | L95: 124.98 | M95: 19 | N95: 44 | O95: PROFITABLE
A96: cooling sheet full size | B96: Lower Relevant | D96: 55 | E96: 29 | F96: 8 | G96: 27.59 | H96: 2.91 | I96: 12.5 | J96: 1 | K96: 23.27 | L96: 60.99 | M96: 38.2 | O96: GROWTH-ACCEPTABLE
A97: cool sheets queen size | B97: Lower Relevant | D97: 22 | E97: 51 | F97: 9 | G97: 17.65 | H97: 2.54 | I97: 11.11 | J97: 1 | K97: 22.82 | L97: 79.99 | M97: 28.5 | O97: PROFITABLE
A98: cool sheets | B98: Highly Relevant | C98: Cooling | D98: 2203 | E98: 108 | F98: 9 | G98: 8.33 | H98: 2.53 | I98: 0 | J98: 0 | K98: 22.73 | L98: 0 | N98: 13 | O98: LOW-DATA
A99: full cooling sheets | B99: Highly Relevant | C99: Cooling|Full | D99: 590 | E99: 53 | F99: 9 | G99: 16.98 | H99: 2.34 | I99: 22.22 | J99: 2 | K99: 21.02 | L99: 169.98 | M99: 12.4 | N99: 15 | O99: PROFITABLE
A100: cooling king bed sheets | B100: Highly Relevant | C100: Cooling|King | D100: 624 | E100: 207 | F100: 8 | G100: 3.86 | H100: 2.63 | I100: 12.5 | J100: 1 | K100: 21.02 | L100: 79.99 | M100: 26.3 | N100: 96 | O100: PROFITABLE
A101: cooling sheets deep pocket | B101: Highly Relevant | C101: Cooling | D101: 489 | E101: 629 | F101: 12 | G101: 1.91 | H101: 1.74 | I101: 0 | J101: 0 | K101: 20.83 | L101: 0 | O101: LOW-DATA
A102: bed sheets queen size cooling | B102: Highly Relevant | C102: Cooling|Queen | D102: 697 | E102: 81 | F102: 7 | G102: 8.64 | H102: 2.95 | I102: 14.29 | J102: 1 | K102: 20.68 | L102: 79.99 | M102: 25.9 | N102: 36 | O102: PROFITABLE
A103: queen size cooling bed sheets | B103: Highly Relevant | D103: 127 | E103: 35 | F103: 7 | G103: 20 | H103: 2.92 | I103: 28.57 | J103: 2 | K103: 20.43 | L103: 154.98 | M103: 13.2 | O103: PROFITABLE
A104: king size sheets set deep pockets cooling | B104: Highly Relevant | C104: Cooling|King | D104: 486 | E104: 20 | F104: 7 | G104: 35 | H104: 2.88 | I104: 14.29 | J104: 1 | K104: 20.14 | L104: 79.99 | M104: 25.2 | O104: PROFITABLE
A105: cooling fitted sheet | B105: Lower Relevant | C105: Cooling | D105: 2922 | E105: 380 | F105: 25 | G105: 6.58 | H105: 0.79 | I105: 0 | J105: 0 | K105: 19.82 | L105: 0 | O105: WASTE
...

Sheet KW_Decolure
A1: Decolure search terms — classified union (Sep 2025 → 8 Oct 2026)
A2: Search terms carry other Decolure products' sales in shared campaigns (own-ASIN rows inflated). Clean non-brand benchmark: 51.6% ACoS / 6.6% CVR / $1.36 CPC.
A4: Keyword | B4: Relevancy | C4: Syntax | D4: Search volume | E4: Clicks | F4: CTR % | G4: CPC | H4: CVR % | I4: Orders | J4: Spend $ | K4: Sales $ | L4: ACoS % | M4: Median organic rank | N4: Class
A5: cooling sheets queen | B5: Highly Relevant | C5: Cooling|Queen | D5: 30225 | E5: 2048 | F5: 1.5 | G5: 1.21 | H5: 6.93 | I5: 142 | J5: 2487.18 | K5: 5412.95 | L5: 45.9 | M5: 29 | N5: MARGINAL(45-60)
A6: cooling sheets full size | B6: Highly Relevant | C6: Cooling|Full | D6: 6228 | E6: 488 | F6: 1.2 | G6: 1.3 | H6: 6.56 | I6: 32 | J6: 635.51 | K6: 1174.87 | L6: 54.1 | M6: 57 | N6: MARGINAL(45-60)
A7: decolure bamboo sheets | B7: Branded | D7: 1023 | E7: 235 | F7: 0.57 | G7: 2.39 | H7: 11.06 | I7: 26 | J7: 561.15 | K7: 1485.77 | L7: 37.8 | N7: GROWTH-ACCEPTABLE
A8: king size sheets set cooling | B8: Highly Relevant | C8: Cooling|King | D8: 3492 | E8: 147 | F8: 4.26 | G8: 2.3 | H8: 6.12 | I8: 9 | J8: 337.65 | K8: 351.55 | L8: 96 | M8: 76 | N8: WASTE
A9: cooling sheets twin | B9: Highly Relevant | C9: Cooling|Twin | D9: 2976 | E9: 296 | F9: 0.32 | G9: 1.13 | H9: 6.42 | I9: 19 | J9: 335.36 | K9: 888.31 | L9: 37.8 | M9: 24 | N9: GROWTH-ACCEPTABLE
A10: cooling sheets | B10: Highly Relevant | C10: Cooling | D10: 77377 | E10: 376 | F10: 2.32 | G10: 0.77 | H10: 2.93 | I10: 11 | J10: 291.07 | K10: 468.54 | L10: 62.1 | M10: 37 | N10: WASTE
A11: queen bed sheets cooling | B11: Highly Relevant | C11: Cooling|Queen | D11: 2630 | E11: 204 | F11: 0.76 | G11: 1.27 | H11: 4.9 | I11: 10 | J11: 259.29 | K11: 349.45 | L11: 74.2 | M11: 24 | N11: WASTE
A12: cooling sheets king size | B12: Highly Relevant | C12: Cooling|King | D12: 19413 | E12: 160 | F12: 6.01 | G12: 1.37 | H12: 5 | I12: 8 | J12: 218.82 | K12: 363.64 | L12: 60.2 | M12: 42 | N12: WASTE
A13: bed sheets cooling | B13: Highly Relevant | C13: Cooling | D13: 1023 | E13: 52 | F13: 10.79 | G13: 3.44 | H13: 3.85 | I13: 2 | J13: 178.83 | K13: 77.9 | L13: 229.6 | M13: 26 | N13: WASTE
A14: decolure cooling sheets | B14: Branded | D14: 25 | E14: 130 | F14: 2.29 | G14: 1.37 | H14: 13.08 | I14: 17 | J14: 177.74 | K14: 900.28 | L14: 19.7 | N14: PROFITABLE
A15: bamboo sheets | B15: Relevant | C15: Bamboo | D15: 116207 | E15: 225 | F15: 3.28 | G15: 0.7 | H15: 6.67 | I15: 15 | J15: 156.66 | K15: 624.56 | L15: 25.1 | M15: 95 | N15: PROFITABLE
A16: queen sheet set cooling | B16: Highly Relevant | C16: Cooling|Queen | D16: 1023 | E16: 33 | F16: 2.76 | G16: 4.22 | H16: 21.21 | I16: 7 | J16: 139.14 | K16: 265.65 | L16: 52.4 | M16: 52 | N16: MARGINAL(45-60)
A17: cooling deep pocket queen sheets | B17: Highly Relevant | D17: 245 | E17: 37 | F17: 10.57 | G17: 3.65 | H17: 13.51 | I17: 5 | J17: 135.2 | K17: 234.75 | L17: 57.6 | M17: 89 | N17: MARGINAL(45-60)
A18: deep pocket queen sheet set | B18: Generic | D18: 4356 | E18: 90 | F18: 0.99 | G18: 1.44 | H18: 2.22 | I18: 2 | J18: 130.03 | K18: 72.1 | L18: 180.3 | N18: WASTE
A19: cooling bed sheets | B19: Highly Relevant | C19: Cooling | D19: 12715 | E19: 87 | F19: 6.37 | G19: 1.29 | H19: 9.2 | I19: 8 | J19: 112.02 | K19: 319.6 | L19: 35.1 | M19: 26 | N19: GROWTH-ACCEPTABLE
A20: sheets cooling | B20: Highly Relevant | C20: Cooling | D20: 924 | E20: 35 | F20: 7.04 | G20: 3.16 | H20: 5.71 | I20: 2 | J20: 110.67 | K20: 81.9 | L20: 135.1 | M20: 36 | N20: WASTE
A21: decolure cooling sheets queen | B21: Branded | D21: 11 | E21: 37 | F21: 1.71 | G21: 2.73 | H21: 18.92 | I21: 7 | J21: 101.02 | K21: 425.06 | L21: 23.8 | N21: PROFITABLE
A22: cooling bed sheets queen | B22: Highly Relevant | C22: Cooling|Queen | D22: 2976 | E22: 46 | F22: 7.67 | G22: 2.12 | H22: 4.35 | I22: 2 | J22: 97.33 | K22: 75.9 | L22: 128.2 | M22: 21 | N22: WASTE
A23: decolure | B23: Branded | D23: 355 | E23: 75 | F23: 1.66 | G23: 1.28 | H23: 12 | I23: 9 | J23: 96.22 | K23: 314.12 | L23: 30.6 | N23: GROWTH-ACCEPTABLE
A24: queen cooling sheets | B24: Highly Relevant | C24: Cooling|Queen | D24: 4728 | E24: 88 | F24: 1.56 | G24: 1.04 | H24: 4.55 | I24: 4 | J24: 91.91 | K24: 139.84 | L24: 65.7 | M24: 21 | N24: WASTE
A25: king size cooling sheets set | B25: Highly Relevant | D25: 203 | E25: 25 | F25: 10.2 | G25: 3.54 | H25: 16 | I25: 4 | J25: 88.49 | K25: 153.8 | L25: 57.5 | M25: 69 | N25: MARGINAL(45-60)
A26: cooling sheets full | B26: Highly Relevant | C26: Cooling|Full | D26: 1216 | E26: 67 | F26: 8.63 | G26: 1.26 | H26: 7.46 | I26: 5 | J26: 84.7 | K26: 177.93 | L26: 47.6 | M26: 46 | N26: MARGINAL(45-60)
A27: queen size cooling sheets | B27: Highly Relevant | C27: Cooling|Queen | D27: 2632 | E27: 67 | F27: 1.14 | G27: 1.24 | H27: 4.48 | I27: 3 | J27: 82.81 | K27: 111.95 | L27: 74 | M27: 25 | N27: WASTE
A28: cooling queen sheet set | B28: Highly Relevant | C28: Cooling|Queen | D28: 1023 | E28: 40 | F28: 1.6 | G28: 1.91 | H28: 5 | I28: 2 | J28: 76.57 | K28: 90.9 | L28: 84.2 | M28: 37 | N28: WASTE
A29: cal king cooling sheets | B29: Highly Relevant | C29: Cooling|California King | D29: 672 | E29: 48 | F29: 3.77 | G29: 1.59 | H29: 4.17 | I29: 2 | J29: 76.29 | K29: 71.91 | L29: 106.1 | M29: 42 | N29: WASTE
A30: queen sheets cooling | B30: Highly Relevant | C30: Cooling|Queen | D30: 4964 | E30: 45 | F30: 5.47 | G30: 1.62 | H30: 8.89 | I30: 4 | J30: 72.97 | K30: 151.8 | L30: 48.1 | M30: 57 | N30: MARGINAL(45-60)
A31: queen sheets | B31: Generic | D31: 141869 | E31: 115 | F31: 4.07 | G31: 0.62 | H31: 5.22 | I31: 6 | J31: 71.22 | K31: 217.8 | L31: 32.7 | N31: GROWTH-ACCEPTABLE
A32: cooling sheets queen size | B32: Highly Relevant | C32: Cooling|Queen | D32: 924 | E32: 65 | F32: 3.16 | G32: 1 | H32: 3.08 | I32: 2 | J32: 65.13 | K32: 74 | L32: 88 | M32: 32 | N32: WASTE
A33: king cooling sheet set | B33: Highly Relevant | C33: Cooling|King | D33: 644 | E33: 18 | F33: 8.22 | G33: 3.53 | H33: 0 | I33: 0 | J33: 63.55 | K33: 0 | M33: 104 | N33: WASTE
A34: cooling bed sheets full | B34: Highly Relevant | C34: Cooling|Full | D34: 924 | E34: 28 | F34: 22.4 | G34: 2.18 | H34: 10.71 | I34: 3 | J34: 60.96 | K34: 107.85 | L34: 56.5 | M34: 46 | N34: MARGINAL(45-60)
A35: queen bed set | B35: Generic | D35: 18413 | E35: 104 | F35: 3.19 | G35: 0.58 | H35: 2.88 | I35: 3 | J35: 59.9 | K35: 111.95 | L35: 53.5 | N35: MARGINAL(45-60)
A36: king sheets bamboo cooling | B36: Highly Relevant | C36: Bamboo|Cooling | D36: 412 | E36: 10 | F36: 20.41 | G36: 5.92 | H36: 10 | I36: 1 | J36: 59.16 | K36: 75.9 | L36: 77.9 | M36: 48 | N36: WASTE
A37: queen sheet set | B37: Generic | D37: 113557 | E37: 84 | F37: 0.49 | G37: 0.69 | H37: 1.19 | I37: 1 | J37: 57.69 | K37: 37.95 | L37: 152 | N37: WASTE
A38: deep pocket cooling queen sheets | B38: Highly Relevant | D38: 111 | E38: 20 | F38: 16.26 | G38: 2.86 | H38: 0 | I38: 0 | J38: 57.15 | K38: 0 | M38: 132 | N38: WASTE
A39: sheets queen size bed set | B39: Generic | D39: 40723 | E39: 81 | F39: 0.85 | G39: 0.7 | H39: 6.17 | I39: 5 | J39: 56.55 | K39: 187.85 | L39: 30.1 | N39: GROWTH-ACCEPTABLE
A40: chair covers for dining chairs | B40: Not Relevant | E40: 117 | F40: 0.57 | G40: 0.45 | H40: 11.97 | I40: 14 | J40: 52.53 | K40: 405.85 | L40: 12.9 | N40: PROFITABLE
A41: red satin sheets | B41: Not Relevant | E41: 117 | F41: 2.03 | G41: 0.45 | H41: 7.69 | I41: 9 | J41: 52.28 | K41: 255.4 | L41: 20.5 | N41: PROFITABLE
A42: king sheet set cooling | B42: Highly Relevant | C42: Cooling|King | D42: 1023 | E42: 17 | F42: 12.32 | G42: 2.96 | H42: 0 | I42: 0 | J42: 50.31 | K42: 0 | M42: 63 | N42: WASTE
A43: cooling sheets king | B43: Highly Relevant | C43: Cooling|King | D43: 2630 | E43: 28 | F43: 10.89 | G43: 1.78 | H43: 17.86 | I43: 5 | J43: 49.89 | K43: 211.75 | L43: 23.6 | M43: 56 | N43: PROFITABLE
A44: best cooling sheets for hot sleepers | B44: Highly Relevant | C44: Cooling | D44: 575 | E44: 18 | F44: 11.61 | G44: 2.76 | H44: 0 | I44: 0 | J44: 49.66 | K44: 0 | N44: WASTE
A45: bamboo sheets king size | B45: Relevant | C45: Bamboo|King | D45: 21541 | E45: 64 | F45: 5.34 | G45: 0.76 | H45: 9.38 | I45: 6 | J45: 48.67 | K45: 233.69 | L45: 20.8 | M45: 94 | N45: PROFITABLE
A46: twin cooling sheets | B46: Highly Relevant | C46: Cooling|Twin | D46: 1305 | E46: 26 | F46: 2.12 | G46: 1.84 | H46: 7.69 | I46: 2 | J46: 47.78 | K46: 93.93 | L46: 50.9 | M46: 23 | N46: MARGINAL(45-60)
A47: silk sheets | B47: Not Relevant | D47: 51852 | E47: 84 | F47: 3.38 | G47: 0.55 | H47: 7.14 | I47: 6 | J47: 46.51 | K47: 176 | L47: 26.4 | N47: PROFITABLE
A48: cooling soft sheets | B48: Highly Relevant | C48: Cooling | D48: 401 | E48: 12 | F48: 13.64 | G48: 3.73 | H48: 0 | I48: 0 | J48: 44.72 | K48: 0 | N48: LOW-DATA
A49: summer bedding sets queen | B49: Lower Relevant | D49: 1817 | E49: 71 | F49: 6.51 | G49: 0.59 | H49: 1.41 | I49: 1 | J49: 41.68 | K49: 37.95 | L49: 109.8 | N49: WASTE
A50: sheets king size cooling | B50: Highly Relevant | C50: Cooling|King | D50: 369 | E50: 11 | F50: 22.45 | G50: 3.72 | H50: 9.09 | I50: 1 | J50: 40.87 | K50: 39.95 | L50: 102.3 | N50: WASTE
A51: king size sheets bamboo cooling | B51: Highly Relevant | C51: Bamboo|Cooling | D51: 308 | E51: 10 | F51: 17.54 | G51: 4.06 | H51: 0 | I51: 0 | J51: 40.65 | K51: 0 | N51: LOW-DATA
A52: bamboo cooling sheets queen | B52: Highly Relevant | C52: Bamboo|Cooling | D52: 2271 | E52: 33 | F52: 8.51 | G52: 1.15 | H52: 6.06 | I52: 2 | J52: 37.91 | K52: 73.99 | L52: 51.2 | M52: 66 | N52: MARGINAL(45-60)
A53: satin sheets queen size | B53: Not Relevant | D53: 7792 | E53: 77 | F53: 3.13 | G53: 0.48 | H53: 10.39 | I53: 8 | J53: 37.16 | K53: 222.85 | L53: 16.7 | N53: PROFITABLE
A54: cooling sheets queen deep pockets | B54: Highly Relevant | C54: Cooling|Queen | D54: 695 | E54: 32 | F54: 6.25 | G54: 1.13 | H54: 0 | I54: 0 | J54: 36.3 | K54: 0 | M54: 125 | N54: WASTE
A55: queen bed sheets | B55: Generic | D55: 56962 | E55: 62 | F55: 3.66 | G55: 0.58 | H55: 6.45 | I55: 4 | J55: 36.02 | K55: 151.8 | L55: 23.7 | N55: PROFITABLE
A56: bamboo sheets queen size | B56: Relevant | C56: Bamboo|Queen | D56: 30200 | E56: 59 | F56: 4.28 | G56: 0.6 | H56: 16.95 | I56: 10 | J56: 35.27 | K56: 424.74 | L56: 8.3 | M56: 97 | N56: PROFITABLE
A57: deep pocket cooling sheets | B57: Highly Relevant | C57: Cooling | D57: 901 | E57: 16 | F57: 27.59 | G57: 2.2 | H57: 0 | I57: 0 | J57: 35.24 | K57: 0 | M57: 118 | N57: WASTE
A58: cooling full size sheets | B58: Highly Relevant | C58: Cooling|Full | D58: 822 | E58: 32 | F58: 8.23 | G58: 1.09 | H58: 9.38 | I58: 3 | J58: 34.93 | K58: 145.8 | L58: 24 | M58: 81 | N58: PROFITABLE
A59: bed sheet cooling | B59: Relevant | C59: Cooling | D59: 250 | E59: 9 | F59: 26.47 | G59: 3.75 | H59: 11.11 | I59: 1 | J59: 33.71 | K59: 35.95 | L59: 93.8 | N59: WASTE
A60: bedelite bamboo viscose sheets - 100% organically grown, up to 18" deep pocket queen sheet set, all round elastic & corner straps, luxury silky soft cooling sheets for hot sleepers, 4 pieces, white | B60: Branded | D60: 2177 | E60: 28 | F60: 1.13 | G60: 1.17 | H60: 3.57 | I60: 1 | J60: 32.89 | K60: 35.95 | L60: 91.5 | N60: WASTE
A61: bed sheets king size cooling | B61: Highly Relevant | C61: Cooling|King | D61: 580 | E61: 13 | F61: 20.31 | G61: 2.52 | H61: 7.69 | I61: 1 | J61: 32.72 | K61: 39.95 | L61: 81.9 | N61: WASTE
A62: queen bedding sets | B62: Generic | D62: 27749 | E62: 55 | F62: 2.34 | G62: 0.59 | H62: 0 | I62: 0 | J62: 32.27 | K62: 0 | N62: WASTE
A63: black cooling sheets | B63: Highly Relevant | C63: Cooling | D63: 924 | E63: 23 | F63: 1.23 | G63: 1.37 | H63: 0 | I63: 0 | J63: 31.62 | K63: 0 | M63: 43 | N63: WASTE
A64: satin sheets | B64: Not Relevant | D64: 30210 | E64: 57 | F64: 3.76 | G64: 0.55 | H64: 7.02 | I64: 4 | J64: 31.59 | K64: 135.01 | L64: 23.4 | N64: PROFITABLE
A65: cooling bed set | B65: Lower Relevant | D65: 1109 | E65: 49 | F65: 8.39 | G65: 0.62 | H65: 0 | I65: 0 | J65: 30.22 | K65: 0 | M65: 19 | N65: WASTE
A66: silk sheets queen | B66: Not Relevant | D66: 15189 | E66: 58 | F66: 2.35 | G66: 0.52 | H66: 3.45 | I66: 2 | J66: 29.97 | K66: 63.44 | L66: 47.2 | N66: MARGINAL(45-60)
A67: queen comforter set | B67: Not Relevant | D67: 186091 | E67: 49 | F67: 4.84 | G67: 0.59 | H67: 4.08 | I67: 2 | J67: 28.77 | K67: 74 | L67: 38.9 | N67: GROWTH-ACCEPTABLE(low orders)
A68: bed sheets king cooling | B68: Relevant | D68: 37 | E68: 6 | F68: 26.09 | G68: 4.76 | H68: 0 | I68: 0 | J68: 28.55 | K68: 0 | N68: LOW-DATA
A69: california king sheet sets | B69: Generic | D69: 43812 | E69: 51 | F69: 4.64 | G69: 0.54 | H69: 3.92 | I69: 2 | J69: 27.76 | K69: 77.9 | L69: 35.6 | N69: GROWTH-ACCEPTABLE(low orders)
A70: silk bed sheets | B70: Not Relevant | D70: 12374 | E70: 53 | F70: 2.71 | G70: 0.52 | H70: 1.89 | I70: 1 | J70: 27.72 | K70: 17.95 | L70: 154.4 | N70: WASTE
A71: cool sheets queen | B71: Highly Relevant | C71: Cooling|Queen | D71: 766 | E71: 27 | F71: 12.39 | G71: 1 | H71: 14.81 | I71: 4 | J71: 27.09 | K71: 151.77 | L71: 17.8 | M71: 34 | N71: PROFITABLE
A72: chair covers | B72: Not Relevant | E72: 60 | F72: 0.81 | G72: 0.44 | H72: 6.67 | I72: 4 | J72: 26.64 | K72: 86.96 | L72: 30.6 | N72: GROWTH-ACCEPTABLE(low orders)
A73: queen size sheets | B73: Generic | D73: 25566 | E73: 43 | F73: 5.42 | G73: 0.61 | H73: 2.33 | I73: 1 | J73: 26.23 | K73: 37.95 | L73: 69.1 | N73: WASTE
A74: full size cooling sheets | B74: Highly Relevant | C74: Cooling|Full | D74: 1735 | E74: 25 | F74: 19.23 | G74: 1.05 | H74: 8 | I74: 2 | J74: 26.21 | K74: 73.9 | L74: 35.5 | M74: 62 | N74: GROWTH-ACCEPTABLE(low orders)
A75: gold satin sheets | B75: Not Relevant | E75: 59 | F75: 2.46 | G75: 0.43 | H75: 27.12 | I75: 16 | J75: 25.29 | K75: 532.64 | L75: 4.7 | N75: PROFITABLE
A76: queen size 4 piece sheet set - comfy breathable & cooling sheets - hotel luxury bed sheets for women & men - deep pockets, easy-fit, extra soft and wrinkle free sheets - white oeko-tex bed sheet set | B76: Not Relevant | D76: 94713 | E76: 41 | F76: 3.14 | G76: 0.59 | H76: 4.88 | I76: 2 | J76: 24.04 | K76: 75.9 | L76: 31.7 | N76: GROWTH-ACCEPTABLE(low orders)
A77: bed sheets queen size | B77: Generic | D77: 39916 | E77: 41 | F77: 6.04 | G77: 0.58 | H77: 2.44 | I77: 1 | J77: 23.77 | K77: 37.95 | L77: 62.6 | N77: WASTE
A78: cool sheets for hot sleepers | B78: Highly Relevant | C78: Cooling | D78: 1961 | E78: 13 | F78: 2.34 | G78: 1.82 | H78: 15.38 | I78: 2 | J78: 23.63 | K78: 77.9 | L78: 30.3 | M78: 55 | N78: GROWTH-ACCEPTABLE(low orders)
A79: bed set | B79: Generic | D79: 16092 | E79: 41 | F79: 3.15 | G79: 0.58 | H79: 0 | I79: 0 | J79: 23.58 | K79: 0 | N79: WASTE
A80: deep pocket queen sheets | B80: Generic | D80: 44089 | E80: 40 | F80: 4.66 | G80: 0.59 | H80: 0 | I80: 0 | J80: 23.55 | K80: 0 | N80: WASTE
A81: bed sheets | B81: Generic | D81: 158688 | E81: 43 | F81: 0.18 | G81: 0.54 | H81: 4.65 | I81: 2 | J81: 23.24 | K81: 75.9 | L81: 30.6 | N81: GROWTH-ACCEPTABLE(low orders)
A82: bed set queen size | B82: Generic | D82: 12710 | E82: 39 | F82: 3.41 | G82: 0.59 | H82: 0 | I82: 0 | J82: 22.84 | K82: 0 | N82: WASTE
A83: queen sheets set cooling | B83: Highly Relevant | C83: Cooling|Queen | D83: 392 | E83: 12 | F83: 24 | G83: 1.89 | H83: 16.67 | I83: 2 | J83: 22.66 | K83: 112.94 | L83: 20.1 | N83: PROFITABLE
A84: queen size comforter sets | B84: Not Relevant | D84: 36126 | E84: 39 | F84: 3.57 | G84: 0.58 | H84: 0 | I84: 0 | J84: 22.57 | K84: 0 | N84: WASTE
A85: king size cooling sheets | B85: Highly Relevant | C85: Cooling|King | D85: 4967 | E85: 38 | F85: 10.7 | G85: 0.59 | H85: 0 | I85: 0 | J85: 22.42 | K85: 0 | M85: 26 | N85: WASTE
A86: cooling blanket | B86: Not Relevant | E86: 37 | F86: 2.04 | G86: 0.59 | H86: 0 | I86: 0 | J86: 21.83 | K86: 0 | N86: WASTE
A87: queen size sheet set | B87: Generic | D87: 9249 | E87: 34 | F87: 13.23 | G87: 0.62 | H87: 14.71 | I87: 5 | J87: 21.19 | K87: 185.95 | L87: 11.4 | N87: PROFITABLE
A88: queen sheets deep pocket | B88: Generic | D88: 19613 | E88: 36 | F88: 3.43 | G88: 0.59 | H88: 0 | I88: 0 | J88: 21.16 | K88: 0 | N88: WASTE
A89: queen size bed sheets cooling | B89: Highly Relevant | C89: Cooling|Queen | D89: 649 | E89: 15 | F89: 8.93 | G89: 1.39 | H89: 20 | I89: 3 | J89: 20.79 | K89: 113.84 | L89: 18.3 | M89: 34 | N89: PROFITABLE
A90: king cooling sheets | B90: Highly Relevant | C90: Cooling|King | D90: 3271 | E90: 20 | F90: 12.35 | G90: 1.03 | H90: 0 | I90: 0 | J90: 20.62 | K90: 0 | M90: 66 | N90: WASTE
A91: cooling comforter set | B91: Not Relevant | D91: 1245 | E91: 34 | F91: 10.4 | G91: 0.59 | H91: 0 | I91: 0 | J91: 20.06 | K91: 0 | N91: WASTE
A92: cooling bedding set | B92: Lower Relevant | D92: 1093 | E92: 34 | F92: 9.97 | G92: 0.58 | H92: 2.94 | I92: 1 | J92: 19.79 | K92: 46.95 | L92: 42.2 | M92: 81 | N92: GROWTH-ACCEPTABLE(low orders)
A93: king size sheets | B93: Generic | D93: 33249 | E93: 34 | F93: 5.27 | G93: 0.58 | H93: 0 | I93: 0 | J93: 19.58 | K93: 0 | N93: WASTE
A94: queen comforter set cooling | B94: Not Relevant | D94: 908 | E94: 33 | F94: 12.13 | G94: 0.59 | H94: 6.06 | I94: 2 | J94: 19.43 | K94: 75.9 | L94: 25.6 | N94: PROFITABLE
A95: comforters queen size | B95: Not Relevant | D95: 89804 | E95: 33 | F95: 2.92 | G95: 0.59 | H95: 9.09 | I95: 3 | J95: 19.4 | K95: 113.85 | L95: 17 | N95: PROFITABLE
A96: king size comforter set cooling | B96: Not Relevant | D96: 1224 | E96: 32 | F96: 11.72 | G96: 0.59 | H96: 3.13 | I96: 1 | J96: 18.84 | K96: 39.95 | L96: 47.2 | N96: MARGINAL(45-60)
A97: * | B97: Not Relevant | E97: 52 | F97: 6.08 | G97: 0.35 | H97: 0 | I97: 0 | J97: 18.01 | K97: 0 | N97: WASTE
A98: bedding | B98: Generic | D98: 56164 | E98: 32 | F98: 4.04 | G98: 0.56 | H98: 3.13 | I98: 1 | J98: 17.89 | K98: 33.96 | L98: 52.7 | N98: MARGINAL(45-60)
A99: cooling bed set queen | B99: Lower Relevant | D99: 639 | E99: 27 | F99: 23.08 | G99: 0.66 | H99: 11.11 | I99: 3 | J99: 17.82 | K99: 111.95 | L99: 15.9 | M99: 48 | N99: PROFITABLE
A100: full size comforter sets | B100: Not Relevant | D100: 33924 | E100: 30 | F100: 4.68 | G100: 0.59 | H100: 3.33 | I100: 1 | J100: 17.61 | K100: 35.95 | L100: 49 | N100: MARGINAL(45-60)
A101: dining chair covers set of 6 | B101: Not Relevant | E101: 40 | F101: 0.18 | G101: 0.44 | H101: 7.5 | I101: 3 | J101: 17.57 | K101: 85.97 | L101: 20.4 | N101: PROFITABLE
...

Sheet Rank_History
A1: Organic rank history — Sleephoria (DataDive Rank Radar B0FTSWF3M7, monthly median) & Decolure (command-center crawl)
A2: Rank 101/999 = not ranked in top 100. Sleephoria spend context: Oct-25 $608/day, Jan-26 $53/day, Jul-26 $65/day, Aug–Sep-26 $212–247/day.
A4: Keyword (Sleephoria) | B4: DataDive SV | C4: 2025-10 | D4: 2025-11 | E4: 2025-12 | F4: 2026-01 | G4: 2026-02 | H4: 2026-03 | I4: 2026-04 | J4: 2026-05 | K4: 2026-06 | L4: 2026-07 | M4: 2026-08 | N4: 2026-09 | O4: 2026-10 | P4: top10_days_last30 | Q4: first_top20 | R4: first_top10 | S4: best
A5: cooling sheets | B5: 116610 | C5: 5 | D5: 6 | E5: 12 | F5: 14 | G5: 4.5 | H5: 3 | I5: 4 | J5: 19 | K5: 42 | L5: 101 | M5: 9 | N5: 16 | O5: 18 | P5: 1 | Q5: 2025-10-07 | R5: 2025-10-13 | S5: (1, '2026-04-22')
A6: cooling sheets queen | B6: 39490 | C6: 5 | D6: 5 | E6: 18 | F6: 67 | G6: 11 | H6: 8 | I6: 9.5 | J6: 24 | K6: 42 | L6: 101 | M6: 39 | N6: 33 | O6: 45 | P6: 0 | Q6: 2025-10-11 | R6: 2025-10-12 | S6: (2, '2025-10-23')
A7: cooling sheets king size | B7: 25230 | C7: 8 | D7: 5 | E7: 90 | F7: 17 | G7: 6 | H7: 5 | I7: 6 | J7: 14 | K7: 24 | L7: 46 | M7: 47 | N7: 11 | O7: 17 | P7: 16 | Q7: 2025-10-11 | R7: 2025-10-12 | S7: (2, '2026-03-22')
A8: cooling bed sheets | B8: 15460 | C8: 5 | D8: 6 | E8: 11 | F8: 12 | G8: 9 | H8: 5 | I8: 4 | J8: 17 | K8: 22.5 | L8: 39 | M8: 20 | N8: 16.5 | O8: 18 | P8: 1 | Q8: 2025-10-10 | R8: 2025-10-12 | S8: (1, '2026-03-21')
A9: bed cooling system | B9: 11955 | L9: 101 | M9: 101 | N9: 101 | O9: 101 | P9: 0
A10: king sheets cooling | B10: 6385 | C10: 41.5 | D10: 30.5 | E10: 101 | F10: 77 | G10: 37.5 | H10: 31 | I10: 30 | J10: 56 | K10: 83.5 | L10: 101 | M10: 101 | N10: 29 | O10: 10 | P10: 9 | Q10: 2026-02-12 | R10: 2026-09-21 | S10: (7, '2026-09-21')
A11: cooling sheets full size | B11: 6126 | C11: 8 | D11: 4.5 | E11: 17 | F11: 12 | G11: 5 | H11: 5 | I11: 5 | J11: 5 | K11: 75 | L11: 24 | M11: 19 | N11: 17 | O11: 21 | P11: 2 | Q11: 2025-10-13 | R11: 2025-10-14 | S11: (2, '2026-03-23')
A12: king size cooling sheets | B12: 5975 | C12: 8 | D12: 8 | E12: 101 | F12: 18 | G12: 7 | H12: 7 | I12: 6 | J12: 10 | K12: 34 | L12: 31 | M12: 27 | N12: 8.5 | O12: 4 | P12: 24 | Q12: 2025-10-09 | R12: 2025-10-14 | S12: (2, '2026-04-02')
A13: queen sheets cooling | B13: 5790 | C13: 13 | D13: 8 | E13: 17 | F13: 49 | G13: 11 | H13: 11 | I13: 18 | J13: 39 | K13: 59 | L13: 101 | M13: 101 | N13: 48 | O13: 64 | P13: 0 | Q13: 2025-10-12 | R13: 2025-10-15 | S13: (4, '2025-10-17')
A14: queen cooling sheets | B14: 5358 | C14: 5.5 | D14: 5 | E14: 12 | F14: 56 | G14: 10 | H14: 11 | I14: 18 | J14: 49 | K14: 46.5 | L14: 101 | M14: 101 | N14: 39 | O14: 13 | P14: 0 | Q14: 2025-10-10 | R14: 2025-10-12 | S14: (3, '2025-11-08')
A15: king size sheets set cooling | B15: 5292 | C15: 101 | D15: 101 | E15: 101 | K15: 63 | L15: 101 | M15: 101 | N15: 55.5 | O15: 51 | P15: 0 | Q15: 2026-09-21 | S15: (12, '2026-09-21')
A16: cooling sheets king | B16: 5075 | C16: 25 | D16: 15 | E16: 101 | F16: 24 | G16: 10 | H16: 8 | I16: 15 | J16: 27 | K16: 43.5 | L16: 101 | M16: 83 | N16: 19 | O16: 22 | P16: 4 | Q16: 2025-10-09 | R16: 2025-10-15 | S16: (4, '2026-03-19')
A17: king cooling sheets | B17: 4713 | C17: 14 | D17: 15.5 | E17: 101 | F17: 48 | G17: 10 | H17: 11 | I17: 16 | J17: 24 | K17: 39 | L17: 85 | M17: 82 | N17: 19 | O17: 17 | P17: 5 | Q17: 2025-10-12 | R17: 2025-10-13 | S17: (5, '2026-02-14')
A18: cooling bed sheets queen | B18: 4300 | C18: 5 | D18: 4 | E18: 8 | F18: 13 | G18: 7 | H18: 5 | I18: 4 | J18: 10 | K18: 57 | L18: 101 | M18: 53 | N18: 12 | O18: 9 | P18: 11 | Q18: 2025-10-09 | R18: 2025-10-11 | S18: (1, '2026-03-21')
A19: cooling king sheets | B19: 4030 | C19: 10 | D19: 10 | E19: 101 | F19: 46 | G19: 14 | H19: 9 | I19: 10 | J19: 22 | K19: 40.5 | L19: 101 | M19: 69 | N19: 20 | O19: 17 | P19: 2 | Q19: 2025-10-10 | R19: 2025-10-13 | S19: (5, '2025-11-13')
A20: hot sleepers must haves | B20: 3865 | L20: 101 | M20: 101 | N20: 101 | O20: 101 | P20: 0 | S20: (82, '2026-08-06')
A21: cooling fitted sheet | B21: 3701 | K21: 101 | L21: 101 | M21: 101 | N21: 101 | O21: 101 | P21: 0 | S21: (89, '2026-10-06')
A22: bed cooling | B22: 3606 | L22: 101 | M22: 101 | N22: 71 | O22: 69 | P22: 0 | S22: (44, '2026-10-07')
A23: oeko-tex sheets | B23: 3203 | L23: 101 | M23: 101 | N23: 101 | O23: 101 | P23: 0
A24: queen size cooling sheets | B24: 2948 | C24: 8 | D24: 5 | E24: 8 | F24: 54 | G24: 7 | H24: 6 | I24: 8 | J24: 18 | K24: 34 | L24: 93 | M24: 35 | N24: 36 | O24: 39 | P24: 2 | Q24: 2025-10-12 | R24: 2025-10-16 | S24: (2, '2026-03-20')
A25: cooling queen sheets | B25: 2892 | C25: 5 | D25: 6 | E25: 13 | F25: 50 | G25: 15.5 | H25: 11 | I25: 18 | J25: 51 | K25: 30.5 | L25: 101 | M25: 54 | N25: 17.5 | O25: 15 | P25: 9 | Q25: 2025-10-12 | R25: 2025-10-13 | S25: (4, '2025-10-15')
A26: cooling bed | B26: 2826 | L26: 101 | M26: 101 | N26: 101 | O26: 101 | P26: 0 | S26: (67, '2026-09-20')
A27: cool sheets | B27: 2709 | C27: 5 | D27: 6 | E27: 8 | F27: 24 | G27: 6 | H27: 6 | I27: 6 | J27: 10 | K27: 31 | L27: 37 | M27: 39 | N27: 19 | O27: 11 | P27: 10 | Q27: 2025-10-10 | R27: 2025-10-12 | S27: (1, '2025-10-20')
A28: cooling sheets twin | B28: 2689 | C28: 4 | D28: 4 | E28: 101 | F28: 10 | G28: 2 | H28: 2 | I28: 2 | J28: 3 | K28: 8 | L28: 6 | M28: 3 | N28: 4 | O28: 5 | P28: 30 | Q28: 2025-10-04 | R28: 2025-10-05 | S28: (1, '2026-02-10')
A29: cooling fitted sheet queen | B29: 2641 | K29: 101 | L29: 101 | M29: 101 | N29: 101 | O29: 101 | P29: 0 | S29: (90, '2026-09-28')
A30: queen sheet set cooling | B30: 2597 | C30: 56.5 | D30: 36 | E30: 43 | F30: 92 | G30: 34.5 | H30: 28 | I30: 30 | J30: 59 | K30: 101 | L30: 101 | M30: 101 | N30: 73 | O30: 28 | P30: 1 | Q30: 2026-03-16 | R30: 2026-10-01 | S30: (9, '2026-10-01')
A31: cooling sheet set | B31: 2566 | C31: 34 | D31: 11.5 | E31: 9 | F31: 42 | G31: 21 | H31: 15 | I31: 13.5 | J31: 56 | K31: 87.5 | L31: 101 | M31: 52 | N31: 35 | O31: 38 | P31: 2 | Q31: 2025-10-17 | R31: 2025-10-28 | S31: (4, '2025-11-07')
A32: queen bed sheets cooling | B32: 2560 | C32: 10 | D32: 9 | E32: 17 | F32: 67 | G32: 16 | H32: 14 | I32: 7.5 | J32: 22 | K32: 60.5 | L32: 84 | M32: 75 | N32: 33 | O32: 30 | P32: 0 | Q32: 2025-10-14 | R32: 2025-10-15 | S32: (4, '2026-04-05')
A33: full size cooling sheets | B33: 2174 | C33: 20.5 | D33: 8 | E33: 28 | F33: 17 | G33: 11 | H33: 8 | I33: 9 | J33: 9 | K33: 90 | L33: 38 | M33: 29 | N33: 27.5 | O33: 20 | P33: 3 | Q33: 2025-10-14 | R33: 2025-10-16 | S33: (4, '2025-10-20')
A34: cool sheets for hot sleepers | B34: 2161 | C34: 24 | D34: 11 | E34: 8 | F34: 9 | G34: 9 | H34: 7 | I34: 8 | J34: 13 | K34: 27 | L34: 61 | M34: 41 | N34: 18 | O34: 13 | P34: 9 | Q34: 2025-10-11 | R34: 2025-10-13 | S34: (2, '2026-03-18')
A35: cooling sheet | B35: 2137 | C35: 8.5 | D35: 7 | E35: 14 | F35: 16 | G35: 10 | H35: 6 | I35: 9 | J35: 23 | K35: 51 | L35: 101 | M35: 24 | N35: 15.5 | O35: 15 | P35: 0 | Q35: 2025-10-14 | R35: 2025-10-14 | S35: (2, '2026-02-26')
A36: best cooling sheets | B36: 1821 | C36: 35.5 | D36: 14 | E36: 20 | F36: 32 | G36: 10.5 | H36: 9 | I36: 15.5 | J36: 22 | K36: 68 | L36: 52 | M36: 48 | N36: 23 | O36: 16 | P36: 8 | Q36: 2025-10-17 | R36: 2025-11-11 | S36: (4, '2026-03-15')
A37: cooling fitted sheet king | B37: 1768 | J37: 101 | L37: 101 | M37: 101 | N37: 101 | O37: 101 | P37: 0 | Q37: 2026-08-21 | S37: (16, '2026-08-21')
A38: cooling bed sheets king | B38: 1725 | C38: 9 | D38: 11.5 | E38: 73 | F38: 101 | G38: 34.5 | H38: 35 | I38: 41 | J38: 55 | K38: 45.5 | L38: 101 | M38: 76 | N38: 10.5 | O38: 16 | P38: 14 | Q38: 2025-10-12 | R38: 2025-10-16 | S38: (2, '2026-09-17')
A39: king bed sheets cooling | B39: 1692 | C39: 20.5 | D39: 23 | E39: 101 | F39: 101 | G39: 51 | H39: 49 | I39: 54 | J39: 62 | K39: 58 | L39: 101 | M39: 101 | N39: 26 | O39: 19 | P39: 3 | Q39: 2025-10-15 | R39: 2025-10-16 | S39: (9, '2025-10-20')
A40: cooling sheets full | B40: 1586 | C40: 6 | D40: 6 | E40: 81 | F40: 13 | G40: 6 | H40: 8 | I40: 6 | J40: 5 | K40: 101 | L40: 17 | M40: 11 | N40: 17.5 | O40: 18 | P40: 8 | Q40: 2025-10-12 | R40: 2025-10-15 | S40: (1, '2026-04-21')
A41: full size sheets cooling | B41: 1519 | C41: 31.5 | D41: 11.5 | E41: 30 | F41: 29 | G41: 12.5 | H41: 11 | I41: 12 | J41: 14 | K41: 92.5 | L41: 56 | M41: 36 | N41: 35 | O41: 33 | P41: 0 | Q41: 2025-10-16 | R41: 2025-10-16 | S41: (5, '2025-10-16')
A42: deep pocket cooling sheets | B42: 1505 | C42: 20 | D42: 23 | E42: 30 | F42: 101 | G42: 92.5 | H42: 25 | I42: 26 | J42: 49 | K42: 63 | L42: 101 | M42: 101 | N42: 42 | O42: 14 | P42: 6 | Q42: 2025-10-12 | R42: 2025-10-15 | S42: (5, '2026-09-27')
A43: king sheet set cooling | B43: 1485 | C43: 31 | D43: 40 | E43: 101 | F43: 101 | G43: 91.5 | H43: 71 | I43: 94.5 | J43: 101 | K43: 63.5 | L43: 101 | M43: 101 | N43: 68 | O43: 77 | P43: 0 | Q43: 2025-10-15 | R43: 2025-10-17 | S43: (7, '2025-10-18')
A44: sheets cooling | B44: 1459 | C44: 7.5 | D44: 8 | E44: 9 | F44: 20 | G44: 9 | H44: 5 | I44: 4.5 | J44: 19 | K44: 67.5 | L44: 101 | M44: 9 | N44: 9.5 | O44: 12 | P44: 15 | Q44: 2025-10-13 | R44: 2025-10-15 | S44: (2, '2025-10-18')
A46: Decolure rank summary (1 Apr 2025 → 7 Oct 2026)
A47: Keyword (Decolure) | B47: Best rank | C47: Best date | D47: Days top 10 | E47: Days top 20 | F47: Monthly median rank (Apr-25 → Oct-26)
A48: cooling sheets | B48: 4 | C48: 2025-04-25 | D48: 38 | E48: 114 | F48: 2025-04:9;2025-05:9;2025-06:19;2025-07:20;2025-08:31;2025-09:39;2025-10:51;2025-11:40;2025-12:19;2026-01:28;2026-02:35;2026-03:37;2026-04:58;2026-05:74;2026-06:124;2026-07:134;2026-08:NR;2026-09:NR;2026-10:144
A49: cooling sheets queen | B49: 3 | C49: 2025-04-25 | D49: 73 | E49: 166 | F49: 2025-04:12;2025-05:6;2025-06:8;2025-07:12;2025-08:23;2025-09:25;2025-10:41;2025-11:66;2025-12:82;2026-01:98;2026-02:89;2026-03:20;2026-04:23;2026-05:24;2026-06:30;2026-07:46;2026-08:NR;2026-09:129;2026-10:104
A50: cooling sheets king | B50: 10 | C50: 2025-04-27 | D50: 1 | E50: 90 | F50: 2025-04:58;2025-05:22;2025-06:18;2025-07:19;2025-08:18;2025-09:24;2025-10:37;2025-11:62;2025-12:80;2026-01:80;2026-02:58;2026-03:50;2026-04:56;2026-05:85;2026-06:NR;2026-07:NR;2026-08:NR;2026-09:113;2026-10:72
A51: cooling sheets king size | B51: 5 | C51: 2025-05-03 | D51: 29 | E51: 105 | F51: 2025-04:21;2025-05:9;2025-06:14;2025-07:18;2025-08:20;2025-09:77;2025-10:92;2025-11:37;2025-12:43;2026-01:42;2026-02:59;2026-03:37;2026-04:43;2026-05:62;2026-06:NR;2026-07:NR;2026-08:NR;2026-09:NR;2026-10:95
A52: cooling sheets full size | B52: 4 | C52: 2025-04-26 | D52: 63 | E52: 92 | F52: 2025-04:24;2025-05:6;2025-06:9;2025-07:29;2025-08:37;2025-09:41;2025-10:51;2025-11:25;2025-12:51;2026-01:65;2026-02:63;2026-03:68;2026-04:66;2026-05:127;2026-06:115;2026-07:104;2026-08:69;2026-09:64;2026-10:75
A53: cooling sheets twin | B53: 3 | C53: 2025-08-08 | D53: 102 | E53: 193 | F53: 2025-04:21;2025-05:11;2025-06:15;2025-07:11;2025-08:8;2025-09:9;2025-10:11;2025-11:12;2025-12:NR;2026-01:NR;2026-02:NR;2026-03:NR;2026-04:37;2026-05:63;2026-06:62;2026-07:65;2026-08:31;2026-09:47;2026-10:54
A54: cooling bed sheets | B54: 3 | C54: 2025-04-25 | D54: 95 | E54: 182 | F54: 2025-04:11;2025-05:6;2025-06:7;2025-07:8;2025-08:13;2025-09:19;2025-10:71;2025-11:27;2025-12:28;2026-01:27;2026-02:38;2026-03:30;2026-04:35;2026-05:23;2026-06:29;2026-07:49;2026-08:NR;2026-09:NR;2026-10:96
A55: cooling bed sheets queen | B55: 6 | C55: 2025-06-03 | D55: 73 | E55: 249 | F55: 2025-04:12;2025-05:10;2025-06:9;2025-07:12;2025-08:17;2025-09:12;2025-10:51;2025-11:39;2025-12:29;2026-01:30;2026-02:34;2026-03:23;2026-04:21;2026-05:20;2026-06:23;2026-07:39;2026-08:NR;2026-09:126;2026-10:122
A56: queen cooling sheets | B56: 4 | C56: 2025-06-18 | D56: 103 | E56: 260 | F56: 2025-04:8;2025-05:6;2025-06:6;2025-07:11;2025-08:18;2025-09:22;2025-10:39;2025-11:27;2025-12:30;2026-01:41;2026-02:77;2026-03:17;2026-04:16;2026-05:16;2026-06:19;2026-07:35;2026-08:NR;2026-09:131;2026-10:115
A57: bamboo cooling sheets | B57: 6 | C57: 2025-04-27 | D57: 12 | E57: 65 | F57: 2025-04:27;2025-05:21;2025-06:18;2025-07:22;2025-08:26;2025-09:35;2025-10:74;2025-11:73;2025-12:64;2026-01:50;2026-02:71;2026-03:67;2026-04:64;2026-05:61;2026-06:52;2026-07:46;2026-08:47;2026-09:NR;2026-10:141
A58: cooling sheets for hot sleepers | B58: 23 | C58: 2026-03-31 | D58: 0 | E58: 0 | F58: 2025-04:NR;2025-05:NR;2025-06:NR;2025-07:NR;2025-08:NR;2025-09:NR;2025-10:NR;2025-11:NR;2025-12:NR;2026-01:NR;2026-02:76;2026-03:71;2026-04:72;2026-05:30;2026-06:40;2026-07:NR;2026-08:NR;2026-09:NR;2026-10:NR
A59: bamboo sheets | B59: 27 | C59: 2025-12-30 | D59: 0 | E59: 0 | F59: 2025-04:NR;2025-05:NR;2025-06:NR;2025-07:NR;2025-08:NR;2025-09:72;2025-10:60;2025-11:92;2025-12:NR;2026-01:78;2026-02:93;2026-03:103;2026-04:101;2026-05:119;2026-06:NR;2026-07:101;2026-08:NR;2026-09:NR;2026-10:NR
... A61: bamboo sheets king size | B61: 42 | C61: 2026-04-07 | D61: 0 | E61: 0 | F61: 2025-04:NR;2025-05:NR;2025-06:NR;2025-07:NR;2025-08:NR;2025-09:48;2025-10:91;2025-11:98;2025-12:89;2026-01:91;2026-02:98;2026-03:106;2026-04:60;2026-05:63;2026-06:NR;2026-07:NR;2026-08:NR;2026-09:571;2026-10:99
A62: queen sheets | F62: ,,,
A63: sheets queen size bed set | F63: ,,,
A64: cooling sheets queen size | B64: 7 | C64: 2025-04-25 | D64: 50 | E64: 178 | F64: 2025-04:13;2025-05:13;2025-06:23;2025-07:31;2025-08:45;2025-09:48;2025-10:66;2025-11:52;2025-12:39;2026-01:35;2026-02:52;2026-03:34;2026-04:12;2026-05:10;2026-06:12;2026-07:19;2026-08:NR;2026-09:NR;2026-10:123
A65: queen bed sheets cooling | B65: 9 | C65: 2025-04-25 | D65: 7 | E65: 214 | F65: 2025-04:14;2025-05:13;2025-06:14;2025-07:19;2025-08:20;2025-09:25;2025-10:61;2025-11:52;2025-12:50;2026-01:43;2026-02:48;2026-03:39;2026-04:18;2026-05:14;2026-06:19;2026-07:41;2026-08:NR;2026-09:NR;2026-10:NR
A66: king size sheets set cooling | B66: 6 | C66: 2025-04-23 | D66: 74 | E66: 151 | F66: 2025-04:16;2025-05:10;2025-06:16;2025-07:9;2025-08:9;2025-09:81;2025-10:105;2025-11:109;2025-12:NR;2026-01:NR;2026-02:NR;2026-03:80;2026-04:78;2026-05:100;2026-06:85;2026-07:NR;2026-08:NR;2026-09:94;2026-10:68
A67: cooling sheets full | B67: 5 | C67: 2025-04-02 | D67: 41 | E67: 166 | F67: 2025-04:14;2025-05:11;2025-06:11;2025-07:15;2025-08:15;2025-09:24;2025-10:48;2025-11:22;2025-12:24;2026-01:62;2026-02:42;2026-03:37;2026-04:84;2026-05:135;2026-06:77;2026-07:94;2026-08:66;2026-09:72;2026-10:66
A68: twin cooling sheets | B68: 5 | C68: 2025-04-28 | D68: 87 | E68: 238 | F68: 2025-04:27;2025-05:8;2025-06:15;2025-07:15;2025-08:9;2025-09:10;2025-10:16;2025-11:22;2025-12:18;2026-01:20;2026-02:15;2026-03:24;2026-04:46;2026-05:77;2026-06:61;2026-07:73;2026-08:50;2026-09:72;2026-10:84
A69: cal king cooling sheets | B69: 10 | C69: 2026-09-24 | D69: 1 | E69: 6 | F69: 2025-04:NR;2025-05:NR;2025-06:NR;2025-07:NR;2025-08:NR;2025-09:NR;2025-10:NR;2025-11:NR;2025-12:NR;2026-01:NR;2026-02:NR;2026-03:NR;2026-04:33;2026-05:64;2026-06:43;2026-07:43;2026-08:41;2026-09:47;2026-10:35
A70: best cooling sheets for hot sleepers | F70: ,,,
A71: cooling sheets for hot sleepers queen | F71: ,,,
A72: microfiber sheets | D72: 0 | E72: 0 | F72: 2025-04:NR;2025-05:NR;2025-06:NR;2025-07:NR;2025-08:NR;2025-09:NR;2025-10:NR;2025-11:NR;2025-12:NR;2026-01:NR;2026-02:NR;2026-03:NR;2026-04:NR;2026-05:NR;2026-06:NR;2026-07:NR;2026-08:NR;2026-09:NR;2026-10:NR
A73: queen sheet set | F73: ,,,

Sheet Competitors
A1: Cooling-sheet competitor set (de-duplicated by parent)
A2: Sources: command-center hub snapshot 5 Oct 2026, ASINsight exports 28–29 Sep 2026, DataDive niches (May & 5 Oct 2026). Traffic = ASINsight 7-day impression-like figure, not sales. PREMIUM = $60+ Queen.
A4: brand | B4: parent_asin | C4: main_child | D4: type | E4: material_claim | F4: queen_or_ref_price | G4: band | H4: rating | I4: reviews | J4: bsr_latest | K4: est_sales | L4: est_revenue | M4: asinsight_7d_traffic | N4: ad_share_of_traffic | O4: sp_keywords | P4: notes
A5: REST Evercool+ | B5: B0HC6866B7 (+B0C56VXVB3) | C5: B0BLYSGFRW (King) / hub B0D9JJSNC5 | D5: 4pc + 3pc Starter (no flat) | E5: Evercool+ cooling yarn + silver ionic yarn | F5: King $261.75 (list $349); 4/6pc $164.25; Twin starter $141.75 | G5: PREMIUM | H5: 4.3 | I5: 1133 | J5: 8557 (Oct-05) | K5: 35/wk hub; 3946/mo DD May (King child) | L5: $1.03M/mo DD May | M5: 522593 | N5: 0.78 | O5: 3278 | P5: hot sleeper/night sweats/sensitive skin; SB on 3623 kw
A6: Breescape | B6: B0H41M1N4B (+B0DSPY326Y/B0H2797BXF) | C6: B0DSPZJKTB (King) / B0DSPZ9151 (Q) | D6: 4pc | E6: BlendTek Dry&Cool Q-Max>0.46; 18in pocket | F6: Q $159.99 (May); King $149.99 list $179.99 (Oct) | G6: PREMIUM | H6: 4.2 (old parents 3.8/72) | I6: 593 | J6: 62365 | K6: 35/wk hub; ~1540/mo DD May | L6: $246k/mo DD May (Q) | M6: 107224 | N6: 0.47 | O6: 529 | P6: SBV on 1163 kw; DD May 134 adv kw/44 TOS
A7: SHEEX | B7: B081KX96XD | C7: B00EWJS3PO (Q) / B00EWJHJU4 | D7: 4pc | E7: performance moisture-wicking fabric | F7: Q $149 (Oct); $239.20 (May) | G7: PREMIUM | H7: 4.5 | I7: 3254 | J7: 101244 | K7: 5/wk hub; 556/mo DD May | L7: $133k/mo DD May | M7: unmeasured | O7: 0 (DD May) | P7: no ASINsight export; top10 on 0/178 cooling kw (May)
A8: Elegear | B8: B0H7YWGBW3 | C8: B0GCHG6VG6 (Q) / hero B0GCHRGYZZ | D8: 4pc | E8: silver-infused Arc-Chill 3.0; 18in | F8: Q $89.99 (Oct); $86.44 (May) | G8: PREMIUM | H8: 4.4 | I8: 129 | J8: 179108 | K8: 5/wk hub; 276/mo DD May | L8: $23.9k DD May | M8: 15624 | N8: 0.39 | O8: 159 | P8: SB 292 kw; organic top10 on 1 cooling kw
A9: Bedsure Cooling (Chill Cool) | B9: B0CPDTJ5NN | C9: B0CPDR1RQ9 (King) / B0DGX391VC (CalK) / hub B0DGWZTTRL | D9: 4pc | E9: synthetic Chill Cool; 18in | F9: King $75.99 / CalK $82.99 (May); hub child $139.99 | G9: PREMIUM (King) | H9: 4.2-4.4 | I9: 401-508 | J9: 435989 (Oct) vs 44575 (May) | K9: 1104/mo DD May | L9: $83.9k DD May | M9: 170 (export incomplete) | P9: ASINsight export only 22 kw - unmeasured
A10: Bedsure PureWoven bamboo | B10: B0BZ8T5BJ6 | C10: B07YKCZHGK (Q) | D10: 4pc | E10: 100% rayon from bamboo | F10: Q $64.59-67.99 | G10: PREMIUM (edge) | H10: 4.4 | I10: 64995 | J10: 258 | K10: 809/wk hub; 29688/mo DD Oct | L10: $1.63M DD Oct | M10: 2166046 | N10: 0.41 | O10: 4052 | P10: cooling sheets org #2 + AC; avoid PAT
A11: Bedsure PureWoven Cooling | B11: B0FB8XS4D1 | C11: B0FB8XR43Q (Q) | D11: 4pc | E11: bamboo viscose 18in for hot sleepers | F11: Q $89.99 (list $119.99) | G11: PREMIUM | H11: 4.5 | I11: 568 | J11: 13496 | K11: 92/wk hub; 3062/mo DD Oct | L11: $276k DD Oct | M11: 840292 | N11: 0.86 | O11: 2689 | P11: cooling sheets queen SP#2
A12: Pure Bamboo | B12: B0CZQ52MTQ | C12: B07DZTQ4JC / hero B07MZ4GKZH | D12: 4pc | E12: bamboo viscose | F12: $109.99 (hub child) | G12: PREMIUM | H12: 4.5 | I12: 21857 | J12: 247 | K12: 809/wk hub | M12: 2565055 | N12: 0.54 | O12: 3955 | P12: cooling sheets org 11/SP 19
A13: Love's cabin | B13: B0DN1GGFL7 | C13: B0DN1DVKH5 (Q) | D13: 4pc | E13: rayon from bamboo 16in | F13: Q $37.99 (list $44.99) | G13: BUDGET | H13: 4.4 | I13: 1856 | J13: 628 | K13: 924/wk hub; 21959/mo DD Oct | L13: $834k DD Oct | M13: 906346 | N13: low (cooling ad traffic 3.3k) | O13: 85 cooling kw | P13: organic top10 on 81 cooling kw; avoid
A14: BC Bella Coterie | B14: B0H29V113N | C14: B08L86VLZB (King) | D14: 4pc | E14: bamboo viscose 18in | F14: King $134.99 | G14: PREMIUM | H14: 4.4 | I14: 5859 | J14: 2249 | K14: 81/wk hub; 10255/mo DD Oct | L14: $1.38M DD Oct | M14: 591713 | O14: 155 cooling kw | P14: DD Oct 327 adv kw (68%)/58 TOS
A15: Hotel Sheets Direct | B15: B0G5N99X9R | C15: B01N9L2O9P (Q) | D15: 4pc | E15: viscose from bamboo | F15: Q $79.99 | G15: PREMIUM | H15: 4.4 | I15: 37169 | J15: 5122 | K15: 185/wk hub | M15: 451969 | O15: 112 cooling kw | P15: 37k reviews - avoid
A16: Bambaw | B16: B07K6SYX8L | C16: B0DR99Q37Y (Q) | D16: 4pc | E16: viscose from bamboo 16in | F16: Q $89.99 | G16: PREMIUM | H16: 4.3 | I16: 2736 | J16: 17710 | K16: 173/wk hub; 2543/mo DD Oct | L16: $471k DD Oct | M16: 407949 | O16: 134 cooling kw | P16: cooling sheets org 24/SP 6
A17: KRIMANO | B17: B0FT7L9RSX | C17: B0FT7LZ2CD / B0FT7LV7PP | D17: 4pc | E17: organic viscose bamboo 17in | F17: Q $79.99-89.99 | G17: PREMIUM | H17: 4.5 | I17: 252 | J17: 5790 | K17: 173/wk hub | M17: 390744 | O17: 97 cooling kw | P17: king size cooling sheets org 4-5
A18: TRUE BAMBOO | B18: B0HHQ97HBL | C18: B0H5WYMXJK (King) | D18: 4pc | E18: bamboo | F18: King $99.99 | G18: PREMIUM | H18: 4.5 | I18: 155 | J18: 7509 | K18: 92/wk hub | M18: 605126 | O18: 118 cooling kw | P18: cooling sheets queen org 7/SP 7
A19: KARISSA MAE | B19: B0GT172Y8L | C19: B0G1CSCQTB | D19: unverified | E19: unverified (bamboo-led keyword profile) | F19: $119.99 | G19: PREMIUM | H19: 4.3 | I19: 472 | J19: 15394 | K19: 35/wk hub | M19: 243610 | N19: 0.86 | O19: 3224 | P19: ads-only on cooling (0 org top10)
A20: Pillcase (Tencel+bamboo) | B20: B0H1GGHHVN / B0HK71WHZW / B0HJYG8V9Q / B0FLDYD61P | C20: B0HFZQRXXQ (Q) | D20: 4pc | E20: Tencel lyocell + bamboo viscose 18in | F20: Q $79 (list $109); $99 white; old King $109.99-199 | G20: PREMIUM | H20: 4.9 (old 2.3-2.6) | I20: 203-294 (old 24-35) | J20: 23295 | K20: 35/wk hub | M20: 216953+116001+57075 | O20: few SP | P20: low ad; B0HJYG8V9Q org #3 on cooling sheets king size
A21: TWK | B21: B0HHQG3RSW | C21: B0H35S6VLR (Q) | D21: 4pc | E21: viscose bamboo 18in | F21: Q $62.10 (list $69); old King $109.99-199 3.6/37 | G21: PREMIUM (edge) | H21: 4.8 | I21: 131 | J21: 93032 | K21: 35/wk hub | M21: 82471 | O21: 13 cooling kw
A22: California Design Den | B22: B0HFBJPD56 | C22: B0GWHFGLVL (Q) | D22: 4pc | E22: viscose bamboo | F22: Q $89.99 | G22: PREMIUM | H22: 4.7 | I22: 66 | J22: 22545 | K22: 18/wk hub | M22: 103642 | O22: 72 cooling kw
A23: BEDELITE | B23: B0GT98GVQN | C23: B0GT8Z4X5D (Q) | D23: 4pc | E23: bamboo viscose | F23: Q $89.90 | G23: PREMIUM | H23: 4.6 | I23: 108 | J23: 90451 | K23: 35/wk hub | M23: 212120 | O23: 62 cooling kw | P23: SP#1 cool sheets for hot sleepers
A24: SONORO KATE | B24: B0F4852T9V / B0F29FQLFD | C24: B0F4873G4H / B0F29F1JM5 | D24: 4pc | E24: viscose bamboo 18-24in | F24: $79.99 / $59.99 | G24: PREMIUM/edge | H24: 4.5 | I24: 3767-3909 | J24: 10779 / 32866 | K24: 104 + 81/wk hub | M24: 185157+114504 | N24: mostly organic | O24: 21-37 cooling kw
A25: Shilucheng (4 parents) | B25: B0HJSVWNRS / B09PYQ2VQL / B0F2TDDFGJ / B098JT1RF2 | C25: B0FWY1TGFK (Q $29.74) | D25: 4pc | E25: rayon-bamboo blend / viscose | F25: Q $29.74; others $37.90-74.99 | G25: BUDGET (mostly) | H25: 4.3-4.5 | I25: 24339 (B0FWY1TGFK) | J25: 5219 | K25: 92/wk hub; 11904/mo DD Mar | M25: 135323 (+55k/42k/23k) | O25: 42-55 cooling kw | P25: avoid B0FWY1TGFK
A26: Degrees of Comfort Coolmax | B26: B0DXT68BBR | C26: B08YS6WZRR (Q) | D26: 4pc | E26: Coolmax polyester | F26: Q $28.49 (list $29.99) | G26: BUDGET | H26: 4.1 | I26: 7324 | J26: 38796 | K26: 35/wk hub; 1431-1533/mo DD May | L26: $48.6k DD May | M26: unmeasured | O26: 0 (DD May) | P26: strong organic: top10 on 20-25 cooling kw (May); PolarEdge Pro B0DYS4HVM3 Q $148.99 4.3/59 BSR 806589
A27: Comfort Spaces Coolmax fitted | B27: B0DCGL5646 | C27: B08R6MTY36 (Q) | D27: fitted only | E27: Coolmax | F27: $28.49 | G27: BUDGET | H27: 4.1 | I27: 23009 | J27: 2001 | K27: 347/wk hub | M27: unmeasured | P27: fitted-only demand leader; avoid
A28: Amazon Basics Cooling | C28: B0FX4P92L8 (Full) | D28: 4pc | E28: 100% recycled polyester 15in | F28: Full $49.99 | G28: mid | H28: 4.7 | I28: 23 | J28: 8889 (May) | K28: 5213/mo DD May | L28: $261k DD May | M28: unmeasured | O28: 0 | P28: top10 on 25 cooling kw (May); 1P - avoid
A29: Cozy Bliss Premium Cooling | C29: B0DMNQDZNB (Q) / B0DMNP5BC8 (K) | D29: 3pc no flat | E29: Q-Max>0.45 18in | F29: Q $89.99; King $99.99 | G29: PREMIUM | H29: 4.5 | I29: 436 | J29: 92159 (May) | K29: 653/mo DD May | L29: $58.8k DD May | M29: unmeasured | O29: 0 | P29: PAT target: 3pc at higher price
A30: DOWNCOOL | B30: B0F93XRVSZ | C30: B0F93XMMQY (Q) / B0GFHLLGJ1 (Full) | D30: 4pc | E30: Q-Max>0.4 15in | F30: Q $79.99 (May); Full $54.99 | G30: PREMIUM (Q) | H30: 4.1 (Q 24 rev); 4.5 (Full 91); parent 4.2/6 | I30: 24-91 | J30: 92100 (Full May); 2798999 (hub Sep-14) | K30: 585/mo Full DD May | L30: $32k | M30: unmeasured | O30: 0
A31: OMERAI | B31: B0HDC7BMTC | C31: B0FX8K1CG9 / old B09SPRMT9F | D31: 4pc | E31: unverified | F31: $59.99 (new); old Q $109.99 | G31: mid/PREMIUM | H31: 4.6 (3 rev); old 4.2/320 | I31: 3-320 | J31: 170691 | K31: 5/wk hub | M31: 13712 (Sep-18) | N31: 0.11 | O31: 129
A32: CGK Unlimited Cooling | B32: B0FT4VV426 | C32: B0FT575735 / B0FT4TC7NV | D32: 3pc Twin XL | E32: poly cooling | F32: $57.99 TwinXL | G32: mid | H32: 4.1-4.2 | I32: 50-117 | J32: 364130 | K32: 5/wk hub; 238/mo DD May | M32: unmeasured | O32: 59 adv kw (DD May) | P32: CGK microfiber B01M16WBW1 $24.99 461815 rev BSR 2 with 337 adv kw - avoid
A33: Brookstone cooling fitted | B33: B0CXB579TZ | C33: B0CTKL3YJ2 | D33: fitted only | E33: unverified | F33: $69.99 | G33: PREMIUM (fitted) | H33: 4.1 | I33: 183 | J33: 574513 | K33: 5/wk hub | M33: unmeasured
A34: HOT SLEEPER SHEETS | C34: B0D3M9TXW7 / B0D3XQM7DL (Q) | D34: 4pc | E34: viscose bamboo 16in | F34: Q $51.29-65.99 | G34: mid | H34: 4.4-4.5 | I34: 478-671 | J34: 41741-45396 | K34: 1273-1541/mo DD | L34: $84-92k | M34: unmeasured | O34: 0
A35: MR&HM | C35: B0DL5NCTYF (Q) | D35: 4pc | E35: rayon bamboo + polyester 15in | F35: Q $36.99-40.99 | G35: BUDGET | H35: 4.4 | I35: 600 | J35: 24811-36016 | K35: 2012-2174/mo DD | L35: $80-82k | M35: unmeasured | O35: 37 adv kw (DD May)
A36: SISTER Sleephoria | B36: B0F7LXFGLX | C36: B0F7LY3K8C (Q) / B0F7M19VYV | D36: 4pc | E36: BreezeWeave | F36: Q $64.99 (May) | G36: PREMIUM (edge) | H36: 4.3 | I36: 842 | J36: 42927 (May) | K36: 1470/mo DD May | L36: $95.5k DD May | M36: 38974 (Oct-06) | P36: traffic 54433 (Sep-18) -> 38974 (Oct-06)
A37: SISTER Decolure | B37: B0CWJ2ZQJR | C37: B0C9LQWPC7 (Q) / hero B0C9LS5H2T | D37: 4pc | E37: bamboo viscose microfiber | F37: Q $37.95 (May); $49.95 (Oct DD - shown FBM/0 sellers) | G37: BUDGET | H37: 4.2-4.3 | I37: 1304-1418 | J37: 104996 (May) -> 176326-189815 (Oct) | K37: 477/mo May -> 209-212/mo Oct | L37: $10.5k Oct | M37: 13066 (Oct-06) | P37: DD Oct flags B0C9LQWPC7 as FBM/0 active sellers - check stock

Sheet Market_KW
A1: Top-100 cooling-sheet market keywords
A2: Wk SV = weekly searches (ASINsight 6 Oct 2026, off-season). DD = DataDive monthly SV (May niches = peak season). Rivals = 28 mapped rivals of Sleephoria. S45/D48 = Sleephoria / Decolure organic & SP rank.
A4: Keyword | B4: Theme | C4: Wk SV | D4: DD monthly SV (May) | E4: Relevancy | F4: Ad share | G4: Rivals present | H4: Rivals org top 10 | I4: Rivals org top 20 | J4: Rivals w/ SP | K4: Leader | L4: Sleephoria org | M4: Sleephoria SP | N4: Decolure org | O4: Decolure SP | P4: REST org | Q4: REST SP | R4: Breescape org | S4: Breescape SP | T4: Bedsure PW org | U4: Bedsure PW SP
A5: cooling sheets | B5: cooling core | C5: 16968 | D5: 129480 | E5: Highly Relevant | F5: 0.509 | G5: 27 | H5: 3 | I5: 5 | J5: 20 | K5: Bedsure | L5: 13 | M5: 23 | N5: 132 | O5: 18 | P5: 36 | Q5: 18 | R5: 27 | S5: 8 | T5: 2 | U5: 10
A6: cooling sheets queen | B6: cooling + size | C6: 7904 | D6: 41329 | E6: Highly Relevant | F6: 0.451 | G6: 28 | H6: 4 | I6: 6 | J6: 24 | K6: Bedsure | L6: 45 | M6: 3 | N6: 110 | O6: 3 | P6: 77 | Q6: 16 | R6: 40 | S6: 15 | T6: 6 | U6: 4
A7: cooling sheets king size | B7: cooling + size | C7: 5684 | D7: 33283 | E7: Highly Relevant | F7: 0.4 | G7: 27 | H7: 2 | I7: 5 | J7: 23 | K7: Pure Bamboo | L7: 18 | M7: 1 | N7: 98 | O7: 4 | P7: 42 | Q7: 2 | R7: 21 | S7: 6 | T7: 70 | U7: 23
A8: cooling bed sheets | B8: cooling core | C8: 3632 | D8: 21134 | E8: Highly Relevant | F8: 0.425 | G8: 27 | H8: 4 | I8: 5 | J8: 16 | K8: Bedsure | L8: 18 | M8: 20 | N8: 92 | O8: 2 | P8: 51 | Q8: 11 | R8: 43 | S8: 15 | T8: 2 | U8: 11
A9: cooling sheets full size | B9: cooling + size | C9: 1263 | D9: 6214 | E9: Highly Relevant | F9: 0.345 | G9: 22 | H9: 1 | I9: 4 | J9: 16 | K9: Bedsure | L9: 22 | N9: 86 | P9: 24 | Q9: 12 | R9: 37 | S9: 7 | T9: 15 | U9: 10
A10: king sheets cooling | B10: cooling + size | C10: 1289 | D10: 8083 | E10: Relevant | F10: 0.279 | G10: 26 | H10: 3 | I10: 6 | J10: 12 | K10: Bedsure | L10: 27 | N10: 111 | P10: 77 | Q10: 8 | R10: 23 | S10: 8 | T10: 5 | U10: 20
A11: king size cooling sheets | B11: cooling + size | C11: 1112 | D11: 7525 | E11: Highly Relevant | F11: 0.335 | G11: 27 | H11: 3 | I11: 4 | J11: 16 | K11: Bedsure | L11: 17 | N11: 65 | P11: 102 | Q11: 20 | R11: 11 | S11: 14 | T11: 10 | U11: 23
A12: queen sheets cooling | B12: cooling + size | C12: 1212 | E12: Highly Relevant | F12: 0.365 | G12: 25 | H12: 2 | I12: 3 | J12: 14 | K12: Bedsure | L12: 69 | M12: 11 | N12: 127 | P12: 51 | Q12: 12 | R12: 40 | S12: 9 | T12: 9 | U12: 20
A13: queen cooling sheets | B13: cooling + size | C13: 1127 | D13: 6994 | E13: Relevant | F13: 0.367 | G13: 26 | H13: 2 | I13: 3 | J13: 15 | K13: Bedsure | L13: 45 | N13: 130 | P13: 130 | Q13: 12 | R13: 30 | S13: 9 | T13: 4 | U13: 11
A14: cooling sheets king | B14: cooling + size | C14: 654 | D14: 4445 | E14: Highly Relevant | F14: 0.354 | G14: 26 | H14: 2 | I14: 6 | J14: 15 | K14: REST | L14: 37 | N14: 76 | P14: 21 | Q14: 12 | R14: 13 | S14: 21 | T14: 4 | U14: 26
A15: king size sheets set cooling | B15: cooling + size | C15: 842 | D15: 6530 | E15: Relevant | F15: 0.326 | G15: 26 | H15: 3 | I15: 4 | J15: 8 | K15: Bedsure | L15: 65 | M15: 12 | N15: 50 | P15: 142 | R15: 52 | S15: 6 | T15: 5 | U15: 7
A16: cooling king sheets | B16: cooling + size | C16: 607 | D16: 2768 | E16: Highly Relevant | F16: 0.271 | G16: 26 | H16: 2 | I16: 5 | J16: 14 | K16: Bedsure | L16: 37 | N16: 111 | P16: 85 | Q16: 3 | R16: 20 | S16: 18 | T16: 3 | U16: 19
A17: king cooling sheets | B17: cooling + size | C17: 642 | D17: 5237 | E17: Highly Relevant | F17: 0.315 | G17: 26 | H17: 4 | I17: 7 | J17: 10 | K17: Bedsure | L17: 37 | N17: 73 | P17: 40 | Q17: 27 | R17: 15 | S17: 4 | T17: 4 | U17: 11
A18: queen bed sheets cooling | B18: cooling + size | C18: 506 | E18: Highly Relevant | F18: 0.394 | G18: 26 | H18: 3 | I18: 4 | J18: 16 | K18: Bedsure | L18: 14 | N18: 105 | P18: 85 | Q18: 29 | R18: 63 | S18: 21 | T18: 3 | U18: 19
A19: cooling bed sheets queen | B19: cooling + size | C19: 598 | D19: 4766 | E19: Highly Relevant | F19: 0.305 | G19: 26 | H19: 4 | I19: 5 | J19: 14 | K19: Bedsure | L19: 18 | M19: 4 | N19: 140 | P19: 41 | Q19: 10 | R19: 33 | S19: 5 | T19: 4 | U19: 4
A20: cooling queen sheets | B20: cooling + size | C20: 592 | E20: Highly Relevant | F20: 0.311 | G20: 26 | H20: 2 | I20: 5 | J20: 14 | K20: Bedsure | L20: 24 | M20: 5 | N20: 124 | P20: 79 | Q20: 11 | R20: 50 | S20: 20 | T20: 5 | U20: 21
A21: cooling bed sheets king | B21: cooling + size | C21: 401 | D21: 3231 | E21: Highly Relevant | F21: 0.382 | G21: 25 | H21: 4 | I21: 7 | J21: 14 | K21: Bedsure | L21: 24 | N21: 110 | P21: 24 | Q21: 12 | R21: 12 | S21: 11 | T21: 3 | U21: 4
A22: queen size cooling sheets | B22: cooling + size | C22: 572 | E22: Highly Relevant | F22: 0.349 | G22: 27 | H22: 2 | I22: 4 | J22: 14 | K22: Bedsure | L22: 48 | M22: 4 | N22: 142 | P22: 74 | Q22: 1 | R22: 44 | S22: 11 | T22: 5 | U22: 27
A23: cool sheets for hot sleepers | B23: hot sleepers / night sweats | C23: 409 | D23: 3167 | E23: Highly Relevant | F23: 0.353 | G23: 27 | H23: 2 | I23: 3 | J23: 11 | K23: Bedsure | L23: 7 | M23: 1 | N23: 93 | P23: 55 | Q23: 11 | R23: 31 | S23: 4 | T23: 1 | U23: 16
A24: cooling sheets twin | B24: cooling + size | C24: 651 | D24: 3771 | E24: Highly Relevant | F24: 0.658 | G24: 18 | H24: 0 | I24: 1 | J24: 11 | K24: REST | L24: 11 | M24: 11 | N24: 68 | O24: 3 | P24: 110 | Q24: 12 | R24: 17 | T24: 84 | U24: 7
A25: king bed sheets cooling | B25: cooling + size | C25: 253 | D25: 2142 | E25: Highly Relevant | F25: 0.369 | G25: 25 | H25: 3 | I25: 6 | J25: 14 | K25: Bedsure | L25: 45 | M25: 8 | N25: 98 | P25: 24 | Q25: 25 | R25: 17 | S25: 2 | T25: 7 | U25: 8
A26: fitted sheet queen | B26: fitted-only | C26: 10450 | E26: Highly Relevant | F26: 0.387 | G26: 13 | H26: 0 | I26: 0 | J26: 10 | K26: Pure Bamboo | P26: 143 | Q26: 28 | T26: 64 | U26: 2
A27: cooling sheet set | B27: cooling + set terms | C27: 337 | D27: 3289 | E27: Highly Relevant | F27: 0.415 | G27: 26 | H27: 3 | I27: 7 | J27: 15 | K27: Pure Bamboo | L27: 38 | M27: 8 | N27: 135 | P27: 66 | Q27: 3 | R27: 10 | S27: 16 | T27: 1 | U27: 15
A28: cool sheets | B28: cooling core | C28: 393 | D28: 3411 | E28: Highly Relevant | F28: 0.296 | G28: 26 | H28: 2 | I28: 5 | J28: 14 | K28: Bedsure | L28: 13 | N28: 110 | P28: 22 | Q28: 7 | R28: 17 | S28: 5 | T28: 1 | U28: 18
A29: best cooling sheets | B29: cooling core | C29: 259 | E29: Highly Relevant | F29: 0.253 | G29: 26 | H29: 4 | I29: 8 | J29: 10 | K29: Pure Bamboo | L29: 34 | M29: 3 | N29: 140 | P29: 17 | Q29: 3 | R29: 24 | S29: 8 | T29: 1 | U29: 3
A30: cooling fitted sheet | B30: fitted-only | C30: 760 | E30: Relevant | F30: 0.68 | G30: 24 | H30: 0 | I30: 0 | J30: 11 | K30: Bedsure | L30: 117 | P30: 95 | Q30: 21 | R30: 116 | S30: 11 | T30: 37 | U30: 11
A31: full size cooling sheets | B31: cooling + size | C31: 390 | D31: 2745 | E31: Highly Relevant | F31: 0.464 | G31: 21 | H31: 1 | I31: 2 | J31: 11 | K31: REST | L31: 23 | N31: 92 | P31: 96 | Q31: 6 | R31: 48 | S31: 8 | T31: 11 | U31: 17
A32: queen sheet set cooling | B32: cooling + size | C32: 452 | D32: 1246 | E32: Relevant | F32: 0.401 | G32: 26 | H32: 2 | I32: 3 | J32: 15 | K32: Bedsure | L32: 30 | M32: 11 | N32: 81 | O32: 1 | P32: 109 | Q32: 22 | R32: 38 | S32: 12 | T32: 10 | U32: 11
A33: cooling sheet | B33: cooling core | C33: 198 | D33: 3233 | E33: Highly Relevant | F33: 0.499 | G33: 25 | H33: 3 | I33: 5 | J33: 17 | K33: REST | L33: 13 | M33: 12 | P33: 17 | Q33: 11 | R33: 10 | S33: 5 | T33: 3 | U33: 12
A34: cooling sheets california king | B34: cooling + size | C34: 170 | E34: Highly Relevant | F34: 0.494 | G34: 23 | H34: 2 | I34: 3 | J34: 14 | K34: Bedsure | L34: 9 | N34: 38 | P34: 21 | Q34: 2 | R34: 48 | S34: 4 | T34: 54 | U34: 10
A35: king cooling sheet set | B35: cooling + size | C35: 161 | E35: Relevant | F35: 0.448 | G35: 27 | H35: 3 | I35: 7 | J35: 15 | K35: Bedsure | L35: 87 | M35: 3 | N35: 90 | O35: 3 | P35: 14 | R35: 9 | S35: 9 | T35: 3 | U35: 20
A36: cool care | B36: cooling core | C36: 3901 | F36: 1 | G36: 1 | H36: 0 | I36: 0 | J36: 1 | K36: REST | Q36: 2
A37: soft cooling sheets | B37: cooling core | C37: 170 | D37: 1100 | E37: Highly Relevant | F37: 0.416 | G37: 25 | H37: 4 | I37: 6 | J37: 11 | K37: Bedsure | L37: 43 | M37: 4 | N37: 134 | O37: 10 | P37: 119 | Q37: 8 | R37: 65 | S37: 14 | T37: 1 | U37: 19
A38: king size cooling sheets set | B38: cooling + size | C38: 203 | D38: 1525 | E38: Highly Relevant | F38: 0.348 | G38: 26 | H38: 1 | I38: 4 | J38: 16 | K38: Bedsure | L38: 45 | M38: 4 | N38: 84 | O38: 5 | P38: 55 | R38: 40 | S38: 17 | T38: 6 | U38: 26
A39: king sheet set cooling | B39: cooling + size | C39: 279 | E39: Relevant | F39: 0.4 | G39: 26 | H39: 2 | I39: 3 | J39: 17 | K39: Bedsure | L39: 88 | M39: 1 | N39: 102 | O39: 7 | P39: 96 | Q39: 27 | R39: 45 | S39: 3 | T39: 78 | U39: 12
A40: bed sheets cooling | B40: cooling core | C40: 217 | D40: 1879 | E40: Highly Relevant | F40: 0.408 | G40: 26 | H40: 5 | I40: 6 | J40: 11 | K40: Bedsure | L40: 10 | N40: 101 | O40: 2 | P40: 23 | Q40: 27 | R40: 39 | S40: 10 | T40: 2 | U40: 12
A41: cooling bed set | B41: cooling + set terms | C41: 248 | D41: 2320 | E41: Relevant | F41: 0.542 | G41: 25 | H41: 2 | I41: 3 | J41: 11 | K41: REST | L41: 42 | N41: 131 | P41: 87 | Q41: 5 | R41: 42 | S41: 18 | T41: 9 | U41: 4
A42: sheets cooling | B42: cooling core | C42: 136 | E42: Highly Relevant | F42: 0.479 | G42: 25 | H42: 2 | I42: 7 | J42: 17 | K42: Bedsure | L42: 9 | M42: 4 | N42: 130 | O42: 1 | P42: 92 | Q42: 1 | R42: 22 | S42: 4 | T42: 1 | U42: 17
A43: hot sleepers must haves | B43: hot sleepers / night sweats | C43: 463 | D43: 3837 | E43: Relevant | F43: 0.718 | G43: 14 | H43: 0 | I43: 1 | J43: 6 | K43: REST | L43: 130 | P43: 80 | Q43: 11 | R43: 104 | T43: 11 | U43: 9
A44: king size bed sheets cooling | B44: cooling + size | C44: 136 | D44: 1547 | E44: Highly Relevant | F44: 0.278 | G44: 26 | H44: 3 | I44: 6 | J44: 14 | K44: Bedsure | L44: 39 | M44: 19 | N44: 127 | P44: 48 | Q44: 3 | R44: 19 | S44: 9 | T44: 3 | U44: 27
A45: cooling sheets queen size | B45: cooling + size | C45: 209 | D45: 1668 | E45: Highly Relevant | F45: 0.31 | G45: 26 | H45: 3 | I45: 5 | J45: 15 | K45: Bedsure | L45: 46 | M45: 10 | N45: 122 | P45: 31 | Q45: 1 | R45: 39 | S45: 12 | T45: 5 | U45: 4
A46: full size sheets cooling | B46: cooling + size | C46: 192 | E46: Highly Relevant | F46: 0.441 | G46: 20 | H46: 2 | I46: 3 | J46: 8 | K46: Bedsure | L46: 39 | N46: 101 | P46: 119 | Q46: 3 | R46: 43 | T46: 8 | U46: 3
A47: cooling sheets full | B47: cooling + size | C47: 167 | D47: 1679 | E47: Highly Relevant | F47: 0.482 | G47: 21 | H47: 2 | I47: 3 | J47: 10 | K47: REST | L47: 10 | N47: 63 | P47: 69 | Q47: 25 | R47: 80 | S47: 4 | T47: 17 | U47: 7
A48: sabanas frias | B48: cooling core | C48: 220 | D48: 977 | E48: Lower Relevant | F48: 0.34 | G48: 18 | H48: 2 | I48: 2 | J48: 14 | K48: Bedsure | L48: 19 | M48: 1 | N48: 132 | P48: 85 | Q48: 6 | R48: 45 | S48: 2 | T48: 1 | U48: 8
A49: cooling | B49: cooling core | C49: 1918 | E49: Lower Relevant | F49: 0.943 | G49: 7 | H49: 0 | I49: 0 | J49: 6 | K49: REST | P49: 109 | Q49: 14 | S49: 18 | T49: 41 | U49: 21
A50: cold sheets for hot sleepers | B50: hot sleepers / night sweats | C50: 122 | D50: 1478 | E50: Highly Relevant | F50: 0.443 | G50: 24 | H50: 3 | I50: 5 | J50: 15 | K50: REST | L50: 5 | M50: 1 | N50: 74 | P50: 19 | Q50: 7 | R50: 9 | S50: 9 | T50: 1 | U50: 11
A51: black cooling sheets | B51: cooling core | C51: 147 | E51: Highly Relevant | F51: 0.499 | G51: 18 | H51: 1 | I51: 3 | J51: 10 | K51: Bedsure | L51: 30 | M51: 1 | N51: 54 | P51: 112 | R51: 52 | S51: 21 | T51: 15 | U51: 19
A52: twin fitted sheet | B52: fitted-only | C52: 9402 | E52: Lower Relevant | F52: 0.969 | G52: 6 | H52: 0 | I52: 0 | J52: 3 | K52: Pure Bamboo | Q52: 27 | T52: 65
A53: queen size sheets cooling | B53: cooling + size | C53: 226 | D53: 1615 | E53: Highly Relevant | F53: 0.415 | G53: 26 | H53: 3 | I53: 5 | J53: 15 | K53: Bedsure | L53: 60 | M53: 2 | N53: 134 | P53: 82 | Q53: 15 | R53: 40 | S53: 25 | T53: 6 | U53: 19
A54: cooling bedding set | B54: cooling + set terms | C54: 239 | D54: 1327 | E54: Lower Relevant | F54: 0.57 | G54: 21 | H54: 1 | I54: 2 | J54: 10 | K54: REST | L54: 74 | M54: 10 | P54: 60 | Q54: 1 | R54: 37 | S54: 11 | T54: 9 | U54: 29
A55: cooling king size sheets | B55: cooling + size | C55: 139 | D55: 576 | E55: Highly Relevant | F55: 0.269 | G55: 26 | H55: 2 | I55: 4 | J55: 16 | K55: Bedsure | L55: 23 | M55: 3 | N55: 51 | P55: 92 | Q55: 1 | R55: 32 | S55: 7 | T55: 3 | U55: 23
A56: cooling sheets king size deep pocket | B56: cooling + size | C56: 178 | D56: 2034 | E56: Highly Relevant | F56: 0.436 | G56: 26 | H56: 3 | I56: 6 | J56: 12 | K56: Bedsure | L56: 59 | N56: 118 | O56: 7 | P56: 107 | R56: 10 | S56: 10 | T56: 8 | U56: 8
A57: cooling bedding | B57: cooling core | C57: 494 | D57: 4862 | E57: Lower Relevant | F57: 0.406 | G57: 18 | H57: 0 | I57: 1 | J57: 7 | K57: Bedsure | P57: 59 | Q57: 11 | R57: 74 | S57: 8 | T57: 14 | U57: 7
A58: california king cooling sheets | B58: cooling + size | C58: 150 | D58: 1007 | E58: Highly Relevant | F58: 0.428 | G58: 23 | H58: 0 | I58: 2 | J58: 12 | K58: Bedsure | L58: 3 | M58: 8 | N58: 18 | P58: 45 | R58: 52 | S58: 12 | T58: 49 | U58: 10
A59: cooling sheets for hot sleepers | B59: hot sleepers / night sweats | C59: 150 | D59: 2418 | E59: Highly Relevant | F59: 0.418 | G59: 26 | H59: 2 | I59: 7 | J59: 16 | K59: Bedsure | L59: 29 | M59: 4 | N59: 108 | O59: 7 | P59: 11 | Q59: 2 | R59: 69 | S59: 7 | T59: 2 | U59: 23
A60: california king fitted sheet | B60: fitted-only | C60: 1259 | E60: Lower Relevant | F60: 0.921 | G60: 9 | H60: 0 | I60: 0 | J60: 4 | K60: Bedsure | P60: 89 | T60: 112 | U60: 15
A61: deep pocket cooling sheets | B61: cooling core | C61: 178 | D61: 1626 | E61: Highly Relevant | F61: 0.463 | G61: 26 | H61: 2 | I61: 4 | J61: 12 | K61: Bedsure | L61: 40 | M61: 4 | O61: 2 | P61: 75 | R61: 72 | S61: 11 | T61: 9 | U61: 11
A62: sheets queen cooling | B62: cooling + size | C62: 173 | D62: 1102 | E62: Highly Relevant | F62: 0.36 | G62: 25 | H62: 2 | I62: 3 | J62: 17 | K62: Bedsure | L62: 35 | M62: 3 | N62: 122 | O62: 8 | P62: 122 | Q62: 12 | R62: 21 | S62: 12 | T62: 2 | U62: 12
A63: cooling fitted sheet queen | B63: fitted-only | C63: 503 | D63: 4399 | E63: Relevant | F63: 0.608 | G63: 19 | H63: 0 | I63: 0 | J63: 5 | K63: Bedsure | L63: 124 | P63: 43 | Q63: 9 | T63: 41 | U63: 9
A64: cooling bedsheets | B64: cooling core | C64: 103 | D64: 1130 | E64: Highly Relevant | F64: 0.445 | G64: 27 | H64: 4 | I64: 5 | J64: 13 | K64: Bedsure | L64: 17 | M64: 3 | N64: 98 | O64: 2 | P64: 54 | Q64: 12 | R64: 20 | S64: 12 | T64: 2 | U64: 12
A65: twin cooling sheets | B65: cooling + size | C65: 231 | D65: 1281 | E65: Highly Relevant | F65: 0.629 | G65: 16 | H65: 0 | I65: 0 | J65: 10 | K65: REST | L65: 13 | N65: 134 | P65: 131 | Q65: 3 | R65: 27 | S65: 2 | T65: 58 | U65: 9
A66: cold sheets | B66: cooling core | C66: 161 | D66: 1247 | E66: Highly Relevant | F66: 0.423 | G66: 23 | H66: 1 | I66: 4 | J66: 11 | K66: REST | L66: 4 | N66: 19 | P66: 25 | Q66: 8 | R66: 18 | S66: 15 | T66: 1 | U66: 22
A67: sheets for hot sleepers | B67: hot sleepers / night sweats | C67: 122 | E67: Highly Relevant | F67: 0.395 | G67: 26 | H67: 2 | I67: 3 | J67: 17 | K67: Bedsure | L67: 18 | N67: 58 | P67: 86 | Q67: 18 | R67: 60 | S67: 11 | T67: 1 | U67: 3
A68: best cooling sheets for hot sleepers | B68: hot sleepers / night sweats | C68: 74 | D68: 902 | E68: Highly Relevant | F68: 0.306 | G68: 25 | H68: 3 | I68: 4 | J68: 16 | K68: Bedsure | L68: 19 | M68: 10 | N68: 91 | O68: 3 | P68: 55 | Q68: 16 | R68: 23 | S68: 7 | T68: 1 | U68: 11
A69: white cooling sheets | B69: cooling core | C69: 80 | D69: 894 | E69: Highly Relevant | F69: 0.471 | G69: 24 | H69: 2 | I69: 4 | J69: 11 | K69: Bedsure | L69: 52 | M69: 19 | N69: 46 | O69: 2 | P69: 48 | R69: 42 | S69: 1 | T69: 2 | U69: 17
A70: best sheets for hot sleepers | B70: hot sleepers / night sweats | C70: 51 | D70: 1037 | E70: Highly Relevant | F70: 0.306 | G70: 26 | H70: 4 | I70: 6 | J70: 13 | K70: REST | L70: 54 | N70: 120 | P70: 23 | Q70: 7 | R70: 51 | S70: 17 | T70: 1 | U70: 7
A71: sabanas frias queen | B71: cooling + size | C71: 103 | D71: 612 | E71: Lower Relevant | F71: 0.323 | G71: 19 | H71: 1 | I71: 2 | J71: 14 | K71: Bedsure | L71: 8 | M71: 2 | N71: 135 | P71: 29 | Q71: 4 | R71: 49 | S71: 1 | T71: 9 | U71: 8
A72: cooling deep pocket queen sheets | B72: cooling + size | C72: 245 | D72: 806 | E72: Highly Relevant | F72: 0.417 | G72: 25 | H72: 2 | I72: 3 | J72: 14 | K72: Bedsure | L72: 124 | M72: 19 | N72: 94 | O72: 1 | P72: 115 | R72: 83 | S72: 27 | T72: 21 | U72: 8
A73: queen cooling sheet set | B73: cooling + size | C73: 150 | D73: 969 | E73: Relevant | F73: 0.309 | G73: 26 | H73: 2 | I73: 3 | J73: 18 | K73: Bedsure | L73: 47 | M73: 11 | N73: 134 | O73: 12 | P73: 77 | Q73: 29 | R73: 44 | S73: 8 | T73: 4 | U73: 11
A74: cooling fitted sheet king | B74: fitted-only | C74: 421 | E74: Relevant | F74: 0.604 | G74: 21 | H74: 0 | I74: 1 | J74: 7 | K74: Bedsure | L74: 120 | P74: 118 | Q74: 12 | R74: 101 | T74: 19 | U74: 4
A75: king sheets deep pocket cooling | B75: cooling + size | C75: 88 | E75: Highly Relevant | F75: 0.374 | G75: 24 | H75: 2 | I75: 5 | J75: 12 | K75: Bedsure | L75: 105 | N75: 114 | O75: 1 | P75: 95 | R75: 46 | S75: 7 | T75: 7 | U75: 10
A76: cooling california king sheets | B76: cooling + size | C76: 108 | E76: Highly Relevant | F76: 0.489 | G76: 22 | H76: 3 | I76: 5 | J76: 11 | K76: Bedsure | L76: 10 | N76: 54 | P76: 79 | R76: 30 | S76: 6 | T76: 3 | U76: 22
A77: cold bed sheets | B77: cooling core | C77: 122 | E77: Highly Relevant | F77: 0.334 | G77: 25 | H77: 3 | I77: 5 | J77: 10 | K77: REST | L77: 10 | M77: 2 | N77: 80 | P77: 37 | Q77: 10 | R77: 17 | S77: 28 | T77: 1 | U77: 34
A78: cooling full size sheets | B78: cooling + size | C78: 77 | D78: 898 | E78: Highly Relevant | F78: 0.454 | G78: 21 | H78: 1 | I78: 1 | J78: 13 | K78: REST | L78: 33 | N78: 71 | P78: 144 | Q78: 21 | R78: 41 | S78: 15 | T78: 33 | U78: 22
A79: cooling sheets queen deep pockets | B79: cooling + size | C79: 125 | D79: 1237 | E79: Highly Relevant | F79: 0.421 | G79: 25 | H79: 2 | I79: 3 | J79: 18 | K79: Bedsure | L79: 53 | M79: 12 | N79: 119 | O79: 8 | P79: 110 | Q79: 2 | R79: 78 | S79: 16 | T79: 8 | U79: 20
A80: king size sheets set | B80: generic: size + sheets | C80: 74908 | E80: Generic | F80: 0.43 | G80: 23 | H80: 1 | I80: 3 | J80: 14 | K80: Pure Bamboo | P80: 74 | R80: 70 | T80: 15 | U80: 18
A81: sheets | B81: generic: sheets/other | C81: 34934 | E81: Lower Relevant | F81: 0.478 | G81: 23 | H81: 1 | I81: 2 | J81: 15 | K81: Pure Bamboo | P81: 119 | Q81: 3 | R81: 80 | S81: 28 | T81: 34 | U81: 11
A82: queen sheets | B82: generic: size + sheets | C82: 51969 | E82: Lower Relevant | F82: 0.472 | G82: 22 | H82: 1 | I82: 2 | J82: 14 | K82: TRUE BAMBOO | P82: 142 | R82: 117 | T82: 25 | U82: 10
A83: queen sheet set | B83: generic: size + sheets | C83: 61335 | E83: Generic | F83: 0.488 | G83: 20 | H83: 0 | I83: 0 | J83: 11 | K83: Pure Bamboo | N83: 122 | O83: 16 | P83: 139 | T83: 27 | U83: 18
A84: bed sheets | B84: generic: sheets/other | C84: 45439 | D84: 227467 | E84: Lower Relevant | F84: 0.488 | G84: 20 | H84: 2 | I84: 2 | J84: 13 | K84: Pure Bamboo | P84: 94 | Q84: 9 | R84: 74 | S84: 22 | T84: 27 | U84: 12
A85: queen bed sheets | B85: generic: size + sheets | C85: 33182 | E85: Generic | F85: 0.483 | G85: 22 | H85: 1 | I85: 2 | J85: 17 | K85: TRUE BAMBOO | P85: 123 | Q85: 16 | S85: 18 | T85: 24 | U85: 15
A86: sheets queen size bed set | B86: generic: size + sheets | C86: 22586 | E86: Lower Relevant | F86: 0.521 | G86: 21 | H86: 0 | I86: 1 | J86: 18 | K86: Bedsure | Q86: 15 | T86: 26 | U86: 6
A87: california king sheet sets | B87: generic: size + sheets | C87: 12816 | E87: Lower Relevant | F87: 0.504 | G87: 18 | H87: 2 | I87: 2 | J87: 12 | K87: Bedsure | P87: 57 | T87: 33 | U87: 19
A88: full size sheets | B88: generic: size + sheets | C88: 26462 | E88: Lower Relevant | F88: 0.533 | G88: 15 | H88: 0 | I88: 0 | J88: 11 | K88: TRUE BAMBOO | N88: 133 | T88: 72 | U88: 19
A89: bedding | B89: generic: sheets/other | C89: 24387 | E89: Lower Relevant | F89: 0.771 | G89: 12 | H89: 0 | I89: 0 | J89: 11 | K89: Pure Bamboo | P89: 140 | Q89: 18 | T89: 91 | U89: 19
A90: sheets king size | B90: generic: size + sheets | C90: 8592 | E90: Generic | F90: 0.348 | G90: 21 | H90: 0 | I90: 3 | J90: 17 | K90: Pure Bamboo | P90: 31 | Q90: 12 | R90: 77 | S90: 18 | T90: 18 | U90: 6
A91: king bed sheets | B91: generic: size + sheets | C91: 10436 | E91: Generic | F91: 0.455 | G91: 20 | H91: 0 | I91: 2 | J91: 15 | K91: Pure Bamboo | P91: 118 | Q91: 5 | R91: 131 | S91: 19 | T91: 16 | U91: 10
A92: bed sheets queen size | B92: generic: size + sheets | C92: 12964 | E92: Lower Relevant | F92: 0.298 | G92: 19 | H92: 0 | I92: 1 | J92: 15 | K92: TRUE BAMBOO | P92: 142 | Q92: 21 | T92: 17 | U92: 7
A93: king size sheets | B93: generic: size + sheets | C93: 10954 | E93: Generic | F93: 0.421 | G93: 23 | H93: 1 | I93: 3 | J93: 14 | K93: Pure Bamboo | P93: 136 | T93: 14 | U93: 19
A94: queen size sheets | B94: generic: size + sheets | C94: 14103 | E94: Generic | F94: 0.408 | G94: 21 | H94: 0 | I94: 0 | J94: 15 | K94: TRUE BAMBOO | P94: 144 | T94: 40 | U94: 21
A95: bedsure cooling sheets | B95: competitor brand | C95: 1578 | D95: 7312 | E95: Branded | F95: 0.387 | G95: 19 | H95: 1 | I95: 2 | J95: 18 | K95: Bedsure | L95: 70 | M95: 12 | N95: 127 | P95: 56 | Q95: 11 | R95: 31 | S95: 11 | T95: 4 | U95: 1
A96: breescape cooling sheets | B96: competitor brand | C96: 534 | E96: Branded | F96: 0.421 | G96: 17 | H96: 1 | I96: 2 | J96: 14 | K96: Breescape | L96: 24 | N96: 112 | P96: 45 | Q96: 4 | R96: 2 | S96: 2 | T96: 11 | U96: 7
A97: rest evercool cooling comforter | B97: competitor brand | C97: 3705 | D97: 13388 | F97: 0.737 | G97: 2 | H97: 0 | I97: 0 | J97: 2 | K97: REST | P97: 21 | Q97: 15
A98: purple sheets | B98: competitor brand | C98: 2775 | E98: Lower Relevant | F98: 0.756 | G98: 15 | H98: 0 | I98: 0 | J98: 13 | K98: Pure Bamboo | L98: 95 | M98: 2 | N98: 138 | P98: 80 | Q98: 26 | S98: 14 | T98: 59 | U98: 24
A99: rest evercool cooling sheets | B99: competitor brand | C99: 469 | D99: 594 | E99: Branded | F99: 0.266 | G99: 15 | H99: 1 | I99: 2 | J99: 11 | K99: REST | L99: 31 | N99: 104 | P99: 4 | Q99: 1 | R99: 26 | S99: 12 | T99: 14 | U99: 10
A100: bed jet cooling system | B100: competitor brand | C100: 1457 | D100: 8225 | E100: Not Relevant | F100: 0.577 | G100: 11 | H100: 0 | I100: 0 | J100: 10 | K100: REST | M100: 7 | P100: 43 | Q100: 21 | R100: 72 | S100: 14 | U100: 26
A101: love's cabin 4 piece queen sheet set, 100% rayon derived from bamboo, cooling & breathable, soft sil | B101: competitor brand | C101: 294 | F101: 0.243 | G101: 21 | H101: 2 | I101: 2 | J101: 9 | K101: Love's cabin | N101: 82 | T101: 9 | U101: 4
...

Sheet MKL_Intake
A1: MKL intake — paste the Master Keyword List here when shared
A2: G12: every term needs a syntax tag + relevancy score, MKL refreshed ≤ 30 days. The MKL will (1) confirm/replace batch-1 terms, (2) feed Batch 2, (3) extend negatives, (4) add relevancy re-scored against the live CooLinens listing.
A4: Keyword | B4: Search volume | C4: Relevancy (score) | D4: Syntax tag | E4: Root | F4: Size | G4: Indexed on B0H6K1MKQW? (Y/N) | H4: Proposed owner (CooLinens / Sleephoria / shared) | I4: Batch (1 / 2 / Phase 2 / negative) | J4: Notes
A5: cooling sheets queen | B5: 41329 | C5: Highly Relevant (9) | D5: Cooling|Queen | E5: cooling sheets | F5: Queen | G5: Y | H5: CooLinens (proposed) | I5: 1 | J5: Example row — replace with MKL data
