Workbook

Sheet Read_Me
A1: How to read this workbook
A2: CooLinens Cooling Sheets 4PC launch · Amazon US · prepared 8 Oct 2026 · analysis and proposal only — nothing has been changed in the account.
A4: Main_Strategy | B4: The decision tab. One row per keyword we keep (Batch 1, 2 or 3). Filter column B. Each row carries relevance, confidence, demand, rank history, competitors, live Sleephoria/Decolure PPC history, the ranking calculation, campaign structure, budget, stock and the full story.
A5: Batch_Summary | B5: Live totals per batch and the rules that put a keyword in a batch, plus the weekly decision rule.
A6: Campaigns | B6: One row per campaign. Daily budget = SUMIF of its keywords' planned spend × (1 + headroom), minimum $10. Main_Strategy reads its budget from here.
A7: Assumptions | B7: Every input the formulas use: paid click share, probe cap, modifier limits, the rank → click-share table (measured on Sleephoria) and economics by size. Change a blue cell and the whole plan recalculates.
A8: Inventory | B8: Stock, inbound, velocity and days of cover per SKU; preferred / backup per size; stock-out history; constraints. Main_Strategy reads stock status and cover from here.
A9: Competitors | B9: Profiles (price, material, variations, keywords, organic and PPC presence, strengths / weaknesses, comparison) and a keyword × rival rank matrix for every Main_Strategy keyword.
A10: Decolure_History / Sleephoria_History | B10: Full product history: summary, monthly business + PPC, year-on-year windows, size and SKU performance, ad formats and placements, organic rank history, stock-outs, rises and declines with causes, and the keyword table that Main_Strategy looks up.
A11: Excluded | B11: Every keyword considered and rejected, with its reason.
A12: Relevance % | B12: Product type 25 + use case (cooling / hot sleeper) 30 + material 15 + intent 15 + size fit 15 (specific size 15, no size 10). ✓ = full points, ⚠ = half, ✗ = 0 (and the keyword is excluded). Research wording ("best …") −5.
A13: Confidence | B13: Evidence score out of 12: Sleephoria PPC on the exact term (−2 to +4; same product, strongest weight) + root|size syntax proven on Sleephoria when the term itself has < 20 clicks (+1.5) + Sleephoria organic rank reached (0 to +2) + market CVR from SQP (0 to +2) + rivals in the organic top 20 (0 to +1) + Decolure term history and rank (−0.5 to +1.5, adjacent product). High ≥ 6.5 · Medium 4–6.4 · Low < 4. "Medium (syntax-proven)" = a long-tail with little data of its own whose root|size syntax Sleephoria proved — used only inside capped Halo campaigns. The build-up is shown on every row.
A14: Ranking calculation | B14: Searches/day × market clicks per search = market clicks/day → × click share needed for the target rank (Sleephoria-measured table) × paid share = clicks/day needed. Funded clicks: Ranking = needed, floored at 1/day so CVR can be read; capped probes = 50 clicks / 14 days (they build first sales and read CVR until the size is assigned to CooLinens); Halo probes = 0.75/day per term; support terms = needed. Every term is limited to 10% of its daily searches (what an exact ad can realistically buy). Orders = clicks × expected CVR. Base bid = Sleephoria's CPC on the same term, capped at the max ranking CPC. Top-of-Search modifier = the largest 25% step that keeps base × (1 + modifier) ≤ price × ranking-ceiling ACoS × CVR, limited to +100% where Sleephoria proved CVR on the term and +50% where it did not; 0 for probes and support terms. Effective CPC × clicks = spend; campaign budget sums its keywords.
A15: Expected CVR | B15: Sleephoria CVR on the exact term (≥ 50 clicks), otherwise its root/size group, × 0.8 for a new listing (24 Vine ratings vs Sleephoria's 889), bounded 3–14%.
... A17: Structure rule | B17: Launch-window SV > 300/mo → Hero single-keyword campaign; ≤ 300 → Halo campaign per size, ad groups by intent. Exact match only on day 1. Naming: CLCS4-SP-{keyword}-{SV tier}-Exact-{objective}-Fix-{SKU}.

Sheet Main_Strategy
A1: CooLinens Cooling Sheets 4PC — Main Strategy (Batch 1 / 2 / 3)
A2: One row per keyword we keep. Filter column B for Batch 1, 2 or 3. Blue = input value; black = live formula; green = pulled live from a supporting tab. Excluded keywords and their reasons are on the Excluded tab.
A4: Keyword | F4: Relevance & Confidence | K4: Demand | O4: Organic Rank | U4: Competitors | V4: Historical PPC (Live from History Tabs) | AD4: Click & Order Model (Live) | AW4: Bid & Placement Model (Live) | BL4: Campaign Structure | BR4: Budget & Stock (Live) | BU4: Keyword Story — Why We Chose It
A5: Exact search term | B5: 1 · 2 · 3 | C5: Launch date / gate | D5: Size in the query | E5: Action for this keyword | F5: Type 25 + Use 30 + Material 15 + Intent 15 + Size 15 | G5: Type · Use · Material · Intent (✓ / ⚠ / ✗) | H5: High ≥ 6.5 · Medium 4–6.4 · Low < 4 | I5: Sum of the build-up | J5: Sleephoria PPC + rank, market CVR, rivals, Decolure | K5: DataDive MKL build 618 | L5: Oct–Jan seasonal level | M5: Calc: Launch SV ÷ 30 | N5: All brands: purchases ÷ clicks, 12 mo | O5: Best · median · now | P5: Best · PPC-period median · now | Q5: Best-ranked tracked rival | R5: Of 20 tracked rivals | S5: Exact rank to reach by week 8 | T5: Checkpoints for the weekly verdict | U5: ASINsight, late Sep 2026 | V5: Sleephoria_History §12 | W5: Sleephoria_History §12 | X5: Sleephoria_History §12 | Y5: Sleephoria_History §12 | Z5: Sleephoria_History §12 | AA5: Decolure_History §10 | AB5: Decolure_History §10 | AC5: Decolure_History §10 | AD5: Sleephoria CVR × 0.8 (new listing) | AE5: Source of the CVR | AF5: SQP clicks ÷ searches | AG5: Calc: Searches/day × clicks per search | AH5: Sleephoria-measured (Assumptions) | AI5: Ads share during a push | AJ5: Calc: Market clicks × share × paid | AK5: Calc: Required clicks × expected CVR | AL5: Calc: Required clicks/day × 56 | AM5: Calc: Required orders/day × 56 | AN5: Calc: Searches/day × 10% | AO5: All campaigns are ranking campaigns | AP5: Reason for the objective and its funding level | AQ5: Exact on day 1 | AS5: Full push: MAX(required, 1) · capped: MAX(required, 1) up to 3.57 · long-tail: required up to 0.75 — all ≤ supply | AT5: Planned ÷ required clicks | AU5: Calc: Planned clicks × CVR | AV5: Calc: Orders × price | AW5: What Sleephoria paid | AX5: Term or size average | AY5: Assumptions · economics | AZ5: Calc: MIN(80%, 1.5 × break-even) | BA5: Calc: Margin ÷ price | BB5: Calc: Price × ceiling × CVR | BC5: Calc: MIN(reference CPC, max ranking CPC) | BD5: ≥ 50 clicks and CVR ≥ 8% | BE5: Largest 25% step keeping effective CPC ≤ max | BF5: Decision with the ceiling maths and final values | BG5: Calc: Base bid × (1 + modifier) | BH5: Calc: Planned clicks × effective CPC | BI5: Calc: Effective CPC ÷ (price × CVR) | BJ5: vs break-even and ceiling | BK5: Full chain with final values | BL5: Root | size | BM5: Hero > 300 SV/mo · Halo ≤ 300 | BN5: CLCS4 · SP · keyword/size · SV tier · match · objective · bid type · SKU | BO5: Hero: keyword · Halo: intent | BP5: Preferred child (colour terms: colour child) | BR5: Calc: Campaign spend × 1.25, min $10 | BS5: Inventory tab | BT5: Inventory tab
A6: Keyword | B6: Batch | C6: Go-Live | D6: Size | E6: Launch Recommendation | F6: Relevance (%) | G6: Relevance Check | H6: Confidence Level | I6: Evidence Score (/12) | J6: Evidence Score Build-Up | K6: Search Volume / Month (MKL) | L6: Search Volume / Month (Launch Window) | M6: Searches / Day | N6: Market CVR (SQP) | O6: Decolure Organic Rank (History) | P6: Sleephoria Organic Rank (History) | Q6: Market Organic Leader | R6: Rivals in Organic Top 20 | S6: Target Organic Rank (#) | T6: Rank Path (Wk 2 → Wk 4 → Wk 8) | U6: Competitor Presence (Organic · Sponsored) | V6: Sleephoria Clicks | W6: Sleephoria CVR | X6: Sleephoria CPC ($) | Y6: Sleephoria ACoS | Z6: Sleephoria Ad Sales ($) | AA6: Decolure Clicks | AB6: Decolure CVR | AC6: Decolure ACoS | AD6: Expected CVR | AE6: CVR Basis | AF6: Market Clicks per Search | AG6: Market Clicks / Day | AH6: Click Share for Target Rank | AI6: Paid Share of Clicks | AJ6: Clicks / Day Required for Target Rank | AK6: Orders / Day Required for Target Rank | AL6: Clicks Required — 8-Week Push | AM6: Orders Required — 8-Week Push | AN6: Click Supply Cap / Day | AO6: Campaign Objective | AP6: Why This Objective | AQ6: Match Type | AR6: Why This Match Type | AS6: Planned Clicks / Day | AT6: Funding vs Requirement | AU6: Expected Orders / Day | AV6: Expected Ad Sales / Day ($) | AW6: Reference CPC ($) | AX6: Reference CPC Source | AY6: Price ($) | AZ6: Ranking Ceiling ACoS | BA6: Break-Even ACoS | BB6: Max Ranking CPC ($) | BC6: Base Bid ($) | BD6: Sleephoria CVR Proven? | BE6: TOS Modifier (%) | BF6: TOS Modifier Decision (+100%?) | BG6: Effective TOS CPC ($) | BH6: Planned Spend / Day ($) | BI6: Expected ACoS | BJ6: ACoS Check | BK6: Bid & Budget Calculation (Worked Example) | BL6: Syntax Group (Root | Size) | BM6: Campaign Structure | BN6: Campaign Name | BO6: Ad Group | BP6: Advertised SKU | BQ6: Advertised ASIN | BR6: Campaign Daily Budget ($) | BS6: Stock Status | BT6: Days of Cover | BU6: Why It Is Relevant to CooLinens | BV6: Evidence from Decolure | BW6: Evidence from Sleephoria | BX6: Market Demand and Trend | BY6: Who Ranks and Who Advertises | BZ6: Competitive Opportunity | CA6: Why Launch It Now | CB6: Why This Batch (1 vs 2 vs 3) | CC6: Target Rank Rationale
A7: cooling sheets queen | B7: 1 | C7: 15 Oct 2026 | D7: Queen | E7: LAUNCH 15 Oct — rank push | F7: 1 | G7: Type ✓ · Use ✓ · Material ✓ · Intent ✓ | H7: High | I7: 9.5 | J7: Sleephoria PPC +4 · Sleephoria rank +2 · market CVR +1.5 · competitors +1 · Decolure +1 | K7: 30225 | L7: 36640 | M7: =L7/30 -> 1221.3333 | N7: 0.033473097 | O7: best #3 (2025-04-25) · median #27 · now #110 | P7: best #2 (2025-10-23) · PPC-period median #23 · now #45 | Q7: #3 Pillcase | R7: 5 | S7: 15 | T7: #50 → #30 → #15 | U7: Pillcase #3, Love's cabin #5, Bedsure PW #6, TRUE BAMBOO #7, Bambaw #12; Ads: Bedsure PW Cooling SP#2, Love's cabin SP#4, Bedsure PW SP#4, California Design Den SP#4 | V7: =IFERROR(INDEX(Sleephoria_History!$F$454:$F$2115,MATCH($A7,Sleephoria_History!$A$454:$A$2115,0)),"") -> 2552 | W7: =IFERROR(INDEX(Sleephoria_History!$J$454:$J$2115,MATCH($A7,Sleephoria_History!$A$454:$A$2115,0)),"") -> 0.1187 | X7: =IFERROR(INDEX(Sleephoria_History!$H$454:$H$2115,MATCH($A7,Sleephoria_History!$A$454:$A$2115,0)),"") -> 2.24 | Y7: =IFERROR(INDEX(Sleephoria_History!$M$454:$M$2115,MATCH($A7,Sleephoria_History!$A$454:$A$2115,0)),"") -> 0.289 | Z7: =IFERROR(INDEX(Sleephoria_History!$L$454:$L$2115,MATCH($A7,Sleephoria_History!$A$454:$A$2115,0)),"") -> 19776.51 | AA7: =IFERROR(INDEX(Decolure_History!$F$397:$F$709,MATCH($A7,Decolure_History!$A$397:$A$709,0)),"") -> 2048 | AB7: =IFERROR(INDEX(Decolure_History!$J$397:$J$709,MATCH($A7,Decolure_History!$A$397:$A$709,0)),"") -> 0.0693 | AC7: =IFERROR(INDEX(Decolure_History!$M$397:$M$709,MATCH($A7,Decolure_History!$A$397:$A$709,0)),"") -> 0.459 | AD7: 0.095 | AE7: Sleephoria term CVR 11.9% on 2552 clicks ×0.8 launch | AF7: 0.476 | AG7: =M7*AF7 -> 581.35467 | AH7: =IF(AO7="Brand Defense",0,IFERROR(VLOOKUP(S7,Assumptions!$A$24:$B$28,2,FALSE()),0)) -> 0.0149 | AI7: =Assumptions!$B$6 -> 0.66 | AJ7: =AG7*AH7*AI7 -> 5.7170418 | AK7: =AJ7*AD7 -> 0.54311897 | AL7: =AJ7*56 -> 320.15434 | AM7: =AK7*56 -> 30.414662 | AN7: =M7*Assumptions!$B$8 -> 122.13333 | AO7: Ranking — Full Push | AP7: Full ranking push: Queen is CooLinens' own size (its keywords are not shared with Sleephoria) and the evidence is High (9.5/12). Every click the target rank requires is funded, with a Top-of-Search modifier where the ceiling allows. | AQ7: Exact | AR7: Exact: organic rank is earned per exact query, so sales must land on this wording; one keyword per campaign gives full control of bid, TOS modifier and budget, and clean attribution. Phrase / broad / auto open from week 4 for harvesting only. | AS7: =IF(AO7="Ranking — Full Push",MIN(MAX(AJ7,Assumptions!$B$9),AN7),IF(AO7="Brand Defense",MIN(Assumptions!$B$7,AN7),IF(OR(AO7="Ranking — Head Term (Capped)",AO7="Ranking — Capped Entry"),MIN(MAX(AJ7,Assumptions!$B$9),Assumptions!$B$7,AN7),IF(AO7="Ranking — Capped Long-Tail",MIN(AJ7,Assumptions!$B$10,AN7),MIN(AJ7,AN7))))) -> 5.7170418 | AT7: =IF(AJ7<=0,"",IF(AS7>=AJ7,IF(AS7>AJ7*1.05,"Floor of "&TEXT(AS7,"0.0")&" click/day to read CVR (rank needs "&TEXT(AJ7,"0.00")&")","Fully funded (100%)"),"Capped at "&TEXT(AS7/AJ7,"0%")&" of required")) -> Fully funded (100%) | AU7: =AS7*AD7 -> 0.54311897 | AV7: =AU7*AY7 -> 43.444086 | AW7: 2.24 | AX7: Sleephoria CPC on this exact term (2552 clicks) | AY7: =INDEX(Assumptions!$B$33:$B$37,MATCH(IF($D7="","Queen",$D7),Assumptions!$A$33:$A$37,0)) -> 79.99 | AZ7: =INDEX(Assumptions!$K$33:$K$37,MATCH(IF($D7="","Queen",$D7),Assumptions!$A$33:$A$37,0)) -> 0.55866046 | BA7: =INDEX(Assumptions!$H$33:$H$37,MATCH(IF($D7="","Queen",$D7),Assumptions!$A$33:$A$37,0)) -> 0.37244031 | BB7: =AY7*AZ7*AD7 -> 4.2452888 | BC7: =ROUND(MIN(AW7*Assumptions!$B$11,BB7),2) -> 2.24 | BD7: Yes | BE7: =IF(AO7="Ranking — Full Push",MAX(0,MIN(IF(BD7="Yes",Assumptions!$B$12,Assumptions!$B$13),FLOOR(MAX(0,BB7/BC7-1),Assumptions!$B$14))),0) -> 0.75 | BF7: =IF(AO7="Ranking — Full Push",IF(BE7>=1,"YES — +100% Top of Search. Effective CPC $"&TEXT(BG7,"0.00")&" (= $"&TEXT(BC7,"0.00")&" × 2) stays within the $"&TEXT(BB7,"0.00")&" max ranking CPC"&" (= $"&TEXT(AY7,"0.00")&" price × "&TEXT(AZ7,"0.0%")&" ranking ceiling × "&TEXT(AD7,"0.0%")&" CVR)"&". Sleephoria CVR is proven on this term, so the full push is justified.",IF(AND(BD7="No",BE7>=Assumptions!$B$13),"PARTIAL — +"&TEXT(BE7,"0%")&" Top of Search (limit for terms without proven CVR). Effective CPC $"&TEXT(BG7,"0.00")&" vs $"&TEXT(BB7,"0.00")&" max ranking CPC"&" (= $"&TEXT(AY7,"0.00")&" price × "&TEXT(AZ7,"0.0%")&" ranking ceiling × "&TEXT(AD7,"0.0%")&" CVR)"&". Raise to +100% only after CooLinens converts at ≥ "&TEXT(AD7,"0.0%")&" on 50+ clicks and $"&TEXT(BC7*2,"0.00")&" ≤ the max.",IF(BE7>0,"PARTIAL — +"&TEXT(BE7,"0%")&" Top of Search. Effective CPC $"&TEXT(BG7,"0.00")&" stays within the $"&TEXT(BB7,"0.00")&" max ranking CPC"&" (= $"&TEXT(AY7,"0.00")&" price × "&TEXT(AZ7,"0.0%")&" ranking ceiling × "&TEXT(AD7,"0.0%")&" CVR)"&". +100% would cost $"&TEXT(BC7*2,"0.00")&" per click and push ACoS to "&TEXT(BC7*2/(AY7*AD7),"0.0%")&", above the "&TEXT(AZ7,"0.0%")&" ceiling.","NO — 0%. Base bid $"&TEXT(BC7,"0.00")&" already equals the $"&TEXT(BB7,"0.00")&" max ranking CPC"&" (= $"&TEXT(AY7,"0.00")&" price × "&TEXT(AZ7,"0.0%")&" ranking ceiling × "&TEXT(AD7,"0.0%")&" CVR)"&"; any modifier would push ACoS above the "&TEXT(AZ7,"0.0%")&" ceiling."))),IF(OR(AO7="Ranking — Head Term (Capped)",AO7="Ranking — Capped Entry",AO7="Ranking — Capped Long-Tail"),"NO — 0% (capped ranking entry). Bid $"&TEXT(BC7,"0.00")&" vs $"&TEXT(BB7,"0.00")&" max ranking CPC"&" (= $"&TEXT(AY7,"0.00")&" price × "&TEXT(AZ7,"0.0%")&" ranking ceiling × "&TEXT(AD7,"0.0%")&" CVR)"&". While spend is capped at "&TEXT(AS7,"0.00")&" clicks/day, a placement premium would only raise CPC without buying more rank; the modifier is set when this term moves to a full push.","NO — 0% (support / brand term). Bid $"&TEXT(BC7,"0.00")&" vs $"&TEXT(BB7,"0.00")&" max ranking CPC"&" (= $"&TEXT(AY7,"0.00")&" price × "&TEXT(AZ7,"0.0%")&" ranking ceiling × "&TEXT(AD7,"0.0%")&" CVR)"&"; expected ACoS "&TEXT(BI7,"0.0%")&" vs the "&TEXT(AZ7,"0.0%")&" ceiling.")) -> PARTIAL — +75% Top of Search. Effective CPC $3.92 stays within the $4.25 max ranking CPC (= $79.99 price × 55.9% ranking ceiling × 9.5% CVR). +100% would cost $4.48 per click and push ACoS to 59.0%, above the 55.9% ceiling. | BG7: =BC7*(1+BE7) -> 3.92 | BH7: =AS7*BG7 -> 22.410804 | BI7: =IFERROR(BG7/(AY7*AD7),"") -> 0.51585396 | BJ7: =IF(BI7="","",IF(BI7<=BA7,"Profitable (≤ break-even)",IF(BI7<=AZ7,"Ranking investment (≤ ceiling)","Above ceiling — reduce bid"))) -> Ranking investment (≤ ceiling) | BK7: ="Base $"&TEXT(BC7,"0.00")&" × (1 + "&TEXT(BE7,"0%")&" TOS) = $"&TEXT(BG7,"0.00")&" effective CPC [max $"&TEXT(BB7,"0.00")&"]. "&TEXT(AG7,"0.0")&" market clicks/day × "&TEXT(AH7,"0.00%")&" click share × "&TEXT(AI7,"0%")&" paid = "&TEXT(AJ7,"0.00")&" clicks/day needed; "&"planned "&TEXT(AS7,"0.00")&" clicks/day × "&TEXT(AD7,"0.0%")&" CVR = "&TEXT(AU7,"0.00")&" orders/day. "&"Spend $"&TEXT(BH7,"0.00")&"/day, ACoS "&TEXT(BI7,"0.0%")&" (ceiling "&TEXT(AZ7,"0.0%")&", break-even "&TEXT(BA7,"0.0%")&"). "&"Target organic rank #"&S7&" by week 8 ("&T7&")." -> Base $2.24 × (1 + 75% TOS) = $3.92 effective CPC [max $4.25]. 581.4 market clicks/day × 1.49% click share × 66% paid = 5.72 clicks/day needed; planned 5.72 clicks/day × 9.5% CVR = 0.54 orders/day. Spend $22.41/day, ACoS 51.6% (ceiling 55.9%, break-even 37.2%). Target organic rank #15 by week 8 (#50 → #30 → #15). | BL7: cooling sheets|Queen | BM7: Hero (single-keyword campaign) | BN7: CLCS4-SP-cooling sheets queen-VHSV-Exact-Rank-Fix-Q-GRAPHITE | BO7: cooling sheets queen | BP7: CL-COOLING-SHEET-QUEEN-GRAPHITE | BQ7: B0H6K1MKQW | BR7: =IFERROR(INDEX(Campaigns!$L:$L,MATCH(BN7,Campaigns!$A:$A,0)),"") -> 29 | BS7: =IFERROR(INDEX(Inventory!$O:$O,MATCH(BP7,Inventory!$A:$A,0)),"") -> OK | BT7: =IFERROR(INDEX(Inventory!$N:$N,MATCH(BP7,Inventory!$A:$A,0)),"") -> 91.53226 | BU7: "cooling sheets queen" asks for a Queen cooling sheet product that CooLinens sells (BreezeWeave nylon/spandex knit, 16″ pocket, 4-piece set). Relevance 100%: product type ✓, use case ✓, material ✓, intent ✓. | BV7: Decolure ($38 microfiber — adjacent, lower weight): converted but costly at the $38 tier (2048 clicks, CVR 6.9%, ACoS 46%); organic best #3 (2025-04-25), 73 days in top 10, median #28. | BW7: Sleephoria (same product and price — strongest evidence): proven on the same product (2552 clicks, CVR 11.9%, ACoS 29%); organic best #2 (2025-10-23), first top-10 2025-10-12, now #45. Launch entry Oct-25: 7.8 clicks/day, 1.34 orders/day, $41/day → top 10 in 9 days. | BX7: SV 30,225/mo (MKL (DataDive)); launch window ≈ 36,640/mo; SQP 12-mo 589,245 searches, peak 2026-06, Oct at 0.80× its avg; Mar-24→Mar-26 ×1.94; market CVR 3.3% (head term 1.5%). | BY7: Organic top 20: Pillcase #3, Love's cabin #5, Bedsure PW #6, TRUE BAMBOO #7. Advertising: Bedsure PW Cooling SP#2, Love's cabin SP#4, Bedsure PW SP#4, California Design Den SP#4. Rival ad share 54%. | BZ7: Top-20 is held by bamboo/viscose sets (Pillcase, Love's cabin, Bedsure PW); no synthetic cooling-knit rival ranks here. CooLinens is the only nylon/spandex cooling option on the page at $79.99 — Sleephoria proved the knit ranks here. | CA7: Launch-window demand is ~35% of the June peak but these are the terms where evidence is strongest; ranking now means CooLinens holds position before the March ramp (SQP March ≈ 2× January). Queen roots belong to CooLinens, so this can be pushed at ranking spend from day 1. | CB7: Batch 1 Hero: relevance 100% ≥ 90%, clean wording, launch-window demand 36,640 searches/mo > 300 (own campaign), and evidence score 9.5/12 ≥ 6.0 (Sleephoria PPC +4 · Sleephoria rank +2 · market CVR +1.5 · competitors +1 · Decolure +1). Sleephoria did not overpay on it beyond the ranking ceiling. | CC7: ≤15 (≤50 by wk 2, ≤30 by wk 4, ≤15 by wk 8): a 36,640-searches/mo page. Sleephoria's best was #2 (2025-10-23), but its launch ran into Prime Big Deal Days (7–8 Oct 2025). CooLinens launches with 24 Vine ratings and no deal tailwind in a 35%-of-peak window, so top 15 is the evidence-supported goal.
A8: queen sheets cooling | B8: 1 | C8: 15 Oct 2026 | D8: Queen | E8: LAUNCH 15 Oct — rank push | F8: 1 | G8: Type ✓ · Use ✓ · Material ✓ · Intent ✓ | H8: High | I8: 9.5 | J8: Sleephoria PPC +4 · Sleephoria rank +2 · market CVR +2 · competitors +1 · Decolure +0.5 | K8: 4964 | L8: 5693 | M8: =L8/30 -> 189.76667 | N8: 0.05029491 | O8: now #127 | P8: best #4 (2025-10-17) · PPC-period median #30 · now #69 | Q8: #5 Love's cabin | R8: 3 | S8: 10 | T8: #40 → #20 → #10 | U8: Love's cabin #5, Bedsure PW #9, Bambaw #18; Ads: Bambaw SP#6, TRUE BAMBOO SP#8, Breescape SP#9, Pure Bamboo SP#10 | V8: =IFERROR(INDEX(Sleephoria_History!$F$454:$F$2115,MATCH($A8,Sleephoria_History!$A$454:$A$2115,0)),"") -> 55 | W8: =IFERROR(INDEX(Sleephoria_History!$J$454:$J$2115,MATCH($A8,Sleephoria_History!$A$454:$A$2115,0)),"") -> 0.0909 | X8: =IFERROR(INDEX(Sleephoria_History!$H$454:$H$2115,MATCH($A8,Sleephoria_History!$A$454:$A$2115,0)),"") -> 2.42 | Y8: =IFERROR(INDEX(Sleephoria_History!$M$454:$M$2115,MATCH($A8,Sleephoria_History!$A$454:$A$2115,0)),"") -> 0.37 | Z8: =IFERROR(INDEX(Sleephoria_History!$L$454:$L$2115,MATCH($A8,Sleephoria_History!$A$454:$A$2115,0)),"") -> 359.95 | AA8: =IFERROR(INDEX(Decolure_History!$F$397:$F$709,MATCH($A8,Decolure_History!$A$397:$A$709,0)),"") -> 45 | AB8: =IFERROR(INDEX(Decolure_History!$J$397:$J$709,MATCH($A8,Decolure_History!$A$397:$A$709,0)),"") -> 0.0889 | AC8: =IFERROR(INDEX(Decolure_History!$M$397:$M$709,MATCH($A8,Decolure_History!$A$397:$A$709,0)),"") -> 0.481 | AD8: 0.0727 | AE8: Sleephoria term CVR 9.1% on 55 clicks ×0.8 launch | AF8: 0.471 | AG8: =M8*AF8 -> 89.3801 | AH8: =IF(AO8="Brand Defense",0,IFERROR(VLOOKUP(S8,Assumptions!$A$24:$B$28,2,FALSE()),0)) -> 0.028 | AI8: =Assumptions!$B$6 -> 0.66 | AJ8: =AG8*AH8*AI8 -> 1.6517442 | AK8: =AJ8*AD8 -> 0.12008181 | AL8: =AJ8*56 -> 92.497678 | AM8: =AK8*56 -> 6.7245812 | AN8: =M8*Assumptions!$B$8 -> 18.976667 | AO8: Ranking — Full Push | AP8: Full ranking push: Queen is CooLinens' own size (its keywords are not shared with Sleephoria) and the evidence is High (9.5/12). Every click the target rank requires is funded, with a Top-of-Search modifier where the ceiling allows. | AQ8: Exact | AR8: Exact: organic rank is earned per exact query, so sales must land on this wording; one keyword per campaign gives full control of bid, TOS modifier and budget, and clean attribution. Phrase / broad / auto open from week 4 for harvesting only. | AS8: =IF(AO8="Ranking — Full Push",MIN(MAX(AJ8,Assumptions!$B$9),AN8),IF(AO8="Brand Defense",MIN(Assumptions!$B$7,AN8),IF(OR(AO8="Ranking — Head Term (Capped)",AO8="Ranking — Capped Entry"),MIN(MAX(AJ8,Assumptions!$B$9),Assumptions!$B$7,AN8),IF(AO8="Ranking — Capped Long-Tail",MIN(AJ8,Assumptions!$B$10,AN8),MIN(AJ8,AN8))))) -> 1.6517442 | AT8: =IF(AJ8<=0,"",IF(AS8>=AJ8,IF(AS8>AJ8*1.05,"Floor of "&TEXT(AS8,"0.0")&" click/day to read CVR (rank needs "&TEXT(AJ8,"0.00")&")","Fully funded (100%)"),"Capped at "&TEXT(AS8/AJ8,"0%")&" of required")) -> Fully funded (100%) | AU8: =AS8*AD8 -> 0.12008181 | AV8: =AU8*AY8 -> 9.6053437 | AW8: 2.42 | AX8: Sleephoria CPC on this exact term (55 clicks) | AY8: =INDEX(Assumptions!$B$33:$B$37,MATCH(IF($D8="","Queen",$D8),Assumptions!$A$33:$A$37,0)) -> 79.99 | AZ8: =INDEX(Assumptions!$K$33:$K$37,MATCH(IF($D8="","Queen",$D8),Assumptions!$A$33:$A$37,0)) -> 0.55866046 | BA8: =INDEX(Assumptions!$H$33:$H$37,MATCH(IF($D8="","Queen",$D8),Assumptions!$A$33:$A$37,0)) -> 0.37244031 | BB8: =AY8*AZ8*AD8 -> 3.2487631 | BC8: =ROUND(MIN(AW8*Assumptions!$B$11,BB8),2) -> 2.42 | BD8: Yes | BE8: =IF(AO8="Ranking — Full Push",MAX(0,MIN(IF(BD8="Yes",Assumptions!$B$12,Assumptions!$B$13),FLOOR(MAX(0,BB8/BC8-1),Assumptions!$B$14))),0) -> 0.25 | BF8: =IF(AO8="Ranking — Full Push",IF(BE8>=1,"YES — +100% Top of Search. Effective CPC $"&TEXT(BG8,"0.00")&" (= $"&TEXT(BC8,"0.00")&" × 2) stays within the $"&TEXT(BB8,"0.00")&" max ranking CPC"&" (= $"&TEXT(AY8,"0.00")&" price × "&TEXT(AZ8,"0.0%")&" ranking ceiling × "&TEXT(AD8,"0.0%")&" CVR)"&". Sleephoria CVR is proven on this term, so the full push is justified.",IF(AND(BD8="No",BE8>=Assumptions!$B$13),"PARTIAL — +"&TEXT(BE8,"0%")&" Top of Search (limit for terms without proven CVR). Effective CPC $"&TEXT(BG8,"0.00")&" vs $"&TEXT(BB8,"0.00")&" max ranking CPC"&" (= $"&TEXT(AY8,"0.00")&" price × "&TEXT(AZ8,"0.0%")&" ranking ceiling × "&TEXT(AD8,"0.0%")&" CVR)"&". Raise to +100% only after CooLinens converts at ≥ "&TEXT(AD8,"0.0%")&" on 50+ clicks and $"&TEXT(BC8*2,"0.00")&" ≤ the max.",IF(BE8>0,"PARTIAL — +"&TEXT(BE8,"0%")&" Top of Search. Effective CPC $"&TEXT(BG8,"0.00")&" stays within the $"&TEXT(BB8,"0.00")&" max ranking CPC"&" (= $"&TEXT(AY8,"0.00")&" price × "&TEXT(AZ8,"0.0%")&" ranking ceiling × "&TEXT(AD8,"0.0%")&" CVR)"&". +100% would cost $"&TEXT(BC8*2,"0.00")&" per click and push ACoS to "&TEXT(BC8*2/(AY8*AD8),"0.0%")&", above the "&TEXT(AZ8,"0.0%")&" ceiling.","NO — 0%. Base bid $"&TEXT(BC8,"0.00")&" already equals the $"&TEXT(BB8,"0.00")&" max ranking CPC"&" (= $"&TEXT(AY8,"0.00")&" price × "&TEXT(AZ8,"0.0%")&" ranking ceiling × "&TEXT(AD8,"0.0%")&" CVR)"&"; any modifier would push ACoS above the "&TEXT(AZ8,"0.0%")&" ceiling."))),IF(OR(AO8="Ranking — Head Term (Capped)",AO8="Ranking — Capped Entry",AO8="Ranking — Capped Long-Tail"),"NO — 0% (capped ranking entry). Bid $"&TEXT(BC8,"0.00")&" vs $"&TEXT(BB8,"0.00")&" max ranking CPC"&" (= $"&TEXT(AY8,"0.00")&" price × "&TEXT(AZ8,"0.0%")&" ranking ceiling × "&TEXT(AD8,"0.0%")&" CVR)"&". While spend is capped at "&TEXT(AS8,"0.00")&" clicks/day, a placement premium would only raise CPC without buying more rank; the modifier is set when this term moves to a full push.","NO — 0% (support / brand term). Bid $"&TEXT(BC8,"0.00")&" vs $"&TEXT(BB8,"0.00")&" max ranking CPC"&" (= $"&TEXT(AY8,"0.00")&" price × "&TEXT(AZ8,"0.0%")&" ranking ceiling × "&TEXT(AD8,"0.0%")&" CVR)"&"; expected ACoS "&TEXT(BI8,"0.0%")&" vs the "&TEXT(AZ8,"0.0%")&" ceiling.")) -> PARTIAL — +25% Top of Search. Effective CPC $3.03 stays within the $3.25 max ranking CPC (= $79.99 price × 55.9% ranking ceiling × 7.3% CVR). +100% would cost $4.84 per click and push ACoS to 83.2%, above the 55.9% ceiling. | BG8: =BC8*(1+BE8) -> 3.025 | BH8: =AS8*BG8 -> 4.9965264 | BI8: =IFERROR(BG8/(AY8*AD8),"") -> 0.52018194 | BJ8: =IF(BI8="","",IF(BI8<=BA8,"Profitable (≤ break-even)",IF(BI8<=AZ8,"Ranking investment (≤ ceiling)","Above ceiling — reduce bid"))) -> Ranking investment (≤ ceiling) | BK8: ="Base $"&TEXT(BC8,"0.00")&" × (1 + "&TEXT(BE8,"0%")&" TOS) = $"&TEXT(BG8,"0.00")&" effective CPC [max $"&TEXT(BB8,"0.00")&"]. "&TEXT(AG8,"0.0")&" market clicks/day × "&TEXT(AH8,"0.00%")&" click share × "&TEXT(AI8,"0%")&" paid = "&TEXT(AJ8,"0.00")&" clicks/day needed; "&"planned "&TEXT(AS8,"0.00")&" clicks/day × "&TEXT(AD8,"0.0%")&" CVR = "&TEXT(AU8,"0.00")&" orders/day. "&"Spend $"&TEXT(BH8,"0.00")&"/day, ACoS "&TEXT(BI8,"0.0%")&" (ceiling "&TEXT(AZ8,"0.0%")&", break-even "&TEXT(BA8,"0.0%")&"). "&"Target organic rank #"&S8&" by week 8 ("&T8&")." -> Base $2.42 × (1 + 25% TOS) = $3.03 effective CPC [max $3.25]. 89.4 market clicks/day × 2.80% click share × 66% paid = 1.65 clicks/day needed; planned 1.65 clicks/day × 7.3% CVR = 0.12 orders/day. Spend $5.00/day, ACoS 52.0% (ceiling 55.9%, break-even 37.2%). Target organic rank #10 by week 8 (#40 → #20 → #10). | BL8: cooling sheets|Queen | BM8: Hero (single-keyword campaign) | BN8: CLCS4-SP-queen sheets cooling-HSV-Exact-Rank-Fix-Q-GRAPHITE | BO8: queen sheets cooling | BP8: CL-COOLING-SHEET-QUEEN-GRAPHITE | BQ8: B0H6K1MKQW | BR8: =IFERROR(INDEX(Campaigns!$L:$L,MATCH(BN8,Campaigns!$A:$A,0)),"") -> 10 | BS8: =IFERROR(INDEX(Inventory!$O:$O,MATCH(BP8,Inventory!$A:$A,0)),"") -> OK | BT8: =IFERROR(INDEX(Inventory!$N:$N,MATCH(BP8,Inventory!$A:$A,0)),"") -> 91.53226 | BU8: "queen sheets cooling" asks for a Queen cooling sheet product that CooLinens sells (BreezeWeave nylon/spandex knit, 16″ pocket, 4-piece set). Relevance 100%: product type ✓, use case ✓, material ✓, intent ✓. | BV8: Decolure ($38 microfiber — adjacent, lower weight): converted but costly at the $38 tier (45 clicks, CVR 8.9%, ACoS 48%). | BW8: Sleephoria (same product and price — strongest evidence): proven on the same product (55 clicks, CVR 9.1%, ACoS 37%); organic best #4 (2025-10-17), first top-10 2025-10-15, now #69. | BX8: SV 4,964/mo (MKL (DataDive)); launch window ≈ 5,693/mo; SQP 12-mo 78,457 searches, peak 2026-07, Oct at 0.94× its avg; market CVR 5.0% (head term 1.5%). | BY8: Organic top 20: Love's cabin #5, Bedsure PW #9, Bambaw #18. Advertising: Bambaw SP#6, TRUE BAMBOO SP#8, Breescape SP#9, Pure Bamboo SP#10. Rival ad share 52%. | BZ8: Top-20 is held by bamboo/viscose sets (Love's cabin, Bedsure PW, Bambaw); no synthetic cooling-knit rival ranks here. CooLinens is the only nylon/spandex cooling option on the page at $79.99 — Sleephoria proved the knit ranks here. | CA8: Launch-window demand is ~35% of the June peak but these are the terms where evidence is strongest; ranking now means CooLinens holds position before the March ramp (SQP March ≈ 2× January). Queen roots belong to CooLinens, so this can be pushed at ranking spend from day 1. | CB8: Batch 1 Hero: relevance 100% ≥ 90%, clean wording, launch-window demand 5,693 searches/mo > 300 (own campaign), and evidence score 9.5/12 ≥ 6.0 (Sleephoria PPC +4 · Sleephoria rank +2 · market CVR +2 · competitors +1 · Decolure +0.5). Sleephoria did not overpay on it beyond the ranking ceiling. | CC8: ≤10 (≤40 by wk 2, ≤20 by wk 4, ≤10 by wk 8): Sleephoria, the same product, reached #4 here; 3 tracked rival(s) in the top 20.
A9: queen cooling sheets | B9: 1 | C9: 15 Oct 2026 | D9: Queen | E9: LAUNCH 15 Oct — rank push | F9: 1 | G9: Type ✓ · Use ✓ · Material ✓ · Intent ✓ | H9: High | I9: 9 | J9: Sleephoria PPC +4 · Sleephoria rank +2 · market CVR +2 · competitors +0.5 · Decolure +0.5 | K9: 4728 | L9: 5605 | M9: =L9/30 -> 186.83333 | N9: 0.049716135 | O9: best #4 (2025-06-18) · median #20 · now #130 | P9: best #3 (2025-11-08) · PPC-period median #29 · now #45 | Q9: #1 Love's cabin | R9: 2 | S9: 10 | T9: #40 → #20 → #10 | U9: Love's cabin #1, Bedsure PW #4; Ads: OMERAI SP#4, Bambaw SP#5, BEDELITE SP#8, Breescape SP#9 | V9: =IFERROR(INDEX(Sleephoria_History!$F$454:$F$2115,MATCH($A9,Sleephoria_History!$A$454:$A$2115,0)),"") -> 78 | W9: =IFERROR(INDEX(Sleephoria_History!$J$454:$J$2115,MATCH($A9,Sleephoria_History!$A$454:$A$2115,0)),"") -> 0.1282 | X9: =IFERROR(INDEX(Sleephoria_History!$H$454:$H$2115,MATCH($A9,Sleephoria_History!$A$454:$A$2115,0)),"") -> 2.38 | Y9: =IFERROR(INDEX(Sleephoria_History!$M$454:$M$2115,MATCH($A9,Sleephoria_History!$A$454:$A$2115,0)),"") -> 0.23 | Z9: =IFERROR(INDEX(Sleephoria_History!$L$454:$L$2115,MATCH($A9,Sleephoria_History!$A$454:$A$2115,0)),"") -> 804.9 | AA9: =IFERROR(INDEX(Decolure_History!$F$397:$F$709,MATCH($A9,Decolure_History!$A$397:$A$709,0)),"") -> 88 | AB9: =IFERROR(INDEX(Decolure_History!$J$397:$J$709,MATCH($A9,Decolure_History!$A$397:$A$709,0)),"") -> 0.0455 | AC9: =IFERROR(INDEX(Decolure_History!$M$397:$M$709,MATCH($A9,Decolure_History!$A$397:$A$709,0)),"") -> 0.657 | AD9: 0.1026 | AE9: Sleephoria term CVR 12.8% on 78 clicks ×0.8 launch | AF9: 0.492 | AG9: =M9*AF9 -> 91.922 | AH9: =IF(AO9="Brand Defense",0,IFERROR(VLOOKUP(S9,Assumptions!$A$24:$B$28,2,FALSE()),0)) -> 0.028 | AI9: =Assumptions!$B$6 -> 0.66 | AJ9: =AG9*AH9*AI9 -> 1.6987186 | AK9: =AJ9*AD9 -> 0.17428852 | AL9: =AJ9*56 -> 95.128239 | AM9: =AK9*56 -> 9.7601574 | AN9: =M9*Assumptions!$B$8 -> 18.683333 | AO9: Ranking — Full Push | AP9: Full ranking push: Queen is CooLinens' own size (its keywords are not shared with Sleephoria) and the evidence is High (9.0/12). Every click the target rank requires is funded, with a Top-of-Search modifier where the ceiling allows. | AQ9: Exact | AR9: Exact: organic rank is earned per exact query, so sales must land on this wording; one keyword per campaign gives full control of bid, TOS modifier and budget, and clean attribution. Phrase / broad / auto open from week 4 for harvesting only. | AS9: =IF(AO9="Ranking — Full Push",MIN(MAX(AJ9,Assumptions!$B$9),AN9),IF(AO9="Brand Defense",MIN(Assumptions!$B$7,AN9),IF(OR(AO9="Ranking — Head Term (Capped)",AO9="Ranking — Capped Entry"),MIN(MAX(AJ9,Assumptions!$B$9),Assumptions!$B$7,AN9),IF(AO9="Ranking — Capped Long-Tail",MIN(AJ9,Assumptions!$B$10,AN9),MIN(AJ9,AN9))))) -> 1.6987186 | AT9: =IF(AJ9<=0,"",IF(AS9>=AJ9,IF(AS9>AJ9*1.05,"Floor of "&TEXT(AS9,"0.0")&" click/day to read CVR (rank needs "&TEXT(AJ9,"0.00")&")","Fully funded (100%)"),"Capped at "&TEXT(AS9/AJ9,"0%")&" of required")) -> Fully funded (100%) | AU9: =AS9*AD9 -> 0.17428852 | AV9: =AU9*AY9 -> 13.941339 | AW9: 2.38 | AX9: Sleephoria CPC on this exact term (78 clicks) | AY9: =INDEX(Assumptions!$B$33:$B$37,MATCH(IF($D9="","Queen",$D9),Assumptions!$A$33:$A$37,0)) -> 79.99 | AZ9: =INDEX(Assumptions!$K$33:$K$37,MATCH(IF($D9="","Queen",$D9),Assumptions!$A$33:$A$37,0)) -> 0.55866046 | BA9: =INDEX(Assumptions!$H$33:$H$37,MATCH(IF($D9="","Queen",$D9),Assumptions!$A$33:$A$37,0)) -> 0.37244031 | BB9: =AY9*AZ9*AD9 -> 4.5849119 | BC9: =ROUND(MIN(AW9*Assumptions!$B$11,BB9),2) -> 2.38 | BD9: Yes | BE9: =IF(AO9="Ranking — Full Push",MAX(0,MIN(IF(BD9="Yes",Assumptions!$B$12,Assumptions!$B$13),FLOOR(MAX(0,BB9/BC9-1),Assumptions!$B$14))),0) -> 0.75 | BF9: =IF(AO9="Ranking — Full Push",IF(BE9>=1,"YES — +100% Top of Search. Effective CPC $"&TEXT(BG9,"0.00")&" (= $"&TEXT(BC9,"0.00")&" × 2) stays within the $"&TEXT(BB9,"0.00")&" max ranking CPC"&" (= $"&TEXT(AY9,"0.00")&" price × "&TEXT(AZ9,"0.0%")&" ranking ceiling × "&TEXT(AD9,"0.0%")&" CVR)"&". Sleephoria CVR is proven on this term, so the full push is justified.",IF(AND(BD9="No",BE9>=Assumptions!$B$13),"PARTIAL — +"&TEXT(BE9,"0%")&" Top of Search (limit for terms without proven CVR). Effective CPC $"&TEXT(BG9,"0.00")&" vs $"&TEXT(BB9,"0.00")&" max ranking CPC"&" (= $"&TEXT(AY9,"0.00")&" price × "&TEXT(AZ9,"0.0%")&" ranking ceiling × "&TEXT(AD9,"0.0%")&" CVR)"&". Raise to +100% only after CooLinens converts at ≥ "&TEXT(AD9,"0.0%")&" on 50+ clicks and $"&TEXT(BC9*2,"0.00")&" ≤ the max.",IF(BE9>0,"PARTIAL — +"&TEXT(BE9,"0%")&" Top of Search. Effective CPC $"&TEXT(BG9,"0.00")&" stays within the $"&TEXT(BB9,"0.00")&" max ranking CPC"&" (= $"&TEXT(AY9,"0.00")&" price × "&TEXT(AZ9,"0.0%")&" ranking ceiling × "&TEXT(AD9,"0.0%")&" CVR)"&". +100% would cost $"&TEXT(BC9*2,"0.00")&" per click and push ACoS to "&TEXT(BC9*2/(AY9*AD9),"0.0%")&", above the "&TEXT(AZ9,"0.0%")&" ceiling.","NO — 0%. Base bid $"&TEXT(BC9,"0.00")&" already equals the $"&TEXT(BB9,"0.00")&" max ranking CPC"&" (= $"&TEXT(AY9,"0.00")&" price × "&TEXT(AZ9,"0.0%")&" ranking ceiling × "&TEXT(AD9,"0.0%")&" CVR)"&"; any modifier would push ACoS above the "&TEXT(AZ9,"0.0%")&" ceiling."))),IF(OR(AO9="Ranking — Head Term (Capped)",AO9="Ranking — Capped Entry",AO9="Ranking — Capped Long-Tail"),"NO — 0% (capped ranking entry). Bid $"&TEXT(BC9,"0.00")&" vs $"&TEXT(BB9,"0.00")&" max ranking CPC"&" (= $"&TEXT(AY9,"0.00")&" price × "&TEXT(AZ9,"0.0%")&" ranking ceiling × "&TEXT(AD9,"0.0%")&" CVR)"&". While spend is capped at "&TEXT(AS9,"0.00")&" clicks/day, a placement premium would only raise CPC without buying more rank; the modifier is set when this term moves to a full push.","NO — 0% (support / brand term). Bid $"&TEXT(BC9,"0.00")&" vs $"&TEXT(BB9,"0.00")&" max ranking CPC"&" (= $"&TEXT(AY9,"0.00")&" price × "&TEXT(AZ9,"0.0%")&" ranking ceiling × "&TEXT(AD9,"0.0%")&" CVR)"&"; expected ACoS "&TEXT(BI9,"0.0%")&" vs the "&TEXT(AZ9,"0.0%")&" ceiling.")) -> PARTIAL — +75% Top of Search. Effective CPC $4.17 stays within the $4.58 max ranking CPC (= $79.99 price × 55.9% ranking ceiling × 10.3% CVR). +100% would cost $4.76 per click and push ACoS to 58.0%, above the 55.9% ceiling. | BG9: =BC9*(1+BE9) -> 4.165 | BH9: =AS9*BG9 -> 7.0751628 | BI9: =IFERROR(BG9/(AY9*AD9),"") -> 0.50749521 | BJ9: =IF(BI9="","",IF(BI9<=BA9,"Profitable (≤ break-even)",IF(BI9<=AZ9,"Ranking investment (≤ ceiling)","Above ceiling — reduce bid"))) -> Ranking investment (≤ ceiling) | BK9: ="Base $"&TEXT(BC9,"0.00")&" × (1 + "&TEXT(BE9,"0%")&" TOS) = $"&TEXT(BG9,"0.00")&" effective CPC [max $"&TEXT(BB9,"0.00")&"]. "&TEXT(AG9,"0.0")&" market clicks/day × "&TEXT(AH9,"0.00%")&" click share × "&TEXT(AI9,"0%")&" paid = "&TEXT(AJ9,"0.00")&" clicks/day needed; "&"planned "&TEXT(AS9,"0.00")&" clicks/day × "&TEXT(AD9,"0.0%")&" CVR = "&TEXT(AU9,"0.00")&" orders/day. "&"Spend $"&TEXT(BH9,"0.00")&"/day, ACoS "&TEXT(BI9,"0.0%")&" (ceiling "&TEXT(AZ9,"0.0%")&", break-even "&TEXT(BA9,"0.0%")&"). "&"Target organic rank #"&S9&" by week 8 ("&T9&")." -> Base $2.38 × (1 + 75% TOS) = $4.17 effective CPC [max $4.58]. 91.9 market clicks/day × 2.80% click share × 66% paid = 1.70 clicks/day needed; planned 1.70 clicks/day × 10.3% CVR = 0.17 orders/day. Spend $7.08/day, ACoS 50.7% (ceiling 55.9%, break-even 37.2%). Target organic rank #10 by week 8 (#40 → #20 → #10). | BL9: cooling sheets|Queen | BM9: Hero (single-keyword campaign) | BN9: CLCS4-SP-queen cooling sheets-HSV-Exact-Rank-Fix-Q-GRAPHITE | BO9: queen cooling sheets | BP9: CL-COOLING-SHEET-QUEEN-GRAPHITE | BQ9: B0H6K1MKQW | BR9: =IFERROR(INDEX(Campaigns!$L:$L,MATCH(BN9,Campaigns!$A:$A,0)),"") -> 10 | BS9: =IFERROR(INDEX(Inventory!$O:$O,MATCH(BP9,Inventory!$A:$A,0)),"") -> OK | BT9: =IFERROR(INDEX(Inventory!$N:$N,MATCH(BP9,Inventory!$A:$A,0)),"") -> 91.53226 | BU9: "queen cooling sheets" asks for a Queen cooling sheet product that CooLinens sells (BreezeWeave nylon/spandex knit, 16″ pocket, 4-piece set). Relevance 100%: product type ✓, use case ✓, material ✓, intent ✓. | BV9: Decolure ($38 microfiber — adjacent, lower weight): small sample (88 clicks); organic best #4 (2025-06-18), 103 days in top 10, median #20. | BW9: Sleephoria (same product and price — strongest evidence): proven on the same product (78 clicks, CVR 12.8%, ACoS 23%); organic best #3 (2025-11-08), first top-10 2025-10-12, now #45. | BX9: SV 4,728/mo (MKL (DataDive)); launch window ≈ 5,605/mo; SQP 12-mo 86,358 searches, peak 2026-07, Oct at 0.91× its avg; Mar-24→Mar-26 ×2.19; market CVR 5.0% (head term 1.5%). | BY9: Organic top 20: Love's cabin #1, Bedsure PW #4. Advertising: OMERAI SP#4, Bambaw SP#5, BEDELITE SP#8, Breescape SP#9. Rival ad share 52%. | BZ9: Top-20 is held by bamboo/viscose sets (Love's cabin, Bedsure PW); no synthetic cooling-knit rival ranks here. CooLinens is the only nylon/spandex cooling option on the page at $79.99 — Sleephoria proved the knit ranks here. | CA9: Launch-window demand is ~35% of the June peak but these are the terms where evidence is strongest; ranking now means CooLinens holds position before the March ramp (SQP March ≈ 2× January). Queen roots belong to CooLinens, so this can be pushed at ranking spend from day 1. | CB9: Batch 1 Hero: relevance 100% ≥ 90%, clean wording, launch-window demand 5,605 searches/mo > 300 (own campaign), and evidence score 9.0/12 ≥ 6.0 (Sleephoria PPC +4 · Sleephoria rank +2 · market CVR +2 · competitors +0.5 · Decolure +0.5). Sleephoria did not overpay on it beyond the ranking ceiling. | CC9: ≤10 (≤40 by wk 2, ≤20 by wk 4, ≤10 by wk 8): Sleephoria, the same product, reached #3 here; 2 tracked rival(s) in the top 20.
A10: cooling queen sheets | B10: 1 | C10: 15 Oct 2026 | D10: Queen | E10: LAUNCH 15 Oct — rank push | F10: 1 | G10: Type ✓ · Use ✓ · Material ✓ · Intent ✓ | H10: High | I10: 8.5 | J10: Sleephoria PPC +4 · Sleephoria rank +2 · market CVR +1.5 · competitors +1 · Decolure +0 | K10: 2635 | L10: 2787 | M10: =L10/30 -> 92.9 | N10: 0.037781212 | O10: now #124 | P10: best #4 (2025-10-15) · PPC-period median #20 · now #24 | Q10: #4 Love's cabin | R10: 3 | S10: 10 | T10: #40 → #20 → #10 | U10: Love's cabin #4, Bedsure PW #5, Bambaw #11; Ads: KARISSA MAE SP#4, BEDELITE SP#5, Bambaw SP#6, REST SP#11 | V10: =IFERROR(INDEX(Sleephoria_History!$F$454:$F$2115,MATCH($A10,Sleephoria_History!$A$454:$A$2115,0)),"") -> 234 | W10: =IFERROR(INDEX(Sleephoria_History!$J$454:$J$2115,MATCH($A10,Sleephoria_History!$A$454:$A$2115,0)),"") -> 0.1111 | X10: =IFERROR(INDEX(Sleephoria_History!$H$454:$H$2115,MATCH($A10,Sleephoria_History!$A$454:$A$2115,0)),"") -> 2.95 | Y10: =IFERROR(INDEX(Sleephoria_History!$M$454:$M$2115,MATCH($A10,Sleephoria_History!$A$454:$A$2115,0)),"") -> 0.38 | Z10: =IFERROR(INDEX(Sleephoria_History!$L$454:$L$2115,MATCH($A10,Sleephoria_History!$A$454:$A$2115,0)),"") -> 1814.7 | AA10: =IFERROR(INDEX(Decolure_History!$F$397:$F$709,MATCH($A10,Decolure_History!$A$397:$A$709,0)),"") | AB10: =IFERROR(INDEX(Decolure_History!$J$397:$J$709,MATCH($A10,Decolure_History!$A$397:$A$709,0)),"") | AC10: =IFERROR(INDEX(Decolure_History!$M$397:$M$709,MATCH($A10,Decolure_History!$A$397:$A$709,0)),"") | AD10: 0.0889 | AE10: Sleephoria term CVR 11.1% on 234 clicks ×0.8 launch | AF10: 0.475 | AG10: =M10*AF10 -> 44.1275 | AH10: =IF(AO10="Brand Defense",0,IFERROR(VLOOKUP(S10,Assumptions!$A$24:$B$28,2,FALSE()),0)) -> 0.028 | AI10: =Assumptions!$B$6 -> 0.66 | AJ10: =AG10*AH10*AI10 -> 0.8154762 | AK10: =AJ10*AD10 -> 0.072495834 | AL10: =AJ10*56 -> 45.666667 | AM10: =AK10*56 -> 4.0597667 | AN10: =M10*Assumptions!$B$8 -> 9.29 | AO10: Ranking — Full Push | AP10: Full ranking push: Queen is CooLinens' own size (its keywords are not shared with Sleephoria) and the evidence is High (8.5/12). Every click the target rank requires is funded, with a Top-of-Search modifier where the ceiling allows. | AQ10: Exact | AR10: Exact: organic rank is earned per exact query, so sales must land on this wording; one keyword per campaign gives full control of bid, TOS modifier and budget, and clean attribution. Phrase / broad / auto open from week 4 for harvesting only. | AS10: =IF(AO10="Ranking — Full Push",MIN(MAX(AJ10,Assumptions!$B$9),AN10),IF(AO10="Brand Defense",MIN(Assumptions!$B$7,AN10),IF(OR(AO10="Ranking — Head Term (Capped)",AO10="Ranking — Capped Entry"),MIN(MAX(AJ10,Assumptions!$B$9),Assumptions!$B$7,AN10),IF(AO10="Ranking — Capped Long-Tail",MIN(AJ10,Assumptions!$B$10,AN10),MIN(AJ10,AN10))))) -> 1 | AT10: =IF(AJ10<=0,"",IF(AS10>=AJ10,IF(AS10>AJ10*1.05,"Floor of "&TEXT(AS10,"0.0")&" click/day to read CVR (rank needs "&TEXT(AJ10,"0.00")&")","Fully funded (100%)"),"Capped at "&TEXT(AS10/AJ10,"0%")&" of required")) -> Floor of 1.0 click/day to read CVR (rank needs 0.82) | AU10: =AS10*AD10 -> 0.0889 | AV10: =AU10*AY10 -> 7.111111 | AW10: 2.95 | AX10: Sleephoria CPC on this exact term (234 clicks) | AY10: =INDEX(Assumptions!$B$33:$B$37,MATCH(IF($D10="","Queen",$D10),Assumptions!$A$33:$A$37,0)) -> 79.99 | AZ10: =INDEX(Assumptions!$K$33:$K$37,MATCH(IF($D10="","Queen",$D10),Assumptions!$A$33:$A$37,0)) -> 0.55866046 | BA10: =INDEX(Assumptions!$H$33:$H$37,MATCH(IF($D10="","Queen",$D10),Assumptions!$A$33:$A$37,0)) -> 0.37244031 | BB10: =AY10*AZ10*AD10 -> 3.9726965 | BC10: =ROUND(MIN(AW10*Assumptions!$B$11,BB10),2) -> 2.95 | BD10: Yes | BE10: =IF(AO10="Ranking — Full Push",MAX(0,MIN(IF(BD10="Yes",Assumptions!$B$12,Assumptions!$B$13),FLOOR(MAX(0,BB10/BC10-1),Assumptions!$B$14))),0) -> 0.25 | BF10: =IF(AO10="Ranking — Full Push",IF(BE10>=1,"YES — +100% Top of Search. Effective CPC $"&TEXT(BG10,"0.00")&" (= $"&TEXT(BC10,"0.00")&" × 2) stays within the $"&TEXT(BB10,"0.00")&" max ranking CPC"&" (= $"&TEXT(AY10,"0.00")&" price × "&TEXT(AZ10,"0.0%")&" ranking ceiling × "&TEXT(AD10,"0.0%")&" CVR)"&". Sleephoria CVR is proven on this term, so the full push is justified.",IF(AND(BD10="No",BE10>=Assumptions!$B$13),"PARTIAL — +"&TEXT(BE10,"0%")&" Top of Search (limit for terms without proven CVR). Effective CPC $"&TEXT(BG10,"0.00")&" vs $"&TEXT(BB10,"0.00")&" max ranking CPC"&" (= $"&TEXT(AY10,"0.00")&" price × "&TEXT(AZ10,"0.0%")&" ranking ceiling × "&TEXT(AD10,"0.0%")&" CVR)"&". Raise to +100% only after CooLinens converts at ≥ "&TEXT(AD10,"0.0%")&" on 50+ clicks and $"&TEXT(BC10*2,"0.00")&" ≤ the max.",IF(BE10>0,"PARTIAL — +"&TEXT(BE10,"0%")&" Top of Search. Effective CPC $"&TEXT(BG10,"0.00")&" stays within the $"&TEXT(BB10,"0.00")&" max ranking CPC"&" (= $"&TEXT(AY10,"0.00")&" price × "&TEXT(AZ10,"0.0%")&" ranking ceiling × "&TEXT(AD10,"0.0%")&" CVR)"&". +100% would cost $"&TEXT(BC10*2,"0.00")&" per click and push ACoS to "&TEXT(BC10*2/(AY10*AD10),"0.0%")&", above the "&TEXT(AZ10,"0.0%")&" ceiling.","NO — 0%. Base bid $"&TEXT(BC10,"0.00")&" already equals the $"&TEXT(BB10,"0.00")&" max ranking CPC"&" (= $"&TEXT(AY10,"0.00")&" price × "&TEXT(AZ10,"0.0%")&" ranking ceiling × "&TEXT(AD10,"0.0%")&" CVR)"&"; any modifier would push ACoS above the "&TEXT(AZ10,"0.0%")&" ceiling."))),IF(OR(AO10="Ranking — Head Term (Capped)",AO10="Ranking — Capped Entry",AO10="Ranking — Capped Long-Tail"),"NO — 0% (capped ranking entry). Bid $"&TEXT(BC10,"0.00")&" vs $"&TEXT(BB10,"0.00")&" max ranking CPC"&" (= $"&TEXT(AY10,"0.00")&" price × "&TEXT(AZ10,"0.0%")&" ranking ceiling × "&TEXT(AD10,"0.0%")&" CVR)"&". While spend is capped at "&TEXT(AS10,"0.00")&" clicks/day, a placement premium would only raise CPC without buying more rank; the modifier is set when this term moves to a full push.","NO — 0% (support / brand term). Bid $"&TEXT(BC10,"0.00")&" vs $"&TEXT(BB10,"0.00")&" max ranking CPC"&" (= $"&TEXT(AY10,"0.00")&" price × "&TEXT(AZ10,"0.0%")&" ranking ceiling × "&TEXT(AD10,"0.0%")&" CVR)"&"; expected ACoS "&TEXT(BI10,"0.0%")&" vs the "&TEXT(AZ10,"0.0%")&" ceiling.")) -> PARTIAL — +25% Top of Search. Effective CPC $3.69 stays within the $3.97 max ranking CPC (= $79.99 price × 55.9% ranking ceiling × 8.9% CVR). +100% would cost $5.90 per click and push ACoS to 83.0%, above the 55.9% ceiling. | BG10: =BC10*(1+BE10) -> 3.6875 | BH10: =AS10*BG10 -> 3.6875 | BI10: =IFERROR(BG10/(AY10*AD10),"") -> 0.5185547 | BJ10: =IF(BI10="","",IF(BI10<=BA10,"Profitable (≤ break-even)",IF(BI10<=AZ10,"Ranking investment (≤ ceiling)","Above ceiling — reduce bid"))) -> Ranking investment (≤ ceiling) | BK10: ="Base $"&TEXT(BC10,"0.00")&" × (1 + "&TEXT(BE10,"0%")&" TOS) = $"&TEXT(BG10,"0.00")&" effective CPC [max $"&TEXT(BB10,"0.00")&"]. "&TEXT(AG10,"0.0")&" market clicks/day × "&TEXT(AH10,"0.00%")&" click share × "&TEXT(AI10,"0%")&" paid = "&TEXT(AJ10,"0.00")&" clicks/day needed; "&"planned "&TEXT(AS10,"0.00")&" clicks/day × "&TEXT(AD10,"0.0%")&" CVR = "&TEXT(AU10,"0.00")&" orders/day. "&"Spend $"&TEXT(BH10,"0.00")&"/day, ACoS "&TEXT(BI10,"0.0%")&" (ceiling "&TEXT(AZ10,"0.0%")&", break-even "&TEXT(BA10,"0.0%")&"). "&"Target organic rank #"&S10&" by week 8 ("&T10&")." -> Base $2.95 × (1 + 25% TOS) = $3.69 effective CPC [max $3.97]. 44.1 market clicks/day × 2.80% click share × 66% paid = 0.82 clicks/day needed; planned 1.00 clicks/day × 8.9% CVR = 0.09 orders/day. Spend $3.69/day, ACoS 51.9% (ceiling 55.9%, break-even 37.2%). Target organic rank #10 by week 8 (#40 → #20 → #10). | BL10: cooling sheets|Queen | BM10: Hero (single-keyword campaign) | BN10: CLCS4-SP-cooling queen sheets-HSV-Exact-Rank-Fix-Q-GRAPHITE | BO10: cooling queen sheets | BP10: CL-COOLING-SHEET-QUEEN-GRAPHITE | BQ10: B0H6K1MKQW | BR10: =IFERROR(INDEX(Campaigns!$L:$L,MATCH(BN10,Campaigns!$A:$A,0)),"") -> 10 | BS10: =IFERROR(INDEX(Inventory!$O:$O,MATCH(BP10,Inventory!$A:$A,0)),"") -> OK | BT10: =IFERROR(INDEX(Inventory!$N:$N,MATCH(BP10,Inventory!$A:$A,0)),"") -> 91.53226 | BU10: "cooling queen sheets" asks for a Queen cooling sheet product that CooLinens sells (BreezeWeave nylon/spandex knit, 16″ pocket, 4-piece set). Relevance 100%: product type ✓, use case ✓, material ✓, intent ✓. | BV10: Decolure ($38 microfiber — adjacent, lower weight): no search-term history. | BW10: Sleephoria (same product and price — strongest evidence): proven on the same product (234 clicks, CVR 11.1%, ACoS 38%); organic best #4 (2025-10-15), first top-10 2025-10-13, now #24. Launch entry Oct-25: 1.2 clicks/day, 0.28 orders/day, $7/day → top 10 in 10 days. | BX10: SV 2,635/mo (MKL (DataDive)); launch window ≈ 2,787/mo; SQP 12-mo 28,627 searches, peak 2026-06, Oct at 0.67× its avg; Mar-24→Mar-26 ×1.06; market CVR 3.8% (head term 1.5%). | BY10: Organic top 20: Love's cabin #4, Bedsure PW #5, Bambaw #11. Advertising: KARISSA MAE SP#4, BEDELITE SP#5, Bambaw SP#6, REST SP#11. Rival ad share 49%. | BZ10: Top-20 is held by bamboo/viscose sets (Love's cabin, Bedsure PW, Bambaw); no synthetic cooling-knit rival ranks here. CooLinens is the only nylon/spandex cooling option on the page at $79.99 — Sleephoria proved the knit ranks here. | CA10: Launch-window demand is ~35% of the June peak but these are the terms where evidence is strongest; ranking now means CooLinens holds position before the March ramp (SQP March ≈ 2× January). Queen roots belong to CooLinens, so this can be pushed at ranking spend from day 1. | CB10: Batch 1 Hero: relevance 100% ≥ 90%, clean wording, launch-window demand 2,787 searches/mo > 300 (own campaign), and evidence score 8.5/12 ≥ 6.0 (Sleephoria PPC +4 · Sleephoria rank +2 · market CVR +1.5 · competitors +1 · Decolure +0). Sleephoria did not overpay on it beyond the ranking ceiling. | CC10: ≤10 (≤40 by wk 2, ≤20 by wk 4, ≤10 by wk 8): Sleephoria, the same product, reached #4 here and entered the top 10 within 10 days; 3 tracked rival(s) in the top 20.
A11: queen bed sheets cooling | B11: 1 | C11: 15 Oct 2026 | D11: Queen | E11: LAUNCH 15 Oct — rank push | F11: 1 | G11: Type ✓ · Use ✓ · Material ✓ · Intent ✓ | H11: High | I11: 7.5 | J11: Sleephoria PPC +2 · Sleephoria rank +2 · market CVR +2 · competitors +1 · Decolure +0.5 | K11: 2630 | L11: 2485 | M11: =L11/30 -> 82.833333 | N11: 0.061472715 | O11: best #9 (2025-04-25) · median #22 · now #105 | P11: best #4 (2026-04-05) · PPC-period median #26 · now #14 | Q11: #3 Bedsure PW | R11: 3 | S11: 10 | T11: #40 → #20 → #10 | U11: Bedsure PW #3, Love's cabin #4, Bambaw #9; Ads: Bambaw SP#7, BEDELITE SP#9, Love's cabin SP#12, Hotel Sheets Direct SP#12 | V11: =IFERROR(INDEX(Sleephoria_History!$F$454:$F$2115,MATCH($A11,Sleephoria_History!$A$454:$A$2115,0)),"") -> 35 | W11: =IFERROR(INDEX(Sleephoria_History!$J$454:$J$2115,MATCH($A11,Sleephoria_History!$A$454:$A$2115,0)),"") -> 0.1143 | X11: =IFERROR(INDEX(Sleephoria_History!$H$454:$H$2115,MATCH($A11,Sleephoria_History!$A$454:$A$2115,0)),"") -> 3.14 | Y11: =IFERROR(INDEX(Sleephoria_History!$M$454:$M$2115,MATCH($A11,Sleephoria_History!$A$454:$A$2115,0)),"") -> 0.355 | Z11: =IFERROR(INDEX(Sleephoria_History!$L$454:$L$2115,MATCH($A11,Sleephoria_History!$A$454:$A$2115,0)),"") -> 309.96 | AA11: =IFERROR(INDEX(Decolure_History!$F$397:$F$709,MATCH($A11,Decolure_History!$A$397:$A$709,0)),"") -> 204 | AB11: =IFERROR(INDEX(Decolure_History!$J$397:$J$709,MATCH($A11,Decolure_History!$A$397:$A$709,0)),"") -> 0.049 | AC11: =IFERROR(INDEX(Decolure_History!$M$397:$M$709,MATCH($A11,Decolure_History!$A$397:$A$709,0)),"") -> 0.742 | AD11: 0.064 | AE11: bucket default (no history) ×0.8 launch | AF11: 0.409 | AG11: =M11*AF11 -> 33.878833 | AH11: =IF(AO11="Brand Defense",0,IFERROR(VLOOKUP(S11,Assumptions!$A$24:$B$28,2,FALSE()),0)) -> 0.028 | AI11: =Assumptions!$B$6 -> 0.66 | AJ11: =AG11*AH11*AI11 -> 0.62608084 | AK11: =AJ11*AD11 -> 0.040069174 | AL11: =AJ11*56 -> 35.060527 | AM11: =AK11*56 -> 2.2438737 | AN11: =M11*Assumptions!$B$8 -> 8.2833333 | AO11: Ranking — Full Push | AP11: Full ranking push: Queen is CooLinens' own size (its keywords are not shared with Sleephoria) and the evidence is High (7.5/12). Every click the target rank requires is funded, with a Top-of-Search modifier where the ceiling allows. | AQ11: Exact | AR11: Exact: organic rank is earned per exact query, so sales must land on this wording; one keyword per campaign gives full control of bid, TOS modifier and budget, and clean attribution. Phrase / broad / auto open from week 4 for harvesting only. | AS11: =IF(AO11="Ranking — Full Push",MIN(MAX(AJ11,Assumptions!$B$9),AN11),IF(AO11="Brand Defense",MIN(Assumptions!$B$7,AN11),IF(OR(AO11="Ranking — Head Term (Capped)",AO11="Ranking — Capped Entry"),MIN(MAX(AJ11,Assumptions!$B$9),Assumptions!$B$7,AN11),IF(AO11="Ranking — Capped Long-Tail",MIN(AJ11,Assumptions!$B$10,AN11),MIN(AJ11,AN11))))) -> 1 | AT11: =IF(AJ11<=0,"",IF(AS11>=AJ11,IF(AS11>AJ11*1.05,"Floor of "&TEXT(AS11,"0.0")&" click/day to read CVR (rank needs "&TEXT(AJ11,"0.00")&")","Fully funded (100%)"),"Capped at "&TEXT(AS11/AJ11,"0%")&" of required")) -> Floor of 1.0 click/day to read CVR (rank needs 0.63) | AU11: =AS11*AD11 -> 0.064 | AV11: =AU11*AY11 -> 5.11936 | AW11: 3.14 | AX11: Sleephoria CPC on this exact term (35 clicks) | AY11: =INDEX(Assumptions!$B$33:$B$37,MATCH(IF($D11="","Queen",$D11),Assumptions!$A$33:$A$37,0)) -> 79.99 | AZ11: =INDEX(Assumptions!$K$33:$K$37,MATCH(IF($D11="","Queen",$D11),Assumptions!$A$33:$A$37,0)) -> 0.55866046 | BA11: =INDEX(Assumptions!$H$33:$H$37,MATCH(IF($D11="","Queen",$D11),Assumptions!$A$33:$A$37,0)) -> 0.37244031 | BB11: =AY11*AZ11*AD11 -> 2.859984 | BC11: =ROUND(MIN(AW11*Assumptions!$B$11,BB11),2) -> 2.86 | BD11: No | BE11: =IF(AO11="Ranking — Full Push",MAX(0,MIN(IF(BD11="Yes",Assumptions!$B$12,Assumptions!$B$13),FLOOR(MAX(0,BB11/BC11-1),Assumptions!$B$14))),0) -> 0 | BF11: =IF(AO11="Ranking — Full Push",IF(BE11>=1,"YES — +100% Top of Search. Effective CPC $"&TEXT(BG11,"0.00")&" (= $"&TEXT(BC11,"0.00")&" × 2) stays within the $"&TEXT(BB11,"0.00")&" max ranking CPC"&" (= $"&TEXT(AY11,"0.00")&" price × "&TEXT(AZ11,"0.0%")&" ranking ceiling × "&TEXT(AD11,"0.0%")&" CVR)"&". Sleephoria CVR is proven on this term, so the full push is justified.",IF(AND(BD11="No",BE11>=Assumptions!$B$13),"PARTIAL — +"&TEXT(BE11,"0%")&" Top of Search (limit for terms without proven CVR). Effective CPC $"&TEXT(BG11,"0.00")&" vs $"&TEXT(BB11,"0.00")&" max ranking CPC"&" (= $"&TEXT(AY11,"0.00")&" price × "&TEXT(AZ11,"0.0%")&" ranking ceiling × "&TEXT(AD11,"0.0%")&" CVR)"&". Raise to +100% only after CooLinens converts at ≥ "&TEXT(AD11,"0.0%")&" on 50+ clicks and $"&TEXT(BC11*2,"0.00")&" ≤ the max.",IF(BE11>0,"PARTIAL — +"&TEXT(BE11,"0%")&" Top of Search. Effective CPC $"&TEXT(BG11,"0.00")&" stays within the $"&TEXT(BB11,"0.00")&" max ranking CPC"&" (= $"&TEXT(AY11,"0.00")&" price × "&TEXT(AZ11,"0.0%")&" ranking ceiling × "&TEXT(AD11,"0.0%")&" CVR)"&". +100% would cost $"&TEXT(BC11*2,"0.00")&" per click and push ACoS to "&TEXT(BC11*2/(AY11*AD11),"0.0%")&", above the "&TEXT(AZ11,"0.0%")&" ceiling.","NO — 0%. Base bid $"&TEXT(BC11,"0.00")&" already equals the $"&TEXT(BB11,"0.00")&" max ranking CPC"&" (= $"&TEXT(AY11,"0.00")&" price × "&TEXT(AZ11,"0.0%")&" ranking ceiling × "&TEXT(AD11,"0.0%")&" CVR)"&"; any modifier would push ACoS above the "&TEXT(AZ11,"0.0%")&" ceiling."))),IF(OR(AO11="Ranking — Head Term (Capped)",AO11="Ranking — Capped Entry",AO11="Ranking — Capped Long-Tail"),"NO — 0% (capped ranking entry). Bid $"&TEXT(BC11,"0.00")&" vs $"&TEXT(BB11,"0.00")&" max ranking CPC"&" (= $"&TEXT(AY11,"0.00")&" price × "&TEXT(AZ11,"0.0%")&" ranking ceiling × "&TEXT(AD11,"0.0%")&" CVR)"&". While spend is capped at "&TEXT(AS11,"0.00")&" clicks/day, a placement premium would only raise CPC without buying more rank; the modifier is set when this term moves to a full push.","NO — 0% (support / brand term). Bid $"&TEXT(BC11,"0.00")&" vs $"&TEXT(BB11,"0.00")&" max ranking CPC"&" (= $"&TEXT(AY11,"0.00")&" price × "&TEXT(AZ11,"0.0%")&" ranking ceiling × "&TEXT(AD11,"0.0%")&" CVR)"&"; expected ACoS "&TEXT(BI11,"0.0%")&" vs the "&TEXT(AZ11,"0.0%")&" ceiling.")) -> NO — 0%. Base bid $2.86 already equals the $2.86 max ranking CPC (= $79.99 price × 55.9% ranking ceiling × 6.4% CVR); any modifier would push ACoS above the 55.9% ceiling. | BG11: =BC11*(1+BE11) -> 2.86 | BH11: =AS11*BG11 -> 2.86 | BI11: =IFERROR(BG11/(AY11*AD11),"") -> 0.55866358 | BJ11: =IF(BI11="","",IF(BI11<=BA11,"Profitable (≤ break-even)",IF(BI11<=AZ11,"Ranking investment (≤ ceiling)","Above ceiling — reduce bid"))) -> Above ceiling — reduce bid | BK11: ="Base $"&TEXT(BC11,"0.00")&" × (1 + "&TEXT(BE11,"0%")&" TOS) = $"&TEXT(BG11,"0.00")&" effective CPC [max $"&TEXT(BB11,"0.00")&"]. "&TEXT(AG11,"0.0")&" market clicks/day × "&TEXT(AH11,"0.00%")&" click share × "&TEXT(AI11,"0%")&" paid = "&TEXT(AJ11,"0.00")&" clicks/day needed; "&"planned "&TEXT(AS11,"0.00")&" clicks/day × "&TEXT(AD11,"0.0%")&" CVR = "&TEXT(AU11,"0.00")&" orders/day. "&"Spend $"&TEXT(BH11,"0.00")&"/day, ACoS "&TEXT(BI11,"0.0%")&" (ceiling "&TEXT(AZ11,"0.0%")&", break-even "&TEXT(BA11,"0.0%")&"). "&"Target organic rank #"&S11&" by week 8 ("&T11&")." -> Base $2.86 × (1 + 0% TOS) = $2.86 effective CPC [max $2.86]. 33.9 market clicks/day × 2.80% click share × 66% paid = 0.63 clicks/day needed; planned 1.00 clicks/day × 6.4% CVR = 0.06 orders/day. Spend $2.86/day, ACoS 55.9% (ceiling 55.9%, break-even 37.2%). Target organic rank #10 by week 8 (#40 → #20 → #10). | BL11: cooling bed sheets|Queen | BM11: Hero (single-keyword campaign) | BN11: CLCS4-SP-queen bed sheets cooling-HSV-Exact-Rank-Fix-Q-GRAPHITE | BO11: queen bed sheets cooling | BP11: CL-COOLING-SHEET-QUEEN-GRAPHITE | BQ11: B0H6K1MKQW | BR11: =IFERROR(INDEX(Campaigns!$L:$L,MATCH(BN11,Campaigns!$A:$A,0)),"") -> 10 | BS11: =IFERROR(INDEX(Inventory!$O:$O,MATCH(BP11,Inventory!$A:$A,0)),"") -> OK | BT11: =IFERROR(INDEX(Inventory!$N:$N,MATCH(BP11,Inventory!$A:$A,0)),"") -> 91.53226 | BU11: "queen bed sheets cooling" asks for a Queen cooling sheet product that CooLinens sells (BreezeWeave nylon/spandex knit, 16″ pocket, 4-piece set). Relevance 100%: product type ✓, use case ✓, material ✓, intent ✓. | BV11: Decolure ($38 microfiber — adjacent, lower weight): small sample (204 clicks); organic best #9 (2025-04-25), 7 days in top 10, median #22. | BW11: Sleephoria (same product and price — strongest evidence): positive but small sample (35 clicks, CVR 11.4%); organic best #4 (2026-04-05), first top-10 2025-10-15, now #14. | BX11: SV 2,630/mo (MKL (DataDive)); launch window ≈ 2,485/mo; SQP 12-mo 51,598 searches, peak 2026-07, Oct at 0.86× its avg; Mar-24→Mar-26 ×1.75; market CVR 6.1% (head term 1.5%). | BY11: Organic top 20: Bedsure PW #3, Love's cabin #4, Bambaw #9. Advertising: Bambaw SP#7, BEDELITE SP#9, Love's cabin SP#12, Hotel Sheets Direct SP#12. Rival ad share 56%. | BZ11: Top-20 is held by bamboo/viscose sets (Bedsure PW, Love's cabin, Bambaw); no synthetic cooling-knit rival ranks here. CooLinens is the only nylon/spandex cooling option on the page at $79.99 — Sleephoria proved the knit ranks here. | CA11: Launch-window demand is ~35% of the June peak but these are the terms where evidence is strongest; ranking now means CooLinens holds position before the March ramp (SQP March ≈ 2× January). Queen roots belong to CooLinens, so this can be pushed at ranking spend from day 1. | CB11: Batch 1 Hero: relevance 100% ≥ 90%, clean wording, launch-window demand 2,485 searches/mo > 300 (own campaign), and evidence score 7.5/12 ≥ 6.0 (Sleephoria PPC +2 · Sleephoria rank +2 · market CVR +2 · competitors +1 · Decolure +0.5). Sleephoria did not overpay on it beyond the ranking ceiling. | CC11: ≤10 (≤40 by wk 2, ≤20 by wk 4, ≤10 by wk 8): Sleephoria, the same product, reached #4 here; 3 tracked rival(s) in the top 20.
A12: queen size sheets cooling | B12: 1 | C12: 15 Oct 2026 | D12: Queen | E12: LAUNCH 15 Oct — rank push | F12: 1 | G12: Type ✓ · Use ✓ · Material ✓ · Intent ✓ | H12: High | I12: 6.5 | J12: Sleephoria PPC +0 · root|size group proven on Sleephoria +1.5 (cooling sheets|Queen: CVR 10.9% on 3,545 clicks) · Sleephoria rank +2 · market CVR +2 · competitors +1 · Decolure +0 | K12: 1023 | L12: 1061 | M12: =L12/30 -> 35.366667 | N12: 0.059016932 | O12: now #134 | P12: best #4 (2025-10-20) · PPC-period median #30 · now #60 | Q12: #3 Love's cabin | R12: 4 | S12: 10 | T12: #40 → #20 → #10 | U12: Love's cabin #3, Bedsure PW #6, Bambaw #14, KRIMANO #15; Ads: KRIMANO SP#10, Bambaw SP#11, Hotel Sheets Direct SP#12, REST SP#15 | V12: =IFERROR(INDEX(Sleephoria_History!$F$454:$F$2115,MATCH($A12,Sleephoria_History!$A$454:$A$2115,0)),"") -> 12 | W12: =IFERROR(INDEX(Sleephoria_History!$J$454:$J$2115,MATCH($A12,Sleephoria_History!$A$454:$A$2115,0)),"") -> 0.0833 | X12: =IFERROR(INDEX(Sleephoria_History!$H$454:$H$2115,MATCH($A12,Sleephoria_History!$A$454:$A$2115,0)),"") -> 2.41 | Y12: =IFERROR(INDEX(Sleephoria_History!$M$454:$M$2115,MATCH($A12,Sleephoria_History!$A$454:$A$2115,0)),"") -> 0.361 | Z12: =IFERROR(INDEX(Sleephoria_History!$L$454:$L$2115,MATCH($A12,Sleephoria_History!$A$454:$A$2115,0)),"") -> 79.99 | AA12: =IFERROR(INDEX(Decolure_History!$F$397:$F$709,MATCH($A12,Decolure_History!$A$397:$A$709,0)),"") | AB12: =IFERROR(INDEX(Decolure_History!$J$397:$J$709,MATCH($A12,Decolure_History!$A$397:$A$709,0)),"") | AC12: =IFERROR(INDEX(Decolure_History!$M$397:$M$709,MATCH($A12,Decolure_History!$A$397:$A$709,0)),"") | AD12: 0.064 | AE12: bucket default (no history) ×0.8 launch | AF12: 0.428 | AG12: =M12*AF12 -> 15.136933 | AH12: =IF(AO12="Brand Defense",0,IFERROR(VLOOKUP(S12,Assumptions!$A$24:$B$28,2,FALSE()),0)) -> 0.028 | AI12: =Assumptions!$B$6 -> 0.66 | AJ12: =AG12*AH12*AI12 -> 0.27973053 | AK12: =AJ12*AD12 -> 0.017902754 | AL12: =AJ12*56 -> 15.66491 | AM12: =AK12*56 -> 1.0025542 | AN12: =M12*Assumptions!$B$8 -> 3.5366667 | AO12: Ranking — Full Push | AP12: Full ranking push: Queen is CooLinens' own size (its keywords are not shared with Sleephoria) and the evidence is High (6.5/12). Every click the target rank requires is funded, with a Top-of-Search modifier where the ceiling allows. | AQ12: Exact | AR12: Exact: organic rank is earned per exact query, so sales must land on this wording; one keyword per campaign gives full control of bid, TOS modifier and budget, and clean attribution. Phrase / broad / auto open from week 4 for harvesting only. | AS12: =IF(AO12="Ranking — Full Push",MIN(MAX(AJ12,Assumptions!$B$9),AN12),IF(AO12="Brand Defense",MIN(Assumptions!$B$7,AN12),IF(OR(AO12="Ranking — Head Term (Capped)",AO12="Ranking — Capped Entry"),MIN(MAX(AJ12,Assumptions!$B$9),Assumptions!$B$7,AN12),IF(AO12="Ranking — Capped Long-Tail",MIN(AJ12,Assumptions!$B$10,AN12),MIN(AJ12,AN12))))) -> 1 | AT12: =IF(AJ12<=0,"",IF(AS12>=AJ12,IF(AS12>AJ12*1.05,"Floor of "&TEXT(AS12,"0.0")&" click/day to read CVR (rank needs "&TEXT(AJ12,"0.00")&")","Fully funded (100%)"),"Capped at "&TEXT(AS12/AJ12,"0%")&" of required")) -> Floor of 1.0 click/day to read CVR (rank needs 0.28) | AU12: =AS12*AD12 -> 0.064 | AV12: =AU12*AY12 -> 5.11936 | AW12: 2.18 | AX12: Sleephoria avg CPC, Queen cooling terms | AY12: =INDEX(Assumptions!$B$33:$B$37,MATCH(IF($D12="","Queen",$D12),Assumptions!$A$33:$A$37,0)) -> 79.99 | AZ12: =INDEX(Assumptions!$K$33:$K$37,MATCH(IF($D12="","Queen",$D12),Assumptions!$A$33:$A$37,0)) -> 0.55866046 | BA12: =INDEX(Assumptions!$H$33:$H$37,MATCH(IF($D12="","Queen",$D12),Assumptions!$A$33:$A$37,0)) -> 0.37244031 | BB12: =AY12*AZ12*AD12 -> 2.859984 | BC12: =ROUND(MIN(AW12*Assumptions!$B$11,BB12),2) -> 2.18 | BD12: No | BE12: =IF(AO12="Ranking — Full Push",MAX(0,MIN(IF(BD12="Yes",Assumptions!$B$12,Assumptions!$B$13),FLOOR(MAX(0,BB12/BC12-1),Assumptions!$B$14))),0) -> 0.25 | BF12: =IF(AO12="Ranking — Full Push",IF(BE12>=1,"YES — +100% Top of Search. Effective CPC $"&TEXT(BG12,"0.00")&" (= $"&TEXT(BC12,"0.00")&" × 2) stays within the $"&TEXT(BB12,"0.00")&" max ranking CPC"&" (= $"&TEXT(AY12,"0.00")&" price × "&TEXT(AZ12,"0.0%")&" ranking ceiling × "&TEXT(AD12,"0.0%")&" CVR)"&". Sleephoria CVR is proven on this term, so the full push is justified.",IF(AND(BD12="No",BE12>=Assumptions!$B$13),"PARTIAL — +"&TEXT(BE12,"0%")&" Top of Search (limit for terms without proven CVR). Effective CPC $"&TEXT(BG12,"0.00")&" vs $"&TEXT(BB12,"0.00")&" max ranking CPC"&" (= $"&TEXT(AY12,"0.00")&" price × "&TEXT(AZ12,"0.0%")&" ranking ceiling × "&TEXT(AD12,"0.0%")&" CVR)"&". Raise to +100% only after CooLinens converts at ≥ "&TEXT(AD12,"0.0%")&" on 50+ clicks and $"&TEXT(BC12*2,"0.00")&" ≤ the max.",IF(BE12>0,"PARTIAL — +"&TEXT(BE12,"0%")&" Top of Search. Effective CPC $"&TEXT(BG12,"0.00")&" stays within the $"&TEXT(BB12,"0.00")&" max ranking CPC"&" (= $"&TEXT(AY12,"0.00")&" price × "&TEXT(AZ12,"0.0%")&" ranking ceiling × "&TEXT(AD12,"0.0%")&" CVR)"&". +100% would cost $"&TEXT(BC12*2,"0.00")&" per click and push ACoS to "&TEXT(BC12*2/(AY12*AD12),"0.0%")&", above the "&TEXT(AZ12,"0.0%")&" ceiling.","NO — 0%. Base bid $"&TEXT(BC12,"0.00")&" already equals the $"&TEXT(BB12,"0.00")&" max ranking CPC"&" (= $"&TEXT(AY12,"0.00")&" price × "&TEXT(AZ12,"0.0%")&" ranking ceiling × "&TEXT(AD12,"0.0%")&" CVR)"&"; any modifier would push ACoS above the "&TEXT(AZ12,"0.0%")&" ceiling."))),IF(OR(AO12="Ranking — Head Term (Capped)",AO12="Ranking — Capped Entry",AO12="Ranking — Capped Long-Tail"),"NO — 0% (capped ranking entry). Bid $"&TEXT(BC12,"0.00")&" vs $"&TEXT(BB12,"0.00")&" max ranking CPC"&" (= $"&TEXT(AY12,"0.00")&" price × "&TEXT(AZ12,"0.0%")&" ranking ceiling × "&TEXT(AD12,"0.0%")&" CVR)"&". While spend is capped at "&TEXT(AS12,"0.00")&" clicks/day, a placement premium would only raise CPC without buying more rank; the modifier is set when this term moves to a full push.","NO — 0% (support / brand term). Bid $"&TEXT(BC12,"0.00")&" vs $"&TEXT(BB12,"0.00")&" max ranking CPC"&" (= $"&TEXT(AY12,"0.00")&" price × "&TEXT(AZ12,"0.0%")&" ranking ceiling × "&TEXT(AD12,"0.0%")&" CVR)"&"; expected ACoS "&TEXT(BI12,"0.0%")&" vs the "&TEXT(AZ12,"0.0%")&" ceiling.")) -> PARTIAL — +25% Top of Search. Effective CPC $2.73 stays within the $2.86 max ranking CPC (= $79.99 price × 55.9% ranking ceiling × 6.4% CVR). +100% would cost $4.36 per click and push ACoS to 85.2%, above the 55.9% ceiling. | BG12: =BC12*(1+BE12) -> 2.725 | BH12: =AS12*BG12 -> 2.725 | BI12: =IFERROR(BG12/(AY12*AD12),"") -> 0.5322931 | BJ12: =IF(BI12="","",IF(BI12<=BA12,"Profitable (≤ break-even)",IF(BI12<=AZ12,"Ranking investment (≤ ceiling)","Above ceiling — reduce bid"))) -> Ranking investment (≤ ceiling) | BK12: ="Base $"&TEXT(BC12,"0.00")&" × (1 + "&TEXT(BE12,"0%")&" TOS) = $"&TEXT(BG12,"0.00")&" effective CPC [max $"&TEXT(BB12,"0.00")&"]. "&TEXT(AG12,"0.0")&" market clicks/day × "&TEXT(AH12,"0.00%")&" click share × "&TEXT(AI12,"0%")&" paid = "&TEXT(AJ12,"0.00")&" clicks/day needed; "&"planned "&TEXT(AS12,"0.00")&" clicks/day × "&TEXT(AD12,"0.0%")&" CVR = "&TEXT(AU12,"0.00")&" orders/day. "&"Spend $"&TEXT(BH12,"0.00")&"/day, ACoS "&TEXT(BI12,"0.0%")&" (ceiling "&TEXT(AZ12,"0.0%")&", break-even "&TEXT(BA12,"0.0%")&"). "&"Target organic rank #"&S12&" by week 8 ("&T12&")." -> Base $2.18 × (1 + 25% TOS) = $2.73 effective CPC [max $2.86]. 15.1 market clicks/day × 2.80% click share × 66% paid = 0.28 clicks/day needed; planned 1.00 clicks/day × 6.4% CVR = 0.06 orders/day. Spend $2.73/day, ACoS 53.2% (ceiling 55.9%, break-even 37.2%). Target organic rank #10 by week 8 (#40 → #20 → #10). | BL12: cooling sheets|Queen | BM12: Hero (single-keyword campaign) | BN12: CLCS4-SP-queen size sheets cooling-HSV-Exact-Rank-Fix-Q-GRAPHITE | BO12: queen size sheets cooling | BP12: CL-COOLING-SHEET-QUEEN-GRAPHITE | BQ12: B0H6K1MKQW | BR12: =IFERROR(INDEX(Campaigns!$L:$L,MATCH(BN12,Campaigns!$A:$A,0)),"") -> 10 | BS12: =IFERROR(INDEX(Inventory!$O:$O,MATCH(BP12,Inventory!$A:$A,0)),"") -> OK | BT12: =IFERROR(INDEX(Inventory!$N:$N,MATCH(BP12,Inventory!$A:$A,0)),"") -> 91.53226 | BU12: "queen size sheets cooling" asks for a Queen cooling sheet product that CooLinens sells (BreezeWeave nylon/spandex knit, 16″ pocket, 4-piece set). Relevance 100%: product type ✓, use case ✓, material ✓, intent ✓. | BV12: Decolure ($38 microfiber — adjacent, lower weight): no search-term history. | BW12: Sleephoria (same product and price — strongest evidence): too few clicks to read (12); organic best #4 (2025-10-20), first top-10 2025-10-14, now #60. | BX12: SV 1,023/mo (MKL (DataDive)); launch window ≈ 1,061/mo; SQP 12-mo 19,210 searches, peak 2026-06, Oct at 0.73× its avg; Mar-24→Mar-26 ×3.02; market CVR 5.9% (head term 1.5%). | BY12: Organic top 20: Love's cabin #3, Bedsure PW #6, Bambaw #14, KRIMANO #15. Advertising: KRIMANO SP#10, Bambaw SP#11, Hotel Sheets Direct SP#12, REST SP#15. Rival ad share 57%. | BZ12: Top-20 is held by bamboo/viscose sets (Love's cabin, Bedsure PW, Bambaw); no synthetic cooling-knit rival ranks here. CooLinens is the only nylon/spandex cooling option on the page at $79.99 — Sleephoria proved the knit ranks here. | CA12: Launch-window demand is ~35% of the June peak but these are the terms where evidence is strongest; ranking now means CooLinens holds position before the March ramp (SQP March ≈ 2× January). Queen roots belong to CooLinens, so this can be pushed at ranking spend from day 1. | CB12: Batch 1 Hero: relevance 100% ≥ 90%, clean wording, launch-window demand 1,061 searches/mo > 300 (own campaign), and evidence score 6.5/12 ≥ 6.0 (Sleephoria PPC +0 · root|size group proven on Sleephoria +1.5 (cooling sheets|Queen: CVR 10.9% on 3,545 clicks) · Sleephoria rank +2 · market CVR +2 · competitors +1 · Decolure +0). Sleephoria did not overpay on it beyond the ranking ceiling. | CC12: ≤10 (≤40 by wk 2, ≤20 by wk 4, ≤10 by wk 8): Sleephoria, the same product, reached #4 here; 4 tracked rival(s) in the top 20.
A13: cool sheets queen | B13: 1 | C13: 15 Oct 2026 | D13: Queen | E13: LAUNCH 15 Oct — rank push | F13: 1 | G13: Type ✓ · Use ✓ · Material ✓ · Intent ✓ | H13: High | I13: 9 | J13: Sleephoria PPC +4 · Sleephoria rank +2 · market CVR +2 · competitors +1 · Decolure +0 | K13: 766 | L13: 643 | M13: =L13/30 -> 21.433333 | N13: 0.045944298 | O13: now #114 | P13: best #2 (2025-10-22) · PPC-period median #19 · now #12 | Q13: #4 Bedsure PW | R13: 3 | S13: 10 | T13: #40 → #20 → #10 | U13: Bedsure PW #4, Love's cabin #5, Bambaw #7; Ads: KRIMANO SP#5, TRUE BAMBOO SP#7, Bedsure PW SP#7, Bambaw SP#7 | V13: =IFERROR(INDEX(Sleephoria_History!$F$454:$F$2115,MATCH($A13,Sleephoria_History!$A$454:$A$2115,0)),"") -> 120 | W13: =IFERROR(INDEX(Sleephoria_History!$J$454:$J$2115,MATCH($A13,Sleephoria_History!$A$454:$A$2115,0)),"") -> 0.15 | X13: =IFERROR(INDEX(Sleephoria_History!$H$454:$H$2115,MATCH($A13,Sleephoria_History!$A$454:$A$2115,0)),"") -> 2.39 | Y13: =IFERROR(INDEX(Sleephoria_History!$M$454:$M$2115,MATCH($A13,Sleephoria_History!$A$454:$A$2115,0)),"") -> 0.228 | Z13: =IFERROR(INDEX(Sleephoria_History!$L$454:$L$2115,MATCH($A13,Sleephoria_History!$A$454:$A$2115,0)),"") -> 1254.81 | AA13: =IFERROR(INDEX(Decolure_History!$F$397:$F$709,MATCH($A13,Decolure_History!$A$397:$A$709,0)),"") -> 27 | AB13: =IFERROR(INDEX(Decolure_History!$J$397:$J$709,MATCH($A13,Decolure_History!$A$397:$A$709,0)),"") -> 0.1481 | AC13: =IFERROR(INDEX(Decolure_History!$M$397:$M$709,MATCH($A13,Decolure_History!$A$397:$A$709,0)),"") -> 0.178 | AD13: 0.12 | AE13: Sleephoria term CVR 15.0% on 120 clicks ×0.8 launch | AF13: 0.406 | AG13: =M13*AF13 -> 8.7019333 | AH13: =IF(AO13="Brand Defense",0,IFERROR(VLOOKUP(S13,Assumptions!$A$24:$B$28,2,FALSE()),0)) -> 0.028 | AI13: =Assumptions!$B$6 -> 0.66 | AJ13: =AG13*AH13*AI13 -> 0.16081173 | AK13: =AJ13*AD13 -> 0.019297407 | AL13: =AJ13*56 -> 9.0054568 | AM13: =AK13*56 -> 1.0806548 | AN13: =M13*Assumptions!$B$8 -> 2.1433333 | AO13: Ranking — Full Push | AP13: Full ranking push: Queen is CooLinens' own size (its keywords are not shared with Sleephoria) and the evidence is High (9.0/12). Every click the target rank requires is funded, with a Top-of-Search modifier where the ceiling allows. | AQ13: Exact | AR13: Exact: organic rank is earned per exact query, so sales must land on this wording; one keyword per campaign gives full control of bid, TOS modifier and budget, and clean attribution. Phrase / broad / auto open from week 4 for harvesting only. | AS13: =IF(AO13="Ranking — Full Push",MIN(MAX(AJ13,Assumptions!$B$9),AN13),IF(AO13="Brand Defense",MIN(Assumptions!$B$7,AN13),IF(OR(AO13="Ranking — Head Term (Capped)",AO13="Ranking — Capped Entry"),MIN(MAX(AJ13,Assumptions!$B$9),Assumptions!$B$7,AN13),IF(AO13="Ranking — Capped Long-Tail",MIN(AJ13,Assumptions!$B$10,AN13),MIN(AJ13,AN13))))) -> 1 | AT13: =IF(AJ13<=0,"",IF(AS13>=AJ13,IF(AS13>AJ13*1.05,"Floor of "&TEXT(AS13,"0.0")&" click/day to read CVR (rank needs "&TEXT(AJ13,"0.00")&")","Fully funded (100%)"),"Capped at "&TEXT(AS13/AJ13,"0%")&" of required")) -> Floor of 1.0 click/day to read CVR (rank needs 0.16) | AU13: =AS13*AD13 -> 0.12 | AV13: =AU13*AY13 -> 9.5988 | AW13: 2.39 | AX13: Sleephoria CPC on this exact term (120 clicks) | AY13: =INDEX(Assumptions!$B$33:$B$37,MATCH(IF($D13="","Queen",$D13),Assumptions!$A$33:$A$37,0)) -> 79.99 | AZ13: =INDEX(Assumptions!$K$33:$K$37,MATCH(IF($D13="","Queen",$D13),Assumptions!$A$33:$A$37,0)) -> 0.55866046 | BA13: =INDEX(Assumptions!$H$33:$H$37,MATCH(IF($D13="","Queen",$D13),Assumptions!$A$33:$A$37,0)) -> 0.37244031 | BB13: =AY13*AZ13*AD13 -> 5.36247 | BC13: =ROUND(MIN(AW13*Assumptions!$B$11,BB13),2) -> 2.39 | BD13: Yes | BE13: =IF(AO13="Ranking — Full Push",MAX(0,MIN(IF(BD13="Yes",Assumptions!$B$12,Assumptions!$B$13),FLOOR(MAX(0,BB13/BC13-1),Assumptions!$B$14))),0) -> 1 | BF13: =IF(AO13="Ranking — Full Push",IF(BE13>=1,"YES — +100% Top of Search. Effective CPC $"&TEXT(BG13,"0.00")&" (= $"&TEXT(BC13,"0.00")&" × 2) stays within the $"&TEXT(BB13,"0.00")&" max ranking CPC"&" (= $"&TEXT(AY13,"0.00")&" price × "&TEXT(AZ13,"0.0%")&" ranking ceiling × "&TEXT(AD13,"0.0%")&" CVR)"&". Sleephoria CVR is proven on this term, so the full push is justified.",IF(AND(BD13="No",BE13>=Assumptions!$B$13),"PARTIAL — +"&TEXT(BE13,"0%")&" Top of Search (limit for terms without proven CVR). Effective CPC $"&TEXT(BG13,"0.00")&" vs $"&TEXT(BB13,"0.00")&" max ranking CPC"&" (= $"&TEXT(AY13,"0.00")&" price × "&TEXT(AZ13,"0.0%")&" ranking ceiling × "&TEXT(AD13,"0.0%")&" CVR)"&". Raise to +100% only after CooLinens converts at ≥ "&TEXT(AD13,"0.0%")&" on 50+ clicks and $"&TEXT(BC13*2,"0.00")&" ≤ the max.",IF(BE13>0,"PARTIAL — +"&TEXT(BE13,"0%")&" Top of Search. Effective CPC $"&TEXT(BG13,"0.00")&" stays within the $"&TEXT(BB13,"0.00")&" max ranking CPC"&" (= $"&TEXT(AY13,"0.00")&" price × "&TEXT(AZ13,"0.0%")&" ranking ceiling × "&TEXT(AD13,"0.0%")&" CVR)"&". +100% would cost $"&TEXT(BC13*2,"0.00")&" per click and push ACoS to "&TEXT(BC13*2/(AY13*AD13),"0.0%")&", above the "&TEXT(AZ13,"0.0%")&" ceiling.","NO — 0%. Base bid $"&TEXT(BC13,"0.00")&" already equals the $"&TEXT(BB13,"0.00")&" max ranking CPC"&" (= $"&TEXT(AY13,"0.00")&" price × "&TEXT(AZ13,"0.0%")&" ranking ceiling × "&TEXT(AD13,"0.0%")&" CVR)"&"; any modifier would push ACoS above the "&TEXT(AZ13,"0.0%")&" ceiling."))),IF(OR(AO13="Ranking — Head Term (Capped)",AO13="Ranking — Capped Entry",AO13="Ranking — Capped Long-Tail"),"NO — 0% (capped ranking entry). Bid $"&TEXT(BC13,"0.00")&" vs $"&TEXT(BB13,"0.00")&" max ranking CPC"&" (= $"&TEXT(AY13,"0.00")&" price × "&TEXT(AZ13,"0.0%")&" ranking ceiling × "&TEXT(AD13,"0.0%")&" CVR)"&". While spend is capped at "&TEXT(AS13,"0.00")&" clicks/day, a placement premium would only raise CPC without buying more rank; the modifier is set when this term moves to a full push.","NO — 0% (support / brand term). Bid $"&TEXT(BC13,"0.00")&" vs $"&TEXT(BB13,"0.00")&" max ranking CPC"&" (= $"&TEXT(AY13,"0.00")&" price × "&TEXT(AZ13,"0.0%")&" ranking ceiling × "&TEXT(AD13,"0.0%")&" CVR)"&"; expected ACoS "&TEXT(BI13,"0.0%")&" vs the "&TEXT(AZ13,"0.0%")&" ceiling.")) -> YES — +100% Top of Search. Effective CPC $4.78 (= $2.39 × 2) stays within the $5.36 max ranking CPC (= $79.99 price × 55.9% ranking ceiling × 12.0% CVR). Sleephoria CVR is proven on this term, so the full push is justified. | BG13: =BC13*(1+BE13) -> 4.78 | BH13: =AS13*BG13 -> 4.78 | BI13: =IFERROR(BG13/(AY13*AD13),"") -> 0.49797891 | BJ13: =IF(BI13="","",IF(BI13<=BA13,"Profitable (≤ break-even)",IF(BI13<=AZ13,"Ranking investment (≤ ceiling)","Above ceiling — reduce bid"))) -> Ranking investment (≤ ceiling) | BK13: ="Base $"&TEXT(BC13,"0.00")&" × (1 + "&TEXT(BE13,"0%")&" TOS) = $"&TEXT(BG13,"0.00")&" effective CPC [max $"&TEXT(BB13,"0.00")&"]. "&TEXT(AG13,"0.0")&" market clicks/day × "&TEXT(AH13,"0.00%")&" click share × "&TEXT(AI13,"0%")&" paid = "&TEXT(AJ13,"0.00")&" clicks/day needed; "&"planned "&TEXT(AS13,"0.00")&" clicks/day × "&TEXT(AD13,"0.0%")&" CVR = "&TEXT(AU13,"0.00")&" orders/day. "&"Spend $"&TEXT(BH13,"0.00")&"/day, ACoS "&TEXT(BI13,"0.0%")&" (ceiling "&TEXT(AZ13,"0.0%")&", break-even "&TEXT(BA13,"0.0%")&"). "&"Target organic rank #"&S13&" by week 8 ("&T13&")." -> Base $2.39 × (1 + 100% TOS) = $4.78 effective CPC [max $5.36]. 8.7 market clicks/day × 2.80% click share × 66% paid = 0.16 clicks/day needed; planned 1.00 clicks/day × 12.0% CVR = 0.12 orders/day. Spend $4.78/day, ACoS 49.8% (ceiling 55.9%, break-even 37.2%). Target organic rank #10 by week 8 (#40 → #20 → #10). | BL13: cool sheets|Queen | BM13: Hero (single-keyword campaign) | BN13: CLCS4-SP-cool sheets queen-MSV-Exact-Rank-Fix-Q-GRAPHITE | BO13: cool sheets queen | BP13: CL-COOLING-SHEET-QUEEN-GRAPHITE | BQ13: B0H6K1MKQW | BR13: =IFERROR(INDEX(Campaigns!$L:$L,MATCH(BN13,Campaigns!$A:$A,0)),"") -> 10 | BS13: =IFERROR(INDEX(Inventory!$O:$O,MATCH(BP13,Inventory!$A:$A,0)),"") -> OK | BT13: =IFERROR(INDEX(Inventory!$N:$N,MATCH(BP13,Inventory!$A:$A,0)),"") -> 91.53226 | BU13: "cool sheets queen" asks for a Queen cooling sheet product that CooLinens sells (BreezeWeave nylon/spandex knit, 16″ pocket, 4-piece set). Relevance 100%: product type ✓, use case ✓, material ✓, intent ✓. | BV13: Decolure ($38 microfiber — adjacent, lower weight): small sample (27 clicks). | BW13: Sleephoria (same product and price — strongest evidence): proven on the same product (120 clicks, CVR 15.0%, ACoS 23%); organic best #2 (2025-10-22), first top-10 2025-10-12, now #12. | BX13: SV 766/mo (MKL (DataDive)); launch window ≈ 643/mo; SQP 12-mo 16,425 searches, peak 2026-06, Oct at 0.90× its avg; market CVR 4.6% (head term 1.5%). | BY13: Organic top 20: Bedsure PW #4, Love's cabin #5, Bambaw #7. Advertising: KRIMANO SP#5, TRUE BAMBOO SP#7, Bedsure PW SP#7, Bambaw SP#7. Rival ad share 47%. | BZ13: Top-20 is held by bamboo/viscose sets (Bedsure PW, Love's cabin, Bambaw); no synthetic cooling-knit rival ranks here. CooLinens is the only nylon/spandex cooling option on the page at $79.99 — Sleephoria proved the knit ranks here. | CA13: Launch-window demand is ~35% of the June peak but these are the terms where evidence is strongest; ranking now means CooLinens holds position before the March ramp (SQP March ≈ 2× January). Queen roots belong to CooLinens, so this can be pushed at ranking spend from day 1. | CB13: Batch 1 Hero: relevance 100% ≥ 90%, clean wording, launch-window demand 643 searches/mo > 300 (own campaign), and evidence score 9.0/12 ≥ 6.0 (Sleephoria PPC +4 · Sleephoria rank +2 · market CVR +2 · competitors +1 · Decolure +0). Sleephoria did not overpay on it beyond the ranking ceiling. | CC13: ≤10 (≤40 by wk 2, ≤20 by wk 4, ≤10 by wk 8): Sleephoria, the same product, reached #2 here; 3 tracked rival(s) in the top 20.
A14: cool sheets for hot sleepers | B14: 1 | C14: 15 Oct 2026 | E14: LAUNCH 15 Oct — supporting rank | F14: 0.95 | G14: Type ✓ · Use ✓ · Material ✓ · Intent ✓ | H14: High | I14: 7.5 | J14: Sleephoria PPC +4 · Sleephoria rank +2 · market CVR +0.5 · competitors +1 · Decolure +0 | K14: 1961 | L14: 2298 | M14: =L14/30 -> 76.6 | N14: 0.018013291 | O14: now #93 | P14: best #2 (2026-03-18) · PPC-period median #14 · now #7 | Q14: #1 Bedsure PW | R14: 3 | S14: 10 | T14: #40 → #20 → #10 | U14: Bedsure PW #1, Love's cabin #4, Pure Bamboo #18; Ads: BEDELITE SP#1, Breescape SP#4, Pure Bamboo SP#6, Love's cabin SP#8 | V14: =IFERROR(INDEX(Sleephoria_History!$F$454:$F$2115,MATCH($A14,Sleephoria_History!$A$454:$A$2115,0)),"") -> 71 | W14: =IFERROR(INDEX(Sleephoria_History!$J$454:$J$2115,MATCH($A14,Sleephoria_History!$A$454:$A$2115,0)),"") -> 0.0986 | X14: =IFERROR(INDEX(Sleephoria_History!$H$454:$H$2115,MATCH($A14,Sleephoria_History!$A$454:$A$2115,0)),"") -> 2.81 | Y14: =IFERROR(INDEX(Sleephoria_History!$M$454:$M$2115,MATCH($A14,Sleephoria_History!$A$454:$A$2115,0)),"") -> 0.353 | Z14: =IFERROR(INDEX(Sleephoria_History!$L$454:$L$2115,MATCH($A14,Sleephoria_History!$A$454:$A$2115,0)),"") -> 564.93 | AA14: =IFERROR(INDEX(Decolure_History!$F$397:$F$709,MATCH($A14,Decolure_History!$A$397:$A$709,0)),"") -> 13 | AB14: =IFERROR(INDEX(Decolure_History!$J$397:$J$709,MATCH($A14,Decolure_History!$A$397:$A$709,0)),"") -> 0.1538 | AC14: =IFERROR(INDEX(Decolure_History!$M$397:$M$709,MATCH($A14,Decolure_History!$A$397:$A$709,0)),"") -> 0.303 | AD14: 0.0789 | AE14: Sleephoria term CVR 9.9% on 71 clicks ×0.8 launch | AF14: 0.443 | AG14: =M14*AF14 -> 33.9338 | AH14: =IF(AO14="Brand Defense",0,IFERROR(VLOOKUP(S14,Assumptions!$A$24:$B$28,2,FALSE()),0)) -> 0.028 | AI14: =Assumptions!$B$6 -> 0.66 | AJ14: =AG14*AH14*AI14 -> 0.62709662 | AK14: =AJ14*AD14 -> 0.049477924 | AL14: =AJ14*56 -> 35.117411 | AM14: =AK14*56 -> 2.7707637 | AN14: =M14*Assumptions!$B$8 -> 7.66 | AO14: Ranking — Support | AP14: Ranking support: relevant no-size wording with thinner evidence (7.5/12). Funded to what its own rank requires, no placement premium; its sales add velocity to the Queen hero terms. | AQ14: Exact | AR14: Exact: organic rank is earned per exact query, so sales must land on this wording; one keyword per campaign gives full control of bid, TOS modifier and budget, and clean attribution. Phrase / broad / auto open from week 4 for harvesting only. | AS14: =IF(AO14="Ranking — Full Push",MIN(MAX(AJ14,Assumptions!$B$9),AN14),IF(AO14="Brand Defense",MIN(Assumptions!$B$7,AN14),IF(OR(AO14="Ranking — Head Term (Capped)",AO14="Ranking — Capped Entry"),MIN(MAX(AJ14,Assumptions!$B$9),Assumptions!$B$7,AN14),IF(AO14="Ranking — Capped Long-Tail",MIN(AJ14,Assumptions!$B$10,AN14),MIN(AJ14,AN14))))) -> 0.62709662 | AT14: =IF(AJ14<=0,"",IF(AS14>=AJ14,IF(AS14>AJ14*1.05,"Floor of "&TEXT(AS14,"0.0")&" click/day to read CVR (rank needs "&TEXT(AJ14,"0.00")&")","Fully funded (100%)"),"Capped at "&TEXT(AS14/AJ14,"0%")&" of required")) -> Fully funded (100%) | AU14: =AS14*AD14 -> 0.049477924 | AV14: =AU14*AY14 -> 3.9577391 | AW14: 2.81 | AX14: Sleephoria CPC on this exact term (71 clicks) | AY14: =INDEX(Assumptions!$B$33:$B$37,MATCH(IF($D14="","Queen",$D14),Assumptions!$A$33:$A$37,0)) -> 79.99 | AZ14: =INDEX(Assumptions!$K$33:$K$37,MATCH(IF($D14="","Queen",$D14),Assumptions!$A$33:$A$37,0)) -> 0.55866046 | BA14: =INDEX(Assumptions!$H$33:$H$37,MATCH(IF($D14="","Queen",$D14),Assumptions!$A$33:$A$37,0)) -> 0.37244031 | BB14: =AY14*AZ14*AD14 -> 3.525824 | BC14: =ROUND(MIN(AW14*Assumptions!$B$11,BB14),2) -> 2.81 | BD14: Yes | BE14: =IF(AO14="Ranking — Full Push",MAX(0,MIN(IF(BD14="Yes",Assumptions!$B$12,Assumptions!$B$13),FLOOR(MAX(0,BB14/BC14-1),Assumptions!$B$14))),0) -> 0 | BF14: =IF(AO14="Ranking — Full Push",IF(BE14>=1,"YES — +100% Top of Search. Effective CPC $"&TEXT(BG14,"0.00")&" (= $"&TEXT(BC14,"0.00")&" × 2) stays within the $"&TEXT(BB14,"0.00")&" max ranking CPC"&" (= $"&TEXT(AY14,"0.00")&" price × "&TEXT(AZ14,"0.0%")&" ranking ceiling × "&TEXT(AD14,"0.0%")&" CVR)"&". Sleephoria CVR is proven on this term, so the full push is justified.",IF(AND(BD14="No",BE14>=Assumptions!$B$13),"PARTIAL — +"&TEXT(BE14,"0%")&" Top of Search (limit for terms without proven CVR). Effective CPC $"&TEXT(BG14,"0.00")&" vs $"&TEXT(BB14,"0.00")&" max ranking CPC"&" (= $"&TEXT(AY14,"0.00")&" price × "&TEXT(AZ14,"0.0%")&" ranking ceiling × "&TEXT(AD14,"0.0%")&" CVR)"&". Raise to +100% only after CooLinens converts at ≥ "&TEXT(AD14,"0.0%")&" on 50+ clicks and $"&TEXT(BC14*2,"0.00")&" ≤ the max.",IF(BE14>0,"PARTIAL — +"&TEXT(BE14,"0%")&" Top of Search. Effective CPC $"&TEXT(BG14,"0.00")&" stays within the $"&TEXT(BB14,"0.00")&" max ranking CPC"&" (= $"&TEXT(AY14,"0.00")&" price × "&TEXT(AZ14,"0.0%")&" ranking ceiling × "&TEXT(AD14,"0.0%")&" CVR)"&". +100% would cost $"&TEXT(BC14*2,"0.00")&" per click and push ACoS to "&TEXT(BC14*2/(AY14*AD14),"0.0%")&", above the "&TEXT(AZ14,"0.0%")&" ceiling.","NO — 0%. Base bid $"&TEXT(BC14,"0.00")&" already equals the $"&TEXT(BB14,"0.00")&" max ranking CPC"&" (= $"&TEXT(AY14,"0.00")&" price × "&TEXT(AZ14,"0.0%")&" ranking ceiling × "&TEXT(AD14,"0.0%")&" CVR)"&"; any modifier would push ACoS above the "&TEXT(AZ14,"0.0%")&" ceiling."))),IF(OR(AO14="Ranking — Head Term (Capped)",AO14="Ranking — Capped Entry",AO14="Ranking — Capped Long-Tail"),"NO — 0% (capped ranking entry). Bid $"&TEXT(BC14,"0.00")&" vs $"&TEXT(BB14,"0.00")&" max ranking CPC"&" (= $"&TEXT(AY14,"0.00")&" price × "&TEXT(AZ14,"0.0%")&" ranking ceiling × "&TEXT(AD14,"0.0%")&" CVR)"&". While spend is capped at "&TEXT(AS14,"0.00")&" clicks/day, a placement premium would only raise CPC without buying more rank; the modifier is set when this term moves to a full push.","NO — 0% (support / brand term). Bid $"&TEXT(BC14,"0.00")&" vs $"&TEXT(BB14,"0.00")&" max ranking CPC"&" (= $"&TEXT(AY14,"0.00")&" price × "&TEXT(AZ14,"0.0%")&" ranking ceiling × "&TEXT(AD14,"0.0%")&" CVR)"&"; expected ACoS "&TEXT(BI14,"0.0%")&" vs the "&TEXT(AZ14,"0.0%")&" ceiling.")) -> NO — 0% (support / brand term). Bid $2.81 vs $3.53 max ranking CPC (= $79.99 price × 55.9% ranking ceiling × 7.9% CVR); expected ACoS 44.5% vs the 55.9% ceiling. | BG14: =BC14*(1+BE14) -> 2.81 | BH14: =AS14*BG14 -> 1.7621415 | BI14: =IFERROR(BG14/(AY14*AD14),"") -> 0.44523943 | BJ14: =IF(BI14="","",IF(BI14<=BA14,"Profitable (≤ break-even)",IF(BI14<=AZ14,"Ranking investment (≤ ceiling)","Above ceiling — reduce bid"))) -> Ranking investment (≤ ceiling) | BK14: ="Base $"&TEXT(BC14,"0.00")&" × (1 + "&TEXT(BE14,"0%")&" TOS) = $"&TEXT(BG14,"0.00")&" effective CPC [max $"&TEXT(BB14,"0.00")&"]. "&TEXT(AG14,"0.0")&" market clicks/day × "&TEXT(AH14,"0.00%")&" click share × "&TEXT(AI14,"0%")&" paid = "&TEXT(AJ14,"0.00")&" clicks/day needed; "&"planned "&TEXT(AS14,"0.00")&" clicks/day × "&TEXT(AD14,"0.0%")&" CVR = "&TEXT(AU14,"0.00")&" orders/day. "&"Spend $"&TEXT(BH14,"0.00")&"/day, ACoS "&TEXT(BI14,"0.0%")&" (ceiling "&TEXT(AZ14,"0.0%")&", break-even "&TEXT(BA14,"0.0%")&"). "&"Target organic rank #"&S14&" by week 8 ("&T14&")." -> Base $2.81 × (1 + 0% TOS) = $2.81 effective CPC [max $3.53]. 33.9 market clicks/day × 2.80% click share × 66% paid = 0.63 clicks/day needed; planned 0.63 clicks/day × 7.9% CVR = 0.05 orders/day. Spend $1.76/day, ACoS 44.5% (ceiling 55.9%, break-even 37.2%). Target organic rank #10 by week 8 (#40 → #20 → #10). | BL14: cool sheets|no size | BM14: Hero (single-keyword campaign) | BN14: CLCS4-SP-cool sheets for hot sleepers-HSV-Exact-Rank-Fix-Q-GRAPHITE | BO14: cool sheets for hot sleepers | BP14: CL-COOLING-SHEET-QUEEN-GRAPHITE | BQ14: B0H6K1MKQW | BR14: =IFERROR(INDEX(Campaigns!$L:$L,MATCH(BN14,Campaigns!$A:$A,0)),"") -> 10 | BS14: =IFERROR(INDEX(Inventory!$O:$O,MATCH(BP14,Inventory!$A:$A,0)),"") -> OK | BT14: =IFERROR(INDEX(Inventory!$N:$N,MATCH(BP14,Inventory!$A:$A,0)),"") -> 91.53226 | BU14: "cool sheets for hot sleepers" asks for cooling sheet product that CooLinens sells (BreezeWeave nylon/spandex knit, 16″ pocket, 4-piece set). Relevance 95%: product type ✓, use case ✓, material ✓, intent ✓. | BV14: Decolure ($38 microfiber — adjacent, lower weight): small sample (13 clicks). | BW14: Sleephoria (same product and price — strongest evidence): proven on the same product (71 clicks, CVR 9.9%, ACoS 35%); organic best #2 (2026-03-18), first top-10 2025-10-13, now #7. | BX14: SV 1,961/mo (MKL (DataDive)); launch window ≈ 2,298/mo; SQP 12-mo 32,730 searches, peak 2026-06, Oct at 0.71× its avg; Mar-24→Mar-26 ×0.31; market CVR 1.8% (head term 1.5%). | BY14: Organic top 20: Bedsure PW #1, Love's cabin #4, Pure Bamboo #18. Advertising: BEDELITE SP#1, Breescape SP#4, Pure Bamboo SP#6, Love's cabin SP#8. Rival ad share 45%. | BZ14: Top-20 is held by bamboo/viscose sets (Bedsure PW, Love's cabin, Pure Bamboo); no synthetic cooling-knit rival ranks here. CooLinens is the only nylon/spandex cooling option on the page at $79.99 — Sleephoria proved the knit ranks here. | CA14: Launch-window demand is ~35% of the June peak but these are the terms where evidence is strongest; ranking now means CooLinens holds position before the March ramp (SQP March ≈ 2× January). No-size roots are shared with Sleephoria and not yet assigned: launch capped (50 clicks / 14 days) to read CooLinens CVR for the ownership decision. | CB14: Batch 1 Hero: relevance 95% ≥ 90%, clean wording, launch-window demand 2,298 searches/mo > 300 (own campaign), and evidence score 7.5/12 ≥ 6.0 (Sleephoria PPC +4 · Sleephoria rank +2 · market CVR +0.5 · competitors +1 · Decolure +0). Sleephoria did not overpay on it beyond the ranking ceiling. | CC14: ≤10 (≤40 by wk 2, ≤20 by wk 4, ≤10 by wk 8): Sleephoria, the same product, reached #2 here; 3 tracked rival(s) in the top 20.
A15: cooling sheets queen size | B15: 1 | C15: 15 Oct 2026 | D15: Queen | E15: LAUNCH 15 Oct — supporting rank | F15: 1 | G15: Type ✓ · Use ✓ · Material ✓ · Intent ✓ | H15: Medium | I15: 6 | J15: Sleephoria PPC +1 · Sleephoria rank +2 · market CVR +1.5 · competitors +1 · Decolure +0.5 | K15: 924 | L15: 1012 | M15: =L15/30 -> 33.733333 | N15: 0.039200091 | O15: best #7 (2025-04-25) · median #34 · now #122 | P15: best #4 (2026-03-04) · PPC-period median #20 · now #46 | Q15: #4 Love's cabin | R15: 3 | S15: 20 | T15: #60 → #35 → #20 | U15: Love's cabin #4, Bedsure PW #5, Bambaw #14; Ads: REST SP#1, Bedsure PW SP#4, TRUE BAMBOO SP#6, Bambaw SP#8 | V15: =IFERROR(INDEX(Sleephoria_History!$F$454:$F$2115,MATCH($A15,Sleephoria_History!$A$454:$A$2115,0)),"") -> 504 | W15: =IFERROR(INDEX(Sleephoria_History!$J$454:$J$2115,MATCH($A15,Sleephoria_History!$A$454:$A$2115,0)),"") -> 0.0575 | X15: =IFERROR(INDEX(Sleephoria_History!$H$454:$H$2115,MATCH($A15,Sleephoria_History!$A$454:$A$2115,0)),"") -> 1.4 | Y15: =IFERROR(INDEX(Sleephoria_History!$M$454:$M$2115,MATCH($A15,Sleephoria_History!$A$454:$A$2115,0)),"") -> 0.386 | Z15: =IFERROR(INDEX(Sleephoria_History!$L$454:$L$2115,MATCH($A15,Sleephoria_History!$A$454:$A$2115,0)),"") -> 1828.63 | AA15: =IFERROR(INDEX(Decolure_History!$F$397:$F$709,MATCH($A15,Decolure_History!$A$397:$A$709,0)),"") -> 65 | AB15: =IFERROR(INDEX(Decolure_History!$J$397:$J$709,MATCH($A15,Decolure_History!$A$397:$A$709,0)),"") -> 0.0308 | AC15: =IFERROR(INDEX(Decolure_History!$M$397:$M$709,MATCH($A15,Decolure_History!$A$397:$A$709,0)),"") -> 0.88 | AD15: 0.046 | AE15: Sleephoria term CVR 5.8% on 504 clicks ×0.8 launch | AF15: 0.448 | AG15: =M15*AF15 -> 15.112533 | AH15: =IF(AO15="Brand Defense",0,IFERROR(VLOOKUP(S15,Assumptions!$A$24:$B$28,2,FALSE()),0)) -> 0.0124 | AI15: =Assumptions!$B$6 -> 0.66 | AJ15: =AG15*AH15*AI15 -> 0.12368097 | AK15: =AJ15*AD15 -> 0.0056893247 | AL15: =AJ15*56 -> 6.9261345 | AM15: =AK15*56 -> 0.31860219 | AN15: =M15*Assumptions!$B$8 -> 3.3733333 | AO15: Ranking — Support | AP15: Ranking support: relevant Queen wording with thinner evidence (6.0/12). Funded to what its own rank requires, no placement premium; its sales add velocity to the Queen hero terms. | AQ15: Exact | AR15: Exact: organic rank is earned per exact query, so sales must land on this wording; one keyword per campaign gives full control of bid, TOS modifier and budget, and clean attribution. Phrase / broad / auto open from week 4 for harvesting only. | AS15: =IF(AO15="Ranking — Full Push",MIN(MAX(AJ15,Assumptions!$B$9),AN15),IF(AO15="Brand Defense",MIN(Assumptions!$B$7,AN15),IF(OR(AO15="Ranking — Head Term (Capped)",AO15="Ranking — Capped Entry"),MIN(MAX(AJ15,Assumptions!$B$9),Assumptions!$B$7,AN15),IF(AO15="Ranking — Capped Long-Tail",MIN(AJ15,Assumptions!$B$10,AN15),MIN(AJ15,AN15))))) -> 0.12368097 | AT15: =IF(AJ15<=0,"",IF(AS15>=AJ15,IF(AS15>AJ15*1.05,"Floor of "&TEXT(AS15,"0.0")&" click/day to read CVR (rank needs "&TEXT(AJ15,"0.00")&")","Fully funded (100%)"),"Capped at "&TEXT(AS15/AJ15,"0%")&" of required")) -> Fully funded (100%) | AU15: =AS15*AD15 -> 0.0056893247 | AV15: =AU15*AY15 -> 0.45508909 | AW15: 1.4 | AX15: Sleephoria CPC on this exact term (504 clicks) | AY15: =INDEX(Assumptions!$B$33:$B$37,MATCH(IF($D15="","Queen",$D15),Assumptions!$A$33:$A$37,0)) -> 79.99 | AZ15: =INDEX(Assumptions!$K$33:$K$37,MATCH(IF($D15="","Queen",$D15),Assumptions!$A$33:$A$37,0)) -> 0.55866046 | BA15: =INDEX(Assumptions!$H$33:$H$37,MATCH(IF($D15="","Queen",$D15),Assumptions!$A$33:$A$37,0)) -> 0.37244031 | BB15: =AY15*AZ15*AD15 -> 2.0556135 | BC15: =ROUND(MIN(AW15*Assumptions!$B$11,BB15),2) -> 1.4 | BD15: No | BE15: =IF(AO15="Ranking — Full Push",MAX(0,MIN(IF(BD15="Yes",Assumptions!$B$12,Assumptions!$B$13),FLOOR(MAX(0,BB15/BC15-1),Assumptions!$B$14))),0) -> 0 | BF15: =IF(AO15="Ranking — Full Push",IF(BE15>=1,"YES — +100% Top of Search. Effective CPC $"&TEXT(BG15,"0.00")&" (= $"&TEXT(BC15,"0.00")&" × 2) stays within the $"&TEXT(BB15,"0.00")&" max ranking CPC"&" (= $"&TEXT(AY15,"0.00")&" price × "&TEXT(AZ15,"0.0%")&" ranking ceiling × "&TEXT(AD15,"0.0%")&" CVR)"&". Sleephoria CVR is proven on this term, so the full push is justified.",IF(AND(BD15="No",BE15>=Assumptions!$B$13),"PARTIAL — +"&TEXT(BE15,"0%")&" Top of Search (limit for terms without proven CVR). Effective CPC $"&TEXT(BG15,"0.00")&" vs $"&TEXT(BB15,"0.00")&" max ranking CPC"&" (= $"&TEXT(AY15,"0.00")&" price × "&TEXT(AZ15,"0.0%")&" ranking ceiling × "&TEXT(AD15,"0.0%")&" CVR)"&". Raise to +100% only after CooLinens converts at ≥ "&TEXT(AD15,"0.0%")&" on 50+ clicks and $"&TEXT(BC15*2,"0.00")&" ≤ the max.",IF(BE15>0,"PARTIAL — +"&TEXT(BE15,"0%")&" Top of Search. Effective CPC $"&TEXT(BG15,"0.00")&" stays within the $"&TEXT(BB15,"0.00")&" max ranking CPC"&" (= $"&TEXT(AY15,"0.00")&" price × "&TEXT(AZ15,"0.0%")&" ranking ceiling × "&TEXT(AD15,"0.0%")&" CVR)"&". +100% would cost $"&TEXT(BC15*2,"0.00")&" per click and push ACoS to "&TEXT(BC15*2/(AY15*AD15),"0.0%")&", above the "&TEXT(AZ15,"0.0%")&" ceiling.","NO — 0%. Base bid $"&TEXT(BC15,"0.00")&" already equals the $"&TEXT(BB15,"0.00")&" max ranking CPC"&" (= $"&TEXT(AY15,"0.00")&" price × "&TEXT(AZ15,"0.0%")&" ranking ceiling × "&TEXT(AD15,"0.0%")&" CVR)"&"; any modifier would push ACoS above the "&TEXT(AZ15,"0.0%")&" ceiling."))),IF(OR(AO15="Ranking — Head Term (Capped)",AO15="Ranking — Capped Entry",AO15="Ranking — Capped Long-Tail"),"NO — 0% (capped ranking entry). Bid $"&TEXT(BC15,"0.00")&" vs $"&TEXT(BB15,"0.00")&" max ranking CPC"&" (= $"&TEXT(AY15,"0.00")&" price × "&TEXT(AZ15,"0.0%")&" ranking ceiling × "&TEXT(AD15,"0.0%")&" CVR)"&". While spend is capped at "&TEXT(AS15,"0.00")&" clicks/day, a placement premium would only raise CPC without buying more rank; the modifier is set when this term moves to a full push.","NO — 0% (support / brand term). Bid $"&TEXT(BC15,"0.00")&" vs $"&TEXT(BB15,"0.00")&" max ranking CPC"&" (= $"&TEXT(AY15,"0.00")&" price × "&TEXT(AZ15,"0.0%")&" ranking ceiling × "&TEXT(AD15,"0.0%")&" CVR)"&"; expected ACoS "&TEXT(BI15,"0.0%")&" vs the "&TEXT(AZ15,"0.0%")&" ceiling.")) -> NO — 0% (support / brand term). Bid $1.40 vs $2.06 max ranking CPC (= $79.99 price × 55.9% ranking ceiling × 4.6% CVR); expected ACoS 38.0% vs the 55.9% ceiling. | BG15: =BC15*(1+BE15) -> 1.4 | BH15: =AS15*BG15 -> 0.17315336 | BI15: =IFERROR(BG15/(AY15*AD15),"") -> 0.38048234 | BJ15: =IF(BI15="","",IF(BI15<=BA15,"Profitable (≤ break-even)",IF(BI15<=AZ15,"Ranking investment (≤ ceiling)","Above ceiling — reduce bid"))) -> Ranking investment (≤ ceiling) | BK15: ="Base $"&TEXT(BC15,"0.00")&" × (1 + "&TEXT(BE15,"0%")&" TOS) = $"&TEXT(BG15,"0.00")&" effective CPC [max $"&TEXT(BB15,"0.00")&"]. "&TEXT(AG15,"0.0")&" market clicks/day × "&TEXT(AH15,"0.00%")&" click share × "&TEXT(AI15,"0%")&" paid = "&TEXT(AJ15,"0.00")&" clicks/day needed; "&"planned "&TEXT(AS15,"0.00")&" clicks/day × "&TEXT(AD15,"0.0%")&" CVR = "&TEXT(AU15,"0.00")&" orders/day. "&"Spend $"&TEXT(BH15,"0.00")&"/day, ACoS "&TEXT(BI15,"0.0%")&" (ceiling "&TEXT(AZ15,"0.0%")&", break-even "&TEXT(BA15,"0.0%")&"). "&"Target organic rank #"&S15&" by week 8 ("&T15&")." -> Base $1.40 × (1 + 0% TOS) = $1.40 effective CPC [max $2.06]. 15.1 market clicks/day × 1.24% click share × 66% paid = 0.12 clicks/day needed; planned 0.12 clicks/day × 4.6% CVR = 0.01 orders/day. Spend $0.17/day, ACoS 38.0% (ceiling 55.9%, break-even 37.2%). Target organic rank #20 by week 8 (#60 → #35 → #20). | BL15: cooling sheets|Queen | BM15: Hero (single-keyword campaign) | BN15: CLCS4-SP-cooling sheets queen size-HSV-Exact-Rank-Fix-Q-GRAPHITE | BO15: cooling sheets queen size | BP15: CL-COOLING-SHEET-QUEEN-GRAPHITE | BQ15: B0H6K1MKQW | BR15: =IFERROR(INDEX(Campaigns!$L:$L,MATCH(BN15,Campaigns!$A:$A,0)),"") -> 10 | BS15: =IFERROR(INDEX(Inventory!$O:$O,MATCH(BP15,Inventory!$A:$A,0)),"") -> OK | BT15: =IFERROR(INDEX(Inventory!$N:$N,MATCH(BP15,Inventory!$A:$A,0)),"") -> 91.53226 | BU15: "cooling sheets queen size" asks for a Queen cooling sheet product that CooLinens sells (BreezeWeave nylon/spandex knit, 16″ pocket, 4-piece set). Relevance 100%: product type ✓, use case ✓, material ✓, intent ✓. | BV15: Decolure ($38 microfiber — adjacent, lower weight): small sample (65 clicks); organic best #7 (2025-04-25), 50 days in top 10, median #34. | BW15: Sleephoria (same product and price — strongest evidence): middling (504 clicks, CVR 5.8%); organic best #4 (2026-03-04), first top-10 2025-10-17, now #46. Launch entry Oct-25: 2.2 clicks/day, 0.31 orders/day, $13/day → top 10 in 14 days. | BX15: SV 924/mo (MKL (DataDive)); launch window ≈ 1,012/mo; SQP 12-mo 21,790 searches, peak 2026-06, Oct at 1.02× its avg; Mar-24→Mar-26 ×1.97; market CVR 3.9% (head term 1.5%). | BY15: Organic top 20: Love's cabin #4, Bedsure PW #5, Bambaw #14. Advertising: REST SP#1, Bedsure PW SP#4, TRUE BAMBOO SP#6, Bambaw SP#8. Rival ad share 46%. | BZ15: Top-20 is held by bamboo/viscose sets (Love's cabin, Bedsure PW, Bambaw); no synthetic cooling-knit rival ranks here. CooLinens is the only nylon/spandex cooling option on the page at $79.99 — Sleephoria proved the knit ranks here. | CA15: Launch-window demand is ~35% of the June peak but these are the terms where evidence is strongest; ranking now means CooLinens holds position before the March ramp (SQP March ≈ 2× January). Queen roots belong to CooLinens, so this can be pushed at ranking spend from day 1. | CB15: Batch 1 Hero: relevance 100% ≥ 90%, clean wording, launch-window demand 1,012 searches/mo > 300 (own campaign), and evidence score 6.0/12 ≥ 6.0 (Sleephoria PPC +1 · Sleephoria rank +2 · market CVR +1.5 · competitors +1 · Decolure +0.5). Sleephoria did not overpay on it beyond the ranking ceiling. | CC15: ≤20 (≤60 by wk 2, ≤35 by wk 4, ≤20 by wk 8): supporting rank — evidence or ownership does not justify a top-10 push yet.
A16: sheets queen cooling | B16: 1 | C16: 15 Oct 2026 | D16: Queen | E16: LAUNCH 15 Oct — supporting rank | F16: 1 | G16: Type ✓ · Use ✓ · Material ✓ · Intent ✓ | H16: Medium | I16: 6 | J16: Sleephoria PPC +0 · root|size group proven on Sleephoria +1.5 (cooling sheets|Queen: CVR 10.9% on 3,545 clicks) · Sleephoria rank +2 · market CVR +2 · competitors +0.5 · Decolure +0 | K16: 924 | L16: 752 | M16: =L16/30 -> 25.066667 | N16: 0.045266178 | O16: now #122 | P16: best #8 (2026-09-18) · PPC-period median #41 · now #35 | Q16: #1 Love's cabin | R16: 2 | S16: 20 | T16: #60 → #35 → #20 | U16: Love's cabin #1, Bedsure PW #2; Ads: California Design Den SP#2, Bambaw SP#6, Hotel Sheets Direct SP#9, Bedsure PW Cooling SP#9 | V16: =IFERROR(INDEX(Sleephoria_History!$F$454:$F$2115,MATCH($A16,Sleephoria_History!$A$454:$A$2115,0)),"") -> 1 | W16: =IFERROR(INDEX(Sleephoria_History!$J$454:$J$2115,MATCH($A16,Sleephoria_History!$A$454:$A$2115,0)),"") -> 1 | X16: =IFERROR(INDEX(Sleephoria_History!$H$454:$H$2115,MATCH($A16,Sleephoria_History!$A$454:$A$2115,0)),"") -> 2.84 | Y16: =IFERROR(INDEX(Sleephoria_History!$M$454:$M$2115,MATCH($A16,Sleephoria_History!$A$454:$A$2115,0)),"") -> 0.038 | Z16: =IFERROR(INDEX(Sleephoria_History!$L$454:$L$2115,MATCH($A16,Sleephoria_History!$A$454:$A$2115,0)),"") -> 74.99 | AA16: =IFERROR(INDEX(Decolure_History!$F$397:$F$709,MATCH($A16,Decolure_History!$A$397:$A$709,0)),"") | AB16: =IFERROR(INDEX(Decolure_History!$J$397:$J$709,MATCH($A16,Decolure_History!$A$397:$A$709,0)),"") | AC16: =IFERROR(INDEX(Decolure_History!$M$397:$M$709,MATCH($A16,Decolure_History!$A$397:$A$709,0)),"") | AD16: 0.064 | AE16: bucket default (no history) ×0.8 launch | AF16: 0.618 | AG16: =M16*AF16 -> 15.4912 | AH16: =IF(AO16="Brand Defense",0,IFERROR(VLOOKUP(S16,Assumptions!$A$24:$B$28,2,FALSE()),0)) -> 0.0124 | AI16: =Assumptions!$B$6 -> 0.66 | AJ16: =AG16*AH16*AI16 -> 0.12677998 | AK16: =AJ16*AD16 -> 0.0081139188 | AL16: =AJ16*56 -> 7.0996789 | AM16: =AK16*56 -> 0.45437945 | AN16: =M16*Assumptions!$B$8 -> 2.5066667 | AO16: Ranking — Support | AP16: Ranking support: relevant Queen wording with thinner evidence (6.0/12). Funded to what its own rank requires, no placement premium; its sales add velocity to the Queen hero terms. | AQ16: Exact | AR16: Exact: organic rank is earned per exact query, so sales must land on this wording; one keyword per campaign gives full control of bid, TOS modifier and budget, and clean attribution. Phrase / broad / auto open from week 4 for harvesting only. | AS16: =IF(AO16="Ranking — Full Push",MIN(MAX(AJ16,Assumptions!$B$9),AN16),IF(AO16="Brand Defense",MIN(Assumptions!$B$7,AN16),IF(OR(AO16="Ranking — Head Term (Capped)",AO16="Ranking — Capped Entry"),MIN(MAX(AJ16,Assumptions!$B$9),Assumptions!$B$7,AN16),IF(AO16="Ranking — Capped Long-Tail",MIN(AJ16,Assumptions!$B$10,AN16),MIN(AJ16,AN16))))) -> 0.12677998 | AT16: =IF(AJ16<=0,"",IF(AS16>=AJ16,IF(AS16>AJ16*1.05,"Floor of "&TEXT(AS16,"0.0")&" click/day to read CVR (rank needs "&TEXT(AJ16,"0.00")&")","Fully funded (100%)"),"Capped at "&TEXT(AS16/AJ16,"0%")&" of required")) -> Fully funded (100%) | AU16: =AS16*AD16 -> 0.0081139188 | AV16: =AU16*AY16 -> 0.64903236 | AW16: 2.18 | AX16: Sleephoria avg CPC, Queen cooling terms | AY16: =INDEX(Assumptions!$B$33:$B$37,MATCH(IF($D16="","Queen",$D16),Assumptions!$A$33:$A$37,0)) -> 79.99 | AZ16: =INDEX(Assumptions!$K$33:$K$37,MATCH(IF($D16="","Queen",$D16),Assumptions!$A$33:$A$37,0)) -> 0.55866046 | BA16: =INDEX(Assumptions!$H$33:$H$37,MATCH(IF($D16="","Queen",$D16),Assumptions!$A$33:$A$37,0)) -> 0.37244031 | BB16: =AY16*AZ16*AD16 -> 2.859984 | BC16: =ROUND(MIN(AW16*Assumptions!$B$11,BB16),2) -> 2.18 | BD16: No | BE16: =IF(AO16="Ranking — Full Push",MAX(0,MIN(IF(BD16="Yes",Assumptions!$B$12,Assumptions!$B$13),FLOOR(MAX(0,BB16/BC16-1),Assumptions!$B$14))),0) -> 0 | BF16: =IF(AO16="Ranking — Full Push",IF(BE16>=1,"YES — +100% Top of Search. Effective CPC $"&TEXT(BG16,"0.00")&" (= $"&TEXT(BC16,"0.00")&" × 2) stays within the $"&TEXT(BB16,"0.00")&" max ranking CPC"&" (= $"&TEXT(AY16,"0.00")&" price × "&TEXT(AZ16,"0.0%")&" ranking ceiling × "&TEXT(AD16,"0.0%")&" CVR)"&". Sleephoria CVR is proven on this term, so the full push is justified.",IF(AND(BD16="No",BE16>=Assumptions!$B$13),"PARTIAL — +"&TEXT(BE16,"0%")&" Top of Search (limit for terms without proven CVR). Effective CPC $"&TEXT(BG16,"0.00")&" vs $"&TEXT(BB16,"0.00")&" max ranking CPC"&" (= $"&TEXT(AY16,"0.00")&" price × "&TEXT(AZ16,"0.0%")&" ranking ceiling × "&TEXT(AD16,"0.0%")&" CVR)"&". Raise to +100% only after CooLinens converts at ≥ "&TEXT(AD16,"0.0%")&" on 50+ clicks and $"&TEXT(BC16*2,"0.00")&" ≤ the max.",IF(BE16>0,"PARTIAL — +"&TEXT(BE16,"0%")&" Top of Search. Effective CPC $"&TEXT(BG16,"0.00")&" stays within the $"&TEXT(BB16,"0.00")&" max ranking CPC"&" (= $"&TEXT(AY16,"0.00")&" price × "&TEXT(AZ16,"0.0%")&" ranking ceiling × "&TEXT(AD16,"0.0%")&" CVR)"&". +100% would cost $"&TEXT(BC16*2,"0.00")&" per click and push ACoS to "&TEXT(BC16*2/(AY16*AD16),"0.0%")&", above the "&TEXT(AZ16,"0.0%")&" ceiling.","NO — 0%. Base bid $"&TEXT(BC16,"0.00")&" already equals the $"&TEXT(BB16,"0.00")&" max ranking CPC"&" (= $"&TEXT(AY16,"0.00")&" price × "&TEXT(AZ16,"0.0%")&" ranking ceiling × "&TEXT(AD16,"0.0%")&" CVR)"&"; any modifier would push ACoS above the "&TEXT(AZ16,"0.0%")&" ceiling."))),IF(OR(AO16="Ranking — Head Term (Capped)",AO16="Ranking — Capped Entry",AO16="Ranking — Capped Long-Tail"),"NO — 0% (capped ranking entry). Bid $"&TEXT(BC16,"0.00")&" vs $"&TEXT(BB16,"0.00")&" max ranking CPC"&" (= $"&TEXT(AY16,"0.00")&" price × "&TEXT(AZ16,"0.0%")&" ranking ceiling × "&TEXT(AD16,"0.0%")&" CVR)"&". While spend is capped at "&TEXT(AS16,"0.00")&" clicks/day, a placement premium would only raise CPC without buying more rank; the modifier is set when this term moves to a full push.","NO — 0% (support / brand term). Bid $"&TEXT(BC16,"0.00")&" vs $"&TEXT(BB16,"0.00")&" max ranking CPC"&" (= $"&TEXT(AY16,"0.00")&" price × "&TEXT(AZ16,"0.0%")&" ranking ceiling × "&TEXT(AD16,"0.0%")&" CVR)"&"; expected ACoS "&TEXT(BI16,"0.0%")&" vs the "&TEXT(AZ16,"0.0%")&" ceiling.")) -> NO — 0% (support / brand term). Bid $2.18 vs $2.86 max ranking CPC (= $79.99 price × 55.9% ranking ceiling × 6.4% CVR); expected ACoS 42.6% vs the 55.9% ceiling. | BG16: =BC16*(1+BE16) -> 2.18 | BH16: =AS16*BG16 -> 0.27638036 | BI16: =IFERROR(BG16/(AY16*AD16),"") -> 0.42583448 | BJ16: =IF(BI16="","",IF(BI16<=BA16,"Profitable (≤ break-even)",IF(BI16<=AZ16,"Ranking investment (≤ ceiling)","Above ceiling — reduce bid"))) -> Ranking investment (≤ ceiling) | BK16: ="Base $"&TEXT(BC16,"0.00")&" × (1 + "&TEXT(BE16,"0%")&" TOS) = $"&TEXT(BG16,"0.00")&" effective CPC [max $"&TEXT(BB16,"0.00")&"]. "&TEXT(AG16,"0.0")&" market clicks/day × "&TEXT(AH16,"0.00%")&" click share × "&TEXT(AI16,"0%")&" paid = "&TEXT(AJ16,"0.00")&" clicks/day needed; "&"planned "&TEXT(AS16,"0.00")&" clicks/day × "&TEXT(AD16,"0.0%")&" CVR = "&TEXT(AU16,"0.00")&" orders/day. "&"Spend $"&TEXT(BH16,"0.00")&"/day, ACoS "&TEXT(BI16,"0.0%")&" (ceiling "&TEXT(AZ16,"0.0%")&", break-even "&TEXT(BA16,"0.0%")&"). "&"Target organic rank #"&S16&" by week 8 ("&T16&")." -> Base $2.18 × (1 + 0% TOS) = $2.18 effective CPC [max $2.86]. 15.5 market clicks/day × 1.24% click share × 66% paid = 0.13 clicks/day needed; planned 0.13 clicks/day × 6.4% CVR = 0.01 orders/day. Spend $0.28/day, ACoS 42.6% (ceiling 55.9%, break-even 37.2%). Target organic rank #20 by week 8 (#60 → #35 → #20). | BL16: cooling sheets|Queen | BM16: Hero (single-keyword campaign) | BN16: CLCS4-SP-sheets queen cooling-MSV-Exact-Rank-Fix-Q-GRAPHITE | BO16: sheets queen cooling | BP16: CL-COOLING-SHEET-QUEEN-GRAPHITE | BQ16: B0H6K1MKQW | BR16: =IFERROR(INDEX(Campaigns!$L:$L,MATCH(BN16,Campaigns!$A:$A,0)),"") -> 10 | BS16: =IFERROR(INDEX(Inventory!$O:$O,MATCH(BP16,Inventory!$A:$A,0)),"") -> OK | BT16: =IFERROR(INDEX(Inventory!$N:$N,MATCH(BP16,Inventory!$A:$A,0)),"") -> 91.53226 | BU16: "sheets queen cooling" asks for a Queen cooling sheet product that CooLinens sells (BreezeWeave nylon/spandex knit, 16″ pocket, 4-piece set). Relevance 100%: product type ✓, use case ✓, material ✓, intent ✓. | BV16: Decolure ($38 microfiber — adjacent, lower weight): no search-term history. | BW16: Sleephoria (same product and price — strongest evidence): too few clicks to read (1); organic best #8 (2026-09-18), first top-10 2026-09-16, now #35. | BX16: SV 924/mo (MKL (DataDive)); launch window ≈ 752/mo; SQP 12-mo 8,227 searches, peak 2026-07, Oct at 0.39× its avg; market CVR 4.5% (head term 1.5%). | BY16: Organic top 20: Love's cabin #1, Bedsure PW #2. Advertising: California Design Den SP#2, Bambaw SP#6, Hotel Sheets Direct SP#9, Bedsure PW Cooling SP#9. Rival ad share 51%. | BZ16: Top-20 is held by bamboo/viscose sets (Love's cabin, Bedsure PW); no synthetic cooling-knit rival ranks here. CooLinens is the only nylon/spandex cooling option on the page at $79.99 — Sleephoria proved the knit ranks here. | CA16: Launch-window demand is ~35% of the June peak but these are the terms where evidence is strongest; ranking now means CooLinens holds position before the March ramp (SQP March ≈ 2× January). Queen roots belong to CooLinens, so this can be pushed at ranking spend from day 1. | CB16: Batch 1 Hero: relevance 100% ≥ 90%, clean wording, launch-window demand 752 searches/mo > 300 (own campaign), and evidence score 6.0/12 ≥ 6.0 (Sleephoria PPC +0 · root|size group proven on Sleephoria +1.5 (cooling sheets|Queen: CVR 10.9% on 3,545 clicks) · Sleephoria rank +2 · market CVR +2 · competitors +0.5 · Decolure +0). Sleephoria did not overpay on it beyond the ranking ceiling. | CC16: ≤20 (≤60 by wk 2, ≤35 by wk 4, ≤20 by wk 8): supporting rank — evidence or ownership does not justify a top-10 push yet.
A17: cooling sheets | B17: 1 | C17: 15 Oct 2026 | E17: LAUNCH 15 Oct — capped ranking entry | F17: 0.95 | G17: Type ✓ · Use ✓ · Material ✓ · Intent ✓ | H17: High | I17: 7.5 | J17: Sleephoria PPC +4 · Sleephoria rank +2 · market CVR +0.5 · competitors +1 · Decolure +0 | K17: 77377 | L17: 83823 | M17: =L17/30 -> 2794.1 | N17: 0.015443056 | O17: best #4 (2025-04-25) · median #37 · now #132 | P17: best #1 (2026-04-22) · PPC-period median #11 · now #13 | Q17: #2 Bedsure PW | R17: 4 | S17: 20 | T17: #60 → #35 → #20 | U17: Bedsure PW #2, Pillcase #3, Love's cabin #5, Pure Bamboo #11, Pillcase #19; Ads: Pillcase SP#2, California Design Den SP#3, Hotel Sheets Direct SP#4, BC Bella Coterie SP#4 | V17: =IFERROR(INDEX(Sleephoria_History!$F$454:$F$2115,MATCH($A17,Sleephoria_History!$A$454:$A$2115,0)),"") -> 485 | W17: =IFERROR(INDEX(Sleephoria_History!$J$454:$J$2115,MATCH($A17,Sleephoria_History!$A$454:$A$2115,0)),"") -> 0.0948 | X17: =IFERROR(INDEX(Sleephoria_History!$H$454:$H$2115,MATCH($A17,Sleephoria_History!$A$454:$A$2115,0)),"") -> 2.01 | Y17: =IFERROR(INDEX(Sleephoria_History!$M$454:$M$2115,MATCH($A17,Sleephoria_History!$A$454:$A$2115,0)),"") -> 0.295 | Z17: =IFERROR(INDEX(Sleephoria_History!$L$454:$L$2115,MATCH($A17,Sleephoria_History!$A$454:$A$2115,0)),"") -> 3298.46 | AA17: =IFERROR(INDEX(Decolure_History!$F$397:$F$709,MATCH($A17,Decolure_History!$A$397:$A$709,0)),"") -> 376 | AB17: =IFERROR(INDEX(Decolure_History!$J$397:$J$709,MATCH($A17,Decolure_History!$A$397:$A$709,0)),"") -> 0.0293 | AC17: =IFERROR(INDEX(Decolure_History!$M$397:$M$709,MATCH($A17,Decolure_History!$A$397:$A$709,0)),"") -> 0.621 | AD17: 0.0758 | AE17: Sleephoria term CVR 9.5% on 485 clicks ×0.8 launch | AF17: 0.443 | AG17: =M17*AF17 -> 1237.7863 | AH17: =IF(AO17="Brand Defense",0,IFERROR(VLOOKUP(S17,Assumptions!$A$24:$B$28,2,FALSE()),0)) -> 0.0124 | AI17: =Assumptions!$B$6 -> 0.66 | AJ17: =AG17*AH17*AI17 -> 10.130043 | AK17: =AJ17*AD17 -> 0.76785727 | AL17: =AJ17*56 -> 567.28241 | AM17: =AK17*56 -> 43.000007 | AN17: =M17*Assumptions!$B$8 -> 279.41 | AO17: Ranking — Head Term (Capped) | AP17: Head term, capped: rank on broad heads follows sales velocity on the size terms — Sleephoria held #3–5 on "cooling sheets" with almost no spend on it, while bidding it directly ran 117% ACoS. Funded to what its rank needs (minimum 1 click/day), never above 3.57 clicks/day, to collect first sales and relevance. | AQ17: Exact | AR17: Exact: organic rank is earned per exact query, so sales must land on this wording; one keyword per campaign gives full control of bid, TOS modifier and budget, and clean attribution. Phrase / broad / auto open from week 4 for harvesting only. | AS17: =IF(AO17="Ranking — Full Push",MIN(MAX(AJ17,Assumptions!$B$9),AN17),IF(AO17="Brand Defense",MIN(Assumptions!$B$7,AN17),IF(OR(AO17="Ranking — Head Term (Capped)",AO17="Ranking — Capped Entry"),MIN(MAX(AJ17,Assumptions!$B$9),Assumptions!$B$7,AN17),IF(AO17="Ranking — Capped Long-Tail",MIN(AJ17,Assumptions!$B$10,AN17),MIN(AJ17,AN17))))) -> 3.5714286 | AT17: =IF(AJ17<=0,"",IF(AS17>=AJ17,IF(AS17>AJ17*1.05,"Floor of "&TEXT(AS17,"0.0")&" click/day to read CVR (rank needs "&TEXT(AJ17,"0.00")&")","Fully funded (100%)"),"Capped at "&TEXT(AS17/AJ17,"0%")&" of required")) -> Capped at 35% of required | AU17: =AS17*AD17 -> 0.27071429 | AV17: =AU17*AY17 -> 21.654436 | AW17: 2.01 | AX17: Sleephoria CPC on this exact term (485 clicks) | AY17: =INDEX(Assumptions!$B$33:$B$37,MATCH(IF($D17="","Queen",$D17),Assumptions!$A$33:$A$37,0)) -> 79.99 | AZ17: =INDEX(Assumptions!$K$33:$K$37,MATCH(IF($D17="","Queen",$D17),Assumptions!$A$33:$A$37,0)) -> 0.55866046 | BA17: =INDEX(Assumptions!$H$33:$H$37,MATCH(IF($D17="","Queen",$D17),Assumptions!$A$33:$A$37,0)) -> 0.37244031 | BB17: =AY17*AZ17*AD17 -> 3.3872935 | BC17: =ROUND(MIN(AW17*Assumptions!$B$11,BB17),2) -> 2.01 | BD17: Yes | BE17: =IF(AO17="Ranking — Full Push",MAX(0,MIN(IF(BD17="Yes",Assumptions!$B$12,Assumptions!$B$13),FLOOR(MAX(0,BB17/BC17-1),Assumptions!$B$14))),0) -> 0 | BF17: =IF(AO17="Ranking — Full Push",IF(BE17>=1,"YES — +100% Top of Search. Effective CPC $"&TEXT(BG17,"0.00")&" (= $"&TEXT(BC17,"0.00")&" × 2) stays within the $"&TEXT(BB17,"0.00")&" max ranking CPC"&" (= $"&TEXT(AY17,"0.00")&" price × "&TEXT(AZ17,"0.0%")&" ranking ceiling × "&TEXT(AD17,"0.0%")&" CVR)"&". Sleephoria CVR is proven on this term, so the full push is justified.",IF(AND(BD17="No",BE17>=Assumptions!$B$13),"PARTIAL — +"&TEXT(BE17,"0%")&" Top of Search (limit for terms without proven CVR). Effective CPC $"&TEXT(BG17,"0.00")&" vs $"&TEXT(BB17,"0.00")&" max ranking CPC"&" (= $"&TEXT(AY17,"0.00")&" price × "&TEXT(AZ17,"0.0%")&" ranking ceiling × "&TEXT(AD17,"0.0%")&" CVR)"&". Raise to +100% only after CooLinens converts at ≥ "&TEXT(AD17,"0.0%")&" on 50+ clicks and $"&TEXT(BC17*2,"0.00")&" ≤ the max.",IF(BE17>0,"PARTIAL — +"&TEXT(BE17,"0%")&" Top of Search. Effective CPC $"&TEXT(BG17,"0.00")&" stays within the $"&TEXT(BB17,"0.00")&" max ranking CPC"&" (= $"&TEXT(AY17,"0.00")&" price × "&TEXT(AZ17,"0.0%")&" ranking ceiling × "&TEXT(AD17,"0.0%")&" CVR)"&". +100% would cost $"&TEXT(BC17*2,"0.00")&" per click and push ACoS to "&TEXT(BC17*2/(AY17*AD17),"0.0%")&", above the "&TEXT(AZ17,"0.0%")&" ceiling.","NO — 0%. Base bid $"&TEXT(BC17,"0.00")&" already equals the $"&TEXT(BB17,"0.00")&" max ranking CPC"&" (= $"&TEXT(AY17,"0.00")&" price × "&TEXT(AZ17,"0.0%")&" ranking ceiling × "&TEXT(AD17,"0.0%")&" CVR)"&"; any modifier would push ACoS above the "&TEXT(AZ17,"0.0%")&" ceiling."))),IF(OR(AO17="Ranking — Head Term (Capped)",AO17="Ranking — Capped Entry",AO17="Ranking — Capped Long-Tail"),"NO — 0% (capped ranking entry). Bid $"&TEXT(BC17,"0.00")&" vs $"&TEXT(BB17,"0.00")&" max ranking CPC"&" (= $"&TEXT(AY17,"0.00")&" price × "&TEXT(AZ17,"0.0%")&" ranking ceiling × "&TEXT(AD17,"0.0%")&" CVR)"&". While spend is capped at "&TEXT(AS17,"0.00")&" clicks/day, a placement premium would only raise CPC without buying more rank; the modifier is set when this term moves to a full push.","NO — 0% (support / brand term). Bid $"&TEXT(BC17,"0.00")&" vs $"&TEXT(BB17,"0.00")&" max ranking CPC"&" (= $"&TEXT(AY17,"0.00")&" price × "&TEXT(AZ17,"0.0%")&" ranking ceiling × "&TEXT(AD17,"0.0%")&" CVR)"&"; expected ACoS "&TEXT(BI17,"0.0%")&" vs the "&TEXT(AZ17,"0.0%")&" ceiling.")) -> NO — 0% (capped ranking entry). Bid $2.01 vs $3.39 max ranking CPC (= $79.99 price × 55.9% ranking ceiling × 7.6% CVR). While spend is capped at 3.57 clicks/day, a placement premium would only raise CPC without buying more rank; the modifier is set when this term moves to a full push. | BG17: =BC17*(1+BE17) -> 2.01 | BH17: =AS17*BG17 -> 7.1785714 | BI17: =IFERROR(BG17/(AY17*AD17),"") -> 0.33150582 | BJ17: =IF(BI17="","",IF(BI17<=BA17,"Profitable (≤ break-even)",IF(BI17<=AZ17,"Ranking investment (≤ ceiling)","Above ceiling — reduce bid"))) -> Profitable (≤ break-even) | BK17: ="Base $"&TEXT(BC17,"0.00")&" × (1 + "&TEXT(BE17,"0%")&" TOS) = $"&TEXT(BG17,"0.00")&" effective CPC [max $"&TEXT(BB17,"0.00")&"]. "&TEXT(AG17,"0.0")&" market clicks/day × "&TEXT(AH17,"0.00%")&" click share × "&TEXT(AI17,"0%")&" paid = "&TEXT(AJ17,"0.00")&" clicks/day needed; "&"planned "&TEXT(AS17,"0.00")&" clicks/day × "&TEXT(AD17,"0.0%")&" CVR = "&TEXT(AU17,"0.00")&" orders/day. "&"Spend $"&TEXT(BH17,"0.00")&"/day, ACoS "&TEXT(BI17,"0.0%")&" (ceiling "&TEXT(AZ17,"0.0%")&", break-even "&TEXT(BA17,"0.0%")&"). "&"Target organic rank #"&S17&" by week 8 ("&T17&")." -> Base $2.01 × (1 + 0% TOS) = $2.01 effective CPC [max $3.39]. 1237.8 market clicks/day × 1.24% click share × 66% paid = 10.13 clicks/day needed; planned 3.57 clicks/day × 7.6% CVR = 0.27 orders/day. Spend $7.18/day, ACoS 33.2% (ceiling 55.9%, break-even 37.2%). Target organic rank #20 by week 8 (#60 → #35 → #20). | BL17: cooling sheets|no size | BM17: Hero (single-keyword campaign) | BN17: CLCS4-SP-cooling sheets-VHSV-Exact-Disc-Fix-Q-GRAPHITE | BO17: cooling sheets | BP17: CL-COOLING-SHEET-QUEEN-GRAPHITE | BQ17: B0H6K1MKQW | BR17: =IFERROR(INDEX(Campaigns!$L:$L,MATCH(BN17,Campaigns!$A:$A,0)),"") -> 10 | BS17: =IFERROR(INDEX(Inventory!$O:$O,MATCH(BP17,Inventory!$A:$A,0)),"") -> OK | BT17: =IFERROR(INDEX(Inventory!$N:$N,MATCH(BP17,Inventory!$A:$A,0)),"") -> 91.53226 | BU17: "cooling sheets" asks for cooling sheet product that CooLinens sells (BreezeWeave nylon/spandex knit, 16″ pocket, 4-piece set). Relevance 95%: product type ✓, use case ✓, material ✓, intent ✓. | BV17: Decolure ($38 microfiber — adjacent, lower weight): weak at the $38 tier (376 clicks, CVR 2.9%); organic best #4 (2025-04-25), 38 days in top 10, median #37. | BW17: Sleephoria (same product and price — strongest evidence): proven on the same product (485 clicks, CVR 9.5%, ACoS 30%); organic best #1 (2026-04-22), first top-10 2025-10-13, now #13. Launch entry Oct-25: 5.0 clicks/day, 0.38 orders/day, $28/day → top 10 in 10 days. | BX17: SV 77,377/mo (MKL (DataDive)); launch window ≈ 83,823/mo; SQP 12-mo 1,388,684 searches, peak 2026-07, Oct at 0.85× its avg; Mar-24→Mar-26 ×1.64; market CVR 1.5% (head term 1.5%). | BY17: Organic top 20: Bedsure PW #2, Pillcase #3, Love's cabin #5, Pure Bamboo #11. Advertising: Pillcase SP#2, California Design Den SP#3, Hotel Sheets Direct SP#4, BC Bella Coterie SP#4. Rival ad share 55%. | BZ17: Top-20 is held by bamboo/viscose sets (Bedsure PW, Pillcase, Love's cabin); no synthetic cooling-knit rival ranks here. CooLinens is the only nylon/spandex cooling option on the page at $79.99 — Sleephoria proved the knit ranks here. | CA17: Launch-window demand is ~35% of the June peak but these are the terms where evidence is strongest; ranking now means CooLinens holds position before the March ramp (SQP March ≈ 2× January). Head term — ranked by Queen size-term velocity (Sleephoria precedent); funded only as a capped probe. | CB17: Batch 1 Hero: relevance 95% ≥ 90%, clean wording, launch-window demand 83,823 searches/mo > 300 (own campaign), and evidence score 7.5/12 ≥ 6.0 (Sleephoria PPC +4 · Sleephoria rank +2 · market CVR +0.5 · competitors +1 · Decolure +0). Sleephoria did not overpay on it beyond the ranking ceiling. | CC17: ≤20 by week 8, earned from Queen/size-term velocity rather than direct bids (Sleephoria held #3–5 on "cooling sheets" with < $0.10/day on that exact term; bidding it directly ran 117% ACoS).
A18: cooling bed sheets | B18: 1 | C18: 15 Oct 2026 | E18: LAUNCH 15 Oct — capped ranking entry | F18: 0.95 | G18: Type ✓ · Use ✓ · Material ✓ · Intent ✓ | H18: Medium | I18: 6 | J18: Sleephoria PPC +1 · Sleephoria rank +2 · market CVR +0.5 · competitors +1 · Decolure +1.5 | K18: 12715 | L18: 18222 | M18: =L18/30 -> 607.4 | N18: 0.015497315 | O18: best #3 (2025-04-25) · median #27 · now #92 | P18: best #1 (2026-03-21) · PPC-period median #13 · now #18 | Q18: #2 Bedsure PW | R18: 5 | S18: 20 | T18: #60 → #35 → #20 | U18: Bedsure PW #2, Love's cabin #4, Pillcase #7, Bambaw #9, Pure Bamboo #19; Ads: Pillcase SP#3, KRIMANO SP#5, TRUE BAMBOO SP#5, Bambaw SP#10 | V18: =IFERROR(INDEX(Sleephoria_History!$F$454:$F$2115,MATCH($A18,Sleephoria_History!$A$454:$A$2115,0)),"") -> 259 | W18: =IFERROR(INDEX(Sleephoria_History!$J$454:$J$2115,MATCH($A18,Sleephoria_History!$A$454:$A$2115,0)),"") -> 0.0772 | X18: =IFERROR(INDEX(Sleephoria_History!$H$454:$H$2115,MATCH($A18,Sleephoria_History!$A$454:$A$2115,0)),"") -> 2.45 | Y18: =IFERROR(INDEX(Sleephoria_History!$M$454:$M$2115,MATCH($A18,Sleephoria_History!$A$454:$A$2115,0)),"") -> 0.421 | Z18: =IFERROR(INDEX(Sleephoria_History!$L$454:$L$2115,MATCH($A18,Sleephoria_History!$A$454:$A$2115,0)),"") -> 1508.3 | AA18: =IFERROR(INDEX(Decolure_History!$F$397:$F$709,MATCH($A18,Decolure_History!$A$397:$A$709,0)),"") -> 87 | AB18: =IFERROR(INDEX(Decolure_History!$J$397:$J$709,MATCH($A18,Decolure_History!$A$397:$A$709,0)),"") -> 0.092 | AC18: =IFERROR(INDEX(Decolure_History!$M$397:$M$709,MATCH($A18,Decolure_History!$A$397:$A$709,0)),"") -> 0.351 | AD18: 0.0618 | AE18: Sleephoria term CVR 7.7% on 259 clicks ×0.8 launch | AF18: 0.449 | AG18: =M18*AF18 -> 272.7226 | AH18: =IF(AO18="Brand Defense",0,IFERROR(VLOOKUP(S18,Assumptions!$A$24:$B$28,2,FALSE()),0)) -> 0.0124 | AI18: =Assumptions!$B$6 -> 0.66 | AJ18: =AG18*AH18*AI18 -> 2.2319618 | AK18: =AJ18*AD18 -> 0.13793524 | AL18: =AJ18*56 -> 124.98986 | AM18: =AK18*56 -> 7.7243733 | AN18: =M18*Assumptions!$B$8 -> 60.74 | AO18: Ranking — Head Term (Capped) | AP18: Head term, capped: rank on broad heads follows sales velocity on the size terms — Sleephoria held #3–5 on "cooling sheets" with almost no spend on it, while bidding it directly ran 117% ACoS. Funded to what its rank needs (minimum 1 click/day), never above 3.57 clicks/day, to collect first sales and relevance. | AQ18: Exact | AR18: Exact: organic rank is earned per exact query, so sales must land on this wording; one keyword per campaign gives full control of bid, TOS modifier and budget, and clean attribution. Phrase / broad / auto open from week 4 for harvesting only. | AS18: =IF(AO18="Ranking — Full Push",MIN(MAX(AJ18,Assumptions!$B$9),AN18),IF(AO18="Brand Defense",MIN(Assumptions!$B$7,AN18),IF(OR(AO18="Ranking — Head Term (Capped)",AO18="Ranking — Capped Entry"),MIN(MAX(AJ18,Assumptions!$B$9),Assumptions!$B$7,AN18),IF(AO18="Ranking — Capped Long-Tail",MIN(AJ18,Assumptions!$B$10,AN18),MIN(AJ18,AN18))))) -> 2.2319618 | AT18: =IF(AJ18<=0,"",IF(AS18>=AJ18,IF(AS18>AJ18*1.05,"Floor of "&TEXT(AS18,"0.0")&" click/day to read CVR (rank needs "&TEXT(AJ18,"0.00")&")","Fully funded (100%)"),"Capped at "&TEXT(AS18/AJ18,"0%")&" of required")) -> Fully funded (100%) | AU18: =AS18*AD18 -> 0.13793524 | AV18: =AU18*AY18 -> 11.03344 | AW18: 2.45 | AX18: Sleephoria CPC on this exact term (259 clicks) | AY18: =INDEX(Assumptions!$B$33:$B$37,MATCH(IF($D18="","Queen",$D18),Assumptions!$A$33:$A$37,0)) -> 79.99 | AZ18: =INDEX(Assumptions!$K$33:$K$37,MATCH(IF($D18="","Queen",$D18),Assumptions!$A$33:$A$37,0)) -> 0.55866046 | BA18: =INDEX(Assumptions!$H$33:$H$37,MATCH(IF($D18="","Queen",$D18),Assumptions!$A$33:$A$37,0)) -> 0.37244031 | BB18: =AY18*AZ18*AD18 -> 2.7616721 | BC18: =ROUND(MIN(AW18*Assumptions!$B$11,BB18),2) -> 2.45 | BD18: No | BE18: =IF(AO18="Ranking — Full Push",MAX(0,MIN(IF(BD18="Yes",Assumptions!$B$12,Assumptions!$B$13),FLOOR(MAX(0,BB18/BC18-1),Assumptions!$B$14))),0) -> 0 | BF18: =IF(AO18="Ranking — Full Push",IF(BE18>=1,"YES — +100% Top of Search. Effective CPC $"&TEXT(BG18,"0.00")&" (= $"&TEXT(BC18,"0.00")&" × 2) stays within the $"&TEXT(BB18,"0.00")&" max ranking CPC"&" (= $"&TEXT(AY18,"0.00")&" price × "&TEXT(AZ18,"0.0%")&" ranking ceiling × "&TEXT(AD18,"0.0%")&" CVR)"&". Sleephoria CVR is proven on this term, so the full push is justified.",IF(AND(BD18="No",BE18>=Assumptions!$B$13),"PARTIAL — +"&TEXT(BE18,"0%")&" Top of Search (limit for terms without proven CVR). Effective CPC $"&TEXT(BG18,"0.00")&" vs $"&TEXT(BB18,"0.00")&" max ranking CPC"&" (= $"&TEXT(AY18,"0.00")&" price × "&TEXT(AZ18,"0.0%")&" ranking ceiling × "&TEXT(AD18,"0.0%")&" CVR)"&". Raise to +100% only after CooLinens converts at ≥ "&TEXT(AD18,"0.0%")&" on 50+ clicks and $"&TEXT(BC18*2,"0.00")&" ≤ the max.",IF(BE18>0,"PARTIAL — +"&TEXT(BE18,"0%")&" Top of Search. Effective CPC $"&TEXT(BG18,"0.00")&" stays within the $"&TEXT(BB18,"0.00")&" max ranking CPC"&" (= $"&TEXT(AY18,"0.00")&" price × "&TEXT(AZ18,"0.0%")&" ranking ceiling × "&TEXT(AD18,"0.0%")&" CVR)"&". +100% would cost $"&TEXT(BC18*2,"0.00")&" per click and push ACoS to "&TEXT(BC18*2/(AY18*AD18),"0.0%")&", above the "&TEXT(AZ18,"0.0%")&" ceiling.","NO — 0%. Base bid $"&TEXT(BC18,"0.00")&" already equals the $"&TEXT(BB18,"0.00")&" max ranking CPC"&" (= $"&TEXT(AY18,"0.00")&" price × "&TEXT(AZ18,"0.0%")&" ranking ceiling × "&TEXT(AD18,"0.0%")&" CVR)"&"; any modifier would push ACoS above the "&TEXT(AZ18,"0.0%")&" ceiling."))),IF(OR(AO18="Ranking — Head Term (Capped)",AO18="Ranking — Capped Entry",AO18="Ranking — Capped Long-Tail"),"NO — 0% (capped ranking entry). Bid $"&TEXT(BC18,"0.00")&" vs $"&TEXT(BB18,"0.00")&" max ranking CPC"&" (= $"&TEXT(AY18,"0.00")&" price × "&TEXT(AZ18,"0.0%")&" ranking ceiling × "&TEXT(AD18,"0.0%")&" CVR)"&". While spend is capped at "&TEXT(AS18,"0.00")&" clicks/day, a placement premium would only raise CPC without buying more rank; the modifier is set when this term moves to a full push.","NO — 0% (support / brand term). Bid $"&TEXT(BC18,"0.00")&" vs $"&TEXT(BB18,"0.00")&" max ranking CPC"&" (= $"&TEXT(AY18,"0.00")&" price × "&TEXT(AZ18,"0.0%")&" ranking ceiling × "&TEXT(AD18,"0.0%")&" CVR)"&"; expected ACoS "&TEXT(BI18,"0.0%")&" vs the "&TEXT(AZ18,"0.0%")&" ceiling.")) -> NO — 0% (capped ranking entry). Bid $2.45 vs $2.76 max ranking CPC (= $79.99 price × 55.9% ranking ceiling × 6.2% CVR). While spend is capped at 2.23 clicks/day, a placement premium would only raise CPC without buying more rank; the modifier is set when this term moves to a full push. | BG18: =BC18*(1+BE18) -> 2.45 | BH18: =AS18*BG18 -> 5.4683063 | BI18: =IFERROR(BG18/(AY18*AD18),"") -> 0.49561211 | BJ18: =IF(BI18="","",IF(BI18<=BA18,"Profitable (≤ break-even)",IF(BI18<=AZ18,"Ranking investment (≤ ceiling)","Above ceiling — reduce bid"))) -> Ranking investment (≤ ceiling) | BK18: ="Base $"&TEXT(BC18,"0.00")&" × (1 + "&TEXT(BE18,"0%")&" TOS) = $"&TEXT(BG18,"0.00")&" effective CPC [max $"&TEXT(BB18,"0.00")&"]. "&TEXT(AG18,"0.0")&" market clicks/day × "&TEXT(AH18,"0.00%")&" click share × "&TEXT(AI18,"0%")&" paid = "&TEXT(AJ18,"0.00")&" clicks/day needed; "&"planned "&TEXT(AS18,"0.00")&" clicks/day × "&TEXT(AD18,"0.0%")&" CVR = "&TEXT(AU18,"0.00")&" orders/day. "&"Spend $"&TEXT(BH18,"0.00")&"/day, ACoS "&TEXT(BI18,"0.0%")&" (ceiling "&TEXT(AZ18,"0.0%")&", break-even "&TEXT(BA18,"0.0%")&"). "&"Target organic rank #"&S18&" by week 8 ("&T18&")." -> Base $2.45 × (1 + 0% TOS) = $2.45 effective CPC [max $2.76]. 272.7 market clicks/day × 1.24% click share × 66% paid = 2.23 clicks/day needed; planned 2.23 clicks/day × 6.2% CVR = 0.14 orders/day. Spend $5.47/day, ACoS 49.6% (ceiling 55.9%, break-even 37.2%). Target organic rank #20 by week 8 (#60 → #35 → #20). | BL18: cooling bed sheets|no size | BM18: Hero (single-keyword campaign) | BN18: CLCS4-SP-cooling bed sheets-VHSV-Exact-Disc-Fix-Q-GRAPHITE | BO18: cooling bed sheets | BP18: CL-COOLING-SHEET-QUEEN-GRAPHITE | BQ18: B0H6K1MKQW | BR18: =IFERROR(INDEX(Campaigns!$L:$L,MATCH(BN18,Campaigns!$A:$A,0)),"") -> 10 | BS18: =IFERROR(INDEX(Inventory!$O:$O,MATCH(BP18,Inventory!$A:$A,0)),"") -> OK | BT18: =IFERROR(INDEX(Inventory!$N:$N,MATCH(BP18,Inventory!$A:$A,0)),"") -> 91.53226 | BU18: "cooling bed sheets" asks for cooling sheet product that CooLinens sells (BreezeWeave nylon/spandex knit, 16″ pocket, 4-piece set). Relevance 95%: product type ✓, use case ✓, material ✓, intent ✓. | BV18: Decolure ($38 microfiber — adjacent, lower weight): converted at the $38 tier (87 clicks, CVR 9.2%, ACoS 35%); organic best #3 (2025-04-25), 95 days in top 10, median #27. | BW18: Sleephoria (same product and price — strongest evidence): middling (259 clicks, CVR 7.7%); organic best #1 (2026-03-21), first top-10 2025-10-12, now #18. Launch entry Oct-25: 2.6 clicks/day, 0.28 orders/day, $11/day → top 10 in 9 days. | BX18: SV 12,715/mo (MKL (DataDive)); launch window ≈ 18,222/mo; SQP 12-mo 250,049 searches, peak 2026-06, Oct at 0.67× its avg; Mar-24→Mar-26 ×1.85; market CVR 1.5% (head term 1.5%). | BY18: Organic top 20: Bedsure PW #2, Love's cabin #4, Pillcase #7, Bambaw #9. Advertising: Pillcase SP#3, KRIMANO SP#5, TRUE BAMBOO SP#5, Bambaw SP#10. Rival ad share 51%. | BZ18: Top-20 is held by bamboo/viscose sets (Bedsure PW, Love's cabin, Pillcase); no synthetic cooling-knit rival ranks here. CooLinens is the only nylon/spandex cooling option on the page at $79.99 — Sleephoria proved the knit ranks here. | CA18: Launch-window demand is ~35% of the June peak but these are the terms where evidence is strongest; ranking now means CooLinens holds position before the March ramp (SQP March ≈ 2× January). Head term — ranked by Queen size-term velocity (Sleephoria precedent); funded only as a capped probe. | CB18: Batch 1 Hero: relevance 95% ≥ 90%, clean wording, launch-window demand 18,222 searches/mo > 300 (own campaign), and evidence score 6.0/12 ≥ 6.0 (Sleephoria PPC +1 · Sleephoria rank +2 · market CVR +0.5 · competitors +1 · Decolure +1.5). Sleephoria did not overpay on it beyond the ranking ceiling. | CC18: ≤20 by week 8, earned from Queen/size-term velocity rather than direct bids (Sleephoria held #3–5 on "cooling sheets" with < $0.10/day on that exact term; bidding it directly ran 117% ACoS).
A19: cooling sheet set | B19: 1 | C19: 15 Oct 2026 | E19: LAUNCH 15 Oct — capped ranking entry | F19: 0.95 | G19: Type ✓ · Use ✓ · Material ✓ · Intent ✓ | H19: High | I19: 7.5 | J19: Sleephoria PPC +4 · Sleephoria rank +2 · market CVR +0.5 · competitors +1 · Decolure +0 | K19: 1669 | L19: 1546 | M19: =L19/30 -> 51.533333 | N19: 0.014025389 | O19: now #135 | P19: best #4 (2025-11-07) · PPC-period median #32 · now #38 | Q19: #1 Bedsure PW | R19: 6 | S19: 20 | T19: #60 → #35 → #20 | U19: Bedsure PW #1, Love's cabin #5, Breescape #10, Pure Bamboo #11, KRIMANO #17; Ads: California Design Den SP#2, REST SP#3, KARISSA MAE SP#4, Bambaw SP#6 | V19: =IFERROR(INDEX(Sleephoria_History!$F$454:$F$2115,MATCH($A19,Sleephoria_History!$A$454:$A$2115,0)),"") -> 61 | W19: =IFERROR(INDEX(Sleephoria_History!$J$454:$J$2115,MATCH($A19,Sleephoria_History!$A$454:$A$2115,0)),"") -> 0.0984 | X19: =IFERROR(INDEX(Sleephoria_History!$H$454:$H$2115,MATCH($A19,Sleephoria_History!$A$454:$A$2115,0)),"") -> 2.35 | Y19: =IFERROR(INDEX(Sleephoria_History!$M$454:$M$2115,MATCH($A19,Sleephoria_History!$A$454:$A$2115,0)),"") -> 0.302 | Z19: =IFERROR(INDEX(Sleephoria_History!$L$454:$L$2115,MATCH($A19,Sleephoria_History!$A$454:$A$2115,0)),"") -> 474.94 | AA19: =IFERROR(INDEX(Decolure_History!$F$397:$F$709,MATCH($A19,Decolure_History!$A$397:$A$709,0)),"") | AB19: =IFERROR(INDEX(Decolure_History!$J$397:$J$709,MATCH($A19,Decolure_History!$A$397:$A$709,0)),"") | AC19: =IFERROR(INDEX(Decolure_History!$M$397:$M$709,MATCH($A19,Decolure_History!$A$397:$A$709,0)),"") | AD19: 0.0787 | AE19: Sleephoria term CVR 9.8% on 61 clicks ×0.8 launch | AF19: 0.433 | AG19: =M19*AF19 -> 22.313933 | AH19: =IF(AO19="Brand Defense",0,IFERROR(VLOOKUP(S19,Assumptions!$A$24:$B$28,2,FALSE()),0)) -> 0.0124 | AI19: =Assumptions!$B$6 -> 0.66 | AJ19: =AG19*AH19*AI19 -> 0.18261723 | AK19: =AJ19*AD19 -> 0.014371976 | AL19: =AJ19*56 -> 10.226565 | AM19: =AK19*56 -> 0.80483066 | AN19: =M19*Assumptions!$B$8 -> 5.1533333 | AO19: Ranking — Head Term (Capped) | AP19: Head term, capped: rank on broad heads follows sales velocity on the size terms — Sleephoria held #3–5 on "cooling sheets" with almost no spend on it, while bidding it directly ran 117% ACoS. Funded to what its rank needs (minimum 1 click/day), never above 3.57 clicks/day, to collect first sales and relevance. | AQ19: Exact | AR19: Exact: organic rank is earned per exact query, so sales must land on this wording; one keyword per campaign gives full control of bid, TOS modifier and budget, and clean attribution. Phrase / broad / auto open from week 4 for harvesting only. | AS19: =IF(AO19="Ranking — Full Push",MIN(MAX(AJ19,Assumptions!$B$9),AN19),IF(AO19="Brand Defense",MIN(Assumptions!$B$7,AN19),IF(OR(AO19="Ranking — Head Term (Capped)",AO19="Ranking — Capped Entry"),MIN(MAX(AJ19,Assumptions!$B$9),Assumptions!$B$7,AN19),IF(AO19="Ranking — Capped Long-Tail",MIN(AJ19,Assumptions!$B$10,AN19),MIN(AJ19,AN19))))) -> 1 | AT19: =IF(AJ19<=0,"",IF(AS19>=AJ19,IF(AS19>AJ19*1.05,"Floor of "&TEXT(AS19,"0.0")&" click/day to read CVR (rank needs "&TEXT(AJ19,"0.00")&")","Fully funded (100%)"),"Capped at "&TEXT(AS19/AJ19,"0%")&" of required")) -> Floor of 1.0 click/day to read CVR (rank needs 0.18) | AU19: =AS19*AD19 -> 0.0787 | AV19: =AU19*AY19 -> 6.295213 | AW19: 2.35 | AX19: Sleephoria CPC on this exact term (61 clicks) | AY19: =INDEX(Assumptions!$B$33:$B$37,MATCH(IF($D19="","Queen",$D19),Assumptions!$A$33:$A$37,0)) -> 79.99 | AZ19: =INDEX(Assumptions!$K$33:$K$37,MATCH(IF($D19="","Queen",$D19),Assumptions!$A$33:$A$37,0)) -> 0.55866046 | BA19: =INDEX(Assumptions!$H$33:$H$37,MATCH(IF($D19="","Queen",$D19),Assumptions!$A$33:$A$37,0)) -> 0.37244031 | BB19: =AY19*AZ19*AD19 -> 3.5168866 | BC19: =ROUND(MIN(AW19*Assumptions!$B$11,BB19),2) -> 2.35 | BD19: Yes | BE19: =IF(AO19="Ranking — Full Push",MAX(0,MIN(IF(BD19="Yes",Assumptions!$B$12,Assumptions!$B$13),FLOOR(MAX(0,BB19/BC19-1),Assumptions!$B$14))),0) -> 0 | BF19: =IF(AO19="Ranking — Full Push",IF(BE19>=1,"YES — +100% Top of Search. Effective CPC $"&TEXT(BG19,"0.00")&" (= $"&TEXT(BC19,"0.00")&" × 2) stays within the $"&TEXT(BB19,"0.00")&" max ranking CPC"&" (= $"&TEXT(AY19,"0.00")&" price × "&TEXT(AZ19,"0.0%")&" ranking ceiling × "&TEXT(AD19,"0.0%")&" CVR)"&". Sleephoria CVR is proven on this term, so the full push is justified.",IF(AND(BD19="No",BE19>=Assumptions!$B$13),"PARTIAL — +"&TEXT(BE19,"0%")&" Top of Search (limit for terms without proven CVR). Effective CPC $"&TEXT(BG19,"0.00")&" vs $"&TEXT(BB19,"0.00")&" max ranking CPC"&" (= $"&TEXT(AY19,"0.00")&" price × "&TEXT(AZ19,"0.0%")&" ranking ceiling × "&TEXT(AD19,"0.0%")&" CVR)"&". Raise to +100% only after CooLinens converts at ≥ "&TEXT(AD19,"0.0%")&" on 50+ clicks and $"&TEXT(BC19*2,"0.00")&" ≤ the max.",IF(BE19>0,"PARTIAL — +"&TEXT(BE19,"0%")&" Top of Search. Effective CPC $"&TEXT(BG19,"0.00")&" stays within the $"&TEXT(BB19,"0.00")&" max ranking CPC"&" (= $"&TEXT(AY19,"0.00")&" price × "&TEXT(AZ19,"0.0%")&" ranking ceiling × "&TEXT(AD19,"0.0%")&" CVR)"&". +100% would cost $"&TEXT(BC19*2,"0.00")&" per click and push ACoS to "&TEXT(BC19*2/(AY19*AD19),"0.0%")&", above the "&TEXT(AZ19,"0.0%")&" ceiling.","NO — 0%. Base bid $"&TEXT(BC19,"0.00")&" already equals the $"&TEXT(BB19,"0.00")&" max ranking CPC"&" (= $"&TEXT(AY19,"0.00")&" price × "&TEXT(AZ19,"0.0%")&" ranking ceiling × "&TEXT(AD19,"0.0%")&" CVR)"&"; any modifier would push ACoS above the "&TEXT(AZ19,"0.0%")&" ceiling."))),IF(OR(AO19="Ranking — Head Term (Capped)",AO19="Ranking — Capped Entry",AO19="Ranking — Capped Long-Tail"),"NO — 0% (capped ranking entry). Bid $"&TEXT(BC19,"0.00")&" vs $"&TEXT(BB19,"0.00")&" max ranking CPC"&" (= $"&TEXT(AY19,"0.00")&" price × "&TEXT(AZ19,"0.0%")&" ranking ceiling × "&TEXT(AD19,"0.0%")&" CVR)"&". While spend is capped at "&TEXT(AS19,"0.00")&" clicks/day, a placement premium would only raise CPC without buying more rank; the modifier is set when this term moves to a full push.","NO — 0% (support / brand term). Bid $"&TEXT(BC19,"0.00")&" vs $"&TEXT(BB19,"0.00")&" max ranking CPC"&" (= $"&TEXT(AY19,"0.00")&" price × "&TEXT(AZ19,"0.0%")&" ranking ceiling × "&TEXT(AD19,"0.0%")&" CVR)"&"; expected ACoS "&TEXT(BI19,"0.0%")&" vs the "&TEXT(AZ19,"0.0%")&" ceiling.")) -> NO — 0% (capped ranking entry). Bid $2.35 vs $3.52 max ranking CPC (= $79.99 price × 55.9% ranking ceiling × 7.9% CVR). While spend is capped at 1.00 clicks/day, a placement premium would only raise CPC without buying more rank; the modifier is set when this term moves to a full push. | BG19: =BC19*(1+BE19) -> 2.35 | BH19: =AS19*BG19 -> 2.35 | BI19: =IFERROR(BG19/(AY19*AD19),"") -> 0.37329952 | BJ19: =IF(BI19="","",IF(BI19<=BA19,"Profitable (≤ break-even)",IF(BI19<=AZ19,"Ranking investment (≤ ceiling)","Above ceiling — reduce bid"))) -> Ranking investment (≤ ceiling) | BK19: ="Base $"&TEXT(BC19,"0.00")&" × (1 + "&TEXT(BE19,"0%")&" TOS) = $"&TEXT(BG19,"0.00")&" effective CPC [max $"&TEXT(BB19,"0.00")&"]. "&TEXT(AG19,"0.0")&" market clicks/day × "&TEXT(AH19,"0.00%")&" click share × "&TEXT(AI19,"0%")&" paid = "&TEXT(AJ19,"0.00")&" clicks/day needed; "&"planned "&TEXT(AS19,"0.00")&" clicks/day × "&TEXT(AD19,"0.0%")&" CVR = "&TEXT(AU19,"0.00")&" orders/day. "&"Spend $"&TEXT(BH19,"0.00")&"/day, ACoS "&TEXT(BI19,"0.0%")&" (ceiling "&TEXT(AZ19,"0.0%")&", break-even "&TEXT(BA19,"0.0%")&"). "&"Target organic rank #"&S19&" by week 8 ("&T19&")." -> Base $2.35 × (1 + 0% TOS) = $2.35 effective CPC [max $3.52]. 22.3 market clicks/day × 1.24% click share × 66% paid = 0.18 clicks/day needed; planned 1.00 clicks/day × 7.9% CVR = 0.08 orders/day. Spend $2.35/day, ACoS 37.3% (ceiling 55.9%, break-even 37.2%). Target organic rank #20 by week 8 (#60 → #35 → #20). | BL19: cooling sheet set|no size | BM19: Hero (single-keyword campaign) | BN19: CLCS4-SP-cooling sheet set-HSV-Exact-Disc-Fix-Q-GRAPHITE | BO19: cooling sheet set | BP19: CL-COOLING-SHEET-QUEEN-GRAPHITE | BQ19: B0H6K1MKQW | BR19: =IFERROR(INDEX(Campaigns!$L:$L,MATCH(BN19,Campaigns!$A:$A,0)),"") -> 10 | BS19: =IFERROR(INDEX(Inventory!$O:$O,MATCH(BP19,Inventory!$A:$A,0)),"") -> OK | BT19: =IFERROR(INDEX(Inventory!$N:$N,MATCH(BP19,Inventory!$A:$A,0)),"") -> 91.53226 | BU19: "cooling sheet set" asks for cooling sheet product that CooLinens sells (BreezeWeave nylon/spandex knit, 16″ pocket, 4-piece set). Relevance 95%: product type ✓, use case ✓, material ✓, intent ✓. | BV19: Decolure ($38 microfiber — adjacent, lower weight): no search-term history. | BW19: Sleephoria (same product and price — strongest evidence): proven on the same product (61 clicks, CVR 9.8%, ACoS 30%); organic best #4 (2025-11-07), first top-10 2025-10-28, now #38. | BX19: SV 1,669/mo (MKL (DataDive)); launch window ≈ 1,546/mo; SQP 12-mo 29,717 searches, peak 2026-07, Oct at 0.76× its avg; Mar-24→Mar-26 ×1.09; market CVR 1.4% (head term 1.5%). | BY19: Organic top 20: Bedsure PW #1, Love's cabin #5, Breescape #10, Pure Bamboo #11. Advertising: California Design Den SP#2, REST SP#3, KARISSA MAE SP#4, Bambaw SP#6. Rival ad share 49%. | BZ19: Direct cooling-tech rivals rank here (Breescape), priced $89.99–$224 vs CooLinens $79.99; bamboo sets hold the rest. Price and fabric are the wedge. | CA19: Launch-window demand is ~35% of the June peak but these are the terms where evidence is strongest; ranking now means CooLinens holds position before the March ramp (SQP March ≈ 2× January). Head term — ranked by Queen size-term velocity (Sleephoria precedent); funded only as a capped probe. | CB19: Batch 1 Hero: relevance 95% ≥ 90%, clean wording, launch-window demand 1,546 searches/mo > 300 (own campaign), and evidence score 7.5/12 ≥ 6.0 (Sleephoria PPC +4 · Sleephoria rank +2 · market CVR +0.5 · competitors +1 · Decolure +0). Sleephoria did not overpay on it beyond the ranking ceiling. | CC19: ≤20 by week 8, earned from Queen/size-term velocity rather than direct bids (Sleephoria held #3–5 on "cooling sheets" with < $0.10/day on that exact term; bidding it directly ran 117% ACoS).
A20: california king cooling sheets | B20: 1 | C20: 15 Oct 2026 | D20: Cal King | E20: LAUNCH 15 Oct — capped ranking entry | F20: 1 | G20: Type ✓ · Use ✓ · Material ✓ · Intent ✓ | H20: High | I20: 8.5 | J20: Sleephoria PPC +4 · Sleephoria rank +2 · market CVR +2 · competitors +0.5 · Decolure +0 | K20: 924 | L20: 815 | M20: =L20/30 -> 27.166667 | N20: 0.041045911 | O20: now #18 | P20: best #1 (2026-08-08) · PPC-period median #6 · now #3 | Q20: #11 Pillcase | R20: 2 | S20: 10 | T20: #40 → #20 → #10 (full push after size assignment) | U20: Pillcase #11, BC Bella Coterie #19; Ads: California Design Den SP#1, KARISSA MAE SP#5, Bambaw SP#7, Bedsure PW Cooling SP#8 | V20: =IFERROR(INDEX(Sleephoria_History!$F$454:$F$2115,MATCH($A20,Sleephoria_History!$A$454:$A$2115,0)),"") -> 324 | W20: =IFERROR(INDEX(Sleephoria_History!$J$454:$J$2115,MATCH($A20,Sleephoria_History!$A$454:$A$2115,0)),"") -> 0.1667 | X20: =IFERROR(INDEX(Sleephoria_History!$H$454:$H$2115,MATCH($A20,Sleephoria_History!$A$454:$A$2115,0)),"") -> 3.69 | Y20: =IFERROR(INDEX(Sleephoria_History!$M$454:$M$2115,MATCH($A20,Sleephoria_History!$A$454:$A$2115,0)),"") -> 0.304 | Z20: =IFERROR(INDEX(Sleephoria_History!$L$454:$L$2115,MATCH($A20,Sleephoria_History!$A$454:$A$2115,0)),"") -> 3934.45 | AA20: =IFERROR(INDEX(Decolure_History!$F$397:$F$709,MATCH($A20,Decolure_History!$A$397:$A$709,0)),"") | AB20: =IFERROR(INDEX(Decolure_History!$J$397:$J$709,MATCH($A20,Decolure_History!$A$397:$A$709,0)),"") | AC20: =IFERROR(INDEX(Decolure_History!$M$397:$M$709,MATCH($A20,Decolure_History!$A$397:$A$709,0)),"") | AD20: 0.1334 | AE20: Sleephoria term CVR 16.7% on 324 clicks ×0.8 launch | AF20: 0.502 | AG20: =M20*AF20 -> 13.637667 | AH20: =IF(AO20="Brand Defense",0,IFERROR(VLOOKUP(S20,Assumptions!$A$24:$B$28,2,FALSE()),0)) -> 0.028 | AI20: =Assumptions!$B$6 -> 0.66 | AJ20: =AG20*AH20*AI20 -> 0.25202408 | AK20: =AJ20*AD20 -> 0.033620012 | AL20: =AJ20*56 -> 14.113348 | AM20: =AK20*56 -> 1.8827207 | AN20: =M20*Assumptions!$B$8 -> 2.7166667 | AO20: Ranking — Capped Entry | AP20: Ranking entry, capped: Cal King is also Sleephoria's size on the same keywords, so CooLinens enters funded to what the target rank needs (minimum 1 click/day for a CVR read) but never above 3.57 clicks/day (50 clicks in 14 days), with no placement premium. It moves to a full push, with the TOS modifier, once Cal King is assigned to CooLinens. | AQ20: Exact | AR20: Exact: organic rank is earned per exact query, so sales must land on this wording; one keyword per campaign gives full control of bid, TOS modifier and budget, and clean attribution. Phrase / broad / auto open from week 4 for harvesting only. | AS20: =IF(AO20="Ranking — Full Push",MIN(MAX(AJ20,Assumptions!$B$9),AN20),IF(AO20="Brand Defense",MIN(Assumptions!$B$7,AN20),IF(OR(AO20="Ranking — Head Term (Capped)",AO20="Ranking — Capped Entry"),MIN(MAX(AJ20,Assumptions!$B$9),Assumptions!$B$7,AN20),IF(AO20="Ranking — Capped Long-Tail",MIN(AJ20,Assumptions!$B$10,AN20),MIN(AJ20,AN20))))) -> 1 | AT20: =IF(AJ20<=0,"",IF(AS20>=AJ20,IF(AS20>AJ20*1.05,"Floor of "&TEXT(AS20,"0.0")&" click/day to read CVR (rank needs "&TEXT(AJ20,"0.00")&")","Fully funded (100%)"),"Capped at "&TEXT(AS20/AJ20,"0%")&" of required")) -> Floor of 1.0 click/day to read CVR (rank needs 0.25) | AU20: =AS20*AD20 -> 0.1334 | AV20: =AU20*AY20 -> 11.604466 | AW20: 3.69 | AX20: Sleephoria CPC on this exact term (324 clicks) | AY20: =INDEX(Assumptions!$B$33:$B$37,MATCH(IF($D20="","Queen",$D20),Assumptions!$A$33:$A$37,0)) -> 86.99 | AZ20: =INDEX(Assumptions!$K$33:$K$37,MATCH(IF($D20="","Queen",$D20),Assumptions!$A$33:$A$37,0)) -> 0.53129383 | BA20: =INDEX(Assumptions!$H$33:$H$37,MATCH(IF($D20="","Queen",$D20),Assumptions!$A$33:$A$37,0)) -> 0.35419588 | BB20: =AY20*AZ20*AD20 -> 6.1653811 | BC20: =ROUND(MIN(AW20*Assumptions!$B$11,BB20),2) -> 3.69 | BD20: Yes | BE20: =IF(AO20="Ranking — Full Push",MAX(0,MIN(IF(BD20="Yes",Assumptions!$B$12,Assumptions!$B$13),FLOOR(MAX(0,BB20/BC20-1),Assumptions!$B$14))),0) -> 0 | BF20: =IF(AO20="Ranking — Full Push",IF(BE20>=1,"YES — +100% Top of Search. Effective CPC $"&TEXT(BG20,"0.00")&" (= $"&TEXT(BC20,"0.00")&" × 2) stays within the $"&TEXT(BB20,"0.00")&" max ranking CPC"&" (= $"&TEXT(AY20,"0.00")&" price × "&TEXT(AZ20,"0.0%")&" ranking ceiling × "&TEXT(AD20,"0.0%")&" CVR)"&". Sleephoria CVR is proven on this term, so the full push is justified.",IF(AND(BD20="No",BE20>=Assumptions!$B$13),"PARTIAL — +"&TEXT(BE20,"0%")&" Top of Search (limit for terms without proven CVR). Effective CPC $"&TEXT(BG20,"0.00")&" vs $"&TEXT(BB20,"0.00")&" max ranking CPC"&" (= $"&TEXT(AY20,"0.00")&" price × "&TEXT(AZ20,"0.0%")&" ranking ceiling × "&TEXT(AD20,"0.0%")&" CVR)"&". Raise to +100% only after CooLinens converts at ≥ "&TEXT(AD20,"0.0%")&" on 50+ clicks and $"&TEXT(BC20*2,"0.00")&" ≤ the max.",IF(BE20>0,"PARTIAL — +"&TEXT(BE20,"0%")&" Top of Search. Effective CPC $"&TEXT(BG20,"0.00")&" stays within the $"&TEXT(BB20,"0.00")&" max ranking CPC"&" (= $"&TEXT(AY20,"0.00")&" price × "&TEXT(AZ20,"0.0%")&" ranking ceiling × "&TEXT(AD20,"0.0%")&" CVR)"&". +100% would cost $"&TEXT(BC20*2,"0.00")&" per click and push ACoS to "&TEXT(BC20*2/(AY20*AD20),"0.0%")&", above the "&TEXT(AZ20,"0.0%")&" ceiling.","NO — 0%. Base bid $"&TEXT(BC20,"0.00")&" already equals the $"&TEXT(BB20,"0.00")&" max ranking CPC"&" (= $"&TEXT(AY20,"0.00")&" price × "&TEXT(AZ20,"0.0%")&" ranking ceiling × "&TEXT(AD20,"0.0%")&" CVR)"&"; any modifier would push ACoS above the "&TEXT(AZ20,"0.0%")&" ceiling."))),IF(OR(AO20="Ranking — Head Term (Capped)",AO20="Ranking — Capped Entry",AO20="Ranking — Capped Long-Tail"),"NO — 0% (capped ranking entry). Bid $"&TEXT(BC20,"0.00")&" vs $"&TEXT(BB20,"0.00")&" max ranking CPC"&" (= $"&TEXT(AY20,"0.00")&" price × "&TEXT(AZ20,"0.0%")&" ranking ceiling × "&TEXT(AD20,"0.0%")&" CVR)"&". While spend is capped at "&TEXT(AS20,"0.00")&" clicks/day, a placement premium would only raise CPC without buying more rank; the modifier is set when this term moves to a full push.","NO — 0% (support / brand term). Bid $"&TEXT(BC20,"0.00")&" vs $"&TEXT(BB20,"0.00")&" max ranking CPC"&" (= $"&TEXT(AY20,"0.00")&" price × "&TEXT(AZ20,"0.0%")&" ranking ceiling × "&TEXT(AD20,"0.0%")&" CVR)"&"; expected ACoS "&TEXT(BI20,"0.0%")&" vs the "&TEXT(AZ20,"0.0%")&" ceiling.")) -> NO — 0% (capped ranking entry). Bid $3.69 vs $6.17 max ranking CPC (= $86.99 price × 53.1% ranking ceiling × 13.3% CVR). While spend is capped at 1.00 clicks/day, a placement premium would only raise CPC without buying more rank; the modifier is set when this term moves to a full push. | BG20: =BC20*(1+BE20) -> 3.69 | BH20: =AS20*BG20 -> 3.69 | BI20: =IFERROR(BG20/(AY20*AD20),"") -> 0.31798103 | BJ20: =IF(BI20="","",IF(BI20<=BA20,"Profitable (≤ break-even)",IF(BI20<=AZ20,"Ranking investment (≤ ceiling)","Above ceiling — reduce bid"))) -> Profitable (≤ break-even) | BK20: ="Base $"&TEXT(BC20,"0.00")&" × (1 + "&TEXT(BE20,"0%")&" TOS) = $"&TEXT(BG20,"0.00")&" effective CPC [max $"&TEXT(BB20,"0.00")&"]. "&TEXT(AG20,"0.0")&" market clicks/day × "&TEXT(AH20,"0.00%")&" click share × "&TEXT(AI20,"0%")&" paid = "&TEXT(AJ20,"0.00")&" clicks/day needed; "&"planned "&TEXT(AS20,"0.00")&" clicks/day × "&TEXT(AD20,"0.0%")&" CVR = "&TEXT(AU20,"0.00")&" orders/day. "&"Spend $"&TEXT(BH20,"0.00")&"/day, ACoS "&TEXT(BI20,"0.0%")&" (ceiling "&TEXT(AZ20,"0.0%")&", break-even "&TEXT(BA20,"0.0%")&"). "&"Target organic rank #"&S20&" by week 8 ("&T20&")." -> Base $3.69 × (1 + 0% TOS) = $3.69 effective CPC [max $6.17]. 13.6 market clicks/day × 2.80% click share × 66% paid = 0.25 clicks/day needed; planned 1.00 clicks/day × 13.3% CVR = 0.13 orders/day. Spend $3.69/day, ACoS 31.8% (ceiling 53.1%, break-even 35.4%). Target organic rank #10 by week 8 (#40 → #20 → #10 (full push after size assignment)). | BL20: cooling sheets|Cal King | BM20: Hero (single-keyword campaign) | BN20: CLCS4-SP-california king cooling sheets-MSV-Exact-Disc-Fix-CK-GRAPHITE | BO20: california king cooling sheets | BP20: CL-COOLING-SHEET-CAL-KING-GRAPHITE | BQ20: B0H6JV73R5 | BR20: =IFERROR(INDEX(Campaigns!$L:$L,MATCH(BN20,Campaigns!$A:$A,0)),"") -> 10 | BS20: =IFERROR(INDEX(Inventory!$O:$O,MATCH(BP20,Inventory!$A:$A,0)),"") -> OK | BT20: =IFERROR(INDEX(Inventory!$N:$N,MATCH(BP20,Inventory!$A:$A,0)),"") -> 77.969814 | BU20: "california king cooling sheets" asks for a Cal King cooling sheet product that CooLinens sells (BreezeWeave nylon/spandex knit, 16″ pocket, 4-piece set). Relevance 100%: product type ✓, use case ✓, material ✓, intent ✓. | BV20: Decolure ($38 microfiber — adjacent, lower weight): no search-term history. | BW20: Sleephoria (same product and price — strongest evidence): proven on the same product (324 clicks, CVR 16.7%, ACoS 30%); organic best #1 (2026-08-08), first top-10 2025-10-09, now #3. Reached top 10 6 days after ads started (Oct-25). | BX20: SV 924/mo (MKL (DataDive)); launch window ≈ 815/mo; SQP 12-mo 14,212 searches, peak 2026-06, Oct at 0.67× its avg; market CVR 4.1% (head term 1.5%). | BY20: Organic top 20: Pillcase #11, BC Bella Coterie #19. Advertising: California Design Den SP#1, KARISSA MAE SP#5, Bambaw SP#7, Bedsure PW Cooling SP#8. Rival ad share 47%. | BZ20: Top-20 is held by bamboo/viscose sets (Pillcase, BC Bella Coterie); no synthetic cooling-knit rival ranks here. CooLinens is the only nylon/spandex cooling option on the page at $86.99 — Sleephoria proved the knit ranks here. | CA20: Launch-window demand is ~35% of the June peak but these are the terms where evidence is strongest; ranking now means CooLinens holds position before the March ramp (SQP March ≈ 2× January). Cal King roots are shared with Sleephoria and not yet assigned: launch capped (50 clicks / 14 days) to read CooLinens CVR for the ownership decision. | CB20: Batch 1 Hero: relevance 100% ≥ 90%, clean wording, launch-window demand 815 searches/mo > 300 (own campaign), and evidence score 8.5/12 ≥ 6.0 (Sleephoria PPC +4 · Sleephoria rank +2 · market CVR +2 · competitors +0.5 · Decolure +0). Sleephoria did not overpay on it beyond the ranking ceiling. | CC20: ≤10 (≤40 by wk 2, ≤20 by wk 4, ≤10 by wk 8): Sleephoria, the same product, reached #1 here and entered the top 10 within 6 days; 2 tracked rival(s) in the top 20. Full rank push starts once this size is assigned to CooLinens; until then spend is capped and the campaign builds first sales and a CVR read.
A21: cal king cooling sheets | B21: 1 | C21: 15 Oct 2026 | D21: Cal King | E21: LAUNCH 15 Oct — capped ranking entry | F21: 1 | G21: Type ✓ · Use ✓ · Material ✓ · Intent ✓ | H21: High | I21: 9 | J21: Sleephoria PPC +4 · Sleephoria rank +2 · market CVR +1.5 · competitors +1 · Decolure +0.5 | K21: 672 | L21: 496 | M21: =L21/30 -> 16.533333 | N21: 0.03451022 | O21: best #10 (2026-09-24) · median #43 · now #11 | P21: best #1 (2026-10-02) · PPC-period median #10 · now #3 | Q21: #5 California Design Den | R21: 7 | S21: 15 | T21: #50 → #30 → #15 (full push after size assignment) | U21: California Design Den #5, Pure Bamboo #6, Breescape #9, Bedsure PW Cooling #11, Love's cabin #13; Ads: Hotel Sheets Direct SP#3, Pure Bamboo SP#4, Breescape SP#8, KARISSA MAE SP#8 | V21: =IFERROR(INDEX(Sleephoria_History!$F$454:$F$2115,MATCH($A21,Sleephoria_History!$A$454:$A$2115,0)),"") -> 227 | W21: =IFERROR(INDEX(Sleephoria_History!$J$454:$J$2115,MATCH($A21,Sleephoria_History!$A$454:$A$2115,0)),"") -> 0.1718 | X21: =IFERROR(INDEX(Sleephoria_History!$H$454:$H$2115,MATCH($A21,Sleephoria_History!$A$454:$A$2115,0)),"") -> 3.71 | Y21: =IFERROR(INDEX(Sleephoria_History!$M$454:$M$2115,MATCH($A21,Sleephoria_History!$A$454:$A$2115,0)),"") -> 0.297 | Z21: =IFERROR(INDEX(Sleephoria_History!$L$454:$L$2115,MATCH($A21,Sleephoria_History!$A$454:$A$2115,0)),"") -> 2831.6 | AA21: =IFERROR(INDEX(Decolure_History!$F$397:$F$709,MATCH($A21,Decolure_History!$A$397:$A$709,0)),"") -> 48 | AB21: =IFERROR(INDEX(Decolure_History!$J$397:$J$709,MATCH($A21,Decolure_History!$A$397:$A$709,0)),"") -> 0.0417 | AC21: =IFERROR(INDEX(Decolure_History!$M$397:$M$709,MATCH($A21,Decolure_History!$A$397:$A$709,0)),"") -> 1.061 | AD21: 0.1374 | AE21: Sleephoria term CVR 17.2% on 227 clicks ×0.8 launch | AF21: 0.507 | AG21: =M21*AF21 -> 8.3824 | AH21: =IF(AO21="Brand Defense",0,IFERROR(VLOOKUP(S21,Assumptions!$A$24:$B$28,2,FALSE()),0)) -> 0.0149 | AI21: =Assumptions!$B$6 -> 0.66 | AJ21: =AG21*AH21*AI21 -> 0.082432522 | AK21: =AJ21*AD21 -> 0.011326228 | AL21: =AJ21*56 -> 4.6162212 | AM21: =AK21*56 -> 0.63426879 | AN21: =M21*Assumptions!$B$8 -> 1.6533333 | AO21: Ranking — Capped Entry | AP21: Ranking entry, capped: Cal King is also Sleephoria's size on the same keywords, so CooLinens enters funded to what the target rank needs (minimum 1 click/day for a CVR read) but never above 3.57 clicks/day (50 clicks in 14 days), with no placement premium. It moves to a full push, with the TOS modifier, once Cal King is assigned to CooLinens. | AQ21: Exact | AR21: Exact: organic rank is earned per exact query, so sales must land on this wording; one keyword per campaign gives full control of bid, TOS modifier and budget, and clean attribution. Phrase / broad / auto open from week 4 for harvesting only. | AS21: =IF(AO21="Ranking — Full Push",MIN(MAX(AJ21,Assumptions!$B$9),AN21),IF(AO21="Brand Defense",MIN(Assumptions!$B$7,AN21),IF(OR(AO21="Ranking — Head Term (Capped)",AO21="Ranking — Capped Entry"),MIN(MAX(AJ21,Assumptions!$B$9),Assumptions!$B$7,AN21),IF(AO21="Ranking — Capped Long-Tail",MIN(AJ21,Assumptions!$B$10,AN21),MIN(AJ21,AN21))))) -> 1 | AT21: =IF(AJ21<=0,"",IF(AS21>=AJ21,IF(AS21>AJ21*1.05,"Floor of "&TEXT(AS21,"0.0")&" click/day to read CVR (rank needs "&TEXT(AJ21,"0.00")&")","Fully funded (100%)"),"Capped at "&TEXT(AS21/AJ21,"0%")&" of required")) -> Floor of 1.0 click/day to read CVR (rank needs 0.08) | AU21: =AS21*AD21 -> 0.1374 | AV21: =AU21*AY21 -> 11.952426 | AW21: 3.71 | AX21: Sleephoria CPC on this exact term (227 clicks) | AY21: =INDEX(Assumptions!$B$33:$B$37,MATCH(IF($D21="","Queen",$D21),Assumptions!$A$33:$A$37,0)) -> 86.99 | AZ21: =INDEX(Assumptions!$K$33:$K$37,MATCH(IF($D21="","Queen",$D21),Assumptions!$A$33:$A$37,0)) -> 0.53129383 | BA21: =INDEX(Assumptions!$H$33:$H$37,MATCH(IF($D21="","Queen",$D21),Assumptions!$A$33:$A$37,0)) -> 0.35419588 | BB21: =AY21*AZ21*AD21 -> 6.3502501 | BC21: =ROUND(MIN(AW21*Assumptions!$B$11,BB21),2) -> 3.71 | BD21: Yes | BE21: =IF(AO21="Ranking — Full Push",MAX(0,MIN(IF(BD21="Yes",Assumptions!$B$12,Assumptions!$B$13),FLOOR(MAX(0,BB21/BC21-1),Assumptions!$B$14))),0) -> 0 | BF21: =IF(AO21="Ranking — Full Push",IF(BE21>=1,"YES — +100% Top of Search. Effective CPC $"&TEXT(BG21,"0.00")&" (= $"&TEXT(BC21,"0.00")&" × 2) stays within the $"&TEXT(BB21,"0.00")&" max ranking CPC"&" (= $"&TEXT(AY21,"0.00")&" price × "&TEXT(AZ21,"0.0%")&" ranking ceiling × "&TEXT(AD21,"0.0%")&" CVR)"&". Sleephoria CVR is proven on this term, so the full push is justified.",IF(AND(BD21="No",BE21>=Assumptions!$B$13),"PARTIAL — +"&TEXT(BE21,"0%")&" Top of Search (limit for terms without proven CVR). Effective CPC $"&TEXT(BG21,"0.00")&" vs $"&TEXT(BB21,"0.00")&" max ranking CPC"&" (= $"&TEXT(AY21,"0.00")&" price × "&TEXT(AZ21,"0.0%")&" ranking ceiling × "&TEXT(AD21,"0.0%")&" CVR)"&". Raise to +100% only after CooLinens converts at ≥ "&TEXT(AD21,"0.0%")&" on 50+ clicks and $"&TEXT(BC21*2,"0.00")&" ≤ the max.",IF(BE21>0,"PARTIAL — +"&TEXT(BE21,"0%")&" Top of Search. Effective CPC $"&TEXT(BG21,"0.00")&" stays within the $"&TEXT(BB21,"0.00")&" max ranking CPC"&" (= $"&TEXT(AY21,"0.00")&" price × "&TEXT(AZ21,"0.0%")&" ranking ceiling × "&TEXT(AD21,"0.0%")&" CVR)"&". +100% would cost $"&TEXT(BC21*2,"0.00")&" per click and push ACoS to "&TEXT(BC21*2/(AY21*AD21),"0.0%")&", above the "&TEXT(AZ21,"0.0%")&" ceiling.","NO — 0%. Base bid $"&TEXT(BC21,"0.00")&" already equals the $"&TEXT(BB21,"0.00")&" max ranking CPC"&" (= $"&TEXT(AY21,"0.00")&" price × "&TEXT(AZ21,"0.0%")&" ranking ceiling × "&TEXT(AD21,"0.0%")&" CVR)"&"; any modifier would push ACoS above the "&TEXT(AZ21,"0.0%")&" ceiling."))),IF(OR(AO21="Ranking — Head Term (Capped)",AO21="Ranking — Capped Entry",AO21="Ranking — Capped Long-Tail"),"NO — 0% (capped ranking entry). Bid $"&TEXT(BC21,"0.00")&" vs $"&TEXT(BB21,"0.00")&" max ranking CPC"&" (= $"&TEXT(AY21,"0.00")&" price × "&TEXT(AZ21,"0.0%")&" ranking ceiling × "&TEXT(AD21,"0.0%")&" CVR)"&". While spend is capped at "&TEXT(AS21,"0.00")&" clicks/day, a placement premium would only raise CPC without buying more rank; the modifier is set when this term moves to a full push.","NO — 0% (support / brand term). Bid $"&TEXT(BC21,"0.00")&" vs $"&TEXT(BB21,"0.00")&" max ranking CPC"&" (= $"&TEXT(AY21,"0.00")&" price × "&TEXT(AZ21,"0.0%")&" ranking ceiling × "&TEXT(AD21,"0.0%")&" CVR)"&"; expected ACoS "&TEXT(BI21,"0.0%")&" vs the "&TEXT(AZ21,"0.0%")&" ceiling.")) -> NO — 0% (capped ranking entry). Bid $3.71 vs $6.35 max ranking CPC (= $86.99 price × 53.1% ranking ceiling × 13.7% CVR). While spend is capped at 1.00 clicks/day, a placement premium would only raise CPC without buying more rank; the modifier is set when this term moves to a full push. | BG21: =BC21*(1+BE21) -> 3.71 | BH21: =AS21*BG21 -> 3.71 | BI21: =IFERROR(BG21/(AY21*AD21),"") -> 0.31039724 | BJ21: =IF(BI21="","",IF(BI21<=BA21,"Profitable (≤ break-even)",IF(BI21<=AZ21,"Ranking investment (≤ ceiling)","Above ceiling — reduce bid"))) -> Profitable (≤ break-even) | BK21: ="Base $"&TEXT(BC21,"0.00")&" × (1 + "&TEXT(BE21,"0%")&" TOS) = $"&TEXT(BG21,"0.00")&" effective CPC [max $"&TEXT(BB21,"0.00")&"]. "&TEXT(AG21,"0.0")&" market clicks/day × "&TEXT(AH21,"0.00%")&" click share × "&TEXT(AI21,"0%")&" paid = "&TEXT(AJ21,"0.00")&" clicks/day needed; "&"planned "&TEXT(AS21,"0.00")&" clicks/day × "&TEXT(AD21,"0.0%")&" CVR = "&TEXT(AU21,"0.00")&" orders/day. "&"Spend $"&TEXT(BH21,"0.00")&"/day, ACoS "&TEXT(BI21,"0.0%")&" (ceiling "&TEXT(AZ21,"0.0%")&", break-even "&TEXT(BA21,"0.0%")&"). "&"Target organic rank #"&S21&" by week 8 ("&T21&")." -> Base $3.71 × (1 + 0% TOS) = $3.71 effective CPC [max $6.35]. 8.4 market clicks/day × 1.49% click share × 66% paid = 0.08 clicks/day needed; planned 1.00 clicks/day × 13.7% CVR = 0.14 orders/day. Spend $3.71/day, ACoS 31.0% (ceiling 53.1%, break-even 35.4%). Target organic rank #15 by week 8 (#50 → #30 → #15 (full push after size assignment)). | BL21: cooling sheets|Cal King | BM21: Hero (single-keyword campaign) | BN21: CLCS4-SP-cal king cooling sheets-LSV-Exact-Disc-Fix-CK-GRAPHITE | BO21: cal king cooling sheets | BP21: CL-COOLING-SHEET-CAL-KING-GRAPHITE | BQ21: B0H6JV73R5 | BR21: =IFERROR(INDEX(Campaigns!$L:$L,MATCH(BN21,Campaigns!$A:$A,0)),"") -> 10 | BS21: =IFERROR(INDEX(Inventory!$O:$O,MATCH(BP21,Inventory!$A:$A,0)),"") -> OK | BT21: =IFERROR(INDEX(Inventory!$N:$N,MATCH(BP21,Inventory!$A:$A,0)),"") -> 77.969814 | BU21: "cal king cooling sheets" asks for a Cal King cooling sheet product that CooLinens sells (BreezeWeave nylon/spandex knit, 16″ pocket, 4-piece set). Relevance 100%: product type ✓, use case ✓, material ✓, intent ✓. | BV21: Decolure ($38 microfiber — adjacent, lower weight): small sample (48 clicks); organic best #10 (2026-09-24), 1 days in top 10, median #43. | BW21: Sleephoria (same product and price — strongest evidence): proven on the same product (227 clicks, CVR 17.2%, ACoS 30%); organic best #1 (2026-10-02), first top-10 2025-10-23, now #3. Reached top 10 20 days after ads started (Oct-25). | BX21: SV 672/mo (MKL (DataDive)); launch window ≈ 496/mo; SQP 12-mo 8,460 searches, peak 2026-07, Oct at 0.50× its avg; market CVR 3.5% (head term 1.5%). | BY21: Organic top 20: California Design Den #5, Pure Bamboo #6, Breescape #9, Bedsure PW Cooling #11. Advertising: Hotel Sheets Direct SP#3, Pure Bamboo SP#4, Breescape SP#8, KARISSA MAE SP#8. Rival ad share 62%. | BZ21: Direct cooling-tech rivals rank here (Breescape, REST), priced $89.99–$224 vs CooLinens $86.99; bamboo sets hold the rest. Price and fabric are the wedge. | CA21: Launch-window demand is ~35% of the June peak but these are the terms where evidence is strongest; ranking now means CooLinens holds position before the March ramp (SQP March ≈ 2× January). Cal King roots are shared with Sleephoria and not yet assigned: launch capped (50 clicks / 14 days) to read CooLinens CVR for the ownership decision. | CB21: Batch 1 Hero: relevance 100% ≥ 90%, clean wording, launch-window demand 496 searches/mo > 300 (own campaign), and evidence score 9.0/12 ≥ 6.0 (Sleephoria PPC +4 · Sleephoria rank +2 · market CVR +1.5 · competitors +1 · Decolure +0.5). Sleephoria did not overpay on it beyond the ranking ceiling. | CC21: ≤15 (≤50 by wk 2, ≤30 by wk 4, ≤15 by wk 8): a crowded page (7 tracked rivals in the organic top 20). Sleephoria's best was #1 (2026-10-02), but its launch ran into Prime Big Deal Days (7–8 Oct 2025). CooLinens launches with 24 Vine ratings and no deal tailwind in a 35%-of-peak window, so top 15 is the evidence-supported goal. Full rank push starts once this size is assigned to CooLinens; until then spend is capped and the campaign builds first sales and a CVR read.
A22: cooling california king sheets | B22: 1 | C22: 15 Oct 2026 | D22: Cal King | E22: LAUNCH 15 Oct — capped ranking entry | F22: 1 | G22: Type ✓ · Use ✓ · Material ✓ · Intent ✓ | H22: Medium | I22: 6 | J22: Sleephoria PPC +0 · root|size group proven on Sleephoria +1.5 (cooling sheets|Cal King: CVR 15.7% on 706 clicks) · Sleephoria rank +2 · market CVR +1.5 · competitors +1 · Decolure +0 | K22: 639 | L22: 457 | M22: =L22/30 -> 15.233333 | N22: 0.034095634 | O22: now #54 | P22: best #1 (2026-08-10) · PPC-period median #10 · now #10 | Q22: #3 Bedsure PW | R22: 5 | S22: 20 | T22: #60 → #35 → #20 (full push after size assignment) | U22: Bedsure PW #3, Pure Bamboo #5, Pillcase #9, Love's cabin #12, BC Bella Coterie #19; Ads: Breescape SP#6, Bedsure PW Cooling SP#9, TRUE BAMBOO SP#9, Bambaw SP#11 | V22: =IFERROR(INDEX(Sleephoria_History!$F$454:$F$2115,MATCH($A22,Sleephoria_History!$A$454:$A$2115,0)),"") -> 13 | W22: =IFERROR(INDEX(Sleephoria_History!$J$454:$J$2115,MATCH($A22,Sleephoria_History!$A$454:$A$2115,0)),"") -> 0 | X22: =IFERROR(INDEX(Sleephoria_History!$H$454:$H$2115,MATCH($A22,Sleephoria_History!$A$454:$A$2115,0)),"") -> 2.05 | Y22: =IFERROR(INDEX(Sleephoria_History!$M$454:$M$2115,MATCH($A22,Sleephoria_History!$A$454:$A$2115,0)),"") -> 0 | Z22: =IFERROR(INDEX(Sleephoria_History!$L$454:$L$2115,MATCH($A22,Sleephoria_History!$A$454:$A$2115,0)),"") -> 0 | AA22: =IFERROR(INDEX(Decolure_History!$F$397:$F$709,MATCH($A22,Decolure_History!$A$397:$A$709,0)),"") | AB22: =IFERROR(INDEX(Decolure_History!$J$397:$J$709,MATCH($A22,Decolure_History!$A$397:$A$709,0)),"") | AC22: =IFERROR(INDEX(Decolure_History!$M$397:$M$709,MATCH($A22,Decolure_History!$A$397:$A$709,0)),"") | AD22: 0.064 | AE22: bucket default (no history) ×0.8 launch | AF22: 0.515 | AG22: =M22*AF22 -> 7.8451667 | AH22: =IF(AO22="Brand Defense",0,IFERROR(VLOOKUP(S22,Assumptions!$A$24:$B$28,2,FALSE()),0)) -> 0.0124 | AI22: =Assumptions!$B$6 -> 0.66 | AJ22: =AG22*AH22*AI22 -> 0.064204844 | AK22: =AJ22*AD22 -> 0.00410911 | AL22: =AJ22*56 -> 3.5954713 | AM22: =AK22*56 -> 0.23011016 | AN22: =M22*Assumptions!$B$8 -> 1.5233333 | AO22: Ranking — Capped Entry | AP22: Ranking entry, capped: Cal King is also Sleephoria's size on the same keywords, so CooLinens enters funded to what the target rank needs (minimum 1 click/day for a CVR read) but never above 3.57 clicks/day (50 clicks in 14 days), with no placement premium. It moves to a full push, with the TOS modifier, once Cal King is assigned to CooLinens. | AQ22: Exact | AR22: Exact: organic rank is earned per exact query, so sales must land on this wording; one keyword per campaign gives full control of bid, TOS modifier and budget, and clean attribution. Phrase / broad / auto open from week 4 for harvesting only. | AS22: =IF(AO22="Ranking — Full Push",MIN(MAX(AJ22,Assumptions!$B$9),AN22),IF(AO22="Brand Defense",MIN(Assumptions!$B$7,AN22),IF(OR(AO22="Ranking — Head Term (Capped)",AO22="Ranking — Capped Entry"),MIN(MAX(AJ22,Assumptions!$B$9),Assumptions!$B$7,AN22),IF(AO22="Ranking — Capped Long-Tail",MIN(AJ22,Assumptions!$B$10,AN22),MIN(AJ22,AN22))))) -> 1 | AT22: =IF(AJ22<=0,"",IF(AS22>=AJ22,IF(AS22>AJ22*1.05,"Floor of "&TEXT(AS22,"0.0")&" click/day to read CVR (rank needs "&TEXT(AJ22,"0.00")&")","Fully funded (100%)"),"Capped at "&TEXT(AS22/AJ22,"0%")&" of required")) -> Floor of 1.0 click/day to read CVR (rank needs 0.06) | AU22: =AS22*AD22 -> 0.064 | AV22: =AU22*AY22 -> 5.56736 | AW22: 3.66 | AX22: Sleephoria avg CPC, Cal King cooling terms | AY22: =INDEX(Assumptions!$B$33:$B$37,MATCH(IF($D22="","Queen",$D22),Assumptions!$A$33:$A$37,0)) -> 86.99 | AZ22: =INDEX(Assumptions!$K$33:$K$37,MATCH(IF($D22="","Queen",$D22),Assumptions!$A$33:$A$37,0)) -> 0.53129383 | BA22: =INDEX(Assumptions!$H$33:$H$37,MATCH(IF($D22="","Queen",$D22),Assumptions!$A$33:$A$37,0)) -> 0.35419588 | BB22: =AY22*AZ22*AD22 -> 2.957904 | BC22: =ROUND(MIN(AW22*Assumptions!$B$11,BB22),2) -> 2.96 | BD22: No | BE22: =IF(AO22="Ranking — Full Push",MAX(0,MIN(IF(BD22="Yes",Assumptions!$B$12,Assumptions!$B$13),FLOOR(MAX(0,BB22/BC22-1),Assumptions!$B$14))),0) -> 0 | BF22: =IF(AO22="Ranking — Full Push",IF(BE22>=1,"YES — +100% Top of Search. Effective CPC $"&TEXT(BG22,"0.00")&" (= $"&TEXT(BC22,"0.00")&" × 2) stays within the $"&TEXT(BB22,"0.00")&" max ranking CPC"&" (= $"&TEXT(AY22,"0.00")&" price × "&TEXT(AZ22,"0.0%")&" ranking ceiling × "&TEXT(AD22,"0.0%")&" CVR)"&". Sleephoria CVR is proven on this term, so the full push is justified.",IF(AND(BD22="No",BE22>=Assumptions!$B$13),"PARTIAL — +"&TEXT(BE22,"0%")&" Top of Search (limit for terms without proven CVR). Effective CPC $"&TEXT(BG22,"0.00")&" vs $"&TEXT(BB22,"0.00")&" max ranking CPC"&" (= $"&TEXT(AY22,"0.00")&" price × "&TEXT(AZ22,"0.0%")&" ranking ceiling × "&TEXT(AD22,"0.0%")&" CVR)"&". Raise to +100% only after CooLinens converts at ≥ "&TEXT(AD22,"0.0%")&" on 50+ clicks and $"&TEXT(BC22*2,"0.00")&" ≤ the max.",IF(BE22>0,"PARTIAL — +"&TEXT(BE22,"0%")&" Top of Search. Effective CPC $"&TEXT(BG22,"0.00")&" stays within the $"&TEXT(BB22,"0.00")&" max ranking CPC"&" (= $"&TEXT(AY22,"0.00")&" price × "&TEXT(AZ22,"0.0%")&" ranking ceiling × "&TEXT(AD22,"0.0%")&" CVR)"&". +100% would cost $"&TEXT(BC22*2,"0.00")&" per click and push ACoS to "&TEXT(BC22*2/(AY22*AD22),"0.0%")&", above the "&TEXT(AZ22,"0.0%")&" ceiling.","NO — 0%. Base bid $"&TEXT(BC22,"0.00")&" already equals the $"&TEXT(BB22,"0.00")&" max ranking CPC"&" (= $"&TEXT(AY22,"0.00")&" price × "&TEXT(AZ22,"0.0%")&" ranking ceiling × "&TEXT(AD22,"0.0%")&" CVR)"&"; any modifier would push ACoS above the "&TEXT(AZ22,"0.0%")&" ceiling."))),IF(OR(AO22="Ranking — Head Term (Capped)",AO22="Ranking — Capped Entry",AO22="Ranking — Capped Long-Tail"),"NO — 0% (capped ranking entry). Bid $"&TEXT(BC22,"0.00")&" vs $"&TEXT(BB22,"0.00")&" max ranking CPC"&" (= $"&TEXT(AY22,"0.00")&" price × "&TEXT(AZ22,"0.0%")&" ranking ceiling × "&TEXT(AD22,"0.0%")&" CVR)"&". While spend is capped at "&TEXT(AS22,"0.00")&" clicks/day, a placement premium would only raise CPC without buying more rank; the modifier is set when this term moves to a full push.","NO — 0% (support / brand term). Bid $"&TEXT(BC22,"0.00")&" vs $"&TEXT(BB22,"0.00")&" max ranking CPC"&" (= $"&TEXT(AY22,"0.00")&" price × "&TEXT(AZ22,"0.0%")&" ranking ceiling × "&TEXT(AD22,"0.0%")&" CVR)"&"; expected ACoS "&TEXT(BI22,"0.0%")&" vs the "&TEXT(AZ22,"0.0%")&" ceiling.")) -> NO — 0% (capped ranking entry). Bid $2.96 vs $2.96 max ranking CPC (= $86.99 price × 53.1% ranking ceiling × 6.4% CVR). While spend is capped at 1.00 clicks/day, a placement premium would only raise CPC without buying more rank; the modifier is set when this term moves to a full push. | BG22: =BC22*(1+BE22) -> 2.96 | BH22: =AS22*BG22 -> 2.96 | BI22: =IFERROR(BG22/(AY22*AD22),"") -> 0.53167031 | BJ22: =IF(BI22="","",IF(BI22<=BA22,"Profitable (≤ break-even)",IF(BI22<=AZ22,"Ranking investment (≤ ceiling)","Above ceiling — reduce bid"))) -> Above ceiling — reduce bid | BK22: ="Base $"&TEXT(BC22,"0.00")&" × (1 + "&TEXT(BE22,"0%")&" TOS) = $"&TEXT(BG22,"0.00")&" effective CPC [max $"&TEXT(BB22,"0.00")&"]. "&TEXT(AG22,"0.0")&" market clicks/day × "&TEXT(AH22,"0.00%")&" click share × "&TEXT(AI22,"0%")&" paid = "&TEXT(AJ22,"0.00")&" clicks/day needed; "&"planned "&TEXT(AS22,"0.00")&" clicks/day × "&TEXT(AD22,"0.0%")&" CVR = "&TEXT(AU22,"0.00")&" orders/day. "&"Spend $"&TEXT(BH22,"0.00")&"/day, ACoS "&TEXT(BI22,"0.0%")&" (ceiling "&TEXT(AZ22,"0.0%")&", break-even "&TEXT(BA22,"0.0%")&"). "&"Target organic rank #"&S22&" by week 8 ("&T22&")." -> Base $2.96 × (1 + 0% TOS) = $2.96 effective CPC [max $2.96]. 7.8 market clicks/day × 1.24% click share × 66% paid = 0.06 clicks/day needed; planned 1.00 clicks/day × 6.4% CVR = 0.06 orders/day. Spend $2.96/day, ACoS 53.2% (ceiling 53.1%, break-even 35.4%). Target organic rank #20 by week 8 (#60 → #35 → #20 (full push after size assignment)). | BL22: cooling sheets|Cal King | BM22: Hero (single-keyword campaign) | BN22: CLCS4-SP-cooling california king sheets-LSV-Exact-Disc-Fix-CK-GRAPHITE | BO22: cooling california king sheets | BP22: CL-COOLING-SHEET-CAL-KING-GRAPHITE | BQ22: B0H6JV73R5 | BR22: =IFERROR(INDEX(Campaigns!$L:$L,MATCH(BN22,Campaigns!$A:$A,0)),"") -> 10 | BS22: =IFERROR(INDEX(Inventory!$O:$O,MATCH(BP22,Inventory!$A:$A,0)),"") -> OK | BT22: =IFERROR(INDEX(Inventory!$N:$N,MATCH(BP22,Inventory!$A:$A,0)),"") -> 77.969814 | BU22: "cooling california king sheets" asks for a Cal King cooling sheet product that CooLinens sells (BreezeWeave nylon/spandex knit, 16″ pocket, 4-piece set). Relevance 100%: product type ✓, use case ✓, material ✓, intent ✓. | BV22: Decolure ($38 microfiber — adjacent, lower weight): no search-term history. | BW22: Sleephoria (same product and price — strongest evidence): too few clicks to read (13); organic best #1 (2026-08-10), first top-10 2026-08-03, now #10. | BX22: SV 639/mo (MKL (DataDive)); launch window ≈ 457/mo; SQP 12-mo 5,765 searches, peak 2026-08, Oct at 0.52× its avg; market CVR 3.4% (head term 1.5%). | BY22: Organic top 20: Bedsure PW #3, Pure Bamboo #5, Pillcase #9, Love's cabin #12. Advertising: Breescape SP#6, Bedsure PW Cooling SP#9, TRUE BAMBOO SP#9, Bambaw SP#11. Rival ad share 52%. | BZ22: Top-20 is held by bamboo/viscose sets (Bedsure PW, Pure Bamboo, Pillcase); no synthetic cooling-knit rival ranks here. CooLinens is the only nylon/spandex cooling option on the page at $86.99 — Sleephoria proved the knit ranks here. | CA22: Launch-window demand is ~35% of the June peak but these are the terms where evidence is strongest; ranking now means CooLinens holds position before the March ramp (SQP March ≈ 2× January). Cal King roots are shared with Sleephoria and not yet assigned: launch capped (50 clicks / 14 days) to read CooLinens CVR for the ownership decision. | CB22: Batch 1 Hero: relevance 100% ≥ 90%, clean wording, launch-window demand 457 searches/mo > 300 (own campaign), and evidence score 6.0/12 ≥ 6.0 (Sleephoria PPC +0 · root|size group proven on Sleephoria +1.5 (cooling sheets|Cal King: CVR 15.7% on 706 clicks) · Sleephoria rank +2 · market CVR +1.5 · competitors +1 · Decolure +0). Sleephoria did not overpay on it beyond the ranking ceiling. | CC22: ≤20 (≤60 by wk 2, ≤35 by wk 4, ≤20 by wk 8): supporting rank — evidence or ownership does not justify a top-10 push yet. Full rank push starts once this size is assigned to CooLinens; until then spend is capped and the campaign builds first sales and a CVR read.
A23: cooling sheets full size | B23: 1 | C23: 15 Oct 2026 | D23: Full | E23: LAUNCH 15 Oct — capped ranking entry | F23: 1 | G23: Type ✓ · Use ✓ · Material ✓ · Intent ✓ | H23: High | I23: 9.5 | J23: Sleephoria PPC +4 · Sleephoria rank +2 · market CVR +1.5 · competitors +1 · Decolure +1 | K23: 6228 | L23: 7387 | M23: =L23/30 -> 246.23333 | N23: 0.035438828 | O23: best #4 (2025-04-26) · median #63 · now #86 | P23: best #2 (2026-03-23) · PPC-period median #11 · now #22 | Q23: #5 Love's cabin | R23: 3 | S23: 10 | T23: #40 → #20 → #10 (full push after size assignment) | U23: Love's cabin #5, KRIMANO #12, Bedsure PW #15; Ads: California Design Den SP#3, Hotel Sheets Direct SP#4, Bambaw SP#5, Elegear SP#7 | V23: =IFERROR(INDEX(Sleephoria_History!$F$454:$F$2115,MATCH($A23,Sleephoria_History!$A$454:$A$2115,0)),"") -> 2305 | W23: =IFERROR(INDEX(Sleephoria_History!$J$454:$J$2115,MATCH($A23,Sleephoria_History!$A$454:$A$2115,0)),"") -> 0.1202 | X23: =IFERROR(INDEX(Sleephoria_History!$H$454:$H$2115,MATCH($A23,Sleephoria_History!$A$454:$A$2115,0)),"") -> 2.49 | Y23: =IFERROR(INDEX(Sleephoria_History!$M$454:$M$2115,MATCH($A23,Sleephoria_History!$A$454:$A$2115,0)),"") -> 0.349 | Z23: =IFERROR(INDEX(Sleephoria_History!$L$454:$L$2115,MATCH($A23,Sleephoria_History!$A$454:$A$2115,0)),"") -> 16455.32 | AA23: =IFERROR(INDEX(Decolure_History!$F$397:$F$709,MATCH($A23,Decolure_History!$A$397:$A$709,0)),"") -> 488 | AB23: =IFERROR(INDEX(Decolure_History!$J$397:$J$709,MATCH($A23,Decolure_History!$A$397:$A$709,0)),"") -> 0.0656 | AC23: =IFERROR(INDEX(Decolure_History!$M$397:$M$709,MATCH($A23,Decolure_History!$A$397:$A$709,0)),"") -> 0.541 | AD23: 0.0962 | AE23: Sleephoria term CVR 12.0% on 2305 clicks ×0.8 launch | AF23: 0.498 | AG23: =M23*AF23 -> 122.6242 | AH23: =IF(AO23="Brand Defense",0,IFERROR(VLOOKUP(S23,Assumptions!$A$24:$B$28,2,FALSE()),0)) -> 0.028 | AI23: =Assumptions!$B$6 -> 0.66 | AJ23: =AG23*AH23*AI23 -> 2.2660952 | AK23: =AJ23*AD23 -> 0.21799836 | AL23: =AJ23*56 -> 126.90133 | AM23: =AK23*56 -> 12.207908 | AN23: =M23*Assumptions!$B$8 -> 24.623333 | AO23: Ranking — Capped Entry | AP23: Ranking entry, capped: Full is also Sleephoria's size on the same keywords, so CooLinens enters funded to what the target rank needs (minimum 1 click/day for a CVR read) but never above 3.57 clicks/day (50 clicks in 14 days), with no placement premium. It moves to a full push, with the TOS modifier, once Full is assigned to CooLinens. | AQ23: Exact | AR23: Exact: organic rank is earned per exact query, so sales must land on this wording; one keyword per campaign gives full control of bid, TOS modifier and budget, and clean attribution. Phrase / broad / auto open from week 4 for harvesting only. | AS23: =IF(AO23="Ranking — Full Push",MIN(MAX(AJ23,Assumptions!$B$9),AN23),IF(AO23="Brand Defense",MIN(Assumptions!$B$7,AN23),IF(OR(AO23="Ranking — Head Term (Capped)",AO23="Ranking — Capped Entry"),MIN(MAX(AJ23,Assumptions!$B$9),Assumptions!$B$7,AN23),IF(AO23="Ranking — Capped Long-Tail",MIN(AJ23,Assumptions!$B$10,AN23),MIN(AJ23,AN23))))) -> 2.2660952 | AT23: =IF(AJ23<=0,"",IF(AS23>=AJ23,IF(AS23>AJ23*1.05,"Floor of "&TEXT(AS23,"0.0")&" click/day to read CVR (rank needs "&TEXT(AJ23,"0.00")&")","Fully funded (100%)"),"Capped at "&TEXT(AS23/AJ23,"0%")&" of required")) -> Fully funded (100%) | AU23: =AS23*AD23 -> 0.21799836 | AV23: =AU23*AY23 -> 14.821708 | AW23: 2.49 | AX23: Sleephoria CPC on this exact term (2305 clicks) | AY23: =INDEX(Assumptions!$B$33:$B$37,MATCH(IF($D23="","Queen",$D23),Assumptions!$A$33:$A$37,0)) -> 67.99 | AZ23: =INDEX(Assumptions!$K$33:$K$37,MATCH(IF($D23="","Queen",$D23),Assumptions!$A$33:$A$37,0)) -> 0.46885204 | BA23: =INDEX(Assumptions!$H$33:$H$37,MATCH(IF($D23="","Queen",$D23),Assumptions!$A$33:$A$37,0)) -> 0.31256802 | BB23: =AY23*AZ23*AD23 -> 3.0665915 | BC23: =ROUND(MIN(AW23*Assumptions!$B$11,BB23),2) -> 2.49 | BD23: Yes | BE23: =IF(AO23="Ranking — Full Push",MAX(0,MIN(IF(BD23="Yes",Assumptions!$B$12,Assumptions!$B$13),FLOOR(MAX(0,BB23/BC23-1),Assumptions!$B$14))),0) -> 0 | BF23: =IF(AO23="Ranking — Full Push",IF(BE23>=1,"YES — +100% Top of Search. Effective CPC $"&TEXT(BG23,"0.00")&" (= $"&TEXT(BC23,"0.00")&" × 2) stays within the $"&TEXT(BB23,"0.00")&" max ranking CPC"&" (= $"&TEXT(AY23,"0.00")&" price × "&TEXT(AZ23,"0.0%")&" ranking ceiling × "&TEXT(AD23,"0.0%")&" CVR)"&". Sleephoria CVR is proven on this term, so the full push is justified.",IF(AND(BD23="No",BE23>=Assumptions!$B$13),"PARTIAL — +"&TEXT(BE23,"0%")&" Top of Search (limit for terms without proven CVR). Effective CPC $"&TEXT(BG23,"0.00")&" vs $"&TEXT(BB23,"0.00")&" max ranking CPC"&" (= $"&TEXT(AY23,"0.00")&" price × "&TEXT(AZ23,"0.0%")&" ranking ceiling × "&TEXT(AD23,"0.0%")&" CVR)"&". Raise to +100% only after CooLinens converts at ≥ "&TEXT(AD23,"0.0%")&" on 50+ clicks and $"&TEXT(BC23*2,"0.00")&" ≤ the max.",IF(BE23>0,"PARTIAL — +"&TEXT(BE23,"0%")&" Top of Search. Effective CPC $"&TEXT(BG23,"0.00")&" stays within the $"&TEXT(BB23,"0.00")&" max ranking CPC"&" (= $"&TEXT(AY23,"0.00")&" price × "&TEXT(AZ23,"0.0%")&" ranking ceiling × "&TEXT(AD23,"0.0%")&" CVR)"&". +100% would cost $"&TEXT(BC23*2,"0.00")&" per click and push ACoS to "&TEXT(BC23*2/(AY23*AD23),"0.0%")&", above the "&TEXT(AZ23,"0.0%")&" ceiling.","NO — 0%. Base bid $"&TEXT(BC23,"0.00")&" already equals the $"&TEXT(BB23,"0.00")&" max ranking CPC"&" (= $"&TEXT(AY23,"0.00")&" price × "&TEXT(AZ23,"0.0%")&" ranking ceiling × "&TEXT(AD23,"0.0%")&" CVR)"&"; any modifier would push ACoS above the "&TEXT(AZ23,"0.0%")&" ceiling."))),IF(OR(AO23="Ranking — Head Term (Capped)",AO23="Ranking — Capped Entry",AO23="Ranking — Capped Long-Tail"),"NO — 0% (capped ranking entry). Bid $"&TEXT(BC23,"0.00")&" vs $"&TEXT(BB23,"0.00")&" max ranking CPC"&" (= $"&TEXT(AY23,"0.00")&" price × "&TEXT(AZ23,"0.0%")&" ranking ceiling × "&TEXT(AD23,"0.0%")&" CVR)"&". While spend is capped at "&TEXT(AS23,"0.00")&" clicks/day, a placement premium would only raise CPC without buying more rank; the modifier is set when this term moves to a full push.","NO — 0% (support / brand term). Bid $"&TEXT(BC23,"0.00")&" vs $"&TEXT(BB23,"0.00")&" max ranking CPC"&" (= $"&TEXT(AY23,"0.00")&" price × "&TEXT(AZ23,"0.0%")&" ranking ceiling × "&TEXT(AD23,"0.0%")&" CVR)"&"; expected ACoS "&TEXT(BI23,"0.0%")&" vs the "&TEXT(AZ23,"0.0%")&" ceiling.")) -> NO — 0% (capped ranking entry). Bid $2.49 vs $3.07 max ranking CPC (= $67.99 price × 46.9% ranking ceiling × 9.6% CVR). While spend is capped at 2.27 clicks/day, a placement premium would only raise CPC without buying more rank; the modifier is set when this term moves to a full push. | BG23: =BC23*(1+BE23) -> 2.49 | BH23: =AS23*BG23 -> 5.6425771 | BI23: =IFERROR(BG23/(AY23*AD23),"") -> 0.38069681 | BJ23: =IF(BI23="","",IF(BI23<=BA23,"Profitable (≤ break-even)",IF(BI23<=AZ23,"Ranking investment (≤ ceiling)","Above ceiling — reduce bid"))) -> Ranking investment (≤ ceiling) | BK23: ="Base $"&TEXT(BC23,"0.00")&" × (1 + "&TEXT(BE23,"0%")&" TOS) = $"&TEXT(BG23,"0.00")&" effective CPC [max $"&TEXT(BB23,"0.00")&"]. "&TEXT(AG23,"0.0")&" market clicks/day × "&TEXT(AH23,"0.00%")&" click share × "&TEXT(AI23,"0%")&" paid = "&TEXT(AJ23,"0.00")&" clicks/day needed; "&"planned "&TEXT(AS23,"0.00")&" clicks/day × "&TEXT(AD23,"0.0%")&" CVR = "&TEXT(AU23,"0.00")&" orders/day. "&"Spend $"&TEXT(BH23,"0.00")&"/day, ACoS "&TEXT(BI23,"0.0%")&" (ceiling "&TEXT(AZ23,"0.0%")&", break-even "&TEXT(BA23,"0.0%")&"). "&"Target organic rank #"&S23&" by week 8 ("&T23&")." -> Base $2.49 × (1 + 0% TOS) = $2.49 effective CPC [max $3.07]. 122.6 market clicks/day × 2.80% click share × 66% paid = 2.27 clicks/day needed; planned 2.27 clicks/day × 9.6% CVR = 0.22 orders/day. Spend $5.64/day, ACoS 38.1% (ceiling 46.9%, break-even 31.3%). Target organic rank #10 by week 8 (#40 → #20 → #10 (full push after size assignment)). | BL23: cooling sheets|Full | BM23: Hero (single-keyword campaign) | BN23: CLCS4-SP-cooling sheets full size-HSV-Exact-Disc-Fix-F-COOL-GREY | BO23: cooling sheets full size | BP23: CL-COOLING-SHEET-FULL-COOL-GREY | BQ23: B0H6K4KPGJ | BR23: =IFERROR(INDEX(Campaigns!$L:$L,MATCH(BN23,Campaigns!$A:$A,0)),"") -> 10 | BS23: =IFERROR(INDEX(Inventory!$O:$O,MATCH(BP23,Inventory!$A:$A,0)),"") -> OK | BT23: =IFERROR(INDEX(Inventory!$N:$N,MATCH(BP23,Inventory!$A:$A,0)),"") -> 67.229536 | BU23: "cooling sheets full size" asks for a Full cooling sheet product that CooLinens sells (BreezeWeave nylon/spandex knit, 16″ pocket, 4-piece set). Relevance 100%: product type ✓, use case ✓, material ✓, intent ✓. | BV23: Decolure ($38 microfiber — adjacent, lower weight): converted but costly at the $38 tier (488 clicks, CVR 6.6%, ACoS 54%); organic best #4 (2025-04-26), 63 days in top 10, median #63. | BW23: Sleephoria (same product and price — strongest evidence): proven on the same product (2305 clicks, CVR 12.0%, ACoS 35%); organic best #2 (2026-03-23), first top-10 2025-10-14, now #22. Launch entry Oct-25: 2.7 clicks/day, 0.31 orders/day, $12/day → top 10 in 11 days. | BX23: SV 6,228/mo (MKL (DataDive)); launch window ≈ 7,387/mo; SQP 12-mo 109,449 searches, peak 2026-06, Oct at 0.71× its avg; market CVR 3.5% (head term 1.5%). | BY23: Organic top 20: Love's cabin #5, KRIMANO #12, Bedsure PW #15. Advertising: California Design Den SP#3, Hotel Sheets Direct SP#4, Bambaw SP#5, Elegear SP#7. Rival ad share 36%. | BZ23: Top-20 is held by bamboo/viscose sets (Love's cabin, KRIMANO, Bedsure PW); no synthetic cooling-knit rival ranks here. CooLinens is the only nylon/spandex cooling option on the page at $67.99 — Sleephoria proved the knit ranks here. | CA23: Launch-window demand is ~35% of the June peak but these are the terms where evidence is strongest; ranking now means CooLinens holds position before the March ramp (SQP March ≈ 2× January). Full roots are shared with Sleephoria and not yet assigned: launch capped (50 clicks / 14 days) to read CooLinens CVR for the ownership decision. | CB23: Batch 1 Hero: relevance 100% ≥ 90%, clean wording, launch-window demand 7,387 searches/mo > 300 (own campaign), and evidence score 9.5/12 ≥ 6.0 (Sleephoria PPC +4 · Sleephoria rank +2 · market CVR +1.5 · competitors +1 · Decolure +1). Sleephoria did not overpay on it beyond the ranking ceiling. | CC23: ≤10 (≤40 by wk 2, ≤20 by wk 4, ≤10 by wk 8): Sleephoria, the same product, reached #2 here and entered the top 10 within 11 days; 3 tracked rival(s) in the top 20. Full rank push starts once this size is assigned to CooLinens; until then spend is capped and the campaign builds first sales and a CVR read.
A24: full size sheets cooling | B24: 1 | C24: 15 Oct 2026 | D24: Full | E24: LAUNCH 15 Oct — capped ranking entry | F24: 1 | G24: Type ✓ · Use ✓ · Material ✓ · Intent ✓ | H24: High | I24: 8.5 | J24: Sleephoria PPC +4 · Sleephoria rank +2 · market CVR +2 · competitors +0.5 · Decolure +0 | K24: 1959 | L24: 1209 | M24: =L24/30 -> 40.3 | N24: 0.055423055 | O24: now #101 | P24: best #5 (2025-10-16) · PPC-period median #20 · now #39 | Q24: #4 Love's cabin | R24: 2 | S24: 10 | T24: #40 → #20 → #10 (full push after size assignment) | U24: Love's cabin #4, Bedsure PW #8; Ads: TRUE BAMBOO SP#1, Bedsure PW SP#3, REST SP#3, Love's cabin SP#7 | V24: =IFERROR(INDEX(Sleephoria_History!$F$454:$F$2115,MATCH($A24,Sleephoria_History!$A$454:$A$2115,0)),"") -> 112 | W24: =IFERROR(INDEX(Sleephoria_History!$J$454:$J$2115,MATCH($A24,Sleephoria_History!$A$454:$A$2115,0)),"") -> 0.0893 | X24: =IFERROR(INDEX(Sleephoria_History!$H$454:$H$2115,MATCH($A24,Sleephoria_History!$A$454:$A$2115,0)),"") -> 1.45 | Y24: =IFERROR(INDEX(Sleephoria_History!$M$454:$M$2115,MATCH($A24,Sleephoria_History!$A$454:$A$2115,0)),"") -> 0.272 | Z24: =IFERROR(INDEX(Sleephoria_History!$L$454:$L$2115,MATCH($A24,Sleephoria_History!$A$454:$A$2115,0)),"") -> 596.55 | AA24: =IFERROR(INDEX(Decolure_History!$F$397:$F$709,MATCH($A24,Decolure_History!$A$397:$A$709,0)),"") | AB24: =IFERROR(INDEX(Decolure_History!$J$397:$J$709,MATCH($A24,Decolure_History!$A$397:$A$709,0)),"") | AC24: =IFERROR(INDEX(Decolure_History!$M$397:$M$709,MATCH($A24,Decolure_History!$A$397:$A$709,0)),"") | AD24: 0.0714 | AE24: Sleephoria term CVR 8.9% on 112 clicks ×0.8 launch | AF24: 0.483 | AG24: =M24*AF24 -> 19.4649 | AH24: =IF(AO24="Brand Defense",0,IFERROR(VLOOKUP(S24,Assumptions!$A$24:$B$28,2,FALSE()),0)) -> 0.028 | AI24: =Assumptions!$B$6 -> 0.66 | AJ24: =AG24*AH24*AI24 -> 0.35971135 | AK24: =AJ24*AD24 -> 0.025683391 | AL24: =AJ24*56 -> 20.143836 | AM24: =AK24*56 -> 1.4382699 | AN24: =M24*Assumptions!$B$8 -> 4.03 | AO24: Ranking — Capped Entry | AP24: Ranking entry, capped: Full is also Sleephoria's size on the same keywords, so CooLinens enters funded to what the target rank needs (minimum 1 click/day for a CVR read) but never above 3.57 clicks/day (50 clicks in 14 days), with no placement premium. It moves to a full push, with the TOS modifier, once Full is assigned to CooLinens. | AQ24: Exact | AR24: Exact: organic rank is earned per exact query, so sales must land on this wording; one keyword per campaign gives full control of bid, TOS modifier and budget, and clean attribution. Phrase / broad / auto open from week 4 for harvesting only. | AS24: =IF(AO24="Ranking — Full Push",MIN(MAX(AJ24,Assumptions!$B$9),AN24),IF(AO24="Brand Defense",MIN(Assumptions!$B$7,AN24),IF(OR(AO24="Ranking — Head Term (Capped)",AO24="Ranking — Capped Entry"),MIN(MAX(AJ24,Assumptions!$B$9),Assumptions!$B$7,AN24),IF(AO24="Ranking — Capped Long-Tail",MIN(AJ24,Assumptions!$B$10,AN24),MIN(AJ24,AN24))))) -> 1 | AT24: =IF(AJ24<=0,"",IF(AS24>=AJ24,IF(AS24>AJ24*1.05,"Floor of "&TEXT(AS24,"0.0")&" click/day to read CVR (rank needs "&TEXT(AJ24,"0.00")&")","Fully funded (100%)"),"Capped at "&TEXT(AS24/AJ24,"0%")&" of required")) -> Floor of 1.0 click/day to read CVR (rank needs 0.36) | AU24: =AS24*AD24 -> 0.0714 | AV24: =AU24*AY24 -> 4.854486 | AW24: 1.45 | AX24: Sleephoria CPC on this exact term (112 clicks) | AY24: =INDEX(Assumptions!$B$33:$B$37,MATCH(IF($D24="","Queen",$D24),Assumptions!$A$33:$A$37,0)) -> 67.99 | AZ24: =INDEX(Assumptions!$K$33:$K$37,MATCH(IF($D24="","Queen",$D24),Assumptions!$A$33:$A$37,0)) -> 0.46885204 | BA24: =INDEX(Assumptions!$H$33:$H$37,MATCH(IF($D24="","Queen",$D24),Assumptions!$A$33:$A$37,0)) -> 0.31256802 | BB24: =AY24*AZ24*AD24 -> 2.2760356 | BC24: =ROUND(MIN(AW24*Assumptions!$B$11,BB24),2) -> 1.45 | BD24: Yes | BE24: =IF(AO24="Ranking — Full Push",MAX(0,MIN(IF(BD24="Yes",Assumptions!$B$12,Assumptions!$B$13),FLOOR(MAX(0,BB24/BC24-1),Assumptions!$B$14))),0) -> 0 | BF24: =IF(AO24="Ranking — Full Push",IF(BE24>=1,"YES — +100% Top of Search. Effective CPC $"&TEXT(BG24,"0.00")&" (= $"&TEXT(BC24,"0.00")&" × 2) stays within the $"&TEXT(BB24,"0.00")&" max ranking CPC"&" (= $"&TEXT(AY24,"0.00")&" price × "&TEXT(AZ24,"0.0%")&" ranking ceiling × "&TEXT(AD24,"0.0%")&" CVR)"&". Sleephoria CVR is proven on this term, so the full push is justified.",IF(AND(BD24="No",BE24>=Assumptions!$B$13),"PARTIAL — +"&TEXT(BE24,"0%")&" Top of Search (limit for terms without proven CVR). Effective CPC $"&TEXT(BG24,"0.00")&" vs $"&TEXT(BB24,"0.00")&" max ranking CPC"&" (= $"&TEXT(AY24,"0.00")&" price × "&TEXT(AZ24,"0.0%")&" ranking ceiling × "&TEXT(AD24,"0.0%")&" CVR)"&". Raise to +100% only after CooLinens converts at ≥ "&TEXT(AD24,"0.0%")&" on 50+ clicks and $"&TEXT(BC24*2,"0.00")&" ≤ the max.",IF(BE24>0,"PARTIAL — +"&TEXT(BE24,"0%")&" Top of Search. Effective CPC $"&TEXT(BG24,"0.00")&" stays within the $"&TEXT(BB24,"0.00")&" max ranking CPC"&" (= $"&TEXT(AY24,"0.00")&" price × "&TEXT(AZ24,"0.0%")&" ranking ceiling × "&TEXT(AD24,"0.0%")&" CVR)"&". +100% would cost $"&TEXT(BC24*2,"0.00")&" per click and push ACoS to "&TEXT(BC24*2/(AY24*AD24),"0.0%")&", above the "&TEXT(AZ24,"0.0%")&" ceiling.","NO — 0%. Base bid $"&TEXT(BC24,"0.00")&" already equals the $"&TEXT(BB24,"0.00")&" max ranking CPC"&" (= $"&TEXT(AY24,"0.00")&" price × "&TEXT(AZ24,"0.0%")&" ranking ceiling × "&TEXT(AD24,"0.0%")&" CVR)"&"; any modifier would push ACoS above the "&TEXT(AZ24,"0.0%")&" ceiling."))),IF(OR(AO24="Ranking — Head Term (Capped)",AO24="Ranking — Capped Entry",AO24="Ranking — Capped Long-Tail"),"NO — 0% (capped ranking entry). Bid $"&TEXT(BC24,"0.00")&" vs $"&TEXT(BB24,"0.00")&" max ranking CPC"&" (= $"&TEXT(AY24,"0.00")&" price × "&TEXT(AZ24,"0.0%")&" ranking ceiling × "&TEXT(AD24,"0.0%")&" CVR)"&". While spend is capped at "&TEXT(AS24,"0.00")&" clicks/day, a placement premium would only raise CPC without buying more rank; the modifier is set when this term moves to a full push.","NO — 0% (support / brand term). Bid $"&TEXT(BC24,"0.00")&" vs $"&TEXT(BB24,"0.00")&" max ranking CPC"&" (= $"&TEXT(AY24,"0.00")&" price × "&TEXT(AZ24,"0.0%")&" ranking ceiling × "&TEXT(AD24,"0.0%")&" CVR)"&"; expected ACoS "&TEXT(BI24,"0.0%")&" vs the "&TEXT(AZ24,"0.0%")&" ceiling.")) -> NO — 0% (capped ranking entry). Bid $1.45 vs $2.28 max ranking CPC (= $67.99 price × 46.9% ranking ceiling × 7.1% CVR). While spend is capped at 1.00 clicks/day, a placement premium would only raise CPC without buying more rank; the modifier is set when this term moves to a full push. | BG24: =BC24*(1+BE24) -> 1.45 | BH24: =AS24*BG24 -> 1.45 | BI24: =IFERROR(BG24/(AY24*AD24),"") -> 0.2986928 | BJ24: =IF(BI24="","",IF(BI24<=BA24,"Profitable (≤ break-even)",IF(BI24<=AZ24,"Ranking investment (≤ ceiling)","Above ceiling — reduce bid"))) -> Profitable (≤ break-even) | BK24: ="Base $"&TEXT(BC24,"0.00")&" × (1 + "&TEXT(BE24,"0%")&" TOS) = $"&TEXT(BG24,"0.00")&" effective CPC [max $"&TEXT(BB24,"0.00")&"]. "&TEXT(AG24,"0.0")&" market clicks/day × "&TEXT(AH24,"0.00%")&" click share × "&TEXT(AI24,"0%")&" paid = "&TEXT(AJ24,"0.00")&" clicks/day needed; "&"planned "&TEXT(AS24,"0.00")&" clicks/day × "&TEXT(AD24,"0.0%")&" CVR = "&TEXT(AU24,"0.00")&" orders/day. "&"Spend $"&TEXT(BH24,"0.00")&"/day, ACoS "&TEXT(BI24,"0.0%")&" (ceiling "&TEXT(AZ24,"0.0%")&", break-even "&TEXT(BA24,"0.0%")&"). "&"Target organic rank #"&S24&" by week 8 ("&T24&")." -> Base $1.45 × (1 + 0% TOS) = $1.45 effective CPC [max $2.28]. 19.5 market clicks/day × 2.80% click share × 66% paid = 0.36 clicks/day needed; planned 1.00 clicks/day × 7.1% CVR = 0.07 orders/day. Spend $1.45/day, ACoS 29.9% (ceiling 46.9%, break-even 31.3%). Target organic rank #10 by week 8 (#40 → #20 → #10 (full push after size assignment)). | BL24: cooling sheets|Full | BM24: Hero (single-keyword campaign) | BN24: CLCS4-SP-full size sheets cooling-HSV-Exact-Disc-Fix-F-COOL-GREY | BO24: full size sheets cooling | BP24: CL-COOLING-SHEET-FULL-COOL-GREY | BQ24: B0H6K4KPGJ | BR24: =IFERROR(INDEX(Campaigns!$L:$L,MATCH(BN24,Campaigns!$A:$A,0)),"") -> 10 | BS24: =IFERROR(INDEX(Inventory!$O:$O,MATCH(BP24,Inventory!$A:$A,0)),"") -> OK | BT24: =IFERROR(INDEX(Inventory!$N:$N,MATCH(BP24,Inventory!$A:$A,0)),"") -> 67.229536 | BU24: "full size sheets cooling" asks for a Full cooling sheet product that CooLinens sells (BreezeWeave nylon/spandex knit, 16″ pocket, 4-piece set). Relevance 100%: product type ✓, use case ✓, material ✓, intent ✓. | BV24: Decolure ($38 microfiber — adjacent, lower weight): no search-term history. | BW24: Sleephoria (same product and price — strongest evidence): proven on the same product (112 clicks, CVR 8.9%, ACoS 27%); organic best #5 (2025-10-16), first top-10 2025-10-16, now #39. | BX24: SV 1,959/mo (MKL (DataDive)); launch window ≈ 1,209/mo; SQP 12-mo 21,514 searches, peak 2026-08, Oct at 0.85× its avg; market CVR 5.5% (head term 1.5%). | BY24: Organic top 20: Love's cabin #4, Bedsure PW #8. Advertising: TRUE BAMBOO SP#1, Bedsure PW SP#3, REST SP#3, Love's cabin SP#7. Rival ad share 46%. | BZ24: Top-20 is held by bamboo/viscose sets (Love's cabin, Bedsure PW); no synthetic cooling-knit rival ranks here. CooLinens is the only nylon/spandex cooling option on the page at $67.99 — Sleephoria proved the knit ranks here. | CA24: Launch-window demand is ~35% of the June peak but these are the terms where evidence is strongest; ranking now means CooLinens holds position before the March ramp (SQP March ≈ 2× January). Full roots are shared with Sleephoria and not yet assigned: launch capped (50 clicks / 14 days) to read CooLinens CVR for the ownership decision. | CB24: Batch 1 Hero: relevance 100% ≥ 90%, clean wording, launch-window demand 1,209 searches/mo > 300 (own campaign), and evidence score 8.5/12 ≥ 6.0 (Sleephoria PPC +4 · Sleephoria rank +2 · market CVR +2 · competitors +0.5 · Decolure +0). Sleephoria did not overpay on it beyond the ranking ceiling. | CC24: ≤10 (≤40 by wk 2, ≤20 by wk 4, ≤10 by wk 8): Sleephoria, the same product, reached #5 here; 2 tracked rival(s) in the top 20. Full rank push starts once this size is assigned to CooLinens; until then spend is capped and the campaign builds first sales and a CVR read.
